Workbook

Sheet Como usar
A1: Custo-hora do escritório
A2: Kit de Gestão para Advogados · Seu Sócio Gestor · versão 1.0 (setembro de 2026)
A4: O que esta planilha faz | B4: Responde "quanto custa uma hora do meu escritório?". Soma custos fixos e pró-labore, divide pelas horas que podem ser cobradas de clientes e mostra o custo-hora, a hora mínima a cobrar (com margem e impostos) e o que acontece se as horas faturáveis caírem.
A5: Passo 1 | B5: Em Custos fixos, liste o que o escritório paga todo mês (aluguel, contador, sistemas, bolsa de estágio, marketing). Uma linha por item, de cima para baixo.
A6: Passo 2 | B6: Em Pessoas, cada pessoa com pró-labore ou salário, horas de trabalho e horas faturáveis por mês. Se o custo dela já está em Custos fixos, marque "Sim" para não contar duas vezes.
A7: Passo 3 | B7: Em Config, a margem que você quer sobre o preço e o percentual de impostos e taxas que sai de cada recebimento (confira com o contador).
A8: Passo 4 | B8: Em Painel: custo-hora do escritório, hora mínima a cobrar, custo-hora de cada pessoa e a sensibilidade. Leve o CUSTO-HORA do escritório (Painel B13) como entrada das planilhas 06 (Simulador) e 08 (Tabela de referência): é sobre ele que elas aplicam imposto e margem. A hora mínima serve para comparar preço, não como entrada — usá-la no lugar do custo-hora aplica margem e imposto duas vezes.
A9: Rotina | B9: Revise uma vez por trimestre ou quando mudar aluguel, equipe ou pró-labore. Leva 10 minutos.
A10: Com a IA | B10: Copie "Como chegamos ao número" e use o prompt "Honorários 01 · Entender o meu custo-hora" da biblioteca do kit para explicar o custo-hora ao sócio em linguagem simples, ou para sugerir o que fazer se a ocupação estiver abaixo de 50%.
A11: Legenda | B11: Células amarelas: você preenche. Brancas: calculadas. Não é preciso mexer em nada fora do amarelo.
A12: Proteção | B12: Fórmulas protegidas sem senha. Para editar: Revisar > Desproteger planilha (Excel) ou Dados > Proteger intervalos (Google Sheets).
A13: Requisitos | B13: Excel 2016 ou mais novo, Microsoft 365 ou Google Sheets (só funções do Excel 2007+; nada de MÍNIMOSES, MÁXIMOSES ou UNIRTEXTO). No celular abre nos aplicativos; para preencher, use o computador.
A14: Google Sheets | B14: Faça upload no Google Drive e abra com o Google Sheets. Fórmulas, listas, cores, semáforos e gráficos funcionam: as regras de cor que dependem do mês escolhido em Config usam INDIRECT, que é a forma que o Sheets aceita para regra condicional apontar para outra aba.
A15: Exemplos | B15: Ferraz & Lima Advocacia é um escritório fictício. Clientes, processos, nomes e valores são inventados. Apague-os antes de começar.
... A17: Suporte | B17: suporte@seusociogestor.com.br · resposta em até 5 dias úteis · reembolso em até 7 dias pelo mesmo canal.

Sheet Painel
A1: =Config!$B$4&" · Custo-hora · "&Config!$B$5 -> Ferraz & Lima Advocacia (exemplo fictício) · Custo-hora · Setembro de 2026
A2: Nada para digitar aqui, exceto os percentuais da sensibilidade. Custos vêm da aba Custos fixos, pessoas da aba Pessoas, margem e impostos de Config.
A4: Custo total do mês | C4: Horas faturáveis no mês | E4: Custo-hora do escritório | G4: Hora mínima a cobrar | I4: Tempo faturável (planejado)
A5: =B11 -> 18500 | C5: =B12 -> 280 | E5: =B13 -> 66.071429 | G5: =B17 -> 110 | I5: =B21 -> 0.63636364
A6: =IF(SUM(Pessoas!$K$5:$K$14)=0,"","Atenção: "&SUM(Pessoas!$K$5:$K$14)&" pessoa(s) na aba Pessoas sem pró-labore ou sem horas faturáveis. O custo do mês, o custo-hora e a hora mínima ficam como 'cadastro incompleto' até você completar: uma soma parcial daria um custo-hora MENOR do que o real.")
A7: Como chegamos ao número
A8: Passo | B8: Valor | C8: De onde vem
A9: Custos fixos do mês | B9: ='Custos fixos'!B36 -> 6500 | C9: Aba Custos fixos
A10: Pró-labore e salários fora dos custos fixos | B10: =IF(SUM(Pessoas!$K$5:$K$14)>0,"cadastro incompleto",SUMIFS(Pessoas!$C$5:$C$14,Pessoas!$D$5:$D$14,"Não")) -> 12000 | C10: Aba Pessoas, quem está marcado "Não"
A11: Custo total do mês | B11: =IF(SUM(Pessoas!$K$5:$K$14)>0,"cadastro incompleto",B9+B10) -> 18500 | C11: Soma dos dois acima
A12: Horas faturáveis no mês (todas as pessoas) | B12: =IF(SUM(Pessoas!$K$5:$K$14)>0,"cadastro incompleto",SUM(Pessoas!$F$5:$F$14)) -> 280 | C12: Aba Pessoas
A13: Custo-hora do escritório | B13: =IF(SUM(Pessoas!$K$5:$K$14)>0,"cadastro incompleto",IF(B12=0,"",B11/B12)) -> 66.071429 | C13: Custo total ÷ horas faturáveis
A14: Margem desejada sobre o preço | B14: =Config!$B$7 -> 0.3 | C14: Config
A15: Impostos e taxas sobre o que entra | B15: =Config!$B$8 -> 0.08 | C15: Config
A16: Hora mínima a cobrar (exata) | B16: =IF(B13="","",IF(NOT(ISNUMBER(B13)),B13,IF(Config!$B$10<>"Sim","margens inválidas (Config)",B13/(1-Config!$B$7-Config!$B$8)))) -> 106.56682 | C16: Custo-hora ÷ (1 − margem − impostos)
A17: Hora mínima a cobrar (arredondada) | B17: =IF(B16="","",IF(NOT(ISNUMBER(B16)),B16,CEILING(B16,Config!$B$9))) -> 110 | C17: Arredondada para cima, no múltiplo de Config
A18: Custos indiretos (custos fixos menos pessoas já contadas neles) | B18: =IF(SUM(Pessoas!$K$5:$K$14)>0,"cadastro incompleto",B9-SUMIFS(Pessoas!$C$5:$C$14,Pessoas!$D$5:$D$14,"Sim")) -> 5100 | C18: Para ratear entre as pessoas
A19: Custo indireto por hora faturável | B19: =IF(SUM(Pessoas!$K$5:$K$14)>0,"cadastro incompleto",IF(B12=0,0,B18/B12)) -> 18.214286 | C19: Custos indiretos ÷ horas faturáveis
A20: Horas de trabalho no mês (todas as pessoas) | B20: =SUM(Pessoas!$E$5:$E$14) -> 440 | C20: Aba Pessoas
A21: Tempo faturável planejado (horas faturáveis ÷ horas de trabalho) | B21: =IF(OR(B20=0,NOT(ISNUMBER(B12))),"",B12/B20) -> 0.63636364 | C21: Quanto do tempo pago vira hora cobrável (a planilha 16 mede o realizado contra a meta)
A24: Por pessoa
A25: Pessoa | B25: Papel | C25: Horas faturáveis | D25: Ocupação | E25: Custo direto por hora | F25: Custo-hora completo | G25: Hora mínima a cobrar
A26: =IF(Pessoas!$A$5="","",Pessoas!$A$5) -> Marina Ferraz | B26: =IF(Pessoas!$A$5="","",Pessoas!$B$5) -> Sócia · cível e empresarial | C26: =IF(Pessoas!$A$5="","",Pessoas!$F$5) -> 110 | D26: =IF(Pessoas!$A$5="","",Pessoas!$G$5) -> 0.6875 | E26: =IF(Pessoas!$A$5="","",Pessoas!$H$5) -> 54.545455 | F26: =IF(Pessoas!$A$5="","",Pessoas!$I$5) -> 72.75974 | G26: =IF(Pessoas!$A$5="","",Pessoas!$J$5) -> 117.35442
A27: =IF(Pessoas!$A$6="","",Pessoas!$A$6) -> Rafael Lima | B27: =IF(Pessoas!$A$6="","",Pessoas!$B$6) -> Sócio · trabalhista e previdenciário | C27: =IF(Pessoas!$A$6="","",Pessoas!$F$6) -> 110 | D27: =IF(Pessoas!$A$6="","",Pessoas!$G$6) -> 0.6875 | E27: =IF(Pessoas!$A$6="","",Pessoas!$H$6) -> 54.545455 | F27: =IF(Pessoas!$A$6="","",Pessoas!$I$6) -> 72.75974 | G27: =IF(Pessoas!$A$6="","",Pessoas!$J$6) -> 117.35442
A28: =IF(Pessoas!$A$7="","",Pessoas!$A$7) -> Júlia Prado | B28: =IF(Pessoas!$A$7="","",Pessoas!$B$7) -> Estagiária | C28: =IF(Pessoas!$A$7="","",Pessoas!$F$7) -> 60 | D28: =IF(Pessoas!$A$7="","",Pessoas!$G$7) -> 0.5 | E28: =IF(Pessoas!$A$7="","",Pessoas!$H$7) -> 23.333333 | F28: =IF(Pessoas!$A$7="","",Pessoas!$I$7) -> 41.547619 | G28: =IF(Pessoas!$A$7="","",Pessoas!$J$7) -> 67.012289
A29: =IF(Pessoas!$A$8="","",Pessoas!$A$8) | B29: =IF(Pessoas!$A$8="","",Pessoas!$B$8) | C29: =IF(Pessoas!$A$8="","",Pessoas!$F$8) | D29: =IF(Pessoas!$A$8="","",Pessoas!$G$8) | E29: =IF(Pessoas!$A$8="","",Pessoas!$H$8) | F29: =IF(Pessoas!$A$8="","",Pessoas!$I$8) | G29: =IF(Pessoas!$A$8="","",Pessoas!$J$8)
A30: =IF(Pessoas!$A$9="","",Pessoas!$A$9) | B30: =IF(Pessoas!$A$9="","",Pessoas!$B$9) | C30: =IF(Pessoas!$A$9="","",Pessoas!$F$9) | D30: =IF(Pessoas!$A$9="","",Pessoas!$G$9) | E30: =IF(Pessoas!$A$9="","",Pessoas!$H$9) | F30: =IF(Pessoas!$A$9="","",Pessoas!$I$9) | G30: =IF(Pessoas!$A$9="","",Pessoas!$J$9)
A31: =IF(Pessoas!$A$10="","",Pessoas!$A$10) | B31: =IF(Pessoas!$A$10="","",Pessoas!$B$10) | C31: =IF(Pessoas!$A$10="","",Pessoas!$F$10) | D31: =IF(Pessoas!$A$10="","",Pessoas!$G$10) | E31: =IF(Pessoas!$A$10="","",Pessoas!$H$10) | F31: =IF(Pessoas!$A$10="","",Pessoas!$I$10) | G31: =IF(Pessoas!$A$10="","",Pessoas!$J$10)
A32: =IF(Pessoas!$A$11="","",Pessoas!$A$11) | B32: =IF(Pessoas!$A$11="","",Pessoas!$B$11) | C32: =IF(Pessoas!$A$11="","",Pessoas!$F$11) | D32: =IF(Pessoas!$A$11="","",Pessoas!$G$11) | E32: =IF(Pessoas!$A$11="","",Pessoas!$H$11) | F32: =IF(Pessoas!$A$11="","",Pessoas!$I$11) | G32: =IF(Pessoas!$A$11="","",Pessoas!$J$11)
A33: =IF(Pessoas!$A$12="","",Pessoas!$A$12) | B33: =IF(Pessoas!$A$12="","",Pessoas!$B$12) | C33: =IF(Pessoas!$A$12="","",Pessoas!$F$12) | D33: =IF(Pessoas!$A$12="","",Pessoas!$G$12) | E33: =IF(Pessoas!$A$12="","",Pessoas!$H$12) | F33: =IF(Pessoas!$A$12="","",Pessoas!$I$12) | G33: =IF(Pessoas!$A$12="","",Pessoas!$J$12)
A34: =IF(Pessoas!$A$13="","",Pessoas!$A$13) | B34: =IF(Pessoas!$A$13="","",Pessoas!$B$13) | C34: =IF(Pessoas!$A$13="","",Pessoas!$F$13) | D34: =IF(Pessoas!$A$13="","",Pessoas!$G$13) | E34: =IF(Pessoas!$A$13="","",Pessoas!$H$13) | F34: =IF(Pessoas!$A$13="","",Pessoas!$I$13) | G34: =IF(Pessoas!$A$13="","",Pessoas!$J$13)
A35: =IF(Pessoas!$A$14="","",Pessoas!$A$14) | B35: =IF(Pessoas!$A$14="","",Pessoas!$B$14) | C35: =IF(Pessoas!$A$14="","",Pessoas!$F$14) | D35: =IF(Pessoas!$A$14="","",Pessoas!$G$14) | E35: =IF(Pessoas!$A$14="","",Pessoas!$H$14) | F35: =IF(Pessoas!$A$14="","",Pessoas!$I$14) | G35: =IF(Pessoas!$A$14="","",Pessoas!$J$14)
A36: Ocupação abaixo de 50% fica destacada: ou há horas trabalhadas que não estão sendo cobradas, ou falta caso para a pessoa.
A38: Sensibilidade: e se as horas faturáveis caírem?
A39: Mês fraco, férias, um sócio doente: o custo fixo continua e cada hora fica mais cara. Os percentuais em amarelo podem ser trocados.
A40: Cenário | B40: Queda nas horas | C40: Horas faturáveis | D40: Custo-hora | E40: Hora mínima a cobrar | F40: Diferença por hora
A41: Hoje | B41: 0 | C41: =IF(ISNUMBER($B$12),$B$12*(1-B41),"") -> 280 | D41: =IF(OR(C41="",C41=0,NOT(ISNUMBER($B$11))),"",$B$11/C41) -> 66.071429 | E41: =IF(D41="","",IF(Config!$B$10<>"Sim","margens inválidas (Config)",D41/(1-Config!$B$7-Config!$B$8))) -> 106.56682 | F41: =IF(D41="","",D41-$D$41) -> 0
A42: ="Queda de "&ROUND(B42*100,0)&"%" -> Queda de 10% | B42: 0.1 | C42: =IF(ISNUMBER($B$12),$B$12*(1-B42),"") -> 252 | D42: =IF(OR(C42="",C42=0,NOT(ISNUMBER($B$11))),"",$B$11/C42) -> 73.412698 | E42: =IF(D42="","",IF(Config!$B$10<>"Sim","margens inválidas (Config)",D42/(1-Config!$B$7-Config!$B$8))) -> 118.40758 | F42: =IF(D42="","",D42-$D$41) -> 7.3412698
A43: ="Queda de "&ROUND(B43*100,0)&"%" -> Queda de 20% | B43: 0.2 | C43: =IF(ISNUMBER($B$12),$B$12*(1-B43),"") -> 224 | D43: =IF(OR(C43="",C43=0,NOT(ISNUMBER($B$11))),"",$B$11/C43) -> 82.589286 | E43: =IF(D43="","",IF(Config!$B$10<>"Sim","margens inválidas (Config)",D43/(1-Config!$B$7-Config!$B$8))) -> 133.20853 | F43: =IF(D43="","",D43-$D$41) -> 16.517857
A44: ="Queda de "&ROUND(B44*100,0)&"%" -> Queda de 30% | B44: 0.3 | C44: =IF(ISNUMBER($B$12),$B$12*(1-B44),"") -> 196 | D44: =IF(OR(C44="",C44=0,NOT(ISNUMBER($B$11))),"",$B$11/C44) -> 94.387755 | E44: =IF(D44="","",IF(Config!$B$10<>"Sim","margens inválidas (Config)",D44/(1-Config!$B$7-Config!$B$8))) -> 152.23831 | F44: =IF(D44="","",D44-$D$41) -> 28.316327

Sheet Config
A1: Configurações
A2: Células amarelas: você preenche. Margem e impostos definem a hora mínima a cobrar.
A4: Nome do escritório | B4: Ferraz & Lima Advocacia (exemplo fictício)
A5: Mês de referência | B5: Setembro de 2026
A6: Data de referência | B6: 46279
A7: Margem desejada sobre o preço (%) | B7: 0.3 | C7: Quanto do preço deve sobrar depois de pagar o custo do escritório. 30% é um ponto de partida; ajuste ao seu mercado.
A8: Impostos e taxas sobre o que entra (%) | B8: 0.08 | C8: Percentual que sai de cada real recebido (imposto do escritório e taxa de recebimento). Exemplo; confira com o seu contador.
A9: Arredondar a hora mínima para múltiplos de (R$) | B9: 5 | C9: Só para o número ficar redondo na proposta.
A10: Margem e impostos conferem? (calculado) | B10: =IF(AND(ISNUMBER(B7),ISNUMBER(B8)),IF(AND(B7>=0,B7<1,B8>=0,B8<1,B7+B8<1),"Sim","Não"),"Não") -> Sim | C10: "Não" suspende a hora mínima em todas as abas: cada percentual precisa ficar entre 0 % e 99 %, e margem + impostos abaixo de 100 %.
A11: A hora mínima a cobrar é: custo-hora ÷ (1 − margem − impostos). Assim a margem é calculada sobre o preço, e não sobre o custo.
A12: Esta é a hora mínima do kit (no exemplo: R$ 106,57, arredondada para R$ 110). A planilha 06 usa a mesma conta; a planilha 08 acrescenta uma folga de 20 % para horas não previstas e por isso mostra um valor maior ("hora mínima com folga").

Sheet Custos fixos
A1: Custos fixos do mês
A2: Tudo que o escritório paga todo mês mesmo sem nenhum caso novo. Preencha de cima para baixo, sem pular linha.
A4: Custo fixo | B4: Valor mensal (R$) | C4: Observação
A5: Aluguel e condomínio | B5: 2800
A6: Contador | B6: 600
A7: Sistemas e assinaturas | B7: 450
A8: Telefone e internet | B8: 220
A9: Anuidades OAB e cursos | B9: 250
A10: Marketing e site | B10: 400
A11: Estagiária (bolsa) | B11: 1400 | C11: Mesma pessoa da aba Pessoas (marcada "Sim" lá)
A12: Material, correio e outros | B12: 380
A36: Total de custos fixos | B36: =SUM(B5:B34) -> 6500
A38: Pró-labore dos sócios vai na aba Pessoas. Se alguém da equipe já aparece aqui (bolsa de estágio, salário), marque "Sim" na aba Pessoas para não contar duas vezes.

Sheet Pessoas
A1: Pessoas, pró-labore e horas faturáveis
A2: Uma linha por pessoa que trabalha nos casos. Horas faturáveis: as que podem ser cobradas de algum cliente (reunião interna e administração não contam).
A4: Pessoa | B4: Papel | C4: Pró-labore ou salário (R$/mês) | D4: Já está nos custos fixos? | E4: Horas de trabalho no mês | F4: Horas faturáveis no mês | G4: Ocupação | H4: Custo direto por hora | I4: Custo-hora completo | J4: Hora mínima a cobrar
A5: Marina Ferraz | B5: Sócia · cível e empresarial | C5: 6000 | D5: Não | E5: 160 | F5: 110 | G5: =IF(OR(A5="",E5="",E5=0),"",F5/E5) -> 0.6875 | H5: =IF(A5="","",IF(NOT(ISNUMBER(C5)),"falta o pró-labore",IF(OR(NOT(ISNUMBER(F5)),F5=0),"faltam as horas faturáveis",C5/F5))) -> 54.545455 | I5: =IF(H5="","",IF(NOT(ISNUMBER(H5)),H5,IF(NOT(ISNUMBER(Painel!$B$19)),"cadastro incompleto",H5+Painel!$B$19))) -> 72.75974 | J5: =IF(I5="","",IF(NOT(ISNUMBER(I5)),I5,IF(Config!$B$10<>"Sim","margens inválidas (Config)",I5/(1-Config!$B$7-Config!$B$8)))) -> 117.35442 | K5: =IF(AND(A5<>"",OR(NOT(ISNUMBER(C5)),NOT(ISNUMBER(F5)))),1,0) -> 0
A6: Rafael Lima | B6: Sócio · trabalhista e previdenciário | C6: 6000 | D6: Não | E6: 160 | F6: 110 | G6: =IF(OR(A6="",E6="",E6=0),"",F6/E6) -> 0.6875 | H6: =IF(A6="","",IF(NOT(ISNUMBER(C6)),"falta o pró-labore",IF(OR(NOT(ISNUMBER(F6)),F6=0),"faltam as horas faturáveis",C6/F6))) -> 54.545455 | I6: =IF(H6="","",IF(NOT(ISNUMBER(H6)),H6,IF(NOT(ISNUMBER(Painel!$B$19)),"cadastro incompleto",H6+Painel!$B$19))) -> 72.75974 | J6: =IF(I6="","",IF(NOT(ISNUMBER(I6)),I6,IF(Config!$B$10<>"Sim","margens inválidas (Config)",I6/(1-Config!$B$7-Config!$B$8)))) -> 117.35442 | K6: =IF(AND(A6<>"",OR(NOT(ISNUMBER(C6)),NOT(ISNUMBER(F6)))),1,0) -> 0
A7: Júlia Prado | B7: Estagiária | C7: 1400 | D7: Sim | E7: 120 | F7: 60 | G7: =IF(OR(A7="",E7="",E7=0),"",F7/E7) -> 0.5 | H7: =IF(A7="","",IF(NOT(ISNUMBER(C7)),"falta o pró-labore",IF(OR(NOT(ISNUMBER(F7)),F7=0),"faltam as horas faturáveis",C7/F7))) -> 23.333333 | I7: =IF(H7="","",IF(NOT(ISNUMBER(H7)),H7,IF(NOT(ISNUMBER(Painel!$B$19)),"cadastro incompleto",H7+Painel!$B$19))) -> 41.547619 | J7: =IF(I7="","",IF(NOT(ISNUMBER(I7)),I7,IF(Config!$B$10<>"Sim","margens inválidas (Config)",I7/(1-Config!$B$7-Config!$B$8)))) -> 67.012289 | K7: =IF(AND(A7<>"",OR(NOT(ISNUMBER(C7)),NOT(ISNUMBER(F7)))),1,0) -> 0
G8: =IF(OR(A8="",E8="",E8=0),"",F8/E8) | H8: =IF(A8="","",IF(NOT(ISNUMBER(C8)),"falta o pró-labore",IF(OR(NOT(ISNUMBER(F8)),F8=0),"faltam as horas faturáveis",C8/F8))) | I8: =IF(H8="","",IF(NOT(ISNUMBER(H8)),H8,IF(NOT(ISNUMBER(Painel!$B$19)),"cadastro incompleto",H8+Painel!$B$19))) | J8: =IF(I8="","",IF(NOT(ISNUMBER(I8)),I8,IF(Config!$B$10<>"Sim","margens inválidas (Config)",I8/(1-Config!$B$7-Config!$B$8)))) | K8: =IF(AND(A8<>"",OR(NOT(ISNUMBER(C8)),NOT(ISNUMBER(F8)))),1,0) -> 0
G9: =IF(OR(A9="",E9="",E9=0),"",F9/E9) | H9: =IF(A9="","",IF(NOT(ISNUMBER(C9)),"falta o pró-labore",IF(OR(NOT(ISNUMBER(F9)),F9=0),"faltam as horas faturáveis",C9/F9))) | I9: =IF(H9="","",IF(NOT(ISNUMBER(H9)),H9,IF(NOT(ISNUMBER(Painel!$B$19)),"cadastro incompleto",H9+Painel!$B$19))) | J9: =IF(I9="","",IF(NOT(ISNUMBER(I9)),I9,IF(Config!$B$10<>"Sim","margens inválidas (Config)",I9/(1-Config!$B$7-Config!$B$8)))) | K9: =IF(AND(A9<>"",OR(NOT(ISNUMBER(C9)),NOT(ISNUMBER(F9)))),1,0) -> 0
G10: =IF(OR(A10="",E10="",E10=0),"",F10/E10) | H10: =IF(A10="","",IF(NOT(ISNUMBER(C10)),"falta o pró-labore",IF(OR(NOT(ISNUMBER(F10)),F10=0),"faltam as horas faturáveis",C10/F10))) | I10: =IF(H10="","",IF(NOT(ISNUMBER(H10)),H10,IF(NOT(ISNUMBER(Painel!$B$19)),"cadastro incompleto",H10+Painel!$B$19))) | J10: =IF(I10="","",IF(NOT(ISNUMBER(I10)),I10,IF(Config!$B$10<>"Sim","margens inválidas (Config)",I10/(1-Config!$B$7-Config!$B$8)))) | K10: =IF(AND(A10<>"",OR(NOT(ISNUMBER(C10)),NOT(ISNUMBER(F10)))),1,0) -> 0
G11: =IF(OR(A11="",E11="",E11=0),"",F11/E11) | H11: =IF(A11="","",IF(NOT(ISNUMBER(C11)),"falta o pró-labore",IF(OR(NOT(ISNUMBER(F11)),F11=0),"faltam as horas faturáveis",C11/F11))) | I11: =IF(H11="","",IF(NOT(ISNUMBER(H11)),H11,IF(NOT(ISNUMBER(Painel!$B$19)),"cadastro incompleto",H11+Painel!$B$19))) | J11: =IF(I11="","",IF(NOT(ISNUMBER(I11)),I11,IF(Config!$B$10<>"Sim","margens inválidas (Config)",I11/(1-Config!$B$7-Config!$B$8)))) | K11: =IF(AND(A11<>"",OR(NOT(ISNUMBER(C11)),NOT(ISNUMBER(F11)))),1,0) -> 0
G12: =IF(OR(A12="",E12="",E12=0),"",F12/E12) | H12: =IF(A12="","",IF(NOT(ISNUMBER(C12)),"falta o pró-labore",IF(OR(NOT(ISNUMBER(F12)),F12=0),"faltam as horas faturáveis",C12/F12))) | I12: =IF(H12="","",IF(NOT(ISNUMBER(H12)),H12,IF(NOT(ISNUMBER(Painel!$B$19)),"cadastro incompleto",H12+Painel!$B$19))) | J12: =IF(I12="","",IF(NOT(ISNUMBER(I12)),I12,IF(Config!$B$10<>"Sim","margens inválidas (Config)",I12/(1-Config!$B$7-Config!$B$8)))) | K12: =IF(AND(A12<>"",OR(NOT(ISNUMBER(C12)),NOT(ISNUMBER(F12)))),1,0) -> 0
G13: =IF(OR(A13="",E13="",E13=0),"",F13/E13) | H13: =IF(A13="","",IF(NOT(ISNUMBER(C13)),"falta o pró-labore",IF(OR(NOT(ISNUMBER(F13)),F13=0),"faltam as horas faturáveis",C13/F13))) | I13: =IF(H13="","",IF(NOT(ISNUMBER(H13)),H13,IF(NOT(ISNUMBER(Painel!$B$19)),"cadastro incompleto",H13+Painel!$B$19))) | J13: =IF(I13="","",IF(NOT(ISNUMBER(I13)),I13,IF(Config!$B$10<>"Sim","margens inválidas (Config)",I13/(1-Config!$B$7-Config!$B$8)))) | K13: =IF(AND(A13<>"",OR(NOT(ISNUMBER(C13)),NOT(ISNUMBER(F13)))),1,0) -> 0
G14: =IF(OR(A14="",E14="",E14=0),"",F14/E14) | H14: =IF(A14="","",IF(NOT(ISNUMBER(C14)),"falta o pró-labore",IF(OR(NOT(ISNUMBER(F14)),F14=0),"faltam as horas faturáveis",C14/F14))) | I14: =IF(H14="","",IF(NOT(ISNUMBER(H14)),H14,IF(NOT(ISNUMBER(Painel!$B$19)),"cadastro incompleto",H14+Painel!$B$19))) | J14: =IF(I14="","",IF(NOT(ISNUMBER(I14)),I14,IF(Config!$B$10<>"Sim","margens inválidas (Config)",I14/(1-Config!$B$7-Config!$B$8)))) | K14: =IF(AND(A14<>"",OR(NOT(ISNUMBER(C14)),NOT(ISNUMBER(F14)))),1,0) -> 0
A16: Custo direto por hora = pró-labore ou salário ÷ horas faturáveis. Custo-hora completo = custo direto + rateio dos custos indiretos do escritório por hora faturável (o rateio é calculado no Painel). Hora mínima = custo-hora completo ÷ (1 − margem − impostos).
A17: Horas de trabalho no mês: 160 para tempo integral; 120 para meio período. Horas faturáveis: uma média realista; 60% a 70% das horas de trabalho já é bom para quem também administra o escritório.
