Workbook

Sheet Como usar
A1: Caixa do escritório
A2: Kit de Gestão para Advogados · Seu Sócio Gestor · versão 1.0 (setembro de 2026)
A4: O que esta planilha faz | B4: Você lança o que entra (honorários por cliente e caso) e o que sai (custo fixo, pró-labore, impostos, custas). Ela mostra o mês: entrou, saiu, sobrou, saldo acumulado, a receber, a pagar; para onde foi o dinheiro por categoria, quanto veio de cada cliente e o ano mês a mês com gráfico.
A5: Passo 1 | B5: Em Config, preencha o nome do escritório, o ano, o saldo que havia em caixa antes do primeiro lançamento e o mês do painel. Ajuste categorias e clientes de cima para baixo, sem pular linha.
A6: Passo 2 | B6: Em Lançamentos, uma linha por movimento: data, tipo (entrada ou saída), categoria, cliente, caso, descrição, valor, forma e Pago?. Honorário faturado e ainda não recebido entra com Pago? = Não e aparece em A receber; quando cair na conta, troque para Sim.
A7: Passo 3 | B7: Em Painel, escolha o mês em Config e leia de cima para baixo. Só o que está com Pago? = Sim conta como caixa; o resto é previsão.
A8: Rotina de sexta | B8: 15 minutos: lançar o que entrou e saiu na semana, conferir A receber contra o extrato e marcar Sim no que caiu. No fechamento do mês, olhar Sobrou e Saldo acumulado antes de decidir retirada extra ou gasto grande.
A9: Ligação com as outras planilhas | B9: O total de entradas do mês alimenta a planilha 10 (provisão de impostos) e a 17 (painel); as saídas de pró-labore, a 11; o saldo acumulado e o custo fixo, a 12 (reserva); as entradas por categoria, a 18 (resultado). Cada arquivo tem a própria aba de entrada amarela: copie os números do painel. Cada honorário lançado aqui é uma parcela marcada como paga na 14.
A10: Com a IA | B10: Copie "Para onde foi o dinheiro" e "O ano, mês a mês" e use o prompt "Caixa 01 · Explicar o mês do caixa" da biblioteca do kit. Nunca cole nome de cliente ou número de processo na IA sem necessidade: use a coluna Categoria.
A11: Legenda | B11: Células amarelas: você preenche. Brancas: calculadas. Não é preciso mexer em nada fora do amarelo.
A12: Proteção | B12: Fórmulas protegidas sem senha. Para editar: Revisar > Desproteger planilha (Excel) ou Dados > Proteger intervalos (Google Sheets).
A13: Requisitos | B13: Excel 2016 ou mais novo, Microsoft 365 ou Google Sheets (só funções do Excel 2007+; nada de MÍNIMOSES, MÁXIMOSES ou UNIRTEXTO). No celular abre nos aplicativos; para preencher, use o computador.
A14: Google Sheets | B14: Faça upload no Google Drive e abra com o Google Sheets. Fórmulas, listas, cores e gráficos funcionam.
A15: Exemplos | B15: Ferraz & Lima Advocacia é um escritório fictício. Clientes, processos, nomes e valores são inventados. Apague-os antes de começar. Datas de prazo do exemplo são relativas a hoje.
A16: Suporte | B16: suporte@seusociogestor.com.br · resposta em até 5 dias úteis · reembolso em até 7 dias pelo mesmo canal.

Sheet Painel
A1: =Config!B4&" · Caixa do escritório · "&Config!B6&" de "&Config!B5 -> Ferraz & Lima Advocacia (exemplo fictício) · Caixa do escritório · Setembro de 2026
A2: Nada para digitar aqui. Escolha o mês em Config; tudo vem de Lançamentos. Só o que está com Pago? = Sim conta como caixa.
A4: Entrou no mês | C4: Saiu no mês | E4: Sobrou no mês | G4: Saldo acumulado | I4: A receber (Pago? = Não) | K4: A pagar (Pago? = Não)
A5: =SUMIFS(Lançamentos!$G$5:$G$604,Lançamentos!$B$5:$B$604,"Entrada",Lançamentos!$I$5:$I$604,"Sim",Lançamentos!$J$5:$J$604,Config!$B$7,Lançamentos!$K$5:$K$604,Config!$B$5) -> 5220 | C5: =SUMIFS(Lançamentos!$G$5:$G$604,Lançamentos!$B$5:$B$604,"Saída",Lançamentos!$I$5:$I$604,"Sim",Lançamentos!$J$5:$J$604,Config!$B$7,Lançamentos!$K$5:$K$604,Config!$B$5) -> 5320 | E5: =A5-C5 -> -100 | G5: =Config!$B$8+SUMIFS(Lançamentos!$G$5:$G$604,Lançamentos!$B$5:$B$604,"Entrada",Lançamentos!$I$5:$I$604,"Sim",Lançamentos!$A$5:$A$604,"<="&DATE(Config!$B$5,Config!$B$7+1,0))-SUMIFS(Lançamentos!$G$5:$G$604,Lançamentos!$B$5:$B$604,"Saída",Lançamentos!$I$5:$I$604,"Sim",Lançamentos!$A$5:$A$604,"<="&DATE(Config!$B$5,Config!$B$7+1,0)) -> 43683 | I5: =SUMIFS(Lançamentos!$G$5:$G$604,Lançamentos!$B$5:$B$604,"Entrada",Lançamentos!$I$5:$I$604,"Não") -> 27330 | K5: =SUMIFS(Lançamentos!$G$5:$G$604,Lançamentos!$B$5:$B$604,"Saída",Lançamentos!$I$5:$I$604,"Não") -> 15402
A7: Para onde foi o dinheiro
A8: Categoria de saída | B8: Valor no mês | C8: % do total | D8: Mês anterior | E8: Acumulado no ano | F8: Barra
A9: =IF(Config!$F$5="","",Config!$F$5) -> Pró-labore dos sócios | B9: =IF(Config!$F$5="","",SUMIFS(Lançamentos!$G$5:$G$604,Lançamentos!$B$5:$B$604,"Saída",Lançamentos!$I$5:$I$604,"Sim",Lançamentos!$J$5:$J$604,Config!$B$7,Lançamentos!$K$5:$K$604,Config!$B$5,Lançamentos!$C$5:$C$604,Config!$F$5)) -> 0 | C9: =IF(OR(Config!$F$5="",$C$5=0),"",B9/$C$5) -> 0 | D9: =IF(Config!$F$5="","",IF(Config!$B$7=1,SUMIFS(Lançamentos!$G$5:$G$604,Lançamentos!$B$5:$B$604,"Saída",Lançamentos!$I$5:$I$604,"Sim",Lançamentos!$J$5:$J$604,12,Lançamentos!$K$5:$K$604,Config!$B$5-1,Lançamentos!$C$5:$C$604,Config!$F$5),SUMIFS(Lançamentos!$G$5:$G$604,Lançamentos!$B$5:$B$604,"Saída",Lançamentos!$I$5:$I$604,"Sim",Lançamentos!$J$5:$J$604,Config!$B$7-1,Lançamentos!$K$5:$K$604,Config!$B$5,Lançamentos!$C$5:$C$604,Config!$F$5))) -> 12000 | E9: =IF(Config!$F$5="","",SUMIFS(Lançamentos!$G$5:$G$604,Lançamentos!$B$5:$B$604,"Saída",Lançamentos!$I$5:$I$604,"Sim",Lançamentos!$C$5:$C$604,Config!$F$5,Lançamentos!$K$5:$K$604,Config!$B$5,Lançamentos!$J$5:$J$604,"<="&Config!$B$7)) -> 112405 | F9: =IF(C9="","",REPT("█",ROUND(C9*40,0)))
A10: =IF(Config!$F$6="","",Config!$F$6) -> Aluguel e condomínio | B10: =IF(Config!$F$6="","",SUMIFS(Lançamentos!$G$5:$G$604,Lançamentos!$B$5:$B$604,"Saída",Lançamentos!$I$5:$I$604,"Sim",Lançamentos!$J$5:$J$604,Config!$B$7,Lançamentos!$K$5:$K$604,Config!$B$5,Lançamentos!$C$5:$C$604,Config!$F$6)) -> 2800 | C10: =IF(OR(Config!$F$6="",$C$5=0),"",B10/$C$5) -> 0.52631579 | D10: =IF(Config!$F$6="","",IF(Config!$B$7=1,SUMIFS(Lançamentos!$G$5:$G$604,Lançamentos!$B$5:$B$604,"Saída",Lançamentos!$I$5:$I$604,"Sim",Lançamentos!$J$5:$J$604,12,Lançamentos!$K$5:$K$604,Config!$B$5-1,Lançamentos!$C$5:$C$604,Config!$F$6),SUMIFS(Lançamentos!$G$5:$G$604,Lançamentos!$B$5:$B$604,"Saída",Lançamentos!$I$5:$I$604,"Sim",Lançamentos!$J$5:$J$604,Config!$B$7-1,Lançamentos!$K$5:$K$604,Config!$B$5,Lançamentos!$C$5:$C$604,Config!$F$6))) -> 2800 | E10: =IF(Config!$F$6="","",SUMIFS(Lançamentos!$G$5:$G$604,Lançamentos!$B$5:$B$604,"Saída",Lançamentos!$I$5:$I$604,"Sim",Lançamentos!$C$5:$C$604,Config!$F$6,Lançamentos!$K$5:$K$604,Config!$B$5,Lançamentos!$J$5:$J$604,"<="&Config!$B$7)) -> 25200 | F10: =IF(C10="","",REPT("█",ROUND(C10*40,0))) -> █████████████████████
A11: =IF(Config!$F$7="","",Config!$F$7) -> Contador | B11: =IF(Config!$F$7="","",SUMIFS(Lançamentos!$G$5:$G$604,Lançamentos!$B$5:$B$604,"Saída",Lançamentos!$I$5:$I$604,"Sim",Lançamentos!$J$5:$J$604,Config!$B$7,Lançamentos!$K$5:$K$604,Config!$B$5,Lançamentos!$C$5:$C$604,Config!$F$7)) -> 600 | C11: =IF(OR(Config!$F$7="",$C$5=0),"",B11/$C$5) -> 0.11278195 | D11: =IF(Config!$F$7="","",IF(Config!$B$7=1,SUMIFS(Lançamentos!$G$5:$G$604,Lançamentos!$B$5:$B$604,"Saída",Lançamentos!$I$5:$I$604,"Sim",Lançamentos!$J$5:$J$604,12,Lançamentos!$K$5:$K$604,Config!$B$5-1,Lançamentos!$C$5:$C$604,Config!$F$7),SUMIFS(Lançamentos!$G$5:$G$604,Lançamentos!$B$5:$B$604,"Saída",Lançamentos!$I$5:$I$604,"Sim",Lançamentos!$J$5:$J$604,Config!$B$7-1,Lançamentos!$K$5:$K$604,Config!$B$5,Lançamentos!$C$5:$C$604,Config!$F$7))) -> 600 | E11: =IF(Config!$F$7="","",SUMIFS(Lançamentos!$G$5:$G$604,Lançamentos!$B$5:$B$604,"Saída",Lançamentos!$I$5:$I$604,"Sim",Lançamentos!$C$5:$C$604,Config!$F$7,Lançamentos!$K$5:$K$604,Config!$B$5,Lançamentos!$J$5:$J$604,"<="&Config!$B$7)) -> 5400 | F11: =IF(C11="","",REPT("█",ROUND(C11*40,0))) -> █████
A12: =IF(Config!$F$8="","",Config!$F$8) -> Sistemas e assinaturas | B12: =IF(Config!$F$8="","",SUMIFS(Lançamentos!$G$5:$G$604,Lançamentos!$B$5:$B$604,"Saída",Lançamentos!$I$5:$I$604,"Sim",Lançamentos!$J$5:$J$604,Config!$B$7,Lançamentos!$K$5:$K$604,Config!$B$5,Lançamentos!$C$5:$C$604,Config!$F$8)) -> 450 | C12: =IF(OR(Config!$F$8="",$C$5=0),"",B12/$C$5) -> 0.084586466 | D12: =IF(Config!$F$8="","",IF(Config!$B$7=1,SUMIFS(Lançamentos!$G$5:$G$604,Lançamentos!$B$5:$B$604,"Saída",Lançamentos!$I$5:$I$604,"Sim",Lançamentos!$J$5:$J$604,12,Lançamentos!$K$5:$K$604,Config!$B$5-1,Lançamentos!$C$5:$C$604,Config!$F$8),SUMIFS(Lançamentos!$G$5:$G$604,Lançamentos!$B$5:$B$604,"Saída",Lançamentos!$I$5:$I$604,"Sim",Lançamentos!$J$5:$J$604,Config!$B$7-1,Lançamentos!$K$5:$K$604,Config!$B$5,Lançamentos!$C$5:$C$604,Config!$F$8))) -> 450 | E12: =IF(Config!$F$8="","",SUMIFS(Lançamentos!$G$5:$G$604,Lançamentos!$B$5:$B$604,"Saída",Lançamentos!$I$5:$I$604,"Sim",Lançamentos!$C$5:$C$604,Config!$F$8,Lançamentos!$K$5:$K$604,Config!$B$5,Lançamentos!$J$5:$J$604,"<="&Config!$B$7)) -> 4050 | F12: =IF(C12="","",REPT("█",ROUND(C12*40,0))) -> ███
A13: =IF(Config!$F$9="","",Config!$F$9) -> Telefone e internet | B13: =IF(Config!$F$9="","",SUMIFS(Lançamentos!$G$5:$G$604,Lançamentos!$B$5:$B$604,"Saída",Lançamentos!$I$5:$I$604,"Sim",Lançamentos!$J$5:$J$604,Config!$B$7,Lançamentos!$K$5:$K$604,Config!$B$5,Lançamentos!$C$5:$C$604,Config!$F$9)) -> 0 | C13: =IF(OR(Config!$F$9="",$C$5=0),"",B13/$C$5) -> 0 | D13: =IF(Config!$F$9="","",IF(Config!$B$7=1,SUMIFS(Lançamentos!$G$5:$G$604,Lançamentos!$B$5:$B$604,"Saída",Lançamentos!$I$5:$I$604,"Sim",Lançamentos!$J$5:$J$604,12,Lançamentos!$K$5:$K$604,Config!$B$5-1,Lançamentos!$C$5:$C$604,Config!$F$9),SUMIFS(Lançamentos!$G$5:$G$604,Lançamentos!$B$5:$B$604,"Saída",Lançamentos!$I$5:$I$604,"Sim",Lançamentos!$J$5:$J$604,Config!$B$7-1,Lançamentos!$K$5:$K$604,Config!$B$5,Lançamentos!$C$5:$C$604,Config!$F$9))) -> 220 | E13: =IF(Config!$F$9="","",SUMIFS(Lançamentos!$G$5:$G$604,Lançamentos!$B$5:$B$604,"Saída",Lançamentos!$I$5:$I$604,"Sim",Lançamentos!$C$5:$C$604,Config!$F$9,Lançamentos!$K$5:$K$604,Config!$B$5,Lançamentos!$J$5:$J$604,"<="&Config!$B$7)) -> 1760 | F13: =IF(C13="","",REPT("█",ROUND(C13*40,0)))
A14: =IF(Config!$F$10="","",Config!$F$10) -> Anuidades OAB e cursos | B14: =IF(Config!$F$10="","",SUMIFS(Lançamentos!$G$5:$G$604,Lançamentos!$B$5:$B$604,"Saída",Lançamentos!$I$5:$I$604,"Sim",Lançamentos!$J$5:$J$604,Config!$B$7,Lançamentos!$K$5:$K$604,Config!$B$5,Lançamentos!$C$5:$C$604,Config!$F$10)) -> 0 | C14: =IF(OR(Config!$F$10="",$C$5=0),"",B14/$C$5) -> 0 | D14: =IF(Config!$F$10="","",IF(Config!$B$7=1,SUMIFS(Lançamentos!$G$5:$G$604,Lançamentos!$B$5:$B$604,"Saída",Lançamentos!$I$5:$I$604,"Sim",Lançamentos!$J$5:$J$604,12,Lançamentos!$K$5:$K$604,Config!$B$5-1,Lançamentos!$C$5:$C$604,Config!$F$10),SUMIFS(Lançamentos!$G$5:$G$604,Lançamentos!$B$5:$B$604,"Saída",Lançamentos!$I$5:$I$604,"Sim",Lançamentos!$J$5:$J$604,Config!$B$7-1,Lançamentos!$K$5:$K$604,Config!$B$5,Lançamentos!$C$5:$C$604,Config!$F$10))) -> 250 | E14: =IF(Config!$F$10="","",SUMIFS(Lançamentos!$G$5:$G$604,Lançamentos!$B$5:$B$604,"Saída",Lançamentos!$I$5:$I$604,"Sim",Lançamentos!$C$5:$C$604,Config!$F$10,Lançamentos!$K$5:$K$604,Config!$B$5,Lançamentos!$J$5:$J$604,"<="&Config!$B$7)) -> 2000 | F14: =IF(C14="","",REPT("█",ROUND(C14*40,0)))
A15: =IF(Config!$F$11="","",Config!$F$11) -> Marketing e site | B15: =IF(Config!$F$11="","",SUMIFS(Lançamentos!$G$5:$G$604,Lançamentos!$B$5:$B$604,"Saída",Lançamentos!$I$5:$I$604,"Sim",Lançamentos!$J$5:$J$604,Config!$B$7,Lançamentos!$K$5:$K$604,Config!$B$5,Lançamentos!$C$5:$C$604,Config!$F$11)) -> 0 | C15: =IF(OR(Config!$F$11="",$C$5=0),"",B15/$C$5) -> 0 | D15: =IF(Config!$F$11="","",IF(Config!$B$7=1,SUMIFS(Lançamentos!$G$5:$G$604,Lançamentos!$B$5:$B$604,"Saída",Lançamentos!$I$5:$I$604,"Sim",Lançamentos!$J$5:$J$604,12,Lançamentos!$K$5:$K$604,Config!$B$5-1,Lançamentos!$C$5:$C$604,Config!$F$11),SUMIFS(Lançamentos!$G$5:$G$604,Lançamentos!$B$5:$B$604,"Saída",Lançamentos!$I$5:$I$604,"Sim",Lançamentos!$J$5:$J$604,Config!$B$7-1,Lançamentos!$K$5:$K$604,Config!$B$5,Lançamentos!$C$5:$C$604,Config!$F$11))) -> 400 | E15: =IF(Config!$F$11="","",SUMIFS(Lançamentos!$G$5:$G$604,Lançamentos!$B$5:$B$604,"Saída",Lançamentos!$I$5:$I$604,"Sim",Lançamentos!$C$5:$C$604,Config!$F$11,Lançamentos!$K$5:$K$604,Config!$B$5,Lançamentos!$J$5:$J$604,"<="&Config!$B$7)) -> 3200 | F15: =IF(C15="","",REPT("█",ROUND(C15*40,0)))
A16: =IF(Config!$F$12="","",Config!$F$12) -> Estagiária (bolsa) | B16: =IF(Config!$F$12="","",SUMIFS(Lançamentos!$G$5:$G$604,Lançamentos!$B$5:$B$604,"Saída",Lançamentos!$I$5:$I$604,"Sim",Lançamentos!$J$5:$J$604,Config!$B$7,Lançamentos!$K$5:$K$604,Config!$B$5,Lançamentos!$C$5:$C$604,Config!$F$12)) -> 1400 | C16: =IF(OR(Config!$F$12="",$C$5=0),"",B16/$C$5) -> 0.26315789 | D16: =IF(Config!$F$12="","",IF(Config!$B$7=1,SUMIFS(Lançamentos!$G$5:$G$604,Lançamentos!$B$5:$B$604,"Saída",Lançamentos!$I$5:$I$604,"Sim",Lançamentos!$J$5:$J$604,12,Lançamentos!$K$5:$K$604,Config!$B$5-1,Lançamentos!$C$5:$C$604,Config!$F$12),SUMIFS(Lançamentos!$G$5:$G$604,Lançamentos!$B$5:$B$604,"Saída",Lançamentos!$I$5:$I$604,"Sim",Lançamentos!$J$5:$J$604,Config!$B$7-1,Lançamentos!$K$5:$K$604,Config!$B$5,Lançamentos!$C$5:$C$604,Config!$F$12))) -> 1400 | E16: =IF(Config!$F$12="","",SUMIFS(Lançamentos!$G$5:$G$604,Lançamentos!$B$5:$B$604,"Saída",Lançamentos!$I$5:$I$604,"Sim",Lançamentos!$C$5:$C$604,Config!$F$12,Lançamentos!$K$5:$K$604,Config!$B$5,Lançamentos!$J$5:$J$604,"<="&Config!$B$7)) -> 12600 | F16: =IF(C16="","",REPT("█",ROUND(C16*40,0))) -> ███████████
A17: =IF(Config!$F$13="","",Config!$F$13) -> Material, correio e outros | B17: =IF(Config!$F$13="","",SUMIFS(Lançamentos!$G$5:$G$604,Lançamentos!$B$5:$B$604,"Saída",Lançamentos!$I$5:$I$604,"Sim",Lançamentos!$J$5:$J$604,Config!$B$7,Lançamentos!$K$5:$K$604,Config!$B$5,Lançamentos!$C$5:$C$604,Config!$F$13)) -> 0 | C17: =IF(OR(Config!$F$13="",$C$5=0),"",B17/$C$5) -> 0 | D17: =IF(Config!$F$13="","",IF(Config!$B$7=1,SUMIFS(Lançamentos!$G$5:$G$604,Lançamentos!$B$5:$B$604,"Saída",Lançamentos!$I$5:$I$604,"Sim",Lançamentos!$J$5:$J$604,12,Lançamentos!$K$5:$K$604,Config!$B$5-1,Lançamentos!$C$5:$C$604,Config!$F$13),SUMIFS(Lançamentos!$G$5:$G$604,Lançamentos!$B$5:$B$604,"Saída",Lançamentos!$I$5:$I$604,"Sim",Lançamentos!$J$5:$J$604,Config!$B$7-1,Lançamentos!$K$5:$K$604,Config!$B$5,Lançamentos!$C$5:$C$604,Config!$F$13))) -> 380 | E17: =IF(Config!$F$13="","",SUMIFS(Lançamentos!$G$5:$G$604,Lançamentos!$B$5:$B$604,"Saída",Lançamentos!$I$5:$I$604,"Sim",Lançamentos!$C$5:$C$604,Config!$F$13,Lançamentos!$K$5:$K$604,Config!$B$5,Lançamentos!$J$5:$J$604,"<="&Config!$B$7)) -> 3040 | F17: =IF(C17="","",REPT("█",ROUND(C17*40,0)))
A18: =IF(Config!$F$14="","",Config!$F$14) -> Impostos e taxas | B18: =IF(Config!$F$14="","",SUMIFS(Lançamentos!$G$5:$G$604,Lançamentos!$B$5:$B$604,"Saída",Lançamentos!$I$5:$I$604,"Sim",Lançamentos!$J$5:$J$604,Config!$B$7,Lançamentos!$K$5:$K$604,Config!$B$5,Lançamentos!$C$5:$C$604,Config!$F$14)) -> 0 | C18: =IF(OR(Config!$F$14="",$C$5=0),"",B18/$C$5) -> 0 | D18: =IF(Config!$F$14="","",IF(Config!$B$7=1,SUMIFS(Lançamentos!$G$5:$G$604,Lançamentos!$B$5:$B$604,"Saída",Lançamentos!$I$5:$I$604,"Sim",Lançamentos!$J$5:$J$604,12,Lançamentos!$K$5:$K$604,Config!$B$5-1,Lançamentos!$C$5:$C$604,Config!$F$14),SUMIFS(Lançamentos!$G$5:$G$604,Lançamentos!$B$5:$B$604,"Saída",Lançamentos!$I$5:$I$604,"Sim",Lançamentos!$J$5:$J$604,Config!$B$7-1,Lançamentos!$K$5:$K$604,Config!$B$5,Lançamentos!$C$5:$C$604,Config!$F$14))) -> 2357 | E18: =IF(Config!$F$14="","",SUMIFS(Lançamentos!$G$5:$G$604,Lançamentos!$B$5:$B$604,"Saída",Lançamentos!$I$5:$I$604,"Sim",Lançamentos!$C$5:$C$604,Config!$F$14,Lançamentos!$K$5:$K$604,Config!$B$5,Lançamentos!$J$5:$J$604,"<="&Config!$B$7)) -> 16087 | F18: =IF(C18="","",REPT("█",ROUND(C18*40,0)))
A19: =IF(Config!$F$15="","",Config!$F$15) -> Custas e despesas de processo | B19: =IF(Config!$F$15="","",SUMIFS(Lançamentos!$G$5:$G$604,Lançamentos!$B$5:$B$604,"Saída",Lançamentos!$I$5:$I$604,"Sim",Lançamentos!$J$5:$J$604,Config!$B$7,Lançamentos!$K$5:$K$604,Config!$B$5,Lançamentos!$C$5:$C$604,Config!$F$15)) -> 70 | C19: =IF(OR(Config!$F$15="",$C$5=0),"",B19/$C$5) -> 0.013157895 | D19: =IF(Config!$F$15="","",IF(Config!$B$7=1,SUMIFS(Lançamentos!$G$5:$G$604,Lançamentos!$B$5:$B$604,"Saída",Lançamentos!$I$5:$I$604,"Sim",Lançamentos!$J$5:$J$604,12,Lançamentos!$K$5:$K$604,Config!$B$5-1,Lançamentos!$C$5:$C$604,Config!$F$15),SUMIFS(Lançamentos!$G$5:$G$604,Lançamentos!$B$5:$B$604,"Saída",Lançamentos!$I$5:$I$604,"Sim",Lançamentos!$J$5:$J$604,Config!$B$7-1,Lançamentos!$K$5:$K$604,Config!$B$5,Lançamentos!$C$5:$C$604,Config!$F$15))) -> 380 | E19: =IF(Config!$F$15="","",SUMIFS(Lançamentos!$G$5:$G$604,Lançamentos!$B$5:$B$604,"Saída",Lançamentos!$I$5:$I$604,"Sim",Lançamentos!$C$5:$C$604,Config!$F$15,Lançamentos!$K$5:$K$604,Config!$B$5,Lançamentos!$J$5:$J$604,"<="&Config!$B$7)) -> 2875 | F19: =IF(C19="","",REPT("█",ROUND(C19*40,0))) -> █
A20: =IF(Config!$F$16="","",Config!$F$16) -> Deslocamento e viagens | B20: =IF(Config!$F$16="","",SUMIFS(Lançamentos!$G$5:$G$604,Lançamentos!$B$5:$B$604,"Saída",Lançamentos!$I$5:$I$604,"Sim",Lançamentos!$J$5:$J$604,Config!$B$7,Lançamentos!$K$5:$K$604,Config!$B$5,Lançamentos!$C$5:$C$604,Config!$F$16)) -> 0 | C20: =IF(OR(Config!$F$16="",$C$5=0),"",B20/$C$5) -> 0 | D20: =IF(Config!$F$16="","",IF(Config!$B$7=1,SUMIFS(Lançamentos!$G$5:$G$604,Lançamentos!$B$5:$B$604,"Saída",Lançamentos!$I$5:$I$604,"Sim",Lançamentos!$J$5:$J$604,12,Lançamentos!$K$5:$K$604,Config!$B$5-1,Lançamentos!$C$5:$C$604,Config!$F$16),SUMIFS(Lançamentos!$G$5:$G$604,Lançamentos!$B$5:$B$604,"Saída",Lançamentos!$I$5:$I$604,"Sim",Lançamentos!$J$5:$J$604,Config!$B$7-1,Lançamentos!$K$5:$K$604,Config!$B$5,Lançamentos!$C$5:$C$604,Config!$F$16))) -> 180 | E20: =IF(Config!$F$16="","",SUMIFS(Lançamentos!$G$5:$G$604,Lançamentos!$B$5:$B$604,"Saída",Lançamentos!$I$5:$I$604,"Sim",Lançamentos!$C$5:$C$604,Config!$F$16,Lançamentos!$K$5:$K$604,Config!$B$5,Lançamentos!$J$5:$J$604,"<="&Config!$B$7)) -> 730 | F20: =IF(C20="","",REPT("█",ROUND(C20*40,0)))
A21: =IF(Config!$F$17="","",Config!$F$17) -> Outras saídas | B21: =IF(Config!$F$17="","",SUMIFS(Lançamentos!$G$5:$G$604,Lançamentos!$B$5:$B$604,"Saída",Lançamentos!$I$5:$I$604,"Sim",Lançamentos!$J$5:$J$604,Config!$B$7,Lançamentos!$K$5:$K$604,Config!$B$5,Lançamentos!$C$5:$C$604,Config!$F$17)) -> 0 | C21: =IF(OR(Config!$F$17="",$C$5=0),"",B21/$C$5) -> 0 | D21: =IF(Config!$F$17="","",IF(Config!$B$7=1,SUMIFS(Lançamentos!$G$5:$G$604,Lançamentos!$B$5:$B$604,"Saída",Lançamentos!$I$5:$I$604,"Sim",Lançamentos!$J$5:$J$604,12,Lançamentos!$K$5:$K$604,Config!$B$5-1,Lançamentos!$C$5:$C$604,Config!$F$17),SUMIFS(Lançamentos!$G$5:$G$604,Lançamentos!$B$5:$B$604,"Saída",Lançamentos!$I$5:$I$604,"Sim",Lançamentos!$J$5:$J$604,Config!$B$7-1,Lançamentos!$K$5:$K$604,Config!$B$5,Lançamentos!$C$5:$C$604,Config!$F$17))) -> 480 | E21: =IF(Config!$F$17="","",SUMIFS(Lançamentos!$G$5:$G$604,Lançamentos!$B$5:$B$604,"Saída",Lançamentos!$I$5:$I$604,"Sim",Lançamentos!$C$5:$C$604,Config!$F$17,Lançamentos!$K$5:$K$604,Config!$B$5,Lançamentos!$J$5:$J$604,"<="&Config!$B$7)) -> 2040 | F21: =IF(C21="","",REPT("█",ROUND(C21*40,0)))
A22: =IF(Config!$F$18="","",Config!$F$18) | B22: =IF(Config!$F$18="","",SUMIFS(Lançamentos!$G$5:$G$604,Lançamentos!$B$5:$B$604,"Saída",Lançamentos!$I$5:$I$604,"Sim",Lançamentos!$J$5:$J$604,Config!$B$7,Lançamentos!$K$5:$K$604,Config!$B$5,Lançamentos!$C$5:$C$604,Config!$F$18)) | C22: =IF(OR(Config!$F$18="",$C$5=0),"",B22/$C$5) | D22: =IF(Config!$F$18="","",IF(Config!$B$7=1,SUMIFS(Lançamentos!$G$5:$G$604,Lançamentos!$B$5:$B$604,"Saída",Lançamentos!$I$5:$I$604,"Sim",Lançamentos!$J$5:$J$604,12,Lançamentos!$K$5:$K$604,Config!$B$5-1,Lançamentos!$C$5:$C$604,Config!$F$18),SUMIFS(Lançamentos!$G$5:$G$604,Lançamentos!$B$5:$B$604,"Saída",Lançamentos!$I$5:$I$604,"Sim",Lançamentos!$J$5:$J$604,Config!$B$7-1,Lançamentos!$K$5:$K$604,Config!$B$5,Lançamentos!$C$5:$C$604,Config!$F$18))) | E22: =IF(Config!$F$18="","",SUMIFS(Lançamentos!$G$5:$G$604,Lançamentos!$B$5:$B$604,"Saída",Lançamentos!$I$5:$I$604,"Sim",Lançamentos!$C$5:$C$604,Config!$F$18,Lançamentos!$K$5:$K$604,Config!$B$5,Lançamentos!$J$5:$J$604,"<="&Config!$B$7)) | F22: =IF(C22="","",REPT("█",ROUND(C22*40,0)))
A23: =IF(Config!$F$19="","",Config!$F$19) | B23: =IF(Config!$F$19="","",SUMIFS(Lançamentos!$G$5:$G$604,Lançamentos!$B$5:$B$604,"Saída",Lançamentos!$I$5:$I$604,"Sim",Lançamentos!$J$5:$J$604,Config!$B$7,Lançamentos!$K$5:$K$604,Config!$B$5,Lançamentos!$C$5:$C$604,Config!$F$19)) | C23: =IF(OR(Config!$F$19="",$C$5=0),"",B23/$C$5) | D23: =IF(Config!$F$19="","",IF(Config!$B$7=1,SUMIFS(Lançamentos!$G$5:$G$604,Lançamentos!$B$5:$B$604,"Saída",Lançamentos!$I$5:$I$604,"Sim",Lançamentos!$J$5:$J$604,12,Lançamentos!$K$5:$K$604,Config!$B$5-1,Lançamentos!$C$5:$C$604,Config!$F$19),SUMIFS(Lançamentos!$G$5:$G$604,Lançamentos!$B$5:$B$604,"Saída",Lançamentos!$I$5:$I$604,"Sim",Lançamentos!$J$5:$J$604,Config!$B$7-1,Lançamentos!$K$5:$K$604,Config!$B$5,Lançamentos!$C$5:$C$604,Config!$F$19))) | E23: =IF(Config!$F$19="","",SUMIFS(Lançamentos!$G$5:$G$604,Lançamentos!$B$5:$B$604,"Saída",Lançamentos!$I$5:$I$604,"Sim",Lançamentos!$C$5:$C$604,Config!$F$19,Lançamentos!$K$5:$K$604,Config!$B$5,Lançamentos!$J$5:$J$604,"<="&Config!$B$7)) | F23: =IF(C23="","",REPT("█",ROUND(C23*40,0)))
A24: =IF(Config!$F$20="","",Config!$F$20) | B24: =IF(Config!$F$20="","",SUMIFS(Lançamentos!$G$5:$G$604,Lançamentos!$B$5:$B$604,"Saída",Lançamentos!$I$5:$I$604,"Sim",Lançamentos!$J$5:$J$604,Config!$B$7,Lançamentos!$K$5:$K$604,Config!$B$5,Lançamentos!$C$5:$C$604,Config!$F$20)) | C24: =IF(OR(Config!$F$20="",$C$5=0),"",B24/$C$5) | D24: =IF(Config!$F$20="","",IF(Config!$B$7=1,SUMIFS(Lançamentos!$G$5:$G$604,Lançamentos!$B$5:$B$604,"Saída",Lançamentos!$I$5:$I$604,"Sim",Lançamentos!$J$5:$J$604,12,Lançamentos!$K$5:$K$604,Config!$B$5-1,Lançamentos!$C$5:$C$604,Config!$F$20),SUMIFS(Lançamentos!$G$5:$G$604,Lançamentos!$B$5:$B$604,"Saída",Lançamentos!$I$5:$I$604,"Sim",Lançamentos!$J$5:$J$604,Config!$B$7-1,Lançamentos!$K$5:$K$604,Config!$B$5,Lançamentos!$C$5:$C$604,Config!$F$20))) | E24: =IF(Config!$F$20="","",SUMIFS(Lançamentos!$G$5:$G$604,Lançamentos!$B$5:$B$604,"Saída",Lançamentos!$I$5:$I$604,"Sim",Lançamentos!$C$5:$C$604,Config!$F$20,Lançamentos!$K$5:$K$604,Config!$B$5,Lançamentos!$J$5:$J$604,"<="&Config!$B$7)) | F24: =IF(C24="","",REPT("█",ROUND(C24*40,0)))
A25: Total | B25: =SUM(B9:B24) -> 5320 | D25: =SUM(D9:D24) -> 21897 | E25: =SUM(E9:E24) -> 191387
A27: De onde veio o dinheiro
A28: Categoria de entrada | B28: Valor no mês | C28: % do total | D28: Mês anterior | E28: Acumulado no ano | F28: Barra
A29: =IF(Config!$D$5="","",Config!$D$5) -> Honorários fixos | B29: =IF(Config!$D$5="","",SUMIFS(Lançamentos!$G$5:$G$604,Lançamentos!$B$5:$B$604,"Entrada",Lançamentos!$I$5:$I$604,"Sim",Lançamentos!$J$5:$J$604,Config!$B$7,Lançamentos!$K$5:$K$604,Config!$B$5,Lançamentos!$C$5:$C$604,Config!$D$5)) -> 1000 | C29: =IF(OR(Config!$D$5="",$A$5=0),"",B29/$A$5) -> 0.19157088 | D29: =IF(Config!$D$5="","",IF(Config!$B$7=1,SUMIFS(Lançamentos!$G$5:$G$604,Lançamentos!$B$5:$B$604,"Entrada",Lançamentos!$I$5:$I$604,"Sim",Lançamentos!$J$5:$J$604,12,Lançamentos!$K$5:$K$604,Config!$B$5-1,Lançamentos!$C$5:$C$604,Config!$D$5),SUMIFS(Lançamentos!$G$5:$G$604,Lançamentos!$B$5:$B$604,"Entrada",Lançamentos!$I$5:$I$604,"Sim",Lançamentos!$J$5:$J$604,Config!$B$7-1,Lançamentos!$K$5:$K$604,Config!$B$5,Lançamentos!$C$5:$C$604,Config!$D$5))) -> 15300 | E29: =IF(Config!$D$5="","",SUMIFS(Lançamentos!$G$5:$G$604,Lançamentos!$B$5:$B$604,"Entrada",Lançamentos!$I$5:$I$604,"Sim",Lançamentos!$C$5:$C$604,Config!$D$5,Lançamentos!$K$5:$K$604,Config!$B$5,Lançamentos!$J$5:$J$604,"<="&Config!$B$7)) -> 124450 | F29: =IF(C29="","",REPT("█",ROUND(C29*40,0))) -> ████████
A30: =IF(Config!$D$6="","",Config!$D$6) -> Honorários por hora | B30: =IF(Config!$D$6="","",SUMIFS(Lançamentos!$G$5:$G$604,Lançamentos!$B$5:$B$604,"Entrada",Lançamentos!$I$5:$I$604,"Sim",Lançamentos!$J$5:$J$604,Config!$B$7,Lançamentos!$K$5:$K$604,Config!$B$5,Lançamentos!$C$5:$C$604,Config!$D$6)) -> 0 | C30: =IF(OR(Config!$D$6="",$A$5=0),"",B30/$A$5) -> 0 | D30: =IF(Config!$D$6="","",IF(Config!$B$7=1,SUMIFS(Lançamentos!$G$5:$G$604,Lançamentos!$B$5:$B$604,"Entrada",Lançamentos!$I$5:$I$604,"Sim",Lançamentos!$J$5:$J$604,12,Lançamentos!$K$5:$K$604,Config!$B$5-1,Lançamentos!$C$5:$C$604,Config!$D$6),SUMIFS(Lançamentos!$G$5:$G$604,Lançamentos!$B$5:$B$604,"Entrada",Lançamentos!$I$5:$I$604,"Sim",Lançamentos!$J$5:$J$604,Config!$B$7-1,Lançamentos!$K$5:$K$604,Config!$B$5,Lançamentos!$C$5:$C$604,Config!$D$6))) -> 0 | E30: =IF(Config!$D$6="","",SUMIFS(Lançamentos!$G$5:$G$604,Lançamentos!$B$5:$B$604,"Entrada",Lançamentos!$I$5:$I$604,"Sim",Lançamentos!$C$5:$C$604,Config!$D$6,Lançamentos!$K$5:$K$604,Config!$B$5,Lançamentos!$J$5:$J$604,"<="&Config!$B$7)) -> 18900 | F30: =IF(C30="","",REPT("█",ROUND(C30*40,0)))
A31: =IF(Config!$D$7="","",Config!$D$7) -> Honorários de êxito | B31: =IF(Config!$D$7="","",SUMIFS(Lançamentos!$G$5:$G$604,Lançamentos!$B$5:$B$604,"Entrada",Lançamentos!$I$5:$I$604,"Sim",Lançamentos!$J$5:$J$604,Config!$B$7,Lançamentos!$K$5:$K$604,Config!$B$5,Lançamentos!$C$5:$C$604,Config!$D$7)) -> 0 | C31: =IF(OR(Config!$D$7="",$A$5=0),"",B31/$A$5) -> 0 | D31: =IF(Config!$D$7="","",IF(Config!$B$7=1,SUMIFS(Lançamentos!$G$5:$G$604,Lançamentos!$B$5:$B$604,"Entrada",Lançamentos!$I$5:$I$604,"Sim",Lançamentos!$J$5:$J$604,12,Lançamentos!$K$5:$K$604,Config!$B$5-1,Lançamentos!$C$5:$C$604,Config!$D$7),SUMIFS(Lançamentos!$G$5:$G$604,Lançamentos!$B$5:$B$604,"Entrada",Lançamentos!$I$5:$I$604,"Sim",Lançamentos!$J$5:$J$604,Config!$B$7-1,Lançamentos!$K$5:$K$604,Config!$B$5,Lançamentos!$C$5:$C$604,Config!$D$7))) -> 0 | E31: =IF(Config!$D$7="","",SUMIFS(Lançamentos!$G$5:$G$604,Lançamentos!$B$5:$B$604,"Entrada",Lançamentos!$I$5:$I$604,"Sim",Lançamentos!$C$5:$C$604,Config!$D$7,Lançamentos!$K$5:$K$604,Config!$B$5,Lançamentos!$J$5:$J$604,"<="&Config!$B$7)) -> 27000 | F31: =IF(C31="","",REPT("█",ROUND(C31*40,0)))
A32: =IF(Config!$D$8="","",Config!$D$8) -> Consultoria e pareceres | B32: =IF(Config!$D$8="","",SUMIFS(Lançamentos!$G$5:$G$604,Lançamentos!$B$5:$B$604,"Entrada",Lançamentos!$I$5:$I$604,"Sim",Lançamentos!$J$5:$J$604,Config!$B$7,Lançamentos!$K$5:$K$604,Config!$B$5,Lançamentos!$C$5:$C$604,Config!$D$8)) -> 4220 | C32: =IF(OR(Config!$D$8="",$A$5=0),"",B32/$A$5) -> 0.80842912 | D32: =IF(Config!$D$8="","",IF(Config!$B$7=1,SUMIFS(Lançamentos!$G$5:$G$604,Lançamentos!$B$5:$B$604,"Entrada",Lançamentos!$I$5:$I$604,"Sim",Lançamentos!$J$5:$J$604,12,Lançamentos!$K$5:$K$604,Config!$B$5-1,Lançamentos!$C$5:$C$604,Config!$D$8),SUMIFS(Lançamentos!$G$5:$G$604,Lançamentos!$B$5:$B$604,"Entrada",Lançamentos!$I$5:$I$604,"Sim",Lançamentos!$J$5:$J$604,Config!$B$7-1,Lançamentos!$K$5:$K$604,Config!$B$5,Lançamentos!$C$5:$C$604,Config!$D$8))) -> 11290 | E32: =IF(Config!$D$8="","",SUMIFS(Lançamentos!$G$5:$G$604,Lançamentos!$B$5:$B$604,"Entrada",Lançamentos!$I$5:$I$604,"Sim",Lançamentos!$C$5:$C$604,Config!$D$8,Lançamentos!$K$5:$K$604,Config!$B$5,Lançamentos!$J$5:$J$604,"<="&Config!$B$7)) -> 40610 | F32: =IF(C32="","",REPT("█",ROUND(C32*40,0))) -> ████████████████████████████████
A33: =IF(Config!$D$9="","",Config!$D$9) -> Reembolso de custas | B33: =IF(Config!$D$9="","",SUMIFS(Lançamentos!$G$5:$G$604,Lançamentos!$B$5:$B$604,"Entrada",Lançamentos!$I$5:$I$604,"Sim",Lançamentos!$J$5:$J$604,Config!$B$7,Lançamentos!$K$5:$K$604,Config!$B$5,Lançamentos!$C$5:$C$604,Config!$D$9)) -> 0 | C33: =IF(OR(Config!$D$9="",$A$5=0),"",B33/$A$5) -> 0 | D33: =IF(Config!$D$9="","",IF(Config!$B$7=1,SUMIFS(Lançamentos!$G$5:$G$604,Lançamentos!$B$5:$B$604,"Entrada",Lançamentos!$I$5:$I$604,"Sim",Lançamentos!$J$5:$J$604,12,Lançamentos!$K$5:$K$604,Config!$B$5-1,Lançamentos!$C$5:$C$604,Config!$D$9),SUMIFS(Lançamentos!$G$5:$G$604,Lançamentos!$B$5:$B$604,"Entrada",Lançamentos!$I$5:$I$604,"Sim",Lançamentos!$J$5:$J$604,Config!$B$7-1,Lançamentos!$K$5:$K$604,Config!$B$5,Lançamentos!$C$5:$C$604,Config!$D$9))) -> 310 | E33: =IF(Config!$D$9="","",SUMIFS(Lançamentos!$G$5:$G$604,Lançamentos!$B$5:$B$604,"Entrada",Lançamentos!$I$5:$I$604,"Sim",Lançamentos!$C$5:$C$604,Config!$D$9,Lançamentos!$K$5:$K$604,Config!$B$5,Lançamentos!$J$5:$J$604,"<="&Config!$B$7)) -> 1630 | F33: =IF(C33="","",REPT("█",ROUND(C33*40,0)))
A34: =IF(Config!$D$10="","",Config!$D$10) -> Outras entradas | B34: =IF(Config!$D$10="","",SUMIFS(Lançamentos!$G$5:$G$604,Lançamentos!$B$5:$B$604,"Entrada",Lançamentos!$I$5:$I$604,"Sim",Lançamentos!$J$5:$J$604,Config!$B$7,Lançamentos!$K$5:$K$604,Config!$B$5,Lançamentos!$C$5:$C$604,Config!$D$10)) -> 0 | C34: =IF(OR(Config!$D$10="",$A$5=0),"",B34/$A$5) -> 0 | D34: =IF(Config!$D$10="","",IF(Config!$B$7=1,SUMIFS(Lançamentos!$G$5:$G$604,Lançamentos!$B$5:$B$604,"Entrada",Lançamentos!$I$5:$I$604,"Sim",Lançamentos!$J$5:$J$604,12,Lançamentos!$K$5:$K$604,Config!$B$5-1,Lançamentos!$C$5:$C$604,Config!$D$10),SUMIFS(Lançamentos!$G$5:$G$604,Lançamentos!$B$5:$B$604,"Entrada",Lançamentos!$I$5:$I$604,"Sim",Lançamentos!$J$5:$J$604,Config!$B$7-1,Lançamentos!$K$5:$K$604,Config!$B$5,Lançamentos!$C$5:$C$604,Config!$D$10))) -> 0 | E34: =IF(Config!$D$10="","",SUMIFS(Lançamentos!$G$5:$G$604,Lançamentos!$B$5:$B$604,"Entrada",Lançamentos!$I$5:$I$604,"Sim",Lançamentos!$C$5:$C$604,Config!$D$10,Lançamentos!$K$5:$K$604,Config!$B$5,Lançamentos!$J$5:$J$604,"<="&Config!$B$7)) -> 480 | F34: =IF(C34="","",REPT("█",ROUND(C34*40,0)))
A35: =IF(Config!$D$11="","",Config!$D$11) | B35: =IF(Config!$D$11="","",SUMIFS(Lançamentos!$G$5:$G$604,Lançamentos!$B$5:$B$604,"Entrada",Lançamentos!$I$5:$I$604,"Sim",Lançamentos!$J$5:$J$604,Config!$B$7,Lançamentos!$K$5:$K$604,Config!$B$5,Lançamentos!$C$5:$C$604,Config!$D$11)) | C35: =IF(OR(Config!$D$11="",$A$5=0),"",B35/$A$5) | D35: =IF(Config!$D$11="","",IF(Config!$B$7=1,SUMIFS(Lançamentos!$G$5:$G$604,Lançamentos!$B$5:$B$604,"Entrada",Lançamentos!$I$5:$I$604,"Sim",Lançamentos!$J$5:$J$604,12,Lançamentos!$K$5:$K$604,Config!$B$5-1,Lançamentos!$C$5:$C$604,Config!$D$11),SUMIFS(Lançamentos!$G$5:$G$604,Lançamentos!$B$5:$B$604,"Entrada",Lançamentos!$I$5:$I$604,"Sim",Lançamentos!$J$5:$J$604,Config!$B$7-1,Lançamentos!$K$5:$K$604,Config!$B$5,Lançamentos!$C$5:$C$604,Config!$D$11))) | E35: =IF(Config!$D$11="","",SUMIFS(Lançamentos!$G$5:$G$604,Lançamentos!$B$5:$B$604,"Entrada",Lançamentos!$I$5:$I$604,"Sim",Lançamentos!$C$5:$C$604,Config!$D$11,Lançamentos!$K$5:$K$604,Config!$B$5,Lançamentos!$J$5:$J$604,"<="&Config!$B$7)) | F35: =IF(C35="","",REPT("█",ROUND(C35*40,0)))
A36: =IF(Config!$D$12="","",Config!$D$12) | B36: =IF(Config!$D$12="","",SUMIFS(Lançamentos!$G$5:$G$604,Lançamentos!$B$5:$B$604,"Entrada",Lançamentos!$I$5:$I$604,"Sim",Lançamentos!$J$5:$J$604,Config!$B$7,Lançamentos!$K$5:$K$604,Config!$B$5,Lançamentos!$C$5:$C$604,Config!$D$12)) | C36: =IF(OR(Config!$D$12="",$A$5=0),"",B36/$A$5) | D36: =IF(Config!$D$12="","",IF(Config!$B$7=1,SUMIFS(Lançamentos!$G$5:$G$604,Lançamentos!$B$5:$B$604,"Entrada",Lançamentos!$I$5:$I$604,"Sim",Lançamentos!$J$5:$J$604,12,Lançamentos!$K$5:$K$604,Config!$B$5-1,Lançamentos!$C$5:$C$604,Config!$D$12),SUMIFS(Lançamentos!$G$5:$G$604,Lançamentos!$B$5:$B$604,"Entrada",Lançamentos!$I$5:$I$604,"Sim",Lançamentos!$J$5:$J$604,Config!$B$7-1,Lançamentos!$K$5:$K$604,Config!$B$5,Lançamentos!$C$5:$C$604,Config!$D$12))) | E36: =IF(Config!$D$12="","",SUMIFS(Lançamentos!$G$5:$G$604,Lançamentos!$B$5:$B$604,"Entrada",Lançamentos!$I$5:$I$604,"Sim",Lançamentos!$C$5:$C$604,Config!$D$12,Lançamentos!$K$5:$K$604,Config!$B$5,Lançamentos!$J$5:$J$604,"<="&Config!$B$7)) | F36: =IF(C36="","",REPT("█",ROUND(C36*40,0)))
A37: =IF(Config!$D$13="","",Config!$D$13) | B37: =IF(Config!$D$13="","",SUMIFS(Lançamentos!$G$5:$G$604,Lançamentos!$B$5:$B$604,"Entrada",Lançamentos!$I$5:$I$604,"Sim",Lançamentos!$J$5:$J$604,Config!$B$7,Lançamentos!$K$5:$K$604,Config!$B$5,Lançamentos!$C$5:$C$604,Config!$D$13)) | C37: =IF(OR(Config!$D$13="",$A$5=0),"",B37/$A$5) | D37: =IF(Config!$D$13="","",IF(Config!$B$7=1,SUMIFS(Lançamentos!$G$5:$G$604,Lançamentos!$B$5:$B$604,"Entrada",Lançamentos!$I$5:$I$604,"Sim",Lançamentos!$J$5:$J$604,12,Lançamentos!$K$5:$K$604,Config!$B$5-1,Lançamentos!$C$5:$C$604,Config!$D$13),SUMIFS(Lançamentos!$G$5:$G$604,Lançamentos!$B$5:$B$604,"Entrada",Lançamentos!$I$5:$I$604,"Sim",Lançamentos!$J$5:$J$604,Config!$B$7-1,Lançamentos!$K$5:$K$604,Config!$B$5,Lançamentos!$C$5:$C$604,Config!$D$13))) | E37: =IF(Config!$D$13="","",SUMIFS(Lançamentos!$G$5:$G$604,Lançamentos!$B$5:$B$604,"Entrada",Lançamentos!$I$5:$I$604,"Sim",Lançamentos!$C$5:$C$604,Config!$D$13,Lançamentos!$K$5:$K$604,Config!$B$5,Lançamentos!$J$5:$J$604,"<="&Config!$B$7)) | F37: =IF(C37="","",REPT("█",ROUND(C37*40,0)))
A38: =IF(Config!$D$14="","",Config!$D$14) | B38: =IF(Config!$D$14="","",SUMIFS(Lançamentos!$G$5:$G$604,Lançamentos!$B$5:$B$604,"Entrada",Lançamentos!$I$5:$I$604,"Sim",Lançamentos!$J$5:$J$604,Config!$B$7,Lançamentos!$K$5:$K$604,Config!$B$5,Lançamentos!$C$5:$C$604,Config!$D$14)) | C38: =IF(OR(Config!$D$14="",$A$5=0),"",B38/$A$5) | D38: =IF(Config!$D$14="","",IF(Config!$B$7=1,SUMIFS(Lançamentos!$G$5:$G$604,Lançamentos!$B$5:$B$604,"Entrada",Lançamentos!$I$5:$I$604,"Sim",Lançamentos!$J$5:$J$604,12,Lançamentos!$K$5:$K$604,Config!$B$5-1,Lançamentos!$C$5:$C$604,Config!$D$14),SUMIFS(Lançamentos!$G$5:$G$604,Lançamentos!$B$5:$B$604,"Entrada",Lançamentos!$I$5:$I$604,"Sim",Lançamentos!$J$5:$J$604,Config!$B$7-1,Lançamentos!$K$5:$K$604,Config!$B$5,Lançamentos!$C$5:$C$604,Config!$D$14))) | E38: =IF(Config!$D$14="","",SUMIFS(Lançamentos!$G$5:$G$604,Lançamentos!$B$5:$B$604,"Entrada",Lançamentos!$I$5:$I$604,"Sim",Lançamentos!$C$5:$C$604,Config!$D$14,Lançamentos!$K$5:$K$604,Config!$B$5,Lançamentos!$J$5:$J$604,"<="&Config!$B$7)) | F38: =IF(C38="","",REPT("█",ROUND(C38*40,0)))
A39: =IF(Config!$D$15="","",Config!$D$15) | B39: =IF(Config!$D$15="","",SUMIFS(Lançamentos!$G$5:$G$604,Lançamentos!$B$5:$B$604,"Entrada",Lançamentos!$I$5:$I$604,"Sim",Lançamentos!$J$5:$J$604,Config!$B$7,Lançamentos!$K$5:$K$604,Config!$B$5,Lançamentos!$C$5:$C$604,Config!$D$15)) | C39: =IF(OR(Config!$D$15="",$A$5=0),"",B39/$A$5) | D39: =IF(Config!$D$15="","",IF(Config!$B$7=1,SUMIFS(Lançamentos!$G$5:$G$604,Lançamentos!$B$5:$B$604,"Entrada",Lançamentos!$I$5:$I$604,"Sim",Lançamentos!$J$5:$J$604,12,Lançamentos!$K$5:$K$604,Config!$B$5-1,Lançamentos!$C$5:$C$604,Config!$D$15),SUMIFS(Lançamentos!$G$5:$G$604,Lançamentos!$B$5:$B$604,"Entrada",Lançamentos!$I$5:$I$604,"Sim",Lançamentos!$J$5:$J$604,Config!$B$7-1,Lançamentos!$K$5:$K$604,Config!$B$5,Lançamentos!$C$5:$C$604,Config!$D$15))) | E39: =IF(Config!$D$15="","",SUMIFS(Lançamentos!$G$5:$G$604,Lançamentos!$B$5:$B$604,"Entrada",Lançamentos!$I$5:$I$604,"Sim",Lançamentos!$C$5:$C$604,Config!$D$15,Lançamentos!$K$5:$K$604,Config!$B$5,Lançamentos!$J$5:$J$604,"<="&Config!$B$7)) | F39: =IF(C39="","",REPT("█",ROUND(C39*40,0)))
A40: =IF(Config!$D$16="","",Config!$D$16) | B40: =IF(Config!$D$16="","",SUMIFS(Lançamentos!$G$5:$G$604,Lançamentos!$B$5:$B$604,"Entrada",Lançamentos!$I$5:$I$604,"Sim",Lançamentos!$J$5:$J$604,Config!$B$7,Lançamentos!$K$5:$K$604,Config!$B$5,Lançamentos!$C$5:$C$604,Config!$D$16)) | C40: =IF(OR(Config!$D$16="",$A$5=0),"",B40/$A$5) | D40: =IF(Config!$D$16="","",IF(Config!$B$7=1,SUMIFS(Lançamentos!$G$5:$G$604,Lançamentos!$B$5:$B$604,"Entrada",Lançamentos!$I$5:$I$604,"Sim",Lançamentos!$J$5:$J$604,12,Lançamentos!$K$5:$K$604,Config!$B$5-1,Lançamentos!$C$5:$C$604,Config!$D$16),SUMIFS(Lançamentos!$G$5:$G$604,Lançamentos!$B$5:$B$604,"Entrada",Lançamentos!$I$5:$I$604,"Sim",Lançamentos!$J$5:$J$604,Config!$B$7-1,Lançamentos!$K$5:$K$604,Config!$B$5,Lançamentos!$C$5:$C$604,Config!$D$16))) | E40: =IF(Config!$D$16="","",SUMIFS(Lançamentos!$G$5:$G$604,Lançamentos!$B$5:$B$604,"Entrada",Lançamentos!$I$5:$I$604,"Sim",Lançamentos!$C$5:$C$604,Config!$D$16,Lançamentos!$K$5:$K$604,Config!$B$5,Lançamentos!$J$5:$J$604,"<="&Config!$B$7)) | F40: =IF(C40="","",REPT("█",ROUND(C40*40,0)))
A41: Total | B41: =SUM(B29:B40) -> 5220 | D41: =SUM(D29:D40) -> 26900 | E41: =SUM(E29:E40) -> 213070
A43: Por cliente
A44: Cliente | B44: Entrou no mês | C44: Entrou no ano | D44: % do ano | E44: A receber (Pago? = Não) | F44: Custas pagas no ano
A45: =IF(Config!$J$5="","",Config!$J$5) -> Padaria do Sol Ltda | B45: =IF(Config!$J$5="","",SUMIFS(Lançamentos!$G$5:$G$604,Lançamentos!$B$5:$B$604,"Entrada",Lançamentos!$I$5:$I$604,"Sim",Lançamentos!$J$5:$J$604,Config!$B$7,Lançamentos!$K$5:$K$604,Config!$B$5,Lançamentos!$D$5:$D$604,Config!$J$5)) -> 1500 | C45: =IF(Config!$J$5="","",SUMIFS(Lançamentos!$G$5:$G$604,Lançamentos!$B$5:$B$604,"Entrada",Lançamentos!$I$5:$I$604,"Sim",Lançamentos!$D$5:$D$604,Config!$J$5,Lançamentos!$K$5:$K$604,Config!$B$5)) -> 11250 | D45: =IF(OR(Config!$J$5="",$C$75=0),"",C45/$C$75) -> 0.052918764 | E45: =IF(Config!$J$5="","",SUMIFS(Lançamentos!$G$5:$G$604,Lançamentos!$B$5:$B$604,"Entrada",Lançamentos!$I$5:$I$604,"Não",Lançamentos!$D$5:$D$604,Config!$J$5)) -> 0 | F45: =IF(Config!$J$5="","",SUMIFS(Lançamentos!$G$5:$G$604,Lançamentos!$B$5:$B$604,"Saída",Lançamentos!$I$5:$I$604,"Sim",Lançamentos!$D$5:$D$604,Config!$J$5,Lançamentos!$K$5:$K$604,Config!$B$5)) -> 0
A46: =IF(Config!$J$6="","",Config!$J$6) -> Ana Beatriz Moreira | B46: =IF(Config!$J$6="","",SUMIFS(Lançamentos!$G$5:$G$604,Lançamentos!$B$5:$B$604,"Entrada",Lançamentos!$I$5:$I$604,"Sim",Lançamentos!$J$5:$J$604,Config!$B$7,Lançamentos!$K$5:$K$604,Config!$B$5,Lançamentos!$D$5:$D$604,Config!$J$6)) -> 0 | C46: =IF(Config!$J$6="","",SUMIFS(Lançamentos!$G$5:$G$604,Lançamentos!$B$5:$B$604,"Entrada",Lançamentos!$I$5:$I$604,"Sim",Lançamentos!$D$5:$D$604,Config!$J$6,Lançamentos!$K$5:$K$604,Config!$B$5)) -> 5500 | D46: =IF(OR(Config!$J$6="",$C$75=0),"",C46/$C$75) -> 0.025871396 | E46: =IF(Config!$J$6="","",SUMIFS(Lançamentos!$G$5:$G$604,Lançamentos!$B$5:$B$604,"Entrada",Lançamentos!$I$5:$I$604,"Não",Lançamentos!$D$5:$D$604,Config!$J$6)) -> 0 | F46: =IF(Config!$J$6="","",SUMIFS(Lançamentos!$G$5:$G$604,Lançamentos!$B$5:$B$604,"Saída",Lançamentos!$I$5:$I$604,"Sim",Lançamentos!$D$5:$D$604,Config!$J$6,Lançamentos!$K$5:$K$604,Config!$B$5)) -> 0
A47: =IF(Config!$J$7="","",Config!$J$7) -> Construtora Horizonte | B47: =IF(Config!$J$7="","",SUMIFS(Lançamentos!$G$5:$G$604,Lançamentos!$B$5:$B$604,"Entrada",Lançamentos!$I$5:$I$604,"Sim",Lançamentos!$J$5:$J$604,Config!$B$7,Lançamentos!$K$5:$K$604,Config!$B$5,Lançamentos!$D$5:$D$604,Config!$J$7)) -> 0 | C47: =IF(Config!$J$7="","",SUMIFS(Lançamentos!$G$5:$G$604,Lançamentos!$B$5:$B$604,"Entrada",Lançamentos!$I$5:$I$604,"Sim",Lançamentos!$D$5:$D$604,Config!$J$7,Lançamentos!$K$5:$K$604,Config!$B$5)) -> 16080 | D47: =IF(OR(Config!$J$7="",$C$75=0),"",C47/$C$75) -> 0.075638553 | E47: =IF(Config!$J$7="","",SUMIFS(Lançamentos!$G$5:$G$604,Lançamentos!$B$5:$B$604,"Entrada",Lançamentos!$I$5:$I$604,"Não",Lançamentos!$D$5:$D$604,Config!$J$7)) -> 2100 | F47: =IF(Config!$J$7="","",SUMIFS(Lançamentos!$G$5:$G$604,Lançamentos!$B$5:$B$604,"Saída",Lançamentos!$I$5:$I$604,"Sim",Lançamentos!$D$5:$D$604,Config!$J$7,Lançamentos!$K$5:$K$604,Config!$B$5)) -> 780
A48: =IF(Config!$J$8="","",Config!$J$8) -> Carlos Eduardo Nunes | B48: =IF(Config!$J$8="","",SUMIFS(Lançamentos!$G$5:$G$604,Lançamentos!$B$5:$B$604,"Entrada",Lançamentos!$I$5:$I$604,"Sim",Lançamentos!$J$5:$J$604,Config!$B$7,Lançamentos!$K$5:$K$604,Config!$B$5,Lançamentos!$D$5:$D$604,Config!$J$8)) -> 0 | C48: =IF(Config!$J$8="","",SUMIFS(Lançamentos!$G$5:$G$604,Lançamentos!$B$5:$B$604,"Entrada",Lançamentos!$I$5:$I$604,"Sim",Lançamentos!$D$5:$D$604,Config!$J$8,Lançamentos!$K$5:$K$604,Config!$B$5)) -> 7500 | D48: =IF(OR(Config!$J$8="",$C$75=0),"",C48/$C$75) -> 0.035279176 | E48: =IF(Config!$J$8="","",SUMIFS(Lançamentos!$G$5:$G$604,Lançamentos!$B$5:$B$604,"Entrada",Lançamentos!$I$5:$I$604,"Não",Lançamentos!$D$5:$D$604,Config!$J$8)) -> 1500 | F48: =IF(Config!$J$8="","",SUMIFS(Lançamentos!$G$5:$G$604,Lançamentos!$B$5:$B$604,"Saída",Lançamentos!$I$5:$I$604,"Sim",Lançamentos!$D$5:$D$604,Config!$J$8,Lançamentos!$K$5:$K$604,Config!$B$5)) -> 0
A49: =IF(Config!$J$9="","",Config!$J$9) -> Loja Verde Comércio | B49: =IF(Config!$J$9="","",SUMIFS(Lançamentos!$G$5:$G$604,Lançamentos!$B$5:$B$604,"Entrada",Lançamentos!$I$5:$I$604,"Sim",Lançamentos!$J$5:$J$604,Config!$B$7,Lançamentos!$K$5:$K$604,Config!$B$5,Lançamentos!$D$5:$D$604,Config!$J$9)) -> 0 | C49: =IF(Config!$J$9="","",SUMIFS(Lançamentos!$G$5:$G$604,Lançamentos!$B$5:$B$604,"Entrada",Lançamentos!$I$5:$I$604,"Sim",Lançamentos!$D$5:$D$604,Config!$J$9,Lançamentos!$K$5:$K$604,Config!$B$5)) -> 3800 | D49: =IF(OR(Config!$J$9="",$C$75=0),"",C49/$C$75) -> 0.017874782 | E49: =IF(Config!$J$9="","",SUMIFS(Lançamentos!$G$5:$G$604,Lançamentos!$B$5:$B$604,"Entrada",Lançamentos!$I$5:$I$604,"Não",Lançamentos!$D$5:$D$604,Config!$J$9)) -> 2800 | F49: =IF(Config!$J$9="","",SUMIFS(Lançamentos!$G$5:$G$604,Lançamentos!$B$5:$B$604,"Saída",Lançamentos!$I$5:$I$604,"Sim",Lançamentos!$D$5:$D$604,Config!$J$9,Lançamentos!$K$5:$K$604,Config!$B$5)) -> 0
A50: =IF(Config!$J$10="","",Config!$J$10) -> Fernanda Castro | B50: =IF(Config!$J$10="","",SUMIFS(Lançamentos!$G$5:$G$604,Lançamentos!$B$5:$B$604,"Entrada",Lançamentos!$I$5:$I$604,"Sim",Lançamentos!$J$5:$J$604,Config!$B$7,Lançamentos!$K$5:$K$604,Config!$B$5,Lançamentos!$D$5:$D$604,Config!$J$10)) -> 0 | C50: =IF(Config!$J$10="","",SUMIFS(Lançamentos!$G$5:$G$604,Lançamentos!$B$5:$B$604,"Entrada",Lançamentos!$I$5:$I$604,"Sim",Lançamentos!$D$5:$D$604,Config!$J$10,Lançamentos!$K$5:$K$604,Config!$B$5)) -> 1400 | D50: =IF(OR(Config!$J$10="",$C$75=0),"",C50/$C$75) -> 0.0065854462 | E50: =IF(Config!$J$10="","",SUMIFS(Lançamentos!$G$5:$G$604,Lançamentos!$B$5:$B$604,"Entrada",Lançamentos!$I$5:$I$604,"Não",Lançamentos!$D$5:$D$604,Config!$J$10)) -> 1400 | F50: =IF(Config!$J$10="","",SUMIFS(Lançamentos!$G$5:$G$604,Lançamentos!$B$5:$B$604,"Saída",Lançamentos!$I$5:$I$604,"Sim",Lançamentos!$D$5:$D$604,Config!$J$10,Lançamentos!$K$5:$K$604,Config!$B$5)) -> 0
A51: =IF(Config!$J$11="","",Config!$J$11) -> Bistrô 42 | B51: =IF(Config!$J$11="","",SUMIFS(Lançamentos!$G$5:$G$604,Lançamentos!$B$5:$B$604,"Entrada",Lançamentos!$I$5:$I$604,"Sim",Lançamentos!$J$5:$J$604,Config!$B$7,Lançamentos!$K$5:$K$604,Config!$B$5,Lançamentos!$D$5:$D$604,Config!$J$11)) -> 0 | C51: =IF(Config!$J$11="","",SUMIFS(Lançamentos!$G$5:$G$604,Lançamentos!$B$5:$B$604,"Entrada",Lançamentos!$I$5:$I$604,"Sim",Lançamentos!$D$5:$D$604,Config!$J$11,Lançamentos!$K$5:$K$604,Config!$B$5)) -> 5300 | D51: =IF(OR(Config!$J$11="",$C$75=0),"",C51/$C$75) -> 0.024930618 | E51: =IF(Config!$J$11="","",SUMIFS(Lançamentos!$G$5:$G$604,Lançamentos!$B$5:$B$604,"Entrada",Lançamentos!$I$5:$I$604,"Não",Lançamentos!$D$5:$D$604,Config!$J$11)) -> 4200 | F51: =IF(Config!$J$11="","",SUMIFS(Lançamentos!$G$5:$G$604,Lançamentos!$B$5:$B$604,"Saída",Lançamentos!$I$5:$I$604,"Sim",Lançamentos!$D$5:$D$604,Config!$J$11,Lançamentos!$K$5:$K$604,Config!$B$5)) -> 95
A52: =IF(Config!$J$12="","",Config!$J$12) -> Roberto Almeida | B52: =IF(Config!$J$12="","",SUMIFS(Lançamentos!$G$5:$G$604,Lançamentos!$B$5:$B$604,"Entrada",Lançamentos!$I$5:$I$604,"Sim",Lançamentos!$J$5:$J$604,Config!$B$7,Lançamentos!$K$5:$K$604,Config!$B$5,Lançamentos!$D$5:$D$604,Config!$J$12)) -> 0 | C52: =IF(Config!$J$12="","",SUMIFS(Lançamentos!$G$5:$G$604,Lançamentos!$B$5:$B$604,"Entrada",Lançamentos!$I$5:$I$604,"Sim",Lançamentos!$D$5:$D$604,Config!$J$12,Lançamentos!$K$5:$K$604,Config!$B$5)) -> 16510 | D52: =IF(OR(Config!$J$12="",$C$75=0),"",C52/$C$75) -> 0.077661226 | E52: =IF(Config!$J$12="","",SUMIFS(Lançamentos!$G$5:$G$604,Lançamentos!$B$5:$B$604,"Entrada",Lançamentos!$I$5:$I$604,"Não",Lançamentos!$D$5:$D$604,Config!$J$12)) -> 0 | F52: =IF(Config!$J$12="","",SUMIFS(Lançamentos!$G$5:$G$604,Lançamentos!$B$5:$B$604,"Saída",Lançamentos!$I$5:$I$604,"Sim",Lançamentos!$D$5:$D$604,Config!$J$12,Lançamentos!$K$5:$K$604,Config!$B$5)) -> 310
A53: =IF(Config!$J$13="","",Config!$J$13) -> Clínica Bem-Estar | B53: =IF(Config!$J$13="","",SUMIFS(Lançamentos!$G$5:$G$604,Lançamentos!$B$5:$B$604,"Entrada",Lançamentos!$I$5:$I$604,"Sim",Lançamentos!$J$5:$J$604,Config!$B$7,Lançamentos!$K$5:$K$604,Config!$B$5,Lançamentos!$D$5:$D$604,Config!$J$13)) -> 1620 | C53: =IF(Config!$J$13="","",SUMIFS(Lançamentos!$G$5:$G$604,Lançamentos!$B$5:$B$604,"Entrada",Lançamentos!$I$5:$I$604,"Sim",Lançamentos!$D$5:$D$604,Config!$J$13,Lançamentos!$K$5:$K$604,Config!$B$5)) -> 32760 | D53: =IF(OR(Config!$J$13="",$C$75=0),"",C53/$C$75) -> 0.15409944 | E53: =IF(Config!$J$13="","",SUMIFS(Lançamentos!$G$5:$G$604,Lançamentos!$B$5:$B$604,"Entrada",Lançamentos!$I$5:$I$604,"Não",Lançamentos!$D$5:$D$604,Config!$J$13)) -> 2700 | F53: =IF(Config!$J$13="","",SUMIFS(Lançamentos!$G$5:$G$604,Lançamentos!$B$5:$B$604,"Saída",Lançamentos!$I$5:$I$604,"Sim",Lançamentos!$D$5:$D$604,Config!$J$13,Lançamentos!$K$5:$K$604,Config!$B$5)) -> 0
A54: =IF(Config!$J$14="","",Config!$J$14) -> Marcos Vinícius Teles | B54: =IF(Config!$J$14="","",SUMIFS(Lançamentos!$G$5:$G$604,Lançamentos!$B$5:$B$604,"Entrada",Lançamentos!$I$5:$I$604,"Sim",Lançamentos!$J$5:$J$604,Config!$B$7,Lançamentos!$K$5:$K$604,Config!$B$5,Lançamentos!$D$5:$D$604,Config!$J$14)) -> 1000 | C54: =IF(Config!$J$14="","",SUMIFS(Lançamentos!$G$5:$G$604,Lançamentos!$B$5:$B$604,"Entrada",Lançamentos!$I$5:$I$604,"Sim",Lançamentos!$D$5:$D$604,Config!$J$14,Lançamentos!$K$5:$K$604,Config!$B$5)) -> 14150 | D54: =IF(OR(Config!$J$14="",$C$75=0),"",C54/$C$75) -> 0.066560045 | E54: =IF(Config!$J$14="","",SUMIFS(Lançamentos!$G$5:$G$604,Lançamentos!$B$5:$B$604,"Entrada",Lançamentos!$I$5:$I$604,"Não",Lançamentos!$D$5:$D$604,Config!$J$14)) -> 2250 | F54: =IF(Config!$J$14="","",SUMIFS(Lançamentos!$G$5:$G$604,Lançamentos!$B$5:$B$604,"Saída",Lançamentos!$I$5:$I$604,"Sim",Lançamentos!$D$5:$D$604,Config!$J$14,Lançamentos!$K$5:$K$604,Config!$B$5)) -> 0
A55: =IF(Config!$J$15="","",Config!$J$15) -> Transportadora Rota Sul | B55: =IF(Config!$J$15="","",SUMIFS(Lançamentos!$G$5:$G$604,Lançamentos!$B$5:$B$604,"Entrada",Lançamentos!$I$5:$I$604,"Sim",Lançamentos!$J$5:$J$604,Config!$B$7,Lançamentos!$K$5:$K$604,Config!$B$5,Lançamentos!$D$5:$D$604,Config!$J$15)) -> 0 | C55: =IF(Config!$J$15="","",SUMIFS(Lançamentos!$G$5:$G$604,Lançamentos!$B$5:$B$604,"Entrada",Lançamentos!$I$5:$I$604,"Sim",Lançamentos!$D$5:$D$604,Config!$J$15,Lançamentos!$K$5:$K$604,Config!$B$5)) -> 12400 | D55: =IF(OR(Config!$J$15="",$C$75=0),"",C55/$C$75) -> 0.058328237 | E55: =IF(Config!$J$15="","",SUMIFS(Lançamentos!$G$5:$G$604,Lançamentos!$B$5:$B$604,"Entrada",Lançamentos!$I$5:$I$604,"Não",Lançamentos!$D$5:$D$604,Config!$J$15)) -> 0 | F55: =IF(Config!$J$15="","",SUMIFS(Lançamentos!$G$5:$G$604,Lançamentos!$B$5:$B$604,"Saída",Lançamentos!$I$5:$I$604,"Sim",Lançamentos!$D$5:$D$604,Config!$J$15,Lançamentos!$K$5:$K$604,Config!$B$5)) -> 130
A56: =IF(Config!$J$16="","",Config!$J$16) -> Patrícia Gomes | B56: =IF(Config!$J$16="","",SUMIFS(Lançamentos!$G$5:$G$604,Lançamentos!$B$5:$B$604,"Entrada",Lançamentos!$I$5:$I$604,"Sim",Lançamentos!$J$5:$J$604,Config!$B$7,Lançamentos!$K$5:$K$604,Config!$B$5,Lançamentos!$D$5:$D$604,Config!$J$16)) -> 0 | C56: =IF(Config!$J$16="","",SUMIFS(Lançamentos!$G$5:$G$604,Lançamentos!$B$5:$B$604,"Entrada",Lançamentos!$I$5:$I$604,"Sim",Lançamentos!$D$5:$D$604,Config!$J$16,Lançamentos!$K$5:$K$604,Config!$B$5)) -> 13500 | D56: =IF(OR(Config!$J$16="",$C$75=0),"",C56/$C$75) -> 0.063502517 | E56: =IF(Config!$J$16="","",SUMIFS(Lançamentos!$G$5:$G$604,Lançamentos!$B$5:$B$604,"Entrada",Lançamentos!$I$5:$I$604,"Não",Lançamentos!$D$5:$D$604,Config!$J$16)) -> 2100 | F56: =IF(Config!$J$16="","",SUMIFS(Lançamentos!$G$5:$G$604,Lançamentos!$B$5:$B$604,"Saída",Lançamentos!$I$5:$I$604,"Sim",Lançamentos!$D$5:$D$604,Config!$J$16,Lançamentos!$K$5:$K$604,Config!$B$5)) -> 380
A57: =IF(Config!$J$17="","",Config!$J$17) -> Escola Aurora | B57: =IF(Config!$J$17="","",SUMIFS(Lançamentos!$G$5:$G$604,Lançamentos!$B$5:$B$604,"Entrada",Lançamentos!$I$5:$I$604,"Sim",Lançamentos!$J$5:$J$604,Config!$B$7,Lançamentos!$K$5:$K$604,Config!$B$5,Lançamentos!$D$5:$D$604,Config!$J$17)) -> 1100 | C57: =IF(Config!$J$17="","",SUMIFS(Lançamentos!$G$5:$G$604,Lançamentos!$B$5:$B$604,"Entrada",Lançamentos!$I$5:$I$604,"Sim",Lançamentos!$D$5:$D$604,Config!$J$17,Lançamentos!$K$5:$K$604,Config!$B$5)) -> 3400 | D57: =IF(OR(Config!$J$17="",$C$75=0),"",C57/$C$75) -> 0.015993226 | E57: =IF(Config!$J$17="","",SUMIFS(Lançamentos!$G$5:$G$604,Lançamentos!$B$5:$B$604,"Entrada",Lançamentos!$I$5:$I$604,"Não",Lançamentos!$D$5:$D$604,Config!$J$17)) -> 0 | F57: =IF(Config!$J$17="","",SUMIFS(Lançamentos!$G$5:$G$604,Lançamentos!$B$5:$B$604,"Saída",Lançamentos!$I$5:$I$604,"Sim",Lançamentos!$D$5:$D$604,Config!$J$17,Lançamentos!$K$5:$K$604,Config!$B$5)) -> 70
A58: =IF(Config!$J$18="","",Config!$J$18) -> José Antônio Ribeiro | B58: =IF(Config!$J$18="","",SUMIFS(Lançamentos!$G$5:$G$604,Lançamentos!$B$5:$B$604,"Entrada",Lançamentos!$I$5:$I$604,"Sim",Lançamentos!$J$5:$J$604,Config!$B$7,Lançamentos!$K$5:$K$604,Config!$B$5,Lançamentos!$D$5:$D$604,Config!$J$18)) -> 0 | C58: =IF(Config!$J$18="","",SUMIFS(Lançamentos!$G$5:$G$604,Lançamentos!$B$5:$B$604,"Entrada",Lançamentos!$I$5:$I$604,"Sim",Lançamentos!$D$5:$D$604,Config!$J$18,Lançamentos!$K$5:$K$604,Config!$B$5)) -> 6000 | D58: =IF(OR(Config!$J$18="",$C$75=0),"",C58/$C$75) -> 0.028223341 | E58: =IF(Config!$J$18="","",SUMIFS(Lançamentos!$G$5:$G$604,Lançamentos!$B$5:$B$604,"Entrada",Lançamentos!$I$5:$I$604,"Não",Lançamentos!$D$5:$D$604,Config!$J$18)) -> 0 | F58: =IF(Config!$J$18="","",SUMIFS(Lançamentos!$G$5:$G$604,Lançamentos!$B$5:$B$604,"Saída",Lançamentos!$I$5:$I$604,"Sim",Lançamentos!$D$5:$D$604,Config!$J$18,Lançamentos!$K$5:$K$604,Config!$B$5)) -> 260
A59: =IF(Config!$J$19="","",Config!$J$19) -> Oficina Mecânica Central | B59: =IF(Config!$J$19="","",SUMIFS(Lançamentos!$G$5:$G$604,Lançamentos!$B$5:$B$604,"Entrada",Lançamentos!$I$5:$I$604,"Sim",Lançamentos!$J$5:$J$604,Config!$B$7,Lançamentos!$K$5:$K$604,Config!$B$5,Lançamentos!$D$5:$D$604,Config!$J$19)) -> 0 | C59: =IF(Config!$J$19="","",SUMIFS(Lançamentos!$G$5:$G$604,Lançamentos!$B$5:$B$604,"Entrada",Lançamentos!$I$5:$I$604,"Sim",Lançamentos!$D$5:$D$604,Config!$J$19,Lançamentos!$K$5:$K$604,Config!$B$5)) -> 16500 | D59: =IF(OR(Config!$J$19="",$C$75=0),"",C59/$C$75) -> 0.077614187 | E59: =IF(Config!$J$19="","",SUMIFS(Lançamentos!$G$5:$G$604,Lançamentos!$B$5:$B$604,"Entrada",Lançamentos!$I$5:$I$604,"Não",Lançamentos!$D$5:$D$604,Config!$J$19)) -> 1500 | F59: =IF(Config!$J$19="","",SUMIFS(Lançamentos!$G$5:$G$604,Lançamentos!$B$5:$B$604,"Saída",Lançamentos!$I$5:$I$604,"Sim",Lançamentos!$D$5:$D$604,Config!$J$19,Lançamentos!$K$5:$K$604,Config!$B$5)) -> 310
A60: =IF(Config!$J$20="","",Config!$J$20) -> Luciana Farias | B60: =IF(Config!$J$20="","",SUMIFS(Lançamentos!$G$5:$G$604,Lançamentos!$B$5:$B$604,"Entrada",Lançamentos!$I$5:$I$604,"Sim",Lançamentos!$J$5:$J$604,Config!$B$7,Lançamentos!$K$5:$K$604,Config!$B$5,Lançamentos!$D$5:$D$604,Config!$J$20)) -> 0 | C60: =IF(Config!$J$20="","",SUMIFS(Lançamentos!$G$5:$G$604,Lançamentos!$B$5:$B$604,"Entrada",Lançamentos!$I$5:$I$604,"Sim",Lançamentos!$D$5:$D$604,Config!$J$20,Lançamentos!$K$5:$K$604,Config!$B$5)) -> 15600 | D60: =IF(OR(Config!$J$20="",$C$75=0),"",C60/$C$75) -> 0.073380686 | E60: =IF(Config!$J$20="","",SUMIFS(Lançamentos!$G$5:$G$604,Lançamentos!$B$5:$B$604,"Entrada",Lançamentos!$I$5:$I$604,"Não",Lançamentos!$D$5:$D$604,Config!$J$20)) -> 0 | F60: =IF(Config!$J$20="","",SUMIFS(Lançamentos!$G$5:$G$604,Lançamentos!$B$5:$B$604,"Saída",Lançamentos!$I$5:$I$604,"Sim",Lançamentos!$D$5:$D$604,Config!$J$20,Lançamentos!$K$5:$K$604,Config!$B$5)) -> 0
A61: =IF(Config!$J$21="","",Config!$J$21) -> Agência Prisma | B61: =IF(Config!$J$21="","",SUMIFS(Lançamentos!$G$5:$G$604,Lançamentos!$B$5:$B$604,"Entrada",Lançamentos!$I$5:$I$604,"Sim",Lançamentos!$J$5:$J$604,Config!$B$7,Lançamentos!$K$5:$K$604,Config!$B$5,Lançamentos!$D$5:$D$604,Config!$J$21)) -> 0 | C61: =IF(Config!$J$21="","",SUMIFS(Lançamentos!$G$5:$G$604,Lançamentos!$B$5:$B$604,"Entrada",Lançamentos!$I$5:$I$604,"Sim",Lançamentos!$D$5:$D$604,Config!$J$21,Lançamentos!$K$5:$K$604,Config!$B$5)) -> 26440 | D61: =IF(OR(Config!$J$21="",$C$75=0),"",C61/$C$75) -> 0.12437085 | E61: =IF(Config!$J$21="","",SUMIFS(Lançamentos!$G$5:$G$604,Lançamentos!$B$5:$B$604,"Entrada",Lançamentos!$I$5:$I$604,"Não",Lançamentos!$D$5:$D$604,Config!$J$21)) -> 3780 | F61: =IF(Config!$J$21="","",SUMIFS(Lançamentos!$G$5:$G$604,Lançamentos!$B$5:$B$604,"Saída",Lançamentos!$I$5:$I$604,"Sim",Lançamentos!$D$5:$D$604,Config!$J$21,Lançamentos!$K$5:$K$604,Config!$B$5)) -> 540
A62: =IF(Config!$J$22="","",Config!$J$22) -> Helena Duarte | B62: =IF(Config!$J$22="","",SUMIFS(Lançamentos!$G$5:$G$604,Lançamentos!$B$5:$B$604,"Entrada",Lançamentos!$I$5:$I$604,"Sim",Lançamentos!$J$5:$J$604,Config!$B$7,Lançamentos!$K$5:$K$604,Config!$B$5,Lançamentos!$D$5:$D$604,Config!$J$22)) -> 0 | C62: =IF(Config!$J$22="","",SUMIFS(Lançamentos!$G$5:$G$604,Lançamentos!$B$5:$B$604,"Entrada",Lançamentos!$I$5:$I$604,"Sim",Lançamentos!$D$5:$D$604,Config!$J$22,Lançamentos!$K$5:$K$604,Config!$B$5)) -> 4500 | D62: =IF(OR(Config!$J$22="",$C$75=0),"",C62/$C$75) -> 0.021167506 | E62: =IF(Config!$J$22="","",SUMIFS(Lançamentos!$G$5:$G$604,Lançamentos!$B$5:$B$604,"Entrada",Lançamentos!$I$5:$I$604,"Não",Lançamentos!$D$5:$D$604,Config!$J$22)) -> 3000 | F62: =IF(Config!$J$22="","",SUMIFS(Lançamentos!$G$5:$G$604,Lançamentos!$B$5:$B$604,"Saída",Lançamentos!$I$5:$I$604,"Sim",Lançamentos!$D$5:$D$604,Config!$J$22,Lançamentos!$K$5:$K$604,Config!$B$5)) -> 0
A63: =IF(Config!$J$23="","",Config!$J$23) | B63: =IF(Config!$J$23="","",SUMIFS(Lançamentos!$G$5:$G$604,Lançamentos!$B$5:$B$604,"Entrada",Lançamentos!$I$5:$I$604,"Sim",Lançamentos!$J$5:$J$604,Config!$B$7,Lançamentos!$K$5:$K$604,Config!$B$5,Lançamentos!$D$5:$D$604,Config!$J$23)) | C63: =IF(Config!$J$23="","",SUMIFS(Lançamentos!$G$5:$G$604,Lançamentos!$B$5:$B$604,"Entrada",Lançamentos!$I$5:$I$604,"Sim",Lançamentos!$D$5:$D$604,Config!$J$23,Lançamentos!$K$5:$K$604,Config!$B$5)) | D63: =IF(OR(Config!$J$23="",$C$75=0),"",C63/$C$75) | E63: =IF(Config!$J$23="","",SUMIFS(Lançamentos!$G$5:$G$604,Lançamentos!$B$5:$B$604,"Entrada",Lançamentos!$I$5:$I$604,"Não",Lançamentos!$D$5:$D$604,Config!$J$23)) | F63: =IF(Config!$J$23="","",SUMIFS(Lançamentos!$G$5:$G$604,Lançamentos!$B$5:$B$604,"Saída",Lançamentos!$I$5:$I$604,"Sim",Lançamentos!$D$5:$D$604,Config!$J$23,Lançamentos!$K$5:$K$604,Config!$B$5))
A64: =IF(Config!$J$24="","",Config!$J$24) | B64: =IF(Config!$J$24="","",SUMIFS(Lançamentos!$G$5:$G$604,Lançamentos!$B$5:$B$604,"Entrada",Lançamentos!$I$5:$I$604,"Sim",Lançamentos!$J$5:$J$604,Config!$B$7,Lançamentos!$K$5:$K$604,Config!$B$5,Lançamentos!$D$5:$D$604,Config!$J$24)) | C64: =IF(Config!$J$24="","",SUMIFS(Lançamentos!$G$5:$G$604,Lançamentos!$B$5:$B$604,"Entrada",Lançamentos!$I$5:$I$604,"Sim",Lançamentos!$D$5:$D$604,Config!$J$24,Lançamentos!$K$5:$K$604,Config!$B$5)) | D64: =IF(OR(Config!$J$24="",$C$75=0),"",C64/$C$75) | E64: =IF(Config!$J$24="","",SUMIFS(Lançamentos!$G$5:$G$604,Lançamentos!$B$5:$B$604,"Entrada",Lançamentos!$I$5:$I$604,"Não",Lançamentos!$D$5:$D$604,Config!$J$24)) | F64: =IF(Config!$J$24="","",SUMIFS(Lançamentos!$G$5:$G$604,Lançamentos!$B$5:$B$604,"Saída",Lançamentos!$I$5:$I$604,"Sim",Lançamentos!$D$5:$D$604,Config!$J$24,Lançamentos!$K$5:$K$604,Config!$B$5))
A65: =IF(Config!$J$25="","",Config!$J$25) | B65: =IF(Config!$J$25="","",SUMIFS(Lançamentos!$G$5:$G$604,Lançamentos!$B$5:$B$604,"Entrada",Lançamentos!$I$5:$I$604,"Sim",Lançamentos!$J$5:$J$604,Config!$B$7,Lançamentos!$K$5:$K$604,Config!$B$5,Lançamentos!$D$5:$D$604,Config!$J$25)) | C65: =IF(Config!$J$25="","",SUMIFS(Lançamentos!$G$5:$G$604,Lançamentos!$B$5:$B$604,"Entrada",Lançamentos!$I$5:$I$604,"Sim",Lançamentos!$D$5:$D$604,Config!$J$25,Lançamentos!$K$5:$K$604,Config!$B$5)) | D65: =IF(OR(Config!$J$25="",$C$75=0),"",C65/$C$75) | E65: =IF(Config!$J$25="","",SUMIFS(Lançamentos!$G$5:$G$604,Lançamentos!$B$5:$B$604,"Entrada",Lançamentos!$I$5:$I$604,"Não",Lançamentos!$D$5:$D$604,Config!$J$25)) | F65: =IF(Config!$J$25="","",SUMIFS(Lançamentos!$G$5:$G$604,Lançamentos!$B$5:$B$604,"Saída",Lançamentos!$I$5:$I$604,"Sim",Lançamentos!$D$5:$D$604,Config!$J$25,Lançamentos!$K$5:$K$604,Config!$B$5))
A66: =IF(Config!$J$26="","",Config!$J$26) | B66: =IF(Config!$J$26="","",SUMIFS(Lançamentos!$G$5:$G$604,Lançamentos!$B$5:$B$604,"Entrada",Lançamentos!$I$5:$I$604,"Sim",Lançamentos!$J$5:$J$604,Config!$B$7,Lançamentos!$K$5:$K$604,Config!$B$5,Lançamentos!$D$5:$D$604,Config!$J$26)) | C66: =IF(Config!$J$26="","",SUMIFS(Lançamentos!$G$5:$G$604,Lançamentos!$B$5:$B$604,"Entrada",Lançamentos!$I$5:$I$604,"Sim",Lançamentos!$D$5:$D$604,Config!$J$26,Lançamentos!$K$5:$K$604,Config!$B$5)) | D66: =IF(OR(Config!$J$26="",$C$75=0),"",C66/$C$75) | E66: =IF(Config!$J$26="","",SUMIFS(Lançamentos!$G$5:$G$604,Lançamentos!$B$5:$B$604,"Entrada",Lançamentos!$I$5:$I$604,"Não",Lançamentos!$D$5:$D$604,Config!$J$26)) | F66: =IF(Config!$J$26="","",SUMIFS(Lançamentos!$G$5:$G$604,Lançamentos!$B$5:$B$604,"Saída",Lançamentos!$I$5:$I$604,"Sim",Lançamentos!$D$5:$D$604,Config!$J$26,Lançamentos!$K$5:$K$604,Config!$B$5))
A67: =IF(Config!$J$27="","",Config!$J$27) | B67: =IF(Config!$J$27="","",SUMIFS(Lançamentos!$G$5:$G$604,Lançamentos!$B$5:$B$604,"Entrada",Lançamentos!$I$5:$I$604,"Sim",Lançamentos!$J$5:$J$604,Config!$B$7,Lançamentos!$K$5:$K$604,Config!$B$5,Lançamentos!$D$5:$D$604,Config!$J$27)) | C67: =IF(Config!$J$27="","",SUMIFS(Lançamentos!$G$5:$G$604,Lançamentos!$B$5:$B$604,"Entrada",Lançamentos!$I$5:$I$604,"Sim",Lançamentos!$D$5:$D$604,Config!$J$27,Lançamentos!$K$5:$K$604,Config!$B$5)) | D67: =IF(OR(Config!$J$27="",$C$75=0),"",C67/$C$75) | E67: =IF(Config!$J$27="","",SUMIFS(Lançamentos!$G$5:$G$604,Lançamentos!$B$5:$B$604,"Entrada",Lançamentos!$I$5:$I$604,"Não",Lançamentos!$D$5:$D$604,Config!$J$27)) | F67: =IF(Config!$J$27="","",SUMIFS(Lançamentos!$G$5:$G$604,Lançamentos!$B$5:$B$604,"Saída",Lançamentos!$I$5:$I$604,"Sim",Lançamentos!$D$5:$D$604,Config!$J$27,Lançamentos!$K$5:$K$604,Config!$B$5))
A68: =IF(Config!$J$28="","",Config!$J$28) | B68: =IF(Config!$J$28="","",SUMIFS(Lançamentos!$G$5:$G$604,Lançamentos!$B$5:$B$604,"Entrada",Lançamentos!$I$5:$I$604,"Sim",Lançamentos!$J$5:$J$604,Config!$B$7,Lançamentos!$K$5:$K$604,Config!$B$5,Lançamentos!$D$5:$D$604,Config!$J$28)) | C68: =IF(Config!$J$28="","",SUMIFS(Lançamentos!$G$5:$G$604,Lançamentos!$B$5:$B$604,"Entrada",Lançamentos!$I$5:$I$604,"Sim",Lançamentos!$D$5:$D$604,Config!$J$28,Lançamentos!$K$5:$K$604,Config!$B$5)) | D68: =IF(OR(Config!$J$28="",$C$75=0),"",C68/$C$75) | E68: =IF(Config!$J$28="","",SUMIFS(Lançamentos!$G$5:$G$604,Lançamentos!$B$5:$B$604,"Entrada",Lançamentos!$I$5:$I$604,"Não",Lançamentos!$D$5:$D$604,Config!$J$28)) | F68: =IF(Config!$J$28="","",SUMIFS(Lançamentos!$G$5:$G$604,Lançamentos!$B$5:$B$604,"Saída",Lançamentos!$I$5:$I$604,"Sim",Lançamentos!$D$5:$D$604,Config!$J$28,Lançamentos!$K$5:$K$604,Config!$B$5))
A69: =IF(Config!$J$29="","",Config!$J$29) | B69: =IF(Config!$J$29="","",SUMIFS(Lançamentos!$G$5:$G$604,Lançamentos!$B$5:$B$604,"Entrada",Lançamentos!$I$5:$I$604,"Sim",Lançamentos!$J$5:$J$604,Config!$B$7,Lançamentos!$K$5:$K$604,Config!$B$5,Lançamentos!$D$5:$D$604,Config!$J$29)) | C69: =IF(Config!$J$29="","",SUMIFS(Lançamentos!$G$5:$G$604,Lançamentos!$B$5:$B$604,"Entrada",Lançamentos!$I$5:$I$604,"Sim",Lançamentos!$D$5:$D$604,Config!$J$29,Lançamentos!$K$5:$K$604,Config!$B$5)) | D69: =IF(OR(Config!$J$29="",$C$75=0),"",C69/$C$75) | E69: =IF(Config!$J$29="","",SUMIFS(Lançamentos!$G$5:$G$604,Lançamentos!$B$5:$B$604,"Entrada",Lançamentos!$I$5:$I$604,"Não",Lançamentos!$D$5:$D$604,Config!$J$29)) | F69: =IF(Config!$J$29="","",SUMIFS(Lançamentos!$G$5:$G$604,Lançamentos!$B$5:$B$604,"Saída",Lançamentos!$I$5:$I$604,"Sim",Lançamentos!$D$5:$D$604,Config!$J$29,Lançamentos!$K$5:$K$604,Config!$B$5))
A70: =IF(Config!$J$30="","",Config!$J$30) | B70: =IF(Config!$J$30="","",SUMIFS(Lançamentos!$G$5:$G$604,Lançamentos!$B$5:$B$604,"Entrada",Lançamentos!$I$5:$I$604,"Sim",Lançamentos!$J$5:$J$604,Config!$B$7,Lançamentos!$K$5:$K$604,Config!$B$5,Lançamentos!$D$5:$D$604,Config!$J$30)) | C70: =IF(Config!$J$30="","",SUMIFS(Lançamentos!$G$5:$G$604,Lançamentos!$B$5:$B$604,"Entrada",Lançamentos!$I$5:$I$604,"Sim",Lançamentos!$D$5:$D$604,Config!$J$30,Lançamentos!$K$5:$K$604,Config!$B$5)) | D70: =IF(OR(Config!$J$30="",$C$75=0),"",C70/$C$75) | E70: =IF(Config!$J$30="","",SUMIFS(Lançamentos!$G$5:$G$604,Lançamentos!$B$5:$B$604,"Entrada",Lançamentos!$I$5:$I$604,"Não",Lançamentos!$D$5:$D$604,Config!$J$30)) | F70: =IF(Config!$J$30="","",SUMIFS(Lançamentos!$G$5:$G$604,Lançamentos!$B$5:$B$604,"Saída",Lançamentos!$I$5:$I$604,"Sim",Lançamentos!$D$5:$D$604,Config!$J$30,Lançamentos!$K$5:$K$604,Config!$B$5))
A71: =IF(Config!$J$31="","",Config!$J$31) | B71: =IF(Config!$J$31="","",SUMIFS(Lançamentos!$G$5:$G$604,Lançamentos!$B$5:$B$604,"Entrada",Lançamentos!$I$5:$I$604,"Sim",Lançamentos!$J$5:$J$604,Config!$B$7,Lançamentos!$K$5:$K$604,Config!$B$5,Lançamentos!$D$5:$D$604,Config!$J$31)) | C71: =IF(Config!$J$31="","",SUMIFS(Lançamentos!$G$5:$G$604,Lançamentos!$B$5:$B$604,"Entrada",Lançamentos!$I$5:$I$604,"Sim",Lançamentos!$D$5:$D$604,Config!$J$31,Lançamentos!$K$5:$K$604,Config!$B$5)) | D71: =IF(OR(Config!$J$31="",$C$75=0),"",C71/$C$75) | E71: =IF(Config!$J$31="","",SUMIFS(Lançamentos!$G$5:$G$604,Lançamentos!$B$5:$B$604,"Entrada",Lançamentos!$I$5:$I$604,"Não",Lançamentos!$D$5:$D$604,Config!$J$31)) | F71: =IF(Config!$J$31="","",SUMIFS(Lançamentos!$G$5:$G$604,Lançamentos!$B$5:$B$604,"Saída",Lançamentos!$I$5:$I$604,"Sim",Lançamentos!$D$5:$D$604,Config!$J$31,Lançamentos!$K$5:$K$604,Config!$B$5))
A72: =IF(Config!$J$32="","",Config!$J$32) | B72: =IF(Config!$J$32="","",SUMIFS(Lançamentos!$G$5:$G$604,Lançamentos!$B$5:$B$604,"Entrada",Lançamentos!$I$5:$I$604,"Sim",Lançamentos!$J$5:$J$604,Config!$B$7,Lançamentos!$K$5:$K$604,Config!$B$5,Lançamentos!$D$5:$D$604,Config!$J$32)) | C72: =IF(Config!$J$32="","",SUMIFS(Lançamentos!$G$5:$G$604,Lançamentos!$B$5:$B$604,"Entrada",Lançamentos!$I$5:$I$604,"Sim",Lançamentos!$D$5:$D$604,Config!$J$32,Lançamentos!$K$5:$K$604,Config!$B$5)) | D72: =IF(OR(Config!$J$32="",$C$75=0),"",C72/$C$75) | E72: =IF(Config!$J$32="","",SUMIFS(Lançamentos!$G$5:$G$604,Lançamentos!$B$5:$B$604,"Entrada",Lançamentos!$I$5:$I$604,"Não",Lançamentos!$D$5:$D$604,Config!$J$32)) | F72: =IF(Config!$J$32="","",SUMIFS(Lançamentos!$G$5:$G$604,Lançamentos!$B$5:$B$604,"Saída",Lançamentos!$I$5:$I$604,"Sim",Lançamentos!$D$5:$D$604,Config!$J$32,Lançamentos!$K$5:$K$604,Config!$B$5))
A73: =IF(Config!$J$33="","",Config!$J$33) | B73: =IF(Config!$J$33="","",SUMIFS(Lançamentos!$G$5:$G$604,Lançamentos!$B$5:$B$604,"Entrada",Lançamentos!$I$5:$I$604,"Sim",Lançamentos!$J$5:$J$604,Config!$B$7,Lançamentos!$K$5:$K$604,Config!$B$5,Lançamentos!$D$5:$D$604,Config!$J$33)) | C73: =IF(Config!$J$33="","",SUMIFS(Lançamentos!$G$5:$G$604,Lançamentos!$B$5:$B$604,"Entrada",Lançamentos!$I$5:$I$604,"Sim",Lançamentos!$D$5:$D$604,Config!$J$33,Lançamentos!$K$5:$K$604,Config!$B$5)) | D73: =IF(OR(Config!$J$33="",$C$75=0),"",C73/$C$75) | E73: =IF(Config!$J$33="","",SUMIFS(Lançamentos!$G$5:$G$604,Lançamentos!$B$5:$B$604,"Entrada",Lançamentos!$I$5:$I$604,"Não",Lançamentos!$D$5:$D$604,Config!$J$33)) | F73: =IF(Config!$J$33="","",SUMIFS(Lançamentos!$G$5:$G$604,Lançamentos!$B$5:$B$604,"Saída",Lançamentos!$I$5:$I$604,"Sim",Lançamentos!$D$5:$D$604,Config!$J$33,Lançamentos!$K$5:$K$604,Config!$B$5))
A74: =IF(Config!$J$34="","",Config!$J$34) | B74: =IF(Config!$J$34="","",SUMIFS(Lançamentos!$G$5:$G$604,Lançamentos!$B$5:$B$604,"Entrada",Lançamentos!$I$5:$I$604,"Sim",Lançamentos!$J$5:$J$604,Config!$B$7,Lançamentos!$K$5:$K$604,Config!$B$5,Lançamentos!$D$5:$D$604,Config!$J$34)) | C74: =IF(Config!$J$34="","",SUMIFS(Lançamentos!$G$5:$G$604,Lançamentos!$B$5:$B$604,"Entrada",Lançamentos!$I$5:$I$604,"Sim",Lançamentos!$D$5:$D$604,Config!$J$34,Lançamentos!$K$5:$K$604,Config!$B$5)) | D74: =IF(OR(Config!$J$34="",$C$75=0),"",C74/$C$75) | E74: =IF(Config!$J$34="","",SUMIFS(Lançamentos!$G$5:$G$604,Lançamentos!$B$5:$B$604,"Entrada",Lançamentos!$I$5:$I$604,"Não",Lançamentos!$D$5:$D$604,Config!$J$34)) | F74: =IF(Config!$J$34="","",SUMIFS(Lançamentos!$G$5:$G$604,Lançamentos!$B$5:$B$604,"Saída",Lançamentos!$I$5:$I$604,"Sim",Lançamentos!$D$5:$D$604,Config!$J$34,Lançamentos!$K$5:$K$604,Config!$B$5))
A75: Total | B75: =SUM(B45:B74) -> 5220 | C75: =SUM(C45:C74) -> 212590 | E75: =SUM(E45:E74) -> 27330 | F75: =SUM(F45:F74) -> 2875
A76: Lançamentos sem cliente (aluguel, pró-labore, impostos) não aparecem aqui; estão em "Para onde foi o dinheiro".
A78: O ano, mês a mês
A79: Mês | B79: Entrou | C79: Saiu | D79: Sobrou | E79: Saldo ao fim do mês
A80: Janeiro | B80: =SUMIFS(Lançamentos!$G$5:$G$604,Lançamentos!$B$5:$B$604,"Entrada",Lançamentos!$I$5:$I$604,"Sim",Lançamentos!$J$5:$J$604,1,Lançamentos!$K$5:$K$604,Config!$B$5) -> 21050 | C80: =SUMIFS(Lançamentos!$G$5:$G$604,Lançamentos!$B$5:$B$604,"Saída",Lançamentos!$I$5:$I$604,"Sim",Lançamentos!$J$5:$J$604,1,Lançamentos!$K$5:$K$604,Config!$B$5) -> 20408 | D80: =B80-C80 -> 642 | E80: =Config!$B$8+SUMIFS(Lançamentos!$G$5:$G$604,Lançamentos!$B$5:$B$604,"Entrada",Lançamentos!$I$5:$I$604,"Sim",Lançamentos!$A$5:$A$604,"<="&DATE(Config!$B$5,2,0))-SUMIFS(Lançamentos!$G$5:$G$604,Lançamentos!$B$5:$B$604,"Saída",Lançamentos!$I$5:$I$604,"Sim",Lançamentos!$A$5:$A$604,"<="&DATE(Config!$B$5,2,0)) -> 22642
A81: Fevereiro | B81: =SUMIFS(Lançamentos!$G$5:$G$604,Lançamentos!$B$5:$B$604,"Entrada",Lançamentos!$I$5:$I$604,"Sim",Lançamentos!$J$5:$J$604,2,Lançamentos!$K$5:$K$604,Config!$B$5) -> 23070 | C81: =SUMIFS(Lançamentos!$G$5:$G$604,Lançamentos!$B$5:$B$604,"Saída",Lançamentos!$I$5:$I$604,"Sim",Lançamentos!$J$5:$J$604,2,Lançamentos!$K$5:$K$604,Config!$B$5) -> 21684 | D81: =B81-C81 -> 1386 | E81: =Config!$B$8+SUMIFS(Lançamentos!$G$5:$G$604,Lançamentos!$B$5:$B$604,"Entrada",Lançamentos!$I$5:$I$604,"Sim",Lançamentos!$A$5:$A$604,"<="&DATE(Config!$B$5,3,0))-SUMIFS(Lançamentos!$G$5:$G$604,Lançamentos!$B$5:$B$604,"Saída",Lançamentos!$I$5:$I$604,"Sim",Lançamentos!$A$5:$A$604,"<="&DATE(Config!$B$5,3,0)) -> 24028
A82: Março | B82: =SUMIFS(Lançamentos!$G$5:$G$604,Lançamentos!$B$5:$B$604,"Entrada",Lançamentos!$I$5:$I$604,"Sim",Lançamentos!$J$5:$J$604,3,Lançamentos!$K$5:$K$604,Config!$B$5) -> 28590 | C82: =SUMIFS(Lançamentos!$G$5:$G$604,Lançamentos!$B$5:$B$604,"Saída",Lançamentos!$I$5:$I$604,"Sim",Lançamentos!$J$5:$J$604,3,Lançamentos!$K$5:$K$604,Config!$B$5) -> 22276 | D82: =B82-C82 -> 6314 | E82: =Config!$B$8+SUMIFS(Lançamentos!$G$5:$G$604,Lançamentos!$B$5:$B$604,"Entrada",Lançamentos!$I$5:$I$604,"Sim",Lançamentos!$A$5:$A$604,"<="&DATE(Config!$B$5,4,0))-SUMIFS(Lançamentos!$G$5:$G$604,Lançamentos!$B$5:$B$604,"Saída",Lançamentos!$I$5:$I$604,"Sim",Lançamentos!$A$5:$A$604,"<="&DATE(Config!$B$5,4,0)) -> 30342
A83: Abril | B83: =SUMIFS(Lançamentos!$G$5:$G$604,Lançamentos!$B$5:$B$604,"Entrada",Lançamentos!$I$5:$I$604,"Sim",Lançamentos!$J$5:$J$604,4,Lançamentos!$K$5:$K$604,Config!$B$5) -> 20240 | C83: =SUMIFS(Lançamentos!$G$5:$G$604,Lançamentos!$B$5:$B$604,"Saída",Lançamentos!$I$5:$I$604,"Sim",Lançamentos!$J$5:$J$604,4,Lançamentos!$K$5:$K$604,Config!$B$5) -> 26638 | D83: =B83-C83 -> -6398 | E83: =Config!$B$8+SUMIFS(Lançamentos!$G$5:$G$604,Lançamentos!$B$5:$B$604,"Entrada",Lançamentos!$I$5:$I$604,"Sim",Lançamentos!$A$5:$A$604,"<="&DATE(Config!$B$5,5,0))-SUMIFS(Lançamentos!$G$5:$G$604,Lançamentos!$B$5:$B$604,"Saída",Lançamentos!$I$5:$I$604,"Sim",Lançamentos!$A$5:$A$604,"<="&DATE(Config!$B$5,5,0)) -> 23944
A84: Maio | B84: =SUMIFS(Lançamentos!$G$5:$G$604,Lançamentos!$B$5:$B$604,"Entrada",Lançamentos!$I$5:$I$604,"Sim",Lançamentos!$J$5:$J$604,5,Lançamentos!$K$5:$K$604,Config!$B$5) -> 31120 | C84: =SUMIFS(Lançamentos!$G$5:$G$604,Lançamentos!$B$5:$B$604,"Saída",Lançamentos!$I$5:$I$604,"Sim",Lançamentos!$J$5:$J$604,5,Lançamentos!$K$5:$K$604,Config!$B$5) -> 21181 | D84: =B84-C84 -> 9939 | E84: =Config!$B$8+SUMIFS(Lançamentos!$G$5:$G$604,Lançamentos!$B$5:$B$604,"Entrada",Lançamentos!$I$5:$I$604,"Sim",Lançamentos!$A$5:$A$604,"<="&DATE(Config!$B$5,6,0))-SUMIFS(Lançamentos!$G$5:$G$604,Lançamentos!$B$5:$B$604,"Saída",Lançamentos!$I$5:$I$604,"Sim",Lançamentos!$A$5:$A$604,"<="&DATE(Config!$B$5,6,0)) -> 33883
A85: Junho | B85: =SUMIFS(Lançamentos!$G$5:$G$604,Lançamentos!$B$5:$B$604,"Entrada",Lançamentos!$I$5:$I$604,"Sim",Lançamentos!$J$5:$J$604,6,Lançamentos!$K$5:$K$604,Config!$B$5) -> 27420 | C85: =SUMIFS(Lançamentos!$G$5:$G$604,Lançamentos!$B$5:$B$604,"Saída",Lançamentos!$I$5:$I$604,"Sim",Lançamentos!$J$5:$J$604,6,Lançamentos!$K$5:$K$604,Config!$B$5) -> 23085 | D85: =B85-C85 -> 4335 | E85: =Config!$B$8+SUMIFS(Lançamentos!$G$5:$G$604,Lançamentos!$B$5:$B$604,"Entrada",Lançamentos!$I$5:$I$604,"Sim",Lançamentos!$A$5:$A$604,"<="&DATE(Config!$B$5,7,0))-SUMIFS(Lançamentos!$G$5:$G$604,Lançamentos!$B$5:$B$604,"Saída",Lançamentos!$I$5:$I$604,"Sim",Lançamentos!$A$5:$A$604,"<="&DATE(Config!$B$5,7,0)) -> 38218
A86: Julho | B86: =SUMIFS(Lançamentos!$G$5:$G$604,Lançamentos!$B$5:$B$604,"Entrada",Lançamentos!$I$5:$I$604,"Sim",Lançamentos!$J$5:$J$604,7,Lançamentos!$K$5:$K$604,Config!$B$5) -> 29460 | C86: =SUMIFS(Lançamentos!$G$5:$G$604,Lançamentos!$B$5:$B$604,"Saída",Lançamentos!$I$5:$I$604,"Sim",Lançamentos!$J$5:$J$604,7,Lançamentos!$K$5:$K$604,Config!$B$5) -> 28898 | D86: =B86-C86 -> 562 | E86: =Config!$B$8+SUMIFS(Lançamentos!$G$5:$G$604,Lançamentos!$B$5:$B$604,"Entrada",Lançamentos!$I$5:$I$604,"Sim",Lançamentos!$A$5:$A$604,"<="&DATE(Config!$B$5,8,0))-SUMIFS(Lançamentos!$G$5:$G$604,Lançamentos!$B$5:$B$604,"Saída",Lançamentos!$I$5:$I$604,"Sim",Lançamentos!$A$5:$A$604,"<="&DATE(Config!$B$5,8,0)) -> 38780
A87: Agosto | B87: =SUMIFS(Lançamentos!$G$5:$G$604,Lançamentos!$B$5:$B$604,"Entrada",Lançamentos!$I$5:$I$604,"Sim",Lançamentos!$J$5:$J$604,8,Lançamentos!$K$5:$K$604,Config!$B$5) -> 26900 | C87: =SUMIFS(Lançamentos!$G$5:$G$604,Lançamentos!$B$5:$B$604,"Saída",Lançamentos!$I$5:$I$604,"Sim",Lançamentos!$J$5:$J$604,8,Lançamentos!$K$5:$K$604,Config!$B$5) -> 21897 | D87: =B87-C87 -> 5003 | E87: =Config!$B$8+SUMIFS(Lançamentos!$G$5:$G$604,Lançamentos!$B$5:$B$604,"Entrada",Lançamentos!$I$5:$I$604,"Sim",Lançamentos!$A$5:$A$604,"<="&DATE(Config!$B$5,9,0))-SUMIFS(Lançamentos!$G$5:$G$604,Lançamentos!$B$5:$B$604,"Saída",Lançamentos!$I$5:$I$604,"Sim",Lançamentos!$A$5:$A$604,"<="&DATE(Config!$B$5,9,0)) -> 43783
A88: Setembro | B88: =SUMIFS(Lançamentos!$G$5:$G$604,Lançamentos!$B$5:$B$604,"Entrada",Lançamentos!$I$5:$I$604,"Sim",Lançamentos!$J$5:$J$604,9,Lançamentos!$K$5:$K$604,Config!$B$5) -> 5220 | C88: =SUMIFS(Lançamentos!$G$5:$G$604,Lançamentos!$B$5:$B$604,"Saída",Lançamentos!$I$5:$I$604,"Sim",Lançamentos!$J$5:$J$604,9,Lançamentos!$K$5:$K$604,Config!$B$5) -> 5320 | D88: =B88-C88 -> -100 | E88: =Config!$B$8+SUMIFS(Lançamentos!$G$5:$G$604,Lançamentos!$B$5:$B$604,"Entrada",Lançamentos!$I$5:$I$604,"Sim",Lançamentos!$A$5:$A$604,"<="&DATE(Config!$B$5,10,0))-SUMIFS(Lançamentos!$G$5:$G$604,Lançamentos!$B$5:$B$604,"Saída",Lançamentos!$I$5:$I$604,"Sim",Lançamentos!$A$5:$A$604,"<="&DATE(Config!$B$5,10,0)) -> 43683
A89: Outubro | B89: =SUMIFS(Lançamentos!$G$5:$G$604,Lançamentos!$B$5:$B$604,"Entrada",Lançamentos!$I$5:$I$604,"Sim",Lançamentos!$J$5:$J$604,10,Lançamentos!$K$5:$K$604,Config!$B$5) -> 0 | C89: =SUMIFS(Lançamentos!$G$5:$G$604,Lançamentos!$B$5:$B$604,"Saída",Lançamentos!$I$5:$I$604,"Sim",Lançamentos!$J$5:$J$604,10,Lançamentos!$K$5:$K$604,Config!$B$5) -> 0 | D89: =B89-C89 -> 0 | E89: =Config!$B$8+SUMIFS(Lançamentos!$G$5:$G$604,Lançamentos!$B$5:$B$604,"Entrada",Lançamentos!$I$5:$I$604,"Sim",Lançamentos!$A$5:$A$604,"<="&DATE(Config!$B$5,11,0))-SUMIFS(Lançamentos!$G$5:$G$604,Lançamentos!$B$5:$B$604,"Saída",Lançamentos!$I$5:$I$604,"Sim",Lançamentos!$A$5:$A$604,"<="&DATE(Config!$B$5,11,0)) -> 43683
A90: Novembro | B90: =SUMIFS(Lançamentos!$G$5:$G$604,Lançamentos!$B$5:$B$604,"Entrada",Lançamentos!$I$5:$I$604,"Sim",Lançamentos!$J$5:$J$604,11,Lançamentos!$K$5:$K$604,Config!$B$5) -> 0 | C90: =SUMIFS(Lançamentos!$G$5:$G$604,Lançamentos!$B$5:$B$604,"Saída",Lançamentos!$I$5:$I$604,"Sim",Lançamentos!$J$5:$J$604,11,Lançamentos!$K$5:$K$604,Config!$B$5) -> 0 | D90: =B90-C90 -> 0 | E90: =Config!$B$8+SUMIFS(Lançamentos!$G$5:$G$604,Lançamentos!$B$5:$B$604,"Entrada",Lançamentos!$I$5:$I$604,"Sim",Lançamentos!$A$5:$A$604,"<="&DATE(Config!$B$5,12,0))-SUMIFS(Lançamentos!$G$5:$G$604,Lançamentos!$B$5:$B$604,"Saída",Lançamentos!$I$5:$I$604,"Sim",Lançamentos!$A$5:$A$604,"<="&DATE(Config!$B$5,12,0)) -> 43683
A91: Dezembro | B91: =SUMIFS(Lançamentos!$G$5:$G$604,Lançamentos!$B$5:$B$604,"Entrada",Lançamentos!$I$5:$I$604,"Sim",Lançamentos!$J$5:$J$604,12,Lançamentos!$K$5:$K$604,Config!$B$5) -> 0 | C91: =SUMIFS(Lançamentos!$G$5:$G$604,Lançamentos!$B$5:$B$604,"Saída",Lançamentos!$I$5:$I$604,"Sim",Lançamentos!$J$5:$J$604,12,Lançamentos!$K$5:$K$604,Config!$B$5) -> 0 | D91: =B91-C91 -> 0 | E91: =Config!$B$8+SUMIFS(Lançamentos!$G$5:$G$604,Lançamentos!$B$5:$B$604,"Entrada",Lançamentos!$I$5:$I$604,"Sim",Lançamentos!$A$5:$A$604,"<="&DATE(Config!$B$5,13,0))-SUMIFS(Lançamentos!$G$5:$G$604,Lançamentos!$B$5:$B$604,"Saída",Lançamentos!$I$5:$I$604,"Sim",Lançamentos!$A$5:$A$604,"<="&DATE(Config!$B$5,13,0)) -> 43683
A92: Meses sem lançamento pago aparecem zerados. Compare só os meses já fechados; o mês corrente ainda não tem todas as saídas.

Sheet Config
A1: Configurações
A2: Células amarelas: você preenche. Categorias e clientes alimentam as listas de Lançamentos e o Painel.
A4: Escritório | B4: Ferraz & Lima Advocacia (exemplo fictício) | D4: Categorias de entrada (até 12) | F4: Categorias de saída (até 16) | H4: Todas as categorias (automático) | J4: Clientes (até 30) | L4: Meses
A5: Ano do painel | B5: 2026 | D5: Honorários fixos | F5: Pró-labore dos sócios | H5: =IF(1<=COUNTA($D$5:$D$16),INDEX($D$5:$D$16,1),IF(1<=COUNTA($D$5:$D$16)+COUNTA($F$5:$F$20),INDEX($F$5:$F$20,1-COUNTA($D$5:$D$16)),"")) -> Honorários fixos | J5: Padaria do Sol Ltda | L5: Janeiro
A6: Mês do painel | B6: Setembro | D6: Honorários por hora | F6: Aluguel e condomínio | H6: =IF(2<=COUNTA($D$5:$D$16),INDEX($D$5:$D$16,2),IF(2<=COUNTA($D$5:$D$16)+COUNTA($F$5:$F$20),INDEX($F$5:$F$20,2-COUNTA($D$5:$D$16)),"")) -> Honorários por hora | J6: Ana Beatriz Moreira | L6: Fevereiro
A7: Número do mês | B7: =MATCH(B6,$L$5:$L$16,0) -> 9 | D7: Honorários de êxito | F7: Contador | H7: =IF(3<=COUNTA($D$5:$D$16),INDEX($D$5:$D$16,3),IF(3<=COUNTA($D$5:$D$16)+COUNTA($F$5:$F$20),INDEX($F$5:$F$20,3-COUNTA($D$5:$D$16)),"")) -> Honorários de êxito | J7: Construtora Horizonte | L7: Março
A8: Saldo em caixa antes do 1º lançamento | B8: 22000 | D8: Consultoria e pareceres | F8: Sistemas e assinaturas | H8: =IF(4<=COUNTA($D$5:$D$16),INDEX($D$5:$D$16,4),IF(4<=COUNTA($D$5:$D$16)+COUNTA($F$5:$F$20),INDEX($F$5:$F$20,4-COUNTA($D$5:$D$16)),"")) -> Consultoria e pareceres | J8: Carlos Eduardo Nunes | L8: Abril
A9: Data de referência | B9: =TODAY() -> 46279 | D9: Reembolso de custas | F9: Telefone e internet | H9: =IF(5<=COUNTA($D$5:$D$16),INDEX($D$5:$D$16,5),IF(5<=COUNTA($D$5:$D$16)+COUNTA($F$5:$F$20),INDEX($F$5:$F$20,5-COUNTA($D$5:$D$16)),"")) -> Reembolso de custas | J9: Loja Verde Comércio | L9: Maio
D10: Outras entradas | F10: Anuidades OAB e cursos | H10: =IF(6<=COUNTA($D$5:$D$16),INDEX($D$5:$D$16,6),IF(6<=COUNTA($D$5:$D$16)+COUNTA($F$5:$F$20),INDEX($F$5:$F$20,6-COUNTA($D$5:$D$16)),"")) -> Outras entradas | J10: Fernanda Castro | L10: Junho
F11: Marketing e site | H11: =IF(7<=COUNTA($D$5:$D$16),INDEX($D$5:$D$16,7),IF(7<=COUNTA($D$5:$D$16)+COUNTA($F$5:$F$20),INDEX($F$5:$F$20,7-COUNTA($D$5:$D$16)),"")) -> Pró-labore dos sócios | J11: Bistrô 42 | L11: Julho
F12: Estagiária (bolsa) | H12: =IF(8<=COUNTA($D$5:$D$16),INDEX($D$5:$D$16,8),IF(8<=COUNTA($D$5:$D$16)+COUNTA($F$5:$F$20),INDEX($F$5:$F$20,8-COUNTA($D$5:$D$16)),"")) -> Aluguel e condomínio | J12: Roberto Almeida | L12: Agosto
F13: Material, correio e outros | H13: =IF(9<=COUNTA($D$5:$D$16),INDEX($D$5:$D$16,9),IF(9<=COUNTA($D$5:$D$16)+COUNTA($F$5:$F$20),INDEX($F$5:$F$20,9-COUNTA($D$5:$D$16)),"")) -> Contador | J13: Clínica Bem-Estar | L13: Setembro
F14: Impostos e taxas | H14: =IF(10<=COUNTA($D$5:$D$16),INDEX($D$5:$D$16,10),IF(10<=COUNTA($D$5:$D$16)+COUNTA($F$5:$F$20),INDEX($F$5:$F$20,10-COUNTA($D$5:$D$16)),"")) -> Sistemas e assinaturas | J14: Marcos Vinícius Teles | L14: Outubro
F15: Custas e despesas de processo | H15: =IF(11<=COUNTA($D$5:$D$16),INDEX($D$5:$D$16,11),IF(11<=COUNTA($D$5:$D$16)+COUNTA($F$5:$F$20),INDEX($F$5:$F$20,11-COUNTA($D$5:$D$16)),"")) -> Telefone e internet | J15: Transportadora Rota Sul | L15: Novembro
F16: Deslocamento e viagens | H16: =IF(12<=COUNTA($D$5:$D$16),INDEX($D$5:$D$16,12),IF(12<=COUNTA($D$5:$D$16)+COUNTA($F$5:$F$20),INDEX($F$5:$F$20,12-COUNTA($D$5:$D$16)),"")) -> Anuidades OAB e cursos | J16: Patrícia Gomes | L16: Dezembro
F17: Outras saídas | H17: =IF(13<=COUNTA($D$5:$D$16),INDEX($D$5:$D$16,13),IF(13<=COUNTA($D$5:$D$16)+COUNTA($F$5:$F$20),INDEX($F$5:$F$20,13-COUNTA($D$5:$D$16)),"")) -> Marketing e site | J17: Escola Aurora
H18: =IF(14<=COUNTA($D$5:$D$16),INDEX($D$5:$D$16,14),IF(14<=COUNTA($D$5:$D$16)+COUNTA($F$5:$F$20),INDEX($F$5:$F$20,14-COUNTA($D$5:$D$16)),"")) -> Estagiária (bolsa) | J18: José Antônio Ribeiro
H19: =IF(15<=COUNTA($D$5:$D$16),INDEX($D$5:$D$16,15),IF(15<=COUNTA($D$5:$D$16)+COUNTA($F$5:$F$20),INDEX($F$5:$F$20,15-COUNTA($D$5:$D$16)),"")) -> Material, correio e outros | J19: Oficina Mecânica Central
H20: =IF(16<=COUNTA($D$5:$D$16),INDEX($D$5:$D$16,16),IF(16<=COUNTA($D$5:$D$16)+COUNTA($F$5:$F$20),INDEX($F$5:$F$20,16-COUNTA($D$5:$D$16)),"")) -> Impostos e taxas | J20: Luciana Farias
H21: =IF(17<=COUNTA($D$5:$D$16),INDEX($D$5:$D$16,17),IF(17<=COUNTA($D$5:$D$16)+COUNTA($F$5:$F$20),INDEX($F$5:$F$20,17-COUNTA($D$5:$D$16)),"")) -> Custas e despesas de processo | J21: Agência Prisma
H22: =IF(18<=COUNTA($D$5:$D$16),INDEX($D$5:$D$16,18),IF(18<=COUNTA($D$5:$D$16)+COUNTA($F$5:$F$20),INDEX($F$5:$F$20,18-COUNTA($D$5:$D$16)),"")) -> Deslocamento e viagens | J22: Helena Duarte
H23: =IF(19<=COUNTA($D$5:$D$16),INDEX($D$5:$D$16,19),IF(19<=COUNTA($D$5:$D$16)+COUNTA($F$5:$F$20),INDEX($F$5:$F$20,19-COUNTA($D$5:$D$16)),"")) -> Outras saídas
H24: =IF(20<=COUNTA($D$5:$D$16),INDEX($D$5:$D$16,20),IF(20<=COUNTA($D$5:$D$16)+COUNTA($F$5:$F$20),INDEX($F$5:$F$20,20-COUNTA($D$5:$D$16)),""))
H25: =IF(21<=COUNTA($D$5:$D$16),INDEX($D$5:$D$16,21),IF(21<=COUNTA($D$5:$D$16)+COUNTA($F$5:$F$20),INDEX($F$5:$F$20,21-COUNTA($D$5:$D$16)),""))
H26: =IF(22<=COUNTA($D$5:$D$16),INDEX($D$5:$D$16,22),IF(22<=COUNTA($D$5:$D$16)+COUNTA($F$5:$F$20),INDEX($F$5:$F$20,22-COUNTA($D$5:$D$16)),""))
H27: =IF(23<=COUNTA($D$5:$D$16),INDEX($D$5:$D$16,23),IF(23<=COUNTA($D$5:$D$16)+COUNTA($F$5:$F$20),INDEX($F$5:$F$20,23-COUNTA($D$5:$D$16)),""))
H28: =IF(24<=COUNTA($D$5:$D$16),INDEX($D$5:$D$16,24),IF(24<=COUNTA($D$5:$D$16)+COUNTA($F$5:$F$20),INDEX($F$5:$F$20,24-COUNTA($D$5:$D$16)),""))
H29: =IF(25<=COUNTA($D$5:$D$16),INDEX($D$5:$D$16,25),IF(25<=COUNTA($D$5:$D$16)+COUNTA($F$5:$F$20),INDEX($F$5:$F$20,25-COUNTA($D$5:$D$16)),""))
H30: =IF(26<=COUNTA($D$5:$D$16),INDEX($D$5:$D$16,26),IF(26<=COUNTA($D$5:$D$16)+COUNTA($F$5:$F$20),INDEX($F$5:$F$20,26-COUNTA($D$5:$D$16)),""))
H31: =IF(27<=COUNTA($D$5:$D$16),INDEX($D$5:$D$16,27),IF(27<=COUNTA($D$5:$D$16)+COUNTA($F$5:$F$20),INDEX($F$5:$F$20,27-COUNTA($D$5:$D$16)),""))
H32: =IF(28<=COUNTA($D$5:$D$16),INDEX($D$5:$D$16,28),IF(28<=COUNTA($D$5:$D$16)+COUNTA($F$5:$F$20),INDEX($F$5:$F$20,28-COUNTA($D$5:$D$16)),""))
A37: Preencha categorias e clientes de cima para baixo, sem pular linha: as listas suspensas de Lançamentos param na última linha preenchida.
A38: Saldo antes do 1º lançamento: o que havia na conta do escritório na data do primeiro lançamento (no exemplo, 01/01/2026, já contando honorários recebidos em 2025).
A39: Pró-labore dos sócios é uma categoria de saída como qualquer outra: o que sai do caixa do escritório para a pessoa física. A separação detalhada fica na planilha 11.
A40: Exemplo: cada entrada de honorários é uma parcela paga da planilha 14 (Parcelas), dos casos da 13 (Carteira). Pago? = Não são as parcelas já vencidas e as que vencem até o fim do mês (faturadas); o cronograma completo fica na 14. Lançamentos pagos vão até 11/09/2026 (a última sexta).

Sheet Lançamentos
A1: Lançamentos
A2: Uma linha por entrada ou saída. Preencha o amarelo; mês e ano são calculados. Pago? = Não fica em A receber / A pagar e só entra no caixa quando virar Sim.
A4: Data | B4: Tipo | C4: Categoria | D4: Cliente | E4: Caso (nº ou referência) | F4: Descrição | G4: Valor | H4: Forma | I4: Pago? | J4: Mês | K4: Ano
A5: 46027 | B5: Saída | C5: Aluguel e condomínio | F5: Aluguel e condomínio da sala | G5: 2800 | H5: Boleto | I5: Sim | J5: =IF(A5="","",MONTH(A5)) -> 1 | K5: =IF(A5="","",YEAR(A5)) -> 2026
A6: 46027 | B6: Saída | C6: Estagiária (bolsa) | F6: Bolsa da estagiária · Júlia Prado | G6: 1400 | H6: Cartão | I6: Sim | J6: =IF(A6="","",MONTH(A6)) -> 1 | K6: =IF(A6="","",YEAR(A6)) -> 2026
A7: 46029 | B7: Entrada | C7: Honorários fixos | D7: Transportadora Rota Sul | E7: 9225646-96.2025.8.26.0322 | F7: Honorários · parcela 1 | G7: 2000 | H7: Pix | I7: Sim | J7: =IF(A7="","",MONTH(A7)) -> 1 | K7: =IF(A7="","",YEAR(A7)) -> 2026
A8: 46030 | B8: Saída | C8: Sistemas e assinaturas | F8: Sistemas e assinaturas | G8: 450 | H8: Cartão | I8: Sim | J8: =IF(A8="","",MONTH(A8)) -> 1 | K8: =IF(A8="","",YEAR(A8)) -> 2026
A9: 46032 | B9: Saída | C9: Contador | F9: Honorários do contador | G9: 600 | H9: Boleto | I9: Sim | J9: =IF(A9="","",MONTH(A9)) -> 1 | K9: =IF(A9="","",YEAR(A9)) -> 2026
A10: 46034 | B10: Entrada | C10: Consultoria e pareceres | D10: Clínica Bem-Estar | E10: CONS-2025-05 | F10: Fatura de horas · 2 | G10: 2520 | H10: Boleto | I10: Sim | J10: =IF(A10="","",MONTH(A10)) -> 1 | K10: =IF(A10="","",YEAR(A10)) -> 2026
A11: 46034 | B11: Entrada | C11: Honorários fixos | D11: Roberto Almeida | E11: 5025425-10.2025.8.26.0629 | F11: Honorários · parcela 1 | G11: 3000 | H11: Pix | I11: Sim | J11: =IF(A11="","",MONTH(A11)) -> 1 | K11: =IF(A11="","",YEAR(A11)) -> 2026
A12: 46034 | B12: Entrada | C12: Honorários fixos | D12: Oficina Mecânica Central | E12: 8663770-96.2025.8.26.0481 | F12: Honorários · parcela 8 | G12: 800 | H12: Pix | I12: Sim | J12: =IF(A12="","",MONTH(A12)) -> 1 | K12: =IF(A12="","",YEAR(A12)) -> 2026
A13: 46034 | B13: Entrada | C13: Honorários por hora | D13: Agência Prisma | E13: 9362688-24.2025.8.26.0436 | F13: Fatura de horas · 1 | G13: 2880 | H13: Boleto | I13: Sim | J13: =IF(A13="","",MONTH(A13)) -> 1 | K13: =IF(A13="","",YEAR(A13)) -> 2026
A14: 46034 | B14: Saída | C14: Telefone e internet | F14: Telefone e internet | G14: 220 | H14: Boleto | I14: Sim | J14: =IF(A14="","",MONTH(A14)) -> 1 | K14: =IF(A14="","",YEAR(A14)) -> 2026
A15: 46036 | B15: Saída | C15: Custas e despesas de processo | D15: José Antônio Ribeiro | E15: 5900991-46.2026.8.26.0469 | F15: Custas iniciais | G15: 260 | H15: Boleto | I15: Sim | J15: =IF(A15="","",MONTH(A15)) -> 1 | K15: =IF(A15="","",YEAR(A15)) -> 2026
A16: 46037 | B16: Entrada | C16: Honorários fixos | D16: Fernanda Castro | E16: 5211189-81.2025.8.26.0412 | F16: Honorários · parcela 3 | G16: 1400 | H16: Pix | I16: Sim | J16: =IF(A16="","",MONTH(A16)) -> 1 | K16: =IF(A16="","",YEAR(A16)) -> 2026
A17: 46037 | B17: Saída | C17: Anuidades OAB e cursos | F17: Anuidades OAB e cursos | G17: 250 | H17: Cartão | I17: Sim | J17: =IF(A17="","",MONTH(A17)) -> 1 | K17: =IF(A17="","",YEAR(A17)) -> 2026
A18: 46040 | B18: Saída | C18: Material, correio e outros | F18: Material, correio e outros | G18: 380 | H18: Cartão | I18: Sim | J18: =IF(A18="","",MONTH(A18)) -> 1 | K18: =IF(A18="","",YEAR(A18)) -> 2026
A19: 46041 | B19: Entrada | C19: Honorários fixos | D19: Bistrô 42 | E19: 8056747-83.2026.8.26.0561 | F19: Honorários · entrada | G19: 3200 | H19: Pix | I19: Sim | J19: =IF(A19="","",MONTH(A19)) -> 1 | K19: =IF(A19="","",YEAR(A19)) -> 2026
A20: 46041 | B20: Entrada | C20: Honorários fixos | D20: Padaria do Sol Ltda | E20: 4766902-26.2025.8.26.0051 | F20: Honorários · parcela 2 | G20: 2250 | H20: Pix | I20: Sim | J20: =IF(A20="","",MONTH(A20)) -> 1 | K20: =IF(A20="","",YEAR(A20)) -> 2026
A21: 46042 | B21: Saída | C21: Impostos e taxas | F21: Guia de impostos do mês anterior (alíquota efetiva combinada com o contador) | G21: 1648 | H21: Boleto | I21: Sim | J21: =IF(A21="","",MONTH(A21)) -> 1 | K21: =IF(A21="","",YEAR(A21)) -> 2026
A22: 46042 | B22: Saída | C22: Marketing e site | F22: Marketing e site | G22: 400 | H22: Cartão | I22: Sim | J22: =IF(A22="","",MONTH(A22)) -> 1 | K22: =IF(A22="","",YEAR(A22)) -> 2026
A23: 46044 | B23: Entrada | C23: Honorários fixos | D23: Loja Verde Comércio | E23: 9088515-39.2025.8.26.0125 | F23: Honorários · parcela 4 | G23: 1000 | H23: Pix | I23: Sim | J23: =IF(A23="","",MONTH(A23)) -> 1 | K23: =IF(A23="","",YEAR(A23)) -> 2026
A24: 46045 | B24: Entrada | C24: Honorários fixos | D24: Oficina Mecânica Central | E24: 3363714-92.2025.8.26.0592 | F24: Honorários · parcela 2 | G24: 2000 | H24: Pix | I24: Sim | J24: =IF(A24="","",MONTH(A24)) -> 1 | K24: =IF(A24="","",YEAR(A24)) -> 2026
A25: 46050 | B25: Saída | C25: Pró-labore dos sócios | F25: Pró-labore · Marina Ferraz | G25: 6000 | H25: Transferência | I25: Sim | J25: =IF(A25="","",MONTH(A25)) -> 1 | K25: =IF(A25="","",YEAR(A25)) -> 2026
A26: 46050 | B26: Saída | C26: Pró-labore dos sócios | F26: Pró-labore · Rafael Lima | G26: 6000 | H26: Transferência | I26: Sim | J26: =IF(A26="","",MONTH(A26)) -> 1 | K26: =IF(A26="","",YEAR(A26)) -> 2026
A27: 46055 | B27: Entrada | C27: Honorários fixos | D27: Escola Aurora | E27: 6710873-21.2025.8.26.0571 | F27: Honorários · parcela 3 | G27: 1200 | H27: Pix | I27: Sim | J27: =IF(A27="","",MONTH(A27)) -> 2 | K27: =IF(A27="","",YEAR(A27)) -> 2026
A28: 46058 | B28: Saída | C28: Aluguel e condomínio | F28: Aluguel e condomínio da sala | G28: 2800 | H28: Boleto | I28: Sim | J28: =IF(A28="","",MONTH(A28)) -> 2 | K28: =IF(A28="","",YEAR(A28)) -> 2026
A29: 46058 | B29: Saída | C29: Estagiária (bolsa) | F29: Bolsa da estagiária · Júlia Prado | G29: 1400 | H29: Cartão | I29: Sim | J29: =IF(A29="","",MONTH(A29)) -> 2 | K29: =IF(A29="","",YEAR(A29)) -> 2026
A30: 46059 | B30: Entrada | C30: Honorários de êxito | D30: Marcos Vinícius Teles | E30: 8204296-70.2025.8.26.0146 | F30: Honorários de êxito (fim do caso) | G30: 6500 | H30: Pix | I30: Sim | J30: =IF(A30="","",MONTH(A30)) -> 2 | K30: =IF(A30="","",YEAR(A30)) -> 2026
A31: 46059 | B31: Entrada | C31: Honorários fixos | D31: Transportadora Rota Sul | E31: 9225646-96.2025.8.26.0322 | F31: Honorários · parcela 2 | G31: 2000 | H31: Pix | I31: Sim | J31: =IF(A31="","",MONTH(A31)) -> 2 | K31: =IF(A31="","",YEAR(A31)) -> 2026
A32: 46059 | B32: Saída | C32: Outras saídas | F32: Despesa pessoal · Marina Ferraz · plano de saúde particular (a acertar) | G32: 480 | H32: Boleto | I32: Sim | J32: =IF(A32="","",MONTH(A32)) -> 2 | K32: =IF(A32="","",YEAR(A32)) -> 2026
A33: 46061 | B33: Saída | C33: Sistemas e assinaturas | F33: Sistemas e assinaturas | G33: 450 | H33: Cartão | I33: Sim | J33: =IF(A33="","",MONTH(A33)) -> 2 | K33: =IF(A33="","",YEAR(A33)) -> 2026
A34: 46062 | B34: Entrada | C34: Honorários fixos | D34: Roberto Almeida | E34: 5025425-10.2025.8.26.0629 | F34: Honorários · parcela 2 | G34: 3000 | H34: Pix | I34: Sim | J34: =IF(A34="","",MONTH(A34)) -> 2 | K34: =IF(A34="","",YEAR(A34)) -> 2026
A35: 46062 | B35: Saída | C35: Custas e despesas de processo | D35: Construtora Horizonte | E35: 9778116-95.2025.8.26.0106 | F35: Honorários periciais adiantados | G35: 780 | H35: Boleto | I35: Sim | J35: =IF(A35="","",MONTH(A35)) -> 2 | K35: =IF(A35="","",YEAR(A35)) -> 2026
A36: 46063 | B36: Entrada | C36: Consultoria e pareceres | D36: Clínica Bem-Estar | E36: CONS-2025-05 | F36: Fatura de horas · 3 | G36: 1980 | H36: Boleto | I36: Sim | J36: =IF(A36="","",MONTH(A36)) -> 2 | K36: =IF(A36="","",YEAR(A36)) -> 2026
A37: 46063 | B37: Entrada | C37: Honorários por hora | D37: Agência Prisma | E37: 9362688-24.2025.8.26.0436 | F37: Fatura de horas · 2 | G37: 3240 | H37: Boleto | I37: Sim | J37: =IF(A37="","",MONTH(A37)) -> 2 | K37: =IF(A37="","",YEAR(A37)) -> 2026
A38: 46063 | B38: Saída | C38: Contador | F38: Honorários do contador | G38: 600 | H38: Boleto | I38: Sim | J38: =IF(A38="","",MONTH(A38)) -> 2 | K38: =IF(A38="","",YEAR(A38)) -> 2026
A39: 46065 | B39: Entrada | C39: Honorários fixos | D39: Oficina Mecânica Central | E39: 8663770-96.2025.8.26.0481 | F39: Honorários · parcela 9 | G39: 800 | H39: Pix | I39: Sim | J39: =IF(A39="","",MONTH(A39)) -> 2 | K39: =IF(A39="","",YEAR(A39)) -> 2026
A40: 46065 | B40: Saída | C40: Telefone e internet | F40: Telefone e internet | G40: 220 | H40: Boleto | I40: Sim | J40: =IF(A40="","",MONTH(A40)) -> 2 | K40: =IF(A40="","",YEAR(A40)) -> 2026
A41: 46066 | B41: Entrada | C41: Honorários fixos | D41: Fernanda Castro | E41: 5211189-81.2025.8.26.0412 | F41: Honorários · parcela 4 (vencida) | G41: 1400 | H41: Boleto | I41: Não | J41: =IF(A41="","",MONTH(A41)) -> 2 | K41: =IF(A41="","",YEAR(A41)) -> 2026
A42: 46068 | B42: Saída | C42: Anuidades OAB e cursos | F42: Anuidades OAB e cursos | G42: 250 | H42: Cartão | I42: Sim | J42: =IF(A42="","",MONTH(A42)) -> 2 | K42: =IF(A42="","",YEAR(A42)) -> 2026
A43: 46070 | B43: Entrada | C43: Honorários fixos | D43: Padaria do Sol Ltda | E43: 4766902-26.2025.8.26.0051 | F43: Honorários · parcela 3 | G43: 2250 | H43: Pix | I43: Sim | J43: =IF(A43="","",MONTH(A43)) -> 2 | K43: =IF(A43="","",YEAR(A43)) -> 2026
A44: 46070 | B44: Saída | C44: Deslocamento e viagens | F44: Combustível e estacionamento (audiências) | G44: 240 | H44: Cartão | I44: Sim | J44: =IF(A44="","",MONTH(A44)) -> 2 | K44: =IF(A44="","",YEAR(A44)) -> 2026
A45: 46071 | B45: Saída | C45: Material, correio e outros | F45: Material, correio e outros | G45: 380 | H45: Cartão | I45: Sim | J45: =IF(A45="","",MONTH(A45)) -> 2 | K45: =IF(A45="","",YEAR(A45)) -> 2026
A46: 46073 | B46: Entrada | C46: Honorários fixos | D46: Bistrô 42 | E46: 8056747-83.2026.8.26.0561 | F46: Honorários · parcela 1 | G46: 2100 | H46: Pix | I46: Sim | J46: =IF(A46="","",MONTH(A46)) -> 2 | K46: =IF(A46="","",YEAR(A46)) -> 2026
A47: 46073 | B47: Saída | C47: Impostos e taxas | F47: Guia de impostos do mês anterior (alíquota efetiva combinada com o contador) | G47: 1684 | H47: Boleto | I47: Sim | J47: =IF(A47="","",MONTH(A47)) -> 2 | K47: =IF(A47="","",YEAR(A47)) -> 2026
A48: 46073 | B48: Saída | C48: Marketing e site | F48: Marketing e site | G48: 400 | H48: Cartão | I48: Sim | J48: =IF(A48="","",MONTH(A48)) -> 2 | K48: =IF(A48="","",YEAR(A48)) -> 2026
A49: 46081 | B49: Saída | C49: Pró-labore dos sócios | F49: Pró-labore · Marina Ferraz | G49: 6000 | H49: Transferência | I49: Sim | J49: =IF(A49="","",MONTH(A49)) -> 2 | K49: =IF(A49="","",YEAR(A49)) -> 2026
A50: 46081 | B50: Saída | C50: Pró-labore dos sócios | F50: Pró-labore · Rafael Lima | G50: 6000 | H50: Transferência | I50: Sim | J50: =IF(A50="","",MONTH(A50)) -> 2 | K50: =IF(A50="","",YEAR(A50)) -> 2026
A51: 46083 | B51: Entrada | C51: Honorários fixos | D51: Oficina Mecânica Central | E51: 3363714-92.2025.8.26.0592 | F51: Honorários · parcela 3 | G51: 2000 | H51: Pix | I51: Sim | J51: =IF(A51="","",MONTH(A51)) -> 3 | K51: =IF(A51="","",YEAR(A51)) -> 2026
A52: 46084 | B52: Saída | C52: Custas e despesas de processo | D52: Transportadora Rota Sul | E52: 9225646-96.2025.8.26.0322 | F52: Diligência de oficial de justiça | G52: 130 | H52: Boleto | I52: Sim | J52: =IF(A52="","",MONTH(A52)) -> 3 | K52: =IF(A52="","",YEAR(A52)) -> 2026
A53: 46086 | B53: Saída | C53: Aluguel e condomínio | F53: Aluguel e condomínio da sala | G53: 2800 | H53: Boleto | I53: Sim | J53: =IF(A53="","",MONTH(A53)) -> 3 | K53: =IF(A53="","",YEAR(A53)) -> 2026
A54: 46086 | B54: Saída | C54: Estagiária (bolsa) | F54: Bolsa da estagiária · Júlia Prado | G54: 1400 | H54: Cartão | I54: Sim | J54: =IF(A54="","",MONTH(A54)) -> 3 | K54: =IF(A54="","",YEAR(A54)) -> 2026
A55: 46089 | B55: Saída | C55: Sistemas e assinaturas | F55: Sistemas e assinaturas | G55: 450 | H55: Cartão | I55: Sim | J55: =IF(A55="","",MONTH(A55)) -> 3 | K55: =IF(A55="","",YEAR(A55)) -> 2026
A56: 46090 | B56: Entrada | C56: Honorários fixos | D56: Roberto Almeida | E56: 5025425-10.2025.8.26.0629 | F56: Honorários · parcela 3 | G56: 3000 | H56: Pix | I56: Sim | J56: =IF(A56="","",MONTH(A56)) -> 3 | K56: =IF(A56="","",YEAR(A56)) -> 2026
A57: 46090 | B57: Entrada | C57: Reembolso de custas | D57: Construtora Horizonte | E57: 9778116-95.2025.8.26.0106 | F57: Reembolso das custas periciais | G57: 780 | H57: Transferência | I57: Sim | J57: =IF(A57="","",MONTH(A57)) -> 3 | K57: =IF(A57="","",YEAR(A57)) -> 2026
A58: 46091 | B58: Entrada | C58: Consultoria e pareceres | D58: Clínica Bem-Estar | E58: CONS-2025-05 | F58: Fatura de horas · 4 | G58: 2340 | H58: Boleto | I58: Sim | J58: =IF(A58="","",MONTH(A58)) -> 3 | K58: =IF(A58="","",YEAR(A58)) -> 2026
A59: 46091 | B59: Entrada | C59: Honorários por hora | D59: Agência Prisma | E59: 9362688-24.2025.8.26.0436 | F59: Fatura de horas · 3 | G59: 2520 | H59: Boleto | I59: Sim | J59: =IF(A59="","",MONTH(A59)) -> 3 | K59: =IF(A59="","",YEAR(A59)) -> 2026
A60: 46091 | B60: Saída | C60: Contador | F60: Honorários do contador | G60: 600 | H60: Boleto | I60: Sim | J60: =IF(A60="","",MONTH(A60)) -> 3 | K60: =IF(A60="","",YEAR(A60)) -> 2026
A61: 46092 | B61: Saída | C61: Outras saídas | F61: Despesa pessoal · Rafael Lima · combustível particular (a acertar) | G61: 300 | H61: Cartão | I61: Sim | J61: =IF(A61="","",MONTH(A61)) -> 3 | K61: =IF(A61="","",YEAR(A61)) -> 2026
A62: 46093 | B62: Entrada | C62: Honorários fixos | D62: Oficina Mecânica Central | E62: 8663770-96.2025.8.26.0481 | F62: Honorários · parcela 10 | G62: 800 | H62: Pix | I62: Sim | J62: =IF(A62="","",MONTH(A62)) -> 3 | K62: =IF(A62="","",YEAR(A62)) -> 2026
A63: 46093 | B63: Saída | C63: Telefone e internet | F63: Telefone e internet | G63: 220 | H63: Boleto | I63: Sim | J63: =IF(A63="","",MONTH(A63)) -> 3 | K63: =IF(A63="","",YEAR(A63)) -> 2026
A64: 46096 | B64: Saída | C64: Anuidades OAB e cursos | F64: Anuidades OAB e cursos | G64: 250 | H64: Cartão | I64: Sim | J64: =IF(A64="","",MONTH(A64)) -> 3 | K64: =IF(A64="","",YEAR(A64)) -> 2026
A65: 46097 | B65: Entrada | C65: Honorários fixos | D65: Carlos Eduardo Nunes | E65: 8045862-82.2026.8.26.0491 | F65: Honorários · entrada | G65: 1800 | H65: Pix | I65: Sim | J65: =IF(A65="","",MONTH(A65)) -> 3 | K65: =IF(A65="","",YEAR(A65)) -> 2026
A66: 46097 | B66: Saída | C66: Pró-labore dos sócios | F66: Retirada extra · Rafael Lima · adiantamento para viagem | G66: 1500 | H66: Transferência | I66: Sim | J66: =IF(A66="","",MONTH(A66)) -> 3 | K66: =IF(A66="","",YEAR(A66)) -> 2026
A67: 46098 | B67: Entrada | C67: Honorários fixos | D67: Padaria do Sol Ltda | E67: 4766902-26.2025.8.26.0051 | F67: Honorários · parcela 4 | G67: 2250 | H67: Pix | I67: Sim | J67: =IF(A67="","",MONTH(A67)) -> 3 | K67: =IF(A67="","",YEAR(A67)) -> 2026
A68: 46099 | B68: Entrada | C68: Honorários fixos | D68: Bistrô 42 | E68: 8056747-83.2026.8.26.0561 | F68: Honorários · parcela 2 (vencida) | G68: 2100 | H68: Boleto | I68: Não | J68: =IF(A68="","",MONTH(A68)) -> 3 | K68: =IF(A68="","",YEAR(A68)) -> 2026
A69: 46099 | B69: Saída | C69: Material, correio e outros | F69: Material, correio e outros | G69: 380 | H69: Cartão | I69: Sim | J69: =IF(A69="","",MONTH(A69)) -> 3 | K69: =IF(A69="","",YEAR(A69)) -> 2026
A70: 46101 | B70: Entrada | C70: Honorários de êxito | D70: Ana Beatriz Moreira | E70: 9420478-99.2025.8.26.0491 | F70: Honorários de êxito (fim do caso) | G70: 5500 | H70: Pix | I70: Sim | J70: =IF(A70="","",MONTH(A70)) -> 3 | K70: =IF(A70="","",YEAR(A70)) -> 2026
A71: 46101 | B71: Entrada | C71: Honorários fixos | D71: Transportadora Rota Sul | E71: 9225646-96.2025.8.26.0322 | F71: Honorários · parcela 3 | G71: 2000 | H71: Pix | I71: Sim | J71: =IF(A71="","",MONTH(A71)) -> 3 | K71: =IF(A71="","",YEAR(A71)) -> 2026
A72: 46101 | B72: Saída | C72: Impostos e taxas | F72: Guia de impostos do mês anterior (alíquota efetiva combinada com o contador) | G72: 1846 | H72: Boleto | I72: Sim | J72: =IF(A72="","",MONTH(A72)) -> 3 | K72: =IF(A72="","",YEAR(A72)) -> 2026
A73: 46101 | B73: Saída | C73: Marketing e site | F73: Marketing e site | G73: 400 | H73: Cartão | I73: Sim | J73: =IF(A73="","",MONTH(A73)) -> 3 | K73: =IF(A73="","",YEAR(A73)) -> 2026
A74: 46104 | B74: Entrada | C74: Honorários fixos | D74: Patrícia Gomes | E74: 6832730-55.2026.8.26.0386 | F74: Honorários · entrada | G74: 3600 | H74: Pix | I74: Sim | J74: =IF(A74="","",MONTH(A74)) -> 3 | K74: =IF(A74="","",YEAR(A74)) -> 2026
A75: 46104 | B75: Entrada | C75: Honorários fixos | D75: Oficina Mecânica Central | E75: 3363714-92.2025.8.26.0592 | F75: Honorários · parcela 4 | G75: 2000 | H75: Pix | I75: Sim | J75: =IF(A75="","",MONTH(A75)) -> 3 | K75: =IF(A75="","",YEAR(A75)) -> 2026
A76: 46109 | B76: Saída | C76: Pró-labore dos sócios | F76: Pró-labore · Marina Ferraz | G76: 6000 | H76: Transferência | I76: Sim | J76: =IF(A76="","",MONTH(A76)) -> 3 | K76: =IF(A76="","",YEAR(A76)) -> 2026
A77: 46109 | B77: Saída | C77: Pró-labore dos sócios | F77: Pró-labore · Rafael Lima | G77: 6000 | H77: Transferência | I77: Sim | J77: =IF(A77="","",MONTH(A77)) -> 3 | K77: =IF(A77="","",YEAR(A77)) -> 2026
A78: 46117 | B78: Saída | C78: Aluguel e condomínio | F78: Aluguel e condomínio da sala | G78: 2800 | H78: Boleto | I78: Sim | J78: =IF(A78="","",MONTH(A78)) -> 4 | K78: =IF(A78="","",YEAR(A78)) -> 2026
A79: 46117 | B79: Saída | C79: Estagiária (bolsa) | F79: Bolsa da estagiária · Júlia Prado | G79: 1400 | H79: Cartão | I79: Sim | J79: =IF(A79="","",MONTH(A79)) -> 4 | K79: =IF(A79="","",YEAR(A79)) -> 2026
A80: 46120 | B80: Entrada | C80: Honorários fixos | D80: Transportadora Rota Sul | E80: 9225646-96.2025.8.26.0322 | F80: Honorários · parcela 4 | G80: 2000 | H80: Pix | I80: Sim | J80: =IF(A80="","",MONTH(A80)) -> 4 | K80: =IF(A80="","",YEAR(A80)) -> 2026
A81: 46120 | B81: Saída | C81: Sistemas e assinaturas | F81: Sistemas e assinaturas | G81: 450 | H81: Cartão | I81: Sim | J81: =IF(A81="","",MONTH(A81)) -> 4 | K81: =IF(A81="","",YEAR(A81)) -> 2026
A82: 46122 | B82: Entrada | C82: Consultoria e pareceres | D82: Clínica Bem-Estar | E82: CONS-2025-05 | F82: Fatura de horas · 5 | G82: 1800 | H82: Boleto | I82: Sim | J82: =IF(A82="","",MONTH(A82)) -> 4 | K82: =IF(A82="","",YEAR(A82)) -> 2026
A83: 46122 | B83: Entrada | C83: Honorários por hora | D83: Agência Prisma | E83: 9362688-24.2025.8.26.0436 | F83: Fatura de horas · 4 | G83: 3060 | H83: Boleto | I83: Sim | J83: =IF(A83="","",MONTH(A83)) -> 4 | K83: =IF(A83="","",YEAR(A83)) -> 2026
A84: 46122 | B84: Saída | C84: Contador | F84: Honorários do contador | G84: 600 | H84: Boleto | I84: Sim | J84: =IF(A84="","",MONTH(A84)) -> 4 | K84: =IF(A84="","",YEAR(A84)) -> 2026
A85: 46122 | B85: Saída | C85: Pró-labore dos sócios | F85: Distribuição de lucro · 1º trimestre · Marina Ferraz | G85: 2655 | H85: Transferência | I85: Sim | J85: =IF(A85="","",MONTH(A85)) -> 4 | K85: =IF(A85="","",YEAR(A85)) -> 2026
A86: 46122 | B86: Saída | C86: Pró-labore dos sócios | F86: Distribuição de lucro · 1º trimestre · Rafael Lima | G86: 2656 | H86: Transferência | I86: Sim | J86: =IF(A86="","",MONTH(A86)) -> 4 | K86: =IF(A86="","",YEAR(A86)) -> 2026
A87: 46124 | B87: Saída | C87: Telefone e internet | F87: Telefone e internet | G87: 220 | H87: Boleto | I87: Sim | J87: =IF(A87="","",MONTH(A87)) -> 4 | K87: =IF(A87="","",YEAR(A87)) -> 2026
A88: 46125 | B88: Entrada | C88: Consultoria e pareceres | D88: Agência Prisma | E88: CONS-2026-07 | F88: Honorários · parcela 1 | G88: 3500 | H88: Pix | I88: Sim | J88: =IF(A88="","",MONTH(A88)) -> 4 | K88: =IF(A88="","",YEAR(A88)) -> 2026
A89: 46125 | B89: Entrada | C89: Honorários fixos | D89: Oficina Mecânica Central | E89: 8663770-96.2025.8.26.0481 | F89: Honorários · parcela 11 | G89: 800 | H89: Pix | I89: Sim | J89: =IF(A89="","",MONTH(A89)) -> 4 | K89: =IF(A89="","",YEAR(A89)) -> 2026
A90: 46126 | B90: Entrada | C90: Outras entradas | F90: Devolução de despesa pessoal · Marina Ferraz | G90: 480 | H90: Pix | I90: Sim | J90: =IF(A90="","",MONTH(A90)) -> 4 | K90: =IF(A90="","",YEAR(A90)) -> 2026
A91: 46127 | B91: Entrada | C91: Honorários fixos | D91: Carlos Eduardo Nunes | E91: 8045862-82.2026.8.26.0491 | F91: Honorários · parcela 1 | G91: 1800 | H91: Pix | I91: Sim | J91: =IF(A91="","",MONTH(A91)) -> 4 | K91: =IF(A91="","",YEAR(A91)) -> 2026
A92: 46127 | B92: Saída | C92: Anuidades OAB e cursos | F92: Anuidades OAB e cursos | G92: 250 | H92: Cartão | I92: Sim | J92: =IF(A92="","",MONTH(A92)) -> 4 | K92: =IF(A92="","",YEAR(A92)) -> 2026
A93: 46128 | B93: Saída | C93: Custas e despesas de processo | D93: Agência Prisma | E93: 9362688-24.2025.8.26.0436 | F93: Custas de recurso | G93: 540 | H93: Boleto | I93: Sim | J93: =IF(A93="","",MONTH(A93)) -> 4 | K93: =IF(A93="","",YEAR(A93)) -> 2026
A94: 46129 | B94: Entrada | C94: Honorários fixos | D94: Bistrô 42 | E94: 8056747-83.2026.8.26.0561 | F94: Honorários · parcela 3 (vencida) | G94: 2100 | H94: Boleto | I94: Não | J94: =IF(A94="","",MONTH(A94)) -> 4 | K94: =IF(A94="","",YEAR(A94)) -> 2026
A95: 46130 | B95: Saída | C95: Material, correio e outros | F95: Material, correio e outros | G95: 380 | H95: Cartão | I95: Sim | J95: =IF(A95="","",MONTH(A95)) -> 4 | K95: =IF(A95="","",YEAR(A95)) -> 2026
A96: 46132 | B96: Entrada | C96: Honorários fixos | D96: Oficina Mecânica Central | E96: 6184138-13.2026.8.26.0378 | F96: Honorários · entrada | G96: 3000 | H96: Pix | I96: Sim | J96: =IF(A96="","",MONTH(A96)) -> 4 | K96: =IF(A96="","",YEAR(A96)) -> 2026
A97: 46132 | B97: Saída | C97: Impostos e taxas | F97: Guia de impostos do mês anterior (alíquota efetiva combinada com o contador) | G97: 2287 | H97: Boleto | I97: Sim | J97: =IF(A97="","",MONTH(A97)) -> 4 | K97: =IF(A97="","",YEAR(A97)) -> 2026
A98: 46132 | B98: Saída | C98: Marketing e site | F98: Marketing e site | G98: 400 | H98: Cartão | I98: Sim | J98: =IF(A98="","",MONTH(A98)) -> 4 | K98: =IF(A98="","",YEAR(A98)) -> 2026
A99: 46134 | B99: Entrada | C99: Honorários fixos | D99: Patrícia Gomes | E99: 6832730-55.2026.8.26.0386 | F99: Honorários · parcela 1 | G99: 1800 | H99: Pix | I99: Sim | J99: =IF(A99="","",MONTH(A99)) -> 4 | K99: =IF(A99="","",YEAR(A99)) -> 2026
A100: 46135 | B100: Entrada | C100: Honorários fixos | D100: Oficina Mecânica Central | E100: 3363714-92.2025.8.26.0592 | F100: Honorários · parcela 5 | G100: 2000 | H100: Pix | I100: Sim | J100: =IF(A100="","",MONTH(A100)) -> 4 | K100: =IF(A100="","",YEAR(A100)) -> 2026
A101: 46140 | B101: Saída | C101: Pró-labore dos sócios | F101: Pró-labore · Marina Ferraz | G101: 6000 | H101: Transferência | I101: Sim | J101: =IF(A101="","",MONTH(A101)) -> 4 | K101: =IF(A101="","",YEAR(A101)) -> 2026
...
