Workbook

Sheet Como usar
A1: Horas por Caso e por Pessoa
A2: Kit de Gestão para Advogados · Seu Sócio Gestor · versão 1.0 (setembro de 2026)
A4: O que esta planilha faz | B4: Cada pessoa lança as horas por caso; ela transforma em custo pelo custo-hora, compara com as horas estimadas e o valor contratado, mostra a margem de cada caso com um semáforo ("consome mais do que paga") e a ocupação de cada pessoa no mês.
A5: Passo 1 | B5: Em Config, cadastre as pessoas com custo mensal e meta de horas faturáveis, os custos fixos do escritório (da planilha 05) e as atividades. O custo-hora é calculado.
A6: Passo 2 | B6: Em Casos, cole a lista da planilha 13 (Carteira) com valor contratado e horas estimadas. Se o caso já vinha de antes, anote as horas gastas até aqui. Trabalho interno (gestão, captação) entra como modalidade Interno.
A7: Passo 3 | B7: Em Lançamentos, uma linha por pessoa, por dia, por caso: data, pessoa, caso, atividade, horas e se é faturável. Dois minutos no fim do dia bastam.
A8: Passo 4 | B8: Em Painel, escolha o mês em Config. "Casos para olhar primeiro" mostra os que consomem mais do que pagam; "Por pessoa" mostra horas, % faturável e ocupação contra a meta; "Todos os casos" traz o semáforo completo.
A9: Rotina | B9: Cada pessoa lança no fim do dia ou na sexta (10 minutos). Dia 1 do mês: olhar a margem por caso antes de precificar a próxima proposta (planilha 06).
A10: Exemplo | B10: No exemplo o mês do painel é agosto de 2026, o último mês completo; setembro está lançado até o dia 14. Os lançamentos vão de julho a setembro; o que veio antes está em "horas gastas antes".
A11: Com a IA | B11: Copie "Casos para olhar primeiro" e use o prompt "Revisar a proposta de honorários" ou "Explicar o mês ao sócio" da biblioteca. Para justificar horas a um cliente, copie os lançamentos do caso e peça um resumo por atividade.
A12: Legenda | B12: Células amarelas: você preenche. Brancas: calculadas. Não é preciso mexer em nada fora do amarelo.
A13: Proteção | B13: Fórmulas protegidas sem senha. Para editar: Revisar > Desproteger planilha (Excel) ou Dados > Proteger intervalos (Google Sheets).
A14: Requisitos | B14: Excel 2019 ou mais novo, Microsoft 365 ou Google Sheets. No celular abre nos aplicativos; para preencher, use o computador.
A15: Google Sheets | B15: Faça upload no Google Drive e abra com o Google Sheets. Fórmulas, listas, cores e gráficos funcionam.
... A17: Suporte | B17: suporte@seusociogestor.com.br · resposta em até 5 dias úteis · reembolso em até 7 dias pelo mesmo canal.

Sheet Painel
A1: =Config!$B$4&" · Horas por caso · "&Config!$B$6&" de "&Config!$B$5
A2: Nada para digitar aqui. Escolha o mês em Config; tudo vem de Lançamentos e Casos.
A4: Horas no mês | C4: Faturáveis no mês | E4: Custo das horas no mês | G4: Ocupação da equipe | I4: Consomem mais do que pagam
A5: =SUMIFS(Lançamentos!$E$5:$E$604,Lançamentos!$I$5:$I$604,Config!$B$7,Lançamentos!$J$5:$J$604,Config!$B$5) | C5: =IFERROR(SUMIFS(Lançamentos!$E$5:$E$604,Lançamentos!$I$5:$I$604,Config!$B$7,Lançamentos!$J$5:$J$604,Config!$B$5,Lançamentos!$F$5:$F$604,"Sim")/A5,0) | E5: =SUMIFS(Lançamentos!$H$5:$H$604,Lançamentos!$I$5:$I$604,Config!$B$7,Lançamentos!$J$5:$J$604,Config!$B$5) | G5: =IFERROR(SUMIFS(Lançamentos!$E$5:$E$604,Lançamentos!$I$5:$I$604,Config!$B$7,Lançamentos!$J$5:$J$604,Config!$B$5,Lançamentos!$F$5:$F$604,"Sim")/SUMIFS(Config!$C$12:$C$21,Config!$A$12:$A$21,"<>"),0) | I5: =COUNTIF($L$32:$L$91,"Consome mais do que paga")
A7: Ocupação = horas faturáveis lançadas no mês ÷ soma das metas de horas faturáveis (Config). Custo das horas = horas × custo-hora de quem lançou.
A9: Casos para olhar primeiro (todo o período)
A10: Casos em que o custo das horas já chegou perto do valor contratado, passou dele ou estourou as horas estimadas. Ordem: custo ÷ contratado, do maior para o menor.
A11: # | B11: Caso | C11: Cliente | D11: Responsável | E11: Horas estimadas | F11: Horas gastas | G11: Custo das horas | H11: Valor contratado | I11: Margem (R$) | J11: Situação
A12: 1 | B12: =IFERROR(IF(LARGE($M$32:$M$91,1)>0,INDEX($A$32:$A$91,MATCH(LARGE($M$32:$M$91,1),$M$32:$M$91,0)),""),"") | C12: =IFERROR(IF(LARGE($M$32:$M$91,1)>0,INDEX($B$32:$B$91,MATCH(LARGE($M$32:$M$91,1),$M$32:$M$91,0)),""),"") | D12: =IFERROR(IF(LARGE($M$32:$M$91,1)>0,INDEX($C$32:$C$91,MATCH(LARGE($M$32:$M$91,1),$M$32:$M$91,0)),""),"") | E12: =IFERROR(IF(LARGE($M$32:$M$91,1)>0,INDEX($E$32:$E$91,MATCH(LARGE($M$32:$M$91,1),$M$32:$M$91,0)),""),"") | F12: =IFERROR(IF(LARGE($M$32:$M$91,1)>0,INDEX($F$32:$F$91,MATCH(LARGE($M$32:$M$91,1),$M$32:$M$91,0)),""),"") | G12: =IFERROR(IF(LARGE($M$32:$M$91,1)>0,INDEX($H$32:$H$91,MATCH(LARGE($M$32:$M$91,1),$M$32:$M$91,0)),""),"") | H12: =IFERROR(IF(LARGE($M$32:$M$91,1)>0,INDEX($I$32:$I$91,MATCH(LARGE($M$32:$M$91,1),$M$32:$M$91,0)),""),"") | I12: =IFERROR(IF(LARGE($M$32:$M$91,1)>0,INDEX($J$32:$J$91,MATCH(LARGE($M$32:$M$91,1),$M$32:$M$91,0)),""),"") | J12: =IFERROR(IF(LARGE($M$32:$M$91,1)>0,INDEX($L$32:$L$91,MATCH(LARGE($M$32:$M$91,1),$M$32:$M$91,0)),""),"")
A13: 2 | B13: =IFERROR(IF(LARGE($M$32:$M$91,2)>0,INDEX($A$32:$A$91,MATCH(LARGE($M$32:$M$91,2),$M$32:$M$91,0)),""),"") | C13: =IFERROR(IF(LARGE($M$32:$M$91,2)>0,INDEX($B$32:$B$91,MATCH(LARGE($M$32:$M$91,2),$M$32:$M$91,0)),""),"") | D13: =IFERROR(IF(LARGE($M$32:$M$91,2)>0,INDEX($C$32:$C$91,MATCH(LARGE($M$32:$M$91,2),$M$32:$M$91,0)),""),"") | E13: =IFERROR(IF(LARGE($M$32:$M$91,2)>0,INDEX($E$32:$E$91,MATCH(LARGE($M$32:$M$91,2),$M$32:$M$91,0)),""),"") | F13: =IFERROR(IF(LARGE($M$32:$M$91,2)>0,INDEX($F$32:$F$91,MATCH(LARGE($M$32:$M$91,2),$M$32:$M$91,0)),""),"") | G13: =IFERROR(IF(LARGE($M$32:$M$91,2)>0,INDEX($H$32:$H$91,MATCH(LARGE($M$32:$M$91,2),$M$32:$M$91,0)),""),"") | H13: =IFERROR(IF(LARGE($M$32:$M$91,2)>0,INDEX($I$32:$I$91,MATCH(LARGE($M$32:$M$91,2),$M$32:$M$91,0)),""),"") | I13: =IFERROR(IF(LARGE($M$32:$M$91,2)>0,INDEX($J$32:$J$91,MATCH(LARGE($M$32:$M$91,2),$M$32:$M$91,0)),""),"") | J13: =IFERROR(IF(LARGE($M$32:$M$91,2)>0,INDEX($L$32:$L$91,MATCH(LARGE($M$32:$M$91,2),$M$32:$M$91,0)),""),"")
A14: 3 | B14: =IFERROR(IF(LARGE($M$32:$M$91,3)>0,INDEX($A$32:$A$91,MATCH(LARGE($M$32:$M$91,3),$M$32:$M$91,0)),""),"") | C14: =IFERROR(IF(LARGE($M$32:$M$91,3)>0,INDEX($B$32:$B$91,MATCH(LARGE($M$32:$M$91,3),$M$32:$M$91,0)),""),"") | D14: =IFERROR(IF(LARGE($M$32:$M$91,3)>0,INDEX($C$32:$C$91,MATCH(LARGE($M$32:$M$91,3),$M$32:$M$91,0)),""),"") | E14: =IFERROR(IF(LARGE($M$32:$M$91,3)>0,INDEX($E$32:$E$91,MATCH(LARGE($M$32:$M$91,3),$M$32:$M$91,0)),""),"") | F14: =IFERROR(IF(LARGE($M$32:$M$91,3)>0,INDEX($F$32:$F$91,MATCH(LARGE($M$32:$M$91,3),$M$32:$M$91,0)),""),"") | G14: =IFERROR(IF(LARGE($M$32:$M$91,3)>0,INDEX($H$32:$H$91,MATCH(LARGE($M$32:$M$91,3),$M$32:$M$91,0)),""),"") | H14: =IFERROR(IF(LARGE($M$32:$M$91,3)>0,INDEX($I$32:$I$91,MATCH(LARGE($M$32:$M$91,3),$M$32:$M$91,0)),""),"") | I14: =IFERROR(IF(LARGE($M$32:$M$91,3)>0,INDEX($J$32:$J$91,MATCH(LARGE($M$32:$M$91,3),$M$32:$M$91,0)),""),"") | J14: =IFERROR(IF(LARGE($M$32:$M$91,3)>0,INDEX($L$32:$L$91,MATCH(LARGE($M$32:$M$91,3),$M$32:$M$91,0)),""),"")
A15: 4 | B15: =IFERROR(IF(LARGE($M$32:$M$91,4)>0,INDEX($A$32:$A$91,MATCH(LARGE($M$32:$M$91,4),$M$32:$M$91,0)),""),"") | C15: =IFERROR(IF(LARGE($M$32:$M$91,4)>0,INDEX($B$32:$B$91,MATCH(LARGE($M$32:$M$91,4),$M$32:$M$91,0)),""),"") | D15: =IFERROR(IF(LARGE($M$32:$M$91,4)>0,INDEX($C$32:$C$91,MATCH(LARGE($M$32:$M$91,4),$M$32:$M$91,0)),""),"") | E15: =IFERROR(IF(LARGE($M$32:$M$91,4)>0,INDEX($E$32:$E$91,MATCH(LARGE($M$32:$M$91,4),$M$32:$M$91,0)),""),"") | F15: =IFERROR(IF(LARGE($M$32:$M$91,4)>0,INDEX($F$32:$F$91,MATCH(LARGE($M$32:$M$91,4),$M$32:$M$91,0)),""),"") | G15: =IFERROR(IF(LARGE($M$32:$M$91,4)>0,INDEX($H$32:$H$91,MATCH(LARGE($M$32:$M$91,4),$M$32:$M$91,0)),""),"") | H15: =IFERROR(IF(LARGE($M$32:$M$91,4)>0,INDEX($I$32:$I$91,MATCH(LARGE($M$32:$M$91,4),$M$32:$M$91,0)),""),"") | I15: =IFERROR(IF(LARGE($M$32:$M$91,4)>0,INDEX($J$32:$J$91,MATCH(LARGE($M$32:$M$91,4),$M$32:$M$91,0)),""),"") | J15: =IFERROR(IF(LARGE($M$32:$M$91,4)>0,INDEX($L$32:$L$91,MATCH(LARGE($M$32:$M$91,4),$M$32:$M$91,0)),""),"")
A16: 5 | B16: =IFERROR(IF(LARGE($M$32:$M$91,5)>0,INDEX($A$32:$A$91,MATCH(LARGE($M$32:$M$91,5),$M$32:$M$91,0)),""),"") | C16: =IFERROR(IF(LARGE($M$32:$M$91,5)>0,INDEX($B$32:$B$91,MATCH(LARGE($M$32:$M$91,5),$M$32:$M$91,0)),""),"") | D16: =IFERROR(IF(LARGE($M$32:$M$91,5)>0,INDEX($C$32:$C$91,MATCH(LARGE($M$32:$M$91,5),$M$32:$M$91,0)),""),"") | E16: =IFERROR(IF(LARGE($M$32:$M$91,5)>0,INDEX($E$32:$E$91,MATCH(LARGE($M$32:$M$91,5),$M$32:$M$91,0)),""),"") | F16: =IFERROR(IF(LARGE($M$32:$M$91,5)>0,INDEX($F$32:$F$91,MATCH(LARGE($M$32:$M$91,5),$M$32:$M$91,0)),""),"") | G16: =IFERROR(IF(LARGE($M$32:$M$91,5)>0,INDEX($H$32:$H$91,MATCH(LARGE($M$32:$M$91,5),$M$32:$M$91,0)),""),"") | H16: =IFERROR(IF(LARGE($M$32:$M$91,5)>0,INDEX($I$32:$I$91,MATCH(LARGE($M$32:$M$91,5),$M$32:$M$91,0)),""),"") | I16: =IFERROR(IF(LARGE($M$32:$M$91,5)>0,INDEX($J$32:$J$91,MATCH(LARGE($M$32:$M$91,5),$M$32:$M$91,0)),""),"") | J16: =IFERROR(IF(LARGE($M$32:$M$91,5)>0,INDEX($L$32:$L$91,MATCH(LARGE($M$32:$M$91,5),$M$32:$M$91,0)),""),"")
A17: 6 | B17: =IFERROR(IF(LARGE($M$32:$M$91,6)>0,INDEX($A$32:$A$91,MATCH(LARGE($M$32:$M$91,6),$M$32:$M$91,0)),""),"") | C17: =IFERROR(IF(LARGE($M$32:$M$91,6)>0,INDEX($B$32:$B$91,MATCH(LARGE($M$32:$M$91,6),$M$32:$M$91,0)),""),"") | D17: =IFERROR(IF(LARGE($M$32:$M$91,6)>0,INDEX($C$32:$C$91,MATCH(LARGE($M$32:$M$91,6),$M$32:$M$91,0)),""),"") | E17: =IFERROR(IF(LARGE($M$32:$M$91,6)>0,INDEX($E$32:$E$91,MATCH(LARGE($M$32:$M$91,6),$M$32:$M$91,0)),""),"") | F17: =IFERROR(IF(LARGE($M$32:$M$91,6)>0,INDEX($F$32:$F$91,MATCH(LARGE($M$32:$M$91,6),$M$32:$M$91,0)),""),"") | G17: =IFERROR(IF(LARGE($M$32:$M$91,6)>0,INDEX($H$32:$H$91,MATCH(LARGE($M$32:$M$91,6),$M$32:$M$91,0)),""),"") | H17: =IFERROR(IF(LARGE($M$32:$M$91,6)>0,INDEX($I$32:$I$91,MATCH(LARGE($M$32:$M$91,6),$M$32:$M$91,0)),""),"") | I17: =IFERROR(IF(LARGE($M$32:$M$91,6)>0,INDEX($J$32:$J$91,MATCH(LARGE($M$32:$M$91,6),$M$32:$M$91,0)),""),"") | J17: =IFERROR(IF(LARGE($M$32:$M$91,6)>0,INDEX($L$32:$L$91,MATCH(LARGE($M$32:$M$91,6),$M$32:$M$91,0)),""),"")
A18: 7 | B18: =IFERROR(IF(LARGE($M$32:$M$91,7)>0,INDEX($A$32:$A$91,MATCH(LARGE($M$32:$M$91,7),$M$32:$M$91,0)),""),"") | C18: =IFERROR(IF(LARGE($M$32:$M$91,7)>0,INDEX($B$32:$B$91,MATCH(LARGE($M$32:$M$91,7),$M$32:$M$91,0)),""),"") | D18: =IFERROR(IF(LARGE($M$32:$M$91,7)>0,INDEX($C$32:$C$91,MATCH(LARGE($M$32:$M$91,7),$M$32:$M$91,0)),""),"") | E18: =IFERROR(IF(LARGE($M$32:$M$91,7)>0,INDEX($E$32:$E$91,MATCH(LARGE($M$32:$M$91,7),$M$32:$M$91,0)),""),"") | F18: =IFERROR(IF(LARGE($M$32:$M$91,7)>0,INDEX($F$32:$F$91,MATCH(LARGE($M$32:$M$91,7),$M$32:$M$91,0)),""),"") | G18: =IFERROR(IF(LARGE($M$32:$M$91,7)>0,INDEX($H$32:$H$91,MATCH(LARGE($M$32:$M$91,7),$M$32:$M$91,0)),""),"") | H18: =IFERROR(IF(LARGE($M$32:$M$91,7)>0,INDEX($I$32:$I$91,MATCH(LARGE($M$32:$M$91,7),$M$32:$M$91,0)),""),"") | I18: =IFERROR(IF(LARGE($M$32:$M$91,7)>0,INDEX($J$32:$J$91,MATCH(LARGE($M$32:$M$91,7),$M$32:$M$91,0)),""),"") | J18: =IFERROR(IF(LARGE($M$32:$M$91,7)>0,INDEX($L$32:$L$91,MATCH(LARGE($M$32:$M$91,7),$M$32:$M$91,0)),""),"")
A19: 8 | B19: =IFERROR(IF(LARGE($M$32:$M$91,8)>0,INDEX($A$32:$A$91,MATCH(LARGE($M$32:$M$91,8),$M$32:$M$91,0)),""),"") | C19: =IFERROR(IF(LARGE($M$32:$M$91,8)>0,INDEX($B$32:$B$91,MATCH(LARGE($M$32:$M$91,8),$M$32:$M$91,0)),""),"") | D19: =IFERROR(IF(LARGE($M$32:$M$91,8)>0,INDEX($C$32:$C$91,MATCH(LARGE($M$32:$M$91,8),$M$32:$M$91,0)),""),"") | E19: =IFERROR(IF(LARGE($M$32:$M$91,8)>0,INDEX($E$32:$E$91,MATCH(LARGE($M$32:$M$91,8),$M$32:$M$91,0)),""),"") | F19: =IFERROR(IF(LARGE($M$32:$M$91,8)>0,INDEX($F$32:$F$91,MATCH(LARGE($M$32:$M$91,8),$M$32:$M$91,0)),""),"") | G19: =IFERROR(IF(LARGE($M$32:$M$91,8)>0,INDEX($H$32:$H$91,MATCH(LARGE($M$32:$M$91,8),$M$32:$M$91,0)),""),"") | H19: =IFERROR(IF(LARGE($M$32:$M$91,8)>0,INDEX($I$32:$I$91,MATCH(LARGE($M$32:$M$91,8),$M$32:$M$91,0)),""),"") | I19: =IFERROR(IF(LARGE($M$32:$M$91,8)>0,INDEX($J$32:$J$91,MATCH(LARGE($M$32:$M$91,8),$M$32:$M$91,0)),""),"") | J19: =IFERROR(IF(LARGE($M$32:$M$91,8)>0,INDEX($L$32:$L$91,MATCH(LARGE($M$32:$M$91,8),$M$32:$M$91,0)),""),"")
A21: ="Por pessoa em "&Config!$B$6
A22: Pessoa | B22: Horas lançadas | C22: Faturáveis | D22: % faturável | E22: Meta faturável/mês | F22: % da meta | G22: Custo no mês (R$) | H22: Custo-hora (R$)
A23: =IF(Config!$A$12="","",Config!$A$12) | B23: =IF(Config!$A$12="","",SUMIFS(Lançamentos!$E$5:$E$604,Lançamentos!$B$5:$B$604,Config!$A$12,Lançamentos!$I$5:$I$604,Config!$B$7,Lançamentos!$J$5:$J$604,Config!$B$5)) | C23: =IF(Config!$A$12="","",SUMIFS(Lançamentos!$E$5:$E$604,Lançamentos!$B$5:$B$604,Config!$A$12,Lançamentos!$I$5:$I$604,Config!$B$7,Lançamentos!$J$5:$J$604,Config!$B$5,Lançamentos!$F$5:$F$604,"Sim")) | D23: =IF(OR(Config!$A$12="",B23=0),"",C23/B23) | E23: =IF(Config!$A$12="","",Config!$C$12) | F23: =IF(OR(Config!$A$12="",E23=0,E23=""),"",C23/E23) | G23: =IF(Config!$A$12="","",SUMIFS(Lançamentos!$H$5:$H$604,Lançamentos!$B$5:$B$604,Config!$A$12,Lançamentos!$I$5:$I$604,Config!$B$7,Lançamentos!$J$5:$J$604,Config!$B$5)) | H23: =IF(Config!$A$12="","",Config!$D$12)
A24: =IF(Config!$A$13="","",Config!$A$13) | B24: =IF(Config!$A$13="","",SUMIFS(Lançamentos!$E$5:$E$604,Lançamentos!$B$5:$B$604,Config!$A$13,Lançamentos!$I$5:$I$604,Config!$B$7,Lançamentos!$J$5:$J$604,Config!$B$5)) | C24: =IF(Config!$A$13="","",SUMIFS(Lançamentos!$E$5:$E$604,Lançamentos!$B$5:$B$604,Config!$A$13,Lançamentos!$I$5:$I$604,Config!$B$7,Lançamentos!$J$5:$J$604,Config!$B$5,Lançamentos!$F$5:$F$604,"Sim")) | D24: =IF(OR(Config!$A$13="",B24=0),"",C24/B24) | E24: =IF(Config!$A$13="","",Config!$C$13) | F24: =IF(OR(Config!$A$13="",E24=0,E24=""),"",C24/E24) | G24: =IF(Config!$A$13="","",SUMIFS(Lançamentos!$H$5:$H$604,Lançamentos!$B$5:$B$604,Config!$A$13,Lançamentos!$I$5:$I$604,Config!$B$7,Lançamentos!$J$5:$J$604,Config!$B$5)) | H24: =IF(Config!$A$13="","",Config!$D$13)
A25: =IF(Config!$A$14="","",Config!$A$14) | B25: =IF(Config!$A$14="","",SUMIFS(Lançamentos!$E$5:$E$604,Lançamentos!$B$5:$B$604,Config!$A$14,Lançamentos!$I$5:$I$604,Config!$B$7,Lançamentos!$J$5:$J$604,Config!$B$5)) | C25: =IF(Config!$A$14="","",SUMIFS(Lançamentos!$E$5:$E$604,Lançamentos!$B$5:$B$604,Config!$A$14,Lançamentos!$I$5:$I$604,Config!$B$7,Lançamentos!$J$5:$J$604,Config!$B$5,Lançamentos!$F$5:$F$604,"Sim")) | D25: =IF(OR(Config!$A$14="",B25=0),"",C25/B25) | E25: =IF(Config!$A$14="","",Config!$C$14) | F25: =IF(OR(Config!$A$14="",E25=0,E25=""),"",C25/E25) | G25: =IF(Config!$A$14="","",SUMIFS(Lançamentos!$H$5:$H$604,Lançamentos!$B$5:$B$604,Config!$A$14,Lançamentos!$I$5:$I$604,Config!$B$7,Lançamentos!$J$5:$J$604,Config!$B$5)) | H25: =IF(Config!$A$14="","",Config!$D$14)
A26: =IF(Config!$A$15="","",Config!$A$15) | B26: =IF(Config!$A$15="","",SUMIFS(Lançamentos!$E$5:$E$604,Lançamentos!$B$5:$B$604,Config!$A$15,Lançamentos!$I$5:$I$604,Config!$B$7,Lançamentos!$J$5:$J$604,Config!$B$5)) | C26: =IF(Config!$A$15="","",SUMIFS(Lançamentos!$E$5:$E$604,Lançamentos!$B$5:$B$604,Config!$A$15,Lançamentos!$I$5:$I$604,Config!$B$7,Lançamentos!$J$5:$J$604,Config!$B$5,Lançamentos!$F$5:$F$604,"Sim")) | D26: =IF(OR(Config!$A$15="",B26=0),"",C26/B26) | E26: =IF(Config!$A$15="","",Config!$C$15) | F26: =IF(OR(Config!$A$15="",E26=0,E26=""),"",C26/E26) | G26: =IF(Config!$A$15="","",SUMIFS(Lançamentos!$H$5:$H$604,Lançamentos!$B$5:$B$604,Config!$A$15,Lançamentos!$I$5:$I$604,Config!$B$7,Lançamentos!$J$5:$J$604,Config!$B$5)) | H26: =IF(Config!$A$15="","",Config!$D$15)
A27: =IF(Config!$A$16="","",Config!$A$16) | B27: =IF(Config!$A$16="","",SUMIFS(Lançamentos!$E$5:$E$604,Lançamentos!$B$5:$B$604,Config!$A$16,Lançamentos!$I$5:$I$604,Config!$B$7,Lançamentos!$J$5:$J$604,Config!$B$5)) | C27: =IF(Config!$A$16="","",SUMIFS(Lançamentos!$E$5:$E$604,Lançamentos!$B$5:$B$604,Config!$A$16,Lançamentos!$I$5:$I$604,Config!$B$7,Lançamentos!$J$5:$J$604,Config!$B$5,Lançamentos!$F$5:$F$604,"Sim")) | D27: =IF(OR(Config!$A$16="",B27=0),"",C27/B27) | E27: =IF(Config!$A$16="","",Config!$C$16) | F27: =IF(OR(Config!$A$16="",E27=0,E27=""),"",C27/E27) | G27: =IF(Config!$A$16="","",SUMIFS(Lançamentos!$H$5:$H$604,Lançamentos!$B$5:$B$604,Config!$A$16,Lançamentos!$I$5:$I$604,Config!$B$7,Lançamentos!$J$5:$J$604,Config!$B$5)) | H27: =IF(Config!$A$16="","",Config!$D$16)
A28: =IF(Config!$A$17="","",Config!$A$17) | B28: =IF(Config!$A$17="","",SUMIFS(Lançamentos!$E$5:$E$604,Lançamentos!$B$5:$B$604,Config!$A$17,Lançamentos!$I$5:$I$604,Config!$B$7,Lançamentos!$J$5:$J$604,Config!$B$5)) | C28: =IF(Config!$A$17="","",SUMIFS(Lançamentos!$E$5:$E$604,Lançamentos!$B$5:$B$604,Config!$A$17,Lançamentos!$I$5:$I$604,Config!$B$7,Lançamentos!$J$5:$J$604,Config!$B$5,Lançamentos!$F$5:$F$604,"Sim")) | D28: =IF(OR(Config!$A$17="",B28=0),"",C28/B28) | E28: =IF(Config!$A$17="","",Config!$C$17) | F28: =IF(OR(Config!$A$17="",E28=0,E28=""),"",C28/E28) | G28: =IF(Config!$A$17="","",SUMIFS(Lançamentos!$H$5:$H$604,Lançamentos!$B$5:$B$604,Config!$A$17,Lançamentos!$I$5:$I$604,Config!$B$7,Lançamentos!$J$5:$J$604,Config!$B$5)) | H28: =IF(Config!$A$17="","",Config!$D$17)
A29: =IF(Config!$A$18="","",Config!$A$18) | B29: =IF(Config!$A$18="","",SUMIFS(Lançamentos!$E$5:$E$604,Lançamentos!$B$5:$B$604,Config!$A$18,Lançamentos!$I$5:$I$604,Config!$B$7,Lançamentos!$J$5:$J$604,Config!$B$5)) | C29: =IF(Config!$A$18="","",SUMIFS(Lançamentos!$E$5:$E$604,Lançamentos!$B$5:$B$604,Config!$A$18,Lançamentos!$I$5:$I$604,Config!$B$7,Lançamentos!$J$5:$J$604,Config!$B$5,Lançamentos!$F$5:$F$604,"Sim")) | D29: =IF(OR(Config!$A$18="",B29=0),"",C29/B29) | E29: =IF(Config!$A$18="","",Config!$C$18) | F29: =IF(OR(Config!$A$18="",E29=0,E29=""),"",C29/E29) | G29: =IF(Config!$A$18="","",SUMIFS(Lançamentos!$H$5:$H$604,Lançamentos!$B$5:$B$604,Config!$A$18,Lançamentos!$I$5:$I$604,Config!$B$7,Lançamentos!$J$5:$J$604,Config!$B$5)) | H29: =IF(Config!$A$18="","",Config!$D$18)
A30: Todos os casos (todo o período) | B30: =IF(Config!$A$19="","",SUMIFS(Lançamentos!$E$5:$E$604,Lançamentos!$B$5:$B$604,Config!$A$19,Lançamentos!$I$5:$I$604,Config!$B$7,Lançamentos!$J$5:$J$604,Config!$B$5)) | C30: =IF(Config!$A$19="","",SUMIFS(Lançamentos!$E$5:$E$604,Lançamentos!$B$5:$B$604,Config!$A$19,Lançamentos!$I$5:$I$604,Config!$B$7,Lançamentos!$J$5:$J$604,Config!$B$5,Lançamentos!$F$5:$F$604,"Sim")) | D30: =IF(OR(Config!$A$19="",B30=0),"",C30/B30) | E30: Mostra os 60 primeiros casos da aba Casos; horas gastas = horas de antes + lançadas aqui. | F30: =IF(OR(Config!$A$19="",E30=0,E30=""),"",C30/E30) | G30: =IF(Config!$A$19="","",SUMIFS(Lançamentos!$H$5:$H$604,Lançamentos!$B$5:$B$604,Config!$A$19,Lançamentos!$I$5:$I$604,Config!$B$7,Lançamentos!$J$5:$J$604,Config!$B$5)) | H30: =IF(Config!$A$19="","",Config!$D$19)
A31: Caso | B31: Cliente | C31: Responsável | D31: Modalidade | E31: Horas estimadas | F31: Horas gastas | G31: % das estimadas | H31: Custo das horas (R$) | I31: Valor contratado (R$) | J31: Margem (R$) | K31: Margem (%) | L31: Situação
A32: =IF(Casos!$A$5="","",Casos!$A$5) | B32: =IF(Casos!$A$5="","",Casos!$B$5) | C32: =IF(Casos!$A$5="","",Casos!$D$5) | D32: =IF(Casos!$A$5="","",Casos!$E$5) | E32: =IF(Casos!$A$5="","",N(Casos!$G$5)) | F32: =IF(Casos!$A$5="","",N(Casos!$H$5)+SUMIFS(Lançamentos!$E$5:$E$604,Lançamentos!$C$5:$C$604,Casos!$A$5)) | G32: =IF(OR(Casos!$A$5="",E32=0),"",F32/E32) | H32: =IF(Casos!$A$5="","",N(Casos!$H$5)*Config!$B$23+SUMIFS(Lançamentos!$H$5:$H$604,Lançamentos!$C$5:$C$604,Casos!$A$5)) | I32: =IF(Casos!$A$5="","",N(Casos!$F$5)) | J32: =IF(OR(Casos!$A$5="",D32="Interno"),"",I32-H32) | K32: =IF(OR(Casos!$A$5="",D32="Interno",I32=0),"",J32/I32) | L32: =IF(Casos!$A$5="","",IF(D32="Interno","Interno",IF(F32=0,"Sem horas",IF(H32>I32,"Consome mais do que paga",IF(AND(G32<>"",G32>1),"Estourou as horas",IF(AND(K32<>"",K32<0.2),"Margem baixa",IF(AND(G32<>"",G32>0.85),"Perto do limite","Saudável"))))))) | M32: =IF(OR(L32="Consome mais do que paga",L32="Margem baixa",L32="Estourou as horas"),IFERROR(H32/I32,9)+ROW()/1000000,0)
A33: =IF(Casos!$A$6="","",Casos!$A$6) | B33: =IF(Casos!$A$6="","",Casos!$B$6) | C33: =IF(Casos!$A$6="","",Casos!$D$6) | D33: =IF(Casos!$A$6="","",Casos!$E$6) | E33: =IF(Casos!$A$6="","",N(Casos!$G$6)) | F33: =IF(Casos!$A$6="","",N(Casos!$H$6)+SUMIFS(Lançamentos!$E$5:$E$604,Lançamentos!$C$5:$C$604,Casos!$A$6)) | G33: =IF(OR(Casos!$A$6="",E33=0),"",F33/E33) | H33: =IF(Casos!$A$6="","",N(Casos!$H$6)*Config!$B$23+SUMIFS(Lançamentos!$H$5:$H$604,Lançamentos!$C$5:$C$604,Casos!$A$6)) | I33: =IF(Casos!$A$6="","",N(Casos!$F$6)) | J33: =IF(OR(Casos!$A$6="",D33="Interno"),"",I33-H33) | K33: =IF(OR(Casos!$A$6="",D33="Interno",I33=0),"",J33/I33) | L33: =IF(Casos!$A$6="","",IF(D33="Interno","Interno",IF(F33=0,"Sem horas",IF(H33>I33,"Consome mais do que paga",IF(AND(G33<>"",G33>1),"Estourou as horas",IF(AND(K33<>"",K33<0.2),"Margem baixa",IF(AND(G33<>"",G33>0.85),"Perto do limite","Saudável"))))))) | M33: =IF(OR(L33="Consome mais do que paga",L33="Margem baixa",L33="Estourou as horas"),IFERROR(H33/I33,9)+ROW()/1000000,0)
A34: =IF(Casos!$A$7="","",Casos!$A$7) | B34: =IF(Casos!$A$7="","",Casos!$B$7) | C34: =IF(Casos!$A$7="","",Casos!$D$7) | D34: =IF(Casos!$A$7="","",Casos!$E$7) | E34: =IF(Casos!$A$7="","",N(Casos!$G$7)) | F34: =IF(Casos!$A$7="","",N(Casos!$H$7)+SUMIFS(Lançamentos!$E$5:$E$604,Lançamentos!$C$5:$C$604,Casos!$A$7)) | G34: =IF(OR(Casos!$A$7="",E34=0),"",F34/E34) | H34: =IF(Casos!$A$7="","",N(Casos!$H$7)*Config!$B$23+SUMIFS(Lançamentos!$H$5:$H$604,Lançamentos!$C$5:$C$604,Casos!$A$7)) | I34: =IF(Casos!$A$7="","",N(Casos!$F$7)) | J34: =IF(OR(Casos!$A$7="",D34="Interno"),"",I34-H34) | K34: =IF(OR(Casos!$A$7="",D34="Interno",I34=0),"",J34/I34) | L34: =IF(Casos!$A$7="","",IF(D34="Interno","Interno",IF(F34=0,"Sem horas",IF(H34>I34,"Consome mais do que paga",IF(AND(G34<>"",G34>1),"Estourou as horas",IF(AND(K34<>"",K34<0.2),"Margem baixa",IF(AND(G34<>"",G34>0.85),"Perto do limite","Saudável"))))))) | M34: =IF(OR(L34="Consome mais do que paga",L34="Margem baixa",L34="Estourou as horas"),IFERROR(H34/I34,9)+ROW()/1000000,0)
A35: =IF(Casos!$A$8="","",Casos!$A$8) | B35: =IF(Casos!$A$8="","",Casos!$B$8) | C35: =IF(Casos!$A$8="","",Casos!$D$8) | D35: =IF(Casos!$A$8="","",Casos!$E$8) | E35: =IF(Casos!$A$8="","",N(Casos!$G$8)) | F35: =IF(Casos!$A$8="","",N(Casos!$H$8)+SUMIFS(Lançamentos!$E$5:$E$604,Lançamentos!$C$5:$C$604,Casos!$A$8)) | G35: =IF(OR(Casos!$A$8="",E35=0),"",F35/E35) | H35: =IF(Casos!$A$8="","",N(Casos!$H$8)*Config!$B$23+SUMIFS(Lançamentos!$H$5:$H$604,Lançamentos!$C$5:$C$604,Casos!$A$8)) | I35: =IF(Casos!$A$8="","",N(Casos!$F$8)) | J35: =IF(OR(Casos!$A$8="",D35="Interno"),"",I35-H35) | K35: =IF(OR(Casos!$A$8="",D35="Interno",I35=0),"",J35/I35) | L35: =IF(Casos!$A$8="","",IF(D35="Interno","Interno",IF(F35=0,"Sem horas",IF(H35>I35,"Consome mais do que paga",IF(AND(G35<>"",G35>1),"Estourou as horas",IF(AND(K35<>"",K35<0.2),"Margem baixa",IF(AND(G35<>"",G35>0.85),"Perto do limite","Saudável"))))))) | M35: =IF(OR(L35="Consome mais do que paga",L35="Margem baixa",L35="Estourou as horas"),IFERROR(H35/I35,9)+ROW()/1000000,0)
A36: =IF(Casos!$A$9="","",Casos!$A$9) | B36: =IF(Casos!$A$9="","",Casos!$B$9) | C36: =IF(Casos!$A$9="","",Casos!$D$9) | D36: =IF(Casos!$A$9="","",Casos!$E$9) | E36: =IF(Casos!$A$9="","",N(Casos!$G$9)) | F36: =IF(Casos!$A$9="","",N(Casos!$H$9)+SUMIFS(Lançamentos!$E$5:$E$604,Lançamentos!$C$5:$C$604,Casos!$A$9)) | G36: =IF(OR(Casos!$A$9="",E36=0),"",F36/E36) | H36: =IF(Casos!$A$9="","",N(Casos!$H$9)*Config!$B$23+SUMIFS(Lançamentos!$H$5:$H$604,Lançamentos!$C$5:$C$604,Casos!$A$9)) | I36: =IF(Casos!$A$9="","",N(Casos!$F$9)) | J36: =IF(OR(Casos!$A$9="",D36="Interno"),"",I36-H36) | K36: =IF(OR(Casos!$A$9="",D36="Interno",I36=0),"",J36/I36) | L36: =IF(Casos!$A$9="","",IF(D36="Interno","Interno",IF(F36=0,"Sem horas",IF(H36>I36,"Consome mais do que paga",IF(AND(G36<>"",G36>1),"Estourou as horas",IF(AND(K36<>"",K36<0.2),"Margem baixa",IF(AND(G36<>"",G36>0.85),"Perto do limite","Saudável"))))))) | M36: =IF(OR(L36="Consome mais do que paga",L36="Margem baixa",L36="Estourou as horas"),IFERROR(H36/I36,9)+ROW()/1000000,0)
A37: =IF(Casos!$A$10="","",Casos!$A$10) | B37: =IF(Casos!$A$10="","",Casos!$B$10) | C37: =IF(Casos!$A$10="","",Casos!$D$10) | D37: =IF(Casos!$A$10="","",Casos!$E$10) | E37: =IF(Casos!$A$10="","",N(Casos!$G$10)) | F37: =IF(Casos!$A$10="","",N(Casos!$H$10)+SUMIFS(Lançamentos!$E$5:$E$604,Lançamentos!$C$5:$C$604,Casos!$A$10)) | G37: =IF(OR(Casos!$A$10="",E37=0),"",F37/E37) | H37: =IF(Casos!$A$10="","",N(Casos!$H$10)*Config!$B$23+SUMIFS(Lançamentos!$H$5:$H$604,Lançamentos!$C$5:$C$604,Casos!$A$10)) | I37: =IF(Casos!$A$10="","",N(Casos!$F$10)) | J37: =IF(OR(Casos!$A$10="",D37="Interno"),"",I37-H37) | K37: =IF(OR(Casos!$A$10="",D37="Interno",I37=0),"",J37/I37) | L37: =IF(Casos!$A$10="","",IF(D37="Interno","Interno",IF(F37=0,"Sem horas",IF(H37>I37,"Consome mais do que paga",IF(AND(G37<>"",G37>1),"Estourou as horas",IF(AND(K37<>"",K37<0.2),"Margem baixa",IF(AND(G37<>"",G37>0.85),"Perto do limite","Saudável"))))))) | M37: =IF(OR(L37="Consome mais do que paga",L37="Margem baixa",L37="Estourou as horas"),IFERROR(H37/I37,9)+ROW()/1000000,0)
A38: =IF(Casos!$A$11="","",Casos!$A$11) | B38: =IF(Casos!$A$11="","",Casos!$B$11) | C38: =IF(Casos!$A$11="","",Casos!$D$11) | D38: =IF(Casos!$A$11="","",Casos!$E$11) | E38: =IF(Casos!$A$11="","",N(Casos!$G$11)) | F38: =IF(Casos!$A$11="","",N(Casos!$H$11)+SUMIFS(Lançamentos!$E$5:$E$604,Lançamentos!$C$5:$C$604,Casos!$A$11)) | G38: =IF(OR(Casos!$A$11="",E38=0),"",F38/E38) | H38: =IF(Casos!$A$11="","",N(Casos!$H$11)*Config!$B$23+SUMIFS(Lançamentos!$H$5:$H$604,Lançamentos!$C$5:$C$604,Casos!$A$11)) | I38: =IF(Casos!$A$11="","",N(Casos!$F$11)) | J38: =IF(OR(Casos!$A$11="",D38="Interno"),"",I38-H38) | K38: =IF(OR(Casos!$A$11="",D38="Interno",I38=0),"",J38/I38) | L38: =IF(Casos!$A$11="","",IF(D38="Interno","Interno",IF(F38=0,"Sem horas",IF(H38>I38,"Consome mais do que paga",IF(AND(G38<>"",G38>1),"Estourou as horas",IF(AND(K38<>"",K38<0.2),"Margem baixa",IF(AND(G38<>"",G38>0.85),"Perto do limite","Saudável"))))))) | M38: =IF(OR(L38="Consome mais do que paga",L38="Margem baixa",L38="Estourou as horas"),IFERROR(H38/I38,9)+ROW()/1000000,0)
A39: =IF(Casos!$A$12="","",Casos!$A$12) | B39: =IF(Casos!$A$12="","",Casos!$B$12) | C39: =IF(Casos!$A$12="","",Casos!$D$12) | D39: =IF(Casos!$A$12="","",Casos!$E$12) | E39: =IF(Casos!$A$12="","",N(Casos!$G$12)) | F39: =IF(Casos!$A$12="","",N(Casos!$H$12)+SUMIFS(Lançamentos!$E$5:$E$604,Lançamentos!$C$5:$C$604,Casos!$A$12)) | G39: =IF(OR(Casos!$A$12="",E39=0),"",F39/E39) | H39: =IF(Casos!$A$12="","",N(Casos!$H$12)*Config!$B$23+SUMIFS(Lançamentos!$H$5:$H$604,Lançamentos!$C$5:$C$604,Casos!$A$12)) | I39: =IF(Casos!$A$12="","",N(Casos!$F$12)) | J39: =IF(OR(Casos!$A$12="",D39="Interno"),"",I39-H39) | K39: =IF(OR(Casos!$A$12="",D39="Interno",I39=0),"",J39/I39) | L39: =IF(Casos!$A$12="","",IF(D39="Interno","Interno",IF(F39=0,"Sem horas",IF(H39>I39,"Consome mais do que paga",IF(AND(G39<>"",G39>1),"Estourou as horas",IF(AND(K39<>"",K39<0.2),"Margem baixa",IF(AND(G39<>"",G39>0.85),"Perto do limite","Saudável"))))))) | M39: =IF(OR(L39="Consome mais do que paga",L39="Margem baixa",L39="Estourou as horas"),IFERROR(H39/I39,9)+ROW()/1000000,0)
A40: =IF(Casos!$A$13="","",Casos!$A$13) | B40: =IF(Casos!$A$13="","",Casos!$B$13) | C40: =IF(Casos!$A$13="","",Casos!$D$13) | D40: =IF(Casos!$A$13="","",Casos!$E$13) | E40: =IF(Casos!$A$13="","",N(Casos!$G$13)) | F40: =IF(Casos!$A$13="","",N(Casos!$H$13)+SUMIFS(Lançamentos!$E$5:$E$604,Lançamentos!$C$5:$C$604,Casos!$A$13)) | G40: =IF(OR(Casos!$A$13="",E40=0),"",F40/E40) | H40: =IF(Casos!$A$13="","",N(Casos!$H$13)*Config!$B$23+SUMIFS(Lançamentos!$H$5:$H$604,Lançamentos!$C$5:$C$604,Casos!$A$13)) | I40: =IF(Casos!$A$13="","",N(Casos!$F$13)) | J40: =IF(OR(Casos!$A$13="",D40="Interno"),"",I40-H40) | K40: =IF(OR(Casos!$A$13="",D40="Interno",I40=0),"",J40/I40) | L40: =IF(Casos!$A$13="","",IF(D40="Interno","Interno",IF(F40=0,"Sem horas",IF(H40>I40,"Consome mais do que paga",IF(AND(G40<>"",G40>1),"Estourou as horas",IF(AND(K40<>"",K40<0.2),"Margem baixa",IF(AND(G40<>"",G40>0.85),"Perto do limite","Saudável"))))))) | M40: =IF(OR(L40="Consome mais do que paga",L40="Margem baixa",L40="Estourou as horas"),IFERROR(H40/I40,9)+ROW()/1000000,0)
A41: =IF(Casos!$A$14="","",Casos!$A$14) | B41: =IF(Casos!$A$14="","",Casos!$B$14) | C41: =IF(Casos!$A$14="","",Casos!$D$14) | D41: =IF(Casos!$A$14="","",Casos!$E$14) | E41: =IF(Casos!$A$14="","",N(Casos!$G$14)) | F41: =IF(Casos!$A$14="","",N(Casos!$H$14)+SUMIFS(Lançamentos!$E$5:$E$604,Lançamentos!$C$5:$C$604,Casos!$A$14)) | G41: =IF(OR(Casos!$A$14="",E41=0),"",F41/E41) | H41: =IF(Casos!$A$14="","",N(Casos!$H$14)*Config!$B$23+SUMIFS(Lançamentos!$H$5:$H$604,Lançamentos!$C$5:$C$604,Casos!$A$14)) | I41: =IF(Casos!$A$14="","",N(Casos!$F$14)) | J41: =IF(OR(Casos!$A$14="",D41="Interno"),"",I41-H41) | K41: =IF(OR(Casos!$A$14="",D41="Interno",I41=0),"",J41/I41) | L41: =IF(Casos!$A$14="","",IF(D41="Interno","Interno",IF(F41=0,"Sem horas",IF(H41>I41,"Consome mais do que paga",IF(AND(G41<>"",G41>1),"Estourou as horas",IF(AND(K41<>"",K41<0.2),"Margem baixa",IF(AND(G41<>"",G41>0.85),"Perto do limite","Saudável"))))))) | M41: =IF(OR(L41="Consome mais do que paga",L41="Margem baixa",L41="Estourou as horas"),IFERROR(H41/I41,9)+ROW()/1000000,0)
A42: =IF(Casos!$A$15="","",Casos!$A$15) | B42: =IF(Casos!$A$15="","",Casos!$B$15) | C42: =IF(Casos!$A$15="","",Casos!$D$15) | D42: =IF(Casos!$A$15="","",Casos!$E$15) | E42: =IF(Casos!$A$15="","",N(Casos!$G$15)) | F42: =IF(Casos!$A$15="","",N(Casos!$H$15)+SUMIFS(Lançamentos!$E$5:$E$604,Lançamentos!$C$5:$C$604,Casos!$A$15)) | G42: =IF(OR(Casos!$A$15="",E42=0),"",F42/E42) | H42: =IF(Casos!$A$15="","",N(Casos!$H$15)*Config!$B$23+SUMIFS(Lançamentos!$H$5:$H$604,Lançamentos!$C$5:$C$604,Casos!$A$15)) | I42: =IF(Casos!$A$15="","",N(Casos!$F$15)) | J42: =IF(OR(Casos!$A$15="",D42="Interno"),"",I42-H42) | K42: =IF(OR(Casos!$A$15="",D42="Interno",I42=0),"",J42/I42) | L42: =IF(Casos!$A$15="","",IF(D42="Interno","Interno",IF(F42=0,"Sem horas",IF(H42>I42,"Consome mais do que paga",IF(AND(G42<>"",G42>1),"Estourou as horas",IF(AND(K42<>"",K42<0.2),"Margem baixa",IF(AND(G42<>"",G42>0.85),"Perto do limite","Saudável"))))))) | M42: =IF(OR(L42="Consome mais do que paga",L42="Margem baixa",L42="Estourou as horas"),IFERROR(H42/I42,9)+ROW()/1000000,0)
A43: =IF(Casos!$A$16="","",Casos!$A$16) | B43: =IF(Casos!$A$16="","",Casos!$B$16) | C43: =IF(Casos!$A$16="","",Casos!$D$16) | D43: =IF(Casos!$A$16="","",Casos!$E$16) | E43: =IF(Casos!$A$16="","",N(Casos!$G$16)) | F43: =IF(Casos!$A$16="","",N(Casos!$H$16)+SUMIFS(Lançamentos!$E$5:$E$604,Lançamentos!$C$5:$C$604,Casos!$A$16)) | G43: =IF(OR(Casos!$A$16="",E43=0),"",F43/E43) | H43: =IF(Casos!$A$16="","",N(Casos!$H$16)*Config!$B$23+SUMIFS(Lançamentos!$H$5:$H$604,Lançamentos!$C$5:$C$604,Casos!$A$16)) | I43: =IF(Casos!$A$16="","",N(Casos!$F$16)) | J43: =IF(OR(Casos!$A$16="",D43="Interno"),"",I43-H43) | K43: =IF(OR(Casos!$A$16="",D43="Interno",I43=0),"",J43/I43) | L43: =IF(Casos!$A$16="","",IF(D43="Interno","Interno",IF(F43=0,"Sem horas",IF(H43>I43,"Consome mais do que paga",IF(AND(G43<>"",G43>1),"Estourou as horas",IF(AND(K43<>"",K43<0.2),"Margem baixa",IF(AND(G43<>"",G43>0.85),"Perto do limite","Saudável"))))))) | M43: =IF(OR(L43="Consome mais do que paga",L43="Margem baixa",L43="Estourou as horas"),IFERROR(H43/I43,9)+ROW()/1000000,0)
A44: =IF(Casos!$A$17="","",Casos!$A$17) | B44: =IF(Casos!$A$17="","",Casos!$B$17) | C44: =IF(Casos!$A$17="","",Casos!$D$17) | D44: =IF(Casos!$A$17="","",Casos!$E$17) | E44: =IF(Casos!$A$17="","",N(Casos!$G$17)) | F44: =IF(Casos!$A$17="","",N(Casos!$H$17)+SUMIFS(Lançamentos!$E$5:$E$604,Lançamentos!$C$5:$C$604,Casos!$A$17)) | G44: =IF(OR(Casos!$A$17="",E44=0),"",F44/E44) | H44: =IF(Casos!$A$17="","",N(Casos!$H$17)*Config!$B$23+SUMIFS(Lançamentos!$H$5:$H$604,Lançamentos!$C$5:$C$604,Casos!$A$17)) | I44: =IF(Casos!$A$17="","",N(Casos!$F$17)) | J44: =IF(OR(Casos!$A$17="",D44="Interno"),"",I44-H44) | K44: =IF(OR(Casos!$A$17="",D44="Interno",I44=0),"",J44/I44) | L44: =IF(Casos!$A$17="","",IF(D44="Interno","Interno",IF(F44=0,"Sem horas",IF(H44>I44,"Consome mais do que paga",IF(AND(G44<>"",G44>1),"Estourou as horas",IF(AND(K44<>"",K44<0.2),"Margem baixa",IF(AND(G44<>"",G44>0.85),"Perto do limite","Saudável"))))))) | M44: =IF(OR(L44="Consome mais do que paga",L44="Margem baixa",L44="Estourou as horas"),IFERROR(H44/I44,9)+ROW()/1000000,0)
A45: =IF(Casos!$A$18="","",Casos!$A$18) | B45: =IF(Casos!$A$18="","",Casos!$B$18) | C45: =IF(Casos!$A$18="","",Casos!$D$18) | D45: =IF(Casos!$A$18="","",Casos!$E$18) | E45: =IF(Casos!$A$18="","",N(Casos!$G$18)) | F45: =IF(Casos!$A$18="","",N(Casos!$H$18)+SUMIFS(Lançamentos!$E$5:$E$604,Lançamentos!$C$5:$C$604,Casos!$A$18)) | G45: =IF(OR(Casos!$A$18="",E45=0),"",F45/E45) | H45: =IF(Casos!$A$18="","",N(Casos!$H$18)*Config!$B$23+SUMIFS(Lançamentos!$H$5:$H$604,Lançamentos!$C$5:$C$604,Casos!$A$18)) | I45: =IF(Casos!$A$18="","",N(Casos!$F$18)) | J45: =IF(OR(Casos!$A$18="",D45="Interno"),"",I45-H45) | K45: =IF(OR(Casos!$A$18="",D45="Interno",I45=0),"",J45/I45) | L45: =IF(Casos!$A$18="","",IF(D45="Interno","Interno",IF(F45=0,"Sem horas",IF(H45>I45,"Consome mais do que paga",IF(AND(G45<>"",G45>1),"Estourou as horas",IF(AND(K45<>"",K45<0.2),"Margem baixa",IF(AND(G45<>"",G45>0.85),"Perto do limite","Saudável"))))))) | M45: =IF(OR(L45="Consome mais do que paga",L45="Margem baixa",L45="Estourou as horas"),IFERROR(H45/I45,9)+ROW()/1000000,0)
A46: =IF(Casos!$A$19="","",Casos!$A$19) | B46: =IF(Casos!$A$19="","",Casos!$B$19) | C46: =IF(Casos!$A$19="","",Casos!$D$19) | D46: =IF(Casos!$A$19="","",Casos!$E$19) | E46: =IF(Casos!$A$19="","",N(Casos!$G$19)) | F46: =IF(Casos!$A$19="","",N(Casos!$H$19)+SUMIFS(Lançamentos!$E$5:$E$604,Lançamentos!$C$5:$C$604,Casos!$A$19)) | G46: =IF(OR(Casos!$A$19="",E46=0),"",F46/E46) | H46: =IF(Casos!$A$19="","",N(Casos!$H$19)*Config!$B$23+SUMIFS(Lançamentos!$H$5:$H$604,Lançamentos!$C$5:$C$604,Casos!$A$19)) | I46: =IF(Casos!$A$19="","",N(Casos!$F$19)) | J46: =IF(OR(Casos!$A$19="",D46="Interno"),"",I46-H46) | K46: =IF(OR(Casos!$A$19="",D46="Interno",I46=0),"",J46/I46) | L46: =IF(Casos!$A$19="","",IF(D46="Interno","Interno",IF(F46=0,"Sem horas",IF(H46>I46,"Consome mais do que paga",IF(AND(G46<>"",G46>1),"Estourou as horas",IF(AND(K46<>"",K46<0.2),"Margem baixa",IF(AND(G46<>"",G46>0.85),"Perto do limite","Saudável"))))))) | M46: =IF(OR(L46="Consome mais do que paga",L46="Margem baixa",L46="Estourou as horas"),IFERROR(H46/I46,9)+ROW()/1000000,0)
A47: =IF(Casos!$A$20="","",Casos!$A$20) | B47: =IF(Casos!$A$20="","",Casos!$B$20) | C47: =IF(Casos!$A$20="","",Casos!$D$20) | D47: =IF(Casos!$A$20="","",Casos!$E$20) | E47: =IF(Casos!$A$20="","",N(Casos!$G$20)) | F47: =IF(Casos!$A$20="","",N(Casos!$H$20)+SUMIFS(Lançamentos!$E$5:$E$604,Lançamentos!$C$5:$C$604,Casos!$A$20)) | G47: =IF(OR(Casos!$A$20="",E47=0),"",F47/E47) | H47: =IF(Casos!$A$20="","",N(Casos!$H$20)*Config!$B$23+SUMIFS(Lançamentos!$H$5:$H$604,Lançamentos!$C$5:$C$604,Casos!$A$20)) | I47: =IF(Casos!$A$20="","",N(Casos!$F$20)) | J47: =IF(OR(Casos!$A$20="",D47="Interno"),"",I47-H47) | K47: =IF(OR(Casos!$A$20="",D47="Interno",I47=0),"",J47/I47) | L47: =IF(Casos!$A$20="","",IF(D47="Interno","Interno",IF(F47=0,"Sem horas",IF(H47>I47,"Consome mais do que paga",IF(AND(G47<>"",G47>1),"Estourou as horas",IF(AND(K47<>"",K47<0.2),"Margem baixa",IF(AND(G47<>"",G47>0.85),"Perto do limite","Saudável"))))))) | M47: =IF(OR(L47="Consome mais do que paga",L47="Margem baixa",L47="Estourou as horas"),IFERROR(H47/I47,9)+ROW()/1000000,0)
A48: =IF(Casos!$A$21="","",Casos!$A$21) | B48: =IF(Casos!$A$21="","",Casos!$B$21) | C48: =IF(Casos!$A$21="","",Casos!$D$21) | D48: =IF(Casos!$A$21="","",Casos!$E$21) | E48: =IF(Casos!$A$21="","",N(Casos!$G$21)) | F48: =IF(Casos!$A$21="","",N(Casos!$H$21)+SUMIFS(Lançamentos!$E$5:$E$604,Lançamentos!$C$5:$C$604,Casos!$A$21)) | G48: =IF(OR(Casos!$A$21="",E48=0),"",F48/E48) | H48: =IF(Casos!$A$21="","",N(Casos!$H$21)*Config!$B$23+SUMIFS(Lançamentos!$H$5:$H$604,Lançamentos!$C$5:$C$604,Casos!$A$21)) | I48: =IF(Casos!$A$21="","",N(Casos!$F$21)) | J48: =IF(OR(Casos!$A$21="",D48="Interno"),"",I48-H48) | K48: =IF(OR(Casos!$A$21="",D48="Interno",I48=0),"",J48/I48) | L48: =IF(Casos!$A$21="","",IF(D48="Interno","Interno",IF(F48=0,"Sem horas",IF(H48>I48,"Consome mais do que paga",IF(AND(G48<>"",G48>1),"Estourou as horas",IF(AND(K48<>"",K48<0.2),"Margem baixa",IF(AND(G48<>"",G48>0.85),"Perto do limite","Saudável"))))))) | M48: =IF(OR(L48="Consome mais do que paga",L48="Margem baixa",L48="Estourou as horas"),IFERROR(H48/I48,9)+ROW()/1000000,0)
A49: =IF(Casos!$A$22="","",Casos!$A$22) | B49: =IF(Casos!$A$22="","",Casos!$B$22) | C49: =IF(Casos!$A$22="","",Casos!$D$22) | D49: =IF(Casos!$A$22="","",Casos!$E$22) | E49: =IF(Casos!$A$22="","",N(Casos!$G$22)) | F49: =IF(Casos!$A$22="","",N(Casos!$H$22)+SUMIFS(Lançamentos!$E$5:$E$604,Lançamentos!$C$5:$C$604,Casos!$A$22)) | G49: =IF(OR(Casos!$A$22="",E49=0),"",F49/E49) | H49: =IF(Casos!$A$22="","",N(Casos!$H$22)*Config!$B$23+SUMIFS(Lançamentos!$H$5:$H$604,Lançamentos!$C$5:$C$604,Casos!$A$22)) | I49: =IF(Casos!$A$22="","",N(Casos!$F$22)) | J49: =IF(OR(Casos!$A$22="",D49="Interno"),"",I49-H49) | K49: =IF(OR(Casos!$A$22="",D49="Interno",I49=0),"",J49/I49) | L49: =IF(Casos!$A$22="","",IF(D49="Interno","Interno",IF(F49=0,"Sem horas",IF(H49>I49,"Consome mais do que paga",IF(AND(G49<>"",G49>1),"Estourou as horas",IF(AND(K49<>"",K49<0.2),"Margem baixa",IF(AND(G49<>"",G49>0.85),"Perto do limite","Saudável"))))))) | M49: =IF(OR(L49="Consome mais do que paga",L49="Margem baixa",L49="Estourou as horas"),IFERROR(H49/I49,9)+ROW()/1000000,0)
A50: =IF(Casos!$A$23="","",Casos!$A$23) | B50: =IF(Casos!$A$23="","",Casos!$B$23) | C50: =IF(Casos!$A$23="","",Casos!$D$23) | D50: =IF(Casos!$A$23="","",Casos!$E$23) | E50: =IF(Casos!$A$23="","",N(Casos!$G$23)) | F50: =IF(Casos!$A$23="","",N(Casos!$H$23)+SUMIFS(Lançamentos!$E$5:$E$604,Lançamentos!$C$5:$C$604,Casos!$A$23)) | G50: =IF(OR(Casos!$A$23="",E50=0),"",F50/E50) | H50: =IF(Casos!$A$23="","",N(Casos!$H$23)*Config!$B$23+SUMIFS(Lançamentos!$H$5:$H$604,Lançamentos!$C$5:$C$604,Casos!$A$23)) | I50: =IF(Casos!$A$23="","",N(Casos!$F$23)) | J50: =IF(OR(Casos!$A$23="",D50="Interno"),"",I50-H50) | K50: =IF(OR(Casos!$A$23="",D50="Interno",I50=0),"",J50/I50) | L50: =IF(Casos!$A$23="","",IF(D50="Interno","Interno",IF(F50=0,"Sem horas",IF(H50>I50,"Consome mais do que paga",IF(AND(G50<>"",G50>1),"Estourou as horas",IF(AND(K50<>"",K50<0.2),"Margem baixa",IF(AND(G50<>"",G50>0.85),"Perto do limite","Saudável"))))))) | M50: =IF(OR(L50="Consome mais do que paga",L50="Margem baixa",L50="Estourou as horas"),IFERROR(H50/I50,9)+ROW()/1000000,0)
A51: =IF(Casos!$A$24="","",Casos!$A$24) | B51: =IF(Casos!$A$24="","",Casos!$B$24) | C51: =IF(Casos!$A$24="","",Casos!$D$24) | D51: =IF(Casos!$A$24="","",Casos!$E$24) | E51: =IF(Casos!$A$24="","",N(Casos!$G$24)) | F51: =IF(Casos!$A$24="","",N(Casos!$H$24)+SUMIFS(Lançamentos!$E$5:$E$604,Lançamentos!$C$5:$C$604,Casos!$A$24)) | G51: =IF(OR(Casos!$A$24="",E51=0),"",F51/E51) | H51: =IF(Casos!$A$24="","",N(Casos!$H$24)*Config!$B$23+SUMIFS(Lançamentos!$H$5:$H$604,Lançamentos!$C$5:$C$604,Casos!$A$24)) | I51: =IF(Casos!$A$24="","",N(Casos!$F$24)) | J51: =IF(OR(Casos!$A$24="",D51="Interno"),"",I51-H51) | K51: =IF(OR(Casos!$A$24="",D51="Interno",I51=0),"",J51/I51) | L51: =IF(Casos!$A$24="","",IF(D51="Interno","Interno",IF(F51=0,"Sem horas",IF(H51>I51,"Consome mais do que paga",IF(AND(G51<>"",G51>1),"Estourou as horas",IF(AND(K51<>"",K51<0.2),"Margem baixa",IF(AND(G51<>"",G51>0.85),"Perto do limite","Saudável"))))))) | M51: =IF(OR(L51="Consome mais do que paga",L51="Margem baixa",L51="Estourou as horas"),IFERROR(H51/I51,9)+ROW()/1000000,0)
A52: =IF(Casos!$A$25="","",Casos!$A$25) | B52: =IF(Casos!$A$25="","",Casos!$B$25) | C52: =IF(Casos!$A$25="","",Casos!$D$25) | D52: =IF(Casos!$A$25="","",Casos!$E$25) | E52: =IF(Casos!$A$25="","",N(Casos!$G$25)) | F52: =IF(Casos!$A$25="","",N(Casos!$H$25)+SUMIFS(Lançamentos!$E$5:$E$604,Lançamentos!$C$5:$C$604,Casos!$A$25)) | G52: =IF(OR(Casos!$A$25="",E52=0),"",F52/E52) | H52: =IF(Casos!$A$25="","",N(Casos!$H$25)*Config!$B$23+SUMIFS(Lançamentos!$H$5:$H$604,Lançamentos!$C$5:$C$604,Casos!$A$25)) | I52: =IF(Casos!$A$25="","",N(Casos!$F$25)) | J52: =IF(OR(Casos!$A$25="",D52="Interno"),"",I52-H52) | K52: =IF(OR(Casos!$A$25="",D52="Interno",I52=0),"",J52/I52) | L52: =IF(Casos!$A$25="","",IF(D52="Interno","Interno",IF(F52=0,"Sem horas",IF(H52>I52,"Consome mais do que paga",IF(AND(G52<>"",G52>1),"Estourou as horas",IF(AND(K52<>"",K52<0.2),"Margem baixa",IF(AND(G52<>"",G52>0.85),"Perto do limite","Saudável"))))))) | M52: =IF(OR(L52="Consome mais do que paga",L52="Margem baixa",L52="Estourou as horas"),IFERROR(H52/I52,9)+ROW()/1000000,0)
A53: =IF(Casos!$A$26="","",Casos!$A$26) | B53: =IF(Casos!$A$26="","",Casos!$B$26) | C53: =IF(Casos!$A$26="","",Casos!$D$26) | D53: =IF(Casos!$A$26="","",Casos!$E$26) | E53: =IF(Casos!$A$26="","",N(Casos!$G$26)) | F53: =IF(Casos!$A$26="","",N(Casos!$H$26)+SUMIFS(Lançamentos!$E$5:$E$604,Lançamentos!$C$5:$C$604,Casos!$A$26)) | G53: =IF(OR(Casos!$A$26="",E53=0),"",F53/E53) | H53: =IF(Casos!$A$26="","",N(Casos!$H$26)*Config!$B$23+SUMIFS(Lançamentos!$H$5:$H$604,Lançamentos!$C$5:$C$604,Casos!$A$26)) | I53: =IF(Casos!$A$26="","",N(Casos!$F$26)) | J53: =IF(OR(Casos!$A$26="",D53="Interno"),"",I53-H53) | K53: =IF(OR(Casos!$A$26="",D53="Interno",I53=0),"",J53/I53) | L53: =IF(Casos!$A$26="","",IF(D53="Interno","Interno",IF(F53=0,"Sem horas",IF(H53>I53,"Consome mais do que paga",IF(AND(G53<>"",G53>1),"Estourou as horas",IF(AND(K53<>"",K53<0.2),"Margem baixa",IF(AND(G53<>"",G53>0.85),"Perto do limite","Saudável"))))))) | M53: =IF(OR(L53="Consome mais do que paga",L53="Margem baixa",L53="Estourou as horas"),IFERROR(H53/I53,9)+ROW()/1000000,0)
A54: =IF(Casos!$A$27="","",Casos!$A$27) | B54: =IF(Casos!$A$27="","",Casos!$B$27) | C54: =IF(Casos!$A$27="","",Casos!$D$27) | D54: =IF(Casos!$A$27="","",Casos!$E$27) | E54: =IF(Casos!$A$27="","",N(Casos!$G$27)) | F54: =IF(Casos!$A$27="","",N(Casos!$H$27)+SUMIFS(Lançamentos!$E$5:$E$604,Lançamentos!$C$5:$C$604,Casos!$A$27)) | G54: =IF(OR(Casos!$A$27="",E54=0),"",F54/E54) | H54: =IF(Casos!$A$27="","",N(Casos!$H$27)*Config!$B$23+SUMIFS(Lançamentos!$H$5:$H$604,Lançamentos!$C$5:$C$604,Casos!$A$27)) | I54: =IF(Casos!$A$27="","",N(Casos!$F$27)) | J54: =IF(OR(Casos!$A$27="",D54="Interno"),"",I54-H54) | K54: =IF(OR(Casos!$A$27="",D54="Interno",I54=0),"",J54/I54) | L54: =IF(Casos!$A$27="","",IF(D54="Interno","Interno",IF(F54=0,"Sem horas",IF(H54>I54,"Consome mais do que paga",IF(AND(G54<>"",G54>1),"Estourou as horas",IF(AND(K54<>"",K54<0.2),"Margem baixa",IF(AND(G54<>"",G54>0.85),"Perto do limite","Saudável"))))))) | M54: =IF(OR(L54="Consome mais do que paga",L54="Margem baixa",L54="Estourou as horas"),IFERROR(H54/I54,9)+ROW()/1000000,0)
A55: =IF(Casos!$A$28="","",Casos!$A$28) | B55: =IF(Casos!$A$28="","",Casos!$B$28) | C55: =IF(Casos!$A$28="","",Casos!$D$28) | D55: =IF(Casos!$A$28="","",Casos!$E$28) | E55: =IF(Casos!$A$28="","",N(Casos!$G$28)) | F55: =IF(Casos!$A$28="","",N(Casos!$H$28)+SUMIFS(Lançamentos!$E$5:$E$604,Lançamentos!$C$5:$C$604,Casos!$A$28)) | G55: =IF(OR(Casos!$A$28="",E55=0),"",F55/E55) | H55: =IF(Casos!$A$28="","",N(Casos!$H$28)*Config!$B$23+SUMIFS(Lançamentos!$H$5:$H$604,Lançamentos!$C$5:$C$604,Casos!$A$28)) | I55: =IF(Casos!$A$28="","",N(Casos!$F$28)) | J55: =IF(OR(Casos!$A$28="",D55="Interno"),"",I55-H55) | K55: =IF(OR(Casos!$A$28="",D55="Interno",I55=0),"",J55/I55) | L55: =IF(Casos!$A$28="","",IF(D55="Interno","Interno",IF(F55=0,"Sem horas",IF(H55>I55,"Consome mais do que paga",IF(AND(G55<>"",G55>1),"Estourou as horas",IF(AND(K55<>"",K55<0.2),"Margem baixa",IF(AND(G55<>"",G55>0.85),"Perto do limite","Saudável"))))))) | M55: =IF(OR(L55="Consome mais do que paga",L55="Margem baixa",L55="Estourou as horas"),IFERROR(H55/I55,9)+ROW()/1000000,0)
A56: =IF(Casos!$A$29="","",Casos!$A$29) | B56: =IF(Casos!$A$29="","",Casos!$B$29) | C56: =IF(Casos!$A$29="","",Casos!$D$29) | D56: =IF(Casos!$A$29="","",Casos!$E$29) | E56: =IF(Casos!$A$29="","",N(Casos!$G$29)) | F56: =IF(Casos!$A$29="","",N(Casos!$H$29)+SUMIFS(Lançamentos!$E$5:$E$604,Lançamentos!$C$5:$C$604,Casos!$A$29)) | G56: =IF(OR(Casos!$A$29="",E56=0),"",F56/E56) | H56: =IF(Casos!$A$29="","",N(Casos!$H$29)*Config!$B$23+SUMIFS(Lançamentos!$H$5:$H$604,Lançamentos!$C$5:$C$604,Casos!$A$29)) | I56: =IF(Casos!$A$29="","",N(Casos!$F$29)) | J56: =IF(OR(Casos!$A$29="",D56="Interno"),"",I56-H56) | K56: =IF(OR(Casos!$A$29="",D56="Interno",I56=0),"",J56/I56) | L56: =IF(Casos!$A$29="","",IF(D56="Interno","Interno",IF(F56=0,"Sem horas",IF(H56>I56,"Consome mais do que paga",IF(AND(G56<>"",G56>1),"Estourou as horas",IF(AND(K56<>"",K56<0.2),"Margem baixa",IF(AND(G56<>"",G56>0.85),"Perto do limite","Saudável"))))))) | M56: =IF(OR(L56="Consome mais do que paga",L56="Margem baixa",L56="Estourou as horas"),IFERROR(H56/I56,9)+ROW()/1000000,0)
A57: =IF(Casos!$A$30="","",Casos!$A$30) | B57: =IF(Casos!$A$30="","",Casos!$B$30) | C57: =IF(Casos!$A$30="","",Casos!$D$30) | D57: =IF(Casos!$A$30="","",Casos!$E$30) | E57: =IF(Casos!$A$30="","",N(Casos!$G$30)) | F57: =IF(Casos!$A$30="","",N(Casos!$H$30)+SUMIFS(Lançamentos!$E$5:$E$604,Lançamentos!$C$5:$C$604,Casos!$A$30)) | G57: =IF(OR(Casos!$A$30="",E57=0),"",F57/E57) | H57: =IF(Casos!$A$30="","",N(Casos!$H$30)*Config!$B$23+SUMIFS(Lançamentos!$H$5:$H$604,Lançamentos!$C$5:$C$604,Casos!$A$30)) | I57: =IF(Casos!$A$30="","",N(Casos!$F$30)) | J57: =IF(OR(Casos!$A$30="",D57="Interno"),"",I57-H57) | K57: =IF(OR(Casos!$A$30="",D57="Interno",I57=0),"",J57/I57) | L57: =IF(Casos!$A$30="","",IF(D57="Interno","Interno",IF(F57=0,"Sem horas",IF(H57>I57,"Consome mais do que paga",IF(AND(G57<>"",G57>1),"Estourou as horas",IF(AND(K57<>"",K57<0.2),"Margem baixa",IF(AND(G57<>"",G57>0.85),"Perto do limite","Saudável"))))))) | M57: =IF(OR(L57="Consome mais do que paga",L57="Margem baixa",L57="Estourou as horas"),IFERROR(H57/I57,9)+ROW()/1000000,0)
A58: =IF(Casos!$A$31="","",Casos!$A$31) | B58: =IF(Casos!$A$31="","",Casos!$B$31) | C58: =IF(Casos!$A$31="","",Casos!$D$31) | D58: =IF(Casos!$A$31="","",Casos!$E$31) | E58: =IF(Casos!$A$31="","",N(Casos!$G$31)) | F58: =IF(Casos!$A$31="","",N(Casos!$H$31)+SUMIFS(Lançamentos!$E$5:$E$604,Lançamentos!$C$5:$C$604,Casos!$A$31)) | G58: =IF(OR(Casos!$A$31="",E58=0),"",F58/E58) | H58: =IF(Casos!$A$31="","",N(Casos!$H$31)*Config!$B$23+SUMIFS(Lançamentos!$H$5:$H$604,Lançamentos!$C$5:$C$604,Casos!$A$31)) | I58: =IF(Casos!$A$31="","",N(Casos!$F$31)) | J58: =IF(OR(Casos!$A$31="",D58="Interno"),"",I58-H58) | K58: =IF(OR(Casos!$A$31="",D58="Interno",I58=0),"",J58/I58) | L58: =IF(Casos!$A$31="","",IF(D58="Interno","Interno",IF(F58=0,"Sem horas",IF(H58>I58,"Consome mais do que paga",IF(AND(G58<>"",G58>1),"Estourou as horas",IF(AND(K58<>"",K58<0.2),"Margem baixa",IF(AND(G58<>"",G58>0.85),"Perto do limite","Saudável"))))))) | M58: =IF(OR(L58="Consome mais do que paga",L58="Margem baixa",L58="Estourou as horas"),IFERROR(H58/I58,9)+ROW()/1000000,0)
A59: =IF(Casos!$A$32="","",Casos!$A$32) | B59: =IF(Casos!$A$32="","",Casos!$B$32) | C59: =IF(Casos!$A$32="","",Casos!$D$32) | D59: =IF(Casos!$A$32="","",Casos!$E$32) | E59: =IF(Casos!$A$32="","",N(Casos!$G$32)) | F59: =IF(Casos!$A$32="","",N(Casos!$H$32)+SUMIFS(Lançamentos!$E$5:$E$604,Lançamentos!$C$5:$C$604,Casos!$A$32)) | G59: =IF(OR(Casos!$A$32="",E59=0),"",F59/E59) | H59: =IF(Casos!$A$32="","",N(Casos!$H$32)*Config!$B$23+SUMIFS(Lançamentos!$H$5:$H$604,Lançamentos!$C$5:$C$604,Casos!$A$32)) | I59: =IF(Casos!$A$32="","",N(Casos!$F$32)) | J59: =IF(OR(Casos!$A$32="",D59="Interno"),"",I59-H59) | K59: =IF(OR(Casos!$A$32="",D59="Interno",I59=0),"",J59/I59) | L59: =IF(Casos!$A$32="","",IF(D59="Interno","Interno",IF(F59=0,"Sem horas",IF(H59>I59,"Consome mais do que paga",IF(AND(G59<>"",G59>1),"Estourou as horas",IF(AND(K59<>"",K59<0.2),"Margem baixa",IF(AND(G59<>"",G59>0.85),"Perto do limite","Saudável"))))))) | M59: =IF(OR(L59="Consome mais do que paga",L59="Margem baixa",L59="Estourou as horas"),IFERROR(H59/I59,9)+ROW()/1000000,0)
A60: =IF(Casos!$A$33="","",Casos!$A$33) | B60: =IF(Casos!$A$33="","",Casos!$B$33) | C60: =IF(Casos!$A$33="","",Casos!$D$33) | D60: =IF(Casos!$A$33="","",Casos!$E$33) | E60: =IF(Casos!$A$33="","",N(Casos!$G$33)) | F60: =IF(Casos!$A$33="","",N(Casos!$H$33)+SUMIFS(Lançamentos!$E$5:$E$604,Lançamentos!$C$5:$C$604,Casos!$A$33)) | G60: =IF(OR(Casos!$A$33="",E60=0),"",F60/E60) | H60: =IF(Casos!$A$33="","",N(Casos!$H$33)*Config!$B$23+SUMIFS(Lançamentos!$H$5:$H$604,Lançamentos!$C$5:$C$604,Casos!$A$33)) | I60: =IF(Casos!$A$33="","",N(Casos!$F$33)) | J60: =IF(OR(Casos!$A$33="",D60="Interno"),"",I60-H60) | K60: =IF(OR(Casos!$A$33="",D60="Interno",I60=0),"",J60/I60) | L60: =IF(Casos!$A$33="","",IF(D60="Interno","Interno",IF(F60=0,"Sem horas",IF(H60>I60,"Consome mais do que paga",IF(AND(G60<>"",G60>1),"Estourou as horas",IF(AND(K60<>"",K60<0.2),"Margem baixa",IF(AND(G60<>"",G60>0.85),"Perto do limite","Saudável"))))))) | M60: =IF(OR(L60="Consome mais do que paga",L60="Margem baixa",L60="Estourou as horas"),IFERROR(H60/I60,9)+ROW()/1000000,0)
A61: =IF(Casos!$A$34="","",Casos!$A$34) | B61: =IF(Casos!$A$34="","",Casos!$B$34) | C61: =IF(Casos!$A$34="","",Casos!$D$34) | D61: =IF(Casos!$A$34="","",Casos!$E$34) | E61: =IF(Casos!$A$34="","",N(Casos!$G$34)) | F61: =IF(Casos!$A$34="","",N(Casos!$H$34)+SUMIFS(Lançamentos!$E$5:$E$604,Lançamentos!$C$5:$C$604,Casos!$A$34)) | G61: =IF(OR(Casos!$A$34="",E61=0),"",F61/E61) | H61: =IF(Casos!$A$34="","",N(Casos!$H$34)*Config!$B$23+SUMIFS(Lançamentos!$H$5:$H$604,Lançamentos!$C$5:$C$604,Casos!$A$34)) | I61: =IF(Casos!$A$34="","",N(Casos!$F$34)) | J61: =IF(OR(Casos!$A$34="",D61="Interno"),"",I61-H61) | K61: =IF(OR(Casos!$A$34="",D61="Interno",I61=0),"",J61/I61) | L61: =IF(Casos!$A$34="","",IF(D61="Interno","Interno",IF(F61=0,"Sem horas",IF(H61>I61,"Consome mais do que paga",IF(AND(G61<>"",G61>1),"Estourou as horas",IF(AND(K61<>"",K61<0.2),"Margem baixa",IF(AND(G61<>"",G61>0.85),"Perto do limite","Saudável"))))))) | M61: =IF(OR(L61="Consome mais do que paga",L61="Margem baixa",L61="Estourou as horas"),IFERROR(H61/I61,9)+ROW()/1000000,0)
A62: =IF(Casos!$A$35="","",Casos!$A$35) | B62: =IF(Casos!$A$35="","",Casos!$B$35) | C62: =IF(Casos!$A$35="","",Casos!$D$35) | D62: =IF(Casos!$A$35="","",Casos!$E$35) | E62: =IF(Casos!$A$35="","",N(Casos!$G$35)) | F62: =IF(Casos!$A$35="","",N(Casos!$H$35)+SUMIFS(Lançamentos!$E$5:$E$604,Lançamentos!$C$5:$C$604,Casos!$A$35)) | G62: =IF(OR(Casos!$A$35="",E62=0),"",F62/E62) | H62: =IF(Casos!$A$35="","",N(Casos!$H$35)*Config!$B$23+SUMIFS(Lançamentos!$H$5:$H$604,Lançamentos!$C$5:$C$604,Casos!$A$35)) | I62: =IF(Casos!$A$35="","",N(Casos!$F$35)) | J62: =IF(OR(Casos!$A$35="",D62="Interno"),"",I62-H62) | K62: =IF(OR(Casos!$A$35="",D62="Interno",I62=0),"",J62/I62) | L62: =IF(Casos!$A$35="","",IF(D62="Interno","Interno",IF(F62=0,"Sem horas",IF(H62>I62,"Consome mais do que paga",IF(AND(G62<>"",G62>1),"Estourou as horas",IF(AND(K62<>"",K62<0.2),"Margem baixa",IF(AND(G62<>"",G62>0.85),"Perto do limite","Saudável"))))))) | M62: =IF(OR(L62="Consome mais do que paga",L62="Margem baixa",L62="Estourou as horas"),IFERROR(H62/I62,9)+ROW()/1000000,0)
A63: =IF(Casos!$A$36="","",Casos!$A$36) | B63: =IF(Casos!$A$36="","",Casos!$B$36) | C63: =IF(Casos!$A$36="","",Casos!$D$36) | D63: =IF(Casos!$A$36="","",Casos!$E$36) | E63: =IF(Casos!$A$36="","",N(Casos!$G$36)) | F63: =IF(Casos!$A$36="","",N(Casos!$H$36)+SUMIFS(Lançamentos!$E$5:$E$604,Lançamentos!$C$5:$C$604,Casos!$A$36)) | G63: =IF(OR(Casos!$A$36="",E63=0),"",F63/E63) | H63: =IF(Casos!$A$36="","",N(Casos!$H$36)*Config!$B$23+SUMIFS(Lançamentos!$H$5:$H$604,Lançamentos!$C$5:$C$604,Casos!$A$36)) | I63: =IF(Casos!$A$36="","",N(Casos!$F$36)) | J63: =IF(OR(Casos!$A$36="",D63="Interno"),"",I63-H63) | K63: =IF(OR(Casos!$A$36="",D63="Interno",I63=0),"",J63/I63) | L63: =IF(Casos!$A$36="","",IF(D63="Interno","Interno",IF(F63=0,"Sem horas",IF(H63>I63,"Consome mais do que paga",IF(AND(G63<>"",G63>1),"Estourou as horas",IF(AND(K63<>"",K63<0.2),"Margem baixa",IF(AND(G63<>"",G63>0.85),"Perto do limite","Saudável"))))))) | M63: =IF(OR(L63="Consome mais do que paga",L63="Margem baixa",L63="Estourou as horas"),IFERROR(H63/I63,9)+ROW()/1000000,0)
A64: =IF(Casos!$A$37="","",Casos!$A$37) | B64: =IF(Casos!$A$37="","",Casos!$B$37) | C64: =IF(Casos!$A$37="","",Casos!$D$37) | D64: =IF(Casos!$A$37="","",Casos!$E$37) | E64: =IF(Casos!$A$37="","",N(Casos!$G$37)) | F64: =IF(Casos!$A$37="","",N(Casos!$H$37)+SUMIFS(Lançamentos!$E$5:$E$604,Lançamentos!$C$5:$C$604,Casos!$A$37)) | G64: =IF(OR(Casos!$A$37="",E64=0),"",F64/E64) | H64: =IF(Casos!$A$37="","",N(Casos!$H$37)*Config!$B$23+SUMIFS(Lançamentos!$H$5:$H$604,Lançamentos!$C$5:$C$604,Casos!$A$37)) | I64: =IF(Casos!$A$37="","",N(Casos!$F$37)) | J64: =IF(OR(Casos!$A$37="",D64="Interno"),"",I64-H64) | K64: =IF(OR(Casos!$A$37="",D64="Interno",I64=0),"",J64/I64) | L64: =IF(Casos!$A$37="","",IF(D64="Interno","Interno",IF(F64=0,"Sem horas",IF(H64>I64,"Consome mais do que paga",IF(AND(G64<>"",G64>1),"Estourou as horas",IF(AND(K64<>"",K64<0.2),"Margem baixa",IF(AND(G64<>"",G64>0.85),"Perto do limite","Saudável"))))))) | M64: =IF(OR(L64="Consome mais do que paga",L64="Margem baixa",L64="Estourou as horas"),IFERROR(H64/I64,9)+ROW()/1000000,0)
A65: =IF(Casos!$A$38="","",Casos!$A$38) | B65: =IF(Casos!$A$38="","",Casos!$B$38) | C65: =IF(Casos!$A$38="","",Casos!$D$38) | D65: =IF(Casos!$A$38="","",Casos!$E$38) | E65: =IF(Casos!$A$38="","",N(Casos!$G$38)) | F65: =IF(Casos!$A$38="","",N(Casos!$H$38)+SUMIFS(Lançamentos!$E$5:$E$604,Lançamentos!$C$5:$C$604,Casos!$A$38)) | G65: =IF(OR(Casos!$A$38="",E65=0),"",F65/E65) | H65: =IF(Casos!$A$38="","",N(Casos!$H$38)*Config!$B$23+SUMIFS(Lançamentos!$H$5:$H$604,Lançamentos!$C$5:$C$604,Casos!$A$38)) | I65: =IF(Casos!$A$38="","",N(Casos!$F$38)) | J65: =IF(OR(Casos!$A$38="",D65="Interno"),"",I65-H65) | K65: =IF(OR(Casos!$A$38="",D65="Interno",I65=0),"",J65/I65) | L65: =IF(Casos!$A$38="","",IF(D65="Interno","Interno",IF(F65=0,"Sem horas",IF(H65>I65,"Consome mais do que paga",IF(AND(G65<>"",G65>1),"Estourou as horas",IF(AND(K65<>"",K65<0.2),"Margem baixa",IF(AND(G65<>"",G65>0.85),"Perto do limite","Saudável"))))))) | M65: =IF(OR(L65="Consome mais do que paga",L65="Margem baixa",L65="Estourou as horas"),IFERROR(H65/I65,9)+ROW()/1000000,0)
A66: =IF(Casos!$A$39="","",Casos!$A$39) | B66: =IF(Casos!$A$39="","",Casos!$B$39) | C66: =IF(Casos!$A$39="","",Casos!$D$39) | D66: =IF(Casos!$A$39="","",Casos!$E$39) | E66: =IF(Casos!$A$39="","",N(Casos!$G$39)) | F66: =IF(Casos!$A$39="","",N(Casos!$H$39)+SUMIFS(Lançamentos!$E$5:$E$604,Lançamentos!$C$5:$C$604,Casos!$A$39)) | G66: =IF(OR(Casos!$A$39="",E66=0),"",F66/E66) | H66: =IF(Casos!$A$39="","",N(Casos!$H$39)*Config!$B$23+SUMIFS(Lançamentos!$H$5:$H$604,Lançamentos!$C$5:$C$604,Casos!$A$39)) | I66: =IF(Casos!$A$39="","",N(Casos!$F$39)) | J66: =IF(OR(Casos!$A$39="",D66="Interno"),"",I66-H66) | K66: =IF(OR(Casos!$A$39="",D66="Interno",I66=0),"",J66/I66) | L66: =IF(Casos!$A$39="","",IF(D66="Interno","Interno",IF(F66=0,"Sem horas",IF(H66>I66,"Consome mais do que paga",IF(AND(G66<>"",G66>1),"Estourou as horas",IF(AND(K66<>"",K66<0.2),"Margem baixa",IF(AND(G66<>"",G66>0.85),"Perto do limite","Saudável"))))))) | M66: =IF(OR(L66="Consome mais do que paga",L66="Margem baixa",L66="Estourou as horas"),IFERROR(H66/I66,9)+ROW()/1000000,0)
A67: =IF(Casos!$A$40="","",Casos!$A$40) | B67: =IF(Casos!$A$40="","",Casos!$B$40) | C67: =IF(Casos!$A$40="","",Casos!$D$40) | D67: =IF(Casos!$A$40="","",Casos!$E$40) | E67: =IF(Casos!$A$40="","",N(Casos!$G$40)) | F67: =IF(Casos!$A$40="","",N(Casos!$H$40)+SUMIFS(Lançamentos!$E$5:$E$604,Lançamentos!$C$5:$C$604,Casos!$A$40)) | G67: =IF(OR(Casos!$A$40="",E67=0),"",F67/E67) | H67: =IF(Casos!$A$40="","",N(Casos!$H$40)*Config!$B$23+SUMIFS(Lançamentos!$H$5:$H$604,Lançamentos!$C$5:$C$604,Casos!$A$40)) | I67: =IF(Casos!$A$40="","",N(Casos!$F$40)) | J67: =IF(OR(Casos!$A$40="",D67="Interno"),"",I67-H67) | K67: =IF(OR(Casos!$A$40="",D67="Interno",I67=0),"",J67/I67) | L67: =IF(Casos!$A$40="","",IF(D67="Interno","Interno",IF(F67=0,"Sem horas",IF(H67>I67,"Consome mais do que paga",IF(AND(G67<>"",G67>1),"Estourou as horas",IF(AND(K67<>"",K67<0.2),"Margem baixa",IF(AND(G67<>"",G67>0.85),"Perto do limite","Saudável"))))))) | M67: =IF(OR(L67="Consome mais do que paga",L67="Margem baixa",L67="Estourou as horas"),IFERROR(H67/I67,9)+ROW()/1000000,0)
A68: =IF(Casos!$A$41="","",Casos!$A$41) | B68: =IF(Casos!$A$41="","",Casos!$B$41) | C68: =IF(Casos!$A$41="","",Casos!$D$41) | D68: =IF(Casos!$A$41="","",Casos!$E$41) | E68: =IF(Casos!$A$41="","",N(Casos!$G$41)) | F68: =IF(Casos!$A$41="","",N(Casos!$H$41)+SUMIFS(Lançamentos!$E$5:$E$604,Lançamentos!$C$5:$C$604,Casos!$A$41)) | G68: =IF(OR(Casos!$A$41="",E68=0),"",F68/E68) | H68: =IF(Casos!$A$41="","",N(Casos!$H$41)*Config!$B$23+SUMIFS(Lançamentos!$H$5:$H$604,Lançamentos!$C$5:$C$604,Casos!$A$41)) | I68: =IF(Casos!$A$41="","",N(Casos!$F$41)) | J68: =IF(OR(Casos!$A$41="",D68="Interno"),"",I68-H68) | K68: =IF(OR(Casos!$A$41="",D68="Interno",I68=0),"",J68/I68) | L68: =IF(Casos!$A$41="","",IF(D68="Interno","Interno",IF(F68=0,"Sem horas",IF(H68>I68,"Consome mais do que paga",IF(AND(G68<>"",G68>1),"Estourou as horas",IF(AND(K68<>"",K68<0.2),"Margem baixa",IF(AND(G68<>"",G68>0.85),"Perto do limite","Saudável"))))))) | M68: =IF(OR(L68="Consome mais do que paga",L68="Margem baixa",L68="Estourou as horas"),IFERROR(H68/I68,9)+ROW()/1000000,0)
A69: =IF(Casos!$A$42="","",Casos!$A$42) | B69: =IF(Casos!$A$42="","",Casos!$B$42) | C69: =IF(Casos!$A$42="","",Casos!$D$42) | D69: =IF(Casos!$A$42="","",Casos!$E$42) | E69: =IF(Casos!$A$42="","",N(Casos!$G$42)) | F69: =IF(Casos!$A$42="","",N(Casos!$H$42)+SUMIFS(Lançamentos!$E$5:$E$604,Lançamentos!$C$5:$C$604,Casos!$A$42)) | G69: =IF(OR(Casos!$A$42="",E69=0),"",F69/E69) | H69: =IF(Casos!$A$42="","",N(Casos!$H$42)*Config!$B$23+SUMIFS(Lançamentos!$H$5:$H$604,Lançamentos!$C$5:$C$604,Casos!$A$42)) | I69: =IF(Casos!$A$42="","",N(Casos!$F$42)) | J69: =IF(OR(Casos!$A$42="",D69="Interno"),"",I69-H69) | K69: =IF(OR(Casos!$A$42="",D69="Interno",I69=0),"",J69/I69) | L69: =IF(Casos!$A$42="","",IF(D69="Interno","Interno",IF(F69=0,"Sem horas",IF(H69>I69,"Consome mais do que paga",IF(AND(G69<>"",G69>1),"Estourou as horas",IF(AND(K69<>"",K69<0.2),"Margem baixa",IF(AND(G69<>"",G69>0.85),"Perto do limite","Saudável"))))))) | M69: =IF(OR(L69="Consome mais do que paga",L69="Margem baixa",L69="Estourou as horas"),IFERROR(H69/I69,9)+ROW()/1000000,0)
A70: =IF(Casos!$A$43="","",Casos!$A$43) | B70: =IF(Casos!$A$43="","",Casos!$B$43) | C70: =IF(Casos!$A$43="","",Casos!$D$43) | D70: =IF(Casos!$A$43="","",Casos!$E$43) | E70: =IF(Casos!$A$43="","",N(Casos!$G$43)) | F70: =IF(Casos!$A$43="","",N(Casos!$H$43)+SUMIFS(Lançamentos!$E$5:$E$604,Lançamentos!$C$5:$C$604,Casos!$A$43)) | G70: =IF(OR(Casos!$A$43="",E70=0),"",F70/E70) | H70: =IF(Casos!$A$43="","",N(Casos!$H$43)*Config!$B$23+SUMIFS(Lançamentos!$H$5:$H$604,Lançamentos!$C$5:$C$604,Casos!$A$43)) | I70: =IF(Casos!$A$43="","",N(Casos!$F$43)) | J70: =IF(OR(Casos!$A$43="",D70="Interno"),"",I70-H70) | K70: =IF(OR(Casos!$A$43="",D70="Interno",I70=0),"",J70/I70) | L70: =IF(Casos!$A$43="","",IF(D70="Interno","Interno",IF(F70=0,"Sem horas",IF(H70>I70,"Consome mais do que paga",IF(AND(G70<>"",G70>1),"Estourou as horas",IF(AND(K70<>"",K70<0.2),"Margem baixa",IF(AND(G70<>"",G70>0.85),"Perto do limite","Saudável"))))))) | M70: =IF(OR(L70="Consome mais do que paga",L70="Margem baixa",L70="Estourou as horas"),IFERROR(H70/I70,9)+ROW()/1000000,0)
A71: =IF(Casos!$A$44="","",Casos!$A$44) | B71: =IF(Casos!$A$44="","",Casos!$B$44) | C71: =IF(Casos!$A$44="","",Casos!$D$44) | D71: =IF(Casos!$A$44="","",Casos!$E$44) | E71: =IF(Casos!$A$44="","",N(Casos!$G$44)) | F71: =IF(Casos!$A$44="","",N(Casos!$H$44)+SUMIFS(Lançamentos!$E$5:$E$604,Lançamentos!$C$5:$C$604,Casos!$A$44)) | G71: =IF(OR(Casos!$A$44="",E71=0),"",F71/E71) | H71: =IF(Casos!$A$44="","",N(Casos!$H$44)*Config!$B$23+SUMIFS(Lançamentos!$H$5:$H$604,Lançamentos!$C$5:$C$604,Casos!$A$44)) | I71: =IF(Casos!$A$44="","",N(Casos!$F$44)) | J71: =IF(OR(Casos!$A$44="",D71="Interno"),"",I71-H71) | K71: =IF(OR(Casos!$A$44="",D71="Interno",I71=0),"",J71/I71) | L71: =IF(Casos!$A$44="","",IF(D71="Interno","Interno",IF(F71=0,"Sem horas",IF(H71>I71,"Consome mais do que paga",IF(AND(G71<>"",G71>1),"Estourou as horas",IF(AND(K71<>"",K71<0.2),"Margem baixa",IF(AND(G71<>"",G71>0.85),"Perto do limite","Saudável"))))))) | M71: =IF(OR(L71="Consome mais do que paga",L71="Margem baixa",L71="Estourou as horas"),IFERROR(H71/I71,9)+ROW()/1000000,0)
A72: =IF(Casos!$A$45="","",Casos!$A$45) | B72: =IF(Casos!$A$45="","",Casos!$B$45) | C72: =IF(Casos!$A$45="","",Casos!$D$45) | D72: =IF(Casos!$A$45="","",Casos!$E$45) | E72: =IF(Casos!$A$45="","",N(Casos!$G$45)) | F72: =IF(Casos!$A$45="","",N(Casos!$H$45)+SUMIFS(Lançamentos!$E$5:$E$604,Lançamentos!$C$5:$C$604,Casos!$A$45)) | G72: =IF(OR(Casos!$A$45="",E72=0),"",F72/E72) | H72: =IF(Casos!$A$45="","",N(Casos!$H$45)*Config!$B$23+SUMIFS(Lançamentos!$H$5:$H$604,Lançamentos!$C$5:$C$604,Casos!$A$45)) | I72: =IF(Casos!$A$45="","",N(Casos!$F$45)) | J72: =IF(OR(Casos!$A$45="",D72="Interno"),"",I72-H72) | K72: =IF(OR(Casos!$A$45="",D72="Interno",I72=0),"",J72/I72) | L72: =IF(Casos!$A$45="","",IF(D72="Interno","Interno",IF(F72=0,"Sem horas",IF(H72>I72,"Consome mais do que paga",IF(AND(G72<>"",G72>1),"Estourou as horas",IF(AND(K72<>"",K72<0.2),"Margem baixa",IF(AND(G72<>"",G72>0.85),"Perto do limite","Saudável"))))))) | M72: =IF(OR(L72="Consome mais do que paga",L72="Margem baixa",L72="Estourou as horas"),IFERROR(H72/I72,9)+ROW()/1000000,0)
A73: =IF(Casos!$A$46="","",Casos!$A$46) | B73: =IF(Casos!$A$46="","",Casos!$B$46) | C73: =IF(Casos!$A$46="","",Casos!$D$46) | D73: =IF(Casos!$A$46="","",Casos!$E$46) | E73: =IF(Casos!$A$46="","",N(Casos!$G$46)) | F73: =IF(Casos!$A$46="","",N(Casos!$H$46)+SUMIFS(Lançamentos!$E$5:$E$604,Lançamentos!$C$5:$C$604,Casos!$A$46)) | G73: =IF(OR(Casos!$A$46="",E73=0),"",F73/E73) | H73: =IF(Casos!$A$46="","",N(Casos!$H$46)*Config!$B$23+SUMIFS(Lançamentos!$H$5:$H$604,Lançamentos!$C$5:$C$604,Casos!$A$46)) | I73: =IF(Casos!$A$46="","",N(Casos!$F$46)) | J73: =IF(OR(Casos!$A$46="",D73="Interno"),"",I73-H73) | K73: =IF(OR(Casos!$A$46="",D73="Interno",I73=0),"",J73/I73) | L73: =IF(Casos!$A$46="","",IF(D73="Interno","Interno",IF(F73=0,"Sem horas",IF(H73>I73,"Consome mais do que paga",IF(AND(G73<>"",G73>1),"Estourou as horas",IF(AND(K73<>"",K73<0.2),"Margem baixa",IF(AND(G73<>"",G73>0.85),"Perto do limite","Saudável"))))))) | M73: =IF(OR(L73="Consome mais do que paga",L73="Margem baixa",L73="Estourou as horas"),IFERROR(H73/I73,9)+ROW()/1000000,0)
A74: =IF(Casos!$A$47="","",Casos!$A$47) | B74: =IF(Casos!$A$47="","",Casos!$B$47) | C74: =IF(Casos!$A$47="","",Casos!$D$47) | D74: =IF(Casos!$A$47="","",Casos!$E$47) | E74: =IF(Casos!$A$47="","",N(Casos!$G$47)) | F74: =IF(Casos!$A$47="","",N(Casos!$H$47)+SUMIFS(Lançamentos!$E$5:$E$604,Lançamentos!$C$5:$C$604,Casos!$A$47)) | G74: =IF(OR(Casos!$A$47="",E74=0),"",F74/E74) | H74: =IF(Casos!$A$47="","",N(Casos!$H$47)*Config!$B$23+SUMIFS(Lançamentos!$H$5:$H$604,Lançamentos!$C$5:$C$604,Casos!$A$47)) | I74: =IF(Casos!$A$47="","",N(Casos!$F$47)) | J74: =IF(OR(Casos!$A$47="",D74="Interno"),"",I74-H74) | K74: =IF(OR(Casos!$A$47="",D74="Interno",I74=0),"",J74/I74) | L74: =IF(Casos!$A$47="","",IF(D74="Interno","Interno",IF(F74=0,"Sem horas",IF(H74>I74,"Consome mais do que paga",IF(AND(G74<>"",G74>1),"Estourou as horas",IF(AND(K74<>"",K74<0.2),"Margem baixa",IF(AND(G74<>"",G74>0.85),"Perto do limite","Saudável"))))))) | M74: =IF(OR(L74="Consome mais do que paga",L74="Margem baixa",L74="Estourou as horas"),IFERROR(H74/I74,9)+ROW()/1000000,0)
A75: =IF(Casos!$A$48="","",Casos!$A$48) | B75: =IF(Casos!$A$48="","",Casos!$B$48) | C75: =IF(Casos!$A$48="","",Casos!$D$48) | D75: =IF(Casos!$A$48="","",Casos!$E$48) | E75: =IF(Casos!$A$48="","",N(Casos!$G$48)) | F75: =IF(Casos!$A$48="","",N(Casos!$H$48)+SUMIFS(Lançamentos!$E$5:$E$604,Lançamentos!$C$5:$C$604,Casos!$A$48)) | G75: =IF(OR(Casos!$A$48="",E75=0),"",F75/E75) | H75: =IF(Casos!$A$48="","",N(Casos!$H$48)*Config!$B$23+SUMIFS(Lançamentos!$H$5:$H$604,Lançamentos!$C$5:$C$604,Casos!$A$48)) | I75: =IF(Casos!$A$48="","",N(Casos!$F$48)) | J75: =IF(OR(Casos!$A$48="",D75="Interno"),"",I75-H75) | K75: =IF(OR(Casos!$A$48="",D75="Interno",I75=0),"",J75/I75) | L75: =IF(Casos!$A$48="","",IF(D75="Interno","Interno",IF(F75=0,"Sem horas",IF(H75>I75,"Consome mais do que paga",IF(AND(G75<>"",G75>1),"Estourou as horas",IF(AND(K75<>"",K75<0.2),"Margem baixa",IF(AND(G75<>"",G75>0.85),"Perto do limite","Saudável"))))))) | M75: =IF(OR(L75="Consome mais do que paga",L75="Margem baixa",L75="Estourou as horas"),IFERROR(H75/I75,9)+ROW()/1000000,0)
A76: =IF(Casos!$A$49="","",Casos!$A$49) | B76: =IF(Casos!$A$49="","",Casos!$B$49) | C76: =IF(Casos!$A$49="","",Casos!$D$49) | D76: =IF(Casos!$A$49="","",Casos!$E$49) | E76: =IF(Casos!$A$49="","",N(Casos!$G$49)) | F76: =IF(Casos!$A$49="","",N(Casos!$H$49)+SUMIFS(Lançamentos!$E$5:$E$604,Lançamentos!$C$5:$C$604,Casos!$A$49)) | G76: =IF(OR(Casos!$A$49="",E76=0),"",F76/E76) | H76: =IF(Casos!$A$49="","",N(Casos!$H$49)*Config!$B$23+SUMIFS(Lançamentos!$H$5:$H$604,Lançamentos!$C$5:$C$604,Casos!$A$49)) | I76: =IF(Casos!$A$49="","",N(Casos!$F$49)) | J76: =IF(OR(Casos!$A$49="",D76="Interno"),"",I76-H76) | K76: =IF(OR(Casos!$A$49="",D76="Interno",I76=0),"",J76/I76) | L76: =IF(Casos!$A$49="","",IF(D76="Interno","Interno",IF(F76=0,"Sem horas",IF(H76>I76,"Consome mais do que paga",IF(AND(G76<>"",G76>1),"Estourou as horas",IF(AND(K76<>"",K76<0.2),"Margem baixa",IF(AND(G76<>"",G76>0.85),"Perto do limite","Saudável"))))))) | M76: =IF(OR(L76="Consome mais do que paga",L76="Margem baixa",L76="Estourou as horas"),IFERROR(H76/I76,9)+ROW()/1000000,0)
A77: =IF(Casos!$A$50="","",Casos!$A$50) | B77: =IF(Casos!$A$50="","",Casos!$B$50) | C77: =IF(Casos!$A$50="","",Casos!$D$50) | D77: =IF(Casos!$A$50="","",Casos!$E$50) | E77: =IF(Casos!$A$50="","",N(Casos!$G$50)) | F77: =IF(Casos!$A$50="","",N(Casos!$H$50)+SUMIFS(Lançamentos!$E$5:$E$604,Lançamentos!$C$5:$C$604,Casos!$A$50)) | G77: =IF(OR(Casos!$A$50="",E77=0),"",F77/E77) | H77: =IF(Casos!$A$50="","",N(Casos!$H$50)*Config!$B$23+SUMIFS(Lançamentos!$H$5:$H$604,Lançamentos!$C$5:$C$604,Casos!$A$50)) | I77: =IF(Casos!$A$50="","",N(Casos!$F$50)) | J77: =IF(OR(Casos!$A$50="",D77="Interno"),"",I77-H77) | K77: =IF(OR(Casos!$A$50="",D77="Interno",I77=0),"",J77/I77) | L77: =IF(Casos!$A$50="","",IF(D77="Interno","Interno",IF(F77=0,"Sem horas",IF(H77>I77,"Consome mais do que paga",IF(AND(G77<>"",G77>1),"Estourou as horas",IF(AND(K77<>"",K77<0.2),"Margem baixa",IF(AND(G77<>"",G77>0.85),"Perto do limite","Saudável"))))))) | M77: =IF(OR(L77="Consome mais do que paga",L77="Margem baixa",L77="Estourou as horas"),IFERROR(H77/I77,9)+ROW()/1000000,0)
A78: =IF(Casos!$A$51="","",Casos!$A$51) | B78: =IF(Casos!$A$51="","",Casos!$B$51) | C78: =IF(Casos!$A$51="","",Casos!$D$51) | D78: =IF(Casos!$A$51="","",Casos!$E$51) | E78: =IF(Casos!$A$51="","",N(Casos!$G$51)) | F78: =IF(Casos!$A$51="","",N(Casos!$H$51)+SUMIFS(Lançamentos!$E$5:$E$604,Lançamentos!$C$5:$C$604,Casos!$A$51)) | G78: =IF(OR(Casos!$A$51="",E78=0),"",F78/E78) | H78: =IF(Casos!$A$51="","",N(Casos!$H$51)*Config!$B$23+SUMIFS(Lançamentos!$H$5:$H$604,Lançamentos!$C$5:$C$604,Casos!$A$51)) | I78: =IF(Casos!$A$51="","",N(Casos!$F$51)) | J78: =IF(OR(Casos!$A$51="",D78="Interno"),"",I78-H78) | K78: =IF(OR(Casos!$A$51="",D78="Interno",I78=0),"",J78/I78) | L78: =IF(Casos!$A$51="","",IF(D78="Interno","Interno",IF(F78=0,"Sem horas",IF(H78>I78,"Consome mais do que paga",IF(AND(G78<>"",G78>1),"Estourou as horas",IF(AND(K78<>"",K78<0.2),"Margem baixa",IF(AND(G78<>"",G78>0.85),"Perto do limite","Saudável"))))))) | M78: =IF(OR(L78="Consome mais do que paga",L78="Margem baixa",L78="Estourou as horas"),IFERROR(H78/I78,9)+ROW()/1000000,0)
A79: =IF(Casos!$A$52="","",Casos!$A$52) | B79: =IF(Casos!$A$52="","",Casos!$B$52) | C79: =IF(Casos!$A$52="","",Casos!$D$52) | D79: =IF(Casos!$A$52="","",Casos!$E$52) | E79: =IF(Casos!$A$52="","",N(Casos!$G$52)) | F79: =IF(Casos!$A$52="","",N(Casos!$H$52)+SUMIFS(Lançamentos!$E$5:$E$604,Lançamentos!$C$5:$C$604,Casos!$A$52)) | G79: =IF(OR(Casos!$A$52="",E79=0),"",F79/E79) | H79: =IF(Casos!$A$52="","",N(Casos!$H$52)*Config!$B$23+SUMIFS(Lançamentos!$H$5:$H$604,Lançamentos!$C$5:$C$604,Casos!$A$52)) | I79: =IF(Casos!$A$52="","",N(Casos!$F$52)) | J79: =IF(OR(Casos!$A$52="",D79="Interno"),"",I79-H79) | K79: =IF(OR(Casos!$A$52="",D79="Interno",I79=0),"",J79/I79) | L79: =IF(Casos!$A$52="","",IF(D79="Interno","Interno",IF(F79=0,"Sem horas",IF(H79>I79,"Consome mais do que paga",IF(AND(G79<>"",G79>1),"Estourou as horas",IF(AND(K79<>"",K79<0.2),"Margem baixa",IF(AND(G79<>"",G79>0.85),"Perto do limite","Saudável"))))))) | M79: =IF(OR(L79="Consome mais do que paga",L79="Margem baixa",L79="Estourou as horas"),IFERROR(H79/I79,9)+ROW()/1000000,0)
A80: =IF(Casos!$A$53="","",Casos!$A$53) | B80: =IF(Casos!$A$53="","",Casos!$B$53) | C80: =IF(Casos!$A$53="","",Casos!$D$53) | D80: =IF(Casos!$A$53="","",Casos!$E$53) | E80: =IF(Casos!$A$53="","",N(Casos!$G$53)) | F80: =IF(Casos!$A$53="","",N(Casos!$H$53)+SUMIFS(Lançamentos!$E$5:$E$604,Lançamentos!$C$5:$C$604,Casos!$A$53)) | G80: =IF(OR(Casos!$A$53="",E80=0),"",F80/E80) | H80: =IF(Casos!$A$53="","",N(Casos!$H$53)*Config!$B$23+SUMIFS(Lançamentos!$H$5:$H$604,Lançamentos!$C$5:$C$604,Casos!$A$53)) | I80: =IF(Casos!$A$53="","",N(Casos!$F$53)) | J80: =IF(OR(Casos!$A$53="",D80="Interno"),"",I80-H80) | K80: =IF(OR(Casos!$A$53="",D80="Interno",I80=0),"",J80/I80) | L80: =IF(Casos!$A$53="","",IF(D80="Interno","Interno",IF(F80=0,"Sem horas",IF(H80>I80,"Consome mais do que paga",IF(AND(G80<>"",G80>1),"Estourou as horas",IF(AND(K80<>"",K80<0.2),"Margem baixa",IF(AND(G80<>"",G80>0.85),"Perto do limite","Saudável"))))))) | M80: =IF(OR(L80="Consome mais do que paga",L80="Margem baixa",L80="Estourou as horas"),IFERROR(H80/I80,9)+ROW()/1000000,0)
A81: =IF(Casos!$A$54="","",Casos!$A$54) | B81: =IF(Casos!$A$54="","",Casos!$B$54) | C81: =IF(Casos!$A$54="","",Casos!$D$54) | D81: =IF(Casos!$A$54="","",Casos!$E$54) | E81: =IF(Casos!$A$54="","",N(Casos!$G$54)) | F81: =IF(Casos!$A$54="","",N(Casos!$H$54)+SUMIFS(Lançamentos!$E$5:$E$604,Lançamentos!$C$5:$C$604,Casos!$A$54)) | G81: =IF(OR(Casos!$A$54="",E81=0),"",F81/E81) | H81: =IF(Casos!$A$54="","",N(Casos!$H$54)*Config!$B$23+SUMIFS(Lançamentos!$H$5:$H$604,Lançamentos!$C$5:$C$604,Casos!$A$54)) | I81: =IF(Casos!$A$54="","",N(Casos!$F$54)) | J81: =IF(OR(Casos!$A$54="",D81="Interno"),"",I81-H81) | K81: =IF(OR(Casos!$A$54="",D81="Interno",I81=0),"",J81/I81) | L81: =IF(Casos!$A$54="","",IF(D81="Interno","Interno",IF(F81=0,"Sem horas",IF(H81>I81,"Consome mais do que paga",IF(AND(G81<>"",G81>1),"Estourou as horas",IF(AND(K81<>"",K81<0.2),"Margem baixa",IF(AND(G81<>"",G81>0.85),"Perto do limite","Saudável"))))))) | M81: =IF(OR(L81="Consome mais do que paga",L81="Margem baixa",L81="Estourou as horas"),IFERROR(H81/I81,9)+ROW()/1000000,0)
A82: =IF(Casos!$A$55="","",Casos!$A$55) | B82: =IF(Casos!$A$55="","",Casos!$B$55) | C82: =IF(Casos!$A$55="","",Casos!$D$55) | D82: =IF(Casos!$A$55="","",Casos!$E$55) | E82: =IF(Casos!$A$55="","",N(Casos!$G$55)) | F82: =IF(Casos!$A$55="","",N(Casos!$H$55)+SUMIFS(Lançamentos!$E$5:$E$604,Lançamentos!$C$5:$C$604,Casos!$A$55)) | G82: =IF(OR(Casos!$A$55="",E82=0),"",F82/E82) | H82: =IF(Casos!$A$55="","",N(Casos!$H$55)*Config!$B$23+SUMIFS(Lançamentos!$H$5:$H$604,Lançamentos!$C$5:$C$604,Casos!$A$55)) | I82: =IF(Casos!$A$55="","",N(Casos!$F$55)) | J82: =IF(OR(Casos!$A$55="",D82="Interno"),"",I82-H82) | K82: =IF(OR(Casos!$A$55="",D82="Interno",I82=0),"",J82/I82) | L82: =IF(Casos!$A$55="","",IF(D82="Interno","Interno",IF(F82=0,"Sem horas",IF(H82>I82,"Consome mais do que paga",IF(AND(G82<>"",G82>1),"Estourou as horas",IF(AND(K82<>"",K82<0.2),"Margem baixa",IF(AND(G82<>"",G82>0.85),"Perto do limite","Saudável"))))))) | M82: =IF(OR(L82="Consome mais do que paga",L82="Margem baixa",L82="Estourou as horas"),IFERROR(H82/I82,9)+ROW()/1000000,0)
A83: =IF(Casos!$A$56="","",Casos!$A$56) | B83: =IF(Casos!$A$56="","",Casos!$B$56) | C83: =IF(Casos!$A$56="","",Casos!$D$56) | D83: =IF(Casos!$A$56="","",Casos!$E$56) | E83: =IF(Casos!$A$56="","",N(Casos!$G$56)) | F83: =IF(Casos!$A$56="","",N(Casos!$H$56)+SUMIFS(Lançamentos!$E$5:$E$604,Lançamentos!$C$5:$C$604,Casos!$A$56)) | G83: =IF(OR(Casos!$A$56="",E83=0),"",F83/E83) | H83: =IF(Casos!$A$56="","",N(Casos!$H$56)*Config!$B$23+SUMIFS(Lançamentos!$H$5:$H$604,Lançamentos!$C$5:$C$604,Casos!$A$56)) | I83: =IF(Casos!$A$56="","",N(Casos!$F$56)) | J83: =IF(OR(Casos!$A$56="",D83="Interno"),"",I83-H83) | K83: =IF(OR(Casos!$A$56="",D83="Interno",I83=0),"",J83/I83) | L83: =IF(Casos!$A$56="","",IF(D83="Interno","Interno",IF(F83=0,"Sem horas",IF(H83>I83,"Consome mais do que paga",IF(AND(G83<>"",G83>1),"Estourou as horas",IF(AND(K83<>"",K83<0.2),"Margem baixa",IF(AND(G83<>"",G83>0.85),"Perto do limite","Saudável"))))))) | M83: =IF(OR(L83="Consome mais do que paga",L83="Margem baixa",L83="Estourou as horas"),IFERROR(H83/I83,9)+ROW()/1000000,0)
A84: =IF(Casos!$A$57="","",Casos!$A$57) | B84: =IF(Casos!$A$57="","",Casos!$B$57) | C84: =IF(Casos!$A$57="","",Casos!$D$57) | D84: =IF(Casos!$A$57="","",Casos!$E$57) | E84: =IF(Casos!$A$57="","",N(Casos!$G$57)) | F84: =IF(Casos!$A$57="","",N(Casos!$H$57)+SUMIFS(Lançamentos!$E$5:$E$604,Lançamentos!$C$5:$C$604,Casos!$A$57)) | G84: =IF(OR(Casos!$A$57="",E84=0),"",F84/E84) | H84: =IF(Casos!$A$57="","",N(Casos!$H$57)*Config!$B$23+SUMIFS(Lançamentos!$H$5:$H$604,Lançamentos!$C$5:$C$604,Casos!$A$57)) | I84: =IF(Casos!$A$57="","",N(Casos!$F$57)) | J84: =IF(OR(Casos!$A$57="",D84="Interno"),"",I84-H84) | K84: =IF(OR(Casos!$A$57="",D84="Interno",I84=0),"",J84/I84) | L84: =IF(Casos!$A$57="","",IF(D84="Interno","Interno",IF(F84=0,"Sem horas",IF(H84>I84,"Consome mais do que paga",IF(AND(G84<>"",G84>1),"Estourou as horas",IF(AND(K84<>"",K84<0.2),"Margem baixa",IF(AND(G84<>"",G84>0.85),"Perto do limite","Saudável"))))))) | M84: =IF(OR(L84="Consome mais do que paga",L84="Margem baixa",L84="Estourou as horas"),IFERROR(H84/I84,9)+ROW()/1000000,0)
A85: =IF(Casos!$A$58="","",Casos!$A$58) | B85: =IF(Casos!$A$58="","",Casos!$B$58) | C85: =IF(Casos!$A$58="","",Casos!$D$58) | D85: =IF(Casos!$A$58="","",Casos!$E$58) | E85: =IF(Casos!$A$58="","",N(Casos!$G$58)) | F85: =IF(Casos!$A$58="","",N(Casos!$H$58)+SUMIFS(Lançamentos!$E$5:$E$604,Lançamentos!$C$5:$C$604,Casos!$A$58)) | G85: =IF(OR(Casos!$A$58="",E85=0),"",F85/E85) | H85: =IF(Casos!$A$58="","",N(Casos!$H$58)*Config!$B$23+SUMIFS(Lançamentos!$H$5:$H$604,Lançamentos!$C$5:$C$604,Casos!$A$58)) | I85: =IF(Casos!$A$58="","",N(Casos!$F$58)) | J85: =IF(OR(Casos!$A$58="",D85="Interno"),"",I85-H85) | K85: =IF(OR(Casos!$A$58="",D85="Interno",I85=0),"",J85/I85) | L85: =IF(Casos!$A$58="","",IF(D85="Interno","Interno",IF(F85=0,"Sem horas",IF(H85>I85,"Consome mais do que paga",IF(AND(G85<>"",G85>1),"Estourou as horas",IF(AND(K85<>"",K85<0.2),"Margem baixa",IF(AND(G85<>"",G85>0.85),"Perto do limite","Saudável"))))))) | M85: =IF(OR(L85="Consome mais do que paga",L85="Margem baixa",L85="Estourou as horas"),IFERROR(H85/I85,9)+ROW()/1000000,0)
A86: =IF(Casos!$A$59="","",Casos!$A$59) | B86: =IF(Casos!$A$59="","",Casos!$B$59) | C86: =IF(Casos!$A$59="","",Casos!$D$59) | D86: =IF(Casos!$A$59="","",Casos!$E$59) | E86: =IF(Casos!$A$59="","",N(Casos!$G$59)) | F86: =IF(Casos!$A$59="","",N(Casos!$H$59)+SUMIFS(Lançamentos!$E$5:$E$604,Lançamentos!$C$5:$C$604,Casos!$A$59)) | G86: =IF(OR(Casos!$A$59="",E86=0),"",F86/E86) | H86: =IF(Casos!$A$59="","",N(Casos!$H$59)*Config!$B$23+SUMIFS(Lançamentos!$H$5:$H$604,Lançamentos!$C$5:$C$604,Casos!$A$59)) | I86: =IF(Casos!$A$59="","",N(Casos!$F$59)) | J86: =IF(OR(Casos!$A$59="",D86="Interno"),"",I86-H86) | K86: =IF(OR(Casos!$A$59="",D86="Interno",I86=0),"",J86/I86) | L86: =IF(Casos!$A$59="","",IF(D86="Interno","Interno",IF(F86=0,"Sem horas",IF(H86>I86,"Consome mais do que paga",IF(AND(G86<>"",G86>1),"Estourou as horas",IF(AND(K86<>"",K86<0.2),"Margem baixa",IF(AND(G86<>"",G86>0.85),"Perto do limite","Saudável"))))))) | M86: =IF(OR(L86="Consome mais do que paga",L86="Margem baixa",L86="Estourou as horas"),IFERROR(H86/I86,9)+ROW()/1000000,0)
A87: =IF(Casos!$A$60="","",Casos!$A$60) | B87: =IF(Casos!$A$60="","",Casos!$B$60) | C87: =IF(Casos!$A$60="","",Casos!$D$60) | D87: =IF(Casos!$A$60="","",Casos!$E$60) | E87: =IF(Casos!$A$60="","",N(Casos!$G$60)) | F87: =IF(Casos!$A$60="","",N(Casos!$H$60)+SUMIFS(Lançamentos!$E$5:$E$604,Lançamentos!$C$5:$C$604,Casos!$A$60)) | G87: =IF(OR(Casos!$A$60="",E87=0),"",F87/E87) | H87: =IF(Casos!$A$60="","",N(Casos!$H$60)*Config!$B$23+SUMIFS(Lançamentos!$H$5:$H$604,Lançamentos!$C$5:$C$604,Casos!$A$60)) | I87: =IF(Casos!$A$60="","",N(Casos!$F$60)) | J87: =IF(OR(Casos!$A$60="",D87="Interno"),"",I87-H87) | K87: =IF(OR(Casos!$A$60="",D87="Interno",I87=0),"",J87/I87) | L87: =IF(Casos!$A$60="","",IF(D87="Interno","Interno",IF(F87=0,"Sem horas",IF(H87>I87,"Consome mais do que paga",IF(AND(G87<>"",G87>1),"Estourou as horas",IF(AND(K87<>"",K87<0.2),"Margem baixa",IF(AND(G87<>"",G87>0.85),"Perto do limite","Saudável"))))))) | M87: =IF(OR(L87="Consome mais do que paga",L87="Margem baixa",L87="Estourou as horas"),IFERROR(H87/I87,9)+ROW()/1000000,0)
A88: =IF(Casos!$A$61="","",Casos!$A$61) | B88: =IF(Casos!$A$61="","",Casos!$B$61) | C88: =IF(Casos!$A$61="","",Casos!$D$61) | D88: =IF(Casos!$A$61="","",Casos!$E$61) | E88: =IF(Casos!$A$61="","",N(Casos!$G$61)) | F88: =IF(Casos!$A$61="","",N(Casos!$H$61)+SUMIFS(Lançamentos!$E$5:$E$604,Lançamentos!$C$5:$C$604,Casos!$A$61)) | G88: =IF(OR(Casos!$A$61="",E88=0),"",F88/E88) | H88: =IF(Casos!$A$61="","",N(Casos!$H$61)*Config!$B$23+SUMIFS(Lançamentos!$H$5:$H$604,Lançamentos!$C$5:$C$604,Casos!$A$61)) | I88: =IF(Casos!$A$61="","",N(Casos!$F$61)) | J88: =IF(OR(Casos!$A$61="",D88="Interno"),"",I88-H88) | K88: =IF(OR(Casos!$A$61="",D88="Interno",I88=0),"",J88/I88) | L88: =IF(Casos!$A$61="","",IF(D88="Interno","Interno",IF(F88=0,"Sem horas",IF(H88>I88,"Consome mais do que paga",IF(AND(G88<>"",G88>1),"Estourou as horas",IF(AND(K88<>"",K88<0.2),"Margem baixa",IF(AND(G88<>"",G88>0.85),"Perto do limite","Saudável"))))))) | M88: =IF(OR(L88="Consome mais do que paga",L88="Margem baixa",L88="Estourou as horas"),IFERROR(H88/I88,9)+ROW()/1000000,0)
A89: =IF(Casos!$A$62="","",Casos!$A$62) | B89: =IF(Casos!$A$62="","",Casos!$B$62) | C89: =IF(Casos!$A$62="","",Casos!$D$62) | D89: =IF(Casos!$A$62="","",Casos!$E$62) | E89: =IF(Casos!$A$62="","",N(Casos!$G$62)) | F89: =IF(Casos!$A$62="","",N(Casos!$H$62)+SUMIFS(Lançamentos!$E$5:$E$604,Lançamentos!$C$5:$C$604,Casos!$A$62)) | G89: =IF(OR(Casos!$A$62="",E89=0),"",F89/E89) | H89: =IF(Casos!$A$62="","",N(Casos!$H$62)*Config!$B$23+SUMIFS(Lançamentos!$H$5:$H$604,Lançamentos!$C$5:$C$604,Casos!$A$62)) | I89: =IF(Casos!$A$62="","",N(Casos!$F$62)) | J89: =IF(OR(Casos!$A$62="",D89="Interno"),"",I89-H89) | K89: =IF(OR(Casos!$A$62="",D89="Interno",I89=0),"",J89/I89) | L89: =IF(Casos!$A$62="","",IF(D89="Interno","Interno",IF(F89=0,"Sem horas",IF(H89>I89,"Consome mais do que paga",IF(AND(G89<>"",G89>1),"Estourou as horas",IF(AND(K89<>"",K89<0.2),"Margem baixa",IF(AND(G89<>"",G89>0.85),"Perto do limite","Saudável"))))))) | M89: =IF(OR(L89="Consome mais do que paga",L89="Margem baixa",L89="Estourou as horas"),IFERROR(H89/I89,9)+ROW()/1000000,0)
A90: =IF(Casos!$A$63="","",Casos!$A$63) | B90: =IF(Casos!$A$63="","",Casos!$B$63) | C90: =IF(Casos!$A$63="","",Casos!$D$63) | D90: =IF(Casos!$A$63="","",Casos!$E$63) | E90: =IF(Casos!$A$63="","",N(Casos!$G$63)) | F90: =IF(Casos!$A$63="","",N(Casos!$H$63)+SUMIFS(Lançamentos!$E$5:$E$604,Lançamentos!$C$5:$C$604,Casos!$A$63)) | G90: =IF(OR(Casos!$A$63="",E90=0),"",F90/E90) | H90: =IF(Casos!$A$63="","",N(Casos!$H$63)*Config!$B$23+SUMIFS(Lançamentos!$H$5:$H$604,Lançamentos!$C$5:$C$604,Casos!$A$63)) | I90: =IF(Casos!$A$63="","",N(Casos!$F$63)) | J90: =IF(OR(Casos!$A$63="",D90="Interno"),"",I90-H90) | K90: =IF(OR(Casos!$A$63="",D90="Interno",I90=0),"",J90/I90) | L90: =IF(Casos!$A$63="","",IF(D90="Interno","Interno",IF(F90=0,"Sem horas",IF(H90>I90,"Consome mais do que paga",IF(AND(G90<>"",G90>1),"Estourou as horas",IF(AND(K90<>"",K90<0.2),"Margem baixa",IF(AND(G90<>"",G90>0.85),"Perto do limite","Saudável"))))))) | M90: =IF(OR(L90="Consome mais do que paga",L90="Margem baixa",L90="Estourou as horas"),IFERROR(H90/I90,9)+ROW()/1000000,0)
A91: =IF(Casos!$A$64="","",Casos!$A$64) | B91: =IF(Casos!$A$64="","",Casos!$B$64) | C91: =IF(Casos!$A$64="","",Casos!$D$64) | D91: =IF(Casos!$A$64="","",Casos!$E$64) | E91: =IF(Casos!$A$64="","",N(Casos!$G$64)) | F91: =IF(Casos!$A$64="","",N(Casos!$H$64)+SUMIFS(Lançamentos!$E$5:$E$604,Lançamentos!$C$5:$C$604,Casos!$A$64)) | G91: =IF(OR(Casos!$A$64="",E91=0),"",F91/E91) | H91: =IF(Casos!$A$64="","",N(Casos!$H$64)*Config!$B$23+SUMIFS(Lançamentos!$H$5:$H$604,Lançamentos!$C$5:$C$604,Casos!$A$64)) | I91: =IF(Casos!$A$64="","",N(Casos!$F$64)) | J91: =IF(OR(Casos!$A$64="",D91="Interno"),"",I91-H91) | K91: =IF(OR(Casos!$A$64="",D91="Interno",I91=0),"",J91/I91) | L91: =IF(Casos!$A$64="","",IF(D91="Interno","Interno",IF(F91=0,"Sem horas",IF(H91>I91,"Consome mais do que paga",IF(AND(G91<>"",G91>1),"Estourou as horas",IF(AND(K91<>"",K91<0.2),"Margem baixa",IF(AND(G91<>"",G91>0.85),"Perto do limite","Saudável"))))))) | M91: =IF(OR(L91="Consome mais do que paga",L91="Margem baixa",L91="Estourou as horas"),IFERROR(H91/I91,9)+ROW()/1000000,0)
A93: Semáforo: Consome mais do que paga = custo das horas maior que o contratado. Estourou as horas = gastas acima das estimadas. Margem baixa = menos de 20%. Perto do limite = mais de 85% das horas estimadas. Em caso por êxito, o contratado é o honorário esperado no fim.

Sheet Config
A1: Configurações
A2: Células amarelas: você preenche. Custo-hora de cada pessoa = custo mensal ÷ horas faturáveis + rateio dos custos fixos por hora.
A4: Escritório | B4: Ferraz & Lima Advocacia (exemplo fictício) | H4: Meses
A5: Ano | B5: 2026 | H5: Janeiro
A6: Mês do painel | B6: Agosto | H6: Fevereiro
A7: Número do mês | B7: =MATCH(B6,$H$5:$H$16,0) | H7: Março
A8: Custos fixos mensais, sem a equipe (R$) | B8: 5100 | C8: Copie da planilha 05 (Custo-hora): aluguel, contador, sistemas, telefone, anuidades, marketing e outros. Sem pró-labore e sem salários. | H8: Abril
H9: Maio
A10: Pessoas (até 10) | H10: Junho
A11: Pessoa | B11: Custo mensal (R$) | C11: Horas faturáveis por mês (meta) | D11: Custo-hora (R$) | F11: Atividades (até 12) | H11: Julho
A12: Marina Ferraz | B12: 6000 | C12: 110 | D12: =IF(OR(A12="",C12=0,C12=""),"",B12/C12+IFERROR($B$8/SUM($C$12:$C$21),0)) | F12: Reunião com cliente | H12: Agosto
A13: Rafael Lima | B13: 6000 | C13: 110 | D13: =IF(OR(A13="",C13=0,C13=""),"",B13/C13+IFERROR($B$8/SUM($C$12:$C$21),0)) | F13: Audiência | H13: Setembro
A14: Júlia Prado | B14: 1400 | C14: 60 | D14: =IF(OR(A14="",C14=0,C14=""),"",B14/C14+IFERROR($B$8/SUM($C$12:$C$21),0)) | F14: Elaboração de documento | H14: Outubro
D15: =IF(OR(A15="",C15=0,C15=""),"",B15/C15+IFERROR($B$8/SUM($C$12:$C$21),0)) | F15: Pesquisa e estudo do caso | H15: Novembro
D16: =IF(OR(A16="",C16=0,C16=""),"",B16/C16+IFERROR($B$8/SUM($C$12:$C$21),0)) | F16: Análise de documentos | H16: Dezembro
D17: =IF(OR(A17="",C17=0,C17=""),"",B17/C17+IFERROR($B$8/SUM($C$12:$C$21),0)) | F17: Atendimento por telefone ou WhatsApp
D18: =IF(OR(A18="",C18=0,C18=""),"",B18/C18+IFERROR($B$8/SUM($C$12:$C$21),0)) | F18: Diligência externa
D19: =IF(OR(A19="",C19=0,C19=""),"",B19/C19+IFERROR($B$8/SUM($C$12:$C$21),0)) | F19: Deslocamento
D20: =IF(OR(A20="",C20=0,C20=""),"",B20/C20+IFERROR($B$8/SUM($C$12:$C$21),0)) | F20: Administrativo do caso
D21: =IF(OR(A21="",C21=0,C21=""),"",B21/C21+IFERROR($B$8/SUM($C$12:$C$21),0)) | F21: Gestão do escritório
F22: Captação e propostas
A23: Custo-hora médio do escritório (R$) | B23: =IFERROR(($B$8+SUMIFS($B$12:$B$21,$A$12:$A$21,"<>"))/SUM($C$12:$C$21),0)
F24: Preencha de cima para baixo, sem pular linha.
A26: Custo mensal: pró-labore do sócio, ou salário mais encargos, ou a bolsa. Horas faturáveis por mês: quantas horas a pessoa consegue dedicar a casos (110 para um sócio que também administra; 60 para estagiário). O custo-hora médio vale para as horas lançadas antes de começar a usar esta planilha.

Sheet Casos
A1: Casos (entrada)
A2: Copie daqui da planilha 13 (Carteira): número, cliente, responsável, modalidade, valor e horas estimadas. Trabalho interno entra como modalidade Interno.
A4: Número do processo ou referência | B4: Cliente | C4: Área | D4: Responsável | E4: Modalidade | F4: Valor contratado (R$) | G4: Horas estimadas | H4: Horas gastas antes de usar esta planilha | I4: Fase
A5: 9236009-85.2026.8.26.0452 | B5: Padaria do Sol Ltda | C5: Empresarial | D5: Marina Ferraz | E5: Êxito | F5: 14400 | G5: 63 | H5: 36.5 | I5: Inicial
A6: 9225646-96.2026.8.26.0322 | B6: Ana Beatriz Moreira | C6: Trabalhista | D6: Rafael Lima | E6: Fixo | F6: 8000 | G6: 42 | H6: 24 | I6: Sentença
A7: 6710873-21.2025.8.26.0571 | B7: Construtora Horizonte | C7: Cível | D7: Marina Ferraz | E7: Misto | F7: 8100 | G7: 45 | H7: 48.5 | I7: Sentença
A8: 8735513-64.2025.8.26.0093 | B8: Carlos Eduardo Nunes | C8: Previdenciário | D8: Rafael Lima | E8: Êxito | F8: 5700 | G8: 25 | H8: 22.5 | I8: Recurso
A9: 9802211-43.2025.8.26.0431 | B9: Loja Verde Comércio | C9: Empresarial | D9: Marina Ferraz | E9: Misto | F9: 19600 | G9: 91 | H9: 84.5 | I9: Acordo
A10: 9778116-95.2026.8.26.0106 | B10: Fernanda Castro | C10: Família | D10: Marina Ferraz | E10: Fixo | F10: 9000 | G10: 38 | H10: 32.5 | I10: Encerrado
A11: 8875326-79.2026.8.26.0258 | B11: Bistrô 42 | C11: Trabalhista | D11: Rafael Lima | E11: Misto | F11: 4600 | G11: 24 | H11: 15.5 | I11: Acordo
A12: 4397912-47.2025.8.26.0276 | B12: Roberto Almeida | C12: Cível | D12: Marina Ferraz | E12: Êxito | F12: 11300 | G12: 60 | H12: 57 | I12: Acordo
A13: 4352718-43.2025.8.26.0498 | B13: Clínica Bem-Estar | C13: Empresarial | D13: Marina Ferraz | E13: Fixo | F13: 9300 | G13: 54 | H13: 8 | I13: Consultivo
A14: 2650441-66.2026.8.26.0528 | B14: Marcos Vinícius Teles | C14: Previdenciário | D14: Rafael Lima | E14: Misto | F14: 7800 | G14: 41 | H14: 3.5 | I14: Encerrado
A15: 5470559-73.2026.8.26.0380 | B15: Transportadora Rota Sul | C15: Trabalhista | D15: Rafael Lima | E15: Misto | F15: 10200 | G15: 54 | H15: 41.5 | I15: Recurso
A16: 8570388-84.2025.8.26.0560 | B16: Patrícia Gomes | C16: Família | D16: Marina Ferraz | E16: Hora | F16: 10400 | G16: 46 | H16: 26.5 | I16: Inicial
... A42: 7598076-58.2025.8.26.0552 | B42: Ana Beatriz Moreira | C42: Família | D42: Marina Ferraz | E42: Hora | F42: 11300 | G42: 63 | H42: 14.5 | I42: Encerrado
A43: Gestão do escritório | B43: Escritório (sem cliente) | C43: — | D43: Marina Ferraz | E43: Interno | F43: 0 | G43: 0 | H43: 0
A44: Captação e propostas | B44: Escritório (sem cliente) | C44: — | D44: Marina Ferraz | E44: Interno | F44: 0 | G44: 0 | H44: 0
A206: Horas gastas antes: se o caso já vinha de antes, anote quantas horas ele consumiu até o dia em que você começou a lançar aqui (uma estimativa honesta serve). Elas entram no total do caso pelo custo-hora médio.

Sheet Lançamentos
A1: Lançamentos de horas
A2: Uma linha por pessoa, por dia, por caso. Pessoa, caso e atividade vêm de listas; cliente, custo e mês são calculados.
A4: Data | B4: Pessoa | C4: Caso | D4: Atividade | E4: Horas | F4: Faturável? | G4: Cliente | H4: Custo (R$) | I4: Mês | J4: Ano
A5: 46204 | B5: Rafael Lima | C5: 9236009-85.2026.8.26.0452 | D5: Análise de documentos | E5: 3 | F5: Sim | G5: =IF(C5="","",IFERROR(INDEX(Casos!$B$5:$B$204,MATCH(C5,Casos!$A$5:$A$204,0)),"")) | H5: =IF(OR(B5="",E5=""),"",E5*IFERROR(INDEX(Config!$D$12:$D$21,MATCH(B5,Config!$A$12:$A$21,0)),Config!$B$23)) | I5: =IF(A5="","",MONTH(A5)) | J5: =IF(A5="","",YEAR(A5))
A6: 46205 | B6: Júlia Prado | C6: 9717671-36.2026.8.26.0445 | D6: Diligência externa | E6: 1.5 | F6: Sim | G6: =IF(C6="","",IFERROR(INDEX(Casos!$B$5:$B$204,MATCH(C6,Casos!$A$5:$A$204,0)),"")) | H6: =IF(OR(B6="",E6=""),"",E6*IFERROR(INDEX(Config!$D$12:$D$21,MATCH(B6,Config!$A$12:$A$21,0)),Config!$B$23)) | I6: =IF(A6="","",MONTH(A6)) | J6: =IF(A6="","",YEAR(A6))
A7: 46205 | B7: Marina Ferraz | C7: 6545676-47.2025.8.26.0126 | D7: Diligência externa | E7: 1.5 | F7: Sim | G7: =IF(C7="","",IFERROR(INDEX(Casos!$B$5:$B$204,MATCH(C7,Casos!$A$5:$A$204,0)),"")) | H7: =IF(OR(B7="",E7=""),"",E7*IFERROR(INDEX(Config!$D$12:$D$21,MATCH(B7,Config!$A$12:$A$21,0)),Config!$B$23)) | I7: =IF(A7="","",MONTH(A7)) | J7: =IF(A7="","",YEAR(A7))
A8: 46205 | B8: Rafael Lima | C8: 3930894-43.2025.8.26.0476 | D8: Audiência | E8: 2.5 | F8: Sim | G8: =IF(C8="","",IFERROR(INDEX(Casos!$B$5:$B$204,MATCH(C8,Casos!$A$5:$A$204,0)),"")) | H8: =IF(OR(B8="",E8=""),"",E8*IFERROR(INDEX(Config!$D$12:$D$21,MATCH(B8,Config!$A$12:$A$21,0)),Config!$B$23)) | I8: =IF(A8="","",MONTH(A8)) | J8: =IF(A8="","",YEAR(A8))
A9: 46206 | B9: Júlia Prado | C9: 9236009-85.2026.8.26.0452 | D9: Análise de documentos | E9: 2.5 | F9: Sim | G9: =IF(C9="","",IFERROR(INDEX(Casos!$B$5:$B$204,MATCH(C9,Casos!$A$5:$A$204,0)),"")) | H9: =IF(OR(B9="",E9=""),"",E9*IFERROR(INDEX(Config!$D$12:$D$21,MATCH(B9,Config!$A$12:$A$21,0)),Config!$B$23)) | I9: =IF(A9="","",MONTH(A9)) | J9: =IF(A9="","",YEAR(A9))
A10: 46206 | B10: Júlia Prado | C10: 9236009-85.2026.8.26.0452 | D10: Análise de documentos | E10: 3 | F10: Sim | G10: =IF(C10="","",IFERROR(INDEX(Casos!$B$5:$B$204,MATCH(C10,Casos!$A$5:$A$204,0)),"")) | H10: =IF(OR(B10="",E10=""),"",E10*IFERROR(INDEX(Config!$D$12:$D$21,MATCH(B10,Config!$A$12:$A$21,0)),Config!$B$23)) | I10: =IF(A10="","",MONTH(A10)) | J10: =IF(A10="","",YEAR(A10))
A11: 46206 | B11: Rafael Lima | C11: 5470559-73.2026.8.26.0380 | D11: Deslocamento | E11: 3 | F11: Não | G11: =IF(C11="","",IFERROR(INDEX(Casos!$B$5:$B$204,MATCH(C11,Casos!$A$5:$A$204,0)),"")) | H11: =IF(OR(B11="",E11=""),"",E11*IFERROR(INDEX(Config!$D$12:$D$21,MATCH(B11,Config!$A$12:$A$21,0)),Config!$B$23)) | I11: =IF(A11="","",MONTH(A11)) | J11: =IF(A11="","",YEAR(A11))
A12: 46209 | B12: Marina Ferraz | C12: 7598076-58.2025.8.26.0552 | D12: Administrativo do caso | E12: 0.5 | F12: Sim | G12: =IF(C12="","",IFERROR(INDEX(Casos!$B$5:$B$204,MATCH(C12,Casos!$A$5:$A$204,0)),"")) | H12: =IF(OR(B12="",E12=""),"",E12*IFERROR(INDEX(Config!$D$12:$D$21,MATCH(B12,Config!$A$12:$A$21,0)),Config!$B$23)) | I12: =IF(A12="","",MONTH(A12)) | J12: =IF(A12="","",YEAR(A12))
A13: 46209 | B13: Rafael Lima | C13: 9225646-96.2026.8.26.0322 | D13: Diligência externa | E13: 2 | F13: Sim | G13: =IF(C13="","",IFERROR(INDEX(Casos!$B$5:$B$204,MATCH(C13,Casos!$A$5:$A$204,0)),"")) | H13: =IF(OR(B13="",E13=""),"",E13*IFERROR(INDEX(Config!$D$12:$D$21,MATCH(B13,Config!$A$12:$A$21,0)),Config!$B$23)) | I13: =IF(A13="","",MONTH(A13)) | J13: =IF(A13="","",YEAR(A13))
A14: 46209 | B14: Rafael Lima | C14: Gestão do escritório | D14: Gestão do escritório | E14: 2.5 | F14: Não | G14: =IF(C14="","",IFERROR(INDEX(Casos!$B$5:$B$204,MATCH(C14,Casos!$A$5:$A$204,0)),"")) | H14: =IF(OR(B14="",E14=""),"",E14*IFERROR(INDEX(Config!$D$12:$D$21,MATCH(B14,Config!$A$12:$A$21,0)),Config!$B$23)) | I14: =IF(A14="","",MONTH(A14)) | J14: =IF(A14="","",YEAR(A14))
A15: 46210 | B15: Júlia Prado | C15: 8986364-51.2026.8.26.0700 | D15: Elaboração de documento | E15: 3.5 | F15: Sim | G15: =IF(C15="","",IFERROR(INDEX(Casos!$B$5:$B$204,MATCH(C15,Casos!$A$5:$A$204,0)),"")) | H15: =IF(OR(B15="",E15=""),"",E15*IFERROR(INDEX(Config!$D$12:$D$21,MATCH(B15,Config!$A$12:$A$21,0)),Config!$B$23)) | I15: =IF(A15="","",MONTH(A15)) | J15: =IF(A15="","",YEAR(A15))
A16: 46210 | B16: Marina Ferraz | C16: 8986364-51.2026.8.26.0700 | D16: Elaboração de documento | E16: 2.5 | F16: Sim | G16: =IF(C16="","",IFERROR(INDEX(Casos!$B$5:$B$204,MATCH(C16,Casos!$A$5:$A$204,0)),"")) | H16: =IF(OR(B16="",E16=""),"",E16*IFERROR(INDEX(Config!$D$12:$D$21,MATCH(B16,Config!$A$12:$A$21,0)),Config!$B$23)) | I16: =IF(A16="","",MONTH(A16)) | J16: =IF(A16="","",YEAR(A16))
... A259: 46279 | B259: Rafael Lima | C259: Captação e propostas | D259: Captação e propostas | E259: 1 | F259: Não | G259: =IF(C259="","",IFERROR(INDEX(Casos!$B$5:$B$204,MATCH(C259,Casos!$A$5:$A$204,0)),"")) | H259: =IF(OR(B259="",E259=""),"",E259*IFERROR(INDEX(Config!$D$12:$D$21,MATCH(B259,Config!$A$12:$A$21,0)),Config!$B$23)) | I259: =IF(A259="","",MONTH(A259)) | J259: =IF(A259="","",YEAR(A259))
G260: =IF(C260="","",IFERROR(INDEX(Casos!$B$5:$B$204,MATCH(C260,Casos!$A$5:$A$204,0)),"")) | H260: =IF(OR(B260="",E260=""),"",E260*IFERROR(INDEX(Config!$D$12:$D$21,MATCH(B260,Config!$A$12:$A$21,0)),Config!$B$23)) | I260: =IF(A260="","",MONTH(A260)) | J260: =IF(A260="","",YEAR(A260))
G261: =IF(C261="","",IFERROR(INDEX(Casos!$B$5:$B$204,MATCH(C261,Casos!$A$5:$A$204,0)),"")) | H261: =IF(OR(B261="",E261=""),"",E261*IFERROR(INDEX(Config!$D$12:$D$21,MATCH(B261,Config!$A$12:$A$21,0)),Config!$B$23)) | I261: =IF(A261="","",MONTH(A261)) | J261: =IF(A261="","",YEAR(A261))
G262: =IF(C262="","",IFERROR(INDEX(Casos!$B$5:$B$204,MATCH(C262,Casos!$A$5:$A$204,0)),"")) | H262: =IF(OR(B262="",E262=""),"",E262*IFERROR(INDEX(Config!$D$12:$D$21,MATCH(B262,Config!$A$12:$A$21,0)),Config!$B$23)) | I262: =IF(A262="","",MONTH(A262)) | J262: =IF(A262="","",YEAR(A262))
G263: =IF(C263="","",IFERROR(INDEX(Casos!$B$5:$B$204,MATCH(C263,Casos!$A$5:$A$204,0)),"")) | H263: =IF(OR(B263="",E263=""),"",E263*IFERROR(INDEX(Config!$D$12:$D$21,MATCH(B263,Config!$A$12:$A$21,0)),Config!$B$23)) | I263: =IF(A263="","",MONTH(A263)) | J263: =IF(A263="","",YEAR(A263))
G264: =IF(C264="","",IFERROR(INDEX(Casos!$B$5:$B$204,MATCH(C264,Casos!$A$5:$A$204,0)),"")) | H264: =IF(OR(B264="",E264=""),"",E264*IFERROR(INDEX(Config!$D$12:$D$21,MATCH(B264,Config!$A$12:$A$21,0)),Config!$B$23)) | I264: =IF(A264="","",MONTH(A264)) | J264: =IF(A264="","",YEAR(A264))
G265: =IF(C265="","",IFERROR(INDEX(Casos!$B$5:$B$204,MATCH(C265,Casos!$A$5:$A$204,0)),"")) | H265: =IF(OR(B265="",E265=""),"",E265*IFERROR(INDEX(Config!$D$12:$D$21,MATCH(B265,Config!$A$12:$A$21,0)),Config!$B$23)) | I265: =IF(A265="","",MONTH(A265)) | J265: =IF(A265="","",YEAR(A265))
G266: =IF(C266="","",IFERROR(INDEX(Casos!$B$5:$B$204,MATCH(C266,Casos!$A$5:$A$204,0)),"")) | H266: =IF(OR(B266="",E266=""),"",E266*IFERROR(INDEX(Config!$D$12:$D$21,MATCH(B266,Config!$A$12:$A$21,0)),Config!$B$23)) | I266: =IF(A266="","",MONTH(A266)) | J266: =IF(A266="","",YEAR(A266))
G267: =IF(C267="","",IFERROR(INDEX(Casos!$B$5:$B$204,MATCH(C267,Casos!$A$5:$A$204,0)),"")) | H267: =IF(OR(B267="",E267=""),"",E267*IFERROR(INDEX(Config!$D$12:$D$21,MATCH(B267,Config!$A$12:$A$21,0)),Config!$B$23)) | I267: =IF(A267="","",MONTH(A267)) | J267: =IF(A267="","",YEAR(A267))
G268: =IF(C268="","",IFERROR(INDEX(Casos!$B$5:$B$204,MATCH(C268,Casos!$A$5:$A$204,0)),"")) | H268: =IF(OR(B268="",E268=""),"",E268*IFERROR(INDEX(Config!$D$12:$D$21,MATCH(B268,Config!$A$12:$A$21,0)),Config!$B$23)) | I268: =IF(A268="","",MONTH(A268)) | J268: =IF(A268="","",YEAR(A268))
G269: =IF(C269="","",IFERROR(INDEX(Casos!$B$5:$B$204,MATCH(C269,Casos!$A$5:$A$204,0)),"")) | H269: =IF(OR(B269="",E269=""),"",E269*IFERROR(INDEX(Config!$D$12:$D$21,MATCH(B269,Config!$A$12:$A$21,0)),Config!$B$23)) | I269: =IF(A269="","",MONTH(A269)) | J269: =IF(A269="","",YEAR(A269))
G270: =IF(C270="","",IFERROR(INDEX(Casos!$B$5:$B$204,MATCH(C270,Casos!$A$5:$A$204,0)),"")) | H270: =IF(OR(B270="",E270=""),"",E270*IFERROR(INDEX(Config!$D$12:$D$21,MATCH(B270,Config!$A$12:$A$21,0)),Config!$B$23)) | I270: =IF(A270="","",MONTH(A270)) | J270: =IF(A270="","",YEAR(A270))
G271: =IF(C271="","",IFERROR(INDEX(Casos!$B$5:$B$204,MATCH(C271,Casos!$A$5:$A$204,0)),"")) | H271: =IF(OR(B271="",E271=""),"",E271*IFERROR(INDEX(Config!$D$12:$D$21,MATCH(B271,Config!$A$12:$A$21,0)),Config!$B$23)) | I271: =IF(A271="","",MONTH(A271)) | J271: =IF(A271="","",YEAR(A271))
... G604: =IF(C604="","",IFERROR(INDEX(Casos!$B$5:$B$204,MATCH(C604,Casos!$A$5:$A$204,0)),"")) | H604: =IF(OR(B604="",E604=""),"",E604*IFERROR(INDEX(Config!$D$12:$D$21,MATCH(B604,Config!$A$12:$A$21,0)),Config!$B$23)) | I604: =IF(A604="","",MONTH(A604)) | J604: =IF(A604="","",YEAR(A604))
A606: Faturável em vermelho: lançamento sem dizer se a hora é faturável. Faturável = hora que o cliente paga (direta ou dentro do valor fixo); reunião interna, deslocamento não cobrado e administração não são.
