Workbook

Sheet Como usar
A1: Tabela de preços e referência por procedimento
A2: Kit de Gestão para Médicos · Seu Sócio Gestor · versão 1.0 (setembro de 2026)
A4: O que esta planilha faz | B4: É a tabela interna da clínica: para cada procedimento, o preço particular e a tabela de cada convênio ao lado do custo cheio, do preço mínimo e do preço alvo (a mesma conta da 06), mais o valor por hora que cada pagador paga e o valor médio praticado no mês fechado.
A5: Passo 1 | B5: Em Config, copie o custo-hora da planilha 05, a alíquota, as margens e os pagadores (o primeiro é o particular).
A6: Passo 2 | B6: Em Tabela, uma linha por procedimento: minutos, se gera retorno, material e o valor de cada pagador. Esta é a tabela oficial da clínica: a Config da planilha 01 (agenda), a 06 e a 07 copiam daqui.
A7: Passo 3 | B7: Copie de "Por procedimento" no Painel da 01 (mês fechado) os realizados e a produção do mês: a planilha mostra o valor médio praticado e quanto ele fica acima ou abaixo do mínimo.
A8: Passo 4 | B8: Leia as cores: particular abaixo do mínimo (vermelho) é preço a revisar; tabela de convênio vermelha não cobre o custo cheio (leve para a planilha 07 antes de decidir). O quadro "Valor por hora" é o argumento para negociar tabela.
A9: Ordem de atualização | B9: Mudou um preço? Atualize sempre nesta ordem: 08 (aqui) → 06 · Precificação → 07 · Simulador → 01 · Config (a tabela que a Agenda busca). Procedimento novo: 01 e 02 (Config), 08, 06 e 07. Convênio novo: 01, 02, 06, 07, 08, 09 (categorias de entrada) e 13 (Config, com prazo e dia de envio).
A10: Rotina | B10: Revise quando o custo-hora mudar (05) ou ao renegociar um convênio. Se pesquisar preços da região, anote na coluna "Referência de mercado"; a divulgação de preços segue as regras do CFM.
A11: Com a IA | B11: Copie a Tabela e use o prompt "Preço 04 · Revisar a tabela de preços" da biblioteca do kit, ou "Preço 03 · Vale a pena este convênio?" para um convênio específico.
A12: Legenda | B12: Células amarelas: você preenche. Brancas: calculadas. Não é preciso mexer em nada fora do amarelo.
A13: Proteção | B13: Fórmulas protegidas sem senha. Para editar: Revisar > Desproteger planilha (Excel) ou Dados > Proteger intervalos (Google Sheets).
A14: Requisitos | B14: Excel 2016 ou mais novo, Microsoft 365 ou Google Sheets (só funções do Excel 2007+; nada de MÍNIMOSES, MÁXIMOSES ou UNIRTEXTO). No celular abre nos aplicativos; para preencher, use o computador.
A15: Dados de pacientes | B15: Guarde só o que a gestão precisa (nome, contato, valor, data). Nada de diagnóstico, prontuário ou exame nestas planilhas: o kit é gestão, não é prontuário. Veja o guia LGPD do kit antes de colar qualquer tabela em uma IA.
... A19: Suporte | B19: suporte@seusociogestor.com.br · resposta em até 5 dias úteis · reembolso em até 7 dias pelo mesmo canal.

Sheet Tabela
A1: =Config!$B$4&" · Tabela de preços e referência · volume de "&Config!$B$5 -> Clínica Vida Plena (exemplo fictício) · Tabela de preços e referência · volume de Agosto de 2026
A2: Amarelo: procedimento, minutos, retorno, material, valor de cada pagador e o volume do mês (Painel da 01, por procedimento). Branco: custo cheio, mínimo, alvo, situação e valor médio praticado.
A4: Hora mínima (05) | C4: Particular abaixo do mínimo | E4: Tabelas de convênio abaixo do custo cheio + imposto | G4: Produção no mês (R$) | I4: Valor médio por hora no mês | K4: Contra a hora mínima
A5: =Config!$B$13 -> 338.98305 | C5: =COUNTIF($N$8:$N$19,"Abaixo do mínimo")&" de "&COUNTA($A$8:$A$19) -> 0 de 7 | E5: =SUM($O$8:$O$19) -> 14 | G5: =SUM($Q$8:$Q$19) -> 48631 | I5: =IFERROR(SUM($Q$8:$Q$19)/(SUMPRODUCT($P$8:$P$19,$B$8:$B$19)/60),0) -> 410.9662 | K5: =IFERROR(I5/Config!$B$13-1,0) -> 0.21235028
A7: Procedimento | B7: Minutos | C7: Gera retorno? | D7: Material (R$) | E7: Custo cheio (R$) | F7: Preço mínimo (R$) | G7: Preço alvo (R$) | H7: =IF(Config!$B$17="","",Config!$B$17) -> Particular | I7: =IF(Config!$B$18="","",Config!$B$18) -> Saúde Total | J7: =IF(Config!$B$19="","",Config!$B$19) -> MediPlan | K7: =IF(Config!$B$20="","",Config!$B$20) -> Vida Care | L7: =IF(Config!$B$21="","",Config!$B$21) | M7: =IF(Config!$B$22="","",Config!$B$22) | N7: Situação do particular | O7: Tabelas abaixo do custo cheio + imposto | P7: Realizados no mês | Q7: Produção no mês (R$) | R7: Valor médio praticado (R$) | S7: Valor médio contra o mínimo | T7: Referência de mercado (opcional)
A8: Consulta | B8: 30 | C8: Sim | D8: 4 | E8: =IF(A8="","",(B8+IF(C8="Sim",Config!$B$11*Config!$B$12,0))/60*Config!$B$7+D8) -> 130.66667 | F8: =IF(A8="","",IFERROR(E8/(1-Config!$B$8-Config!$B$9),"")) -> 221.46893 | G8: =IF(A8="","",IFERROR(E8/(1-Config!$B$8-Config!$B$10),"")) -> 296.9697 | H8: 380 | I8: 120 | J8: 100 | K8: 90 | N8: =IF(OR(A8="",H8=""),"",IF(H8=0,"Sem cobrança",IF(H8<F8,"Abaixo do mínimo",IF(H8<G8,"Entre mínimo e alvo","No alvo ou acima")))) -> No alvo ou acima | O8: =IF(A8="","",SUMPRODUCT((I8:M8<>"")*(I8:M8>0)*(I8:M8*(1-Config!$B$8)<E8))) -> 3 | P8: 130 | Q8: 30730 | R8: =IF(OR(A8="",P8="",P8=0),"",Q8/P8) -> 236.38462 | S8: =IF(OR(R8="",F8="",H8=0),"",R8/F8-1) -> 0.067348901
A9: Retorno | B9: 20 | C9: Não | D9: 2 | E9: =IF(A9="","",(B9+IF(C9="Sim",Config!$B$11*Config!$B$12,0))/60*Config!$B$7+D9) -> 68.666667 | F9: =IF(A9="","",IFERROR(E9/(1-Config!$B$8-Config!$B$9),"")) -> 116.38418 | G9: =IF(A9="","",IFERROR(E9/(1-Config!$B$8-Config!$B$10),"")) -> 156.06061 | H9: 0 | I9: 0 | J9: 0 | K9: 0 | N9: =IF(OR(A9="",H9=""),"",IF(H9=0,"Sem cobrança",IF(H9<F9,"Abaixo do mínimo",IF(H9<G9,"Entre mínimo e alvo","No alvo ou acima")))) -> Sem cobrança | O9: =IF(A9="","",SUMPRODUCT((I9:M9<>"")*(I9:M9>0)*(I9:M9*(1-Config!$B$8)<E9))) -> 0 | P9: 48 | Q9: 0 | R9: =IF(OR(A9="",P9="",P9=0),"",Q9/P9) -> 0 | S9: =IF(OR(R9="",F9="",H9=0),"",R9/F9-1)
A10: ECG | B10: 20 | C10: Não | D10: 8 | E10: =IF(A10="","",(B10+IF(C10="Sim",Config!$B$11*Config!$B$12,0))/60*Config!$B$7+D10) -> 74.666667 | F10: =IF(A10="","",IFERROR(E10/(1-Config!$B$8-Config!$B$9),"")) -> 126.55367 | G10: =IF(A10="","",IFERROR(E10/(1-Config!$B$8-Config!$B$10),"")) -> 169.69697 | H10: 130 | I10: 40 | J10: 35 | K10: 32 | N10: =IF(OR(A10="",H10=""),"",IF(H10=0,"Sem cobrança",IF(H10<F10,"Abaixo do mínimo",IF(H10<G10,"Entre mínimo e alvo","No alvo ou acima")))) -> Entre mínimo e alvo | O10: =IF(A10="","",SUMPRODUCT((I10:M10<>"")*(I10:M10>0)*(I10:M10*(1-Config!$B$8)<E10))) -> 3 | P10: 18 | Q10: 1416 | R10: =IF(OR(A10="",P10="",P10=0),"",Q10/P10) -> 78.666667 | S10: =IF(OR(R10="",F10="",H10=0),"",R10/F10-1) -> -0.37839286
A11: MAPA | B11: 20 | C11: Não | D11: 15 | E11: =IF(A11="","",(B11+IF(C11="Sim",Config!$B$11*Config!$B$12,0))/60*Config!$B$7+D11) -> 81.666667 | F11: =IF(A11="","",IFERROR(E11/(1-Config!$B$8-Config!$B$9),"")) -> 138.41808 | G11: =IF(A11="","",IFERROR(E11/(1-Config!$B$8-Config!$B$10),"")) -> 185.60606 | H11: 300 | I11: 95 | J11: 85 | K11: 75 | N11: =IF(OR(A11="",H11=""),"",IF(H11=0,"Sem cobrança",IF(H11<F11,"Abaixo do mínimo",IF(H11<G11,"Entre mínimo e alvo","No alvo ou acima")))) -> No alvo ou acima | O11: =IF(A11="","",SUMPRODUCT((I11:M11<>"")*(I11:M11>0)*(I11:M11*(1-Config!$B$8)<E11))) -> 2 | P11: 8 | Q11: 1345 | R11: =IF(OR(A11="",P11="",P11=0),"",Q11/P11) -> 168.125 | S11: =IF(OR(R11="",F11="",H11=0),"",R11/F11-1) -> 0.21461735
A12: Holter | B12: 20 | C12: Não | D12: 18 | E12: =IF(A12="","",(B12+IF(C12="Sim",Config!$B$11*Config!$B$12,0))/60*Config!$B$7+D12) -> 84.666667 | F12: =IF(A12="","",IFERROR(E12/(1-Config!$B$8-Config!$B$9),"")) -> 143.50282 | G12: =IF(A12="","",IFERROR(E12/(1-Config!$B$8-Config!$B$10),"")) -> 192.42424 | H12: 350 | I12: 105 | J12: 95 | K12: 85 | N12: =IF(OR(A12="",H12=""),"",IF(H12=0,"Sem cobrança",IF(H12<F12,"Abaixo do mínimo",IF(H12<G12,"Entre mínimo e alvo","No alvo ou acima")))) -> No alvo ou acima | O12: =IF(A12="","",SUMPRODUCT((I12:M12<>"")*(I12:M12>0)*(I12:M12*(1-Config!$B$8)<E12))) -> 2 | P12: 10 | Q12: 2490 | R12: =IF(OR(A12="",P12="",P12=0),"",Q12/P12) -> 249 | S12: =IF(OR(R12="",F12="",H12=0),"",R12/F12-1) -> 0.73515748
A13: Teste ergométrico | B13: 40 | C13: Não | D13: 25 | E13: =IF(A13="","",(B13+IF(C13="Sim",Config!$B$11*Config!$B$12,0))/60*Config!$B$7+D13) -> 158.33333 | F13: =IF(A13="","",IFERROR(E13/(1-Config!$B$8-Config!$B$9),"")) -> 268.36158 | G13: =IF(A13="","",IFERROR(E13/(1-Config!$B$8-Config!$B$10),"")) -> 359.84848 | H13: 450 | I13: 140 | J13: 125 | K13: 110 | N13: =IF(OR(A13="",H13=""),"",IF(H13=0,"Sem cobrança",IF(H13<F13,"Abaixo do mínimo",IF(H13<G13,"Entre mínimo e alvo","No alvo ou acima")))) -> No alvo ou acima | O13: =IF(A13="","",SUMPRODUCT((I13:M13<>"")*(I13:M13>0)*(I13:M13*(1-Config!$B$8)<E13))) -> 3 | P13: 8 | Q13: 2270 | R13: =IF(OR(A13="",P13="",P13=0),"",Q13/P13) -> 283.75 | S13: =IF(OR(R13="",F13="",H13=0),"",R13/F13-1) -> 0.057342105
A14: Avaliação endócrina | B14: 40 | C14: Sim | D14: 4 | E14: =IF(A14="","",(B14+IF(C14="Sim",Config!$B$11*Config!$B$12,0))/60*Config!$B$7+D14) -> 164 | F14: =IF(A14="","",IFERROR(E14/(1-Config!$B$8-Config!$B$9),"")) -> 277.9661 | G14: =IF(A14="","",IFERROR(E14/(1-Config!$B$8-Config!$B$10),"")) -> 372.72727 | H14: 400 | I14: 130 | N14: =IF(OR(A14="",H14=""),"",IF(H14=0,"Sem cobrança",IF(H14<F14,"Abaixo do mínimo",IF(H14<G14,"Entre mínimo e alvo","No alvo ou acima")))) -> No alvo ou acima | O14: =IF(A14="","",SUMPRODUCT((I14:M14<>"")*(I14:M14>0)*(I14:M14*(1-Config!$B$8)<E14))) -> 1 | P14: 30 | Q14: 10380 | R14: =IF(OR(A14="",P14="",P14=0),"",Q14/P14) -> 346 | S14: =IF(OR(R14="",F14="",H14=0),"",R14/F14-1) -> 0.2447561
E15: =IF(A15="","",(B15+IF(C15="Sim",Config!$B$11*Config!$B$12,0))/60*Config!$B$7+D15) | F15: =IF(A15="","",IFERROR(E15/(1-Config!$B$8-Config!$B$9),"")) | G15: =IF(A15="","",IFERROR(E15/(1-Config!$B$8-Config!$B$10),"")) | N15: =IF(OR(A15="",H15=""),"",IF(H15=0,"Sem cobrança",IF(H15<F15,"Abaixo do mínimo",IF(H15<G15,"Entre mínimo e alvo","No alvo ou acima")))) | O15: =IF(A15="","",SUMPRODUCT((I15:M15<>"")*(I15:M15>0)*(I15:M15*(1-Config!$B$8)<E15))) | R15: =IF(OR(A15="",P15="",P15=0),"",Q15/P15) | S15: =IF(OR(R15="",F15="",H15=0),"",R15/F15-1)
E16: =IF(A16="","",(B16+IF(C16="Sim",Config!$B$11*Config!$B$12,0))/60*Config!$B$7+D16) | F16: =IF(A16="","",IFERROR(E16/(1-Config!$B$8-Config!$B$9),"")) | G16: =IF(A16="","",IFERROR(E16/(1-Config!$B$8-Config!$B$10),"")) | N16: =IF(OR(A16="",H16=""),"",IF(H16=0,"Sem cobrança",IF(H16<F16,"Abaixo do mínimo",IF(H16<G16,"Entre mínimo e alvo","No alvo ou acima")))) | O16: =IF(A16="","",SUMPRODUCT((I16:M16<>"")*(I16:M16>0)*(I16:M16*(1-Config!$B$8)<E16))) | R16: =IF(OR(A16="",P16="",P16=0),"",Q16/P16) | S16: =IF(OR(R16="",F16="",H16=0),"",R16/F16-1)
E17: =IF(A17="","",(B17+IF(C17="Sim",Config!$B$11*Config!$B$12,0))/60*Config!$B$7+D17) | F17: =IF(A17="","",IFERROR(E17/(1-Config!$B$8-Config!$B$9),"")) | G17: =IF(A17="","",IFERROR(E17/(1-Config!$B$8-Config!$B$10),"")) | N17: =IF(OR(A17="",H17=""),"",IF(H17=0,"Sem cobrança",IF(H17<F17,"Abaixo do mínimo",IF(H17<G17,"Entre mínimo e alvo","No alvo ou acima")))) | O17: =IF(A17="","",SUMPRODUCT((I17:M17<>"")*(I17:M17>0)*(I17:M17*(1-Config!$B$8)<E17))) | R17: =IF(OR(A17="",P17="",P17=0),"",Q17/P17) | S17: =IF(OR(R17="",F17="",H17=0),"",R17/F17-1)
E18: =IF(A18="","",(B18+IF(C18="Sim",Config!$B$11*Config!$B$12,0))/60*Config!$B$7+D18) | F18: =IF(A18="","",IFERROR(E18/(1-Config!$B$8-Config!$B$9),"")) | G18: =IF(A18="","",IFERROR(E18/(1-Config!$B$8-Config!$B$10),"")) | N18: =IF(OR(A18="",H18=""),"",IF(H18=0,"Sem cobrança",IF(H18<F18,"Abaixo do mínimo",IF(H18<G18,"Entre mínimo e alvo","No alvo ou acima")))) | O18: =IF(A18="","",SUMPRODUCT((I18:M18<>"")*(I18:M18>0)*(I18:M18*(1-Config!$B$8)<E18))) | R18: =IF(OR(A18="",P18="",P18=0),"",Q18/P18) | S18: =IF(OR(R18="",F18="",H18=0),"",R18/F18-1)
E19: =IF(A19="","",(B19+IF(C19="Sim",Config!$B$11*Config!$B$12,0))/60*Config!$B$7+D19) | F19: =IF(A19="","",IFERROR(E19/(1-Config!$B$8-Config!$B$9),"")) | G19: =IF(A19="","",IFERROR(E19/(1-Config!$B$8-Config!$B$10),"")) | N19: =IF(OR(A19="",H19=""),"",IF(H19=0,"Sem cobrança",IF(H19<F19,"Abaixo do mínimo",IF(H19<G19,"Entre mínimo e alvo","No alvo ou acima")))) | O19: =IF(A19="","",SUMPRODUCT((I19:M19<>"")*(I19:M19>0)*(I19:M19*(1-Config!$B$8)<E19))) | R19: =IF(OR(A19="",P19="",P19=0),"",Q19/P19) | S19: =IF(OR(R19="",F19="",H19=0),"",R19/F19-1)
A21: Custo cheio, preço mínimo e preço alvo: a mesma conta da planilha 06 (tempo com retorno × custo-hora + material; ÷ (1 − impostos − margem)). Tabela de convênio em vermelho: depois dos impostos não cobre o custo cheio (margem negativa) — é a mesma conta e o mesmo número do KPI "Tabelas de convênio abaixo do custo cheio + imposto" e do Resumo da planilha 06. Amarela: cobre o custo, mas não a margem mínima.
A22: Realizados e Produção no mês: copie de "Por procedimento" no Painel da planilha 01 com o mês fechado escolhido em Config (no exemplo, agosto de 2026). Valor médio praticado = produção ÷ realizados: mistura particular e convênio, por isso fica abaixo do preço particular.
A23: Referência de mercado é opcional e sua: pesquise a faixa da sua região e anote; a planilha não afirma preço de mercado. A tabela de preços e a divulgação de valores seguem as regras do CFM: revise antes de publicar.
A25: Valor por hora de atendimento, por pagador (tabela ÷ tempo com retorno)
A26: Procedimento | B26: Minutos com retorno | C26: =IF(Config!$B$17="","",Config!$B$17) -> Particular | D26: =IF(Config!$B$18="","",Config!$B$18) -> Saúde Total | E26: =IF(Config!$B$19="","",Config!$B$19) -> MediPlan | F26: =IF(Config!$B$20="","",Config!$B$20) -> Vida Care | G26: =IF(Config!$B$21="","",Config!$B$21) | H26: =IF(Config!$B$22="","",Config!$B$22) | I26: Hora mínima | J26: Hora alvo
A27: =IF($A8="","",$A8) -> Consulta | B27: =IF($A8="","",B8+IF(C8="Sim",Config!$B$11*Config!$B$12,0)) -> 38 | C27: =IF(OR($A8="",H8="",$B27=0),"",H8/($B27/60)) -> 600 | D27: =IF(OR($A8="",I8="",$B27=0),"",I8/($B27/60)) -> 189.47368 | E27: =IF(OR($A8="",J8="",$B27=0),"",J8/($B27/60)) -> 157.89474 | F27: =IF(OR($A8="",K8="",$B27=0),"",K8/($B27/60)) -> 142.10526 | G27: =IF(OR($A8="",L8="",$B27=0),"",L8/($B27/60)) | H27: =IF(OR($A8="",M8="",$B27=0),"",M8/($B27/60)) | I27: =IF($A8="","",Config!$B$13) -> 338.98305 | J27: =IF($A8="","",Config!$B$14) -> 454.54545
A28: =IF($A9="","",$A9) -> Retorno | B28: =IF($A9="","",B9+IF(C9="Sim",Config!$B$11*Config!$B$12,0)) -> 20 | C28: =IF(OR($A9="",H9="",$B28=0),"",H9/($B28/60)) -> 0 | D28: =IF(OR($A9="",I9="",$B28=0),"",I9/($B28/60)) -> 0 | E28: =IF(OR($A9="",J9="",$B28=0),"",J9/($B28/60)) -> 0 | F28: =IF(OR($A9="",K9="",$B28=0),"",K9/($B28/60)) -> 0 | G28: =IF(OR($A9="",L9="",$B28=0),"",L9/($B28/60)) | H28: =IF(OR($A9="",M9="",$B28=0),"",M9/($B28/60)) | I28: =IF($A9="","",Config!$B$13) -> 338.98305 | J28: =IF($A9="","",Config!$B$14) -> 454.54545
A29: =IF($A10="","",$A10) -> ECG | B29: =IF($A10="","",B10+IF(C10="Sim",Config!$B$11*Config!$B$12,0)) -> 20 | C29: =IF(OR($A10="",H10="",$B29=0),"",H10/($B29/60)) -> 390 | D29: =IF(OR($A10="",I10="",$B29=0),"",I10/($B29/60)) -> 120 | E29: =IF(OR($A10="",J10="",$B29=0),"",J10/($B29/60)) -> 105 | F29: =IF(OR($A10="",K10="",$B29=0),"",K10/($B29/60)) -> 96 | G29: =IF(OR($A10="",L10="",$B29=0),"",L10/($B29/60)) | H29: =IF(OR($A10="",M10="",$B29=0),"",M10/($B29/60)) | I29: =IF($A10="","",Config!$B$13) -> 338.98305 | J29: =IF($A10="","",Config!$B$14) -> 454.54545
A30: =IF($A11="","",$A11) -> MAPA | B30: =IF($A11="","",B11+IF(C11="Sim",Config!$B$11*Config!$B$12,0)) -> 20 | C30: =IF(OR($A11="",H11="",$B30=0),"",H11/($B30/60)) -> 900 | D30: =IF(OR($A11="",I11="",$B30=0),"",I11/($B30/60)) -> 285 | E30: =IF(OR($A11="",J11="",$B30=0),"",J11/($B30/60)) -> 255 | F30: =IF(OR($A11="",K11="",$B30=0),"",K11/($B30/60)) -> 225 | G30: =IF(OR($A11="",L11="",$B30=0),"",L11/($B30/60)) | H30: =IF(OR($A11="",M11="",$B30=0),"",M11/($B30/60)) | I30: =IF($A11="","",Config!$B$13) -> 338.98305 | J30: =IF($A11="","",Config!$B$14) -> 454.54545
A31: =IF($A12="","",$A12) -> Holter | B31: =IF($A12="","",B12+IF(C12="Sim",Config!$B$11*Config!$B$12,0)) -> 20 | C31: =IF(OR($A12="",H12="",$B31=0),"",H12/($B31/60)) -> 1050 | D31: =IF(OR($A12="",I12="",$B31=0),"",I12/($B31/60)) -> 315 | E31: =IF(OR($A12="",J12="",$B31=0),"",J12/($B31/60)) -> 285 | F31: =IF(OR($A12="",K12="",$B31=0),"",K12/($B31/60)) -> 255 | G31: =IF(OR($A12="",L12="",$B31=0),"",L12/($B31/60)) | H31: =IF(OR($A12="",M12="",$B31=0),"",M12/($B31/60)) | I31: =IF($A12="","",Config!$B$13) -> 338.98305 | J31: =IF($A12="","",Config!$B$14) -> 454.54545
A32: =IF($A13="","",$A13) -> Teste ergométrico | B32: =IF($A13="","",B13+IF(C13="Sim",Config!$B$11*Config!$B$12,0)) -> 40 | C32: =IF(OR($A13="",H13="",$B32=0),"",H13/($B32/60)) -> 675 | D32: =IF(OR($A13="",I13="",$B32=0),"",I13/($B32/60)) -> 210 | E32: =IF(OR($A13="",J13="",$B32=0),"",J13/($B32/60)) -> 187.5 | F32: =IF(OR($A13="",K13="",$B32=0),"",K13/($B32/60)) -> 165 | G32: =IF(OR($A13="",L13="",$B32=0),"",L13/($B32/60)) | H32: =IF(OR($A13="",M13="",$B32=0),"",M13/($B32/60)) | I32: =IF($A13="","",Config!$B$13) -> 338.98305 | J32: =IF($A13="","",Config!$B$14) -> 454.54545
A33: =IF($A14="","",$A14) -> Avaliação endócrina | B33: =IF($A14="","",B14+IF(C14="Sim",Config!$B$11*Config!$B$12,0)) -> 48 | C33: =IF(OR($A14="",H14="",$B33=0),"",H14/($B33/60)) -> 500 | D33: =IF(OR($A14="",I14="",$B33=0),"",I14/($B33/60)) -> 162.5 | E33: =IF(OR($A14="",J14="",$B33=0),"",J14/($B33/60)) | F33: =IF(OR($A14="",K14="",$B33=0),"",K14/($B33/60)) | G33: =IF(OR($A14="",L14="",$B33=0),"",L14/($B33/60)) | H33: =IF(OR($A14="",M14="",$B33=0),"",M14/($B33/60)) | I33: =IF($A14="","",Config!$B$13) -> 338.98305 | J33: =IF($A14="","",Config!$B$14) -> 454.54545
A34: =IF($A15="","",$A15) | B34: =IF($A15="","",B15+IF(C15="Sim",Config!$B$11*Config!$B$12,0)) | C34: =IF(OR($A15="",H15="",$B34=0),"",H15/($B34/60)) | D34: =IF(OR($A15="",I15="",$B34=0),"",I15/($B34/60)) | E34: =IF(OR($A15="",J15="",$B34=0),"",J15/($B34/60)) | F34: =IF(OR($A15="",K15="",$B34=0),"",K15/($B34/60)) | G34: =IF(OR($A15="",L15="",$B34=0),"",L15/($B34/60)) | H34: =IF(OR($A15="",M15="",$B34=0),"",M15/($B34/60)) | I34: =IF($A15="","",Config!$B$13) | J34: =IF($A15="","",Config!$B$14)
A35: =IF($A16="","",$A16) | B35: =IF($A16="","",B16+IF(C16="Sim",Config!$B$11*Config!$B$12,0)) | C35: =IF(OR($A16="",H16="",$B35=0),"",H16/($B35/60)) | D35: =IF(OR($A16="",I16="",$B35=0),"",I16/($B35/60)) | E35: =IF(OR($A16="",J16="",$B35=0),"",J16/($B35/60)) | F35: =IF(OR($A16="",K16="",$B35=0),"",K16/($B35/60)) | G35: =IF(OR($A16="",L16="",$B35=0),"",L16/($B35/60)) | H35: =IF(OR($A16="",M16="",$B35=0),"",M16/($B35/60)) | I35: =IF($A16="","",Config!$B$13) | J35: =IF($A16="","",Config!$B$14)
A36: =IF($A17="","",$A17) | B36: =IF($A17="","",B17+IF(C17="Sim",Config!$B$11*Config!$B$12,0)) | C36: =IF(OR($A17="",H17="",$B36=0),"",H17/($B36/60)) | D36: =IF(OR($A17="",I17="",$B36=0),"",I17/($B36/60)) | E36: =IF(OR($A17="",J17="",$B36=0),"",J17/($B36/60)) | F36: =IF(OR($A17="",K17="",$B36=0),"",K17/($B36/60)) | G36: =IF(OR($A17="",L17="",$B36=0),"",L17/($B36/60)) | H36: =IF(OR($A17="",M17="",$B36=0),"",M17/($B36/60)) | I36: =IF($A17="","",Config!$B$13) | J36: =IF($A17="","",Config!$B$14)
A37: =IF($A18="","",$A18) | B37: =IF($A18="","",B18+IF(C18="Sim",Config!$B$11*Config!$B$12,0)) | C37: =IF(OR($A18="",H18="",$B37=0),"",H18/($B37/60)) | D37: =IF(OR($A18="",I18="",$B37=0),"",I18/($B37/60)) | E37: =IF(OR($A18="",J18="",$B37=0),"",J18/($B37/60)) | F37: =IF(OR($A18="",K18="",$B37=0),"",K18/($B37/60)) | G37: =IF(OR($A18="",L18="",$B37=0),"",L18/($B37/60)) | H37: =IF(OR($A18="",M18="",$B37=0),"",M18/($B37/60)) | I37: =IF($A18="","",Config!$B$13) | J37: =IF($A18="","",Config!$B$14)
A38: =IF($A19="","",$A19) | B38: =IF($A19="","",B19+IF(C19="Sim",Config!$B$11*Config!$B$12,0)) | C38: =IF(OR($A19="",H19="",$B38=0),"",H19/($B38/60)) | D38: =IF(OR($A19="",I19="",$B38=0),"",I19/($B38/60)) | E38: =IF(OR($A19="",J19="",$B38=0),"",J19/($B38/60)) | F38: =IF(OR($A19="",K19="",$B38=0),"",K19/($B38/60)) | G38: =IF(OR($A19="",L19="",$B38=0),"",L19/($B38/60)) | H38: =IF(OR($A19="",M19="",$B38=0),"",M19/($B38/60)) | I38: =IF($A19="","",Config!$B$13) | J38: =IF($A19="","",Config!$B$14)
A39: Vermelho: abaixo da hora mínima. Verde: na hora alvo ou acima. Retorno aparece vazio (valor zero). Este quadro é o argumento na negociação de tabela: quanto cada convênio paga pela hora da clínica.

Sheet Config
A1: Configurações
A2: Células amarelas: você preenche. Custo-hora da planilha 05; margens e impostos iguais aos da 06.
A4: Nome da clínica | B4: Clínica Vida Plena (exemplo fictício)
A5: Mês do volume (mês fechado) | B5: Agosto de 2026
A6: Data de referência | B6: 46279
A7: Custo da hora de atendimento (R$) | B7: 200 | C7: Copie do Painel da planilha 05 ("Custo da hora de atendimento"). No exemplo, R$ 200,00.
A8: Impostos sobre o que entra (%) | B8: 0.11 | C8: A mesma alíquota efetiva das planilhas 05, 06 e 07 (exemplo: 11 %). Só imposto: a taxa da maquininha não entra aqui (fica na 16 e no resultado 18).
A9: Margem mínima sobre o preço (%) | B9: 0.3 | C9: Piso da faixa (a mesma margem da 05 e da 06).
A10: Margem alvo sobre o preço (%) | B10: 0.45 | C10: Teto da faixa (a mesma da 06).
A11: Retornos por consulta (média) | B11: 0.4 | C11: Iguais à 06: o tempo do retorno entra no custo da consulta.
A12: Duração do retorno (minutos) | B12: 20
A13: Hora mínima a cobrar (R$) | B13: =IFERROR(B7/(1-B8-B9),"") -> 338.98305 | C13: Custo-hora ÷ (1 − impostos − margem mínima) = R$ 338,98 no exemplo (a 05 arredonda para R$ 340).
A14: Hora alvo (R$) | B14: =IFERROR(B7/(1-B8-B10),"") -> 454.54545 | C14: Custo-hora ÷ (1 − impostos − margem alvo).
A16: Pagadores (até 6, na ordem das colunas da Tabela; o primeiro é o particular)
A17: Nomes | B17: Particular | C17: Preencha de cima para baixo, sem pular linha. Os mesmos da Config da planilha 01.
B18: Saúde Total
B19: MediPlan
B20: Vida Care
A23: Esta planilha é a FONTE ÚNICA da tabela de preços do kit. A aba Tabela é onde o preço é decidido; 06 (precificação), 07 (simulador) e a Config da planilha 01 (agenda) copiam daqui.
A24: Ordem de atualização quando um preço muda: 1) aqui, na aba Tabela; 2) planilha 06 · Precificação (colunas do particular e dos convênios); 3) planilha 07 · Simulador (quadro 2, valor de tabela); 4) planilha 01 · Config (tabela de preços por pagador, que é o que a Agenda busca). Procedimentos novos: cadastre na 01 (Config), na 02, aqui, na 06 e na 07. Convênio novo: 01, 02, 06, 07, aqui, 09 (categorias de entrada) e 13 (Config).
