Workbook

Sheet Como usar
A1: Provisão de impostos, 13º e férias
A2: Kit de Gestão para Médicos · Seu Sócio Gestor · versão 1.0 (setembro de 2026)
A4: O que esta planilha faz | B4: Separa, todo mês, o dinheiro do imposto sobre o que entrou, do 13º e das férias da equipe. Mostra quanto deveria estar guardado, quanto já foi usado e avisa quando o que está separado não cobre o compromisso do mês seguinte.
A5: Passo 1 | B5: Em Config, digite a alíquota efetiva que a clínica combinou com o contador (a planilha não afirma qual é a sua), o adicional de férias, os encargos, os meses de pagamento do 13º e das férias e a equipe com Sim / Não em cada provisão.
A6: Passo 2 | B6: Em Entradas e pagamentos, uma linha por mês: o total que entrou (copie de Entrou no mês do Painel da planilha 09, sem Outras entradas) e o que foi pago de impostos, 13º e férias. Meses não fechados ficam em branco.
A7: Passo 3 | B7: Em Painel, escolha o mês em Config. A tabela mostra o ano inteiro; a linha do mês fica destacada. Alerta em vermelho = separar mais dinheiro antes do próximo compromisso.
A8: Rotina | B8: No fechamento de cada mês (dia 5): lançar as entradas do mês anterior, transferir o valor de A separar no mês para a conta de provisão e conferir se o extrato dessa conta bate com Saldo provisionado.
A9: Com o contador | B9: Leve esta aba para a reunião mensal: alíquota, provisões e o que foi pago. PJ médica: pergunte sobre o enquadramento (Simples anexo III ou V, fator r, presumido) e ajuste Config sempre que a orientação mudar.
A10: Com a IA | B10: Copie a tabela do Painel e use o prompt "Caixa 04 · Preparar a reunião mensal com o contador" ou "Caixa 05 · Perguntas sobre provisão de impostos, 13º e férias" da biblioteca do kit para montar a pauta e as perguntas.
A11: Legenda | B11: Células amarelas: você preenche. Brancas: calculadas. Não é preciso mexer em nada fora do amarelo.
A12: Proteção | B12: Fórmulas protegidas sem senha. Para editar: Revisar > Desproteger planilha (Excel) ou Dados > Proteger intervalos (Google Sheets).
A13: Requisitos | B13: Excel 2016 ou mais novo, Microsoft 365 ou Google Sheets (só funções do Excel 2007+; nada de MÍNIMOSES, MÁXIMOSES ou UNIRTEXTO). No celular abre nos aplicativos; para preencher, use o computador.
A14: Dados de pacientes | B14: Guarde só o que a gestão precisa (nome, contato, valor, data). Nada de diagnóstico, prontuário ou exame nestas planilhas: o kit é gestão, não é prontuário. Veja o guia LGPD do kit antes de colar qualquer tabela em uma IA.
A15: Google Sheets | B15: Faça upload no Google Drive e abra com o Google Sheets. Fórmulas, listas, cores, semáforos e gráficos funcionam: as regras de cor que dependem do mês escolhido em Config usam INDIRECT, que é a forma que o Sheets aceita para regra condicional apontar para outra aba.
... A18: Suporte | B18: suporte@seusociogestor.com.br · resposta em até 5 dias úteis · reembolso em até 7 dias pelo mesmo canal.

Sheet Painel
A1: =Config!B4&" · Provisão de impostos, 13º e férias · "&Config!B6&" de "&Config!B5 -> Clínica Vida Plena (exemplo fictício) · Provisão de impostos, 13º e férias · Setembro de 2026
A2: Nada para digitar aqui. Alíquota e equipe vêm de Config; entradas e pagamentos, da aba ao lado.
A4: Entradas do mês | C4: A separar no mês | E4: Saldo provisionado ao fim do mês | G4: Compromisso do mês seguinte | I4: Quanto falta separar | K4: Situação
A5: =INDEX(B9:B20,Config!$B$7) -> 20710 | C5: =INDEX(F9:F20,Config!$B$7) -> 4240.1 | E5: =INDEX(J9:J20,Config!$B$7) -> 22448.67 | G5: =INDEX(K9:K20,Config!$B$7) -> 2278.1 | I5: =INDEX(M9:M20,Config!$B$7) -> 0 | K5: =IF(E5<G5,"Atenção: falta separar","Coberto") -> Coberto
A7: O ano, mês a mês
A8: Mês | B8: Entradas | C8: Provisão de impostos | D8: Provisão de 13º | E8: Provisão de férias | F8: Total a separar no mês | G8: Usado no mês | H8: Separado (acumulado) | I8: Usado (acumulado) | J8: Saldo provisionado | K8: Compromisso do mês seguinte | L8: Alerta | M8: Quanto falta
A9: Janeiro | B9: ='Entradas e pagamentos'!B5 -> 25310 | C9: =B9*Config!$B$8 -> 2784.1 | D9: =Config!$E$24 -> 1698 | E9: =Config!$F$24 -> 264 | F9: =SUM(C9:E9) -> 4746.1 | G9: ='Entradas e pagamentos'!F5 -> 3630 | H9: =SUM($F$9:F9) -> 4746.1 | I9: =SUM($G$9:G9) -> 3630 | J9: =H9-I9 -> 1116.1 | K9: =C9+IF(MOD(1,12)+1=MATCH(Config!$B$11,Config!$H$5:$H$16,0),Config!$E$25,0)+IF(MOD(1,12)+1=MATCH(Config!$B$12,Config!$H$5:$H$16,0),Config!$F$25,0) -> 2784.1 | L9: =IF(J9<K9,"Falta separar","Coberto") -> Falta separar | M9: =MAX(0,K9-J9) -> 1668
A10: Fevereiro | B10: ='Entradas e pagamentos'!B6 -> 25650 | C10: =B10*Config!$B$8 -> 2821.5 | D10: =Config!$E$24 -> 1698 | E10: =Config!$F$24 -> 264 | F10: =SUM(C10:E10) -> 4783.5 | G10: ='Entradas e pagamentos'!F6 -> 2784 | H10: =SUM($F$9:F10) -> 9529.6 | I10: =SUM($G$9:G10) -> 6414 | J10: =H10-I10 -> 3115.6 | K10: =C10+IF(MOD(2,12)+1=MATCH(Config!$B$11,Config!$H$5:$H$16,0),Config!$E$25,0)+IF(MOD(2,12)+1=MATCH(Config!$B$12,Config!$H$5:$H$16,0),Config!$F$25,0) -> 2821.5 | L10: =IF(J10<K10,"Falta separar","Coberto") -> Coberto | M10: =MAX(0,K10-J10) -> 0
A11: Março | B11: ='Entradas e pagamentos'!B7 -> 40540 | C11: =B11*Config!$B$8 -> 4459.4 | D11: =Config!$E$24 -> 1698 | E11: =Config!$F$24 -> 264 | F11: =SUM(C11:E11) -> 6421.4 | G11: ='Entradas e pagamentos'!F7 -> 2822 | H11: =SUM($F$9:F11) -> 15951 | I11: =SUM($G$9:G11) -> 9236 | J11: =H11-I11 -> 6715 | K11: =C11+IF(MOD(3,12)+1=MATCH(Config!$B$11,Config!$H$5:$H$16,0),Config!$E$25,0)+IF(MOD(3,12)+1=MATCH(Config!$B$12,Config!$H$5:$H$16,0),Config!$F$25,0) -> 4459.4 | L11: =IF(J11<K11,"Falta separar","Coberto") -> Coberto | M11: =MAX(0,K11-J11) -> 0
A12: Abril | B12: ='Entradas e pagamentos'!B8 -> 40155 | C12: =B12*Config!$B$8 -> 4417.05 | D12: =Config!$E$24 -> 1698 | E12: =Config!$F$24 -> 264 | F12: =SUM(C12:E12) -> 6379.05 | G12: ='Entradas e pagamentos'!F8 -> 4459 | H12: =SUM($F$9:F12) -> 22330.05 | I12: =SUM($G$9:G12) -> 13695 | J12: =H12-I12 -> 8635.05 | K12: =C12+IF(MOD(4,12)+1=MATCH(Config!$B$11,Config!$H$5:$H$16,0),Config!$E$25,0)+IF(MOD(4,12)+1=MATCH(Config!$B$12,Config!$H$5:$H$16,0),Config!$F$25,0) -> 4417.05 | L12: =IF(J12<K12,"Falta separar","Coberto") -> Coberto | M12: =MAX(0,K12-J12) -> 0
A13: Maio | B13: ='Entradas e pagamentos'!B9 -> 45380 | C13: =B13*Config!$B$8 -> 4991.8 | D13: =Config!$E$24 -> 1698 | E13: =Config!$F$24 -> 264 | F13: =SUM(C13:E13) -> 6953.8 | G13: ='Entradas e pagamentos'!F9 -> 4417 | H13: =SUM($F$9:F13) -> 29283.85 | I13: =SUM($G$9:G13) -> 18112 | J13: =H13-I13 -> 11171.85 | K13: =C13+IF(MOD(5,12)+1=MATCH(Config!$B$11,Config!$H$5:$H$16,0),Config!$E$25,0)+IF(MOD(5,12)+1=MATCH(Config!$B$12,Config!$H$5:$H$16,0),Config!$F$25,0) -> 4991.8 | L13: =IF(J13<K13,"Falta separar","Coberto") -> Coberto | M13: =MAX(0,K13-J13) -> 0
A14: Junho | B14: ='Entradas e pagamentos'!B10 -> 47240 | C14: =B14*Config!$B$8 -> 5196.4 | D14: =Config!$E$24 -> 1698 | E14: =Config!$F$24 -> 264 | F14: =SUM(C14:E14) -> 7158.4 | G14: ='Entradas e pagamentos'!F10 -> 4992 | H14: =SUM($F$9:F14) -> 36442.25 | I14: =SUM($G$9:G14) -> 23104 | J14: =H14-I14 -> 13338.25 | K14: =C14+IF(MOD(6,12)+1=MATCH(Config!$B$11,Config!$H$5:$H$16,0),Config!$E$25,0)+IF(MOD(6,12)+1=MATCH(Config!$B$12,Config!$H$5:$H$16,0),Config!$F$25,0) -> 5196.4 | L14: =IF(J14<K14,"Falta separar","Coberto") -> Coberto | M14: =MAX(0,K14-J14) -> 0
A15: Julho | B15: ='Entradas e pagamentos'!B11 -> 44471 | C15: =B15*Config!$B$8 -> 4891.81 | D15: =Config!$E$24 -> 1698 | E15: =Config!$F$24 -> 264 | F15: =SUM(C15:E15) -> 6853.81 | G15: ='Entradas e pagamentos'!F11 -> 5196 | H15: =SUM($F$9:F15) -> 43296.06 | I15: =SUM($G$9:G15) -> 28300 | J15: =H15-I15 -> 14996.06 | K15: =C15+IF(MOD(7,12)+1=MATCH(Config!$B$11,Config!$H$5:$H$16,0),Config!$E$25,0)+IF(MOD(7,12)+1=MATCH(Config!$B$12,Config!$H$5:$H$16,0),Config!$F$25,0) -> 4891.81 | L15: =IF(J15<K15,"Falta separar","Coberto") -> Coberto | M15: =MAX(0,K15-J15) -> 0
A16: Agosto | B16: ='Entradas e pagamentos'!B12 -> 55841 | C16: =B16*Config!$B$8 -> 6142.51 | D16: =Config!$E$24 -> 1698 | E16: =Config!$F$24 -> 264 | F16: =SUM(C16:E16) -> 8104.51 | G16: ='Entradas e pagamentos'!F12 -> 4892 | H16: =SUM($F$9:F16) -> 51400.57 | I16: =SUM($G$9:G16) -> 33192 | J16: =H16-I16 -> 18208.57 | K16: =C16+IF(MOD(8,12)+1=MATCH(Config!$B$11,Config!$H$5:$H$16,0),Config!$E$25,0)+IF(MOD(8,12)+1=MATCH(Config!$B$12,Config!$H$5:$H$16,0),Config!$F$25,0) -> 6142.51 | L16: =IF(J16<K16,"Falta separar","Coberto") -> Coberto | M16: =MAX(0,K16-J16) -> 0
A17: Setembro | B17: ='Entradas e pagamentos'!B13 -> 20710 | C17: =B17*Config!$B$8 -> 2278.1 | D17: =Config!$E$24 -> 1698 | E17: =Config!$F$24 -> 264 | F17: =SUM(C17:E17) -> 4240.1 | G17: ='Entradas e pagamentos'!F13 -> 0 | H17: =SUM($F$9:F17) -> 55640.67 | I17: =SUM($G$9:G17) -> 33192 | J17: =H17-I17 -> 22448.67 | K17: =C17+IF(MOD(9,12)+1=MATCH(Config!$B$11,Config!$H$5:$H$16,0),Config!$E$25,0)+IF(MOD(9,12)+1=MATCH(Config!$B$12,Config!$H$5:$H$16,0),Config!$F$25,0) -> 2278.1 | L17: =IF(J17<K17,"Falta separar","Coberto") -> Coberto | M17: =MAX(0,K17-J17) -> 0
A18: Outubro | B18: ='Entradas e pagamentos'!B14 -> 0 | C18: =B18*Config!$B$8 -> 0 | D18: =Config!$E$24 -> 1698 | E18: =Config!$F$24 -> 264 | F18: =SUM(C18:E18) -> 1962 | G18: ='Entradas e pagamentos'!F14 -> 0 | H18: =SUM($F$9:F18) -> 57602.67 | I18: =SUM($G$9:G18) -> 33192 | J18: =H18-I18 -> 24410.67 | K18: =C18+IF(MOD(10,12)+1=MATCH(Config!$B$11,Config!$H$5:$H$16,0),Config!$E$25,0)+IF(MOD(10,12)+1=MATCH(Config!$B$12,Config!$H$5:$H$16,0),Config!$F$25,0) -> 0 | L18: =IF(J18<K18,"Falta separar","Coberto") -> Coberto | M18: =MAX(0,K18-J18) -> 0
A19: Novembro | B19: ='Entradas e pagamentos'!B15 -> 0 | C19: =B19*Config!$B$8 -> 0 | D19: =Config!$E$24 -> 1698 | E19: =Config!$F$24 -> 264 | F19: =SUM(C19:E19) -> 1962 | G19: ='Entradas e pagamentos'!F15 -> 0 | H19: =SUM($F$9:F19) -> 59564.67 | I19: =SUM($G$9:G19) -> 33192 | J19: =H19-I19 -> 26372.67 | K19: =C19+IF(MOD(11,12)+1=MATCH(Config!$B$11,Config!$H$5:$H$16,0),Config!$E$25,0)+IF(MOD(11,12)+1=MATCH(Config!$B$12,Config!$H$5:$H$16,0),Config!$F$25,0) -> 20376 | L19: =IF(J19<K19,"Falta separar","Coberto") -> Coberto | M19: =MAX(0,K19-J19) -> 0
A20: Dezembro | B20: ='Entradas e pagamentos'!B16 -> 0 | C20: =B20*Config!$B$8 -> 0 | D20: =Config!$E$24 -> 1698 | E20: =Config!$F$24 -> 264 | F20: =SUM(C20:E20) -> 1962 | G20: ='Entradas e pagamentos'!F16 -> 0 | H20: =SUM($F$9:F20) -> 61526.67 | I20: =SUM($G$9:G20) -> 33192 | J20: =H20-I20 -> 28334.67 | K20: =C20+IF(MOD(12,12)+1=MATCH(Config!$B$11,Config!$H$5:$H$16,0),Config!$E$25,0)+IF(MOD(12,12)+1=MATCH(Config!$B$12,Config!$H$5:$H$16,0),Config!$F$25,0) -> 3168 | L20: =IF(J20<K20,"Falta separar","Coberto") -> Coberto | M20: =MAX(0,K20-J20) -> 0
A22: Como ler: Provisão de impostos = entradas do mês × alíquota efetiva de Config. Compromisso do mês seguinte = imposto sobre as entradas deste mês (pago no mês que vem) + 13º e férias inteiros nos meses escolhidos em Config.
A23: Saldo provisionado é o que deveria estar numa conta separada da conta corrente da clínica. Compare com o extrato dessa conta todo fechamento de mês. Meses futuros mostram só 13º e férias até você lançar as entradas.
A24: Confirme alíquotas, encargos e regras de 13º e férias com o contador. Esta planilha separa dinheiro; ela não calcula nem substitui a apuração de imposto.

Sheet Config
A1: Configurações
A2: Células amarelas: você preenche. Alíquotas e regras são as que a clínica combinou com o contador.
A4: Clínica | B4: Clínica Vida Plena (exemplo fictício) | H4: Meses
A5: Ano | B5: 2026 | H5: Janeiro
A6: Mês do painel | B6: Setembro | H6: Fevereiro
A7: Número do mês | B7: =MATCH(B6,$H$5:$H$16,0) -> 9 | H7: Março
A8: Alíquota efetiva de impostos sobre as entradas | B8: 0.11 | D8: Percentual que a clínica separa de cada real recebido, combinado com o contador. PJ médica no Simples (anexo III ou V, conforme o fator r) ou no lucro presumido tem alíquotas efetivas diferentes; esta planilha não afirma qual é a sua. No exemplo, 11 % (a mesma das planilhas 05 a 09 e 18). | H8: Abril
A9: Adicional sobre férias | B9: 0.33333333 | D9: Padrão usual: um terço. Confirme com o contador. | H9: Maio
A10: Encargos sobre 13º e férias | B10: 0.08 | D10: Encargos sobre a folha (FGTS; INSS patronal se houver). No exemplo, 8 % (FGTS) sobre o 13º e as férias da recepcionista. O contador informa o percentual certo. | H10: Junho
A11: Mês em que o 13º é pago | B11: Dezembro | D11: Se o 13º é pago em duas parcelas, escolha Novembro para se antecipar. | H11: Julho
A12: Mês previsto de férias da equipe | B12: Janeiro | H12: Agosto
H13: Setembro
A14: Equipe: 13º e férias a provisionar (até 8 pessoas) | H14: Outubro
A15: Pessoa | B15: Custo mensal | C15: Provisionar 13º? | D15: Provisionar férias? | E15: 13º por mês | F15: Férias por mês | H15: Novembro
A16: Dra. Carolina Mendes | B16: 9000 | C16: Sim | D16: Não | E16: =IF(OR(A16="",C16<>"Sim"),0,B16/12*(1+IF(D16="Sim",$B$10,0))) -> 750 | F16: =IF(OR(A16="",D16<>"Sim"),0,B16*(1+$B$9)/12*(1+$B$10)) -> 0 | H16: Dezembro
A17: Dr. Paulo Andrade | B17: 9000 | C17: Sim | D17: Não | E17: =IF(OR(A17="",C17<>"Sim"),0,B17/12*(1+IF(D17="Sim",$B$10,0))) -> 750 | F17: =IF(OR(A17="",D17<>"Sim"),0,B17*(1+$B$9)/12*(1+$B$10)) -> 0
A18: Bruna Carvalho | B18: 2200 | C18: Sim | D18: Sim | E18: =IF(OR(A18="",C18<>"Sim"),0,B18/12*(1+IF(D18="Sim",$B$10,0))) -> 198 | F18: =IF(OR(A18="",D18<>"Sim"),0,B18*(1+$B$9)/12*(1+$B$10)) -> 264
E19: =IF(OR(A19="",C19<>"Sim"),0,B19/12*(1+IF(D19="Sim",$B$10,0))) -> 0 | F19: =IF(OR(A19="",D19<>"Sim"),0,B19*(1+$B$9)/12*(1+$B$10)) -> 0
E20: =IF(OR(A20="",C20<>"Sim"),0,B20/12*(1+IF(D20="Sim",$B$10,0))) -> 0 | F20: =IF(OR(A20="",D20<>"Sim"),0,B20*(1+$B$9)/12*(1+$B$10)) -> 0
E21: =IF(OR(A21="",C21<>"Sim"),0,B21/12*(1+IF(D21="Sim",$B$10,0))) -> 0 | F21: =IF(OR(A21="",D21<>"Sim"),0,B21*(1+$B$9)/12*(1+$B$10)) -> 0
E22: =IF(OR(A22="",C22<>"Sim"),0,B22/12*(1+IF(D22="Sim",$B$10,0))) -> 0 | F22: =IF(OR(A22="",D22<>"Sim"),0,B22*(1+$B$9)/12*(1+$B$10)) -> 0
E23: =IF(OR(A23="",C23<>"Sim"),0,B23/12*(1+IF(D23="Sim",$B$10,0))) -> 0 | F23: =IF(OR(A23="",D23<>"Sim"),0,B23*(1+$B$9)/12*(1+$B$10)) -> 0
A24: Total por mês | E24: =SUM(E16:E23) -> 1698 | F24: =SUM(F16:F23) -> 264
A25: Total no ano (12 meses) | E25: =E24*12 -> 20376 | F25: =F24*12 -> 3168
A27: Sócios: marque Sim no 13º se quiserem guardar uma retirada extra de dezembro (decisão da clínica, não obrigação); os encargos não se aplicam ao pró-labore aqui. Recepcionista CLT: 13º e férias obrigatórios, com encargos.
A28: Médica parceira por repasse não entra: o repasse é pago por produção (planilha 11). O que é obrigatório provisionar para cada vínculo depende do contrato e da legislação: confirme com o contador.

Sheet Entradas e pagamentos
A1: Entradas e pagamentos do ano
A2: Amarelo: o que entrou no caixa em cada mês (Entrou no mês do Painel da planilha 09, sem a categoria Outras entradas) e o que foi efetivamente pago de impostos, 13º e férias.
A4: Mês | B4: Entradas recebidas | C4: Impostos pagos | D4: 13º pago | E4: Férias pagas | F4: Total usado no mês
A5: Janeiro | B5: 25310 | C5: 3630 | F5: =SUM(C5:E5) -> 3630
A6: Fevereiro | B6: 25650 | C6: 2784 | F6: =SUM(C6:E6) -> 2784
A7: Março | B7: 40540 | C7: 2822 | F7: =SUM(C7:E7) -> 2822
A8: Abril | B8: 40155 | C8: 4459 | F8: =SUM(C8:E8) -> 4459
A9: Maio | B9: 45380 | C9: 4417 | F9: =SUM(C9:E9) -> 4417
A10: Junho | B10: 47240 | C10: 4992 | F10: =SUM(C10:E10) -> 4992
A11: Julho | B11: 44471 | C11: 5196 | F11: =SUM(C11:E11) -> 5196
A12: Agosto | B12: 55841 | C12: 4892 | F12: =SUM(C12:E12) -> 4892
A13: Setembro | B13: 20710 | F13: =SUM(C13:E13) -> 0
A14: Outubro | F14: =SUM(C14:E14) -> 0
A15: Novembro | F15: =SUM(C15:E15) -> 0
A16: Dezembro | F16: =SUM(C16:E16) -> 0
A17: Total | B17: =SUM(B5:B16) -> 345297 | C17: =SUM(C5:C16) -> 33192 | D17: =SUM(D5:D16) -> 0 | E17: =SUM(E5:E16) -> 0 | F17: =SUM(F5:F16) -> 33192
A19: Deixe em branco os meses que ainda não fecharam. Impostos pagos: o valor das guias quitadas no mês (no exemplo, a guia de setembro ainda não foi paga: ver planilha 09). Setembro mostra o que entrou até 11/09.
A20: Entradas recebidas = Entrou no mês (Painel da 09) menos "Outras entradas" (no exemplo, a devolução de despesa pessoal de abril, R$ 620, que não é receita e não paga imposto).
