Workbook

Sheet Como usar
A1: Repasse aos médicos parceiros e pró-labore dos sócios
A2: Kit de Gestão para Médicos · Seu Sócio Gestor · versão 1.0 (setembro de 2026)
A4: O que esta planilha faz | B4: Separa três dinheiros que costumam se misturar: o repasse dos médicos parceiros (% da produção do mês), o pró-labore fixo dos sócios e o que passou do combinado (retirada extra, despesa pessoal paga pela clínica). Mostra se a parceria paga a sala que usa e distribui o lucro de cada trimestre fechado por uma regra clara.
A5: Passo 1 | B5: Em Config, cadastre os sócios (participação no lucro, pró-labore fixo), os parceiros (% de repasse, sobre produção ou recebido, dia de pagamento), a regra de distribuição e o custo indireto por hora (Painel da 05) — que entra só como informação, para mostrar o tamanho da estrutura que o parceiro usa.
A6: Passo 2 | B6: Em Repasse, uma linha por parceiro e mês: produção e horas atendidas (Painel da 01, por profissional, com o mês escolhido em Config), o material e insumo que os atendimentos dele consumiram e, quando pagar, a data e o valor. O repasse pago é a mesma saída do caixa (09).
A7: Passo 3 | B7: Em Resultado mensal, entradas e saídas da clínica sem nada dos sócios (Painel da 09). Em Retiradas, uma linha por movimento entre clínica e sócio: pró-labore, retirada extra, despesa pessoal, devolução e distribuição de lucro.
A8: Passo 4 | B8: Em Painel, escolha o mês em Config: repasse devido e a pagar, margem da parceria, o que cada sócio retirou × o combinado no mês e no ano, o saldo a acertar e o lucro distribuível dos trimestres fechados contra o que já foi pago.
A9: Rotina | B9: Dia 10: pagar o repasse do mês anterior e lançar. Dia 28: pagar o pró-labore e lançar. No fechamento do mês: lançar despesas pessoais que passaram pela conta da clínica e combinar como zerar. No fim de cada trimestre: distribuir o lucro pela regra, não pelo humor do caixa.
A10: Com a IA | B10: Copie "Médicos parceiros" e "Sócios no ano" e use o prompt "Caixa 06 · Separar o que é da clínica e o que é pessoal" ou "Caixa 07 · Conversa sobre o repasse com o médico parceiro" da biblioteca do kit.
A11: Legenda | B11: Células amarelas: você preenche. Brancas: calculadas. Não é preciso mexer em nada fora do amarelo.
A12: Proteção | B12: Fórmulas protegidas sem senha. Para editar: Revisar > Desproteger planilha (Excel) ou Dados > Proteger intervalos (Google Sheets).
A13: Requisitos | B13: Excel 2016 ou mais novo, Microsoft 365 ou Google Sheets (só funções do Excel 2007+; nada de MÍNIMOSES, MÁXIMOSES ou UNIRTEXTO). No celular abre nos aplicativos; para preencher, use o computador.
A14: Dados de pacientes | B14: Guarde só o que a gestão precisa (nome, contato, valor, data). Nada de diagnóstico, prontuário ou exame nestas planilhas: o kit é gestão, não é prontuário. Veja o guia LGPD do kit antes de colar qualquer tabela em uma IA.
A15: Google Sheets | B15: Faça upload no Google Drive e abra com o Google Sheets. Fórmulas, listas, cores e gráficos funcionam.
... A18: Suporte | B18: suporte@seusociogestor.com.br · resposta em até 5 dias úteis · reembolso em até 7 dias pelo mesmo canal.

Sheet Painel
A1: =Config!B4&" · Repasse e pró-labore · "&Config!B6&" de "&Config!B5 -> Clínica Vida Plena (exemplo fictício) · Repasse e pró-labore · Setembro de 2026
A2: Nada para digitar aqui. Parceiros e sócios vêm de Config; repasses, de Repasse; movimentos, de Retiradas; lucro, de Resultado mensal.
A4: Repasse devido no mês | C4: Repasse a pagar (ano) | E4: Pró-labore combinado (mês) | G4: Fora do combinado (mês) | I4: A acertar com a clínica (ano)
A5: =SUM(C9:C12) -> 2925 | C5: =SUM(G9:G12) -> 2925 | E5: =Config!$C$21 -> 18000 | G5: =SUM(I15:I20) -> 0 | I5: =SUM(G26:G31) -> 5440
A7: Médicos parceiros: no mês do painel e no ano
A8: Parceiro | B8: Produção no mês | C8: Repasse devido no mês | D8: Produção no ano | E8: Repasse no ano | F8: Pago no ano | G8: A pagar | H8: Fica com a clínica (ano) | I8: Material e insumo (ano) | J8: Margem da parceria (ano) | K8: Custo indireto das horas (ano, informativo)
A9: =IF(Config!$A$25="","",Config!$A$25) -> Dra. Renata Sousa | B9: =IF(Config!$A$25="","",SUMIFS(Repasse!$D$5:$D$40,Repasse!$C$5:$C$40,Config!$A$25,Repasse!$O$5:$O$40,Config!$B$7,Repasse!$B$5:$B$40,Config!$B$5)) -> 5850 | C9: =IF(Config!$A$25="","",SUMIFS(Repasse!$G$5:$G$40,Repasse!$C$5:$C$40,Config!$A$25,Repasse!$O$5:$O$40,Config!$B$7,Repasse!$B$5:$B$40,Config!$B$5)) -> 2925 | D9: =IF(Config!$A$25="","",SUMIFS(Repasse!$D$5:$D$40,Repasse!$C$5:$C$40,Config!$A$25,Repasse!$B$5:$B$40,Config!$B$5,Repasse!$O$5:$O$40,"<="&Config!$B$7)) -> 80680 | E9: =IF(Config!$A$25="","",SUMIFS(Repasse!$G$5:$G$40,Repasse!$C$5:$C$40,Config!$A$25,Repasse!$B$5:$B$40,Config!$B$5,Repasse!$O$5:$O$40,"<="&Config!$B$7)) -> 40340 | F9: =IF(Config!$A$25="","",SUMIFS(Repasse!$I$5:$I$40,Repasse!$C$5:$C$40,Config!$A$25,Repasse!$B$5:$B$40,Config!$B$5,Repasse!$O$5:$O$40,"<="&Config!$B$7)) -> 37415 | G9: =IF(Config!$A$25="","",E9-F9) -> 2925 | H9: =IF(Config!$A$25="","",D9-E9) -> 40340 | I9: =IF(Config!$A$25="","",SUMIFS(Repasse!$L$5:$L$40,Repasse!$C$5:$C$40,Config!$A$25,Repasse!$B$5:$B$40,Config!$B$5,Repasse!$O$5:$O$40,"<="&Config!$B$7)) -> 1226 | J9: =IF(Config!$A$25="","",H9-I9) -> 39114 | K9: =IF(Config!$A$25="","",SUMIFS(Repasse!$N$5:$N$40,Repasse!$C$5:$C$40,Config!$A$25,Repasse!$B$5:$B$40,Config!$B$5,Repasse!$O$5:$O$40,"<="&Config!$B$7)) -> 14600.006
A10: =IF(Config!$A$26="","",Config!$A$26) | B10: =IF(Config!$A$26="","",SUMIFS(Repasse!$D$5:$D$40,Repasse!$C$5:$C$40,Config!$A$26,Repasse!$O$5:$O$40,Config!$B$7,Repasse!$B$5:$B$40,Config!$B$5)) | C10: =IF(Config!$A$26="","",SUMIFS(Repasse!$G$5:$G$40,Repasse!$C$5:$C$40,Config!$A$26,Repasse!$O$5:$O$40,Config!$B$7,Repasse!$B$5:$B$40,Config!$B$5)) | D10: =IF(Config!$A$26="","",SUMIFS(Repasse!$D$5:$D$40,Repasse!$C$5:$C$40,Config!$A$26,Repasse!$B$5:$B$40,Config!$B$5,Repasse!$O$5:$O$40,"<="&Config!$B$7)) | E10: =IF(Config!$A$26="","",SUMIFS(Repasse!$G$5:$G$40,Repasse!$C$5:$C$40,Config!$A$26,Repasse!$B$5:$B$40,Config!$B$5,Repasse!$O$5:$O$40,"<="&Config!$B$7)) | F10: =IF(Config!$A$26="","",SUMIFS(Repasse!$I$5:$I$40,Repasse!$C$5:$C$40,Config!$A$26,Repasse!$B$5:$B$40,Config!$B$5,Repasse!$O$5:$O$40,"<="&Config!$B$7)) | G10: =IF(Config!$A$26="","",E10-F10) | H10: =IF(Config!$A$26="","",D10-E10) | I10: =IF(Config!$A$26="","",SUMIFS(Repasse!$L$5:$L$40,Repasse!$C$5:$C$40,Config!$A$26,Repasse!$B$5:$B$40,Config!$B$5,Repasse!$O$5:$O$40,"<="&Config!$B$7)) | J10: =IF(Config!$A$26="","",H10-I10) | K10: =IF(Config!$A$26="","",SUMIFS(Repasse!$N$5:$N$40,Repasse!$C$5:$C$40,Config!$A$26,Repasse!$B$5:$B$40,Config!$B$5,Repasse!$O$5:$O$40,"<="&Config!$B$7))
A11: =IF(Config!$A$27="","",Config!$A$27) | B11: =IF(Config!$A$27="","",SUMIFS(Repasse!$D$5:$D$40,Repasse!$C$5:$C$40,Config!$A$27,Repasse!$O$5:$O$40,Config!$B$7,Repasse!$B$5:$B$40,Config!$B$5)) | C11: =IF(Config!$A$27="","",SUMIFS(Repasse!$G$5:$G$40,Repasse!$C$5:$C$40,Config!$A$27,Repasse!$O$5:$O$40,Config!$B$7,Repasse!$B$5:$B$40,Config!$B$5)) | D11: =IF(Config!$A$27="","",SUMIFS(Repasse!$D$5:$D$40,Repasse!$C$5:$C$40,Config!$A$27,Repasse!$B$5:$B$40,Config!$B$5,Repasse!$O$5:$O$40,"<="&Config!$B$7)) | E11: =IF(Config!$A$27="","",SUMIFS(Repasse!$G$5:$G$40,Repasse!$C$5:$C$40,Config!$A$27,Repasse!$B$5:$B$40,Config!$B$5,Repasse!$O$5:$O$40,"<="&Config!$B$7)) | F11: =IF(Config!$A$27="","",SUMIFS(Repasse!$I$5:$I$40,Repasse!$C$5:$C$40,Config!$A$27,Repasse!$B$5:$B$40,Config!$B$5,Repasse!$O$5:$O$40,"<="&Config!$B$7)) | G11: =IF(Config!$A$27="","",E11-F11) | H11: =IF(Config!$A$27="","",D11-E11) | I11: =IF(Config!$A$27="","",SUMIFS(Repasse!$L$5:$L$40,Repasse!$C$5:$C$40,Config!$A$27,Repasse!$B$5:$B$40,Config!$B$5,Repasse!$O$5:$O$40,"<="&Config!$B$7)) | J11: =IF(Config!$A$27="","",H11-I11) | K11: =IF(Config!$A$27="","",SUMIFS(Repasse!$N$5:$N$40,Repasse!$C$5:$C$40,Config!$A$27,Repasse!$B$5:$B$40,Config!$B$5,Repasse!$O$5:$O$40,"<="&Config!$B$7))
A12: =IF(Config!$A$28="","",Config!$A$28) | B12: =IF(Config!$A$28="","",SUMIFS(Repasse!$D$5:$D$40,Repasse!$C$5:$C$40,Config!$A$28,Repasse!$O$5:$O$40,Config!$B$7,Repasse!$B$5:$B$40,Config!$B$5)) | C12: =IF(Config!$A$28="","",SUMIFS(Repasse!$G$5:$G$40,Repasse!$C$5:$C$40,Config!$A$28,Repasse!$O$5:$O$40,Config!$B$7,Repasse!$B$5:$B$40,Config!$B$5)) | D12: =IF(Config!$A$28="","",SUMIFS(Repasse!$D$5:$D$40,Repasse!$C$5:$C$40,Config!$A$28,Repasse!$B$5:$B$40,Config!$B$5,Repasse!$O$5:$O$40,"<="&Config!$B$7)) | E12: =IF(Config!$A$28="","",SUMIFS(Repasse!$G$5:$G$40,Repasse!$C$5:$C$40,Config!$A$28,Repasse!$B$5:$B$40,Config!$B$5,Repasse!$O$5:$O$40,"<="&Config!$B$7)) | F12: =IF(Config!$A$28="","",SUMIFS(Repasse!$I$5:$I$40,Repasse!$C$5:$C$40,Config!$A$28,Repasse!$B$5:$B$40,Config!$B$5,Repasse!$O$5:$O$40,"<="&Config!$B$7)) | G12: =IF(Config!$A$28="","",E12-F12) | H12: =IF(Config!$A$28="","",D12-E12) | I12: =IF(Config!$A$28="","",SUMIFS(Repasse!$L$5:$L$40,Repasse!$C$5:$C$40,Config!$A$28,Repasse!$B$5:$B$40,Config!$B$5,Repasse!$O$5:$O$40,"<="&Config!$B$7)) | J12: =IF(Config!$A$28="","",H12-I12) | K12: =IF(Config!$A$28="","",SUMIFS(Repasse!$N$5:$N$40,Repasse!$C$5:$C$40,Config!$A$28,Repasse!$B$5:$B$40,Config!$B$5,Repasse!$O$5:$O$40,"<="&Config!$B$7))
A13: Sócios no mês
A14: Sócio | B14: Pró-labore combinado | C14: Pró-labore pago | D14: Retiradas extras | E14: Despesas pessoais pela clínica | F14: Devoluções | G14: Distribuição de lucro | H14: Total retirado | I14: Fora do combinado | J14: Situação
A15: =IF(Config!$A$15="","",Config!$A$15) -> Dra. Carolina Mendes | B15: =IF(Config!$A$15="","",Config!$C$15) -> 9000 | C15: =IF(Config!$A$15="","",SUMIFS(Retiradas!$E$5:$E$404,Retiradas!$B$5:$B$404,Config!$A$15,Retiradas!$C$5:$C$404,"Pró-labore",Retiradas!$G$5:$G$404,Config!$B$7,Retiradas!$H$5:$H$404,Config!$B$5)) -> 0 | D15: =IF(Config!$A$15="","",SUMIFS(Retiradas!$E$5:$E$404,Retiradas!$B$5:$B$404,Config!$A$15,Retiradas!$C$5:$C$404,"Retirada extra",Retiradas!$G$5:$G$404,Config!$B$7,Retiradas!$H$5:$H$404,Config!$B$5)) -> 0 | E15: =IF(Config!$A$15="","",SUMIFS(Retiradas!$E$5:$E$404,Retiradas!$B$5:$B$404,Config!$A$15,Retiradas!$C$5:$C$404,"Despesa pessoal paga pela clínica",Retiradas!$G$5:$G$404,Config!$B$7,Retiradas!$H$5:$H$404,Config!$B$5)) -> 0 | F15: =IF(Config!$A$15="","",SUMIFS(Retiradas!$E$5:$E$404,Retiradas!$B$5:$B$404,Config!$A$15,Retiradas!$C$5:$C$404,"Devolução à clínica",Retiradas!$G$5:$G$404,Config!$B$7,Retiradas!$H$5:$H$404,Config!$B$5)) -> 0 | G15: =IF(Config!$A$15="","",SUMIFS(Retiradas!$E$5:$E$404,Retiradas!$B$5:$B$404,Config!$A$15,Retiradas!$C$5:$C$404,"Distribuição de lucro",Retiradas!$G$5:$G$404,Config!$B$7,Retiradas!$H$5:$H$404,Config!$B$5)) -> 0 | H15: =IF(Config!$A$15="","",C15+D15+E15-F15+G15) -> 0 | I15: =IF(Config!$A$15="","",D15+E15-F15) -> 0 | J15: =IF(Config!$A$15="","",IF(I15>0,"Acima do combinado",IF(C15<B15,"Pró-labore ainda não pago por completo","Conforme o combinado"))) -> Pró-labore ainda não pago por completo
A16: =IF(Config!$A$16="","",Config!$A$16) -> Dr. Paulo Andrade | B16: =IF(Config!$A$16="","",Config!$C$16) -> 9000 | C16: =IF(Config!$A$16="","",SUMIFS(Retiradas!$E$5:$E$404,Retiradas!$B$5:$B$404,Config!$A$16,Retiradas!$C$5:$C$404,"Pró-labore",Retiradas!$G$5:$G$404,Config!$B$7,Retiradas!$H$5:$H$404,Config!$B$5)) -> 0 | D16: =IF(Config!$A$16="","",SUMIFS(Retiradas!$E$5:$E$404,Retiradas!$B$5:$B$404,Config!$A$16,Retiradas!$C$5:$C$404,"Retirada extra",Retiradas!$G$5:$G$404,Config!$B$7,Retiradas!$H$5:$H$404,Config!$B$5)) -> 0 | E16: =IF(Config!$A$16="","",SUMIFS(Retiradas!$E$5:$E$404,Retiradas!$B$5:$B$404,Config!$A$16,Retiradas!$C$5:$C$404,"Despesa pessoal paga pela clínica",Retiradas!$G$5:$G$404,Config!$B$7,Retiradas!$H$5:$H$404,Config!$B$5)) -> 0 | F16: =IF(Config!$A$16="","",SUMIFS(Retiradas!$E$5:$E$404,Retiradas!$B$5:$B$404,Config!$A$16,Retiradas!$C$5:$C$404,"Devolução à clínica",Retiradas!$G$5:$G$404,Config!$B$7,Retiradas!$H$5:$H$404,Config!$B$5)) -> 0 | G16: =IF(Config!$A$16="","",SUMIFS(Retiradas!$E$5:$E$404,Retiradas!$B$5:$B$404,Config!$A$16,Retiradas!$C$5:$C$404,"Distribuição de lucro",Retiradas!$G$5:$G$404,Config!$B$7,Retiradas!$H$5:$H$404,Config!$B$5)) -> 0 | H16: =IF(Config!$A$16="","",C16+D16+E16-F16+G16) -> 0 | I16: =IF(Config!$A$16="","",D16+E16-F16) -> 0 | J16: =IF(Config!$A$16="","",IF(I16>0,"Acima do combinado",IF(C16<B16,"Pró-labore ainda não pago por completo","Conforme o combinado"))) -> Pró-labore ainda não pago por completo
A17: =IF(Config!$A$17="","",Config!$A$17) | B17: =IF(Config!$A$17="","",Config!$C$17) | C17: =IF(Config!$A$17="","",SUMIFS(Retiradas!$E$5:$E$404,Retiradas!$B$5:$B$404,Config!$A$17,Retiradas!$C$5:$C$404,"Pró-labore",Retiradas!$G$5:$G$404,Config!$B$7,Retiradas!$H$5:$H$404,Config!$B$5)) | D17: =IF(Config!$A$17="","",SUMIFS(Retiradas!$E$5:$E$404,Retiradas!$B$5:$B$404,Config!$A$17,Retiradas!$C$5:$C$404,"Retirada extra",Retiradas!$G$5:$G$404,Config!$B$7,Retiradas!$H$5:$H$404,Config!$B$5)) | E17: =IF(Config!$A$17="","",SUMIFS(Retiradas!$E$5:$E$404,Retiradas!$B$5:$B$404,Config!$A$17,Retiradas!$C$5:$C$404,"Despesa pessoal paga pela clínica",Retiradas!$G$5:$G$404,Config!$B$7,Retiradas!$H$5:$H$404,Config!$B$5)) | F17: =IF(Config!$A$17="","",SUMIFS(Retiradas!$E$5:$E$404,Retiradas!$B$5:$B$404,Config!$A$17,Retiradas!$C$5:$C$404,"Devolução à clínica",Retiradas!$G$5:$G$404,Config!$B$7,Retiradas!$H$5:$H$404,Config!$B$5)) | G17: =IF(Config!$A$17="","",SUMIFS(Retiradas!$E$5:$E$404,Retiradas!$B$5:$B$404,Config!$A$17,Retiradas!$C$5:$C$404,"Distribuição de lucro",Retiradas!$G$5:$G$404,Config!$B$7,Retiradas!$H$5:$H$404,Config!$B$5)) | H17: =IF(Config!$A$17="","",C17+D17+E17-F17+G17) | I17: =IF(Config!$A$17="","",D17+E17-F17) | J17: =IF(Config!$A$17="","",IF(I17>0,"Acima do combinado",IF(C17<B17,"Pró-labore ainda não pago por completo","Conforme o combinado")))
A18: =IF(Config!$A$18="","",Config!$A$18) | B18: =IF(Config!$A$18="","",Config!$C$18) | C18: =IF(Config!$A$18="","",SUMIFS(Retiradas!$E$5:$E$404,Retiradas!$B$5:$B$404,Config!$A$18,Retiradas!$C$5:$C$404,"Pró-labore",Retiradas!$G$5:$G$404,Config!$B$7,Retiradas!$H$5:$H$404,Config!$B$5)) | D18: =IF(Config!$A$18="","",SUMIFS(Retiradas!$E$5:$E$404,Retiradas!$B$5:$B$404,Config!$A$18,Retiradas!$C$5:$C$404,"Retirada extra",Retiradas!$G$5:$G$404,Config!$B$7,Retiradas!$H$5:$H$404,Config!$B$5)) | E18: =IF(Config!$A$18="","",SUMIFS(Retiradas!$E$5:$E$404,Retiradas!$B$5:$B$404,Config!$A$18,Retiradas!$C$5:$C$404,"Despesa pessoal paga pela clínica",Retiradas!$G$5:$G$404,Config!$B$7,Retiradas!$H$5:$H$404,Config!$B$5)) | F18: =IF(Config!$A$18="","",SUMIFS(Retiradas!$E$5:$E$404,Retiradas!$B$5:$B$404,Config!$A$18,Retiradas!$C$5:$C$404,"Devolução à clínica",Retiradas!$G$5:$G$404,Config!$B$7,Retiradas!$H$5:$H$404,Config!$B$5)) | G18: =IF(Config!$A$18="","",SUMIFS(Retiradas!$E$5:$E$404,Retiradas!$B$5:$B$404,Config!$A$18,Retiradas!$C$5:$C$404,"Distribuição de lucro",Retiradas!$G$5:$G$404,Config!$B$7,Retiradas!$H$5:$H$404,Config!$B$5)) | H18: =IF(Config!$A$18="","",C18+D18+E18-F18+G18) | I18: =IF(Config!$A$18="","",D18+E18-F18) | J18: =IF(Config!$A$18="","",IF(I18>0,"Acima do combinado",IF(C18<B18,"Pró-labore ainda não pago por completo","Conforme o combinado")))
A19: =IF(Config!$A$19="","",Config!$A$19) | B19: =IF(Config!$A$19="","",Config!$C$19) | C19: =IF(Config!$A$19="","",SUMIFS(Retiradas!$E$5:$E$404,Retiradas!$B$5:$B$404,Config!$A$19,Retiradas!$C$5:$C$404,"Pró-labore",Retiradas!$G$5:$G$404,Config!$B$7,Retiradas!$H$5:$H$404,Config!$B$5)) | D19: =IF(Config!$A$19="","",SUMIFS(Retiradas!$E$5:$E$404,Retiradas!$B$5:$B$404,Config!$A$19,Retiradas!$C$5:$C$404,"Retirada extra",Retiradas!$G$5:$G$404,Config!$B$7,Retiradas!$H$5:$H$404,Config!$B$5)) | E19: =IF(Config!$A$19="","",SUMIFS(Retiradas!$E$5:$E$404,Retiradas!$B$5:$B$404,Config!$A$19,Retiradas!$C$5:$C$404,"Despesa pessoal paga pela clínica",Retiradas!$G$5:$G$404,Config!$B$7,Retiradas!$H$5:$H$404,Config!$B$5)) | F19: =IF(Config!$A$19="","",SUMIFS(Retiradas!$E$5:$E$404,Retiradas!$B$5:$B$404,Config!$A$19,Retiradas!$C$5:$C$404,"Devolução à clínica",Retiradas!$G$5:$G$404,Config!$B$7,Retiradas!$H$5:$H$404,Config!$B$5)) | G19: =IF(Config!$A$19="","",SUMIFS(Retiradas!$E$5:$E$404,Retiradas!$B$5:$B$404,Config!$A$19,Retiradas!$C$5:$C$404,"Distribuição de lucro",Retiradas!$G$5:$G$404,Config!$B$7,Retiradas!$H$5:$H$404,Config!$B$5)) | H19: =IF(Config!$A$19="","",C19+D19+E19-F19+G19) | I19: =IF(Config!$A$19="","",D19+E19-F19) | J19: =IF(Config!$A$19="","",IF(I19>0,"Acima do combinado",IF(C19<B19,"Pró-labore ainda não pago por completo","Conforme o combinado")))
A20: =IF(Config!$A$20="","",Config!$A$20) | B20: =IF(Config!$A$20="","",Config!$C$20) | C20: =IF(Config!$A$20="","",SUMIFS(Retiradas!$E$5:$E$404,Retiradas!$B$5:$B$404,Config!$A$20,Retiradas!$C$5:$C$404,"Pró-labore",Retiradas!$G$5:$G$404,Config!$B$7,Retiradas!$H$5:$H$404,Config!$B$5)) | D20: =IF(Config!$A$20="","",SUMIFS(Retiradas!$E$5:$E$404,Retiradas!$B$5:$B$404,Config!$A$20,Retiradas!$C$5:$C$404,"Retirada extra",Retiradas!$G$5:$G$404,Config!$B$7,Retiradas!$H$5:$H$404,Config!$B$5)) | E20: =IF(Config!$A$20="","",SUMIFS(Retiradas!$E$5:$E$404,Retiradas!$B$5:$B$404,Config!$A$20,Retiradas!$C$5:$C$404,"Despesa pessoal paga pela clínica",Retiradas!$G$5:$G$404,Config!$B$7,Retiradas!$H$5:$H$404,Config!$B$5)) | F20: =IF(Config!$A$20="","",SUMIFS(Retiradas!$E$5:$E$404,Retiradas!$B$5:$B$404,Config!$A$20,Retiradas!$C$5:$C$404,"Devolução à clínica",Retiradas!$G$5:$G$404,Config!$B$7,Retiradas!$H$5:$H$404,Config!$B$5)) | G20: =IF(Config!$A$20="","",SUMIFS(Retiradas!$E$5:$E$404,Retiradas!$B$5:$B$404,Config!$A$20,Retiradas!$C$5:$C$404,"Distribuição de lucro",Retiradas!$G$5:$G$404,Config!$B$7,Retiradas!$H$5:$H$404,Config!$B$5)) | H20: =IF(Config!$A$20="","",C20+D20+E20-F20+G20) | I20: =IF(Config!$A$20="","",D20+E20-F20) | J20: =IF(Config!$A$20="","",IF(I20>0,"Acima do combinado",IF(C20<B20,"Pró-labore ainda não pago por completo","Conforme o combinado")))
A21: Fora do combinado = retiradas extras + despesas pessoais pagas pela clínica − devoluções. Distribuição de lucro segue a regra de Config e não conta como "fora".
A24: Sócios no ano, até o mês do painel
A25: Sócio | B25: Pró-labore combinado até o mês | C25: Pró-labore pago | D25: Retiradas extras | E25: Despesas pessoais pela clínica | F25: Devoluções | G25: A acertar com a clínica | H25: Distribuição devida (trimestres fechados) | I25: Distribuição recebida | J25: Distribuição a receber
A26: =IF(Config!$A$15="","",Config!$A$15) -> Dra. Carolina Mendes | B26: =IF(Config!$A$15="","",Config!$C$15*Config!$B$7) -> 81000 | C26: =IF(Config!$A$15="","",SUMIFS(Retiradas!$E$5:$E$404,Retiradas!$B$5:$B$404,Config!$A$15,Retiradas!$C$5:$C$404,"Pró-labore",Retiradas!$G$5:$G$404,"<="&Config!$B$7,Retiradas!$H$5:$H$404,Config!$B$5)) -> 72000 | D26: =IF(Config!$A$15="","",SUMIFS(Retiradas!$E$5:$E$404,Retiradas!$B$5:$B$404,Config!$A$15,Retiradas!$C$5:$C$404,"Retirada extra",Retiradas!$G$5:$G$404,"<="&Config!$B$7,Retiradas!$H$5:$H$404,Config!$B$5)) -> 1500 | E26: =IF(Config!$A$15="","",SUMIFS(Retiradas!$E$5:$E$404,Retiradas!$B$5:$B$404,Config!$A$15,Retiradas!$C$5:$C$404,"Despesa pessoal paga pela clínica",Retiradas!$G$5:$G$404,"<="&Config!$B$7,Retiradas!$H$5:$H$404,Config!$B$5)) -> 1860 | F26: =IF(Config!$A$15="","",SUMIFS(Retiradas!$E$5:$E$404,Retiradas!$B$5:$B$404,Config!$A$15,Retiradas!$C$5:$C$404,"Devolução à clínica",Retiradas!$G$5:$G$404,"<="&Config!$B$7,Retiradas!$H$5:$H$404,Config!$B$5)) -> 620 | G26: =IF(Config!$A$15="","",D26+E26-F26) -> 2740 | H26: =IF(Config!$A$15="","",SUM($G$36:$G$39)*Config!$B$15) -> 3204.435 | I26: =IF(Config!$A$15="","",SUMIFS(Retiradas!$E$5:$E$404,Retiradas!$B$5:$B$404,Config!$A$15,Retiradas!$C$5:$C$404,"Distribuição de lucro",Retiradas!$G$5:$G$404,"<="&Config!$B$7,Retiradas!$H$5:$H$404,Config!$B$5)) -> 3204 | J26: =IF(Config!$A$15="","",IF(ABS(H26-I26)<1,0,H26-I26)) -> 0
A27: =IF(Config!$A$16="","",Config!$A$16) -> Dr. Paulo Andrade | B27: =IF(Config!$A$16="","",Config!$C$16*Config!$B$7) -> 81000 | C27: =IF(Config!$A$16="","",SUMIFS(Retiradas!$E$5:$E$404,Retiradas!$B$5:$B$404,Config!$A$16,Retiradas!$C$5:$C$404,"Pró-labore",Retiradas!$G$5:$G$404,"<="&Config!$B$7,Retiradas!$H$5:$H$404,Config!$B$5)) -> 72000 | D27: =IF(Config!$A$16="","",SUMIFS(Retiradas!$E$5:$E$404,Retiradas!$B$5:$B$404,Config!$A$16,Retiradas!$C$5:$C$404,"Retirada extra",Retiradas!$G$5:$G$404,"<="&Config!$B$7,Retiradas!$H$5:$H$404,Config!$B$5)) -> 2000 | E27: =IF(Config!$A$16="","",SUMIFS(Retiradas!$E$5:$E$404,Retiradas!$B$5:$B$404,Config!$A$16,Retiradas!$C$5:$C$404,"Despesa pessoal paga pela clínica",Retiradas!$G$5:$G$404,"<="&Config!$B$7,Retiradas!$H$5:$H$404,Config!$B$5)) -> 700 | F27: =IF(Config!$A$16="","",SUMIFS(Retiradas!$E$5:$E$404,Retiradas!$B$5:$B$404,Config!$A$16,Retiradas!$C$5:$C$404,"Devolução à clínica",Retiradas!$G$5:$G$404,"<="&Config!$B$7,Retiradas!$H$5:$H$404,Config!$B$5)) -> 0 | G27: =IF(Config!$A$16="","",D27+E27-F27) -> 2700 | H27: =IF(Config!$A$16="","",SUM($G$36:$G$39)*Config!$B$16) -> 3204.435 | I27: =IF(Config!$A$16="","",SUMIFS(Retiradas!$E$5:$E$404,Retiradas!$B$5:$B$404,Config!$A$16,Retiradas!$C$5:$C$404,"Distribuição de lucro",Retiradas!$G$5:$G$404,"<="&Config!$B$7,Retiradas!$H$5:$H$404,Config!$B$5)) -> 3205 | J27: =IF(Config!$A$16="","",IF(ABS(H27-I27)<1,0,H27-I27)) -> 0
A28: =IF(Config!$A$17="","",Config!$A$17) | B28: =IF(Config!$A$17="","",Config!$C$17*Config!$B$7) | C28: =IF(Config!$A$17="","",SUMIFS(Retiradas!$E$5:$E$404,Retiradas!$B$5:$B$404,Config!$A$17,Retiradas!$C$5:$C$404,"Pró-labore",Retiradas!$G$5:$G$404,"<="&Config!$B$7,Retiradas!$H$5:$H$404,Config!$B$5)) | D28: =IF(Config!$A$17="","",SUMIFS(Retiradas!$E$5:$E$404,Retiradas!$B$5:$B$404,Config!$A$17,Retiradas!$C$5:$C$404,"Retirada extra",Retiradas!$G$5:$G$404,"<="&Config!$B$7,Retiradas!$H$5:$H$404,Config!$B$5)) | E28: =IF(Config!$A$17="","",SUMIFS(Retiradas!$E$5:$E$404,Retiradas!$B$5:$B$404,Config!$A$17,Retiradas!$C$5:$C$404,"Despesa pessoal paga pela clínica",Retiradas!$G$5:$G$404,"<="&Config!$B$7,Retiradas!$H$5:$H$404,Config!$B$5)) | F28: =IF(Config!$A$17="","",SUMIFS(Retiradas!$E$5:$E$404,Retiradas!$B$5:$B$404,Config!$A$17,Retiradas!$C$5:$C$404,"Devolução à clínica",Retiradas!$G$5:$G$404,"<="&Config!$B$7,Retiradas!$H$5:$H$404,Config!$B$5)) | G28: =IF(Config!$A$17="","",D28+E28-F28) | H28: =IF(Config!$A$17="","",SUM($G$36:$G$39)*Config!$B$17) | I28: =IF(Config!$A$17="","",SUMIFS(Retiradas!$E$5:$E$404,Retiradas!$B$5:$B$404,Config!$A$17,Retiradas!$C$5:$C$404,"Distribuição de lucro",Retiradas!$G$5:$G$404,"<="&Config!$B$7,Retiradas!$H$5:$H$404,Config!$B$5)) | J28: =IF(Config!$A$17="","",IF(ABS(H28-I28)<1,0,H28-I28))
A29: =IF(Config!$A$18="","",Config!$A$18) | B29: =IF(Config!$A$18="","",Config!$C$18*Config!$B$7) | C29: =IF(Config!$A$18="","",SUMIFS(Retiradas!$E$5:$E$404,Retiradas!$B$5:$B$404,Config!$A$18,Retiradas!$C$5:$C$404,"Pró-labore",Retiradas!$G$5:$G$404,"<="&Config!$B$7,Retiradas!$H$5:$H$404,Config!$B$5)) | D29: =IF(Config!$A$18="","",SUMIFS(Retiradas!$E$5:$E$404,Retiradas!$B$5:$B$404,Config!$A$18,Retiradas!$C$5:$C$404,"Retirada extra",Retiradas!$G$5:$G$404,"<="&Config!$B$7,Retiradas!$H$5:$H$404,Config!$B$5)) | E29: =IF(Config!$A$18="","",SUMIFS(Retiradas!$E$5:$E$404,Retiradas!$B$5:$B$404,Config!$A$18,Retiradas!$C$5:$C$404,"Despesa pessoal paga pela clínica",Retiradas!$G$5:$G$404,"<="&Config!$B$7,Retiradas!$H$5:$H$404,Config!$B$5)) | F29: =IF(Config!$A$18="","",SUMIFS(Retiradas!$E$5:$E$404,Retiradas!$B$5:$B$404,Config!$A$18,Retiradas!$C$5:$C$404,"Devolução à clínica",Retiradas!$G$5:$G$404,"<="&Config!$B$7,Retiradas!$H$5:$H$404,Config!$B$5)) | G29: =IF(Config!$A$18="","",D29+E29-F29) | H29: =IF(Config!$A$18="","",SUM($G$36:$G$39)*Config!$B$18) | I29: =IF(Config!$A$18="","",SUMIFS(Retiradas!$E$5:$E$404,Retiradas!$B$5:$B$404,Config!$A$18,Retiradas!$C$5:$C$404,"Distribuição de lucro",Retiradas!$G$5:$G$404,"<="&Config!$B$7,Retiradas!$H$5:$H$404,Config!$B$5)) | J29: =IF(Config!$A$18="","",IF(ABS(H29-I29)<1,0,H29-I29))
A30: =IF(Config!$A$19="","",Config!$A$19) | B30: =IF(Config!$A$19="","",Config!$C$19*Config!$B$7) | C30: =IF(Config!$A$19="","",SUMIFS(Retiradas!$E$5:$E$404,Retiradas!$B$5:$B$404,Config!$A$19,Retiradas!$C$5:$C$404,"Pró-labore",Retiradas!$G$5:$G$404,"<="&Config!$B$7,Retiradas!$H$5:$H$404,Config!$B$5)) | D30: =IF(Config!$A$19="","",SUMIFS(Retiradas!$E$5:$E$404,Retiradas!$B$5:$B$404,Config!$A$19,Retiradas!$C$5:$C$404,"Retirada extra",Retiradas!$G$5:$G$404,"<="&Config!$B$7,Retiradas!$H$5:$H$404,Config!$B$5)) | E30: =IF(Config!$A$19="","",SUMIFS(Retiradas!$E$5:$E$404,Retiradas!$B$5:$B$404,Config!$A$19,Retiradas!$C$5:$C$404,"Despesa pessoal paga pela clínica",Retiradas!$G$5:$G$404,"<="&Config!$B$7,Retiradas!$H$5:$H$404,Config!$B$5)) | F30: =IF(Config!$A$19="","",SUMIFS(Retiradas!$E$5:$E$404,Retiradas!$B$5:$B$404,Config!$A$19,Retiradas!$C$5:$C$404,"Devolução à clínica",Retiradas!$G$5:$G$404,"<="&Config!$B$7,Retiradas!$H$5:$H$404,Config!$B$5)) | G30: =IF(Config!$A$19="","",D30+E30-F30) | H30: =IF(Config!$A$19="","",SUM($G$36:$G$39)*Config!$B$19) | I30: =IF(Config!$A$19="","",SUMIFS(Retiradas!$E$5:$E$404,Retiradas!$B$5:$B$404,Config!$A$19,Retiradas!$C$5:$C$404,"Distribuição de lucro",Retiradas!$G$5:$G$404,"<="&Config!$B$7,Retiradas!$H$5:$H$404,Config!$B$5)) | J30: =IF(Config!$A$19="","",IF(ABS(H30-I30)<1,0,H30-I30))
A31: =IF(Config!$A$20="","",Config!$A$20) | B31: =IF(Config!$A$20="","",Config!$C$20*Config!$B$7) | C31: =IF(Config!$A$20="","",SUMIFS(Retiradas!$E$5:$E$404,Retiradas!$B$5:$B$404,Config!$A$20,Retiradas!$C$5:$C$404,"Pró-labore",Retiradas!$G$5:$G$404,"<="&Config!$B$7,Retiradas!$H$5:$H$404,Config!$B$5)) | D31: =IF(Config!$A$20="","",SUMIFS(Retiradas!$E$5:$E$404,Retiradas!$B$5:$B$404,Config!$A$20,Retiradas!$C$5:$C$404,"Retirada extra",Retiradas!$G$5:$G$404,"<="&Config!$B$7,Retiradas!$H$5:$H$404,Config!$B$5)) | E31: =IF(Config!$A$20="","",SUMIFS(Retiradas!$E$5:$E$404,Retiradas!$B$5:$B$404,Config!$A$20,Retiradas!$C$5:$C$404,"Despesa pessoal paga pela clínica",Retiradas!$G$5:$G$404,"<="&Config!$B$7,Retiradas!$H$5:$H$404,Config!$B$5)) | F31: =IF(Config!$A$20="","",SUMIFS(Retiradas!$E$5:$E$404,Retiradas!$B$5:$B$404,Config!$A$20,Retiradas!$C$5:$C$404,"Devolução à clínica",Retiradas!$G$5:$G$404,"<="&Config!$B$7,Retiradas!$H$5:$H$404,Config!$B$5)) | G31: =IF(Config!$A$20="","",D31+E31-F31) | H31: =IF(Config!$A$20="","",SUM($G$36:$G$39)*Config!$B$20) | I31: =IF(Config!$A$20="","",SUMIFS(Retiradas!$E$5:$E$404,Retiradas!$B$5:$B$404,Config!$A$20,Retiradas!$C$5:$C$404,"Distribuição de lucro",Retiradas!$G$5:$G$404,"<="&Config!$B$7,Retiradas!$H$5:$H$404,Config!$B$5)) | J31: =IF(Config!$A$20="","",IF(ABS(H31-I31)<1,0,H31-I31))
A32: A acertar com a clínica: o sócio devolve ou desconta da próxima distribuição de lucro. Distribuição devida = distribuível dos trimestres fechados × participação. Pró-labore, retiradas, repasse e distribuição têm tratamento tributário próprio: combine o formato com o contador.
A34: Lucro e distribuição por trimestre
A35: Trimestre | B35: Entradas | C35: Saídas (sem sócios) | D35: Pró-labore fixo | E35: Resultado após pró-labore | F35: Fechado? | G35: Distribuível aos sócios | H35: Já distribuído | I35: Falta distribuir
A36: 1º trimestre | B36: =SUM('Resultado mensal'!B5:B7) -> 91500 | C36: =SUM('Resultado mensal'!C5:C7) -> 53443.72 | D36: =SUM('Resultado mensal'!D5:D7) -> 54000 | E36: =SUM('Resultado mensal'!E5:E7) -> -15943.72 | F36: =IF(Config!$B$7>3,"Sim","Em andamento") -> Sim | G36: =IF(AND(F36="Sim",E36>=Config!$B$10),E36*Config!$B$9,0) -> 0 | H36: =SUMIFS(Retiradas!$E$5:$E$404,Retiradas!$C$5:$C$404,"Distribuição de lucro",Retiradas!$F$5:$F$404,A36,Retiradas!$H$5:$H$404,Config!$B$5) -> 0 | I36: =IF(ABS(G36-H36)<1,0,G36-H36) -> 0
A37: 2º trimestre | B37: =SUM('Resultado mensal'!B8:B10) -> 132775 | C37: =SUM('Resultado mensal'!C8:C10) -> 65957.26 | D37: =SUM('Resultado mensal'!D8:D10) -> 54000 | E37: =SUM('Resultado mensal'!E8:E10) -> 12817.74 | F37: =IF(Config!$B$7>6,"Sim","Em andamento") -> Sim | G37: =IF(AND(F37="Sim",E37>=Config!$B$10),E37*Config!$B$9,0) -> 6408.87 | H37: =SUMIFS(Retiradas!$E$5:$E$404,Retiradas!$C$5:$C$404,"Distribuição de lucro",Retiradas!$F$5:$F$404,A37,Retiradas!$H$5:$H$404,Config!$B$5) -> 6409 | I37: =IF(ABS(G37-H37)<1,0,G37-H37) -> 0
A38: 3º trimestre | B38: =SUM('Resultado mensal'!B11:B13) -> 121022 | C38: =SUM('Resultado mensal'!C11:C13) -> 57441.21 | D38: =SUM('Resultado mensal'!D11:D13) -> 54000 | E38: =SUM('Resultado mensal'!E11:E13) -> 9580.79 | F38: =IF(Config!$B$7>9,"Sim","Em andamento") -> Em andamento | G38: =IF(AND(F38="Sim",E38>=Config!$B$10),E38*Config!$B$9,0) -> 0 | H38: =SUMIFS(Retiradas!$E$5:$E$404,Retiradas!$C$5:$C$404,"Distribuição de lucro",Retiradas!$F$5:$F$404,A38,Retiradas!$H$5:$H$404,Config!$B$5) -> 0 | I38: =IF(ABS(G38-H38)<1,0,G38-H38) -> 0
A39: 4º trimestre | B39: =SUM('Resultado mensal'!B14:B16) -> 0 | C39: =SUM('Resultado mensal'!C14:C16) -> 0 | D39: =SUM('Resultado mensal'!D14:D16) -> 0 | E39: =SUM('Resultado mensal'!E14:E16) -> 0 | F39: =IF(Config!$B$7>12,"Sim","Em andamento") -> Em andamento | G39: =IF(AND(F39="Sim",E39>=Config!$B$10),E39*Config!$B$9,0) -> 0 | H39: =SUMIFS(Retiradas!$E$5:$E$404,Retiradas!$C$5:$C$404,"Distribuição de lucro",Retiradas!$F$5:$F$404,A39,Retiradas!$H$5:$H$404,Config!$B$5) -> 0 | I39: =IF(ABS(G39-H39)<1,0,G39-H39) -> 0
A40: Falta distribuir em amarelo: lucro do trimestre fechado ainda não pago aos sócios. Em vermelho: distribuiu mais do que a regra permite (ou o trimestre ainda não fechou). Diferenças de centavos são ignoradas.

Sheet Config
A1: Configurações
A2: Células amarelas: você preenche. Sócios, pró-labore combinado, médicos parceiros com % de repasse e a regra de distribuição de lucro ficam aqui.
A4: Clínica | B4: Clínica Vida Plena (exemplo fictício) | H4: Meses | J4: Tipos de movimento
A5: Ano | B5: 2026 | H5: Janeiro | J5: Pró-labore
A6: Mês do painel | B6: Setembro | H6: Fevereiro | J6: Retirada extra
A7: Número do mês | B7: =MATCH(B6,$H$5:$H$16,0) -> 9 | H7: Março | J7: Despesa pessoal paga pela clínica
A8: Trimestre do painel | B8: =ROUNDUP(B7/3,0) -> 3 | H8: Abril | J8: Devolução à clínica
A9: Parte do lucro do trimestre distribuída aos sócios | B9: 0.5 | D9: Regra combinada entre os sócios: o restante do lucro fica na clínica (reserva e provisões). Trimestre com lucro abaixo do mínimo não distribui. | H9: Maio | J9: Distribuição de lucro
A10: Lucro mínimo do trimestre para haver distribuição | B10: 3000 | D10: A distribuição é calculada só para trimestres já fechados (os três meses lançados em Resultado mensal e anteriores ao mês do painel). | H10: Junho
A11: Custo indireto por hora (planilha 05; informativo) | B11: 71.4286 | D11: Quanto vale a hora de sala, recepção e estrutura (custos fixos ÷ horas de atendimento: R$ 71,43 no exemplo). Serve só para MOSTRAR o tamanho da estrutura que o parceiro usa: esse custo NÃO é descontado da margem da parceria, porque a estrutura já está inteira dentro do custo-hora dos sócios na planilha 05 (10.000 de custo fixo ÷ 140 h) e o pró-labore dos dois sócios já cobre o mês. Descontar de novo cobraria a mesma estrutura duas vezes. A margem da parceria desconta só o que o parceiro consome de verdade: material e insumo. | H11: Julho
H12: Agosto
A13: Sócios (até 6) | H13: Setembro
A14: Sócio | B14: Participação no lucro | C14: Pró-labore fixo mensal | H14: Outubro
A15: Dra. Carolina Mendes | B15: 0.5 | C15: 9000 | H15: Novembro
A16: Dr. Paulo Andrade | B16: 0.5 | C16: 9000 | H16: Dezembro
A21: Total | B21: =SUM(B15:B20) -> 1 | C21: =SUM(C15:C20) -> 18000 | D21: =IF(ROUND(B21,4)=1,"","A participação deve somar 100 %")
A23: Médicos parceiros por repasse (até 4)
A24: Parceiro | B24: % de repasse (parte do parceiro) | C24: Sobre | D24: Pago no dia
A25: Dra. Renata Sousa | B25: 0.5 | C25: Produção do mês | D25: 10
A29: Preencha de cima para baixo, sem pular linha. Repasse sobre a produção: o parceiro recebe pelo que atendeu, e a glosa do convênio fica com a clínica. Sobre o recebido: o parceiro espera o convênio pagar. Combine por escrito; a planilha só calcula.
A30: Pró-labore fixo: o valor combinado que cada sócio retira todo mês. Retirada extra e despesa pessoal paga pela clínica são o que passou do combinado.

Sheet Repasse
A1: Repasse aos médicos parceiros
A2: Uma linha por parceiro e mês. Amarelo: produção e horas atendidas (Painel da 01, por profissional, com o mês escolhido em Config) e o que foi pago. O resto é calculado.
A4: Mês | B4: Ano | C4: Parceiro | D4: Produção do mês (R$) | E4: Horas atendidas | F4: % de repasse | G4: Repasse devido (R$) | H4: Pago em | I4: Valor pago (R$) | J4: Diferença (R$) | K4: Fica com a clínica (R$) | L4: Material e insumo do parceiro (R$) | M4: Margem da parceria (R$) | N4: Custo indireto das horas (informativo, R$)
A5: Janeiro | B5: 2026 | C5: Dra. Renata Sousa | D5: 7450 | E5: 17.7 | F5: =IF(C5="","",IFERROR(INDEX(Config!$B$25:$B$28,MATCH(C5,Config!$A$25:$A$28,0)),"")) -> 0.5 | G5: =IF(OR(C5="",D5="",F5=""),"",ROUND(D5*F5,0)) -> 3725 | H5: 46063 | I5: 3725 | J5: =IF(G5="","",IF(I5="",G5,G5-I5)) -> 0 | K5: =IF(G5="","",D5-G5) -> 3725 | L5: 106 | M5: =IF(G5="","",K5-N(L5)) -> 3619 | N5: =IF(OR(G5="",E5=""),"",E5*Config!$B$11) -> 1264.2862 | O5: =IF(A5="","",MATCH(A5,Config!$H$5:$H$16,0)) -> 1
A6: Fevereiro | B6: 2026 | C6: Dra. Renata Sousa | D6: 6510 | E6: 18.3 | F6: =IF(C6="","",IFERROR(INDEX(Config!$B$25:$B$28,MATCH(C6,Config!$A$25:$A$28,0)),"")) -> 0.5 | G6: =IF(OR(C6="",D6="",F6=""),"",ROUND(D6*F6,0)) -> 3255 | H6: 46091 | I6: 3255 | J6: =IF(G6="","",IF(I6="",G6,G6-I6)) -> 0 | K6: =IF(G6="","",D6-G6) -> 3255 | L6: 110 | M6: =IF(G6="","",K6-N(L6)) -> 3145 | N6: =IF(OR(G6="",E6=""),"",E6*Config!$B$11) -> 1307.1434 | O6: =IF(A6="","",MATCH(A6,Config!$H$5:$H$16,0)) -> 2
A7: Março | B7: 2026 | C7: Dra. Renata Sousa | D7: 12100 | E7: 28 | F7: =IF(C7="","",IFERROR(INDEX(Config!$B$25:$B$28,MATCH(C7,Config!$A$25:$A$28,0)),"")) -> 0.5 | G7: =IF(OR(C7="",D7="",F7=""),"",ROUND(D7*F7,0)) -> 6050 | H7: 46122 | I7: 6050 | J7: =IF(G7="","",IF(I7="",G7,G7-I7)) -> 0 | K7: =IF(G7="","",D7-G7) -> 6050 | L7: 168 | M7: =IF(G7="","",K7-N(L7)) -> 5882 | N7: =IF(OR(G7="",E7=""),"",E7*Config!$B$11) -> 2000.0008 | O7: =IF(A7="","",MATCH(A7,Config!$H$5:$H$16,0)) -> 3
A8: Abril | B8: 2026 | C8: Dra. Renata Sousa | D8: 8770 | E8: 24 | F8: =IF(C8="","",IFERROR(INDEX(Config!$B$25:$B$28,MATCH(C8,Config!$A$25:$A$28,0)),"")) -> 0.5 | G8: =IF(OR(C8="",D8="",F8=""),"",ROUND(D8*F8,0)) -> 4385 | H8: 46152 | I8: 4385 | J8: =IF(G8="","",IF(I8="",G8,G8-I8)) -> 0 | K8: =IF(G8="","",D8-G8) -> 4385 | L8: 144 | M8: =IF(G8="","",K8-N(L8)) -> 4241 | N8: =IF(OR(G8="",E8=""),"",E8*Config!$B$11) -> 1714.2864 | O8: =IF(A8="","",MATCH(A8,Config!$H$5:$H$16,0)) -> 4
A9: Maio | B9: 2026 | C9: Dra. Renata Sousa | D9: 10490 | E9: 26.7 | F9: =IF(C9="","",IFERROR(INDEX(Config!$B$25:$B$28,MATCH(C9,Config!$A$25:$A$28,0)),"")) -> 0.5 | G9: =IF(OR(C9="",D9="",F9=""),"",ROUND(D9*F9,0)) -> 5245 | H9: 46183 | I9: 5245 | J9: =IF(G9="","",IF(I9="",G9,G9-I9)) -> 0 | K9: =IF(G9="","",D9-G9) -> 5245 | L9: 160 | M9: =IF(G9="","",K9-N(L9)) -> 5085 | N9: =IF(OR(G9="",E9=""),"",E9*Config!$B$11) -> 1907.1436 | O9: =IF(A9="","",MATCH(A9,Config!$H$5:$H$16,0)) -> 5
A10: Junho | B10: 2026 | C10: Dra. Renata Sousa | D10: 9440 | E10: 24 | F10: =IF(C10="","",IFERROR(INDEX(Config!$B$25:$B$28,MATCH(C10,Config!$A$25:$A$28,0)),"")) -> 0.5 | G10: =IF(OR(C10="",D10="",F10=""),"",ROUND(D10*F10,0)) -> 4720 | H10: 46213 | I10: 4720 | J10: =IF(G10="","",IF(I10="",G10,G10-I10)) -> 0 | K10: =IF(G10="","",D10-G10) -> 4720 | L10: 144 | M10: =IF(G10="","",K10-N(L10)) -> 4576 | N10: =IF(OR(G10="",E10=""),"",E10*Config!$B$11) -> 1714.2864 | O10: =IF(A10="","",MATCH(A10,Config!$H$5:$H$16,0)) -> 6
A11: Julho | B11: 2026 | C11: Dra. Renata Sousa | D11: 9690 | E11: 28 | F11: =IF(C11="","",IFERROR(INDEX(Config!$B$25:$B$28,MATCH(C11,Config!$A$25:$A$28,0)),"")) -> 0.5 | G11: =IF(OR(C11="",D11="",F11=""),"",ROUND(D11*F11,0)) -> 4845 | H11: 46244 | I11: 4845 | J11: =IF(G11="","",IF(I11="",G11,G11-I11)) -> 0 | K11: =IF(G11="","",D11-G11) -> 4845 | L11: 168 | M11: =IF(G11="","",K11-N(L11)) -> 4677 | N11: =IF(OR(G11="",E11=""),"",E11*Config!$B$11) -> 2000.0008 | O11: =IF(A11="","",MATCH(A11,Config!$H$5:$H$16,0)) -> 7
A12: Agosto | B12: 2026 | C12: Dra. Renata Sousa | D12: 10380 | E12: 23.7 | F12: =IF(C12="","",IFERROR(INDEX(Config!$B$25:$B$28,MATCH(C12,Config!$A$25:$A$28,0)),"")) -> 0.5 | G12: =IF(OR(C12="",D12="",F12=""),"",ROUND(D12*F12,0)) -> 5190 | H12: 46275 | I12: 5190 | J12: =IF(G12="","",IF(I12="",G12,G12-I12)) -> 0 | K12: =IF(G12="","",D12-G12) -> 5190 | L12: 142 | M12: =IF(G12="","",K12-N(L12)) -> 5048 | N12: =IF(OR(G12="",E12=""),"",E12*Config!$B$11) -> 1692.8578 | O12: =IF(A12="","",MATCH(A12,Config!$H$5:$H$16,0)) -> 8
A13: Setembro | B13: 2026 | C13: Dra. Renata Sousa | D13: 5850 | E13: 14 | F13: =IF(C13="","",IFERROR(INDEX(Config!$B$25:$B$28,MATCH(C13,Config!$A$25:$A$28,0)),"")) -> 0.5 | G13: =IF(OR(C13="",D13="",F13=""),"",ROUND(D13*F13,0)) -> 2925 | J13: =IF(G13="","",IF(I13="",G13,G13-I13)) -> 2925 | K13: =IF(G13="","",D13-G13) -> 2925 | L13: 84 | M13: =IF(G13="","",K13-N(L13)) -> 2841 | N13: =IF(OR(G13="",E13=""),"",E13*Config!$B$11) -> 1000.0004 | O13: =IF(A13="","",MATCH(A13,Config!$H$5:$H$16,0)) -> 9
F14: =IF(C14="","",IFERROR(INDEX(Config!$B$25:$B$28,MATCH(C14,Config!$A$25:$A$28,0)),"")) | G14: =IF(OR(C14="",D14="",F14=""),"",ROUND(D14*F14,0)) | J14: =IF(G14="","",IF(I14="",G14,G14-I14)) | K14: =IF(G14="","",D14-G14) | M14: =IF(G14="","",K14-N(L14)) | N14: =IF(OR(G14="",E14=""),"",E14*Config!$B$11) | O14: =IF(A14="","",MATCH(A14,Config!$H$5:$H$16,0))
F15: =IF(C15="","",IFERROR(INDEX(Config!$B$25:$B$28,MATCH(C15,Config!$A$25:$A$28,0)),"")) | G15: =IF(OR(C15="",D15="",F15=""),"",ROUND(D15*F15,0)) | J15: =IF(G15="","",IF(I15="",G15,G15-I15)) | K15: =IF(G15="","",D15-G15) | M15: =IF(G15="","",K15-N(L15)) | N15: =IF(OR(G15="",E15=""),"",E15*Config!$B$11) | O15: =IF(A15="","",MATCH(A15,Config!$H$5:$H$16,0))
F16: =IF(C16="","",IFERROR(INDEX(Config!$B$25:$B$28,MATCH(C16,Config!$A$25:$A$28,0)),"")) | G16: =IF(OR(C16="",D16="",F16=""),"",ROUND(D16*F16,0)) | J16: =IF(G16="","",IF(I16="",G16,G16-I16)) | K16: =IF(G16="","",D16-G16) | M16: =IF(G16="","",K16-N(L16)) | N16: =IF(OR(G16="",E16=""),"",E16*Config!$B$11) | O16: =IF(A16="","",MATCH(A16,Config!$H$5:$H$16,0))
F17: =IF(C17="","",IFERROR(INDEX(Config!$B$25:$B$28,MATCH(C17,Config!$A$25:$A$28,0)),"")) | G17: =IF(OR(C17="",D17="",F17=""),"",ROUND(D17*F17,0)) | J17: =IF(G17="","",IF(I17="",G17,G17-I17)) | K17: =IF(G17="","",D17-G17) | M17: =IF(G17="","",K17-N(L17)) | N17: =IF(OR(G17="",E17=""),"",E17*Config!$B$11) | O17: =IF(A17="","",MATCH(A17,Config!$H$5:$H$16,0))
F18: =IF(C18="","",IFERROR(INDEX(Config!$B$25:$B$28,MATCH(C18,Config!$A$25:$A$28,0)),"")) | G18: =IF(OR(C18="",D18="",F18=""),"",ROUND(D18*F18,0)) | J18: =IF(G18="","",IF(I18="",G18,G18-I18)) | K18: =IF(G18="","",D18-G18) | M18: =IF(G18="","",K18-N(L18)) | N18: =IF(OR(G18="",E18=""),"",E18*Config!$B$11) | O18: =IF(A18="","",MATCH(A18,Config!$H$5:$H$16,0))
F19: =IF(C19="","",IFERROR(INDEX(Config!$B$25:$B$28,MATCH(C19,Config!$A$25:$A$28,0)),"")) | G19: =IF(OR(C19="",D19="",F19=""),"",ROUND(D19*F19,0)) | J19: =IF(G19="","",IF(I19="",G19,G19-I19)) | K19: =IF(G19="","",D19-G19) | M19: =IF(G19="","",K19-N(L19)) | N19: =IF(OR(G19="",E19=""),"",E19*Config!$B$11) | O19: =IF(A19="","",MATCH(A19,Config!$H$5:$H$16,0))
F20: =IF(C20="","",IFERROR(INDEX(Config!$B$25:$B$28,MATCH(C20,Config!$A$25:$A$28,0)),"")) | G20: =IF(OR(C20="",D20="",F20=""),"",ROUND(D20*F20,0)) | J20: =IF(G20="","",IF(I20="",G20,G20-I20)) | K20: =IF(G20="","",D20-G20) | M20: =IF(G20="","",K20-N(L20)) | N20: =IF(OR(G20="",E20=""),"",E20*Config!$B$11) | O20: =IF(A20="","",MATCH(A20,Config!$H$5:$H$16,0))
F21: =IF(C21="","",IFERROR(INDEX(Config!$B$25:$B$28,MATCH(C21,Config!$A$25:$A$28,0)),"")) | G21: =IF(OR(C21="",D21="",F21=""),"",ROUND(D21*F21,0)) | J21: =IF(G21="","",IF(I21="",G21,G21-I21)) | K21: =IF(G21="","",D21-G21) | M21: =IF(G21="","",K21-N(L21)) | N21: =IF(OR(G21="",E21=""),"",E21*Config!$B$11) | O21: =IF(A21="","",MATCH(A21,Config!$H$5:$H$16,0))
F22: =IF(C22="","",IFERROR(INDEX(Config!$B$25:$B$28,MATCH(C22,Config!$A$25:$A$28,0)),"")) | G22: =IF(OR(C22="",D22="",F22=""),"",ROUND(D22*F22,0)) | J22: =IF(G22="","",IF(I22="",G22,G22-I22)) | K22: =IF(G22="","",D22-G22) | M22: =IF(G22="","",K22-N(L22)) | N22: =IF(OR(G22="",E22=""),"",E22*Config!$B$11) | O22: =IF(A22="","",MATCH(A22,Config!$H$5:$H$16,0))
F23: =IF(C23="","",IFERROR(INDEX(Config!$B$25:$B$28,MATCH(C23,Config!$A$25:$A$28,0)),"")) | G23: =IF(OR(C23="",D23="",F23=""),"",ROUND(D23*F23,0)) | J23: =IF(G23="","",IF(I23="",G23,G23-I23)) | K23: =IF(G23="","",D23-G23) | M23: =IF(G23="","",K23-N(L23)) | N23: =IF(OR(G23="",E23=""),"",E23*Config!$B$11) | O23: =IF(A23="","",MATCH(A23,Config!$H$5:$H$16,0))
F24: =IF(C24="","",IFERROR(INDEX(Config!$B$25:$B$28,MATCH(C24,Config!$A$25:$A$28,0)),"")) | G24: =IF(OR(C24="",D24="",F24=""),"",ROUND(D24*F24,0)) | J24: =IF(G24="","",IF(I24="",G24,G24-I24)) | K24: =IF(G24="","",D24-G24) | M24: =IF(G24="","",K24-N(L24)) | N24: =IF(OR(G24="",E24=""),"",E24*Config!$B$11) | O24: =IF(A24="","",MATCH(A24,Config!$H$5:$H$16,0))
F25: =IF(C25="","",IFERROR(INDEX(Config!$B$25:$B$28,MATCH(C25,Config!$A$25:$A$28,0)),"")) | G25: =IF(OR(C25="",D25="",F25=""),"",ROUND(D25*F25,0)) | J25: =IF(G25="","",IF(I25="",G25,G25-I25)) | K25: =IF(G25="","",D25-G25) | M25: =IF(G25="","",K25-N(L25)) | N25: =IF(OR(G25="",E25=""),"",E25*Config!$B$11) | O25: =IF(A25="","",MATCH(A25,Config!$H$5:$H$16,0))
... F40: =IF(C40="","",IFERROR(INDEX(Config!$B$25:$B$28,MATCH(C40,Config!$A$25:$A$28,0)),"")) | G40: =IF(OR(C40="",D40="",F40=""),"",ROUND(D40*F40,0)) | J40: =IF(G40="","",IF(I40="",G40,G40-I40)) | K40: =IF(G40="","",D40-G40) | M40: =IF(G40="","",K40-N(L40)) | N40: =IF(OR(G40="",E40=""),"",E40*Config!$B$11) | O40: =IF(A40="","",MATCH(A40,Config!$H$5:$H$16,0))
A42: Diferença em amarelo: repasse devido e ainda não pago (ou pago a menos). Margem da parceria = o que fica com a clínica − material e insumo que o parceiro consome (o custo direto da parceria). O custo indireto das horas é só informativo: a estrutura já está paga dentro do custo-hora dos sócios (05), e descontá-la aqui cobraria a mesma sala duas vezes. Margem negativa em vermelho: o repasse combinado não cobre nem o material; reveja o % ou a tabela.
A43: No exemplo, a produção de janeiro a junho veio do fechamento do dia (a agenda na planilha 01 começou em julho); julho e agosto são o Painel da 01 por profissional; setembro está em andamento (até 11/09), sem repasse pago ainda.

Sheet Resultado mensal
A1: Resultado mensal da clínica
A2: Amarelo: entradas e saídas de cada mês, sem nada dos sócios (copie do Painel da planilha 09). O resto é calculado.
A4: Mês | B4: Entradas recebidas | C4: Saídas da clínica (sem sócios) | D4: Pró-labore fixo combinado | E4: Resultado após pró-labore | F4: Trimestre
A5: Janeiro | B5: 25310 | C5: 17932.05 | D5: =IF(AND(B5="",C5=""),0,Config!$C$21) -> 18000 | E5: =B5-C5-D5 -> -10622.05 | F5: 1º trimestre
A6: Fevereiro | B6: 25650 | C6: 17610.54 | D6: =IF(AND(B6="",C6=""),0,Config!$C$21) -> 18000 | E6: =B6-C6-D6 -> -9960.54 | F6: 1º trimestre
A7: Março | B7: 40540 | C7: 17901.13 | D7: =IF(AND(B7="",C7=""),0,Config!$C$21) -> 18000 | E7: =B7-C7-D7 -> 4638.87 | F7: 1º trimestre
A8: Abril | B8: 40155 | C8: 22254.1 | D8: =IF(AND(B8="",C8=""),0,Config!$C$21) -> 18000 | E8: =B8-C8-D8 -> -99.1 | F8: 2º trimestre
A9: Maio | B9: 45380 | C9: 21500.29 | D9: =IF(AND(B9="",C9=""),0,Config!$C$21) -> 18000 | E9: =B9-C9-D9 -> 5879.71 | F9: 2º trimestre
A10: Junho | B10: 47240 | C10: 22202.87 | D10: =IF(AND(B10="",C10=""),0,Config!$C$21) -> 18000 | E10: =B10-C10-D10 -> 7037.13 | F10: 2º trimestre
A11: Julho | B11: 44471 | C11: 21562.6 | D11: =IF(AND(B11="",C11=""),0,Config!$C$21) -> 18000 | E11: =B11-C11-D11 -> 4908.4 | F11: 3º trimestre
A12: Agosto | B12: 55841 | C12: 22248.61 | D12: =IF(AND(B12="",C12=""),0,Config!$C$21) -> 18000 | E12: =B12-C12-D12 -> 15592.39 | F12: 3º trimestre
A13: Setembro | B13: 20710 | C13: 13630 | D13: =IF(AND(B13="",C13=""),0,Config!$C$21) -> 18000 | E13: =B13-C13-D13 -> -10920 | F13: 3º trimestre
A14: Outubro | D14: =IF(AND(B14="",C14=""),0,Config!$C$21) -> 0 | E14: =B14-C14-D14 -> 0 | F14: 4º trimestre
A15: Novembro | D15: =IF(AND(B15="",C15=""),0,Config!$C$21) -> 0 | E15: =B15-C15-D15 -> 0 | F15: 4º trimestre
A16: Dezembro | D16: =IF(AND(B16="",C16=""),0,Config!$C$21) -> 0 | E16: =B16-C16-D16 -> 0 | F16: 4º trimestre
A18: Entradas = Entrou no mês (Painel da planilha 09) menos devoluções dos sócios (Outras entradas). Saídas sem sócios = Saiu no mês menos pró-labore, retiradas extras, distribuição de lucro e despesas pessoais dos sócios (o repasse à parceira fica dentro). Meses não fechados ficam em branco (setembro: até 11/09).

Sheet Retiradas
A1: Retiradas e movimentos sócio × clínica
A2: Uma linha por movimento entre a conta da clínica e a pessoa física de cada sócio. Preencha o amarelo; mês e ano são calculados.
A4: Data | B4: Sócio | C4: Tipo | D4: Descrição | E4: Valor | F4: Trimestre de referência (só distribuição) | G4: Mês | H4: Ano
A5: 46050 | B5: Dr. Paulo Andrade | C5: Pró-labore | D5: Pró-labore de janeiro | E5: 9000 | G5: =IF(A5="","",MONTH(A5)) -> 1 | H5: =IF(A5="","",YEAR(A5)) -> 2026
A6: 46050 | B6: Dra. Carolina Mendes | C6: Pró-labore | D6: Pró-labore de janeiro | E6: 9000 | G6: =IF(A6="","",MONTH(A6)) -> 1 | H6: =IF(A6="","",YEAR(A6)) -> 2026
A7: 46059 | B7: Dra. Carolina Mendes | C7: Despesa pessoal paga pela clínica | D7: Plano de saúde da família | E7: 620 | G7: =IF(A7="","",MONTH(A7)) -> 2 | H7: =IF(A7="","",YEAR(A7)) -> 2026
A8: 46081 | B8: Dr. Paulo Andrade | C8: Pró-labore | D8: Pró-labore de fevereiro | E8: 9000 | G8: =IF(A8="","",MONTH(A8)) -> 2 | H8: =IF(A8="","",YEAR(A8)) -> 2026
A9: 46081 | B9: Dra. Carolina Mendes | C9: Pró-labore | D9: Pró-labore de fevereiro | E9: 9000 | G9: =IF(A9="","",MONTH(A9)) -> 2 | H9: =IF(A9="","",YEAR(A9)) -> 2026
A10: 46092 | B10: Dr. Paulo Andrade | C10: Despesa pessoal paga pela clínica | D10: Combustível particular | E10: 350 | G10: =IF(A10="","",MONTH(A10)) -> 3 | H10: =IF(A10="","",YEAR(A10)) -> 2026
A11: 46097 | B11: Dr. Paulo Andrade | C11: Retirada extra | D11: Adiantamento para congresso | E11: 2000 | G11: =IF(A11="","",MONTH(A11)) -> 3 | H11: =IF(A11="","",YEAR(A11)) -> 2026
A12: 46109 | B12: Dr. Paulo Andrade | C12: Pró-labore | D12: Pró-labore de março | E12: 9000 | G12: =IF(A12="","",MONTH(A12)) -> 3 | H12: =IF(A12="","",YEAR(A12)) -> 2026
A13: 46109 | B13: Dra. Carolina Mendes | C13: Pró-labore | D13: Pró-labore de março | E13: 9000 | G13: =IF(A13="","",MONTH(A13)) -> 3 | H13: =IF(A13="","",YEAR(A13)) -> 2026
A14: 46126 | B14: Dra. Carolina Mendes | C14: Devolução à clínica | D14: Devolução da despesa pessoal (plano de saúde) | E14: 620 | G14: =IF(A14="","",MONTH(A14)) -> 4 | H14: =IF(A14="","",YEAR(A14)) -> 2026
A15: 46140 | B15: Dr. Paulo Andrade | C15: Pró-labore | D15: Pró-labore de abril | E15: 9000 | G15: =IF(A15="","",MONTH(A15)) -> 4 | H15: =IF(A15="","",YEAR(A15)) -> 2026
A16: 46140 | B16: Dra. Carolina Mendes | C16: Pró-labore | D16: Pró-labore de abril | E16: 9000 | G16: =IF(A16="","",MONTH(A16)) -> 4 | H16: =IF(A16="","",YEAR(A16)) -> 2026
... A22: 46201 | B22: Dra. Carolina Mendes | C22: Pró-labore | D22: Pró-labore de junho | E22: 9000 | G22: =IF(A22="","",MONTH(A22)) -> 6 | H22: =IF(A22="","",YEAR(A22)) -> 2026
A23: 46213 | B23: Dr. Paulo Andrade | C23: Distribuição de lucro | D23: Distribuição de lucro · 2º trimestre | E23: 3205 | F23: 2º trimestre | G23: =IF(A23="","",MONTH(A23)) -> 7 | H23: =IF(A23="","",YEAR(A23)) -> 2026
A24: 46213 | B24: Dra. Carolina Mendes | C24: Distribuição de lucro | D24: Distribuição de lucro · 2º trimestre | E24: 3204 | F24: 2º trimestre | G24: =IF(A24="","",MONTH(A24)) -> 7 | H24: =IF(A24="","",YEAR(A24)) -> 2026
A25: 46214 | B25: Dr. Paulo Andrade | C25: Despesa pessoal paga pela clínica | D25: Combustível particular | E25: 350 | G25: =IF(A25="","",MONTH(A25)) -> 7 | H25: =IF(A25="","",YEAR(A25)) -> 2026
A26: 46231 | B26: Dr. Paulo Andrade | C26: Pró-labore | D26: Pró-labore de julho | E26: 9000 | G26: =IF(A26="","",MONTH(A26)) -> 7 | H26: =IF(A26="","",YEAR(A26)) -> 2026
A27: 46231 | B27: Dra. Carolina Mendes | C27: Pró-labore | D27: Pró-labore de julho | E27: 9000 | G27: =IF(A27="","",MONTH(A27)) -> 7 | H27: =IF(A27="","",YEAR(A27)) -> 2026
A28: 46240 | B28: Dra. Carolina Mendes | C28: Despesa pessoal paga pela clínica | D28: Plano de saúde da família | E28: 620 | G28: =IF(A28="","",MONTH(A28)) -> 8 | H28: =IF(A28="","",YEAR(A28)) -> 2026
A29: 46262 | B29: Dr. Paulo Andrade | C29: Pró-labore | D29: Pró-labore de agosto | E29: 9000 | G29: =IF(A29="","",MONTH(A29)) -> 8 | H29: =IF(A29="","",YEAR(A29)) -> 2026
A30: 46262 | B30: Dra. Carolina Mendes | C30: Pró-labore | D30: Pró-labore de agosto | E30: 9000 | G30: =IF(A30="","",MONTH(A30)) -> 8 | H30: =IF(A30="","",YEAR(A30)) -> 2026
G31: =IF(A31="","",MONTH(A31)) | H31: =IF(A31="","",YEAR(A31))
G32: =IF(A32="","",MONTH(A32)) | H32: =IF(A32="","",YEAR(A32))
G33: =IF(A33="","",MONTH(A33)) | H33: =IF(A33="","",YEAR(A33))
G34: =IF(A34="","",MONTH(A34)) | H34: =IF(A34="","",YEAR(A34))
G35: =IF(A35="","",MONTH(A35)) | H35: =IF(A35="","",YEAR(A35))
G36: =IF(A36="","",MONTH(A36)) | H36: =IF(A36="","",YEAR(A36))
G37: =IF(A37="","",MONTH(A37)) | H37: =IF(A37="","",YEAR(A37))
G38: =IF(A38="","",MONTH(A38)) | H38: =IF(A38="","",YEAR(A38))
G39: =IF(A39="","",MONTH(A39)) | H39: =IF(A39="","",YEAR(A39))
G40: =IF(A40="","",MONTH(A40)) | H40: =IF(A40="","",YEAR(A40))
G41: =IF(A41="","",MONTH(A41)) | H41: =IF(A41="","",YEAR(A41))
G42: =IF(A42="","",MONTH(A42)) | H42: =IF(A42="","",YEAR(A42))
... G404: =IF(A404="","",MONTH(A404)) | H404: =IF(A404="","",YEAR(A404))
