Workbook

Sheet Como usar
A1: Conciliação de cartão e taxas
A2: Kit de Gestão para Médicos · Seu Sócio Gestor · versão 1.0 (setembro de 2026)
A4: O que esta planilha faz | B4: Cada pagamento no cartão ou no Pix com a taxa da operadora, o valor líquido e o dia em que cai na conta. Mostra quanto as taxas comem no mês (e a quantas consultas equivalem), o que ainda vai cair, o que já deveria ter caído e não foi conferido, e o dia a dia para bater com o extrato.
A5: Passo 1 | B5: Em Config, digite as taxas e os prazos da sua operadora (contrato da maquininha ou extrato), se antecipa o crédito e o preço da consulta particular (só para a comparação).
A6: Passo 2 | B6: Em Vendas, uma linha por pagamento: data, paciente, procedimento, tipo, parcelas e valor bruto (copie da Agenda da 01, filtrando os particulares pagos com Pix ou cartão). Toda sexta, marque Sim em "Conferido no extrato?" para o que caiu na conta.
A7: Passo 3 | B7: Em Painel, escolha o mês em Config: vendas, taxas, líquido, por tipo, dia a dia e a lista "Falta conferir". No fechamento do mês, lance o total de taxas como saída "Taxas de cartão" no caixa (09).
A8: Rotina | B8: Sexta-feira, 10 minutos: conferir o extrato da operadora contra "Cai na conta neste dia" e marcar as conferidas. Uma vez por semestre: comparar a taxa média com outra operadora.
A9: Ligação com as outras planilhas | B9: O caixa (09) registra o bruto no dia da venda; as taxas do mês são a saída do fim do mês (o total deste Painel). O resultado mensal (18) mostra as taxas como despesa variável. No exemplo o Painel está em agosto (mês fechado); setembro está em andamento.
A10: Com a IA | B10: Copie "Por tipo de pagamento" e use o prompt "Caixa 09 · A taxa da maquininha está comendo a margem?" da biblioteca do kit para decidir entre absorver a taxa, oferecer desconto no Pix ou trocar de operadora.
A11: Legenda | B11: Células amarelas: você preenche. Brancas: calculadas. Não é preciso mexer em nada fora do amarelo.
A12: Proteção | B12: Fórmulas protegidas sem senha. Para editar: Revisar > Desproteger planilha (Excel) ou Dados > Proteger intervalos (Google Sheets).
A13: Requisitos | B13: Excel 2016 ou mais novo, Microsoft 365 ou Google Sheets (só funções do Excel 2007+; nada de MÍNIMOSES, MÁXIMOSES ou UNIRTEXTO). No celular abre nos aplicativos; para preencher, use o computador.
A14: Dados de pacientes | B14: Guarde só o que a gestão precisa (nome, contato, valor, data). Nada de diagnóstico, prontuário ou exame nestas planilhas: o kit é gestão, não é prontuário. Veja o guia LGPD do kit antes de colar qualquer tabela em uma IA.
A15: Google Sheets | B15: Faça upload no Google Drive e abra com o Google Sheets. Fórmulas, listas, cores e gráficos funcionam.
... A17: Suporte | B17: suporte@seusociogestor.com.br · resposta em até 5 dias úteis · reembolso em até 7 dias pelo mesmo canal.

Sheet Painel
A1: =Config!$B$4&" · Conciliação de cartão e taxas · "&Config!$B$6&" de "&Config!$B$5 -> Clínica Vida Plena (exemplo fictício) · Conciliação de cartão e taxas · Agosto de 2026
A2: Nada para digitar aqui. Escolha o mês em Config; tudo vem de Vendas. Taxas por mês da venda; a receber por previsão na conta.
A4: Vendas no mês (bruto) | C4: Taxas no mês | E4: Taxa média | G4: Líquido no mês | I4: Ainda vai cair (todas as vendas) | K4: A conferir
A5: =SUMIFS(Vendas!$F$5:$F$604,Vendas!$L$5:$L$604,Config!$B$7,Vendas!$M$5:$M$604,Config!$B$5) -> 31820 | C5: =SUMIFS(Vendas!$I$5:$I$604,Vendas!$L$5:$L$604,Config!$B$7,Vendas!$M$5:$M$604,Config!$B$5) -> 484.12 | E5: =IF(A5=0,"",C5/A5) -> 0.015214331 | G5: =A5-C5 -> 31335.88 | I5: =SUMIFS(Vendas!$J$5:$J$604,Vendas!$N$5:$N$604,"A cair") -> 10898.71 | K5: =SUMIFS(Vendas!$J$5:$J$604,Vendas!$N$5:$N$604,"A conferir") -> 4047.84
A7: ="As taxas do mês equivalem a "&FIXED(IF(Config!$B$9=0,0,C5/Config!$B$9),1)&" consultas particulares. Lance este total no caixa (09) como saída 'Taxas de cartão' no fim do mês." -> As taxas do mês equivalem a 1.3 consultas particulares. Lance este total no caixa (09) como saída 'Taxas de cartão' no fim do mês.
A9: Por tipo de pagamento no mês
A10: Tipo | B10: Vendas | C10: Bruto (R$) | D10: Taxas (R$) | E10: Taxa média | F10: Líquido (R$) | G10: % do bruto | H10: Barra
A11: Pix | B11: =COUNTIFS(Vendas!$D$5:$D$604,"Pix",Vendas!$L$5:$L$604,Config!$B$7,Vendas!$M$5:$M$604,Config!$B$5) -> 37 | C11: =SUMIFS(Vendas!$F$5:$F$604,Vendas!$D$5:$D$604,"Pix",Vendas!$L$5:$L$604,Config!$B$7,Vendas!$M$5:$M$604,Config!$B$5) -> 13380 | D11: =SUMIFS(Vendas!$I$5:$I$604,Vendas!$D$5:$D$604,"Pix",Vendas!$L$5:$L$604,Config!$B$7,Vendas!$M$5:$M$604,Config!$B$5) -> 0 | E11: =IF(C11=0,"",D11/C11) -> 0 | F11: =C11-D11 -> 13380 | G11: =IF($A$5=0,"",C11/$A$5) -> 0.42049026 | H11: =IF(G11="","",REPT("█",ROUND(G11*30,0))) -> █████████████
A12: Cartão de débito | B12: =COUNTIFS(Vendas!$D$5:$D$604,"Cartão de débito",Vendas!$L$5:$L$604,Config!$B$7,Vendas!$M$5:$M$604,Config!$B$5) -> 22 | C12: =SUMIFS(Vendas!$F$5:$F$604,Vendas!$D$5:$D$604,"Cartão de débito",Vendas!$L$5:$L$604,Config!$B$7,Vendas!$M$5:$M$604,Config!$B$5) -> 8090 | D12: =SUMIFS(Vendas!$I$5:$I$604,Vendas!$D$5:$D$604,"Cartão de débito",Vendas!$L$5:$L$604,Config!$B$7,Vendas!$M$5:$M$604,Config!$B$5) -> 121.35 | E12: =IF(C12=0,"",D12/C12) -> 0.015 | F12: =C12-D12 -> 7968.65 | G12: =IF($A$5=0,"",C12/$A$5) -> 0.25424261 | H12: =IF(G12="","",REPT("█",ROUND(G12*30,0))) -> ████████
A13: Cartão de crédito à vista | B13: =COUNTIFS(Vendas!$D$5:$D$604,"Cartão de crédito",Vendas!$E$5:$E$604,"<2",Vendas!$L$5:$L$604,Config!$B$7,Vendas!$M$5:$M$604,Config!$B$5) -> 0 | C13: =SUMIFS(Vendas!$F$5:$F$604,Vendas!$D$5:$D$604,"Cartão de crédito",Vendas!$E$5:$E$604,"<2",Vendas!$L$5:$L$604,Config!$B$7,Vendas!$M$5:$M$604,Config!$B$5) -> 0 | D13: =SUMIFS(Vendas!$I$5:$I$604,Vendas!$D$5:$D$604,"Cartão de crédito",Vendas!$E$5:$E$604,"<2",Vendas!$L$5:$L$604,Config!$B$7,Vendas!$M$5:$M$604,Config!$B$5) -> 0 | E13: =IF(C13=0,"",D13/C13) | F13: =C13-D13 -> 0 | G13: =IF($A$5=0,"",C13/$A$5) -> 0 | H13: =IF(G13="","",REPT("█",ROUND(G13*30,0)))
A14: Cartão de crédito parcelado | B14: =COUNTIFS(Vendas!$D$5:$D$604,"Cartão de crédito",Vendas!$E$5:$E$604,">1",Vendas!$L$5:$L$604,Config!$B$7,Vendas!$M$5:$M$604,Config!$B$5) -> 12 | C14: =SUMIFS(Vendas!$F$5:$F$604,Vendas!$D$5:$D$604,"Cartão de crédito",Vendas!$E$5:$E$604,">1",Vendas!$L$5:$L$604,Config!$B$7,Vendas!$M$5:$M$604,Config!$B$5) -> 4510 | D14: =SUMIFS(Vendas!$I$5:$I$604,Vendas!$D$5:$D$604,"Cartão de crédito",Vendas!$E$5:$E$604,">1",Vendas!$L$5:$L$604,Config!$B$7,Vendas!$M$5:$M$604,Config!$B$5) -> 175.89 | E14: =IF(C14=0,"",D14/C14) -> 0.039 | F14: =C14-D14 -> 4334.11 | G14: =IF($A$5=0,"",C14/$A$5) -> 0.14173476 | H14: =IF(G14="","",REPT("█",ROUND(G14*30,0))) -> ████
A15: Total | B15: =SUM(B11:B14) -> 71 | C15: =SUM(C11:C14) -> 25980 | D15: =SUM(D11:D14) -> 297.24 | F15: =SUM(F11:F14) -> 25682.76
A16: Parcelado custa mais e demora mais. Se o parcelado pesa, vale oferecer desconto no Pix em vez de absorver a taxa; a decisão é da clínica.
A18: Dia a dia do mês: vendas, taxas e previsão de crédito
A19: Dia | B19: Data | C19: Vendas | D19: Bruto (R$) | E19: Taxas (R$) | F19: Líquido (R$) | G19: Cai na conta neste dia (R$) | H19: Conferido?
A20: 1 | B20: =IF(1>DAY(DATE(Config!$B$5,Config!$B$7+1,0)),"",DATE(Config!$B$5,Config!$B$7,1)) -> 46235 | C20: =IF(B20="","",COUNTIFS(Vendas!$A$5:$A$604,B20)) -> 0 | D20: =IF(B20="","",SUMIFS(Vendas!$F$5:$F$604,Vendas!$A$5:$A$604,B20)) -> 0 | E20: =IF(B20="","",SUMIFS(Vendas!$I$5:$I$604,Vendas!$A$5:$A$604,B20)) -> 0 | F20: =IF(B20="","",D20-E20) -> 0 | G20: =IF(B20="","",SUMIFS(Vendas!$J$5:$J$604,Vendas!$K$5:$K$604,B20)) -> 1862.22 | H20: =IF(OR(B20="",G20=0),"",IF(COUNTIFS(Vendas!$K$5:$K$604,B20,Vendas!$N$5:$N$604,"A conferir")>0,"Falta conferir",IF(COUNTIFS(Vendas!$K$5:$K$604,B20,Vendas!$N$5:$N$604,"A cair")>0,"A cair","Conferido"))) -> Conferido
A21: 2 | B21: =IF(2>DAY(DATE(Config!$B$5,Config!$B$7+1,0)),"",DATE(Config!$B$5,Config!$B$7,2)) -> 46236 | C21: =IF(B21="","",COUNTIFS(Vendas!$A$5:$A$604,B21)) -> 0 | D21: =IF(B21="","",SUMIFS(Vendas!$F$5:$F$604,Vendas!$A$5:$A$604,B21)) -> 0 | E21: =IF(B21="","",SUMIFS(Vendas!$I$5:$I$604,Vendas!$A$5:$A$604,B21)) -> 0 | F21: =IF(B21="","",D21-E21) -> 0 | G21: =IF(B21="","",SUMIFS(Vendas!$J$5:$J$604,Vendas!$K$5:$K$604,B21)) -> 0 | H21: =IF(OR(B21="",G21=0),"",IF(COUNTIFS(Vendas!$K$5:$K$604,B21,Vendas!$N$5:$N$604,"A conferir")>0,"Falta conferir",IF(COUNTIFS(Vendas!$K$5:$K$604,B21,Vendas!$N$5:$N$604,"A cair")>0,"A cair","Conferido")))
A22: 3 | B22: =IF(3>DAY(DATE(Config!$B$5,Config!$B$7+1,0)),"",DATE(Config!$B$5,Config!$B$7,3)) -> 46237 | C22: =IF(B22="","",COUNTIFS(Vendas!$A$5:$A$604,B22)) -> 2 | D22: =IF(B22="","",SUMIFS(Vendas!$F$5:$F$604,Vendas!$A$5:$A$604,B22)) -> 680 | E22: =IF(B22="","",SUMIFS(Vendas!$I$5:$I$604,Vendas!$A$5:$A$604,B22)) -> 16.66 | F22: =IF(B22="","",D22-E22) -> 663.34 | G22: =IF(B22="","",SUMIFS(Vendas!$J$5:$J$604,Vendas!$K$5:$K$604,B22)) -> 0 | H22: =IF(OR(B22="",G22=0),"",IF(COUNTIFS(Vendas!$K$5:$K$604,B22,Vendas!$N$5:$N$604,"A conferir")>0,"Falta conferir",IF(COUNTIFS(Vendas!$K$5:$K$604,B22,Vendas!$N$5:$N$604,"A cair")>0,"A cair","Conferido")))
A23: 4 | B23: =IF(4>DAY(DATE(Config!$B$5,Config!$B$7+1,0)),"",DATE(Config!$B$5,Config!$B$7,4)) -> 46238 | C23: =IF(B23="","",COUNTIFS(Vendas!$A$5:$A$604,B23)) -> 8 | D23: =IF(B23="","",SUMIFS(Vendas!$F$5:$F$604,Vendas!$A$5:$A$604,B23)) -> 3060 | E23: =IF(B23="","",SUMIFS(Vendas!$I$5:$I$604,Vendas!$A$5:$A$604,B23)) -> 47.42 | F23: =IF(B23="","",D23-E23) -> 3012.58 | G23: =IF(B23="","",SUMIFS(Vendas!$J$5:$J$604,Vendas!$K$5:$K$604,B23)) -> 1055.5 | H23: =IF(OR(B23="",G23=0),"",IF(COUNTIFS(Vendas!$K$5:$K$604,B23,Vendas!$N$5:$N$604,"A conferir")>0,"Falta conferir",IF(COUNTIFS(Vendas!$K$5:$K$604,B23,Vendas!$N$5:$N$604,"A cair")>0,"A cair","Conferido"))) -> Conferido
A24: 5 | B24: =IF(5>DAY(DATE(Config!$B$5,Config!$B$7+1,0)),"",DATE(Config!$B$5,Config!$B$7,5)) -> 46239 | C24: =IF(B24="","",COUNTIFS(Vendas!$A$5:$A$604,B24)) -> 3 | D24: =IF(B24="","",SUMIFS(Vendas!$F$5:$F$604,Vendas!$A$5:$A$604,B24)) -> 1140 | E24: =IF(B24="","",SUMIFS(Vendas!$I$5:$I$604,Vendas!$A$5:$A$604,B24)) -> 20.52 | F24: =IF(B24="","",D24-E24) -> 1119.48 | G24: =IF(B24="","",SUMIFS(Vendas!$J$5:$J$604,Vendas!$K$5:$K$604,B24)) -> 2629.92 | H24: =IF(OR(B24="",G24=0),"",IF(COUNTIFS(Vendas!$K$5:$K$604,B24,Vendas!$N$5:$N$604,"A conferir")>0,"Falta conferir",IF(COUNTIFS(Vendas!$K$5:$K$604,B24,Vendas!$N$5:$N$604,"A cair")>0,"A cair","Conferido"))) -> Conferido
A25: 6 | B25: =IF(6>DAY(DATE(Config!$B$5,Config!$B$7+1,0)),"",DATE(Config!$B$5,Config!$B$7,6)) -> 46240 | C25: =IF(B25="","",COUNTIFS(Vendas!$A$5:$A$604,B25)) -> 5 | D25: =IF(B25="","",SUMIFS(Vendas!$F$5:$F$604,Vendas!$A$5:$A$604,B25)) -> 2010 | E25: =IF(B25="","",SUMIFS(Vendas!$I$5:$I$604,Vendas!$A$5:$A$604,B25)) -> 36.12 | F25: =IF(B25="","",D25-E25) -> 1973.88 | G25: =IF(B25="","",SUMIFS(Vendas!$J$5:$J$604,Vendas!$K$5:$K$604,B25)) -> 1959.98 | H25: =IF(OR(B25="",G25=0),"",IF(COUNTIFS(Vendas!$K$5:$K$604,B25,Vendas!$N$5:$N$604,"A conferir")>0,"Falta conferir",IF(COUNTIFS(Vendas!$K$5:$K$604,B25,Vendas!$N$5:$N$604,"A cair")>0,"A cair","Conferido"))) -> Conferido
A26: 7 | B26: =IF(7>DAY(DATE(Config!$B$5,Config!$B$7+1,0)),"",DATE(Config!$B$5,Config!$B$7,7)) -> 46241 | C26: =IF(B26="","",COUNTIFS(Vendas!$A$5:$A$604,B26)) -> 2 | D26: =IF(B26="","",SUMIFS(Vendas!$F$5:$F$604,Vendas!$A$5:$A$604,B26)) -> 510 | E26: =IF(B26="","",SUMIFS(Vendas!$I$5:$I$604,Vendas!$A$5:$A$604,B26)) -> 12.16 | F26: =IF(B26="","",D26-E26) -> 497.84 | G26: =IF(B26="","",SUMIFS(Vendas!$J$5:$J$604,Vendas!$K$5:$K$604,B26)) -> 872.14 | H26: =IF(OR(B26="",G26=0),"",IF(COUNTIFS(Vendas!$K$5:$K$604,B26,Vendas!$N$5:$N$604,"A conferir")>0,"Falta conferir",IF(COUNTIFS(Vendas!$K$5:$K$604,B26,Vendas!$N$5:$N$604,"A cair")>0,"A cair","Conferido"))) -> Conferido
A27: 8 | B27: =IF(8>DAY(DATE(Config!$B$5,Config!$B$7+1,0)),"",DATE(Config!$B$5,Config!$B$7,8)) -> 46242 | C27: =IF(B27="","",COUNTIFS(Vendas!$A$5:$A$604,B27)) -> 0 | D27: =IF(B27="","",SUMIFS(Vendas!$F$5:$F$604,Vendas!$A$5:$A$604,B27)) -> 0 | E27: =IF(B27="","",SUMIFS(Vendas!$I$5:$I$604,Vendas!$A$5:$A$604,B27)) -> 0 | F27: =IF(B27="","",D27-E27) -> 0 | G27: =IF(B27="","",SUMIFS(Vendas!$J$5:$J$604,Vendas!$K$5:$K$604,B27)) -> 1248.72 | H27: =IF(OR(B27="",G27=0),"",IF(COUNTIFS(Vendas!$K$5:$K$604,B27,Vendas!$N$5:$N$604,"A conferir")>0,"Falta conferir",IF(COUNTIFS(Vendas!$K$5:$K$604,B27,Vendas!$N$5:$N$604,"A cair")>0,"A cair","Conferido"))) -> Conferido
A28: 9 | B28: =IF(9>DAY(DATE(Config!$B$5,Config!$B$7+1,0)),"",DATE(Config!$B$5,Config!$B$7,9)) -> 46243 | C28: =IF(B28="","",COUNTIFS(Vendas!$A$5:$A$604,B28)) -> 0 | D28: =IF(B28="","",SUMIFS(Vendas!$F$5:$F$604,Vendas!$A$5:$A$604,B28)) -> 0 | E28: =IF(B28="","",SUMIFS(Vendas!$I$5:$I$604,Vendas!$A$5:$A$604,B28)) -> 0 | F28: =IF(B28="","",D28-E28) -> 0 | G28: =IF(B28="","",SUMIFS(Vendas!$J$5:$J$604,Vendas!$K$5:$K$604,B28)) -> 0 | H28: =IF(OR(B28="",G28=0),"",IF(COUNTIFS(Vendas!$K$5:$K$604,B28,Vendas!$N$5:$N$604,"A conferir")>0,"Falta conferir",IF(COUNTIFS(Vendas!$K$5:$K$604,B28,Vendas!$N$5:$N$604,"A cair")>0,"A cair","Conferido")))
A29: 10 | B29: =IF(10>DAY(DATE(Config!$B$5,Config!$B$7+1,0)),"",DATE(Config!$B$5,Config!$B$7,10)) -> 46244 | C29: =IF(B29="","",COUNTIFS(Vendas!$A$5:$A$604,B29)) -> 3 | D29: =IF(B29="","",SUMIFS(Vendas!$F$5:$F$604,Vendas!$A$5:$A$604,B29)) -> 860 | E29: =IF(B29="","",SUMIFS(Vendas!$I$5:$I$604,Vendas!$A$5:$A$604,B29)) -> 17.41 | F29: =IF(B29="","",D29-E29) -> 842.59 | G29: =IF(B29="","",SUMIFS(Vendas!$J$5:$J$604,Vendas!$K$5:$K$604,B29)) -> 130 | H29: =IF(OR(B29="",G29=0),"",IF(COUNTIFS(Vendas!$K$5:$K$604,B29,Vendas!$N$5:$N$604,"A conferir")>0,"Falta conferir",IF(COUNTIFS(Vendas!$K$5:$K$604,B29,Vendas!$N$5:$N$604,"A cair")>0,"A cair","Conferido"))) -> Conferido
A30: 11 | B30: =IF(11>DAY(DATE(Config!$B$5,Config!$B$7+1,0)),"",DATE(Config!$B$5,Config!$B$7,11)) -> 46245 | C30: =IF(B30="","",COUNTIFS(Vendas!$A$5:$A$604,B30)) -> 7 | D30: =IF(B30="","",SUMIFS(Vendas!$F$5:$F$604,Vendas!$A$5:$A$604,B30)) -> 2490 | E30: =IF(B30="","",SUMIFS(Vendas!$I$5:$I$604,Vendas!$A$5:$A$604,B30)) -> 45.03 | F30: =IF(B30="","",D30-E30) -> 2444.97 | G30: =IF(B30="","",SUMIFS(Vendas!$J$5:$J$604,Vendas!$K$5:$K$604,B30)) -> 1324.75 | H30: =IF(OR(B30="",G30=0),"",IF(COUNTIFS(Vendas!$K$5:$K$604,B30,Vendas!$N$5:$N$604,"A conferir")>0,"Falta conferir",IF(COUNTIFS(Vendas!$K$5:$K$604,B30,Vendas!$N$5:$N$604,"A cair")>0,"A cair","Conferido"))) -> Conferido
A31: 12 | B31: =IF(12>DAY(DATE(Config!$B$5,Config!$B$7+1,0)),"",DATE(Config!$B$5,Config!$B$7,12)) -> 46246 | C31: =IF(B31="","",COUNTIFS(Vendas!$A$5:$A$604,B31)) -> 4 | D31: =IF(B31="","",SUMIFS(Vendas!$F$5:$F$604,Vendas!$A$5:$A$604,B31)) -> 1520 | E31: =IF(B31="","",SUMIFS(Vendas!$I$5:$I$604,Vendas!$A$5:$A$604,B31)) -> 24.32 | F31: =IF(B31="","",D31-E31) -> 1495.68 | G31: =IF(B31="","",SUMIFS(Vendas!$J$5:$J$604,Vendas!$K$5:$K$604,B31)) -> 1595.77 | H31: =IF(OR(B31="",G31=0),"",IF(COUNTIFS(Vendas!$K$5:$K$604,B31,Vendas!$N$5:$N$604,"A conferir")>0,"Falta conferir",IF(COUNTIFS(Vendas!$K$5:$K$604,B31,Vendas!$N$5:$N$604,"A cair")>0,"A cair","Conferido"))) -> Conferido
A32: 13 | B32: =IF(13>DAY(DATE(Config!$B$5,Config!$B$7+1,0)),"",DATE(Config!$B$5,Config!$B$7,13)) -> 46247 | C32: =IF(B32="","",COUNTIFS(Vendas!$A$5:$A$604,B32)) -> 8 | D32: =IF(B32="","",SUMIFS(Vendas!$F$5:$F$604,Vendas!$A$5:$A$604,B32)) -> 3120 | E32: =IF(B32="","",SUMIFS(Vendas!$I$5:$I$604,Vendas!$A$5:$A$604,B32)) -> 24.16 | F32: =IF(B32="","",D32-E32) -> 3095.84 | G32: =IF(B32="","",SUMIFS(Vendas!$J$5:$J$604,Vendas!$K$5:$K$604,B32)) -> 4262.52 | H32: =IF(OR(B32="",G32=0),"",IF(COUNTIFS(Vendas!$K$5:$K$604,B32,Vendas!$N$5:$N$604,"A conferir")>0,"Falta conferir",IF(COUNTIFS(Vendas!$K$5:$K$604,B32,Vendas!$N$5:$N$604,"A cair")>0,"A cair","Conferido"))) -> Conferido
A33: 14 | B33: =IF(14>DAY(DATE(Config!$B$5,Config!$B$7+1,0)),"",DATE(Config!$B$5,Config!$B$7,14)) -> 46248 | C33: =IF(B33="","",COUNTIFS(Vendas!$A$5:$A$604,B33)) -> 0 | D33: =IF(B33="","",SUMIFS(Vendas!$F$5:$F$604,Vendas!$A$5:$A$604,B33)) -> 0 | E33: =IF(B33="","",SUMIFS(Vendas!$I$5:$I$604,Vendas!$A$5:$A$604,B33)) -> 0 | F33: =IF(B33="","",D33-E33) -> 0 | G33: =IF(B33="","",SUMIFS(Vendas!$J$5:$J$604,Vendas!$K$5:$K$604,B33)) -> 1155.84 | H33: =IF(OR(B33="",G33=0),"",IF(COUNTIFS(Vendas!$K$5:$K$604,B33,Vendas!$N$5:$N$604,"A conferir")>0,"Falta conferir",IF(COUNTIFS(Vendas!$K$5:$K$604,B33,Vendas!$N$5:$N$604,"A cair")>0,"A cair","Conferido"))) -> Conferido
A34: 15 | B34: =IF(15>DAY(DATE(Config!$B$5,Config!$B$7+1,0)),"",DATE(Config!$B$5,Config!$B$7,15)) -> 46249 | C34: =IF(B34="","",COUNTIFS(Vendas!$A$5:$A$604,B34)) -> 0 | D34: =IF(B34="","",SUMIFS(Vendas!$F$5:$F$604,Vendas!$A$5:$A$604,B34)) -> 0 | E34: =IF(B34="","",SUMIFS(Vendas!$I$5:$I$604,Vendas!$A$5:$A$604,B34)) -> 0 | F34: =IF(B34="","",D34-E34) -> 0 | G34: =IF(B34="","",SUMIFS(Vendas!$J$5:$J$604,Vendas!$K$5:$K$604,B34)) -> 1122.88 | H34: =IF(OR(B34="",G34=0),"",IF(COUNTIFS(Vendas!$K$5:$K$604,B34,Vendas!$N$5:$N$604,"A conferir")>0,"Falta conferir",IF(COUNTIFS(Vendas!$K$5:$K$604,B34,Vendas!$N$5:$N$604,"A cair")>0,"A cair","Conferido"))) -> Conferido
A35: 16 | B35: =IF(16>DAY(DATE(Config!$B$5,Config!$B$7+1,0)),"",DATE(Config!$B$5,Config!$B$7,16)) -> 46250 | C35: =IF(B35="","",COUNTIFS(Vendas!$A$5:$A$604,B35)) -> 0 | D35: =IF(B35="","",SUMIFS(Vendas!$F$5:$F$604,Vendas!$A$5:$A$604,B35)) -> 0 | E35: =IF(B35="","",SUMIFS(Vendas!$I$5:$I$604,Vendas!$A$5:$A$604,B35)) -> 0 | F35: =IF(B35="","",D35-E35) -> 0 | G35: =IF(B35="","",SUMIFS(Vendas!$J$5:$J$604,Vendas!$K$5:$K$604,B35)) -> 367.84 | H35: =IF(OR(B35="",G35=0),"",IF(COUNTIFS(Vendas!$K$5:$K$604,B35,Vendas!$N$5:$N$604,"A conferir")>0,"Falta conferir",IF(COUNTIFS(Vendas!$K$5:$K$604,B35,Vendas!$N$5:$N$604,"A cair")>0,"A cair","Conferido"))) -> Conferido
A36: 17 | B36: =IF(17>DAY(DATE(Config!$B$5,Config!$B$7+1,0)),"",DATE(Config!$B$5,Config!$B$7,17)) -> 46251 | C36: =IF(B36="","",COUNTIFS(Vendas!$A$5:$A$604,B36)) -> 3 | D36: =IF(B36="","",SUMIFS(Vendas!$F$5:$F$604,Vendas!$A$5:$A$604,B36)) -> 1060 | E36: =IF(B36="","",SUMIFS(Vendas!$I$5:$I$604,Vendas!$A$5:$A$604,B36)) -> 17.4 | F36: =IF(B36="","",D36-E36) -> 1042.6 | G36: =IF(B36="","",SUMIFS(Vendas!$J$5:$J$604,Vendas!$K$5:$K$604,B36)) -> 380 | H36: =IF(OR(B36="",G36=0),"",IF(COUNTIFS(Vendas!$K$5:$K$604,B36,Vendas!$N$5:$N$604,"A conferir")>0,"Falta conferir",IF(COUNTIFS(Vendas!$K$5:$K$604,B36,Vendas!$N$5:$N$604,"A cair")>0,"A cair","Conferido"))) -> Conferido
A37: 18 | B37: =IF(18>DAY(DATE(Config!$B$5,Config!$B$7+1,0)),"",DATE(Config!$B$5,Config!$B$7,18)) -> 46252 | C37: =IF(B37="","",COUNTIFS(Vendas!$A$5:$A$604,B37)) -> 4 | D37: =IF(B37="","",SUMIFS(Vendas!$F$5:$F$604,Vendas!$A$5:$A$604,B37)) -> 1540 | E37: =IF(B37="","",SUMIFS(Vendas!$I$5:$I$604,Vendas!$A$5:$A$604,B37)) -> 20.52 | F37: =IF(B37="","",D37-E37) -> 1519.48 | G37: =IF(B37="","",SUMIFS(Vendas!$J$5:$J$604,Vendas!$K$5:$K$604,B37)) -> 1154.3 | H37: =IF(OR(B37="",G37=0),"",IF(COUNTIFS(Vendas!$K$5:$K$604,B37,Vendas!$N$5:$N$604,"A conferir")>0,"Falta conferir",IF(COUNTIFS(Vendas!$K$5:$K$604,B37,Vendas!$N$5:$N$604,"A cair")>0,"A cair","Conferido"))) -> Conferido
A38: 19 | B38: =IF(19>DAY(DATE(Config!$B$5,Config!$B$7+1,0)),"",DATE(Config!$B$5,Config!$B$7,19)) -> 46253 | C38: =IF(B38="","",COUNTIFS(Vendas!$A$5:$A$604,B38)) -> 2 | D38: =IF(B38="","",SUMIFS(Vendas!$F$5:$F$604,Vendas!$A$5:$A$604,B38)) -> 760 | E38: =IF(B38="","",SUMIFS(Vendas!$I$5:$I$604,Vendas!$A$5:$A$604,B38)) -> 5.7 | F38: =IF(B38="","",D38-E38) -> 754.3 | G38: =IF(B38="","",SUMIFS(Vendas!$J$5:$J$604,Vendas!$K$5:$K$604,B38)) -> 1489.98 | H38: =IF(OR(B38="",G38=0),"",IF(COUNTIFS(Vendas!$K$5:$K$604,B38,Vendas!$N$5:$N$604,"A conferir")>0,"Falta conferir",IF(COUNTIFS(Vendas!$K$5:$K$604,B38,Vendas!$N$5:$N$604,"A cair")>0,"A cair","Conferido"))) -> Conferido
A39: 20 | B39: =IF(20>DAY(DATE(Config!$B$5,Config!$B$7+1,0)),"",DATE(Config!$B$5,Config!$B$7,20)) -> 46254 | C39: =IF(B39="","",COUNTIFS(Vendas!$A$5:$A$604,B39)) -> 9 | D39: =IF(B39="","",SUMIFS(Vendas!$F$5:$F$604,Vendas!$A$5:$A$604,B39)) -> 3370 | E39: =IF(B39="","",SUMIFS(Vendas!$I$5:$I$604,Vendas!$A$5:$A$604,B39)) -> 34.4 | F39: =IF(B39="","",D39-E39) -> 3335.6 | G39: =IF(B39="","",SUMIFS(Vendas!$J$5:$J$604,Vendas!$K$5:$K$604,B39)) -> 3664.52 | H39: =IF(OR(B39="",G39=0),"",IF(COUNTIFS(Vendas!$K$5:$K$604,B39,Vendas!$N$5:$N$604,"A conferir")>0,"Falta conferir",IF(COUNTIFS(Vendas!$K$5:$K$604,B39,Vendas!$N$5:$N$604,"A cair")>0,"A cair","Conferido"))) -> Conferido
A40: 21 | B40: =IF(21>DAY(DATE(Config!$B$5,Config!$B$7+1,0)),"",DATE(Config!$B$5,Config!$B$7,21)) -> 46255 | C40: =IF(B40="","",COUNTIFS(Vendas!$A$5:$A$604,B40)) -> 0 | D40: =IF(B40="","",SUMIFS(Vendas!$F$5:$F$604,Vendas!$A$5:$A$604,B40)) -> 0 | E40: =IF(B40="","",SUMIFS(Vendas!$I$5:$I$604,Vendas!$A$5:$A$604,B40)) -> 0 | F40: =IF(B40="","",D40-E40) -> 0 | G40: =IF(B40="","",SUMIFS(Vendas!$J$5:$J$604,Vendas!$K$5:$K$604,B40)) -> 1129.68 | H40: =IF(OR(B40="",G40=0),"",IF(COUNTIFS(Vendas!$K$5:$K$604,B40,Vendas!$N$5:$N$604,"A conferir")>0,"Falta conferir",IF(COUNTIFS(Vendas!$K$5:$K$604,B40,Vendas!$N$5:$N$604,"A cair")>0,"A cair","Conferido"))) -> Conferido
A41: 22 | B41: =IF(22>DAY(DATE(Config!$B$5,Config!$B$7+1,0)),"",DATE(Config!$B$5,Config!$B$7,22)) -> 46256 | C41: =IF(B41="","",COUNTIFS(Vendas!$A$5:$A$604,B41)) -> 0 | D41: =IF(B41="","",SUMIFS(Vendas!$F$5:$F$604,Vendas!$A$5:$A$604,B41)) -> 0 | E41: =IF(B41="","",SUMIFS(Vendas!$I$5:$I$604,Vendas!$A$5:$A$604,B41)) -> 0 | F41: =IF(B41="","",D41-E41) -> 0 | G41: =IF(B41="","",SUMIFS(Vendas!$J$5:$J$604,Vendas!$K$5:$K$604,B41)) -> 1485.26 | H41: =IF(OR(B41="",G41=0),"",IF(COUNTIFS(Vendas!$K$5:$K$604,B41,Vendas!$N$5:$N$604,"A conferir")>0,"Falta conferir",IF(COUNTIFS(Vendas!$K$5:$K$604,B41,Vendas!$N$5:$N$604,"A cair")>0,"A cair","Conferido"))) -> Conferido
A42: 23 | B42: =IF(23>DAY(DATE(Config!$B$5,Config!$B$7+1,0)),"",DATE(Config!$B$5,Config!$B$7,23)) -> 46257 | C42: =IF(B42="","",COUNTIFS(Vendas!$A$5:$A$604,B42)) -> 0 | D42: =IF(B42="","",SUMIFS(Vendas!$F$5:$F$604,Vendas!$A$5:$A$604,B42)) -> 0 | E42: =IF(B42="","",SUMIFS(Vendas!$I$5:$I$604,Vendas!$A$5:$A$604,B42)) -> 0 | F42: =IF(B42="","",D42-E42) -> 0 | G42: =IF(B42="","",SUMIFS(Vendas!$J$5:$J$604,Vendas!$K$5:$K$604,B42)) -> 0 | H42: =IF(OR(B42="",G42=0),"",IF(COUNTIFS(Vendas!$K$5:$K$604,B42,Vendas!$N$5:$N$604,"A conferir")>0,"Falta conferir",IF(COUNTIFS(Vendas!$K$5:$K$604,B42,Vendas!$N$5:$N$604,"A cair")>0,"A cair","Conferido")))
A43: 24 | B43: =IF(24>DAY(DATE(Config!$B$5,Config!$B$7+1,0)),"",DATE(Config!$B$5,Config!$B$7,24)) -> 46258 | C43: =IF(B43="","",COUNTIFS(Vendas!$A$5:$A$604,B43)) -> 7 | D43: =IF(B43="","",SUMIFS(Vendas!$F$5:$F$604,Vendas!$A$5:$A$604,B43)) -> 2410 | E43: =IF(B43="","",SUMIFS(Vendas!$I$5:$I$604,Vendas!$A$5:$A$604,B43)) -> 36.84 | F43: =IF(B43="","",D43-E43) -> 2373.16 | G43: =IF(B43="","",SUMIFS(Vendas!$J$5:$J$604,Vendas!$K$5:$K$604,B43)) -> 1140 | H43: =IF(OR(B43="",G43=0),"",IF(COUNTIFS(Vendas!$K$5:$K$604,B43,Vendas!$N$5:$N$604,"A conferir")>0,"Falta conferir",IF(COUNTIFS(Vendas!$K$5:$K$604,B43,Vendas!$N$5:$N$604,"A cair")>0,"A cair","Conferido"))) -> Conferido
A44: 25 | B44: =IF(25>DAY(DATE(Config!$B$5,Config!$B$7+1,0)),"",DATE(Config!$B$5,Config!$B$7,25)) -> 46259 | C44: =IF(B44="","",COUNTIFS(Vendas!$A$5:$A$604,B44)) -> 8 | D44: =IF(B44="","",SUMIFS(Vendas!$F$5:$F$604,Vendas!$A$5:$A$604,B44)) -> 3020 | E44: =IF(B44="","",SUMIFS(Vendas!$I$5:$I$604,Vendas!$A$5:$A$604,B44)) -> 76.09 | F44: =IF(B44="","",D44-E44) -> 2943.91 | G44: =IF(B44="","",SUMIFS(Vendas!$J$5:$J$604,Vendas!$K$5:$K$604,B44)) -> 1134.3 | H44: =IF(OR(B44="",G44=0),"",IF(COUNTIFS(Vendas!$K$5:$K$604,B44,Vendas!$N$5:$N$604,"A conferir")>0,"Falta conferir",IF(COUNTIFS(Vendas!$K$5:$K$604,B44,Vendas!$N$5:$N$604,"A cair")>0,"A cair","Conferido"))) -> Conferido
A45: 26 | B45: =IF(26>DAY(DATE(Config!$B$5,Config!$B$7+1,0)),"",DATE(Config!$B$5,Config!$B$7,26)) -> 46260 | C45: =IF(B45="","",COUNTIFS(Vendas!$A$5:$A$604,B45)) -> 3 | D45: =IF(B45="","",SUMIFS(Vendas!$F$5:$F$604,Vendas!$A$5:$A$604,B45)) -> 1140 | E45: =IF(B45="","",SUMIFS(Vendas!$I$5:$I$604,Vendas!$A$5:$A$604,B45)) -> 5.7 | F45: =IF(B45="","",D45-E45) -> 1134.3 | G45: =IF(B45="","",SUMIFS(Vendas!$J$5:$J$604,Vendas!$K$5:$K$604,B45)) -> 1521.84 | H45: =IF(OR(B45="",G45=0),"",IF(COUNTIFS(Vendas!$K$5:$K$604,B45,Vendas!$N$5:$N$604,"A conferir")>0,"Falta conferir",IF(COUNTIFS(Vendas!$K$5:$K$604,B45,Vendas!$N$5:$N$604,"A cair")>0,"A cair","Conferido"))) -> Conferido
A46: 27 | B46: =IF(27>DAY(DATE(Config!$B$5,Config!$B$7+1,0)),"",DATE(Config!$B$5,Config!$B$7,27)) -> 46261 | C46: =IF(B46="","",COUNTIFS(Vendas!$A$5:$A$604,B46)) -> 6 | D46: =IF(B46="","",SUMIFS(Vendas!$F$5:$F$604,Vendas!$A$5:$A$604,B46)) -> 2240 | E46: =IF(B46="","",SUMIFS(Vendas!$I$5:$I$604,Vendas!$A$5:$A$604,B46)) -> 36.02 | F46: =IF(B46="","",D46-E46) -> 2203.98 | G46: =IF(B46="","",SUMIFS(Vendas!$J$5:$J$604,Vendas!$K$5:$K$604,B46)) -> 2262.14 | H46: =IF(OR(B46="",G46=0),"",IF(COUNTIFS(Vendas!$K$5:$K$604,B46,Vendas!$N$5:$N$604,"A conferir")>0,"Falta conferir",IF(COUNTIFS(Vendas!$K$5:$K$604,B46,Vendas!$N$5:$N$604,"A cair")>0,"A cair","Conferido"))) -> Conferido
A47: 28 | B47: =IF(28>DAY(DATE(Config!$B$5,Config!$B$7+1,0)),"",DATE(Config!$B$5,Config!$B$7,28)) -> 46262 | C47: =IF(B47="","",COUNTIFS(Vendas!$A$5:$A$604,B47)) -> 0 | D47: =IF(B47="","",SUMIFS(Vendas!$F$5:$F$604,Vendas!$A$5:$A$604,B47)) -> 0 | E47: =IF(B47="","",SUMIFS(Vendas!$I$5:$I$604,Vendas!$A$5:$A$604,B47)) -> 0 | F47: =IF(B47="","",D47-E47) -> 0 | G47: =IF(B47="","",SUMIFS(Vendas!$J$5:$J$604,Vendas!$K$5:$K$604,B47)) -> 768.3 | H47: =IF(OR(B47="",G47=0),"",IF(COUNTIFS(Vendas!$K$5:$K$604,B47,Vendas!$N$5:$N$604,"A conferir")>0,"Falta conferir",IF(COUNTIFS(Vendas!$K$5:$K$604,B47,Vendas!$N$5:$N$604,"A cair")>0,"A cair","Conferido"))) -> Conferido
A48: 29 | B48: =IF(29>DAY(DATE(Config!$B$5,Config!$B$7+1,0)),"",DATE(Config!$B$5,Config!$B$7,29)) -> 46263 | C48: =IF(B48="","",COUNTIFS(Vendas!$A$5:$A$604,B48)) -> 0 | D48: =IF(B48="","",SUMIFS(Vendas!$F$5:$F$604,Vendas!$A$5:$A$604,B48)) -> 0 | E48: =IF(B48="","",SUMIFS(Vendas!$I$5:$I$604,Vendas!$A$5:$A$604,B48)) -> 0 | F48: =IF(B48="","",D48-E48) -> 0 | G48: =IF(B48="","",SUMIFS(Vendas!$J$5:$J$604,Vendas!$K$5:$K$604,B48)) -> 387.2 | H48: =IF(OR(B48="",G48=0),"",IF(COUNTIFS(Vendas!$K$5:$K$604,B48,Vendas!$N$5:$N$604,"A conferir")>0,"Falta conferir",IF(COUNTIFS(Vendas!$K$5:$K$604,B48,Vendas!$N$5:$N$604,"A cair")>0,"A cair","Conferido"))) -> Conferido
A49: 30 | B49: =IF(30>DAY(DATE(Config!$B$5,Config!$B$7+1,0)),"",DATE(Config!$B$5,Config!$B$7,30)) -> 46264 | C49: =IF(B49="","",COUNTIFS(Vendas!$A$5:$A$604,B49)) -> 0 | D49: =IF(B49="","",SUMIFS(Vendas!$F$5:$F$604,Vendas!$A$5:$A$604,B49)) -> 0 | E49: =IF(B49="","",SUMIFS(Vendas!$I$5:$I$604,Vendas!$A$5:$A$604,B49)) -> 0 | F49: =IF(B49="","",D49-E49) -> 0 | G49: =IF(B49="","",SUMIFS(Vendas!$J$5:$J$604,Vendas!$K$5:$K$604,B49)) -> 929.28 | H49: =IF(OR(B49="",G49=0),"",IF(COUNTIFS(Vendas!$K$5:$K$604,B49,Vendas!$N$5:$N$604,"A conferir")>0,"Falta conferir",IF(COUNTIFS(Vendas!$K$5:$K$604,B49,Vendas!$N$5:$N$604,"A cair")>0,"A cair","Conferido"))) -> Conferido
A50: 31 | B50: =IF(31>DAY(DATE(Config!$B$5,Config!$B$7+1,0)),"",DATE(Config!$B$5,Config!$B$7,31)) -> 46265 | C50: =IF(B50="","",COUNTIFS(Vendas!$A$5:$A$604,B50)) -> 3 | D50: =IF(B50="","",SUMIFS(Vendas!$F$5:$F$604,Vendas!$A$5:$A$604,B50)) -> 890 | E50: =IF(B50="","",SUMIFS(Vendas!$I$5:$I$604,Vendas!$A$5:$A$604,B50)) -> 7.65 | F50: =IF(B50="","",D50-E50) -> 882.35 | G50: =IF(B50="","",SUMIFS(Vendas!$J$5:$J$604,Vendas!$K$5:$K$604,B50)) -> 380 | H50: =IF(OR(B50="",G50=0),"",IF(COUNTIFS(Vendas!$K$5:$K$604,B50,Vendas!$N$5:$N$604,"A conferir")>0,"Falta conferir",IF(COUNTIFS(Vendas!$K$5:$K$604,B50,Vendas!$N$5:$N$604,"A cair")>0,"A cair","Conferido"))) -> Conferido
A51: "Cai na conta neste dia" soma o líquido das vendas com previsão nesse dia (inclusive vendas de meses anteriores): é o número para bater com o extrato da conta.
A54: Falta conferir no extrato (previsão vencida)
A55: # | B55: Data da venda | C55: Paciente | D55: Procedimento | E55: Tipo | F55: Parcelas | G55: Bruto (R$) | H55: Líquido (R$) | I55: Previsão na conta | J55: Dias desde a previsão
A56: 1 | B56: =IFERROR(IF(LARGE(Vendas!$O$5:$O$604,1)>0,INDEX(Vendas!$A$5:$A$604,MATCH(LARGE(Vendas!$O$5:$O$604,1),Vendas!$O$5:$O$604,0)),""),"") -> 46275 | C56: =IFERROR(IF(LARGE(Vendas!$O$5:$O$604,1)>0,INDEX(Vendas!$B$5:$B$604,MATCH(LARGE(Vendas!$O$5:$O$604,1),Vendas!$O$5:$O$604,0)),""),"") -> Mônica Almeida | D56: =IFERROR(IF(LARGE(Vendas!$O$5:$O$604,1)>0,INDEX(Vendas!$C$5:$C$604,MATCH(LARGE(Vendas!$O$5:$O$604,1),Vendas!$O$5:$O$604,0)),""),"") -> Avaliação endócrina | E56: =IFERROR(IF(LARGE(Vendas!$O$5:$O$604,1)>0,INDEX(Vendas!$D$5:$D$604,MATCH(LARGE(Vendas!$O$5:$O$604,1),Vendas!$O$5:$O$604,0)),""),"") -> Pix | F56: =IFERROR(IF(LARGE(Vendas!$O$5:$O$604,1)>0,INDEX(Vendas!$E$5:$E$604,MATCH(LARGE(Vendas!$O$5:$O$604,1),Vendas!$O$5:$O$604,0)),""),"") -> 0 | G56: =IFERROR(IF(LARGE(Vendas!$O$5:$O$604,1)>0,INDEX(Vendas!$F$5:$F$604,MATCH(LARGE(Vendas!$O$5:$O$604,1),Vendas!$O$5:$O$604,0)),""),"") -> 400 | H56: =IFERROR(IF(LARGE(Vendas!$O$5:$O$604,1)>0,INDEX(Vendas!$J$5:$J$604,MATCH(LARGE(Vendas!$O$5:$O$604,1),Vendas!$O$5:$O$604,0)),""),"") -> 400 | I56: =IFERROR(IF(LARGE(Vendas!$O$5:$O$604,1)>0,INDEX(Vendas!$K$5:$K$604,MATCH(LARGE(Vendas!$O$5:$O$604,1),Vendas!$O$5:$O$604,0)),""),"") -> 46275 | J56: =IF(I56="","",Config!$B$8-I56) -> 4
A57: 2 | B57: =IFERROR(IF(LARGE(Vendas!$O$5:$O$604,2)>0,INDEX(Vendas!$A$5:$A$604,MATCH(LARGE(Vendas!$O$5:$O$604,2),Vendas!$O$5:$O$604,0)),""),"") -> 46245 | C57: =IFERROR(IF(LARGE(Vendas!$O$5:$O$604,2)>0,INDEX(Vendas!$B$5:$B$604,MATCH(LARGE(Vendas!$O$5:$O$604,2),Vendas!$O$5:$O$604,0)),""),"") -> Beatriz Monteiro | D57: =IFERROR(IF(LARGE(Vendas!$O$5:$O$604,2)>0,INDEX(Vendas!$C$5:$C$604,MATCH(LARGE(Vendas!$O$5:$O$604,2),Vendas!$O$5:$O$604,0)),""),"") -> Avaliação endócrina | E57: =IFERROR(IF(LARGE(Vendas!$O$5:$O$604,2)>0,INDEX(Vendas!$D$5:$D$604,MATCH(LARGE(Vendas!$O$5:$O$604,2),Vendas!$O$5:$O$604,0)),""),"") -> Cartão de crédito | F57: =IFERROR(IF(LARGE(Vendas!$O$5:$O$604,2)>0,INDEX(Vendas!$E$5:$E$604,MATCH(LARGE(Vendas!$O$5:$O$604,2),Vendas!$O$5:$O$604,0)),""),"") -> 0 | G57: =IFERROR(IF(LARGE(Vendas!$O$5:$O$604,2)>0,INDEX(Vendas!$F$5:$F$604,MATCH(LARGE(Vendas!$O$5:$O$604,2),Vendas!$O$5:$O$604,0)),""),"") -> 400 | H57: =IFERROR(IF(LARGE(Vendas!$O$5:$O$604,2)>0,INDEX(Vendas!$J$5:$J$604,MATCH(LARGE(Vendas!$O$5:$O$604,2),Vendas!$O$5:$O$604,0)),""),"") -> 387.2 | I57: =IFERROR(IF(LARGE(Vendas!$O$5:$O$604,2)>0,INDEX(Vendas!$K$5:$K$604,MATCH(LARGE(Vendas!$O$5:$O$604,2),Vendas!$O$5:$O$604,0)),""),"") -> 46275 | J57: =IF(I57="","",Config!$B$8-I57) -> 4
A58: 3 | B58: =IFERROR(IF(LARGE(Vendas!$O$5:$O$604,3)>0,INDEX(Vendas!$A$5:$A$604,MATCH(LARGE(Vendas!$O$5:$O$604,3),Vendas!$O$5:$O$604,0)),""),"") -> 46275 | C58: =IFERROR(IF(LARGE(Vendas!$O$5:$O$604,3)>0,INDEX(Vendas!$B$5:$B$604,MATCH(LARGE(Vendas!$O$5:$O$604,3),Vendas!$O$5:$O$604,0)),""),"") -> Regina Macedo | D58: =IFERROR(IF(LARGE(Vendas!$O$5:$O$604,3)>0,INDEX(Vendas!$C$5:$C$604,MATCH(LARGE(Vendas!$O$5:$O$604,3),Vendas!$O$5:$O$604,0)),""),"") -> Consulta | E58: =IFERROR(IF(LARGE(Vendas!$O$5:$O$604,3)>0,INDEX(Vendas!$D$5:$D$604,MATCH(LARGE(Vendas!$O$5:$O$604,3),Vendas!$O$5:$O$604,0)),""),"") -> Pix | F58: =IFERROR(IF(LARGE(Vendas!$O$5:$O$604,3)>0,INDEX(Vendas!$E$5:$E$604,MATCH(LARGE(Vendas!$O$5:$O$604,3),Vendas!$O$5:$O$604,0)),""),"") -> 0 | G58: =IFERROR(IF(LARGE(Vendas!$O$5:$O$604,3)>0,INDEX(Vendas!$F$5:$F$604,MATCH(LARGE(Vendas!$O$5:$O$604,3),Vendas!$O$5:$O$604,0)),""),"") -> 380 | H58: =IFERROR(IF(LARGE(Vendas!$O$5:$O$604,3)>0,INDEX(Vendas!$J$5:$J$604,MATCH(LARGE(Vendas!$O$5:$O$604,3),Vendas!$O$5:$O$604,0)),""),"") -> 380 | I58: =IFERROR(IF(LARGE(Vendas!$O$5:$O$604,3)>0,INDEX(Vendas!$K$5:$K$604,MATCH(LARGE(Vendas!$O$5:$O$604,3),Vendas!$O$5:$O$604,0)),""),"") -> 46275 | J58: =IF(I58="","",Config!$B$8-I58) -> 4
A59: 4 | B59: =IFERROR(IF(LARGE(Vendas!$O$5:$O$604,4)>0,INDEX(Vendas!$A$5:$A$604,MATCH(LARGE(Vendas!$O$5:$O$604,4),Vendas!$O$5:$O$604,0)),""),"") -> 46274 | C59: =IFERROR(IF(LARGE(Vendas!$O$5:$O$604,4)>0,INDEX(Vendas!$B$5:$B$604,MATCH(LARGE(Vendas!$O$5:$O$604,4),Vendas!$O$5:$O$604,0)),""),"") -> Cláudia Santos | D59: =IFERROR(IF(LARGE(Vendas!$O$5:$O$604,4)>0,INDEX(Vendas!$C$5:$C$604,MATCH(LARGE(Vendas!$O$5:$O$604,4),Vendas!$O$5:$O$604,0)),""),"") -> Consulta | E59: =IFERROR(IF(LARGE(Vendas!$O$5:$O$604,4)>0,INDEX(Vendas!$D$5:$D$604,MATCH(LARGE(Vendas!$O$5:$O$604,4),Vendas!$O$5:$O$604,0)),""),"") -> Cartão de débito | F59: =IFERROR(IF(LARGE(Vendas!$O$5:$O$604,4)>0,INDEX(Vendas!$E$5:$E$604,MATCH(LARGE(Vendas!$O$5:$O$604,4),Vendas!$O$5:$O$604,0)),""),"") -> 0 | G59: =IFERROR(IF(LARGE(Vendas!$O$5:$O$604,4)>0,INDEX(Vendas!$F$5:$F$604,MATCH(LARGE(Vendas!$O$5:$O$604,4),Vendas!$O$5:$O$604,0)),""),"") -> 380 | H59: =IFERROR(IF(LARGE(Vendas!$O$5:$O$604,4)>0,INDEX(Vendas!$J$5:$J$604,MATCH(LARGE(Vendas!$O$5:$O$604,4),Vendas!$O$5:$O$604,0)),""),"") -> 374.3 | I59: =IFERROR(IF(LARGE(Vendas!$O$5:$O$604,4)>0,INDEX(Vendas!$K$5:$K$604,MATCH(LARGE(Vendas!$O$5:$O$604,4),Vendas!$O$5:$O$604,0)),""),"") -> 46275 | J59: =IF(I59="","",Config!$B$8-I59) -> 4
A60: 5 | B60: =IFERROR(IF(LARGE(Vendas!$O$5:$O$604,5)>0,INDEX(Vendas!$A$5:$A$604,MATCH(LARGE(Vendas!$O$5:$O$604,5),Vendas!$O$5:$O$604,0)),""),"") -> 46245 | C60: =IFERROR(IF(LARGE(Vendas!$O$5:$O$604,5)>0,INDEX(Vendas!$B$5:$B$604,MATCH(LARGE(Vendas!$O$5:$O$604,5),Vendas!$O$5:$O$604,0)),""),"") -> Gustavo Ferreira | D60: =IFERROR(IF(LARGE(Vendas!$O$5:$O$604,5)>0,INDEX(Vendas!$C$5:$C$604,MATCH(LARGE(Vendas!$O$5:$O$604,5),Vendas!$O$5:$O$604,0)),""),"") -> Consulta | E60: =IFERROR(IF(LARGE(Vendas!$O$5:$O$604,5)>0,INDEX(Vendas!$D$5:$D$604,MATCH(LARGE(Vendas!$O$5:$O$604,5),Vendas!$O$5:$O$604,0)),""),"") -> Cartão de crédito | F60: =IFERROR(IF(LARGE(Vendas!$O$5:$O$604,5)>0,INDEX(Vendas!$E$5:$E$604,MATCH(LARGE(Vendas!$O$5:$O$604,5),Vendas!$O$5:$O$604,0)),""),"") -> 0 | G60: =IFERROR(IF(LARGE(Vendas!$O$5:$O$604,5)>0,INDEX(Vendas!$F$5:$F$604,MATCH(LARGE(Vendas!$O$5:$O$604,5),Vendas!$O$5:$O$604,0)),""),"") -> 380 | H60: =IFERROR(IF(LARGE(Vendas!$O$5:$O$604,5)>0,INDEX(Vendas!$J$5:$J$604,MATCH(LARGE(Vendas!$O$5:$O$604,5),Vendas!$O$5:$O$604,0)),""),"") -> 367.84 | I60: =IFERROR(IF(LARGE(Vendas!$O$5:$O$604,5)>0,INDEX(Vendas!$K$5:$K$604,MATCH(LARGE(Vendas!$O$5:$O$604,5),Vendas!$O$5:$O$604,0)),""),"") -> 46275 | J60: =IF(I60="","",Config!$B$8-I60) -> 4
A61: 6 | B61: =IFERROR(IF(LARGE(Vendas!$O$5:$O$604,6)>0,INDEX(Vendas!$A$5:$A$604,MATCH(LARGE(Vendas!$O$5:$O$604,6),Vendas!$O$5:$O$604,0)),""),"") -> 46245 | C61: =IFERROR(IF(LARGE(Vendas!$O$5:$O$604,6)>0,INDEX(Vendas!$B$5:$B$604,MATCH(LARGE(Vendas!$O$5:$O$604,6),Vendas!$O$5:$O$604,0)),""),"") -> Ana Costa | D61: =IFERROR(IF(LARGE(Vendas!$O$5:$O$604,6)>0,INDEX(Vendas!$C$5:$C$604,MATCH(LARGE(Vendas!$O$5:$O$604,6),Vendas!$O$5:$O$604,0)),""),"") -> Consulta | E61: =IFERROR(IF(LARGE(Vendas!$O$5:$O$604,6)>0,INDEX(Vendas!$D$5:$D$604,MATCH(LARGE(Vendas!$O$5:$O$604,6),Vendas!$O$5:$O$604,0)),""),"") -> Cartão de crédito | F61: =IFERROR(IF(LARGE(Vendas!$O$5:$O$604,6)>0,INDEX(Vendas!$E$5:$E$604,MATCH(LARGE(Vendas!$O$5:$O$604,6),Vendas!$O$5:$O$604,0)),""),"") -> 2 | G61: =IFERROR(IF(LARGE(Vendas!$O$5:$O$604,6)>0,INDEX(Vendas!$F$5:$F$604,MATCH(LARGE(Vendas!$O$5:$O$604,6),Vendas!$O$5:$O$604,0)),""),"") -> 380 | H61: =IFERROR(IF(LARGE(Vendas!$O$5:$O$604,6)>0,INDEX(Vendas!$J$5:$J$604,MATCH(LARGE(Vendas!$O$5:$O$604,6),Vendas!$O$5:$O$604,0)),""),"") -> 365.18 | I61: =IFERROR(IF(LARGE(Vendas!$O$5:$O$604,6)>0,INDEX(Vendas!$K$5:$K$604,MATCH(LARGE(Vendas!$O$5:$O$604,6),Vendas!$O$5:$O$604,0)),""),"") -> 46275 | J61: =IF(I61="","",Config!$B$8-I61) -> 4
A62: 7 | B62: =IFERROR(IF(LARGE(Vendas!$O$5:$O$604,7)>0,INDEX(Vendas!$A$5:$A$604,MATCH(LARGE(Vendas!$O$5:$O$604,7),Vendas!$O$5:$O$604,0)),""),"") -> 46275 | C62: =IFERROR(IF(LARGE(Vendas!$O$5:$O$604,7)>0,INDEX(Vendas!$B$5:$B$604,MATCH(LARGE(Vendas!$O$5:$O$604,7),Vendas!$O$5:$O$604,0)),""),"") -> Rafael Dias | D62: =IFERROR(IF(LARGE(Vendas!$O$5:$O$604,7)>0,INDEX(Vendas!$C$5:$C$604,MATCH(LARGE(Vendas!$O$5:$O$604,7),Vendas!$O$5:$O$604,0)),""),"") -> Consulta | E62: =IFERROR(IF(LARGE(Vendas!$O$5:$O$604,7)>0,INDEX(Vendas!$D$5:$D$604,MATCH(LARGE(Vendas!$O$5:$O$604,7),Vendas!$O$5:$O$604,0)),""),"") -> Cartão de débito | F62: =IFERROR(IF(LARGE(Vendas!$O$5:$O$604,7)>0,INDEX(Vendas!$E$5:$E$604,MATCH(LARGE(Vendas!$O$5:$O$604,7),Vendas!$O$5:$O$604,0)),""),"") -> 0 | G62: =IFERROR(IF(LARGE(Vendas!$O$5:$O$604,7)>0,INDEX(Vendas!$F$5:$F$604,MATCH(LARGE(Vendas!$O$5:$O$604,7),Vendas!$O$5:$O$604,0)),""),"") -> 380 | H62: =IFERROR(IF(LARGE(Vendas!$O$5:$O$604,7)>0,INDEX(Vendas!$J$5:$J$604,MATCH(LARGE(Vendas!$O$5:$O$604,7),Vendas!$O$5:$O$604,0)),""),"") -> 374.3 | I62: =IFERROR(IF(LARGE(Vendas!$O$5:$O$604,7)>0,INDEX(Vendas!$K$5:$K$604,MATCH(LARGE(Vendas!$O$5:$O$604,7),Vendas!$O$5:$O$604,0)),""),"") -> 46276 | J62: =IF(I62="","",Config!$B$8-I62) -> 3
A63: 8 | B63: =IFERROR(IF(LARGE(Vendas!$O$5:$O$604,8)>0,INDEX(Vendas!$A$5:$A$604,MATCH(LARGE(Vendas!$O$5:$O$604,8),Vendas!$O$5:$O$604,0)),""),"") -> 46246 | C63: =IFERROR(IF(LARGE(Vendas!$O$5:$O$604,8)>0,INDEX(Vendas!$B$5:$B$604,MATCH(LARGE(Vendas!$O$5:$O$604,8),Vendas!$O$5:$O$604,0)),""),"") -> Otávio Nascimento | D63: =IFERROR(IF(LARGE(Vendas!$O$5:$O$604,8)>0,INDEX(Vendas!$C$5:$C$604,MATCH(LARGE(Vendas!$O$5:$O$604,8),Vendas!$O$5:$O$604,0)),""),"") -> Consulta | E63: =IFERROR(IF(LARGE(Vendas!$O$5:$O$604,8)>0,INDEX(Vendas!$D$5:$D$604,MATCH(LARGE(Vendas!$O$5:$O$604,8),Vendas!$O$5:$O$604,0)),""),"") -> Cartão de crédito | F63: =IFERROR(IF(LARGE(Vendas!$O$5:$O$604,8)>0,INDEX(Vendas!$E$5:$E$604,MATCH(LARGE(Vendas!$O$5:$O$604,8),Vendas!$O$5:$O$604,0)),""),"") -> 0 | G63: =IFERROR(IF(LARGE(Vendas!$O$5:$O$604,8)>0,INDEX(Vendas!$F$5:$F$604,MATCH(LARGE(Vendas!$O$5:$O$604,8),Vendas!$O$5:$O$604,0)),""),"") -> 380 | H63: =IFERROR(IF(LARGE(Vendas!$O$5:$O$604,8)>0,INDEX(Vendas!$J$5:$J$604,MATCH(LARGE(Vendas!$O$5:$O$604,8),Vendas!$O$5:$O$604,0)),""),"") -> 367.84 | I63: =IFERROR(IF(LARGE(Vendas!$O$5:$O$604,8)>0,INDEX(Vendas!$K$5:$K$604,MATCH(LARGE(Vendas!$O$5:$O$604,8),Vendas!$O$5:$O$604,0)),""),"") -> 46276 | J63: =IF(I63="","",Config!$B$8-I63) -> 3
A64: 9 | B64: =IFERROR(IF(LARGE(Vendas!$O$5:$O$604,9)>0,INDEX(Vendas!$A$5:$A$604,MATCH(LARGE(Vendas!$O$5:$O$604,9),Vendas!$O$5:$O$604,0)),""),"") -> 46246 | C64: =IFERROR(IF(LARGE(Vendas!$O$5:$O$604,9)>0,INDEX(Vendas!$B$5:$B$604,MATCH(LARGE(Vendas!$O$5:$O$604,9),Vendas!$O$5:$O$604,0)),""),"") -> Wagner Lima | D64: =IFERROR(IF(LARGE(Vendas!$O$5:$O$604,9)>0,INDEX(Vendas!$C$5:$C$604,MATCH(LARGE(Vendas!$O$5:$O$604,9),Vendas!$O$5:$O$604,0)),""),"") -> Consulta | E64: =IFERROR(IF(LARGE(Vendas!$O$5:$O$604,9)>0,INDEX(Vendas!$D$5:$D$604,MATCH(LARGE(Vendas!$O$5:$O$604,9),Vendas!$O$5:$O$604,0)),""),"") -> Cartão de crédito | F64: =IFERROR(IF(LARGE(Vendas!$O$5:$O$604,9)>0,INDEX(Vendas!$E$5:$E$604,MATCH(LARGE(Vendas!$O$5:$O$604,9),Vendas!$O$5:$O$604,0)),""),"") -> 0 | G64: =IFERROR(IF(LARGE(Vendas!$O$5:$O$604,9)>0,INDEX(Vendas!$F$5:$F$604,MATCH(LARGE(Vendas!$O$5:$O$604,9),Vendas!$O$5:$O$604,0)),""),"") -> 380 | H64: =IFERROR(IF(LARGE(Vendas!$O$5:$O$604,9)>0,INDEX(Vendas!$J$5:$J$604,MATCH(LARGE(Vendas!$O$5:$O$604,9),Vendas!$O$5:$O$604,0)),""),"") -> 367.84 | I64: =IFERROR(IF(LARGE(Vendas!$O$5:$O$604,9)>0,INDEX(Vendas!$K$5:$K$604,MATCH(LARGE(Vendas!$O$5:$O$604,9),Vendas!$O$5:$O$604,0)),""),"") -> 46276 | J64: =IF(I64="","",Config!$B$8-I64) -> 3
A65: 10 | B65: =IFERROR(IF(LARGE(Vendas!$O$5:$O$604,10)>0,INDEX(Vendas!$A$5:$A$604,MATCH(LARGE(Vendas!$O$5:$O$604,10),Vendas!$O$5:$O$604,0)),""),"") -> 46275 | C65: =IFERROR(IF(LARGE(Vendas!$O$5:$O$604,10)>0,INDEX(Vendas!$B$5:$B$604,MATCH(LARGE(Vendas!$O$5:$O$604,10),Vendas!$O$5:$O$604,0)),""),"") -> Eduardo Lima | D65: =IFERROR(IF(LARGE(Vendas!$O$5:$O$604,10)>0,INDEX(Vendas!$C$5:$C$604,MATCH(LARGE(Vendas!$O$5:$O$604,10),Vendas!$O$5:$O$604,0)),""),"") -> MAPA | E65: =IFERROR(IF(LARGE(Vendas!$O$5:$O$604,10)>0,INDEX(Vendas!$D$5:$D$604,MATCH(LARGE(Vendas!$O$5:$O$604,10),Vendas!$O$5:$O$604,0)),""),"") -> Cartão de débito | F65: =IFERROR(IF(LARGE(Vendas!$O$5:$O$604,10)>0,INDEX(Vendas!$E$5:$E$604,MATCH(LARGE(Vendas!$O$5:$O$604,10),Vendas!$O$5:$O$604,0)),""),"") -> 0 | G65: =IFERROR(IF(LARGE(Vendas!$O$5:$O$604,10)>0,INDEX(Vendas!$F$5:$F$604,MATCH(LARGE(Vendas!$O$5:$O$604,10),Vendas!$O$5:$O$604,0)),""),"") -> 300 | H65: =IFERROR(IF(LARGE(Vendas!$O$5:$O$604,10)>0,INDEX(Vendas!$J$5:$J$604,MATCH(LARGE(Vendas!$O$5:$O$604,10),Vendas!$O$5:$O$604,0)),""),"") -> 295.5 | I65: =IFERROR(IF(LARGE(Vendas!$O$5:$O$604,10)>0,INDEX(Vendas!$K$5:$K$604,MATCH(LARGE(Vendas!$O$5:$O$604,10),Vendas!$O$5:$O$604,0)),""),"") -> 46276 | J65: =IF(I65="","",Config!$B$8-I65) -> 3
A66: Venda que não caiu na conta na data prevista: confira o extrato da operadora (estorno, chargeback, erro de bandeira) antes de cobrar o paciente. A planilha aponta; a conferência é sua.

Sheet Config
A1: Configurações
A2: Células amarelas: você preenche. Taxas e prazos da sua operadora (o contrato da maquininha diz; confira no extrato).
A4: Clínica | B4: Clínica Vida Plena (exemplo fictício) | H4: Meses
A5: Ano do painel | B5: 2026 | H5: Janeiro
A6: Mês do painel | B6: Agosto | H6: Fevereiro
A7: Número do mês | B7: =MATCH(B6,$H$5:$H$16,0) -> 8 | H7: Março
A8: Data de referência (hoje) | B8: =TODAY() -> 46279 | H8: Abril
A9: Preço da consulta particular (para a comparação) | B9: 380 | H9: Maio
H10: Junho
A11: Tipo | B11: Taxa (%) | C11: Cai na conta em (dias) | D11: Observação | H11: Julho
A12: Pix | B12: 0 | C12: 0 | D12: Pix na conta PJ: no exemplo, sem taxa (alguns bancos cobram por recebimento). | H12: Agosto
A13: Cartão de débito | B13: 0.015 | C13: 1 | D13: Débito costuma cair no dia útil seguinte. | H13: Setembro
A14: Cartão de crédito | B14: 0.032 | C14: 30 | D14: Crédito à vista cai em 30 dias. | H14: Outubro
A15: Cartão de crédito parcelado | B15: 0.039 | C15: 30 | D15: Parcelado: cada parcela cai 30 dias depois da anterior; a taxa é maior. | H15: Novembro
H16: Dezembro
A17: Antecipar o crédito? (Sim/Não) | B17: Não | D17: Com antecipação, o crédito cai em 1 dia e a operadora cobra a taxa de antecipação sobre o valor pelo prazo antecipado. No exemplo, a clínica não antecipa.
A18: Taxa de antecipação (% ao mês) | B18: 0.018
A20: As taxas do exemplo são ilustrativas. Pegue as suas no contrato da maquininha ou no extrato da operadora; elas mudam por bandeira e por volume.

Sheet Vendas
A1: Vendas no cartão e no Pix
A2: Uma linha por pagamento (copie da Agenda da planilha 01: atendimentos particulares realizados com Pix ou cartão). Amarelo: data, paciente, procedimento, tipo, parcelas, valor bruto e a conferência no extrato.
A4: Data da venda | B4: Paciente | C4: Procedimento | D4: Tipo | E4: Parcelas | F4: Valor bruto (R$) | G4: Conferido no extrato? | H4: Taxa (%) | I4: Taxa (R$) | J4: Valor líquido (R$) | K4: Previsão na conta | L4: Mês | M4: Ano | N4: Situação
A5: 46204 | B5: Cláudia Santos | C5: Consulta | D5: Pix | F5: 380 | G5: Sim | H5: =IF(D5="","",IFERROR(INDEX(Config!$B$12:$B$15,MATCH(IF(AND(D5="Cartão de crédito",N(E5)>1),"Cartão de crédito parcelado",D5),Config!$A$12:$A$15,0)),0)+IF(AND(Config!$B$17="Sim",LEFT(D5,17)="Cartão de crédito"),Config!$B$18*IFERROR(INDEX(Config!$C$12:$C$15,MATCH(IF(AND(D5="Cartão de crédito",N(E5)>1),"Cartão de crédito parcelado",D5),Config!$A$12:$A$15,0)),0)/30*MAX(1,N(E5)),0)) -> 0 | I5: =IF(OR(D5="",F5=""),"",ROUND(F5*H5,2)) -> 0 | J5: =IF(I5="","",F5-I5) -> 380 | K5: =IF(OR(D5="",A5=""),"",A5+IF(AND(Config!$B$17="Sim",LEFT(D5,17)="Cartão de crédito"),1,IFERROR(INDEX(Config!$C$12:$C$15,MATCH(IF(AND(D5="Cartão de crédito",N(E5)>1),"Cartão de crédito parcelado",D5),Config!$A$12:$A$15,0)),0))) -> 46204 | L5: =IF(A5="","",MONTH(A5)) -> 7 | M5: =IF(A5="","",YEAR(A5)) -> 2026 | N5: =IF(K5="","",IF(G5="Sim","Conferido",IF(K5>Config!$B$8,"A cair","A conferir"))) -> Conferido | O5: =IF(N5="A conferir",(Config!$B$8-K5)*1000+N(F5)/1000+ROW()/100000,0) -> 0
A6: 46204 | B6: Lucas Lopes | C6: Consulta | D6: Cartão de débito | F6: 380 | G6: Sim | H6: =IF(D6="","",IFERROR(INDEX(Config!$B$12:$B$15,MATCH(IF(AND(D6="Cartão de crédito",N(E6)>1),"Cartão de crédito parcelado",D6),Config!$A$12:$A$15,0)),0)+IF(AND(Config!$B$17="Sim",LEFT(D6,17)="Cartão de crédito"),Config!$B$18*IFERROR(INDEX(Config!$C$12:$C$15,MATCH(IF(AND(D6="Cartão de crédito",N(E6)>1),"Cartão de crédito parcelado",D6),Config!$A$12:$A$15,0)),0)/30*MAX(1,N(E6)),0)) -> 0.015 | I6: =IF(OR(D6="",F6=""),"",ROUND(F6*H6,2)) -> 5.7 | J6: =IF(I6="","",F6-I6) -> 374.3 | K6: =IF(OR(D6="",A6=""),"",A6+IF(AND(Config!$B$17="Sim",LEFT(D6,17)="Cartão de crédito"),1,IFERROR(INDEX(Config!$C$12:$C$15,MATCH(IF(AND(D6="Cartão de crédito",N(E6)>1),"Cartão de crédito parcelado",D6),Config!$A$12:$A$15,0)),0))) -> 46205 | L6: =IF(A6="","",MONTH(A6)) -> 7 | M6: =IF(A6="","",YEAR(A6)) -> 2026 | N6: =IF(K6="","",IF(G6="Sim","Conferido",IF(K6>Config!$B$8,"A cair","A conferir"))) -> Conferido | O6: =IF(N6="A conferir",(Config!$B$8-K6)*1000+N(F6)/1000+ROW()/100000,0) -> 0
A7: 46204 | B7: Mônica Martins | C7: Consulta | D7: Pix | F7: 380 | G7: Sim | H7: =IF(D7="","",IFERROR(INDEX(Config!$B$12:$B$15,MATCH(IF(AND(D7="Cartão de crédito",N(E7)>1),"Cartão de crédito parcelado",D7),Config!$A$12:$A$15,0)),0)+IF(AND(Config!$B$17="Sim",LEFT(D7,17)="Cartão de crédito"),Config!$B$18*IFERROR(INDEX(Config!$C$12:$C$15,MATCH(IF(AND(D7="Cartão de crédito",N(E7)>1),"Cartão de crédito parcelado",D7),Config!$A$12:$A$15,0)),0)/30*MAX(1,N(E7)),0)) -> 0 | I7: =IF(OR(D7="",F7=""),"",ROUND(F7*H7,2)) -> 0 | J7: =IF(I7="","",F7-I7) -> 380 | K7: =IF(OR(D7="",A7=""),"",A7+IF(AND(Config!$B$17="Sim",LEFT(D7,17)="Cartão de crédito"),1,IFERROR(INDEX(Config!$C$12:$C$15,MATCH(IF(AND(D7="Cartão de crédito",N(E7)>1),"Cartão de crédito parcelado",D7),Config!$A$12:$A$15,0)),0))) -> 46204 | L7: =IF(A7="","",MONTH(A7)) -> 7 | M7: =IF(A7="","",YEAR(A7)) -> 2026 | N7: =IF(K7="","",IF(G7="Sim","Conferido",IF(K7>Config!$B$8,"A cair","A conferir"))) -> Conferido | O7: =IF(N7="A conferir",(Config!$B$8-K7)*1000+N(F7)/1000+ROW()/100000,0) -> 0
A8: 46205 | B8: Débora Ramos | C8: Consulta | D8: Cartão de crédito | F8: 380 | G8: Sim | H8: =IF(D8="","",IFERROR(INDEX(Config!$B$12:$B$15,MATCH(IF(AND(D8="Cartão de crédito",N(E8)>1),"Cartão de crédito parcelado",D8),Config!$A$12:$A$15,0)),0)+IF(AND(Config!$B$17="Sim",LEFT(D8,17)="Cartão de crédito"),Config!$B$18*IFERROR(INDEX(Config!$C$12:$C$15,MATCH(IF(AND(D8="Cartão de crédito",N(E8)>1),"Cartão de crédito parcelado",D8),Config!$A$12:$A$15,0)),0)/30*MAX(1,N(E8)),0)) -> 0.032 | I8: =IF(OR(D8="",F8=""),"",ROUND(F8*H8,2)) -> 12.16 | J8: =IF(I8="","",F8-I8) -> 367.84 | K8: =IF(OR(D8="",A8=""),"",A8+IF(AND(Config!$B$17="Sim",LEFT(D8,17)="Cartão de crédito"),1,IFERROR(INDEX(Config!$C$12:$C$15,MATCH(IF(AND(D8="Cartão de crédito",N(E8)>1),"Cartão de crédito parcelado",D8),Config!$A$12:$A$15,0)),0))) -> 46235 | L8: =IF(A8="","",MONTH(A8)) -> 7 | M8: =IF(A8="","",YEAR(A8)) -> 2026 | N8: =IF(K8="","",IF(G8="Sim","Conferido",IF(K8>Config!$B$8,"A cair","A conferir"))) -> Conferido | O8: =IF(N8="A conferir",(Config!$B$8-K8)*1000+N(F8)/1000+ROW()/100000,0) -> 0
A9: 46205 | B9: Mariana Nascimento | C9: Consulta | D9: Cartão de crédito | F9: 380 | G9: Sim | H9: =IF(D9="","",IFERROR(INDEX(Config!$B$12:$B$15,MATCH(IF(AND(D9="Cartão de crédito",N(E9)>1),"Cartão de crédito parcelado",D9),Config!$A$12:$A$15,0)),0)+IF(AND(Config!$B$17="Sim",LEFT(D9,17)="Cartão de crédito"),Config!$B$18*IFERROR(INDEX(Config!$C$12:$C$15,MATCH(IF(AND(D9="Cartão de crédito",N(E9)>1),"Cartão de crédito parcelado",D9),Config!$A$12:$A$15,0)),0)/30*MAX(1,N(E9)),0)) -> 0.032 | I9: =IF(OR(D9="",F9=""),"",ROUND(F9*H9,2)) -> 12.16 | J9: =IF(I9="","",F9-I9) -> 367.84 | K9: =IF(OR(D9="",A9=""),"",A9+IF(AND(Config!$B$17="Sim",LEFT(D9,17)="Cartão de crédito"),1,IFERROR(INDEX(Config!$C$12:$C$15,MATCH(IF(AND(D9="Cartão de crédito",N(E9)>1),"Cartão de crédito parcelado",D9),Config!$A$12:$A$15,0)),0))) -> 46235 | L9: =IF(A9="","",MONTH(A9)) -> 7 | M9: =IF(A9="","",YEAR(A9)) -> 2026 | N9: =IF(K9="","",IF(G9="Sim","Conferido",IF(K9>Config!$B$8,"A cair","A conferir"))) -> Conferido | O9: =IF(N9="A conferir",(Config!$B$8-K9)*1000+N(F9)/1000+ROW()/100000,0) -> 0
A10: 46205 | B10: Helena Moreira | C10: Consulta | D10: Cartão de crédito | F10: 380 | G10: Sim | H10: =IF(D10="","",IFERROR(INDEX(Config!$B$12:$B$15,MATCH(IF(AND(D10="Cartão de crédito",N(E10)>1),"Cartão de crédito parcelado",D10),Config!$A$12:$A$15,0)),0)+IF(AND(Config!$B$17="Sim",LEFT(D10,17)="Cartão de crédito"),Config!$B$18*IFERROR(INDEX(Config!$C$12:$C$15,MATCH(IF(AND(D10="Cartão de crédito",N(E10)>1),"Cartão de crédito parcelado",D10),Config!$A$12:$A$15,0)),0)/30*MAX(1,N(E10)),0)) -> 0.032 | I10: =IF(OR(D10="",F10=""),"",ROUND(F10*H10,2)) -> 12.16 | J10: =IF(I10="","",F10-I10) -> 367.84 | K10: =IF(OR(D10="",A10=""),"",A10+IF(AND(Config!$B$17="Sim",LEFT(D10,17)="Cartão de crédito"),1,IFERROR(INDEX(Config!$C$12:$C$15,MATCH(IF(AND(D10="Cartão de crédito",N(E10)>1),"Cartão de crédito parcelado",D10),Config!$A$12:$A$15,0)),0))) -> 46235 | L10: =IF(A10="","",MONTH(A10)) -> 7 | M10: =IF(A10="","",YEAR(A10)) -> 2026 | N10: =IF(K10="","",IF(G10="Sim","Conferido",IF(K10>Config!$B$8,"A cair","A conferir"))) -> Conferido | O10: =IF(N10="A conferir",(Config!$B$8-K10)*1000+N(F10)/1000+ROW()/100000,0) -> 0
A11: 46205 | B11: Gabriel Oliveira | C11: ECG | D11: Pix | F11: 130 | G11: Sim | H11: =IF(D11="","",IFERROR(INDEX(Config!$B$12:$B$15,MATCH(IF(AND(D11="Cartão de crédito",N(E11)>1),"Cartão de crédito parcelado",D11),Config!$A$12:$A$15,0)),0)+IF(AND(Config!$B$17="Sim",LEFT(D11,17)="Cartão de crédito"),Config!$B$18*IFERROR(INDEX(Config!$C$12:$C$15,MATCH(IF(AND(D11="Cartão de crédito",N(E11)>1),"Cartão de crédito parcelado",D11),Config!$A$12:$A$15,0)),0)/30*MAX(1,N(E11)),0)) -> 0 | I11: =IF(OR(D11="",F11=""),"",ROUND(F11*H11,2)) -> 0 | J11: =IF(I11="","",F11-I11) -> 130 | K11: =IF(OR(D11="",A11=""),"",A11+IF(AND(Config!$B$17="Sim",LEFT(D11,17)="Cartão de crédito"),1,IFERROR(INDEX(Config!$C$12:$C$15,MATCH(IF(AND(D11="Cartão de crédito",N(E11)>1),"Cartão de crédito parcelado",D11),Config!$A$12:$A$15,0)),0))) -> 46205 | L11: =IF(A11="","",MONTH(A11)) -> 7 | M11: =IF(A11="","",YEAR(A11)) -> 2026 | N11: =IF(K11="","",IF(G11="Sim","Conferido",IF(K11>Config!$B$8,"A cair","A conferir"))) -> Conferido | O11: =IF(N11="A conferir",(Config!$B$8-K11)*1000+N(F11)/1000+ROW()/100000,0) -> 0
A12: 46205 | B12: Beatriz Monteiro | C12: Avaliação endócrina | D12: Cartão de crédito | E12: 2 | F12: 400 | G12: Sim | H12: =IF(D12="","",IFERROR(INDEX(Config!$B$12:$B$15,MATCH(IF(AND(D12="Cartão de crédito",N(E12)>1),"Cartão de crédito parcelado",D12),Config!$A$12:$A$15,0)),0)+IF(AND(Config!$B$17="Sim",LEFT(D12,17)="Cartão de crédito"),Config!$B$18*IFERROR(INDEX(Config!$C$12:$C$15,MATCH(IF(AND(D12="Cartão de crédito",N(E12)>1),"Cartão de crédito parcelado",D12),Config!$A$12:$A$15,0)),0)/30*MAX(1,N(E12)),0)) -> 0.039 | I12: =IF(OR(D12="",F12=""),"",ROUND(F12*H12,2)) -> 15.6 | J12: =IF(I12="","",F12-I12) -> 384.4 | K12: =IF(OR(D12="",A12=""),"",A12+IF(AND(Config!$B$17="Sim",LEFT(D12,17)="Cartão de crédito"),1,IFERROR(INDEX(Config!$C$12:$C$15,MATCH(IF(AND(D12="Cartão de crédito",N(E12)>1),"Cartão de crédito parcelado",D12),Config!$A$12:$A$15,0)),0))) -> 46235 | L12: =IF(A12="","",MONTH(A12)) -> 7 | M12: =IF(A12="","",YEAR(A12)) -> 2026 | N12: =IF(K12="","",IF(G12="Sim","Conferido",IF(K12>Config!$B$8,"A cair","A conferir"))) -> Conferido | O12: =IF(N12="A conferir",(Config!$B$8-K12)*1000+N(F12)/1000+ROW()/100000,0) -> 0
A13: 46206 | B13: Renato Dias | C13: ECG | D13: Pix | F13: 130 | G13: Sim | H13: =IF(D13="","",IFERROR(INDEX(Config!$B$12:$B$15,MATCH(IF(AND(D13="Cartão de crédito",N(E13)>1),"Cartão de crédito parcelado",D13),Config!$A$12:$A$15,0)),0)+IF(AND(Config!$B$17="Sim",LEFT(D13,17)="Cartão de crédito"),Config!$B$18*IFERROR(INDEX(Config!$C$12:$C$15,MATCH(IF(AND(D13="Cartão de crédito",N(E13)>1),"Cartão de crédito parcelado",D13),Config!$A$12:$A$15,0)),0)/30*MAX(1,N(E13)),0)) -> 0 | I13: =IF(OR(D13="",F13=""),"",ROUND(F13*H13,2)) -> 0 | J13: =IF(I13="","",F13-I13) -> 130 | K13: =IF(OR(D13="",A13=""),"",A13+IF(AND(Config!$B$17="Sim",LEFT(D13,17)="Cartão de crédito"),1,IFERROR(INDEX(Config!$C$12:$C$15,MATCH(IF(AND(D13="Cartão de crédito",N(E13)>1),"Cartão de crédito parcelado",D13),Config!$A$12:$A$15,0)),0))) -> 46206 | L13: =IF(A13="","",MONTH(A13)) -> 7 | M13: =IF(A13="","",YEAR(A13)) -> 2026 | N13: =IF(K13="","",IF(G13="Sim","Conferido",IF(K13>Config!$B$8,"A cair","A conferir"))) -> Conferido | O13: =IF(N13="A conferir",(Config!$B$8-K13)*1000+N(F13)/1000+ROW()/100000,0) -> 0
A14: 46206 | B14: Wagner Costa | C14: Consulta | D14: Pix | F14: 380 | G14: Sim | H14: =IF(D14="","",IFERROR(INDEX(Config!$B$12:$B$15,MATCH(IF(AND(D14="Cartão de crédito",N(E14)>1),"Cartão de crédito parcelado",D14),Config!$A$12:$A$15,0)),0)+IF(AND(Config!$B$17="Sim",LEFT(D14,17)="Cartão de crédito"),Config!$B$18*IFERROR(INDEX(Config!$C$12:$C$15,MATCH(IF(AND(D14="Cartão de crédito",N(E14)>1),"Cartão de crédito parcelado",D14),Config!$A$12:$A$15,0)),0)/30*MAX(1,N(E14)),0)) -> 0 | I14: =IF(OR(D14="",F14=""),"",ROUND(F14*H14,2)) -> 0 | J14: =IF(I14="","",F14-I14) -> 380 | K14: =IF(OR(D14="",A14=""),"",A14+IF(AND(Config!$B$17="Sim",LEFT(D14,17)="Cartão de crédito"),1,IFERROR(INDEX(Config!$C$12:$C$15,MATCH(IF(AND(D14="Cartão de crédito",N(E14)>1),"Cartão de crédito parcelado",D14),Config!$A$12:$A$15,0)),0))) -> 46206 | L14: =IF(A14="","",MONTH(A14)) -> 7 | M14: =IF(A14="","",YEAR(A14)) -> 2026 | N14: =IF(K14="","",IF(G14="Sim","Conferido",IF(K14>Config!$B$8,"A cair","A conferir"))) -> Conferido | O14: =IF(N14="A conferir",(Config!$B$8-K14)*1000+N(F14)/1000+ROW()/100000,0) -> 0
A15: 46209 | B15: Wagner Lima | C15: Consulta | D15: Cartão de crédito | E15: 2 | F15: 380 | G15: Sim | H15: =IF(D15="","",IFERROR(INDEX(Config!$B$12:$B$15,MATCH(IF(AND(D15="Cartão de crédito",N(E15)>1),"Cartão de crédito parcelado",D15),Config!$A$12:$A$15,0)),0)+IF(AND(Config!$B$17="Sim",LEFT(D15,17)="Cartão de crédito"),Config!$B$18*IFERROR(INDEX(Config!$C$12:$C$15,MATCH(IF(AND(D15="Cartão de crédito",N(E15)>1),"Cartão de crédito parcelado",D15),Config!$A$12:$A$15,0)),0)/30*MAX(1,N(E15)),0)) -> 0.039 | I15: =IF(OR(D15="",F15=""),"",ROUND(F15*H15,2)) -> 14.82 | J15: =IF(I15="","",F15-I15) -> 365.18 | K15: =IF(OR(D15="",A15=""),"",A15+IF(AND(Config!$B$17="Sim",LEFT(D15,17)="Cartão de crédito"),1,IFERROR(INDEX(Config!$C$12:$C$15,MATCH(IF(AND(D15="Cartão de crédito",N(E15)>1),"Cartão de crédito parcelado",D15),Config!$A$12:$A$15,0)),0))) -> 46239 | L15: =IF(A15="","",MONTH(A15)) -> 7 | M15: =IF(A15="","",YEAR(A15)) -> 2026 | N15: =IF(K15="","",IF(G15="Sim","Conferido",IF(K15>Config!$B$8,"A cair","A conferir"))) -> Conferido | O15: =IF(N15="A conferir",(Config!$B$8-K15)*1000+N(F15)/1000+ROW()/100000,0) -> 0
A16: 46209 | B16: Paulo Reis | C16: Consulta | D16: Cartão de crédito | F16: 380 | G16: Sim | H16: =IF(D16="","",IFERROR(INDEX(Config!$B$12:$B$15,MATCH(IF(AND(D16="Cartão de crédito",N(E16)>1),"Cartão de crédito parcelado",D16),Config!$A$12:$A$15,0)),0)+IF(AND(Config!$B$17="Sim",LEFT(D16,17)="Cartão de crédito"),Config!$B$18*IFERROR(INDEX(Config!$C$12:$C$15,MATCH(IF(AND(D16="Cartão de crédito",N(E16)>1),"Cartão de crédito parcelado",D16),Config!$A$12:$A$15,0)),0)/30*MAX(1,N(E16)),0)) -> 0.032 | I16: =IF(OR(D16="",F16=""),"",ROUND(F16*H16,2)) -> 12.16 | J16: =IF(I16="","",F16-I16) -> 367.84 | K16: =IF(OR(D16="",A16=""),"",A16+IF(AND(Config!$B$17="Sim",LEFT(D16,17)="Cartão de crédito"),1,IFERROR(INDEX(Config!$C$12:$C$15,MATCH(IF(AND(D16="Cartão de crédito",N(E16)>1),"Cartão de crédito parcelado",D16),Config!$A$12:$A$15,0)),0))) -> 46239 | L16: =IF(A16="","",MONTH(A16)) -> 7 | M16: =IF(A16="","",YEAR(A16)) -> 2026 | N16: =IF(K16="","",IF(G16="Sim","Conferido",IF(K16>Config!$B$8,"A cair","A conferir"))) -> Conferido | O16: =IF(N16="A conferir",(Config!$B$8-K16)*1000+N(F16)/1000+ROW()/100000,0) -> 0
A17: 46210 | B17: Marcelo Santos | C17: Consulta | D17: Pix | F17: 380 | G17: Sim | H17: =IF(D17="","",IFERROR(INDEX(Config!$B$12:$B$15,MATCH(IF(AND(D17="Cartão de crédito",N(E17)>1),"Cartão de crédito parcelado",D17),Config!$A$12:$A$15,0)),0)+IF(AND(Config!$B$17="Sim",LEFT(D17,17)="Cartão de crédito"),Config!$B$18*IFERROR(INDEX(Config!$C$12:$C$15,MATCH(IF(AND(D17="Cartão de crédito",N(E17)>1),"Cartão de crédito parcelado",D17),Config!$A$12:$A$15,0)),0)/30*MAX(1,N(E17)),0)) -> 0 | I17: =IF(OR(D17="",F17=""),"",ROUND(F17*H17,2)) -> 0 | J17: =IF(I17="","",F17-I17) -> 380 | K17: =IF(OR(D17="",A17=""),"",A17+IF(AND(Config!$B$17="Sim",LEFT(D17,17)="Cartão de crédito"),1,IFERROR(INDEX(Config!$C$12:$C$15,MATCH(IF(AND(D17="Cartão de crédito",N(E17)>1),"Cartão de crédito parcelado",D17),Config!$A$12:$A$15,0)),0))) -> 46210 | L17: =IF(A17="","",MONTH(A17)) -> 7 | M17: =IF(A17="","",YEAR(A17)) -> 2026 | N17: =IF(K17="","",IF(G17="Sim","Conferido",IF(K17>Config!$B$8,"A cair","A conferir"))) -> Conferido | O17: =IF(N17="A conferir",(Config!$B$8-K17)*1000+N(F17)/1000+ROW()/100000,0) -> 0
A18: 46210 | B18: Regina Teixeira | C18: Consulta | D18: Pix | F18: 380 | G18: Sim | H18: =IF(D18="","",IFERROR(INDEX(Config!$B$12:$B$15,MATCH(IF(AND(D18="Cartão de crédito",N(E18)>1),"Cartão de crédito parcelado",D18),Config!$A$12:$A$15,0)),0)+IF(AND(Config!$B$17="Sim",LEFT(D18,17)="Cartão de crédito"),Config!$B$18*IFERROR(INDEX(Config!$C$12:$C$15,MATCH(IF(AND(D18="Cartão de crédito",N(E18)>1),"Cartão de crédito parcelado",D18),Config!$A$12:$A$15,0)),0)/30*MAX(1,N(E18)),0)) -> 0 | I18: =IF(OR(D18="",F18=""),"",ROUND(F18*H18,2)) -> 0 | J18: =IF(I18="","",F18-I18) -> 380 | K18: =IF(OR(D18="",A18=""),"",A18+IF(AND(Config!$B$17="Sim",LEFT(D18,17)="Cartão de crédito"),1,IFERROR(INDEX(Config!$C$12:$C$15,MATCH(IF(AND(D18="Cartão de crédito",N(E18)>1),"Cartão de crédito parcelado",D18),Config!$A$12:$A$15,0)),0))) -> 46210 | L18: =IF(A18="","",MONTH(A18)) -> 7 | M18: =IF(A18="","",YEAR(A18)) -> 2026 | N18: =IF(K18="","",IF(G18="Sim","Conferido",IF(K18>Config!$B$8,"A cair","A conferir"))) -> Conferido | O18: =IF(N18="A conferir",(Config!$B$8-K18)*1000+N(F18)/1000+ROW()/100000,0) -> 0
A19: 46210 | B19: Gisele Ribeiro | C19: Consulta | D19: Pix | F19: 380 | G19: Sim | H19: =IF(D19="","",IFERROR(INDEX(Config!$B$12:$B$15,MATCH(IF(AND(D19="Cartão de crédito",N(E19)>1),"Cartão de crédito parcelado",D19),Config!$A$12:$A$15,0)),0)+IF(AND(Config!$B$17="Sim",LEFT(D19,17)="Cartão de crédito"),Config!$B$18*IFERROR(INDEX(Config!$C$12:$C$15,MATCH(IF(AND(D19="Cartão de crédito",N(E19)>1),"Cartão de crédito parcelado",D19),Config!$A$12:$A$15,0)),0)/30*MAX(1,N(E19)),0)) -> 0 | I19: =IF(OR(D19="",F19=""),"",ROUND(F19*H19,2)) -> 0 | J19: =IF(I19="","",F19-I19) -> 380 | K19: =IF(OR(D19="",A19=""),"",A19+IF(AND(Config!$B$17="Sim",LEFT(D19,17)="Cartão de crédito"),1,IFERROR(INDEX(Config!$C$12:$C$15,MATCH(IF(AND(D19="Cartão de crédito",N(E19)>1),"Cartão de crédito parcelado",D19),Config!$A$12:$A$15,0)),0))) -> 46210 | L19: =IF(A19="","",MONTH(A19)) -> 7 | M19: =IF(A19="","",YEAR(A19)) -> 2026 | N19: =IF(K19="","",IF(G19="Sim","Conferido",IF(K19>Config!$B$8,"A cair","A conferir"))) -> Conferido | O19: =IF(N19="A conferir",(Config!$B$8-K19)*1000+N(F19)/1000+ROW()/100000,0) -> 0
A20: 46210 | B20: Beatriz Reis | C20: Avaliação endócrina | D20: Pix | F20: 400 | G20: Sim | H20: =IF(D20="","",IFERROR(INDEX(Config!$B$12:$B$15,MATCH(IF(AND(D20="Cartão de crédito",N(E20)>1),"Cartão de crédito parcelado",D20),Config!$A$12:$A$15,0)),0)+IF(AND(Config!$B$17="Sim",LEFT(D20,17)="Cartão de crédito"),Config!$B$18*IFERROR(INDEX(Config!$C$12:$C$15,MATCH(IF(AND(D20="Cartão de crédito",N(E20)>1),"Cartão de crédito parcelado",D20),Config!$A$12:$A$15,0)),0)/30*MAX(1,N(E20)),0)) -> 0 | I20: =IF(OR(D20="",F20=""),"",ROUND(F20*H20,2)) -> 0 | J20: =IF(I20="","",F20-I20) -> 400 | K20: =IF(OR(D20="",A20=""),"",A20+IF(AND(Config!$B$17="Sim",LEFT(D20,17)="Cartão de crédito"),1,IFERROR(INDEX(Config!$C$12:$C$15,MATCH(IF(AND(D20="Cartão de crédito",N(E20)>1),"Cartão de crédito parcelado",D20),Config!$A$12:$A$15,0)),0))) -> 46210 | L20: =IF(A20="","",MONTH(A20)) -> 7 | M20: =IF(A20="","",YEAR(A20)) -> 2026 | N20: =IF(K20="","",IF(G20="Sim","Conferido",IF(K20>Config!$B$8,"A cair","A conferir"))) -> Conferido | O20: =IF(N20="A conferir",(Config!$B$8-K20)*1000+N(F20)/1000+ROW()/100000,0) -> 0
A21: 46210 | B21: Marcelo Ferreira | C21: Consulta | D21: Cartão de crédito | F21: 380 | G21: Sim | H21: =IF(D21="","",IFERROR(INDEX(Config!$B$12:$B$15,MATCH(IF(AND(D21="Cartão de crédito",N(E21)>1),"Cartão de crédito parcelado",D21),Config!$A$12:$A$15,0)),0)+IF(AND(Config!$B$17="Sim",LEFT(D21,17)="Cartão de crédito"),Config!$B$18*IFERROR(INDEX(Config!$C$12:$C$15,MATCH(IF(AND(D21="Cartão de crédito",N(E21)>1),"Cartão de crédito parcelado",D21),Config!$A$12:$A$15,0)),0)/30*MAX(1,N(E21)),0)) -> 0.032 | I21: =IF(OR(D21="",F21=""),"",ROUND(F21*H21,2)) -> 12.16 | J21: =IF(I21="","",F21-I21) -> 367.84 | K21: =IF(OR(D21="",A21=""),"",A21+IF(AND(Config!$B$17="Sim",LEFT(D21,17)="Cartão de crédito"),1,IFERROR(INDEX(Config!$C$12:$C$15,MATCH(IF(AND(D21="Cartão de crédito",N(E21)>1),"Cartão de crédito parcelado",D21),Config!$A$12:$A$15,0)),0))) -> 46240 | L21: =IF(A21="","",MONTH(A21)) -> 7 | M21: =IF(A21="","",YEAR(A21)) -> 2026 | N21: =IF(K21="","",IF(G21="Sim","Conferido",IF(K21>Config!$B$8,"A cair","A conferir"))) -> Conferido | O21: =IF(N21="A conferir",(Config!$B$8-K21)*1000+N(F21)/1000+ROW()/100000,0) -> 0
A22: 46210 | B22: Lucas Cardoso | C22: Consulta | D22: Cartão de crédito | F22: 380 | G22: Sim | H22: =IF(D22="","",IFERROR(INDEX(Config!$B$12:$B$15,MATCH(IF(AND(D22="Cartão de crédito",N(E22)>1),"Cartão de crédito parcelado",D22),Config!$A$12:$A$15,0)),0)+IF(AND(Config!$B$17="Sim",LEFT(D22,17)="Cartão de crédito"),Config!$B$18*IFERROR(INDEX(Config!$C$12:$C$15,MATCH(IF(AND(D22="Cartão de crédito",N(E22)>1),"Cartão de crédito parcelado",D22),Config!$A$12:$A$15,0)),0)/30*MAX(1,N(E22)),0)) -> 0.032 | I22: =IF(OR(D22="",F22=""),"",ROUND(F22*H22,2)) -> 12.16 | J22: =IF(I22="","",F22-I22) -> 367.84 | K22: =IF(OR(D22="",A22=""),"",A22+IF(AND(Config!$B$17="Sim",LEFT(D22,17)="Cartão de crédito"),1,IFERROR(INDEX(Config!$C$12:$C$15,MATCH(IF(AND(D22="Cartão de crédito",N(E22)>1),"Cartão de crédito parcelado",D22),Config!$A$12:$A$15,0)),0))) -> 46240 | L22: =IF(A22="","",MONTH(A22)) -> 7 | M22: =IF(A22="","",YEAR(A22)) -> 2026 | N22: =IF(K22="","",IF(G22="Sim","Conferido",IF(K22>Config!$B$8,"A cair","A conferir"))) -> Conferido | O22: =IF(N22="A conferir",(Config!$B$8-K22)*1000+N(F22)/1000+ROW()/100000,0) -> 0
A23: 46211 | B23: Cláudia Santos | C23: Consulta | D23: Pix | F23: 380 | G23: Sim | H23: =IF(D23="","",IFERROR(INDEX(Config!$B$12:$B$15,MATCH(IF(AND(D23="Cartão de crédito",N(E23)>1),"Cartão de crédito parcelado",D23),Config!$A$12:$A$15,0)),0)+IF(AND(Config!$B$17="Sim",LEFT(D23,17)="Cartão de crédito"),Config!$B$18*IFERROR(INDEX(Config!$C$12:$C$15,MATCH(IF(AND(D23="Cartão de crédito",N(E23)>1),"Cartão de crédito parcelado",D23),Config!$A$12:$A$15,0)),0)/30*MAX(1,N(E23)),0)) -> 0 | I23: =IF(OR(D23="",F23=""),"",ROUND(F23*H23,2)) -> 0 | J23: =IF(I23="","",F23-I23) -> 380 | K23: =IF(OR(D23="",A23=""),"",A23+IF(AND(Config!$B$17="Sim",LEFT(D23,17)="Cartão de crédito"),1,IFERROR(INDEX(Config!$C$12:$C$15,MATCH(IF(AND(D23="Cartão de crédito",N(E23)>1),"Cartão de crédito parcelado",D23),Config!$A$12:$A$15,0)),0))) -> 46211 | L23: =IF(A23="","",MONTH(A23)) -> 7 | M23: =IF(A23="","",YEAR(A23)) -> 2026 | N23: =IF(K23="","",IF(G23="Sim","Conferido",IF(K23>Config!$B$8,"A cair","A conferir"))) -> Conferido | O23: =IF(N23="A conferir",(Config!$B$8-K23)*1000+N(F23)/1000+ROW()/100000,0) -> 0
A24: 46211 | B24: Otávio Nascimento | C24: Consulta | D24: Cartão de crédito | F24: 380 | G24: Sim | H24: =IF(D24="","",IFERROR(INDEX(Config!$B$12:$B$15,MATCH(IF(AND(D24="Cartão de crédito",N(E24)>1),"Cartão de crédito parcelado",D24),Config!$A$12:$A$15,0)),0)+IF(AND(Config!$B$17="Sim",LEFT(D24,17)="Cartão de crédito"),Config!$B$18*IFERROR(INDEX(Config!$C$12:$C$15,MATCH(IF(AND(D24="Cartão de crédito",N(E24)>1),"Cartão de crédito parcelado",D24),Config!$A$12:$A$15,0)),0)/30*MAX(1,N(E24)),0)) -> 0.032 | I24: =IF(OR(D24="",F24=""),"",ROUND(F24*H24,2)) -> 12.16 | J24: =IF(I24="","",F24-I24) -> 367.84 | K24: =IF(OR(D24="",A24=""),"",A24+IF(AND(Config!$B$17="Sim",LEFT(D24,17)="Cartão de crédito"),1,IFERROR(INDEX(Config!$C$12:$C$15,MATCH(IF(AND(D24="Cartão de crédito",N(E24)>1),"Cartão de crédito parcelado",D24),Config!$A$12:$A$15,0)),0))) -> 46241 | L24: =IF(A24="","",MONTH(A24)) -> 7 | M24: =IF(A24="","",YEAR(A24)) -> 2026 | N24: =IF(K24="","",IF(G24="Sim","Conferido",IF(K24>Config!$B$8,"A cair","A conferir"))) -> Conferido | O24: =IF(N24="A conferir",(Config!$B$8-K24)*1000+N(F24)/1000+ROW()/100000,0) -> 0
A25: 46212 | B25: Elaine Cardoso | C25: Consulta | D25: Cartão de crédito | F25: 380 | G25: Sim | H25: =IF(D25="","",IFERROR(INDEX(Config!$B$12:$B$15,MATCH(IF(AND(D25="Cartão de crédito",N(E25)>1),"Cartão de crédito parcelado",D25),Config!$A$12:$A$15,0)),0)+IF(AND(Config!$B$17="Sim",LEFT(D25,17)="Cartão de crédito"),Config!$B$18*IFERROR(INDEX(Config!$C$12:$C$15,MATCH(IF(AND(D25="Cartão de crédito",N(E25)>1),"Cartão de crédito parcelado",D25),Config!$A$12:$A$15,0)),0)/30*MAX(1,N(E25)),0)) -> 0.032 | I25: =IF(OR(D25="",F25=""),"",ROUND(F25*H25,2)) -> 12.16 | J25: =IF(I25="","",F25-I25) -> 367.84 | K25: =IF(OR(D25="",A25=""),"",A25+IF(AND(Config!$B$17="Sim",LEFT(D25,17)="Cartão de crédito"),1,IFERROR(INDEX(Config!$C$12:$C$15,MATCH(IF(AND(D25="Cartão de crédito",N(E25)>1),"Cartão de crédito parcelado",D25),Config!$A$12:$A$15,0)),0))) -> 46242 | L25: =IF(A25="","",MONTH(A25)) -> 7 | M25: =IF(A25="","",YEAR(A25)) -> 2026 | N25: =IF(K25="","",IF(G25="Sim","Conferido",IF(K25>Config!$B$8,"A cair","A conferir"))) -> Conferido | O25: =IF(N25="A conferir",(Config!$B$8-K25)*1000+N(F25)/1000+ROW()/100000,0) -> 0
A26: 46212 | B26: Roberta Araújo | C26: Consulta | D26: Pix | F26: 380 | G26: Sim | H26: =IF(D26="","",IFERROR(INDEX(Config!$B$12:$B$15,MATCH(IF(AND(D26="Cartão de crédito",N(E26)>1),"Cartão de crédito parcelado",D26),Config!$A$12:$A$15,0)),0)+IF(AND(Config!$B$17="Sim",LEFT(D26,17)="Cartão de crédito"),Config!$B$18*IFERROR(INDEX(Config!$C$12:$C$15,MATCH(IF(AND(D26="Cartão de crédito",N(E26)>1),"Cartão de crédito parcelado",D26),Config!$A$12:$A$15,0)),0)/30*MAX(1,N(E26)),0)) -> 0 | I26: =IF(OR(D26="",F26=""),"",ROUND(F26*H26,2)) -> 0 | J26: =IF(I26="","",F26-I26) -> 380 | K26: =IF(OR(D26="",A26=""),"",A26+IF(AND(Config!$B$17="Sim",LEFT(D26,17)="Cartão de crédito"),1,IFERROR(INDEX(Config!$C$12:$C$15,MATCH(IF(AND(D26="Cartão de crédito",N(E26)>1),"Cartão de crédito parcelado",D26),Config!$A$12:$A$15,0)),0))) -> 46212 | L26: =IF(A26="","",MONTH(A26)) -> 7 | M26: =IF(A26="","",YEAR(A26)) -> 2026 | N26: =IF(K26="","",IF(G26="Sim","Conferido",IF(K26>Config!$B$8,"A cair","A conferir"))) -> Conferido | O26: =IF(N26="A conferir",(Config!$B$8-K26)*1000+N(F26)/1000+ROW()/100000,0) -> 0
A27: 46212 | B27: Fábio Gomes | C27: Avaliação endócrina | D27: Cartão de crédito | F27: 400 | G27: Sim | H27: =IF(D27="","",IFERROR(INDEX(Config!$B$12:$B$15,MATCH(IF(AND(D27="Cartão de crédito",N(E27)>1),"Cartão de crédito parcelado",D27),Config!$A$12:$A$15,0)),0)+IF(AND(Config!$B$17="Sim",LEFT(D27,17)="Cartão de crédito"),Config!$B$18*IFERROR(INDEX(Config!$C$12:$C$15,MATCH(IF(AND(D27="Cartão de crédito",N(E27)>1),"Cartão de crédito parcelado",D27),Config!$A$12:$A$15,0)),0)/30*MAX(1,N(E27)),0)) -> 0.032 | I27: =IF(OR(D27="",F27=""),"",ROUND(F27*H27,2)) -> 12.8 | J27: =IF(I27="","",F27-I27) -> 387.2 | K27: =IF(OR(D27="",A27=""),"",A27+IF(AND(Config!$B$17="Sim",LEFT(D27,17)="Cartão de crédito"),1,IFERROR(INDEX(Config!$C$12:$C$15,MATCH(IF(AND(D27="Cartão de crédito",N(E27)>1),"Cartão de crédito parcelado",D27),Config!$A$12:$A$15,0)),0))) -> 46242 | L27: =IF(A27="","",MONTH(A27)) -> 7 | M27: =IF(A27="","",YEAR(A27)) -> 2026 | N27: =IF(K27="","",IF(G27="Sim","Conferido",IF(K27>Config!$B$8,"A cair","A conferir"))) -> Conferido | O27: =IF(N27="A conferir",(Config!$B$8-K27)*1000+N(F27)/1000+ROW()/100000,0) -> 0
... A35: 46216 | B35: Gisele Ribeiro | C35: ECG | D35: Cartão de crédito | F35: 130 | G35: Sim | H35: =IF(D35="","",IFERROR(INDEX(Config!$B$12:$B$15,MATCH(IF(AND(D35="Cartão de crédito",N(E35)>1),"Cartão de crédito parcelado",D35),Config!$A$12:$A$15,0)),0)+IF(AND(Config!$B$17="Sim",LEFT(D35,17)="Cartão de crédito"),Config!$B$18*IFERROR(INDEX(Config!$C$12:$C$15,MATCH(IF(AND(D35="Cartão de crédito",N(E35)>1),"Cartão de crédito parcelado",D35),Config!$A$12:$A$15,0)),0)/30*MAX(1,N(E35)),0)) -> 0.032 | I35: =IF(OR(D35="",F35=""),"",ROUND(F35*H35,2)) -> 4.16 | J35: =IF(I35="","",F35-I35) -> 125.84 | K35: =IF(OR(D35="",A35=""),"",A35+IF(AND(Config!$B$17="Sim",LEFT(D35,17)="Cartão de crédito"),1,IFERROR(INDEX(Config!$C$12:$C$15,MATCH(IF(AND(D35="Cartão de crédito",N(E35)>1),"Cartão de crédito parcelado",D35),Config!$A$12:$A$15,0)),0))) -> 46246 | L35: =IF(A35="","",MONTH(A35)) -> 7 | M35: =IF(A35="","",YEAR(A35)) -> 2026 | N35: =IF(K35="","",IF(G35="Sim","Conferido",IF(K35>Config!$B$8,"A cair","A conferir"))) -> Conferido | O35: =IF(N35="A conferir",(Config!$B$8-K35)*1000+N(F35)/1000+ROW()/100000,0) -> 0
A36: 46216 | B36: Henrique Ribeiro | C36: Consulta | D36: Cartão de crédito | E36: 2 | F36: 380 | G36: Sim | H36: =IF(D36="","",IFERROR(INDEX(Config!$B$12:$B$15,MATCH(IF(AND(D36="Cartão de crédito",N(E36)>1),"Cartão de crédito parcelado",D36),Config!$A$12:$A$15,0)),0)+IF(AND(Config!$B$17="Sim",LEFT(D36,17)="Cartão de crédito"),Config!$B$18*IFERROR(INDEX(Config!$C$12:$C$15,MATCH(IF(AND(D36="Cartão de crédito",N(E36)>1),"Cartão de crédito parcelado",D36),Config!$A$12:$A$15,0)),0)/30*MAX(1,N(E36)),0)) -> 0.039 | I36: =IF(OR(D36="",F36=""),"",ROUND(F36*H36,2)) -> 14.82 | J36: =IF(I36="","",F36-I36) -> 365.18 | K36: =IF(OR(D36="",A36=""),"",A36+IF(AND(Config!$B$17="Sim",LEFT(D36,17)="Cartão de crédito"),1,IFERROR(INDEX(Config!$C$12:$C$15,MATCH(IF(AND(D36="Cartão de crédito",N(E36)>1),"Cartão de crédito parcelado",D36),Config!$A$12:$A$15,0)),0))) -> 46246 | L36: =IF(A36="","",MONTH(A36)) -> 7 | M36: =IF(A36="","",YEAR(A36)) -> 2026 | N36: =IF(K36="","",IF(G36="Sim","Conferido",IF(K36>Config!$B$8,"A cair","A conferir"))) -> Conferido | O36: =IF(N36="A conferir",(Config!$B$8-K36)*1000+N(F36)/1000+ROW()/100000,0) -> 0
A37: 46216 | B37: Gabriel Oliveira | C37: Consulta | D37: Pix | F37: 380 | G37: Sim | H37: =IF(D37="","",IFERROR(INDEX(Config!$B$12:$B$15,MATCH(IF(AND(D37="Cartão de crédito",N(E37)>1),"Cartão de crédito parcelado",D37),Config!$A$12:$A$15,0)),0)+IF(AND(Config!$B$17="Sim",LEFT(D37,17)="Cartão de crédito"),Config!$B$18*IFERROR(INDEX(Config!$C$12:$C$15,MATCH(IF(AND(D37="Cartão de crédito",N(E37)>1),"Cartão de crédito parcelado",D37),Config!$A$12:$A$15,0)),0)/30*MAX(1,N(E37)),0)) -> 0 | I37: =IF(OR(D37="",F37=""),"",ROUND(F37*H37,2)) -> 0 | J37: =IF(I37="","",F37-I37) -> 380 | K37: =IF(OR(D37="",A37=""),"",A37+IF(AND(Config!$B$17="Sim",LEFT(D37,17)="Cartão de crédito"),1,IFERROR(INDEX(Config!$C$12:$C$15,MATCH(IF(AND(D37="Cartão de crédito",N(E37)>1),"Cartão de crédito parcelado",D37),Config!$A$12:$A$15,0)),0))) -> 46216 | L37: =IF(A37="","",MONTH(A37)) -> 7 | M37: =IF(A37="","",YEAR(A37)) -> 2026 | N37: =IF(K37="","",IF(G37="Sim","Conferido",IF(K37>Config!$B$8,"A cair","A conferir"))) -> Conferido | O37: =IF(N37="A conferir",(Config!$B$8-K37)*1000+N(F37)/1000+ROW()/100000,0) -> 0
A38: 46217 | B38: Regina Teixeira | C38: Consulta | D38: Pix | F38: 380 | G38: Sim | H38: =IF(D38="","",IFERROR(INDEX(Config!$B$12:$B$15,MATCH(IF(AND(D38="Cartão de crédito",N(E38)>1),"Cartão de crédito parcelado",D38),Config!$A$12:$A$15,0)),0)+IF(AND(Config!$B$17="Sim",LEFT(D38,17)="Cartão de crédito"),Config!$B$18*IFERROR(INDEX(Config!$C$12:$C$15,MATCH(IF(AND(D38="Cartão de crédito",N(E38)>1),"Cartão de crédito parcelado",D38),Config!$A$12:$A$15,0)),0)/30*MAX(1,N(E38)),0)) -> 0 | I38: =IF(OR(D38="",F38=""),"",ROUND(F38*H38,2)) -> 0 | J38: =IF(I38="","",F38-I38) -> 380 | K38: =IF(OR(D38="",A38=""),"",A38+IF(AND(Config!$B$17="Sim",LEFT(D38,17)="Cartão de crédito"),1,IFERROR(INDEX(Config!$C$12:$C$15,MATCH(IF(AND(D38="Cartão de crédito",N(E38)>1),"Cartão de crédito parcelado",D38),Config!$A$12:$A$15,0)),0))) -> 46217 | L38: =IF(A38="","",MONTH(A38)) -> 7 | M38: =IF(A38="","",YEAR(A38)) -> 2026 | N38: =IF(K38="","",IF(G38="Sim","Conferido",IF(K38>Config!$B$8,"A cair","A conferir"))) -> Conferido | O38: =IF(N38="A conferir",(Config!$B$8-K38)*1000+N(F38)/1000+ROW()/100000,0) -> 0
A39: 46217 | B39: Priscila Reis | C39: Avaliação endócrina | D39: Pix | F39: 400 | G39: Sim | H39: =IF(D39="","",IFERROR(INDEX(Config!$B$12:$B$15,MATCH(IF(AND(D39="Cartão de crédito",N(E39)>1),"Cartão de crédito parcelado",D39),Config!$A$12:$A$15,0)),0)+IF(AND(Config!$B$17="Sim",LEFT(D39,17)="Cartão de crédito"),Config!$B$18*IFERROR(INDEX(Config!$C$12:$C$15,MATCH(IF(AND(D39="Cartão de crédito",N(E39)>1),"Cartão de crédito parcelado",D39),Config!$A$12:$A$15,0)),0)/30*MAX(1,N(E39)),0)) -> 0 | I39: =IF(OR(D39="",F39=""),"",ROUND(F39*H39,2)) -> 0 | J39: =IF(I39="","",F39-I39) -> 400 | K39: =IF(OR(D39="",A39=""),"",A39+IF(AND(Config!$B$17="Sim",LEFT(D39,17)="Cartão de crédito"),1,IFERROR(INDEX(Config!$C$12:$C$15,MATCH(IF(AND(D39="Cartão de crédito",N(E39)>1),"Cartão de crédito parcelado",D39),Config!$A$12:$A$15,0)),0))) -> 46217 | L39: =IF(A39="","",MONTH(A39)) -> 7 | M39: =IF(A39="","",YEAR(A39)) -> 2026 | N39: =IF(K39="","",IF(G39="Sim","Conferido",IF(K39>Config!$B$8,"A cair","A conferir"))) -> Conferido | O39: =IF(N39="A conferir",(Config!$B$8-K39)*1000+N(F39)/1000+ROW()/100000,0) -> 0
A40: 46217 | B40: Cláudia Melo | C40: Avaliação endócrina | D40: Cartão de crédito | F40: 400 | G40: Sim | H40: =IF(D40="","",IFERROR(INDEX(Config!$B$12:$B$15,MATCH(IF(AND(D40="Cartão de crédito",N(E40)>1),"Cartão de crédito parcelado",D40),Config!$A$12:$A$15,0)),0)+IF(AND(Config!$B$17="Sim",LEFT(D40,17)="Cartão de crédito"),Config!$B$18*IFERROR(INDEX(Config!$C$12:$C$15,MATCH(IF(AND(D40="Cartão de crédito",N(E40)>1),"Cartão de crédito parcelado",D40),Config!$A$12:$A$15,0)),0)/30*MAX(1,N(E40)),0)) -> 0.032 | I40: =IF(OR(D40="",F40=""),"",ROUND(F40*H40,2)) -> 12.8 | J40: =IF(I40="","",F40-I40) -> 387.2 | K40: =IF(OR(D40="",A40=""),"",A40+IF(AND(Config!$B$17="Sim",LEFT(D40,17)="Cartão de crédito"),1,IFERROR(INDEX(Config!$C$12:$C$15,MATCH(IF(AND(D40="Cartão de crédito",N(E40)>1),"Cartão de crédito parcelado",D40),Config!$A$12:$A$15,0)),0))) -> 46247 | L40: =IF(A40="","",MONTH(A40)) -> 7 | M40: =IF(A40="","",YEAR(A40)) -> 2026 | N40: =IF(K40="","",IF(G40="Sim","Conferido",IF(K40>Config!$B$8,"A cair","A conferir"))) -> Conferido | O40: =IF(N40="A conferir",(Config!$B$8-K40)*1000+N(F40)/1000+ROW()/100000,0) -> 0
A41: 46217 | B41: Rafael Dias | C41: ECG | D41: Cartão de crédito | F41: 130 | G41: Sim | H41: =IF(D41="","",IFERROR(INDEX(Config!$B$12:$B$15,MATCH(IF(AND(D41="Cartão de crédito",N(E41)>1),"Cartão de crédito parcelado",D41),Config!$A$12:$A$15,0)),0)+IF(AND(Config!$B$17="Sim",LEFT(D41,17)="Cartão de crédito"),Config!$B$18*IFERROR(INDEX(Config!$C$12:$C$15,MATCH(IF(AND(D41="Cartão de crédito",N(E41)>1),"Cartão de crédito parcelado",D41),Config!$A$12:$A$15,0)),0)/30*MAX(1,N(E41)),0)) -> 0.032 | I41: =IF(OR(D41="",F41=""),"",ROUND(F41*H41,2)) -> 4.16 | J41: =IF(I41="","",F41-I41) -> 125.84 | K41: =IF(OR(D41="",A41=""),"",A41+IF(AND(Config!$B$17="Sim",LEFT(D41,17)="Cartão de crédito"),1,IFERROR(INDEX(Config!$C$12:$C$15,MATCH(IF(AND(D41="Cartão de crédito",N(E41)>1),"Cartão de crédito parcelado",D41),Config!$A$12:$A$15,0)),0))) -> 46247 | L41: =IF(A41="","",MONTH(A41)) -> 7 | M41: =IF(A41="","",YEAR(A41)) -> 2026 | N41: =IF(K41="","",IF(G41="Sim","Conferido",IF(K41>Config!$B$8,"A cair","A conferir"))) -> Conferido | O41: =IF(N41="A conferir",(Config!$B$8-K41)*1000+N(F41)/1000+ROW()/100000,0) -> 0
A42: 46217 | B42: Mônica Martins | C42: ECG | D42: Pix | F42: 130 | G42: Sim | H42: =IF(D42="","",IFERROR(INDEX(Config!$B$12:$B$15,MATCH(IF(AND(D42="Cartão de crédito",N(E42)>1),"Cartão de crédito parcelado",D42),Config!$A$12:$A$15,0)),0)+IF(AND(Config!$B$17="Sim",LEFT(D42,17)="Cartão de crédito"),Config!$B$18*IFERROR(INDEX(Config!$C$12:$C$15,MATCH(IF(AND(D42="Cartão de crédito",N(E42)>1),"Cartão de crédito parcelado",D42),Config!$A$12:$A$15,0)),0)/30*MAX(1,N(E42)),0)) -> 0 | I42: =IF(OR(D42="",F42=""),"",ROUND(F42*H42,2)) -> 0 | J42: =IF(I42="","",F42-I42) -> 130 | K42: =IF(OR(D42="",A42=""),"",A42+IF(AND(Config!$B$17="Sim",LEFT(D42,17)="Cartão de crédito"),1,IFERROR(INDEX(Config!$C$12:$C$15,MATCH(IF(AND(D42="Cartão de crédito",N(E42)>1),"Cartão de crédito parcelado",D42),Config!$A$12:$A$15,0)),0))) -> 46217 | L42: =IF(A42="","",MONTH(A42)) -> 7 | M42: =IF(A42="","",YEAR(A42)) -> 2026 | N42: =IF(K42="","",IF(G42="Sim","Conferido",IF(K42>Config!$B$8,"A cair","A conferir"))) -> Conferido | O42: =IF(N42="A conferir",(Config!$B$8-K42)*1000+N(F42)/1000+ROW()/100000,0) -> 0
A43: 46217 | B43: Marcelo Ferreira | C43: Consulta | D43: Cartão de crédito | E43: 2 | F43: 380 | G43: Sim | H43: =IF(D43="","",IFERROR(INDEX(Config!$B$12:$B$15,MATCH(IF(AND(D43="Cartão de crédito",N(E43)>1),"Cartão de crédito parcelado",D43),Config!$A$12:$A$15,0)),0)+IF(AND(Config!$B$17="Sim",LEFT(D43,17)="Cartão de crédito"),Config!$B$18*IFERROR(INDEX(Config!$C$12:$C$15,MATCH(IF(AND(D43="Cartão de crédito",N(E43)>1),"Cartão de crédito parcelado",D43),Config!$A$12:$A$15,0)),0)/30*MAX(1,N(E43)),0)) -> 0.039 | I43: =IF(OR(D43="",F43=""),"",ROUND(F43*H43,2)) -> 14.82 | J43: =IF(I43="","",F43-I43) -> 365.18 | K43: =IF(OR(D43="",A43=""),"",A43+IF(AND(Config!$B$17="Sim",LEFT(D43,17)="Cartão de crédito"),1,IFERROR(INDEX(Config!$C$12:$C$15,MATCH(IF(AND(D43="Cartão de crédito",N(E43)>1),"Cartão de crédito parcelado",D43),Config!$A$12:$A$15,0)),0))) -> 46247 | L43: =IF(A43="","",MONTH(A43)) -> 7 | M43: =IF(A43="","",YEAR(A43)) -> 2026 | N43: =IF(K43="","",IF(G43="Sim","Conferido",IF(K43>Config!$B$8,"A cair","A conferir"))) -> Conferido | O43: =IF(N43="A conferir",(Config!$B$8-K43)*1000+N(F43)/1000+ROW()/100000,0) -> 0
A44: 46217 | B44: Roberta Lima | C44: Avaliação endócrina | D44: Cartão de crédito | F44: 400 | G44: Sim | H44: =IF(D44="","",IFERROR(INDEX(Config!$B$12:$B$15,MATCH(IF(AND(D44="Cartão de crédito",N(E44)>1),"Cartão de crédito parcelado",D44),Config!$A$12:$A$15,0)),0)+IF(AND(Config!$B$17="Sim",LEFT(D44,17)="Cartão de crédito"),Config!$B$18*IFERROR(INDEX(Config!$C$12:$C$15,MATCH(IF(AND(D44="Cartão de crédito",N(E44)>1),"Cartão de crédito parcelado",D44),Config!$A$12:$A$15,0)),0)/30*MAX(1,N(E44)),0)) -> 0.032 | I44: =IF(OR(D44="",F44=""),"",ROUND(F44*H44,2)) -> 12.8 | J44: =IF(I44="","",F44-I44) -> 387.2 | K44: =IF(OR(D44="",A44=""),"",A44+IF(AND(Config!$B$17="Sim",LEFT(D44,17)="Cartão de crédito"),1,IFERROR(INDEX(Config!$C$12:$C$15,MATCH(IF(AND(D44="Cartão de crédito",N(E44)>1),"Cartão de crédito parcelado",D44),Config!$A$12:$A$15,0)),0))) -> 46247 | L44: =IF(A44="","",MONTH(A44)) -> 7 | M44: =IF(A44="","",YEAR(A44)) -> 2026 | N44: =IF(K44="","",IF(G44="Sim","Conferido",IF(K44>Config!$B$8,"A cair","A conferir"))) -> Conferido | O44: =IF(N44="A conferir",(Config!$B$8-K44)*1000+N(F44)/1000+ROW()/100000,0) -> 0
A45: 46217 | B45: Thiago Melo | C45: Avaliação endócrina | D45: Cartão de crédito | E45: 2 | F45: 400 | G45: Sim | H45: =IF(D45="","",IFERROR(INDEX(Config!$B$12:$B$15,MATCH(IF(AND(D45="Cartão de crédito",N(E45)>1),"Cartão de crédito parcelado",D45),Config!$A$12:$A$15,0)),0)+IF(AND(Config!$B$17="Sim",LEFT(D45,17)="Cartão de crédito"),Config!$B$18*IFERROR(INDEX(Config!$C$12:$C$15,MATCH(IF(AND(D45="Cartão de crédito",N(E45)>1),"Cartão de crédito parcelado",D45),Config!$A$12:$A$15,0)),0)/30*MAX(1,N(E45)),0)) -> 0.039 | I45: =IF(OR(D45="",F45=""),"",ROUND(F45*H45,2)) -> 15.6 | J45: =IF(I45="","",F45-I45) -> 384.4 | K45: =IF(OR(D45="",A45=""),"",A45+IF(AND(Config!$B$17="Sim",LEFT(D45,17)="Cartão de crédito"),1,IFERROR(INDEX(Config!$C$12:$C$15,MATCH(IF(AND(D45="Cartão de crédito",N(E45)>1),"Cartão de crédito parcelado",D45),Config!$A$12:$A$15,0)),0))) -> 46247 | L45: =IF(A45="","",MONTH(A45)) -> 7 | M45: =IF(A45="","",YEAR(A45)) -> 2026 | N45: =IF(K45="","",IF(G45="Sim","Conferido",IF(K45>Config!$B$8,"A cair","A conferir"))) -> Conferido | O45: =IF(N45="A conferir",(Config!$B$8-K45)*1000+N(F45)/1000+ROW()/100000,0) -> 0
A46: 46217 | B46: Rafael Barros | C46: Consulta | D46: Pix | F46: 380 | G46: Sim | H46: =IF(D46="","",IFERROR(INDEX(Config!$B$12:$B$15,MATCH(IF(AND(D46="Cartão de crédito",N(E46)>1),"Cartão de crédito parcelado",D46),Config!$A$12:$A$15,0)),0)+IF(AND(Config!$B$17="Sim",LEFT(D46,17)="Cartão de crédito"),Config!$B$18*IFERROR(INDEX(Config!$C$12:$C$15,MATCH(IF(AND(D46="Cartão de crédito",N(E46)>1),"Cartão de crédito parcelado",D46),Config!$A$12:$A$15,0)),0)/30*MAX(1,N(E46)),0)) -> 0 | I46: =IF(OR(D46="",F46=""),"",ROUND(F46*H46,2)) -> 0 | J46: =IF(I46="","",F46-I46) -> 380 | K46: =IF(OR(D46="",A46=""),"",A46+IF(AND(Config!$B$17="Sim",LEFT(D46,17)="Cartão de crédito"),1,IFERROR(INDEX(Config!$C$12:$C$15,MATCH(IF(AND(D46="Cartão de crédito",N(E46)>1),"Cartão de crédito parcelado",D46),Config!$A$12:$A$15,0)),0))) -> 46217 | L46: =IF(A46="","",MONTH(A46)) -> 7 | M46: =IF(A46="","",YEAR(A46)) -> 2026 | N46: =IF(K46="","",IF(G46="Sim","Conferido",IF(K46>Config!$B$8,"A cair","A conferir"))) -> Conferido | O46: =IF(N46="A conferir",(Config!$B$8-K46)*1000+N(F46)/1000+ROW()/100000,0) -> 0
A47: 46217 | B47: Mariana Reis | C47: Avaliação endócrina | D47: Cartão de crédito | E47: 2 | F47: 400 | G47: Sim | H47: =IF(D47="","",IFERROR(INDEX(Config!$B$12:$B$15,MATCH(IF(AND(D47="Cartão de crédito",N(E47)>1),"Cartão de crédito parcelado",D47),Config!$A$12:$A$15,0)),0)+IF(AND(Config!$B$17="Sim",LEFT(D47,17)="Cartão de crédito"),Config!$B$18*IFERROR(INDEX(Config!$C$12:$C$15,MATCH(IF(AND(D47="Cartão de crédito",N(E47)>1),"Cartão de crédito parcelado",D47),Config!$A$12:$A$15,0)),0)/30*MAX(1,N(E47)),0)) -> 0.039 | I47: =IF(OR(D47="",F47=""),"",ROUND(F47*H47,2)) -> 15.6 | J47: =IF(I47="","",F47-I47) -> 384.4 | K47: =IF(OR(D47="",A47=""),"",A47+IF(AND(Config!$B$17="Sim",LEFT(D47,17)="Cartão de crédito"),1,IFERROR(INDEX(Config!$C$12:$C$15,MATCH(IF(AND(D47="Cartão de crédito",N(E47)>1),"Cartão de crédito parcelado",D47),Config!$A$12:$A$15,0)),0))) -> 46247 | L47: =IF(A47="","",MONTH(A47)) -> 7 | M47: =IF(A47="","",YEAR(A47)) -> 2026 | N47: =IF(K47="","",IF(G47="Sim","Conferido",IF(K47>Config!$B$8,"A cair","A conferir"))) -> Conferido | O47: =IF(N47="A conferir",(Config!$B$8-K47)*1000+N(F47)/1000+ROW()/100000,0) -> 0
A48: 46217 | B48: Helena Moreira | C48: MAPA | D48: Cartão de crédito | E48: 2 | F48: 300 | G48: Sim | H48: =IF(D48="","",IFERROR(INDEX(Config!$B$12:$B$15,MATCH(IF(AND(D48="Cartão de crédito",N(E48)>1),"Cartão de crédito parcelado",D48),Config!$A$12:$A$15,0)),0)+IF(AND(Config!$B$17="Sim",LEFT(D48,17)="Cartão de crédito"),Config!$B$18*IFERROR(INDEX(Config!$C$12:$C$15,MATCH(IF(AND(D48="Cartão de crédito",N(E48)>1),"Cartão de crédito parcelado",D48),Config!$A$12:$A$15,0)),0)/30*MAX(1,N(E48)),0)) -> 0.039 | I48: =IF(OR(D48="",F48=""),"",ROUND(F48*H48,2)) -> 11.7 | J48: =IF(I48="","",F48-I48) -> 288.3 | K48: =IF(OR(D48="",A48=""),"",A48+IF(AND(Config!$B$17="Sim",LEFT(D48,17)="Cartão de crédito"),1,IFERROR(INDEX(Config!$C$12:$C$15,MATCH(IF(AND(D48="Cartão de crédito",N(E48)>1),"Cartão de crédito parcelado",D48),Config!$A$12:$A$15,0)),0))) -> 46247 | L48: =IF(A48="","",MONTH(A48)) -> 7 | M48: =IF(A48="","",YEAR(A48)) -> 2026 | N48: =IF(K48="","",IF(G48="Sim","Conferido",IF(K48>Config!$B$8,"A cair","A conferir"))) -> Conferido | O48: =IF(N48="A conferir",(Config!$B$8-K48)*1000+N(F48)/1000+ROW()/100000,0) -> 0
A49: 46218 | B49: Marcelo Santos | C49: Consulta | D49: Cartão de crédito | F49: 380 | G49: Sim | H49: =IF(D49="","",IFERROR(INDEX(Config!$B$12:$B$15,MATCH(IF(AND(D49="Cartão de crédito",N(E49)>1),"Cartão de crédito parcelado",D49),Config!$A$12:$A$15,0)),0)+IF(AND(Config!$B$17="Sim",LEFT(D49,17)="Cartão de crédito"),Config!$B$18*IFERROR(INDEX(Config!$C$12:$C$15,MATCH(IF(AND(D49="Cartão de crédito",N(E49)>1),"Cartão de crédito parcelado",D49),Config!$A$12:$A$15,0)),0)/30*MAX(1,N(E49)),0)) -> 0.032 | I49: =IF(OR(D49="",F49=""),"",ROUND(F49*H49,2)) -> 12.16 | J49: =IF(I49="","",F49-I49) -> 367.84 | K49: =IF(OR(D49="",A49=""),"",A49+IF(AND(Config!$B$17="Sim",LEFT(D49,17)="Cartão de crédito"),1,IFERROR(INDEX(Config!$C$12:$C$15,MATCH(IF(AND(D49="Cartão de crédito",N(E49)>1),"Cartão de crédito parcelado",D49),Config!$A$12:$A$15,0)),0))) -> 46248 | L49: =IF(A49="","",MONTH(A49)) -> 7 | M49: =IF(A49="","",YEAR(A49)) -> 2026 | N49: =IF(K49="","",IF(G49="Sim","Conferido",IF(K49>Config!$B$8,"A cair","A conferir"))) -> Conferido | O49: =IF(N49="A conferir",(Config!$B$8-K49)*1000+N(F49)/1000+ROW()/100000,0) -> 0
A50: 46218 | B50: Gustavo Ferreira | C50: Consulta | D50: Cartão de débito | F50: 380 | G50: Sim | H50: =IF(D50="","",IFERROR(INDEX(Config!$B$12:$B$15,MATCH(IF(AND(D50="Cartão de crédito",N(E50)>1),"Cartão de crédito parcelado",D50),Config!$A$12:$A$15,0)),0)+IF(AND(Config!$B$17="Sim",LEFT(D50,17)="Cartão de crédito"),Config!$B$18*IFERROR(INDEX(Config!$C$12:$C$15,MATCH(IF(AND(D50="Cartão de crédito",N(E50)>1),"Cartão de crédito parcelado",D50),Config!$A$12:$A$15,0)),0)/30*MAX(1,N(E50)),0)) -> 0.015 | I50: =IF(OR(D50="",F50=""),"",ROUND(F50*H50,2)) -> 5.7 | J50: =IF(I50="","",F50-I50) -> 374.3 | K50: =IF(OR(D50="",A50=""),"",A50+IF(AND(Config!$B$17="Sim",LEFT(D50,17)="Cartão de crédito"),1,IFERROR(INDEX(Config!$C$12:$C$15,MATCH(IF(AND(D50="Cartão de crédito",N(E50)>1),"Cartão de crédito parcelado",D50),Config!$A$12:$A$15,0)),0))) -> 46219 | L50: =IF(A50="","",MONTH(A50)) -> 7 | M50: =IF(A50="","",YEAR(A50)) -> 2026 | N50: =IF(K50="","",IF(G50="Sim","Conferido",IF(K50>Config!$B$8,"A cair","A conferir"))) -> Conferido | O50: =IF(N50="A conferir",(Config!$B$8-K50)*1000+N(F50)/1000+ROW()/100000,0) -> 0
A51: 46219 | B51: Otávio Cardoso | C51: Consulta | D51: Cartão de crédito | F51: 380 | G51: Sim | H51: =IF(D51="","",IFERROR(INDEX(Config!$B$12:$B$15,MATCH(IF(AND(D51="Cartão de crédito",N(E51)>1),"Cartão de crédito parcelado",D51),Config!$A$12:$A$15,0)),0)+IF(AND(Config!$B$17="Sim",LEFT(D51,17)="Cartão de crédito"),Config!$B$18*IFERROR(INDEX(Config!$C$12:$C$15,MATCH(IF(AND(D51="Cartão de crédito",N(E51)>1),"Cartão de crédito parcelado",D51),Config!$A$12:$A$15,0)),0)/30*MAX(1,N(E51)),0)) -> 0.032 | I51: =IF(OR(D51="",F51=""),"",ROUND(F51*H51,2)) -> 12.16 | J51: =IF(I51="","",F51-I51) -> 367.84 | K51: =IF(OR(D51="",A51=""),"",A51+IF(AND(Config!$B$17="Sim",LEFT(D51,17)="Cartão de crédito"),1,IFERROR(INDEX(Config!$C$12:$C$15,MATCH(IF(AND(D51="Cartão de crédito",N(E51)>1),"Cartão de crédito parcelado",D51),Config!$A$12:$A$15,0)),0))) -> 46249 | L51: =IF(A51="","",MONTH(A51)) -> 7 | M51: =IF(A51="","",YEAR(A51)) -> 2026 | N51: =IF(K51="","",IF(G51="Sim","Conferido",IF(K51>Config!$B$8,"A cair","A conferir"))) -> Conferido | O51: =IF(N51="A conferir",(Config!$B$8-K51)*1000+N(F51)/1000+ROW()/100000,0) -> 0
A52: 46219 | B52: Gisele Ribeiro | C52: Consulta | D52: Cartão de débito | F52: 380 | G52: Sim | H52: =IF(D52="","",IFERROR(INDEX(Config!$B$12:$B$15,MATCH(IF(AND(D52="Cartão de crédito",N(E52)>1),"Cartão de crédito parcelado",D52),Config!$A$12:$A$15,0)),0)+IF(AND(Config!$B$17="Sim",LEFT(D52,17)="Cartão de crédito"),Config!$B$18*IFERROR(INDEX(Config!$C$12:$C$15,MATCH(IF(AND(D52="Cartão de crédito",N(E52)>1),"Cartão de crédito parcelado",D52),Config!$A$12:$A$15,0)),0)/30*MAX(1,N(E52)),0)) -> 0.015 | I52: =IF(OR(D52="",F52=""),"",ROUND(F52*H52,2)) -> 5.7 | J52: =IF(I52="","",F52-I52) -> 374.3 | K52: =IF(OR(D52="",A52=""),"",A52+IF(AND(Config!$B$17="Sim",LEFT(D52,17)="Cartão de crédito"),1,IFERROR(INDEX(Config!$C$12:$C$15,MATCH(IF(AND(D52="Cartão de crédito",N(E52)>1),"Cartão de crédito parcelado",D52),Config!$A$12:$A$15,0)),0))) -> 46220 | L52: =IF(A52="","",MONTH(A52)) -> 7 | M52: =IF(A52="","",YEAR(A52)) -> 2026 | N52: =IF(K52="","",IF(G52="Sim","Conferido",IF(K52>Config!$B$8,"A cair","A conferir"))) -> Conferido | O52: =IF(N52="A conferir",(Config!$B$8-K52)*1000+N(F52)/1000+ROW()/100000,0) -> 0
A53: 46219 | B53: Wagner Santos | C53: Consulta | D53: Pix | F53: 380 | G53: Sim | H53: =IF(D53="","",IFERROR(INDEX(Config!$B$12:$B$15,MATCH(IF(AND(D53="Cartão de crédito",N(E53)>1),"Cartão de crédito parcelado",D53),Config!$A$12:$A$15,0)),0)+IF(AND(Config!$B$17="Sim",LEFT(D53,17)="Cartão de crédito"),Config!$B$18*IFERROR(INDEX(Config!$C$12:$C$15,MATCH(IF(AND(D53="Cartão de crédito",N(E53)>1),"Cartão de crédito parcelado",D53),Config!$A$12:$A$15,0)),0)/30*MAX(1,N(E53)),0)) -> 0 | I53: =IF(OR(D53="",F53=""),"",ROUND(F53*H53,2)) -> 0 | J53: =IF(I53="","",F53-I53) -> 380 | K53: =IF(OR(D53="",A53=""),"",A53+IF(AND(Config!$B$17="Sim",LEFT(D53,17)="Cartão de crédito"),1,IFERROR(INDEX(Config!$C$12:$C$15,MATCH(IF(AND(D53="Cartão de crédito",N(E53)>1),"Cartão de crédito parcelado",D53),Config!$A$12:$A$15,0)),0))) -> 46219 | L53: =IF(A53="","",MONTH(A53)) -> 7 | M53: =IF(A53="","",YEAR(A53)) -> 2026 | N53: =IF(K53="","",IF(G53="Sim","Conferido",IF(K53>Config!$B$8,"A cair","A conferir"))) -> Conferido | O53: =IF(N53="A conferir",(Config!$B$8-K53)*1000+N(F53)/1000+ROW()/100000,0) -> 0
A54: 46219 | B54: Elaine Cardoso | C54: Consulta | D54: Cartão de crédito | F54: 380 | G54: Sim | H54: =IF(D54="","",IFERROR(INDEX(Config!$B$12:$B$15,MATCH(IF(AND(D54="Cartão de crédito",N(E54)>1),"Cartão de crédito parcelado",D54),Config!$A$12:$A$15,0)),0)+IF(AND(Config!$B$17="Sim",LEFT(D54,17)="Cartão de crédito"),Config!$B$18*IFERROR(INDEX(Config!$C$12:$C$15,MATCH(IF(AND(D54="Cartão de crédito",N(E54)>1),"Cartão de crédito parcelado",D54),Config!$A$12:$A$15,0)),0)/30*MAX(1,N(E54)),0)) -> 0.032 | I54: =IF(OR(D54="",F54=""),"",ROUND(F54*H54,2)) -> 12.16 | J54: =IF(I54="","",F54-I54) -> 367.84 | K54: =IF(OR(D54="",A54=""),"",A54+IF(AND(Config!$B$17="Sim",LEFT(D54,17)="Cartão de crédito"),1,IFERROR(INDEX(Config!$C$12:$C$15,MATCH(IF(AND(D54="Cartão de crédito",N(E54)>1),"Cartão de crédito parcelado",D54),Config!$A$12:$A$15,0)),0))) -> 46249 | L54: =IF(A54="","",MONTH(A54)) -> 7 | M54: =IF(A54="","",YEAR(A54)) -> 2026 | N54: =IF(K54="","",IF(G54="Sim","Conferido",IF(K54>Config!$B$8,"A cair","A conferir"))) -> Conferido | O54: =IF(N54="A conferir",(Config!$B$8-K54)*1000+N(F54)/1000+ROW()/100000,0) -> 0
A55: 46219 | B55: Sérgio Martins | C55: ECG | D55: Cartão de débito | F55: 130 | G55: Sim | H55: =IF(D55="","",IFERROR(INDEX(Config!$B$12:$B$15,MATCH(IF(AND(D55="Cartão de crédito",N(E55)>1),"Cartão de crédito parcelado",D55),Config!$A$12:$A$15,0)),0)+IF(AND(Config!$B$17="Sim",LEFT(D55,17)="Cartão de crédito"),Config!$B$18*IFERROR(INDEX(Config!$C$12:$C$15,MATCH(IF(AND(D55="Cartão de crédito",N(E55)>1),"Cartão de crédito parcelado",D55),Config!$A$12:$A$15,0)),0)/30*MAX(1,N(E55)),0)) -> 0.015 | I55: =IF(OR(D55="",F55=""),"",ROUND(F55*H55,2)) -> 1.95 | J55: =IF(I55="","",F55-I55) -> 128.05 | K55: =IF(OR(D55="",A55=""),"",A55+IF(AND(Config!$B$17="Sim",LEFT(D55,17)="Cartão de crédito"),1,IFERROR(INDEX(Config!$C$12:$C$15,MATCH(IF(AND(D55="Cartão de crédito",N(E55)>1),"Cartão de crédito parcelado",D55),Config!$A$12:$A$15,0)),0))) -> 46220 | L55: =IF(A55="","",MONTH(A55)) -> 7 | M55: =IF(A55="","",YEAR(A55)) -> 2026 | N55: =IF(K55="","",IF(G55="Sim","Conferido",IF(K55>Config!$B$8,"A cair","A conferir"))) -> Conferido | O55: =IF(N55="A conferir",(Config!$B$8-K55)*1000+N(F55)/1000+ROW()/100000,0) -> 0
A56: 46219 | B56: Gisele Xavier | C56: ECG | D56: Pix | F56: 130 | G56: Sim | H56: =IF(D56="","",IFERROR(INDEX(Config!$B$12:$B$15,MATCH(IF(AND(D56="Cartão de crédito",N(E56)>1),"Cartão de crédito parcelado",D56),Config!$A$12:$A$15,0)),0)+IF(AND(Config!$B$17="Sim",LEFT(D56,17)="Cartão de crédito"),Config!$B$18*IFERROR(INDEX(Config!$C$12:$C$15,MATCH(IF(AND(D56="Cartão de crédito",N(E56)>1),"Cartão de crédito parcelado",D56),Config!$A$12:$A$15,0)),0)/30*MAX(1,N(E56)),0)) -> 0 | I56: =IF(OR(D56="",F56=""),"",ROUND(F56*H56,2)) -> 0 | J56: =IF(I56="","",F56-I56) -> 130 | K56: =IF(OR(D56="",A56=""),"",A56+IF(AND(Config!$B$17="Sim",LEFT(D56,17)="Cartão de crédito"),1,IFERROR(INDEX(Config!$C$12:$C$15,MATCH(IF(AND(D56="Cartão de crédito",N(E56)>1),"Cartão de crédito parcelado",D56),Config!$A$12:$A$15,0)),0))) -> 46219 | L56: =IF(A56="","",MONTH(A56)) -> 7 | M56: =IF(A56="","",YEAR(A56)) -> 2026 | N56: =IF(K56="","",IF(G56="Sim","Conferido",IF(K56>Config!$B$8,"A cair","A conferir"))) -> Conferido | O56: =IF(N56="A conferir",(Config!$B$8-K56)*1000+N(F56)/1000+ROW()/100000,0) -> 0
A57: 46219 | B57: Márcia Duarte | C57: Avaliação endócrina | D57: Cartão de crédito | F57: 400 | G57: Sim | H57: =IF(D57="","",IFERROR(INDEX(Config!$B$12:$B$15,MATCH(IF(AND(D57="Cartão de crédito",N(E57)>1),"Cartão de crédito parcelado",D57),Config!$A$12:$A$15,0)),0)+IF(AND(Config!$B$17="Sim",LEFT(D57,17)="Cartão de crédito"),Config!$B$18*IFERROR(INDEX(Config!$C$12:$C$15,MATCH(IF(AND(D57="Cartão de crédito",N(E57)>1),"Cartão de crédito parcelado",D57),Config!$A$12:$A$15,0)),0)/30*MAX(1,N(E57)),0)) -> 0.032 | I57: =IF(OR(D57="",F57=""),"",ROUND(F57*H57,2)) -> 12.8 | J57: =IF(I57="","",F57-I57) -> 387.2 | K57: =IF(OR(D57="",A57=""),"",A57+IF(AND(Config!$B$17="Sim",LEFT(D57,17)="Cartão de crédito"),1,IFERROR(INDEX(Config!$C$12:$C$15,MATCH(IF(AND(D57="Cartão de crédito",N(E57)>1),"Cartão de crédito parcelado",D57),Config!$A$12:$A$15,0)),0))) -> 46249 | L57: =IF(A57="","",MONTH(A57)) -> 7 | M57: =IF(A57="","",YEAR(A57)) -> 2026 | N57: =IF(K57="","",IF(G57="Sim","Conferido",IF(K57>Config!$B$8,"A cair","A conferir"))) -> Conferido | O57: =IF(N57="A conferir",(Config!$B$8-K57)*1000+N(F57)/1000+ROW()/100000,0) -> 0
A58: 46220 | B58: Lucas Cardoso | C58: Consulta | D58: Cartão de crédito | F58: 380 | G58: Sim | H58: =IF(D58="","",IFERROR(INDEX(Config!$B$12:$B$15,MATCH(IF(AND(D58="Cartão de crédito",N(E58)>1),"Cartão de crédito parcelado",D58),Config!$A$12:$A$15,0)),0)+IF(AND(Config!$B$17="Sim",LEFT(D58,17)="Cartão de crédito"),Config!$B$18*IFERROR(INDEX(Config!$C$12:$C$15,MATCH(IF(AND(D58="Cartão de crédito",N(E58)>1),"Cartão de crédito parcelado",D58),Config!$A$12:$A$15,0)),0)/30*MAX(1,N(E58)),0)) -> 0.032 | I58: =IF(OR(D58="",F58=""),"",ROUND(F58*H58,2)) -> 12.16 | J58: =IF(I58="","",F58-I58) -> 367.84 | K58: =IF(OR(D58="",A58=""),"",A58+IF(AND(Config!$B$17="Sim",LEFT(D58,17)="Cartão de crédito"),1,IFERROR(INDEX(Config!$C$12:$C$15,MATCH(IF(AND(D58="Cartão de crédito",N(E58)>1),"Cartão de crédito parcelado",D58),Config!$A$12:$A$15,0)),0))) -> 46250 | L58: =IF(A58="","",MONTH(A58)) -> 7 | M58: =IF(A58="","",YEAR(A58)) -> 2026 | N58: =IF(K58="","",IF(G58="Sim","Conferido",IF(K58>Config!$B$8,"A cair","A conferir"))) -> Conferido | O58: =IF(N58="A conferir",(Config!$B$8-K58)*1000+N(F58)/1000+ROW()/100000,0) -> 0
A59: 46223 | B59: Marcelo Moreira | C59: Consulta | D59: Cartão de débito | F59: 380 | G59: Sim | H59: =IF(D59="","",IFERROR(INDEX(Config!$B$12:$B$15,MATCH(IF(AND(D59="Cartão de crédito",N(E59)>1),"Cartão de crédito parcelado",D59),Config!$A$12:$A$15,0)),0)+IF(AND(Config!$B$17="Sim",LEFT(D59,17)="Cartão de crédito"),Config!$B$18*IFERROR(INDEX(Config!$C$12:$C$15,MATCH(IF(AND(D59="Cartão de crédito",N(E59)>1),"Cartão de crédito parcelado",D59),Config!$A$12:$A$15,0)),0)/30*MAX(1,N(E59)),0)) -> 0.015 | I59: =IF(OR(D59="",F59=""),"",ROUND(F59*H59,2)) -> 5.7 | J59: =IF(I59="","",F59-I59) -> 374.3 | K59: =IF(OR(D59="",A59=""),"",A59+IF(AND(Config!$B$17="Sim",LEFT(D59,17)="Cartão de crédito"),1,IFERROR(INDEX(Config!$C$12:$C$15,MATCH(IF(AND(D59="Cartão de crédito",N(E59)>1),"Cartão de crédito parcelado",D59),Config!$A$12:$A$15,0)),0))) -> 46224 | L59: =IF(A59="","",MONTH(A59)) -> 7 | M59: =IF(A59="","",YEAR(A59)) -> 2026 | N59: =IF(K59="","",IF(G59="Sim","Conferido",IF(K59>Config!$B$8,"A cair","A conferir"))) -> Conferido | O59: =IF(N59="A conferir",(Config!$B$8-K59)*1000+N(F59)/1000+ROW()/100000,0) -> 0
A60: 46223 | B60: Eduardo Lima | C60: Consulta | D60: Cartão de crédito | F60: 380 | G60: Sim | H60: =IF(D60="","",IFERROR(INDEX(Config!$B$12:$B$15,MATCH(IF(AND(D60="Cartão de crédito",N(E60)>1),"Cartão de crédito parcelado",D60),Config!$A$12:$A$15,0)),0)+IF(AND(Config!$B$17="Sim",LEFT(D60,17)="Cartão de crédito"),Config!$B$18*IFERROR(INDEX(Config!$C$12:$C$15,MATCH(IF(AND(D60="Cartão de crédito",N(E60)>1),"Cartão de crédito parcelado",D60),Config!$A$12:$A$15,0)),0)/30*MAX(1,N(E60)),0)) -> 0.032 | I60: =IF(OR(D60="",F60=""),"",ROUND(F60*H60,2)) -> 12.16 | J60: =IF(I60="","",F60-I60) -> 367.84 | K60: =IF(OR(D60="",A60=""),"",A60+IF(AND(Config!$B$17="Sim",LEFT(D60,17)="Cartão de crédito"),1,IFERROR(INDEX(Config!$C$12:$C$15,MATCH(IF(AND(D60="Cartão de crédito",N(E60)>1),"Cartão de crédito parcelado",D60),Config!$A$12:$A$15,0)),0))) -> 46253 | L60: =IF(A60="","",MONTH(A60)) -> 7 | M60: =IF(A60="","",YEAR(A60)) -> 2026 | N60: =IF(K60="","",IF(G60="Sim","Conferido",IF(K60>Config!$B$8,"A cair","A conferir"))) -> Conferido | O60: =IF(N60="A conferir",(Config!$B$8-K60)*1000+N(F60)/1000+ROW()/100000,0) -> 0
... A62: 46223 | B62: Fábio Correia | C62: Consulta | D62: Cartão de crédito | F62: 380 | G62: Sim | H62: =IF(D62="","",IFERROR(INDEX(Config!$B$12:$B$15,MATCH(IF(AND(D62="Cartão de crédito",N(E62)>1),"Cartão de crédito parcelado",D62),Config!$A$12:$A$15,0)),0)+IF(AND(Config!$B$17="Sim",LEFT(D62,17)="Cartão de crédito"),Config!$B$18*IFERROR(INDEX(Config!$C$12:$C$15,MATCH(IF(AND(D62="Cartão de crédito",N(E62)>1),"Cartão de crédito parcelado",D62),Config!$A$12:$A$15,0)),0)/30*MAX(1,N(E62)),0)) -> 0.032 | I62: =IF(OR(D62="",F62=""),"",ROUND(F62*H62,2)) -> 12.16 | J62: =IF(I62="","",F62-I62) -> 367.84 | K62: =IF(OR(D62="",A62=""),"",A62+IF(AND(Config!$B$17="Sim",LEFT(D62,17)="Cartão de crédito"),1,IFERROR(INDEX(Config!$C$12:$C$15,MATCH(IF(AND(D62="Cartão de crédito",N(E62)>1),"Cartão de crédito parcelado",D62),Config!$A$12:$A$15,0)),0))) -> 46253 | L62: =IF(A62="","",MONTH(A62)) -> 7 | M62: =IF(A62="","",YEAR(A62)) -> 2026 | N62: =IF(K62="","",IF(G62="Sim","Conferido",IF(K62>Config!$B$8,"A cair","A conferir"))) -> Conferido | O62: =IF(N62="A conferir",(Config!$B$8-K62)*1000+N(F62)/1000+ROW()/100000,0) -> 0
A63: 46224 | B63: Regina Teixeira | C63: Consulta | D63: Cartão de crédito | E63: 2 | F63: 380 | G63: Sim | H63: =IF(D63="","",IFERROR(INDEX(Config!$B$12:$B$15,MATCH(IF(AND(D63="Cartão de crédito",N(E63)>1),"Cartão de crédito parcelado",D63),Config!$A$12:$A$15,0)),0)+IF(AND(Config!$B$17="Sim",LEFT(D63,17)="Cartão de crédito"),Config!$B$18*IFERROR(INDEX(Config!$C$12:$C$15,MATCH(IF(AND(D63="Cartão de crédito",N(E63)>1),"Cartão de crédito parcelado",D63),Config!$A$12:$A$15,0)),0)/30*MAX(1,N(E63)),0)) -> 0.039 | I63: =IF(OR(D63="",F63=""),"",ROUND(F63*H63,2)) -> 14.82 | J63: =IF(I63="","",F63-I63) -> 365.18 | K63: =IF(OR(D63="",A63=""),"",A63+IF(AND(Config!$B$17="Sim",LEFT(D63,17)="Cartão de crédito"),1,IFERROR(INDEX(Config!$C$12:$C$15,MATCH(IF(AND(D63="Cartão de crédito",N(E63)>1),"Cartão de crédito parcelado",D63),Config!$A$12:$A$15,0)),0))) -> 46254 | L63: =IF(A63="","",MONTH(A63)) -> 7 | M63: =IF(A63="","",YEAR(A63)) -> 2026 | N63: =IF(K63="","",IF(G63="Sim","Conferido",IF(K63>Config!$B$8,"A cair","A conferir"))) -> Conferido | O63: =IF(N63="A conferir",(Config!$B$8-K63)*1000+N(F63)/1000+ROW()/100000,0) -> 0
A64: 46224 | B64: Lucas Lopes | C64: Consulta | D64: Pix | F64: 380 | G64: Sim | H64: =IF(D64="","",IFERROR(INDEX(Config!$B$12:$B$15,MATCH(IF(AND(D64="Cartão de crédito",N(E64)>1),"Cartão de crédito parcelado",D64),Config!$A$12:$A$15,0)),0)+IF(AND(Config!$B$17="Sim",LEFT(D64,17)="Cartão de crédito"),Config!$B$18*IFERROR(INDEX(Config!$C$12:$C$15,MATCH(IF(AND(D64="Cartão de crédito",N(E64)>1),"Cartão de crédito parcelado",D64),Config!$A$12:$A$15,0)),0)/30*MAX(1,N(E64)),0)) -> 0 | I64: =IF(OR(D64="",F64=""),"",ROUND(F64*H64,2)) -> 0 | J64: =IF(I64="","",F64-I64) -> 380 | K64: =IF(OR(D64="",A64=""),"",A64+IF(AND(Config!$B$17="Sim",LEFT(D64,17)="Cartão de crédito"),1,IFERROR(INDEX(Config!$C$12:$C$15,MATCH(IF(AND(D64="Cartão de crédito",N(E64)>1),"Cartão de crédito parcelado",D64),Config!$A$12:$A$15,0)),0))) -> 46224 | L64: =IF(A64="","",MONTH(A64)) -> 7 | M64: =IF(A64="","",YEAR(A64)) -> 2026 | N64: =IF(K64="","",IF(G64="Sim","Conferido",IF(K64>Config!$B$8,"A cair","A conferir"))) -> Conferido | O64: =IF(N64="A conferir",(Config!$B$8-K64)*1000+N(F64)/1000+ROW()/100000,0) -> 0
A65: 46224 | B65: Otávio Nascimento | C65: Consulta | D65: Cartão de crédito | F65: 380 | G65: Sim | H65: =IF(D65="","",IFERROR(INDEX(Config!$B$12:$B$15,MATCH(IF(AND(D65="Cartão de crédito",N(E65)>1),"Cartão de crédito parcelado",D65),Config!$A$12:$A$15,0)),0)+IF(AND(Config!$B$17="Sim",LEFT(D65,17)="Cartão de crédito"),Config!$B$18*IFERROR(INDEX(Config!$C$12:$C$15,MATCH(IF(AND(D65="Cartão de crédito",N(E65)>1),"Cartão de crédito parcelado",D65),Config!$A$12:$A$15,0)),0)/30*MAX(1,N(E65)),0)) -> 0.032 | I65: =IF(OR(D65="",F65=""),"",ROUND(F65*H65,2)) -> 12.16 | J65: =IF(I65="","",F65-I65) -> 367.84 | K65: =IF(OR(D65="",A65=""),"",A65+IF(AND(Config!$B$17="Sim",LEFT(D65,17)="Cartão de crédito"),1,IFERROR(INDEX(Config!$C$12:$C$15,MATCH(IF(AND(D65="Cartão de crédito",N(E65)>1),"Cartão de crédito parcelado",D65),Config!$A$12:$A$15,0)),0))) -> 46254 | L65: =IF(A65="","",MONTH(A65)) -> 7 | M65: =IF(A65="","",YEAR(A65)) -> 2026 | N65: =IF(K65="","",IF(G65="Sim","Conferido",IF(K65>Config!$B$8,"A cair","A conferir"))) -> Conferido | O65: =IF(N65="A conferir",(Config!$B$8-K65)*1000+N(F65)/1000+ROW()/100000,0) -> 0
A66: 46224 | B66: Carlos Freitas | C66: Avaliação endócrina | D66: Pix | F66: 400 | G66: Sim | H66: =IF(D66="","",IFERROR(INDEX(Config!$B$12:$B$15,MATCH(IF(AND(D66="Cartão de crédito",N(E66)>1),"Cartão de crédito parcelado",D66),Config!$A$12:$A$15,0)),0)+IF(AND(Config!$B$17="Sim",LEFT(D66,17)="Cartão de crédito"),Config!$B$18*IFERROR(INDEX(Config!$C$12:$C$15,MATCH(IF(AND(D66="Cartão de crédito",N(E66)>1),"Cartão de crédito parcelado",D66),Config!$A$12:$A$15,0)),0)/30*MAX(1,N(E66)),0)) -> 0 | I66: =IF(OR(D66="",F66=""),"",ROUND(F66*H66,2)) -> 0 | J66: =IF(I66="","",F66-I66) -> 400 | K66: =IF(OR(D66="",A66=""),"",A66+IF(AND(Config!$B$17="Sim",LEFT(D66,17)="Cartão de crédito"),1,IFERROR(INDEX(Config!$C$12:$C$15,MATCH(IF(AND(D66="Cartão de crédito",N(E66)>1),"Cartão de crédito parcelado",D66),Config!$A$12:$A$15,0)),0))) -> 46224 | L66: =IF(A66="","",MONTH(A66)) -> 7 | M66: =IF(A66="","",YEAR(A66)) -> 2026 | N66: =IF(K66="","",IF(G66="Sim","Conferido",IF(K66>Config!$B$8,"A cair","A conferir"))) -> Conferido | O66: =IF(N66="A conferir",(Config!$B$8-K66)*1000+N(F66)/1000+ROW()/100000,0) -> 0
A67: 46224 | B67: Isabela Xavier | C67: Avaliação endócrina | D67: Cartão de crédito | F67: 400 | G67: Sim | H67: =IF(D67="","",IFERROR(INDEX(Config!$B$12:$B$15,MATCH(IF(AND(D67="Cartão de crédito",N(E67)>1),"Cartão de crédito parcelado",D67),Config!$A$12:$A$15,0)),0)+IF(AND(Config!$B$17="Sim",LEFT(D67,17)="Cartão de crédito"),Config!$B$18*IFERROR(INDEX(Config!$C$12:$C$15,MATCH(IF(AND(D67="Cartão de crédito",N(E67)>1),"Cartão de crédito parcelado",D67),Config!$A$12:$A$15,0)),0)/30*MAX(1,N(E67)),0)) -> 0.032 | I67: =IF(OR(D67="",F67=""),"",ROUND(F67*H67,2)) -> 12.8 | J67: =IF(I67="","",F67-I67) -> 387.2 | K67: =IF(OR(D67="",A67=""),"",A67+IF(AND(Config!$B$17="Sim",LEFT(D67,17)="Cartão de crédito"),1,IFERROR(INDEX(Config!$C$12:$C$15,MATCH(IF(AND(D67="Cartão de crédito",N(E67)>1),"Cartão de crédito parcelado",D67),Config!$A$12:$A$15,0)),0))) -> 46254 | L67: =IF(A67="","",MONTH(A67)) -> 7 | M67: =IF(A67="","",YEAR(A67)) -> 2026 | N67: =IF(K67="","",IF(G67="Sim","Conferido",IF(K67>Config!$B$8,"A cair","A conferir"))) -> Conferido | O67: =IF(N67="A conferir",(Config!$B$8-K67)*1000+N(F67)/1000+ROW()/100000,0) -> 0
A68: 46224 | B68: Regina Macedo | C68: ECG | D68: Pix | F68: 130 | G68: Sim | H68: =IF(D68="","",IFERROR(INDEX(Config!$B$12:$B$15,MATCH(IF(AND(D68="Cartão de crédito",N(E68)>1),"Cartão de crédito parcelado",D68),Config!$A$12:$A$15,0)),0)+IF(AND(Config!$B$17="Sim",LEFT(D68,17)="Cartão de crédito"),Config!$B$18*IFERROR(INDEX(Config!$C$12:$C$15,MATCH(IF(AND(D68="Cartão de crédito",N(E68)>1),"Cartão de crédito parcelado",D68),Config!$A$12:$A$15,0)),0)/30*MAX(1,N(E68)),0)) -> 0 | I68: =IF(OR(D68="",F68=""),"",ROUND(F68*H68,2)) -> 0 | J68: =IF(I68="","",F68-I68) -> 130 | K68: =IF(OR(D68="",A68=""),"",A68+IF(AND(Config!$B$17="Sim",LEFT(D68,17)="Cartão de crédito"),1,IFERROR(INDEX(Config!$C$12:$C$15,MATCH(IF(AND(D68="Cartão de crédito",N(E68)>1),"Cartão de crédito parcelado",D68),Config!$A$12:$A$15,0)),0))) -> 46224 | L68: =IF(A68="","",MONTH(A68)) -> 7 | M68: =IF(A68="","",YEAR(A68)) -> 2026 | N68: =IF(K68="","",IF(G68="Sim","Conferido",IF(K68>Config!$B$8,"A cair","A conferir"))) -> Conferido | O68: =IF(N68="A conferir",(Config!$B$8-K68)*1000+N(F68)/1000+ROW()/100000,0) -> 0
A69: 46225 | B69: Ana Costa | C69: Consulta | D69: Pix | F69: 380 | G69: Sim | H69: =IF(D69="","",IFERROR(INDEX(Config!$B$12:$B$15,MATCH(IF(AND(D69="Cartão de crédito",N(E69)>1),"Cartão de crédito parcelado",D69),Config!$A$12:$A$15,0)),0)+IF(AND(Config!$B$17="Sim",LEFT(D69,17)="Cartão de crédito"),Config!$B$18*IFERROR(INDEX(Config!$C$12:$C$15,MATCH(IF(AND(D69="Cartão de crédito",N(E69)>1),"Cartão de crédito parcelado",D69),Config!$A$12:$A$15,0)),0)/30*MAX(1,N(E69)),0)) -> 0 | I69: =IF(OR(D69="",F69=""),"",ROUND(F69*H69,2)) -> 0 | J69: =IF(I69="","",F69-I69) -> 380 | K69: =IF(OR(D69="",A69=""),"",A69+IF(AND(Config!$B$17="Sim",LEFT(D69,17)="Cartão de crédito"),1,IFERROR(INDEX(Config!$C$12:$C$15,MATCH(IF(AND(D69="Cartão de crédito",N(E69)>1),"Cartão de crédito parcelado",D69),Config!$A$12:$A$15,0)),0))) -> 46225 | L69: =IF(A69="","",MONTH(A69)) -> 7 | M69: =IF(A69="","",YEAR(A69)) -> 2026 | N69: =IF(K69="","",IF(G69="Sim","Conferido",IF(K69>Config!$B$8,"A cair","A conferir"))) -> Conferido | O69: =IF(N69="A conferir",(Config!$B$8-K69)*1000+N(F69)/1000+ROW()/100000,0) -> 0
A70: 46225 | B70: Rodrigo Moreira | C70: Consulta | D70: Pix | F70: 380 | G70: Sim | H70: =IF(D70="","",IFERROR(INDEX(Config!$B$12:$B$15,MATCH(IF(AND(D70="Cartão de crédito",N(E70)>1),"Cartão de crédito parcelado",D70),Config!$A$12:$A$15,0)),0)+IF(AND(Config!$B$17="Sim",LEFT(D70,17)="Cartão de crédito"),Config!$B$18*IFERROR(INDEX(Config!$C$12:$C$15,MATCH(IF(AND(D70="Cartão de crédito",N(E70)>1),"Cartão de crédito parcelado",D70),Config!$A$12:$A$15,0)),0)/30*MAX(1,N(E70)),0)) -> 0 | I70: =IF(OR(D70="",F70=""),"",ROUND(F70*H70,2)) -> 0 | J70: =IF(I70="","",F70-I70) -> 380 | K70: =IF(OR(D70="",A70=""),"",A70+IF(AND(Config!$B$17="Sim",LEFT(D70,17)="Cartão de crédito"),1,IFERROR(INDEX(Config!$C$12:$C$15,MATCH(IF(AND(D70="Cartão de crédito",N(E70)>1),"Cartão de crédito parcelado",D70),Config!$A$12:$A$15,0)),0))) -> 46225 | L70: =IF(A70="","",MONTH(A70)) -> 7 | M70: =IF(A70="","",YEAR(A70)) -> 2026 | N70: =IF(K70="","",IF(G70="Sim","Conferido",IF(K70>Config!$B$8,"A cair","A conferir"))) -> Conferido | O70: =IF(N70="A conferir",(Config!$B$8-K70)*1000+N(F70)/1000+ROW()/100000,0) -> 0
A71: 46225 | B71: Roberta Araújo | C71: Consulta | D71: Pix | F71: 380 | G71: Sim | H71: =IF(D71="","",IFERROR(INDEX(Config!$B$12:$B$15,MATCH(IF(AND(D71="Cartão de crédito",N(E71)>1),"Cartão de crédito parcelado",D71),Config!$A$12:$A$15,0)),0)+IF(AND(Config!$B$17="Sim",LEFT(D71,17)="Cartão de crédito"),Config!$B$18*IFERROR(INDEX(Config!$C$12:$C$15,MATCH(IF(AND(D71="Cartão de crédito",N(E71)>1),"Cartão de crédito parcelado",D71),Config!$A$12:$A$15,0)),0)/30*MAX(1,N(E71)),0)) -> 0 | I71: =IF(OR(D71="",F71=""),"",ROUND(F71*H71,2)) -> 0 | J71: =IF(I71="","",F71-I71) -> 380 | K71: =IF(OR(D71="",A71=""),"",A71+IF(AND(Config!$B$17="Sim",LEFT(D71,17)="Cartão de crédito"),1,IFERROR(INDEX(Config!$C$12:$C$15,MATCH(IF(AND(D71="Cartão de crédito",N(E71)>1),"Cartão de crédito parcelado",D71),Config!$A$12:$A$15,0)),0))) -> 46225 | L71: =IF(A71="","",MONTH(A71)) -> 7 | M71: =IF(A71="","",YEAR(A71)) -> 2026 | N71: =IF(K71="","",IF(G71="Sim","Conferido",IF(K71>Config!$B$8,"A cair","A conferir"))) -> Conferido | O71: =IF(N71="A conferir",(Config!$B$8-K71)*1000+N(F71)/1000+ROW()/100000,0) -> 0
A72: 46225 | B72: Marcelo Santos | C72: Consulta | D72: Cartão de crédito | F72: 380 | G72: Sim | H72: =IF(D72="","",IFERROR(INDEX(Config!$B$12:$B$15,MATCH(IF(AND(D72="Cartão de crédito",N(E72)>1),"Cartão de crédito parcelado",D72),Config!$A$12:$A$15,0)),0)+IF(AND(Config!$B$17="Sim",LEFT(D72,17)="Cartão de crédito"),Config!$B$18*IFERROR(INDEX(Config!$C$12:$C$15,MATCH(IF(AND(D72="Cartão de crédito",N(E72)>1),"Cartão de crédito parcelado",D72),Config!$A$12:$A$15,0)),0)/30*MAX(1,N(E72)),0)) -> 0.032 | I72: =IF(OR(D72="",F72=""),"",ROUND(F72*H72,2)) -> 12.16 | J72: =IF(I72="","",F72-I72) -> 367.84 | K72: =IF(OR(D72="",A72=""),"",A72+IF(AND(Config!$B$17="Sim",LEFT(D72,17)="Cartão de crédito"),1,IFERROR(INDEX(Config!$C$12:$C$15,MATCH(IF(AND(D72="Cartão de crédito",N(E72)>1),"Cartão de crédito parcelado",D72),Config!$A$12:$A$15,0)),0))) -> 46255 | L72: =IF(A72="","",MONTH(A72)) -> 7 | M72: =IF(A72="","",YEAR(A72)) -> 2026 | N72: =IF(K72="","",IF(G72="Sim","Conferido",IF(K72>Config!$B$8,"A cair","A conferir"))) -> Conferido | O72: =IF(N72="A conferir",(Config!$B$8-K72)*1000+N(F72)/1000+ROW()/100000,0) -> 0
A73: 46225 | B73: Mônica Martins | C73: Consulta | D73: Cartão de crédito | F73: 380 | G73: Sim | H73: =IF(D73="","",IFERROR(INDEX(Config!$B$12:$B$15,MATCH(IF(AND(D73="Cartão de crédito",N(E73)>1),"Cartão de crédito parcelado",D73),Config!$A$12:$A$15,0)),0)+IF(AND(Config!$B$17="Sim",LEFT(D73,17)="Cartão de crédito"),Config!$B$18*IFERROR(INDEX(Config!$C$12:$C$15,MATCH(IF(AND(D73="Cartão de crédito",N(E73)>1),"Cartão de crédito parcelado",D73),Config!$A$12:$A$15,0)),0)/30*MAX(1,N(E73)),0)) -> 0.032 | I73: =IF(OR(D73="",F73=""),"",ROUND(F73*H73,2)) -> 12.16 | J73: =IF(I73="","",F73-I73) -> 367.84 | K73: =IF(OR(D73="",A73=""),"",A73+IF(AND(Config!$B$17="Sim",LEFT(D73,17)="Cartão de crédito"),1,IFERROR(INDEX(Config!$C$12:$C$15,MATCH(IF(AND(D73="Cartão de crédito",N(E73)>1),"Cartão de crédito parcelado",D73),Config!$A$12:$A$15,0)),0))) -> 46255 | L73: =IF(A73="","",MONTH(A73)) -> 7 | M73: =IF(A73="","",YEAR(A73)) -> 2026 | N73: =IF(K73="","",IF(G73="Sim","Conferido",IF(K73>Config!$B$8,"A cair","A conferir"))) -> Conferido | O73: =IF(N73="A conferir",(Config!$B$8-K73)*1000+N(F73)/1000+ROW()/100000,0) -> 0
A74: 46225 | B74: Débora Ramos | C74: Consulta | D74: Pix | F74: 380 | G74: Sim | H74: =IF(D74="","",IFERROR(INDEX(Config!$B$12:$B$15,MATCH(IF(AND(D74="Cartão de crédito",N(E74)>1),"Cartão de crédito parcelado",D74),Config!$A$12:$A$15,0)),0)+IF(AND(Config!$B$17="Sim",LEFT(D74,17)="Cartão de crédito"),Config!$B$18*IFERROR(INDEX(Config!$C$12:$C$15,MATCH(IF(AND(D74="Cartão de crédito",N(E74)>1),"Cartão de crédito parcelado",D74),Config!$A$12:$A$15,0)),0)/30*MAX(1,N(E74)),0)) -> 0 | I74: =IF(OR(D74="",F74=""),"",ROUND(F74*H74,2)) -> 0 | J74: =IF(I74="","",F74-I74) -> 380 | K74: =IF(OR(D74="",A74=""),"",A74+IF(AND(Config!$B$17="Sim",LEFT(D74,17)="Cartão de crédito"),1,IFERROR(INDEX(Config!$C$12:$C$15,MATCH(IF(AND(D74="Cartão de crédito",N(E74)>1),"Cartão de crédito parcelado",D74),Config!$A$12:$A$15,0)),0))) -> 46225 | L74: =IF(A74="","",MONTH(A74)) -> 7 | M74: =IF(A74="","",YEAR(A74)) -> 2026 | N74: =IF(K74="","",IF(G74="Sim","Conferido",IF(K74>Config!$B$8,"A cair","A conferir"))) -> Conferido | O74: =IF(N74="A conferir",(Config!$B$8-K74)*1000+N(F74)/1000+ROW()/100000,0) -> 0
A75: 46226 | B75: Mariana Nascimento | C75: Consulta | D75: Cartão de débito | F75: 380 | G75: Sim | H75: =IF(D75="","",IFERROR(INDEX(Config!$B$12:$B$15,MATCH(IF(AND(D75="Cartão de crédito",N(E75)>1),"Cartão de crédito parcelado",D75),Config!$A$12:$A$15,0)),0)+IF(AND(Config!$B$17="Sim",LEFT(D75,17)="Cartão de crédito"),Config!$B$18*IFERROR(INDEX(Config!$C$12:$C$15,MATCH(IF(AND(D75="Cartão de crédito",N(E75)>1),"Cartão de crédito parcelado",D75),Config!$A$12:$A$15,0)),0)/30*MAX(1,N(E75)),0)) -> 0.015 | I75: =IF(OR(D75="",F75=""),"",ROUND(F75*H75,2)) -> 5.7 | J75: =IF(I75="","",F75-I75) -> 374.3 | K75: =IF(OR(D75="",A75=""),"",A75+IF(AND(Config!$B$17="Sim",LEFT(D75,17)="Cartão de crédito"),1,IFERROR(INDEX(Config!$C$12:$C$15,MATCH(IF(AND(D75="Cartão de crédito",N(E75)>1),"Cartão de crédito parcelado",D75),Config!$A$12:$A$15,0)),0))) -> 46227 | L75: =IF(A75="","",MONTH(A75)) -> 7 | M75: =IF(A75="","",YEAR(A75)) -> 2026 | N75: =IF(K75="","",IF(G75="Sim","Conferido",IF(K75>Config!$B$8,"A cair","A conferir"))) -> Conferido | O75: =IF(N75="A conferir",(Config!$B$8-K75)*1000+N(F75)/1000+ROW()/100000,0) -> 0
A76: 46226 | B76: Elaine Cardoso | C76: Consulta | D76: Pix | F76: 380 | G76: Sim | H76: =IF(D76="","",IFERROR(INDEX(Config!$B$12:$B$15,MATCH(IF(AND(D76="Cartão de crédito",N(E76)>1),"Cartão de crédito parcelado",D76),Config!$A$12:$A$15,0)),0)+IF(AND(Config!$B$17="Sim",LEFT(D76,17)="Cartão de crédito"),Config!$B$18*IFERROR(INDEX(Config!$C$12:$C$15,MATCH(IF(AND(D76="Cartão de crédito",N(E76)>1),"Cartão de crédito parcelado",D76),Config!$A$12:$A$15,0)),0)/30*MAX(1,N(E76)),0)) -> 0 | I76: =IF(OR(D76="",F76=""),"",ROUND(F76*H76,2)) -> 0 | J76: =IF(I76="","",F76-I76) -> 380 | K76: =IF(OR(D76="",A76=""),"",A76+IF(AND(Config!$B$17="Sim",LEFT(D76,17)="Cartão de crédito"),1,IFERROR(INDEX(Config!$C$12:$C$15,MATCH(IF(AND(D76="Cartão de crédito",N(E76)>1),"Cartão de crédito parcelado",D76),Config!$A$12:$A$15,0)),0))) -> 46226 | L76: =IF(A76="","",MONTH(A76)) -> 7 | M76: =IF(A76="","",YEAR(A76)) -> 2026 | N76: =IF(K76="","",IF(G76="Sim","Conferido",IF(K76>Config!$B$8,"A cair","A conferir"))) -> Conferido | O76: =IF(N76="A conferir",(Config!$B$8-K76)*1000+N(F76)/1000+ROW()/100000,0) -> 0
A77: 46226 | B77: Otávio Cardoso | C77: Consulta | D77: Cartão de crédito | E77: 2 | F77: 380 | G77: Sim | H77: =IF(D77="","",IFERROR(INDEX(Config!$B$12:$B$15,MATCH(IF(AND(D77="Cartão de crédito",N(E77)>1),"Cartão de crédito parcelado",D77),Config!$A$12:$A$15,0)),0)+IF(AND(Config!$B$17="Sim",LEFT(D77,17)="Cartão de crédito"),Config!$B$18*IFERROR(INDEX(Config!$C$12:$C$15,MATCH(IF(AND(D77="Cartão de crédito",N(E77)>1),"Cartão de crédito parcelado",D77),Config!$A$12:$A$15,0)),0)/30*MAX(1,N(E77)),0)) -> 0.039 | I77: =IF(OR(D77="",F77=""),"",ROUND(F77*H77,2)) -> 14.82 | J77: =IF(I77="","",F77-I77) -> 365.18 | K77: =IF(OR(D77="",A77=""),"",A77+IF(AND(Config!$B$17="Sim",LEFT(D77,17)="Cartão de crédito"),1,IFERROR(INDEX(Config!$C$12:$C$15,MATCH(IF(AND(D77="Cartão de crédito",N(E77)>1),"Cartão de crédito parcelado",D77),Config!$A$12:$A$15,0)),0))) -> 46256 | L77: =IF(A77="","",MONTH(A77)) -> 7 | M77: =IF(A77="","",YEAR(A77)) -> 2026 | N77: =IF(K77="","",IF(G77="Sim","Conferido",IF(K77>Config!$B$8,"A cair","A conferir"))) -> Conferido | O77: =IF(N77="A conferir",(Config!$B$8-K77)*1000+N(F77)/1000+ROW()/100000,0) -> 0
A78: 46226 | B78: Helena Moreira | C78: Consulta | D78: Cartão de crédito | F78: 380 | G78: Sim | H78: =IF(D78="","",IFERROR(INDEX(Config!$B$12:$B$15,MATCH(IF(AND(D78="Cartão de crédito",N(E78)>1),"Cartão de crédito parcelado",D78),Config!$A$12:$A$15,0)),0)+IF(AND(Config!$B$17="Sim",LEFT(D78,17)="Cartão de crédito"),Config!$B$18*IFERROR(INDEX(Config!$C$12:$C$15,MATCH(IF(AND(D78="Cartão de crédito",N(E78)>1),"Cartão de crédito parcelado",D78),Config!$A$12:$A$15,0)),0)/30*MAX(1,N(E78)),0)) -> 0.032 | I78: =IF(OR(D78="",F78=""),"",ROUND(F78*H78,2)) -> 12.16 | J78: =IF(I78="","",F78-I78) -> 367.84 | K78: =IF(OR(D78="",A78=""),"",A78+IF(AND(Config!$B$17="Sim",LEFT(D78,17)="Cartão de crédito"),1,IFERROR(INDEX(Config!$C$12:$C$15,MATCH(IF(AND(D78="Cartão de crédito",N(E78)>1),"Cartão de crédito parcelado",D78),Config!$A$12:$A$15,0)),0))) -> 46256 | L78: =IF(A78="","",MONTH(A78)) -> 7 | M78: =IF(A78="","",YEAR(A78)) -> 2026 | N78: =IF(K78="","",IF(G78="Sim","Conferido",IF(K78>Config!$B$8,"A cair","A conferir"))) -> Conferido | O78: =IF(N78="A conferir",(Config!$B$8-K78)*1000+N(F78)/1000+ROW()/100000,0) -> 0
A79: 46226 | B79: Mariana Reis | C79: Avaliação endócrina | D79: Pix | F79: 400 | G79: Sim | H79: =IF(D79="","",IFERROR(INDEX(Config!$B$12:$B$15,MATCH(IF(AND(D79="Cartão de crédito",N(E79)>1),"Cartão de crédito parcelado",D79),Config!$A$12:$A$15,0)),0)+IF(AND(Config!$B$17="Sim",LEFT(D79,17)="Cartão de crédito"),Config!$B$18*IFERROR(INDEX(Config!$C$12:$C$15,MATCH(IF(AND(D79="Cartão de crédito",N(E79)>1),"Cartão de crédito parcelado",D79),Config!$A$12:$A$15,0)),0)/30*MAX(1,N(E79)),0)) -> 0 | I79: =IF(OR(D79="",F79=""),"",ROUND(F79*H79,2)) -> 0 | J79: =IF(I79="","",F79-I79) -> 400 | K79: =IF(OR(D79="",A79=""),"",A79+IF(AND(Config!$B$17="Sim",LEFT(D79,17)="Cartão de crédito"),1,IFERROR(INDEX(Config!$C$12:$C$15,MATCH(IF(AND(D79="Cartão de crédito",N(E79)>1),"Cartão de crédito parcelado",D79),Config!$A$12:$A$15,0)),0))) -> 46226 | L79: =IF(A79="","",MONTH(A79)) -> 7 | M79: =IF(A79="","",YEAR(A79)) -> 2026 | N79: =IF(K79="","",IF(G79="Sim","Conferido",IF(K79>Config!$B$8,"A cair","A conferir"))) -> Conferido | O79: =IF(N79="A conferir",(Config!$B$8-K79)*1000+N(F79)/1000+ROW()/100000,0) -> 0
A80: 46226 | B80: Paulo Reis | C80: Consulta | D80: Cartão de crédito | F80: 380 | G80: Sim | H80: =IF(D80="","",IFERROR(INDEX(Config!$B$12:$B$15,MATCH(IF(AND(D80="Cartão de crédito",N(E80)>1),"Cartão de crédito parcelado",D80),Config!$A$12:$A$15,0)),0)+IF(AND(Config!$B$17="Sim",LEFT(D80,17)="Cartão de crédito"),Config!$B$18*IFERROR(INDEX(Config!$C$12:$C$15,MATCH(IF(AND(D80="Cartão de crédito",N(E80)>1),"Cartão de crédito parcelado",D80),Config!$A$12:$A$15,0)),0)/30*MAX(1,N(E80)),0)) -> 0.032 | I80: =IF(OR(D80="",F80=""),"",ROUND(F80*H80,2)) -> 12.16 | J80: =IF(I80="","",F80-I80) -> 367.84 | K80: =IF(OR(D80="",A80=""),"",A80+IF(AND(Config!$B$17="Sim",LEFT(D80,17)="Cartão de crédito"),1,IFERROR(INDEX(Config!$C$12:$C$15,MATCH(IF(AND(D80="Cartão de crédito",N(E80)>1),"Cartão de crédito parcelado",D80),Config!$A$12:$A$15,0)),0))) -> 46256 | L80: =IF(A80="","",MONTH(A80)) -> 7 | M80: =IF(A80="","",YEAR(A80)) -> 2026 | N80: =IF(K80="","",IF(G80="Sim","Conferido",IF(K80>Config!$B$8,"A cair","A conferir"))) -> Conferido | O80: =IF(N80="A conferir",(Config!$B$8-K80)*1000+N(F80)/1000+ROW()/100000,0) -> 0
A81: 46226 | B81: Priscila Reis | C81: Avaliação endócrina | D81: Cartão de crédito | E81: 2 | F81: 400 | G81: Sim | H81: =IF(D81="","",IFERROR(INDEX(Config!$B$12:$B$15,MATCH(IF(AND(D81="Cartão de crédito",N(E81)>1),"Cartão de crédito parcelado",D81),Config!$A$12:$A$15,0)),0)+IF(AND(Config!$B$17="Sim",LEFT(D81,17)="Cartão de crédito"),Config!$B$18*IFERROR(INDEX(Config!$C$12:$C$15,MATCH(IF(AND(D81="Cartão de crédito",N(E81)>1),"Cartão de crédito parcelado",D81),Config!$A$12:$A$15,0)),0)/30*MAX(1,N(E81)),0)) -> 0.039 | I81: =IF(OR(D81="",F81=""),"",ROUND(F81*H81,2)) -> 15.6 | J81: =IF(I81="","",F81-I81) -> 384.4 | K81: =IF(OR(D81="",A81=""),"",A81+IF(AND(Config!$B$17="Sim",LEFT(D81,17)="Cartão de crédito"),1,IFERROR(INDEX(Config!$C$12:$C$15,MATCH(IF(AND(D81="Cartão de crédito",N(E81)>1),"Cartão de crédito parcelado",D81),Config!$A$12:$A$15,0)),0))) -> 46256 | L81: =IF(A81="","",MONTH(A81)) -> 7 | M81: =IF(A81="","",YEAR(A81)) -> 2026 | N81: =IF(K81="","",IF(G81="Sim","Conferido",IF(K81>Config!$B$8,"A cair","A conferir"))) -> Conferido | O81: =IF(N81="A conferir",(Config!$B$8-K81)*1000+N(F81)/1000+ROW()/100000,0) -> 0
A82: 46227 | B82: Ana Costa | C82: ECG | D82: Pix | F82: 130 | G82: Sim | H82: =IF(D82="","",IFERROR(INDEX(Config!$B$12:$B$15,MATCH(IF(AND(D82="Cartão de crédito",N(E82)>1),"Cartão de crédito parcelado",D82),Config!$A$12:$A$15,0)),0)+IF(AND(Config!$B$17="Sim",LEFT(D82,17)="Cartão de crédito"),Config!$B$18*IFERROR(INDEX(Config!$C$12:$C$15,MATCH(IF(AND(D82="Cartão de crédito",N(E82)>1),"Cartão de crédito parcelado",D82),Config!$A$12:$A$15,0)),0)/30*MAX(1,N(E82)),0)) -> 0 | I82: =IF(OR(D82="",F82=""),"",ROUND(F82*H82,2)) -> 0 | J82: =IF(I82="","",F82-I82) -> 130 | K82: =IF(OR(D82="",A82=""),"",A82+IF(AND(Config!$B$17="Sim",LEFT(D82,17)="Cartão de crédito"),1,IFERROR(INDEX(Config!$C$12:$C$15,MATCH(IF(AND(D82="Cartão de crédito",N(E82)>1),"Cartão de crédito parcelado",D82),Config!$A$12:$A$15,0)),0))) -> 46227 | L82: =IF(A82="","",MONTH(A82)) -> 7 | M82: =IF(A82="","",YEAR(A82)) -> 2026 | N82: =IF(K82="","",IF(G82="Sim","Conferido",IF(K82>Config!$B$8,"A cair","A conferir"))) -> Conferido | O82: =IF(N82="A conferir",(Config!$B$8-K82)*1000+N(F82)/1000+ROW()/100000,0) -> 0
A83: 46230 | B83: Eduardo Lima | C83: Consulta | D83: Cartão de crédito | F83: 380 | G83: Sim | H83: =IF(D83="","",IFERROR(INDEX(Config!$B$12:$B$15,MATCH(IF(AND(D83="Cartão de crédito",N(E83)>1),"Cartão de crédito parcelado",D83),Config!$A$12:$A$15,0)),0)+IF(AND(Config!$B$17="Sim",LEFT(D83,17)="Cartão de crédito"),Config!$B$18*IFERROR(INDEX(Config!$C$12:$C$15,MATCH(IF(AND(D83="Cartão de crédito",N(E83)>1),"Cartão de crédito parcelado",D83),Config!$A$12:$A$15,0)),0)/30*MAX(1,N(E83)),0)) -> 0.032 | I83: =IF(OR(D83="",F83=""),"",ROUND(F83*H83,2)) -> 12.16 | J83: =IF(I83="","",F83-I83) -> 367.84 | K83: =IF(OR(D83="",A83=""),"",A83+IF(AND(Config!$B$17="Sim",LEFT(D83,17)="Cartão de crédito"),1,IFERROR(INDEX(Config!$C$12:$C$15,MATCH(IF(AND(D83="Cartão de crédito",N(E83)>1),"Cartão de crédito parcelado",D83),Config!$A$12:$A$15,0)),0))) -> 46260 | L83: =IF(A83="","",MONTH(A83)) -> 7 | M83: =IF(A83="","",YEAR(A83)) -> 2026 | N83: =IF(K83="","",IF(G83="Sim","Conferido",IF(K83>Config!$B$8,"A cair","A conferir"))) -> Conferido | O83: =IF(N83="A conferir",(Config!$B$8-K83)*1000+N(F83)/1000+ROW()/100000,0) -> 0
A84: 46230 | B84: Débora Moreira | C84: Consulta | D84: Pix | F84: 380 | G84: Sim | H84: =IF(D84="","",IFERROR(INDEX(Config!$B$12:$B$15,MATCH(IF(AND(D84="Cartão de crédito",N(E84)>1),"Cartão de crédito parcelado",D84),Config!$A$12:$A$15,0)),0)+IF(AND(Config!$B$17="Sim",LEFT(D84,17)="Cartão de crédito"),Config!$B$18*IFERROR(INDEX(Config!$C$12:$C$15,MATCH(IF(AND(D84="Cartão de crédito",N(E84)>1),"Cartão de crédito parcelado",D84),Config!$A$12:$A$15,0)),0)/30*MAX(1,N(E84)),0)) -> 0 | I84: =IF(OR(D84="",F84=""),"",ROUND(F84*H84,2)) -> 0 | J84: =IF(I84="","",F84-I84) -> 380 | K84: =IF(OR(D84="",A84=""),"",A84+IF(AND(Config!$B$17="Sim",LEFT(D84,17)="Cartão de crédito"),1,IFERROR(INDEX(Config!$C$12:$C$15,MATCH(IF(AND(D84="Cartão de crédito",N(E84)>1),"Cartão de crédito parcelado",D84),Config!$A$12:$A$15,0)),0))) -> 46230 | L84: =IF(A84="","",MONTH(A84)) -> 7 | M84: =IF(A84="","",YEAR(A84)) -> 2026 | N84: =IF(K84="","",IF(G84="Sim","Conferido",IF(K84>Config!$B$8,"A cair","A conferir"))) -> Conferido | O84: =IF(N84="A conferir",(Config!$B$8-K84)*1000+N(F84)/1000+ROW()/100000,0) -> 0
A85: 46231 | B85: Gisele Ribeiro | C85: Consulta | D85: Cartão de débito | F85: 380 | G85: Sim | H85: =IF(D85="","",IFERROR(INDEX(Config!$B$12:$B$15,MATCH(IF(AND(D85="Cartão de crédito",N(E85)>1),"Cartão de crédito parcelado",D85),Config!$A$12:$A$15,0)),0)+IF(AND(Config!$B$17="Sim",LEFT(D85,17)="Cartão de crédito"),Config!$B$18*IFERROR(INDEX(Config!$C$12:$C$15,MATCH(IF(AND(D85="Cartão de crédito",N(E85)>1),"Cartão de crédito parcelado",D85),Config!$A$12:$A$15,0)),0)/30*MAX(1,N(E85)),0)) -> 0.015 | I85: =IF(OR(D85="",F85=""),"",ROUND(F85*H85,2)) -> 5.7 | J85: =IF(I85="","",F85-I85) -> 374.3 | K85: =IF(OR(D85="",A85=""),"",A85+IF(AND(Config!$B$17="Sim",LEFT(D85,17)="Cartão de crédito"),1,IFERROR(INDEX(Config!$C$12:$C$15,MATCH(IF(AND(D85="Cartão de crédito",N(E85)>1),"Cartão de crédito parcelado",D85),Config!$A$12:$A$15,0)),0))) -> 46232 | L85: =IF(A85="","",MONTH(A85)) -> 7 | M85: =IF(A85="","",YEAR(A85)) -> 2026 | N85: =IF(K85="","",IF(G85="Sim","Conferido",IF(K85>Config!$B$8,"A cair","A conferir"))) -> Conferido | O85: =IF(N85="A conferir",(Config!$B$8-K85)*1000+N(F85)/1000+ROW()/100000,0) -> 0
A86: 46231 | B86: Wagner Santos | C86: Consulta | D86: Cartão de crédito | F86: 380 | G86: Sim | H86: =IF(D86="","",IFERROR(INDEX(Config!$B$12:$B$15,MATCH(IF(AND(D86="Cartão de crédito",N(E86)>1),"Cartão de crédito parcelado",D86),Config!$A$12:$A$15,0)),0)+IF(AND(Config!$B$17="Sim",LEFT(D86,17)="Cartão de crédito"),Config!$B$18*IFERROR(INDEX(Config!$C$12:$C$15,MATCH(IF(AND(D86="Cartão de crédito",N(E86)>1),"Cartão de crédito parcelado",D86),Config!$A$12:$A$15,0)),0)/30*MAX(1,N(E86)),0)) -> 0.032 | I86: =IF(OR(D86="",F86=""),"",ROUND(F86*H86,2)) -> 12.16 | J86: =IF(I86="","",F86-I86) -> 367.84 | K86: =IF(OR(D86="",A86=""),"",A86+IF(AND(Config!$B$17="Sim",LEFT(D86,17)="Cartão de crédito"),1,IFERROR(INDEX(Config!$C$12:$C$15,MATCH(IF(AND(D86="Cartão de crédito",N(E86)>1),"Cartão de crédito parcelado",D86),Config!$A$12:$A$15,0)),0))) -> 46261 | L86: =IF(A86="","",MONTH(A86)) -> 7 | M86: =IF(A86="","",YEAR(A86)) -> 2026 | N86: =IF(K86="","",IF(G86="Sim","Conferido",IF(K86>Config!$B$8,"A cair","A conferir"))) -> Conferido | O86: =IF(N86="A conferir",(Config!$B$8-K86)*1000+N(F86)/1000+ROW()/100000,0) -> 0
A87: 46231 | B87: Carlos Freitas | C87: Avaliação endócrina | D87: Cartão de crédito | E87: 2 | F87: 400 | G87: Sim | H87: =IF(D87="","",IFERROR(INDEX(Config!$B$12:$B$15,MATCH(IF(AND(D87="Cartão de crédito",N(E87)>1),"Cartão de crédito parcelado",D87),Config!$A$12:$A$15,0)),0)+IF(AND(Config!$B$17="Sim",LEFT(D87,17)="Cartão de crédito"),Config!$B$18*IFERROR(INDEX(Config!$C$12:$C$15,MATCH(IF(AND(D87="Cartão de crédito",N(E87)>1),"Cartão de crédito parcelado",D87),Config!$A$12:$A$15,0)),0)/30*MAX(1,N(E87)),0)) -> 0.039 | I87: =IF(OR(D87="",F87=""),"",ROUND(F87*H87,2)) -> 15.6 | J87: =IF(I87="","",F87-I87) -> 384.4 | K87: =IF(OR(D87="",A87=""),"",A87+IF(AND(Config!$B$17="Sim",LEFT(D87,17)="Cartão de crédito"),1,IFERROR(INDEX(Config!$C$12:$C$15,MATCH(IF(AND(D87="Cartão de crédito",N(E87)>1),"Cartão de crédito parcelado",D87),Config!$A$12:$A$15,0)),0))) -> 46261 | L87: =IF(A87="","",MONTH(A87)) -> 7 | M87: =IF(A87="","",YEAR(A87)) -> 2026 | N87: =IF(K87="","",IF(G87="Sim","Conferido",IF(K87>Config!$B$8,"A cair","A conferir"))) -> Conferido | O87: =IF(N87="A conferir",(Config!$B$8-K87)*1000+N(F87)/1000+ROW()/100000,0) -> 0
A88: 46231 | B88: Cláudia Melo | C88: Avaliação endócrina | D88: Pix | F88: 400 | G88: Sim | H88: =IF(D88="","",IFERROR(INDEX(Config!$B$12:$B$15,MATCH(IF(AND(D88="Cartão de crédito",N(E88)>1),"Cartão de crédito parcelado",D88),Config!$A$12:$A$15,0)),0)+IF(AND(Config!$B$17="Sim",LEFT(D88,17)="Cartão de crédito"),Config!$B$18*IFERROR(INDEX(Config!$C$12:$C$15,MATCH(IF(AND(D88="Cartão de crédito",N(E88)>1),"Cartão de crédito parcelado",D88),Config!$A$12:$A$15,0)),0)/30*MAX(1,N(E88)),0)) -> 0 | I88: =IF(OR(D88="",F88=""),"",ROUND(F88*H88,2)) -> 0 | J88: =IF(I88="","",F88-I88) -> 400 | K88: =IF(OR(D88="",A88=""),"",A88+IF(AND(Config!$B$17="Sim",LEFT(D88,17)="Cartão de crédito"),1,IFERROR(INDEX(Config!$C$12:$C$15,MATCH(IF(AND(D88="Cartão de crédito",N(E88)>1),"Cartão de crédito parcelado",D88),Config!$A$12:$A$15,0)),0))) -> 46231 | L88: =IF(A88="","",MONTH(A88)) -> 7 | M88: =IF(A88="","",YEAR(A88)) -> 2026 | N88: =IF(K88="","",IF(G88="Sim","Conferido",IF(K88>Config!$B$8,"A cair","A conferir"))) -> Conferido | O88: =IF(N88="A conferir",(Config!$B$8-K88)*1000+N(F88)/1000+ROW()/100000,0) -> 0
A89: 46231 | B89: Marcelo Ferreira | C89: Consulta | D89: Cartão de débito | F89: 380 | G89: Sim | H89: =IF(D89="","",IFERROR(INDEX(Config!$B$12:$B$15,MATCH(IF(AND(D89="Cartão de crédito",N(E89)>1),"Cartão de crédito parcelado",D89),Config!$A$12:$A$15,0)),0)+IF(AND(Config!$B$17="Sim",LEFT(D89,17)="Cartão de crédito"),Config!$B$18*IFERROR(INDEX(Config!$C$12:$C$15,MATCH(IF(AND(D89="Cartão de crédito",N(E89)>1),"Cartão de crédito parcelado",D89),Config!$A$12:$A$15,0)),0)/30*MAX(1,N(E89)),0)) -> 0.015 | I89: =IF(OR(D89="",F89=""),"",ROUND(F89*H89,2)) -> 5.7 | J89: =IF(I89="","",F89-I89) -> 374.3 | K89: =IF(OR(D89="",A89=""),"",A89+IF(AND(Config!$B$17="Sim",LEFT(D89,17)="Cartão de crédito"),1,IFERROR(INDEX(Config!$C$12:$C$15,MATCH(IF(AND(D89="Cartão de crédito",N(E89)>1),"Cartão de crédito parcelado",D89),Config!$A$12:$A$15,0)),0))) -> 46232 | L89: =IF(A89="","",MONTH(A89)) -> 7 | M89: =IF(A89="","",YEAR(A89)) -> 2026 | N89: =IF(K89="","",IF(G89="Sim","Conferido",IF(K89>Config!$B$8,"A cair","A conferir"))) -> Conferido | O89: =IF(N89="A conferir",(Config!$B$8-K89)*1000+N(F89)/1000+ROW()/100000,0) -> 0
A90: 46231 | B90: Fernanda Freitas | C90: Teste ergométrico | D90: Cartão de crédito | F90: 450 | G90: Sim | H90: =IF(D90="","",IFERROR(INDEX(Config!$B$12:$B$15,MATCH(IF(AND(D90="Cartão de crédito",N(E90)>1),"Cartão de crédito parcelado",D90),Config!$A$12:$A$15,0)),0)+IF(AND(Config!$B$17="Sim",LEFT(D90,17)="Cartão de crédito"),Config!$B$18*IFERROR(INDEX(Config!$C$12:$C$15,MATCH(IF(AND(D90="Cartão de crédito",N(E90)>1),"Cartão de crédito parcelado",D90),Config!$A$12:$A$15,0)),0)/30*MAX(1,N(E90)),0)) -> 0.032 | I90: =IF(OR(D90="",F90=""),"",ROUND(F90*H90,2)) -> 14.4 | J90: =IF(I90="","",F90-I90) -> 435.6 | K90: =IF(OR(D90="",A90=""),"",A90+IF(AND(Config!$B$17="Sim",LEFT(D90,17)="Cartão de crédito"),1,IFERROR(INDEX(Config!$C$12:$C$15,MATCH(IF(AND(D90="Cartão de crédito",N(E90)>1),"Cartão de crédito parcelado",D90),Config!$A$12:$A$15,0)),0))) -> 46261 | L90: =IF(A90="","",MONTH(A90)) -> 7 | M90: =IF(A90="","",YEAR(A90)) -> 2026 | N90: =IF(K90="","",IF(G90="Sim","Conferido",IF(K90>Config!$B$8,"A cair","A conferir"))) -> Conferido | O90: =IF(N90="A conferir",(Config!$B$8-K90)*1000+N(F90)/1000+ROW()/100000,0) -> 0
A91: 46232 | B91: Gisele Xavier | C91: Consulta | D91: Pix | F91: 380 | G91: Sim | H91: =IF(D91="","",IFERROR(INDEX(Config!$B$12:$B$15,MATCH(IF(AND(D91="Cartão de crédito",N(E91)>1),"Cartão de crédito parcelado",D91),Config!$A$12:$A$15,0)),0)+IF(AND(Config!$B$17="Sim",LEFT(D91,17)="Cartão de crédito"),Config!$B$18*IFERROR(INDEX(Config!$C$12:$C$15,MATCH(IF(AND(D91="Cartão de crédito",N(E91)>1),"Cartão de crédito parcelado",D91),Config!$A$12:$A$15,0)),0)/30*MAX(1,N(E91)),0)) -> 0 | I91: =IF(OR(D91="",F91=""),"",ROUND(F91*H91,2)) -> 0 | J91: =IF(I91="","",F91-I91) -> 380 | K91: =IF(OR(D91="",A91=""),"",A91+IF(AND(Config!$B$17="Sim",LEFT(D91,17)="Cartão de crédito"),1,IFERROR(INDEX(Config!$C$12:$C$15,MATCH(IF(AND(D91="Cartão de crédito",N(E91)>1),"Cartão de crédito parcelado",D91),Config!$A$12:$A$15,0)),0))) -> 46232 | L91: =IF(A91="","",MONTH(A91)) -> 7 | M91: =IF(A91="","",YEAR(A91)) -> 2026 | N91: =IF(K91="","",IF(G91="Sim","Conferido",IF(K91>Config!$B$8,"A cair","A conferir"))) -> Conferido | O91: =IF(N91="A conferir",(Config!$B$8-K91)*1000+N(F91)/1000+ROW()/100000,0) -> 0
A92: 46232 | B92: Cláudia Santos | C92: Consulta | D92: Pix | F92: 380 | G92: Sim | H92: =IF(D92="","",IFERROR(INDEX(Config!$B$12:$B$15,MATCH(IF(AND(D92="Cartão de crédito",N(E92)>1),"Cartão de crédito parcelado",D92),Config!$A$12:$A$15,0)),0)+IF(AND(Config!$B$17="Sim",LEFT(D92,17)="Cartão de crédito"),Config!$B$18*IFERROR(INDEX(Config!$C$12:$C$15,MATCH(IF(AND(D92="Cartão de crédito",N(E92)>1),"Cartão de crédito parcelado",D92),Config!$A$12:$A$15,0)),0)/30*MAX(1,N(E92)),0)) -> 0 | I92: =IF(OR(D92="",F92=""),"",ROUND(F92*H92,2)) -> 0 | J92: =IF(I92="","",F92-I92) -> 380 | K92: =IF(OR(D92="",A92=""),"",A92+IF(AND(Config!$B$17="Sim",LEFT(D92,17)="Cartão de crédito"),1,IFERROR(INDEX(Config!$C$12:$C$15,MATCH(IF(AND(D92="Cartão de crédito",N(E92)>1),"Cartão de crédito parcelado",D92),Config!$A$12:$A$15,0)),0))) -> 46232 | L92: =IF(A92="","",MONTH(A92)) -> 7 | M92: =IF(A92="","",YEAR(A92)) -> 2026 | N92: =IF(K92="","",IF(G92="Sim","Conferido",IF(K92>Config!$B$8,"A cair","A conferir"))) -> Conferido | O92: =IF(N92="A conferir",(Config!$B$8-K92)*1000+N(F92)/1000+ROW()/100000,0) -> 0
A93: 46232 | B93: Gustavo Ferreira | C93: Consulta | D93: Cartão de débito | F93: 380 | G93: Sim | H93: =IF(D93="","",IFERROR(INDEX(Config!$B$12:$B$15,MATCH(IF(AND(D93="Cartão de crédito",N(E93)>1),"Cartão de crédito parcelado",D93),Config!$A$12:$A$15,0)),0)+IF(AND(Config!$B$17="Sim",LEFT(D93,17)="Cartão de crédito"),Config!$B$18*IFERROR(INDEX(Config!$C$12:$C$15,MATCH(IF(AND(D93="Cartão de crédito",N(E93)>1),"Cartão de crédito parcelado",D93),Config!$A$12:$A$15,0)),0)/30*MAX(1,N(E93)),0)) -> 0.015 | I93: =IF(OR(D93="",F93=""),"",ROUND(F93*H93,2)) -> 5.7 | J93: =IF(I93="","",F93-I93) -> 374.3 | K93: =IF(OR(D93="",A93=""),"",A93+IF(AND(Config!$B$17="Sim",LEFT(D93,17)="Cartão de crédito"),1,IFERROR(INDEX(Config!$C$12:$C$15,MATCH(IF(AND(D93="Cartão de crédito",N(E93)>1),"Cartão de crédito parcelado",D93),Config!$A$12:$A$15,0)),0))) -> 46233 | L93: =IF(A93="","",MONTH(A93)) -> 7 | M93: =IF(A93="","",YEAR(A93)) -> 2026 | N93: =IF(K93="","",IF(G93="Sim","Conferido",IF(K93>Config!$B$8,"A cair","A conferir"))) -> Conferido | O93: =IF(N93="A conferir",(Config!$B$8-K93)*1000+N(F93)/1000+ROW()/100000,0) -> 0
A94: 46232 | B94: Rafael Dias | C94: Consulta | D94: Cartão de débito | F94: 380 | G94: Sim | H94: =IF(D94="","",IFERROR(INDEX(Config!$B$12:$B$15,MATCH(IF(AND(D94="Cartão de crédito",N(E94)>1),"Cartão de crédito parcelado",D94),Config!$A$12:$A$15,0)),0)+IF(AND(Config!$B$17="Sim",LEFT(D94,17)="Cartão de crédito"),Config!$B$18*IFERROR(INDEX(Config!$C$12:$C$15,MATCH(IF(AND(D94="Cartão de crédito",N(E94)>1),"Cartão de crédito parcelado",D94),Config!$A$12:$A$15,0)),0)/30*MAX(1,N(E94)),0)) -> 0.015 | I94: =IF(OR(D94="",F94=""),"",ROUND(F94*H94,2)) -> 5.7 | J94: =IF(I94="","",F94-I94) -> 374.3 | K94: =IF(OR(D94="",A94=""),"",A94+IF(AND(Config!$B$17="Sim",LEFT(D94,17)="Cartão de crédito"),1,IFERROR(INDEX(Config!$C$12:$C$15,MATCH(IF(AND(D94="Cartão de crédito",N(E94)>1),"Cartão de crédito parcelado",D94),Config!$A$12:$A$15,0)),0))) -> 46233 | L94: =IF(A94="","",MONTH(A94)) -> 7 | M94: =IF(A94="","",YEAR(A94)) -> 2026 | N94: =IF(K94="","",IF(G94="Sim","Conferido",IF(K94>Config!$B$8,"A cair","A conferir"))) -> Conferido | O94: =IF(N94="A conferir",(Config!$B$8-K94)*1000+N(F94)/1000+ROW()/100000,0) -> 0
A95: 46233 | B95: Regina Macedo | C95: Consulta | D95: Pix | F95: 380 | G95: Sim | H95: =IF(D95="","",IFERROR(INDEX(Config!$B$12:$B$15,MATCH(IF(AND(D95="Cartão de crédito",N(E95)>1),"Cartão de crédito parcelado",D95),Config!$A$12:$A$15,0)),0)+IF(AND(Config!$B$17="Sim",LEFT(D95,17)="Cartão de crédito"),Config!$B$18*IFERROR(INDEX(Config!$C$12:$C$15,MATCH(IF(AND(D95="Cartão de crédito",N(E95)>1),"Cartão de crédito parcelado",D95),Config!$A$12:$A$15,0)),0)/30*MAX(1,N(E95)),0)) -> 0 | I95: =IF(OR(D95="",F95=""),"",ROUND(F95*H95,2)) -> 0 | J95: =IF(I95="","",F95-I95) -> 380 | K95: =IF(OR(D95="",A95=""),"",A95+IF(AND(Config!$B$17="Sim",LEFT(D95,17)="Cartão de crédito"),1,IFERROR(INDEX(Config!$C$12:$C$15,MATCH(IF(AND(D95="Cartão de crédito",N(E95)>1),"Cartão de crédito parcelado",D95),Config!$A$12:$A$15,0)),0))) -> 46233 | L95: =IF(A95="","",MONTH(A95)) -> 7 | M95: =IF(A95="","",YEAR(A95)) -> 2026 | N95: =IF(K95="","",IF(G95="Sim","Conferido",IF(K95>Config!$B$8,"A cair","A conferir"))) -> Conferido | O95: =IF(N95="A conferir",(Config!$B$8-K95)*1000+N(F95)/1000+ROW()/100000,0) -> 0
A96: 46233 | B96: Roberta Araújo | C96: Consulta | D96: Pix | F96: 380 | G96: Sim | H96: =IF(D96="","",IFERROR(INDEX(Config!$B$12:$B$15,MATCH(IF(AND(D96="Cartão de crédito",N(E96)>1),"Cartão de crédito parcelado",D96),Config!$A$12:$A$15,0)),0)+IF(AND(Config!$B$17="Sim",LEFT(D96,17)="Cartão de crédito"),Config!$B$18*IFERROR(INDEX(Config!$C$12:$C$15,MATCH(IF(AND(D96="Cartão de crédito",N(E96)>1),"Cartão de crédito parcelado",D96),Config!$A$12:$A$15,0)),0)/30*MAX(1,N(E96)),0)) -> 0 | I96: =IF(OR(D96="",F96=""),"",ROUND(F96*H96,2)) -> 0 | J96: =IF(I96="","",F96-I96) -> 380 | K96: =IF(OR(D96="",A96=""),"",A96+IF(AND(Config!$B$17="Sim",LEFT(D96,17)="Cartão de crédito"),1,IFERROR(INDEX(Config!$C$12:$C$15,MATCH(IF(AND(D96="Cartão de crédito",N(E96)>1),"Cartão de crédito parcelado",D96),Config!$A$12:$A$15,0)),0))) -> 46233 | L96: =IF(A96="","",MONTH(A96)) -> 7 | M96: =IF(A96="","",YEAR(A96)) -> 2026 | N96: =IF(K96="","",IF(G96="Sim","Conferido",IF(K96>Config!$B$8,"A cair","A conferir"))) -> Conferido | O96: =IF(N96="A conferir",(Config!$B$8-K96)*1000+N(F96)/1000+ROW()/100000,0) -> 0
A97: 46233 | B97: Patrícia Dias | C97: Avaliação endócrina | D97: Cartão de crédito | F97: 400 | G97: Sim | H97: =IF(D97="","",IFERROR(INDEX(Config!$B$12:$B$15,MATCH(IF(AND(D97="Cartão de crédito",N(E97)>1),"Cartão de crédito parcelado",D97),Config!$A$12:$A$15,0)),0)+IF(AND(Config!$B$17="Sim",LEFT(D97,17)="Cartão de crédito"),Config!$B$18*IFERROR(INDEX(Config!$C$12:$C$15,MATCH(IF(AND(D97="Cartão de crédito",N(E97)>1),"Cartão de crédito parcelado",D97),Config!$A$12:$A$15,0)),0)/30*MAX(1,N(E97)),0)) -> 0.032 | I97: =IF(OR(D97="",F97=""),"",ROUND(F97*H97,2)) -> 12.8 | J97: =IF(I97="","",F97-I97) -> 387.2 | K97: =IF(OR(D97="",A97=""),"",A97+IF(AND(Config!$B$17="Sim",LEFT(D97,17)="Cartão de crédito"),1,IFERROR(INDEX(Config!$C$12:$C$15,MATCH(IF(AND(D97="Cartão de crédito",N(E97)>1),"Cartão de crédito parcelado",D97),Config!$A$12:$A$15,0)),0))) -> 46263 | L97: =IF(A97="","",MONTH(A97)) -> 7 | M97: =IF(A97="","",YEAR(A97)) -> 2026 | N97: =IF(K97="","",IF(G97="Sim","Conferido",IF(K97>Config!$B$8,"A cair","A conferir"))) -> Conferido | O97: =IF(N97="A conferir",(Config!$B$8-K97)*1000+N(F97)/1000+ROW()/100000,0) -> 0
A98: 46234 | B98: Fábio Machado | C98: Consulta | D98: Cartão de crédito | F98: 380 | G98: Sim | H98: =IF(D98="","",IFERROR(INDEX(Config!$B$12:$B$15,MATCH(IF(AND(D98="Cartão de crédito",N(E98)>1),"Cartão de crédito parcelado",D98),Config!$A$12:$A$15,0)),0)+IF(AND(Config!$B$17="Sim",LEFT(D98,17)="Cartão de crédito"),Config!$B$18*IFERROR(INDEX(Config!$C$12:$C$15,MATCH(IF(AND(D98="Cartão de crédito",N(E98)>1),"Cartão de crédito parcelado",D98),Config!$A$12:$A$15,0)),0)/30*MAX(1,N(E98)),0)) -> 0.032 | I98: =IF(OR(D98="",F98=""),"",ROUND(F98*H98,2)) -> 12.16 | J98: =IF(I98="","",F98-I98) -> 367.84 | K98: =IF(OR(D98="",A98=""),"",A98+IF(AND(Config!$B$17="Sim",LEFT(D98,17)="Cartão de crédito"),1,IFERROR(INDEX(Config!$C$12:$C$15,MATCH(IF(AND(D98="Cartão de crédito",N(E98)>1),"Cartão de crédito parcelado",D98),Config!$A$12:$A$15,0)),0))) -> 46264 | L98: =IF(A98="","",MONTH(A98)) -> 7 | M98: =IF(A98="","",YEAR(A98)) -> 2026 | N98: =IF(K98="","",IF(G98="Sim","Conferido",IF(K98>Config!$B$8,"A cair","A conferir"))) -> Conferido | O98: =IF(N98="A conferir",(Config!$B$8-K98)*1000+N(F98)/1000+ROW()/100000,0) -> 0
A99: 46234 | B99: Fábio Machado | C99: ECG | D99: Cartão de crédito | F99: 130 | G99: Sim | H99: =IF(D99="","",IFERROR(INDEX(Config!$B$12:$B$15,MATCH(IF(AND(D99="Cartão de crédito",N(E99)>1),"Cartão de crédito parcelado",D99),Config!$A$12:$A$15,0)),0)+IF(AND(Config!$B$17="Sim",LEFT(D99,17)="Cartão de crédito"),Config!$B$18*IFERROR(INDEX(Config!$C$12:$C$15,MATCH(IF(AND(D99="Cartão de crédito",N(E99)>1),"Cartão de crédito parcelado",D99),Config!$A$12:$A$15,0)),0)/30*MAX(1,N(E99)),0)) -> 0.032 | I99: =IF(OR(D99="",F99=""),"",ROUND(F99*H99,2)) -> 4.16 | J99: =IF(I99="","",F99-I99) -> 125.84 | K99: =IF(OR(D99="",A99=""),"",A99+IF(AND(Config!$B$17="Sim",LEFT(D99,17)="Cartão de crédito"),1,IFERROR(INDEX(Config!$C$12:$C$15,MATCH(IF(AND(D99="Cartão de crédito",N(E99)>1),"Cartão de crédito parcelado",D99),Config!$A$12:$A$15,0)),0))) -> 46264 | L99: =IF(A99="","",MONTH(A99)) -> 7 | M99: =IF(A99="","",YEAR(A99)) -> 2026 | N99: =IF(K99="","",IF(G99="Sim","Conferido",IF(K99>Config!$B$8,"A cair","A conferir"))) -> Conferido | O99: =IF(N99="A conferir",(Config!$B$8-K99)*1000+N(F99)/1000+ROW()/100000,0) -> 0
... A111: 46238 | B111: Viviane Teixeira | C111: Consulta | D111: Cartão de débito | F111: 380 | G111: Sim | H111: =IF(D111="","",IFERROR(INDEX(Config!$B$12:$B$15,MATCH(IF(AND(D111="Cartão de crédito",N(E111)>1),"Cartão de crédito parcelado",D111),Config!$A$12:$A$15,0)),0)+IF(AND(Config!$B$17="Sim",LEFT(D111,17)="Cartão de crédito"),Config!$B$18*IFERROR(INDEX(Config!$C$12:$C$15,MATCH(IF(AND(D111="Cartão de crédito",N(E111)>1),"Cartão de crédito parcelado",D111),Config!$A$12:$A$15,0)),0)/30*MAX(1,N(E111)),0)) -> 0.015 | I111: =IF(OR(D111="",F111=""),"",ROUND(F111*H111,2)) -> 5.7 | J111: =IF(I111="","",F111-I111) -> 374.3 | K111: =IF(OR(D111="",A111=""),"",A111+IF(AND(Config!$B$17="Sim",LEFT(D111,17)="Cartão de crédito"),1,IFERROR(INDEX(Config!$C$12:$C$15,MATCH(IF(AND(D111="Cartão de crédito",N(E111)>1),"Cartão de crédito parcelado",D111),Config!$A$12:$A$15,0)),0))) -> 46239 | L111: =IF(A111="","",MONTH(A111)) -> 8 | M111: =IF(A111="","",YEAR(A111)) -> 2026 | N111: =IF(K111="","",IF(G111="Sim","Conferido",IF(K111>Config!$B$8,"A cair","A conferir"))) -> Conferido | O111: =IF(N111="A conferir",(Config!$B$8-K111)*1000+N(F111)/1000+ROW()/100000,0) -> 0
A112: 46239 | B112: Regina Duarte | C112: Consulta | D112: Cartão de crédito | E112: 2 | F112: 380 | G112: Sim | H112: =IF(D112="","",IFERROR(INDEX(Config!$B$12:$B$15,MATCH(IF(AND(D112="Cartão de crédito",N(E112)>1),"Cartão de crédito parcelado",D112),Config!$A$12:$A$15,0)),0)+IF(AND(Config!$B$17="Sim",LEFT(D112,17)="Cartão de crédito"),Config!$B$18*IFERROR(INDEX(Config!$C$12:$C$15,MATCH(IF(AND(D112="Cartão de crédito",N(E112)>1),"Cartão de crédito parcelado",D112),Config!$A$12:$A$15,0)),0)/30*MAX(1,N(E112)),0)) -> 0.039 | I112: =IF(OR(D112="",F112=""),"",ROUND(F112*H112,2)) -> 14.82 | J112: =IF(I112="","",F112-I112) -> 365.18 | K112: =IF(OR(D112="",A112=""),"",A112+IF(AND(Config!$B$17="Sim",LEFT(D112,17)="Cartão de crédito"),1,IFERROR(INDEX(Config!$C$12:$C$15,MATCH(IF(AND(D112="Cartão de crédito",N(E112)>1),"Cartão de crédito parcelado",D112),Config!$A$12:$A$15,0)),0))) -> 46269 | L112: =IF(A112="","",MONTH(A112)) -> 8 | M112: =IF(A112="","",YEAR(A112)) -> 2026 | N112: =IF(K112="","",IF(G112="Sim","Conferido",IF(K112>Config!$B$8,"A cair","A conferir"))) -> Conferido | O112: =IF(N112="A conferir",(Config!$B$8-K112)*1000+N(F112)/1000+ROW()/100000,0) -> 0
A113: 46239 | B113: Marcelo Santos | C113: Consulta | D113: Pix | F113: 380 | G113: Sim | H113: =IF(D113="","",IFERROR(INDEX(Config!$B$12:$B$15,MATCH(IF(AND(D113="Cartão de crédito",N(E113)>1),"Cartão de crédito parcelado",D113),Config!$A$12:$A$15,0)),0)+IF(AND(Config!$B$17="Sim",LEFT(D113,17)="Cartão de crédito"),Config!$B$18*IFERROR(INDEX(Config!$C$12:$C$15,MATCH(IF(AND(D113="Cartão de crédito",N(E113)>1),"Cartão de crédito parcelado",D113),Config!$A$12:$A$15,0)),0)/30*MAX(1,N(E113)),0)) -> 0 | I113: =IF(OR(D113="",F113=""),"",ROUND(F113*H113,2)) -> 0 | J113: =IF(I113="","",F113-I113) -> 380 | K113: =IF(OR(D113="",A113=""),"",A113+IF(AND(Config!$B$17="Sim",LEFT(D113,17)="Cartão de crédito"),1,IFERROR(INDEX(Config!$C$12:$C$15,MATCH(IF(AND(D113="Cartão de crédito",N(E113)>1),"Cartão de crédito parcelado",D113),Config!$A$12:$A$15,0)),0))) -> 46239 | L113: =IF(A113="","",MONTH(A113)) -> 8 | M113: =IF(A113="","",YEAR(A113)) -> 2026 | N113: =IF(K113="","",IF(G113="Sim","Conferido",IF(K113>Config!$B$8,"A cair","A conferir"))) -> Conferido | O113: =IF(N113="A conferir",(Config!$B$8-K113)*1000+N(F113)/1000+ROW()/100000,0) -> 0
A114: 46239 | B114: Rodrigo Moreira | C114: Consulta | D114: Cartão de débito | F114: 380 | G114: Sim | H114: =IF(D114="","",IFERROR(INDEX(Config!$B$12:$B$15,MATCH(IF(AND(D114="Cartão de crédito",N(E114)>1),"Cartão de crédito parcelado",D114),Config!$A$12:$A$15,0)),0)+IF(AND(Config!$B$17="Sim",LEFT(D114,17)="Cartão de crédito"),Config!$B$18*IFERROR(INDEX(Config!$C$12:$C$15,MATCH(IF(AND(D114="Cartão de crédito",N(E114)>1),"Cartão de crédito parcelado",D114),Config!$A$12:$A$15,0)),0)/30*MAX(1,N(E114)),0)) -> 0.015 | I114: =IF(OR(D114="",F114=""),"",ROUND(F114*H114,2)) -> 5.7 | J114: =IF(I114="","",F114-I114) -> 374.3 | K114: =IF(OR(D114="",A114=""),"",A114+IF(AND(Config!$B$17="Sim",LEFT(D114,17)="Cartão de crédito"),1,IFERROR(INDEX(Config!$C$12:$C$15,MATCH(IF(AND(D114="Cartão de crédito",N(E114)>1),"Cartão de crédito parcelado",D114),Config!$A$12:$A$15,0)),0))) -> 46240 | L114: =IF(A114="","",MONTH(A114)) -> 8 | M114: =IF(A114="","",YEAR(A114)) -> 2026 | N114: =IF(K114="","",IF(G114="Sim","Conferido",IF(K114>Config!$B$8,"A cair","A conferir"))) -> Conferido | O114: =IF(N114="A conferir",(Config!$B$8-K114)*1000+N(F114)/1000+ROW()/100000,0) -> 0
A115: 46240 | B115: Elaine Cardoso | C115: Consulta | D115: Cartão de crédito | E115: 2 | F115: 380 | G115: Sim | H115: =IF(D115="","",IFERROR(INDEX(Config!$B$12:$B$15,MATCH(IF(AND(D115="Cartão de crédito",N(E115)>1),"Cartão de crédito parcelado",D115),Config!$A$12:$A$15,0)),0)+IF(AND(Config!$B$17="Sim",LEFT(D115,17)="Cartão de crédito"),Config!$B$18*IFERROR(INDEX(Config!$C$12:$C$15,MATCH(IF(AND(D115="Cartão de crédito",N(E115)>1),"Cartão de crédito parcelado",D115),Config!$A$12:$A$15,0)),0)/30*MAX(1,N(E115)),0)) -> 0.039 | I115: =IF(OR(D115="",F115=""),"",ROUND(F115*H115,2)) -> 14.82 | J115: =IF(I115="","",F115-I115) -> 365.18 | K115: =IF(OR(D115="",A115=""),"",A115+IF(AND(Config!$B$17="Sim",LEFT(D115,17)="Cartão de crédito"),1,IFERROR(INDEX(Config!$C$12:$C$15,MATCH(IF(AND(D115="Cartão de crédito",N(E115)>1),"Cartão de crédito parcelado",D115),Config!$A$12:$A$15,0)),0))) -> 46270 | L115: =IF(A115="","",MONTH(A115)) -> 8 | M115: =IF(A115="","",YEAR(A115)) -> 2026 | N115: =IF(K115="","",IF(G115="Sim","Conferido",IF(K115>Config!$B$8,"A cair","A conferir"))) -> Conferido | O115: =IF(N115="A conferir",(Config!$B$8-K115)*1000+N(F115)/1000+ROW()/100000,0) -> 0
A116: 46240 | B116: Patrícia Fernandes | C116: Consulta | D116: Cartão de débito | F116: 380 | G116: Sim | H116: =IF(D116="","",IFERROR(INDEX(Config!$B$12:$B$15,MATCH(IF(AND(D116="Cartão de crédito",N(E116)>1),"Cartão de crédito parcelado",D116),Config!$A$12:$A$15,0)),0)+IF(AND(Config!$B$17="Sim",LEFT(D116,17)="Cartão de crédito"),Config!$B$18*IFERROR(INDEX(Config!$C$12:$C$15,MATCH(IF(AND(D116="Cartão de crédito",N(E116)>1),"Cartão de crédito parcelado",D116),Config!$A$12:$A$15,0)),0)/30*MAX(1,N(E116)),0)) -> 0.015 | I116: =IF(OR(D116="",F116=""),"",ROUND(F116*H116,2)) -> 5.7 | J116: =IF(I116="","",F116-I116) -> 374.3 | K116: =IF(OR(D116="",A116=""),"",A116+IF(AND(Config!$B$17="Sim",LEFT(D116,17)="Cartão de crédito"),1,IFERROR(INDEX(Config!$C$12:$C$15,MATCH(IF(AND(D116="Cartão de crédito",N(E116)>1),"Cartão de crédito parcelado",D116),Config!$A$12:$A$15,0)),0))) -> 46241 | L116: =IF(A116="","",MONTH(A116)) -> 8 | M116: =IF(A116="","",YEAR(A116)) -> 2026 | N116: =IF(K116="","",IF(G116="Sim","Conferido",IF(K116>Config!$B$8,"A cair","A conferir"))) -> Conferido | O116: =IF(N116="A conferir",(Config!$B$8-K116)*1000+N(F116)/1000+ROW()/100000,0) -> 0
A117: 46240 | B117: Fábio Ferreira | C117: Avaliação endócrina | D117: Cartão de crédito | E117: 2 | F117: 400 | G117: Sim | H117: =IF(D117="","",IFERROR(INDEX(Config!$B$12:$B$15,MATCH(IF(AND(D117="Cartão de crédito",N(E117)>1),"Cartão de crédito parcelado",D117),Config!$A$12:$A$15,0)),0)+IF(AND(Config!$B$17="Sim",LEFT(D117,17)="Cartão de crédito"),Config!$B$18*IFERROR(INDEX(Config!$C$12:$C$15,MATCH(IF(AND(D117="Cartão de crédito",N(E117)>1),"Cartão de crédito parcelado",D117),Config!$A$12:$A$15,0)),0)/30*MAX(1,N(E117)),0)) -> 0.039 | I117: =IF(OR(D117="",F117=""),"",ROUND(F117*H117,2)) -> 15.6 | J117: =IF(I117="","",F117-I117) -> 384.4 | K117: =IF(OR(D117="",A117=""),"",A117+IF(AND(Config!$B$17="Sim",LEFT(D117,17)="Cartão de crédito"),1,IFERROR(INDEX(Config!$C$12:$C$15,MATCH(IF(AND(D117="Cartão de crédito",N(E117)>1),"Cartão de crédito parcelado",D117),Config!$A$12:$A$15,0)),0))) -> 46270 | L117: =IF(A117="","",MONTH(A117)) -> 8 | M117: =IF(A117="","",YEAR(A117)) -> 2026 | N117: =IF(K117="","",IF(G117="Sim","Conferido",IF(K117>Config!$B$8,"A cair","A conferir"))) -> Conferido | O117: =IF(N117="A conferir",(Config!$B$8-K117)*1000+N(F117)/1000+ROW()/100000,0) -> 0
A118: 46240 | B118: Cláudia Melo | C118: Avaliação endócrina | D118: Pix | F118: 400 | G118: Sim | H118: =IF(D118="","",IFERROR(INDEX(Config!$B$12:$B$15,MATCH(IF(AND(D118="Cartão de crédito",N(E118)>1),"Cartão de crédito parcelado",D118),Config!$A$12:$A$15,0)),0)+IF(AND(Config!$B$17="Sim",LEFT(D118,17)="Cartão de crédito"),Config!$B$18*IFERROR(INDEX(Config!$C$12:$C$15,MATCH(IF(AND(D118="Cartão de crédito",N(E118)>1),"Cartão de crédito parcelado",D118),Config!$A$12:$A$15,0)),0)/30*MAX(1,N(E118)),0)) -> 0 | I118: =IF(OR(D118="",F118=""),"",ROUND(F118*H118,2)) -> 0 | J118: =IF(I118="","",F118-I118) -> 400 | K118: =IF(OR(D118="",A118=""),"",A118+IF(AND(Config!$B$17="Sim",LEFT(D118,17)="Cartão de crédito"),1,IFERROR(INDEX(Config!$C$12:$C$15,MATCH(IF(AND(D118="Cartão de crédito",N(E118)>1),"Cartão de crédito parcelado",D118),Config!$A$12:$A$15,0)),0))) -> 46240 | L118: =IF(A118="","",MONTH(A118)) -> 8 | M118: =IF(A118="","",YEAR(A118)) -> 2026 | N118: =IF(K118="","",IF(G118="Sim","Conferido",IF(K118>Config!$B$8,"A cair","A conferir"))) -> Conferido | O118: =IF(N118="A conferir",(Config!$B$8-K118)*1000+N(F118)/1000+ROW()/100000,0) -> 0
A119: 46240 | B119: Otávio Cardoso | C119: Teste ergométrico | D119: Pix | F119: 450 | G119: Sim | H119: =IF(D119="","",IFERROR(INDEX(Config!$B$12:$B$15,MATCH(IF(AND(D119="Cartão de crédito",N(E119)>1),"Cartão de crédito parcelado",D119),Config!$A$12:$A$15,0)),0)+IF(AND(Config!$B$17="Sim",LEFT(D119,17)="Cartão de crédito"),Config!$B$18*IFERROR(INDEX(Config!$C$12:$C$15,MATCH(IF(AND(D119="Cartão de crédito",N(E119)>1),"Cartão de crédito parcelado",D119),Config!$A$12:$A$15,0)),0)/30*MAX(1,N(E119)),0)) -> 0 | I119: =IF(OR(D119="",F119=""),"",ROUND(F119*H119,2)) -> 0 | J119: =IF(I119="","",F119-I119) -> 450 | K119: =IF(OR(D119="",A119=""),"",A119+IF(AND(Config!$B$17="Sim",LEFT(D119,17)="Cartão de crédito"),1,IFERROR(INDEX(Config!$C$12:$C$15,MATCH(IF(AND(D119="Cartão de crédito",N(E119)>1),"Cartão de crédito parcelado",D119),Config!$A$12:$A$15,0)),0))) -> 46240 | L119: =IF(A119="","",MONTH(A119)) -> 8 | M119: =IF(A119="","",YEAR(A119)) -> 2026 | N119: =IF(K119="","",IF(G119="Sim","Conferido",IF(K119>Config!$B$8,"A cair","A conferir"))) -> Conferido | O119: =IF(N119="A conferir",(Config!$B$8-K119)*1000+N(F119)/1000+ROW()/100000,0) -> 0
A120: 46241 | B120: Cláudia Costa | C120: ECG | D120: Pix | F120: 130 | G120: Sim | H120: =IF(D120="","",IFERROR(INDEX(Config!$B$12:$B$15,MATCH(IF(AND(D120="Cartão de crédito",N(E120)>1),"Cartão de crédito parcelado",D120),Config!$A$12:$A$15,0)),0)+IF(AND(Config!$B$17="Sim",LEFT(D120,17)="Cartão de crédito"),Config!$B$18*IFERROR(INDEX(Config!$C$12:$C$15,MATCH(IF(AND(D120="Cartão de crédito",N(E120)>1),"Cartão de crédito parcelado",D120),Config!$A$12:$A$15,0)),0)/30*MAX(1,N(E120)),0)) -> 0 | I120: =IF(OR(D120="",F120=""),"",ROUND(F120*H120,2)) -> 0 | J120: =IF(I120="","",F120-I120) -> 130 | K120: =IF(OR(D120="",A120=""),"",A120+IF(AND(Config!$B$17="Sim",LEFT(D120,17)="Cartão de crédito"),1,IFERROR(INDEX(Config!$C$12:$C$15,MATCH(IF(AND(D120="Cartão de crédito",N(E120)>1),"Cartão de crédito parcelado",D120),Config!$A$12:$A$15,0)),0))) -> 46241 | L120: =IF(A120="","",MONTH(A120)) -> 8 | M120: =IF(A120="","",YEAR(A120)) -> 2026 | N120: =IF(K120="","",IF(G120="Sim","Conferido",IF(K120>Config!$B$8,"A cair","A conferir"))) -> Conferido | O120: =IF(N120="A conferir",(Config!$B$8-K120)*1000+N(F120)/1000+ROW()/100000,0) -> 0
...
