Workbook

Sheet Como usar
A1: Resultado Mensal
A2: Kit de Gestão para Médicos · Seu Sócio Gestor · versão 1.0 (setembro de 2026)
A4: O que esta planilha faz | B4: Uma DRE simplificada da clínica: receita por categoria (as mesmas do caixa), custos fixos, despesas variáveis (materiais, taxas de cartão, repasse à parceira, manutenção), pró-labore fixo, impostos provisionados como % da receita, resultado e margem, mês a mês. Compara o mês com o anterior e com o que você previu.
A5: Passo 1 | B5: Em Config, informe o ano, o mês de análise (o último mês fechado) e a % de impostos a provisionar (peça ao contador a alíquota efetiva).
A6: Passo 2 | B6: Em Resultado, preencha por mês o que entrou em cada categoria e o que saiu em cada linha de custo fixo, despesa variável e pró-labore. Os totais por categoria estão no Painel da planilha 09 · Caixa da clínica ("De onde veio" e "Para onde foi o dinheiro").
A7: Passo 3 | B7: Em Previsto, escreva o que espera de receita, custos fixos, despesas variáveis e pró-labore para cada mês. Pode ser o mesmo valor o ano inteiro.
A8: Passo 4 | B8: Abra Painel: receita, saídas, resultado e margem do mês, comparação com o mês anterior e com o previsto (variação da margem em p.p.), receita por categoria e o gráfico do ano.
A9: Fim do mês | B9: Depois de fechar o caixa, lance o mês aqui e troque o mês em Config. Leva 10 minutos. No exemplo, o mês analisado é agosto de 2026 (setembro ainda está em andamento).
A10: Com a IA | B10: Copie a tabela do Painel para o prompt "Painel 01 · Explicar o mês ao sócio", "Caixa 02 · Comparar dois meses do resultado" ou "Caixa 04 · Preparar a reunião mensal com o contador" da biblioteca do kit. A planilha 20 · Resumo do mês já escreve o texto-base.
A11: Legenda | B11: Células amarelas: você preenche. Brancas: calculadas. Não é preciso mexer em nada fora do amarelo.
A12: Proteção | B12: Fórmulas protegidas sem senha. Para editar: Revisar > Desproteger planilha (Excel) ou Dados > Proteger intervalos (Google Sheets).
A13: Requisitos | B13: Excel 2016 ou mais novo, Microsoft 365 ou Google Sheets (só funções do Excel 2007+; nada de MÍNIMOSES, MÁXIMOSES ou UNIRTEXTO). No celular abre nos aplicativos; para preencher, use o computador.
A14: Dados de pacientes | B14: Guarde só o que a gestão precisa (nome, contato, valor, data). Nada de diagnóstico, prontuário ou exame nestas planilhas: o kit é gestão, não é prontuário. Veja o guia LGPD do kit antes de colar qualquer tabela em uma IA.
A15: Google Sheets | B15: Faça upload no Google Drive e abra com o Google Sheets. Fórmulas, listas, cores e gráficos funcionam.
... A17: Suporte | B17: suporte@seusociogestor.com.br · resposta em até 5 dias úteis · reembolso em até 7 dias pelo mesmo canal.

Sheet Painel
A1: =Config!B4&" · Resultado mensal · "&Config!B6&" de "&Config!B5 -> Clínica Vida Plena (exemplo fictício) · Resultado mensal · Agosto de 2026
A2: Nada para digitar aqui. Escolha o mês em Config; os números vêm de Resultado e de Previsto.
A4: Receita do mês | C4: Saídas do mês | E4: Resultado | G4: Margem
A5: =IF(INDEX(Resultado!$B$12:$M$12,Config!$B$8)="","—",INDEX(Resultado!$B$12:$M$12,Config!$B$8)) -> 50336 | C5: =IF(INDEX(Resultado!$B$34:$M$34,Config!$B$8)="","—",INDEX(Resultado!$B$34:$M$34,Config!$B$8)) -> 40696.12 | E5: =IF(INDEX(Resultado!$B$35:$M$35,Config!$B$8)="","—",INDEX(Resultado!$B$35:$M$35,Config!$B$8)) -> 9639.88 | G5: =IF(INDEX(Resultado!$B$36:$M$36,Config!$B$8)="","—",INDEX(Resultado!$B$36:$M$36,Config!$B$8)) -> 0.19151065
A7: Comparação com o mês anterior e com o previsto
A8: Linha | C8: Mês | D8: Mês anterior | E8: Variação | F8: Previsto | G8: Vs. previsto | H8: Situação
A9: Receita total | C9: =IF(INDEX(Resultado!$B$12:$M$12,Config!$B$8)="","—",INDEX(Resultado!$B$12:$M$12,Config!$B$8)) -> 50336 | D9: =IF(Config!$B$8<=1,"—",IF(INDEX(Resultado!$B$12:$M$12,Config!$B$8-1)="","—",INDEX(Resultado!$B$12:$M$12,Config!$B$8-1))) -> 53101 | E9: =IF(OR(C9="—",D9="—",D9=0),"—",(C9-D9)/ABS(D9)) -> -0.052070582 | F9: =IF(INDEX(Previsto!$B$5:$M$5,Config!$B$8)="","—",INDEX(Previsto!$B$5:$M$5,Config!$B$8)) -> 46000 | G9: =IF(OR(C9="—",F9="—",F9=0),"—",(C9-F9)/ABS(F9)) -> 0.09426087 | H9: =IF(OR(C9="—",F9="—"),"—",IF(C9>=F9,"Dentro do previsto",IF(C9>=F9*0.95,"Perto","Fora do previsto"))) -> Dentro do previsto
A10: Custos fixos | C10: =IF(INDEX(Resultado!$B$22:$M$22,Config!$B$8)="","—",INDEX(Resultado!$B$22:$M$22,Config!$B$8)) -> 10000 | D10: =IF(Config!$B$8<=1,"—",IF(INDEX(Resultado!$B$22:$M$22,Config!$B$8-1)="","—",INDEX(Resultado!$B$22:$M$22,Config!$B$8-1))) -> 10000 | E10: =IF(OR(C10="—",D10="—",D10=0),"—",(C10-D10)/ABS(D10)) -> 0 | F10: =IF(INDEX(Previsto!$B$6:$M$6,Config!$B$8)="","—",INDEX(Previsto!$B$6:$M$6,Config!$B$8)) -> 10000 | G10: =IF(OR(C10="—",F10="—",F10=0),"—",(C10-F10)/ABS(F10)) -> 0 | H10: =IF(OR(C10="—",F10="—"),"—",IF(C10<=F10,"Dentro do previsto",IF(C10<=F10*1.05,"Perto","Fora do previsto"))) -> Dentro do previsto
A11: Despesas variáveis | C11: =IF(INDEX(Resultado!$B$28:$M$28,Config!$B$8)="","—",INDEX(Resultado!$B$28:$M$28,Config!$B$8)) -> 7159.12 | D11: =IF(Config!$B$8<=1,"—",IF(INDEX(Resultado!$B$28:$M$28,Config!$B$8-1)="","—",INDEX(Resultado!$B$28:$M$28,Config!$B$8-1))) -> 6661.77 | E11: =IF(OR(C11="—",D11="—",D11=0),"—",(C11-D11)/ABS(D11)) -> 0.074657336 | F11: =IF(INDEX(Previsto!$B$7:$M$7,Config!$B$8)="","—",INDEX(Previsto!$B$7:$M$7,Config!$B$8)) -> 6000 | G11: =IF(OR(C11="—",F11="—",F11=0),"—",(C11-F11)/ABS(F11)) -> 0.19318667 | H11: =IF(OR(C11="—",F11="—"),"—",IF(C11<=F11,"Dentro do previsto",IF(C11<=F11*1.05,"Perto","Fora do previsto"))) -> Fora do previsto
A12: Pró-labore | C12: =IF(INDEX(Resultado!$B$32:$M$32,Config!$B$8)="","—",INDEX(Resultado!$B$32:$M$32,Config!$B$8)) -> 18000 | D12: =IF(Config!$B$8<=1,"—",IF(INDEX(Resultado!$B$32:$M$32,Config!$B$8-1)="","—",INDEX(Resultado!$B$32:$M$32,Config!$B$8-1))) -> 18000 | E12: =IF(OR(C12="—",D12="—",D12=0),"—",(C12-D12)/ABS(D12)) -> 0 | F12: =IF(INDEX(Previsto!$B$8:$M$8,Config!$B$8)="","—",INDEX(Previsto!$B$8:$M$8,Config!$B$8)) -> 18000 | G12: =IF(OR(C12="—",F12="—",F12=0),"—",(C12-F12)/ABS(F12)) -> 0 | H12: Informativo
A13: Impostos provisionados | C13: =IF(INDEX(Resultado!$B$33:$M$33,Config!$B$8)="","—",INDEX(Resultado!$B$33:$M$33,Config!$B$8)) -> 5537 | D13: =IF(Config!$B$8<=1,"—",IF(INDEX(Resultado!$B$33:$M$33,Config!$B$8-1)="","—",INDEX(Resultado!$B$33:$M$33,Config!$B$8-1))) -> 5841 | E13: =IF(OR(C13="—",D13="—",D13=0),"—",(C13-D13)/ABS(D13)) -> -0.052045883 | F13: =IF(INDEX(Previsto!$B$9:$M$9,Config!$B$8)="","—",INDEX(Previsto!$B$9:$M$9,Config!$B$8)) -> 5060 | G13: =IF(OR(C13="—",F13="—",F13=0),"—",(C13-F13)/ABS(F13)) -> 0.094268775 | H13: Informativo
A14: Total de saídas | C14: =IF(INDEX(Resultado!$B$34:$M$34,Config!$B$8)="","—",INDEX(Resultado!$B$34:$M$34,Config!$B$8)) -> 40696.12 | D14: =IF(Config!$B$8<=1,"—",IF(INDEX(Resultado!$B$34:$M$34,Config!$B$8-1)="","—",INDEX(Resultado!$B$34:$M$34,Config!$B$8-1))) -> 40502.77 | E14: =IF(OR(C14="—",D14="—",D14=0),"—",(C14-D14)/ABS(D14)) -> 0.0047737476 | F14: =IF(INDEX(Previsto!$B$10:$M$10,Config!$B$8)="","—",INDEX(Previsto!$B$10:$M$10,Config!$B$8)) -> 39060 | G14: =IF(OR(C14="—",F14="—",F14=0),"—",(C14-F14)/ABS(F14)) -> 0.041887353 | H14: =IF(OR(C14="—",F14="—"),"—",IF(C14<=F14,"Dentro do previsto",IF(C14<=F14*1.05,"Perto","Fora do previsto"))) -> Perto
A15: Resultado do mês | C15: =IF(INDEX(Resultado!$B$35:$M$35,Config!$B$8)="","—",INDEX(Resultado!$B$35:$M$35,Config!$B$8)) -> 9639.88 | D15: =IF(Config!$B$8<=1,"—",IF(INDEX(Resultado!$B$35:$M$35,Config!$B$8-1)="","—",INDEX(Resultado!$B$35:$M$35,Config!$B$8-1))) -> 12598.23 | E15: =IF(OR(C15="—",D15="—",D15=0),"—",(C15-D15)/ABS(D15)) -> -0.23482267 | F15: =IF(INDEX(Previsto!$B$11:$M$11,Config!$B$8)="","—",INDEX(Previsto!$B$11:$M$11,Config!$B$8)) -> 6940 | G15: =IF(OR(C15="—",F15="—",F15=0),"—",(C15-F15)/ABS(F15)) -> 0.3890317 | H15: =IF(OR(C15="—",F15="—"),"—",IF(C15>=F15,"Dentro do previsto",IF(C15>=F15*0.95,"Perto","Fora do previsto"))) -> Dentro do previsto
A16: Margem | C16: =IF(INDEX(Resultado!$B$36:$M$36,Config!$B$8)="","—",INDEX(Resultado!$B$36:$M$36,Config!$B$8)) -> 0.19151065 | D16: =IF(Config!$B$8<=1,"—",IF(INDEX(Resultado!$B$36:$M$36,Config!$B$8-1)="","—",INDEX(Resultado!$B$36:$M$36,Config!$B$8-1))) -> 0.23725033 | E16: =IF(OR(C16="—",D16="—"),"—",(C16-D16)*100) -> -4.5739686 | F16: =IF(INDEX(Previsto!$B$12:$M$12,Config!$B$8)="","—",INDEX(Previsto!$B$12:$M$12,Config!$B$8)) -> 0.15086957 | G16: =IF(OR(C16="—",F16="—"),"—",(C16-F16)*100) -> 4.0641083 | H16: =IF(OR(C16="—",F16="—"),"—",IF(C16>=F16,"Dentro do previsto",IF(C16>=F16*0.95,"Perto","Fora do previsto"))) -> Dentro do previsto
A18: Receita do mês por categoria
A19: Categoria | C19: Mês | D19: Mês anterior | E19: Variação | F19: % da receita
A20: Particular à vista | C20: =IF(INDEX(Resultado!$B$6:$M$6,Config!$B$8)="","—",INDEX(Resultado!$B$6:$M$6,Config!$B$8)) -> 33860 | D20: =IF(Config!$B$8<=1,"—",IF(INDEX(Resultado!$B$6:$M$6,Config!$B$8-1)="","—",INDEX(Resultado!$B$6:$M$6,Config!$B$8-1))) -> 36540 | E20: =IF(OR(C20="—",D20="—",D20=0),"—",(C20-D20)/ABS(D20)) -> -0.07334428 | F20: =IF(OR(C20="—",C9="—",C9=0),"—",C20/C9) -> 0.67267959
A21: Particular a prazo | C21: =IF(INDEX(Resultado!$B$7:$M$7,Config!$B$8)="","—",INDEX(Resultado!$B$7:$M$7,Config!$B$8)) -> 5315 | D21: =IF(Config!$B$8<=1,"—",IF(INDEX(Resultado!$B$7:$M$7,Config!$B$8-1)="","—",INDEX(Resultado!$B$7:$M$7,Config!$B$8-1))) -> 6760 | E21: =IF(OR(C21="—",D21="—",D21=0),"—",(C21-D21)/ABS(D21)) -> -0.2137574 | F21: =IF(OR(C21="—",C9="—",C9=0),"—",C21/C9) -> 0.10559043
A22: Convênio · Saúde Total | C22: =IF(INDEX(Resultado!$B$8:$M$8,Config!$B$8)="","—",INDEX(Resultado!$B$8:$M$8,Config!$B$8)) -> 7320 | D22: =IF(Config!$B$8<=1,"—",IF(INDEX(Resultado!$B$8:$M$8,Config!$B$8-1)="","—",INDEX(Resultado!$B$8:$M$8,Config!$B$8-1))) -> 6655 | E22: =IF(OR(C22="—",D22="—",D22=0),"—",(C22-D22)/ABS(D22)) -> 0.099924869 | F22: =IF(OR(C22="—",C9="—",C9=0),"—",C22/C9) -> 0.14542276
A23: Convênio · MediPlan | C23: =IF(INDEX(Resultado!$B$9:$M$9,Config!$B$8)="","—",INDEX(Resultado!$B$9:$M$9,Config!$B$8)) -> 2130 | D23: =IF(Config!$B$8<=1,"—",IF(INDEX(Resultado!$B$9:$M$9,Config!$B$8-1)="","—",INDEX(Resultado!$B$9:$M$9,Config!$B$8-1))) -> 1570 | E23: =IF(OR(C23="—",D23="—",D23=0),"—",(C23-D23)/ABS(D23)) -> 0.3566879 | F23: =IF(OR(C23="—",C9="—",C9=0),"—",C23/C9) -> 0.042315639
A24: Convênio · Vida Care | C24: =IF(INDEX(Resultado!$B$10:$M$10,Config!$B$8)="","—",INDEX(Resultado!$B$10:$M$10,Config!$B$8)) -> 1711 | D24: =IF(Config!$B$8<=1,"—",IF(INDEX(Resultado!$B$10:$M$10,Config!$B$8-1)="","—",INDEX(Resultado!$B$10:$M$10,Config!$B$8-1))) -> 1576 | E24: =IF(OR(C24="—",D24="—",D24=0),"—",(C24-D24)/ABS(D24)) -> 0.085659898 | F24: =IF(OR(C24="—",C9="—",C9=0),"—",C24/C9) -> 0.033991577
A25: Outras entradas | C25: =IF(INDEX(Resultado!$B$11:$M$11,Config!$B$8)="","—",INDEX(Resultado!$B$11:$M$11,Config!$B$8)) -> 0 | D25: =IF(Config!$B$8<=1,"—",IF(INDEX(Resultado!$B$11:$M$11,Config!$B$8-1)="","—",INDEX(Resultado!$B$11:$M$11,Config!$B$8-1))) -> 0 | E25: =IF(OR(C25="—",D25="—",D25=0),"—",(C25-D25)/ABS(D25)) -> — | F25: =IF(OR(C25="—",C9="—",C9=0),"—",C25/C9) -> 0
A27: Receita, saídas e resultado no ano (meses em branco não aparecem)
A46: Variação da margem em pontos percentuais (p.p.). Para explicar o resultado ao sócio ou ao contador, use a planilha 20 · Resumo do mês e o prompt "Painel 01 · Explicar o mês ao sócio".

Sheet Config
A1: Configurações
A2: Células amarelas: você preenche.
A4: Clínica | B4: Clínica Vida Plena (exemplo fictício) | D4: Meses
A5: Ano | B5: 2026 | D5: Janeiro
A6: Mês de análise | B6: Agosto | C6: Analise o último mês fechado (no exemplo, agosto: setembro ainda está em andamento no caixa). | D6: Fevereiro
A7: Impostos provisionados (% da receita) | B7: 0.11 | C7: Use a alíquota efetiva que o contador informar (Simples anexo III ou V, ou lucro presumido). A provisão sai todo mês, mesmo que o imposto seja pago depois. No exemplo, 11 %, a mesma das planilhas 05 a 10. | D7: Março
A8: Número do mês | B8: =MATCH(B6,$D$5:$D$16,0) -> 8 | D8: Abril
A9: Mês anterior | B9: =IF(B8>1,INDEX($D$5:$D$16,B8-1),"") -> Julho | D9: Maio
D10: Junho
D11: Julho
D12: Agosto
D13: Setembro
D14: Outubro
D15: Novembro
D16: Dezembro

Sheet Resultado
A1: Resultado mensal da clínica
A2: Preencha as linhas amarelas de cada mês com os totais por categoria do Painel do caixa (planilha 09). Totais, impostos provisionados, resultado e margem são calculados. Meses futuros ficam em branco.
A4: Linha | B4: Jan | C4: Fev | D4: Mar | E4: Abr | F4: Mai | G4: Jun | H4: Jul | I4: Ago | J4: Set | K4: Out | L4: Nov | M4: Dez | N4: Total do ano | O4: Média dos meses preenchidos
A5: Receita (o que entrou no mês, por categoria do caixa)
A6: Particular à vista | B6: 25180 | C6: 15870 | D6: 37340 | E6: 28610 | F6: 27400 | G6: 27400 | H6: 36540 | I6: 33860 | N6: =IF(COUNT(B6:M6)=0,"",SUM(B6:M6)) -> 232200 | O6: =IF(COUNT(B6:M6)=0,"",AVERAGE(B6:M6)) -> 29025
A7: Particular a prazo | B7: 0 | C7: 1825 | D7: 3990 | E7: 4195 | F7: 6280 | G7: 8680 | H7: 6760 | I7: 5315 | N7: =IF(COUNT(B7:M7)=0,"",SUM(B7:M7)) -> 37045 | O7: =IF(COUNT(B7:M7)=0,"",AVERAGE(B7:M7)) -> 4630.625
A8: Convênio · Saúde Total | B8: 3930 | C8: 3420 | D8: 3750 | E8: 3295 | F8: 7220 | G8: 4335 | H8: 6655 | I8: 7320 | N8: =IF(COUNT(B8:M8)=0,"",SUM(B8:M8)) -> 39925 | O8: =IF(COUNT(B8:M8)=0,"",AVERAGE(B8:M8)) -> 4990.625
A9: Convênio · MediPlan | B9: 2660 | C9: 2040 | D9: 1530 | E9: 1555 | F9: 2610 | G9: 2155 | H9: 1570 | I9: 2130 | N9: =IF(COUNT(B9:M9)=0,"",SUM(B9:M9)) -> 16250 | O9: =IF(COUNT(B9:M9)=0,"",AVERAGE(B9:M9)) -> 2031.25
A10: Convênio · Vida Care | B10: 1500 | C10: 1640 | D10: 1270 | E10: 1315 | F10: 1250 | G10: 1285 | H10: 1576 | I10: 1711 | N10: =IF(COUNT(B10:M10)=0,"",SUM(B10:M10)) -> 11547 | O10: =IF(COUNT(B10:M10)=0,"",AVERAGE(B10:M10)) -> 1443.375
A11: Outras entradas | B11: 0 | C11: 0 | D11: 0 | E11: 620 | F11: 0 | G11: 0 | H11: 0 | I11: 0 | N11: =IF(COUNT(B11:M11)=0,"",SUM(B11:M11)) -> 620 | O11: =IF(COUNT(B11:M11)=0,"",AVERAGE(B11:M11)) -> 77.5
A12: Receita total | B12: =IF(COUNT(B$6:B$11,B$14:B$21,B$24:B$27,B$30:B$31)=0,"",SUM(B6:B11)) -> 33270 | C12: =IF(COUNT(C$6:C$11,C$14:C$21,C$24:C$27,C$30:C$31)=0,"",SUM(C6:C11)) -> 24795 | D12: =IF(COUNT(D$6:D$11,D$14:D$21,D$24:D$27,D$30:D$31)=0,"",SUM(D6:D11)) -> 47880 | E12: =IF(COUNT(E$6:E$11,E$14:E$21,E$24:E$27,E$30:E$31)=0,"",SUM(E6:E11)) -> 39590 | F12: =IF(COUNT(F$6:F$11,F$14:F$21,F$24:F$27,F$30:F$31)=0,"",SUM(F6:F11)) -> 44760 | G12: =IF(COUNT(G$6:G$11,G$14:G$21,G$24:G$27,G$30:G$31)=0,"",SUM(G6:G11)) -> 43855 | H12: =IF(COUNT(H$6:H$11,H$14:H$21,H$24:H$27,H$30:H$31)=0,"",SUM(H6:H11)) -> 53101 | I12: =IF(COUNT(I$6:I$11,I$14:I$21,I$24:I$27,I$30:I$31)=0,"",SUM(I6:I11)) -> 50336 | ... M12: =IF(COUNT(M$6:M$11,M$14:M$21,M$24:M$27,M$30:M$31)=0,"",SUM(M6:M11)) | N12: =IF(COUNT(B12:M12)=0,"",SUM(B12:M12)) -> 337587 | O12: =IF(COUNT(B12:M12)=0,"",AVERAGE(B12:M12)) -> 42198.375
A13: Custos fixos
A14: Aluguel e condomínio | B14: 3900 | C14: 3900 | D14: 3900 | E14: 3900 | F14: 3900 | G14: 3900 | H14: 3900 | I14: 3900 | N14: =IF(COUNT(B14:M14)=0,"",SUM(B14:M14)) -> 31200 | O14: =IF(COUNT(B14:M14)=0,"",AVERAGE(B14:M14)) -> 3900
A15: Recepção (salário e encargos) | B15: 3100 | C15: 3100 | D15: 3100 | E15: 3100 | F15: 3100 | G15: 3100 | H15: 3100 | I15: 3100 | N15: =IF(COUNT(B15:M15)=0,"",SUM(B15:M15)) -> 24800 | O15: =IF(COUNT(B15:M15)=0,"",AVERAGE(B15:M15)) -> 3100
A16: Contador | B16: 600 | C16: 600 | D16: 600 | E16: 600 | F16: 600 | G16: 600 | H16: 600 | I16: 600 | N16: =IF(COUNT(B16:M16)=0,"",SUM(B16:M16)) -> 4800 | O16: =IF(COUNT(B16:M16)=0,"",AVERAGE(B16:M16)) -> 600
A17: Sistema de agenda e assinaturas | B17: 300 | C17: 300 | D17: 300 | E17: 300 | F17: 300 | G17: 300 | H17: 300 | I17: 300 | N17: =IF(COUNT(B17:M17)=0,"",SUM(B17:M17)) -> 2400 | O17: =IF(COUNT(B17:M17)=0,"",AVERAGE(B17:M17)) -> 300
A18: Energia, água, internet e telefone | B18: 550 | C18: 550 | D18: 550 | E18: 550 | F18: 550 | G18: 550 | H18: 550 | I18: 550 | N18: =IF(COUNT(B18:M18)=0,"",SUM(B18:M18)) -> 4400 | O18: =IF(COUNT(B18:M18)=0,"",AVERAGE(B18:M18)) -> 550
A19: Limpeza e material de escritório | B19: 450 | C19: 450 | D19: 450 | E19: 450 | F19: 450 | G19: 450 | H19: 450 | I19: 450 | N19: =IF(COUNT(B19:M19)=0,"",SUM(B19:M19)) -> 3600 | O19: =IF(COUNT(B19:M19)=0,"",AVERAGE(B19:M19)) -> 450
A20: Marketing e site | B20: 650 | C20: 650 | D20: 650 | E20: 650 | F20: 650 | G20: 650 | H20: 650 | I20: 650 | N20: =IF(COUNT(B20:M20)=0,"",SUM(B20:M20)) -> 5200 | O20: =IF(COUNT(B20:M20)=0,"",AVERAGE(B20:M20)) -> 650
A21: Anuidade CRM, seguro e cursos | B21: 450 | C21: 450 | D21: 450 | E21: 450 | F21: 450 | G21: 450 | H21: 450 | I21: 450 | N21: =IF(COUNT(B21:M21)=0,"",SUM(B21:M21)) -> 3600 | O21: =IF(COUNT(B21:M21)=0,"",AVERAGE(B21:M21)) -> 450
A22: Total de custos fixos | B22: =IF(COUNT(B$6:B$11,B$14:B$21,B$24:B$27,B$30:B$31)=0,"",SUM(B14:B21)) -> 10000 | C22: =IF(COUNT(C$6:C$11,C$14:C$21,C$24:C$27,C$30:C$31)=0,"",SUM(C14:C21)) -> 10000 | D22: =IF(COUNT(D$6:D$11,D$14:D$21,D$24:D$27,D$30:D$31)=0,"",SUM(D14:D21)) -> 10000 | E22: =IF(COUNT(E$6:E$11,E$14:E$21,E$24:E$27,E$30:E$31)=0,"",SUM(E14:E21)) -> 10000 | F22: =IF(COUNT(F$6:F$11,F$14:F$21,F$24:F$27,F$30:F$31)=0,"",SUM(F14:F21)) -> 10000 | G22: =IF(COUNT(G$6:G$11,G$14:G$21,G$24:G$27,G$30:G$31)=0,"",SUM(G14:G21)) -> 10000 | H22: =IF(COUNT(H$6:H$11,H$14:H$21,H$24:H$27,H$30:H$31)=0,"",SUM(H14:H21)) -> 10000 | I22: =IF(COUNT(I$6:I$11,I$14:I$21,I$24:I$27,I$30:I$31)=0,"",SUM(I14:I21)) -> 10000 | ... M22: =IF(COUNT(M$6:M$11,M$14:M$21,M$24:M$27,M$30:M$31)=0,"",SUM(M14:M21)) | N22: =IF(COUNT(B22:M22)=0,"",SUM(B22:M22)) -> 80000 | O22: =IF(COUNT(B22:M22)=0,"",AVERAGE(B22:M22)) -> 10000
A23: Despesas variáveis (materiais, taxas de cartão, repasse, manutenção)
A24: Materiais e insumos de atendimento | B24: 1120 | C24: 820 | D24: 1550 | E24: 1260 | F24: 1420 | G24: 1510 | H24: 1300 | I24: 1380 | N24: =IF(COUNT(B24:M24)=0,"",SUM(B24:M24)) -> 10360 | O24: =IF(COUNT(B24:M24)=0,"",AVERAGE(B24:M24)) -> 1295
A25: Taxas de cartão | B25: 350.56 | C25: 265.28 | D25: 533.25 | E25: 435.7 | F25: 464.12 | G25: 354.91 | H25: 641.77 | I25: 484.12 | N25: =IF(COUNT(B25:M25)=0,"",SUM(B25:M25)) -> 3529.71 | O25: =IF(COUNT(B25:M25)=0,"",AVERAGE(B25:M25)) -> 441.21375
A26: Repasse à médica parceira | B26: 3100 | C26: 3725 | D26: 3255 | E26: 6050 | F26: 4385 | G26: 5245 | H26: 4720 | I26: 4845 | N26: =IF(COUNT(B26:M26)=0,"",SUM(B26:M26)) -> 35325 | O26: =IF(COUNT(B26:M26)=0,"",AVERAGE(B26:M26)) -> 4415.625
A27: Manutenção de equipamentos | B27: 0 | C27: 0 | D27: 0 | E27: 0 | F27: 800 | G27: 0 | H27: 0 | I27: 450 | N27: =IF(COUNT(B27:M27)=0,"",SUM(B27:M27)) -> 1250 | O27: =IF(COUNT(B27:M27)=0,"",AVERAGE(B27:M27)) -> 156.25
A28: Total de despesas variáveis | B28: =IF(COUNT(B$6:B$11,B$14:B$21,B$24:B$27,B$30:B$31)=0,"",SUM(B24:B27)) -> 4570.56 | C28: =IF(COUNT(C$6:C$11,C$14:C$21,C$24:C$27,C$30:C$31)=0,"",SUM(C24:C27)) -> 4810.28 | D28: =IF(COUNT(D$6:D$11,D$14:D$21,D$24:D$27,D$30:D$31)=0,"",SUM(D24:D27)) -> 5338.25 | E28: =IF(COUNT(E$6:E$11,E$14:E$21,E$24:E$27,E$30:E$31)=0,"",SUM(E24:E27)) -> 7745.7 | F28: =IF(COUNT(F$6:F$11,F$14:F$21,F$24:F$27,F$30:F$31)=0,"",SUM(F24:F27)) -> 7069.12 | G28: =IF(COUNT(G$6:G$11,G$14:G$21,G$24:G$27,G$30:G$31)=0,"",SUM(G24:G27)) -> 7109.91 | H28: =IF(COUNT(H$6:H$11,H$14:H$21,H$24:H$27,H$30:H$31)=0,"",SUM(H24:H27)) -> 6661.77 | I28: =IF(COUNT(I$6:I$11,I$14:I$21,I$24:I$27,I$30:I$31)=0,"",SUM(I24:I27)) -> 7159.12 | ... M28: =IF(COUNT(M$6:M$11,M$14:M$21,M$24:M$27,M$30:M$31)=0,"",SUM(M24:M27)) | N28: =IF(COUNT(B28:M28)=0,"",SUM(B28:M28)) -> 50464.71 | O28: =IF(COUNT(B28:M28)=0,"",AVERAGE(B28:M28)) -> 6308.0887
A29: Pró-labore fixo dos sócios
A30: Dra. Carolina Mendes | B30: 9000 | C30: 9000 | D30: 9000 | E30: 9000 | F30: 9000 | G30: 9000 | H30: 9000 | I30: 9000 | N30: =IF(COUNT(B30:M30)=0,"",SUM(B30:M30)) -> 72000 | O30: =IF(COUNT(B30:M30)=0,"",AVERAGE(B30:M30)) -> 9000
A31: Dr. Paulo Andrade | B31: 9000 | C31: 9000 | D31: 9000 | E31: 9000 | F31: 9000 | G31: 9000 | H31: 9000 | I31: 9000 | N31: =IF(COUNT(B31:M31)=0,"",SUM(B31:M31)) -> 72000 | O31: =IF(COUNT(B31:M31)=0,"",AVERAGE(B31:M31)) -> 9000
A32: Total de pró-labore | B32: =IF(COUNT(B$6:B$11,B$14:B$21,B$24:B$27,B$30:B$31)=0,"",SUM(B30:B31)) -> 18000 | C32: =IF(COUNT(C$6:C$11,C$14:C$21,C$24:C$27,C$30:C$31)=0,"",SUM(C30:C31)) -> 18000 | D32: =IF(COUNT(D$6:D$11,D$14:D$21,D$24:D$27,D$30:D$31)=0,"",SUM(D30:D31)) -> 18000 | E32: =IF(COUNT(E$6:E$11,E$14:E$21,E$24:E$27,E$30:E$31)=0,"",SUM(E30:E31)) -> 18000 | F32: =IF(COUNT(F$6:F$11,F$14:F$21,F$24:F$27,F$30:F$31)=0,"",SUM(F30:F31)) -> 18000 | G32: =IF(COUNT(G$6:G$11,G$14:G$21,G$24:G$27,G$30:G$31)=0,"",SUM(G30:G31)) -> 18000 | H32: =IF(COUNT(H$6:H$11,H$14:H$21,H$24:H$27,H$30:H$31)=0,"",SUM(H30:H31)) -> 18000 | I32: =IF(COUNT(I$6:I$11,I$14:I$21,I$24:I$27,I$30:I$31)=0,"",SUM(I30:I31)) -> 18000 | ... M32: =IF(COUNT(M$6:M$11,M$14:M$21,M$24:M$27,M$30:M$31)=0,"",SUM(M30:M31)) | N32: =IF(COUNT(B32:M32)=0,"",SUM(B32:M32)) -> 144000 | O32: =IF(COUNT(B32:M32)=0,"",AVERAGE(B32:M32)) -> 18000
A33: Impostos provisionados (% da receita, Config) | B33: =IF(B12="","",ROUND(B12*Config!$B$7,0)) -> 3660 | C33: =IF(C12="","",ROUND(C12*Config!$B$7,0)) -> 2727 | D33: =IF(D12="","",ROUND(D12*Config!$B$7,0)) -> 5267 | E33: =IF(E12="","",ROUND(E12*Config!$B$7,0)) -> 4355 | F33: =IF(F12="","",ROUND(F12*Config!$B$7,0)) -> 4924 | G33: =IF(G12="","",ROUND(G12*Config!$B$7,0)) -> 4824 | H33: =IF(H12="","",ROUND(H12*Config!$B$7,0)) -> 5841 | I33: =IF(I12="","",ROUND(I12*Config!$B$7,0)) -> 5537 | ... M33: =IF(M12="","",ROUND(M12*Config!$B$7,0)) | N33: =IF(COUNT(B33:M33)=0,"",SUM(B33:M33)) -> 37135 | O33: =IF(COUNT(B33:M33)=0,"",AVERAGE(B33:M33)) -> 4641.875
A34: Total de saídas (custos + variáveis + pró-labore + impostos) | B34: =IF(B12="","",B22+B28+B32+B33) -> 36230.56 | C34: =IF(C12="","",C22+C28+C32+C33) -> 35537.28 | D34: =IF(D12="","",D22+D28+D32+D33) -> 38605.25 | E34: =IF(E12="","",E22+E28+E32+E33) -> 40100.7 | F34: =IF(F12="","",F22+F28+F32+F33) -> 39993.12 | G34: =IF(G12="","",G22+G28+G32+G33) -> 39933.91 | H34: =IF(H12="","",H22+H28+H32+H33) -> 40502.77 | I34: =IF(I12="","",I22+I28+I32+I33) -> 40696.12 | ... M34: =IF(M12="","",M22+M28+M32+M33) | N34: =IF(COUNT(B34:M34)=0,"",SUM(B34:M34)) -> 311599.71 | O34: =IF(COUNT(B34:M34)=0,"",AVERAGE(B34:M34)) -> 38949.964
A35: Resultado do mês (receita − saídas) | B35: =IF(B12="","",B12-B34) -> -2960.56 | C35: =IF(C12="","",C12-C34) -> -10742.28 | D35: =IF(D12="","",D12-D34) -> 9274.75 | E35: =IF(E12="","",E12-E34) -> -510.7 | F35: =IF(F12="","",F12-F34) -> 4766.88 | G35: =IF(G12="","",G12-G34) -> 3921.09 | H35: =IF(H12="","",H12-H34) -> 12598.23 | I35: =IF(I12="","",I12-I34) -> 9639.88 | ... M35: =IF(M12="","",M12-M34) | N35: =IF(COUNT(B35:M35)=0,"",SUM(B35:M35)) -> 25987.29 | O35: =IF(COUNT(B35:M35)=0,"",AVERAGE(B35:M35)) -> 3248.4113
A36: Margem (resultado ÷ receita) | B36: =IF(OR(B12="",B12=0),"",B35/B12) -> -0.088985873 | C36: =IF(OR(C12="",C12=0),"",C35/C12) -> -0.4332438 | D36: =IF(OR(D12="",D12=0),"",D35/D12) -> 0.19370823 | E36: =IF(OR(E12="",E12=0),"",E35/E12) -> -0.012899722 | F36: =IF(OR(F12="",F12=0),"",F35/F12) -> 0.10649866 | G36: =IF(OR(G12="",G12=0),"",G35/G12) -> 0.089410329 | H36: =IF(OR(H12="",H12=0),"",H35/H12) -> 0.23725033 | I36: =IF(OR(I12="",I12=0),"",I35/I12) -> 0.19151065 | ... N36: =IF(OR(N12="",N12=0),"",N35/N12) -> 0.076979534 | O36: =IF(COUNT(B36:M36)=0,"",AVERAGE(B36:M36)) -> 0.035406101
A38: Receita por categoria: copie de "De onde veio o dinheiro" (Painel da 09). Convênio entra quando o lote é pago (menos a glosa); cartão entra pelo bruto e a taxa vai em "Taxas de cartão". Custos e despesas: de "Para onde foi o dinheiro".
A39: Impostos são provisão (11 % do que entrou no mês), não a guia paga; no caixa aparece a guia do mês anterior. Retiradas extras, distribuição de lucro e despesas pessoais dos sócios não entram aqui: são movimentos sócio × clínica (planilha 11). Resultado negativo fica vermelho.
A40: Os valores de exemplo (janeiro a agosto de 2026, meses fechados) são os totais por categoria do Painel do Caixa (09) com Pago? = Sim; setembro fica em branco porque está em andamento. O Painel da clínica (17) e o Resumo do mês (20) usam estes mesmos números.

Sheet Previsto
A1: Previsto para o ano
A2: Preencha o que espera de receita, custos fixos, despesas variáveis e pró-labore em cada mês. O Painel compara o realizado com este previsto.
A4: Linha | B4: Jan | C4: Fev | D4: Mar | E4: Abr | F4: Mai | G4: Jun | H4: Jul | I4: Ago | J4: Set | K4: Out | L4: Nov | M4: Dez | N4: Total do ano
A5: Receita prevista | B5: 36000 | C5: 32000 | D5: 42000 | E5: 42000 | F5: 44000 | G5: 44000 | H5: 46000 | I5: 46000 | J5: 46000 | K5: 46000 | L5: 44000 | M5: 40000 | N5: =IF(COUNT(B5:M5)=0,"",SUM(B5:M5)) -> 508000
A6: Custos fixos previstos | B6: 10000 | C6: 10000 | D6: 10000 | E6: 10000 | F6: 10000 | G6: 10000 | H6: 10000 | I6: 10000 | J6: 10000 | K6: 10000 | L6: 10000 | M6: 10000 | N6: =IF(COUNT(B6:M6)=0,"",SUM(B6:M6)) -> 120000
A7: Despesas variáveis previstas | B7: 6000 | C7: 6000 | D7: 6000 | E7: 6000 | F7: 6000 | G7: 6000 | H7: 6000 | I7: 6000 | J7: 6000 | K7: 6000 | L7: 6000 | M7: 6000 | N7: =IF(COUNT(B7:M7)=0,"",SUM(B7:M7)) -> 72000
A8: Pró-labore previsto | B8: 18000 | C8: 18000 | D8: 18000 | E8: 18000 | F8: 18000 | G8: 18000 | H8: 18000 | I8: 18000 | J8: 18000 | K8: 18000 | L8: 18000 | M8: 18000 | N8: =IF(COUNT(B8:M8)=0,"",SUM(B8:M8)) -> 216000
A9: Impostos previstos (% da receita, Config) | B9: =IF(B5="","",ROUND(B5*Config!$B$7,0)) -> 3960 | C9: =IF(C5="","",ROUND(C5*Config!$B$7,0)) -> 3520 | D9: =IF(D5="","",ROUND(D5*Config!$B$7,0)) -> 4620 | E9: =IF(E5="","",ROUND(E5*Config!$B$7,0)) -> 4620 | F9: =IF(F5="","",ROUND(F5*Config!$B$7,0)) -> 4840 | G9: =IF(G5="","",ROUND(G5*Config!$B$7,0)) -> 4840 | H9: =IF(H5="","",ROUND(H5*Config!$B$7,0)) -> 5060 | I9: =IF(I5="","",ROUND(I5*Config!$B$7,0)) -> 5060 | ... M9: =IF(M5="","",ROUND(M5*Config!$B$7,0)) -> 4400 | N9: =IF(COUNT(B9:M9)=0,"",SUM(B9:M9)) -> 55880
A10: Saídas previstas | B10: =IF(B5="","",N(B6)+N(B7)+N(B8)+B9) -> 37960 | C10: =IF(C5="","",N(C6)+N(C7)+N(C8)+C9) -> 37520 | D10: =IF(D5="","",N(D6)+N(D7)+N(D8)+D9) -> 38620 | E10: =IF(E5="","",N(E6)+N(E7)+N(E8)+E9) -> 38620 | F10: =IF(F5="","",N(F6)+N(F7)+N(F8)+F9) -> 38840 | G10: =IF(G5="","",N(G6)+N(G7)+N(G8)+G9) -> 38840 | H10: =IF(H5="","",N(H6)+N(H7)+N(H8)+H9) -> 39060 | I10: =IF(I5="","",N(I6)+N(I7)+N(I8)+I9) -> 39060 | ... M10: =IF(M5="","",N(M6)+N(M7)+N(M8)+M9) -> 38400 | N10: =IF(COUNT(B10:M10)=0,"",SUM(B10:M10)) -> 463880
A11: Resultado previsto | B11: =IF(B5="","",B5-B10) -> -1960 | C11: =IF(C5="","",C5-C10) -> -5520 | D11: =IF(D5="","",D5-D10) -> 3380 | E11: =IF(E5="","",E5-E10) -> 3380 | F11: =IF(F5="","",F5-F10) -> 5160 | G11: =IF(G5="","",G5-G10) -> 5160 | H11: =IF(H5="","",H5-H10) -> 6940 | I11: =IF(I5="","",I5-I10) -> 6940 | ... M11: =IF(M5="","",M5-M10) -> 1600 | N11: =IF(COUNT(B11:M11)=0,"",SUM(B11:M11)) -> 44120
A12: Margem prevista | B12: =IF(OR(B5="",B5=0),"",B11/B5) -> -0.054444444 | C12: =IF(OR(C5="",C5=0),"",C11/C5) -> -0.1725 | D12: =IF(OR(D5="",D5=0),"",D11/D5) -> 0.08047619 | E12: =IF(OR(E5="",E5=0),"",E11/E5) -> 0.08047619 | F12: =IF(OR(F5="",F5=0),"",F11/F5) -> 0.11727273 | G12: =IF(OR(G5="",G5=0),"",G11/G5) -> 0.11727273 | H12: =IF(OR(H5="",H5=0),"",H11/H5) -> 0.15086957 | I12: =IF(OR(I5="",I5=0),"",I11/I5) -> 0.15086957 | ... N12: =IF(OR(N5="",N5=0),"",N11/N5) -> 0.086850394
A14: Uma boa previsão de custos fixos é a média dos últimos três meses; de receita, a produção típica da agenda (01) descontando glosa e prazo de convênio; de variáveis, repasse + materiais + taxas de cartão de um mês normal. Janeiro e julho costumam ser mais fracos.
