Workbook

Sheet Como usar
A1: Resumo do Mês
A2: Kit de Gestão para Médicos · Seu Sócio Gestor · versão 1.0 (setembro de 2026)
A4: O que esta planilha faz | B4: Você digita até 12 indicadores do mês (valor, mês anterior, meta). Ela calcula variação e situação, monta o Painel e escreve sozinha as frases do mês, os destaques (maior melhora, maior piora, mais longe da meta, respeitando se maior ou menor é melhor) e um bloco único para colar na IA ou mandar ao sócio e ao contador.
A5: Passo 1 | B5: Em Config, preencha a clínica, o ano e escolha o mês do resumo (o último mês fechado; no exemplo, agosto de 2026).
A6: Passo 2 | B6: Em Indicadores, troque os exemplos pelos seus (de cima para baixo, sem pular linha): nome, unidade, casas decimais, meta e se maior é melhor. Depois, o valor do mês anterior e do mês atual, copiados do Painel da clínica (17, aba Histórico) e do Resultado mensal (18). Em %, digite 5,1 e não 0,051.
A7: Passo 3 | B7: Abra Painel: cada indicador com mês, mês anterior, variação (em p.p. para indicadores em %), meta e situação (verde no alvo, vermelho fora).
A8: Passo 4 | B8: Abra Resumo: as frases já estão escritas. Escreva as observações do mês na célula amarela, copie o bloco único e cole no prompt "Painel 01 · Explicar o mês ao sócio" (para o sócio) ou "Caixa 04 · Preparar a reunião mensal com o contador" da biblioteca do kit.
A9: Todo mês | B9: Em Indicadores, mova o "Mês atual" para "Mês anterior", digite os novos valores e troque o mês em Config. O resto se refaz sozinho.
A10: Cuidado com dados | B10: O bloco só tem totais da clínica. Não cole nome de paciente, contato ou qualquer informação clínica na IA: veja o guia LGPD do kit.
A11: Legenda | B11: Células amarelas: você preenche. Brancas: calculadas. Não é preciso mexer em nada fora do amarelo.
A12: Proteção | B12: Fórmulas protegidas sem senha. Para editar: Revisar > Desproteger planilha (Excel) ou Dados > Proteger intervalos (Google Sheets).
A13: Requisitos | B13: Excel 2016 ou mais novo, Microsoft 365 ou Google Sheets (só funções do Excel 2007+; nada de MÍNIMOSES, MÁXIMOSES ou UNIRTEXTO). No celular abre nos aplicativos; para preencher, use o computador.
A14: Dados de pacientes | B14: Guarde só o que a gestão precisa (nome, contato, valor, data). Nada de diagnóstico, prontuário ou exame nestas planilhas: o kit é gestão, não é prontuário. Veja o guia LGPD do kit antes de colar qualquer tabela em uma IA.
A15: Google Sheets | B15: Faça upload no Google Drive e abra com o Google Sheets. Fórmulas, listas, cores, semáforos e gráficos funcionam: as regras de cor que dependem do mês escolhido em Config usam INDIRECT, que é a forma que o Sheets aceita para regra condicional apontar para outra aba.
... A18: Suporte | B18: suporte@seusociogestor.com.br · resposta em até 5 dias úteis · reembolso em até 7 dias pelo mesmo canal.

Sheet Painel
A1: =Config!B4&" · Resumo do mês · "&Config!B6&" de "&Config!B5 -> Clínica Vida Plena (exemplo fictício) · Resumo do mês · Agosto de 2026
A2: Nada para digitar aqui. Escolha o mês em Config; os números vêm de Indicadores. Variação de indicadores em % é em pontos percentuais (p.p.).
A4: Indicador | B4: Mês | C4: Mês anterior | D4: Variação | E4: Meta | F4: Vs. meta | G4: Situação | H4: Unidade
A5: =IF(Indicadores!A5="","",Indicadores!A5) -> Entrou no mês (recebimentos) | B5: =IF(Q5="","",IF(Indicadores!B5="R$","R$ ","")&FIXED(Q5,N5)&IF(Indicadores!B5="%","%",IF(OR(Indicadores!B5="R$",Indicadores!B5="",Indicadores!B5="un"),""," "&Indicadores!B5))) -> R$ 55.841 | C5: =IF(R5="","",IF(Indicadores!B5="R$","R$ ","")&FIXED(R5,N5)&IF(Indicadores!B5="%","%",IF(OR(Indicadores!B5="R$",Indicadores!B5="",Indicadores!B5="un"),""," "&Indicadores!B5))) -> R$ 44.471 | D5: =IF(T5="","",IF(T5>=0,"+","")&IF(Indicadores!B5="%",FIXED(T5,1)&" p.p.",FIXED(T5*100,1)&"%")) -> +25,6% | E5: =IF(S5="","",IF(Indicadores!B5="R$","R$ ","")&FIXED(S5,N5)&IF(Indicadores!B5="%","%",IF(OR(Indicadores!B5="R$",Indicadores!B5="",Indicadores!B5="un"),""," "&Indicadores!B5))) -> R$ 46.000 | F5: =IF(U5="","",IF(U5>=0,"+","")&IF(Indicadores!B5="%",FIXED(U5,1)&" p.p.",FIXED(U5*100,1)&"%")) -> +21,4% | G5: =IF(OR(Q5="",S5=""),"",IF(Indicadores!E5="Não",IF(Q5<=S5,"No alvo","Acima da meta"),IF(Q5>=S5,"No alvo","Abaixo da meta"))) -> No alvo | H5: =IF(Indicadores!A5="","",Indicadores!B5) -> R$ | N5: =IF(Indicadores!C5="",2,Indicadores!C5) -> 0 | O5: =IF(OR(U5="",G5="",G5="No alvo"),"",IF(Indicadores!E5="Não",U5,-U5)) | P5: =IF(T5="","",IF(Indicadores!E5="Não",-T5,T5)) -> 0.25567224 | Q5: =IF(OR(Indicadores!A5="",Indicadores!G5=""),"",Indicadores!G5) -> 55841 | R5: =IF(OR(Indicadores!A5="",Indicadores!F5=""),"",Indicadores!F5) -> 44471 | S5: =IF(OR(Indicadores!A5="",Indicadores!D5=""),"",Indicadores!D5) -> 46000 | T5: =IF(OR(Q5="",R5=""),"",IF(Indicadores!B5="%",Q5-R5,IF(R5=0,"",(Q5-R5)/ABS(R5)))) -> 0.25567224 | U5: =IF(OR(Q5="",S5=""),"",IF(Indicadores!B5="%",Q5-S5,IF(S5=0,"",(Q5-S5)/ABS(S5)))) -> 0.21393478
A6: =IF(Indicadores!A6="","",Indicadores!A6) -> Saídas do mês (custos, variáveis, pró-labore, provisões e impostos) | B6: =IF(Q6="","",IF(Indicadores!B6="R$","R$ ","")&FIXED(Q6,N6)&IF(Indicadores!B6="%","%",IF(OR(Indicadores!B6="R$",Indicadores!B6="",Indicadores!B6="un"),""," "&Indicadores!B6))) -> R$ 43.462 | C6: =IF(R6="","",IF(Indicadores!B6="R$","R$ ","")&FIXED(R6,N6)&IF(Indicadores!B6="%","%",IF(OR(Indicadores!B6="R$",Indicadores!B6="",Indicadores!B6="un"),""," "&Indicadores!B6))) -> R$ 41.221 | D6: =IF(T6="","",IF(T6>=0,"+","")&IF(Indicadores!B6="%",FIXED(T6,1)&" p.p.",FIXED(T6*100,1)&"%")) -> +5,4% | E6: =IF(S6="","",IF(Indicadores!B6="R$","R$ ","")&FIXED(S6,N6)&IF(Indicadores!B6="%","%",IF(OR(Indicadores!B6="R$",Indicadores!B6="",Indicadores!B6="un"),""," "&Indicadores!B6))) -> R$ 44.000 | F6: =IF(U6="","",IF(U6>=0,"+","")&IF(Indicadores!B6="%",FIXED(U6,1)&" p.p.",FIXED(U6*100,1)&"%")) -> -1,2% | G6: =IF(OR(Q6="",S6=""),"",IF(Indicadores!E6="Não",IF(Q6<=S6,"No alvo","Acima da meta"),IF(Q6>=S6,"No alvo","Abaixo da meta"))) -> No alvo | H6: =IF(Indicadores!A6="","",Indicadores!B6) -> R$ | N6: =IF(Indicadores!C6="",2,Indicadores!C6) -> 0 | O6: =IF(OR(U6="",G6="",G6="No alvo"),"",IF(Indicadores!E6="Não",U6,-U6)) | P6: =IF(T6="","",IF(Indicadores!E6="Não",-T6,T6)) -> -0.054365765 | Q6: =IF(OR(Indicadores!A6="",Indicadores!G6=""),"",Indicadores!G6) -> 43461.6 | R6: =IF(OR(Indicadores!A6="",Indicadores!F6=""),"",Indicadores!F6) -> 41220.61 | S6: =IF(OR(Indicadores!A6="",Indicadores!D6=""),"",Indicadores!D6) -> 44000 | T6: =IF(OR(Q6="",R6=""),"",IF(Indicadores!B6="%",Q6-R6,IF(R6=0,"",(Q6-R6)/ABS(R6)))) -> 0.054365765 | U6: =IF(OR(Q6="",S6=""),"",IF(Indicadores!B6="%",Q6-S6,IF(S6=0,"",(Q6-S6)/ABS(S6)))) -> -0.012236364
A7: =IF(Indicadores!A7="","",Indicadores!A7) -> Resultado do mês | B7: =IF(Q7="","",IF(Indicadores!B7="R$","R$ ","")&FIXED(Q7,N7)&IF(Indicadores!B7="%","%",IF(OR(Indicadores!B7="R$",Indicadores!B7="",Indicadores!B7="un"),""," "&Indicadores!B7))) -> R$ 12.379 | C7: =IF(R7="","",IF(Indicadores!B7="R$","R$ ","")&FIXED(R7,N7)&IF(Indicadores!B7="%","%",IF(OR(Indicadores!B7="R$",Indicadores!B7="",Indicadores!B7="un"),""," "&Indicadores!B7))) -> R$ 3.250 | D7: =IF(T7="","",IF(T7>=0,"+","")&IF(Indicadores!B7="%",FIXED(T7,1)&" p.p.",FIXED(T7*100,1)&"%")) -> +280,9% | E7: =IF(S7="","",IF(Indicadores!B7="R$","R$ ","")&FIXED(S7,N7)&IF(Indicadores!B7="%","%",IF(OR(Indicadores!B7="R$",Indicadores!B7="",Indicadores!B7="un"),""," "&Indicadores!B7))) -> R$ 5.000 | F7: =IF(U7="","",IF(U7>=0,"+","")&IF(Indicadores!B7="%",FIXED(U7,1)&" p.p.",FIXED(U7*100,1)&"%")) -> +147,6% | G7: =IF(OR(Q7="",S7=""),"",IF(Indicadores!E7="Não",IF(Q7<=S7,"No alvo","Acima da meta"),IF(Q7>=S7,"No alvo","Abaixo da meta"))) -> No alvo | H7: =IF(Indicadores!A7="","",Indicadores!B7) -> R$ | N7: =IF(Indicadores!C7="",2,Indicadores!C7) -> 0 | O7: =IF(OR(U7="",G7="",G7="No alvo"),"",IF(Indicadores!E7="Não",U7,-U7)) | P7: =IF(T7="","",IF(Indicadores!E7="Não",-T7,T7)) -> 2.8085891 | Q7: =IF(OR(Indicadores!A7="",Indicadores!G7=""),"",Indicadores!G7) -> 12379.4 | R7: =IF(OR(Indicadores!A7="",Indicadores!F7=""),"",Indicadores!F7) -> 3250.39 | S7: =IF(OR(Indicadores!A7="",Indicadores!D7=""),"",Indicadores!D7) -> 5000 | T7: =IF(OR(Q7="",R7=""),"",IF(Indicadores!B7="%",Q7-R7,IF(R7=0,"",(Q7-R7)/ABS(R7)))) -> 2.8085891 | U7: =IF(OR(Q7="",S7=""),"",IF(Indicadores!B7="%",Q7-S7,IF(S7=0,"",(Q7-S7)/ABS(S7)))) -> 1.47588
A8: =IF(Indicadores!A8="","",Indicadores!A8) -> Margem do mês | B8: =IF(Q8="","",IF(Indicadores!B8="R$","R$ ","")&FIXED(Q8,N8)&IF(Indicadores!B8="%","%",IF(OR(Indicadores!B8="R$",Indicadores!B8="",Indicadores!B8="un"),""," "&Indicadores!B8))) -> 22,2% | C8: =IF(R8="","",IF(Indicadores!B8="R$","R$ ","")&FIXED(R8,N8)&IF(Indicadores!B8="%","%",IF(OR(Indicadores!B8="R$",Indicadores!B8="",Indicadores!B8="un"),""," "&Indicadores!B8))) -> 7,3% | D8: =IF(T8="","",IF(T8>=0,"+","")&IF(Indicadores!B8="%",FIXED(T8,1)&" p.p.",FIXED(T8*100,1)&"%")) -> +14,9 p.p. | E8: =IF(S8="","",IF(Indicadores!B8="R$","R$ ","")&FIXED(S8,N8)&IF(Indicadores!B8="%","%",IF(OR(Indicadores!B8="R$",Indicadores!B8="",Indicadores!B8="un"),""," "&Indicadores!B8))) -> 12,0% | F8: =IF(U8="","",IF(U8>=0,"+","")&IF(Indicadores!B8="%",FIXED(U8,1)&" p.p.",FIXED(U8*100,1)&"%")) -> +10,2 p.p. | G8: =IF(OR(Q8="",S8=""),"",IF(Indicadores!E8="Não",IF(Q8<=S8,"No alvo","Acima da meta"),IF(Q8>=S8,"No alvo","Abaixo da meta"))) -> No alvo | H8: =IF(Indicadores!A8="","",Indicadores!B8) -> % | N8: =IF(Indicadores!C8="",2,Indicadores!C8) -> 1 | O8: =IF(OR(U8="",G8="",G8="No alvo"),"",IF(Indicadores!E8="Não",U8,-U8)) | P8: =IF(T8="","",IF(Indicadores!E8="Não",-T8,T8)) -> 14.9 | Q8: =IF(OR(Indicadores!A8="",Indicadores!G8=""),"",Indicadores!G8) -> 22.2 | R8: =IF(OR(Indicadores!A8="",Indicadores!F8=""),"",Indicadores!F8) -> 7.3 | S8: =IF(OR(Indicadores!A8="",Indicadores!D8=""),"",Indicadores!D8) -> 12 | T8: =IF(OR(Q8="",R8=""),"",IF(Indicadores!B8="%",Q8-R8,IF(R8=0,"",(Q8-R8)/ABS(R8)))) -> 14.9 | U8: =IF(OR(Q8="",S8=""),"",IF(Indicadores!B8="%",Q8-S8,IF(S8=0,"",(Q8-S8)/ABS(S8)))) -> 10.2
A9: =IF(Indicadores!A9="","",Indicadores!A9) -> Ocupação da agenda | B9: =IF(Q9="","",IF(Indicadores!B9="R$","R$ ","")&FIXED(Q9,N9)&IF(Indicadores!B9="%","%",IF(OR(Indicadores!B9="R$",Indicadores!B9="",Indicadores!B9="un"),""," "&Indicadores!B9))) -> 70,4% | C9: =IF(R9="","",IF(Indicadores!B9="R$","R$ ","")&FIXED(R9,N9)&IF(Indicadores!B9="%","%",IF(OR(Indicadores!B9="R$",Indicadores!B9="",Indicadores!B9="un"),""," "&Indicadores!B9))) -> 71,7% | D9: =IF(T9="","",IF(T9>=0,"+","")&IF(Indicadores!B9="%",FIXED(T9,1)&" p.p.",FIXED(T9*100,1)&"%")) -> -1,3 p.p. | E9: =IF(S9="","",IF(Indicadores!B9="R$","R$ ","")&FIXED(S9,N9)&IF(Indicadores!B9="%","%",IF(OR(Indicadores!B9="R$",Indicadores!B9="",Indicadores!B9="un"),""," "&Indicadores!B9))) -> 75,0% | F9: =IF(U9="","",IF(U9>=0,"+","")&IF(Indicadores!B9="%",FIXED(U9,1)&" p.p.",FIXED(U9*100,1)&"%")) -> -4,6 p.p. | G9: =IF(OR(Q9="",S9=""),"",IF(Indicadores!E9="Não",IF(Q9<=S9,"No alvo","Acima da meta"),IF(Q9>=S9,"No alvo","Abaixo da meta"))) -> Abaixo da meta | H9: =IF(Indicadores!A9="","",Indicadores!B9) -> % | N9: =IF(Indicadores!C9="",2,Indicadores!C9) -> 1 | O9: =IF(OR(U9="",G9="",G9="No alvo"),"",IF(Indicadores!E9="Não",U9,-U9)) -> 4.6 | P9: =IF(T9="","",IF(Indicadores!E9="Não",-T9,T9)) -> -1.3 | Q9: =IF(OR(Indicadores!A9="",Indicadores!G9=""),"",Indicadores!G9) -> 70.4 | R9: =IF(OR(Indicadores!A9="",Indicadores!F9=""),"",Indicadores!F9) -> 71.7 | S9: =IF(OR(Indicadores!A9="",Indicadores!D9=""),"",Indicadores!D9) -> 75 | T9: =IF(OR(Q9="",R9=""),"",IF(Indicadores!B9="%",Q9-R9,IF(R9=0,"",(Q9-R9)/ABS(R9)))) -> -1.3 | U9: =IF(OR(Q9="",S9=""),"",IF(Indicadores!B9="%",Q9-S9,IF(S9=0,"",(Q9-S9)/ABS(S9)))) -> -4.6
A10: =IF(Indicadores!A10="","",Indicadores!A10) -> Taxa de falta | B10: =IF(Q10="","",IF(Indicadores!B10="R$","R$ ","")&FIXED(Q10,N10)&IF(Indicadores!B10="%","%",IF(OR(Indicadores!B10="R$",Indicadores!B10="",Indicadores!B10="un"),""," "&Indicadores!B10))) -> 8,4% | C10: =IF(R10="","",IF(Indicadores!B10="R$","R$ ","")&FIXED(R10,N10)&IF(Indicadores!B10="%","%",IF(OR(Indicadores!B10="R$",Indicadores!B10="",Indicadores!B10="un"),""," "&Indicadores!B10))) -> 8,8% | D10: =IF(T10="","",IF(T10>=0,"+","")&IF(Indicadores!B10="%",FIXED(T10,1)&" p.p.",FIXED(T10*100,1)&"%")) -> -0,4 p.p. | E10: =IF(S10="","",IF(Indicadores!B10="R$","R$ ","")&FIXED(S10,N10)&IF(Indicadores!B10="%","%",IF(OR(Indicadores!B10="R$",Indicadores!B10="",Indicadores!B10="un"),""," "&Indicadores!B10))) -> 6,0% | F10: =IF(U10="","",IF(U10>=0,"+","")&IF(Indicadores!B10="%",FIXED(U10,1)&" p.p.",FIXED(U10*100,1)&"%")) -> +2,4 p.p. | G10: =IF(OR(Q10="",S10=""),"",IF(Indicadores!E10="Não",IF(Q10<=S10,"No alvo","Acima da meta"),IF(Q10>=S10,"No alvo","Abaixo da meta"))) -> Acima da meta | H10: =IF(Indicadores!A10="","",Indicadores!B10) -> % | N10: =IF(Indicadores!C10="",2,Indicadores!C10) -> 1 | O10: =IF(OR(U10="",G10="",G10="No alvo"),"",IF(Indicadores!E10="Não",U10,-U10)) -> 2.4 | P10: =IF(T10="","",IF(Indicadores!E10="Não",-T10,T10)) -> 0.4 | Q10: =IF(OR(Indicadores!A10="",Indicadores!G10=""),"",Indicadores!G10) -> 8.4 | R10: =IF(OR(Indicadores!A10="",Indicadores!F10=""),"",Indicadores!F10) -> 8.8 | S10: =IF(OR(Indicadores!A10="",Indicadores!D10=""),"",Indicadores!D10) -> 6 | T10: =IF(OR(Q10="",R10=""),"",IF(Indicadores!B10="%",Q10-R10,IF(R10=0,"",(Q10-R10)/ABS(R10)))) -> -0.4 | U10: =IF(OR(Q10="",S10=""),"",IF(Indicadores!B10="%",Q10-S10,IF(S10=0,"",(Q10-S10)/ABS(S10)))) -> 2.4
A11: =IF(Indicadores!A11="","",Indicadores!A11) -> Horas atendidas no mês | B11: =IF(Q11="","",IF(Indicadores!B11="R$","R$ ","")&FIXED(Q11,N11)&IF(Indicadores!B11="%","%",IF(OR(Indicadores!B11="R$",Indicadores!B11="",Indicadores!B11="un"),""," "&Indicadores!B11))) -> 118,3 h | C11: =IF(R11="","",IF(Indicadores!B11="R$","R$ ","")&FIXED(R11,N11)&IF(Indicadores!B11="%","%",IF(OR(Indicadores!B11="R$",Indicadores!B11="",Indicadores!B11="un"),""," "&Indicadores!B11))) -> 129,0 h | D11: =IF(T11="","",IF(T11>=0,"+","")&IF(Indicadores!B11="%",FIXED(T11,1)&" p.p.",FIXED(T11*100,1)&"%")) -> -8,3% | E11: =IF(S11="","",IF(Indicadores!B11="R$","R$ ","")&FIXED(S11,N11)&IF(Indicadores!B11="%","%",IF(OR(Indicadores!B11="R$",Indicadores!B11="",Indicadores!B11="un"),""," "&Indicadores!B11))) -> 140,0 h | F11: =IF(U11="","",IF(U11>=0,"+","")&IF(Indicadores!B11="%",FIXED(U11,1)&" p.p.",FIXED(U11*100,1)&"%")) -> -15,5% | G11: =IF(OR(Q11="",S11=""),"",IF(Indicadores!E11="Não",IF(Q11<=S11,"No alvo","Acima da meta"),IF(Q11>=S11,"No alvo","Abaixo da meta"))) -> Abaixo da meta | H11: =IF(Indicadores!A11="","",Indicadores!B11) -> h | N11: =IF(Indicadores!C11="",2,Indicadores!C11) -> 1 | O11: =IF(OR(U11="",G11="",G11="No alvo"),"",IF(Indicadores!E11="Não",U11,-U11)) -> 0.155 | P11: =IF(T11="","",IF(Indicadores!E11="Não",-T11,T11)) -> -0.082945736 | Q11: =IF(OR(Indicadores!A11="",Indicadores!G11=""),"",Indicadores!G11) -> 118.3 | R11: =IF(OR(Indicadores!A11="",Indicadores!F11=""),"",Indicadores!F11) -> 129 | S11: =IF(OR(Indicadores!A11="",Indicadores!D11=""),"",Indicadores!D11) -> 140 | T11: =IF(OR(Q11="",R11=""),"",IF(Indicadores!B11="%",Q11-R11,IF(R11=0,"",(Q11-R11)/ABS(R11)))) -> -0.082945736 | U11: =IF(OR(Q11="",S11=""),"",IF(Indicadores!B11="%",Q11-S11,IF(S11=0,"",(Q11-S11)/ABS(S11)))) -> -0.155
A12: =IF(Indicadores!A12="","",Indicadores!A12) -> Convênio a receber (lotes enviados) | B12: =IF(Q12="","",IF(Indicadores!B12="R$","R$ ","")&FIXED(Q12,N12)&IF(Indicadores!B12="%","%",IF(OR(Indicadores!B12="R$",Indicadores!B12="",Indicadores!B12="un"),""," "&Indicadores!B12))) -> R$ 12.077 | C12: =IF(R12="","",IF(Indicadores!B12="R$","R$ ","")&FIXED(R12,N12)&IF(Indicadores!B12="%","%",IF(OR(Indicadores!B12="R$",Indicadores!B12="",Indicadores!B12="un"),""," "&Indicadores!B12))) -> R$ 13.553 | D12: =IF(T12="","",IF(T12>=0,"+","")&IF(Indicadores!B12="%",FIXED(T12,1)&" p.p.",FIXED(T12*100,1)&"%")) -> -10,9% | E12: =IF(S12="","",IF(Indicadores!B12="R$","R$ ","")&FIXED(S12,N12)&IF(Indicadores!B12="%","%",IF(OR(Indicadores!B12="R$",Indicadores!B12="",Indicadores!B12="un"),""," "&Indicadores!B12))) | F12: =IF(U12="","",IF(U12>=0,"+","")&IF(Indicadores!B12="%",FIXED(U12,1)&" p.p.",FIXED(U12*100,1)&"%")) | G12: =IF(OR(Q12="",S12=""),"",IF(Indicadores!E12="Não",IF(Q12<=S12,"No alvo","Acima da meta"),IF(Q12>=S12,"No alvo","Abaixo da meta"))) | H12: =IF(Indicadores!A12="","",Indicadores!B12) -> R$ | N12: =IF(Indicadores!C12="",2,Indicadores!C12) -> 0 | O12: =IF(OR(U12="",G12="",G12="No alvo"),"",IF(Indicadores!E12="Não",U12,-U12)) | P12: =IF(T12="","",IF(Indicadores!E12="Não",-T12,T12)) -> -0.10890578 | Q12: =IF(OR(Indicadores!A12="",Indicadores!G12=""),"",Indicadores!G12) -> 12077 | R12: =IF(OR(Indicadores!A12="",Indicadores!F12=""),"",Indicadores!F12) -> 13553 | S12: =IF(OR(Indicadores!A12="",Indicadores!D12=""),"",Indicadores!D12) | T12: =IF(OR(Q12="",R12=""),"",IF(Indicadores!B12="%",Q12-R12,IF(R12=0,"",(Q12-R12)/ABS(R12)))) -> -0.10890578 | U12: =IF(OR(Q12="",S12=""),"",IF(Indicadores!B12="%",Q12-S12,IF(S12=0,"",(Q12-S12)/ABS(S12))))
A13: =IF(Indicadores!A13="","",Indicadores!A13) -> Glosa dos lotes pagos no mês | B13: =IF(Q13="","",IF(Indicadores!B13="R$","R$ ","")&FIXED(Q13,N13)&IF(Indicadores!B13="%","%",IF(OR(Indicadores!B13="R$",Indicadores!B13="",Indicadores!B13="un"),""," "&Indicadores!B13))) -> 5,6% | C13: =IF(R13="","",IF(Indicadores!B13="R$","R$ ","")&FIXED(R13,N13)&IF(Indicadores!B13="%","%",IF(OR(Indicadores!B13="R$",Indicadores!B13="",Indicadores!B13="un"),""," "&Indicadores!B13))) -> 4,3% | D13: =IF(T13="","",IF(T13>=0,"+","")&IF(Indicadores!B13="%",FIXED(T13,1)&" p.p.",FIXED(T13*100,1)&"%")) -> +1,3 p.p. | E13: =IF(S13="","",IF(Indicadores!B13="R$","R$ ","")&FIXED(S13,N13)&IF(Indicadores!B13="%","%",IF(OR(Indicadores!B13="R$",Indicadores!B13="",Indicadores!B13="un"),""," "&Indicadores!B13))) -> 4,0% | F13: =IF(U13="","",IF(U13>=0,"+","")&IF(Indicadores!B13="%",FIXED(U13,1)&" p.p.",FIXED(U13*100,1)&"%")) -> +1,6 p.p. | G13: =IF(OR(Q13="",S13=""),"",IF(Indicadores!E13="Não",IF(Q13<=S13,"No alvo","Acima da meta"),IF(Q13>=S13,"No alvo","Abaixo da meta"))) -> Acima da meta | H13: =IF(Indicadores!A13="","",Indicadores!B13) -> % | N13: =IF(Indicadores!C13="",2,Indicadores!C13) -> 1 | O13: =IF(OR(U13="",G13="",G13="No alvo"),"",IF(Indicadores!E13="Não",U13,-U13)) -> 1.6 | P13: =IF(T13="","",IF(Indicadores!E13="Não",-T13,T13)) -> -1.3 | Q13: =IF(OR(Indicadores!A13="",Indicadores!G13=""),"",Indicadores!G13) -> 5.6 | R13: =IF(OR(Indicadores!A13="",Indicadores!F13=""),"",Indicadores!F13) -> 4.3 | S13: =IF(OR(Indicadores!A13="",Indicadores!D13=""),"",Indicadores!D13) -> 4 | T13: =IF(OR(Q13="",R13=""),"",IF(Indicadores!B13="%",Q13-R13,IF(R13=0,"",(Q13-R13)/ABS(R13)))) -> 1.3 | U13: =IF(OR(Q13="",S13=""),"",IF(Indicadores!B13="%",Q13-S13,IF(S13=0,"",(Q13-S13)/ABS(S13)))) -> 1.6
A14: =IF(Indicadores!A14="","",Indicadores!A14) -> Vencido (parcelas a prazo) | B14: =IF(Q14="","",IF(Indicadores!B14="R$","R$ ","")&FIXED(Q14,N14)&IF(Indicadores!B14="%","%",IF(OR(Indicadores!B14="R$",Indicadores!B14="",Indicadores!B14="un"),""," "&Indicadores!B14))) -> R$ 4.005 | C14: =IF(R14="","",IF(Indicadores!B14="R$","R$ ","")&FIXED(R14,N14)&IF(Indicadores!B14="%","%",IF(OR(Indicadores!B14="R$",Indicadores!B14="",Indicadores!B14="un"),""," "&Indicadores!B14))) -> R$ 3.290 | D14: =IF(T14="","",IF(T14>=0,"+","")&IF(Indicadores!B14="%",FIXED(T14,1)&" p.p.",FIXED(T14*100,1)&"%")) -> +21,7% | E14: =IF(S14="","",IF(Indicadores!B14="R$","R$ ","")&FIXED(S14,N14)&IF(Indicadores!B14="%","%",IF(OR(Indicadores!B14="R$",Indicadores!B14="",Indicadores!B14="un"),""," "&Indicadores!B14))) -> R$ 4.000 | F14: =IF(U14="","",IF(U14>=0,"+","")&IF(Indicadores!B14="%",FIXED(U14,1)&" p.p.",FIXED(U14*100,1)&"%")) -> +0,1% | G14: =IF(OR(Q14="",S14=""),"",IF(Indicadores!E14="Não",IF(Q14<=S14,"No alvo","Acima da meta"),IF(Q14>=S14,"No alvo","Abaixo da meta"))) -> Acima da meta | H14: =IF(Indicadores!A14="","",Indicadores!B14) -> R$ | N14: =IF(Indicadores!C14="",2,Indicadores!C14) -> 0 | O14: =IF(OR(U14="",G14="",G14="No alvo"),"",IF(Indicadores!E14="Não",U14,-U14)) -> 0.00125 | P14: =IF(T14="","",IF(Indicadores!E14="Não",-T14,T14)) -> -0.21732523 | Q14: =IF(OR(Indicadores!A14="",Indicadores!G14=""),"",Indicadores!G14) -> 4005 | R14: =IF(OR(Indicadores!A14="",Indicadores!F14=""),"",Indicadores!F14) -> 3290 | S14: =IF(OR(Indicadores!A14="",Indicadores!D14=""),"",Indicadores!D14) -> 4000 | T14: =IF(OR(Q14="",R14=""),"",IF(Indicadores!B14="%",Q14-R14,IF(R14=0,"",(Q14-R14)/ABS(R14)))) -> 0.21732523 | U14: =IF(OR(Q14="",S14=""),"",IF(Indicadores!B14="%",Q14-S14,IF(S14=0,"",(Q14-S14)/ABS(S14)))) -> 0.00125
A15: =IF(Indicadores!A15="","",Indicadores!A15) -> Inadimplência a prazo (vencido ÷ (pago + vencido)) | B15: =IF(Q15="","",IF(Indicadores!B15="R$","R$ ","")&FIXED(Q15,N15)&IF(Indicadores!B15="%","%",IF(OR(Indicadores!B15="R$",Indicadores!B15="",Indicadores!B15="un"),""," "&Indicadores!B15))) -> 10,5% | C15: =IF(R15="","",IF(Indicadores!B15="R$","R$ ","")&FIXED(R15,N15)&IF(Indicadores!B15="%","%",IF(OR(Indicadores!B15="R$",Indicadores!B15="",Indicadores!B15="un"),""," "&Indicadores!B15))) -> 10,0% | D15: =IF(T15="","",IF(T15>=0,"+","")&IF(Indicadores!B15="%",FIXED(T15,1)&" p.p.",FIXED(T15*100,1)&"%")) -> +0,5 p.p. | E15: =IF(S15="","",IF(Indicadores!B15="R$","R$ ","")&FIXED(S15,N15)&IF(Indicadores!B15="%","%",IF(OR(Indicadores!B15="R$",Indicadores!B15="",Indicadores!B15="un"),""," "&Indicadores!B15))) -> 8,0% | F15: =IF(U15="","",IF(U15>=0,"+","")&IF(Indicadores!B15="%",FIXED(U15,1)&" p.p.",FIXED(U15*100,1)&"%")) -> +2,5 p.p. | G15: =IF(OR(Q15="",S15=""),"",IF(Indicadores!E15="Não",IF(Q15<=S15,"No alvo","Acima da meta"),IF(Q15>=S15,"No alvo","Abaixo da meta"))) -> Acima da meta | H15: =IF(Indicadores!A15="","",Indicadores!B15) -> % | N15: =IF(Indicadores!C15="",2,Indicadores!C15) -> 1 | O15: =IF(OR(U15="",G15="",G15="No alvo"),"",IF(Indicadores!E15="Não",U15,-U15)) -> 2.5 | P15: =IF(T15="","",IF(Indicadores!E15="Não",-T15,T15)) -> -0.5 | Q15: =IF(OR(Indicadores!A15="",Indicadores!G15=""),"",Indicadores!G15) -> 10.5 | R15: =IF(OR(Indicadores!A15="",Indicadores!F15=""),"",Indicadores!F15) -> 10 | S15: =IF(OR(Indicadores!A15="",Indicadores!D15=""),"",Indicadores!D15) -> 8 | T15: =IF(OR(Q15="",R15=""),"",IF(Indicadores!B15="%",Q15-R15,IF(R15=0,"",(Q15-R15)/ABS(R15)))) -> 0.5 | U15: =IF(OR(Q15="",S15=""),"",IF(Indicadores!B15="%",Q15-S15,IF(S15=0,"",(Q15-S15)/ABS(S15)))) -> 2.5
A16: =IF(Indicadores!A16="","",Indicadores!A16) -> Orçamentos em aberto (valor) | B16: =IF(Q16="","",IF(Indicadores!B16="R$","R$ ","")&FIXED(Q16,N16)&IF(Indicadores!B16="%","%",IF(OR(Indicadores!B16="R$",Indicadores!B16="",Indicadores!B16="un"),""," "&Indicadores!B16))) -> R$ 2.700 | C16: =IF(R16="","",IF(Indicadores!B16="R$","R$ ","")&FIXED(R16,N16)&IF(Indicadores!B16="%","%",IF(OR(Indicadores!B16="R$",Indicadores!B16="",Indicadores!B16="un"),""," "&Indicadores!B16))) -> R$ 830 | D16: =IF(T16="","",IF(T16>=0,"+","")&IF(Indicadores!B16="%",FIXED(T16,1)&" p.p.",FIXED(T16*100,1)&"%")) -> +225,3% | E16: =IF(S16="","",IF(Indicadores!B16="R$","R$ ","")&FIXED(S16,N16)&IF(Indicadores!B16="%","%",IF(OR(Indicadores!B16="R$",Indicadores!B16="",Indicadores!B16="un"),""," "&Indicadores!B16))) | F16: =IF(U16="","",IF(U16>=0,"+","")&IF(Indicadores!B16="%",FIXED(U16,1)&" p.p.",FIXED(U16*100,1)&"%")) | G16: =IF(OR(Q16="",S16=""),"",IF(Indicadores!E16="Não",IF(Q16<=S16,"No alvo","Acima da meta"),IF(Q16>=S16,"No alvo","Abaixo da meta"))) | H16: =IF(Indicadores!A16="","",Indicadores!B16) -> R$ | N16: =IF(Indicadores!C16="",2,Indicadores!C16) -> 0 | O16: =IF(OR(U16="",G16="",G16="No alvo"),"",IF(Indicadores!E16="Não",U16,-U16)) | P16: =IF(T16="","",IF(Indicadores!E16="Não",-T16,T16)) -> 2.253012 | Q16: =IF(OR(Indicadores!A16="",Indicadores!G16=""),"",Indicadores!G16) -> 2700 | R16: =IF(OR(Indicadores!A16="",Indicadores!F16=""),"",Indicadores!F16) -> 830 | S16: =IF(OR(Indicadores!A16="",Indicadores!D16=""),"",Indicadores!D16) | T16: =IF(OR(Q16="",R16=""),"",IF(Indicadores!B16="%",Q16-R16,IF(R16=0,"",(Q16-R16)/ABS(R16)))) -> 2.253012 | U16: =IF(OR(Q16="",S16=""),"",IF(Indicadores!B16="%",Q16-S16,IF(S16=0,"",(Q16-S16)/ABS(S16))))
A18: Verde: no alvo. Vermelho: fora da meta. Sem meta: informativo. Os valores são texto formatado (FIXED, casas decimais de Indicadores; separadores no idioma do Excel); as colunas N a U (ocultas) guardam os números e a distância da meta, usadas nos destaques do Resumo.

Sheet Resumo
A1: Resumo do mês, pronto para a IA e para o contador
A2: Só a célula amarela é para digitar (observações da clínica). Copie o bloco único e cole no prompt "Painel 01 · Explicar o mês ao sócio" da biblioteca do kit, ou envie ao sócio e ao contador. Os números vêm do Painel.
A4: ="Resumo de "&Config!B6&" de "&Config!B5&" · "&Config!B4 -> Resumo de Agosto de 2026 · Clínica Vida Plena (exemplo fictício)
A5: Observações da clínica (opcional; entram no fim do bloco):
A6: Agosto fechou com a agenda da Dra. Renata mais cheia (dois turnos por semana desde julho) e o lote de junho da Saúde Total pago com glosa, parte dela em recurso; o lote de junho da Vida Care tinha previsão para 04/09 e ainda estava dentro do prazo no fechamento de agosto — em setembro venceu e entrou na cobrança ao convênio; as faltas de segunda de manhã continuam acima da média e a recepção começou a confirmação de véspera por mensagem.
A8: =IF(OR(Painel!A5="",Painel!Q5=""),"","• "&Painel!A5&": "&Painel!B5&IF(Painel!T5<>"",IF(Painel!T5=0," (igual a "&Config!$B$8&")"," ("&Painel!D5&" em relação a "&Config!$B$8&")"),IF(AND(Painel!R5<>"",Painel!R5=0,Painel!Q5<>0)," (sem base de comparação: "&Config!$B$8&" foi zero)",IF(Painel!R5<>""," (igual a "&Config!$B$8&")","")))&IF(Painel!S5<>"","; meta "&Painel!E5&", "&LOWER(Painel!G5),"")&".") -> • Entrou no mês (recebimentos): R$ 55.841 (+25,6% em relação a Julho); meta R$ 46.000, no alvo.
A9: =IF(OR(Painel!A6="",Painel!Q6=""),"","• "&Painel!A6&": "&Painel!B6&IF(Painel!T6<>"",IF(Painel!T6=0," (igual a "&Config!$B$8&")"," ("&Painel!D6&" em relação a "&Config!$B$8&")"),IF(AND(Painel!R6<>"",Painel!R6=0,Painel!Q6<>0)," (sem base de comparação: "&Config!$B$8&" foi zero)",IF(Painel!R6<>""," (igual a "&Config!$B$8&")","")))&IF(Painel!S6<>"","; meta "&Painel!E6&", "&LOWER(Painel!G6),"")&".") -> • Saídas do mês (custos, variáveis, pró-labore, provisões e impostos): R$ 43.462 (+5,4% em relação a Julho); meta R$ 44.000, no alvo.
A10: =IF(OR(Painel!A7="",Painel!Q7=""),"","• "&Painel!A7&": "&Painel!B7&IF(Painel!T7<>"",IF(Painel!T7=0," (igual a "&Config!$B$8&")"," ("&Painel!D7&" em relação a "&Config!$B$8&")"),IF(AND(Painel!R7<>"",Painel!R7=0,Painel!Q7<>0)," (sem base de comparação: "&Config!$B$8&" foi zero)",IF(Painel!R7<>""," (igual a "&Config!$B$8&")","")))&IF(Painel!S7<>"","; meta "&Painel!E7&", "&LOWER(Painel!G7),"")&".") -> • Resultado do mês: R$ 12.379 (+280,9% em relação a Julho); meta R$ 5.000, no alvo.
A11: =IF(OR(Painel!A8="",Painel!Q8=""),"","• "&Painel!A8&": "&Painel!B8&IF(Painel!T8<>"",IF(Painel!T8=0," (igual a "&Config!$B$8&")"," ("&Painel!D8&" em relação a "&Config!$B$8&")"),IF(AND(Painel!R8<>"",Painel!R8=0,Painel!Q8<>0)," (sem base de comparação: "&Config!$B$8&" foi zero)",IF(Painel!R8<>""," (igual a "&Config!$B$8&")","")))&IF(Painel!S8<>"","; meta "&Painel!E8&", "&LOWER(Painel!G8),"")&".") -> • Margem do mês: 22,2% (+14,9 p.p. em relação a Julho); meta 12,0%, no alvo.
A12: =IF(OR(Painel!A9="",Painel!Q9=""),"","• "&Painel!A9&": "&Painel!B9&IF(Painel!T9<>"",IF(Painel!T9=0," (igual a "&Config!$B$8&")"," ("&Painel!D9&" em relação a "&Config!$B$8&")"),IF(AND(Painel!R9<>"",Painel!R9=0,Painel!Q9<>0)," (sem base de comparação: "&Config!$B$8&" foi zero)",IF(Painel!R9<>""," (igual a "&Config!$B$8&")","")))&IF(Painel!S9<>"","; meta "&Painel!E9&", "&LOWER(Painel!G9),"")&".") -> • Ocupação da agenda: 70,4% (-1,3 p.p. em relação a Julho); meta 75,0%, abaixo da meta.
A13: =IF(OR(Painel!A10="",Painel!Q10=""),"","• "&Painel!A10&": "&Painel!B10&IF(Painel!T10<>"",IF(Painel!T10=0," (igual a "&Config!$B$8&")"," ("&Painel!D10&" em relação a "&Config!$B$8&")"),IF(AND(Painel!R10<>"",Painel!R10=0,Painel!Q10<>0)," (sem base de comparação: "&Config!$B$8&" foi zero)",IF(Painel!R10<>""," (igual a "&Config!$B$8&")","")))&IF(Painel!S10<>"","; meta "&Painel!E10&", "&LOWER(Painel!G10),"")&".") -> • Taxa de falta: 8,4% (-0,4 p.p. em relação a Julho); meta 6,0%, acima da meta.
A14: =IF(OR(Painel!A11="",Painel!Q11=""),"","• "&Painel!A11&": "&Painel!B11&IF(Painel!T11<>"",IF(Painel!T11=0," (igual a "&Config!$B$8&")"," ("&Painel!D11&" em relação a "&Config!$B$8&")"),IF(AND(Painel!R11<>"",Painel!R11=0,Painel!Q11<>0)," (sem base de comparação: "&Config!$B$8&" foi zero)",IF(Painel!R11<>""," (igual a "&Config!$B$8&")","")))&IF(Painel!S11<>"","; meta "&Painel!E11&", "&LOWER(Painel!G11),"")&".") -> • Horas atendidas no mês: 118,3 h (-8,3% em relação a Julho); meta 140,0 h, abaixo da meta.
A15: =IF(OR(Painel!A12="",Painel!Q12=""),"","• "&Painel!A12&": "&Painel!B12&IF(Painel!T12<>"",IF(Painel!T12=0," (igual a "&Config!$B$8&")"," ("&Painel!D12&" em relação a "&Config!$B$8&")"),IF(AND(Painel!R12<>"",Painel!R12=0,Painel!Q12<>0)," (sem base de comparação: "&Config!$B$8&" foi zero)",IF(Painel!R12<>""," (igual a "&Config!$B$8&")","")))&IF(Painel!S12<>"","; meta "&Painel!E12&", "&LOWER(Painel!G12),"")&".") -> • Convênio a receber (lotes enviados): R$ 12.077 (-10,9% em relação a Julho).
A16: =IF(OR(Painel!A13="",Painel!Q13=""),"","• "&Painel!A13&": "&Painel!B13&IF(Painel!T13<>"",IF(Painel!T13=0," (igual a "&Config!$B$8&")"," ("&Painel!D13&" em relação a "&Config!$B$8&")"),IF(AND(Painel!R13<>"",Painel!R13=0,Painel!Q13<>0)," (sem base de comparação: "&Config!$B$8&" foi zero)",IF(Painel!R13<>""," (igual a "&Config!$B$8&")","")))&IF(Painel!S13<>"","; meta "&Painel!E13&", "&LOWER(Painel!G13),"")&".") -> • Glosa dos lotes pagos no mês: 5,6% (+1,3 p.p. em relação a Julho); meta 4,0%, acima da meta.
A17: =IF(OR(Painel!A14="",Painel!Q14=""),"","• "&Painel!A14&": "&Painel!B14&IF(Painel!T14<>"",IF(Painel!T14=0," (igual a "&Config!$B$8&")"," ("&Painel!D14&" em relação a "&Config!$B$8&")"),IF(AND(Painel!R14<>"",Painel!R14=0,Painel!Q14<>0)," (sem base de comparação: "&Config!$B$8&" foi zero)",IF(Painel!R14<>""," (igual a "&Config!$B$8&")","")))&IF(Painel!S14<>"","; meta "&Painel!E14&", "&LOWER(Painel!G14),"")&".") -> • Vencido (parcelas a prazo): R$ 4.005 (+21,7% em relação a Julho); meta R$ 4.000, acima da meta.
A18: =IF(OR(Painel!A15="",Painel!Q15=""),"","• "&Painel!A15&": "&Painel!B15&IF(Painel!T15<>"",IF(Painel!T15=0," (igual a "&Config!$B$8&")"," ("&Painel!D15&" em relação a "&Config!$B$8&")"),IF(AND(Painel!R15<>"",Painel!R15=0,Painel!Q15<>0)," (sem base de comparação: "&Config!$B$8&" foi zero)",IF(Painel!R15<>""," (igual a "&Config!$B$8&")","")))&IF(Painel!S15<>"","; meta "&Painel!E15&", "&LOWER(Painel!G15),"")&".") -> • Inadimplência a prazo (vencido ÷ (pago + vencido)): 10,5% (+0,5 p.p. em relação a Julho); meta 8,0%, acima da meta.
A19: =IF(OR(Painel!A16="",Painel!Q16=""),"","• "&Painel!A16&": "&Painel!B16&IF(Painel!T16<>"",IF(Painel!T16=0," (igual a "&Config!$B$8&")"," ("&Painel!D16&" em relação a "&Config!$B$8&")"),IF(AND(Painel!R16<>"",Painel!R16=0,Painel!Q16<>0)," (sem base de comparação: "&Config!$B$8&" foi zero)",IF(Painel!R16<>""," (igual a "&Config!$B$8&")","")))&IF(Painel!S16<>"","; meta "&Painel!E16&", "&LOWER(Painel!G16),"")&".") -> • Orçamentos em aberto (valor): R$ 2.700 (+225,3% em relação a Julho).
A21: Destaques automáticos
A22: =IF(COUNT(Painel!$P$5:$P$16)=0,"• Melhora e piora: preencha o mês anterior para comparar.",IF(MAX(Painel!$P$5:$P$16)<=0,"• Nenhum indicador melhorou contra "&Config!$B$8&".","• Maior melhora contra "&Config!$B$8&": "&INDEX(Painel!$A$5:$A$16,MATCH(MAX(Painel!$P$5:$P$16),Painel!$P$5:$P$16,0))&" ("&INDEX(Painel!$D$5:$D$16,MATCH(MAX(Painel!$P$5:$P$16),Painel!$P$5:$P$16,0))&").")) -> • Maior melhora contra Julho: Margem do mês (+14,9 p.p.).
A23: =IF(COUNT(Painel!$P$5:$P$16)=0,"",IF(MIN(Painel!$P$5:$P$16)>=0,"• Nenhum indicador piorou contra "&Config!$B$8&".","• Maior piora contra "&Config!$B$8&": "&INDEX(Painel!$A$5:$A$16,MATCH(MIN(Painel!$P$5:$P$16),Painel!$P$5:$P$16,0))&" ("&INDEX(Painel!$D$5:$D$16,MATCH(MIN(Painel!$P$5:$P$16),Painel!$P$5:$P$16,0))&").")) -> • Maior piora contra Julho: Ocupação da agenda (-1,3 p.p.).
A24: =IF((COUNTIF(Painel!$G$5:$G$16,"Acima da meta")+COUNTIF(Painel!$G$5:$G$16,"Abaixo da meta"))=0,"• Nenhum indicador fora da meta.",IF(COUNT(Painel!$O$5:$O$16)=0,"• "&(COUNTIF(Painel!$G$5:$G$16,"Acima da meta")+COUNTIF(Painel!$G$5:$G$16,"Abaixo da meta"))&" indicador(es) fora da meta (sem percentual: a meta é zero).","• Mais longe da meta: "&INDEX(Painel!$A$5:$A$16,MATCH(MAX(Painel!$O$5:$O$16),Painel!$O$5:$O$16,0))&" ("&INDEX(Painel!$F$5:$F$16,MATCH(MAX(Painel!$O$5:$O$16),Painel!$O$5:$O$16,0))&" da meta, "&LOWER(INDEX(Painel!$G$5:$G$16,MATCH(MAX(Painel!$O$5:$O$16),Painel!$O$5:$O$16,0)))&").")) -> • Mais longe da meta: Ocupação da agenda (-4,6 p.p. da meta, abaixo da meta).
A25: ="• Indicadores no alvo: "&COUNTIF(Painel!$G$5:$G$16,"No alvo")&" de "&(COUNTIF(Painel!$G$5:$G$16,"No alvo")+COUNTIF(Painel!$G$5:$G$16,"Acima da meta")+COUNTIF(Painel!$G$5:$G$16,"Abaixo da meta"))&" com meta." -> • Indicadores no alvo: 4 de 10 com meta.
A27: Bloco único para copiar
A28: =A4&CHAR(10)&CHAR(10)&"Indicadores do mês:"&CHAR(10)&IF(A8="","",A8&CHAR(10)) & IF(A9="","",A9&CHAR(10)) & IF(A10="","",A10&CHAR(10)) & IF(A11="","",A11&CHAR(10)) & IF(A12="","",A12&CHAR(10)) & IF(A13="","",A13&CHAR(10)) & IF(A14="","",A14&CHAR(10)) & IF(A15="","",A15&CHAR(10)) & IF(A16="","",A16&CHAR(10)) & IF(A17="","",A17&CHAR(10)) & IF(A18="","",A18&CHAR(10)) & IF(A19="","",A19&CHAR(10))&CHAR(10)&"Destaques:"&CHAR(10)&IF(A22="","",A22&CHAR(10)) & IF(A23="","",A23&CHAR(10)) & IF(A24="","",A24&CHAR(10)) & IF(A25="","",A25&CHAR(10))&IF(A6="","",CHAR(10)&"Observações da clínica: "&A6) -> Resumo de Agosto de 2026 · Clínica Vida Plena (exemplo fictício) Indicadores do mês: • Entrou no mês (recebimentos): R$ 55.841 (+25,6% em relação a Julho); meta R$ 46.000, no alvo. • Saídas do mês (custos, variáveis, pró-labore, provisões e impostos): R$ 43.462 (+5,4% em relação a Julho); meta R$ 44.000, no alvo. • Resultado do mês: R$ 12.379 (+280,9% em relação a Julho); meta R$ 5.000, no alvo. • Margem do mês: 22,2% (+14,9 p.p. em relação a Julho); meta 12,0%, no alvo. • Ocupação da agenda: 70,4% (-1,3 p.p. em relação a Julho); meta 75,0%, abaixo da meta. • Taxa de falta: 8,4% (-0,4 p.p. em relação a Julho); meta 6,0%, acima da meta. • Horas atendidas no mês: 118,3 h (-8,3% em relação a Julho); meta 140,0 h, abaixo da meta. • Convênio a receber (lotes enviados): R$ 12.077 (-10,9% em relação a Julho). • Glosa dos lotes pagos no mês: 5,6% (+1,3 p.p. em relação a Julho); meta 4,0%, acima da meta. • Vencido (parcelas a prazo): R$ 4.005 (+21,7% em relação a Julho); meta R$ 4.000, acima da meta. • Inadimplência a prazo (vencido ÷ (pago + vencido)): 10,5% (+0,5 p.p. em relação a Julho); meta 8,0%, acima da meta. • Orçamentos em aberto (valor): R$ 2.700 (+225,3% em relação a Julho). Destaques: • Maior melhora contra Julho: Margem do mês (+14,9 p.p.). • Maior piora contra Julho: Ocupação da agenda (-1,3 p.p.). • Mais longe da meta: Ocupação da agenda (-4,6 p.p. da meta, abaixo da meta). • Indicadores no alvo: 4 de 10 com meta. Observações da clínica: Agosto fechou com a agenda da Dra. Renata mais cheia (dois turnos por semana desde julho) e o lote de junho da Saúde Total pago com glosa, parte dela em recurso; o lote de junho da Vida Care tinha previsão para 04/09 e ainda estava dentro do prazo no fechamento de agosto — em setembro venceu e entrou na cobrança ao convênio; as faltas de segunda de manhã continuam acima da média e a recepção começou a confirmação de véspera por mensagem.
A30: Os textos são gerados por fórmula. Revise antes de enviar: a IA e o contador precisam do porquê dos números, e isso só a clínica sabe. Nenhum dado de paciente entra aqui: só totais. Variação de indicadores em % em pontos percentuais (p.p.).

Sheet Config
A1: Configurações
A2: Células amarelas: você preenche.
A4: Clínica | B4: Clínica Vida Plena (exemplo fictício) | D4: Meses
A5: Ano | B5: 2026 | D5: Janeiro
A6: Mês do resumo | B6: Agosto | D6: Fevereiro
A7: Número do mês | B7: =MATCH(B6,$D$5:$D$16,0) -> 8 | D7: Março
A8: Mês anterior | B8: =IF(B7>1,INDEX($D$5:$D$16,B7-1),INDEX($D$5:$D$16,12)) -> Julho | D8: Abril
D9: Maio
A10: Use a mesma planilha todo mês: troque o mês aqui e, em Indicadores, mova o "Mês atual" para "Mês anterior" antes de digitar os novos valores. Resuma o último mês fechado (no exemplo, agosto; setembro está em andamento). | D10: Junho
D11: Julho
D12: Agosto
D13: Setembro
D14: Outubro
D15: Novembro
D16: Dezembro

Sheet Indicadores
A1: Indicadores do mês
A2: Até 12 indicadores (de cima para baixo, sem pular linha): nome, unidade, casas decimais, meta, se maior é melhor, valor do mês anterior e do mês atual. Copie os números do Painel da clínica (17, Histórico) e do Resultado mensal (18).
A4: Indicador | B4: Unidade | C4: Casas decimais | D4: Meta do mês | E4: Maior é melhor? | F4: Mês anterior | G4: Mês atual | H4: Copie de (planilha do kit)
A5: Entrou no mês (recebimentos) | B5: R$ | C5: 0 | D5: 46000 | E5: Sim | F5: 44471 | G5: 55841 | H5: 09 · Caixa (Painel) ou 17 · Painel (Histórico)
A6: Saídas do mês (custos, variáveis, pró-labore, provisões e impostos) | B6: R$ | C6: 0 | D6: 44000 | E6: Não | F6: 41220.61 | G6: 43461.6 | H6: 18 · Resultado mensal (Total de saídas)
A7: Resultado do mês | B7: R$ | C7: 0 | D7: 5000 | E7: Sim | F7: 3250.39 | G7: 12379.4 | H7: 18 · Resultado mensal
A8: Margem do mês | B8: % | C8: 1 | D8: 12 | E8: Sim | F8: 7.3 | G8: 22.2 | H8: 18 · Resultado mensal
A9: Ocupação da agenda | B9: % | C9: 1 | D9: 75 | E9: Sim | F9: 71.7 | G9: 70.4 | H9: 01 · Agenda (Painel) ou 17 · Histórico
A10: Taxa de falta | B10: % | C10: 1 | D10: 6 | E10: Não | F10: 8.8 | G10: 8.4 | H10: 02 · Faltas e retornos ou 17 · Histórico
A11: Horas atendidas no mês | B11: h | C11: 1 | D11: 140 | E11: Sim | F11: 129 | G11: 118.3 | H11: 01 · Agenda (Painel) ou 17 · Histórico
A12: Convênio a receber (lotes enviados) | B12: R$ | C12: 0 | E12: Sim | F12: 13553 | G12: 12077 | H12: 13 · Convênios (fim do mês) ou 17 · Histórico
A13: Glosa dos lotes pagos no mês | B13: % | C13: 1 | D13: 4 | E13: Não | F13: 4.3 | G13: 5.6 | H13: 13 · Convênios ou 17 · Histórico
A14: Vencido (parcelas a prazo) | B14: R$ | C14: 0 | D14: 4000 | E14: Não | F14: 3290 | G14: 4005 | H14: 14 · Parcelas (fim do mês) ou 17 · Histórico
A15: Inadimplência a prazo (vencido ÷ (pago + vencido)) | B15: % | C15: 1 | D15: 8 | E15: Não | F15: 10 | G15: 10.5 | H15: 14 · Parcelas e inadimplência ou 17 · Histórico
A16: Orçamentos em aberto (valor) | B16: R$ | C16: 0 | E16: Sim | F16: 830 | G16: 2700 | H16: 15 · Orçamentos ou 17 · Histórico
A18: Para indicadores em %, digite 5,1 (não 0,051). "Maior é melhor?" = Não para saídas, vencido, inadimplência, glosa e taxa de falta. Meta em branco = informativo: é o caso de convênio a receber (o que está no prazo não é problema) e dos orçamentos em aberto (pouco orçamento pendente pode ser bom, se fechou tudo, ou ruim, se a recepção parou de apresentar — quem responde é a taxa de aprovação da 15). Meta 0 funciona: a situação aparece, a distância em % não.
