Workbook

Sheet Como usar
A1: Horas e Custo por Projeto
A2: Kit IA no Trabalho · Completo · Seu Sócio Gestor · versão 1.0 (setembro de 2026)
A4: O que esta planilha faz | B4: Cada pessoa lança as horas por projeto; ela transforma em custo (pelo custo-hora), compara com as horas orçadas e o valor cobrado, mostra a margem de cada projeto e a ocupação de cada pessoa no mês.
A5: Passo 1 | B5: Em Config, cadastre as pessoas com custo mensal e horas disponíveis (o custo-hora é calculado), e os projetos com horas orçadas, valor cobrado e status. Projetos internos (comercial, gestão) entram com status Interno; proposta ainda não fechada pode entrar como Proposta, sem horas.
A6: Passo 2 | B6: Em Horas, uma linha por pessoa, por dia, por projeto: data, pessoa, projeto, atividade, horas e se é faturável.
A7: Passo 3 | B7: Em Painel, escolha o mês em Config. Por projeto: horas usadas contra orçadas, custo, margem e situação. Por pessoa: ocupação e horas faturáveis.
A8: Rotina | B8: Cada pessoa lança no fim do dia (2 minutos) ou na sexta (10 minutos). Dia 1 do mês: olhe margem por projeto antes de precificar o próximo.
A9: Com a IA | B9: Copie "Por projeto" e use "Analisar 02: comparar dois períodos" ou "Analisar 06: perguntas antes de decidir" para revisar preços. Para justificar horas a um cliente, "Escrever 04".
A10: Legenda | B10: Células amarelas: você preenche. Brancas: calculadas. Não é preciso mexer em nada fora do amarelo.
A11: Proteção | B11: Fórmulas protegidas sem senha. Para editar: Revisar > Desproteger planilha (Excel) ou Dados > Proteger intervalos (Google Sheets).
A12: Google Sheets | B12: Faça upload no Google Drive e abra com o Google Sheets. Fórmulas, listas, cores e gráficos funcionam.
A13: Exemplos | B13: Prisma Comunicação é uma empresa fictícia. Nomes e valores são inventados. Apague-os antes de começar.
A14: Suporte | B14: suporte@seusociogestor.com.br · resposta em até 5 dias úteis · reembolso em até 7 dias pelo mesmo canal.

Sheet Painel
A1: =Config!B4&" · "&Config!B6&" de "&Config!B5
A2: Nada para preencher aqui. Escolha o mês em Config; tudo vem de Horas.
A4: Horas no mês | C4: Custo no mês | E4: Horas faturáveis | G4: Ocupação da equipe
A5: =SUMIFS(Horas!$E$5:$E$804,Horas!$G$5:$G$804,Config!$B$7,Horas!$H$5:$H$804,Config!$B$5) | C5: =SUMIFS(Horas!$F$5:$F$804,Horas!$G$5:$G$804,Config!$B$7,Horas!$H$5:$H$804,Config!$B$5) | E5: =IFERROR(SUMIFS(Horas!$E$5:$E$804,Horas!$G$5:$G$804,Config!$B$7,Horas!$H$5:$H$804,Config!$B$5,Horas!$I$5:$I$804,"Sim")/A5,0) | G5: =IFERROR(A5/SUMIFS(Config!$C$11:$C$20,Config!$A$11:$A$20,"<>"),0)
A7: Por projeto (todo o período)
A8: Projeto | B8: Cliente | C8: Horas orçadas | D8: Horas usadas | E8: % do orçado | F8: Custo (R$) | G8: Valor cobrado | H8: Margem (R$) | I8: Margem (%) | J8: Situação
A9: =IF(Config!$A$24="","",Config!$A$24) | B9: =IF(Config!$A$24="","",Config!$B$24) | C9: =IF(Config!$A$24="","",Config!$C$24) | D9: =IF(Config!$A$24="","",SUMIFS(Horas!$E$5:$E$804,Horas!$C$5:$C$804,Config!$A$24)) | E9: =IF(OR(Config!$A$24="",C9=0,C9=""),"",D9/C9) | F9: =IF(Config!$A$24="","",SUMIFS(Horas!$F$5:$F$804,Horas!$C$5:$C$804,Config!$A$24)) | G9: =IF(Config!$A$24="","",Config!$D$24) | H9: =IF(OR(Config!$A$24="",G9=""),"",G9-F9) | I9: =IF(OR(Config!$A$24="",G9="",G9=0),"",H9/G9) | J9: =IF(Config!$A$24="","",IF(Config!$E$24="Interno","Interno",IF(Config!$E$24="Proposta","Proposta",IF(AND(E9<>"",E9>1),"Estourou as horas",IF(AND(I9<>"",I9<0.2),"Margem baixa",IF(AND(E9<>"",E9>0.85,Config!$E$24="Em andamento"),"Perto do limite","Saudável"))))))
A10: =IF(Config!$A$25="","",Config!$A$25) | B10: =IF(Config!$A$25="","",Config!$B$25) | C10: =IF(Config!$A$25="","",Config!$C$25) | D10: =IF(Config!$A$25="","",SUMIFS(Horas!$E$5:$E$804,Horas!$C$5:$C$804,Config!$A$25)) | E10: =IF(OR(Config!$A$25="",C10=0,C10=""),"",D10/C10) | F10: =IF(Config!$A$25="","",SUMIFS(Horas!$F$5:$F$804,Horas!$C$5:$C$804,Config!$A$25)) | G10: =IF(Config!$A$25="","",Config!$D$25) | H10: =IF(OR(Config!$A$25="",G10=""),"",G10-F10) | I10: =IF(OR(Config!$A$25="",G10="",G10=0),"",H10/G10) | J10: =IF(Config!$A$25="","",IF(Config!$E$25="Interno","Interno",IF(Config!$E$25="Proposta","Proposta",IF(AND(E10<>"",E10>1),"Estourou as horas",IF(AND(I10<>"",I10<0.2),"Margem baixa",IF(AND(E10<>"",E10>0.85,Config!$E$25="Em andamento"),"Perto do limite","Saudável"))))))
A11: =IF(Config!$A$26="","",Config!$A$26) | B11: =IF(Config!$A$26="","",Config!$B$26) | C11: =IF(Config!$A$26="","",Config!$C$26) | D11: =IF(Config!$A$26="","",SUMIFS(Horas!$E$5:$E$804,Horas!$C$5:$C$804,Config!$A$26)) | E11: =IF(OR(Config!$A$26="",C11=0,C11=""),"",D11/C11) | F11: =IF(Config!$A$26="","",SUMIFS(Horas!$F$5:$F$804,Horas!$C$5:$C$804,Config!$A$26)) | G11: =IF(Config!$A$26="","",Config!$D$26) | H11: =IF(OR(Config!$A$26="",G11=""),"",G11-F11) | I11: =IF(OR(Config!$A$26="",G11="",G11=0),"",H11/G11) | J11: =IF(Config!$A$26="","",IF(Config!$E$26="Interno","Interno",IF(Config!$E$26="Proposta","Proposta",IF(AND(E11<>"",E11>1),"Estourou as horas",IF(AND(I11<>"",I11<0.2),"Margem baixa",IF(AND(E11<>"",E11>0.85,Config!$E$26="Em andamento"),"Perto do limite","Saudável"))))))
A12: =IF(Config!$A$27="","",Config!$A$27) | B12: =IF(Config!$A$27="","",Config!$B$27) | C12: =IF(Config!$A$27="","",Config!$C$27) | D12: =IF(Config!$A$27="","",SUMIFS(Horas!$E$5:$E$804,Horas!$C$5:$C$804,Config!$A$27)) | E12: =IF(OR(Config!$A$27="",C12=0,C12=""),"",D12/C12) | F12: =IF(Config!$A$27="","",SUMIFS(Horas!$F$5:$F$804,Horas!$C$5:$C$804,Config!$A$27)) | G12: =IF(Config!$A$27="","",Config!$D$27) | H12: =IF(OR(Config!$A$27="",G12=""),"",G12-F12) | I12: =IF(OR(Config!$A$27="",G12="",G12=0),"",H12/G12) | J12: =IF(Config!$A$27="","",IF(Config!$E$27="Interno","Interno",IF(Config!$E$27="Proposta","Proposta",IF(AND(E12<>"",E12>1),"Estourou as horas",IF(AND(I12<>"",I12<0.2),"Margem baixa",IF(AND(E12<>"",E12>0.85,Config!$E$27="Em andamento"),"Perto do limite","Saudável"))))))
A13: =IF(Config!$A$28="","",Config!$A$28) | B13: =IF(Config!$A$28="","",Config!$B$28) | C13: =IF(Config!$A$28="","",Config!$C$28) | D13: =IF(Config!$A$28="","",SUMIFS(Horas!$E$5:$E$804,Horas!$C$5:$C$804,Config!$A$28)) | E13: =IF(OR(Config!$A$28="",C13=0,C13=""),"",D13/C13) | F13: =IF(Config!$A$28="","",SUMIFS(Horas!$F$5:$F$804,Horas!$C$5:$C$804,Config!$A$28)) | G13: =IF(Config!$A$28="","",Config!$D$28) | H13: =IF(OR(Config!$A$28="",G13=""),"",G13-F13) | I13: =IF(OR(Config!$A$28="",G13="",G13=0),"",H13/G13) | J13: =IF(Config!$A$28="","",IF(Config!$E$28="Interno","Interno",IF(Config!$E$28="Proposta","Proposta",IF(AND(E13<>"",E13>1),"Estourou as horas",IF(AND(I13<>"",I13<0.2),"Margem baixa",IF(AND(E13<>"",E13>0.85,Config!$E$28="Em andamento"),"Perto do limite","Saudável"))))))
A14: =IF(Config!$A$29="","",Config!$A$29) | B14: =IF(Config!$A$29="","",Config!$B$29) | C14: =IF(Config!$A$29="","",Config!$C$29) | D14: =IF(Config!$A$29="","",SUMIFS(Horas!$E$5:$E$804,Horas!$C$5:$C$804,Config!$A$29)) | E14: =IF(OR(Config!$A$29="",C14=0,C14=""),"",D14/C14) | F14: =IF(Config!$A$29="","",SUMIFS(Horas!$F$5:$F$804,Horas!$C$5:$C$804,Config!$A$29)) | G14: =IF(Config!$A$29="","",Config!$D$29) | H14: =IF(OR(Config!$A$29="",G14=""),"",G14-F14) | I14: =IF(OR(Config!$A$29="",G14="",G14=0),"",H14/G14) | J14: =IF(Config!$A$29="","",IF(Config!$E$29="Interno","Interno",IF(Config!$E$29="Proposta","Proposta",IF(AND(E14<>"",E14>1),"Estourou as horas",IF(AND(I14<>"",I14<0.2),"Margem baixa",IF(AND(E14<>"",E14>0.85,Config!$E$29="Em andamento"),"Perto do limite","Saudável"))))))
A15: =IF(Config!$A$30="","",Config!$A$30) | B15: =IF(Config!$A$30="","",Config!$B$30) | C15: =IF(Config!$A$30="","",Config!$C$30) | D15: =IF(Config!$A$30="","",SUMIFS(Horas!$E$5:$E$804,Horas!$C$5:$C$804,Config!$A$30)) | E15: =IF(OR(Config!$A$30="",C15=0,C15=""),"",D15/C15) | F15: =IF(Config!$A$30="","",SUMIFS(Horas!$F$5:$F$804,Horas!$C$5:$C$804,Config!$A$30)) | G15: =IF(Config!$A$30="","",Config!$D$30) | H15: =IF(OR(Config!$A$30="",G15=""),"",G15-F15) | I15: =IF(OR(Config!$A$30="",G15="",G15=0),"",H15/G15) | J15: =IF(Config!$A$30="","",IF(Config!$E$30="Interno","Interno",IF(Config!$E$30="Proposta","Proposta",IF(AND(E15<>"",E15>1),"Estourou as horas",IF(AND(I15<>"",I15<0.2),"Margem baixa",IF(AND(E15<>"",E15>0.85,Config!$E$30="Em andamento"),"Perto do limite","Saudável"))))))
A16: =IF(Config!$A$31="","",Config!$A$31) | B16: =IF(Config!$A$31="","",Config!$B$31) | C16: =IF(Config!$A$31="","",Config!$C$31) | D16: =IF(Config!$A$31="","",SUMIFS(Horas!$E$5:$E$804,Horas!$C$5:$C$804,Config!$A$31)) | E16: =IF(OR(Config!$A$31="",C16=0,C16=""),"",D16/C16) | F16: =IF(Config!$A$31="","",SUMIFS(Horas!$F$5:$F$804,Horas!$C$5:$C$804,Config!$A$31)) | G16: =IF(Config!$A$31="","",Config!$D$31) | H16: =IF(OR(Config!$A$31="",G16=""),"",G16-F16) | I16: =IF(OR(Config!$A$31="",G16="",G16=0),"",H16/G16) | J16: =IF(Config!$A$31="","",IF(Config!$E$31="Interno","Interno",IF(Config!$E$31="Proposta","Proposta",IF(AND(E16<>"",E16>1),"Estourou as horas",IF(AND(I16<>"",I16<0.2),"Margem baixa",IF(AND(E16<>"",E16>0.85,Config!$E$31="Em andamento"),"Perto do limite","Saudável"))))))
A17: =IF(Config!$A$32="","",Config!$A$32) | B17: =IF(Config!$A$32="","",Config!$B$32) | C17: =IF(Config!$A$32="","",Config!$C$32) | D17: =IF(Config!$A$32="","",SUMIFS(Horas!$E$5:$E$804,Horas!$C$5:$C$804,Config!$A$32)) | E17: =IF(OR(Config!$A$32="",C17=0,C17=""),"",D17/C17) | F17: =IF(Config!$A$32="","",SUMIFS(Horas!$F$5:$F$804,Horas!$C$5:$C$804,Config!$A$32)) | G17: =IF(Config!$A$32="","",Config!$D$32) | H17: =IF(OR(Config!$A$32="",G17=""),"",G17-F17) | I17: =IF(OR(Config!$A$32="",G17="",G17=0),"",H17/G17) | J17: =IF(Config!$A$32="","",IF(Config!$E$32="Interno","Interno",IF(Config!$E$32="Proposta","Proposta",IF(AND(E17<>"",E17>1),"Estourou as horas",IF(AND(I17<>"",I17<0.2),"Margem baixa",IF(AND(E17<>"",E17>0.85,Config!$E$32="Em andamento"),"Perto do limite","Saudável"))))))
A18: =IF(Config!$A$33="","",Config!$A$33) | B18: =IF(Config!$A$33="","",Config!$B$33) | C18: =IF(Config!$A$33="","",Config!$C$33) | D18: =IF(Config!$A$33="","",SUMIFS(Horas!$E$5:$E$804,Horas!$C$5:$C$804,Config!$A$33)) | E18: =IF(OR(Config!$A$33="",C18=0,C18=""),"",D18/C18) | F18: =IF(Config!$A$33="","",SUMIFS(Horas!$F$5:$F$804,Horas!$C$5:$C$804,Config!$A$33)) | G18: =IF(Config!$A$33="","",Config!$D$33) | H18: =IF(OR(Config!$A$33="",G18=""),"",G18-F18) | I18: =IF(OR(Config!$A$33="",G18="",G18=0),"",H18/G18) | J18: =IF(Config!$A$33="","",IF(Config!$E$33="Interno","Interno",IF(Config!$E$33="Proposta","Proposta",IF(AND(E18<>"",E18>1),"Estourou as horas",IF(AND(I18<>"",I18<0.2),"Margem baixa",IF(AND(E18<>"",E18>0.85,Config!$E$33="Em andamento"),"Perto do limite","Saudável"))))))
A19: =IF(Config!$A$34="","",Config!$A$34) | B19: =IF(Config!$A$34="","",Config!$B$34) | C19: =IF(Config!$A$34="","",Config!$C$34) | D19: =IF(Config!$A$34="","",SUMIFS(Horas!$E$5:$E$804,Horas!$C$5:$C$804,Config!$A$34)) | E19: =IF(OR(Config!$A$34="",C19=0,C19=""),"",D19/C19) | F19: =IF(Config!$A$34="","",SUMIFS(Horas!$F$5:$F$804,Horas!$C$5:$C$804,Config!$A$34)) | G19: =IF(Config!$A$34="","",Config!$D$34) | H19: =IF(OR(Config!$A$34="",G19=""),"",G19-F19) | I19: =IF(OR(Config!$A$34="",G19="",G19=0),"",H19/G19) | J19: =IF(Config!$A$34="","",IF(Config!$E$34="Interno","Interno",IF(Config!$E$34="Proposta","Proposta",IF(AND(E19<>"",E19>1),"Estourou as horas",IF(AND(I19<>"",I19<0.2),"Margem baixa",IF(AND(E19<>"",E19>0.85,Config!$E$34="Em andamento"),"Perto do limite","Saudável"))))))
A20: =IF(Config!$A$35="","",Config!$A$35) | B20: =IF(Config!$A$35="","",Config!$B$35) | C20: =IF(Config!$A$35="","",Config!$C$35) | D20: =IF(Config!$A$35="","",SUMIFS(Horas!$E$5:$E$804,Horas!$C$5:$C$804,Config!$A$35)) | E20: =IF(OR(Config!$A$35="",C20=0,C20=""),"",D20/C20) | F20: =IF(Config!$A$35="","",SUMIFS(Horas!$F$5:$F$804,Horas!$C$5:$C$804,Config!$A$35)) | G20: =IF(Config!$A$35="","",Config!$D$35) | H20: =IF(OR(Config!$A$35="",G20=""),"",G20-F20) | I20: =IF(OR(Config!$A$35="",G20="",G20=0),"",H20/G20) | J20: =IF(Config!$A$35="","",IF(Config!$E$35="Interno","Interno",IF(Config!$E$35="Proposta","Proposta",IF(AND(E20<>"",E20>1),"Estourou as horas",IF(AND(I20<>"",I20<0.2),"Margem baixa",IF(AND(E20<>"",E20>0.85,Config!$E$35="Em andamento"),"Perto do limite","Saudável"))))))
A22: Por pessoa no mês
A23: Pessoa | B23: Horas lançadas | C23: Disponíveis | D23: Ocupação | E23: Faturáveis | F23: Custo no mês | G23: Custo-hora
A24: =IF(Config!$A$11="","",Config!$A$11) | B24: =IF(Config!$A$11="","",SUMIFS(Horas!$E$5:$E$804,Horas!$B$5:$B$804,Config!$A$11,Horas!$G$5:$G$804,Config!$B$7,Horas!$H$5:$H$804,Config!$B$5)) | C24: =IF(Config!$A$11="","",Config!$C$11) | D24: =IF(OR(Config!$A$11="",C24=0,C24=""),"",B24/C24) | E24: =IF(OR(Config!$A$11="",B24=0),"",SUMIFS(Horas!$E$5:$E$804,Horas!$B$5:$B$804,Config!$A$11,Horas!$G$5:$G$804,Config!$B$7,Horas!$H$5:$H$804,Config!$B$5,Horas!$I$5:$I$804,"Sim")/B24) | F24: =IF(Config!$A$11="","",SUMIFS(Horas!$F$5:$F$804,Horas!$B$5:$B$804,Config!$A$11,Horas!$G$5:$G$804,Config!$B$7,Horas!$H$5:$H$804,Config!$B$5)) | G24: =IF(Config!$A$11="","",Config!$D$11)
A25: =IF(Config!$A$12="","",Config!$A$12) | B25: =IF(Config!$A$12="","",SUMIFS(Horas!$E$5:$E$804,Horas!$B$5:$B$804,Config!$A$12,Horas!$G$5:$G$804,Config!$B$7,Horas!$H$5:$H$804,Config!$B$5)) | C25: =IF(Config!$A$12="","",Config!$C$12) | D25: =IF(OR(Config!$A$12="",C25=0,C25=""),"",B25/C25) | E25: =IF(OR(Config!$A$12="",B25=0),"",SUMIFS(Horas!$E$5:$E$804,Horas!$B$5:$B$804,Config!$A$12,Horas!$G$5:$G$804,Config!$B$7,Horas!$H$5:$H$804,Config!$B$5,Horas!$I$5:$I$804,"Sim")/B25) | F25: =IF(Config!$A$12="","",SUMIFS(Horas!$F$5:$F$804,Horas!$B$5:$B$804,Config!$A$12,Horas!$G$5:$G$804,Config!$B$7,Horas!$H$5:$H$804,Config!$B$5)) | G25: =IF(Config!$A$12="","",Config!$D$12)
A26: =IF(Config!$A$13="","",Config!$A$13) | B26: =IF(Config!$A$13="","",SUMIFS(Horas!$E$5:$E$804,Horas!$B$5:$B$804,Config!$A$13,Horas!$G$5:$G$804,Config!$B$7,Horas!$H$5:$H$804,Config!$B$5)) | C26: =IF(Config!$A$13="","",Config!$C$13) | D26: =IF(OR(Config!$A$13="",C26=0,C26=""),"",B26/C26) | E26: =IF(OR(Config!$A$13="",B26=0),"",SUMIFS(Horas!$E$5:$E$804,Horas!$B$5:$B$804,Config!$A$13,Horas!$G$5:$G$804,Config!$B$7,Horas!$H$5:$H$804,Config!$B$5,Horas!$I$5:$I$804,"Sim")/B26) | F26: =IF(Config!$A$13="","",SUMIFS(Horas!$F$5:$F$804,Horas!$B$5:$B$804,Config!$A$13,Horas!$G$5:$G$804,Config!$B$7,Horas!$H$5:$H$804,Config!$B$5)) | G26: =IF(Config!$A$13="","",Config!$D$13)
A27: =IF(Config!$A$14="","",Config!$A$14) | B27: =IF(Config!$A$14="","",SUMIFS(Horas!$E$5:$E$804,Horas!$B$5:$B$804,Config!$A$14,Horas!$G$5:$G$804,Config!$B$7,Horas!$H$5:$H$804,Config!$B$5)) | C27: =IF(Config!$A$14="","",Config!$C$14) | D27: =IF(OR(Config!$A$14="",C27=0,C27=""),"",B27/C27) | E27: =IF(OR(Config!$A$14="",B27=0),"",SUMIFS(Horas!$E$5:$E$804,Horas!$B$5:$B$804,Config!$A$14,Horas!$G$5:$G$804,Config!$B$7,Horas!$H$5:$H$804,Config!$B$5,Horas!$I$5:$I$804,"Sim")/B27) | F27: =IF(Config!$A$14="","",SUMIFS(Horas!$F$5:$F$804,Horas!$B$5:$B$804,Config!$A$14,Horas!$G$5:$G$804,Config!$B$7,Horas!$H$5:$H$804,Config!$B$5)) | G27: =IF(Config!$A$14="","",Config!$D$14)
A28: =IF(Config!$A$15="","",Config!$A$15) | B28: =IF(Config!$A$15="","",SUMIFS(Horas!$E$5:$E$804,Horas!$B$5:$B$804,Config!$A$15,Horas!$G$5:$G$804,Config!$B$7,Horas!$H$5:$H$804,Config!$B$5)) | C28: =IF(Config!$A$15="","",Config!$C$15) | D28: =IF(OR(Config!$A$15="",C28=0,C28=""),"",B28/C28) | E28: =IF(OR(Config!$A$15="",B28=0),"",SUMIFS(Horas!$E$5:$E$804,Horas!$B$5:$B$804,Config!$A$15,Horas!$G$5:$G$804,Config!$B$7,Horas!$H$5:$H$804,Config!$B$5,Horas!$I$5:$I$804,"Sim")/B28) | F28: =IF(Config!$A$15="","",SUMIFS(Horas!$F$5:$F$804,Horas!$B$5:$B$804,Config!$A$15,Horas!$G$5:$G$804,Config!$B$7,Horas!$H$5:$H$804,Config!$B$5)) | G28: =IF(Config!$A$15="","",Config!$D$15)
A29: =IF(Config!$A$16="","",Config!$A$16) | B29: =IF(Config!$A$16="","",SUMIFS(Horas!$E$5:$E$804,Horas!$B$5:$B$804,Config!$A$16,Horas!$G$5:$G$804,Config!$B$7,Horas!$H$5:$H$804,Config!$B$5)) | C29: =IF(Config!$A$16="","",Config!$C$16) | D29: =IF(OR(Config!$A$16="",C29=0,C29=""),"",B29/C29) | E29: =IF(OR(Config!$A$16="",B29=0),"",SUMIFS(Horas!$E$5:$E$804,Horas!$B$5:$B$804,Config!$A$16,Horas!$G$5:$G$804,Config!$B$7,Horas!$H$5:$H$804,Config!$B$5,Horas!$I$5:$I$804,"Sim")/B29) | F29: =IF(Config!$A$16="","",SUMIFS(Horas!$F$5:$F$804,Horas!$B$5:$B$804,Config!$A$16,Horas!$G$5:$G$804,Config!$B$7,Horas!$H$5:$H$804,Config!$B$5)) | G29: =IF(Config!$A$16="","",Config!$D$16)
A30: =IF(Config!$A$17="","",Config!$A$17) | B30: =IF(Config!$A$17="","",SUMIFS(Horas!$E$5:$E$804,Horas!$B$5:$B$804,Config!$A$17,Horas!$G$5:$G$804,Config!$B$7,Horas!$H$5:$H$804,Config!$B$5)) | C30: =IF(Config!$A$17="","",Config!$C$17) | D30: =IF(OR(Config!$A$17="",C30=0,C30=""),"",B30/C30) | E30: =IF(OR(Config!$A$17="",B30=0),"",SUMIFS(Horas!$E$5:$E$804,Horas!$B$5:$B$804,Config!$A$17,Horas!$G$5:$G$804,Config!$B$7,Horas!$H$5:$H$804,Config!$B$5,Horas!$I$5:$I$804,"Sim")/B30) | F30: =IF(Config!$A$17="","",SUMIFS(Horas!$F$5:$F$804,Horas!$B$5:$B$804,Config!$A$17,Horas!$G$5:$G$804,Config!$B$7,Horas!$H$5:$H$804,Config!$B$5)) | G30: =IF(Config!$A$17="","",Config!$D$17)
A31: =IF(Config!$A$18="","",Config!$A$18) | B31: =IF(Config!$A$18="","",SUMIFS(Horas!$E$5:$E$804,Horas!$B$5:$B$804,Config!$A$18,Horas!$G$5:$G$804,Config!$B$7,Horas!$H$5:$H$804,Config!$B$5)) | C31: =IF(Config!$A$18="","",Config!$C$18) | D31: =IF(OR(Config!$A$18="",C31=0,C31=""),"",B31/C31) | E31: =IF(OR(Config!$A$18="",B31=0),"",SUMIFS(Horas!$E$5:$E$804,Horas!$B$5:$B$804,Config!$A$18,Horas!$G$5:$G$804,Config!$B$7,Horas!$H$5:$H$804,Config!$B$5,Horas!$I$5:$I$804,"Sim")/B31) | F31: =IF(Config!$A$18="","",SUMIFS(Horas!$F$5:$F$804,Horas!$B$5:$B$804,Config!$A$18,Horas!$G$5:$G$804,Config!$B$7,Horas!$H$5:$H$804,Config!$B$5)) | G31: =IF(Config!$A$18="","",Config!$D$18)
A32: =IF(Config!$A$19="","",Config!$A$19) | B32: =IF(Config!$A$19="","",SUMIFS(Horas!$E$5:$E$804,Horas!$B$5:$B$804,Config!$A$19,Horas!$G$5:$G$804,Config!$B$7,Horas!$H$5:$H$804,Config!$B$5)) | C32: =IF(Config!$A$19="","",Config!$C$19) | D32: =IF(OR(Config!$A$19="",C32=0,C32=""),"",B32/C32) | E32: =IF(OR(Config!$A$19="",B32=0),"",SUMIFS(Horas!$E$5:$E$804,Horas!$B$5:$B$804,Config!$A$19,Horas!$G$5:$G$804,Config!$B$7,Horas!$H$5:$H$804,Config!$B$5,Horas!$I$5:$I$804,"Sim")/B32) | F32: =IF(Config!$A$19="","",SUMIFS(Horas!$F$5:$F$804,Horas!$B$5:$B$804,Config!$A$19,Horas!$G$5:$G$804,Config!$B$7,Horas!$H$5:$H$804,Config!$B$5)) | G32: =IF(Config!$A$19="","",Config!$D$19)
A33: =IF(Config!$A$20="","",Config!$A$20) | B33: =IF(Config!$A$20="","",SUMIFS(Horas!$E$5:$E$804,Horas!$B$5:$B$804,Config!$A$20,Horas!$G$5:$G$804,Config!$B$7,Horas!$H$5:$H$804,Config!$B$5)) | C33: =IF(Config!$A$20="","",Config!$C$20) | D33: =IF(OR(Config!$A$20="",C33=0,C33=""),"",B33/C33) | E33: =IF(OR(Config!$A$20="",B33=0),"",SUMIFS(Horas!$E$5:$E$804,Horas!$B$5:$B$804,Config!$A$20,Horas!$G$5:$G$804,Config!$B$7,Horas!$H$5:$H$804,Config!$B$5,Horas!$I$5:$I$804,"Sim")/B33) | F33: =IF(Config!$A$20="","",SUMIFS(Horas!$F$5:$F$804,Horas!$B$5:$B$804,Config!$A$20,Horas!$G$5:$G$804,Config!$B$7,Horas!$H$5:$H$804,Config!$B$5)) | G33: =IF(Config!$A$20="","",Config!$D$20)

Sheet Config
A1: Configurações
A2: Células amarelas: você preenche. Custo-hora = custo mensal da pessoa ÷ horas disponíveis no mês.
A4: Empresa ou equipe | B4: Prisma Comunicação (exemplo fictício) | H4: Meses
A5: Ano | B5: 2026 | H5: Janeiro
A6: Mês do painel | B6: Setembro | H6: Fevereiro
A7: Número do mês | B7: =MATCH(B6,$H$5:$H$16,0) | H7: Março
H8: Abril
A9: Pessoas (até 10) | H9: Maio
A10: Pessoa | B10: Custo mensal (R$) | C10: Horas disponíveis/mês | D10: Custo-hora (R$) | H10: Junho
A11: Ana | B11: 9800 | C11: 140 | D11: =IF(OR(A11="",C11=0),"",B11/C11) | H11: Julho
A12: Bruno | B12: 7200 | C12: 140 | D12: =IF(OR(A12="",C12=0),"",B12/C12) | H12: Agosto
A13: Carla | B13: 6500 | C13: 140 | D13: =IF(OR(A13="",C13=0),"",B13/C13) | H13: Setembro
A14: Diego | B14: 5800 | C14: 120 | D14: =IF(OR(A14="",C14=0),"",B14/C14) | H14: Outubro
D15: =IF(OR(A15="",C15=0),"",B15/C15) | H15: Novembro
D16: =IF(OR(A16="",C16=0),"",B16/C16) | H16: Dezembro
D17: =IF(OR(A17="",C17=0),"",B17/C17)
D18: =IF(OR(A18="",C18=0),"",B18/C18)
D19: =IF(OR(A19="",C19=0),"",B19/C19)
D20: =IF(OR(A20="",C20=0),"",B20/C20)
A22: Projetos (até 12)
A23: Projeto | B23: Cliente | C23: Horas orçadas | D23: Valor cobrado (R$) | E23: Status
A24: Site novo · Loja Verde | B24: Loja Verde | C24: 560 | D24: 24000 | E24: Em andamento
A25: Campanha de fim de ano · Bistrô 42 | B25: Bistrô 42 | C25: 300 | D25: 38000 | E25: Em andamento
A26: Relatório anual · Horizonte | B26: Horizonte | C26: 130 | D26: 16000 | E26: Em andamento
A27: Identidade visual · Padaria do Sol | B27: Padaria do Sol | C27: 70 | D27: 9500 | E27: Concluído
A28: Redes sociais · Clínica Bem-Estar | B28: Clínica Bem-Estar | C28: 40 | D28: 4500 | E28: Proposta
A29: Comercial e propostas | B29: Interno | C29: 0 | D29: 0 | E29: Interno
A30: Gestão e reuniões | B30: Interno | C30: 0 | D30: 0 | E30: Interno
A37: Custo mensal: salário + encargos, ou o valor que a pessoa cobra por mês. Horas disponíveis: 160 para tempo integral, menos reuniões e folgas (140 é realista). Status Proposta: projeto ainda não fechado; entra na lista para você já orçar, mas sem horas lançadas.

Sheet Horas
A1: Lançamento de horas
A2: Uma linha por pessoa, por dia, por projeto. Pessoa e projeto vêm de listas; custo e mês são calculados.
A4: Data | B4: Pessoa | C4: Projeto | D4: Atividade | E4: Horas | F4: Custo (R$) | G4: Mês | H4: Ano | I4: Faturável?
A5: 46204 | B5: Ana | C5: Comercial e propostas | D5: Reunião comercial | E5: 6 | F5: =IF(OR(B5="",E5=""),"",E5*IFERROR(INDEX(Config!$D$11:$D$20,MATCH(B5,Config!$A$11:$A$20,0)),0)) | G5: =IF(A5="","",MONTH(A5)) | H5: =IF(A5="","",YEAR(A5)) | I5: Não
A6: 46204 | B6: Ana | C6: Gestão e reuniões | D6: Planejamento | E6: 3 | F6: =IF(OR(B6="",E6=""),"",E6*IFERROR(INDEX(Config!$D$11:$D$20,MATCH(B6,Config!$A$11:$A$20,0)),0)) | G6: =IF(A6="","",MONTH(A6)) | H6: =IF(A6="","",YEAR(A6)) | I6: Não
A7: 46204 | B7: Bruno | C7: Gestão e reuniões | D7: Planejamento | E7: 1 | F7: =IF(OR(B7="",E7=""),"",E7*IFERROR(INDEX(Config!$D$11:$D$20,MATCH(B7,Config!$A$11:$A$20,0)),0)) | G7: =IF(A7="","",MONTH(A7)) | H7: =IF(A7="","",YEAR(A7)) | I7: Não
A8: 46204 | B8: Bruno | C8: Comercial e propostas | D8: Proposta | E8: 6 | F8: =IF(OR(B8="",E8=""),"",E8*IFERROR(INDEX(Config!$D$11:$D$20,MATCH(B8,Config!$A$11:$A$20,0)),0)) | G8: =IF(A8="","",MONTH(A8)) | H8: =IF(A8="","",YEAR(A8)) | I8: Não
A9: 46204 | B9: Carla | C9: Comercial e propostas | D9: Proposta | E9: 5 | F9: =IF(OR(B9="",E9=""),"",E9*IFERROR(INDEX(Config!$D$11:$D$20,MATCH(B9,Config!$A$11:$A$20,0)),0)) | G9: =IF(A9="","",MONTH(A9)) | H9: =IF(A9="","",YEAR(A9)) | I9: Não
A10: 46204 | B10: Carla | C10: Gestão e reuniões | D10: Planejamento | E10: 0.5 | F10: =IF(OR(B10="",E10=""),"",E10*IFERROR(INDEX(Config!$D$11:$D$20,MATCH(B10,Config!$A$11:$A$20,0)),0)) | G10: =IF(A10="","",MONTH(A10)) | H10: =IF(A10="","",YEAR(A10)) | I10: Não
A11: 46204 | B11: Diego | C11: Comercial e propostas | D11: Reunião comercial | E11: 3.5 | F11: =IF(OR(B11="",E11=""),"",E11*IFERROR(INDEX(Config!$D$11:$D$20,MATCH(B11,Config!$A$11:$A$20,0)),0)) | G11: =IF(A11="","",MONTH(A11)) | H11: =IF(A11="","",YEAR(A11)) | I11: Não
A12: 46204 | B12: Diego | C12: Gestão e reuniões | D12: Planejamento | E12: 5 | F12: =IF(OR(B12="",E12=""),"",E12*IFERROR(INDEX(Config!$D$11:$D$20,MATCH(B12,Config!$A$11:$A$20,0)),0)) | G12: =IF(A12="","",MONTH(A12)) | H12: =IF(A12="","",YEAR(A12)) | I12: Não
A13: 46205 | B13: Ana | C13: Comercial e propostas | D13: Proposta | E13: 5.5 | F13: =IF(OR(B13="",E13=""),"",E13*IFERROR(INDEX(Config!$D$11:$D$20,MATCH(B13,Config!$A$11:$A$20,0)),0)) | G13: =IF(A13="","",MONTH(A13)) | H13: =IF(A13="","",YEAR(A13)) | I13: Não
A14: 46205 | B14: Ana | C14: Gestão e reuniões | D14: Planejamento | E14: 3.5 | F14: =IF(OR(B14="",E14=""),"",E14*IFERROR(INDEX(Config!$D$11:$D$20,MATCH(B14,Config!$A$11:$A$20,0)),0)) | G14: =IF(A14="","",MONTH(A14)) | H14: =IF(A14="","",YEAR(A14)) | I14: Não
A15: 46205 | B15: Bruno | C15: Gestão e reuniões | D15: Semanal | E15: 0.5 | F15: =IF(OR(B15="",E15=""),"",E15*IFERROR(INDEX(Config!$D$11:$D$20,MATCH(B15,Config!$A$11:$A$20,0)),0)) | G15: =IF(A15="","",MONTH(A15)) | H15: =IF(A15="","",YEAR(A15)) | I15: Não
A16: 46205 | B16: Bruno | C16: Comercial e propostas | D16: Proposta | E16: 6.5 | F16: =IF(OR(B16="",E16=""),"",E16*IFERROR(INDEX(Config!$D$11:$D$20,MATCH(B16,Config!$A$11:$A$20,0)),0)) | G16: =IF(A16="","",MONTH(A16)) | H16: =IF(A16="","",YEAR(A16)) | I16: Não
... A563: 46276 | B563: Diego | C563: Gestão e reuniões | D563: Semanal | E563: 1.5 | F563: =IF(OR(B563="",E563=""),"",E563*IFERROR(INDEX(Config!$D$11:$D$20,MATCH(B563,Config!$A$11:$A$20,0)),0)) | G563: =IF(A563="","",MONTH(A563)) | H563: =IF(A563="","",YEAR(A563)) | I563: Não
F564: =IF(OR(B564="",E564=""),"",E564*IFERROR(INDEX(Config!$D$11:$D$20,MATCH(B564,Config!$A$11:$A$20,0)),0)) | G564: =IF(A564="","",MONTH(A564)) | H564: =IF(A564="","",YEAR(A564))
F565: =IF(OR(B565="",E565=""),"",E565*IFERROR(INDEX(Config!$D$11:$D$20,MATCH(B565,Config!$A$11:$A$20,0)),0)) | G565: =IF(A565="","",MONTH(A565)) | H565: =IF(A565="","",YEAR(A565))
F566: =IF(OR(B566="",E566=""),"",E566*IFERROR(INDEX(Config!$D$11:$D$20,MATCH(B566,Config!$A$11:$A$20,0)),0)) | G566: =IF(A566="","",MONTH(A566)) | H566: =IF(A566="","",YEAR(A566))
F567: =IF(OR(B567="",E567=""),"",E567*IFERROR(INDEX(Config!$D$11:$D$20,MATCH(B567,Config!$A$11:$A$20,0)),0)) | G567: =IF(A567="","",MONTH(A567)) | H567: =IF(A567="","",YEAR(A567))
F568: =IF(OR(B568="",E568=""),"",E568*IFERROR(INDEX(Config!$D$11:$D$20,MATCH(B568,Config!$A$11:$A$20,0)),0)) | G568: =IF(A568="","",MONTH(A568)) | H568: =IF(A568="","",YEAR(A568))
F569: =IF(OR(B569="",E569=""),"",E569*IFERROR(INDEX(Config!$D$11:$D$20,MATCH(B569,Config!$A$11:$A$20,0)),0)) | G569: =IF(A569="","",MONTH(A569)) | H569: =IF(A569="","",YEAR(A569))
F570: =IF(OR(B570="",E570=""),"",E570*IFERROR(INDEX(Config!$D$11:$D$20,MATCH(B570,Config!$A$11:$A$20,0)),0)) | G570: =IF(A570="","",MONTH(A570)) | H570: =IF(A570="","",YEAR(A570))
F571: =IF(OR(B571="",E571=""),"",E571*IFERROR(INDEX(Config!$D$11:$D$20,MATCH(B571,Config!$A$11:$A$20,0)),0)) | G571: =IF(A571="","",MONTH(A571)) | H571: =IF(A571="","",YEAR(A571))
F572: =IF(OR(B572="",E572=""),"",E572*IFERROR(INDEX(Config!$D$11:$D$20,MATCH(B572,Config!$A$11:$A$20,0)),0)) | G572: =IF(A572="","",MONTH(A572)) | H572: =IF(A572="","",YEAR(A572))
F573: =IF(OR(B573="",E573=""),"",E573*IFERROR(INDEX(Config!$D$11:$D$20,MATCH(B573,Config!$A$11:$A$20,0)),0)) | G573: =IF(A573="","",MONTH(A573)) | H573: =IF(A573="","",YEAR(A573))
F574: =IF(OR(B574="",E574=""),"",E574*IFERROR(INDEX(Config!$D$11:$D$20,MATCH(B574,Config!$A$11:$A$20,0)),0)) | G574: =IF(A574="","",MONTH(A574)) | H574: =IF(A574="","",YEAR(A574))
F575: =IF(OR(B575="",E575=""),"",E575*IFERROR(INDEX(Config!$D$11:$D$20,MATCH(B575,Config!$A$11:$A$20,0)),0)) | G575: =IF(A575="","",MONTH(A575)) | H575: =IF(A575="","",YEAR(A575))
... F804: =IF(OR(B804="",E804=""),"",E804*IFERROR(INDEX(Config!$D$11:$D$20,MATCH(B804,Config!$A$11:$A$20,0)),0)) | G804: =IF(A804="","",MONTH(A804)) | H804: =IF(A804="","",YEAR(A804))
