Workbook

Sheet Como usar
A1: Simulador de honorários
A2: Kit de Gestão para Advogados · Seu Sócio Gestor · versão 1.0 (setembro de 2026)
A4: O que esta planilha faz | B4: Para um caso, estima as horas por etapa e as despesas, calcula o custo do caso e compara quatro formas de cobrar: fixo, por hora, êxito e misto. Mostra a margem esperada, o que acontece se o caso for perdido, o ponto de equilíbrio e o risco de cada uma, e recomenda a de maior margem com risco aceitável.
A5: Passo 1 | B5: Em Config, confira impostos, margem e as regras de risco (chance mínima para êxito puro, folgas). Uma vez só.
A6: Passo 2 | B6: Em Simulador, bloco 1: cliente, área, custo-hora (copie da planilha 05), valor em discussão e a chance de êxito que você estima.
A7: Passo 3 | B7: Blocos 2 e 3: horas por etapa e despesas do caso, marcando o que o cliente reembolsa.
A8: Passo 4 | B8: Bloco 4: o valor que você pretende cobrar em cada modalidade. Mude os números e veja a comparação e a recomendação no topo mudarem na hora.
A9: Rotina | B9: Antes de cada proposta: 10 minutos. Depois, leve a modalidade escolhida para a planilha 07 (Proposta de honorários).
A10: Com a IA | B10: Copie o bloco 5 e use o prompt "Honorários 07 · Fixo, hora, êxito ou misto: perguntas antes de escolher" da biblioteca do kit para listar o que falta perguntar antes de fechar o valor. A decisão continua sua.
A11: Números em texto | B11: As frases da comparação ("Hora mínima sem prejuízo: R$ ...") usam a função FIXED: o separador de milhar e de decimal segue o idioma do Excel (no Excel em português: 1.234,56).
A12: Legenda | B12: Células amarelas: você preenche. Brancas: calculadas. Não é preciso mexer em nada fora do amarelo.
A13: Proteção | B13: Fórmulas protegidas sem senha. Para editar: Revisar > Desproteger planilha (Excel) ou Dados > Proteger intervalos (Google Sheets).
A14: Requisitos | B14: Excel 2016 ou mais novo, Microsoft 365 ou Google Sheets (só funções do Excel 2007+; nada de MÍNIMOSES, MÁXIMOSES ou UNIRTEXTO). No celular abre nos aplicativos; para preencher, use o computador.
A15: Google Sheets | B15: Faça upload no Google Drive e abra com o Google Sheets. Fórmulas, listas, cores, semáforos e gráficos funcionam: as regras de cor que dependem do mês escolhido em Config usam INDIRECT, que é a forma que o Sheets aceita para regra condicional apontar para outra aba.
... A18: Suporte | B18: suporte@seusociogestor.com.br · resposta em até 5 dias úteis · reembolso em até 7 dias pelo mesmo canal.

Sheet Simulador
A1: =Config!$B$4&" · Simulador de honorários · "&Config!$B$5 -> Ferraz & Lima Advocacia (exemplo fictício) · Simulador de honorários · Setembro de 2026
A2: Preencha o amarelo: dados do caso, horas por etapa, despesas e o que pretende cobrar em cada modalidade. A comparação e a recomendação são calculadas.
A4: Modalidade recomendada | C4: Margem esperada | E4: Risco da recomendada | G4: Custo total do caso | I4: Hora mínima para o caso
A5: =IF(NOT(ISNUMBER($B$11)),"Preencha o custo-hora primeiro",IF((Config!$B$13<>"Sim"),"Corrija as margens em Config",IF($B$29<=0,"Estime as horas primeiro",IF(MAX($J$52:$J$55)<=-1E+9,"Nenhuma com risco aceitável",INDEX($A$52:$A$55,MATCH(MAX($J$52:$J$55),$J$52:$J$55,0)))))) -> Hora | C5: =IF(MAX($J$52:$J$55)<=-1E+9,"",INDEX($E$52:$E$55,MATCH(MAX($J$52:$J$55),$J$52:$J$55,0))) -> 4825.0158 | E5: =IF(MAX($J$52:$J$55)<=-1E+9,"",INDEX($I$52:$I$55,MATCH(MAX($J$52:$J$55),$J$52:$J$55,0))) -> Baixo | G5: =$D$40 -> 3951.7842 | I5: =$B$15 -> 120.26124
A6: =IF(OR(COUNT($E$52:$E$55)=0,$B$29<=0),"Sem recomendação ainda: complete o custo-hora, as horas estimadas e a Config.",IF(MAX($J$52:$J$55)<=-1E+9,"Nenhuma modalidade ficou com risco aceitável. Reveja horas, valores ou a chance de êxito; a maior margem em números seria "&INDEX($A$52:$A$55,MATCH(MAX($E$52:$E$55),$E$52:$E$55,0))&".","Regra: maior margem esperada entre as modalidades com risco aceitável. Fora por risco alto: "&IF(COUNTIF($I$52:$I$55,"Alto")=0,"nenhuma",LEFT(IF($I$52="Alto","Fixo, ","")&IF($I$53="Alto","Hora, ","")&IF($I$54="Alto","Êxito, ","")&IF($I$55="Alto","Misto, ",""),LEN(IF($I$52="Alto","Fixo, ","")&IF($I$53="Alto","Hora, ","")&IF($I$54="Alto","Êxito, ","")&IF($I$55="Alto","Misto, ",""))-2))&". Compare também a coluna 'Se o caso for perdido' antes de decidir.")) -> Regra: maior margem esperada entre as modalidades com risco aceitável. Fora por risco alto: Êxito. Compare também a coluna 'Se o caso for perdido' antes de decidir.
A7: 1. O caso
A8: Cliente | B8: Roberto Almeida
A9: Área | B9: Cível
A10: O que será feito (resumo) | B10: Discussão de contrato de prestação de serviços
A11: Custo-hora do escritório (R$) | B11: 66.0714 | C11: ="Copie da planilha 05 · Custo-hora (Painel, ""Custo-hora do escritório""). No exemplo, R$ "&FIXED(B11,4)&" (18.500 ÷ 280 h). A hora mínima do caso (abaixo) é MAIOR do que a hora mínima do escritório na 05 sempre que o caso tiver despesa que o escritório absorve: a da 05 cobre só a estrutura, a daqui cobre também essas despesas rateadas pelas horas do caso." -> Copie da planilha 05 · Custo-hora (Painel, "Custo-hora do escritório"). No exemplo, R$ 66,0714 (18.500 ÷ 280 h). A hora mínima do caso (abaixo) é MAIOR do que a hora mínima do escritório na 05 sempre que o caso tiver despesa que o escritório absorve: a da 05 cobre só a estrutura, a daqui cobre também essas despesas rateadas pelas horas do caso.
A12: Valor em discussão (R$) | B12: 60000 | C12: Quanto o cliente recebe, deixa de pagar ou economiza se o caso der certo. Base do cálculo de êxito.
A13: Chance de êxito estimada (%) | B13: 0.55 | C13: Sua estimativa honesta. Ela define o valor esperado e o risco das modalidades com êxito.
A14: Valor esperado da causa (R$) | B14: =B12*B13 -> 33000 | C14: Valor em discussão × chance. É o que se espera receber, em média.
A15: Hora mínima para este caso (R$) | B15: =IF(NOT(ISNUMBER($B$11)),"Falta o custo-hora (B11)",IF((Config!$B$13<>"Sim"),"Margens inválidas (Config)",IFERROR(IF($B$29=0,B11/(1-Config!$B$7-Config!$B$8),($D$40/$B$29)/(1-Config!$B$7-Config!$B$8)),""))) -> 120.26124 | C15: (custo das horas + despesas absorvidas) ÷ horas estimadas ÷ (1 − impostos − margem). Sem caso montado, cai no custo-hora do escritório.
A17: 2. Horas estimadas por etapa
A18: Etapa | B18: Horas estimadas | C18: Custo (R$)
A19: Reunião inicial e análise dos documentos | B19: 4 | C19: =IF(B19="","",IF(ISNUMBER($B$11),B19*$B$11,"falta o custo-hora")) -> 264.2856
A20: Estudo do caso e estratégia | B20: 6 | C20: =IF(B20="","",IF(ISNUMBER($B$11),B20*$B$11,"falta o custo-hora")) -> 396.4284
A21: Redação e protocolo inicial | B21: 12 | C21: =IF(B21="","",IF(ISNUMBER($B$11),B21*$B$11,"falta o custo-hora")) -> 792.8568
A22: Acompanhamento e manifestações | B22: 20 | C22: =IF(B22="","",IF(ISNUMBER($B$11),B22*$B$11,"falta o custo-hora")) -> 1321.428
A23: Audiências e reuniões | B23: 8 | C23: =IF(B23="","",IF(ISNUMBER($B$11),B23*$B$11,"falta o custo-hora")) -> 528.5712
A24: Encerramento e prestação de contas | B24: 3 | C24: =IF(B24="","",IF(ISNUMBER($B$11),B24*$B$11,"falta o custo-hora")) -> 198.2142
C25: =IF(B25="","",IF(ISNUMBER($B$11),B25*$B$11,"falta o custo-hora"))
C26: =IF(B26="","",IF(ISNUMBER($B$11),B26*$B$11,"falta o custo-hora"))
C27: =IF(B27="","",IF(ISNUMBER($B$11),B27*$B$11,"falta o custo-hora"))
C28: =IF(B28="","",IF(ISNUMBER($B$11),B28*$B$11,"falta o custo-hora"))
A29: Total de horas e custo das horas | B29: =SUM(B19:B28) -> 53 | C29: =IF(ISNUMBER($B$11),SUM(C19:C28),"falta o custo-hora") -> 3501.7842
A31: 3. Despesas do caso
A32: Despesa | B32: Valor (R$) | C32: Cliente reembolsa? | D32: Custo para o escritório (R$)
A33: Taxas e custas | B33: 800 | C33: Sim | D33: =IF(B33="","",IF(C33="Sim",0,B33)) -> 0
A34: Deslocamentos | B34: 300 | C34: Não | D34: =IF(B34="","",IF(C34="Sim",0,B34)) -> 300
A35: Cópias e certidões | B35: 150 | C35: Não | D35: =IF(B35="","",IF(C35="Sim",0,B35)) -> 150
A36: Terceiros (perito, tradutor) | B36: 0 | C36: Sim | D36: =IF(B36="","",IF(C36="Sim",0,B36)) -> 0
D37: =IF(B37="","",IF(C37="Sim",0,B37))
D38: =IF(B38="","",IF(C38="Sim",0,B38))
A39: Total de despesas · custo para o escritório | B39: =SUM(B33:B38) -> 1250 | D39: =SUM(D33:D38) -> 450
A40: Custo total do caso (horas + despesas que o escritório absorve) | D40: =IF(ISNUMBER($B$11),$C$29+$D$39,"Falta o custo-hora (B11)") -> 3951.7842
A42: 4. O que você pretende cobrar em cada modalidade
A43: Modalidade | B43: Valor | C43: Como funciona
A44: Fixo · valor fechado (R$) | B44: 7000 | C44: Um valor pelo caso inteiro, independente das horas. Risco: o caso consumir mais horas que o estimado.
A45: Hora · valor da hora cobrada (R$) | B45: 180 | C45: Cobra as horas trabalhadas: o escritório não absorve hora a mais, mas o cliente pode questionar as horas. Se a hora cobre a hora mínima do caso ou não, quem diz é a coluna Risco ao lado.
A46: Êxito · % sobre o resultado | B46: 0.25 | C46: Só recebe se o caso der certo, no fim. Risco: trabalhar e não receber.
A47: Misto · entrada fixa (R$) | B47: 4500 | C47: Uma parte fixa no início (cobre o custo) mais um percentual sobre o resultado.
A48: Misto · % sobre o resultado | B48: 0.15
A50: 5. Comparação das modalidades
A51: Modalidade | B51: Receita esperada (R$) | C51: Impostos e taxas (R$) | D51: Custo do caso (R$) | E51: Margem esperada (R$) | F51: Margem (%) | G51: Se o caso for perdido (R$) | H51: Ponto de equilíbrio | I51: Risco | J51: Pontuação | K51: Por que este risco
A52: Fixo | B52: =$B$44 -> 7000 | C52: =IF((Config!$B$13<>"Sim"),"",B52*Config!$B$7) -> 560 | D52: =$D$40 -> 3951.7842 | E52: =IF(AND(ISNUMBER(C52),ISNUMBER(D52)),B52-C52-D52,"") -> 2488.2158 | F52: =IF(OR(B52=0,NOT(ISNUMBER(E52))),"",E52/B52) -> 0.3554594 | G52: =IF(AND(ISNUMBER($D$40),NOT((Config!$B$13<>"Sim"))),E52,"") -> 2488.2158 | H52: =IF(NOT(ISNUMBER($D$40)),"Falta o custo-hora (B11)",IF((Config!$B$13<>"Sim"),"Margens inválidas (Config)",IFERROR("Até "&ROUND(($B$44*(1-Config!$B$7)-$D$39)/$B$11,0)&" horas sem prejuízo (estimadas: "&ROUND($B$29,0)&")","Preencha horas e valores"))) -> Até 91 horas sem prejuízo (estimadas: 53) | I52: =IF(NOT(ISNUMBER($D$40)),"Falta o custo-hora",IF((Config!$B$13<>"Sim"),"Margens inválidas",IF($B$29<=0,"Faltam as horas estimadas",IFERROR(IF($B$29=0,"Alto",IF(($B$44*(1-Config!$B$7)-$D$39)/$B$11/$B$29-1>=Config!$B$11,"Baixo",IF(($B$44*(1-Config!$B$7)-$D$39)/$B$11>=$B$29,"Médio","Alto"))),"Alto")))) -> Baixo | J52: =IF(OR(I52="Baixo",AND(I52="Médio",Config!$B$12="Sim")),E52,-1E+9) -> 2488.2158 | K52: =IF(NOT(ISNUMBER($D$40)),"Preencha o custo-hora do escritório (B11): sem ele não há custo do caso, margem nem risco.",IF((Config!$B$13<>"Sim"),"Impostos e margem em Config fora do permitido (cada um de 0 % a 99 %, soma abaixo de 100 %). Corrija a Config.",IF($B$29<=0,"Preencha as horas estimadas no bloco 2: sem elas não há custo do caso por hora, nem margem, nem ponto de equilíbrio.",IFERROR("Folga de horas: "&ROUND((($B$44*(1-Config!$B$7)-$D$39)/$B$11/$B$29-1)*100,0)&"% (mínimo para risco baixo: "&ROUND(Config!$B$11*100,0)&"%)","")))) -> Folga de horas: 71% (mínimo para risco baixo: 20%)
A53: Hora | B53: =$B$45*$B$29 -> 9540 | C53: =IF((Config!$B$13<>"Sim"),"",B53*Config!$B$7) -> 763.2 | D53: =$D$40 -> 3951.7842 | E53: =IF(AND(ISNUMBER(C53),ISNUMBER(D53)),B53-C53-D53,"") -> 4825.0158 | F53: =IF(OR(B53=0,NOT(ISNUMBER(E53))),"",E53/B53) -> 0.50576686 | G53: =IF(AND(ISNUMBER($D$40),NOT((Config!$B$13<>"Sim"))),E53,"") -> 4825.0158 | H53: =IF(NOT(ISNUMBER($D$40)),"Falta o custo-hora (B11)",IF((Config!$B$13<>"Sim"),"Margens inválidas (Config)",IFERROR("Hora mínima sem prejuízo: R$ "&FIXED($D$40/($B$29*(1-Config!$B$7)),2)&" (você cobra R$ "&FIXED($B$45,2)&")","Preencha horas e valores"))) -> Hora mínima sem prejuízo: R$ 81,05 (você cobra R$ 180,00) | I53: =IF(NOT(ISNUMBER($D$40)),"Falta o custo-hora",IF((Config!$B$13<>"Sim"),"Margens inválidas",IF($B$29<=0,"Faltam as horas estimadas",IFERROR(IF($B$45>=$B$15,"Baixo",IF($B$45*$B$29*(1-Config!$B$7)>=$D$40,"Médio","Alto")),"Alto")))) -> Baixo | J53: =IF(OR(I53="Baixo",AND(I53="Médio",Config!$B$12="Sim")),E53,-1E+9) -> 4825.0158 | K53: =IF(NOT(ISNUMBER($D$40)),"Preencha o custo-hora do escritório (B11): sem ele não há custo do caso, margem nem risco.",IF((Config!$B$13<>"Sim"),"Impostos e margem em Config fora do permitido (cada um de 0 % a 99 %, soma abaixo de 100 %). Corrija a Config.",IF($B$29<=0,"Preencha as horas estimadas no bloco 2: sem elas não há custo do caso por hora, nem margem, nem ponto de equilíbrio.",IFERROR(IF($B$45>=$B$15,"A hora cobrada cobre custo, impostos e margem desejada","A hora cobrada fica abaixo da hora mínima com margem (R$ "&FIXED($B$15,2)&")"),"")))) -> A hora cobrada cobre custo, impostos e margem desejada
A54: Êxito | B54: =$B$46*$B$14 -> 8250 | C54: =IF((Config!$B$13<>"Sim"),"",B54*Config!$B$7) -> 660 | D54: =$D$40 -> 3951.7842 | E54: =IF(AND(ISNUMBER(C54),ISNUMBER(D54)),B54-C54-D54,"") -> 3638.2158 | F54: =IF(OR(B54=0,NOT(ISNUMBER(E54))),"",E54/B54) -> 0.44099585 | G54: =IF(AND(ISNUMBER($D$40),NOT((Config!$B$13<>"Sim"))),-$D$40,"") -> -3951.7842 | H54: =IF(NOT(ISNUMBER($D$40)),"Falta o custo-hora (B11)",IF((Config!$B$13<>"Sim"),"Margens inválidas (Config)",IFERROR("Chance mínima de êxito para não ter prejuízo: "&ROUND($D$40/($B$46*$B$12*(1-Config!$B$7))*100,0)&"% (estimada: "&ROUND($B$13*100,0)&"%)","Preencha horas e valores"))) -> Chance mínima de êxito para não ter prejuízo: 29% (estimada: 55%) | I54: =IF(NOT(ISNUMBER($D$40)),"Falta o custo-hora",IF((Config!$B$13<>"Sim"),"Margens inválidas",IF($B$29<=0,"Faltam as horas estimadas",IFERROR(IF(OR($B$13<Config!$B$9,$B$13<$D$40/($B$46*$B$12*(1-Config!$B$7))+Config!$B$10),"Alto","Médio"),"Alto")))) -> Alto | J54: =IF(OR(I54="Baixo",AND(I54="Médio",Config!$B$12="Sim")),E54,-1E+9) -> -1000000000 | K54: =IF(NOT(ISNUMBER($D$40)),"Preencha o custo-hora do escritório (B11): sem ele não há custo do caso, margem nem risco.",IF((Config!$B$13<>"Sim"),"Impostos e margem em Config fora do permitido (cada um de 0 % a 99 %, soma abaixo de 100 %). Corrija a Config.",IF($B$29<=0,"Preencha as horas estimadas no bloco 2: sem elas não há custo do caso por hora, nem margem, nem ponto de equilíbrio.",IFERROR(IF($B$13<Config!$B$9,"Chance estimada abaixo do mínimo aceitável para êxito puro ("&ROUND(Config!$B$9*100,0)&"%)",IF($B$13<$D$40/($B$46*$B$12*(1-Config!$B$7))+Config!$B$10,"Chance estimada perto demais do ponto de equilíbrio","Só recebe no fim; o caixa precisa aguentar até lá")),"")))) -> Chance estimada abaixo do mínimo aceitável para êxito puro (60%)
A55: Misto | B55: =$B$47+$B$48*$B$14 -> 9450 | C55: =IF((Config!$B$13<>"Sim"),"",B55*Config!$B$7) -> 756 | D55: =$D$40 -> 3951.7842 | E55: =IF(AND(ISNUMBER(C55),ISNUMBER(D55)),B55-C55-D55,"") -> 4742.2158 | F55: =IF(OR(B55=0,NOT(ISNUMBER(E55))),"",E55/B55) -> 0.50182178 | G55: =IF(AND(ISNUMBER($D$40),NOT((Config!$B$13<>"Sim"))),$B$47*(1-Config!$B$7)-$D$40,"") -> 188.2158 | H55: =IF(NOT(ISNUMBER($D$40)),"Falta o custo-hora (B11)",IF((Config!$B$13<>"Sim"),"Margens inválidas (Config)",IFERROR(IF($B$47*(1-Config!$B$7)>=$D$40,"A entrada já cobre o custo do caso; o êxito é margem","Chance mínima de êxito para não ter prejuízo: "&ROUND(($D$40-$B$47*(1-Config!$B$7))/($B$48*$B$12*(1-Config!$B$7))*100,0)&"% (estimada: "&ROUND($B$13*100,0)&"%)"),"Preencha horas e valores"))) -> A entrada já cobre o custo do caso; o êxito é margem | I55: =IF(NOT(ISNUMBER($D$40)),"Falta o custo-hora",IF((Config!$B$13<>"Sim"),"Margens inválidas",IF($B$29<=0,"Faltam as horas estimadas",IFERROR(IF($B$13<MAX(0,($D$40-$B$47*(1-Config!$B$7))/($B$48*$B$12*(1-Config!$B$7)))+Config!$B$10,"Alto",IF($B$47*(1-Config!$B$7)<$D$40,"Médio","Baixo")),"Alto")))) -> Baixo | J55: =IF(OR(I55="Baixo",AND(I55="Médio",Config!$B$12="Sim")),E55,-1E+9) -> 4742.2158 | K55: =IF(NOT(ISNUMBER($D$40)),"Preencha o custo-hora do escritório (B11): sem ele não há custo do caso, margem nem risco.",IF((Config!$B$13<>"Sim"),"Impostos e margem em Config fora do permitido (cada um de 0 % a 99 %, soma abaixo de 100 %). Corrija a Config.",IF($B$29<=0,"Preencha as horas estimadas no bloco 2: sem elas não há custo do caso por hora, nem margem, nem ponto de equilíbrio.",IFERROR(IF($B$47*(1-Config!$B$7)>=$D$40,"Entrada cobre o custo: mesmo perdendo, não há prejuízo",IF($B$47*(1-Config!$B$7)<$D$40,"Entrada não cobre todo o custo; parte depende do êxito","")),"")))) -> Entrada cobre o custo: mesmo perdendo, não há prejuízo
A56: Pontuação: coluna auxiliar da recomendação (margem esperada; modalidade com risco recusado vale −1 bilhão). Receita esperada de êxito e misto = percentual × valor esperado da causa.

Sheet Config
A1: Configurações
A2: Células amarelas: você preenche. Impostos, margem e as regras de risco valem para todos os casos simulados.
E3: Preencha de cima para baixo, sem pular linha.
A4: Nome do escritório | B4: Ferraz & Lima Advocacia (exemplo fictício) | E4: Áreas | G4: Modalidades
A5: Mês de referência | B5: Setembro de 2026 | E5: Cível | G5: Fixo
A6: Data de referência | B6: 46279 | E6: Trabalhista | G6: Hora
A7: Impostos e taxas sobre o que entra (%) | B7: 0.08 | C7: Exemplo; confira com o contador. O mesmo percentual da planilha 05. | E7: Previdenciário | G7: Êxito
A8: Margem desejada sobre o preço (%) | B8: 0.3 | C8: Quanto do preço deve sobrar depois do custo. Igual à planilha 05. | E8: Empresarial | G8: Misto
A9: Chance de êxito mínima para aceitar êxito puro (%) | B9: 0.6 | C9: Abaixo disso, êxito puro é marcado como risco alto: o escritório trabalha meses e pode não receber. | E9: Família
A10: Folga mínima de chance acima do ponto de equilíbrio (pontos) | B10: 0.15 | C10: Se a chance estimada está a menos de 15 pontos da chance mínima para não ter prejuízo, o risco é alto.
A11: Folga mínima de horas no valor fixo (%) | B11: 0.2 | C11: No fixo, o risco é o caso consumir mais horas que o estimado. Com 20% de folga ou mais, risco baixo.
A12: Aceitar risco médio na recomendação? | B12: Sim | C12: "Não" faz a recomendação escolher só entre modalidades de risco baixo.
A13: Impostos e margem conferem? (calculado) | B13: =IF(AND(ISNUMBER(B7),ISNUMBER(B8)),IF(AND(B7>=0,B7<1,B8>=0,B8<1,B7+B8<1),"Sim","Não"),"Não") -> Sim | C13: "Não" suspende hora mínima, margens, risco e recomendação no Simulador até a Config ser corrigida.
