Workbook

Sheet Como usar
A1: Agenda e ocupação por profissional e sala
A2: Kit de Gestão para Médicos · Seu Sócio Gestor · versão 1.0 (setembro de 2026)
A4: O que esta planilha faz | B4: Registra cada horário da agenda (quem atende, em que sala, qual paciente, pagador e procedimento, e o que aconteceu) e mede o que ninguém mede: quantas horas a clínica tinha disponíveis, quantas foram atendidas, a ocupação por profissional, por sala e por dia da semana, as faltas e a produção do mês.
A5: Passo 1 | B5: Em Config, cadastre profissionais, salas, pagadores (particular e convênios), procedimentos com duração e a tabela de preços por pagador. Depois os turnos da semana (quem atende em que dia, período e sala) e os feriados. Preencha as listas de cima para baixo, sem pular linha.
A6: Passo 2 | B6: Em Pacientes, uma linha por paciente: nome, pagador, profissional principal e contato. Só o necessário para agendar e cobrar; nada clínico. Esta aba é a fonte do cadastro de pacientes (a 14 copia daqui).
A7: Passo 3 | B7: Em Agenda, uma linha por horário: data, hora, profissional, sala, paciente, pagador, procedimento e situação. No fim do dia, a recepção marca Realizado, Falta, Cancelado ou Remarcado e a forma de pagamento (a planilha 04 tem esse passo no fechamento do dia).
A8: Passo 4 | B8: Em Painel, escolha o mês em Config: horas disponíveis (só dias já passados), atendidas, ocupação, horas vazias, faltas e produção; por profissional, por sala, por dia da semana e período, por procedimento e por pagador; e os próximos 7 dias com as vagas.
A9: Rotina de segunda | B9: 4 minutos: olhar as vagas dos próximos 7 dias e a ocupação da semana. Confirmar os agendados da semana é a rotina seguinte (mais 4 minutos). As duas estão na planilha 03 · Rotina da semana, que soma 12 minutos na segunda e 18 na sexta.
A10: Limite e como estender | B10: A aba Agenda tem 3.000 linhas (5 a 3004): com cerca de 300 atendimentos por mês, dá 10 meses. Quando chegar perto do fim, copie a última linha preenchida para baixo (a aba precisa ser desprotegida em Revisar > Desproteger planilha) e ajuste o número final nas fórmulas do Painel, ou comece um arquivo por ano — é o mais simples e mantém o histórico separado. A aba Pacientes tem 400 linhas.
A11: Ligação com as outras planilhas | B11: A produção por profissional alimenta o repasse (11); os atendimentos de convênio viram guias (13); os a prazo, parcelas (14); os no cartão, a conciliação (16). O Painel da clínica (17) copia horas atendidas, ocupação e faltas daqui. A planilha 02 copia esta Agenda para medir faltas e montar a lista de retorno.
A12: Com a IA | B12: Copie "Por dia da semana e período" e "Por profissional" e use o prompt "Agenda 01 · Onde a agenda esvazia" da biblioteca do kit. Nunca cole a aba Pacientes ou a Agenda com nomes na IA: use só as tabelas do Painel.
A13: Legenda | B13: Células amarelas: você preenche. Brancas: calculadas. Não é preciso mexer em nada fora do amarelo.
A14: Proteção | B14: Fórmulas protegidas sem senha. Para editar: Revisar > Desproteger planilha (Excel) ou Dados > Proteger intervalos (Google Sheets).
A15: Requisitos | B15: Excel 2016 ou mais novo, Microsoft 365 ou Google Sheets (só funções do Excel 2007+; nada de MÍNIMOSES, MÁXIMOSES ou UNIRTEXTO). No celular abre nos aplicativos; para preencher, use o computador.
... A20: Suporte | B20: suporte@seusociogestor.com.br · resposta em até 5 dias úteis · reembolso em até 7 dias pelo mesmo canal.

Sheet Painel
A1: =Config!$B$4&" · Agenda e ocupação · "&Config!$B$6&" de "&Config!$B$5 -> Clínica Vida Plena (exemplo fictício) · Agenda e ocupação · Setembro de 2026
A2: Nada para digitar aqui. Escolha o mês em Config; tudo vem de Agenda e dos turnos. Ocupação = horas atendidas ÷ horas disponíveis (só dias já passados).
A4: Horas disponíveis (até ontem) | C4: Horas atendidas | E4: Ocupação | G4: Horas vazias | I4: Faltas no mês | K4: Produção (R$)
A5: =SUM(Config!$G$20:$G$43) -> 64 | C5: =SUMIFS(Agenda!$R$5:$R$3004,Agenda!$N$5:$N$3004,Config!$B$7,Agenda!$O$5:$O$3004,Config!$B$5) -> 51.833333 | E5: =IF(A5=0,"",C5/A5) -> 0.80989583 | G5: =IF(A5=0,"",MAX(0,A5-C5)) -> 12.166667 | I5: =COUNTIFS(Agenda!$H$5:$H$3004,"Falta",Agenda!$N$5:$N$3004,Config!$B$7,Agenda!$O$5:$O$3004,Config!$B$5) -> 6 | K5: =SUMIFS(Agenda!$M$5:$M$3004,Agenda!$H$5:$H$3004,"Realizado",Agenda!$N$5:$N$3004,Config!$B$7,Agenda!$O$5:$O$3004,Config!$B$5) -> 20045
A7: Horas vazias = disponíveis − atendidas: inclui faltas, cancelamentos e horários que ninguém marcou. Produção = valor de tabela dos atendimentos realizados (particular e convênio), antes de glosa e taxas; o que entrou de fato está no caixa (09).
A8: =IF(SUM(Agenda!$V$5:$V$3004)=0,"","Atenção: "&SUM(Agenda!$V$5:$V$3004)&" atendimento(s) realizado(s) sem minutos ou sem valor na Agenda (em vermelho lá). Eles não entram nas horas atendidas, na ocupação nem na produção: os números deste Painel estão MENORES do que a realidade até você completar. Valor 0 digitado é válido (retorno incluído na consulta).")
A9: Por profissional
A10: Profissional | B10: Horas disponíveis | C10: Horas atendidas | D10: Ocupação | E10: Realizados | F10: Faltas | G10: Taxa de falta | H10: Produção (R$) | I10: Barra
A11: =IF(Config!$D$5="","",Config!$D$5) -> Dra. Carolina Mendes | B11: =IF(Config!$D$5="","",SUMIFS(Config!$G$20:$G$43,Config!$A$20:$A$43,Config!$D$5)) -> 24 | C11: =IF(Config!$D$5="","",SUMIFS(Agenda!$R$5:$R$3004,Agenda!$C$5:$C$3004,Config!$D$5,Agenda!$N$5:$N$3004,Config!$B$7,Agenda!$O$5:$O$3004,Config!$B$5)) -> 22 | D11: =IF(OR(Config!$D$5="",B11=0),"",C11/B11) -> 0.91666667 | E11: =IF(Config!$D$5="","",COUNTIFS(Agenda!$C$5:$C$3004,Config!$D$5,Agenda!$H$5:$H$3004,"Realizado",Agenda!$N$5:$N$3004,Config!$B$7,Agenda!$O$5:$O$3004,Config!$B$5)) -> 47 | F11: =IF(Config!$D$5="","",COUNTIFS(Agenda!$C$5:$C$3004,Config!$D$5,Agenda!$H$5:$H$3004,"Falta",Agenda!$N$5:$N$3004,Config!$B$7,Agenda!$O$5:$O$3004,Config!$B$5)) -> 1 | G11: =IF(Config!$D$5="","",IF(E11+F11=0,"",F11/(E11+F11))) -> 0.020833333 | H11: =IF(Config!$D$5="","",SUMIFS(Agenda!$M$5:$M$3004,Agenda!$C$5:$C$3004,Config!$D$5,Agenda!$H$5:$H$3004,"Realizado",Agenda!$N$5:$N$3004,Config!$B$7,Agenda!$O$5:$O$3004,Config!$B$5)) -> 10050 | I11: =IF(D11="","",REPT("█",ROUND(MIN(1,D11)*30,0))) -> ████████████████████████████
A12: =IF(Config!$D$6="","",Config!$D$6) -> Dr. Paulo Andrade | B12: =IF(Config!$D$6="","",SUMIFS(Config!$G$20:$G$43,Config!$A$20:$A$43,Config!$D$6)) -> 24 | C12: =IF(Config!$D$6="","",SUMIFS(Agenda!$R$5:$R$3004,Agenda!$C$5:$C$3004,Config!$D$6,Agenda!$N$5:$N$3004,Config!$B$7,Agenda!$O$5:$O$3004,Config!$B$5)) -> 15.833333 | D12: =IF(OR(Config!$D$6="",B12=0),"",C12/B12) -> 0.65972222 | E12: =IF(Config!$D$6="","",COUNTIFS(Agenda!$C$5:$C$3004,Config!$D$6,Agenda!$H$5:$H$3004,"Realizado",Agenda!$N$5:$N$3004,Config!$B$7,Agenda!$O$5:$O$3004,Config!$B$5)) -> 36 | F12: =IF(Config!$D$6="","",COUNTIFS(Agenda!$C$5:$C$3004,Config!$D$6,Agenda!$H$5:$H$3004,"Falta",Agenda!$N$5:$N$3004,Config!$B$7,Agenda!$O$5:$O$3004,Config!$B$5)) -> 4 | G12: =IF(Config!$D$6="","",IF(E12+F12=0,"",F12/(E12+F12))) -> 0.1 | H12: =IF(Config!$D$6="","",SUMIFS(Agenda!$M$5:$M$3004,Agenda!$C$5:$C$3004,Config!$D$6,Agenda!$H$5:$H$3004,"Realizado",Agenda!$N$5:$N$3004,Config!$B$7,Agenda!$O$5:$O$3004,Config!$B$5)) -> 4145 | I12: =IF(D12="","",REPT("█",ROUND(MIN(1,D12)*30,0))) -> ████████████████████
A13: =IF(Config!$D$7="","",Config!$D$7) -> Dra. Renata Sousa | B13: =IF(Config!$D$7="","",SUMIFS(Config!$G$20:$G$43,Config!$A$20:$A$43,Config!$D$7)) -> 16 | C13: =IF(Config!$D$7="","",SUMIFS(Agenda!$R$5:$R$3004,Agenda!$C$5:$C$3004,Config!$D$7,Agenda!$N$5:$N$3004,Config!$B$7,Agenda!$O$5:$O$3004,Config!$B$5)) -> 14 | D13: =IF(OR(Config!$D$7="",B13=0),"",C13/B13) -> 0.875 | E13: =IF(Config!$D$7="","",COUNTIFS(Agenda!$C$5:$C$3004,Config!$D$7,Agenda!$H$5:$H$3004,"Realizado",Agenda!$N$5:$N$3004,Config!$B$7,Agenda!$O$5:$O$3004,Config!$B$5)) -> 24 | F13: =IF(Config!$D$7="","",COUNTIFS(Agenda!$C$5:$C$3004,Config!$D$7,Agenda!$H$5:$H$3004,"Falta",Agenda!$N$5:$N$3004,Config!$B$7,Agenda!$O$5:$O$3004,Config!$B$5)) -> 1 | G13: =IF(Config!$D$7="","",IF(E13+F13=0,"",F13/(E13+F13))) -> 0.04 | H13: =IF(Config!$D$7="","",SUMIFS(Agenda!$M$5:$M$3004,Agenda!$C$5:$C$3004,Config!$D$7,Agenda!$H$5:$H$3004,"Realizado",Agenda!$N$5:$N$3004,Config!$B$7,Agenda!$O$5:$O$3004,Config!$B$5)) -> 5850 | I13: =IF(D13="","",REPT("█",ROUND(MIN(1,D13)*30,0))) -> ██████████████████████████
A14: =IF(Config!$D$8="","",Config!$D$8) | B14: =IF(Config!$D$8="","",SUMIFS(Config!$G$20:$G$43,Config!$A$20:$A$43,Config!$D$8)) | C14: =IF(Config!$D$8="","",SUMIFS(Agenda!$R$5:$R$3004,Agenda!$C$5:$C$3004,Config!$D$8,Agenda!$N$5:$N$3004,Config!$B$7,Agenda!$O$5:$O$3004,Config!$B$5)) | D14: =IF(OR(Config!$D$8="",B14=0),"",C14/B14) | E14: =IF(Config!$D$8="","",COUNTIFS(Agenda!$C$5:$C$3004,Config!$D$8,Agenda!$H$5:$H$3004,"Realizado",Agenda!$N$5:$N$3004,Config!$B$7,Agenda!$O$5:$O$3004,Config!$B$5)) | F14: =IF(Config!$D$8="","",COUNTIFS(Agenda!$C$5:$C$3004,Config!$D$8,Agenda!$H$5:$H$3004,"Falta",Agenda!$N$5:$N$3004,Config!$B$7,Agenda!$O$5:$O$3004,Config!$B$5)) | G14: =IF(Config!$D$8="","",IF(E14+F14=0,"",F14/(E14+F14))) | H14: =IF(Config!$D$8="","",SUMIFS(Agenda!$M$5:$M$3004,Agenda!$C$5:$C$3004,Config!$D$8,Agenda!$H$5:$H$3004,"Realizado",Agenda!$N$5:$N$3004,Config!$B$7,Agenda!$O$5:$O$3004,Config!$B$5)) | I14: =IF(D14="","",REPT("█",ROUND(MIN(1,D14)*30,0)))
A15: =IF(Config!$D$9="","",Config!$D$9) | B15: =IF(Config!$D$9="","",SUMIFS(Config!$G$20:$G$43,Config!$A$20:$A$43,Config!$D$9)) | C15: =IF(Config!$D$9="","",SUMIFS(Agenda!$R$5:$R$3004,Agenda!$C$5:$C$3004,Config!$D$9,Agenda!$N$5:$N$3004,Config!$B$7,Agenda!$O$5:$O$3004,Config!$B$5)) | D15: =IF(OR(Config!$D$9="",B15=0),"",C15/B15) | E15: =IF(Config!$D$9="","",COUNTIFS(Agenda!$C$5:$C$3004,Config!$D$9,Agenda!$H$5:$H$3004,"Realizado",Agenda!$N$5:$N$3004,Config!$B$7,Agenda!$O$5:$O$3004,Config!$B$5)) | F15: =IF(Config!$D$9="","",COUNTIFS(Agenda!$C$5:$C$3004,Config!$D$9,Agenda!$H$5:$H$3004,"Falta",Agenda!$N$5:$N$3004,Config!$B$7,Agenda!$O$5:$O$3004,Config!$B$5)) | G15: =IF(Config!$D$9="","",IF(E15+F15=0,"",F15/(E15+F15))) | H15: =IF(Config!$D$9="","",SUMIFS(Agenda!$M$5:$M$3004,Agenda!$C$5:$C$3004,Config!$D$9,Agenda!$H$5:$H$3004,"Realizado",Agenda!$N$5:$N$3004,Config!$B$7,Agenda!$O$5:$O$3004,Config!$B$5)) | I15: =IF(D15="","",REPT("█",ROUND(MIN(1,D15)*30,0)))
A16: =IF(Config!$D$10="","",Config!$D$10) | B16: =IF(Config!$D$10="","",SUMIFS(Config!$G$20:$G$43,Config!$A$20:$A$43,Config!$D$10)) | C16: =IF(Config!$D$10="","",SUMIFS(Agenda!$R$5:$R$3004,Agenda!$C$5:$C$3004,Config!$D$10,Agenda!$N$5:$N$3004,Config!$B$7,Agenda!$O$5:$O$3004,Config!$B$5)) | D16: =IF(OR(Config!$D$10="",B16=0),"",C16/B16) | E16: =IF(Config!$D$10="","",COUNTIFS(Agenda!$C$5:$C$3004,Config!$D$10,Agenda!$H$5:$H$3004,"Realizado",Agenda!$N$5:$N$3004,Config!$B$7,Agenda!$O$5:$O$3004,Config!$B$5)) | F16: =IF(Config!$D$10="","",COUNTIFS(Agenda!$C$5:$C$3004,Config!$D$10,Agenda!$H$5:$H$3004,"Falta",Agenda!$N$5:$N$3004,Config!$B$7,Agenda!$O$5:$O$3004,Config!$B$5)) | G16: =IF(Config!$D$10="","",IF(E16+F16=0,"",F16/(E16+F16))) | H16: =IF(Config!$D$10="","",SUMIFS(Agenda!$M$5:$M$3004,Agenda!$C$5:$C$3004,Config!$D$10,Agenda!$H$5:$H$3004,"Realizado",Agenda!$N$5:$N$3004,Config!$B$7,Agenda!$O$5:$O$3004,Config!$B$5)) | I16: =IF(D16="","",REPT("█",ROUND(MIN(1,D16)*30,0)))
A17: =IF(Config!$D$11="","",Config!$D$11) | B17: =IF(Config!$D$11="","",SUMIFS(Config!$G$20:$G$43,Config!$A$20:$A$43,Config!$D$11)) | C17: =IF(Config!$D$11="","",SUMIFS(Agenda!$R$5:$R$3004,Agenda!$C$5:$C$3004,Config!$D$11,Agenda!$N$5:$N$3004,Config!$B$7,Agenda!$O$5:$O$3004,Config!$B$5)) | D17: =IF(OR(Config!$D$11="",B17=0),"",C17/B17) | E17: =IF(Config!$D$11="","",COUNTIFS(Agenda!$C$5:$C$3004,Config!$D$11,Agenda!$H$5:$H$3004,"Realizado",Agenda!$N$5:$N$3004,Config!$B$7,Agenda!$O$5:$O$3004,Config!$B$5)) | F17: =IF(Config!$D$11="","",COUNTIFS(Agenda!$C$5:$C$3004,Config!$D$11,Agenda!$H$5:$H$3004,"Falta",Agenda!$N$5:$N$3004,Config!$B$7,Agenda!$O$5:$O$3004,Config!$B$5)) | G17: =IF(Config!$D$11="","",IF(E17+F17=0,"",F17/(E17+F17))) | H17: =IF(Config!$D$11="","",SUMIFS(Agenda!$M$5:$M$3004,Agenda!$C$5:$C$3004,Config!$D$11,Agenda!$H$5:$H$3004,"Realizado",Agenda!$N$5:$N$3004,Config!$B$7,Agenda!$O$5:$O$3004,Config!$B$5)) | I17: =IF(D17="","",REPT("█",ROUND(MIN(1,D17)*30,0)))
A18: =IF(Config!$D$12="","",Config!$D$12) | B18: =IF(Config!$D$12="","",SUMIFS(Config!$G$20:$G$43,Config!$A$20:$A$43,Config!$D$12)) | C18: =IF(Config!$D$12="","",SUMIFS(Agenda!$R$5:$R$3004,Agenda!$C$5:$C$3004,Config!$D$12,Agenda!$N$5:$N$3004,Config!$B$7,Agenda!$O$5:$O$3004,Config!$B$5)) | D18: =IF(OR(Config!$D$12="",B18=0),"",C18/B18) | E18: =IF(Config!$D$12="","",COUNTIFS(Agenda!$C$5:$C$3004,Config!$D$12,Agenda!$H$5:$H$3004,"Realizado",Agenda!$N$5:$N$3004,Config!$B$7,Agenda!$O$5:$O$3004,Config!$B$5)) | F18: =IF(Config!$D$12="","",COUNTIFS(Agenda!$C$5:$C$3004,Config!$D$12,Agenda!$H$5:$H$3004,"Falta",Agenda!$N$5:$N$3004,Config!$B$7,Agenda!$O$5:$O$3004,Config!$B$5)) | G18: =IF(Config!$D$12="","",IF(E18+F18=0,"",F18/(E18+F18))) | H18: =IF(Config!$D$12="","",SUMIFS(Agenda!$M$5:$M$3004,Agenda!$C$5:$C$3004,Config!$D$12,Agenda!$H$5:$H$3004,"Realizado",Agenda!$N$5:$N$3004,Config!$B$7,Agenda!$O$5:$O$3004,Config!$B$5)) | I18: =IF(D18="","",REPT("█",ROUND(MIN(1,D18)*30,0)))
A19: Ocupação abaixo de 60 % fica em amarelo; taxa de falta acima de 10 % em vermelho. Taxa de falta = faltas ÷ (faltas + realizados), a mesma conta da planilha 02.
A21: Por sala
A22: Sala | B22: Horas disponíveis | C22: Horas atendidas | D22: Ocupação | E22: Horas vazias | F22: Turnos por semana
A23: =IF(Config!$F$5="","",Config!$F$5) -> Sala 1 | B23: =IF(Config!$F$5="","",SUMIFS(Config!$G$20:$G$43,Config!$D$20:$D$43,Config!$F$5)) -> 40 | C23: =IF(Config!$F$5="","",SUMIFS(Agenda!$R$5:$R$3004,Agenda!$D$5:$D$3004,Config!$F$5,Agenda!$N$5:$N$3004,Config!$B$7,Agenda!$O$5:$O$3004,Config!$B$5)) -> 36 | D23: =IF(OR(Config!$F$5="",B23=0),"",C23/B23) -> 0.9 | E23: =IF(B23="","",MAX(0,B23-C23)) -> 4 | F23: =IF(Config!$F$5="","",COUNTIFS(Config!$D$20:$D$43,Config!$F$5,Config!$A$20:$A$43,"<>")) -> 6
A24: =IF(Config!$F$6="","",Config!$F$6) -> Sala 2 | B24: =IF(Config!$F$6="","",SUMIFS(Config!$G$20:$G$43,Config!$D$20:$D$43,Config!$F$6)) -> 24 | C24: =IF(Config!$F$6="","",SUMIFS(Agenda!$R$5:$R$3004,Agenda!$D$5:$D$3004,Config!$F$6,Agenda!$N$5:$N$3004,Config!$B$7,Agenda!$O$5:$O$3004,Config!$B$5)) -> 15.833333 | D24: =IF(OR(Config!$F$6="",B24=0),"",C24/B24) -> 0.65972222 | E24: =IF(B24="","",MAX(0,B24-C24)) -> 8.1666667 | F24: =IF(Config!$F$6="","",COUNTIFS(Config!$D$20:$D$43,Config!$F$6,Config!$A$20:$A$43,"<>")) -> 4
A25: =IF(Config!$F$7="","",Config!$F$7) | B25: =IF(Config!$F$7="","",SUMIFS(Config!$G$20:$G$43,Config!$D$20:$D$43,Config!$F$7)) | C25: =IF(Config!$F$7="","",SUMIFS(Agenda!$R$5:$R$3004,Agenda!$D$5:$D$3004,Config!$F$7,Agenda!$N$5:$N$3004,Config!$B$7,Agenda!$O$5:$O$3004,Config!$B$5)) | D25: =IF(OR(Config!$F$7="",B25=0),"",C25/B25) | E25: =IF(B25="","",MAX(0,B25-C25)) | F25: =IF(Config!$F$7="","",COUNTIFS(Config!$D$20:$D$43,Config!$F$7,Config!$A$20:$A$43,"<>"))
A26: =IF(Config!$F$8="","",Config!$F$8) | B26: =IF(Config!$F$8="","",SUMIFS(Config!$G$20:$G$43,Config!$D$20:$D$43,Config!$F$8)) | C26: =IF(Config!$F$8="","",SUMIFS(Agenda!$R$5:$R$3004,Agenda!$D$5:$D$3004,Config!$F$8,Agenda!$N$5:$N$3004,Config!$B$7,Agenda!$O$5:$O$3004,Config!$B$5)) | D26: =IF(OR(Config!$F$8="",B26=0),"",C26/B26) | E26: =IF(B26="","",MAX(0,B26-C26)) | F26: =IF(Config!$F$8="","",COUNTIFS(Config!$D$20:$D$43,Config!$F$8,Config!$A$20:$A$43,"<>"))
A27: =IF(Config!$F$9="","",Config!$F$9) | B27: =IF(Config!$F$9="","",SUMIFS(Config!$G$20:$G$43,Config!$D$20:$D$43,Config!$F$9)) | C27: =IF(Config!$F$9="","",SUMIFS(Agenda!$R$5:$R$3004,Agenda!$D$5:$D$3004,Config!$F$9,Agenda!$N$5:$N$3004,Config!$B$7,Agenda!$O$5:$O$3004,Config!$B$5)) | D27: =IF(OR(Config!$F$9="",B27=0),"",C27/B27) | E27: =IF(B27="","",MAX(0,B27-C27)) | F27: =IF(Config!$F$9="","",COUNTIFS(Config!$D$20:$D$43,Config!$F$9,Config!$A$20:$A$43,"<>"))
A28: =IF(Config!$F$10="","",Config!$F$10) | B28: =IF(Config!$F$10="","",SUMIFS(Config!$G$20:$G$43,Config!$D$20:$D$43,Config!$F$10)) | C28: =IF(Config!$F$10="","",SUMIFS(Agenda!$R$5:$R$3004,Agenda!$D$5:$D$3004,Config!$F$10,Agenda!$N$5:$N$3004,Config!$B$7,Agenda!$O$5:$O$3004,Config!$B$5)) | D28: =IF(OR(Config!$F$10="",B28=0),"",C28/B28) | E28: =IF(B28="","",MAX(0,B28-C28)) | F28: =IF(Config!$F$10="","",COUNTIFS(Config!$D$20:$D$43,Config!$F$10,Config!$A$20:$A$43,"<>"))
A29: Sala com poucos turnos por semana é capacidade parada: cabe outro profissional por repasse (planilha 11) sem aumentar o aluguel.
A32: Por dia da semana e período (onde a agenda esvazia)
A33: Dia | B33: Manhã · disponíveis | C33: Manhã · atendidas | D33: Manhã · ocupação | E33: Tarde · disponíveis | F33: Tarde · atendidas | G33: Tarde · ocupação | H33: Faltas no dia
A34: Segunda | B34: =SUMIFS(Config!$G$20:$G$43,Config!$B$20:$B$43,A34,Config!$C$20:$C$43,"Manhã") -> 0 | C34: =SUMIFS(Agenda!$R$5:$R$3004,Agenda!$P$5:$P$3004,A34,Agenda!$Q$5:$Q$3004,"Manhã",Agenda!$N$5:$N$3004,Config!$B$7,Agenda!$O$5:$O$3004,Config!$B$5) -> 0 | D34: =IF(B34=0,"",C34/B34) | E34: =SUMIFS(Config!$G$20:$G$43,Config!$B$20:$B$43,A34,Config!$C$20:$C$43,"Tarde") -> 0 | F34: =SUMIFS(Agenda!$R$5:$R$3004,Agenda!$P$5:$P$3004,A34,Agenda!$Q$5:$Q$3004,"Tarde",Agenda!$N$5:$N$3004,Config!$B$7,Agenda!$O$5:$O$3004,Config!$B$5) -> 0 | G34: =IF(E34=0,"",F34/E34) | H34: =COUNTIFS(Agenda!$P$5:$P$3004,A34,Agenda!$H$5:$H$3004,"Falta",Agenda!$N$5:$N$3004,Config!$B$7,Agenda!$O$5:$O$3004,Config!$B$5) -> 0
A35: Terça | B35: =SUMIFS(Config!$G$20:$G$43,Config!$B$20:$B$43,A35,Config!$C$20:$C$43,"Manhã") -> 8 | C35: =SUMIFS(Agenda!$R$5:$R$3004,Agenda!$P$5:$P$3004,A35,Agenda!$Q$5:$Q$3004,"Manhã",Agenda!$N$5:$N$3004,Config!$B$7,Agenda!$O$5:$O$3004,Config!$B$5) -> 6.8333333 | D35: =IF(B35=0,"",C35/B35) -> 0.85416667 | E35: =SUMIFS(Config!$G$20:$G$43,Config!$B$20:$B$43,A35,Config!$C$20:$C$43,"Tarde") -> 16 | F35: =SUMIFS(Agenda!$R$5:$R$3004,Agenda!$P$5:$P$3004,A35,Agenda!$Q$5:$Q$3004,"Tarde",Agenda!$N$5:$N$3004,Config!$B$7,Agenda!$O$5:$O$3004,Config!$B$5) -> 13 | G35: =IF(E35=0,"",F35/E35) -> 0.8125 | H35: =COUNTIFS(Agenda!$P$5:$P$3004,A35,Agenda!$H$5:$H$3004,"Falta",Agenda!$N$5:$N$3004,Config!$B$7,Agenda!$O$5:$O$3004,Config!$B$5) -> 2
A36: Quarta | B36: =SUMIFS(Config!$G$20:$G$43,Config!$B$20:$B$43,A36,Config!$C$20:$C$43,"Manhã") -> 0 | C36: =SUMIFS(Agenda!$R$5:$R$3004,Agenda!$P$5:$P$3004,A36,Agenda!$Q$5:$Q$3004,"Manhã",Agenda!$N$5:$N$3004,Config!$B$7,Agenda!$O$5:$O$3004,Config!$B$5) -> 0 | D36: =IF(B36=0,"",C36/B36) | E36: =SUMIFS(Config!$G$20:$G$43,Config!$B$20:$B$43,A36,Config!$C$20:$C$43,"Tarde") -> 8 | F36: =SUMIFS(Agenda!$R$5:$R$3004,Agenda!$P$5:$P$3004,A36,Agenda!$Q$5:$Q$3004,"Tarde",Agenda!$N$5:$N$3004,Config!$B$7,Agenda!$O$5:$O$3004,Config!$B$5) -> 7.8333333 | G36: =IF(E36=0,"",F36/E36) -> 0.97916667 | H36: =COUNTIFS(Agenda!$P$5:$P$3004,A36,Agenda!$H$5:$H$3004,"Falta",Agenda!$N$5:$N$3004,Config!$B$7,Agenda!$O$5:$O$3004,Config!$B$5) -> 0
A37: Quinta | B37: =SUMIFS(Config!$G$20:$G$43,Config!$B$20:$B$43,A37,Config!$C$20:$C$43,"Manhã") -> 8 | C37: =SUMIFS(Agenda!$R$5:$R$3004,Agenda!$P$5:$P$3004,A37,Agenda!$Q$5:$Q$3004,"Manhã",Agenda!$N$5:$N$3004,Config!$B$7,Agenda!$O$5:$O$3004,Config!$B$5) -> 7.3333333 | D37: =IF(B37=0,"",C37/B37) -> 0.91666667 | E37: =SUMIFS(Config!$G$20:$G$43,Config!$B$20:$B$43,A37,Config!$C$20:$C$43,"Tarde") -> 16 | F37: =SUMIFS(Agenda!$R$5:$R$3004,Agenda!$P$5:$P$3004,A37,Agenda!$Q$5:$Q$3004,"Tarde",Agenda!$N$5:$N$3004,Config!$B$7,Agenda!$O$5:$O$3004,Config!$B$5) -> 11.666667 | G37: =IF(E37=0,"",F37/E37) -> 0.72916667 | H37: =COUNTIFS(Agenda!$P$5:$P$3004,A37,Agenda!$H$5:$H$3004,"Falta",Agenda!$N$5:$N$3004,Config!$B$7,Agenda!$O$5:$O$3004,Config!$B$5) -> 2
A38: Sexta | B38: =SUMIFS(Config!$G$20:$G$43,Config!$B$20:$B$43,A38,Config!$C$20:$C$43,"Manhã") -> 8 | C38: =SUMIFS(Agenda!$R$5:$R$3004,Agenda!$P$5:$P$3004,A38,Agenda!$Q$5:$Q$3004,"Manhã",Agenda!$N$5:$N$3004,Config!$B$7,Agenda!$O$5:$O$3004,Config!$B$5) -> 5.1666667 | D38: =IF(B38=0,"",C38/B38) -> 0.64583333 | E38: =SUMIFS(Config!$G$20:$G$43,Config!$B$20:$B$43,A38,Config!$C$20:$C$43,"Tarde") -> 0 | F38: =SUMIFS(Agenda!$R$5:$R$3004,Agenda!$P$5:$P$3004,A38,Agenda!$Q$5:$Q$3004,"Tarde",Agenda!$N$5:$N$3004,Config!$B$7,Agenda!$O$5:$O$3004,Config!$B$5) -> 0 | G38: =IF(E38=0,"",F38/E38) | H38: =COUNTIFS(Agenda!$P$5:$P$3004,A38,Agenda!$H$5:$H$3004,"Falta",Agenda!$N$5:$N$3004,Config!$B$7,Agenda!$O$5:$O$3004,Config!$B$5) -> 2
A39: Sábado | B39: =SUMIFS(Config!$G$20:$G$43,Config!$B$20:$B$43,A39,Config!$C$20:$C$43,"Manhã") -> 0 | C39: =SUMIFS(Agenda!$R$5:$R$3004,Agenda!$P$5:$P$3004,A39,Agenda!$Q$5:$Q$3004,"Manhã",Agenda!$N$5:$N$3004,Config!$B$7,Agenda!$O$5:$O$3004,Config!$B$5) -> 0 | D39: =IF(B39=0,"",C39/B39) | E39: =SUMIFS(Config!$G$20:$G$43,Config!$B$20:$B$43,A39,Config!$C$20:$C$43,"Tarde") -> 0 | F39: =SUMIFS(Agenda!$R$5:$R$3004,Agenda!$P$5:$P$3004,A39,Agenda!$Q$5:$Q$3004,"Tarde",Agenda!$N$5:$N$3004,Config!$B$7,Agenda!$O$5:$O$3004,Config!$B$5) -> 0 | G39: =IF(E39=0,"",F39/E39) | H39: =COUNTIFS(Agenda!$P$5:$P$3004,A39,Agenda!$H$5:$H$3004,"Falta",Agenda!$N$5:$N$3004,Config!$B$7,Agenda!$O$5:$O$3004,Config!$B$5) -> 0
A40: Dia em cinza: nenhum turno disponível no período contado. As horas disponíveis só contam dias já passados e pulam os feriados de Config, então num mês em andamento um dia da semana pode aparecer zerado sem que a clínica tenha fechado. No exemplo (setembro), a segunda aparece assim: 07/09 é feriado e 14/09 é hoje, e as duas segundas anteriores ao mês não contam — Dra. Carolina e Dr. Paulo atendem normalmente às segundas.
A42: Por procedimento
A43: Procedimento | B43: Realizados | C43: Horas | D43: Produção (R$) | E43: Valor médio (R$) | G43: Pagador | H43: Realizados | I43: Horas | J43: Faltas | K43: Taxa de falta | L43: Produção (R$) | M43: Valor médio (R$) | N43: % da produção
A44: =IF(Config!$J$5="","",Config!$J$5) -> Consulta | B44: =IF(Config!$J$5="","",COUNTIFS(Agenda!$G$5:$G$3004,Config!$J$5,Agenda!$H$5:$H$3004,"Realizado",Agenda!$N$5:$N$3004,Config!$B$7,Agenda!$O$5:$O$3004,Config!$B$5)) -> 49 | C44: =IF(Config!$J$5="","",SUMIFS(Agenda!$U$5:$U$3004,Agenda!$G$5:$G$3004,Config!$J$5,Agenda!$N$5:$N$3004,Config!$B$7,Agenda!$O$5:$O$3004,Config!$B$5)) -> 24.5 | D44: =IF(Config!$J$5="","",SUMIFS(Agenda!$M$5:$M$3004,Agenda!$G$5:$G$3004,Config!$J$5,Agenda!$H$5:$H$3004,"Realizado",Agenda!$N$5:$N$3004,Config!$B$7,Agenda!$O$5:$O$3004,Config!$B$5)) -> 11240 | E44: =IF(OR(Config!$J$5="",B44=0),"",D44/B44) -> 229.38776 | G44: =IF(Config!$H$5="","",Config!$H$5) -> Particular | H44: =IF(Config!$H$5="","",COUNTIFS(Agenda!$F$5:$F$3004,Config!$H$5,Agenda!$H$5:$H$3004,"Realizado",Agenda!$N$5:$N$3004,Config!$B$7,Agenda!$O$5:$O$3004,Config!$B$5)) -> 55 | I44: =IF(Config!$H$5="","",SUMIFS(Agenda!$U$5:$U$3004,Agenda!$F$5:$F$3004,Config!$H$5,Agenda!$N$5:$N$3004,Config!$B$7,Agenda!$O$5:$O$3004,Config!$B$5)) -> 27 | J44: =IF(Config!$H$5="","",COUNTIFS(Agenda!$F$5:$F$3004,Config!$H$5,Agenda!$H$5:$H$3004,"Falta",Agenda!$N$5:$N$3004,Config!$B$7,Agenda!$O$5:$O$3004,Config!$B$5)) -> 2 | K44: =IF(Config!$H$5="","",IF(H44+J44=0,"",J44/(H44+J44))) -> 0.035087719 | L44: =IF(Config!$H$5="","",SUMIFS(Agenda!$M$5:$M$3004,Agenda!$F$5:$F$3004,Config!$H$5,Agenda!$H$5:$H$3004,"Realizado",Agenda!$N$5:$N$3004,Config!$B$7,Agenda!$O$5:$O$3004,Config!$B$5)) -> 15620 | M44: =IF(OR(Config!$H$5="",H44=0),"",L44/H44) -> 284 | N44: =IF(OR(Config!$H$5="",$K$5=0),"",L44/$K$5) -> 0.77924669
A45: =IF(Config!$J$6="","",Config!$J$6) -> Retorno | B45: =IF(Config!$J$6="","",COUNTIFS(Agenda!$G$5:$G$3004,Config!$J$6,Agenda!$H$5:$H$3004,"Realizado",Agenda!$N$5:$N$3004,Config!$B$7,Agenda!$O$5:$O$3004,Config!$B$5)) -> 23 | C45: =IF(Config!$J$6="","",SUMIFS(Agenda!$U$5:$U$3004,Agenda!$G$5:$G$3004,Config!$J$6,Agenda!$N$5:$N$3004,Config!$B$7,Agenda!$O$5:$O$3004,Config!$B$5)) -> 7.6666667 | D45: =IF(Config!$J$6="","",SUMIFS(Agenda!$M$5:$M$3004,Agenda!$G$5:$G$3004,Config!$J$6,Agenda!$H$5:$H$3004,"Realizado",Agenda!$N$5:$N$3004,Config!$B$7,Agenda!$O$5:$O$3004,Config!$B$5)) -> 0 | E45: =IF(OR(Config!$J$6="",B45=0),"",D45/B45) -> 0 | G45: =IF(Config!$H$6="","",Config!$H$6) -> Saúde Total | H45: =IF(Config!$H$6="","",COUNTIFS(Agenda!$F$5:$F$3004,Config!$H$6,Agenda!$H$5:$H$3004,"Realizado",Agenda!$N$5:$N$3004,Config!$B$7,Agenda!$O$5:$O$3004,Config!$B$5)) -> 26 | I45: =IF(Config!$H$6="","",SUMIFS(Agenda!$U$5:$U$3004,Agenda!$F$5:$F$3004,Config!$H$6,Agenda!$N$5:$N$3004,Config!$B$7,Agenda!$O$5:$O$3004,Config!$B$5)) -> 12.833333 | J45: =IF(Config!$H$6="","",COUNTIFS(Agenda!$F$5:$F$3004,Config!$H$6,Agenda!$H$5:$H$3004,"Falta",Agenda!$N$5:$N$3004,Config!$B$7,Agenda!$O$5:$O$3004,Config!$B$5)) -> 2 | K45: =IF(Config!$H$6="","",IF(H45+J45=0,"",J45/(H45+J45))) -> 0.071428571 | L45: =IF(Config!$H$6="","",SUMIFS(Agenda!$M$5:$M$3004,Agenda!$F$5:$F$3004,Config!$H$6,Agenda!$H$5:$H$3004,"Realizado",Agenda!$N$5:$N$3004,Config!$B$7,Agenda!$O$5:$O$3004,Config!$B$5)) -> 2435 | M45: =IF(OR(Config!$H$6="",H45=0),"",L45/H45) -> 93.653846 | N45: =IF(OR(Config!$H$6="",$K$5=0),"",L45/$K$5) -> 0.12147668
A46: =IF(Config!$J$7="","",Config!$J$7) -> ECG | B46: =IF(Config!$J$7="","",COUNTIFS(Agenda!$G$5:$G$3004,Config!$J$7,Agenda!$H$5:$H$3004,"Realizado",Agenda!$N$5:$N$3004,Config!$B$7,Agenda!$O$5:$O$3004,Config!$B$5)) -> 5 | C46: =IF(Config!$J$7="","",SUMIFS(Agenda!$U$5:$U$3004,Agenda!$G$5:$G$3004,Config!$J$7,Agenda!$N$5:$N$3004,Config!$B$7,Agenda!$O$5:$O$3004,Config!$B$5)) -> 1.6666667 | D46: =IF(Config!$J$7="","",SUMIFS(Agenda!$M$5:$M$3004,Agenda!$G$5:$G$3004,Config!$J$7,Agenda!$H$5:$H$3004,"Realizado",Agenda!$N$5:$N$3004,Config!$B$7,Agenda!$O$5:$O$3004,Config!$B$5)) -> 375 | E46: =IF(OR(Config!$J$7="",B46=0),"",D46/B46) -> 75 | G46: =IF(Config!$H$7="","",Config!$H$7) -> MediPlan | H46: =IF(Config!$H$7="","",COUNTIFS(Agenda!$F$5:$F$3004,Config!$H$7,Agenda!$H$5:$H$3004,"Realizado",Agenda!$N$5:$N$3004,Config!$B$7,Agenda!$O$5:$O$3004,Config!$B$5)) -> 19 | I46: =IF(Config!$H$7="","",SUMIFS(Agenda!$U$5:$U$3004,Agenda!$F$5:$F$3004,Config!$H$7,Agenda!$N$5:$N$3004,Config!$B$7,Agenda!$O$5:$O$3004,Config!$B$5)) -> 8.6666667 | J46: =IF(Config!$H$7="","",COUNTIFS(Agenda!$F$5:$F$3004,Config!$H$7,Agenda!$H$5:$H$3004,"Falta",Agenda!$N$5:$N$3004,Config!$B$7,Agenda!$O$5:$O$3004,Config!$B$5)) -> 1 | K46: =IF(Config!$H$7="","",IF(H46+J46=0,"",J46/(H46+J46))) -> 0.05 | L46: =IF(Config!$H$7="","",SUMIFS(Agenda!$M$5:$M$3004,Agenda!$F$5:$F$3004,Config!$H$7,Agenda!$H$5:$H$3004,"Realizado",Agenda!$N$5:$N$3004,Config!$B$7,Agenda!$O$5:$O$3004,Config!$B$5)) -> 1445 | M46: =IF(OR(Config!$H$7="",H46=0),"",L46/H46) -> 76.052632 | N46: =IF(OR(Config!$H$7="",$K$5=0),"",L46/$K$5) -> 0.072087802
A47: =IF(Config!$J$8="","",Config!$J$8) -> MAPA | B47: =IF(Config!$J$8="","",COUNTIFS(Agenda!$G$5:$G$3004,Config!$J$8,Agenda!$H$5:$H$3004,"Realizado",Agenda!$N$5:$N$3004,Config!$B$7,Agenda!$O$5:$O$3004,Config!$B$5)) -> 5 | C47: =IF(Config!$J$8="","",SUMIFS(Agenda!$U$5:$U$3004,Agenda!$G$5:$G$3004,Config!$J$8,Agenda!$N$5:$N$3004,Config!$B$7,Agenda!$O$5:$O$3004,Config!$B$5)) -> 1.6666667 | D47: =IF(Config!$J$8="","",SUMIFS(Agenda!$M$5:$M$3004,Agenda!$G$5:$G$3004,Config!$J$8,Agenda!$H$5:$H$3004,"Realizado",Agenda!$N$5:$N$3004,Config!$B$7,Agenda!$O$5:$O$3004,Config!$B$5)) -> 1060 | E47: =IF(OR(Config!$J$8="",B47=0),"",D47/B47) -> 212 | G47: =IF(Config!$H$8="","",Config!$H$8) -> Vida Care | H47: =IF(Config!$H$8="","",COUNTIFS(Agenda!$F$5:$F$3004,Config!$H$8,Agenda!$H$5:$H$3004,"Realizado",Agenda!$N$5:$N$3004,Config!$B$7,Agenda!$O$5:$O$3004,Config!$B$5)) -> 7 | I47: =IF(Config!$H$8="","",SUMIFS(Agenda!$U$5:$U$3004,Agenda!$F$5:$F$3004,Config!$H$8,Agenda!$N$5:$N$3004,Config!$B$7,Agenda!$O$5:$O$3004,Config!$B$5)) -> 3.3333333 | J47: =IF(Config!$H$8="","",COUNTIFS(Agenda!$F$5:$F$3004,Config!$H$8,Agenda!$H$5:$H$3004,"Falta",Agenda!$N$5:$N$3004,Config!$B$7,Agenda!$O$5:$O$3004,Config!$B$5)) -> 1 | K47: =IF(Config!$H$8="","",IF(H47+J47=0,"",J47/(H47+J47))) -> 0.125 | L47: =IF(Config!$H$8="","",SUMIFS(Agenda!$M$5:$M$3004,Agenda!$F$5:$F$3004,Config!$H$8,Agenda!$H$5:$H$3004,"Realizado",Agenda!$N$5:$N$3004,Config!$B$7,Agenda!$O$5:$O$3004,Config!$B$5)) -> 545 | M47: =IF(OR(Config!$H$8="",H47=0),"",L47/H47) -> 77.857143 | N47: =IF(OR(Config!$H$8="",$K$5=0),"",L47/$K$5) -> 0.027188825
A48: =IF(Config!$J$9="","",Config!$J$9) -> Holter | B48: =IF(Config!$J$9="","",COUNTIFS(Agenda!$G$5:$G$3004,Config!$J$9,Agenda!$H$5:$H$3004,"Realizado",Agenda!$N$5:$N$3004,Config!$B$7,Agenda!$O$5:$O$3004,Config!$B$5)) -> 1 | C48: =IF(Config!$J$9="","",SUMIFS(Agenda!$U$5:$U$3004,Agenda!$G$5:$G$3004,Config!$J$9,Agenda!$N$5:$N$3004,Config!$B$7,Agenda!$O$5:$O$3004,Config!$B$5)) -> 0.33333333 | D48: =IF(Config!$J$9="","",SUMIFS(Agenda!$M$5:$M$3004,Agenda!$G$5:$G$3004,Config!$J$9,Agenda!$H$5:$H$3004,"Realizado",Agenda!$N$5:$N$3004,Config!$B$7,Agenda!$O$5:$O$3004,Config!$B$5)) -> 105 | E48: =IF(OR(Config!$J$9="",B48=0),"",D48/B48) -> 105 | G48: =IF(Config!$H$9="","",Config!$H$9) | H48: =IF(Config!$H$9="","",COUNTIFS(Agenda!$F$5:$F$3004,Config!$H$9,Agenda!$H$5:$H$3004,"Realizado",Agenda!$N$5:$N$3004,Config!$B$7,Agenda!$O$5:$O$3004,Config!$B$5)) | I48: =IF(Config!$H$9="","",SUMIFS(Agenda!$U$5:$U$3004,Agenda!$F$5:$F$3004,Config!$H$9,Agenda!$N$5:$N$3004,Config!$B$7,Agenda!$O$5:$O$3004,Config!$B$5)) | J48: =IF(Config!$H$9="","",COUNTIFS(Agenda!$F$5:$F$3004,Config!$H$9,Agenda!$H$5:$H$3004,"Falta",Agenda!$N$5:$N$3004,Config!$B$7,Agenda!$O$5:$O$3004,Config!$B$5)) | K48: =IF(Config!$H$9="","",IF(H48+J48=0,"",J48/(H48+J48))) | L48: =IF(Config!$H$9="","",SUMIFS(Agenda!$M$5:$M$3004,Agenda!$F$5:$F$3004,Config!$H$9,Agenda!$H$5:$H$3004,"Realizado",Agenda!$N$5:$N$3004,Config!$B$7,Agenda!$O$5:$O$3004,Config!$B$5)) | M48: =IF(OR(Config!$H$9="",H48=0),"",L48/H48) | N48: =IF(OR(Config!$H$9="",$K$5=0),"",L48/$K$5)
A49: =IF(Config!$J$10="","",Config!$J$10) -> Teste ergométrico | B49: =IF(Config!$J$10="","",COUNTIFS(Agenda!$G$5:$G$3004,Config!$J$10,Agenda!$H$5:$H$3004,"Realizado",Agenda!$N$5:$N$3004,Config!$B$7,Agenda!$O$5:$O$3004,Config!$B$5)) -> 6 | C49: =IF(Config!$J$10="","",SUMIFS(Agenda!$U$5:$U$3004,Agenda!$G$5:$G$3004,Config!$J$10,Agenda!$N$5:$N$3004,Config!$B$7,Agenda!$O$5:$O$3004,Config!$B$5)) -> 4 | D49: =IF(Config!$J$10="","",SUMIFS(Agenda!$M$5:$M$3004,Agenda!$G$5:$G$3004,Config!$J$10,Agenda!$H$5:$H$3004,"Realizado",Agenda!$N$5:$N$3004,Config!$B$7,Agenda!$O$5:$O$3004,Config!$B$5)) -> 1415 | E49: =IF(OR(Config!$J$10="",B49=0),"",D49/B49) -> 235.83333 | G49: =IF(Config!$H$10="","",Config!$H$10) | H49: =IF(Config!$H$10="","",COUNTIFS(Agenda!$F$5:$F$3004,Config!$H$10,Agenda!$H$5:$H$3004,"Realizado",Agenda!$N$5:$N$3004,Config!$B$7,Agenda!$O$5:$O$3004,Config!$B$5)) | I49: =IF(Config!$H$10="","",SUMIFS(Agenda!$U$5:$U$3004,Agenda!$F$5:$F$3004,Config!$H$10,Agenda!$N$5:$N$3004,Config!$B$7,Agenda!$O$5:$O$3004,Config!$B$5)) | J49: =IF(Config!$H$10="","",COUNTIFS(Agenda!$F$5:$F$3004,Config!$H$10,Agenda!$H$5:$H$3004,"Falta",Agenda!$N$5:$N$3004,Config!$B$7,Agenda!$O$5:$O$3004,Config!$B$5)) | K49: =IF(Config!$H$10="","",IF(H49+J49=0,"",J49/(H49+J49))) | L49: =IF(Config!$H$10="","",SUMIFS(Agenda!$M$5:$M$3004,Agenda!$F$5:$F$3004,Config!$H$10,Agenda!$H$5:$H$3004,"Realizado",Agenda!$N$5:$N$3004,Config!$B$7,Agenda!$O$5:$O$3004,Config!$B$5)) | M49: =IF(OR(Config!$H$10="",H49=0),"",L49/H49) | N49: =IF(OR(Config!$H$10="",$K$5=0),"",L49/$K$5)
A50: =IF(Config!$J$11="","",Config!$J$11) -> Avaliação endócrina | B50: =IF(Config!$J$11="","",COUNTIFS(Agenda!$G$5:$G$3004,Config!$J$11,Agenda!$H$5:$H$3004,"Realizado",Agenda!$N$5:$N$3004,Config!$B$7,Agenda!$O$5:$O$3004,Config!$B$5)) -> 18 | C50: =IF(Config!$J$11="","",SUMIFS(Agenda!$U$5:$U$3004,Agenda!$G$5:$G$3004,Config!$J$11,Agenda!$N$5:$N$3004,Config!$B$7,Agenda!$O$5:$O$3004,Config!$B$5)) -> 12 | D50: =IF(Config!$J$11="","",SUMIFS(Agenda!$M$5:$M$3004,Agenda!$G$5:$G$3004,Config!$J$11,Agenda!$H$5:$H$3004,"Realizado",Agenda!$N$5:$N$3004,Config!$B$7,Agenda!$O$5:$O$3004,Config!$B$5)) -> 5850 | E50: =IF(OR(Config!$J$11="",B50=0),"",D50/B50) -> 325
A51: =IF(Config!$J$12="","",Config!$J$12) | B51: =IF(Config!$J$12="","",COUNTIFS(Agenda!$G$5:$G$3004,Config!$J$12,Agenda!$H$5:$H$3004,"Realizado",Agenda!$N$5:$N$3004,Config!$B$7,Agenda!$O$5:$O$3004,Config!$B$5)) | C51: =IF(Config!$J$12="","",SUMIFS(Agenda!$U$5:$U$3004,Agenda!$G$5:$G$3004,Config!$J$12,Agenda!$N$5:$N$3004,Config!$B$7,Agenda!$O$5:$O$3004,Config!$B$5)) | D51: =IF(Config!$J$12="","",SUMIFS(Agenda!$M$5:$M$3004,Agenda!$G$5:$G$3004,Config!$J$12,Agenda!$H$5:$H$3004,"Realizado",Agenda!$N$5:$N$3004,Config!$B$7,Agenda!$O$5:$O$3004,Config!$B$5)) | E51: =IF(OR(Config!$J$12="",B51=0),"",D51/B51)
A52: =IF(Config!$J$13="","",Config!$J$13) | B52: =IF(Config!$J$13="","",COUNTIFS(Agenda!$G$5:$G$3004,Config!$J$13,Agenda!$H$5:$H$3004,"Realizado",Agenda!$N$5:$N$3004,Config!$B$7,Agenda!$O$5:$O$3004,Config!$B$5)) | C52: =IF(Config!$J$13="","",SUMIFS(Agenda!$U$5:$U$3004,Agenda!$G$5:$G$3004,Config!$J$13,Agenda!$N$5:$N$3004,Config!$B$7,Agenda!$O$5:$O$3004,Config!$B$5)) | D52: =IF(Config!$J$13="","",SUMIFS(Agenda!$M$5:$M$3004,Agenda!$G$5:$G$3004,Config!$J$13,Agenda!$H$5:$H$3004,"Realizado",Agenda!$N$5:$N$3004,Config!$B$7,Agenda!$O$5:$O$3004,Config!$B$5)) | E52: =IF(OR(Config!$J$13="",B52=0),"",D52/B52)
A53: =IF(Config!$J$14="","",Config!$J$14) | B53: =IF(Config!$J$14="","",COUNTIFS(Agenda!$G$5:$G$3004,Config!$J$14,Agenda!$H$5:$H$3004,"Realizado",Agenda!$N$5:$N$3004,Config!$B$7,Agenda!$O$5:$O$3004,Config!$B$5)) | C53: =IF(Config!$J$14="","",SUMIFS(Agenda!$U$5:$U$3004,Agenda!$G$5:$G$3004,Config!$J$14,Agenda!$N$5:$N$3004,Config!$B$7,Agenda!$O$5:$O$3004,Config!$B$5)) | D53: =IF(Config!$J$14="","",SUMIFS(Agenda!$M$5:$M$3004,Agenda!$G$5:$G$3004,Config!$J$14,Agenda!$H$5:$H$3004,"Realizado",Agenda!$N$5:$N$3004,Config!$B$7,Agenda!$O$5:$O$3004,Config!$B$5)) | E53: =IF(OR(Config!$J$14="",B53=0),"",D53/B53)
A54: =IF(Config!$J$15="","",Config!$J$15) | B54: =IF(Config!$J$15="","",COUNTIFS(Agenda!$G$5:$G$3004,Config!$J$15,Agenda!$H$5:$H$3004,"Realizado",Agenda!$N$5:$N$3004,Config!$B$7,Agenda!$O$5:$O$3004,Config!$B$5)) | C54: =IF(Config!$J$15="","",SUMIFS(Agenda!$U$5:$U$3004,Agenda!$G$5:$G$3004,Config!$J$15,Agenda!$N$5:$N$3004,Config!$B$7,Agenda!$O$5:$O$3004,Config!$B$5)) | D54: =IF(Config!$J$15="","",SUMIFS(Agenda!$M$5:$M$3004,Agenda!$G$5:$G$3004,Config!$J$15,Agenda!$H$5:$H$3004,"Realizado",Agenda!$N$5:$N$3004,Config!$B$7,Agenda!$O$5:$O$3004,Config!$B$5)) | E54: =IF(OR(Config!$J$15="",B54=0),"",D54/B54)
A55: =IF(Config!$J$16="","",Config!$J$16) | B55: =IF(Config!$J$16="","",COUNTIFS(Agenda!$G$5:$G$3004,Config!$J$16,Agenda!$H$5:$H$3004,"Realizado",Agenda!$N$5:$N$3004,Config!$B$7,Agenda!$O$5:$O$3004,Config!$B$5)) | C55: =IF(Config!$J$16="","",SUMIFS(Agenda!$U$5:$U$3004,Agenda!$G$5:$G$3004,Config!$J$16,Agenda!$N$5:$N$3004,Config!$B$7,Agenda!$O$5:$O$3004,Config!$B$5)) | D55: =IF(Config!$J$16="","",SUMIFS(Agenda!$M$5:$M$3004,Agenda!$G$5:$G$3004,Config!$J$16,Agenda!$H$5:$H$3004,"Realizado",Agenda!$N$5:$N$3004,Config!$B$7,Agenda!$O$5:$O$3004,Config!$B$5)) | E55: =IF(OR(Config!$J$16="",B55=0),"",D55/B55)
A56: Estes dois quadros são do MÊS INTEIRO: realizados, horas e produção contam os mesmos atendimentos. Os quadros de ocupação, no alto, param em ontem, porque a capacidade também para lá — dia que ainda não terminou não entra nos dois lados da conta. Retorno tem valor zero (incluído na consulta): ocupa agenda e não produz. A planilha 06 embute esse tempo no preço da consulta.
A59: Próximos 7 dias (a partir de hoje)
A60: Dia | B60: Data | C60: Agendados | D60: Confirmados | E60: Horas marcadas | F60: Horas de turno | G60: Vagas (horas)
A61: =CHOOSE(WEEKDAY(B61,2),"Segunda","Terça","Quarta","Quinta","Sexta","Sábado","Domingo") -> Segunda | B61: =Config!$B$8+0 -> 46279 | C61: =COUNTIFS(Agenda!$A$5:$A$3004,B61,Agenda!$H$5:$H$3004,"Agendado") -> 4 | D61: =COUNTIFS(Agenda!$A$5:$A$3004,B61,Agenda!$H$5:$H$3004,"Confirmado") -> 11 | E61: =(SUMIFS(Agenda!$L$5:$L$3004,Agenda!$A$5:$A$3004,B61,Agenda!$H$5:$H$3004,"Agendado")+SUMIFS(Agenda!$L$5:$L$3004,Agenda!$A$5:$A$3004,B61,Agenda!$H$5:$H$3004,"Confirmado"))/60 -> 6.6666667 | F61: =IF(COUNTIF(Config!$I$19:$I$38,B61)>0,0,SUMPRODUCT((Config!$B$20:$B$43=A61)*(Config!$A$20:$A$43<>"")*IF(Config!$G$20:$G$43="",0,1)*IF(Config!$F$20:$F$43="",Config!$B$10,Config!$F$20:$F$43))) -> 8 | G61: =MAX(0,F61-E61) -> 1.3333333
A62: =CHOOSE(WEEKDAY(B62,2),"Segunda","Terça","Quarta","Quinta","Sexta","Sábado","Domingo") -> Terça | B62: =Config!$B$8+1 -> 46280 | C62: =COUNTIFS(Agenda!$A$5:$A$3004,B62,Agenda!$H$5:$H$3004,"Agendado") -> 5 | D62: =COUNTIFS(Agenda!$A$5:$A$3004,B62,Agenda!$H$5:$H$3004,"Confirmado") -> 17 | E62: =(SUMIFS(Agenda!$L$5:$L$3004,Agenda!$A$5:$A$3004,B62,Agenda!$H$5:$H$3004,"Agendado")+SUMIFS(Agenda!$L$5:$L$3004,Agenda!$A$5:$A$3004,B62,Agenda!$H$5:$H$3004,"Confirmado"))/60 -> 10.666667 | F62: =IF(COUNTIF(Config!$I$19:$I$38,B62)>0,0,SUMPRODUCT((Config!$B$20:$B$43=A62)*(Config!$A$20:$A$43<>"")*IF(Config!$G$20:$G$43="",0,1)*IF(Config!$F$20:$F$43="",Config!$B$10,Config!$F$20:$F$43))) -> 12 | G62: =MAX(0,F62-E62) -> 1.3333333
A63: =CHOOSE(WEEKDAY(B63,2),"Segunda","Terça","Quarta","Quinta","Sexta","Sábado","Domingo") -> Quarta | B63: =Config!$B$8+2 -> 46281 | C63: =COUNTIFS(Agenda!$A$5:$A$3004,B63,Agenda!$H$5:$H$3004,"Agendado") -> 2 | D63: =COUNTIFS(Agenda!$A$5:$A$3004,B63,Agenda!$H$5:$H$3004,"Confirmado") -> 5 | E63: =(SUMIFS(Agenda!$L$5:$L$3004,Agenda!$A$5:$A$3004,B63,Agenda!$H$5:$H$3004,"Agendado")+SUMIFS(Agenda!$L$5:$L$3004,Agenda!$A$5:$A$3004,B63,Agenda!$H$5:$H$3004,"Confirmado"))/60 -> 3 | F63: =IF(COUNTIF(Config!$I$19:$I$38,B63)>0,0,SUMPRODUCT((Config!$B$20:$B$43=A63)*(Config!$A$20:$A$43<>"")*IF(Config!$G$20:$G$43="",0,1)*IF(Config!$F$20:$F$43="",Config!$B$10,Config!$F$20:$F$43))) -> 4 | G63: =MAX(0,F63-E63) -> 1
A64: =CHOOSE(WEEKDAY(B64,2),"Segunda","Terça","Quarta","Quinta","Sexta","Sábado","Domingo") -> Quinta | B64: =Config!$B$8+3 -> 46282 | C64: =COUNTIFS(Agenda!$A$5:$A$3004,B64,Agenda!$H$5:$H$3004,"Agendado") -> 19 | D64: =COUNTIFS(Agenda!$A$5:$A$3004,B64,Agenda!$H$5:$H$3004,"Confirmado") -> 0 | E64: =(SUMIFS(Agenda!$L$5:$L$3004,Agenda!$A$5:$A$3004,B64,Agenda!$H$5:$H$3004,"Agendado")+SUMIFS(Agenda!$L$5:$L$3004,Agenda!$A$5:$A$3004,B64,Agenda!$H$5:$H$3004,"Confirmado"))/60 -> 9.1666667 | F64: =IF(COUNTIF(Config!$I$19:$I$38,B64)>0,0,SUMPRODUCT((Config!$B$20:$B$43=A64)*(Config!$A$20:$A$43<>"")*IF(Config!$G$20:$G$43="",0,1)*IF(Config!$F$20:$F$43="",Config!$B$10,Config!$F$20:$F$43))) -> 12 | G64: =MAX(0,F64-E64) -> 2.8333333
A65: =CHOOSE(WEEKDAY(B65,2),"Segunda","Terça","Quarta","Quinta","Sexta","Sábado","Domingo") -> Sexta | B65: =Config!$B$8+4 -> 46283 | C65: =COUNTIFS(Agenda!$A$5:$A$3004,B65,Agenda!$H$5:$H$3004,"Agendado") -> 9 | D65: =COUNTIFS(Agenda!$A$5:$A$3004,B65,Agenda!$H$5:$H$3004,"Confirmado") -> 0 | E65: =(SUMIFS(Agenda!$L$5:$L$3004,Agenda!$A$5:$A$3004,B65,Agenda!$H$5:$H$3004,"Agendado")+SUMIFS(Agenda!$L$5:$L$3004,Agenda!$A$5:$A$3004,B65,Agenda!$H$5:$H$3004,"Confirmado"))/60 -> 3.5 | F65: =IF(COUNTIF(Config!$I$19:$I$38,B65)>0,0,SUMPRODUCT((Config!$B$20:$B$43=A65)*(Config!$A$20:$A$43<>"")*IF(Config!$G$20:$G$43="",0,1)*IF(Config!$F$20:$F$43="",Config!$B$10,Config!$F$20:$F$43))) -> 4 | G65: =MAX(0,F65-E65) -> 0.5
A66: =CHOOSE(WEEKDAY(B66,2),"Segunda","Terça","Quarta","Quinta","Sexta","Sábado","Domingo") -> Sábado | B66: =Config!$B$8+5 -> 46284 | C66: =COUNTIFS(Agenda!$A$5:$A$3004,B66,Agenda!$H$5:$H$3004,"Agendado") -> 0 | D66: =COUNTIFS(Agenda!$A$5:$A$3004,B66,Agenda!$H$5:$H$3004,"Confirmado") -> 0 | E66: =(SUMIFS(Agenda!$L$5:$L$3004,Agenda!$A$5:$A$3004,B66,Agenda!$H$5:$H$3004,"Agendado")+SUMIFS(Agenda!$L$5:$L$3004,Agenda!$A$5:$A$3004,B66,Agenda!$H$5:$H$3004,"Confirmado"))/60 -> 0 | F66: =IF(COUNTIF(Config!$I$19:$I$38,B66)>0,0,SUMPRODUCT((Config!$B$20:$B$43=A66)*(Config!$A$20:$A$43<>"")*IF(Config!$G$20:$G$43="",0,1)*IF(Config!$F$20:$F$43="",Config!$B$10,Config!$F$20:$F$43))) -> 0 | G66: =MAX(0,F66-E66) -> 0
A67: =CHOOSE(WEEKDAY(B67,2),"Segunda","Terça","Quarta","Quinta","Sexta","Sábado","Domingo") -> Domingo | B67: =Config!$B$8+6 -> 46285 | C67: =COUNTIFS(Agenda!$A$5:$A$3004,B67,Agenda!$H$5:$H$3004,"Agendado") -> 0 | D67: =COUNTIFS(Agenda!$A$5:$A$3004,B67,Agenda!$H$5:$H$3004,"Confirmado") -> 0 | E67: =(SUMIFS(Agenda!$L$5:$L$3004,Agenda!$A$5:$A$3004,B67,Agenda!$H$5:$H$3004,"Agendado")+SUMIFS(Agenda!$L$5:$L$3004,Agenda!$A$5:$A$3004,B67,Agenda!$H$5:$H$3004,"Confirmado"))/60 -> 0 | F67: =IF(COUNTIF(Config!$I$19:$I$38,B67)>0,0,SUMPRODUCT((Config!$B$20:$B$43=A67)*(Config!$A$20:$A$43<>"")*IF(Config!$G$20:$G$43="",0,1)*IF(Config!$F$20:$F$43="",Config!$B$10,Config!$F$20:$F$43))) -> 0 | G67: =MAX(0,F67-E67) -> 0
A68: Vagas em amarelo: mais de 40 % do turno livre. É a lista para a recepção oferecer horários à lista de retorno (planilha 02) e aos orçamentos aprovados (15). A planilha avisa; a agenda é da clínica.

Sheet Config
A1: Configurações
A2: Células amarelas: você preenche. Profissionais, salas, pagadores, procedimentos, tabela de preços e turnos alimentam a Agenda e o Painel.
M3: Tabela de preços por pagador (R$)
A4: Clínica | B4: Clínica Vida Plena (exemplo fictício) | D4: Profissionais (até 8) | E4: Especialidade | F4: Salas (até 6) | H4: Pagadores (até 6) | J4: Procedimentos (até 12) | K4: Minutos | L4: Retorno em (dias) | M4: =IF($H$5="","",$H$5) -> Particular | N4: =IF($H$6="","",$H$6) -> Saúde Total | O4: =IF($H$7="","",$H$7) -> MediPlan | P4: =IF($H$8="","",$H$8) -> Vida Care | Q4: =IF($H$9="","",$H$9) | R4: =IF($H$10="","",$H$10) | T4: Meses
A5: Ano do painel | B5: 2026 | D5: Dra. Carolina Mendes | E5: Clínica médica | F5: Sala 1 | H5: Particular | J5: Consulta | K5: 30 | L5: 30 | M5: 380 | N5: 120 | O5: 100 | P5: 90 | T5: Janeiro
A6: Mês do painel | B6: Setembro | D6: Dr. Paulo Andrade | E6: Cardiologia | F6: Sala 2 | H6: Saúde Total | J6: Retorno | K6: 20 | L6: 0 | M6: 0 | N6: 0 | O6: 0 | P6: 0 | T6: Fevereiro
A7: Número do mês | B7: =MATCH(B6,$T$5:$T$16,0) -> 9 | D7: Dra. Renata Sousa | E7: Endocrinologia | H7: MediPlan | J7: ECG | K7: 20 | L7: 0 | M7: 130 | N7: 40 | O7: 35 | P7: 32 | T7: Março
A8: Data de referência (hoje) | B8: 46279 | C8: O exemplo está congelado em 14/09/2026, para os arquivos do kit mostrarem a mesma foto. Ao usar com os seus dados, troque por =HOJE(). | H8: Vida Care | J8: MAPA | K8: 20 | L8: 0 | M8: 300 | N8: 95 | O8: 85 | P8: 75 | T8: Abril
A9: Painel conta horas disponíveis até | B9: =MIN(DATE(B5,B7+1,0),B8-1) -> 46278 | C9: Ontem, ou o fim do mês do painel se ele já passou: as horas disponíveis só contam dias que já aconteceram. | J9: Holter | K9: 20 | L9: 0 | M9: 350 | N9: 105 | O9: 95 | P9: 85 | T9: Maio
A10: Horas por turno (padrão) | B10: 4 | J10: Teste ergométrico | K10: 40 | L10: 0 | M10: 450 | N10: 140 | O10: 125 | P10: 110 | T10: Junho
J11: Avaliação endócrina | K11: 40 | L11: 45 | M11: 400 | N11: 130 | T11: Julho
T12: Agosto
T13: Setembro
D14: Preencha as listas de cima para baixo, sem pular linha: as listas suspensas da Agenda param na última linha preenchida. Retorno em (dias) = prazo em que se espera o paciente de volta (0 = não se aplica); a planilha 02 usa isso na lista de retorno. | T14: Outubro
D15: Tabela de preços: valor de cada procedimento para cada pagador. Célula vazia = não credenciado. A Agenda SUGERE o valor daqui nas duas últimas colunas, mas grava na linha o valor que você lançar: reajustar esta tabela não mexe no que já aconteceu. COPIE DA PLANILHA 08 (Tabela de preços): ela é a fonte única da tabela no kit; 06 e 07 também copiam de lá. Mudou um preço? Atualize a 08 primeiro e depois 06, 07 e esta Config. | T15: Novembro
T16: Dezembro
A18: Turnos da semana (até 24): quem atende, em que dia, período e sala | I18: Feriados e dias sem atendimento (até 20)
A19: Profissional | B19: Dia da semana | C19: Período | D19: Sala | E19: Início | F19: Horas | G19: Horas disponíveis no mês (até o limite) | I19: 46023
A20: Dra. Carolina Mendes | B20: Segunda | C20: Manhã | D20: Sala 1 | E20: 0.33333333 | F20: 4 | G20: =IF(A20="","",IF(F20="",$B$10,F20)*IFERROR(INDEX($J$45:$J$50,MATCH(B20,$I$45:$I$50,0)),0)) -> 0 | I20: 46069
A21: Dra. Carolina Mendes | B21: Terça | C21: Manhã | D21: Sala 1 | E21: 0.33333333 | F21: 4 | G21: =IF(A21="","",IF(F21="",$B$10,F21)*IFERROR(INDEX($J$45:$J$50,MATCH(B21,$I$45:$I$50,0)),0)) -> 8 | I21: 46070
A22: Dra. Carolina Mendes | B22: Quarta | C22: Tarde | D22: Sala 1 | E22: 0.58333333 | F22: 4 | G22: =IF(A22="","",IF(F22="",$B$10,F22)*IFERROR(INDEX($J$45:$J$50,MATCH(B22,$I$45:$I$50,0)),0)) -> 8 | I22: 46115
A23: Dra. Carolina Mendes | B23: Quinta | C23: Manhã | D23: Sala 1 | E23: 0.33333333 | F23: 4 | G23: =IF(A23="","",IF(F23="",$B$10,F23)*IFERROR(INDEX($J$45:$J$50,MATCH(B23,$I$45:$I$50,0)),0)) -> 8 | I23: 46133
A24: Dr. Paulo Andrade | B24: Segunda | C24: Tarde | D24: Sala 2 | E24: 0.58333333 | F24: 4 | G24: =IF(A24="","",IF(F24="",$B$10,F24)*IFERROR(INDEX($J$45:$J$50,MATCH(B24,$I$45:$I$50,0)),0)) -> 0 | I24: 46143
A25: Dr. Paulo Andrade | B25: Terça | C25: Tarde | D25: Sala 2 | E25: 0.58333333 | F25: 4 | G25: =IF(A25="","",IF(F25="",$B$10,F25)*IFERROR(INDEX($J$45:$J$50,MATCH(B25,$I$45:$I$50,0)),0)) -> 8 | I25: 46177
A26: Dr. Paulo Andrade | B26: Quinta | C26: Tarde | D26: Sala 2 | E26: 0.58333333 | F26: 4 | G26: =IF(A26="","",IF(F26="",$B$10,F26)*IFERROR(INDEX($J$45:$J$50,MATCH(B26,$I$45:$I$50,0)),0)) -> 8 | I26: 46272
A27: Dr. Paulo Andrade | B27: Sexta | C27: Manhã | D27: Sala 2 | E27: 0.33333333 | F27: 4 | G27: =IF(A27="","",IF(F27="",$B$10,F27)*IFERROR(INDEX($J$45:$J$50,MATCH(B27,$I$45:$I$50,0)),0)) -> 8 | I27: 46307
A28: Dra. Renata Sousa | B28: Terça | C28: Tarde | D28: Sala 1 | E28: 0.58333333 | F28: 4 | G28: =IF(A28="","",IF(F28="",$B$10,F28)*IFERROR(INDEX($J$45:$J$50,MATCH(B28,$I$45:$I$50,0)),0)) -> 8 | I28: 46328
A29: Dra. Renata Sousa | B29: Quinta | C29: Tarde | D29: Sala 1 | E29: 0.58333333 | F29: 4 | G29: =IF(A29="","",IF(F29="",$B$10,F29)*IFERROR(INDEX($J$45:$J$50,MATCH(B29,$I$45:$I$50,0)),0)) -> 8 | I29: 46341
G30: =IF(A30="","",IF(F30="",$B$10,F30)*IFERROR(INDEX($J$45:$J$50,MATCH(B30,$I$45:$I$50,0)),0)) | I30: 46346
G31: =IF(A31="","",IF(F31="",$B$10,F31)*IFERROR(INDEX($J$45:$J$50,MATCH(B31,$I$45:$I$50,0)),0)) | I31: 46381
G32: =IF(A32="","",IF(F32="",$B$10,F32)*IFERROR(INDEX($J$45:$J$50,MATCH(B32,$I$45:$I$50,0)),0))
G33: =IF(A33="","",IF(F33="",$B$10,F33)*IFERROR(INDEX($J$45:$J$50,MATCH(B33,$I$45:$I$50,0)),0))
G34: =IF(A34="","",IF(F34="",$B$10,F34)*IFERROR(INDEX($J$45:$J$50,MATCH(B34,$I$45:$I$50,0)),0))
G35: =IF(A35="","",IF(F35="",$B$10,F35)*IFERROR(INDEX($J$45:$J$50,MATCH(B35,$I$45:$I$50,0)),0))
G36: =IF(A36="","",IF(F36="",$B$10,F36)*IFERROR(INDEX($J$45:$J$50,MATCH(B36,$I$45:$I$50,0)),0))
G37: =IF(A37="","",IF(F37="",$B$10,F37)*IFERROR(INDEX($J$45:$J$50,MATCH(B37,$I$45:$I$50,0)),0))
G38: =IF(A38="","",IF(F38="",$B$10,F38)*IFERROR(INDEX($J$45:$J$50,MATCH(B38,$I$45:$I$50,0)),0))
G39: =IF(A39="","",IF(F39="",$B$10,F39)*IFERROR(INDEX($J$45:$J$50,MATCH(B39,$I$45:$I$50,0)),0))
G40: =IF(A40="","",IF(F40="",$B$10,F40)*IFERROR(INDEX($J$45:$J$50,MATCH(B40,$I$45:$I$50,0)),0))
G41: =IF(A41="","",IF(F41="",$B$10,F41)*IFERROR(INDEX($J$45:$J$50,MATCH(B41,$I$45:$I$50,0)),0))
G42: =IF(A42="","",IF(F42="",$B$10,F42)*IFERROR(INDEX($J$45:$J$50,MATCH(B42,$I$45:$I$50,0)),0))
G43: =IF(A43="","",IF(F43="",$B$10,F43)*IFERROR(INDEX($J$45:$J$50,MATCH(B43,$I$45:$I$50,0)),0)) | I43: Dias úteis do mês do painel (até o limite), por dia da semana
I44: Dia | J44: Dias no mês
I45: Segunda | J45: =COUNTIF($C$50:$C$80,I45) -> 0
I46: Terça | J46: =COUNTIF($C$50:$C$80,I46) -> 2
I47: Quarta | J47: =COUNTIF($C$50:$C$80,I47) -> 2
A48: Auxiliar: dias do mês do painel (calculado; sábado só conta se houver turno de sábado) | I48: Quinta | J48: =COUNTIF($C$50:$C$80,I48) -> 2
A49: Dia | B49: Data | C49: Conta? (dia da semana) | I49: Sexta | J49: =COUNTIF($C$50:$C$80,I49) -> 2
A50: 1 | B50: =IF(1>DAY(DATE($B$5,$B$7+1,0)),"",DATE($B$5,$B$7,1)) -> 46266 | C50: =IF(B50="","",IF(OR(B50>$B$9,WEEKDAY(B50,2)=7,COUNTIF($I$19:$I$38,B50)>0),"",CHOOSE(WEEKDAY(B50,2),"Segunda","Terça","Quarta","Quinta","Sexta","Sábado","Domingo"))) -> Terça | I50: Sábado | J50: =COUNTIF($C$50:$C$80,I50) -> 2
A51: 2 | B51: =IF(2>DAY(DATE($B$5,$B$7+1,0)),"",DATE($B$5,$B$7,2)) -> 46267 | C51: =IF(B51="","",IF(OR(B51>$B$9,WEEKDAY(B51,2)=7,COUNTIF($I$19:$I$38,B51)>0),"",CHOOSE(WEEKDAY(B51,2),"Segunda","Terça","Quarta","Quinta","Sexta","Sábado","Domingo"))) -> Quarta
A52: 3 | B52: =IF(3>DAY(DATE($B$5,$B$7+1,0)),"",DATE($B$5,$B$7,3)) -> 46268 | C52: =IF(B52="","",IF(OR(B52>$B$9,WEEKDAY(B52,2)=7,COUNTIF($I$19:$I$38,B52)>0),"",CHOOSE(WEEKDAY(B52,2),"Segunda","Terça","Quarta","Quinta","Sexta","Sábado","Domingo"))) -> Quinta
A53: 4 | B53: =IF(4>DAY(DATE($B$5,$B$7+1,0)),"",DATE($B$5,$B$7,4)) -> 46269 | C53: =IF(B53="","",IF(OR(B53>$B$9,WEEKDAY(B53,2)=7,COUNTIF($I$19:$I$38,B53)>0),"",CHOOSE(WEEKDAY(B53,2),"Segunda","Terça","Quarta","Quinta","Sexta","Sábado","Domingo"))) -> Sexta
A54: 5 | B54: =IF(5>DAY(DATE($B$5,$B$7+1,0)),"",DATE($B$5,$B$7,5)) -> 46270 | C54: =IF(B54="","",IF(OR(B54>$B$9,WEEKDAY(B54,2)=7,COUNTIF($I$19:$I$38,B54)>0),"",CHOOSE(WEEKDAY(B54,2),"Segunda","Terça","Quarta","Quinta","Sexta","Sábado","Domingo"))) -> Sábado
A55: 6 | B55: =IF(6>DAY(DATE($B$5,$B$7+1,0)),"",DATE($B$5,$B$7,6)) -> 46271 | C55: =IF(B55="","",IF(OR(B55>$B$9,WEEKDAY(B55,2)=7,COUNTIF($I$19:$I$38,B55)>0),"",CHOOSE(WEEKDAY(B55,2),"Segunda","Terça","Quarta","Quinta","Sexta","Sábado","Domingo")))
A56: 7 | B56: =IF(7>DAY(DATE($B$5,$B$7+1,0)),"",DATE($B$5,$B$7,7)) -> 46272 | C56: =IF(B56="","",IF(OR(B56>$B$9,WEEKDAY(B56,2)=7,COUNTIF($I$19:$I$38,B56)>0),"",CHOOSE(WEEKDAY(B56,2),"Segunda","Terça","Quarta","Quinta","Sexta","Sábado","Domingo")))
A57: 8 | B57: =IF(8>DAY(DATE($B$5,$B$7+1,0)),"",DATE($B$5,$B$7,8)) -> 46273 | C57: =IF(B57="","",IF(OR(B57>$B$9,WEEKDAY(B57,2)=7,COUNTIF($I$19:$I$38,B57)>0),"",CHOOSE(WEEKDAY(B57,2),"Segunda","Terça","Quarta","Quinta","Sexta","Sábado","Domingo"))) -> Terça
A58: 9 | B58: =IF(9>DAY(DATE($B$5,$B$7+1,0)),"",DATE($B$5,$B$7,9)) -> 46274 | C58: =IF(B58="","",IF(OR(B58>$B$9,WEEKDAY(B58,2)=7,COUNTIF($I$19:$I$38,B58)>0),"",CHOOSE(WEEKDAY(B58,2),"Segunda","Terça","Quarta","Quinta","Sexta","Sábado","Domingo"))) -> Quarta
A59: 10 | B59: =IF(10>DAY(DATE($B$5,$B$7+1,0)),"",DATE($B$5,$B$7,10)) -> 46275 | C59: =IF(B59="","",IF(OR(B59>$B$9,WEEKDAY(B59,2)=7,COUNTIF($I$19:$I$38,B59)>0),"",CHOOSE(WEEKDAY(B59,2),"Segunda","Terça","Quarta","Quinta","Sexta","Sábado","Domingo"))) -> Quinta
A60: 11 | B60: =IF(11>DAY(DATE($B$5,$B$7+1,0)),"",DATE($B$5,$B$7,11)) -> 46276 | C60: =IF(B60="","",IF(OR(B60>$B$9,WEEKDAY(B60,2)=7,COUNTIF($I$19:$I$38,B60)>0),"",CHOOSE(WEEKDAY(B60,2),"Segunda","Terça","Quarta","Quinta","Sexta","Sábado","Domingo"))) -> Sexta
A61: 12 | B61: =IF(12>DAY(DATE($B$5,$B$7+1,0)),"",DATE($B$5,$B$7,12)) -> 46277 | C61: =IF(B61="","",IF(OR(B61>$B$9,WEEKDAY(B61,2)=7,COUNTIF($I$19:$I$38,B61)>0),"",CHOOSE(WEEKDAY(B61,2),"Segunda","Terça","Quarta","Quinta","Sexta","Sábado","Domingo"))) -> Sábado
A62: 13 | B62: =IF(13>DAY(DATE($B$5,$B$7+1,0)),"",DATE($B$5,$B$7,13)) -> 46278 | C62: =IF(B62="","",IF(OR(B62>$B$9,WEEKDAY(B62,2)=7,COUNTIF($I$19:$I$38,B62)>0),"",CHOOSE(WEEKDAY(B62,2),"Segunda","Terça","Quarta","Quinta","Sexta","Sábado","Domingo")))
A63: 14 | B63: =IF(14>DAY(DATE($B$5,$B$7+1,0)),"",DATE($B$5,$B$7,14)) -> 46279 | C63: =IF(B63="","",IF(OR(B63>$B$9,WEEKDAY(B63,2)=7,COUNTIF($I$19:$I$38,B63)>0),"",CHOOSE(WEEKDAY(B63,2),"Segunda","Terça","Quarta","Quinta","Sexta","Sábado","Domingo")))
A64: 15 | B64: =IF(15>DAY(DATE($B$5,$B$7+1,0)),"",DATE($B$5,$B$7,15)) -> 46280 | C64: =IF(B64="","",IF(OR(B64>$B$9,WEEKDAY(B64,2)=7,COUNTIF($I$19:$I$38,B64)>0),"",CHOOSE(WEEKDAY(B64,2),"Segunda","Terça","Quarta","Quinta","Sexta","Sábado","Domingo")))
A65: 16 | B65: =IF(16>DAY(DATE($B$5,$B$7+1,0)),"",DATE($B$5,$B$7,16)) -> 46281 | C65: =IF(B65="","",IF(OR(B65>$B$9,WEEKDAY(B65,2)=7,COUNTIF($I$19:$I$38,B65)>0),"",CHOOSE(WEEKDAY(B65,2),"Segunda","Terça","Quarta","Quinta","Sexta","Sábado","Domingo")))
A66: 17 | B66: =IF(17>DAY(DATE($B$5,$B$7+1,0)),"",DATE($B$5,$B$7,17)) -> 46282 | C66: =IF(B66="","",IF(OR(B66>$B$9,WEEKDAY(B66,2)=7,COUNTIF($I$19:$I$38,B66)>0),"",CHOOSE(WEEKDAY(B66,2),"Segunda","Terça","Quarta","Quinta","Sexta","Sábado","Domingo")))
A67: 18 | B67: =IF(18>DAY(DATE($B$5,$B$7+1,0)),"",DATE($B$5,$B$7,18)) -> 46283 | C67: =IF(B67="","",IF(OR(B67>$B$9,WEEKDAY(B67,2)=7,COUNTIF($I$19:$I$38,B67)>0),"",CHOOSE(WEEKDAY(B67,2),"Segunda","Terça","Quarta","Quinta","Sexta","Sábado","Domingo")))
A68: 19 | B68: =IF(19>DAY(DATE($B$5,$B$7+1,0)),"",DATE($B$5,$B$7,19)) -> 46284 | C68: =IF(B68="","",IF(OR(B68>$B$9,WEEKDAY(B68,2)=7,COUNTIF($I$19:$I$38,B68)>0),"",CHOOSE(WEEKDAY(B68,2),"Segunda","Terça","Quarta","Quinta","Sexta","Sábado","Domingo")))
A69: 20 | B69: =IF(20>DAY(DATE($B$5,$B$7+1,0)),"",DATE($B$5,$B$7,20)) -> 46285 | C69: =IF(B69="","",IF(OR(B69>$B$9,WEEKDAY(B69,2)=7,COUNTIF($I$19:$I$38,B69)>0),"",CHOOSE(WEEKDAY(B69,2),"Segunda","Terça","Quarta","Quinta","Sexta","Sábado","Domingo")))
A70: 21 | B70: =IF(21>DAY(DATE($B$5,$B$7+1,0)),"",DATE($B$5,$B$7,21)) -> 46286 | C70: =IF(B70="","",IF(OR(B70>$B$9,WEEKDAY(B70,2)=7,COUNTIF($I$19:$I$38,B70)>0),"",CHOOSE(WEEKDAY(B70,2),"Segunda","Terça","Quarta","Quinta","Sexta","Sábado","Domingo")))
A71: 22 | B71: =IF(22>DAY(DATE($B$5,$B$7+1,0)),"",DATE($B$5,$B$7,22)) -> 46287 | C71: =IF(B71="","",IF(OR(B71>$B$9,WEEKDAY(B71,2)=7,COUNTIF($I$19:$I$38,B71)>0),"",CHOOSE(WEEKDAY(B71,2),"Segunda","Terça","Quarta","Quinta","Sexta","Sábado","Domingo")))
A72: 23 | B72: =IF(23>DAY(DATE($B$5,$B$7+1,0)),"",DATE($B$5,$B$7,23)) -> 46288 | C72: =IF(B72="","",IF(OR(B72>$B$9,WEEKDAY(B72,2)=7,COUNTIF($I$19:$I$38,B72)>0),"",CHOOSE(WEEKDAY(B72,2),"Segunda","Terça","Quarta","Quinta","Sexta","Sábado","Domingo")))
A73: 24 | B73: =IF(24>DAY(DATE($B$5,$B$7+1,0)),"",DATE($B$5,$B$7,24)) -> 46289 | C73: =IF(B73="","",IF(OR(B73>$B$9,WEEKDAY(B73,2)=7,COUNTIF($I$19:$I$38,B73)>0),"",CHOOSE(WEEKDAY(B73,2),"Segunda","Terça","Quarta","Quinta","Sexta","Sábado","Domingo")))
A74: 25 | B74: =IF(25>DAY(DATE($B$5,$B$7+1,0)),"",DATE($B$5,$B$7,25)) -> 46290 | C74: =IF(B74="","",IF(OR(B74>$B$9,WEEKDAY(B74,2)=7,COUNTIF($I$19:$I$38,B74)>0),"",CHOOSE(WEEKDAY(B74,2),"Segunda","Terça","Quarta","Quinta","Sexta","Sábado","Domingo")))
A75: 26 | B75: =IF(26>DAY(DATE($B$5,$B$7+1,0)),"",DATE($B$5,$B$7,26)) -> 46291 | C75: =IF(B75="","",IF(OR(B75>$B$9,WEEKDAY(B75,2)=7,COUNTIF($I$19:$I$38,B75)>0),"",CHOOSE(WEEKDAY(B75,2),"Segunda","Terça","Quarta","Quinta","Sexta","Sábado","Domingo")))
A76: 27 | B76: =IF(27>DAY(DATE($B$5,$B$7+1,0)),"",DATE($B$5,$B$7,27)) -> 46292 | C76: =IF(B76="","",IF(OR(B76>$B$9,WEEKDAY(B76,2)=7,COUNTIF($I$19:$I$38,B76)>0),"",CHOOSE(WEEKDAY(B76,2),"Segunda","Terça","Quarta","Quinta","Sexta","Sábado","Domingo")))
A77: 28 | B77: =IF(28>DAY(DATE($B$5,$B$7+1,0)),"",DATE($B$5,$B$7,28)) -> 46293 | C77: =IF(B77="","",IF(OR(B77>$B$9,WEEKDAY(B77,2)=7,COUNTIF($I$19:$I$38,B77)>0),"",CHOOSE(WEEKDAY(B77,2),"Segunda","Terça","Quarta","Quinta","Sexta","Sábado","Domingo")))
A78: 29 | B78: =IF(29>DAY(DATE($B$5,$B$7+1,0)),"",DATE($B$5,$B$7,29)) -> 46294 | C78: =IF(B78="","",IF(OR(B78>$B$9,WEEKDAY(B78,2)=7,COUNTIF($I$19:$I$38,B78)>0),"",CHOOSE(WEEKDAY(B78,2),"Segunda","Terça","Quarta","Quinta","Sexta","Sábado","Domingo")))
A79: 30 | B79: =IF(30>DAY(DATE($B$5,$B$7+1,0)),"",DATE($B$5,$B$7,30)) -> 46295 | C79: =IF(B79="","",IF(OR(B79>$B$9,WEEKDAY(B79,2)=7,COUNTIF($I$19:$I$38,B79)>0),"",CHOOSE(WEEKDAY(B79,2),"Segunda","Terça","Quarta","Quinta","Sexta","Sábado","Domingo")))
A80: 31 | B80: =IF(31>DAY(DATE($B$5,$B$7+1,0)),"",DATE($B$5,$B$7,31)) | C80: =IF(B80="","",IF(OR(B80>$B$9,WEEKDAY(B80,2)=7,COUNTIF($I$19:$I$38,B80)>0),"",CHOOSE(WEEKDAY(B80,2),"Segunda","Terça","Quarta","Quinta","Sexta","Sábado","Domingo")))

Sheet Pacientes
A1: Pacientes
A2: Uma linha por paciente: nome, pagador (particular ou convênio), profissional principal e contato. Só dados de gestão; nada clínico. As colunas brancas vêm da Agenda.
A4: Paciente | B4: Pagador | C4: Profissional principal | D4: Contato | E4: Observação | F4: Atendimentos realizados | G4: Faltas | H4: Último atendimento | I4: Próximo agendado
A5: Ana Costa | B5: Particular | C5: Dra. Carolina Mendes | D5: (11) 90000-0147 | F5: =IF(A5="","",COUNTIFS(Agenda!$E$5:$E$3004,A5,Agenda!$H$5:$H$3004,"Realizado")) -> 12 | G5: =IF(A5="","",COUNTIFS(Agenda!$E$5:$E$3004,A5,Agenda!$H$5:$H$3004,"Falta")) -> 0 | H5: =IF(A5="","",IF(SUMPRODUCT(MAX((Agenda!$E$5:$E$3004=A5)*(Agenda!$H$5:$H$3004="Realizado")*Agenda!$A$5:$A$3004))=0,"",SUMPRODUCT(MAX((Agenda!$E$5:$E$3004=A5)*(Agenda!$H$5:$H$3004="Realizado")*Agenda!$A$5:$A$3004)))) -> 46274 | I5: =IF(A5="","",IF(SUMPRODUCT(MIN(((Agenda!$E$5:$E$3004=A5)*((Agenda!$H$5:$H$3004="Agendado")+(Agenda!$H$5:$H$3004="Confirmado")))*Agenda!$A$5:$A$3004+(1-((Agenda!$E$5:$E$3004=A5)*((Agenda!$H$5:$H$3004="Agendado")+(Agenda!$H$5:$H$3004="Confirmado"))))*1E+10))>=1E+10,"",SUMPRODUCT(MIN(((Agenda!$E$5:$E$3004=A5)*((Agenda!$H$5:$H$3004="Agendado")+(Agenda!$H$5:$H$3004="Confirmado")))*Agenda!$A$5:$A$3004+(1-((Agenda!$E$5:$E$3004=A5)*((Agenda!$H$5:$H$3004="Agendado")+(Agenda!$H$5:$H$3004="Confirmado"))))*1E+10)))) -> 46281
A6: Beatriz Gomes | B6: Particular | C6: Dra. Renata Sousa | D6: (11) 90000-0254 | F6: =IF(A6="","",COUNTIFS(Agenda!$E$5:$E$3004,A6,Agenda!$H$5:$H$3004,"Realizado")) -> 1 | G6: =IF(A6="","",COUNTIFS(Agenda!$E$5:$E$3004,A6,Agenda!$H$5:$H$3004,"Falta")) -> 0 | H6: =IF(A6="","",IF(SUMPRODUCT(MAX((Agenda!$E$5:$E$3004=A6)*(Agenda!$H$5:$H$3004="Realizado")*Agenda!$A$5:$A$3004))=0,"",SUMPRODUCT(MAX((Agenda!$E$5:$E$3004=A6)*(Agenda!$H$5:$H$3004="Realizado")*Agenda!$A$5:$A$3004)))) -> 46273 | I6: =IF(A6="","",IF(SUMPRODUCT(MIN(((Agenda!$E$5:$E$3004=A6)*((Agenda!$H$5:$H$3004="Agendado")+(Agenda!$H$5:$H$3004="Confirmado")))*Agenda!$A$5:$A$3004+(1-((Agenda!$E$5:$E$3004=A6)*((Agenda!$H$5:$H$3004="Agendado")+(Agenda!$H$5:$H$3004="Confirmado"))))*1E+10))>=1E+10,"",SUMPRODUCT(MIN(((Agenda!$E$5:$E$3004=A6)*((Agenda!$H$5:$H$3004="Agendado")+(Agenda!$H$5:$H$3004="Confirmado")))*Agenda!$A$5:$A$3004+(1-((Agenda!$E$5:$E$3004=A6)*((Agenda!$H$5:$H$3004="Agendado")+(Agenda!$H$5:$H$3004="Confirmado"))))*1E+10)))) -> 46280
A7: Beatriz Gonçalves | B7: Saúde Total | C7: Dr. Paulo Andrade | D7: (11) 90000-0177 | F7: =IF(A7="","",COUNTIFS(Agenda!$E$5:$E$3004,A7,Agenda!$H$5:$H$3004,"Realizado")) -> 4 | G7: =IF(A7="","",COUNTIFS(Agenda!$E$5:$E$3004,A7,Agenda!$H$5:$H$3004,"Falta")) -> 0 | H7: =IF(A7="","",IF(SUMPRODUCT(MAX((Agenda!$E$5:$E$3004=A7)*(Agenda!$H$5:$H$3004="Realizado")*Agenda!$A$5:$A$3004))=0,"",SUMPRODUCT(MAX((Agenda!$E$5:$E$3004=A7)*(Agenda!$H$5:$H$3004="Realizado")*Agenda!$A$5:$A$3004)))) -> 46273 | I7: =IF(A7="","",IF(SUMPRODUCT(MIN(((Agenda!$E$5:$E$3004=A7)*((Agenda!$H$5:$H$3004="Agendado")+(Agenda!$H$5:$H$3004="Confirmado")))*Agenda!$A$5:$A$3004+(1-((Agenda!$E$5:$E$3004=A7)*((Agenda!$H$5:$H$3004="Agendado")+(Agenda!$H$5:$H$3004="Confirmado"))))*1E+10))>=1E+10,"",SUMPRODUCT(MIN(((Agenda!$E$5:$E$3004=A7)*((Agenda!$H$5:$H$3004="Agendado")+(Agenda!$H$5:$H$3004="Confirmado")))*Agenda!$A$5:$A$3004+(1-((Agenda!$E$5:$E$3004=A7)*((Agenda!$H$5:$H$3004="Agendado")+(Agenda!$H$5:$H$3004="Confirmado"))))*1E+10)))) -> 46287
A8: Beatriz Monteiro | B8: Particular | C8: Dra. Renata Sousa | D8: (11) 90000-0233 | F8: =IF(A8="","",COUNTIFS(Agenda!$E$5:$E$3004,A8,Agenda!$H$5:$H$3004,"Realizado")) -> 7 | G8: =IF(A8="","",COUNTIFS(Agenda!$E$5:$E$3004,A8,Agenda!$H$5:$H$3004,"Falta")) -> 0 | H8: =IF(A8="","",IF(SUMPRODUCT(MAX((Agenda!$E$5:$E$3004=A8)*(Agenda!$H$5:$H$3004="Realizado")*Agenda!$A$5:$A$3004))=0,"",SUMPRODUCT(MAX((Agenda!$E$5:$E$3004=A8)*(Agenda!$H$5:$H$3004="Realizado")*Agenda!$A$5:$A$3004)))) -> 46259 | I8: =IF(A8="","",IF(SUMPRODUCT(MIN(((Agenda!$E$5:$E$3004=A8)*((Agenda!$H$5:$H$3004="Agendado")+(Agenda!$H$5:$H$3004="Confirmado")))*Agenda!$A$5:$A$3004+(1-((Agenda!$E$5:$E$3004=A8)*((Agenda!$H$5:$H$3004="Agendado")+(Agenda!$H$5:$H$3004="Confirmado"))))*1E+10))>=1E+10,"",SUMPRODUCT(MIN(((Agenda!$E$5:$E$3004=A8)*((Agenda!$H$5:$H$3004="Agendado")+(Agenda!$H$5:$H$3004="Confirmado")))*Agenda!$A$5:$A$3004+(1-((Agenda!$E$5:$E$3004=A8)*((Agenda!$H$5:$H$3004="Agendado")+(Agenda!$H$5:$H$3004="Confirmado"))))*1E+10))))
A9: Beatriz Reis | B9: Particular | C9: Dra. Renata Sousa | D9: (11) 90000-0255 | F9: =IF(A9="","",COUNTIFS(Agenda!$E$5:$E$3004,A9,Agenda!$H$5:$H$3004,"Realizado")) -> 2 | G9: =IF(A9="","",COUNTIFS(Agenda!$E$5:$E$3004,A9,Agenda!$H$5:$H$3004,"Falta")) -> 0 | H9: =IF(A9="","",IF(SUMPRODUCT(MAX((Agenda!$E$5:$E$3004=A9)*(Agenda!$H$5:$H$3004="Realizado")*Agenda!$A$5:$A$3004))=0,"",SUMPRODUCT(MAX((Agenda!$E$5:$E$3004=A9)*(Agenda!$H$5:$H$3004="Realizado")*Agenda!$A$5:$A$3004)))) -> 46224 | I9: =IF(A9="","",IF(SUMPRODUCT(MIN(((Agenda!$E$5:$E$3004=A9)*((Agenda!$H$5:$H$3004="Agendado")+(Agenda!$H$5:$H$3004="Confirmado")))*Agenda!$A$5:$A$3004+(1-((Agenda!$E$5:$E$3004=A9)*((Agenda!$H$5:$H$3004="Agendado")+(Agenda!$H$5:$H$3004="Confirmado"))))*1E+10))>=1E+10,"",SUMPRODUCT(MIN(((Agenda!$E$5:$E$3004=A9)*((Agenda!$H$5:$H$3004="Agendado")+(Agenda!$H$5:$H$3004="Confirmado")))*Agenda!$A$5:$A$3004+(1-((Agenda!$E$5:$E$3004=A9)*((Agenda!$H$5:$H$3004="Agendado")+(Agenda!$H$5:$H$3004="Confirmado"))))*1E+10))))
A10: Bruno Carvalho | B10: Saúde Total | C10: Dr. Paulo Andrade | D10: (11) 90000-0213 | F10: =IF(A10="","",COUNTIFS(Agenda!$E$5:$E$3004,A10,Agenda!$H$5:$H$3004,"Realizado")) -> 3 | G10: =IF(A10="","",COUNTIFS(Agenda!$E$5:$E$3004,A10,Agenda!$H$5:$H$3004,"Falta")) -> 0 | H10: =IF(A10="","",IF(SUMPRODUCT(MAX((Agenda!$E$5:$E$3004=A10)*(Agenda!$H$5:$H$3004="Realizado")*Agenda!$A$5:$A$3004))=0,"",SUMPRODUCT(MAX((Agenda!$E$5:$E$3004=A10)*(Agenda!$H$5:$H$3004="Realizado")*Agenda!$A$5:$A$3004)))) -> 46261 | I10: =IF(A10="","",IF(SUMPRODUCT(MIN(((Agenda!$E$5:$E$3004=A10)*((Agenda!$H$5:$H$3004="Agendado")+(Agenda!$H$5:$H$3004="Confirmado")))*Agenda!$A$5:$A$3004+(1-((Agenda!$E$5:$E$3004=A10)*((Agenda!$H$5:$H$3004="Agendado")+(Agenda!$H$5:$H$3004="Confirmado"))))*1E+10))>=1E+10,"",SUMPRODUCT(MIN(((Agenda!$E$5:$E$3004=A10)*((Agenda!$H$5:$H$3004="Agendado")+(Agenda!$H$5:$H$3004="Confirmado")))*Agenda!$A$5:$A$3004+(1-((Agenda!$E$5:$E$3004=A10)*((Agenda!$H$5:$H$3004="Agendado")+(Agenda!$H$5:$H$3004="Confirmado"))))*1E+10)))) -> 46279
A11: Camila Batista | B11: MediPlan | C11: Dra. Carolina Mendes | D11: (11) 90000-0102 | F11: =IF(A11="","",COUNTIFS(Agenda!$E$5:$E$3004,A11,Agenda!$H$5:$H$3004,"Realizado")) -> 11 | G11: =IF(A11="","",COUNTIFS(Agenda!$E$5:$E$3004,A11,Agenda!$H$5:$H$3004,"Falta")) -> 2 | H11: =IF(A11="","",IF(SUMPRODUCT(MAX((Agenda!$E$5:$E$3004=A11)*(Agenda!$H$5:$H$3004="Realizado")*Agenda!$A$5:$A$3004))=0,"",SUMPRODUCT(MAX((Agenda!$E$5:$E$3004=A11)*(Agenda!$H$5:$H$3004="Realizado")*Agenda!$A$5:$A$3004)))) -> 46269 | I11: =IF(A11="","",IF(SUMPRODUCT(MIN(((Agenda!$E$5:$E$3004=A11)*((Agenda!$H$5:$H$3004="Agendado")+(Agenda!$H$5:$H$3004="Confirmado")))*Agenda!$A$5:$A$3004+(1-((Agenda!$E$5:$E$3004=A11)*((Agenda!$H$5:$H$3004="Agendado")+(Agenda!$H$5:$H$3004="Confirmado"))))*1E+10))>=1E+10,"",SUMPRODUCT(MIN(((Agenda!$E$5:$E$3004=A11)*((Agenda!$H$5:$H$3004="Agendado")+(Agenda!$H$5:$H$3004="Confirmado")))*Agenda!$A$5:$A$3004+(1-((Agenda!$E$5:$E$3004=A11)*((Agenda!$H$5:$H$3004="Agendado")+(Agenda!$H$5:$H$3004="Confirmado"))))*1E+10)))) -> 46279
A12: Camila Dias | B12: Particular | C12: Dra. Renata Sousa | D12: (11) 90000-0241 | F12: =IF(A12="","",COUNTIFS(Agenda!$E$5:$E$3004,A12,Agenda!$H$5:$H$3004,"Realizado")) -> 3 | G12: =IF(A12="","",COUNTIFS(Agenda!$E$5:$E$3004,A12,Agenda!$H$5:$H$3004,"Falta")) -> 0 | H12: =IF(A12="","",IF(SUMPRODUCT(MAX((Agenda!$E$5:$E$3004=A12)*(Agenda!$H$5:$H$3004="Realizado")*Agenda!$A$5:$A$3004))=0,"",SUMPRODUCT(MAX((Agenda!$E$5:$E$3004=A12)*(Agenda!$H$5:$H$3004="Realizado")*Agenda!$A$5:$A$3004)))) -> 46205 | I12: =IF(A12="","",IF(SUMPRODUCT(MIN(((Agenda!$E$5:$E$3004=A12)*((Agenda!$H$5:$H$3004="Agendado")+(Agenda!$H$5:$H$3004="Confirmado")))*Agenda!$A$5:$A$3004+(1-((Agenda!$E$5:$E$3004=A12)*((Agenda!$H$5:$H$3004="Agendado")+(Agenda!$H$5:$H$3004="Confirmado"))))*1E+10))>=1E+10,"",SUMPRODUCT(MIN(((Agenda!$E$5:$E$3004=A12)*((Agenda!$H$5:$H$3004="Agendado")+(Agenda!$H$5:$H$3004="Confirmado")))*Agenda!$A$5:$A$3004+(1-((Agenda!$E$5:$E$3004=A12)*((Agenda!$H$5:$H$3004="Agendado")+(Agenda!$H$5:$H$3004="Confirmado"))))*1E+10))))
A13: Camila Freitas | B13: Particular | C13: Dr. Paulo Andrade | D13: (11) 90000-0212 | F13: =IF(A13="","",COUNTIFS(Agenda!$E$5:$E$3004,A13,Agenda!$H$5:$H$3004,"Realizado")) -> 2 | G13: =IF(A13="","",COUNTIFS(Agenda!$E$5:$E$3004,A13,Agenda!$H$5:$H$3004,"Falta")) -> 0 | H13: =IF(A13="","",IF(SUMPRODUCT(MAX((Agenda!$E$5:$E$3004=A13)*(Agenda!$H$5:$H$3004="Realizado")*Agenda!$A$5:$A$3004))=0,"",SUMPRODUCT(MAX((Agenda!$E$5:$E$3004=A13)*(Agenda!$H$5:$H$3004="Realizado")*Agenda!$A$5:$A$3004)))) -> 46258 | I13: =IF(A13="","",IF(SUMPRODUCT(MIN(((Agenda!$E$5:$E$3004=A13)*((Agenda!$H$5:$H$3004="Agendado")+(Agenda!$H$5:$H$3004="Confirmado")))*Agenda!$A$5:$A$3004+(1-((Agenda!$E$5:$E$3004=A13)*((Agenda!$H$5:$H$3004="Agendado")+(Agenda!$H$5:$H$3004="Confirmado"))))*1E+10))>=1E+10,"",SUMPRODUCT(MIN(((Agenda!$E$5:$E$3004=A13)*((Agenda!$H$5:$H$3004="Agendado")+(Agenda!$H$5:$H$3004="Confirmado")))*Agenda!$A$5:$A$3004+(1-((Agenda!$E$5:$E$3004=A13)*((Agenda!$H$5:$H$3004="Agendado")+(Agenda!$H$5:$H$3004="Confirmado"))))*1E+10)))) -> 46289
A14: Camila Martins | B14: Vida Care | C14: Dr. Paulo Andrade | D14: (11) 90000-0201 | F14: =IF(A14="","",COUNTIFS(Agenda!$E$5:$E$3004,A14,Agenda!$H$5:$H$3004,"Realizado")) -> 7 | G14: =IF(A14="","",COUNTIFS(Agenda!$E$5:$E$3004,A14,Agenda!$H$5:$H$3004,"Falta")) -> 1 | H14: =IF(A14="","",IF(SUMPRODUCT(MAX((Agenda!$E$5:$E$3004=A14)*(Agenda!$H$5:$H$3004="Realizado")*Agenda!$A$5:$A$3004))=0,"",SUMPRODUCT(MAX((Agenda!$E$5:$E$3004=A14)*(Agenda!$H$5:$H$3004="Realizado")*Agenda!$A$5:$A$3004)))) -> 46269 | I14: =IF(A14="","",IF(SUMPRODUCT(MIN(((Agenda!$E$5:$E$3004=A14)*((Agenda!$H$5:$H$3004="Agendado")+(Agenda!$H$5:$H$3004="Confirmado")))*Agenda!$A$5:$A$3004+(1-((Agenda!$E$5:$E$3004=A14)*((Agenda!$H$5:$H$3004="Agendado")+(Agenda!$H$5:$H$3004="Confirmado"))))*1E+10))>=1E+10,"",SUMPRODUCT(MIN(((Agenda!$E$5:$E$3004=A14)*((Agenda!$H$5:$H$3004="Agendado")+(Agenda!$H$5:$H$3004="Confirmado")))*Agenda!$A$5:$A$3004+(1-((Agenda!$E$5:$E$3004=A14)*((Agenda!$H$5:$H$3004="Agendado")+(Agenda!$H$5:$H$3004="Confirmado"))))*1E+10)))) -> 46289
A15: Carlos Barros | B15: MediPlan | C15: Dra. Carolina Mendes | D15: (11) 90000-0131 | F15: =IF(A15="","",COUNTIFS(Agenda!$E$5:$E$3004,A15,Agenda!$H$5:$H$3004,"Realizado")) -> 5 | G15: =IF(A15="","",COUNTIFS(Agenda!$E$5:$E$3004,A15,Agenda!$H$5:$H$3004,"Falta")) -> 0 | H15: =IF(A15="","",IF(SUMPRODUCT(MAX((Agenda!$E$5:$E$3004=A15)*(Agenda!$H$5:$H$3004="Realizado")*Agenda!$A$5:$A$3004))=0,"",SUMPRODUCT(MAX((Agenda!$E$5:$E$3004=A15)*(Agenda!$H$5:$H$3004="Realizado")*Agenda!$A$5:$A$3004)))) -> 46273 | I15: =IF(A15="","",IF(SUMPRODUCT(MIN(((Agenda!$E$5:$E$3004=A15)*((Agenda!$H$5:$H$3004="Agendado")+(Agenda!$H$5:$H$3004="Confirmado")))*Agenda!$A$5:$A$3004+(1-((Agenda!$E$5:$E$3004=A15)*((Agenda!$H$5:$H$3004="Agendado")+(Agenda!$H$5:$H$3004="Confirmado"))))*1E+10))>=1E+10,"",SUMPRODUCT(MIN(((Agenda!$E$5:$E$3004=A15)*((Agenda!$H$5:$H$3004="Agendado")+(Agenda!$H$5:$H$3004="Confirmado")))*Agenda!$A$5:$A$3004+(1-((Agenda!$E$5:$E$3004=A15)*((Agenda!$H$5:$H$3004="Agendado")+(Agenda!$H$5:$H$3004="Confirmado"))))*1E+10)))) -> 46280
A16: Carlos Castro | B16: Saúde Total | C16: Dra. Carolina Mendes | D16: (11) 90000-0123 | F16: =IF(A16="","",COUNTIFS(Agenda!$E$5:$E$3004,A16,Agenda!$H$5:$H$3004,"Realizado")) -> 7 | G16: =IF(A16="","",COUNTIFS(Agenda!$E$5:$E$3004,A16,Agenda!$H$5:$H$3004,"Falta")) -> 1 | H16: =IF(A16="","",IF(SUMPRODUCT(MAX((Agenda!$E$5:$E$3004=A16)*(Agenda!$H$5:$H$3004="Realizado")*Agenda!$A$5:$A$3004))=0,"",SUMPRODUCT(MAX((Agenda!$E$5:$E$3004=A16)*(Agenda!$H$5:$H$3004="Realizado")*Agenda!$A$5:$A$3004)))) -> 46274 | I16: =IF(A16="","",IF(SUMPRODUCT(MIN(((Agenda!$E$5:$E$3004=A16)*((Agenda!$H$5:$H$3004="Agendado")+(Agenda!$H$5:$H$3004="Confirmado")))*Agenda!$A$5:$A$3004+(1-((Agenda!$E$5:$E$3004=A16)*((Agenda!$H$5:$H$3004="Agendado")+(Agenda!$H$5:$H$3004="Confirmado"))))*1E+10))>=1E+10,"",SUMPRODUCT(MIN(((Agenda!$E$5:$E$3004=A16)*((Agenda!$H$5:$H$3004="Agendado")+(Agenda!$H$5:$H$3004="Confirmado")))*Agenda!$A$5:$A$3004+(1-((Agenda!$E$5:$E$3004=A16)*((Agenda!$H$5:$H$3004="Agendado")+(Agenda!$H$5:$H$3004="Confirmado"))))*1E+10)))) -> 46289
... A160: Wagner Santos | B160: Particular | C160: Dra. Carolina Mendes | D160: (11) 90000-0151 | F160: =IF(A160="","",COUNTIFS(Agenda!$E$5:$E$3004,A160,Agenda!$H$5:$H$3004,"Realizado")) -> 8 | G160: =IF(A160="","",COUNTIFS(Agenda!$E$5:$E$3004,A160,Agenda!$H$5:$H$3004,"Falta")) -> 0 | H160: =IF(A160="","",IF(SUMPRODUCT(MAX((Agenda!$E$5:$E$3004=A160)*(Agenda!$H$5:$H$3004="Realizado")*Agenda!$A$5:$A$3004))=0,"",SUMPRODUCT(MAX((Agenda!$E$5:$E$3004=A160)*(Agenda!$H$5:$H$3004="Realizado")*Agenda!$A$5:$A$3004)))) -> 46245 | I160: =IF(A160="","",IF(SUMPRODUCT(MIN(((Agenda!$E$5:$E$3004=A160)*((Agenda!$H$5:$H$3004="Agendado")+(Agenda!$H$5:$H$3004="Confirmado")))*Agenda!$A$5:$A$3004+(1-((Agenda!$E$5:$E$3004=A160)*((Agenda!$H$5:$H$3004="Agendado")+(Agenda!$H$5:$H$3004="Confirmado"))))*1E+10))>=1E+10,"",SUMPRODUCT(MIN(((Agenda!$E$5:$E$3004=A160)*((Agenda!$H$5:$H$3004="Agendado")+(Agenda!$H$5:$H$3004="Confirmado")))*Agenda!$A$5:$A$3004+(1-((Agenda!$E$5:$E$3004=A160)*((Agenda!$H$5:$H$3004="Agendado")+(Agenda!$H$5:$H$3004="Confirmado"))))*1E+10)))) -> 46286
F161: =IF(A161="","",COUNTIFS(Agenda!$E$5:$E$3004,A161,Agenda!$H$5:$H$3004,"Realizado")) | G161: =IF(A161="","",COUNTIFS(Agenda!$E$5:$E$3004,A161,Agenda!$H$5:$H$3004,"Falta")) | H161: =IF(A161="","",IF(SUMPRODUCT(MAX((Agenda!$E$5:$E$3004=A161)*(Agenda!$H$5:$H$3004="Realizado")*Agenda!$A$5:$A$3004))=0,"",SUMPRODUCT(MAX((Agenda!$E$5:$E$3004=A161)*(Agenda!$H$5:$H$3004="Realizado")*Agenda!$A$5:$A$3004)))) | I161: =IF(A161="","",IF(SUMPRODUCT(MIN(((Agenda!$E$5:$E$3004=A161)*((Agenda!$H$5:$H$3004="Agendado")+(Agenda!$H$5:$H$3004="Confirmado")))*Agenda!$A$5:$A$3004+(1-((Agenda!$E$5:$E$3004=A161)*((Agenda!$H$5:$H$3004="Agendado")+(Agenda!$H$5:$H$3004="Confirmado"))))*1E+10))>=1E+10,"",SUMPRODUCT(MIN(((Agenda!$E$5:$E$3004=A161)*((Agenda!$H$5:$H$3004="Agendado")+(Agenda!$H$5:$H$3004="Confirmado")))*Agenda!$A$5:$A$3004+(1-((Agenda!$E$5:$E$3004=A161)*((Agenda!$H$5:$H$3004="Agendado")+(Agenda!$H$5:$H$3004="Confirmado"))))*1E+10))))
F162: =IF(A162="","",COUNTIFS(Agenda!$E$5:$E$3004,A162,Agenda!$H$5:$H$3004,"Realizado")) | G162: =IF(A162="","",COUNTIFS(Agenda!$E$5:$E$3004,A162,Agenda!$H$5:$H$3004,"Falta")) | H162: =IF(A162="","",IF(SUMPRODUCT(MAX((Agenda!$E$5:$E$3004=A162)*(Agenda!$H$5:$H$3004="Realizado")*Agenda!$A$5:$A$3004))=0,"",SUMPRODUCT(MAX((Agenda!$E$5:$E$3004=A162)*(Agenda!$H$5:$H$3004="Realizado")*Agenda!$A$5:$A$3004)))) | I162: =IF(A162="","",IF(SUMPRODUCT(MIN(((Agenda!$E$5:$E$3004=A162)*((Agenda!$H$5:$H$3004="Agendado")+(Agenda!$H$5:$H$3004="Confirmado")))*Agenda!$A$5:$A$3004+(1-((Agenda!$E$5:$E$3004=A162)*((Agenda!$H$5:$H$3004="Agendado")+(Agenda!$H$5:$H$3004="Confirmado"))))*1E+10))>=1E+10,"",SUMPRODUCT(MIN(((Agenda!$E$5:$E$3004=A162)*((Agenda!$H$5:$H$3004="Agendado")+(Agenda!$H$5:$H$3004="Confirmado")))*Agenda!$A$5:$A$3004+(1-((Agenda!$E$5:$E$3004=A162)*((Agenda!$H$5:$H$3004="Agendado")+(Agenda!$H$5:$H$3004="Confirmado"))))*1E+10))))
F163: =IF(A163="","",COUNTIFS(Agenda!$E$5:$E$3004,A163,Agenda!$H$5:$H$3004,"Realizado")) | G163: =IF(A163="","",COUNTIFS(Agenda!$E$5:$E$3004,A163,Agenda!$H$5:$H$3004,"Falta")) | H163: =IF(A163="","",IF(SUMPRODUCT(MAX((Agenda!$E$5:$E$3004=A163)*(Agenda!$H$5:$H$3004="Realizado")*Agenda!$A$5:$A$3004))=0,"",SUMPRODUCT(MAX((Agenda!$E$5:$E$3004=A163)*(Agenda!$H$5:$H$3004="Realizado")*Agenda!$A$5:$A$3004)))) | I163: =IF(A163="","",IF(SUMPRODUCT(MIN(((Agenda!$E$5:$E$3004=A163)*((Agenda!$H$5:$H$3004="Agendado")+(Agenda!$H$5:$H$3004="Confirmado")))*Agenda!$A$5:$A$3004+(1-((Agenda!$E$5:$E$3004=A163)*((Agenda!$H$5:$H$3004="Agendado")+(Agenda!$H$5:$H$3004="Confirmado"))))*1E+10))>=1E+10,"",SUMPRODUCT(MIN(((Agenda!$E$5:$E$3004=A163)*((Agenda!$H$5:$H$3004="Agendado")+(Agenda!$H$5:$H$3004="Confirmado")))*Agenda!$A$5:$A$3004+(1-((Agenda!$E$5:$E$3004=A163)*((Agenda!$H$5:$H$3004="Agendado")+(Agenda!$H$5:$H$3004="Confirmado"))))*1E+10))))
F164: =IF(A164="","",COUNTIFS(Agenda!$E$5:$E$3004,A164,Agenda!$H$5:$H$3004,"Realizado")) | G164: =IF(A164="","",COUNTIFS(Agenda!$E$5:$E$3004,A164,Agenda!$H$5:$H$3004,"Falta")) | H164: =IF(A164="","",IF(SUMPRODUCT(MAX((Agenda!$E$5:$E$3004=A164)*(Agenda!$H$5:$H$3004="Realizado")*Agenda!$A$5:$A$3004))=0,"",SUMPRODUCT(MAX((Agenda!$E$5:$E$3004=A164)*(Agenda!$H$5:$H$3004="Realizado")*Agenda!$A$5:$A$3004)))) | I164: =IF(A164="","",IF(SUMPRODUCT(MIN(((Agenda!$E$5:$E$3004=A164)*((Agenda!$H$5:$H$3004="Agendado")+(Agenda!$H$5:$H$3004="Confirmado")))*Agenda!$A$5:$A$3004+(1-((Agenda!$E$5:$E$3004=A164)*((Agenda!$H$5:$H$3004="Agendado")+(Agenda!$H$5:$H$3004="Confirmado"))))*1E+10))>=1E+10,"",SUMPRODUCT(MIN(((Agenda!$E$5:$E$3004=A164)*((Agenda!$H$5:$H$3004="Agendado")+(Agenda!$H$5:$H$3004="Confirmado")))*Agenda!$A$5:$A$3004+(1-((Agenda!$E$5:$E$3004=A164)*((Agenda!$H$5:$H$3004="Agendado")+(Agenda!$H$5:$H$3004="Confirmado"))))*1E+10))))
F165: =IF(A165="","",COUNTIFS(Agenda!$E$5:$E$3004,A165,Agenda!$H$5:$H$3004,"Realizado")) | G165: =IF(A165="","",COUNTIFS(Agenda!$E$5:$E$3004,A165,Agenda!$H$5:$H$3004,"Falta")) | H165: =IF(A165="","",IF(SUMPRODUCT(MAX((Agenda!$E$5:$E$3004=A165)*(Agenda!$H$5:$H$3004="Realizado")*Agenda!$A$5:$A$3004))=0,"",SUMPRODUCT(MAX((Agenda!$E$5:$E$3004=A165)*(Agenda!$H$5:$H$3004="Realizado")*Agenda!$A$5:$A$3004)))) | I165: =IF(A165="","",IF(SUMPRODUCT(MIN(((Agenda!$E$5:$E$3004=A165)*((Agenda!$H$5:$H$3004="Agendado")+(Agenda!$H$5:$H$3004="Confirmado")))*Agenda!$A$5:$A$3004+(1-((Agenda!$E$5:$E$3004=A165)*((Agenda!$H$5:$H$3004="Agendado")+(Agenda!$H$5:$H$3004="Confirmado"))))*1E+10))>=1E+10,"",SUMPRODUCT(MIN(((Agenda!$E$5:$E$3004=A165)*((Agenda!$H$5:$H$3004="Agendado")+(Agenda!$H$5:$H$3004="Confirmado")))*Agenda!$A$5:$A$3004+(1-((Agenda!$E$5:$E$3004=A165)*((Agenda!$H$5:$H$3004="Agendado")+(Agenda!$H$5:$H$3004="Confirmado"))))*1E+10))))
F166: =IF(A166="","",COUNTIFS(Agenda!$E$5:$E$3004,A166,Agenda!$H$5:$H$3004,"Realizado")) | G166: =IF(A166="","",COUNTIFS(Agenda!$E$5:$E$3004,A166,Agenda!$H$5:$H$3004,"Falta")) | H166: =IF(A166="","",IF(SUMPRODUCT(MAX((Agenda!$E$5:$E$3004=A166)*(Agenda!$H$5:$H$3004="Realizado")*Agenda!$A$5:$A$3004))=0,"",SUMPRODUCT(MAX((Agenda!$E$5:$E$3004=A166)*(Agenda!$H$5:$H$3004="Realizado")*Agenda!$A$5:$A$3004)))) | I166: =IF(A166="","",IF(SUMPRODUCT(MIN(((Agenda!$E$5:$E$3004=A166)*((Agenda!$H$5:$H$3004="Agendado")+(Agenda!$H$5:$H$3004="Confirmado")))*Agenda!$A$5:$A$3004+(1-((Agenda!$E$5:$E$3004=A166)*((Agenda!$H$5:$H$3004="Agendado")+(Agenda!$H$5:$H$3004="Confirmado"))))*1E+10))>=1E+10,"",SUMPRODUCT(MIN(((Agenda!$E$5:$E$3004=A166)*((Agenda!$H$5:$H$3004="Agendado")+(Agenda!$H$5:$H$3004="Confirmado")))*Agenda!$A$5:$A$3004+(1-((Agenda!$E$5:$E$3004=A166)*((Agenda!$H$5:$H$3004="Agendado")+(Agenda!$H$5:$H$3004="Confirmado"))))*1E+10))))
F167: =IF(A167="","",COUNTIFS(Agenda!$E$5:$E$3004,A167,Agenda!$H$5:$H$3004,"Realizado")) | G167: =IF(A167="","",COUNTIFS(Agenda!$E$5:$E$3004,A167,Agenda!$H$5:$H$3004,"Falta")) | H167: =IF(A167="","",IF(SUMPRODUCT(MAX((Agenda!$E$5:$E$3004=A167)*(Agenda!$H$5:$H$3004="Realizado")*Agenda!$A$5:$A$3004))=0,"",SUMPRODUCT(MAX((Agenda!$E$5:$E$3004=A167)*(Agenda!$H$5:$H$3004="Realizado")*Agenda!$A$5:$A$3004)))) | I167: =IF(A167="","",IF(SUMPRODUCT(MIN(((Agenda!$E$5:$E$3004=A167)*((Agenda!$H$5:$H$3004="Agendado")+(Agenda!$H$5:$H$3004="Confirmado")))*Agenda!$A$5:$A$3004+(1-((Agenda!$E$5:$E$3004=A167)*((Agenda!$H$5:$H$3004="Agendado")+(Agenda!$H$5:$H$3004="Confirmado"))))*1E+10))>=1E+10,"",SUMPRODUCT(MIN(((Agenda!$E$5:$E$3004=A167)*((Agenda!$H$5:$H$3004="Agendado")+(Agenda!$H$5:$H$3004="Confirmado")))*Agenda!$A$5:$A$3004+(1-((Agenda!$E$5:$E$3004=A167)*((Agenda!$H$5:$H$3004="Agendado")+(Agenda!$H$5:$H$3004="Confirmado"))))*1E+10))))
F168: =IF(A168="","",COUNTIFS(Agenda!$E$5:$E$3004,A168,Agenda!$H$5:$H$3004,"Realizado")) | G168: =IF(A168="","",COUNTIFS(Agenda!$E$5:$E$3004,A168,Agenda!$H$5:$H$3004,"Falta")) | H168: =IF(A168="","",IF(SUMPRODUCT(MAX((Agenda!$E$5:$E$3004=A168)*(Agenda!$H$5:$H$3004="Realizado")*Agenda!$A$5:$A$3004))=0,"",SUMPRODUCT(MAX((Agenda!$E$5:$E$3004=A168)*(Agenda!$H$5:$H$3004="Realizado")*Agenda!$A$5:$A$3004)))) | I168: =IF(A168="","",IF(SUMPRODUCT(MIN(((Agenda!$E$5:$E$3004=A168)*((Agenda!$H$5:$H$3004="Agendado")+(Agenda!$H$5:$H$3004="Confirmado")))*Agenda!$A$5:$A$3004+(1-((Agenda!$E$5:$E$3004=A168)*((Agenda!$H$5:$H$3004="Agendado")+(Agenda!$H$5:$H$3004="Confirmado"))))*1E+10))>=1E+10,"",SUMPRODUCT(MIN(((Agenda!$E$5:$E$3004=A168)*((Agenda!$H$5:$H$3004="Agendado")+(Agenda!$H$5:$H$3004="Confirmado")))*Agenda!$A$5:$A$3004+(1-((Agenda!$E$5:$E$3004=A168)*((Agenda!$H$5:$H$3004="Agendado")+(Agenda!$H$5:$H$3004="Confirmado"))))*1E+10))))
F169: =IF(A169="","",COUNTIFS(Agenda!$E$5:$E$3004,A169,Agenda!$H$5:$H$3004,"Realizado")) | G169: =IF(A169="","",COUNTIFS(Agenda!$E$5:$E$3004,A169,Agenda!$H$5:$H$3004,"Falta")) | H169: =IF(A169="","",IF(SUMPRODUCT(MAX((Agenda!$E$5:$E$3004=A169)*(Agenda!$H$5:$H$3004="Realizado")*Agenda!$A$5:$A$3004))=0,"",SUMPRODUCT(MAX((Agenda!$E$5:$E$3004=A169)*(Agenda!$H$5:$H$3004="Realizado")*Agenda!$A$5:$A$3004)))) | I169: =IF(A169="","",IF(SUMPRODUCT(MIN(((Agenda!$E$5:$E$3004=A169)*((Agenda!$H$5:$H$3004="Agendado")+(Agenda!$H$5:$H$3004="Confirmado")))*Agenda!$A$5:$A$3004+(1-((Agenda!$E$5:$E$3004=A169)*((Agenda!$H$5:$H$3004="Agendado")+(Agenda!$H$5:$H$3004="Confirmado"))))*1E+10))>=1E+10,"",SUMPRODUCT(MIN(((Agenda!$E$5:$E$3004=A169)*((Agenda!$H$5:$H$3004="Agendado")+(Agenda!$H$5:$H$3004="Confirmado")))*Agenda!$A$5:$A$3004+(1-((Agenda!$E$5:$E$3004=A169)*((Agenda!$H$5:$H$3004="Agendado")+(Agenda!$H$5:$H$3004="Confirmado"))))*1E+10))))
F170: =IF(A170="","",COUNTIFS(Agenda!$E$5:$E$3004,A170,Agenda!$H$5:$H$3004,"Realizado")) | G170: =IF(A170="","",COUNTIFS(Agenda!$E$5:$E$3004,A170,Agenda!$H$5:$H$3004,"Falta")) | H170: =IF(A170="","",IF(SUMPRODUCT(MAX((Agenda!$E$5:$E$3004=A170)*(Agenda!$H$5:$H$3004="Realizado")*Agenda!$A$5:$A$3004))=0,"",SUMPRODUCT(MAX((Agenda!$E$5:$E$3004=A170)*(Agenda!$H$5:$H$3004="Realizado")*Agenda!$A$5:$A$3004)))) | I170: =IF(A170="","",IF(SUMPRODUCT(MIN(((Agenda!$E$5:$E$3004=A170)*((Agenda!$H$5:$H$3004="Agendado")+(Agenda!$H$5:$H$3004="Confirmado")))*Agenda!$A$5:$A$3004+(1-((Agenda!$E$5:$E$3004=A170)*((Agenda!$H$5:$H$3004="Agendado")+(Agenda!$H$5:$H$3004="Confirmado"))))*1E+10))>=1E+10,"",SUMPRODUCT(MIN(((Agenda!$E$5:$E$3004=A170)*((Agenda!$H$5:$H$3004="Agendado")+(Agenda!$H$5:$H$3004="Confirmado")))*Agenda!$A$5:$A$3004+(1-((Agenda!$E$5:$E$3004=A170)*((Agenda!$H$5:$H$3004="Agendado")+(Agenda!$H$5:$H$3004="Confirmado"))))*1E+10))))
F171: =IF(A171="","",COUNTIFS(Agenda!$E$5:$E$3004,A171,Agenda!$H$5:$H$3004,"Realizado")) | G171: =IF(A171="","",COUNTIFS(Agenda!$E$5:$E$3004,A171,Agenda!$H$5:$H$3004,"Falta")) | H171: =IF(A171="","",IF(SUMPRODUCT(MAX((Agenda!$E$5:$E$3004=A171)*(Agenda!$H$5:$H$3004="Realizado")*Agenda!$A$5:$A$3004))=0,"",SUMPRODUCT(MAX((Agenda!$E$5:$E$3004=A171)*(Agenda!$H$5:$H$3004="Realizado")*Agenda!$A$5:$A$3004)))) | I171: =IF(A171="","",IF(SUMPRODUCT(MIN(((Agenda!$E$5:$E$3004=A171)*((Agenda!$H$5:$H$3004="Agendado")+(Agenda!$H$5:$H$3004="Confirmado")))*Agenda!$A$5:$A$3004+(1-((Agenda!$E$5:$E$3004=A171)*((Agenda!$H$5:$H$3004="Agendado")+(Agenda!$H$5:$H$3004="Confirmado"))))*1E+10))>=1E+10,"",SUMPRODUCT(MIN(((Agenda!$E$5:$E$3004=A171)*((Agenda!$H$5:$H$3004="Agendado")+(Agenda!$H$5:$H$3004="Confirmado")))*Agenda!$A$5:$A$3004+(1-((Agenda!$E$5:$E$3004=A171)*((Agenda!$H$5:$H$3004="Agendado")+(Agenda!$H$5:$H$3004="Confirmado"))))*1E+10))))
F172: =IF(A172="","",COUNTIFS(Agenda!$E$5:$E$3004,A172,Agenda!$H$5:$H$3004,"Realizado")) | G172: =IF(A172="","",COUNTIFS(Agenda!$E$5:$E$3004,A172,Agenda!$H$5:$H$3004,"Falta")) | H172: =IF(A172="","",IF(SUMPRODUCT(MAX((Agenda!$E$5:$E$3004=A172)*(Agenda!$H$5:$H$3004="Realizado")*Agenda!$A$5:$A$3004))=0,"",SUMPRODUCT(MAX((Agenda!$E$5:$E$3004=A172)*(Agenda!$H$5:$H$3004="Realizado")*Agenda!$A$5:$A$3004)))) | I172: =IF(A172="","",IF(SUMPRODUCT(MIN(((Agenda!$E$5:$E$3004=A172)*((Agenda!$H$5:$H$3004="Agendado")+(Agenda!$H$5:$H$3004="Confirmado")))*Agenda!$A$5:$A$3004+(1-((Agenda!$E$5:$E$3004=A172)*((Agenda!$H$5:$H$3004="Agendado")+(Agenda!$H$5:$H$3004="Confirmado"))))*1E+10))>=1E+10,"",SUMPRODUCT(MIN(((Agenda!$E$5:$E$3004=A172)*((Agenda!$H$5:$H$3004="Agendado")+(Agenda!$H$5:$H$3004="Confirmado")))*Agenda!$A$5:$A$3004+(1-((Agenda!$E$5:$E$3004=A172)*((Agenda!$H$5:$H$3004="Agendado")+(Agenda!$H$5:$H$3004="Confirmado"))))*1E+10))))
... F404: =IF(A404="","",COUNTIFS(Agenda!$E$5:$E$3004,A404,Agenda!$H$5:$H$3004,"Realizado")) | G404: =IF(A404="","",COUNTIFS(Agenda!$E$5:$E$3004,A404,Agenda!$H$5:$H$3004,"Falta")) | H404: =IF(A404="","",IF(SUMPRODUCT(MAX((Agenda!$E$5:$E$3004=A404)*(Agenda!$H$5:$H$3004="Realizado")*Agenda!$A$5:$A$3004))=0,"",SUMPRODUCT(MAX((Agenda!$E$5:$E$3004=A404)*(Agenda!$H$5:$H$3004="Realizado")*Agenda!$A$5:$A$3004)))) | I404: =IF(A404="","",IF(SUMPRODUCT(MIN(((Agenda!$E$5:$E$3004=A404)*((Agenda!$H$5:$H$3004="Agendado")+(Agenda!$H$5:$H$3004="Confirmado")))*Agenda!$A$5:$A$3004+(1-((Agenda!$E$5:$E$3004=A404)*((Agenda!$H$5:$H$3004="Agendado")+(Agenda!$H$5:$H$3004="Confirmado"))))*1E+10))>=1E+10,"",SUMPRODUCT(MIN(((Agenda!$E$5:$E$3004=A404)*((Agenda!$H$5:$H$3004="Agendado")+(Agenda!$H$5:$H$3004="Confirmado")))*Agenda!$A$5:$A$3004+(1-((Agenda!$E$5:$E$3004=A404)*((Agenda!$H$5:$H$3004="Agendado")+(Agenda!$H$5:$H$3004="Confirmado"))))*1E+10))))
A406: Esta aba é a fonte do cadastro de pacientes do kit: a planilha 14 (parcelas) copia os nomes daqui. Contato fictício no exemplo. Não guarde aqui nada além do necessário para agendar e cobrar.

Sheet Agenda
A1: Agenda
A2: Uma linha por horário marcado. Preencha o amarelo, inclusive minutos e valor (as duas últimas colunas sugerem o que a tabela de Config diz hoje); mês, dia da semana e período são calculados. Situação: Agendado, Confirmado, Realizado, Falta, Cancelado ou Remarcado. Esta aba é a fonte da agenda do kit (02 e 16 copiam daqui).
A4: Data | B4: Hora | C4: Profissional | D4: Sala | E4: Paciente | F4: Pagador | G4: Procedimento | H4: Situação | I4: Forma de pagamento | J4: Parcelas (cartão) | K4: Observação | L4: Minutos | M4: Valor (R$) | N4: Mês | O4: Ano | P4: Dia da semana | Q4: Período | R4: Horas atendidas | S4: Minutos pela tabela de hoje | T4: Valor pela tabela de hoje
A5: 46174 | B5: 0.33333333 | C5: Dra. Carolina Mendes | D5: Sala 1 | E5: Isabela Pinto | F5: Saúde Total | G5: Consulta | H5: Realizado | I5: Convênio | L5: 30 | M5: 120 | N5: =IF(A5="","",MONTH(A5)) -> 6 | O5: =IF(A5="","",YEAR(A5)) -> 2026 | P5: =IF(A5="","",CHOOSE(WEEKDAY(A5,2),"Segunda","Terça","Quarta","Quinta","Sexta","Sábado","Domingo")) -> Segunda | Q5: =IF(B5="","",IF(B5<TIME(12,0,0),"Manhã",IF(B5<TIME(18,0,0),"Tarde","Noite"))) -> Manhã | R5: =IF(AND(H5="Realizado",L5<>"",A5<=Config!$B$9),L5/60,0) -> 0.5 | S5: =IF(G5="","",IFERROR(INDEX(Config!$K$5:$K$16,MATCH(G5,Config!$J$5:$J$16,0)),"")) -> 30 | T5: =IF(OR(G5="",F5=""),"",IFERROR(INDEX(Config!$M$5:$R$16,MATCH(G5,Config!$J$5:$J$16,0),MATCH(F5,Config!$H$5:$H$10,0)),"")) -> 120 | U5: =IF(AND(H5="Realizado",L5<>""),L5/60,0) -> 0.5 | V5: =IF(AND(H5="Realizado",OR(L5="",M5="")),1,0) -> 0
A6: 46174 | B6: 0.375 | C6: Dra. Carolina Mendes | D6: Sala 1 | E6: Tatiana Cunha | F6: Saúde Total | G6: Consulta | H6: Realizado | I6: Convênio | L6: 30 | M6: 120 | N6: =IF(A6="","",MONTH(A6)) -> 6 | O6: =IF(A6="","",YEAR(A6)) -> 2026 | P6: =IF(A6="","",CHOOSE(WEEKDAY(A6,2),"Segunda","Terça","Quarta","Quinta","Sexta","Sábado","Domingo")) -> Segunda | Q6: =IF(B6="","",IF(B6<TIME(12,0,0),"Manhã",IF(B6<TIME(18,0,0),"Tarde","Noite"))) -> Manhã | R6: =IF(AND(H6="Realizado",L6<>"",A6<=Config!$B$9),L6/60,0) -> 0.5 | S6: =IF(G6="","",IFERROR(INDEX(Config!$K$5:$K$16,MATCH(G6,Config!$J$5:$J$16,0)),"")) -> 30 | T6: =IF(OR(G6="",F6=""),"",IFERROR(INDEX(Config!$M$5:$R$16,MATCH(G6,Config!$J$5:$J$16,0),MATCH(F6,Config!$H$5:$H$10,0)),"")) -> 120 | U6: =IF(AND(H6="Realizado",L6<>""),L6/60,0) -> 0.5 | V6: =IF(AND(H6="Realizado",OR(L6="",M6="")),1,0) -> 0
A7: 46174 | B7: 0.39583333 | C7: Dra. Carolina Mendes | D7: Sala 1 | E7: Débora Machado | F7: Saúde Total | G7: Consulta | H7: Realizado | I7: Convênio | L7: 30 | M7: 120 | N7: =IF(A7="","",MONTH(A7)) -> 6 | O7: =IF(A7="","",YEAR(A7)) -> 2026 | P7: =IF(A7="","",CHOOSE(WEEKDAY(A7,2),"Segunda","Terça","Quarta","Quinta","Sexta","Sábado","Domingo")) -> Segunda | Q7: =IF(B7="","",IF(B7<TIME(12,0,0),"Manhã",IF(B7<TIME(18,0,0),"Tarde","Noite"))) -> Manhã | R7: =IF(AND(H7="Realizado",L7<>"",A7<=Config!$B$9),L7/60,0) -> 0.5 | S7: =IF(G7="","",IFERROR(INDEX(Config!$K$5:$K$16,MATCH(G7,Config!$J$5:$J$16,0)),"")) -> 30 | T7: =IF(OR(G7="",F7=""),"",IFERROR(INDEX(Config!$M$5:$R$16,MATCH(G7,Config!$J$5:$J$16,0),MATCH(F7,Config!$H$5:$H$10,0)),"")) -> 120 | U7: =IF(AND(H7="Realizado",L7<>""),L7/60,0) -> 0.5 | V7: =IF(AND(H7="Realizado",OR(L7="",M7="")),1,0) -> 0
A8: 46174 | B8: 0.41666667 | C8: Dra. Carolina Mendes | D8: Sala 1 | E8: Gustavo Ferreira | F8: Particular | G8: Retorno | H8: Realizado | I8: Sem cobrança | L8: 20 | M8: 0 | N8: =IF(A8="","",MONTH(A8)) -> 6 | O8: =IF(A8="","",YEAR(A8)) -> 2026 | P8: =IF(A8="","",CHOOSE(WEEKDAY(A8,2),"Segunda","Terça","Quarta","Quinta","Sexta","Sábado","Domingo")) -> Segunda | Q8: =IF(B8="","",IF(B8<TIME(12,0,0),"Manhã",IF(B8<TIME(18,0,0),"Tarde","Noite"))) -> Manhã | R8: =IF(AND(H8="Realizado",L8<>"",A8<=Config!$B$9),L8/60,0) -> 0.33333333 | S8: =IF(G8="","",IFERROR(INDEX(Config!$K$5:$K$16,MATCH(G8,Config!$J$5:$J$16,0)),"")) -> 20 | T8: =IF(OR(G8="",F8=""),"",IFERROR(INDEX(Config!$M$5:$R$16,MATCH(G8,Config!$J$5:$J$16,0),MATCH(F8,Config!$H$5:$H$10,0)),"")) -> 0 | U8: =IF(AND(H8="Realizado",L8<>""),L8/60,0) -> 0.33333333 | V8: =IF(AND(H8="Realizado",OR(L8="",M8="")),1,0) -> 0
A9: 46174 | B9: 0.45138889 | C9: Dra. Carolina Mendes | D9: Sala 1 | E9: Sérgio Batista | F9: MediPlan | G9: Consulta | H9: Falta | L9: 30 | M9: 100 | N9: =IF(A9="","",MONTH(A9)) -> 6 | O9: =IF(A9="","",YEAR(A9)) -> 2026 | P9: =IF(A9="","",CHOOSE(WEEKDAY(A9,2),"Segunda","Terça","Quarta","Quinta","Sexta","Sábado","Domingo")) -> Segunda | Q9: =IF(B9="","",IF(B9<TIME(12,0,0),"Manhã",IF(B9<TIME(18,0,0),"Tarde","Noite"))) -> Manhã | R9: =IF(AND(H9="Realizado",L9<>"",A9<=Config!$B$9),L9/60,0) -> 0 | S9: =IF(G9="","",IFERROR(INDEX(Config!$K$5:$K$16,MATCH(G9,Config!$J$5:$J$16,0)),"")) -> 30 | T9: =IF(OR(G9="",F9=""),"",IFERROR(INDEX(Config!$M$5:$R$16,MATCH(G9,Config!$J$5:$J$16,0),MATCH(F9,Config!$H$5:$H$10,0)),"")) -> 100 | U9: =IF(AND(H9="Realizado",L9<>""),L9/60,0) -> 0 | V9: =IF(AND(H9="Realizado",OR(L9="",M9="")),1,0) -> 0
A10: 46174 | B10: 0.60416667 | C10: Dr. Paulo Andrade | D10: Sala 2 | E10: Otávio Martins | F10: MediPlan | G10: Consulta | H10: Falta | L10: 30 | M10: 100 | N10: =IF(A10="","",MONTH(A10)) -> 6 | O10: =IF(A10="","",YEAR(A10)) -> 2026 | P10: =IF(A10="","",CHOOSE(WEEKDAY(A10,2),"Segunda","Terça","Quarta","Quinta","Sexta","Sábado","Domingo")) -> Segunda | Q10: =IF(B10="","",IF(B10<TIME(12,0,0),"Manhã",IF(B10<TIME(18,0,0),"Tarde","Noite"))) -> Tarde | R10: =IF(AND(H10="Realizado",L10<>"",A10<=Config!$B$9),L10/60,0) -> 0 | S10: =IF(G10="","",IFERROR(INDEX(Config!$K$5:$K$16,MATCH(G10,Config!$J$5:$J$16,0)),"")) -> 30 | T10: =IF(OR(G10="",F10=""),"",IFERROR(INDEX(Config!$M$5:$R$16,MATCH(G10,Config!$J$5:$J$16,0),MATCH(F10,Config!$H$5:$H$10,0)),"")) -> 100 | U10: =IF(AND(H10="Realizado",L10<>""),L10/60,0) -> 0 | V10: =IF(AND(H10="Realizado",OR(L10="",M10="")),1,0) -> 0
A11: 46174 | B11: 0.625 | C11: Dr. Paulo Andrade | D11: Sala 2 | E11: Natália Martins | F11: Particular | G11: Consulta | H11: Falta | L11: 30 | M11: 380 | N11: =IF(A11="","",MONTH(A11)) -> 6 | O11: =IF(A11="","",YEAR(A11)) -> 2026 | P11: =IF(A11="","",CHOOSE(WEEKDAY(A11,2),"Segunda","Terça","Quarta","Quinta","Sexta","Sábado","Domingo")) -> Segunda | Q11: =IF(B11="","",IF(B11<TIME(12,0,0),"Manhã",IF(B11<TIME(18,0,0),"Tarde","Noite"))) -> Tarde | R11: =IF(AND(H11="Realizado",L11<>"",A11<=Config!$B$9),L11/60,0) -> 0 | S11: =IF(G11="","",IFERROR(INDEX(Config!$K$5:$K$16,MATCH(G11,Config!$J$5:$J$16,0)),"")) -> 30 | T11: =IF(OR(G11="",F11=""),"",IFERROR(INDEX(Config!$M$5:$R$16,MATCH(G11,Config!$J$5:$J$16,0),MATCH(F11,Config!$H$5:$H$10,0)),"")) -> 380 | U11: =IF(AND(H11="Realizado",L11<>""),L11/60,0) -> 0 | V11: =IF(AND(H11="Realizado",OR(L11="",M11="")),1,0) -> 0
A12: 46174 | B12: 0.64583333 | C12: Dr. Paulo Andrade | D12: Sala 2 | E12: Otávio Martins | F12: MediPlan | G12: Consulta | H12: Realizado | I12: Convênio | L12: 30 | M12: 100 | N12: =IF(A12="","",MONTH(A12)) -> 6 | O12: =IF(A12="","",YEAR(A12)) -> 2026 | P12: =IF(A12="","",CHOOSE(WEEKDAY(A12,2),"Segunda","Terça","Quarta","Quinta","Sexta","Sábado","Domingo")) -> Segunda | Q12: =IF(B12="","",IF(B12<TIME(12,0,0),"Manhã",IF(B12<TIME(18,0,0),"Tarde","Noite"))) -> Tarde | R12: =IF(AND(H12="Realizado",L12<>"",A12<=Config!$B$9),L12/60,0) -> 0.5 | S12: =IF(G12="","",IFERROR(INDEX(Config!$K$5:$K$16,MATCH(G12,Config!$J$5:$J$16,0)),"")) -> 30 | T12: =IF(OR(G12="",F12=""),"",IFERROR(INDEX(Config!$M$5:$R$16,MATCH(G12,Config!$J$5:$J$16,0),MATCH(F12,Config!$H$5:$H$10,0)),"")) -> 100 | U12: =IF(AND(H12="Realizado",L12<>""),L12/60,0) -> 0.5 | V12: =IF(AND(H12="Realizado",OR(L12="",M12="")),1,0) -> 0
A13: 46174 | B13: 0.66666667 | C13: Dr. Paulo Andrade | D13: Sala 2 | E13: Cláudia Santos | F13: Particular | G13: MAPA | H13: Realizado | I13: Pix | L13: 20 | M13: 300 | N13: =IF(A13="","",MONTH(A13)) -> 6 | O13: =IF(A13="","",YEAR(A13)) -> 2026 | P13: =IF(A13="","",CHOOSE(WEEKDAY(A13,2),"Segunda","Terça","Quarta","Quinta","Sexta","Sábado","Domingo")) -> Segunda | Q13: =IF(B13="","",IF(B13<TIME(12,0,0),"Manhã",IF(B13<TIME(18,0,0),"Tarde","Noite"))) -> Tarde | R13: =IF(AND(H13="Realizado",L13<>"",A13<=Config!$B$9),L13/60,0) -> 0.33333333 | S13: =IF(G13="","",IFERROR(INDEX(Config!$K$5:$K$16,MATCH(G13,Config!$J$5:$J$16,0)),"")) -> 20 | T13: =IF(OR(G13="",F13=""),"",IFERROR(INDEX(Config!$M$5:$R$16,MATCH(G13,Config!$J$5:$J$16,0),MATCH(F13,Config!$H$5:$H$10,0)),"")) -> 300 | U13: =IF(AND(H13="Realizado",L13<>""),L13/60,0) -> 0.33333333 | V13: =IF(AND(H13="Realizado",OR(L13="",M13="")),1,0) -> 0
A14: 46174 | B14: 0.68055556 | C14: Dr. Paulo Andrade | D14: Sala 2 | E14: Mateus Martins | F14: Vida Care | G14: Consulta | H14: Realizado | I14: Convênio | L14: 30 | M14: 90 | N14: =IF(A14="","",MONTH(A14)) -> 6 | O14: =IF(A14="","",YEAR(A14)) -> 2026 | P14: =IF(A14="","",CHOOSE(WEEKDAY(A14,2),"Segunda","Terça","Quarta","Quinta","Sexta","Sábado","Domingo")) -> Segunda | Q14: =IF(B14="","",IF(B14<TIME(12,0,0),"Manhã",IF(B14<TIME(18,0,0),"Tarde","Noite"))) -> Tarde | R14: =IF(AND(H14="Realizado",L14<>"",A14<=Config!$B$9),L14/60,0) -> 0.5 | S14: =IF(G14="","",IFERROR(INDEX(Config!$K$5:$K$16,MATCH(G14,Config!$J$5:$J$16,0)),"")) -> 30 | T14: =IF(OR(G14="",F14=""),"",IFERROR(INDEX(Config!$M$5:$R$16,MATCH(G14,Config!$J$5:$J$16,0),MATCH(F14,Config!$H$5:$H$10,0)),"")) -> 90 | U14: =IF(AND(H14="Realizado",L14<>""),L14/60,0) -> 0.5 | V14: =IF(AND(H14="Realizado",OR(L14="",M14="")),1,0) -> 0
A15: 46174 | B15: 0.70138889 | C15: Dr. Paulo Andrade | D15: Sala 2 | E15: Wagner Lima | F15: Particular | G15: Retorno | H15: Realizado | I15: Sem cobrança | L15: 20 | M15: 0 | N15: =IF(A15="","",MONTH(A15)) -> 6 | O15: =IF(A15="","",YEAR(A15)) -> 2026 | P15: =IF(A15="","",CHOOSE(WEEKDAY(A15,2),"Segunda","Terça","Quarta","Quinta","Sexta","Sábado","Domingo")) -> Segunda | Q15: =IF(B15="","",IF(B15<TIME(12,0,0),"Manhã",IF(B15<TIME(18,0,0),"Tarde","Noite"))) -> Tarde | R15: =IF(AND(H15="Realizado",L15<>"",A15<=Config!$B$9),L15/60,0) -> 0.33333333 | S15: =IF(G15="","",IFERROR(INDEX(Config!$K$5:$K$16,MATCH(G15,Config!$J$5:$J$16,0)),"")) -> 20 | T15: =IF(OR(G15="",F15=""),"",IFERROR(INDEX(Config!$M$5:$R$16,MATCH(G15,Config!$J$5:$J$16,0),MATCH(F15,Config!$H$5:$H$10,0)),"")) -> 0 | U15: =IF(AND(H15="Realizado",L15<>""),L15/60,0) -> 0.33333333 | V15: =IF(AND(H15="Realizado",OR(L15="",M15="")),1,0) -> 0
A16: 46174 | B16: 0.71527778 | C16: Dr. Paulo Andrade | D16: Sala 2 | E16: Fábio Martins | F16: MediPlan | G16: Retorno | H16: Realizado | I16: Sem cobrança | L16: 20 | M16: 0 | N16: =IF(A16="","",MONTH(A16)) -> 6 | O16: =IF(A16="","",YEAR(A16)) -> 2026 | P16: =IF(A16="","",CHOOSE(WEEKDAY(A16,2),"Segunda","Terça","Quarta","Quinta","Sexta","Sábado","Domingo")) -> Segunda | Q16: =IF(B16="","",IF(B16<TIME(12,0,0),"Manhã",IF(B16<TIME(18,0,0),"Tarde","Noite"))) -> Tarde | R16: =IF(AND(H16="Realizado",L16<>"",A16<=Config!$B$9),L16/60,0) -> 0.33333333 | S16: =IF(G16="","",IFERROR(INDEX(Config!$K$5:$K$16,MATCH(G16,Config!$J$5:$J$16,0)),"")) -> 20 | T16: =IF(OR(G16="",F16=""),"",IFERROR(INDEX(Config!$M$5:$R$16,MATCH(G16,Config!$J$5:$J$16,0),MATCH(F16,Config!$H$5:$H$10,0)),"")) -> 0 | U16: =IF(AND(H16="Realizado",L16<>""),L16/60,0) -> 0.33333333 | V16: =IF(AND(H16="Realizado",OR(L16="",M16="")),1,0) -> 0
A17: 46174 | B17: 0.72916667 | C17: Dr. Paulo Andrade | D17: Sala 2 | E17: Leandro Ferreira | F17: Saúde Total | G17: Holter | H17: Realizado | I17: Convênio | L17: 20 | M17: 105 | N17: =IF(A17="","",MONTH(A17)) -> 6 | O17: =IF(A17="","",YEAR(A17)) -> 2026 | P17: =IF(A17="","",CHOOSE(WEEKDAY(A17,2),"Segunda","Terça","Quarta","Quinta","Sexta","Sábado","Domingo")) -> Segunda | Q17: =IF(B17="","",IF(B17<TIME(12,0,0),"Manhã",IF(B17<TIME(18,0,0),"Tarde","Noite"))) -> Tarde | R17: =IF(AND(H17="Realizado",L17<>"",A17<=Config!$B$9),L17/60,0) -> 0.33333333 | S17: =IF(G17="","",IFERROR(INDEX(Config!$K$5:$K$16,MATCH(G17,Config!$J$5:$J$16,0)),"")) -> 20 | T17: =IF(OR(G17="",F17=""),"",IFERROR(INDEX(Config!$M$5:$R$16,MATCH(G17,Config!$J$5:$J$16,0),MATCH(F17,Config!$H$5:$H$10,0)),"")) -> 105 | U17: =IF(AND(H17="Realizado",L17<>""),L17/60,0) -> 0.33333333 | V17: =IF(AND(H17="Realizado",OR(L17="",M17="")),1,0) -> 0
A18: 46175 | B18: 0.33333333 | C18: Dra. Carolina Mendes | D18: Sala 1 | E18: Ricardo Melo | F18: Saúde Total | G18: Retorno | H18: Realizado | I18: Sem cobrança | L18: 20 | M18: 0 | N18: =IF(A18="","",MONTH(A18)) -> 6 | O18: =IF(A18="","",YEAR(A18)) -> 2026 | P18: =IF(A18="","",CHOOSE(WEEKDAY(A18,2),"Segunda","Terça","Quarta","Quinta","Sexta","Sábado","Domingo")) -> Terça | Q18: =IF(B18="","",IF(B18<TIME(12,0,0),"Manhã",IF(B18<TIME(18,0,0),"Tarde","Noite"))) -> Manhã | R18: =IF(AND(H18="Realizado",L18<>"",A18<=Config!$B$9),L18/60,0) -> 0.33333333 | S18: =IF(G18="","",IFERROR(INDEX(Config!$K$5:$K$16,MATCH(G18,Config!$J$5:$J$16,0)),"")) -> 20 | T18: =IF(OR(G18="",F18=""),"",IFERROR(INDEX(Config!$M$5:$R$16,MATCH(G18,Config!$J$5:$J$16,0),MATCH(F18,Config!$H$5:$H$10,0)),"")) -> 0 | U18: =IF(AND(H18="Realizado",L18<>""),L18/60,0) -> 0.33333333 | V18: =IF(AND(H18="Realizado",OR(L18="",M18="")),1,0) -> 0
A19: 46175 | B19: 0.34722222 | C19: Dra. Carolina Mendes | D19: Sala 1 | E19: Sérgio Batista | F19: MediPlan | G19: Consulta | H19: Realizado | I19: Convênio | L19: 30 | M19: 100 | N19: =IF(A19="","",MONTH(A19)) -> 6 | O19: =IF(A19="","",YEAR(A19)) -> 2026 | P19: =IF(A19="","",CHOOSE(WEEKDAY(A19,2),"Segunda","Terça","Quarta","Quinta","Sexta","Sábado","Domingo")) -> Terça | Q19: =IF(B19="","",IF(B19<TIME(12,0,0),"Manhã",IF(B19<TIME(18,0,0),"Tarde","Noite"))) -> Manhã | R19: =IF(AND(H19="Realizado",L19<>"",A19<=Config!$B$9),L19/60,0) -> 0.5 | S19: =IF(G19="","",IFERROR(INDEX(Config!$K$5:$K$16,MATCH(G19,Config!$J$5:$J$16,0)),"")) -> 30 | T19: =IF(OR(G19="",F19=""),"",IFERROR(INDEX(Config!$M$5:$R$16,MATCH(G19,Config!$J$5:$J$16,0),MATCH(F19,Config!$H$5:$H$10,0)),"")) -> 100 | U19: =IF(AND(H19="Realizado",L19<>""),L19/60,0) -> 0.5 | V19: =IF(AND(H19="Realizado",OR(L19="",M19="")),1,0) -> 0
A20: 46175 | B20: 0.36805556 | C20: Dra. Carolina Mendes | D20: Sala 1 | E20: Otávio Nascimento | F20: Particular | G20: Consulta | H20: Realizado | I20: Cartão de crédito | L20: 30 | M20: 380 | N20: =IF(A20="","",MONTH(A20)) -> 6 | O20: =IF(A20="","",YEAR(A20)) -> 2026 | P20: =IF(A20="","",CHOOSE(WEEKDAY(A20,2),"Segunda","Terça","Quarta","Quinta","Sexta","Sábado","Domingo")) -> Terça | Q20: =IF(B20="","",IF(B20<TIME(12,0,0),"Manhã",IF(B20<TIME(18,0,0),"Tarde","Noite"))) -> Manhã | R20: =IF(AND(H20="Realizado",L20<>"",A20<=Config!$B$9),L20/60,0) -> 0.5 | S20: =IF(G20="","",IFERROR(INDEX(Config!$K$5:$K$16,MATCH(G20,Config!$J$5:$J$16,0)),"")) -> 30 | T20: =IF(OR(G20="",F20=""),"",IFERROR(INDEX(Config!$M$5:$R$16,MATCH(G20,Config!$J$5:$J$16,0),MATCH(F20,Config!$H$5:$H$10,0)),"")) -> 380 | U20: =IF(AND(H20="Realizado",L20<>""),L20/60,0) -> 0.5 | V20: =IF(AND(H20="Realizado",OR(L20="",M20="")),1,0) -> 0
A21: 46175 | B21: 0.38888889 | C21: Dra. Carolina Mendes | D21: Sala 1 | E21: Leandro Oliveira | F21: Particular | G21: Consulta | H21: Cancelado | L21: 30 | M21: 380 | N21: =IF(A21="","",MONTH(A21)) -> 6 | O21: =IF(A21="","",YEAR(A21)) -> 2026 | P21: =IF(A21="","",CHOOSE(WEEKDAY(A21,2),"Segunda","Terça","Quarta","Quinta","Sexta","Sábado","Domingo")) -> Terça | Q21: =IF(B21="","",IF(B21<TIME(12,0,0),"Manhã",IF(B21<TIME(18,0,0),"Tarde","Noite"))) -> Manhã | R21: =IF(AND(H21="Realizado",L21<>"",A21<=Config!$B$9),L21/60,0) -> 0 | S21: =IF(G21="","",IFERROR(INDEX(Config!$K$5:$K$16,MATCH(G21,Config!$J$5:$J$16,0)),"")) -> 30 | T21: =IF(OR(G21="",F21=""),"",IFERROR(INDEX(Config!$M$5:$R$16,MATCH(G21,Config!$J$5:$J$16,0),MATCH(F21,Config!$H$5:$H$10,0)),"")) -> 380 | U21: =IF(AND(H21="Realizado",L21<>""),L21/60,0) -> 0 | V21: =IF(AND(H21="Realizado",OR(L21="",M21="")),1,0) -> 0
A22: 46175 | B22: 0.40972222 | C22: Dra. Carolina Mendes | D22: Sala 1 | E22: Leandro Oliveira | F22: Particular | G22: Consulta | H22: Realizado | I22: Pix | L22: 30 | M22: 380 | N22: =IF(A22="","",MONTH(A22)) -> 6 | O22: =IF(A22="","",YEAR(A22)) -> 2026 | P22: =IF(A22="","",CHOOSE(WEEKDAY(A22,2),"Segunda","Terça","Quarta","Quinta","Sexta","Sábado","Domingo")) -> Terça | Q22: =IF(B22="","",IF(B22<TIME(12,0,0),"Manhã",IF(B22<TIME(18,0,0),"Tarde","Noite"))) -> Manhã | R22: =IF(AND(H22="Realizado",L22<>"",A22<=Config!$B$9),L22/60,0) -> 0.5 | S22: =IF(G22="","",IFERROR(INDEX(Config!$K$5:$K$16,MATCH(G22,Config!$J$5:$J$16,0)),"")) -> 30 | T22: =IF(OR(G22="",F22=""),"",IFERROR(INDEX(Config!$M$5:$R$16,MATCH(G22,Config!$J$5:$J$16,0),MATCH(F22,Config!$H$5:$H$10,0)),"")) -> 380 | U22: =IF(AND(H22="Realizado",L22<>""),L22/60,0) -> 0.5 | V22: =IF(AND(H22="Realizado",OR(L22="",M22="")),1,0) -> 0
A23: 46175 | B23: 0.43055556 | C23: Dra. Carolina Mendes | D23: Sala 1 | E23: Carlos Castro | F23: Saúde Total | G23: Consulta | H23: Realizado | I23: Convênio | L23: 30 | M23: 120 | N23: =IF(A23="","",MONTH(A23)) -> 6 | O23: =IF(A23="","",YEAR(A23)) -> 2026 | P23: =IF(A23="","",CHOOSE(WEEKDAY(A23,2),"Segunda","Terça","Quarta","Quinta","Sexta","Sábado","Domingo")) -> Terça | Q23: =IF(B23="","",IF(B23<TIME(12,0,0),"Manhã",IF(B23<TIME(18,0,0),"Tarde","Noite"))) -> Manhã | R23: =IF(AND(H23="Realizado",L23<>"",A23<=Config!$B$9),L23/60,0) -> 0.5 | S23: =IF(G23="","",IFERROR(INDEX(Config!$K$5:$K$16,MATCH(G23,Config!$J$5:$J$16,0)),"")) -> 30 | T23: =IF(OR(G23="",F23=""),"",IFERROR(INDEX(Config!$M$5:$R$16,MATCH(G23,Config!$J$5:$J$16,0),MATCH(F23,Config!$H$5:$H$10,0)),"")) -> 120 | U23: =IF(AND(H23="Realizado",L23<>""),L23/60,0) -> 0.5 | V23: =IF(AND(H23="Realizado",OR(L23="",M23="")),1,0) -> 0
A24: 46175 | B24: 0.45138889 | C24: Dra. Carolina Mendes | D24: Sala 1 | E24: Cláudia Costa | F24: Particular | G24: Consulta | H24: Realizado | I24: Pix | L24: 30 | M24: 380 | N24: =IF(A24="","",MONTH(A24)) -> 6 | O24: =IF(A24="","",YEAR(A24)) -> 2026 | P24: =IF(A24="","",CHOOSE(WEEKDAY(A24,2),"Segunda","Terça","Quarta","Quinta","Sexta","Sábado","Domingo")) -> Terça | Q24: =IF(B24="","",IF(B24<TIME(12,0,0),"Manhã",IF(B24<TIME(18,0,0),"Tarde","Noite"))) -> Manhã | R24: =IF(AND(H24="Realizado",L24<>"",A24<=Config!$B$9),L24/60,0) -> 0.5 | S24: =IF(G24="","",IFERROR(INDEX(Config!$K$5:$K$16,MATCH(G24,Config!$J$5:$J$16,0)),"")) -> 30 | T24: =IF(OR(G24="",F24=""),"",IFERROR(INDEX(Config!$M$5:$R$16,MATCH(G24,Config!$J$5:$J$16,0),MATCH(F24,Config!$H$5:$H$10,0)),"")) -> 380 | U24: =IF(AND(H24="Realizado",L24<>""),L24/60,0) -> 0.5 | V24: =IF(AND(H24="Realizado",OR(L24="",M24="")),1,0) -> 0
A25: 46175 | B25: 0.47222222 | C25: Dra. Carolina Mendes | D25: Sala 1 | E25: Lucas Xavier | F25: Saúde Total | G25: Consulta | H25: Realizado | I25: Convênio | L25: 30 | M25: 120 | N25: =IF(A25="","",MONTH(A25)) -> 6 | O25: =IF(A25="","",YEAR(A25)) -> 2026 | P25: =IF(A25="","",CHOOSE(WEEKDAY(A25,2),"Segunda","Terça","Quarta","Quinta","Sexta","Sábado","Domingo")) -> Terça | Q25: =IF(B25="","",IF(B25<TIME(12,0,0),"Manhã",IF(B25<TIME(18,0,0),"Tarde","Noite"))) -> Manhã | R25: =IF(AND(H25="Realizado",L25<>"",A25<=Config!$B$9),L25/60,0) -> 0.5 | S25: =IF(G25="","",IFERROR(INDEX(Config!$K$5:$K$16,MATCH(G25,Config!$J$5:$J$16,0)),"")) -> 30 | T25: =IF(OR(G25="",F25=""),"",IFERROR(INDEX(Config!$M$5:$R$16,MATCH(G25,Config!$J$5:$J$16,0),MATCH(F25,Config!$H$5:$H$10,0)),"")) -> 120 | U25: =IF(AND(H25="Realizado",L25<>""),L25/60,0) -> 0.5 | V25: =IF(AND(H25="Realizado",OR(L25="",M25="")),1,0) -> 0
A26: 46175 | B26: 0.58333333 | C26: Dra. Renata Sousa | D26: Sala 1 | E26: Rafael Nascimento | F26: Saúde Total | G26: Avaliação endócrina | H26: Realizado | I26: Convênio | L26: 40 | M26: 130 | N26: =IF(A26="","",MONTH(A26)) -> 6 | O26: =IF(A26="","",YEAR(A26)) -> 2026 | P26: =IF(A26="","",CHOOSE(WEEKDAY(A26,2),"Segunda","Terça","Quarta","Quinta","Sexta","Sábado","Domingo")) -> Terça | Q26: =IF(B26="","",IF(B26<TIME(12,0,0),"Manhã",IF(B26<TIME(18,0,0),"Tarde","Noite"))) -> Tarde | R26: =IF(AND(H26="Realizado",L26<>"",A26<=Config!$B$9),L26/60,0) -> 0.66666667 | S26: =IF(G26="","",IFERROR(INDEX(Config!$K$5:$K$16,MATCH(G26,Config!$J$5:$J$16,0)),"")) -> 40 | T26: =IF(OR(G26="",F26=""),"",IFERROR(INDEX(Config!$M$5:$R$16,MATCH(G26,Config!$J$5:$J$16,0),MATCH(F26,Config!$H$5:$H$10,0)),"")) -> 130 | U26: =IF(AND(H26="Realizado",L26<>""),L26/60,0) -> 0.66666667 | V26: =IF(AND(H26="Realizado",OR(L26="",M26="")),1,0) -> 0
A27: 46175 | B27: 0.58333333 | C27: Dr. Paulo Andrade | D27: Sala 2 | E27: Sérgio Teixeira | F27: MediPlan | G27: Retorno | H27: Realizado | I27: Sem cobrança | L27: 20 | M27: 0 | N27: =IF(A27="","",MONTH(A27)) -> 6 | O27: =IF(A27="","",YEAR(A27)) -> 2026 | P27: =IF(A27="","",CHOOSE(WEEKDAY(A27,2),"Segunda","Terça","Quarta","Quinta","Sexta","Sábado","Domingo")) -> Terça | Q27: =IF(B27="","",IF(B27<TIME(12,0,0),"Manhã",IF(B27<TIME(18,0,0),"Tarde","Noite"))) -> Tarde | R27: =IF(AND(H27="Realizado",L27<>"",A27<=Config!$B$9),L27/60,0) -> 0.33333333 | S27: =IF(G27="","",IFERROR(INDEX(Config!$K$5:$K$16,MATCH(G27,Config!$J$5:$J$16,0)),"")) -> 20 | T27: =IF(OR(G27="",F27=""),"",IFERROR(INDEX(Config!$M$5:$R$16,MATCH(G27,Config!$J$5:$J$16,0),MATCH(F27,Config!$H$5:$H$10,0)),"")) -> 0 | U27: =IF(AND(H27="Realizado",L27<>""),L27/60,0) -> 0.33333333 | V27: =IF(AND(H27="Realizado",OR(L27="",M27="")),1,0) -> 0
A28: 46175 | B28: 0.61111111 | C28: Dra. Renata Sousa | D28: Sala 1 | E28: Roberta Lima | F28: Particular | G28: Retorno | H28: Realizado | I28: Sem cobrança | L28: 20 | M28: 0 | N28: =IF(A28="","",MONTH(A28)) -> 6 | O28: =IF(A28="","",YEAR(A28)) -> 2026 | P28: =IF(A28="","",CHOOSE(WEEKDAY(A28,2),"Segunda","Terça","Quarta","Quinta","Sexta","Sábado","Domingo")) -> Terça | Q28: =IF(B28="","",IF(B28<TIME(12,0,0),"Manhã",IF(B28<TIME(18,0,0),"Tarde","Noite"))) -> Tarde | R28: =IF(AND(H28="Realizado",L28<>"",A28<=Config!$B$9),L28/60,0) -> 0.33333333 | S28: =IF(G28="","",IFERROR(INDEX(Config!$K$5:$K$16,MATCH(G28,Config!$J$5:$J$16,0)),"")) -> 20 | T28: =IF(OR(G28="",F28=""),"",IFERROR(INDEX(Config!$M$5:$R$16,MATCH(G28,Config!$J$5:$J$16,0),MATCH(F28,Config!$H$5:$H$10,0)),"")) -> 0 | U28: =IF(AND(H28="Realizado",L28<>""),L28/60,0) -> 0.33333333 | V28: =IF(AND(H28="Realizado",OR(L28="",M28="")),1,0) -> 0
A29: 46175 | B29: 0.625 | C29: Dra. Renata Sousa | D29: Sala 1 | E29: Beatriz Monteiro | F29: Particular | G29: Retorno | H29: Realizado | I29: Sem cobrança | L29: 20 | M29: 0 | N29: =IF(A29="","",MONTH(A29)) -> 6 | O29: =IF(A29="","",YEAR(A29)) -> 2026 | P29: =IF(A29="","",CHOOSE(WEEKDAY(A29,2),"Segunda","Terça","Quarta","Quinta","Sexta","Sábado","Domingo")) -> Terça | Q29: =IF(B29="","",IF(B29<TIME(12,0,0),"Manhã",IF(B29<TIME(18,0,0),"Tarde","Noite"))) -> Tarde | R29: =IF(AND(H29="Realizado",L29<>"",A29<=Config!$B$9),L29/60,0) -> 0.33333333 | S29: =IF(G29="","",IFERROR(INDEX(Config!$K$5:$K$16,MATCH(G29,Config!$J$5:$J$16,0)),"")) -> 20 | T29: =IF(OR(G29="",F29=""),"",IFERROR(INDEX(Config!$M$5:$R$16,MATCH(G29,Config!$J$5:$J$16,0),MATCH(F29,Config!$H$5:$H$10,0)),"")) -> 0 | U29: =IF(AND(H29="Realizado",L29<>""),L29/60,0) -> 0.33333333 | V29: =IF(AND(H29="Realizado",OR(L29="",M29="")),1,0) -> 0
A30: 46175 | B30: 0.63888889 | C30: Dra. Renata Sousa | D30: Sala 1 | E30: Eduardo Pereira | F30: Particular | G30: Avaliação endócrina | H30: Realizado | I30: Pix | L30: 40 | M30: 400 | N30: =IF(A30="","",MONTH(A30)) -> 6 | O30: =IF(A30="","",YEAR(A30)) -> 2026 | P30: =IF(A30="","",CHOOSE(WEEKDAY(A30,2),"Segunda","Terça","Quarta","Quinta","Sexta","Sábado","Domingo")) -> Terça | Q30: =IF(B30="","",IF(B30<TIME(12,0,0),"Manhã",IF(B30<TIME(18,0,0),"Tarde","Noite"))) -> Tarde | R30: =IF(AND(H30="Realizado",L30<>"",A30<=Config!$B$9),L30/60,0) -> 0.66666667 | S30: =IF(G30="","",IFERROR(INDEX(Config!$K$5:$K$16,MATCH(G30,Config!$J$5:$J$16,0)),"")) -> 40 | T30: =IF(OR(G30="",F30=""),"",IFERROR(INDEX(Config!$M$5:$R$16,MATCH(G30,Config!$J$5:$J$16,0),MATCH(F30,Config!$H$5:$H$10,0)),"")) -> 400 | U30: =IF(AND(H30="Realizado",L30<>""),L30/60,0) -> 0.66666667 | V30: =IF(AND(H30="Realizado",OR(L30="",M30="")),1,0) -> 0
A31: 46175 | B31: 0.63888889 | C31: Dr. Paulo Andrade | D31: Sala 2 | E31: Wagner Costa | F31: Particular | G31: Consulta | H31: Realizado | I31: A prazo | L31: 30 | M31: 380 | N31: =IF(A31="","",MONTH(A31)) -> 6 | O31: =IF(A31="","",YEAR(A31)) -> 2026 | P31: =IF(A31="","",CHOOSE(WEEKDAY(A31,2),"Segunda","Terça","Quarta","Quinta","Sexta","Sábado","Domingo")) -> Terça | Q31: =IF(B31="","",IF(B31<TIME(12,0,0),"Manhã",IF(B31<TIME(18,0,0),"Tarde","Noite"))) -> Tarde | R31: =IF(AND(H31="Realizado",L31<>"",A31<=Config!$B$9),L31/60,0) -> 0.5 | S31: =IF(G31="","",IFERROR(INDEX(Config!$K$5:$K$16,MATCH(G31,Config!$J$5:$J$16,0)),"")) -> 30 | T31: =IF(OR(G31="",F31=""),"",IFERROR(INDEX(Config!$M$5:$R$16,MATCH(G31,Config!$J$5:$J$16,0),MATCH(F31,Config!$H$5:$H$10,0)),"")) -> 380 | U31: =IF(AND(H31="Realizado",L31<>""),L31/60,0) -> 0.5 | V31: =IF(AND(H31="Realizado",OR(L31="",M31="")),1,0) -> 0
A32: 46175 | B32: 0.65972222 | C32: Dr. Paulo Andrade | D32: Sala 2 | E32: Fábio Correia | F32: Particular | G32: Retorno | H32: Realizado | I32: Sem cobrança | L32: 20 | M32: 0 | N32: =IF(A32="","",MONTH(A32)) -> 6 | O32: =IF(A32="","",YEAR(A32)) -> 2026 | P32: =IF(A32="","",CHOOSE(WEEKDAY(A32,2),"Segunda","Terça","Quarta","Quinta","Sexta","Sábado","Domingo")) -> Terça | Q32: =IF(B32="","",IF(B32<TIME(12,0,0),"Manhã",IF(B32<TIME(18,0,0),"Tarde","Noite"))) -> Tarde | R32: =IF(AND(H32="Realizado",L32<>"",A32<=Config!$B$9),L32/60,0) -> 0.33333333 | S32: =IF(G32="","",IFERROR(INDEX(Config!$K$5:$K$16,MATCH(G32,Config!$J$5:$J$16,0)),"")) -> 20 | T32: =IF(OR(G32="",F32=""),"",IFERROR(INDEX(Config!$M$5:$R$16,MATCH(G32,Config!$J$5:$J$16,0),MATCH(F32,Config!$H$5:$H$10,0)),"")) -> 0 | U32: =IF(AND(H32="Realizado",L32<>""),L32/60,0) -> 0.33333333 | V32: =IF(AND(H32="Realizado",OR(L32="",M32="")),1,0) -> 0
A33: 46175 | B33: 0.66666667 | C33: Dra. Renata Sousa | D33: Sala 1 | E33: Rafael Pereira | F33: Particular | G33: Avaliação endócrina | H33: Realizado | I33: Pix | L33: 40 | M33: 400 | N33: =IF(A33="","",MONTH(A33)) -> 6 | O33: =IF(A33="","",YEAR(A33)) -> 2026 | P33: =IF(A33="","",CHOOSE(WEEKDAY(A33,2),"Segunda","Terça","Quarta","Quinta","Sexta","Sábado","Domingo")) -> Terça | Q33: =IF(B33="","",IF(B33<TIME(12,0,0),"Manhã",IF(B33<TIME(18,0,0),"Tarde","Noite"))) -> Tarde | R33: =IF(AND(H33="Realizado",L33<>"",A33<=Config!$B$9),L33/60,0) -> 0.66666667 | S33: =IF(G33="","",IFERROR(INDEX(Config!$K$5:$K$16,MATCH(G33,Config!$J$5:$J$16,0)),"")) -> 40 | T33: =IF(OR(G33="",F33=""),"",IFERROR(INDEX(Config!$M$5:$R$16,MATCH(G33,Config!$J$5:$J$16,0),MATCH(F33,Config!$H$5:$H$10,0)),"")) -> 400 | U33: =IF(AND(H33="Realizado",L33<>""),L33/60,0) -> 0.66666667 | V33: =IF(AND(H33="Realizado",OR(L33="",M33="")),1,0) -> 0
... A35: 46175 | B35: 0.6875 | C35: Dr. Paulo Andrade | D35: Sala 2 | E35: Leandro Cardoso | F35: MediPlan | G35: Consulta | H35: Realizado | I35: Convênio | L35: 30 | M35: 100 | N35: =IF(A35="","",MONTH(A35)) -> 6 | O35: =IF(A35="","",YEAR(A35)) -> 2026 | P35: =IF(A35="","",CHOOSE(WEEKDAY(A35,2),"Segunda","Terça","Quarta","Quinta","Sexta","Sábado","Domingo")) -> Terça | Q35: =IF(B35="","",IF(B35<TIME(12,0,0),"Manhã",IF(B35<TIME(18,0,0),"Tarde","Noite"))) -> Tarde | R35: =IF(AND(H35="Realizado",L35<>"",A35<=Config!$B$9),L35/60,0) -> 0.5 | S35: =IF(G35="","",IFERROR(INDEX(Config!$K$5:$K$16,MATCH(G35,Config!$J$5:$J$16,0)),"")) -> 30 | T35: =IF(OR(G35="",F35=""),"",IFERROR(INDEX(Config!$M$5:$R$16,MATCH(G35,Config!$J$5:$J$16,0),MATCH(F35,Config!$H$5:$H$10,0)),"")) -> 100 | U35: =IF(AND(H35="Realizado",L35<>""),L35/60,0) -> 0.5 | V35: =IF(AND(H35="Realizado",OR(L35="",M35="")),1,0) -> 0
A36: 46175 | B36: 0.70833333 | C36: Dr. Paulo Andrade | D36: Sala 2 | E36: Elaine Cardoso | F36: Particular | G36: Teste ergométrico | H36: Realizado | I36: Cartão de crédito | J36: 2 | L36: 40 | M36: 450 | N36: =IF(A36="","",MONTH(A36)) -> 6 | O36: =IF(A36="","",YEAR(A36)) -> 2026 | P36: =IF(A36="","",CHOOSE(WEEKDAY(A36,2),"Segunda","Terça","Quarta","Quinta","Sexta","Sábado","Domingo")) -> Terça | Q36: =IF(B36="","",IF(B36<TIME(12,0,0),"Manhã",IF(B36<TIME(18,0,0),"Tarde","Noite"))) -> Tarde | R36: =IF(AND(H36="Realizado",L36<>"",A36<=Config!$B$9),L36/60,0) -> 0.66666667 | S36: =IF(G36="","",IFERROR(INDEX(Config!$K$5:$K$16,MATCH(G36,Config!$J$5:$J$16,0)),"")) -> 40 | T36: =IF(OR(G36="",F36=""),"",IFERROR(INDEX(Config!$M$5:$R$16,MATCH(G36,Config!$J$5:$J$16,0),MATCH(F36,Config!$H$5:$H$10,0)),"")) -> 450 | U36: =IF(AND(H36="Realizado",L36<>""),L36/60,0) -> 0.66666667 | V36: =IF(AND(H36="Realizado",OR(L36="",M36="")),1,0) -> 0
A37: 46175 | B37: 0.71527778 | C37: Dra. Renata Sousa | D37: Sala 1 | E37: Gisele Lopes | F37: Saúde Total | G37: Avaliação endócrina | H37: Realizado | I37: Convênio | L37: 40 | M37: 130 | N37: =IF(A37="","",MONTH(A37)) -> 6 | O37: =IF(A37="","",YEAR(A37)) -> 2026 | P37: =IF(A37="","",CHOOSE(WEEKDAY(A37,2),"Segunda","Terça","Quarta","Quinta","Sexta","Sábado","Domingo")) -> Terça | Q37: =IF(B37="","",IF(B37<TIME(12,0,0),"Manhã",IF(B37<TIME(18,0,0),"Tarde","Noite"))) -> Tarde | R37: =IF(AND(H37="Realizado",L37<>"",A37<=Config!$B$9),L37/60,0) -> 0.66666667 | S37: =IF(G37="","",IFERROR(INDEX(Config!$K$5:$K$16,MATCH(G37,Config!$J$5:$J$16,0)),"")) -> 40 | T37: =IF(OR(G37="",F37=""),"",IFERROR(INDEX(Config!$M$5:$R$16,MATCH(G37,Config!$J$5:$J$16,0),MATCH(F37,Config!$H$5:$H$10,0)),"")) -> 130 | U37: =IF(AND(H37="Realizado",L37<>""),L37/60,0) -> 0.66666667 | V37: =IF(AND(H37="Realizado",OR(L37="",M37="")),1,0) -> 0
A38: 46175 | B38: 0.73611111 | C38: Dr. Paulo Andrade | D38: Sala 2 | E38: Camila Batista | F38: MediPlan | G38: ECG | H38: Realizado | I38: Convênio | L38: 20 | M38: 35 | N38: =IF(A38="","",MONTH(A38)) -> 6 | O38: =IF(A38="","",YEAR(A38)) -> 2026 | P38: =IF(A38="","",CHOOSE(WEEKDAY(A38,2),"Segunda","Terça","Quarta","Quinta","Sexta","Sábado","Domingo")) -> Terça | Q38: =IF(B38="","",IF(B38<TIME(12,0,0),"Manhã",IF(B38<TIME(18,0,0),"Tarde","Noite"))) -> Tarde | R38: =IF(AND(H38="Realizado",L38<>"",A38<=Config!$B$9),L38/60,0) -> 0.33333333 | S38: =IF(G38="","",IFERROR(INDEX(Config!$K$5:$K$16,MATCH(G38,Config!$J$5:$J$16,0)),"")) -> 20 | T38: =IF(OR(G38="",F38=""),"",IFERROR(INDEX(Config!$M$5:$R$16,MATCH(G38,Config!$J$5:$J$16,0),MATCH(F38,Config!$H$5:$H$10,0)),"")) -> 35 | U38: =IF(AND(H38="Realizado",L38<>""),L38/60,0) -> 0.33333333 | V38: =IF(AND(H38="Realizado",OR(L38="",M38="")),1,0) -> 0
A39: 46176 | B39: 0.58333333 | C39: Dra. Carolina Mendes | D39: Sala 1 | E39: Leandro Gomes | F39: Saúde Total | G39: Consulta | H39: Falta | L39: 30 | M39: 120 | N39: =IF(A39="","",MONTH(A39)) -> 6 | O39: =IF(A39="","",YEAR(A39)) -> 2026 | P39: =IF(A39="","",CHOOSE(WEEKDAY(A39,2),"Segunda","Terça","Quarta","Quinta","Sexta","Sábado","Domingo")) -> Quarta | Q39: =IF(B39="","",IF(B39<TIME(12,0,0),"Manhã",IF(B39<TIME(18,0,0),"Tarde","Noite"))) -> Tarde | R39: =IF(AND(H39="Realizado",L39<>"",A39<=Config!$B$9),L39/60,0) -> 0 | S39: =IF(G39="","",IFERROR(INDEX(Config!$K$5:$K$16,MATCH(G39,Config!$J$5:$J$16,0)),"")) -> 30 | T39: =IF(OR(G39="",F39=""),"",IFERROR(INDEX(Config!$M$5:$R$16,MATCH(G39,Config!$J$5:$J$16,0),MATCH(F39,Config!$H$5:$H$10,0)),"")) -> 120 | U39: =IF(AND(H39="Realizado",L39<>""),L39/60,0) -> 0 | V39: =IF(AND(H39="Realizado",OR(L39="",M39="")),1,0) -> 0
A40: 46176 | B40: 0.60416667 | C40: Dra. Carolina Mendes | D40: Sala 1 | E40: Fernanda Freitas | F40: Particular | G40: Retorno | H40: Realizado | I40: Sem cobrança | L40: 20 | M40: 0 | N40: =IF(A40="","",MONTH(A40)) -> 6 | O40: =IF(A40="","",YEAR(A40)) -> 2026 | P40: =IF(A40="","",CHOOSE(WEEKDAY(A40,2),"Segunda","Terça","Quarta","Quinta","Sexta","Sábado","Domingo")) -> Quarta | Q40: =IF(B40="","",IF(B40<TIME(12,0,0),"Manhã",IF(B40<TIME(18,0,0),"Tarde","Noite"))) -> Tarde | R40: =IF(AND(H40="Realizado",L40<>"",A40<=Config!$B$9),L40/60,0) -> 0.33333333 | S40: =IF(G40="","",IFERROR(INDEX(Config!$K$5:$K$16,MATCH(G40,Config!$J$5:$J$16,0)),"")) -> 20 | T40: =IF(OR(G40="",F40=""),"",IFERROR(INDEX(Config!$M$5:$R$16,MATCH(G40,Config!$J$5:$J$16,0),MATCH(F40,Config!$H$5:$H$10,0)),"")) -> 0 | U40: =IF(AND(H40="Realizado",L40<>""),L40/60,0) -> 0.33333333 | V40: =IF(AND(H40="Realizado",OR(L40="",M40="")),1,0) -> 0
A41: 46176 | B41: 0.61805556 | C41: Dra. Carolina Mendes | D41: Sala 1 | E41: Ana Costa | F41: Particular | G41: Consulta | H41: Realizado | I41: A prazo | L41: 30 | M41: 380 | N41: =IF(A41="","",MONTH(A41)) -> 6 | O41: =IF(A41="","",YEAR(A41)) -> 2026 | P41: =IF(A41="","",CHOOSE(WEEKDAY(A41,2),"Segunda","Terça","Quarta","Quinta","Sexta","Sábado","Domingo")) -> Quarta | Q41: =IF(B41="","",IF(B41<TIME(12,0,0),"Manhã",IF(B41<TIME(18,0,0),"Tarde","Noite"))) -> Tarde | R41: =IF(AND(H41="Realizado",L41<>"",A41<=Config!$B$9),L41/60,0) -> 0.5 | S41: =IF(G41="","",IFERROR(INDEX(Config!$K$5:$K$16,MATCH(G41,Config!$J$5:$J$16,0)),"")) -> 30 | T41: =IF(OR(G41="",F41=""),"",IFERROR(INDEX(Config!$M$5:$R$16,MATCH(G41,Config!$J$5:$J$16,0),MATCH(F41,Config!$H$5:$H$10,0)),"")) -> 380 | U41: =IF(AND(H41="Realizado",L41<>""),L41/60,0) -> 0.5 | V41: =IF(AND(H41="Realizado",OR(L41="",M41="")),1,0) -> 0
A42: 46176 | B42: 0.65972222 | C42: Dra. Carolina Mendes | D42: Sala 1 | E42: Priscila Carvalho | F42: Vida Care | G42: Consulta | H42: Realizado | I42: Convênio | L42: 30 | M42: 90 | N42: =IF(A42="","",MONTH(A42)) -> 6 | O42: =IF(A42="","",YEAR(A42)) -> 2026 | P42: =IF(A42="","",CHOOSE(WEEKDAY(A42,2),"Segunda","Terça","Quarta","Quinta","Sexta","Sábado","Domingo")) -> Quarta | Q42: =IF(B42="","",IF(B42<TIME(12,0,0),"Manhã",IF(B42<TIME(18,0,0),"Tarde","Noite"))) -> Tarde | R42: =IF(AND(H42="Realizado",L42<>"",A42<=Config!$B$9),L42/60,0) -> 0.5 | S42: =IF(G42="","",IFERROR(INDEX(Config!$K$5:$K$16,MATCH(G42,Config!$J$5:$J$16,0)),"")) -> 30 | T42: =IF(OR(G42="",F42=""),"",IFERROR(INDEX(Config!$M$5:$R$16,MATCH(G42,Config!$J$5:$J$16,0),MATCH(F42,Config!$H$5:$H$10,0)),"")) -> 90 | U42: =IF(AND(H42="Realizado",L42<>""),L42/60,0) -> 0.5 | V42: =IF(AND(H42="Realizado",OR(L42="",M42="")),1,0) -> 0
A43: 46176 | B43: 0.68055556 | C43: Dra. Carolina Mendes | D43: Sala 1 | E43: Lucas Lopes | F43: Particular | G43: Consulta | H43: Realizado | I43: Cartão de crédito | L43: 30 | M43: 380 | N43: =IF(A43="","",MONTH(A43)) -> 6 | O43: =IF(A43="","",YEAR(A43)) -> 2026 | P43: =IF(A43="","",CHOOSE(WEEKDAY(A43,2),"Segunda","Terça","Quarta","Quinta","Sexta","Sábado","Domingo")) -> Quarta | Q43: =IF(B43="","",IF(B43<TIME(12,0,0),"Manhã",IF(B43<TIME(18,0,0),"Tarde","Noite"))) -> Tarde | R43: =IF(AND(H43="Realizado",L43<>"",A43<=Config!$B$9),L43/60,0) -> 0.5 | S43: =IF(G43="","",IFERROR(INDEX(Config!$K$5:$K$16,MATCH(G43,Config!$J$5:$J$16,0)),"")) -> 30 | T43: =IF(OR(G43="",F43=""),"",IFERROR(INDEX(Config!$M$5:$R$16,MATCH(G43,Config!$J$5:$J$16,0),MATCH(F43,Config!$H$5:$H$10,0)),"")) -> 380 | U43: =IF(AND(H43="Realizado",L43<>""),L43/60,0) -> 0.5 | V43: =IF(AND(H43="Realizado",OR(L43="",M43="")),1,0) -> 0
A44: 46176 | B44: 0.70138889 | C44: Dra. Carolina Mendes | D44: Sala 1 | E44: Helena Moreira | F44: Particular | G44: Consulta | H44: Realizado | I44: Pix | L44: 30 | M44: 380 | N44: =IF(A44="","",MONTH(A44)) -> 6 | O44: =IF(A44="","",YEAR(A44)) -> 2026 | P44: =IF(A44="","",CHOOSE(WEEKDAY(A44,2),"Segunda","Terça","Quarta","Quinta","Sexta","Sábado","Domingo")) -> Quarta | Q44: =IF(B44="","",IF(B44<TIME(12,0,0),"Manhã",IF(B44<TIME(18,0,0),"Tarde","Noite"))) -> Tarde | R44: =IF(AND(H44="Realizado",L44<>"",A44<=Config!$B$9),L44/60,0) -> 0.5 | S44: =IF(G44="","",IFERROR(INDEX(Config!$K$5:$K$16,MATCH(G44,Config!$J$5:$J$16,0)),"")) -> 30 | T44: =IF(OR(G44="",F44=""),"",IFERROR(INDEX(Config!$M$5:$R$16,MATCH(G44,Config!$J$5:$J$16,0),MATCH(F44,Config!$H$5:$H$10,0)),"")) -> 380 | U44: =IF(AND(H44="Realizado",L44<>""),L44/60,0) -> 0.5 | V44: =IF(AND(H44="Realizado",OR(L44="",M44="")),1,0) -> 0
A45: 46176 | B45: 0.72222222 | C45: Dra. Carolina Mendes | D45: Sala 1 | E45: Mônica Batista | F45: MediPlan | G45: Consulta | H45: Falta | L45: 30 | M45: 100 | N45: =IF(A45="","",MONTH(A45)) -> 6 | O45: =IF(A45="","",YEAR(A45)) -> 2026 | P45: =IF(A45="","",CHOOSE(WEEKDAY(A45,2),"Segunda","Terça","Quarta","Quinta","Sexta","Sábado","Domingo")) -> Quarta | Q45: =IF(B45="","",IF(B45<TIME(12,0,0),"Manhã",IF(B45<TIME(18,0,0),"Tarde","Noite"))) -> Tarde | R45: =IF(AND(H45="Realizado",L45<>"",A45<=Config!$B$9),L45/60,0) -> 0 | S45: =IF(G45="","",IFERROR(INDEX(Config!$K$5:$K$16,MATCH(G45,Config!$J$5:$J$16,0)),"")) -> 30 | T45: =IF(OR(G45="",F45=""),"",IFERROR(INDEX(Config!$M$5:$R$16,MATCH(G45,Config!$J$5:$J$16,0),MATCH(F45,Config!$H$5:$H$10,0)),"")) -> 100 | U45: =IF(AND(H45="Realizado",L45<>""),L45/60,0) -> 0 | V45: =IF(AND(H45="Realizado",OR(L45="",M45="")),1,0) -> 0
A46: 46178 | B46: 0.33333333 | C46: Dr. Paulo Andrade | D46: Sala 2 | E46: Priscila Castro | F46: Saúde Total | G46: ECG | H46: Realizado | I46: Convênio | L46: 20 | M46: 40 | N46: =IF(A46="","",MONTH(A46)) -> 6 | O46: =IF(A46="","",YEAR(A46)) -> 2026 | P46: =IF(A46="","",CHOOSE(WEEKDAY(A46,2),"Segunda","Terça","Quarta","Quinta","Sexta","Sábado","Domingo")) -> Sexta | Q46: =IF(B46="","",IF(B46<TIME(12,0,0),"Manhã",IF(B46<TIME(18,0,0),"Tarde","Noite"))) -> Manhã | R46: =IF(AND(H46="Realizado",L46<>"",A46<=Config!$B$9),L46/60,0) -> 0.33333333 | S46: =IF(G46="","",IFERROR(INDEX(Config!$K$5:$K$16,MATCH(G46,Config!$J$5:$J$16,0)),"")) -> 20 | T46: =IF(OR(G46="",F46=""),"",IFERROR(INDEX(Config!$M$5:$R$16,MATCH(G46,Config!$J$5:$J$16,0),MATCH(F46,Config!$H$5:$H$10,0)),"")) -> 40 | U46: =IF(AND(H46="Realizado",L46<>""),L46/60,0) -> 0.33333333 | V46: =IF(AND(H46="Realizado",OR(L46="",M46="")),1,0) -> 0
A47: 46178 | B47: 0.34722222 | C47: Dr. Paulo Andrade | D47: Sala 2 | E47: Carlos Fernandes | F47: Particular | G47: ECG | H47: Realizado | I47: Dinheiro | L47: 20 | M47: 130 | N47: =IF(A47="","",MONTH(A47)) -> 6 | O47: =IF(A47="","",YEAR(A47)) -> 2026 | P47: =IF(A47="","",CHOOSE(WEEKDAY(A47,2),"Segunda","Terça","Quarta","Quinta","Sexta","Sábado","Domingo")) -> Sexta | Q47: =IF(B47="","",IF(B47<TIME(12,0,0),"Manhã",IF(B47<TIME(18,0,0),"Tarde","Noite"))) -> Manhã | R47: =IF(AND(H47="Realizado",L47<>"",A47<=Config!$B$9),L47/60,0) -> 0.33333333 | S47: =IF(G47="","",IFERROR(INDEX(Config!$K$5:$K$16,MATCH(G47,Config!$J$5:$J$16,0)),"")) -> 20 | T47: =IF(OR(G47="",F47=""),"",IFERROR(INDEX(Config!$M$5:$R$16,MATCH(G47,Config!$J$5:$J$16,0),MATCH(F47,Config!$H$5:$H$10,0)),"")) -> 130 | U47: =IF(AND(H47="Realizado",L47<>""),L47/60,0) -> 0.33333333 | V47: =IF(AND(H47="Realizado",OR(L47="",M47="")),1,0) -> 0
A48: 46178 | B48: 0.38194444 | C48: Dr. Paulo Andrade | D48: Sala 2 | E48: Priscila Pinto | F48: Saúde Total | G48: Consulta | H48: Falta | L48: 30 | M48: 120 | N48: =IF(A48="","",MONTH(A48)) -> 6 | O48: =IF(A48="","",YEAR(A48)) -> 2026 | P48: =IF(A48="","",CHOOSE(WEEKDAY(A48,2),"Segunda","Terça","Quarta","Quinta","Sexta","Sábado","Domingo")) -> Sexta | Q48: =IF(B48="","",IF(B48<TIME(12,0,0),"Manhã",IF(B48<TIME(18,0,0),"Tarde","Noite"))) -> Manhã | R48: =IF(AND(H48="Realizado",L48<>"",A48<=Config!$B$9),L48/60,0) -> 0 | S48: =IF(G48="","",IFERROR(INDEX(Config!$K$5:$K$16,MATCH(G48,Config!$J$5:$J$16,0)),"")) -> 30 | T48: =IF(OR(G48="",F48=""),"",IFERROR(INDEX(Config!$M$5:$R$16,MATCH(G48,Config!$J$5:$J$16,0),MATCH(F48,Config!$H$5:$H$10,0)),"")) -> 120 | U48: =IF(AND(H48="Realizado",L48<>""),L48/60,0) -> 0 | V48: =IF(AND(H48="Realizado",OR(L48="",M48="")),1,0) -> 0
A49: 46178 | B49: 0.46527778 | C49: Dr. Paulo Andrade | D49: Sala 2 | E49: Simone Monteiro | F49: Vida Care | G49: Holter | H49: Realizado | I49: Convênio | L49: 20 | M49: 85 | N49: =IF(A49="","",MONTH(A49)) -> 6 | O49: =IF(A49="","",YEAR(A49)) -> 2026 | P49: =IF(A49="","",CHOOSE(WEEKDAY(A49,2),"Segunda","Terça","Quarta","Quinta","Sexta","Sábado","Domingo")) -> Sexta | Q49: =IF(B49="","",IF(B49<TIME(12,0,0),"Manhã",IF(B49<TIME(18,0,0),"Tarde","Noite"))) -> Manhã | R49: =IF(AND(H49="Realizado",L49<>"",A49<=Config!$B$9),L49/60,0) -> 0.33333333 | S49: =IF(G49="","",IFERROR(INDEX(Config!$K$5:$K$16,MATCH(G49,Config!$J$5:$J$16,0)),"")) -> 20 | T49: =IF(OR(G49="",F49=""),"",IFERROR(INDEX(Config!$M$5:$R$16,MATCH(G49,Config!$J$5:$J$16,0),MATCH(F49,Config!$H$5:$H$10,0)),"")) -> 85 | U49: =IF(AND(H49="Realizado",L49<>""),L49/60,0) -> 0.33333333 | V49: =IF(AND(H49="Realizado",OR(L49="",M49="")),1,0) -> 0
A50: 46178 | B50: 0.47916667 | C50: Dr. Paulo Andrade | D50: Sala 2 | E50: Tatiana Gonçalves | F50: Saúde Total | G50: Consulta | H50: Realizado | I50: Convênio | L50: 30 | M50: 120 | N50: =IF(A50="","",MONTH(A50)) -> 6 | O50: =IF(A50="","",YEAR(A50)) -> 2026 | P50: =IF(A50="","",CHOOSE(WEEKDAY(A50,2),"Segunda","Terça","Quarta","Quinta","Sexta","Sábado","Domingo")) -> Sexta | Q50: =IF(B50="","",IF(B50<TIME(12,0,0),"Manhã",IF(B50<TIME(18,0,0),"Tarde","Noite"))) -> Manhã | R50: =IF(AND(H50="Realizado",L50<>"",A50<=Config!$B$9),L50/60,0) -> 0.5 | S50: =IF(G50="","",IFERROR(INDEX(Config!$K$5:$K$16,MATCH(G50,Config!$J$5:$J$16,0)),"")) -> 30 | T50: =IF(OR(G50="",F50=""),"",IFERROR(INDEX(Config!$M$5:$R$16,MATCH(G50,Config!$J$5:$J$16,0),MATCH(F50,Config!$H$5:$H$10,0)),"")) -> 120 | U50: =IF(AND(H50="Realizado",L50<>""),L50/60,0) -> 0.5 | V50: =IF(AND(H50="Realizado",OR(L50="",M50="")),1,0) -> 0
A51: 46181 | B51: 0.33333333 | C51: Dra. Carolina Mendes | D51: Sala 1 | E51: Gisele Xavier | F51: Particular | G51: Retorno | H51: Realizado | I51: Sem cobrança | L51: 20 | M51: 0 | N51: =IF(A51="","",MONTH(A51)) -> 6 | O51: =IF(A51="","",YEAR(A51)) -> 2026 | P51: =IF(A51="","",CHOOSE(WEEKDAY(A51,2),"Segunda","Terça","Quarta","Quinta","Sexta","Sábado","Domingo")) -> Segunda | Q51: =IF(B51="","",IF(B51<TIME(12,0,0),"Manhã",IF(B51<TIME(18,0,0),"Tarde","Noite"))) -> Manhã | R51: =IF(AND(H51="Realizado",L51<>"",A51<=Config!$B$9),L51/60,0) -> 0.33333333 | S51: =IF(G51="","",IFERROR(INDEX(Config!$K$5:$K$16,MATCH(G51,Config!$J$5:$J$16,0)),"")) -> 20 | T51: =IF(OR(G51="",F51=""),"",IFERROR(INDEX(Config!$M$5:$R$16,MATCH(G51,Config!$J$5:$J$16,0),MATCH(F51,Config!$H$5:$H$10,0)),"")) -> 0 | U51: =IF(AND(H51="Realizado",L51<>""),L51/60,0) -> 0.33333333 | V51: =IF(AND(H51="Realizado",OR(L51="",M51="")),1,0) -> 0
A52: 46181 | B52: 0.34722222 | C52: Dra. Carolina Mendes | D52: Sala 1 | E52: Juliana Silva | F52: Vida Care | G52: Retorno | H52: Realizado | I52: Sem cobrança | L52: 20 | M52: 0 | N52: =IF(A52="","",MONTH(A52)) -> 6 | O52: =IF(A52="","",YEAR(A52)) -> 2026 | P52: =IF(A52="","",CHOOSE(WEEKDAY(A52,2),"Segunda","Terça","Quarta","Quinta","Sexta","Sábado","Domingo")) -> Segunda | Q52: =IF(B52="","",IF(B52<TIME(12,0,0),"Manhã",IF(B52<TIME(18,0,0),"Tarde","Noite"))) -> Manhã | R52: =IF(AND(H52="Realizado",L52<>"",A52<=Config!$B$9),L52/60,0) -> 0.33333333 | S52: =IF(G52="","",IFERROR(INDEX(Config!$K$5:$K$16,MATCH(G52,Config!$J$5:$J$16,0)),"")) -> 20 | T52: =IF(OR(G52="",F52=""),"",IFERROR(INDEX(Config!$M$5:$R$16,MATCH(G52,Config!$J$5:$J$16,0),MATCH(F52,Config!$H$5:$H$10,0)),"")) -> 0 | U52: =IF(AND(H52="Realizado",L52<>""),L52/60,0) -> 0.33333333 | V52: =IF(AND(H52="Realizado",OR(L52="",M52="")),1,0) -> 0
A53: 46181 | B53: 0.38194444 | C53: Dra. Carolina Mendes | D53: Sala 1 | E53: Rodrigo Gomes | F53: Vida Care | G53: Retorno | H53: Realizado | I53: Sem cobrança | L53: 20 | M53: 0 | N53: =IF(A53="","",MONTH(A53)) -> 6 | O53: =IF(A53="","",YEAR(A53)) -> 2026 | P53: =IF(A53="","",CHOOSE(WEEKDAY(A53,2),"Segunda","Terça","Quarta","Quinta","Sexta","Sábado","Domingo")) -> Segunda | Q53: =IF(B53="","",IF(B53<TIME(12,0,0),"Manhã",IF(B53<TIME(18,0,0),"Tarde","Noite"))) -> Manhã | R53: =IF(AND(H53="Realizado",L53<>"",A53<=Config!$B$9),L53/60,0) -> 0.33333333 | S53: =IF(G53="","",IFERROR(INDEX(Config!$K$5:$K$16,MATCH(G53,Config!$J$5:$J$16,0)),"")) -> 20 | T53: =IF(OR(G53="",F53=""),"",IFERROR(INDEX(Config!$M$5:$R$16,MATCH(G53,Config!$J$5:$J$16,0),MATCH(F53,Config!$H$5:$H$10,0)),"")) -> 0 | U53: =IF(AND(H53="Realizado",L53<>""),L53/60,0) -> 0.33333333 | V53: =IF(AND(H53="Realizado",OR(L53="",M53="")),1,0) -> 0
A54: 46181 | B54: 0.39583333 | C54: Dra. Carolina Mendes | D54: Sala 1 | E54: Mônica Martins | F54: Particular | G54: Consulta | H54: Realizado | I54: Cartão de débito | L54: 30 | M54: 380 | N54: =IF(A54="","",MONTH(A54)) -> 6 | O54: =IF(A54="","",YEAR(A54)) -> 2026 | P54: =IF(A54="","",CHOOSE(WEEKDAY(A54,2),"Segunda","Terça","Quarta","Quinta","Sexta","Sábado","Domingo")) -> Segunda | Q54: =IF(B54="","",IF(B54<TIME(12,0,0),"Manhã",IF(B54<TIME(18,0,0),"Tarde","Noite"))) -> Manhã | R54: =IF(AND(H54="Realizado",L54<>"",A54<=Config!$B$9),L54/60,0) -> 0.5 | S54: =IF(G54="","",IFERROR(INDEX(Config!$K$5:$K$16,MATCH(G54,Config!$J$5:$J$16,0)),"")) -> 30 | T54: =IF(OR(G54="",F54=""),"",IFERROR(INDEX(Config!$M$5:$R$16,MATCH(G54,Config!$J$5:$J$16,0),MATCH(F54,Config!$H$5:$H$10,0)),"")) -> 380 | U54: =IF(AND(H54="Realizado",L54<>""),L54/60,0) -> 0.5 | V54: =IF(AND(H54="Realizado",OR(L54="",M54="")),1,0) -> 0
A55: 46181 | B55: 0.41666667 | C55: Dra. Carolina Mendes | D55: Sala 1 | E55: Eduardo Nunes | F55: MediPlan | G55: Consulta | H55: Realizado | I55: Convênio | L55: 30 | M55: 100 | N55: =IF(A55="","",MONTH(A55)) -> 6 | O55: =IF(A55="","",YEAR(A55)) -> 2026 | P55: =IF(A55="","",CHOOSE(WEEKDAY(A55,2),"Segunda","Terça","Quarta","Quinta","Sexta","Sábado","Domingo")) -> Segunda | Q55: =IF(B55="","",IF(B55<TIME(12,0,0),"Manhã",IF(B55<TIME(18,0,0),"Tarde","Noite"))) -> Manhã | R55: =IF(AND(H55="Realizado",L55<>"",A55<=Config!$B$9),L55/60,0) -> 0.5 | S55: =IF(G55="","",IFERROR(INDEX(Config!$K$5:$K$16,MATCH(G55,Config!$J$5:$J$16,0)),"")) -> 30 | T55: =IF(OR(G55="",F55=""),"",IFERROR(INDEX(Config!$M$5:$R$16,MATCH(G55,Config!$J$5:$J$16,0),MATCH(F55,Config!$H$5:$H$10,0)),"")) -> 100 | U55: =IF(AND(H55="Realizado",L55<>""),L55/60,0) -> 0.5 | V55: =IF(AND(H55="Realizado",OR(L55="",M55="")),1,0) -> 0
A56: 46181 | B56: 0.4375 | C56: Dra. Carolina Mendes | D56: Sala 1 | E56: Priscila Castro | F56: Saúde Total | G56: Consulta | H56: Realizado | I56: Convênio | L56: 30 | M56: 120 | N56: =IF(A56="","",MONTH(A56)) -> 6 | O56: =IF(A56="","",YEAR(A56)) -> 2026 | P56: =IF(A56="","",CHOOSE(WEEKDAY(A56,2),"Segunda","Terça","Quarta","Quinta","Sexta","Sábado","Domingo")) -> Segunda | Q56: =IF(B56="","",IF(B56<TIME(12,0,0),"Manhã",IF(B56<TIME(18,0,0),"Tarde","Noite"))) -> Manhã | R56: =IF(AND(H56="Realizado",L56<>"",A56<=Config!$B$9),L56/60,0) -> 0.5 | S56: =IF(G56="","",IFERROR(INDEX(Config!$K$5:$K$16,MATCH(G56,Config!$J$5:$J$16,0)),"")) -> 30 | T56: =IF(OR(G56="",F56=""),"",IFERROR(INDEX(Config!$M$5:$R$16,MATCH(G56,Config!$J$5:$J$16,0),MATCH(F56,Config!$H$5:$H$10,0)),"")) -> 120 | U56: =IF(AND(H56="Realizado",L56<>""),L56/60,0) -> 0.5 | V56: =IF(AND(H56="Realizado",OR(L56="",M56="")),1,0) -> 0
A57: 46181 | B57: 0.45833333 | C57: Dra. Carolina Mendes | D57: Sala 1 | E57: Tatiana Cunha | F57: Saúde Total | G57: Consulta | H57: Realizado | I57: Convênio | L57: 30 | M57: 120 | N57: =IF(A57="","",MONTH(A57)) -> 6 | O57: =IF(A57="","",YEAR(A57)) -> 2026 | P57: =IF(A57="","",CHOOSE(WEEKDAY(A57,2),"Segunda","Terça","Quarta","Quinta","Sexta","Sábado","Domingo")) -> Segunda | Q57: =IF(B57="","",IF(B57<TIME(12,0,0),"Manhã",IF(B57<TIME(18,0,0),"Tarde","Noite"))) -> Manhã | R57: =IF(AND(H57="Realizado",L57<>"",A57<=Config!$B$9),L57/60,0) -> 0.5 | S57: =IF(G57="","",IFERROR(INDEX(Config!$K$5:$K$16,MATCH(G57,Config!$J$5:$J$16,0)),"")) -> 30 | T57: =IF(OR(G57="",F57=""),"",IFERROR(INDEX(Config!$M$5:$R$16,MATCH(G57,Config!$J$5:$J$16,0),MATCH(F57,Config!$H$5:$H$10,0)),"")) -> 120 | U57: =IF(AND(H57="Realizado",L57<>""),L57/60,0) -> 0.5 | V57: =IF(AND(H57="Realizado",OR(L57="",M57="")),1,0) -> 0
A58: 46181 | B58: 0.47916667 | C58: Dra. Carolina Mendes | D58: Sala 1 | E58: Mariana Nascimento | F58: Particular | G58: Consulta | H58: Realizado | I58: Pix | L58: 30 | M58: 380 | N58: =IF(A58="","",MONTH(A58)) -> 6 | O58: =IF(A58="","",YEAR(A58)) -> 2026 | P58: =IF(A58="","",CHOOSE(WEEKDAY(A58,2),"Segunda","Terça","Quarta","Quinta","Sexta","Sábado","Domingo")) -> Segunda | Q58: =IF(B58="","",IF(B58<TIME(12,0,0),"Manhã",IF(B58<TIME(18,0,0),"Tarde","Noite"))) -> Manhã | R58: =IF(AND(H58="Realizado",L58<>"",A58<=Config!$B$9),L58/60,0) -> 0.5 | S58: =IF(G58="","",IFERROR(INDEX(Config!$K$5:$K$16,MATCH(G58,Config!$J$5:$J$16,0)),"")) -> 30 | T58: =IF(OR(G58="",F58=""),"",IFERROR(INDEX(Config!$M$5:$R$16,MATCH(G58,Config!$J$5:$J$16,0),MATCH(F58,Config!$H$5:$H$10,0)),"")) -> 380 | U58: =IF(AND(H58="Realizado",L58<>""),L58/60,0) -> 0.5 | V58: =IF(AND(H58="Realizado",OR(L58="",M58="")),1,0) -> 0
A59: 46181 | B59: 0.58333333 | C59: Dr. Paulo Andrade | D59: Sala 2 | E59: Priscila Nunes | F59: MediPlan | G59: Teste ergométrico | H59: Realizado | I59: Convênio | L59: 40 | M59: 125 | N59: =IF(A59="","",MONTH(A59)) -> 6 | O59: =IF(A59="","",YEAR(A59)) -> 2026 | P59: =IF(A59="","",CHOOSE(WEEKDAY(A59,2),"Segunda","Terça","Quarta","Quinta","Sexta","Sábado","Domingo")) -> Segunda | Q59: =IF(B59="","",IF(B59<TIME(12,0,0),"Manhã",IF(B59<TIME(18,0,0),"Tarde","Noite"))) -> Tarde | R59: =IF(AND(H59="Realizado",L59<>"",A59<=Config!$B$9),L59/60,0) -> 0.66666667 | S59: =IF(G59="","",IFERROR(INDEX(Config!$K$5:$K$16,MATCH(G59,Config!$J$5:$J$16,0)),"")) -> 40 | T59: =IF(OR(G59="",F59=""),"",IFERROR(INDEX(Config!$M$5:$R$16,MATCH(G59,Config!$J$5:$J$16,0),MATCH(F59,Config!$H$5:$H$10,0)),"")) -> 125 | U59: =IF(AND(H59="Realizado",L59<>""),L59/60,0) -> 0.66666667 | V59: =IF(AND(H59="Realizado",OR(L59="",M59="")),1,0) -> 0
A60: 46181 | B60: 0.61111111 | C60: Dr. Paulo Andrade | D60: Sala 2 | E60: Daniel Melo | F60: Saúde Total | G60: Holter | H60: Realizado | I60: Convênio | L60: 20 | M60: 105 | N60: =IF(A60="","",MONTH(A60)) -> 6 | O60: =IF(A60="","",YEAR(A60)) -> 2026 | P60: =IF(A60="","",CHOOSE(WEEKDAY(A60,2),"Segunda","Terça","Quarta","Quinta","Sexta","Sábado","Domingo")) -> Segunda | Q60: =IF(B60="","",IF(B60<TIME(12,0,0),"Manhã",IF(B60<TIME(18,0,0),"Tarde","Noite"))) -> Tarde | R60: =IF(AND(H60="Realizado",L60<>"",A60<=Config!$B$9),L60/60,0) -> 0.33333333 | S60: =IF(G60="","",IFERROR(INDEX(Config!$K$5:$K$16,MATCH(G60,Config!$J$5:$J$16,0)),"")) -> 20 | T60: =IF(OR(G60="",F60=""),"",IFERROR(INDEX(Config!$M$5:$R$16,MATCH(G60,Config!$J$5:$J$16,0),MATCH(F60,Config!$H$5:$H$10,0)),"")) -> 105 | U60: =IF(AND(H60="Realizado",L60<>""),L60/60,0) -> 0.33333333 | V60: =IF(AND(H60="Realizado",OR(L60="",M60="")),1,0) -> 0
... A71: 46182 | B71: 0.36805556 | C71: Dra. Carolina Mendes | D71: Sala 1 | E71: Juliana Ribeiro | F71: Saúde Total | G71: Consulta | H71: Realizado | I71: Convênio | L71: 30 | M71: 120 | N71: =IF(A71="","",MONTH(A71)) -> 6 | O71: =IF(A71="","",YEAR(A71)) -> 2026 | P71: =IF(A71="","",CHOOSE(WEEKDAY(A71,2),"Segunda","Terça","Quarta","Quinta","Sexta","Sábado","Domingo")) -> Terça | Q71: =IF(B71="","",IF(B71<TIME(12,0,0),"Manhã",IF(B71<TIME(18,0,0),"Tarde","Noite"))) -> Manhã | R71: =IF(AND(H71="Realizado",L71<>"",A71<=Config!$B$9),L71/60,0) -> 0.5 | S71: =IF(G71="","",IFERROR(INDEX(Config!$K$5:$K$16,MATCH(G71,Config!$J$5:$J$16,0)),"")) -> 30 | T71: =IF(OR(G71="",F71=""),"",IFERROR(INDEX(Config!$M$5:$R$16,MATCH(G71,Config!$J$5:$J$16,0),MATCH(F71,Config!$H$5:$H$10,0)),"")) -> 120 | U71: =IF(AND(H71="Realizado",L71<>""),L71/60,0) -> 0.5 | V71: =IF(AND(H71="Realizado",OR(L71="",M71="")),1,0) -> 0
A72: 46182 | B72: 0.38888889 | C72: Dra. Carolina Mendes | D72: Sala 1 | E72: Lucas Xavier | F72: Saúde Total | G72: Retorno | H72: Falta | L72: 20 | M72: 0 | N72: =IF(A72="","",MONTH(A72)) -> 6 | O72: =IF(A72="","",YEAR(A72)) -> 2026 | P72: =IF(A72="","",CHOOSE(WEEKDAY(A72,2),"Segunda","Terça","Quarta","Quinta","Sexta","Sábado","Domingo")) -> Terça | Q72: =IF(B72="","",IF(B72<TIME(12,0,0),"Manhã",IF(B72<TIME(18,0,0),"Tarde","Noite"))) -> Manhã | R72: =IF(AND(H72="Realizado",L72<>"",A72<=Config!$B$9),L72/60,0) -> 0 | S72: =IF(G72="","",IFERROR(INDEX(Config!$K$5:$K$16,MATCH(G72,Config!$J$5:$J$16,0)),"")) -> 20 | T72: =IF(OR(G72="",F72=""),"",IFERROR(INDEX(Config!$M$5:$R$16,MATCH(G72,Config!$J$5:$J$16,0),MATCH(F72,Config!$H$5:$H$10,0)),"")) -> 0 | U72: =IF(AND(H72="Realizado",L72<>""),L72/60,0) -> 0 | V72: =IF(AND(H72="Realizado",OR(L72="",M72="")),1,0) -> 0
A73: 46182 | B73: 0.40277778 | C73: Dra. Carolina Mendes | D73: Sala 1 | E73: Regina Macedo | F73: Particular | G73: Consulta | H73: Realizado | I73: Cartão de crédito | L73: 30 | M73: 380 | N73: =IF(A73="","",MONTH(A73)) -> 6 | O73: =IF(A73="","",YEAR(A73)) -> 2026 | P73: =IF(A73="","",CHOOSE(WEEKDAY(A73,2),"Segunda","Terça","Quarta","Quinta","Sexta","Sábado","Domingo")) -> Terça | Q73: =IF(B73="","",IF(B73<TIME(12,0,0),"Manhã",IF(B73<TIME(18,0,0),"Tarde","Noite"))) -> Manhã | R73: =IF(AND(H73="Realizado",L73<>"",A73<=Config!$B$9),L73/60,0) -> 0.5 | S73: =IF(G73="","",IFERROR(INDEX(Config!$K$5:$K$16,MATCH(G73,Config!$J$5:$J$16,0)),"")) -> 30 | T73: =IF(OR(G73="",F73=""),"",IFERROR(INDEX(Config!$M$5:$R$16,MATCH(G73,Config!$J$5:$J$16,0),MATCH(F73,Config!$H$5:$H$10,0)),"")) -> 380 | U73: =IF(AND(H73="Realizado",L73<>""),L73/60,0) -> 0.5 | V73: =IF(AND(H73="Realizado",OR(L73="",M73="")),1,0) -> 0
A74: 46182 | B74: 0.42361111 | C74: Dra. Carolina Mendes | D74: Sala 1 | E74: Cláudia Santos | F74: Particular | G74: Consulta | H74: Realizado | I74: Cartão de crédito | J74: 2 | L74: 30 | M74: 380 | N74: =IF(A74="","",MONTH(A74)) -> 6 | O74: =IF(A74="","",YEAR(A74)) -> 2026 | P74: =IF(A74="","",CHOOSE(WEEKDAY(A74,2),"Segunda","Terça","Quarta","Quinta","Sexta","Sábado","Domingo")) -> Terça | Q74: =IF(B74="","",IF(B74<TIME(12,0,0),"Manhã",IF(B74<TIME(18,0,0),"Tarde","Noite"))) -> Manhã | R74: =IF(AND(H74="Realizado",L74<>"",A74<=Config!$B$9),L74/60,0) -> 0.5 | S74: =IF(G74="","",IFERROR(INDEX(Config!$K$5:$K$16,MATCH(G74,Config!$J$5:$J$16,0)),"")) -> 30 | T74: =IF(OR(G74="",F74=""),"",IFERROR(INDEX(Config!$M$5:$R$16,MATCH(G74,Config!$J$5:$J$16,0),MATCH(F74,Config!$H$5:$H$10,0)),"")) -> 380 | U74: =IF(AND(H74="Realizado",L74<>""),L74/60,0) -> 0.5 | V74: =IF(AND(H74="Realizado",OR(L74="",M74="")),1,0) -> 0
A75: 46182 | B75: 0.44444444 | C75: Dra. Carolina Mendes | D75: Sala 1 | E75: Simone Monteiro | F75: Vida Care | G75: Consulta | H75: Realizado | I75: Convênio | L75: 30 | M75: 90 | N75: =IF(A75="","",MONTH(A75)) -> 6 | O75: =IF(A75="","",YEAR(A75)) -> 2026 | P75: =IF(A75="","",CHOOSE(WEEKDAY(A75,2),"Segunda","Terça","Quarta","Quinta","Sexta","Sábado","Domingo")) -> Terça | Q75: =IF(B75="","",IF(B75<TIME(12,0,0),"Manhã",IF(B75<TIME(18,0,0),"Tarde","Noite"))) -> Manhã | R75: =IF(AND(H75="Realizado",L75<>"",A75<=Config!$B$9),L75/60,0) -> 0.5 | S75: =IF(G75="","",IFERROR(INDEX(Config!$K$5:$K$16,MATCH(G75,Config!$J$5:$J$16,0)),"")) -> 30 | T75: =IF(OR(G75="",F75=""),"",IFERROR(INDEX(Config!$M$5:$R$16,MATCH(G75,Config!$J$5:$J$16,0),MATCH(F75,Config!$H$5:$H$10,0)),"")) -> 90 | U75: =IF(AND(H75="Realizado",L75<>""),L75/60,0) -> 0.5 | V75: =IF(AND(H75="Realizado",OR(L75="",M75="")),1,0) -> 0
A76: 46182 | B76: 0.46527778 | C76: Dra. Carolina Mendes | D76: Sala 1 | E76: Otávio Cardoso | F76: Particular | G76: Retorno | H76: Realizado | I76: Sem cobrança | L76: 20 | M76: 0 | N76: =IF(A76="","",MONTH(A76)) -> 6 | O76: =IF(A76="","",YEAR(A76)) -> 2026 | P76: =IF(A76="","",CHOOSE(WEEKDAY(A76,2),"Segunda","Terça","Quarta","Quinta","Sexta","Sábado","Domingo")) -> Terça | Q76: =IF(B76="","",IF(B76<TIME(12,0,0),"Manhã",IF(B76<TIME(18,0,0),"Tarde","Noite"))) -> Manhã | R76: =IF(AND(H76="Realizado",L76<>"",A76<=Config!$B$9),L76/60,0) -> 0.33333333 | S76: =IF(G76="","",IFERROR(INDEX(Config!$K$5:$K$16,MATCH(G76,Config!$J$5:$J$16,0)),"")) -> 20 | T76: =IF(OR(G76="",F76=""),"",IFERROR(INDEX(Config!$M$5:$R$16,MATCH(G76,Config!$J$5:$J$16,0),MATCH(F76,Config!$H$5:$H$10,0)),"")) -> 0 | U76: =IF(AND(H76="Realizado",L76<>""),L76/60,0) -> 0.33333333 | V76: =IF(AND(H76="Realizado",OR(L76="",M76="")),1,0) -> 0
A77: 46182 | B77: 0.47916667 | C77: Dra. Carolina Mendes | D77: Sala 1 | E77: Leandro Gomes | F77: Saúde Total | G77: Consulta | H77: Realizado | I77: Convênio | L77: 30 | M77: 120 | N77: =IF(A77="","",MONTH(A77)) -> 6 | O77: =IF(A77="","",YEAR(A77)) -> 2026 | P77: =IF(A77="","",CHOOSE(WEEKDAY(A77,2),"Segunda","Terça","Quarta","Quinta","Sexta","Sábado","Domingo")) -> Terça | Q77: =IF(B77="","",IF(B77<TIME(12,0,0),"Manhã",IF(B77<TIME(18,0,0),"Tarde","Noite"))) -> Manhã | R77: =IF(AND(H77="Realizado",L77<>"",A77<=Config!$B$9),L77/60,0) -> 0.5 | S77: =IF(G77="","",IFERROR(INDEX(Config!$K$5:$K$16,MATCH(G77,Config!$J$5:$J$16,0)),"")) -> 30 | T77: =IF(OR(G77="",F77=""),"",IFERROR(INDEX(Config!$M$5:$R$16,MATCH(G77,Config!$J$5:$J$16,0),MATCH(F77,Config!$H$5:$H$10,0)),"")) -> 120 | U77: =IF(AND(H77="Realizado",L77<>""),L77/60,0) -> 0.5 | V77: =IF(AND(H77="Realizado",OR(L77="",M77="")),1,0) -> 0
A78: 46182 | B78: 0.58333333 | C78: Dr. Paulo Andrade | D78: Sala 2 | E78: Eduardo Reis | F78: Vida Care | G78: Teste ergométrico | H78: Realizado | I78: Convênio | L78: 40 | M78: 110 | N78: =IF(A78="","",MONTH(A78)) -> 6 | O78: =IF(A78="","",YEAR(A78)) -> 2026 | P78: =IF(A78="","",CHOOSE(WEEKDAY(A78,2),"Segunda","Terça","Quarta","Quinta","Sexta","Sábado","Domingo")) -> Terça | Q78: =IF(B78="","",IF(B78<TIME(12,0,0),"Manhã",IF(B78<TIME(18,0,0),"Tarde","Noite"))) -> Tarde | R78: =IF(AND(H78="Realizado",L78<>"",A78<=Config!$B$9),L78/60,0) -> 0.66666667 | S78: =IF(G78="","",IFERROR(INDEX(Config!$K$5:$K$16,MATCH(G78,Config!$J$5:$J$16,0)),"")) -> 40 | T78: =IF(OR(G78="",F78=""),"",IFERROR(INDEX(Config!$M$5:$R$16,MATCH(G78,Config!$J$5:$J$16,0),MATCH(F78,Config!$H$5:$H$10,0)),"")) -> 110 | U78: =IF(AND(H78="Realizado",L78<>""),L78/60,0) -> 0.66666667 | V78: =IF(AND(H78="Realizado",OR(L78="",M78="")),1,0) -> 0
A79: 46182 | B79: 0.60416667 | C79: Dra. Renata Sousa | D79: Sala 1 | E79: Camila Dias | F79: Particular | G79: Avaliação endócrina | H79: Realizado | I79: Pix | L79: 40 | M79: 400 | N79: =IF(A79="","",MONTH(A79)) -> 6 | O79: =IF(A79="","",YEAR(A79)) -> 2026 | P79: =IF(A79="","",CHOOSE(WEEKDAY(A79,2),"Segunda","Terça","Quarta","Quinta","Sexta","Sábado","Domingo")) -> Terça | Q79: =IF(B79="","",IF(B79<TIME(12,0,0),"Manhã",IF(B79<TIME(18,0,0),"Tarde","Noite"))) -> Tarde | R79: =IF(AND(H79="Realizado",L79<>"",A79<=Config!$B$9),L79/60,0) -> 0.66666667 | S79: =IF(G79="","",IFERROR(INDEX(Config!$K$5:$K$16,MATCH(G79,Config!$J$5:$J$16,0)),"")) -> 40 | T79: =IF(OR(G79="",F79=""),"",IFERROR(INDEX(Config!$M$5:$R$16,MATCH(G79,Config!$J$5:$J$16,0),MATCH(F79,Config!$H$5:$H$10,0)),"")) -> 400 | U79: =IF(AND(H79="Realizado",L79<>""),L79/60,0) -> 0.66666667 | V79: =IF(AND(H79="Realizado",OR(L79="",M79="")),1,0) -> 0
A80: 46182 | B80: 0.61111111 | C80: Dr. Paulo Andrade | D80: Sala 2 | E80: Vanessa Carvalho | F80: Saúde Total | G80: Consulta | H80: Realizado | I80: Convênio | L80: 30 | M80: 120 | N80: =IF(A80="","",MONTH(A80)) -> 6 | O80: =IF(A80="","",YEAR(A80)) -> 2026 | P80: =IF(A80="","",CHOOSE(WEEKDAY(A80,2),"Segunda","Terça","Quarta","Quinta","Sexta","Sábado","Domingo")) -> Terça | Q80: =IF(B80="","",IF(B80<TIME(12,0,0),"Manhã",IF(B80<TIME(18,0,0),"Tarde","Noite"))) -> Tarde | R80: =IF(AND(H80="Realizado",L80<>"",A80<=Config!$B$9),L80/60,0) -> 0.5 | S80: =IF(G80="","",IFERROR(INDEX(Config!$K$5:$K$16,MATCH(G80,Config!$J$5:$J$16,0)),"")) -> 30 | T80: =IF(OR(G80="",F80=""),"",IFERROR(INDEX(Config!$M$5:$R$16,MATCH(G80,Config!$J$5:$J$16,0),MATCH(F80,Config!$H$5:$H$10,0)),"")) -> 120 | U80: =IF(AND(H80="Realizado",L80<>""),L80/60,0) -> 0.5 | V80: =IF(AND(H80="Realizado",OR(L80="",M80="")),1,0) -> 0
A81: 46182 | B81: 0.63194444 | C81: Dra. Renata Sousa | D81: Sala 1 | E81: Mariana Gomes | F81: Particular | G81: Avaliação endócrina | H81: Realizado | I81: Cartão de crédito | J81: 2 | L81: 40 | M81: 400 | N81: =IF(A81="","",MONTH(A81)) -> 6 | O81: =IF(A81="","",YEAR(A81)) -> 2026 | P81: =IF(A81="","",CHOOSE(WEEKDAY(A81,2),"Segunda","Terça","Quarta","Quinta","Sexta","Sábado","Domingo")) -> Terça | Q81: =IF(B81="","",IF(B81<TIME(12,0,0),"Manhã",IF(B81<TIME(18,0,0),"Tarde","Noite"))) -> Tarde | R81: =IF(AND(H81="Realizado",L81<>"",A81<=Config!$B$9),L81/60,0) -> 0.66666667 | S81: =IF(G81="","",IFERROR(INDEX(Config!$K$5:$K$16,MATCH(G81,Config!$J$5:$J$16,0)),"")) -> 40 | T81: =IF(OR(G81="",F81=""),"",IFERROR(INDEX(Config!$M$5:$R$16,MATCH(G81,Config!$J$5:$J$16,0),MATCH(F81,Config!$H$5:$H$10,0)),"")) -> 400 | U81: =IF(AND(H81="Realizado",L81<>""),L81/60,0) -> 0.66666667 | V81: =IF(AND(H81="Realizado",OR(L81="",M81="")),1,0) -> 0
A82: 46182 | B82: 0.63194444 | C82: Dr. Paulo Andrade | D82: Sala 2 | E82: Bruno Carvalho | F82: Saúde Total | G82: Consulta | H82: Realizado | I82: Convênio | L82: 30 | M82: 120 | N82: =IF(A82="","",MONTH(A82)) -> 6 | O82: =IF(A82="","",YEAR(A82)) -> 2026 | P82: =IF(A82="","",CHOOSE(WEEKDAY(A82,2),"Segunda","Terça","Quarta","Quinta","Sexta","Sábado","Domingo")) -> Terça | Q82: =IF(B82="","",IF(B82<TIME(12,0,0),"Manhã",IF(B82<TIME(18,0,0),"Tarde","Noite"))) -> Tarde | R82: =IF(AND(H82="Realizado",L82<>"",A82<=Config!$B$9),L82/60,0) -> 0.5 | S82: =IF(G82="","",IFERROR(INDEX(Config!$K$5:$K$16,MATCH(G82,Config!$J$5:$J$16,0)),"")) -> 30 | T82: =IF(OR(G82="",F82=""),"",IFERROR(INDEX(Config!$M$5:$R$16,MATCH(G82,Config!$J$5:$J$16,0),MATCH(F82,Config!$H$5:$H$10,0)),"")) -> 120 | U82: =IF(AND(H82="Realizado",L82<>""),L82/60,0) -> 0.5 | V82: =IF(AND(H82="Realizado",OR(L82="",M82="")),1,0) -> 0
A83: 46182 | B83: 0.65972222 | C83: Dra. Renata Sousa | D83: Sala 1 | E83: Márcia Duarte | F83: Particular | G83: Retorno | H83: Falta | L83: 20 | M83: 0 | N83: =IF(A83="","",MONTH(A83)) -> 6 | O83: =IF(A83="","",YEAR(A83)) -> 2026 | P83: =IF(A83="","",CHOOSE(WEEKDAY(A83,2),"Segunda","Terça","Quarta","Quinta","Sexta","Sábado","Domingo")) -> Terça | Q83: =IF(B83="","",IF(B83<TIME(12,0,0),"Manhã",IF(B83<TIME(18,0,0),"Tarde","Noite"))) -> Tarde | R83: =IF(AND(H83="Realizado",L83<>"",A83<=Config!$B$9),L83/60,0) -> 0 | S83: =IF(G83="","",IFERROR(INDEX(Config!$K$5:$K$16,MATCH(G83,Config!$J$5:$J$16,0)),"")) -> 20 | T83: =IF(OR(G83="",F83=""),"",IFERROR(INDEX(Config!$M$5:$R$16,MATCH(G83,Config!$J$5:$J$16,0),MATCH(F83,Config!$H$5:$H$10,0)),"")) -> 0 | U83: =IF(AND(H83="Realizado",L83<>""),L83/60,0) -> 0 | V83: =IF(AND(H83="Realizado",OR(L83="",M83="")),1,0) -> 0
A84: 46182 | B84: 0.67361111 | C84: Dra. Renata Sousa | D84: Sala 1 | E84: Cláudia Melo | F84: Particular | G84: Avaliação endócrina | H84: Realizado | I84: Cartão de crédito | L84: 40 | M84: 400 | N84: =IF(A84="","",MONTH(A84)) -> 6 | O84: =IF(A84="","",YEAR(A84)) -> 2026 | P84: =IF(A84="","",CHOOSE(WEEKDAY(A84,2),"Segunda","Terça","Quarta","Quinta","Sexta","Sábado","Domingo")) -> Terça | Q84: =IF(B84="","",IF(B84<TIME(12,0,0),"Manhã",IF(B84<TIME(18,0,0),"Tarde","Noite"))) -> Tarde | R84: =IF(AND(H84="Realizado",L84<>"",A84<=Config!$B$9),L84/60,0) -> 0.66666667 | S84: =IF(G84="","",IFERROR(INDEX(Config!$K$5:$K$16,MATCH(G84,Config!$J$5:$J$16,0)),"")) -> 40 | T84: =IF(OR(G84="",F84=""),"",IFERROR(INDEX(Config!$M$5:$R$16,MATCH(G84,Config!$J$5:$J$16,0),MATCH(F84,Config!$H$5:$H$10,0)),"")) -> 400 | U84: =IF(AND(H84="Realizado",L84<>""),L84/60,0) -> 0.66666667 | V84: =IF(AND(H84="Realizado",OR(L84="",M84="")),1,0) -> 0
A85: 46182 | B85: 0.67361111 | C85: Dr. Paulo Andrade | D85: Sala 2 | E85: Fernanda Nunes | F85: MediPlan | G85: Retorno | H85: Realizado | I85: Sem cobrança | L85: 20 | M85: 0 | N85: =IF(A85="","",MONTH(A85)) -> 6 | O85: =IF(A85="","",YEAR(A85)) -> 2026 | P85: =IF(A85="","",CHOOSE(WEEKDAY(A85,2),"Segunda","Terça","Quarta","Quinta","Sexta","Sábado","Domingo")) -> Terça | Q85: =IF(B85="","",IF(B85<TIME(12,0,0),"Manhã",IF(B85<TIME(18,0,0),"Tarde","Noite"))) -> Tarde | R85: =IF(AND(H85="Realizado",L85<>"",A85<=Config!$B$9),L85/60,0) -> 0.33333333 | S85: =IF(G85="","",IFERROR(INDEX(Config!$K$5:$K$16,MATCH(G85,Config!$J$5:$J$16,0)),"")) -> 20 | T85: =IF(OR(G85="",F85=""),"",IFERROR(INDEX(Config!$M$5:$R$16,MATCH(G85,Config!$J$5:$J$16,0),MATCH(F85,Config!$H$5:$H$10,0)),"")) -> 0 | U85: =IF(AND(H85="Realizado",L85<>""),L85/60,0) -> 0.33333333 | V85: =IF(AND(H85="Realizado",OR(L85="",M85="")),1,0) -> 0
A86: 46182 | B86: 0.6875 | C86: Dr. Paulo Andrade | D86: Sala 2 | E86: Natália Martins | F86: Particular | G86: Consulta | H86: Realizado | I86: Pix | L86: 30 | M86: 380 | N86: =IF(A86="","",MONTH(A86)) -> 6 | O86: =IF(A86="","",YEAR(A86)) -> 2026 | P86: =IF(A86="","",CHOOSE(WEEKDAY(A86,2),"Segunda","Terça","Quarta","Quinta","Sexta","Sábado","Domingo")) -> Terça | Q86: =IF(B86="","",IF(B86<TIME(12,0,0),"Manhã",IF(B86<TIME(18,0,0),"Tarde","Noite"))) -> Tarde | R86: =IF(AND(H86="Realizado",L86<>"",A86<=Config!$B$9),L86/60,0) -> 0.5 | S86: =IF(G86="","",IFERROR(INDEX(Config!$K$5:$K$16,MATCH(G86,Config!$J$5:$J$16,0)),"")) -> 30 | T86: =IF(OR(G86="",F86=""),"",IFERROR(INDEX(Config!$M$5:$R$16,MATCH(G86,Config!$J$5:$J$16,0),MATCH(F86,Config!$H$5:$H$10,0)),"")) -> 380 | U86: =IF(AND(H86="Realizado",L86<>""),L86/60,0) -> 0.5 | V86: =IF(AND(H86="Realizado",OR(L86="",M86="")),1,0) -> 0
A87: 46182 | B87: 0.70138889 | C87: Dra. Renata Sousa | D87: Sala 1 | E87: Paulo Freitas | F87: Saúde Total | G87: Retorno | H87: Realizado | I87: Sem cobrança | L87: 20 | M87: 0 | N87: =IF(A87="","",MONTH(A87)) -> 6 | O87: =IF(A87="","",YEAR(A87)) -> 2026 | P87: =IF(A87="","",CHOOSE(WEEKDAY(A87,2),"Segunda","Terça","Quarta","Quinta","Sexta","Sábado","Domingo")) -> Terça | Q87: =IF(B87="","",IF(B87<TIME(12,0,0),"Manhã",IF(B87<TIME(18,0,0),"Tarde","Noite"))) -> Tarde | R87: =IF(AND(H87="Realizado",L87<>"",A87<=Config!$B$9),L87/60,0) -> 0.33333333 | S87: =IF(G87="","",IFERROR(INDEX(Config!$K$5:$K$16,MATCH(G87,Config!$J$5:$J$16,0)),"")) -> 20 | T87: =IF(OR(G87="",F87=""),"",IFERROR(INDEX(Config!$M$5:$R$16,MATCH(G87,Config!$J$5:$J$16,0),MATCH(F87,Config!$H$5:$H$10,0)),"")) -> 0 | U87: =IF(AND(H87="Realizado",L87<>""),L87/60,0) -> 0.33333333 | V87: =IF(AND(H87="Realizado",OR(L87="",M87="")),1,0) -> 0
A88: 46182 | B88: 0.70833333 | C88: Dr. Paulo Andrade | D88: Sala 2 | E88: Paulo Ribeiro | F88: Saúde Total | G88: Consulta | H88: Realizado | I88: Convênio | L88: 30 | M88: 120 | N88: =IF(A88="","",MONTH(A88)) -> 6 | O88: =IF(A88="","",YEAR(A88)) -> 2026 | P88: =IF(A88="","",CHOOSE(WEEKDAY(A88,2),"Segunda","Terça","Quarta","Quinta","Sexta","Sábado","Domingo")) -> Terça | Q88: =IF(B88="","",IF(B88<TIME(12,0,0),"Manhã",IF(B88<TIME(18,0,0),"Tarde","Noite"))) -> Tarde | R88: =IF(AND(H88="Realizado",L88<>"",A88<=Config!$B$9),L88/60,0) -> 0.5 | S88: =IF(G88="","",IFERROR(INDEX(Config!$K$5:$K$16,MATCH(G88,Config!$J$5:$J$16,0)),"")) -> 30 | T88: =IF(OR(G88="",F88=""),"",IFERROR(INDEX(Config!$M$5:$R$16,MATCH(G88,Config!$J$5:$J$16,0),MATCH(F88,Config!$H$5:$H$10,0)),"")) -> 120 | U88: =IF(AND(H88="Realizado",L88<>""),L88/60,0) -> 0.5 | V88: =IF(AND(H88="Realizado",OR(L88="",M88="")),1,0) -> 0
A89: 46182 | B89: 0.71527778 | C89: Dra. Renata Sousa | D89: Sala 1 | E89: Carlos Gomes | F89: Saúde Total | G89: Retorno | H89: Realizado | I89: Sem cobrança | L89: 20 | M89: 0 | N89: =IF(A89="","",MONTH(A89)) -> 6 | O89: =IF(A89="","",YEAR(A89)) -> 2026 | P89: =IF(A89="","",CHOOSE(WEEKDAY(A89,2),"Segunda","Terça","Quarta","Quinta","Sexta","Sábado","Domingo")) -> Terça | Q89: =IF(B89="","",IF(B89<TIME(12,0,0),"Manhã",IF(B89<TIME(18,0,0),"Tarde","Noite"))) -> Tarde | R89: =IF(AND(H89="Realizado",L89<>"",A89<=Config!$B$9),L89/60,0) -> 0.33333333 | S89: =IF(G89="","",IFERROR(INDEX(Config!$K$5:$K$16,MATCH(G89,Config!$J$5:$J$16,0)),"")) -> 20 | T89: =IF(OR(G89="",F89=""),"",IFERROR(INDEX(Config!$M$5:$R$16,MATCH(G89,Config!$J$5:$J$16,0),MATCH(F89,Config!$H$5:$H$10,0)),"")) -> 0 | U89: =IF(AND(H89="Realizado",L89<>""),L89/60,0) -> 0.33333333 | V89: =IF(AND(H89="Realizado",OR(L89="",M89="")),1,0) -> 0
A90: 46182 | B90: 0.72916667 | C90: Dra. Renata Sousa | D90: Sala 1 | E90: Paulo Fernandes | F90: Particular | G90: Retorno | H90: Realizado | I90: Sem cobrança | L90: 20 | M90: 0 | N90: =IF(A90="","",MONTH(A90)) -> 6 | O90: =IF(A90="","",YEAR(A90)) -> 2026 | P90: =IF(A90="","",CHOOSE(WEEKDAY(A90,2),"Segunda","Terça","Quarta","Quinta","Sexta","Sábado","Domingo")) -> Terça | Q90: =IF(B90="","",IF(B90<TIME(12,0,0),"Manhã",IF(B90<TIME(18,0,0),"Tarde","Noite"))) -> Tarde | R90: =IF(AND(H90="Realizado",L90<>"",A90<=Config!$B$9),L90/60,0) -> 0.33333333 | S90: =IF(G90="","",IFERROR(INDEX(Config!$K$5:$K$16,MATCH(G90,Config!$J$5:$J$16,0)),"")) -> 20 | T90: =IF(OR(G90="",F90=""),"",IFERROR(INDEX(Config!$M$5:$R$16,MATCH(G90,Config!$J$5:$J$16,0),MATCH(F90,Config!$H$5:$H$10,0)),"")) -> 0 | U90: =IF(AND(H90="Realizado",L90<>""),L90/60,0) -> 0.33333333 | V90: =IF(AND(H90="Realizado",OR(L90="",M90="")),1,0) -> 0
A91: 46182 | B91: 0.72916667 | C91: Dr. Paulo Andrade | D91: Sala 2 | E91: Marcelo Santos | F91: Particular | G91: ECG | H91: Realizado | I91: Pix | L91: 20 | M91: 130 | N91: =IF(A91="","",MONTH(A91)) -> 6 | O91: =IF(A91="","",YEAR(A91)) -> 2026 | P91: =IF(A91="","",CHOOSE(WEEKDAY(A91,2),"Segunda","Terça","Quarta","Quinta","Sexta","Sábado","Domingo")) -> Terça | Q91: =IF(B91="","",IF(B91<TIME(12,0,0),"Manhã",IF(B91<TIME(18,0,0),"Tarde","Noite"))) -> Tarde | R91: =IF(AND(H91="Realizado",L91<>"",A91<=Config!$B$9),L91/60,0) -> 0.33333333 | S91: =IF(G91="","",IFERROR(INDEX(Config!$K$5:$K$16,MATCH(G91,Config!$J$5:$J$16,0)),"")) -> 20 | T91: =IF(OR(G91="",F91=""),"",IFERROR(INDEX(Config!$M$5:$R$16,MATCH(G91,Config!$J$5:$J$16,0),MATCH(F91,Config!$H$5:$H$10,0)),"")) -> 130 | U91: =IF(AND(H91="Realizado",L91<>""),L91/60,0) -> 0.33333333 | V91: =IF(AND(H91="Realizado",OR(L91="",M91="")),1,0) -> 0
A92: 46183 | B92: 0.58333333 | C92: Dra. Carolina Mendes | D92: Sala 1 | E92: Leandro Gomes | F92: Saúde Total | G92: Retorno | H92: Realizado | I92: Sem cobrança | L92: 20 | M92: 0 | N92: =IF(A92="","",MONTH(A92)) -> 6 | O92: =IF(A92="","",YEAR(A92)) -> 2026 | P92: =IF(A92="","",CHOOSE(WEEKDAY(A92,2),"Segunda","Terça","Quarta","Quinta","Sexta","Sábado","Domingo")) -> Quarta | Q92: =IF(B92="","",IF(B92<TIME(12,0,0),"Manhã",IF(B92<TIME(18,0,0),"Tarde","Noite"))) -> Tarde | R92: =IF(AND(H92="Realizado",L92<>"",A92<=Config!$B$9),L92/60,0) -> 0.33333333 | S92: =IF(G92="","",IFERROR(INDEX(Config!$K$5:$K$16,MATCH(G92,Config!$J$5:$J$16,0)),"")) -> 20 | T92: =IF(OR(G92="",F92=""),"",IFERROR(INDEX(Config!$M$5:$R$16,MATCH(G92,Config!$J$5:$J$16,0),MATCH(F92,Config!$H$5:$H$10,0)),"")) -> 0 | U92: =IF(AND(H92="Realizado",L92<>""),L92/60,0) -> 0.33333333 | V92: =IF(AND(H92="Realizado",OR(L92="",M92="")),1,0) -> 0
A93: 46183 | B93: 0.59722222 | C93: Dra. Carolina Mendes | D93: Sala 1 | E93: Débora Machado | F93: Saúde Total | G93: Consulta | H93: Realizado | I93: Convênio | L93: 30 | M93: 120 | N93: =IF(A93="","",MONTH(A93)) -> 6 | O93: =IF(A93="","",YEAR(A93)) -> 2026 | P93: =IF(A93="","",CHOOSE(WEEKDAY(A93,2),"Segunda","Terça","Quarta","Quinta","Sexta","Sábado","Domingo")) -> Quarta | Q93: =IF(B93="","",IF(B93<TIME(12,0,0),"Manhã",IF(B93<TIME(18,0,0),"Tarde","Noite"))) -> Tarde | R93: =IF(AND(H93="Realizado",L93<>"",A93<=Config!$B$9),L93/60,0) -> 0.5 | S93: =IF(G93="","",IFERROR(INDEX(Config!$K$5:$K$16,MATCH(G93,Config!$J$5:$J$16,0)),"")) -> 30 | T93: =IF(OR(G93="",F93=""),"",IFERROR(INDEX(Config!$M$5:$R$16,MATCH(G93,Config!$J$5:$J$16,0),MATCH(F93,Config!$H$5:$H$10,0)),"")) -> 120 | U93: =IF(AND(H93="Realizado",L93<>""),L93/60,0) -> 0.5 | V93: =IF(AND(H93="Realizado",OR(L93="",M93="")),1,0) -> 0
A94: 46183 | B94: 0.61805556 | C94: Dra. Carolina Mendes | D94: Sala 1 | E94: Elaine Cardoso | F94: Particular | G94: Consulta | H94: Falta | L94: 30 | M94: 380 | N94: =IF(A94="","",MONTH(A94)) -> 6 | O94: =IF(A94="","",YEAR(A94)) -> 2026 | P94: =IF(A94="","",CHOOSE(WEEKDAY(A94,2),"Segunda","Terça","Quarta","Quinta","Sexta","Sábado","Domingo")) -> Quarta | Q94: =IF(B94="","",IF(B94<TIME(12,0,0),"Manhã",IF(B94<TIME(18,0,0),"Tarde","Noite"))) -> Tarde | R94: =IF(AND(H94="Realizado",L94<>"",A94<=Config!$B$9),L94/60,0) -> 0 | S94: =IF(G94="","",IFERROR(INDEX(Config!$K$5:$K$16,MATCH(G94,Config!$J$5:$J$16,0)),"")) -> 30 | T94: =IF(OR(G94="",F94=""),"",IFERROR(INDEX(Config!$M$5:$R$16,MATCH(G94,Config!$J$5:$J$16,0),MATCH(F94,Config!$H$5:$H$10,0)),"")) -> 380 | U94: =IF(AND(H94="Realizado",L94<>""),L94/60,0) -> 0 | V94: =IF(AND(H94="Realizado",OR(L94="",M94="")),1,0) -> 0
A95: 46183 | B95: 0.65972222 | C95: Dra. Carolina Mendes | D95: Sala 1 | E95: Patrícia Fernandes | F95: Particular | G95: Retorno | H95: Realizado | I95: Sem cobrança | L95: 20 | M95: 0 | N95: =IF(A95="","",MONTH(A95)) -> 6 | O95: =IF(A95="","",YEAR(A95)) -> 2026 | P95: =IF(A95="","",CHOOSE(WEEKDAY(A95,2),"Segunda","Terça","Quarta","Quinta","Sexta","Sábado","Domingo")) -> Quarta | Q95: =IF(B95="","",IF(B95<TIME(12,0,0),"Manhã",IF(B95<TIME(18,0,0),"Tarde","Noite"))) -> Tarde | R95: =IF(AND(H95="Realizado",L95<>"",A95<=Config!$B$9),L95/60,0) -> 0.33333333 | S95: =IF(G95="","",IFERROR(INDEX(Config!$K$5:$K$16,MATCH(G95,Config!$J$5:$J$16,0)),"")) -> 20 | T95: =IF(OR(G95="",F95=""),"",IFERROR(INDEX(Config!$M$5:$R$16,MATCH(G95,Config!$J$5:$J$16,0),MATCH(F95,Config!$H$5:$H$10,0)),"")) -> 0 | U95: =IF(AND(H95="Realizado",L95<>""),L95/60,0) -> 0.33333333 | V95: =IF(AND(H95="Realizado",OR(L95="",M95="")),1,0) -> 0
A96: 46183 | B96: 0.67361111 | C96: Dra. Carolina Mendes | D96: Sala 1 | E96: Viviane Ribeiro | F96: Particular | G96: Retorno | H96: Realizado | I96: Sem cobrança | L96: 20 | M96: 0 | N96: =IF(A96="","",MONTH(A96)) -> 6 | O96: =IF(A96="","",YEAR(A96)) -> 2026 | P96: =IF(A96="","",CHOOSE(WEEKDAY(A96,2),"Segunda","Terça","Quarta","Quinta","Sexta","Sábado","Domingo")) -> Quarta | Q96: =IF(B96="","",IF(B96<TIME(12,0,0),"Manhã",IF(B96<TIME(18,0,0),"Tarde","Noite"))) -> Tarde | R96: =IF(AND(H96="Realizado",L96<>"",A96<=Config!$B$9),L96/60,0) -> 0.33333333 | S96: =IF(G96="","",IFERROR(INDEX(Config!$K$5:$K$16,MATCH(G96,Config!$J$5:$J$16,0)),"")) -> 20 | T96: =IF(OR(G96="",F96=""),"",IFERROR(INDEX(Config!$M$5:$R$16,MATCH(G96,Config!$J$5:$J$16,0),MATCH(F96,Config!$H$5:$H$10,0)),"")) -> 0 | U96: =IF(AND(H96="Realizado",L96<>""),L96/60,0) -> 0.33333333 | V96: =IF(AND(H96="Realizado",OR(L96="",M96="")),1,0) -> 0
A97: 46183 | B97: 0.6875 | C97: Dra. Carolina Mendes | D97: Sala 1 | E97: Carlos Castro | F97: Saúde Total | G97: Consulta | H97: Cancelado | L97: 30 | M97: 120 | N97: =IF(A97="","",MONTH(A97)) -> 6 | O97: =IF(A97="","",YEAR(A97)) -> 2026 | P97: =IF(A97="","",CHOOSE(WEEKDAY(A97,2),"Segunda","Terça","Quarta","Quinta","Sexta","Sábado","Domingo")) -> Quarta | Q97: =IF(B97="","",IF(B97<TIME(12,0,0),"Manhã",IF(B97<TIME(18,0,0),"Tarde","Noite"))) -> Tarde | R97: =IF(AND(H97="Realizado",L97<>"",A97<=Config!$B$9),L97/60,0) -> 0 | S97: =IF(G97="","",IFERROR(INDEX(Config!$K$5:$K$16,MATCH(G97,Config!$J$5:$J$16,0)),"")) -> 30 | T97: =IF(OR(G97="",F97=""),"",IFERROR(INDEX(Config!$M$5:$R$16,MATCH(G97,Config!$J$5:$J$16,0),MATCH(F97,Config!$H$5:$H$10,0)),"")) -> 120 | U97: =IF(AND(H97="Realizado",L97<>""),L97/60,0) -> 0 | V97: =IF(AND(H97="Realizado",OR(L97="",M97="")),1,0) -> 0
A98: 46183 | B98: 0.70833333 | C98: Dra. Carolina Mendes | D98: Sala 1 | E98: Lucas Lopes | F98: Particular | G98: Consulta | H98: Realizado | I98: Pix | L98: 30 | M98: 380 | N98: =IF(A98="","",MONTH(A98)) -> 6 | O98: =IF(A98="","",YEAR(A98)) -> 2026 | P98: =IF(A98="","",CHOOSE(WEEKDAY(A98,2),"Segunda","Terça","Quarta","Quinta","Sexta","Sábado","Domingo")) -> Quarta | Q98: =IF(B98="","",IF(B98<TIME(12,0,0),"Manhã",IF(B98<TIME(18,0,0),"Tarde","Noite"))) -> Tarde | R98: =IF(AND(H98="Realizado",L98<>"",A98<=Config!$B$9),L98/60,0) -> 0.5 | S98: =IF(G98="","",IFERROR(INDEX(Config!$K$5:$K$16,MATCH(G98,Config!$J$5:$J$16,0)),"")) -> 30 | T98: =IF(OR(G98="",F98=""),"",IFERROR(INDEX(Config!$M$5:$R$16,MATCH(G98,Config!$J$5:$J$16,0),MATCH(F98,Config!$H$5:$H$10,0)),"")) -> 380 | U98: =IF(AND(H98="Realizado",L98<>""),L98/60,0) -> 0.5 | V98: =IF(AND(H98="Realizado",OR(L98="",M98="")),1,0) -> 0
A99: 46183 | B99: 0.72916667 | C99: Dra. Carolina Mendes | D99: Sala 1 | E99: Regina Teixeira | F99: Particular | G99: Consulta | H99: Realizado | I99: A prazo | L99: 30 | M99: 380 | N99: =IF(A99="","",MONTH(A99)) -> 6 | O99: =IF(A99="","",YEAR(A99)) -> 2026 | P99: =IF(A99="","",CHOOSE(WEEKDAY(A99,2),"Segunda","Terça","Quarta","Quinta","Sexta","Sábado","Domingo")) -> Quarta | Q99: =IF(B99="","",IF(B99<TIME(12,0,0),"Manhã",IF(B99<TIME(18,0,0),"Tarde","Noite"))) -> Tarde | R99: =IF(AND(H99="Realizado",L99<>"",A99<=Config!$B$9),L99/60,0) -> 0.5 | S99: =IF(G99="","",IFERROR(INDEX(Config!$K$5:$K$16,MATCH(G99,Config!$J$5:$J$16,0)),"")) -> 30 | T99: =IF(OR(G99="",F99=""),"",IFERROR(INDEX(Config!$M$5:$R$16,MATCH(G99,Config!$J$5:$J$16,0),MATCH(F99,Config!$H$5:$H$10,0)),"")) -> 380 | U99: =IF(AND(H99="Realizado",L99<>""),L99/60,0) -> 0.5 | V99: =IF(AND(H99="Realizado",OR(L99="",M99="")),1,0) -> 0
A100: 46184 | B100: 0.33333333 | C100: Dra. Carolina Mendes | D100: Sala 1 | E100: Daniel Melo | F100: Saúde Total | G100: Retorno | H100: Falta | L100: 20 | M100: 0 | N100: =IF(A100="","",MONTH(A100)) -> 6 | O100: =IF(A100="","",YEAR(A100)) -> 2026 | P100: =IF(A100="","",CHOOSE(WEEKDAY(A100,2),"Segunda","Terça","Quarta","Quinta","Sexta","Sábado","Domingo")) -> Quinta | Q100: =IF(B100="","",IF(B100<TIME(12,0,0),"Manhã",IF(B100<TIME(18,0,0),"Tarde","Noite"))) -> Manhã | R100: =IF(AND(H100="Realizado",L100<>"",A100<=Config!$B$9),L100/60,0) -> 0 | S100: =IF(G100="","",IFERROR(INDEX(Config!$K$5:$K$16,MATCH(G100,Config!$J$5:$J$16,0)),"")) -> 20 | T100: =IF(OR(G100="",F100=""),"",IFERROR(INDEX(Config!$M$5:$R$16,MATCH(G100,Config!$J$5:$J$16,0),MATCH(F100,Config!$H$5:$H$10,0)),"")) -> 0 | U100: =IF(AND(H100="Realizado",L100<>""),L100/60,0) -> 0 | V100: =IF(AND(H100="Realizado",OR(L100="",M100="")),1,0) -> 0
A101: 46184 | B101: 0.36805556 | C101: Dra. Carolina Mendes | D101: Sala 1 | E101: Elaine Cardoso | F101: Particular | G101: Consulta | H101: Realizado | I101: Pix | L101: 30 | M101: 380 | N101: =IF(A101="","",MONTH(A101)) -> 6 | O101: =IF(A101="","",YEAR(A101)) -> 2026 | P101: =IF(A101="","",CHOOSE(WEEKDAY(A101,2),"Segunda","Terça","Quarta","Quinta","Sexta","Sábado","Domingo")) -> Quinta | Q101: =IF(B101="","",IF(B101<TIME(12,0,0),"Manhã",IF(B101<TIME(18,0,0),"Tarde","Noite"))) -> Manhã | R101: =IF(AND(H101="Realizado",L101<>"",A101<=Config!$B$9),L101/60,0) -> 0.5 | S101: =IF(G101="","",IFERROR(INDEX(Config!$K$5:$K$16,MATCH(G101,Config!$J$5:$J$16,0)),"")) -> 30 | T101: =IF(OR(G101="",F101=""),"",IFERROR(INDEX(Config!$M$5:$R$16,MATCH(G101,Config!$J$5:$J$16,0),MATCH(F101,Config!$H$5:$H$10,0)),"")) -> 380 | U101: =IF(AND(H101="Realizado",L101<>""),L101/60,0) -> 0.5 | V101: =IF(AND(H101="Realizado",OR(L101="",M101="")),1,0) -> 0
A102: 46184 | B102: 0.38888889 | C102: Dra. Carolina Mendes | D102: Sala 1 | E102: Gustavo Ferreira | F102: Particular | G102: Consulta | H102: Realizado | I102: Dinheiro | L102: 30 | M102: 380 | N102: =IF(A102="","",MONTH(A102)) -> 6 | O102: =IF(A102="","",YEAR(A102)) -> 2026 | P102: =IF(A102="","",CHOOSE(WEEKDAY(A102,2),"Segunda","Terça","Quarta","Quinta","Sexta","Sábado","Domingo")) -> Quinta | Q102: =IF(B102="","",IF(B102<TIME(12,0,0),"Manhã",IF(B102<TIME(18,0,0),"Tarde","Noite"))) -> Manhã | R102: =IF(AND(H102="Realizado",L102<>"",A102<=Config!$B$9),L102/60,0) -> 0.5 | S102: =IF(G102="","",IFERROR(INDEX(Config!$K$5:$K$16,MATCH(G102,Config!$J$5:$J$16,0)),"")) -> 30 | T102: =IF(OR(G102="",F102=""),"",IFERROR(INDEX(Config!$M$5:$R$16,MATCH(G102,Config!$J$5:$J$16,0),MATCH(F102,Config!$H$5:$H$10,0)),"")) -> 380 | U102: =IF(AND(H102="Realizado",L102<>""),L102/60,0) -> 0.5 | V102: =IF(AND(H102="Realizado",OR(L102="",M102="")),1,0) -> 0
A103: 46184 | B103: 0.40972222 | C103: Dra. Carolina Mendes | D103: Sala 1 | E103: Ricardo Melo | F103: Saúde Total | G103: Consulta | H103: Realizado | I103: Convênio | L103: 30 | M103: 120 | N103: =IF(A103="","",MONTH(A103)) -> 6 | O103: =IF(A103="","",YEAR(A103)) -> 2026 | P103: =IF(A103="","",CHOOSE(WEEKDAY(A103,2),"Segunda","Terça","Quarta","Quinta","Sexta","Sábado","Domingo")) -> Quinta | Q103: =IF(B103="","",IF(B103<TIME(12,0,0),"Manhã",IF(B103<TIME(18,0,0),"Tarde","Noite"))) -> Manhã | R103: =IF(AND(H103="Realizado",L103<>"",A103<=Config!$B$9),L103/60,0) -> 0.5 | S103: =IF(G103="","",IFERROR(INDEX(Config!$K$5:$K$16,MATCH(G103,Config!$J$5:$J$16,0)),"")) -> 30 | T103: =IF(OR(G103="",F103=""),"",IFERROR(INDEX(Config!$M$5:$R$16,MATCH(G103,Config!$J$5:$J$16,0),MATCH(F103,Config!$H$5:$H$10,0)),"")) -> 120 | U103: =IF(AND(H103="Realizado",L103<>""),L103/60,0) -> 0.5 | V103: =IF(AND(H103="Realizado",OR(L103="",M103="")),1,0) -> 0
A104: 46184 | B104: 0.43055556 | C104: Dra. Carolina Mendes | D104: Sala 1 | E104: Daniel Melo | F104: Saúde Total | G104: Consulta | H104: Realizado | I104: Convênio | L104: 30 | M104: 120 | N104: =IF(A104="","",MONTH(A104)) -> 6 | O104: =IF(A104="","",YEAR(A104)) -> 2026 | P104: =IF(A104="","",CHOOSE(WEEKDAY(A104,2),"Segunda","Terça","Quarta","Quinta","Sexta","Sábado","Domingo")) -> Quinta | Q104: =IF(B104="","",IF(B104<TIME(12,0,0),"Manhã",IF(B104<TIME(18,0,0),"Tarde","Noite"))) -> Manhã | R104: =IF(AND(H104="Realizado",L104<>"",A104<=Config!$B$9),L104/60,0) -> 0.5 | S104: =IF(G104="","",IFERROR(INDEX(Config!$K$5:$K$16,MATCH(G104,Config!$J$5:$J$16,0)),"")) -> 30 | T104: =IF(OR(G104="",F104=""),"",IFERROR(INDEX(Config!$M$5:$R$16,MATCH(G104,Config!$J$5:$J$16,0),MATCH(F104,Config!$H$5:$H$10,0)),"")) -> 120 | U104: =IF(AND(H104="Realizado",L104<>""),L104/60,0) -> 0.5 | V104: =IF(AND(H104="Realizado",OR(L104="",M104="")),1,0) -> 0
A105: 46184 | B105: 0.45138889 | C105: Dra. Carolina Mendes | D105: Sala 1 | E105: Wagner Santos | F105: Particular | G105: Consulta | H105: Realizado | I105: Pix | L105: 30 | M105: 380 | N105: =IF(A105="","",MONTH(A105)) -> 6 | O105: =IF(A105="","",YEAR(A105)) -> 2026 | P105: =IF(A105="","",CHOOSE(WEEKDAY(A105,2),"Segunda","Terça","Quarta","Quinta","Sexta","Sábado","Domingo")) -> Quinta | Q105: =IF(B105="","",IF(B105<TIME(12,0,0),"Manhã",IF(B105<TIME(18,0,0),"Tarde","Noite"))) -> Manhã | R105: =IF(AND(H105="Realizado",L105<>"",A105<=Config!$B$9),L105/60,0) -> 0.5 | S105: =IF(G105="","",IFERROR(INDEX(Config!$K$5:$K$16,MATCH(G105,Config!$J$5:$J$16,0)),"")) -> 30 | T105: =IF(OR(G105="",F105=""),"",IFERROR(INDEX(Config!$M$5:$R$16,MATCH(G105,Config!$J$5:$J$16,0),MATCH(F105,Config!$H$5:$H$10,0)),"")) -> 380 | U105: =IF(AND(H105="Realizado",L105<>""),L105/60,0) -> 0.5 | V105: =IF(AND(H105="Realizado",OR(L105="",M105="")),1,0) -> 0
A106: 46184 | B106: 0.47222222 | C106: Dra. Carolina Mendes | D106: Sala 1 | E106: Isabela Pinto | F106: Saúde Total | G106: Consulta | H106: Realizado | I106: Convênio | L106: 30 | M106: 120 | N106: =IF(A106="","",MONTH(A106)) -> 6 | O106: =IF(A106="","",YEAR(A106)) -> 2026 | P106: =IF(A106="","",CHOOSE(WEEKDAY(A106,2),"Segunda","Terça","Quarta","Quinta","Sexta","Sábado","Domingo")) -> Quinta | Q106: =IF(B106="","",IF(B106<TIME(12,0,0),"Manhã",IF(B106<TIME(18,0,0),"Tarde","Noite"))) -> Manhã | R106: =IF(AND(H106="Realizado",L106<>"",A106<=Config!$B$9),L106/60,0) -> 0.5 | S106: =IF(G106="","",IFERROR(INDEX(Config!$K$5:$K$16,MATCH(G106,Config!$J$5:$J$16,0)),"")) -> 30 | T106: =IF(OR(G106="",F106=""),"",IFERROR(INDEX(Config!$M$5:$R$16,MATCH(G106,Config!$J$5:$J$16,0),MATCH(F106,Config!$H$5:$H$10,0)),"")) -> 120 | U106: =IF(AND(H106="Realizado",L106<>""),L106/60,0) -> 0.5 | V106: =IF(AND(H106="Realizado",OR(L106="",M106="")),1,0) -> 0
A107: 46184 | B107: 0.58333333 | C107: Dra. Renata Sousa | D107: Sala 1 | E107: Daniel Moreira | F107: Saúde Total | G107: Avaliação endócrina | H107: Realizado | I107: Convênio | L107: 40 | M107: 130 | N107: =IF(A107="","",MONTH(A107)) -> 6 | O107: =IF(A107="","",YEAR(A107)) -> 2026 | P107: =IF(A107="","",CHOOSE(WEEKDAY(A107,2),"Segunda","Terça","Quarta","Quinta","Sexta","Sábado","Domingo")) -> Quinta | Q107: =IF(B107="","",IF(B107<TIME(12,0,0),"Manhã",IF(B107<TIME(18,0,0),"Tarde","Noite"))) -> Tarde | R107: =IF(AND(H107="Realizado",L107<>"",A107<=Config!$B$9),L107/60,0) -> 0.66666667 | S107: =IF(G107="","",IFERROR(INDEX(Config!$K$5:$K$16,MATCH(G107,Config!$J$5:$J$16,0)),"")) -> 40 | T107: =IF(OR(G107="",F107=""),"",IFERROR(INDEX(Config!$M$5:$R$16,MATCH(G107,Config!$J$5:$J$16,0),MATCH(F107,Config!$H$5:$H$10,0)),"")) -> 130 | U107: =IF(AND(H107="Realizado",L107<>""),L107/60,0) -> 0.66666667 | V107: =IF(AND(H107="Realizado",OR(L107="",M107="")),1,0) -> 0
A108: 46184 | B108: 0.58333333 | C108: Dr. Paulo Andrade | D108: Sala 2 | E108: Fábio Correia | F108: Particular | G108: Consulta | H108: Falta | L108: 30 | M108: 380 | N108: =IF(A108="","",MONTH(A108)) -> 6 | O108: =IF(A108="","",YEAR(A108)) -> 2026 | P108: =IF(A108="","",CHOOSE(WEEKDAY(A108,2),"Segunda","Terça","Quarta","Quinta","Sexta","Sábado","Domingo")) -> Quinta | Q108: =IF(B108="","",IF(B108<TIME(12,0,0),"Manhã",IF(B108<TIME(18,0,0),"Tarde","Noite"))) -> Tarde | R108: =IF(AND(H108="Realizado",L108<>"",A108<=Config!$B$9),L108/60,0) -> 0 | S108: =IF(G108="","",IFERROR(INDEX(Config!$K$5:$K$16,MATCH(G108,Config!$J$5:$J$16,0)),"")) -> 30 | T108: =IF(OR(G108="",F108=""),"",IFERROR(INDEX(Config!$M$5:$R$16,MATCH(G108,Config!$J$5:$J$16,0),MATCH(F108,Config!$H$5:$H$10,0)),"")) -> 380 | U108: =IF(AND(H108="Realizado",L108<>""),L108/60,0) -> 0 | V108: =IF(AND(H108="Realizado",OR(L108="",M108="")),1,0) -> 0
A109: 46184 | B109: 0.60416667 | C109: Dr. Paulo Andrade | D109: Sala 2 | E109: Priscila Pinto | F109: Saúde Total | G109: Consulta | H109: Realizado | I109: Convênio | L109: 30 | M109: 120 | N109: =IF(A109="","",MONTH(A109)) -> 6 | O109: =IF(A109="","",YEAR(A109)) -> 2026 | P109: =IF(A109="","",CHOOSE(WEEKDAY(A109,2),"Segunda","Terça","Quarta","Quinta","Sexta","Sábado","Domingo")) -> Quinta | Q109: =IF(B109="","",IF(B109<TIME(12,0,0),"Manhã",IF(B109<TIME(18,0,0),"Tarde","Noite"))) -> Tarde | R109: =IF(AND(H109="Realizado",L109<>"",A109<=Config!$B$9),L109/60,0) -> 0.5 | S109: =IF(G109="","",IFERROR(INDEX(Config!$K$5:$K$16,MATCH(G109,Config!$J$5:$J$16,0)),"")) -> 30 | T109: =IF(OR(G109="",F109=""),"",IFERROR(INDEX(Config!$M$5:$R$16,MATCH(G109,Config!$J$5:$J$16,0),MATCH(F109,Config!$H$5:$H$10,0)),"")) -> 120 | U109: =IF(AND(H109="Realizado",L109<>""),L109/60,0) -> 0.5 | V109: =IF(AND(H109="Realizado",OR(L109="",M109="")),1,0) -> 0
A110: 46184 | B110: 0.63194444 | C110: Dra. Renata Sousa | D110: Sala 1 | E110: Roberta Lima | F110: Particular | G110: Avaliação endócrina | H110: Realizado | I110: Pix | L110: 40 | M110: 400 | N110: =IF(A110="","",MONTH(A110)) -> 6 | O110: =IF(A110="","",YEAR(A110)) -> 2026 | P110: =IF(A110="","",CHOOSE(WEEKDAY(A110,2),"Segunda","Terça","Quarta","Quinta","Sexta","Sábado","Domingo")) -> Quinta | Q110: =IF(B110="","",IF(B110<TIME(12,0,0),"Manhã",IF(B110<TIME(18,0,0),"Tarde","Noite"))) -> Tarde | R110: =IF(AND(H110="Realizado",L110<>"",A110<=Config!$B$9),L110/60,0) -> 0.66666667 | S110: =IF(G110="","",IFERROR(INDEX(Config!$K$5:$K$16,MATCH(G110,Config!$J$5:$J$16,0)),"")) -> 40 | T110: =IF(OR(G110="",F110=""),"",IFERROR(INDEX(Config!$M$5:$R$16,MATCH(G110,Config!$J$5:$J$16,0),MATCH(F110,Config!$H$5:$H$10,0)),"")) -> 400 | U110: =IF(AND(H110="Realizado",L110<>""),L110/60,0) -> 0.66666667 | V110: =IF(AND(H110="Realizado",OR(L110="",M110="")),1,0) -> 0
A111: 46184 | B111: 0.64583333 | C111: Dr. Paulo Andrade | D111: Sala 2 | E111: Fábio Martins | F111: MediPlan | G111: ECG | H111: Realizado | I111: Convênio | L111: 20 | M111: 35 | N111: =IF(A111="","",MONTH(A111)) -> 6 | O111: =IF(A111="","",YEAR(A111)) -> 2026 | P111: =IF(A111="","",CHOOSE(WEEKDAY(A111,2),"Segunda","Terça","Quarta","Quinta","Sexta","Sábado","Domingo")) -> Quinta | Q111: =IF(B111="","",IF(B111<TIME(12,0,0),"Manhã",IF(B111<TIME(18,0,0),"Tarde","Noite"))) -> Tarde | R111: =IF(AND(H111="Realizado",L111<>"",A111<=Config!$B$9),L111/60,0) -> 0.33333333 | S111: =IF(G111="","",IFERROR(INDEX(Config!$K$5:$K$16,MATCH(G111,Config!$J$5:$J$16,0)),"")) -> 20 | T111: =IF(OR(G111="",F111=""),"",IFERROR(INDEX(Config!$M$5:$R$16,MATCH(G111,Config!$J$5:$J$16,0),MATCH(F111,Config!$H$5:$H$10,0)),"")) -> 35 | U111: =IF(AND(H111="Realizado",L111<>""),L111/60,0) -> 0.33333333 | V111: =IF(AND(H111="Realizado",OR(L111="",M111="")),1,0) -> 0
A112: 46184 | B112: 0.65972222 | C112: Dr. Paulo Andrade | D112: Sala 2 | E112: Rafael Araújo | F112: MediPlan | G112: Consulta | H112: Cancelado | L112: 30 | M112: 100 | N112: =IF(A112="","",MONTH(A112)) -> 6 | O112: =IF(A112="","",YEAR(A112)) -> 2026 | P112: =IF(A112="","",CHOOSE(WEEKDAY(A112,2),"Segunda","Terça","Quarta","Quinta","Sexta","Sábado","Domingo")) -> Quinta | Q112: =IF(B112="","",IF(B112<TIME(12,0,0),"Manhã",IF(B112<TIME(18,0,0),"Tarde","Noite"))) -> Tarde | R112: =IF(AND(H112="Realizado",L112<>"",A112<=Config!$B$9),L112/60,0) -> 0 | S112: =IF(G112="","",IFERROR(INDEX(Config!$K$5:$K$16,MATCH(G112,Config!$J$5:$J$16,0)),"")) -> 30 | T112: =IF(OR(G112="",F112=""),"",IFERROR(INDEX(Config!$M$5:$R$16,MATCH(G112,Config!$J$5:$J$16,0),MATCH(F112,Config!$H$5:$H$10,0)),"")) -> 100 | U112: =IF(AND(H112="Realizado",L112<>""),L112/60,0) -> 0 | V112: =IF(AND(H112="Realizado",OR(L112="",M112="")),1,0) -> 0
...
