Workbook

Sheet Como usar
A1: Precificação de consulta e procedimento
A2: Kit de Gestão para Médicos · Seu Sócio Gestor · versão 1.0 (setembro de 2026)
A4: O que esta planilha faz | B4: Calcula o custo cheio de cada consulta e procedimento (tempo × custo-hora + material, com o tempo de retorno embutido nas consultas), o preço mínimo (margem mínima) e o preço alvo (margem alvo), e mostra a margem do preço particular praticado e de cada tabela de convênio.
A5: Passo 1 | B5: Em Config, copie o custo-hora da planilha 05, a alíquota de impostos e as margens mínima e alvo. Ajuste a média de retornos por consulta e a duração do retorno. Liste até 4 convênios.
A6: Passo 2 | B6: Em Precificação, uma linha por procedimento: minutos, se gera retorno, material por atendimento, o preço particular que você pratica hoje e a tabela de cada convênio. Copie os valores da planilha 08 · Tabela de preços: ela é a fonte única da tabela no kit (a 07 e a Config da 01 também copiam de lá).
A7: Passo 3 | B7: Leia a Situação e as margens: vermelho não cobre o custo cheio; amarelo cobre o custo mas não a margem mínima; verde está na faixa. Use o bloco "Simular" para testar um procedimento ou um preço novo antes de mudar a tabela.
A8: Rotina | B8: Revise quando o custo-hora mudar (05) ou uma vez por semestre. Decidiu mudar um preço? Atualize na ordem: 08 (tabela de preços, a fonte) → 06 (esta) → 07 (simulador) → 01 (Config da agenda). Assim os quatro arquivos continuam com o mesmo número.
A9: Convênio abaixo do custo | B9: Não decida só por esta tela: com horários vazios, uma tabela baixa ainda pode contribuir; com agenda cheia, toma o lugar de um particular. A planilha 07 faz essa conta com prazo de pagamento e glosa.
A10: Com a IA | B10: Copie a tabela Precificação (sem os nomes dos convênios, se preferir) e use o prompt "Preço 02 · Revisar a tabela de preços pela margem" da biblioteca do kit. A IA ajuda a explicar o número ao sócio; o preço é decisão da clínica.
A11: Legenda | B11: Células amarelas: você preenche. Brancas: calculadas. Não é preciso mexer em nada fora do amarelo.
A12: Proteção | B12: Fórmulas protegidas sem senha. Para editar: Revisar > Desproteger planilha (Excel) ou Dados > Proteger intervalos (Google Sheets).
A13: Requisitos | B13: Excel 2016 ou mais novo, Microsoft 365 ou Google Sheets (só funções do Excel 2007+; nada de MÍNIMOSES, MÁXIMOSES ou UNIRTEXTO). No celular abre nos aplicativos; para preencher, use o computador.
A14: Dados de pacientes | B14: Guarde só o que a gestão precisa (nome, contato, valor, data). Nada de diagnóstico, prontuário ou exame nestas planilhas: o kit é gestão, não é prontuário. Veja o guia LGPD do kit antes de colar qualquer tabela em uma IA.
A15: Google Sheets | B15: Faça upload no Google Drive e abra com o Google Sheets. Fórmulas, listas, cores, semáforos e gráficos funcionam: as regras de cor que dependem do mês escolhido em Config usam INDIRECT, que é a forma que o Sheets aceita para regra condicional apontar para outra aba.
... A18: Suporte | B18: suporte@seusociogestor.com.br · resposta em até 5 dias úteis · reembolso em até 7 dias pelo mesmo canal.

Sheet Precificação
A1: =Config!$B$4&" · Precificação de consulta e procedimento · "&Config!$B$5 -> Clínica Vida Plena (exemplo fictício) · Precificação de consulta e procedimento · Setembro de 2026
A2: Amarelo: procedimento, minutos, se gera retorno, material, preço particular praticado e tabelas de convênio. O resto é calculado: custo cheio, preço mínimo, preço alvo e margem por pagador.
A4: Procedimento | B4: Minutos | C4: Gera retorno? | D4: Material (R$) | E4: Tempo com retorno (min) | F4: Custo cheio (R$) | G4: Preço mínimo (R$) | H4: Preço alvo (R$) | I4: Particular praticado (R$) | J4: Margem no particular | K4: Situação | L4: =IF(Config!$B$15="","",Config!$B$15) -> Saúde Total | M4: =IF(Config!$B$15="","","Margem") -> Margem | N4: =IF(Config!$B$16="","",Config!$B$16) -> MediPlan | O4: =IF(Config!$B$16="","","Margem") -> Margem | P4: =IF(Config!$B$17="","",Config!$B$17) -> Vida Care | Q4: =IF(Config!$B$17="","","Margem") -> Margem | R4: =IF(Config!$B$18="","",Config!$B$18) | S4: =IF(Config!$B$18="","","Margem")
A5: Consulta | B5: 30 | C5: Sim | D5: 4 | E5: =IF(A5="","",IF(NOT(IF(ISNUMBER(B5),AND(B5>=0),FALSE)),"faltam os minutos",IF(AND(C5<>"Sim",C5<>"Não"),"falta: gera retorno?",IF(AND(C5="Sim",NOT(AND(IF(ISNUMBER(Config!$B$11),AND(Config!$B$11>=0),FALSE),IF(ISNUMBER(Config!$B$12),AND(Config!$B$12>=0),FALSE)))),"falta o retorno em Config",B5+IF(C5="Sim",Config!$B$11*Config!$B$12,0))))) -> 38 | F5: =IF(A5="","",IF(NOT(ISNUMBER(E5)),E5,IF(NOT(ISNUMBER(Config!$B$7)),"falta o custo-hora em Config",IF(NOT(IF(ISNUMBER(D5),AND(D5>=0),FALSE)),"falta o material",E5/60*Config!$B$7+D5)))) -> 130.66667 | G5: =IF(A5="","",IF(NOT(ISNUMBER(F5)),F5,IF((Config!$B$13<>"Sim"),"margens inválidas (Config)",F5/(1-Config!$B$8-Config!$B$9)))) -> 221.46893 | H5: =IF(A5="","",IF(NOT(ISNUMBER(F5)),F5,IF((Config!$B$13<>"Sim"),"margens inválidas (Config)",F5/(1-Config!$B$8-Config!$B$10)))) -> 296.9697 | I5: 380 | J5: =IF(OR(A5="",I5="",NOT(ISNUMBER(I5)),N(I5)=0,NOT(ISNUMBER(F5)),(Config!$B$13<>"Sim")),"",(I5*(1-Config!$B$8)-F5)/I5) -> 0.54614035 | K5: =IF(OR(A5="",I5=""),"",IF(NOT(ISNUMBER(I5)),"Preço inválido",IF(NOT(ISNUMBER(F5)),IF(ISNUMBER(Config!$B$7),"Faltam dados da linha","Falta o custo-hora"),IF(OR(NOT(ISNUMBER(G5)),NOT(ISNUMBER(H5))),"Margens inválidas",IF(I5=0,"Sem cobrança",IF(I5<G5,"Abaixo do mínimo",IF(I5<H5,"Entre mínimo e alvo","No alvo ou acima"))))))) -> No alvo ou acima | L5: 120 | M5: =IF(OR(A5="",L5="",NOT(ISNUMBER(L5)),N(L5)=0,NOT(ISNUMBER(F5)),(Config!$B$13<>"Sim")),"",(L5*(1-Config!$B$8)-F5)/L5) -> -0.19888889 | N5: 100 | O5: =IF(OR(A5="",N5="",NOT(ISNUMBER(N5)),N(N5)=0,NOT(ISNUMBER(F5)),(Config!$B$13<>"Sim")),"",(N5*(1-Config!$B$8)-F5)/N5) -> -0.41666667 | P5: 90 | Q5: =IF(OR(A5="",P5="",NOT(ISNUMBER(P5)),N(P5)=0,NOT(ISNUMBER(F5)),(Config!$B$13<>"Sim")),"",(P5*(1-Config!$B$8)-F5)/P5) -> -0.56185185 | S5: =IF(OR(A5="",R5="",NOT(ISNUMBER(R5)),N(R5)=0,NOT(ISNUMBER(F5)),(Config!$B$13<>"Sim")),"",(R5*(1-Config!$B$8)-F5)/R5) | T5: =IF(AND(ISNUMBER(M5),M5<0),M5*L5,0) -> -23.866667 | U5: =IF(AND(ISNUMBER(O5),O5<0),O5*N5,0) -> -41.666667 | V5: =IF(AND(ISNUMBER(Q5),Q5<0),Q5*P5,0) -> -50.566667 | W5: =IF(AND(ISNUMBER(S5),S5<0),S5*R5,0) -> 0
A6: Retorno | B6: 20 | C6: Não | D6: 2 | E6: =IF(A6="","",IF(NOT(IF(ISNUMBER(B6),AND(B6>=0),FALSE)),"faltam os minutos",IF(AND(C6<>"Sim",C6<>"Não"),"falta: gera retorno?",IF(AND(C6="Sim",NOT(AND(IF(ISNUMBER(Config!$B$11),AND(Config!$B$11>=0),FALSE),IF(ISNUMBER(Config!$B$12),AND(Config!$B$12>=0),FALSE)))),"falta o retorno em Config",B6+IF(C6="Sim",Config!$B$11*Config!$B$12,0))))) -> 20 | F6: =IF(A6="","",IF(NOT(ISNUMBER(E6)),E6,IF(NOT(ISNUMBER(Config!$B$7)),"falta o custo-hora em Config",IF(NOT(IF(ISNUMBER(D6),AND(D6>=0),FALSE)),"falta o material",E6/60*Config!$B$7+D6)))) -> 68.666667 | G6: =IF(A6="","",IF(NOT(ISNUMBER(F6)),F6,IF((Config!$B$13<>"Sim"),"margens inválidas (Config)",F6/(1-Config!$B$8-Config!$B$9)))) -> 116.38418 | H6: =IF(A6="","",IF(NOT(ISNUMBER(F6)),F6,IF((Config!$B$13<>"Sim"),"margens inválidas (Config)",F6/(1-Config!$B$8-Config!$B$10)))) -> 156.06061 | I6: 0 | J6: =IF(OR(A6="",I6="",NOT(ISNUMBER(I6)),N(I6)=0,NOT(ISNUMBER(F6)),(Config!$B$13<>"Sim")),"",(I6*(1-Config!$B$8)-F6)/I6) | K6: =IF(OR(A6="",I6=""),"",IF(NOT(ISNUMBER(I6)),"Preço inválido",IF(NOT(ISNUMBER(F6)),IF(ISNUMBER(Config!$B$7),"Faltam dados da linha","Falta o custo-hora"),IF(OR(NOT(ISNUMBER(G6)),NOT(ISNUMBER(H6))),"Margens inválidas",IF(I6=0,"Sem cobrança",IF(I6<G6,"Abaixo do mínimo",IF(I6<H6,"Entre mínimo e alvo","No alvo ou acima"))))))) -> Sem cobrança | L6: 0 | M6: =IF(OR(A6="",L6="",NOT(ISNUMBER(L6)),N(L6)=0,NOT(ISNUMBER(F6)),(Config!$B$13<>"Sim")),"",(L6*(1-Config!$B$8)-F6)/L6) | N6: 0 | O6: =IF(OR(A6="",N6="",NOT(ISNUMBER(N6)),N(N6)=0,NOT(ISNUMBER(F6)),(Config!$B$13<>"Sim")),"",(N6*(1-Config!$B$8)-F6)/N6) | P6: 0 | Q6: =IF(OR(A6="",P6="",NOT(ISNUMBER(P6)),N(P6)=0,NOT(ISNUMBER(F6)),(Config!$B$13<>"Sim")),"",(P6*(1-Config!$B$8)-F6)/P6) | S6: =IF(OR(A6="",R6="",NOT(ISNUMBER(R6)),N(R6)=0,NOT(ISNUMBER(F6)),(Config!$B$13<>"Sim")),"",(R6*(1-Config!$B$8)-F6)/R6) | T6: =IF(AND(ISNUMBER(M6),M6<0),M6*L6,0) -> 0 | U6: =IF(AND(ISNUMBER(O6),O6<0),O6*N6,0) -> 0 | V6: =IF(AND(ISNUMBER(Q6),Q6<0),Q6*P6,0) -> 0 | W6: =IF(AND(ISNUMBER(S6),S6<0),S6*R6,0) -> 0
A7: ECG | B7: 20 | C7: Não | D7: 8 | E7: =IF(A7="","",IF(NOT(IF(ISNUMBER(B7),AND(B7>=0),FALSE)),"faltam os minutos",IF(AND(C7<>"Sim",C7<>"Não"),"falta: gera retorno?",IF(AND(C7="Sim",NOT(AND(IF(ISNUMBER(Config!$B$11),AND(Config!$B$11>=0),FALSE),IF(ISNUMBER(Config!$B$12),AND(Config!$B$12>=0),FALSE)))),"falta o retorno em Config",B7+IF(C7="Sim",Config!$B$11*Config!$B$12,0))))) -> 20 | F7: =IF(A7="","",IF(NOT(ISNUMBER(E7)),E7,IF(NOT(ISNUMBER(Config!$B$7)),"falta o custo-hora em Config",IF(NOT(IF(ISNUMBER(D7),AND(D7>=0),FALSE)),"falta o material",E7/60*Config!$B$7+D7)))) -> 74.666667 | G7: =IF(A7="","",IF(NOT(ISNUMBER(F7)),F7,IF((Config!$B$13<>"Sim"),"margens inválidas (Config)",F7/(1-Config!$B$8-Config!$B$9)))) -> 126.55367 | H7: =IF(A7="","",IF(NOT(ISNUMBER(F7)),F7,IF((Config!$B$13<>"Sim"),"margens inválidas (Config)",F7/(1-Config!$B$8-Config!$B$10)))) -> 169.69697 | I7: 130 | J7: =IF(OR(A7="",I7="",NOT(ISNUMBER(I7)),N(I7)=0,NOT(ISNUMBER(F7)),(Config!$B$13<>"Sim")),"",(I7*(1-Config!$B$8)-F7)/I7) -> 0.31564103 | K7: =IF(OR(A7="",I7=""),"",IF(NOT(ISNUMBER(I7)),"Preço inválido",IF(NOT(ISNUMBER(F7)),IF(ISNUMBER(Config!$B$7),"Faltam dados da linha","Falta o custo-hora"),IF(OR(NOT(ISNUMBER(G7)),NOT(ISNUMBER(H7))),"Margens inválidas",IF(I7=0,"Sem cobrança",IF(I7<G7,"Abaixo do mínimo",IF(I7<H7,"Entre mínimo e alvo","No alvo ou acima"))))))) -> Entre mínimo e alvo | L7: 40 | M7: =IF(OR(A7="",L7="",NOT(ISNUMBER(L7)),N(L7)=0,NOT(ISNUMBER(F7)),(Config!$B$13<>"Sim")),"",(L7*(1-Config!$B$8)-F7)/L7) -> -0.97666667 | N7: 35 | O7: =IF(OR(A7="",N7="",NOT(ISNUMBER(N7)),N(N7)=0,NOT(ISNUMBER(F7)),(Config!$B$13<>"Sim")),"",(N7*(1-Config!$B$8)-F7)/N7) -> -1.2433333 | P7: 32 | Q7: =IF(OR(A7="",P7="",NOT(ISNUMBER(P7)),N(P7)=0,NOT(ISNUMBER(F7)),(Config!$B$13<>"Sim")),"",(P7*(1-Config!$B$8)-F7)/P7) -> -1.4433333 | S7: =IF(OR(A7="",R7="",NOT(ISNUMBER(R7)),N(R7)=0,NOT(ISNUMBER(F7)),(Config!$B$13<>"Sim")),"",(R7*(1-Config!$B$8)-F7)/R7) | T7: =IF(AND(ISNUMBER(M7),M7<0),M7*L7,0) -> -39.066667 | U7: =IF(AND(ISNUMBER(O7),O7<0),O7*N7,0) -> -43.516667 | V7: =IF(AND(ISNUMBER(Q7),Q7<0),Q7*P7,0) -> -46.186667 | W7: =IF(AND(ISNUMBER(S7),S7<0),S7*R7,0) -> 0
A8: MAPA | B8: 20 | C8: Não | D8: 15 | E8: =IF(A8="","",IF(NOT(IF(ISNUMBER(B8),AND(B8>=0),FALSE)),"faltam os minutos",IF(AND(C8<>"Sim",C8<>"Não"),"falta: gera retorno?",IF(AND(C8="Sim",NOT(AND(IF(ISNUMBER(Config!$B$11),AND(Config!$B$11>=0),FALSE),IF(ISNUMBER(Config!$B$12),AND(Config!$B$12>=0),FALSE)))),"falta o retorno em Config",B8+IF(C8="Sim",Config!$B$11*Config!$B$12,0))))) -> 20 | F8: =IF(A8="","",IF(NOT(ISNUMBER(E8)),E8,IF(NOT(ISNUMBER(Config!$B$7)),"falta o custo-hora em Config",IF(NOT(IF(ISNUMBER(D8),AND(D8>=0),FALSE)),"falta o material",E8/60*Config!$B$7+D8)))) -> 81.666667 | G8: =IF(A8="","",IF(NOT(ISNUMBER(F8)),F8,IF((Config!$B$13<>"Sim"),"margens inválidas (Config)",F8/(1-Config!$B$8-Config!$B$9)))) -> 138.41808 | H8: =IF(A8="","",IF(NOT(ISNUMBER(F8)),F8,IF((Config!$B$13<>"Sim"),"margens inválidas (Config)",F8/(1-Config!$B$8-Config!$B$10)))) -> 185.60606 | I8: 300 | J8: =IF(OR(A8="",I8="",NOT(ISNUMBER(I8)),N(I8)=0,NOT(ISNUMBER(F8)),(Config!$B$13<>"Sim")),"",(I8*(1-Config!$B$8)-F8)/I8) -> 0.61777778 | K8: =IF(OR(A8="",I8=""),"",IF(NOT(ISNUMBER(I8)),"Preço inválido",IF(NOT(ISNUMBER(F8)),IF(ISNUMBER(Config!$B$7),"Faltam dados da linha","Falta o custo-hora"),IF(OR(NOT(ISNUMBER(G8)),NOT(ISNUMBER(H8))),"Margens inválidas",IF(I8=0,"Sem cobrança",IF(I8<G8,"Abaixo do mínimo",IF(I8<H8,"Entre mínimo e alvo","No alvo ou acima"))))))) -> No alvo ou acima | L8: 95 | M8: =IF(OR(A8="",L8="",NOT(ISNUMBER(L8)),N(L8)=0,NOT(ISNUMBER(F8)),(Config!$B$13<>"Sim")),"",(L8*(1-Config!$B$8)-F8)/L8) -> 0.030350877 | N8: 85 | O8: =IF(OR(A8="",N8="",NOT(ISNUMBER(N8)),N(N8)=0,NOT(ISNUMBER(F8)),(Config!$B$13<>"Sim")),"",(N8*(1-Config!$B$8)-F8)/N8) -> -0.070784314 | P8: 75 | Q8: =IF(OR(A8="",P8="",NOT(ISNUMBER(P8)),N(P8)=0,NOT(ISNUMBER(F8)),(Config!$B$13<>"Sim")),"",(P8*(1-Config!$B$8)-F8)/P8) -> -0.19888889 | S8: =IF(OR(A8="",R8="",NOT(ISNUMBER(R8)),N(R8)=0,NOT(ISNUMBER(F8)),(Config!$B$13<>"Sim")),"",(R8*(1-Config!$B$8)-F8)/R8) | T8: =IF(AND(ISNUMBER(M8),M8<0),M8*L8,0) -> 0 | U8: =IF(AND(ISNUMBER(O8),O8<0),O8*N8,0) -> -6.0166667 | V8: =IF(AND(ISNUMBER(Q8),Q8<0),Q8*P8,0) -> -14.916667 | W8: =IF(AND(ISNUMBER(S8),S8<0),S8*R8,0) -> 0
A9: Holter | B9: 20 | C9: Não | D9: 18 | E9: =IF(A9="","",IF(NOT(IF(ISNUMBER(B9),AND(B9>=0),FALSE)),"faltam os minutos",IF(AND(C9<>"Sim",C9<>"Não"),"falta: gera retorno?",IF(AND(C9="Sim",NOT(AND(IF(ISNUMBER(Config!$B$11),AND(Config!$B$11>=0),FALSE),IF(ISNUMBER(Config!$B$12),AND(Config!$B$12>=0),FALSE)))),"falta o retorno em Config",B9+IF(C9="Sim",Config!$B$11*Config!$B$12,0))))) -> 20 | F9: =IF(A9="","",IF(NOT(ISNUMBER(E9)),E9,IF(NOT(ISNUMBER(Config!$B$7)),"falta o custo-hora em Config",IF(NOT(IF(ISNUMBER(D9),AND(D9>=0),FALSE)),"falta o material",E9/60*Config!$B$7+D9)))) -> 84.666667 | G9: =IF(A9="","",IF(NOT(ISNUMBER(F9)),F9,IF((Config!$B$13<>"Sim"),"margens inválidas (Config)",F9/(1-Config!$B$8-Config!$B$9)))) -> 143.50282 | H9: =IF(A9="","",IF(NOT(ISNUMBER(F9)),F9,IF((Config!$B$13<>"Sim"),"margens inválidas (Config)",F9/(1-Config!$B$8-Config!$B$10)))) -> 192.42424 | I9: 350 | J9: =IF(OR(A9="",I9="",NOT(ISNUMBER(I9)),N(I9)=0,NOT(ISNUMBER(F9)),(Config!$B$13<>"Sim")),"",(I9*(1-Config!$B$8)-F9)/I9) -> 0.64809524 | K9: =IF(OR(A9="",I9=""),"",IF(NOT(ISNUMBER(I9)),"Preço inválido",IF(NOT(ISNUMBER(F9)),IF(ISNUMBER(Config!$B$7),"Faltam dados da linha","Falta o custo-hora"),IF(OR(NOT(ISNUMBER(G9)),NOT(ISNUMBER(H9))),"Margens inválidas",IF(I9=0,"Sem cobrança",IF(I9<G9,"Abaixo do mínimo",IF(I9<H9,"Entre mínimo e alvo","No alvo ou acima"))))))) -> No alvo ou acima | L9: 105 | M9: =IF(OR(A9="",L9="",NOT(ISNUMBER(L9)),N(L9)=0,NOT(ISNUMBER(F9)),(Config!$B$13<>"Sim")),"",(L9*(1-Config!$B$8)-F9)/L9) -> 0.083650794 | N9: 95 | O9: =IF(OR(A9="",N9="",NOT(ISNUMBER(N9)),N(N9)=0,NOT(ISNUMBER(F9)),(Config!$B$13<>"Sim")),"",(N9*(1-Config!$B$8)-F9)/N9) -> -0.0012280702 | P9: 85 | Q9: =IF(OR(A9="",P9="",NOT(ISNUMBER(P9)),N(P9)=0,NOT(ISNUMBER(F9)),(Config!$B$13<>"Sim")),"",(P9*(1-Config!$B$8)-F9)/P9) -> -0.10607843 | S9: =IF(OR(A9="",R9="",NOT(ISNUMBER(R9)),N(R9)=0,NOT(ISNUMBER(F9)),(Config!$B$13<>"Sim")),"",(R9*(1-Config!$B$8)-F9)/R9) | T9: =IF(AND(ISNUMBER(M9),M9<0),M9*L9,0) -> 0 | U9: =IF(AND(ISNUMBER(O9),O9<0),O9*N9,0) -> -0.11666667 | V9: =IF(AND(ISNUMBER(Q9),Q9<0),Q9*P9,0) -> -9.0166667 | W9: =IF(AND(ISNUMBER(S9),S9<0),S9*R9,0) -> 0
A10: Teste ergométrico | B10: 40 | C10: Não | D10: 25 | E10: =IF(A10="","",IF(NOT(IF(ISNUMBER(B10),AND(B10>=0),FALSE)),"faltam os minutos",IF(AND(C10<>"Sim",C10<>"Não"),"falta: gera retorno?",IF(AND(C10="Sim",NOT(AND(IF(ISNUMBER(Config!$B$11),AND(Config!$B$11>=0),FALSE),IF(ISNUMBER(Config!$B$12),AND(Config!$B$12>=0),FALSE)))),"falta o retorno em Config",B10+IF(C10="Sim",Config!$B$11*Config!$B$12,0))))) -> 40 | F10: =IF(A10="","",IF(NOT(ISNUMBER(E10)),E10,IF(NOT(ISNUMBER(Config!$B$7)),"falta o custo-hora em Config",IF(NOT(IF(ISNUMBER(D10),AND(D10>=0),FALSE)),"falta o material",E10/60*Config!$B$7+D10)))) -> 158.33333 | G10: =IF(A10="","",IF(NOT(ISNUMBER(F10)),F10,IF((Config!$B$13<>"Sim"),"margens inválidas (Config)",F10/(1-Config!$B$8-Config!$B$9)))) -> 268.36158 | H10: =IF(A10="","",IF(NOT(ISNUMBER(F10)),F10,IF((Config!$B$13<>"Sim"),"margens inválidas (Config)",F10/(1-Config!$B$8-Config!$B$10)))) -> 359.84848 | I10: 450 | J10: =IF(OR(A10="",I10="",NOT(ISNUMBER(I10)),N(I10)=0,NOT(ISNUMBER(F10)),(Config!$B$13<>"Sim")),"",(I10*(1-Config!$B$8)-F10)/I10) -> 0.53814815 | K10: =IF(OR(A10="",I10=""),"",IF(NOT(ISNUMBER(I10)),"Preço inválido",IF(NOT(ISNUMBER(F10)),IF(ISNUMBER(Config!$B$7),"Faltam dados da linha","Falta o custo-hora"),IF(OR(NOT(ISNUMBER(G10)),NOT(ISNUMBER(H10))),"Margens inválidas",IF(I10=0,"Sem cobrança",IF(I10<G10,"Abaixo do mínimo",IF(I10<H10,"Entre mínimo e alvo","No alvo ou acima"))))))) -> No alvo ou acima | L10: 140 | M10: =IF(OR(A10="",L10="",NOT(ISNUMBER(L10)),N(L10)=0,NOT(ISNUMBER(F10)),(Config!$B$13<>"Sim")),"",(L10*(1-Config!$B$8)-F10)/L10) -> -0.24095238 | N10: 125 | O10: =IF(OR(A10="",N10="",NOT(ISNUMBER(N10)),N(N10)=0,NOT(ISNUMBER(F10)),(Config!$B$13<>"Sim")),"",(N10*(1-Config!$B$8)-F10)/N10) -> -0.37666667 | P10: 110 | Q10: =IF(OR(A10="",P10="",NOT(ISNUMBER(P10)),N(P10)=0,NOT(ISNUMBER(F10)),(Config!$B$13<>"Sim")),"",(P10*(1-Config!$B$8)-F10)/P10) -> -0.54939394 | S10: =IF(OR(A10="",R10="",NOT(ISNUMBER(R10)),N(R10)=0,NOT(ISNUMBER(F10)),(Config!$B$13<>"Sim")),"",(R10*(1-Config!$B$8)-F10)/R10) | T10: =IF(AND(ISNUMBER(M10),M10<0),M10*L10,0) -> -33.733333 | U10: =IF(AND(ISNUMBER(O10),O10<0),O10*N10,0) -> -47.083333 | V10: =IF(AND(ISNUMBER(Q10),Q10<0),Q10*P10,0) -> -60.433333 | W10: =IF(AND(ISNUMBER(S10),S10<0),S10*R10,0) -> 0
A11: Avaliação endócrina | B11: 40 | C11: Sim | D11: 4 | E11: =IF(A11="","",IF(NOT(IF(ISNUMBER(B11),AND(B11>=0),FALSE)),"faltam os minutos",IF(AND(C11<>"Sim",C11<>"Não"),"falta: gera retorno?",IF(AND(C11="Sim",NOT(AND(IF(ISNUMBER(Config!$B$11),AND(Config!$B$11>=0),FALSE),IF(ISNUMBER(Config!$B$12),AND(Config!$B$12>=0),FALSE)))),"falta o retorno em Config",B11+IF(C11="Sim",Config!$B$11*Config!$B$12,0))))) -> 48 | F11: =IF(A11="","",IF(NOT(ISNUMBER(E11)),E11,IF(NOT(ISNUMBER(Config!$B$7)),"falta o custo-hora em Config",IF(NOT(IF(ISNUMBER(D11),AND(D11>=0),FALSE)),"falta o material",E11/60*Config!$B$7+D11)))) -> 164 | G11: =IF(A11="","",IF(NOT(ISNUMBER(F11)),F11,IF((Config!$B$13<>"Sim"),"margens inválidas (Config)",F11/(1-Config!$B$8-Config!$B$9)))) -> 277.9661 | H11: =IF(A11="","",IF(NOT(ISNUMBER(F11)),F11,IF((Config!$B$13<>"Sim"),"margens inválidas (Config)",F11/(1-Config!$B$8-Config!$B$10)))) -> 372.72727 | I11: 400 | J11: =IF(OR(A11="",I11="",NOT(ISNUMBER(I11)),N(I11)=0,NOT(ISNUMBER(F11)),(Config!$B$13<>"Sim")),"",(I11*(1-Config!$B$8)-F11)/I11) -> 0.48 | K11: =IF(OR(A11="",I11=""),"",IF(NOT(ISNUMBER(I11)),"Preço inválido",IF(NOT(ISNUMBER(F11)),IF(ISNUMBER(Config!$B$7),"Faltam dados da linha","Falta o custo-hora"),IF(OR(NOT(ISNUMBER(G11)),NOT(ISNUMBER(H11))),"Margens inválidas",IF(I11=0,"Sem cobrança",IF(I11<G11,"Abaixo do mínimo",IF(I11<H11,"Entre mínimo e alvo","No alvo ou acima"))))))) -> No alvo ou acima | L11: 130 | M11: =IF(OR(A11="",L11="",NOT(ISNUMBER(L11)),N(L11)=0,NOT(ISNUMBER(F11)),(Config!$B$13<>"Sim")),"",(L11*(1-Config!$B$8)-F11)/L11) -> -0.37153846 | O11: =IF(OR(A11="",N11="",NOT(ISNUMBER(N11)),N(N11)=0,NOT(ISNUMBER(F11)),(Config!$B$13<>"Sim")),"",(N11*(1-Config!$B$8)-F11)/N11) | Q11: =IF(OR(A11="",P11="",NOT(ISNUMBER(P11)),N(P11)=0,NOT(ISNUMBER(F11)),(Config!$B$13<>"Sim")),"",(P11*(1-Config!$B$8)-F11)/P11) | S11: =IF(OR(A11="",R11="",NOT(ISNUMBER(R11)),N(R11)=0,NOT(ISNUMBER(F11)),(Config!$B$13<>"Sim")),"",(R11*(1-Config!$B$8)-F11)/R11) | T11: =IF(AND(ISNUMBER(M11),M11<0),M11*L11,0) -> -48.3 | U11: =IF(AND(ISNUMBER(O11),O11<0),O11*N11,0) -> 0 | V11: =IF(AND(ISNUMBER(Q11),Q11<0),Q11*P11,0) -> 0 | W11: =IF(AND(ISNUMBER(S11),S11<0),S11*R11,0) -> 0
E12: =IF(A12="","",IF(NOT(IF(ISNUMBER(B12),AND(B12>=0),FALSE)),"faltam os minutos",IF(AND(C12<>"Sim",C12<>"Não"),"falta: gera retorno?",IF(AND(C12="Sim",NOT(AND(IF(ISNUMBER(Config!$B$11),AND(Config!$B$11>=0),FALSE),IF(ISNUMBER(Config!$B$12),AND(Config!$B$12>=0),FALSE)))),"falta o retorno em Config",B12+IF(C12="Sim",Config!$B$11*Config!$B$12,0))))) | F12: =IF(A12="","",IF(NOT(ISNUMBER(E12)),E12,IF(NOT(ISNUMBER(Config!$B$7)),"falta o custo-hora em Config",IF(NOT(IF(ISNUMBER(D12),AND(D12>=0),FALSE)),"falta o material",E12/60*Config!$B$7+D12)))) | G12: =IF(A12="","",IF(NOT(ISNUMBER(F12)),F12,IF((Config!$B$13<>"Sim"),"margens inválidas (Config)",F12/(1-Config!$B$8-Config!$B$9)))) | H12: =IF(A12="","",IF(NOT(ISNUMBER(F12)),F12,IF((Config!$B$13<>"Sim"),"margens inválidas (Config)",F12/(1-Config!$B$8-Config!$B$10)))) | J12: =IF(OR(A12="",I12="",NOT(ISNUMBER(I12)),N(I12)=0,NOT(ISNUMBER(F12)),(Config!$B$13<>"Sim")),"",(I12*(1-Config!$B$8)-F12)/I12) | K12: =IF(OR(A12="",I12=""),"",IF(NOT(ISNUMBER(I12)),"Preço inválido",IF(NOT(ISNUMBER(F12)),IF(ISNUMBER(Config!$B$7),"Faltam dados da linha","Falta o custo-hora"),IF(OR(NOT(ISNUMBER(G12)),NOT(ISNUMBER(H12))),"Margens inválidas",IF(I12=0,"Sem cobrança",IF(I12<G12,"Abaixo do mínimo",IF(I12<H12,"Entre mínimo e alvo","No alvo ou acima"))))))) | M12: =IF(OR(A12="",L12="",NOT(ISNUMBER(L12)),N(L12)=0,NOT(ISNUMBER(F12)),(Config!$B$13<>"Sim")),"",(L12*(1-Config!$B$8)-F12)/L12) | O12: =IF(OR(A12="",N12="",NOT(ISNUMBER(N12)),N(N12)=0,NOT(ISNUMBER(F12)),(Config!$B$13<>"Sim")),"",(N12*(1-Config!$B$8)-F12)/N12) | Q12: =IF(OR(A12="",P12="",NOT(ISNUMBER(P12)),N(P12)=0,NOT(ISNUMBER(F12)),(Config!$B$13<>"Sim")),"",(P12*(1-Config!$B$8)-F12)/P12) | S12: =IF(OR(A12="",R12="",NOT(ISNUMBER(R12)),N(R12)=0,NOT(ISNUMBER(F12)),(Config!$B$13<>"Sim")),"",(R12*(1-Config!$B$8)-F12)/R12) | T12: =IF(AND(ISNUMBER(M12),M12<0),M12*L12,0) -> 0 | U12: =IF(AND(ISNUMBER(O12),O12<0),O12*N12,0) -> 0 | V12: =IF(AND(ISNUMBER(Q12),Q12<0),Q12*P12,0) -> 0 | W12: =IF(AND(ISNUMBER(S12),S12<0),S12*R12,0) -> 0
E13: =IF(A13="","",IF(NOT(IF(ISNUMBER(B13),AND(B13>=0),FALSE)),"faltam os minutos",IF(AND(C13<>"Sim",C13<>"Não"),"falta: gera retorno?",IF(AND(C13="Sim",NOT(AND(IF(ISNUMBER(Config!$B$11),AND(Config!$B$11>=0),FALSE),IF(ISNUMBER(Config!$B$12),AND(Config!$B$12>=0),FALSE)))),"falta o retorno em Config",B13+IF(C13="Sim",Config!$B$11*Config!$B$12,0))))) | F13: =IF(A13="","",IF(NOT(ISNUMBER(E13)),E13,IF(NOT(ISNUMBER(Config!$B$7)),"falta o custo-hora em Config",IF(NOT(IF(ISNUMBER(D13),AND(D13>=0),FALSE)),"falta o material",E13/60*Config!$B$7+D13)))) | G13: =IF(A13="","",IF(NOT(ISNUMBER(F13)),F13,IF((Config!$B$13<>"Sim"),"margens inválidas (Config)",F13/(1-Config!$B$8-Config!$B$9)))) | H13: =IF(A13="","",IF(NOT(ISNUMBER(F13)),F13,IF((Config!$B$13<>"Sim"),"margens inválidas (Config)",F13/(1-Config!$B$8-Config!$B$10)))) | J13: =IF(OR(A13="",I13="",NOT(ISNUMBER(I13)),N(I13)=0,NOT(ISNUMBER(F13)),(Config!$B$13<>"Sim")),"",(I13*(1-Config!$B$8)-F13)/I13) | K13: =IF(OR(A13="",I13=""),"",IF(NOT(ISNUMBER(I13)),"Preço inválido",IF(NOT(ISNUMBER(F13)),IF(ISNUMBER(Config!$B$7),"Faltam dados da linha","Falta o custo-hora"),IF(OR(NOT(ISNUMBER(G13)),NOT(ISNUMBER(H13))),"Margens inválidas",IF(I13=0,"Sem cobrança",IF(I13<G13,"Abaixo do mínimo",IF(I13<H13,"Entre mínimo e alvo","No alvo ou acima"))))))) | M13: =IF(OR(A13="",L13="",NOT(ISNUMBER(L13)),N(L13)=0,NOT(ISNUMBER(F13)),(Config!$B$13<>"Sim")),"",(L13*(1-Config!$B$8)-F13)/L13) | O13: =IF(OR(A13="",N13="",NOT(ISNUMBER(N13)),N(N13)=0,NOT(ISNUMBER(F13)),(Config!$B$13<>"Sim")),"",(N13*(1-Config!$B$8)-F13)/N13) | Q13: =IF(OR(A13="",P13="",NOT(ISNUMBER(P13)),N(P13)=0,NOT(ISNUMBER(F13)),(Config!$B$13<>"Sim")),"",(P13*(1-Config!$B$8)-F13)/P13) | S13: =IF(OR(A13="",R13="",NOT(ISNUMBER(R13)),N(R13)=0,NOT(ISNUMBER(F13)),(Config!$B$13<>"Sim")),"",(R13*(1-Config!$B$8)-F13)/R13) | T13: =IF(AND(ISNUMBER(M13),M13<0),M13*L13,0) -> 0 | U13: =IF(AND(ISNUMBER(O13),O13<0),O13*N13,0) -> 0 | V13: =IF(AND(ISNUMBER(Q13),Q13<0),Q13*P13,0) -> 0 | W13: =IF(AND(ISNUMBER(S13),S13<0),S13*R13,0) -> 0
E14: =IF(A14="","",IF(NOT(IF(ISNUMBER(B14),AND(B14>=0),FALSE)),"faltam os minutos",IF(AND(C14<>"Sim",C14<>"Não"),"falta: gera retorno?",IF(AND(C14="Sim",NOT(AND(IF(ISNUMBER(Config!$B$11),AND(Config!$B$11>=0),FALSE),IF(ISNUMBER(Config!$B$12),AND(Config!$B$12>=0),FALSE)))),"falta o retorno em Config",B14+IF(C14="Sim",Config!$B$11*Config!$B$12,0))))) | F14: =IF(A14="","",IF(NOT(ISNUMBER(E14)),E14,IF(NOT(ISNUMBER(Config!$B$7)),"falta o custo-hora em Config",IF(NOT(IF(ISNUMBER(D14),AND(D14>=0),FALSE)),"falta o material",E14/60*Config!$B$7+D14)))) | G14: =IF(A14="","",IF(NOT(ISNUMBER(F14)),F14,IF((Config!$B$13<>"Sim"),"margens inválidas (Config)",F14/(1-Config!$B$8-Config!$B$9)))) | H14: =IF(A14="","",IF(NOT(ISNUMBER(F14)),F14,IF((Config!$B$13<>"Sim"),"margens inválidas (Config)",F14/(1-Config!$B$8-Config!$B$10)))) | J14: =IF(OR(A14="",I14="",NOT(ISNUMBER(I14)),N(I14)=0,NOT(ISNUMBER(F14)),(Config!$B$13<>"Sim")),"",(I14*(1-Config!$B$8)-F14)/I14) | K14: =IF(OR(A14="",I14=""),"",IF(NOT(ISNUMBER(I14)),"Preço inválido",IF(NOT(ISNUMBER(F14)),IF(ISNUMBER(Config!$B$7),"Faltam dados da linha","Falta o custo-hora"),IF(OR(NOT(ISNUMBER(G14)),NOT(ISNUMBER(H14))),"Margens inválidas",IF(I14=0,"Sem cobrança",IF(I14<G14,"Abaixo do mínimo",IF(I14<H14,"Entre mínimo e alvo","No alvo ou acima"))))))) | M14: =IF(OR(A14="",L14="",NOT(ISNUMBER(L14)),N(L14)=0,NOT(ISNUMBER(F14)),(Config!$B$13<>"Sim")),"",(L14*(1-Config!$B$8)-F14)/L14) | O14: =IF(OR(A14="",N14="",NOT(ISNUMBER(N14)),N(N14)=0,NOT(ISNUMBER(F14)),(Config!$B$13<>"Sim")),"",(N14*(1-Config!$B$8)-F14)/N14) | Q14: =IF(OR(A14="",P14="",NOT(ISNUMBER(P14)),N(P14)=0,NOT(ISNUMBER(F14)),(Config!$B$13<>"Sim")),"",(P14*(1-Config!$B$8)-F14)/P14) | S14: =IF(OR(A14="",R14="",NOT(ISNUMBER(R14)),N(R14)=0,NOT(ISNUMBER(F14)),(Config!$B$13<>"Sim")),"",(R14*(1-Config!$B$8)-F14)/R14) | T14: =IF(AND(ISNUMBER(M14),M14<0),M14*L14,0) -> 0 | U14: =IF(AND(ISNUMBER(O14),O14<0),O14*N14,0) -> 0 | V14: =IF(AND(ISNUMBER(Q14),Q14<0),Q14*P14,0) -> 0 | W14: =IF(AND(ISNUMBER(S14),S14<0),S14*R14,0) -> 0
E15: =IF(A15="","",IF(NOT(IF(ISNUMBER(B15),AND(B15>=0),FALSE)),"faltam os minutos",IF(AND(C15<>"Sim",C15<>"Não"),"falta: gera retorno?",IF(AND(C15="Sim",NOT(AND(IF(ISNUMBER(Config!$B$11),AND(Config!$B$11>=0),FALSE),IF(ISNUMBER(Config!$B$12),AND(Config!$B$12>=0),FALSE)))),"falta o retorno em Config",B15+IF(C15="Sim",Config!$B$11*Config!$B$12,0))))) | F15: =IF(A15="","",IF(NOT(ISNUMBER(E15)),E15,IF(NOT(ISNUMBER(Config!$B$7)),"falta o custo-hora em Config",IF(NOT(IF(ISNUMBER(D15),AND(D15>=0),FALSE)),"falta o material",E15/60*Config!$B$7+D15)))) | G15: =IF(A15="","",IF(NOT(ISNUMBER(F15)),F15,IF((Config!$B$13<>"Sim"),"margens inválidas (Config)",F15/(1-Config!$B$8-Config!$B$9)))) | H15: =IF(A15="","",IF(NOT(ISNUMBER(F15)),F15,IF((Config!$B$13<>"Sim"),"margens inválidas (Config)",F15/(1-Config!$B$8-Config!$B$10)))) | J15: =IF(OR(A15="",I15="",NOT(ISNUMBER(I15)),N(I15)=0,NOT(ISNUMBER(F15)),(Config!$B$13<>"Sim")),"",(I15*(1-Config!$B$8)-F15)/I15) | K15: =IF(OR(A15="",I15=""),"",IF(NOT(ISNUMBER(I15)),"Preço inválido",IF(NOT(ISNUMBER(F15)),IF(ISNUMBER(Config!$B$7),"Faltam dados da linha","Falta o custo-hora"),IF(OR(NOT(ISNUMBER(G15)),NOT(ISNUMBER(H15))),"Margens inválidas",IF(I15=0,"Sem cobrança",IF(I15<G15,"Abaixo do mínimo",IF(I15<H15,"Entre mínimo e alvo","No alvo ou acima"))))))) | M15: =IF(OR(A15="",L15="",NOT(ISNUMBER(L15)),N(L15)=0,NOT(ISNUMBER(F15)),(Config!$B$13<>"Sim")),"",(L15*(1-Config!$B$8)-F15)/L15) | O15: =IF(OR(A15="",N15="",NOT(ISNUMBER(N15)),N(N15)=0,NOT(ISNUMBER(F15)),(Config!$B$13<>"Sim")),"",(N15*(1-Config!$B$8)-F15)/N15) | Q15: =IF(OR(A15="",P15="",NOT(ISNUMBER(P15)),N(P15)=0,NOT(ISNUMBER(F15)),(Config!$B$13<>"Sim")),"",(P15*(1-Config!$B$8)-F15)/P15) | S15: =IF(OR(A15="",R15="",NOT(ISNUMBER(R15)),N(R15)=0,NOT(ISNUMBER(F15)),(Config!$B$13<>"Sim")),"",(R15*(1-Config!$B$8)-F15)/R15) | T15: =IF(AND(ISNUMBER(M15),M15<0),M15*L15,0) -> 0 | U15: =IF(AND(ISNUMBER(O15),O15<0),O15*N15,0) -> 0 | V15: =IF(AND(ISNUMBER(Q15),Q15<0),Q15*P15,0) -> 0 | W15: =IF(AND(ISNUMBER(S15),S15<0),S15*R15,0) -> 0
E16: =IF(A16="","",IF(NOT(IF(ISNUMBER(B16),AND(B16>=0),FALSE)),"faltam os minutos",IF(AND(C16<>"Sim",C16<>"Não"),"falta: gera retorno?",IF(AND(C16="Sim",NOT(AND(IF(ISNUMBER(Config!$B$11),AND(Config!$B$11>=0),FALSE),IF(ISNUMBER(Config!$B$12),AND(Config!$B$12>=0),FALSE)))),"falta o retorno em Config",B16+IF(C16="Sim",Config!$B$11*Config!$B$12,0))))) | F16: =IF(A16="","",IF(NOT(ISNUMBER(E16)),E16,IF(NOT(ISNUMBER(Config!$B$7)),"falta o custo-hora em Config",IF(NOT(IF(ISNUMBER(D16),AND(D16>=0),FALSE)),"falta o material",E16/60*Config!$B$7+D16)))) | G16: =IF(A16="","",IF(NOT(ISNUMBER(F16)),F16,IF((Config!$B$13<>"Sim"),"margens inválidas (Config)",F16/(1-Config!$B$8-Config!$B$9)))) | H16: =IF(A16="","",IF(NOT(ISNUMBER(F16)),F16,IF((Config!$B$13<>"Sim"),"margens inválidas (Config)",F16/(1-Config!$B$8-Config!$B$10)))) | J16: =IF(OR(A16="",I16="",NOT(ISNUMBER(I16)),N(I16)=0,NOT(ISNUMBER(F16)),(Config!$B$13<>"Sim")),"",(I16*(1-Config!$B$8)-F16)/I16) | K16: =IF(OR(A16="",I16=""),"",IF(NOT(ISNUMBER(I16)),"Preço inválido",IF(NOT(ISNUMBER(F16)),IF(ISNUMBER(Config!$B$7),"Faltam dados da linha","Falta o custo-hora"),IF(OR(NOT(ISNUMBER(G16)),NOT(ISNUMBER(H16))),"Margens inválidas",IF(I16=0,"Sem cobrança",IF(I16<G16,"Abaixo do mínimo",IF(I16<H16,"Entre mínimo e alvo","No alvo ou acima"))))))) | M16: =IF(OR(A16="",L16="",NOT(ISNUMBER(L16)),N(L16)=0,NOT(ISNUMBER(F16)),(Config!$B$13<>"Sim")),"",(L16*(1-Config!$B$8)-F16)/L16) | O16: =IF(OR(A16="",N16="",NOT(ISNUMBER(N16)),N(N16)=0,NOT(ISNUMBER(F16)),(Config!$B$13<>"Sim")),"",(N16*(1-Config!$B$8)-F16)/N16) | Q16: =IF(OR(A16="",P16="",NOT(ISNUMBER(P16)),N(P16)=0,NOT(ISNUMBER(F16)),(Config!$B$13<>"Sim")),"",(P16*(1-Config!$B$8)-F16)/P16) | S16: =IF(OR(A16="",R16="",NOT(ISNUMBER(R16)),N(R16)=0,NOT(ISNUMBER(F16)),(Config!$B$13<>"Sim")),"",(R16*(1-Config!$B$8)-F16)/R16) | T16: =IF(AND(ISNUMBER(M16),M16<0),M16*L16,0) -> 0 | U16: =IF(AND(ISNUMBER(O16),O16<0),O16*N16,0) -> 0 | V16: =IF(AND(ISNUMBER(Q16),Q16<0),Q16*P16,0) -> 0 | W16: =IF(AND(ISNUMBER(S16),S16<0),S16*R16,0) -> 0
A18: Custo cheio = tempo (com retorno embutido) ÷ 60 × custo-hora + material. Preço mínimo = custo ÷ (1 − impostos − margem mínima); preço alvo, com a margem alvo. Margem = (preço × (1 − impostos) − custo) ÷ preço. Vermelho: não cobre o custo cheio. Amarelo: cobre o custo, mas fica abaixo da margem mínima. Verde: margem mínima ou mais.
A19: Retorno tem preço zero de propósito: o tempo dele já está no custo da consulta. Tabela de convênio abaixo do custo cheio não é automaticamente "não aceitar": com agenda vazia, o que importa é a contribuição (planilha 07).
A21: Resumo
A22: Custo da hora de atendimento (planilha 05) | E22: =IF(ISNUMBER(Config!$B$7),Config!$B$7,"falta o custo-hora em Config") -> 200
A23: Hora mínima a cobrar (custo-hora ÷ (1 − impostos − margem mínima)) | E23: =IF(NOT(ISNUMBER(Config!$B$7)),"falta o custo-hora em Config",IF((Config!$B$13<>"Sim"),"margens inválidas (Config)",IF((SUMPRODUCT(($A$5:$A$16<>"")*(ISNUMBER($F$5:$F$16)=FALSE))+SUMPRODUCT(ISTEXT($I$5:$I$16)*1)+SUMPRODUCT(ISTEXT($L$5:$L$16)*1)+SUMPRODUCT(ISTEXT($N$5:$N$16)*1)+SUMPRODUCT(ISTEXT($P$5:$P$16)*1)+SUMPRODUCT(ISTEXT($R$5:$R$16)*1))>0,(SUMPRODUCT(($A$5:$A$16<>"")*(ISNUMBER($F$5:$F$16)=FALSE))+SUMPRODUCT(ISTEXT($I$5:$I$16)*1)+SUMPRODUCT(ISTEXT($L$5:$L$16)*1)+SUMPRODUCT(ISTEXT($N$5:$N$16)*1)+SUMPRODUCT(ISTEXT($P$5:$P$16)*1)+SUMPRODUCT(ISTEXT($R$5:$R$16)*1))&" linha(s) ou preço(s) incompletos",Config!$B$7/(1-Config!$B$8-Config!$B$9)))) -> 338.98305
A24: Procedimentos com particular abaixo do mínimo | E24: =IF(NOT(ISNUMBER(Config!$B$7)),"falta o custo-hora em Config",IF((Config!$B$13<>"Sim"),"margens inválidas (Config)",IF((SUMPRODUCT(($A$5:$A$16<>"")*(ISNUMBER($F$5:$F$16)=FALSE))+SUMPRODUCT(ISTEXT($I$5:$I$16)*1)+SUMPRODUCT(ISTEXT($L$5:$L$16)*1)+SUMPRODUCT(ISTEXT($N$5:$N$16)*1)+SUMPRODUCT(ISTEXT($P$5:$P$16)*1)+SUMPRODUCT(ISTEXT($R$5:$R$16)*1))>0,(SUMPRODUCT(($A$5:$A$16<>"")*(ISNUMBER($F$5:$F$16)=FALSE))+SUMPRODUCT(ISTEXT($I$5:$I$16)*1)+SUMPRODUCT(ISTEXT($L$5:$L$16)*1)+SUMPRODUCT(ISTEXT($N$5:$N$16)*1)+SUMPRODUCT(ISTEXT($P$5:$P$16)*1)+SUMPRODUCT(ISTEXT($R$5:$R$16)*1))&" linha(s) ou preço(s) incompletos",COUNTIF($K$5:$K$16,"Abaixo do mínimo")&" de "&COUNTA($A$5:$A$16)))) -> 0 de 7
A25: Tabelas de convênio abaixo do custo cheio + imposto | E25: =IF(NOT(ISNUMBER(Config!$B$7)),"falta o custo-hora em Config",IF((Config!$B$13<>"Sim"),"margens inválidas (Config)",IF((SUMPRODUCT(($A$5:$A$16<>"")*(ISNUMBER($F$5:$F$16)=FALSE))+SUMPRODUCT(ISTEXT($I$5:$I$16)*1)+SUMPRODUCT(ISTEXT($L$5:$L$16)*1)+SUMPRODUCT(ISTEXT($N$5:$N$16)*1)+SUMPRODUCT(ISTEXT($P$5:$P$16)*1)+SUMPRODUCT(ISTEXT($R$5:$R$16)*1))>0,(SUMPRODUCT(($A$5:$A$16<>"")*(ISNUMBER($F$5:$F$16)=FALSE))+SUMPRODUCT(ISTEXT($I$5:$I$16)*1)+SUMPRODUCT(ISTEXT($L$5:$L$16)*1)+SUMPRODUCT(ISTEXT($N$5:$N$16)*1)+SUMPRODUCT(ISTEXT($P$5:$P$16)*1)+SUMPRODUCT(ISTEXT($R$5:$R$16)*1))&" linha(s) ou preço(s) incompletos",COUNTIF($T$5:$W$16,"<0")))) -> 14
A26: Maior prejuízo por atendimento em convênio (R$) | E26: =IF(NOT(ISNUMBER(Config!$B$7)),"falta o custo-hora em Config",IF((Config!$B$13<>"Sim"),"margens inválidas (Config)",IF((SUMPRODUCT(($A$5:$A$16<>"")*(ISNUMBER($F$5:$F$16)=FALSE))+SUMPRODUCT(ISTEXT($I$5:$I$16)*1)+SUMPRODUCT(ISTEXT($L$5:$L$16)*1)+SUMPRODUCT(ISTEXT($N$5:$N$16)*1)+SUMPRODUCT(ISTEXT($P$5:$P$16)*1)+SUMPRODUCT(ISTEXT($R$5:$R$16)*1))>0,(SUMPRODUCT(($A$5:$A$16<>"")*(ISNUMBER($F$5:$F$16)=FALSE))+SUMPRODUCT(ISTEXT($I$5:$I$16)*1)+SUMPRODUCT(ISTEXT($L$5:$L$16)*1)+SUMPRODUCT(ISTEXT($N$5:$N$16)*1)+SUMPRODUCT(ISTEXT($P$5:$P$16)*1)+SUMPRODUCT(ISTEXT($R$5:$R$16)*1))&" linha(s) ou preço(s) incompletos",-MIN($T$5:$W$16)))) -> 60.433333
A27: "Abaixo do custo cheio + imposto" conta as células de Margem negativas: a tabela do convênio, depois dos impostos, não paga o custo cheio do atendimento. É a mesma conta e o mesmo número do KPI "Tabelas de convênio abaixo do custo cheio + imposto" da planilha 08. "Maior prejuízo" = margem negativa × tabela do convênio: a célula mais vermelha da tabela, em reais por atendimento (colunas auxiliares T a W, ocultas).
A29: Simular um procedimento ou um preço novo
A30: Nome | B30: Consulta particular estendida (45 min)
A31: Minutos | B31: 45
A32: Gera retorno? (Sim/Não) | B32: Sim
A33: Material (R$) | B33: 4
A34: Preço pretendido (R$) | B34: 480
A35: Tempo com retorno (min) | B35: =IF(NOT(IF(ISNUMBER(B31),AND(B31>=0),FALSE)),"faltam os minutos",IF(AND(B32<>"Sim",B32<>"Não"),"falta: gera retorno?",IF(AND(B32="Sim",NOT(AND(IF(ISNUMBER(Config!$B$11),AND(Config!$B$11>=0),FALSE),IF(ISNUMBER(Config!$B$12),AND(Config!$B$12>=0),FALSE)))),"falta o retorno em Config",B31+IF(B32="Sim",Config!$B$11*Config!$B$12,0)))) -> 53
A36: Custo cheio (R$) | B36: =IF(NOT(ISNUMBER(B35)),B35,IF(NOT(ISNUMBER(Config!$B$7)),"falta o custo-hora em Config",IF(NOT(IF(ISNUMBER(B33),AND(B33>=0),FALSE)),"falta o material",B35/60*Config!$B$7+B33))) -> 180.66667
A37: Preço mínimo (R$) | B37: =IF(NOT(ISNUMBER(B36)),B36,IF((Config!$B$13<>"Sim"),"margens inválidas (Config)",B36/(1-Config!$B$8-Config!$B$9))) -> 306.21469
A38: Preço alvo (R$) | B38: =IF(NOT(ISNUMBER(B36)),B36,IF((Config!$B$13<>"Sim"),"margens inválidas (Config)",B36/(1-Config!$B$8-Config!$B$10))) -> 410.60606
A39: Margem no preço pretendido | B39: =IF(OR(NOT(ISNUMBER(B34)),N(B34)=0,NOT(ISNUMBER(B36)),(Config!$B$13<>"Sim")),"",(B34*(1-Config!$B$8)-B36)/B34) -> 0.51361111
A40: Leitura | B40: =IF(B34="","",IF(NOT(ISNUMBER(B34)),"Preço pretendido inválido",IF(B34=0,"",IF(NOT(ISNUMBER(B36)),IF(ISNUMBER(Config!$B$7),"Faltam dados: "&B36,"Falta o custo-hora em Config"),IF(OR(NOT(ISNUMBER(B37)),NOT(ISNUMBER(B38))),"Margens inválidas em Config",IF(B34<B37,"Abaixo do mínimo: cobre parte do custo, não a margem",IF(B34<B38,"Entre o mínimo e o alvo","No alvo ou acima"))))))) -> No alvo ou acima

Sheet Config
A1: Configurações
A2: Células amarelas: você preenche. Custo-hora da planilha 05; impostos e margens valem para todos os procedimentos.
A4: Nome da clínica | B4: Clínica Vida Plena (exemplo fictício)
A5: Mês de referência | B5: Setembro de 2026
A6: Data de referência | B6: 46279
A7: Custo da hora de atendimento (R$) | B7: 200 | C7: Copie do Painel da planilha 05 ("Custo da hora de atendimento"). No exemplo, R$ 200,00 (R$ 28.000 ÷ 140 h).
A8: Impostos sobre o que entra (%) | B8: 0.11 | C8: A mesma alíquota efetiva da planilha 05 (exemplo: 11 %; confira com o contador). Só imposto: a taxa da maquininha não entra aqui (ela está na 16 e no resultado 18).
A9: Margem mínima sobre o preço (%) | B9: 0.3 | C9: Abaixo disso o procedimento não vale a pena. É o piso da faixa (a mesma margem da 05).
A10: Margem alvo sobre o preço (%) | B10: 0.45 | C10: A margem que a clínica quer de verdade. É o teto da faixa.
A11: Retornos por consulta (média) | B11: 0.4 | C11: Consulta que costuma gerar retorno sem cobrança: em média, quantos retornos por consulta. O tempo do retorno entra no custo da consulta.
A12: Duração do retorno (minutos) | B12: 20 | C12: Minutos de um retorno (planilha 01, Config).
A13: Impostos e margens conferem? (calculado) | B13: =IF(AND(ISNUMBER(B8),ISNUMBER(B9),ISNUMBER(B10)),IF(AND(B8>=0,B8<1,B9>=0,B9<=B10,B10<1,B8+B10<1),"Sim","Não"),"Não") -> Sim | C13: "Não" suspende preços, margens, situação e resumo: impostos e margens de 0 % a 99 %, mínima ≤ alvo e impostos + margem alvo abaixo de 100 %.
A14: Convênios (até 4, na ordem das colunas da aba Precificação)
A15: Nomes | B15: Saúde Total | C15: Preencha de cima para baixo, sem pular linha. As tabelas de cada convênio ficam na aba Precificação.
B16: MediPlan
B17: Vida Care
