Workbook

Sheet Como usar
A1: Tabela de preços e referência por procedimento
A2: Kit de Gestão para Médicos · Seu Sócio Gestor · versão 1.0 (setembro de 2026)
A4: O que esta planilha faz | B4: É a tabela interna da clínica: para cada procedimento, o preço particular e a tabela de cada convênio ao lado do custo cheio, do preço mínimo e do preço alvo (a mesma conta da 06), mais o valor por hora que cada pagador paga e o valor médio praticado no mês fechado.
A5: Passo 1 | B5: Em Config, copie o custo-hora da planilha 05, a alíquota, as margens e os pagadores (o primeiro é o particular).
A6: Passo 2 | B6: Em Tabela, uma linha por procedimento: minutos, se gera retorno, material e o valor de cada pagador. Esta é a tabela oficial da clínica: a Config da planilha 01 (agenda), a 06 e a 07 copiam daqui.
A7: Passo 3 | B7: Copie de "Por procedimento" no Painel da 01 (mês fechado) os realizados e a produção do mês: a planilha mostra o valor médio praticado e quanto ele fica acima ou abaixo do mínimo.
A8: Passo 4 | B8: Leia as cores: particular abaixo do mínimo (vermelho) é preço a revisar; tabela de convênio vermelha não cobre o custo cheio (leve para a planilha 07 antes de decidir). O quadro "Valor por hora" é o argumento para negociar tabela.
A9: Ordem de atualização | B9: Mudou um preço? Atualize sempre nesta ordem: 08 (aqui) → 06 · Precificação → 07 · Simulador → 01 · Config (a tabela que a Agenda busca). Procedimento novo: 01 e 02 (Config), 08, 06 e 07. Convênio novo: 01, 02, 06, 07, 08, 09 (categorias de entrada) e 13 (Config, com prazo e dia de envio).
A10: Rotina | B10: Revise quando o custo-hora mudar (05) ou ao renegociar um convênio. Se pesquisar preços da região, anote na coluna "Referência de mercado"; a divulgação de preços segue as regras do CFM.
A11: Com a IA | B11: Copie a Tabela e use o prompt "Preço 04 · Revisar a tabela de preços" da biblioteca do kit, ou "Preço 03 · Vale a pena este convênio?" para um convênio específico.
A12: Legenda | B12: Células amarelas: você preenche. Brancas: calculadas. Não é preciso mexer em nada fora do amarelo.
A13: Proteção | B13: Fórmulas protegidas sem senha. Para editar: Revisar > Desproteger planilha (Excel) ou Dados > Proteger intervalos (Google Sheets).
A14: Requisitos | B14: Excel 2016 ou mais novo, Microsoft 365 ou Google Sheets (só funções do Excel 2007+; nada de MÍNIMOSES, MÁXIMOSES ou UNIRTEXTO). No celular abre nos aplicativos; para preencher, use o computador.
A15: Dados de pacientes | B15: Guarde só o que a gestão precisa (nome, contato, valor, data). Nada de diagnóstico, prontuário ou exame nestas planilhas: o kit é gestão, não é prontuário. Veja o guia LGPD do kit antes de colar qualquer tabela em uma IA.
... A19: Suporte | B19: suporte@seusociogestor.com.br · resposta em até 5 dias úteis · reembolso em até 7 dias pelo mesmo canal.

Sheet Tabela
A1: =Config!$B$4&" · Tabela de preços e referência · volume de "&Config!$B$5 -> Clínica Vida Plena (exemplo fictício) · Tabela de preços e referência · volume de Agosto de 2026
A2: Amarelo: procedimento, minutos, retorno, material, valor de cada pagador e o volume do mês (Painel da 01, por procedimento). Branco: custo cheio, mínimo, alvo, situação e valor médio praticado.
A4: Hora mínima (05) | C4: Particular abaixo do mínimo | E4: Tabelas de convênio abaixo do custo cheio + imposto | G4: Produção no mês (R$) | I4: Valor médio por hora no mês | K4: Contra a hora mínima
A5: =Config!$B$13 -> 338.98305 | C5: =IF(NOT(ISNUMBER(Config!$B$13)),Config!$B$13,IF((SUMPRODUCT(($A$8:$A$19<>"")*(ISNUMBER($F$8:$F$19)=FALSE))+SUMPRODUCT(($A$8:$A$19<>"")*($H$8:$H$19=""))+SUMPRODUCT(ISTEXT($H$8:$M$19)+ISNUMBER($H$8:$M$19)*($H$8:$M$19<0))+SUMPRODUCT(($A$8:$A$19="")*(($B$8:$B$19<>"")+($C$8:$C$19<>"")+($D$8:$D$19<>"")+($H$8:$H$19<>"")+($I$8:$I$19<>"")+($J$8:$J$19<>"")+($K$8:$K$19<>"")+($L$8:$L$19<>"")+($M$8:$M$19<>"")+($P$8:$P$19<>"")+($Q$8:$Q$19<>"")>0)))>0,(SUMPRODUCT(($A$8:$A$19<>"")*(ISNUMBER($F$8:$F$19)=FALSE))+SUMPRODUCT(($A$8:$A$19<>"")*($H$8:$H$19=""))+SUMPRODUCT(ISTEXT($H$8:$M$19)+ISNUMBER($H$8:$M$19)*($H$8:$M$19<0))+SUMPRODUCT(($A$8:$A$19="")*(($B$8:$B$19<>"")+($C$8:$C$19<>"")+($D$8:$D$19<>"")+($H$8:$H$19<>"")+($I$8:$I$19<>"")+($J$8:$J$19<>"")+($K$8:$K$19<>"")+($L$8:$L$19<>"")+($M$8:$M$19<>"")+($P$8:$P$19<>"")+($Q$8:$Q$19<>"")>0)))&" linha(s) ou preço(s) incompletos",COUNTIF($N$8:$N$19,"Abaixo do mínimo")&" de "&COUNTA($A$8:$A$19))) -> 0 de 7 | E5: =IF(NOT(ISNUMBER(Config!$B$13)),Config!$B$13,IF((SUMPRODUCT(($A$8:$A$19<>"")*(ISNUMBER($F$8:$F$19)=FALSE))+SUMPRODUCT(($A$8:$A$19<>"")*($H$8:$H$19=""))+SUMPRODUCT(ISTEXT($H$8:$M$19)+ISNUMBER($H$8:$M$19)*($H$8:$M$19<0))+SUMPRODUCT(($A$8:$A$19="")*(($B$8:$B$19<>"")+($C$8:$C$19<>"")+($D$8:$D$19<>"")+($H$8:$H$19<>"")+($I$8:$I$19<>"")+($J$8:$J$19<>"")+($K$8:$K$19<>"")+($L$8:$L$19<>"")+($M$8:$M$19<>"")+($P$8:$P$19<>"")+($Q$8:$Q$19<>"")>0)))>0,(SUMPRODUCT(($A$8:$A$19<>"")*(ISNUMBER($F$8:$F$19)=FALSE))+SUMPRODUCT(($A$8:$A$19<>"")*($H$8:$H$19=""))+SUMPRODUCT(ISTEXT($H$8:$M$19)+ISNUMBER($H$8:$M$19)*($H$8:$M$19<0))+SUMPRODUCT(($A$8:$A$19="")*(($B$8:$B$19<>"")+($C$8:$C$19<>"")+($D$8:$D$19<>"")+($H$8:$H$19<>"")+($I$8:$I$19<>"")+($J$8:$J$19<>"")+($K$8:$K$19<>"")+($L$8:$L$19<>"")+($M$8:$M$19<>"")+($P$8:$P$19<>"")+($Q$8:$Q$19<>"")>0)))&" linha(s) ou preço(s) incompletos",SUM($O$8:$O$19))) -> 14 | G5: =IF((SUMPRODUCT((($P$8:$P$19<>"")+($Q$8:$Q$19<>"")>0)*((ISNUMBER($P$8:$P$19)=FALSE)+ISNUMBER($P$8:$P$19)*($P$8:$P$19<0)+(ISNUMBER($Q$8:$Q$19)=FALSE)+ISNUMBER($Q$8:$Q$19)*($Q$8:$Q$19<0)>0))+SUMPRODUCT(($A$8:$A$19="")*(($B$8:$B$19<>"")+($C$8:$C$19<>"")+($D$8:$D$19<>"")+($H$8:$H$19<>"")+($I$8:$I$19<>"")+($J$8:$J$19<>"")+($K$8:$K$19<>"")+($L$8:$L$19<>"")+($M$8:$M$19<>"")+($P$8:$P$19<>"")+($Q$8:$Q$19<>"")>0)))>0,"produção incompleta em "&(SUMPRODUCT((($P$8:$P$19<>"")+($Q$8:$Q$19<>"")>0)*((ISNUMBER($P$8:$P$19)=FALSE)+ISNUMBER($P$8:$P$19)*($P$8:$P$19<0)+(ISNUMBER($Q$8:$Q$19)=FALSE)+ISNUMBER($Q$8:$Q$19)*($Q$8:$Q$19<0)>0))+SUMPRODUCT(($A$8:$A$19="")*(($B$8:$B$19<>"")+($C$8:$C$19<>"")+($D$8:$D$19<>"")+($H$8:$H$19<>"")+($I$8:$I$19<>"")+($J$8:$J$19<>"")+($K$8:$K$19<>"")+($L$8:$L$19<>"")+($M$8:$M$19<>"")+($P$8:$P$19<>"")+($Q$8:$Q$19<>"")>0)))&" linha(s)",SUM($Q$8:$Q$19)) -> 48631 | I5: =IF((SUMPRODUCT((($P$8:$P$19<>"")+($Q$8:$Q$19<>"")>0)*((ISNUMBER($P$8:$P$19)=FALSE)+ISNUMBER($P$8:$P$19)*($P$8:$P$19<0)+(ISNUMBER($Q$8:$Q$19)=FALSE)+ISNUMBER($Q$8:$Q$19)*($Q$8:$Q$19<0)+(ISNUMBER($B$8:$B$19)=FALSE)+ISNUMBER($B$8:$B$19)*($B$8:$B$19<0)>0))+SUMPRODUCT(($A$8:$A$19="")*(($B$8:$B$19<>"")+($C$8:$C$19<>"")+($D$8:$D$19<>"")+($H$8:$H$19<>"")+($I$8:$I$19<>"")+($J$8:$J$19<>"")+($K$8:$K$19<>"")+($L$8:$L$19<>"")+($M$8:$M$19<>"")+($P$8:$P$19<>"")+($Q$8:$Q$19<>"")>0)))>0,"volume incompleto em "&(SUMPRODUCT((($P$8:$P$19<>"")+($Q$8:$Q$19<>"")>0)*((ISNUMBER($P$8:$P$19)=FALSE)+ISNUMBER($P$8:$P$19)*($P$8:$P$19<0)+(ISNUMBER($Q$8:$Q$19)=FALSE)+ISNUMBER($Q$8:$Q$19)*($Q$8:$Q$19<0)+(ISNUMBER($B$8:$B$19)=FALSE)+ISNUMBER($B$8:$B$19)*($B$8:$B$19<0)>0))+SUMPRODUCT(($A$8:$A$19="")*(($B$8:$B$19<>"")+($C$8:$C$19<>"")+($D$8:$D$19<>"")+($H$8:$H$19<>"")+($I$8:$I$19<>"")+($J$8:$J$19<>"")+($K$8:$K$19<>"")+($L$8:$L$19<>"")+($M$8:$M$19<>"")+($P$8:$P$19<>"")+($Q$8:$Q$19<>"")>0)))&" linha(s)",IFERROR(SUM($Q$8:$Q$19)/(SUMPRODUCT($P$8:$P$19,$B$8:$B$19)/60),"")) -> 410.9662 | K5: =IF(NOT(ISNUMBER(Config!$B$13)),"",IF(Config!$B$13=0,"sem base (mínimo zero)",IFERROR(I5/Config!$B$13-1,""))) -> 0.21235028
A7: Procedimento | B7: Minutos | C7: Gera retorno? | D7: Material (R$) | E7: Custo cheio (R$) | F7: Preço mínimo (R$) | G7: Preço alvo (R$) | H7: =IF(Config!$B$17="","",Config!$B$17) -> Particular | I7: =IF(Config!$B$18="","",Config!$B$18) -> Saúde Total | J7: =IF(Config!$B$19="","",Config!$B$19) -> MediPlan | K7: =IF(Config!$B$20="","",Config!$B$20) -> Vida Care | L7: =IF(Config!$B$21="","",Config!$B$21) | M7: =IF(Config!$B$22="","",Config!$B$22) | N7: Situação do particular | O7: Tabelas abaixo do custo cheio + imposto | P7: Realizados no mês | Q7: Produção no mês (R$) | R7: Valor médio praticado (R$) | S7: Valor médio contra o mínimo | T7: Referência de mercado (opcional)
A8: Consulta | B8: 30 | C8: Sim | D8: 4 | E8: =IF(A8="","",IF(NOT(ISNUMBER((IF(NOT(IF(ISNUMBER(B8),AND(B8>=0),FALSE)),"faltam os minutos",IF(AND(C8<>"Sim",C8<>"Não"),"falta: gera retorno?",IF(AND(C8="Sim",NOT(AND(IF(ISNUMBER(Config!$B$11),AND(Config!$B$11>=0),FALSE),IF(ISNUMBER(Config!$B$12),AND(Config!$B$12>=0),FALSE)))),"falta o retorno em Config",B8+IF(C8="Sim",Config!$B$11*Config!$B$12,0))))))),(IF(NOT(IF(ISNUMBER(B8),AND(B8>=0),FALSE)),"faltam os minutos",IF(AND(C8<>"Sim",C8<>"Não"),"falta: gera retorno?",IF(AND(C8="Sim",NOT(AND(IF(ISNUMBER(Config!$B$11),AND(Config!$B$11>=0),FALSE),IF(ISNUMBER(Config!$B$12),AND(Config!$B$12>=0),FALSE)))),"falta o retorno em Config",B8+IF(C8="Sim",Config!$B$11*Config!$B$12,0))))),IF(NOT(IF(ISNUMBER(Config!$B$7),AND(Config!$B$7>=0),FALSE)),"falta o custo-hora em Config",IF(NOT(IF(ISNUMBER(D8),AND(D8>=0),FALSE)),"falta o material",(IF(NOT(IF(ISNUMBER(B8),AND(B8>=0),FALSE)),"faltam os minutos",IF(AND(C8<>"Sim",C8<>"Não"),"falta: gera retorno?",IF(AND(C8="Sim",NOT(AND(IF(ISNUMBER(Config!$B$11),AND(Config!$B$11>=0),FALSE),IF(ISNUMBER(Config!$B$12),AND(Config!$B$12>=0),FALSE)))),"falta o retorno em Config",B8+IF(C8="Sim",Config!$B$11*Config!$B$12,0)))))/60*Config!$B$7+D8)))) -> 130.66667 | F8: =IF(A8="","",IF(NOT(ISNUMBER(E8)),E8,IF((Config!$B$15<>"Sim"),"margens inválidas (Config)",E8/(1-Config!$B$8-Config!$B$9)))) -> 221.46893 | G8: =IF(A8="","",IF(NOT(ISNUMBER(E8)),E8,IF((Config!$B$15<>"Sim"),"margens inválidas (Config)",E8/(1-Config!$B$8-Config!$B$10)))) -> 296.9697 | H8: 380 | I8: 120 | J8: 100 | K8: 90 | N8: =IF(A8="","",IF(H8="","Falta o preço particular",IF(NOT(IF(ISNUMBER(H8),AND(H8>=0),FALSE)),"Preço inválido",IF(NOT(ISNUMBER(E8)),IF(IF(ISNUMBER(Config!$B$7),Config!$B$7>=0,FALSE),"Faltam dados da linha","Falta o custo-hora"),IF(OR(NOT(ISNUMBER(F8)),NOT(ISNUMBER(G8))),"Margens inválidas",IF(H8=0,"Sem cobrança",IF(H8<F8,"Abaixo do mínimo",IF(H8<G8,"Entre mínimo e alvo","No alvo ou acima")))))))) -> No alvo ou acima | O8: =IF(OR(A8="",NOT(ISNUMBER(F8))),"",IF(SUMPRODUCT(ISTEXT(I8:M8)+ISNUMBER(I8:M8)*(I8:M8<0))>0,"tabela inválida (texto ou negativo)",SUMPRODUCT((I8:M8<>"")*ISNUMBER(I8:M8)*(((I8:M8)>0)+(N(H8)>0)>0)*(I8:M8*(1-Config!$B$8)<E8)))) -> 3 | P8: 130 | Q8: 30730 | R8: =IF(OR(A8="",AND(P8="",Q8="")),"",IF(OR(NOT(IF(ISNUMBER(P8),AND(P8>=0),FALSE)),NOT(IF(ISNUMBER(Q8),AND(Q8>=0),FALSE))),"volume ou produção faltando ou negativos",IF(P8=0,"",Q8/P8))) -> 236.38462 | S8: =IF(OR(NOT(ISNUMBER(R8)),NOT(ISNUMBER(F8)),NOT(IF(ISNUMBER(H8),H8>0,FALSE))),"",IF(F8=0,"sem base (mínimo zero)",R8/F8-1)) -> 0.067348901
A9: Retorno | B9: 20 | C9: Não | D9: 2 | E9: =IF(A9="","",IF(NOT(ISNUMBER((IF(NOT(IF(ISNUMBER(B9),AND(B9>=0),FALSE)),"faltam os minutos",IF(AND(C9<>"Sim",C9<>"Não"),"falta: gera retorno?",IF(AND(C9="Sim",NOT(AND(IF(ISNUMBER(Config!$B$11),AND(Config!$B$11>=0),FALSE),IF(ISNUMBER(Config!$B$12),AND(Config!$B$12>=0),FALSE)))),"falta o retorno em Config",B9+IF(C9="Sim",Config!$B$11*Config!$B$12,0))))))),(IF(NOT(IF(ISNUMBER(B9),AND(B9>=0),FALSE)),"faltam os minutos",IF(AND(C9<>"Sim",C9<>"Não"),"falta: gera retorno?",IF(AND(C9="Sim",NOT(AND(IF(ISNUMBER(Config!$B$11),AND(Config!$B$11>=0),FALSE),IF(ISNUMBER(Config!$B$12),AND(Config!$B$12>=0),FALSE)))),"falta o retorno em Config",B9+IF(C9="Sim",Config!$B$11*Config!$B$12,0))))),IF(NOT(IF(ISNUMBER(Config!$B$7),AND(Config!$B$7>=0),FALSE)),"falta o custo-hora em Config",IF(NOT(IF(ISNUMBER(D9),AND(D9>=0),FALSE)),"falta o material",(IF(NOT(IF(ISNUMBER(B9),AND(B9>=0),FALSE)),"faltam os minutos",IF(AND(C9<>"Sim",C9<>"Não"),"falta: gera retorno?",IF(AND(C9="Sim",NOT(AND(IF(ISNUMBER(Config!$B$11),AND(Config!$B$11>=0),FALSE),IF(ISNUMBER(Config!$B$12),AND(Config!$B$12>=0),FALSE)))),"falta o retorno em Config",B9+IF(C9="Sim",Config!$B$11*Config!$B$12,0)))))/60*Config!$B$7+D9)))) -> 68.666667 | F9: =IF(A9="","",IF(NOT(ISNUMBER(E9)),E9,IF((Config!$B$15<>"Sim"),"margens inválidas (Config)",E9/(1-Config!$B$8-Config!$B$9)))) -> 116.38418 | G9: =IF(A9="","",IF(NOT(ISNUMBER(E9)),E9,IF((Config!$B$15<>"Sim"),"margens inválidas (Config)",E9/(1-Config!$B$8-Config!$B$10)))) -> 156.06061 | H9: 0 | I9: 0 | J9: 0 | K9: 0 | N9: =IF(A9="","",IF(H9="","Falta o preço particular",IF(NOT(IF(ISNUMBER(H9),AND(H9>=0),FALSE)),"Preço inválido",IF(NOT(ISNUMBER(E9)),IF(IF(ISNUMBER(Config!$B$7),Config!$B$7>=0,FALSE),"Faltam dados da linha","Falta o custo-hora"),IF(OR(NOT(ISNUMBER(F9)),NOT(ISNUMBER(G9))),"Margens inválidas",IF(H9=0,"Sem cobrança",IF(H9<F9,"Abaixo do mínimo",IF(H9<G9,"Entre mínimo e alvo","No alvo ou acima")))))))) -> Sem cobrança | O9: =IF(OR(A9="",NOT(ISNUMBER(F9))),"",IF(SUMPRODUCT(ISTEXT(I9:M9)+ISNUMBER(I9:M9)*(I9:M9<0))>0,"tabela inválida (texto ou negativo)",SUMPRODUCT((I9:M9<>"")*ISNUMBER(I9:M9)*(((I9:M9)>0)+(N(H9)>0)>0)*(I9:M9*(1-Config!$B$8)<E9)))) -> 0 | P9: 48 | Q9: 0 | R9: =IF(OR(A9="",AND(P9="",Q9="")),"",IF(OR(NOT(IF(ISNUMBER(P9),AND(P9>=0),FALSE)),NOT(IF(ISNUMBER(Q9),AND(Q9>=0),FALSE))),"volume ou produção faltando ou negativos",IF(P9=0,"",Q9/P9))) -> 0 | S9: =IF(OR(NOT(ISNUMBER(R9)),NOT(ISNUMBER(F9)),NOT(IF(ISNUMBER(H9),H9>0,FALSE))),"",IF(F9=0,"sem base (mínimo zero)",R9/F9-1))
A10: ECG | B10: 20 | C10: Não | D10: 8 | E10: =IF(A10="","",IF(NOT(ISNUMBER((IF(NOT(IF(ISNUMBER(B10),AND(B10>=0),FALSE)),"faltam os minutos",IF(AND(C10<>"Sim",C10<>"Não"),"falta: gera retorno?",IF(AND(C10="Sim",NOT(AND(IF(ISNUMBER(Config!$B$11),AND(Config!$B$11>=0),FALSE),IF(ISNUMBER(Config!$B$12),AND(Config!$B$12>=0),FALSE)))),"falta o retorno em Config",B10+IF(C10="Sim",Config!$B$11*Config!$B$12,0))))))),(IF(NOT(IF(ISNUMBER(B10),AND(B10>=0),FALSE)),"faltam os minutos",IF(AND(C10<>"Sim",C10<>"Não"),"falta: gera retorno?",IF(AND(C10="Sim",NOT(AND(IF(ISNUMBER(Config!$B$11),AND(Config!$B$11>=0),FALSE),IF(ISNUMBER(Config!$B$12),AND(Config!$B$12>=0),FALSE)))),"falta o retorno em Config",B10+IF(C10="Sim",Config!$B$11*Config!$B$12,0))))),IF(NOT(IF(ISNUMBER(Config!$B$7),AND(Config!$B$7>=0),FALSE)),"falta o custo-hora em Config",IF(NOT(IF(ISNUMBER(D10),AND(D10>=0),FALSE)),"falta o material",(IF(NOT(IF(ISNUMBER(B10),AND(B10>=0),FALSE)),"faltam os minutos",IF(AND(C10<>"Sim",C10<>"Não"),"falta: gera retorno?",IF(AND(C10="Sim",NOT(AND(IF(ISNUMBER(Config!$B$11),AND(Config!$B$11>=0),FALSE),IF(ISNUMBER(Config!$B$12),AND(Config!$B$12>=0),FALSE)))),"falta o retorno em Config",B10+IF(C10="Sim",Config!$B$11*Config!$B$12,0)))))/60*Config!$B$7+D10)))) -> 74.666667 | F10: =IF(A10="","",IF(NOT(ISNUMBER(E10)),E10,IF((Config!$B$15<>"Sim"),"margens inválidas (Config)",E10/(1-Config!$B$8-Config!$B$9)))) -> 126.55367 | G10: =IF(A10="","",IF(NOT(ISNUMBER(E10)),E10,IF((Config!$B$15<>"Sim"),"margens inválidas (Config)",E10/(1-Config!$B$8-Config!$B$10)))) -> 169.69697 | H10: 130 | I10: 40 | J10: 35 | K10: 32 | N10: =IF(A10="","",IF(H10="","Falta o preço particular",IF(NOT(IF(ISNUMBER(H10),AND(H10>=0),FALSE)),"Preço inválido",IF(NOT(ISNUMBER(E10)),IF(IF(ISNUMBER(Config!$B$7),Config!$B$7>=0,FALSE),"Faltam dados da linha","Falta o custo-hora"),IF(OR(NOT(ISNUMBER(F10)),NOT(ISNUMBER(G10))),"Margens inválidas",IF(H10=0,"Sem cobrança",IF(H10<F10,"Abaixo do mínimo",IF(H10<G10,"Entre mínimo e alvo","No alvo ou acima")))))))) -> Entre mínimo e alvo | O10: =IF(OR(A10="",NOT(ISNUMBER(F10))),"",IF(SUMPRODUCT(ISTEXT(I10:M10)+ISNUMBER(I10:M10)*(I10:M10<0))>0,"tabela inválida (texto ou negativo)",SUMPRODUCT((I10:M10<>"")*ISNUMBER(I10:M10)*(((I10:M10)>0)+(N(H10)>0)>0)*(I10:M10*(1-Config!$B$8)<E10)))) -> 3 | P10: 18 | Q10: 1416 | R10: =IF(OR(A10="",AND(P10="",Q10="")),"",IF(OR(NOT(IF(ISNUMBER(P10),AND(P10>=0),FALSE)),NOT(IF(ISNUMBER(Q10),AND(Q10>=0),FALSE))),"volume ou produção faltando ou negativos",IF(P10=0,"",Q10/P10))) -> 78.666667 | S10: =IF(OR(NOT(ISNUMBER(R10)),NOT(ISNUMBER(F10)),NOT(IF(ISNUMBER(H10),H10>0,FALSE))),"",IF(F10=0,"sem base (mínimo zero)",R10/F10-1)) -> -0.37839286
A11: MAPA | B11: 20 | C11: Não | D11: 15 | E11: =IF(A11="","",IF(NOT(ISNUMBER((IF(NOT(IF(ISNUMBER(B11),AND(B11>=0),FALSE)),"faltam os minutos",IF(AND(C11<>"Sim",C11<>"Não"),"falta: gera retorno?",IF(AND(C11="Sim",NOT(AND(IF(ISNUMBER(Config!$B$11),AND(Config!$B$11>=0),FALSE),IF(ISNUMBER(Config!$B$12),AND(Config!$B$12>=0),FALSE)))),"falta o retorno em Config",B11+IF(C11="Sim",Config!$B$11*Config!$B$12,0))))))),(IF(NOT(IF(ISNUMBER(B11),AND(B11>=0),FALSE)),"faltam os minutos",IF(AND(C11<>"Sim",C11<>"Não"),"falta: gera retorno?",IF(AND(C11="Sim",NOT(AND(IF(ISNUMBER(Config!$B$11),AND(Config!$B$11>=0),FALSE),IF(ISNUMBER(Config!$B$12),AND(Config!$B$12>=0),FALSE)))),"falta o retorno em Config",B11+IF(C11="Sim",Config!$B$11*Config!$B$12,0))))),IF(NOT(IF(ISNUMBER(Config!$B$7),AND(Config!$B$7>=0),FALSE)),"falta o custo-hora em Config",IF(NOT(IF(ISNUMBER(D11),AND(D11>=0),FALSE)),"falta o material",(IF(NOT(IF(ISNUMBER(B11),AND(B11>=0),FALSE)),"faltam os minutos",IF(AND(C11<>"Sim",C11<>"Não"),"falta: gera retorno?",IF(AND(C11="Sim",NOT(AND(IF(ISNUMBER(Config!$B$11),AND(Config!$B$11>=0),FALSE),IF(ISNUMBER(Config!$B$12),AND(Config!$B$12>=0),FALSE)))),"falta o retorno em Config",B11+IF(C11="Sim",Config!$B$11*Config!$B$12,0)))))/60*Config!$B$7+D11)))) -> 81.666667 | F11: =IF(A11="","",IF(NOT(ISNUMBER(E11)),E11,IF((Config!$B$15<>"Sim"),"margens inválidas (Config)",E11/(1-Config!$B$8-Config!$B$9)))) -> 138.41808 | G11: =IF(A11="","",IF(NOT(ISNUMBER(E11)),E11,IF((Config!$B$15<>"Sim"),"margens inválidas (Config)",E11/(1-Config!$B$8-Config!$B$10)))) -> 185.60606 | H11: 300 | I11: 95 | J11: 85 | K11: 75 | N11: =IF(A11="","",IF(H11="","Falta o preço particular",IF(NOT(IF(ISNUMBER(H11),AND(H11>=0),FALSE)),"Preço inválido",IF(NOT(ISNUMBER(E11)),IF(IF(ISNUMBER(Config!$B$7),Config!$B$7>=0,FALSE),"Faltam dados da linha","Falta o custo-hora"),IF(OR(NOT(ISNUMBER(F11)),NOT(ISNUMBER(G11))),"Margens inválidas",IF(H11=0,"Sem cobrança",IF(H11<F11,"Abaixo do mínimo",IF(H11<G11,"Entre mínimo e alvo","No alvo ou acima")))))))) -> No alvo ou acima | O11: =IF(OR(A11="",NOT(ISNUMBER(F11))),"",IF(SUMPRODUCT(ISTEXT(I11:M11)+ISNUMBER(I11:M11)*(I11:M11<0))>0,"tabela inválida (texto ou negativo)",SUMPRODUCT((I11:M11<>"")*ISNUMBER(I11:M11)*(((I11:M11)>0)+(N(H11)>0)>0)*(I11:M11*(1-Config!$B$8)<E11)))) -> 2 | P11: 8 | Q11: 1345 | R11: =IF(OR(A11="",AND(P11="",Q11="")),"",IF(OR(NOT(IF(ISNUMBER(P11),AND(P11>=0),FALSE)),NOT(IF(ISNUMBER(Q11),AND(Q11>=0),FALSE))),"volume ou produção faltando ou negativos",IF(P11=0,"",Q11/P11))) -> 168.125 | S11: =IF(OR(NOT(ISNUMBER(R11)),NOT(ISNUMBER(F11)),NOT(IF(ISNUMBER(H11),H11>0,FALSE))),"",IF(F11=0,"sem base (mínimo zero)",R11/F11-1)) -> 0.21461735
A12: Holter | B12: 20 | C12: Não | D12: 18 | E12: =IF(A12="","",IF(NOT(ISNUMBER((IF(NOT(IF(ISNUMBER(B12),AND(B12>=0),FALSE)),"faltam os minutos",IF(AND(C12<>"Sim",C12<>"Não"),"falta: gera retorno?",IF(AND(C12="Sim",NOT(AND(IF(ISNUMBER(Config!$B$11),AND(Config!$B$11>=0),FALSE),IF(ISNUMBER(Config!$B$12),AND(Config!$B$12>=0),FALSE)))),"falta o retorno em Config",B12+IF(C12="Sim",Config!$B$11*Config!$B$12,0))))))),(IF(NOT(IF(ISNUMBER(B12),AND(B12>=0),FALSE)),"faltam os minutos",IF(AND(C12<>"Sim",C12<>"Não"),"falta: gera retorno?",IF(AND(C12="Sim",NOT(AND(IF(ISNUMBER(Config!$B$11),AND(Config!$B$11>=0),FALSE),IF(ISNUMBER(Config!$B$12),AND(Config!$B$12>=0),FALSE)))),"falta o retorno em Config",B12+IF(C12="Sim",Config!$B$11*Config!$B$12,0))))),IF(NOT(IF(ISNUMBER(Config!$B$7),AND(Config!$B$7>=0),FALSE)),"falta o custo-hora em Config",IF(NOT(IF(ISNUMBER(D12),AND(D12>=0),FALSE)),"falta o material",(IF(NOT(IF(ISNUMBER(B12),AND(B12>=0),FALSE)),"faltam os minutos",IF(AND(C12<>"Sim",C12<>"Não"),"falta: gera retorno?",IF(AND(C12="Sim",NOT(AND(IF(ISNUMBER(Config!$B$11),AND(Config!$B$11>=0),FALSE),IF(ISNUMBER(Config!$B$12),AND(Config!$B$12>=0),FALSE)))),"falta o retorno em Config",B12+IF(C12="Sim",Config!$B$11*Config!$B$12,0)))))/60*Config!$B$7+D12)))) -> 84.666667 | F12: =IF(A12="","",IF(NOT(ISNUMBER(E12)),E12,IF((Config!$B$15<>"Sim"),"margens inválidas (Config)",E12/(1-Config!$B$8-Config!$B$9)))) -> 143.50282 | G12: =IF(A12="","",IF(NOT(ISNUMBER(E12)),E12,IF((Config!$B$15<>"Sim"),"margens inválidas (Config)",E12/(1-Config!$B$8-Config!$B$10)))) -> 192.42424 | H12: 350 | I12: 105 | J12: 95 | K12: 85 | N12: =IF(A12="","",IF(H12="","Falta o preço particular",IF(NOT(IF(ISNUMBER(H12),AND(H12>=0),FALSE)),"Preço inválido",IF(NOT(ISNUMBER(E12)),IF(IF(ISNUMBER(Config!$B$7),Config!$B$7>=0,FALSE),"Faltam dados da linha","Falta o custo-hora"),IF(OR(NOT(ISNUMBER(F12)),NOT(ISNUMBER(G12))),"Margens inválidas",IF(H12=0,"Sem cobrança",IF(H12<F12,"Abaixo do mínimo",IF(H12<G12,"Entre mínimo e alvo","No alvo ou acima")))))))) -> No alvo ou acima | O12: =IF(OR(A12="",NOT(ISNUMBER(F12))),"",IF(SUMPRODUCT(ISTEXT(I12:M12)+ISNUMBER(I12:M12)*(I12:M12<0))>0,"tabela inválida (texto ou negativo)",SUMPRODUCT((I12:M12<>"")*ISNUMBER(I12:M12)*(((I12:M12)>0)+(N(H12)>0)>0)*(I12:M12*(1-Config!$B$8)<E12)))) -> 2 | P12: 10 | Q12: 2490 | R12: =IF(OR(A12="",AND(P12="",Q12="")),"",IF(OR(NOT(IF(ISNUMBER(P12),AND(P12>=0),FALSE)),NOT(IF(ISNUMBER(Q12),AND(Q12>=0),FALSE))),"volume ou produção faltando ou negativos",IF(P12=0,"",Q12/P12))) -> 249 | S12: =IF(OR(NOT(ISNUMBER(R12)),NOT(ISNUMBER(F12)),NOT(IF(ISNUMBER(H12),H12>0,FALSE))),"",IF(F12=0,"sem base (mínimo zero)",R12/F12-1)) -> 0.73515748
A13: Teste ergométrico | B13: 40 | C13: Não | D13: 25 | E13: =IF(A13="","",IF(NOT(ISNUMBER((IF(NOT(IF(ISNUMBER(B13),AND(B13>=0),FALSE)),"faltam os minutos",IF(AND(C13<>"Sim",C13<>"Não"),"falta: gera retorno?",IF(AND(C13="Sim",NOT(AND(IF(ISNUMBER(Config!$B$11),AND(Config!$B$11>=0),FALSE),IF(ISNUMBER(Config!$B$12),AND(Config!$B$12>=0),FALSE)))),"falta o retorno em Config",B13+IF(C13="Sim",Config!$B$11*Config!$B$12,0))))))),(IF(NOT(IF(ISNUMBER(B13),AND(B13>=0),FALSE)),"faltam os minutos",IF(AND(C13<>"Sim",C13<>"Não"),"falta: gera retorno?",IF(AND(C13="Sim",NOT(AND(IF(ISNUMBER(Config!$B$11),AND(Config!$B$11>=0),FALSE),IF(ISNUMBER(Config!$B$12),AND(Config!$B$12>=0),FALSE)))),"falta o retorno em Config",B13+IF(C13="Sim",Config!$B$11*Config!$B$12,0))))),IF(NOT(IF(ISNUMBER(Config!$B$7),AND(Config!$B$7>=0),FALSE)),"falta o custo-hora em Config",IF(NOT(IF(ISNUMBER(D13),AND(D13>=0),FALSE)),"falta o material",(IF(NOT(IF(ISNUMBER(B13),AND(B13>=0),FALSE)),"faltam os minutos",IF(AND(C13<>"Sim",C13<>"Não"),"falta: gera retorno?",IF(AND(C13="Sim",NOT(AND(IF(ISNUMBER(Config!$B$11),AND(Config!$B$11>=0),FALSE),IF(ISNUMBER(Config!$B$12),AND(Config!$B$12>=0),FALSE)))),"falta o retorno em Config",B13+IF(C13="Sim",Config!$B$11*Config!$B$12,0)))))/60*Config!$B$7+D13)))) -> 158.33333 | F13: =IF(A13="","",IF(NOT(ISNUMBER(E13)),E13,IF((Config!$B$15<>"Sim"),"margens inválidas (Config)",E13/(1-Config!$B$8-Config!$B$9)))) -> 268.36158 | G13: =IF(A13="","",IF(NOT(ISNUMBER(E13)),E13,IF((Config!$B$15<>"Sim"),"margens inválidas (Config)",E13/(1-Config!$B$8-Config!$B$10)))) -> 359.84848 | H13: 450 | I13: 140 | J13: 125 | K13: 110 | N13: =IF(A13="","",IF(H13="","Falta o preço particular",IF(NOT(IF(ISNUMBER(H13),AND(H13>=0),FALSE)),"Preço inválido",IF(NOT(ISNUMBER(E13)),IF(IF(ISNUMBER(Config!$B$7),Config!$B$7>=0,FALSE),"Faltam dados da linha","Falta o custo-hora"),IF(OR(NOT(ISNUMBER(F13)),NOT(ISNUMBER(G13))),"Margens inválidas",IF(H13=0,"Sem cobrança",IF(H13<F13,"Abaixo do mínimo",IF(H13<G13,"Entre mínimo e alvo","No alvo ou acima")))))))) -> No alvo ou acima | O13: =IF(OR(A13="",NOT(ISNUMBER(F13))),"",IF(SUMPRODUCT(ISTEXT(I13:M13)+ISNUMBER(I13:M13)*(I13:M13<0))>0,"tabela inválida (texto ou negativo)",SUMPRODUCT((I13:M13<>"")*ISNUMBER(I13:M13)*(((I13:M13)>0)+(N(H13)>0)>0)*(I13:M13*(1-Config!$B$8)<E13)))) -> 3 | P13: 8 | Q13: 2270 | R13: =IF(OR(A13="",AND(P13="",Q13="")),"",IF(OR(NOT(IF(ISNUMBER(P13),AND(P13>=0),FALSE)),NOT(IF(ISNUMBER(Q13),AND(Q13>=0),FALSE))),"volume ou produção faltando ou negativos",IF(P13=0,"",Q13/P13))) -> 283.75 | S13: =IF(OR(NOT(ISNUMBER(R13)),NOT(ISNUMBER(F13)),NOT(IF(ISNUMBER(H13),H13>0,FALSE))),"",IF(F13=0,"sem base (mínimo zero)",R13/F13-1)) -> 0.057342105
A14: Avaliação endócrina | B14: 40 | C14: Sim | D14: 4 | E14: =IF(A14="","",IF(NOT(ISNUMBER((IF(NOT(IF(ISNUMBER(B14),AND(B14>=0),FALSE)),"faltam os minutos",IF(AND(C14<>"Sim",C14<>"Não"),"falta: gera retorno?",IF(AND(C14="Sim",NOT(AND(IF(ISNUMBER(Config!$B$11),AND(Config!$B$11>=0),FALSE),IF(ISNUMBER(Config!$B$12),AND(Config!$B$12>=0),FALSE)))),"falta o retorno em Config",B14+IF(C14="Sim",Config!$B$11*Config!$B$12,0))))))),(IF(NOT(IF(ISNUMBER(B14),AND(B14>=0),FALSE)),"faltam os minutos",IF(AND(C14<>"Sim",C14<>"Não"),"falta: gera retorno?",IF(AND(C14="Sim",NOT(AND(IF(ISNUMBER(Config!$B$11),AND(Config!$B$11>=0),FALSE),IF(ISNUMBER(Config!$B$12),AND(Config!$B$12>=0),FALSE)))),"falta o retorno em Config",B14+IF(C14="Sim",Config!$B$11*Config!$B$12,0))))),IF(NOT(IF(ISNUMBER(Config!$B$7),AND(Config!$B$7>=0),FALSE)),"falta o custo-hora em Config",IF(NOT(IF(ISNUMBER(D14),AND(D14>=0),FALSE)),"falta o material",(IF(NOT(IF(ISNUMBER(B14),AND(B14>=0),FALSE)),"faltam os minutos",IF(AND(C14<>"Sim",C14<>"Não"),"falta: gera retorno?",IF(AND(C14="Sim",NOT(AND(IF(ISNUMBER(Config!$B$11),AND(Config!$B$11>=0),FALSE),IF(ISNUMBER(Config!$B$12),AND(Config!$B$12>=0),FALSE)))),"falta o retorno em Config",B14+IF(C14="Sim",Config!$B$11*Config!$B$12,0)))))/60*Config!$B$7+D14)))) -> 164 | F14: =IF(A14="","",IF(NOT(ISNUMBER(E14)),E14,IF((Config!$B$15<>"Sim"),"margens inválidas (Config)",E14/(1-Config!$B$8-Config!$B$9)))) -> 277.9661 | G14: =IF(A14="","",IF(NOT(ISNUMBER(E14)),E14,IF((Config!$B$15<>"Sim"),"margens inválidas (Config)",E14/(1-Config!$B$8-Config!$B$10)))) -> 372.72727 | H14: 400 | I14: 130 | N14: =IF(A14="","",IF(H14="","Falta o preço particular",IF(NOT(IF(ISNUMBER(H14),AND(H14>=0),FALSE)),"Preço inválido",IF(NOT(ISNUMBER(E14)),IF(IF(ISNUMBER(Config!$B$7),Config!$B$7>=0,FALSE),"Faltam dados da linha","Falta o custo-hora"),IF(OR(NOT(ISNUMBER(F14)),NOT(ISNUMBER(G14))),"Margens inválidas",IF(H14=0,"Sem cobrança",IF(H14<F14,"Abaixo do mínimo",IF(H14<G14,"Entre mínimo e alvo","No alvo ou acima")))))))) -> No alvo ou acima | O14: =IF(OR(A14="",NOT(ISNUMBER(F14))),"",IF(SUMPRODUCT(ISTEXT(I14:M14)+ISNUMBER(I14:M14)*(I14:M14<0))>0,"tabela inválida (texto ou negativo)",SUMPRODUCT((I14:M14<>"")*ISNUMBER(I14:M14)*(((I14:M14)>0)+(N(H14)>0)>0)*(I14:M14*(1-Config!$B$8)<E14)))) -> 1 | P14: 30 | Q14: 10380 | R14: =IF(OR(A14="",AND(P14="",Q14="")),"",IF(OR(NOT(IF(ISNUMBER(P14),AND(P14>=0),FALSE)),NOT(IF(ISNUMBER(Q14),AND(Q14>=0),FALSE))),"volume ou produção faltando ou negativos",IF(P14=0,"",Q14/P14))) -> 346 | S14: =IF(OR(NOT(ISNUMBER(R14)),NOT(ISNUMBER(F14)),NOT(IF(ISNUMBER(H14),H14>0,FALSE))),"",IF(F14=0,"sem base (mínimo zero)",R14/F14-1)) -> 0.2447561
E15: =IF(A15="","",IF(NOT(ISNUMBER((IF(NOT(IF(ISNUMBER(B15),AND(B15>=0),FALSE)),"faltam os minutos",IF(AND(C15<>"Sim",C15<>"Não"),"falta: gera retorno?",IF(AND(C15="Sim",NOT(AND(IF(ISNUMBER(Config!$B$11),AND(Config!$B$11>=0),FALSE),IF(ISNUMBER(Config!$B$12),AND(Config!$B$12>=0),FALSE)))),"falta o retorno em Config",B15+IF(C15="Sim",Config!$B$11*Config!$B$12,0))))))),(IF(NOT(IF(ISNUMBER(B15),AND(B15>=0),FALSE)),"faltam os minutos",IF(AND(C15<>"Sim",C15<>"Não"),"falta: gera retorno?",IF(AND(C15="Sim",NOT(AND(IF(ISNUMBER(Config!$B$11),AND(Config!$B$11>=0),FALSE),IF(ISNUMBER(Config!$B$12),AND(Config!$B$12>=0),FALSE)))),"falta o retorno em Config",B15+IF(C15="Sim",Config!$B$11*Config!$B$12,0))))),IF(NOT(IF(ISNUMBER(Config!$B$7),AND(Config!$B$7>=0),FALSE)),"falta o custo-hora em Config",IF(NOT(IF(ISNUMBER(D15),AND(D15>=0),FALSE)),"falta o material",(IF(NOT(IF(ISNUMBER(B15),AND(B15>=0),FALSE)),"faltam os minutos",IF(AND(C15<>"Sim",C15<>"Não"),"falta: gera retorno?",IF(AND(C15="Sim",NOT(AND(IF(ISNUMBER(Config!$B$11),AND(Config!$B$11>=0),FALSE),IF(ISNUMBER(Config!$B$12),AND(Config!$B$12>=0),FALSE)))),"falta o retorno em Config",B15+IF(C15="Sim",Config!$B$11*Config!$B$12,0)))))/60*Config!$B$7+D15)))) | F15: =IF(A15="","",IF(NOT(ISNUMBER(E15)),E15,IF((Config!$B$15<>"Sim"),"margens inválidas (Config)",E15/(1-Config!$B$8-Config!$B$9)))) | G15: =IF(A15="","",IF(NOT(ISNUMBER(E15)),E15,IF((Config!$B$15<>"Sim"),"margens inválidas (Config)",E15/(1-Config!$B$8-Config!$B$10)))) | N15: =IF(A15="","",IF(H15="","Falta o preço particular",IF(NOT(IF(ISNUMBER(H15),AND(H15>=0),FALSE)),"Preço inválido",IF(NOT(ISNUMBER(E15)),IF(IF(ISNUMBER(Config!$B$7),Config!$B$7>=0,FALSE),"Faltam dados da linha","Falta o custo-hora"),IF(OR(NOT(ISNUMBER(F15)),NOT(ISNUMBER(G15))),"Margens inválidas",IF(H15=0,"Sem cobrança",IF(H15<F15,"Abaixo do mínimo",IF(H15<G15,"Entre mínimo e alvo","No alvo ou acima")))))))) | O15: =IF(OR(A15="",NOT(ISNUMBER(F15))),"",IF(SUMPRODUCT(ISTEXT(I15:M15)+ISNUMBER(I15:M15)*(I15:M15<0))>0,"tabela inválida (texto ou negativo)",SUMPRODUCT((I15:M15<>"")*ISNUMBER(I15:M15)*(((I15:M15)>0)+(N(H15)>0)>0)*(I15:M15*(1-Config!$B$8)<E15)))) | R15: =IF(OR(A15="",AND(P15="",Q15="")),"",IF(OR(NOT(IF(ISNUMBER(P15),AND(P15>=0),FALSE)),NOT(IF(ISNUMBER(Q15),AND(Q15>=0),FALSE))),"volume ou produção faltando ou negativos",IF(P15=0,"",Q15/P15))) | S15: =IF(OR(NOT(ISNUMBER(R15)),NOT(ISNUMBER(F15)),NOT(IF(ISNUMBER(H15),H15>0,FALSE))),"",IF(F15=0,"sem base (mínimo zero)",R15/F15-1))
E16: =IF(A16="","",IF(NOT(ISNUMBER((IF(NOT(IF(ISNUMBER(B16),AND(B16>=0),FALSE)),"faltam os minutos",IF(AND(C16<>"Sim",C16<>"Não"),"falta: gera retorno?",IF(AND(C16="Sim",NOT(AND(IF(ISNUMBER(Config!$B$11),AND(Config!$B$11>=0),FALSE),IF(ISNUMBER(Config!$B$12),AND(Config!$B$12>=0),FALSE)))),"falta o retorno em Config",B16+IF(C16="Sim",Config!$B$11*Config!$B$12,0))))))),(IF(NOT(IF(ISNUMBER(B16),AND(B16>=0),FALSE)),"faltam os minutos",IF(AND(C16<>"Sim",C16<>"Não"),"falta: gera retorno?",IF(AND(C16="Sim",NOT(AND(IF(ISNUMBER(Config!$B$11),AND(Config!$B$11>=0),FALSE),IF(ISNUMBER(Config!$B$12),AND(Config!$B$12>=0),FALSE)))),"falta o retorno em Config",B16+IF(C16="Sim",Config!$B$11*Config!$B$12,0))))),IF(NOT(IF(ISNUMBER(Config!$B$7),AND(Config!$B$7>=0),FALSE)),"falta o custo-hora em Config",IF(NOT(IF(ISNUMBER(D16),AND(D16>=0),FALSE)),"falta o material",(IF(NOT(IF(ISNUMBER(B16),AND(B16>=0),FALSE)),"faltam os minutos",IF(AND(C16<>"Sim",C16<>"Não"),"falta: gera retorno?",IF(AND(C16="Sim",NOT(AND(IF(ISNUMBER(Config!$B$11),AND(Config!$B$11>=0),FALSE),IF(ISNUMBER(Config!$B$12),AND(Config!$B$12>=0),FALSE)))),"falta o retorno em Config",B16+IF(C16="Sim",Config!$B$11*Config!$B$12,0)))))/60*Config!$B$7+D16)))) | F16: =IF(A16="","",IF(NOT(ISNUMBER(E16)),E16,IF((Config!$B$15<>"Sim"),"margens inválidas (Config)",E16/(1-Config!$B$8-Config!$B$9)))) | G16: =IF(A16="","",IF(NOT(ISNUMBER(E16)),E16,IF((Config!$B$15<>"Sim"),"margens inválidas (Config)",E16/(1-Config!$B$8-Config!$B$10)))) | N16: =IF(A16="","",IF(H16="","Falta o preço particular",IF(NOT(IF(ISNUMBER(H16),AND(H16>=0),FALSE)),"Preço inválido",IF(NOT(ISNUMBER(E16)),IF(IF(ISNUMBER(Config!$B$7),Config!$B$7>=0,FALSE),"Faltam dados da linha","Falta o custo-hora"),IF(OR(NOT(ISNUMBER(F16)),NOT(ISNUMBER(G16))),"Margens inválidas",IF(H16=0,"Sem cobrança",IF(H16<F16,"Abaixo do mínimo",IF(H16<G16,"Entre mínimo e alvo","No alvo ou acima")))))))) | O16: =IF(OR(A16="",NOT(ISNUMBER(F16))),"",IF(SUMPRODUCT(ISTEXT(I16:M16)+ISNUMBER(I16:M16)*(I16:M16<0))>0,"tabela inválida (texto ou negativo)",SUMPRODUCT((I16:M16<>"")*ISNUMBER(I16:M16)*(((I16:M16)>0)+(N(H16)>0)>0)*(I16:M16*(1-Config!$B$8)<E16)))) | R16: =IF(OR(A16="",AND(P16="",Q16="")),"",IF(OR(NOT(IF(ISNUMBER(P16),AND(P16>=0),FALSE)),NOT(IF(ISNUMBER(Q16),AND(Q16>=0),FALSE))),"volume ou produção faltando ou negativos",IF(P16=0,"",Q16/P16))) | S16: =IF(OR(NOT(ISNUMBER(R16)),NOT(ISNUMBER(F16)),NOT(IF(ISNUMBER(H16),H16>0,FALSE))),"",IF(F16=0,"sem base (mínimo zero)",R16/F16-1))
E17: =IF(A17="","",IF(NOT(ISNUMBER((IF(NOT(IF(ISNUMBER(B17),AND(B17>=0),FALSE)),"faltam os minutos",IF(AND(C17<>"Sim",C17<>"Não"),"falta: gera retorno?",IF(AND(C17="Sim",NOT(AND(IF(ISNUMBER(Config!$B$11),AND(Config!$B$11>=0),FALSE),IF(ISNUMBER(Config!$B$12),AND(Config!$B$12>=0),FALSE)))),"falta o retorno em Config",B17+IF(C17="Sim",Config!$B$11*Config!$B$12,0))))))),(IF(NOT(IF(ISNUMBER(B17),AND(B17>=0),FALSE)),"faltam os minutos",IF(AND(C17<>"Sim",C17<>"Não"),"falta: gera retorno?",IF(AND(C17="Sim",NOT(AND(IF(ISNUMBER(Config!$B$11),AND(Config!$B$11>=0),FALSE),IF(ISNUMBER(Config!$B$12),AND(Config!$B$12>=0),FALSE)))),"falta o retorno em Config",B17+IF(C17="Sim",Config!$B$11*Config!$B$12,0))))),IF(NOT(IF(ISNUMBER(Config!$B$7),AND(Config!$B$7>=0),FALSE)),"falta o custo-hora em Config",IF(NOT(IF(ISNUMBER(D17),AND(D17>=0),FALSE)),"falta o material",(IF(NOT(IF(ISNUMBER(B17),AND(B17>=0),FALSE)),"faltam os minutos",IF(AND(C17<>"Sim",C17<>"Não"),"falta: gera retorno?",IF(AND(C17="Sim",NOT(AND(IF(ISNUMBER(Config!$B$11),AND(Config!$B$11>=0),FALSE),IF(ISNUMBER(Config!$B$12),AND(Config!$B$12>=0),FALSE)))),"falta o retorno em Config",B17+IF(C17="Sim",Config!$B$11*Config!$B$12,0)))))/60*Config!$B$7+D17)))) | F17: =IF(A17="","",IF(NOT(ISNUMBER(E17)),E17,IF((Config!$B$15<>"Sim"),"margens inválidas (Config)",E17/(1-Config!$B$8-Config!$B$9)))) | G17: =IF(A17="","",IF(NOT(ISNUMBER(E17)),E17,IF((Config!$B$15<>"Sim"),"margens inválidas (Config)",E17/(1-Config!$B$8-Config!$B$10)))) | N17: =IF(A17="","",IF(H17="","Falta o preço particular",IF(NOT(IF(ISNUMBER(H17),AND(H17>=0),FALSE)),"Preço inválido",IF(NOT(ISNUMBER(E17)),IF(IF(ISNUMBER(Config!$B$7),Config!$B$7>=0,FALSE),"Faltam dados da linha","Falta o custo-hora"),IF(OR(NOT(ISNUMBER(F17)),NOT(ISNUMBER(G17))),"Margens inválidas",IF(H17=0,"Sem cobrança",IF(H17<F17,"Abaixo do mínimo",IF(H17<G17,"Entre mínimo e alvo","No alvo ou acima")))))))) | O17: =IF(OR(A17="",NOT(ISNUMBER(F17))),"",IF(SUMPRODUCT(ISTEXT(I17:M17)+ISNUMBER(I17:M17)*(I17:M17<0))>0,"tabela inválida (texto ou negativo)",SUMPRODUCT((I17:M17<>"")*ISNUMBER(I17:M17)*(((I17:M17)>0)+(N(H17)>0)>0)*(I17:M17*(1-Config!$B$8)<E17)))) | R17: =IF(OR(A17="",AND(P17="",Q17="")),"",IF(OR(NOT(IF(ISNUMBER(P17),AND(P17>=0),FALSE)),NOT(IF(ISNUMBER(Q17),AND(Q17>=0),FALSE))),"volume ou produção faltando ou negativos",IF(P17=0,"",Q17/P17))) | S17: =IF(OR(NOT(ISNUMBER(R17)),NOT(ISNUMBER(F17)),NOT(IF(ISNUMBER(H17),H17>0,FALSE))),"",IF(F17=0,"sem base (mínimo zero)",R17/F17-1))
E18: =IF(A18="","",IF(NOT(ISNUMBER((IF(NOT(IF(ISNUMBER(B18),AND(B18>=0),FALSE)),"faltam os minutos",IF(AND(C18<>"Sim",C18<>"Não"),"falta: gera retorno?",IF(AND(C18="Sim",NOT(AND(IF(ISNUMBER(Config!$B$11),AND(Config!$B$11>=0),FALSE),IF(ISNUMBER(Config!$B$12),AND(Config!$B$12>=0),FALSE)))),"falta o retorno em Config",B18+IF(C18="Sim",Config!$B$11*Config!$B$12,0))))))),(IF(NOT(IF(ISNUMBER(B18),AND(B18>=0),FALSE)),"faltam os minutos",IF(AND(C18<>"Sim",C18<>"Não"),"falta: gera retorno?",IF(AND(C18="Sim",NOT(AND(IF(ISNUMBER(Config!$B$11),AND(Config!$B$11>=0),FALSE),IF(ISNUMBER(Config!$B$12),AND(Config!$B$12>=0),FALSE)))),"falta o retorno em Config",B18+IF(C18="Sim",Config!$B$11*Config!$B$12,0))))),IF(NOT(IF(ISNUMBER(Config!$B$7),AND(Config!$B$7>=0),FALSE)),"falta o custo-hora em Config",IF(NOT(IF(ISNUMBER(D18),AND(D18>=0),FALSE)),"falta o material",(IF(NOT(IF(ISNUMBER(B18),AND(B18>=0),FALSE)),"faltam os minutos",IF(AND(C18<>"Sim",C18<>"Não"),"falta: gera retorno?",IF(AND(C18="Sim",NOT(AND(IF(ISNUMBER(Config!$B$11),AND(Config!$B$11>=0),FALSE),IF(ISNUMBER(Config!$B$12),AND(Config!$B$12>=0),FALSE)))),"falta o retorno em Config",B18+IF(C18="Sim",Config!$B$11*Config!$B$12,0)))))/60*Config!$B$7+D18)))) | F18: =IF(A18="","",IF(NOT(ISNUMBER(E18)),E18,IF((Config!$B$15<>"Sim"),"margens inválidas (Config)",E18/(1-Config!$B$8-Config!$B$9)))) | G18: =IF(A18="","",IF(NOT(ISNUMBER(E18)),E18,IF((Config!$B$15<>"Sim"),"margens inválidas (Config)",E18/(1-Config!$B$8-Config!$B$10)))) | N18: =IF(A18="","",IF(H18="","Falta o preço particular",IF(NOT(IF(ISNUMBER(H18),AND(H18>=0),FALSE)),"Preço inválido",IF(NOT(ISNUMBER(E18)),IF(IF(ISNUMBER(Config!$B$7),Config!$B$7>=0,FALSE),"Faltam dados da linha","Falta o custo-hora"),IF(OR(NOT(ISNUMBER(F18)),NOT(ISNUMBER(G18))),"Margens inválidas",IF(H18=0,"Sem cobrança",IF(H18<F18,"Abaixo do mínimo",IF(H18<G18,"Entre mínimo e alvo","No alvo ou acima")))))))) | O18: =IF(OR(A18="",NOT(ISNUMBER(F18))),"",IF(SUMPRODUCT(ISTEXT(I18:M18)+ISNUMBER(I18:M18)*(I18:M18<0))>0,"tabela inválida (texto ou negativo)",SUMPRODUCT((I18:M18<>"")*ISNUMBER(I18:M18)*(((I18:M18)>0)+(N(H18)>0)>0)*(I18:M18*(1-Config!$B$8)<E18)))) | R18: =IF(OR(A18="",AND(P18="",Q18="")),"",IF(OR(NOT(IF(ISNUMBER(P18),AND(P18>=0),FALSE)),NOT(IF(ISNUMBER(Q18),AND(Q18>=0),FALSE))),"volume ou produção faltando ou negativos",IF(P18=0,"",Q18/P18))) | S18: =IF(OR(NOT(ISNUMBER(R18)),NOT(ISNUMBER(F18)),NOT(IF(ISNUMBER(H18),H18>0,FALSE))),"",IF(F18=0,"sem base (mínimo zero)",R18/F18-1))
E19: =IF(A19="","",IF(NOT(ISNUMBER((IF(NOT(IF(ISNUMBER(B19),AND(B19>=0),FALSE)),"faltam os minutos",IF(AND(C19<>"Sim",C19<>"Não"),"falta: gera retorno?",IF(AND(C19="Sim",NOT(AND(IF(ISNUMBER(Config!$B$11),AND(Config!$B$11>=0),FALSE),IF(ISNUMBER(Config!$B$12),AND(Config!$B$12>=0),FALSE)))),"falta o retorno em Config",B19+IF(C19="Sim",Config!$B$11*Config!$B$12,0))))))),(IF(NOT(IF(ISNUMBER(B19),AND(B19>=0),FALSE)),"faltam os minutos",IF(AND(C19<>"Sim",C19<>"Não"),"falta: gera retorno?",IF(AND(C19="Sim",NOT(AND(IF(ISNUMBER(Config!$B$11),AND(Config!$B$11>=0),FALSE),IF(ISNUMBER(Config!$B$12),AND(Config!$B$12>=0),FALSE)))),"falta o retorno em Config",B19+IF(C19="Sim",Config!$B$11*Config!$B$12,0))))),IF(NOT(IF(ISNUMBER(Config!$B$7),AND(Config!$B$7>=0),FALSE)),"falta o custo-hora em Config",IF(NOT(IF(ISNUMBER(D19),AND(D19>=0),FALSE)),"falta o material",(IF(NOT(IF(ISNUMBER(B19),AND(B19>=0),FALSE)),"faltam os minutos",IF(AND(C19<>"Sim",C19<>"Não"),"falta: gera retorno?",IF(AND(C19="Sim",NOT(AND(IF(ISNUMBER(Config!$B$11),AND(Config!$B$11>=0),FALSE),IF(ISNUMBER(Config!$B$12),AND(Config!$B$12>=0),FALSE)))),"falta o retorno em Config",B19+IF(C19="Sim",Config!$B$11*Config!$B$12,0)))))/60*Config!$B$7+D19)))) | F19: =IF(A19="","",IF(NOT(ISNUMBER(E19)),E19,IF((Config!$B$15<>"Sim"),"margens inválidas (Config)",E19/(1-Config!$B$8-Config!$B$9)))) | G19: =IF(A19="","",IF(NOT(ISNUMBER(E19)),E19,IF((Config!$B$15<>"Sim"),"margens inválidas (Config)",E19/(1-Config!$B$8-Config!$B$10)))) | N19: =IF(A19="","",IF(H19="","Falta o preço particular",IF(NOT(IF(ISNUMBER(H19),AND(H19>=0),FALSE)),"Preço inválido",IF(NOT(ISNUMBER(E19)),IF(IF(ISNUMBER(Config!$B$7),Config!$B$7>=0,FALSE),"Faltam dados da linha","Falta o custo-hora"),IF(OR(NOT(ISNUMBER(F19)),NOT(ISNUMBER(G19))),"Margens inválidas",IF(H19=0,"Sem cobrança",IF(H19<F19,"Abaixo do mínimo",IF(H19<G19,"Entre mínimo e alvo","No alvo ou acima")))))))) | O19: =IF(OR(A19="",NOT(ISNUMBER(F19))),"",IF(SUMPRODUCT(ISTEXT(I19:M19)+ISNUMBER(I19:M19)*(I19:M19<0))>0,"tabela inválida (texto ou negativo)",SUMPRODUCT((I19:M19<>"")*ISNUMBER(I19:M19)*(((I19:M19)>0)+(N(H19)>0)>0)*(I19:M19*(1-Config!$B$8)<E19)))) | R19: =IF(OR(A19="",AND(P19="",Q19="")),"",IF(OR(NOT(IF(ISNUMBER(P19),AND(P19>=0),FALSE)),NOT(IF(ISNUMBER(Q19),AND(Q19>=0),FALSE))),"volume ou produção faltando ou negativos",IF(P19=0,"",Q19/P19))) | S19: =IF(OR(NOT(ISNUMBER(R19)),NOT(ISNUMBER(F19)),NOT(IF(ISNUMBER(H19),H19>0,FALSE))),"",IF(F19=0,"sem base (mínimo zero)",R19/F19-1))
A21: Custo cheio, preço mínimo e preço alvo: a mesma conta da planilha 06 (tempo com retorno × custo-hora + material; ÷ (1 − impostos − margem)). Tabela de convênio em vermelho: depois dos impostos não cobre o custo cheio (margem negativa) — é a mesma conta e o mesmo número do KPI "Tabelas de convênio abaixo do custo cheio + imposto" e do Resumo da planilha 06. Tabela 0 em procedimento cobrado conta (o convênio não paga o custo); no retorno, com particular 0 também, não conta. Amarela: cobre o custo, mas não a margem mínima.
A22: Realizados e Produção no mês: copie de "Por procedimento" no Painel da planilha 01 com o mês fechado escolhido em Config (no exemplo, agosto de 2026). Valor médio praticado = produção ÷ realizados: mistura particular e convênio, por isso fica abaixo do preço particular.
A23: Referência de mercado é opcional e sua: pesquise a faixa da sua região e anote; a planilha não afirma preço de mercado. A tabela de preços e a divulgação de valores seguem as regras do CFM: revise antes de publicar.
A25: Valor por hora de atendimento, por pagador (tabela ÷ tempo com retorno)
A26: Procedimento | B26: Minutos com retorno | C26: =IF(Config!$B$17="","",Config!$B$17) -> Particular | D26: =IF(Config!$B$18="","",Config!$B$18) -> Saúde Total | E26: =IF(Config!$B$19="","",Config!$B$19) -> MediPlan | F26: =IF(Config!$B$20="","",Config!$B$20) -> Vida Care | G26: =IF(Config!$B$21="","",Config!$B$21) | H26: =IF(Config!$B$22="","",Config!$B$22) | I26: Hora mínima | J26: Hora alvo
A27: =IF($A8="","",$A8) -> Consulta | B27: =IF($A8="","",IF(NOT(IF(ISNUMBER(B8),AND(B8>=0),FALSE)),"faltam os minutos",IF(AND(C8<>"Sim",C8<>"Não"),"falta: gera retorno?",IF(AND(C8="Sim",NOT(AND(IF(ISNUMBER(Config!$B$11),AND(Config!$B$11>=0),FALSE),IF(ISNUMBER(Config!$B$12),AND(Config!$B$12>=0),FALSE)))),"falta o retorno em Config",B8+IF(C8="Sim",Config!$B$11*Config!$B$12,0))))) -> 38 | C27: =IF(OR($A8="",H8="",NOT(IF(ISNUMBER(H8),AND(H8>=0),FALSE)),NOT(ISNUMBER($B27)),N($B27)=0),"",H8/($B27/60)) -> 600 | D27: =IF(OR($A8="",I8="",NOT(IF(ISNUMBER(I8),AND(I8>=0),FALSE)),NOT(ISNUMBER($B27)),N($B27)=0),"",I8/($B27/60)) -> 189.47368 | E27: =IF(OR($A8="",J8="",NOT(IF(ISNUMBER(J8),AND(J8>=0),FALSE)),NOT(ISNUMBER($B27)),N($B27)=0),"",J8/($B27/60)) -> 157.89474 | F27: =IF(OR($A8="",K8="",NOT(IF(ISNUMBER(K8),AND(K8>=0),FALSE)),NOT(ISNUMBER($B27)),N($B27)=0),"",K8/($B27/60)) -> 142.10526 | G27: =IF(OR($A8="",L8="",NOT(IF(ISNUMBER(L8),AND(L8>=0),FALSE)),NOT(ISNUMBER($B27)),N($B27)=0),"",L8/($B27/60)) | H27: =IF(OR($A8="",M8="",NOT(IF(ISNUMBER(M8),AND(M8>=0),FALSE)),NOT(ISNUMBER($B27)),N($B27)=0),"",M8/($B27/60)) | I27: =IF($A8="","",Config!$B$13) -> 338.98305 | J27: =IF($A8="","",Config!$B$14) -> 454.54545
A28: =IF($A9="","",$A9) -> Retorno | B28: =IF($A9="","",IF(NOT(IF(ISNUMBER(B9),AND(B9>=0),FALSE)),"faltam os minutos",IF(AND(C9<>"Sim",C9<>"Não"),"falta: gera retorno?",IF(AND(C9="Sim",NOT(AND(IF(ISNUMBER(Config!$B$11),AND(Config!$B$11>=0),FALSE),IF(ISNUMBER(Config!$B$12),AND(Config!$B$12>=0),FALSE)))),"falta o retorno em Config",B9+IF(C9="Sim",Config!$B$11*Config!$B$12,0))))) -> 20 | C28: =IF(OR($A9="",H9="",NOT(IF(ISNUMBER(H9),AND(H9>=0),FALSE)),NOT(ISNUMBER($B28)),N($B28)=0),"",H9/($B28/60)) -> 0 | D28: =IF(OR($A9="",I9="",NOT(IF(ISNUMBER(I9),AND(I9>=0),FALSE)),NOT(ISNUMBER($B28)),N($B28)=0),"",I9/($B28/60)) -> 0 | E28: =IF(OR($A9="",J9="",NOT(IF(ISNUMBER(J9),AND(J9>=0),FALSE)),NOT(ISNUMBER($B28)),N($B28)=0),"",J9/($B28/60)) -> 0 | F28: =IF(OR($A9="",K9="",NOT(IF(ISNUMBER(K9),AND(K9>=0),FALSE)),NOT(ISNUMBER($B28)),N($B28)=0),"",K9/($B28/60)) -> 0 | G28: =IF(OR($A9="",L9="",NOT(IF(ISNUMBER(L9),AND(L9>=0),FALSE)),NOT(ISNUMBER($B28)),N($B28)=0),"",L9/($B28/60)) | H28: =IF(OR($A9="",M9="",NOT(IF(ISNUMBER(M9),AND(M9>=0),FALSE)),NOT(ISNUMBER($B28)),N($B28)=0),"",M9/($B28/60)) | I28: =IF($A9="","",Config!$B$13) -> 338.98305 | J28: =IF($A9="","",Config!$B$14) -> 454.54545
A29: =IF($A10="","",$A10) -> ECG | B29: =IF($A10="","",IF(NOT(IF(ISNUMBER(B10),AND(B10>=0),FALSE)),"faltam os minutos",IF(AND(C10<>"Sim",C10<>"Não"),"falta: gera retorno?",IF(AND(C10="Sim",NOT(AND(IF(ISNUMBER(Config!$B$11),AND(Config!$B$11>=0),FALSE),IF(ISNUMBER(Config!$B$12),AND(Config!$B$12>=0),FALSE)))),"falta o retorno em Config",B10+IF(C10="Sim",Config!$B$11*Config!$B$12,0))))) -> 20 | C29: =IF(OR($A10="",H10="",NOT(IF(ISNUMBER(H10),AND(H10>=0),FALSE)),NOT(ISNUMBER($B29)),N($B29)=0),"",H10/($B29/60)) -> 390 | D29: =IF(OR($A10="",I10="",NOT(IF(ISNUMBER(I10),AND(I10>=0),FALSE)),NOT(ISNUMBER($B29)),N($B29)=0),"",I10/($B29/60)) -> 120 | E29: =IF(OR($A10="",J10="",NOT(IF(ISNUMBER(J10),AND(J10>=0),FALSE)),NOT(ISNUMBER($B29)),N($B29)=0),"",J10/($B29/60)) -> 105 | F29: =IF(OR($A10="",K10="",NOT(IF(ISNUMBER(K10),AND(K10>=0),FALSE)),NOT(ISNUMBER($B29)),N($B29)=0),"",K10/($B29/60)) -> 96 | G29: =IF(OR($A10="",L10="",NOT(IF(ISNUMBER(L10),AND(L10>=0),FALSE)),NOT(ISNUMBER($B29)),N($B29)=0),"",L10/($B29/60)) | H29: =IF(OR($A10="",M10="",NOT(IF(ISNUMBER(M10),AND(M10>=0),FALSE)),NOT(ISNUMBER($B29)),N($B29)=0),"",M10/($B29/60)) | I29: =IF($A10="","",Config!$B$13) -> 338.98305 | J29: =IF($A10="","",Config!$B$14) -> 454.54545
A30: =IF($A11="","",$A11) -> MAPA | B30: =IF($A11="","",IF(NOT(IF(ISNUMBER(B11),AND(B11>=0),FALSE)),"faltam os minutos",IF(AND(C11<>"Sim",C11<>"Não"),"falta: gera retorno?",IF(AND(C11="Sim",NOT(AND(IF(ISNUMBER(Config!$B$11),AND(Config!$B$11>=0),FALSE),IF(ISNUMBER(Config!$B$12),AND(Config!$B$12>=0),FALSE)))),"falta o retorno em Config",B11+IF(C11="Sim",Config!$B$11*Config!$B$12,0))))) -> 20 | C30: =IF(OR($A11="",H11="",NOT(IF(ISNUMBER(H11),AND(H11>=0),FALSE)),NOT(ISNUMBER($B30)),N($B30)=0),"",H11/($B30/60)) -> 900 | D30: =IF(OR($A11="",I11="",NOT(IF(ISNUMBER(I11),AND(I11>=0),FALSE)),NOT(ISNUMBER($B30)),N($B30)=0),"",I11/($B30/60)) -> 285 | E30: =IF(OR($A11="",J11="",NOT(IF(ISNUMBER(J11),AND(J11>=0),FALSE)),NOT(ISNUMBER($B30)),N($B30)=0),"",J11/($B30/60)) -> 255 | F30: =IF(OR($A11="",K11="",NOT(IF(ISNUMBER(K11),AND(K11>=0),FALSE)),NOT(ISNUMBER($B30)),N($B30)=0),"",K11/($B30/60)) -> 225 | G30: =IF(OR($A11="",L11="",NOT(IF(ISNUMBER(L11),AND(L11>=0),FALSE)),NOT(ISNUMBER($B30)),N($B30)=0),"",L11/($B30/60)) | H30: =IF(OR($A11="",M11="",NOT(IF(ISNUMBER(M11),AND(M11>=0),FALSE)),NOT(ISNUMBER($B30)),N($B30)=0),"",M11/($B30/60)) | I30: =IF($A11="","",Config!$B$13) -> 338.98305 | J30: =IF($A11="","",Config!$B$14) -> 454.54545
A31: =IF($A12="","",$A12) -> Holter | B31: =IF($A12="","",IF(NOT(IF(ISNUMBER(B12),AND(B12>=0),FALSE)),"faltam os minutos",IF(AND(C12<>"Sim",C12<>"Não"),"falta: gera retorno?",IF(AND(C12="Sim",NOT(AND(IF(ISNUMBER(Config!$B$11),AND(Config!$B$11>=0),FALSE),IF(ISNUMBER(Config!$B$12),AND(Config!$B$12>=0),FALSE)))),"falta o retorno em Config",B12+IF(C12="Sim",Config!$B$11*Config!$B$12,0))))) -> 20 | C31: =IF(OR($A12="",H12="",NOT(IF(ISNUMBER(H12),AND(H12>=0),FALSE)),NOT(ISNUMBER($B31)),N($B31)=0),"",H12/($B31/60)) -> 1050 | D31: =IF(OR($A12="",I12="",NOT(IF(ISNUMBER(I12),AND(I12>=0),FALSE)),NOT(ISNUMBER($B31)),N($B31)=0),"",I12/($B31/60)) -> 315 | E31: =IF(OR($A12="",J12="",NOT(IF(ISNUMBER(J12),AND(J12>=0),FALSE)),NOT(ISNUMBER($B31)),N($B31)=0),"",J12/($B31/60)) -> 285 | F31: =IF(OR($A12="",K12="",NOT(IF(ISNUMBER(K12),AND(K12>=0),FALSE)),NOT(ISNUMBER($B31)),N($B31)=0),"",K12/($B31/60)) -> 255 | G31: =IF(OR($A12="",L12="",NOT(IF(ISNUMBER(L12),AND(L12>=0),FALSE)),NOT(ISNUMBER($B31)),N($B31)=0),"",L12/($B31/60)) | H31: =IF(OR($A12="",M12="",NOT(IF(ISNUMBER(M12),AND(M12>=0),FALSE)),NOT(ISNUMBER($B31)),N($B31)=0),"",M12/($B31/60)) | I31: =IF($A12="","",Config!$B$13) -> 338.98305 | J31: =IF($A12="","",Config!$B$14) -> 454.54545
A32: =IF($A13="","",$A13) -> Teste ergométrico | B32: =IF($A13="","",IF(NOT(IF(ISNUMBER(B13),AND(B13>=0),FALSE)),"faltam os minutos",IF(AND(C13<>"Sim",C13<>"Não"),"falta: gera retorno?",IF(AND(C13="Sim",NOT(AND(IF(ISNUMBER(Config!$B$11),AND(Config!$B$11>=0),FALSE),IF(ISNUMBER(Config!$B$12),AND(Config!$B$12>=0),FALSE)))),"falta o retorno em Config",B13+IF(C13="Sim",Config!$B$11*Config!$B$12,0))))) -> 40 | C32: =IF(OR($A13="",H13="",NOT(IF(ISNUMBER(H13),AND(H13>=0),FALSE)),NOT(ISNUMBER($B32)),N($B32)=0),"",H13/($B32/60)) -> 675 | D32: =IF(OR($A13="",I13="",NOT(IF(ISNUMBER(I13),AND(I13>=0),FALSE)),NOT(ISNUMBER($B32)),N($B32)=0),"",I13/($B32/60)) -> 210 | E32: =IF(OR($A13="",J13="",NOT(IF(ISNUMBER(J13),AND(J13>=0),FALSE)),NOT(ISNUMBER($B32)),N($B32)=0),"",J13/($B32/60)) -> 187.5 | F32: =IF(OR($A13="",K13="",NOT(IF(ISNUMBER(K13),AND(K13>=0),FALSE)),NOT(ISNUMBER($B32)),N($B32)=0),"",K13/($B32/60)) -> 165 | G32: =IF(OR($A13="",L13="",NOT(IF(ISNUMBER(L13),AND(L13>=0),FALSE)),NOT(ISNUMBER($B32)),N($B32)=0),"",L13/($B32/60)) | H32: =IF(OR($A13="",M13="",NOT(IF(ISNUMBER(M13),AND(M13>=0),FALSE)),NOT(ISNUMBER($B32)),N($B32)=0),"",M13/($B32/60)) | I32: =IF($A13="","",Config!$B$13) -> 338.98305 | J32: =IF($A13="","",Config!$B$14) -> 454.54545
A33: =IF($A14="","",$A14) -> Avaliação endócrina | B33: =IF($A14="","",IF(NOT(IF(ISNUMBER(B14),AND(B14>=0),FALSE)),"faltam os minutos",IF(AND(C14<>"Sim",C14<>"Não"),"falta: gera retorno?",IF(AND(C14="Sim",NOT(AND(IF(ISNUMBER(Config!$B$11),AND(Config!$B$11>=0),FALSE),IF(ISNUMBER(Config!$B$12),AND(Config!$B$12>=0),FALSE)))),"falta o retorno em Config",B14+IF(C14="Sim",Config!$B$11*Config!$B$12,0))))) -> 48 | C33: =IF(OR($A14="",H14="",NOT(IF(ISNUMBER(H14),AND(H14>=0),FALSE)),NOT(ISNUMBER($B33)),N($B33)=0),"",H14/($B33/60)) -> 500 | D33: =IF(OR($A14="",I14="",NOT(IF(ISNUMBER(I14),AND(I14>=0),FALSE)),NOT(ISNUMBER($B33)),N($B33)=0),"",I14/($B33/60)) -> 162.5 | E33: =IF(OR($A14="",J14="",NOT(IF(ISNUMBER(J14),AND(J14>=0),FALSE)),NOT(ISNUMBER($B33)),N($B33)=0),"",J14/($B33/60)) | F33: =IF(OR($A14="",K14="",NOT(IF(ISNUMBER(K14),AND(K14>=0),FALSE)),NOT(ISNUMBER($B33)),N($B33)=0),"",K14/($B33/60)) | G33: =IF(OR($A14="",L14="",NOT(IF(ISNUMBER(L14),AND(L14>=0),FALSE)),NOT(ISNUMBER($B33)),N($B33)=0),"",L14/($B33/60)) | H33: =IF(OR($A14="",M14="",NOT(IF(ISNUMBER(M14),AND(M14>=0),FALSE)),NOT(ISNUMBER($B33)),N($B33)=0),"",M14/($B33/60)) | I33: =IF($A14="","",Config!$B$13) -> 338.98305 | J33: =IF($A14="","",Config!$B$14) -> 454.54545
A34: =IF($A15="","",$A15) | B34: =IF($A15="","",IF(NOT(IF(ISNUMBER(B15),AND(B15>=0),FALSE)),"faltam os minutos",IF(AND(C15<>"Sim",C15<>"Não"),"falta: gera retorno?",IF(AND(C15="Sim",NOT(AND(IF(ISNUMBER(Config!$B$11),AND(Config!$B$11>=0),FALSE),IF(ISNUMBER(Config!$B$12),AND(Config!$B$12>=0),FALSE)))),"falta o retorno em Config",B15+IF(C15="Sim",Config!$B$11*Config!$B$12,0))))) | C34: =IF(OR($A15="",H15="",NOT(IF(ISNUMBER(H15),AND(H15>=0),FALSE)),NOT(ISNUMBER($B34)),N($B34)=0),"",H15/($B34/60)) | D34: =IF(OR($A15="",I15="",NOT(IF(ISNUMBER(I15),AND(I15>=0),FALSE)),NOT(ISNUMBER($B34)),N($B34)=0),"",I15/($B34/60)) | E34: =IF(OR($A15="",J15="",NOT(IF(ISNUMBER(J15),AND(J15>=0),FALSE)),NOT(ISNUMBER($B34)),N($B34)=0),"",J15/($B34/60)) | F34: =IF(OR($A15="",K15="",NOT(IF(ISNUMBER(K15),AND(K15>=0),FALSE)),NOT(ISNUMBER($B34)),N($B34)=0),"",K15/($B34/60)) | G34: =IF(OR($A15="",L15="",NOT(IF(ISNUMBER(L15),AND(L15>=0),FALSE)),NOT(ISNUMBER($B34)),N($B34)=0),"",L15/($B34/60)) | H34: =IF(OR($A15="",M15="",NOT(IF(ISNUMBER(M15),AND(M15>=0),FALSE)),NOT(ISNUMBER($B34)),N($B34)=0),"",M15/($B34/60)) | I34: =IF($A15="","",Config!$B$13) | J34: =IF($A15="","",Config!$B$14)
A35: =IF($A16="","",$A16) | B35: =IF($A16="","",IF(NOT(IF(ISNUMBER(B16),AND(B16>=0),FALSE)),"faltam os minutos",IF(AND(C16<>"Sim",C16<>"Não"),"falta: gera retorno?",IF(AND(C16="Sim",NOT(AND(IF(ISNUMBER(Config!$B$11),AND(Config!$B$11>=0),FALSE),IF(ISNUMBER(Config!$B$12),AND(Config!$B$12>=0),FALSE)))),"falta o retorno em Config",B16+IF(C16="Sim",Config!$B$11*Config!$B$12,0))))) | C35: =IF(OR($A16="",H16="",NOT(IF(ISNUMBER(H16),AND(H16>=0),FALSE)),NOT(ISNUMBER($B35)),N($B35)=0),"",H16/($B35/60)) | D35: =IF(OR($A16="",I16="",NOT(IF(ISNUMBER(I16),AND(I16>=0),FALSE)),NOT(ISNUMBER($B35)),N($B35)=0),"",I16/($B35/60)) | E35: =IF(OR($A16="",J16="",NOT(IF(ISNUMBER(J16),AND(J16>=0),FALSE)),NOT(ISNUMBER($B35)),N($B35)=0),"",J16/($B35/60)) | F35: =IF(OR($A16="",K16="",NOT(IF(ISNUMBER(K16),AND(K16>=0),FALSE)),NOT(ISNUMBER($B35)),N($B35)=0),"",K16/($B35/60)) | G35: =IF(OR($A16="",L16="",NOT(IF(ISNUMBER(L16),AND(L16>=0),FALSE)),NOT(ISNUMBER($B35)),N($B35)=0),"",L16/($B35/60)) | H35: =IF(OR($A16="",M16="",NOT(IF(ISNUMBER(M16),AND(M16>=0),FALSE)),NOT(ISNUMBER($B35)),N($B35)=0),"",M16/($B35/60)) | I35: =IF($A16="","",Config!$B$13) | J35: =IF($A16="","",Config!$B$14)
A36: =IF($A17="","",$A17) | B36: =IF($A17="","",IF(NOT(IF(ISNUMBER(B17),AND(B17>=0),FALSE)),"faltam os minutos",IF(AND(C17<>"Sim",C17<>"Não"),"falta: gera retorno?",IF(AND(C17="Sim",NOT(AND(IF(ISNUMBER(Config!$B$11),AND(Config!$B$11>=0),FALSE),IF(ISNUMBER(Config!$B$12),AND(Config!$B$12>=0),FALSE)))),"falta o retorno em Config",B17+IF(C17="Sim",Config!$B$11*Config!$B$12,0))))) | C36: =IF(OR($A17="",H17="",NOT(IF(ISNUMBER(H17),AND(H17>=0),FALSE)),NOT(ISNUMBER($B36)),N($B36)=0),"",H17/($B36/60)) | D36: =IF(OR($A17="",I17="",NOT(IF(ISNUMBER(I17),AND(I17>=0),FALSE)),NOT(ISNUMBER($B36)),N($B36)=0),"",I17/($B36/60)) | E36: =IF(OR($A17="",J17="",NOT(IF(ISNUMBER(J17),AND(J17>=0),FALSE)),NOT(ISNUMBER($B36)),N($B36)=0),"",J17/($B36/60)) | F36: =IF(OR($A17="",K17="",NOT(IF(ISNUMBER(K17),AND(K17>=0),FALSE)),NOT(ISNUMBER($B36)),N($B36)=0),"",K17/($B36/60)) | G36: =IF(OR($A17="",L17="",NOT(IF(ISNUMBER(L17),AND(L17>=0),FALSE)),NOT(ISNUMBER($B36)),N($B36)=0),"",L17/($B36/60)) | H36: =IF(OR($A17="",M17="",NOT(IF(ISNUMBER(M17),AND(M17>=0),FALSE)),NOT(ISNUMBER($B36)),N($B36)=0),"",M17/($B36/60)) | I36: =IF($A17="","",Config!$B$13) | J36: =IF($A17="","",Config!$B$14)
A37: =IF($A18="","",$A18) | B37: =IF($A18="","",IF(NOT(IF(ISNUMBER(B18),AND(B18>=0),FALSE)),"faltam os minutos",IF(AND(C18<>"Sim",C18<>"Não"),"falta: gera retorno?",IF(AND(C18="Sim",NOT(AND(IF(ISNUMBER(Config!$B$11),AND(Config!$B$11>=0),FALSE),IF(ISNUMBER(Config!$B$12),AND(Config!$B$12>=0),FALSE)))),"falta o retorno em Config",B18+IF(C18="Sim",Config!$B$11*Config!$B$12,0))))) | C37: =IF(OR($A18="",H18="",NOT(IF(ISNUMBER(H18),AND(H18>=0),FALSE)),NOT(ISNUMBER($B37)),N($B37)=0),"",H18/($B37/60)) | D37: =IF(OR($A18="",I18="",NOT(IF(ISNUMBER(I18),AND(I18>=0),FALSE)),NOT(ISNUMBER($B37)),N($B37)=0),"",I18/($B37/60)) | E37: =IF(OR($A18="",J18="",NOT(IF(ISNUMBER(J18),AND(J18>=0),FALSE)),NOT(ISNUMBER($B37)),N($B37)=0),"",J18/($B37/60)) | F37: =IF(OR($A18="",K18="",NOT(IF(ISNUMBER(K18),AND(K18>=0),FALSE)),NOT(ISNUMBER($B37)),N($B37)=0),"",K18/($B37/60)) | G37: =IF(OR($A18="",L18="",NOT(IF(ISNUMBER(L18),AND(L18>=0),FALSE)),NOT(ISNUMBER($B37)),N($B37)=0),"",L18/($B37/60)) | H37: =IF(OR($A18="",M18="",NOT(IF(ISNUMBER(M18),AND(M18>=0),FALSE)),NOT(ISNUMBER($B37)),N($B37)=0),"",M18/($B37/60)) | I37: =IF($A18="","",Config!$B$13) | J37: =IF($A18="","",Config!$B$14)
A38: =IF($A19="","",$A19) | B38: =IF($A19="","",IF(NOT(IF(ISNUMBER(B19),AND(B19>=0),FALSE)),"faltam os minutos",IF(AND(C19<>"Sim",C19<>"Não"),"falta: gera retorno?",IF(AND(C19="Sim",NOT(AND(IF(ISNUMBER(Config!$B$11),AND(Config!$B$11>=0),FALSE),IF(ISNUMBER(Config!$B$12),AND(Config!$B$12>=0),FALSE)))),"falta o retorno em Config",B19+IF(C19="Sim",Config!$B$11*Config!$B$12,0))))) | C38: =IF(OR($A19="",H19="",NOT(IF(ISNUMBER(H19),AND(H19>=0),FALSE)),NOT(ISNUMBER($B38)),N($B38)=0),"",H19/($B38/60)) | D38: =IF(OR($A19="",I19="",NOT(IF(ISNUMBER(I19),AND(I19>=0),FALSE)),NOT(ISNUMBER($B38)),N($B38)=0),"",I19/($B38/60)) | E38: =IF(OR($A19="",J19="",NOT(IF(ISNUMBER(J19),AND(J19>=0),FALSE)),NOT(ISNUMBER($B38)),N($B38)=0),"",J19/($B38/60)) | F38: =IF(OR($A19="",K19="",NOT(IF(ISNUMBER(K19),AND(K19>=0),FALSE)),NOT(ISNUMBER($B38)),N($B38)=0),"",K19/($B38/60)) | G38: =IF(OR($A19="",L19="",NOT(IF(ISNUMBER(L19),AND(L19>=0),FALSE)),NOT(ISNUMBER($B38)),N($B38)=0),"",L19/($B38/60)) | H38: =IF(OR($A19="",M19="",NOT(IF(ISNUMBER(M19),AND(M19>=0),FALSE)),NOT(ISNUMBER($B38)),N($B38)=0),"",M19/($B38/60)) | I38: =IF($A19="","",Config!$B$13) | J38: =IF($A19="","",Config!$B$14)
A39: Vermelho: abaixo da hora mínima. Verde: na hora alvo ou acima. Retorno aparece vazio (valor zero). Este quadro é o argumento na negociação de tabela: quanto cada convênio paga pela hora da clínica.

Sheet Config
A1: Configurações
A2: Células amarelas: você preenche. Custo-hora da planilha 05; margens e impostos iguais aos da 06.
A4: Nome da clínica | B4: Clínica Vida Plena (exemplo fictício)
A5: Mês do volume (mês fechado) | B5: Agosto de 2026
A6: Data de referência | B6: 46279
A7: Custo da hora de atendimento (R$) | B7: 200 | C7: Copie do Painel da planilha 05 ("Custo da hora de atendimento"). No exemplo, R$ 200,00.
A8: Impostos sobre o que entra (%) | B8: 0.11 | C8: A mesma alíquota efetiva das planilhas 05, 06 e 07 (exemplo: 11 %). Só imposto: a taxa da maquininha não entra aqui (fica na 16 e no resultado 18).
A9: Margem mínima sobre o preço (%) | B9: 0.3 | C9: Piso da faixa (a mesma margem da 05 e da 06).
A10: Margem alvo sobre o preço (%) | B10: 0.45 | C10: Teto da faixa (a mesma da 06).
A11: Retornos por consulta (média) | B11: 0.4 | C11: Iguais à 06: o tempo do retorno entra no custo da consulta.
A12: Duração do retorno (minutos) | B12: 20
A13: Hora mínima a cobrar (R$) | B13: =IF(NOT(IF(ISNUMBER(B7),B7>=0,FALSE)),"falta o custo-hora",IF(B15<>"Sim","margens inválidas (Config)",B7/(1-B8-B9))) -> 338.98305 | C13: Custo-hora ÷ (1 − impostos − margem mínima) = R$ 338,98 no exemplo (a 05 arredonda para R$ 340).
A14: Hora alvo (R$) | B14: =IF(NOT(IF(ISNUMBER(B7),B7>=0,FALSE)),"falta o custo-hora",IF(B15<>"Sim","margens inválidas (Config)",B7/(1-B8-B10))) -> 454.54545 | C14: Custo-hora ÷ (1 − impostos − margem alvo).
A15: Impostos e margens conferem? (calculado) | B15: =IF(AND(ISNUMBER(B8),ISNUMBER(B9),ISNUMBER(B10)),IF(AND(B8>=0,B8<1,B9>=0,B9<=B10,B10<1,B8+B10<1),"Sim","Não"),"Não") -> Sim | C15: "Não" suspende preços, situação e contagens: impostos e margens de 0 % a 99 %, mínima ≤ alvo e impostos + margem alvo abaixo de 100 %.
A16: Pagadores (até 6, na ordem das colunas da Tabela; o primeiro é o particular)
A17: Nomes | B17: Particular | C17: Preencha de cima para baixo, sem pular linha. Os mesmos da Config da planilha 01.
B18: Saúde Total
B19: MediPlan
B20: Vida Care
A23: Esta planilha é a FONTE ÚNICA da tabela de preços do kit. A aba Tabela é onde o preço é decidido; 06 (precificação), 07 (simulador) e a Config da planilha 01 (agenda) copiam daqui.
A24: Ordem de atualização quando um preço muda: 1) aqui, na aba Tabela; 2) planilha 06 · Precificação (colunas do particular e dos convênios); 3) planilha 07 · Simulador (quadro 2, valor de tabela); 4) planilha 01 · Config (tabela de preços por pagador, que é o que a Agenda busca). Procedimentos novos: cadastre na 01 (Config), na 02, aqui, na 06 e na 07. Convênio novo: 01, 02, 06, 07, aqui, 09 (categorias de entrada) e 13 (Config).
