Workbook

Sheet Como usar
A1: Conciliação de cartão e taxas
A2: Kit de Gestão para Médicos · Seu Sócio Gestor · versão 1.0 (setembro de 2026)
A4: O que esta planilha faz | B4: Cada pagamento no cartão ou no Pix com a taxa da operadora, o valor líquido e o dia em que cai na conta. Mostra quanto as taxas comem no mês (e a quantas consultas equivalem), o que ainda vai cair, o que já deveria ter caído e não foi conferido, e o dia a dia para bater com o extrato.
A5: Passo 1 | B5: Em Config, digite as taxas e os prazos da sua operadora (contrato da maquininha ou extrato), se antecipa o crédito e o preço da consulta particular (só para a comparação).
A6: Passo 2 | B6: Em Vendas, uma linha por pagamento: data, paciente, procedimento, tipo, parcelas e valor bruto (copie da Agenda da 01, filtrando os particulares pagos com Pix ou cartão). A cada quinzena, escreva em "Parcelas já conferidas" quantas parcelas daquela venda você já achou no extrato: 1 para Pix, débito e crédito à vista; no parcelado vá somando conforme cada parcela cai. Assim a venda volta para "A conferir" quando a parcela seguinte vencer, em vez de ficar conferida para sempre depois da primeira.
A7: Passo 3 | B7: Em Painel, escolha o mês em Config: vendas, taxas, líquido, por tipo, dia a dia e a lista "Falta conferir". No fechamento do mês, lance o total de taxas como saída "Taxas de cartão" no caixa (09).
A8: Rotina | B8: É uma planilha QUINZENAL, fora dos 30 minutos semanais da planilha 03: a cada 15 dias, 10 minutos para conferir o extrato da operadora contra "Cai na conta neste dia" e marcar as conferidas. No fechamento do mês, lance o total de taxas no caixa (09). Uma vez por semestre: comparar a taxa média com outra operadora.
A9: Limite e como estender | B9: A aba Vendas tem 2.000 linhas (5 a 2004): mais de um ano com cerca de 100 pagamentos por mês. Perto do fim, desproteja a aba, copie a última linha para baixo e ajuste o número final nas fórmulas do Painel, ou comece um arquivo por ano.
A10: Ligação com as outras planilhas | B10: O caixa (09) registra o bruto na data em que cai na conta, usando as datas desta planilha; a taxa do mês é a saída do fim do mês em que o dinheiro caiu. Por isso a taxa desta tela (vendas de agosto) e a do caixa (recebimentos de agosto) são números diferentes de propósito. O resultado mensal (18) mostra as taxas como despesa variável. No exemplo o Painel está em agosto (mês fechado); setembro está em andamento.
A11: Com a IA | B11: Copie "Por tipo de pagamento" e use o prompt "Caixa 09 · A taxa da maquininha está comendo a margem?" da biblioteca do kit para decidir entre absorver a taxa, oferecer desconto no Pix ou trocar de operadora.
A12: Legenda | B12: Células amarelas: você preenche. Brancas: calculadas. Não é preciso mexer em nada fora do amarelo.
A13: Proteção | B13: Fórmulas protegidas sem senha. Para editar: Revisar > Desproteger planilha (Excel) ou Dados > Proteger intervalos (Google Sheets).
A14: Requisitos | B14: Excel 2016 ou mais novo, Microsoft 365 ou Google Sheets (só funções do Excel 2007+; nada de MÍNIMOSES, MÁXIMOSES ou UNIRTEXTO). No celular abre nos aplicativos; para preencher, use o computador.
A15: Dados de pacientes | B15: Guarde só o que a gestão precisa (nome, contato, valor, data). Nada de diagnóstico, prontuário ou exame nestas planilhas: o kit é gestão, não é prontuário. Veja o guia LGPD do kit antes de colar qualquer tabela em uma IA.
... A19: Suporte | B19: suporte@seusociogestor.com.br · resposta em até 5 dias úteis · reembolso em até 7 dias pelo mesmo canal.

Sheet Painel
A1: =Config!$B$4&" · Conciliação de cartão e taxas · "&Config!$B$6&" de "&Config!$B$5 -> Clínica Vida Plena (exemplo fictício) · Conciliação de cartão e taxas · Agosto de 2026
A2: Nada para digitar aqui. Escolha o mês em Config; tudo vem de Vendas. Taxas por mês da venda; a receber por previsão na conta.
A4: Vendas no mês (bruto) | C4: Taxas no mês | E4: Taxa média | G4: Líquido no mês | I4: Ainda vai cair (todas as vendas) | K4: A conferir
A5: =SUMIFS(Vendas!$F$5:$F$2004,Vendas!$P$5:$P$2004,Config!$B$7,Vendas!$Q$5:$Q$2004,Config!$B$5) -> 31820 | C5: =SUMIFS(Vendas!$I$5:$I$2004,Vendas!$P$5:$P$2004,Config!$B$7,Vendas!$Q$5:$Q$2004,Config!$B$5) -> 484.12 | E5: =IF(A5=0,"",C5/A5) -> 0.015214331 | G5: =A5-C5 -> 31335.88 | I5: =SUM(Vendas!$O$5:$O$2004) -> 12388.26 | K5: =SUM(Vendas!$T$5:$T$2004) -> 5652.71
A7: ="As taxas do mês equivalem a "&FIXED(IF(Config!$B$9=0,0,C5/Config!$B$9),1)&" consultas particulares. Lance este total no caixa (09) como saída 'Taxas de cartão' no fim do mês." -> As taxas do mês equivalem a 1,3 consultas particulares. Lance este total no caixa (09) como saída 'Taxas de cartão' no fim do mês.
A9: Por tipo de pagamento no mês
A10: Tipo | B10: Vendas | C10: Bruto (R$) | D10: Taxas (R$) | E10: Taxa média | F10: Líquido (R$) | G10: % do bruto | H10: Barra
A11: Pix | B11: =COUNTIFS(Vendas!$D$5:$D$2004,"Pix",Vendas!$P$5:$P$2004,Config!$B$7,Vendas!$Q$5:$Q$2004,Config!$B$5) -> 37 | C11: =SUMIFS(Vendas!$F$5:$F$2004,Vendas!$D$5:$D$2004,"Pix",Vendas!$P$5:$P$2004,Config!$B$7,Vendas!$Q$5:$Q$2004,Config!$B$5) -> 13380 | D11: =SUMIFS(Vendas!$I$5:$I$2004,Vendas!$D$5:$D$2004,"Pix",Vendas!$P$5:$P$2004,Config!$B$7,Vendas!$Q$5:$Q$2004,Config!$B$5) -> 0 | E11: =IF(C11=0,"",D11/C11) -> 0 | F11: =C11-D11 -> 13380 | G11: =IF($A$5=0,"",C11/$A$5) -> 0.42049026 | H11: =IF(G11="","",REPT("█",ROUND(G11*30,0))) -> █████████████
A12: Cartão de débito | B12: =COUNTIFS(Vendas!$D$5:$D$2004,"Cartão de débito",Vendas!$P$5:$P$2004,Config!$B$7,Vendas!$Q$5:$Q$2004,Config!$B$5) -> 22 | C12: =SUMIFS(Vendas!$F$5:$F$2004,Vendas!$D$5:$D$2004,"Cartão de débito",Vendas!$P$5:$P$2004,Config!$B$7,Vendas!$Q$5:$Q$2004,Config!$B$5) -> 8090 | D12: =SUMIFS(Vendas!$I$5:$I$2004,Vendas!$D$5:$D$2004,"Cartão de débito",Vendas!$P$5:$P$2004,Config!$B$7,Vendas!$Q$5:$Q$2004,Config!$B$5) -> 121.35 | E12: =IF(C12=0,"",D12/C12) -> 0.015 | F12: =C12-D12 -> 7968.65 | G12: =IF($A$5=0,"",C12/$A$5) -> 0.25424261 | H12: =IF(G12="","",REPT("█",ROUND(G12*30,0))) -> ████████
A13: Cartão de crédito à vista | B13: =COUNTIFS(Vendas!$D$5:$D$2004,"Cartão de crédito",Vendas!$P$5:$P$2004,Config!$B$7,Vendas!$Q$5:$Q$2004,Config!$B$5)-COUNTIFS(Vendas!$D$5:$D$2004,"Cartão de crédito",Vendas!$E$5:$E$2004,">1",Vendas!$P$5:$P$2004,Config!$B$7,Vendas!$Q$5:$Q$2004,Config!$B$5) -> 16 | C13: =SUMIFS(Vendas!$F$5:$F$2004,Vendas!$D$5:$D$2004,"Cartão de crédito",Vendas!$P$5:$P$2004,Config!$B$7,Vendas!$Q$5:$Q$2004,Config!$B$5)-SUMIFS(Vendas!$F$5:$F$2004,Vendas!$D$5:$D$2004,"Cartão de crédito",Vendas!$E$5:$E$2004,">1",Vendas!$P$5:$P$2004,Config!$B$7,Vendas!$Q$5:$Q$2004,Config!$B$5) -> 5840 | D13: =SUMIFS(Vendas!$I$5:$I$2004,Vendas!$D$5:$D$2004,"Cartão de crédito",Vendas!$P$5:$P$2004,Config!$B$7,Vendas!$Q$5:$Q$2004,Config!$B$5)-SUMIFS(Vendas!$I$5:$I$2004,Vendas!$D$5:$D$2004,"Cartão de crédito",Vendas!$E$5:$E$2004,">1",Vendas!$P$5:$P$2004,Config!$B$7,Vendas!$Q$5:$Q$2004,Config!$B$5) -> 186.88 | E13: =IF(C13=0,"",D13/C13) -> 0.032 | F13: =C13-D13 -> 5653.12 | G13: =IF($A$5=0,"",C13/$A$5) -> 0.18353237 | H13: =IF(G13="","",REPT("█",ROUND(G13*30,0))) -> ██████
A14: Cartão de crédito parcelado | B14: =COUNTIFS(Vendas!$D$5:$D$2004,"Cartão de crédito",Vendas!$E$5:$E$2004,">1",Vendas!$P$5:$P$2004,Config!$B$7,Vendas!$Q$5:$Q$2004,Config!$B$5) -> 12 | C14: =SUMIFS(Vendas!$F$5:$F$2004,Vendas!$D$5:$D$2004,"Cartão de crédito",Vendas!$E$5:$E$2004,">1",Vendas!$P$5:$P$2004,Config!$B$7,Vendas!$Q$5:$Q$2004,Config!$B$5) -> 4510 | D14: =SUMIFS(Vendas!$I$5:$I$2004,Vendas!$D$5:$D$2004,"Cartão de crédito",Vendas!$E$5:$E$2004,">1",Vendas!$P$5:$P$2004,Config!$B$7,Vendas!$Q$5:$Q$2004,Config!$B$5) -> 175.89 | E14: =IF(C14=0,"",D14/C14) -> 0.039 | F14: =C14-D14 -> 4334.11 | G14: =IF($A$5=0,"",C14/$A$5) -> 0.14173476 | H14: =IF(G14="","",REPT("█",ROUND(G14*30,0))) -> ████
A15: Total | B15: =SUM(B11:B14) -> 87 | C15: =SUM(C11:C14) -> 31820 | D15: =SUM(D11:D14) -> 484.12 | F15: =SUM(F11:F14) -> 31335.88
A16: Parcelado custa mais e demora mais. Se o parcelado pesa, vale oferecer desconto no Pix em vez de absorver a taxa; a decisão é da clínica.
A18: Dia a dia do mês: vendas, taxas e previsão de crédito
A19: Dia | B19: Data | C19: Vendas | D19: Bruto (R$) | E19: Taxas (R$) | F19: Líquido (R$) | G19: Cai na conta neste dia (R$) | H19: Conferido?
A20: 1 | B20: =IF(1>DAY(DATE(Config!$B$5,Config!$B$7+1,0)),"",DATE(Config!$B$5,Config!$B$7,1)) -> 46235 | C20: =IF(B20="","",COUNTIFS(Vendas!$A$5:$A$2004,B20)) -> 0 | D20: =IF(B20="","",SUMIFS(Vendas!$F$5:$F$2004,Vendas!$A$5:$A$2004,B20)) -> 0 | E20: =IF(B20="","",SUMIFS(Vendas!$I$5:$I$2004,Vendas!$A$5:$A$2004,B20)) -> 0 | F20: =IF(B20="","",D20-E20) -> 0 | G20: =IF(B20="","",SUMPRODUCT((Vendas!$U$5:$U$2004>0)*(Vendas!$U$5:$U$2004<=B20)*(MOD(B20-Vendas!$U$5:$U$2004,30)=0)*((B20-Vendas!$U$5:$U$2004)/30<Vendas!$V$5:$V$2004)*Vendas!$W$5:$W$2004)) -> 1886.245 | H20: =IF(OR(B20="",G20=0),"",IF(COUNTIFS(Vendas!$L$5:$L$2004,B20,Vendas!$R$5:$R$2004,"A conferir")>0,"Falta conferir",IF(B20>Config!$B$8,"A cair","Conferido"))) -> Conferido
A21: 2 | B21: =IF(2>DAY(DATE(Config!$B$5,Config!$B$7+1,0)),"",DATE(Config!$B$5,Config!$B$7,2)) -> 46236 | C21: =IF(B21="","",COUNTIFS(Vendas!$A$5:$A$2004,B21)) -> 0 | D21: =IF(B21="","",SUMIFS(Vendas!$F$5:$F$2004,Vendas!$A$5:$A$2004,B21)) -> 0 | E21: =IF(B21="","",SUMIFS(Vendas!$I$5:$I$2004,Vendas!$A$5:$A$2004,B21)) -> 0 | F21: =IF(B21="","",D21-E21) -> 0 | G21: =IF(B21="","",SUMPRODUCT((Vendas!$U$5:$U$2004>0)*(Vendas!$U$5:$U$2004<=B21)*(MOD(B21-Vendas!$U$5:$U$2004,30)=0)*((B21-Vendas!$U$5:$U$2004)/30<Vendas!$V$5:$V$2004)*Vendas!$W$5:$W$2004)) -> 0 | H21: =IF(OR(B21="",G21=0),"",IF(COUNTIFS(Vendas!$L$5:$L$2004,B21,Vendas!$R$5:$R$2004,"A conferir")>0,"Falta conferir",IF(B21>Config!$B$8,"A cair","Conferido")))
A22: 3 | B22: =IF(3>DAY(DATE(Config!$B$5,Config!$B$7+1,0)),"",DATE(Config!$B$5,Config!$B$7,3)) -> 46237 | C22: =IF(B22="","",COUNTIFS(Vendas!$A$5:$A$2004,B22)) -> 2 | D22: =IF(B22="","",SUMIFS(Vendas!$F$5:$F$2004,Vendas!$A$5:$A$2004,B22)) -> 680 | E22: =IF(B22="","",SUMIFS(Vendas!$I$5:$I$2004,Vendas!$A$5:$A$2004,B22)) -> 16.66 | F22: =IF(B22="","",D22-E22) -> 663.34 | G22: =IF(B22="","",SUMPRODUCT((Vendas!$U$5:$U$2004>0)*(Vendas!$U$5:$U$2004<=B22)*(MOD(B22-Vendas!$U$5:$U$2004,30)=0)*((B22-Vendas!$U$5:$U$2004)/30<Vendas!$V$5:$V$2004)*Vendas!$W$5:$W$2004)) -> 0 | H22: =IF(OR(B22="",G22=0),"",IF(COUNTIFS(Vendas!$L$5:$L$2004,B22,Vendas!$R$5:$R$2004,"A conferir")>0,"Falta conferir",IF(B22>Config!$B$8,"A cair","Conferido")))
A23: 4 | B23: =IF(4>DAY(DATE(Config!$B$5,Config!$B$7+1,0)),"",DATE(Config!$B$5,Config!$B$7,4)) -> 46238 | C23: =IF(B23="","",COUNTIFS(Vendas!$A$5:$A$2004,B23)) -> 8 | D23: =IF(B23="","",SUMIFS(Vendas!$F$5:$F$2004,Vendas!$A$5:$A$2004,B23)) -> 3060 | E23: =IF(B23="","",SUMIFS(Vendas!$I$5:$I$2004,Vendas!$A$5:$A$2004,B23)) -> 47.42 | F23: =IF(B23="","",D23-E23) -> 3012.58 | G23: =IF(B23="","",SUMPRODUCT((Vendas!$U$5:$U$2004>0)*(Vendas!$U$5:$U$2004<=B23)*(MOD(B23-Vendas!$U$5:$U$2004,30)=0)*((B23-Vendas!$U$5:$U$2004)/30<Vendas!$V$5:$V$2004)*Vendas!$W$5:$W$2004)) -> 1055.5 | H23: =IF(OR(B23="",G23=0),"",IF(COUNTIFS(Vendas!$L$5:$L$2004,B23,Vendas!$R$5:$R$2004,"A conferir")>0,"Falta conferir",IF(B23>Config!$B$8,"A cair","Conferido"))) -> Conferido
A24: 5 | B24: =IF(5>DAY(DATE(Config!$B$5,Config!$B$7+1,0)),"",DATE(Config!$B$5,Config!$B$7,5)) -> 46239 | C24: =IF(B24="","",COUNTIFS(Vendas!$A$5:$A$2004,B24)) -> 3 | D24: =IF(B24="","",SUMIFS(Vendas!$F$5:$F$2004,Vendas!$A$5:$A$2004,B24)) -> 1140 | E24: =IF(B24="","",SUMIFS(Vendas!$I$5:$I$2004,Vendas!$A$5:$A$2004,B24)) -> 20.52 | F24: =IF(B24="","",D24-E24) -> 1119.48 | G24: =IF(B24="","",SUMPRODUCT((Vendas!$U$5:$U$2004>0)*(Vendas!$U$5:$U$2004<=B24)*(MOD(B24-Vendas!$U$5:$U$2004,30)=0)*((B24-Vendas!$U$5:$U$2004)/30<Vendas!$V$5:$V$2004)*Vendas!$W$5:$W$2004)) -> 2447.33 | H24: =IF(OR(B24="",G24=0),"",IF(COUNTIFS(Vendas!$L$5:$L$2004,B24,Vendas!$R$5:$R$2004,"A conferir")>0,"Falta conferir",IF(B24>Config!$B$8,"A cair","Conferido"))) -> Conferido
A25: 6 | B25: =IF(6>DAY(DATE(Config!$B$5,Config!$B$7+1,0)),"",DATE(Config!$B$5,Config!$B$7,6)) -> 46240 | C25: =IF(B25="","",COUNTIFS(Vendas!$A$5:$A$2004,B25)) -> 5 | D25: =IF(B25="","",SUMIFS(Vendas!$F$5:$F$2004,Vendas!$A$5:$A$2004,B25)) -> 2010 | E25: =IF(B25="","",SUMIFS(Vendas!$I$5:$I$2004,Vendas!$A$5:$A$2004,B25)) -> 36.12 | F25: =IF(B25="","",D25-E25) -> 1973.88 | G25: =IF(B25="","",SUMPRODUCT((Vendas!$U$5:$U$2004>0)*(Vendas!$U$5:$U$2004<=B25)*(MOD(B25-Vendas!$U$5:$U$2004,30)=0)*((B25-Vendas!$U$5:$U$2004)/30<Vendas!$V$5:$V$2004)*Vendas!$W$5:$W$2004)) -> 1959.98 | H25: =IF(OR(B25="",G25=0),"",IF(COUNTIFS(Vendas!$L$5:$L$2004,B25,Vendas!$R$5:$R$2004,"A conferir")>0,"Falta conferir",IF(B25>Config!$B$8,"A cair","Conferido"))) -> Conferido
A26: 7 | B26: =IF(7>DAY(DATE(Config!$B$5,Config!$B$7+1,0)),"",DATE(Config!$B$5,Config!$B$7,7)) -> 46241 | C26: =IF(B26="","",COUNTIFS(Vendas!$A$5:$A$2004,B26)) -> 2 | D26: =IF(B26="","",SUMIFS(Vendas!$F$5:$F$2004,Vendas!$A$5:$A$2004,B26)) -> 510 | E26: =IF(B26="","",SUMIFS(Vendas!$I$5:$I$2004,Vendas!$A$5:$A$2004,B26)) -> 12.16 | F26: =IF(B26="","",D26-E26) -> 497.84 | G26: =IF(B26="","",SUMPRODUCT((Vendas!$U$5:$U$2004>0)*(Vendas!$U$5:$U$2004<=B26)*(MOD(B26-Vendas!$U$5:$U$2004,30)=0)*((B26-Vendas!$U$5:$U$2004)/30<Vendas!$V$5:$V$2004)*Vendas!$W$5:$W$2004)) -> 872.14 | H26: =IF(OR(B26="",G26=0),"",IF(COUNTIFS(Vendas!$L$5:$L$2004,B26,Vendas!$R$5:$R$2004,"A conferir")>0,"Falta conferir",IF(B26>Config!$B$8,"A cair","Conferido"))) -> Conferido
A27: 8 | B27: =IF(8>DAY(DATE(Config!$B$5,Config!$B$7+1,0)),"",DATE(Config!$B$5,Config!$B$7,8)) -> 46242 | C27: =IF(B27="","",COUNTIFS(Vendas!$A$5:$A$2004,B27)) -> 0 | D27: =IF(B27="","",SUMIFS(Vendas!$F$5:$F$2004,Vendas!$A$5:$A$2004,B27)) -> 0 | E27: =IF(B27="","",SUMIFS(Vendas!$I$5:$I$2004,Vendas!$A$5:$A$2004,B27)) -> 0 | F27: =IF(B27="","",D27-E27) -> 0 | G27: =IF(B27="","",SUMPRODUCT((Vendas!$U$5:$U$2004>0)*(Vendas!$U$5:$U$2004<=B27)*(MOD(B27-Vendas!$U$5:$U$2004,30)=0)*((B27-Vendas!$U$5:$U$2004)/30<Vendas!$V$5:$V$2004)*Vendas!$W$5:$W$2004)) -> 1623.51 | H27: =IF(OR(B27="",G27=0),"",IF(COUNTIFS(Vendas!$L$5:$L$2004,B27,Vendas!$R$5:$R$2004,"A conferir")>0,"Falta conferir",IF(B27>Config!$B$8,"A cair","Conferido"))) -> Conferido
A28: 9 | B28: =IF(9>DAY(DATE(Config!$B$5,Config!$B$7+1,0)),"",DATE(Config!$B$5,Config!$B$7,9)) -> 46243 | C28: =IF(B28="","",COUNTIFS(Vendas!$A$5:$A$2004,B28)) -> 0 | D28: =IF(B28="","",SUMIFS(Vendas!$F$5:$F$2004,Vendas!$A$5:$A$2004,B28)) -> 0 | E28: =IF(B28="","",SUMIFS(Vendas!$I$5:$I$2004,Vendas!$A$5:$A$2004,B28)) -> 0 | F28: =IF(B28="","",D28-E28) -> 0 | G28: =IF(B28="","",SUMPRODUCT((Vendas!$U$5:$U$2004>0)*(Vendas!$U$5:$U$2004<=B28)*(MOD(B28-Vendas!$U$5:$U$2004,30)=0)*((B28-Vendas!$U$5:$U$2004)/30<Vendas!$V$5:$V$2004)*Vendas!$W$5:$W$2004)) -> 0 | H28: =IF(OR(B28="",G28=0),"",IF(COUNTIFS(Vendas!$L$5:$L$2004,B28,Vendas!$R$5:$R$2004,"A conferir")>0,"Falta conferir",IF(B28>Config!$B$8,"A cair","Conferido")))
A29: 10 | B29: =IF(10>DAY(DATE(Config!$B$5,Config!$B$7+1,0)),"",DATE(Config!$B$5,Config!$B$7,10)) -> 46244 | C29: =IF(B29="","",COUNTIFS(Vendas!$A$5:$A$2004,B29)) -> 3 | D29: =IF(B29="","",SUMIFS(Vendas!$F$5:$F$2004,Vendas!$A$5:$A$2004,B29)) -> 860 | E29: =IF(B29="","",SUMIFS(Vendas!$I$5:$I$2004,Vendas!$A$5:$A$2004,B29)) -> 17.41 | F29: =IF(B29="","",D29-E29) -> 842.59 | G29: =IF(B29="","",SUMPRODUCT((Vendas!$U$5:$U$2004>0)*(Vendas!$U$5:$U$2004<=B29)*(MOD(B29-Vendas!$U$5:$U$2004,30)=0)*((B29-Vendas!$U$5:$U$2004)/30<Vendas!$V$5:$V$2004)*Vendas!$W$5:$W$2004)) -> 130 | H29: =IF(OR(B29="",G29=0),"",IF(COUNTIFS(Vendas!$L$5:$L$2004,B29,Vendas!$R$5:$R$2004,"A conferir")>0,"Falta conferir",IF(B29>Config!$B$8,"A cair","Conferido"))) -> Conferido
A30: 11 | B30: =IF(11>DAY(DATE(Config!$B$5,Config!$B$7+1,0)),"",DATE(Config!$B$5,Config!$B$7,11)) -> 46245 | C30: =IF(B30="","",COUNTIFS(Vendas!$A$5:$A$2004,B30)) -> 7 | D30: =IF(B30="","",SUMIFS(Vendas!$F$5:$F$2004,Vendas!$A$5:$A$2004,B30)) -> 2490 | E30: =IF(B30="","",SUMIFS(Vendas!$I$5:$I$2004,Vendas!$A$5:$A$2004,B30)) -> 45.03 | F30: =IF(B30="","",D30-E30) -> 2444.97 | G30: =IF(B30="","",SUMPRODUCT((Vendas!$U$5:$U$2004>0)*(Vendas!$U$5:$U$2004<=B30)*(MOD(B30-Vendas!$U$5:$U$2004,30)=0)*((B30-Vendas!$U$5:$U$2004)/30<Vendas!$V$5:$V$2004)*Vendas!$W$5:$W$2004)) -> 1540.975 | H30: =IF(OR(B30="",G30=0),"",IF(COUNTIFS(Vendas!$L$5:$L$2004,B30,Vendas!$R$5:$R$2004,"A conferir")>0,"Falta conferir",IF(B30>Config!$B$8,"A cair","Conferido"))) -> Conferido
A31: 12 | B31: =IF(12>DAY(DATE(Config!$B$5,Config!$B$7+1,0)),"",DATE(Config!$B$5,Config!$B$7,12)) -> 46246 | C31: =IF(B31="","",COUNTIFS(Vendas!$A$5:$A$2004,B31)) -> 4 | D31: =IF(B31="","",SUMIFS(Vendas!$F$5:$F$2004,Vendas!$A$5:$A$2004,B31)) -> 1520 | E31: =IF(B31="","",SUMIFS(Vendas!$I$5:$I$2004,Vendas!$A$5:$A$2004,B31)) -> 24.32 | F31: =IF(B31="","",D31-E31) -> 1495.68 | G31: =IF(B31="","",SUMPRODUCT((Vendas!$U$5:$U$2004>0)*(Vendas!$U$5:$U$2004<=B31)*(MOD(B31-Vendas!$U$5:$U$2004,30)=0)*((B31-Vendas!$U$5:$U$2004)/30<Vendas!$V$5:$V$2004)*Vendas!$W$5:$W$2004)) -> 1413.18 | H31: =IF(OR(B31="",G31=0),"",IF(COUNTIFS(Vendas!$L$5:$L$2004,B31,Vendas!$R$5:$R$2004,"A conferir")>0,"Falta conferir",IF(B31>Config!$B$8,"A cair","Conferido"))) -> Falta conferir
A32: 13 | B32: =IF(13>DAY(DATE(Config!$B$5,Config!$B$7+1,0)),"",DATE(Config!$B$5,Config!$B$7,13)) -> 46247 | C32: =IF(B32="","",COUNTIFS(Vendas!$A$5:$A$2004,B32)) -> 8 | D32: =IF(B32="","",SUMIFS(Vendas!$F$5:$F$2004,Vendas!$A$5:$A$2004,B32)) -> 3120 | E32: =IF(B32="","",SUMIFS(Vendas!$I$5:$I$2004,Vendas!$A$5:$A$2004,B32)) -> 24.16 | F32: =IF(B32="","",D32-E32) -> 3095.84 | G32: =IF(B32="","",SUMPRODUCT((Vendas!$U$5:$U$2004>0)*(Vendas!$U$5:$U$2004<=B32)*(MOD(B32-Vendas!$U$5:$U$2004,30)=0)*((B32-Vendas!$U$5:$U$2004)/30<Vendas!$V$5:$V$2004)*Vendas!$W$5:$W$2004)) -> 3551.38 | H32: =IF(OR(B32="",G32=0),"",IF(COUNTIFS(Vendas!$L$5:$L$2004,B32,Vendas!$R$5:$R$2004,"A conferir")>0,"Falta conferir",IF(B32>Config!$B$8,"A cair","Conferido"))) -> Falta conferir
A33: 14 | B33: =IF(14>DAY(DATE(Config!$B$5,Config!$B$7+1,0)),"",DATE(Config!$B$5,Config!$B$7,14)) -> 46248 | C33: =IF(B33="","",COUNTIFS(Vendas!$A$5:$A$2004,B33)) -> 0 | D33: =IF(B33="","",SUMIFS(Vendas!$F$5:$F$2004,Vendas!$A$5:$A$2004,B33)) -> 0 | E33: =IF(B33="","",SUMIFS(Vendas!$I$5:$I$2004,Vendas!$A$5:$A$2004,B33)) -> 0 | F33: =IF(B33="","",D33-E33) -> 0 | G33: =IF(B33="","",SUMPRODUCT((Vendas!$U$5:$U$2004>0)*(Vendas!$U$5:$U$2004<=B33)*(MOD(B33-Vendas!$U$5:$U$2004,30)=0)*((B33-Vendas!$U$5:$U$2004)/30<Vendas!$V$5:$V$2004)*Vendas!$W$5:$W$2004)) -> 1155.84 | H33: =IF(OR(B33="",G33=0),"",IF(COUNTIFS(Vendas!$L$5:$L$2004,B33,Vendas!$R$5:$R$2004,"A conferir")>0,"Falta conferir",IF(B33>Config!$B$8,"A cair","Conferido"))) -> Conferido
A34: 15 | B34: =IF(15>DAY(DATE(Config!$B$5,Config!$B$7+1,0)),"",DATE(Config!$B$5,Config!$B$7,15)) -> 46249 | C34: =IF(B34="","",COUNTIFS(Vendas!$A$5:$A$2004,B34)) -> 0 | D34: =IF(B34="","",SUMIFS(Vendas!$F$5:$F$2004,Vendas!$A$5:$A$2004,B34)) -> 0 | E34: =IF(B34="","",SUMIFS(Vendas!$I$5:$I$2004,Vendas!$A$5:$A$2004,B34)) -> 0 | F34: =IF(B34="","",D34-E34) -> 0 | G34: =IF(B34="","",SUMPRODUCT((Vendas!$U$5:$U$2004>0)*(Vendas!$U$5:$U$2004<=B34)*(MOD(B34-Vendas!$U$5:$U$2004,30)=0)*((B34-Vendas!$U$5:$U$2004)/30<Vendas!$V$5:$V$2004)*Vendas!$W$5:$W$2004)) -> 1122.88 | H34: =IF(OR(B34="",G34=0),"",IF(COUNTIFS(Vendas!$L$5:$L$2004,B34,Vendas!$R$5:$R$2004,"A conferir")>0,"Falta conferir",IF(B34>Config!$B$8,"A cair","Conferido"))) -> Conferido
A35: 16 | B35: =IF(16>DAY(DATE(Config!$B$5,Config!$B$7+1,0)),"",DATE(Config!$B$5,Config!$B$7,16)) -> 46250 | C35: =IF(B35="","",COUNTIFS(Vendas!$A$5:$A$2004,B35)) -> 0 | D35: =IF(B35="","",SUMIFS(Vendas!$F$5:$F$2004,Vendas!$A$5:$A$2004,B35)) -> 0 | E35: =IF(B35="","",SUMIFS(Vendas!$I$5:$I$2004,Vendas!$A$5:$A$2004,B35)) -> 0 | F35: =IF(B35="","",D35-E35) -> 0 | G35: =IF(B35="","",SUMPRODUCT((Vendas!$U$5:$U$2004>0)*(Vendas!$U$5:$U$2004<=B35)*(MOD(B35-Vendas!$U$5:$U$2004,30)=0)*((B35-Vendas!$U$5:$U$2004)/30<Vendas!$V$5:$V$2004)*Vendas!$W$5:$W$2004)) -> 367.84 | H35: =IF(OR(B35="",G35=0),"",IF(COUNTIFS(Vendas!$L$5:$L$2004,B35,Vendas!$R$5:$R$2004,"A conferir")>0,"Falta conferir",IF(B35>Config!$B$8,"A cair","Conferido"))) -> Conferido
A36: 17 | B36: =IF(17>DAY(DATE(Config!$B$5,Config!$B$7+1,0)),"",DATE(Config!$B$5,Config!$B$7,17)) -> 46251 | C36: =IF(B36="","",COUNTIFS(Vendas!$A$5:$A$2004,B36)) -> 3 | D36: =IF(B36="","",SUMIFS(Vendas!$F$5:$F$2004,Vendas!$A$5:$A$2004,B36)) -> 1060 | E36: =IF(B36="","",SUMIFS(Vendas!$I$5:$I$2004,Vendas!$A$5:$A$2004,B36)) -> 17.4 | F36: =IF(B36="","",D36-E36) -> 1042.6 | G36: =IF(B36="","",SUMPRODUCT((Vendas!$U$5:$U$2004>0)*(Vendas!$U$5:$U$2004<=B36)*(MOD(B36-Vendas!$U$5:$U$2004,30)=0)*((B36-Vendas!$U$5:$U$2004)/30<Vendas!$V$5:$V$2004)*Vendas!$W$5:$W$2004)) -> 380 | H36: =IF(OR(B36="",G36=0),"",IF(COUNTIFS(Vendas!$L$5:$L$2004,B36,Vendas!$R$5:$R$2004,"A conferir")>0,"Falta conferir",IF(B36>Config!$B$8,"A cair","Conferido"))) -> Conferido
A37: 18 | B37: =IF(18>DAY(DATE(Config!$B$5,Config!$B$7+1,0)),"",DATE(Config!$B$5,Config!$B$7,18)) -> 46252 | C37: =IF(B37="","",COUNTIFS(Vendas!$A$5:$A$2004,B37)) -> 4 | D37: =IF(B37="","",SUMIFS(Vendas!$F$5:$F$2004,Vendas!$A$5:$A$2004,B37)) -> 1540 | E37: =IF(B37="","",SUMIFS(Vendas!$I$5:$I$2004,Vendas!$A$5:$A$2004,B37)) -> 20.52 | F37: =IF(B37="","",D37-E37) -> 1519.48 | G37: =IF(B37="","",SUMPRODUCT((Vendas!$U$5:$U$2004>0)*(Vendas!$U$5:$U$2004<=B37)*(MOD(B37-Vendas!$U$5:$U$2004,30)=0)*((B37-Vendas!$U$5:$U$2004)/30<Vendas!$V$5:$V$2004)*Vendas!$W$5:$W$2004)) -> 1154.3 | H37: =IF(OR(B37="",G37=0),"",IF(COUNTIFS(Vendas!$L$5:$L$2004,B37,Vendas!$R$5:$R$2004,"A conferir")>0,"Falta conferir",IF(B37>Config!$B$8,"A cair","Conferido"))) -> Conferido
A38: 19 | B38: =IF(19>DAY(DATE(Config!$B$5,Config!$B$7+1,0)),"",DATE(Config!$B$5,Config!$B$7,19)) -> 46253 | C38: =IF(B38="","",COUNTIFS(Vendas!$A$5:$A$2004,B38)) -> 2 | D38: =IF(B38="","",SUMIFS(Vendas!$F$5:$F$2004,Vendas!$A$5:$A$2004,B38)) -> 760 | E38: =IF(B38="","",SUMIFS(Vendas!$I$5:$I$2004,Vendas!$A$5:$A$2004,B38)) -> 5.7 | F38: =IF(B38="","",D38-E38) -> 754.3 | G38: =IF(B38="","",SUMPRODUCT((Vendas!$U$5:$U$2004>0)*(Vendas!$U$5:$U$2004<=B38)*(MOD(B38-Vendas!$U$5:$U$2004,30)=0)*((B38-Vendas!$U$5:$U$2004)/30<Vendas!$V$5:$V$2004)*Vendas!$W$5:$W$2004)) -> 1489.98 | H38: =IF(OR(B38="",G38=0),"",IF(COUNTIFS(Vendas!$L$5:$L$2004,B38,Vendas!$R$5:$R$2004,"A conferir")>0,"Falta conferir",IF(B38>Config!$B$8,"A cair","Conferido"))) -> Conferido
A39: 20 | B39: =IF(20>DAY(DATE(Config!$B$5,Config!$B$7+1,0)),"",DATE(Config!$B$5,Config!$B$7,20)) -> 46254 | C39: =IF(B39="","",COUNTIFS(Vendas!$A$5:$A$2004,B39)) -> 9 | D39: =IF(B39="","",SUMIFS(Vendas!$F$5:$F$2004,Vendas!$A$5:$A$2004,B39)) -> 3370 | E39: =IF(B39="","",SUMIFS(Vendas!$I$5:$I$2004,Vendas!$A$5:$A$2004,B39)) -> 34.4 | F39: =IF(B39="","",D39-E39) -> 3335.6 | G39: =IF(B39="","",SUMPRODUCT((Vendas!$U$5:$U$2004>0)*(Vendas!$U$5:$U$2004<=B39)*(MOD(B39-Vendas!$U$5:$U$2004,30)=0)*((B39-Vendas!$U$5:$U$2004)/30<Vendas!$V$5:$V$2004)*Vendas!$W$5:$W$2004)) -> 3481.93 | H39: =IF(OR(B39="",G39=0),"",IF(COUNTIFS(Vendas!$L$5:$L$2004,B39,Vendas!$R$5:$R$2004,"A conferir")>0,"Falta conferir",IF(B39>Config!$B$8,"A cair","Conferido"))) -> Conferido
A40: 21 | B40: =IF(21>DAY(DATE(Config!$B$5,Config!$B$7+1,0)),"",DATE(Config!$B$5,Config!$B$7,21)) -> 46255 | C40: =IF(B40="","",COUNTIFS(Vendas!$A$5:$A$2004,B40)) -> 0 | D40: =IF(B40="","",SUMIFS(Vendas!$F$5:$F$2004,Vendas!$A$5:$A$2004,B40)) -> 0 | E40: =IF(B40="","",SUMIFS(Vendas!$I$5:$I$2004,Vendas!$A$5:$A$2004,B40)) -> 0 | F40: =IF(B40="","",D40-E40) -> 0 | G40: =IF(B40="","",SUMPRODUCT((Vendas!$U$5:$U$2004>0)*(Vendas!$U$5:$U$2004<=B40)*(MOD(B40-Vendas!$U$5:$U$2004,30)=0)*((B40-Vendas!$U$5:$U$2004)/30<Vendas!$V$5:$V$2004)*Vendas!$W$5:$W$2004)) -> 1129.68 | H40: =IF(OR(B40="",G40=0),"",IF(COUNTIFS(Vendas!$L$5:$L$2004,B40,Vendas!$R$5:$R$2004,"A conferir")>0,"Falta conferir",IF(B40>Config!$B$8,"A cair","Conferido"))) -> Conferido
A41: 22 | B41: =IF(22>DAY(DATE(Config!$B$5,Config!$B$7+1,0)),"",DATE(Config!$B$5,Config!$B$7,22)) -> 46256 | C41: =IF(B41="","",COUNTIFS(Vendas!$A$5:$A$2004,B41)) -> 0 | D41: =IF(B41="","",SUMIFS(Vendas!$F$5:$F$2004,Vendas!$A$5:$A$2004,B41)) -> 0 | E41: =IF(B41="","",SUMIFS(Vendas!$I$5:$I$2004,Vendas!$A$5:$A$2004,B41)) -> 0 | F41: =IF(B41="","",D41-E41) -> 0 | G41: =IF(B41="","",SUMPRODUCT((Vendas!$U$5:$U$2004>0)*(Vendas!$U$5:$U$2004<=B41)*(MOD(B41-Vendas!$U$5:$U$2004,30)=0)*((B41-Vendas!$U$5:$U$2004)/30<Vendas!$V$5:$V$2004)*Vendas!$W$5:$W$2004)) -> 1485.26 | H41: =IF(OR(B41="",G41=0),"",IF(COUNTIFS(Vendas!$L$5:$L$2004,B41,Vendas!$R$5:$R$2004,"A conferir")>0,"Falta conferir",IF(B41>Config!$B$8,"A cair","Conferido"))) -> Conferido
A42: 23 | B42: =IF(23>DAY(DATE(Config!$B$5,Config!$B$7+1,0)),"",DATE(Config!$B$5,Config!$B$7,23)) -> 46257 | C42: =IF(B42="","",COUNTIFS(Vendas!$A$5:$A$2004,B42)) -> 0 | D42: =IF(B42="","",SUMIFS(Vendas!$F$5:$F$2004,Vendas!$A$5:$A$2004,B42)) -> 0 | E42: =IF(B42="","",SUMIFS(Vendas!$I$5:$I$2004,Vendas!$A$5:$A$2004,B42)) -> 0 | F42: =IF(B42="","",D42-E42) -> 0 | G42: =IF(B42="","",SUMPRODUCT((Vendas!$U$5:$U$2004>0)*(Vendas!$U$5:$U$2004<=B42)*(MOD(B42-Vendas!$U$5:$U$2004,30)=0)*((B42-Vendas!$U$5:$U$2004)/30<Vendas!$V$5:$V$2004)*Vendas!$W$5:$W$2004)) -> 0 | H42: =IF(OR(B42="",G42=0),"",IF(COUNTIFS(Vendas!$L$5:$L$2004,B42,Vendas!$R$5:$R$2004,"A conferir")>0,"Falta conferir",IF(B42>Config!$B$8,"A cair","Conferido")))
A43: 24 | B43: =IF(24>DAY(DATE(Config!$B$5,Config!$B$7+1,0)),"",DATE(Config!$B$5,Config!$B$7,24)) -> 46258 | C43: =IF(B43="","",COUNTIFS(Vendas!$A$5:$A$2004,B43)) -> 7 | D43: =IF(B43="","",SUMIFS(Vendas!$F$5:$F$2004,Vendas!$A$5:$A$2004,B43)) -> 2410 | E43: =IF(B43="","",SUMIFS(Vendas!$I$5:$I$2004,Vendas!$A$5:$A$2004,B43)) -> 36.84 | F43: =IF(B43="","",D43-E43) -> 2373.16 | G43: =IF(B43="","",SUMPRODUCT((Vendas!$U$5:$U$2004>0)*(Vendas!$U$5:$U$2004<=B43)*(MOD(B43-Vendas!$U$5:$U$2004,30)=0)*((B43-Vendas!$U$5:$U$2004)/30<Vendas!$V$5:$V$2004)*Vendas!$W$5:$W$2004)) -> 1140 | H43: =IF(OR(B43="",G43=0),"",IF(COUNTIFS(Vendas!$L$5:$L$2004,B43,Vendas!$R$5:$R$2004,"A conferir")>0,"Falta conferir",IF(B43>Config!$B$8,"A cair","Conferido"))) -> Conferido
A44: 25 | B44: =IF(25>DAY(DATE(Config!$B$5,Config!$B$7+1,0)),"",DATE(Config!$B$5,Config!$B$7,25)) -> 46259 | C44: =IF(B44="","",COUNTIFS(Vendas!$A$5:$A$2004,B44)) -> 8 | D44: =IF(B44="","",SUMIFS(Vendas!$F$5:$F$2004,Vendas!$A$5:$A$2004,B44)) -> 3020 | E44: =IF(B44="","",SUMIFS(Vendas!$I$5:$I$2004,Vendas!$A$5:$A$2004,B44)) -> 76.09 | F44: =IF(B44="","",D44-E44) -> 2943.91 | G44: =IF(B44="","",SUMPRODUCT((Vendas!$U$5:$U$2004>0)*(Vendas!$U$5:$U$2004<=B44)*(MOD(B44-Vendas!$U$5:$U$2004,30)=0)*((B44-Vendas!$U$5:$U$2004)/30<Vendas!$V$5:$V$2004)*Vendas!$W$5:$W$2004)) -> 1134.3 | H44: =IF(OR(B44="",G44=0),"",IF(COUNTIFS(Vendas!$L$5:$L$2004,B44,Vendas!$R$5:$R$2004,"A conferir")>0,"Falta conferir",IF(B44>Config!$B$8,"A cair","Conferido"))) -> Conferido
A45: 26 | B45: =IF(26>DAY(DATE(Config!$B$5,Config!$B$7+1,0)),"",DATE(Config!$B$5,Config!$B$7,26)) -> 46260 | C45: =IF(B45="","",COUNTIFS(Vendas!$A$5:$A$2004,B45)) -> 3 | D45: =IF(B45="","",SUMIFS(Vendas!$F$5:$F$2004,Vendas!$A$5:$A$2004,B45)) -> 1140 | E45: =IF(B45="","",SUMIFS(Vendas!$I$5:$I$2004,Vendas!$A$5:$A$2004,B45)) -> 5.7 | F45: =IF(B45="","",D45-E45) -> 1134.3 | G45: =IF(B45="","",SUMPRODUCT((Vendas!$U$5:$U$2004>0)*(Vendas!$U$5:$U$2004<=B45)*(MOD(B45-Vendas!$U$5:$U$2004,30)=0)*((B45-Vendas!$U$5:$U$2004)/30<Vendas!$V$5:$V$2004)*Vendas!$W$5:$W$2004)) -> 1521.84 | H45: =IF(OR(B45="",G45=0),"",IF(COUNTIFS(Vendas!$L$5:$L$2004,B45,Vendas!$R$5:$R$2004,"A conferir")>0,"Falta conferir",IF(B45>Config!$B$8,"A cair","Conferido"))) -> Conferido
A46: 27 | B46: =IF(27>DAY(DATE(Config!$B$5,Config!$B$7+1,0)),"",DATE(Config!$B$5,Config!$B$7,27)) -> 46261 | C46: =IF(B46="","",COUNTIFS(Vendas!$A$5:$A$2004,B46)) -> 6 | D46: =IF(B46="","",SUMIFS(Vendas!$F$5:$F$2004,Vendas!$A$5:$A$2004,B46)) -> 2240 | E46: =IF(B46="","",SUMIFS(Vendas!$I$5:$I$2004,Vendas!$A$5:$A$2004,B46)) -> 36.02 | F46: =IF(B46="","",D46-E46) -> 2203.98 | G46: =IF(B46="","",SUMPRODUCT((Vendas!$U$5:$U$2004>0)*(Vendas!$U$5:$U$2004<=B46)*(MOD(B46-Vendas!$U$5:$U$2004,30)=0)*((B46-Vendas!$U$5:$U$2004)/30<Vendas!$V$5:$V$2004)*Vendas!$W$5:$W$2004)) -> 2069.94 | H46: =IF(OR(B46="",G46=0),"",IF(COUNTIFS(Vendas!$L$5:$L$2004,B46,Vendas!$R$5:$R$2004,"A conferir")>0,"Falta conferir",IF(B46>Config!$B$8,"A cair","Conferido"))) -> Conferido
A47: 28 | B47: =IF(28>DAY(DATE(Config!$B$5,Config!$B$7+1,0)),"",DATE(Config!$B$5,Config!$B$7,28)) -> 46262 | C47: =IF(B47="","",COUNTIFS(Vendas!$A$5:$A$2004,B47)) -> 0 | D47: =IF(B47="","",SUMIFS(Vendas!$F$5:$F$2004,Vendas!$A$5:$A$2004,B47)) -> 0 | E47: =IF(B47="","",SUMIFS(Vendas!$I$5:$I$2004,Vendas!$A$5:$A$2004,B47)) -> 0 | F47: =IF(B47="","",D47-E47) -> 0 | G47: =IF(B47="","",SUMPRODUCT((Vendas!$U$5:$U$2004>0)*(Vendas!$U$5:$U$2004<=B47)*(MOD(B47-Vendas!$U$5:$U$2004,30)=0)*((B47-Vendas!$U$5:$U$2004)/30<Vendas!$V$5:$V$2004)*Vendas!$W$5:$W$2004)) -> 950.89 | H47: =IF(OR(B47="",G47=0),"",IF(COUNTIFS(Vendas!$L$5:$L$2004,B47,Vendas!$R$5:$R$2004,"A conferir")>0,"Falta conferir",IF(B47>Config!$B$8,"A cair","Conferido"))) -> Conferido
A48: 29 | B48: =IF(29>DAY(DATE(Config!$B$5,Config!$B$7+1,0)),"",DATE(Config!$B$5,Config!$B$7,29)) -> 46263 | C48: =IF(B48="","",COUNTIFS(Vendas!$A$5:$A$2004,B48)) -> 0 | D48: =IF(B48="","",SUMIFS(Vendas!$F$5:$F$2004,Vendas!$A$5:$A$2004,B48)) -> 0 | E48: =IF(B48="","",SUMIFS(Vendas!$I$5:$I$2004,Vendas!$A$5:$A$2004,B48)) -> 0 | F48: =IF(B48="","",D48-E48) -> 0 | G48: =IF(B48="","",SUMPRODUCT((Vendas!$U$5:$U$2004>0)*(Vendas!$U$5:$U$2004<=B48)*(MOD(B48-Vendas!$U$5:$U$2004,30)=0)*((B48-Vendas!$U$5:$U$2004)/30<Vendas!$V$5:$V$2004)*Vendas!$W$5:$W$2004)) -> 761.99 | H48: =IF(OR(B48="",G48=0),"",IF(COUNTIFS(Vendas!$L$5:$L$2004,B48,Vendas!$R$5:$R$2004,"A conferir")>0,"Falta conferir",IF(B48>Config!$B$8,"A cair","Conferido"))) -> Conferido
A49: 30 | B49: =IF(30>DAY(DATE(Config!$B$5,Config!$B$7+1,0)),"",DATE(Config!$B$5,Config!$B$7,30)) -> 46264 | C49: =IF(B49="","",COUNTIFS(Vendas!$A$5:$A$2004,B49)) -> 0 | D49: =IF(B49="","",SUMIFS(Vendas!$F$5:$F$2004,Vendas!$A$5:$A$2004,B49)) -> 0 | E49: =IF(B49="","",SUMIFS(Vendas!$I$5:$I$2004,Vendas!$A$5:$A$2004,B49)) -> 0 | F49: =IF(B49="","",D49-E49) -> 0 | G49: =IF(B49="","",SUMPRODUCT((Vendas!$U$5:$U$2004>0)*(Vendas!$U$5:$U$2004<=B49)*(MOD(B49-Vendas!$U$5:$U$2004,30)=0)*((B49-Vendas!$U$5:$U$2004)/30<Vendas!$V$5:$V$2004)*Vendas!$W$5:$W$2004)) -> 929.28 | H49: =IF(OR(B49="",G49=0),"",IF(COUNTIFS(Vendas!$L$5:$L$2004,B49,Vendas!$R$5:$R$2004,"A conferir")>0,"Falta conferir",IF(B49>Config!$B$8,"A cair","Conferido"))) -> Conferido
A50: 31 | B50: =IF(31>DAY(DATE(Config!$B$5,Config!$B$7+1,0)),"",DATE(Config!$B$5,Config!$B$7,31)) -> 46265 | C50: =IF(B50="","",COUNTIFS(Vendas!$A$5:$A$2004,B50)) -> 3 | D50: =IF(B50="","",SUMIFS(Vendas!$F$5:$F$2004,Vendas!$A$5:$A$2004,B50)) -> 890 | E50: =IF(B50="","",SUMIFS(Vendas!$I$5:$I$2004,Vendas!$A$5:$A$2004,B50)) -> 7.65 | F50: =IF(B50="","",D50-E50) -> 882.35 | G50: =IF(B50="","",SUMPRODUCT((Vendas!$U$5:$U$2004>0)*(Vendas!$U$5:$U$2004<=B50)*(MOD(B50-Vendas!$U$5:$U$2004,30)=0)*((B50-Vendas!$U$5:$U$2004)/30<Vendas!$V$5:$V$2004)*Vendas!$W$5:$W$2004)) -> 572.2 | H50: =IF(OR(B50="",G50=0),"",IF(COUNTIFS(Vendas!$L$5:$L$2004,B50,Vendas!$R$5:$R$2004,"A conferir")>0,"Falta conferir",IF(B50>Config!$B$8,"A cair","Conferido"))) -> Conferido
A51: "Cai na conta neste dia" soma as parcelas que caem nesse dia (inclusive as de vendas de meses anteriores e as parcelas 2, 3… de vendas parceladas): é o número para bater com o extrato da conta. Uma venda em 2× aparece metade num dia e metade 30 dias depois.
A54: Falta conferir no extrato (previsão vencida)
A55: # | B55: Data da venda | C55: Paciente | D55: Procedimento | E55: Tipo | F55: Parcelas | G55: Bruto (R$) | H55: Líquido já previsto (R$) | I55: 1ª parcela caía em | J55: Dias desde a previsão
A56: 1 | B56: =IFERROR(IF(LARGE(Vendas!$S$5:$S$2004,1)>0,INDEX(Vendas!$A$5:$A$2004,MATCH(LARGE(Vendas!$S$5:$S$2004,1),Vendas!$S$5:$S$2004,0)),""),"") -> 46216 | C56: =IFERROR(IF(LARGE(Vendas!$S$5:$S$2004,1)>0,INDEX(Vendas!$B$5:$B$2004,MATCH(LARGE(Vendas!$S$5:$S$2004,1),Vendas!$S$5:$S$2004,0)),""),"") -> Henrique Ribeiro | D56: =IFERROR(IF(LARGE(Vendas!$S$5:$S$2004,1)>0,INDEX(Vendas!$C$5:$C$2004,MATCH(LARGE(Vendas!$S$5:$S$2004,1),Vendas!$S$5:$S$2004,0)),""),"") -> Consulta | E56: =IFERROR(IF(LARGE(Vendas!$S$5:$S$2004,1)>0,INDEX(Vendas!$D$5:$D$2004,MATCH(LARGE(Vendas!$S$5:$S$2004,1),Vendas!$S$5:$S$2004,0)),""),"") -> Cartão de crédito | F56: =IFERROR(IF(LARGE(Vendas!$S$5:$S$2004,1)>0,INDEX(Vendas!$E$5:$E$2004,MATCH(LARGE(Vendas!$S$5:$S$2004,1),Vendas!$S$5:$S$2004,0)),""),"") -> 2 | G56: =IFERROR(IF(LARGE(Vendas!$S$5:$S$2004,1)>0,INDEX(Vendas!$F$5:$F$2004,MATCH(LARGE(Vendas!$S$5:$S$2004,1),Vendas!$S$5:$S$2004,0)),""),"") -> 380 | H56: =IFERROR(IF(LARGE(Vendas!$S$5:$S$2004,1)>0,INDEX(Vendas!$N$5:$N$2004,MATCH(LARGE(Vendas!$S$5:$S$2004,1),Vendas!$S$5:$S$2004,0)),""),"") -> 365.18 | I56: =IFERROR(IF(LARGE(Vendas!$S$5:$S$2004,1)>0,INDEX(Vendas!$L$5:$L$2004,MATCH(LARGE(Vendas!$S$5:$S$2004,1),Vendas!$S$5:$S$2004,0)),""),"") -> 46246 | J56: =IF(I56="","",Config!$B$8-I56) -> 33
A57: 2 | B57: =IFERROR(IF(LARGE(Vendas!$S$5:$S$2004,2)>0,INDEX(Vendas!$A$5:$A$2004,MATCH(LARGE(Vendas!$S$5:$S$2004,2),Vendas!$S$5:$S$2004,0)),""),"") -> 46217 | C57: =IFERROR(IF(LARGE(Vendas!$S$5:$S$2004,2)>0,INDEX(Vendas!$B$5:$B$2004,MATCH(LARGE(Vendas!$S$5:$S$2004,2),Vendas!$S$5:$S$2004,0)),""),"") -> Mariana Reis | D57: =IFERROR(IF(LARGE(Vendas!$S$5:$S$2004,2)>0,INDEX(Vendas!$C$5:$C$2004,MATCH(LARGE(Vendas!$S$5:$S$2004,2),Vendas!$S$5:$S$2004,0)),""),"") -> Avaliação endócrina | E57: =IFERROR(IF(LARGE(Vendas!$S$5:$S$2004,2)>0,INDEX(Vendas!$D$5:$D$2004,MATCH(LARGE(Vendas!$S$5:$S$2004,2),Vendas!$S$5:$S$2004,0)),""),"") -> Cartão de crédito | F57: =IFERROR(IF(LARGE(Vendas!$S$5:$S$2004,2)>0,INDEX(Vendas!$E$5:$E$2004,MATCH(LARGE(Vendas!$S$5:$S$2004,2),Vendas!$S$5:$S$2004,0)),""),"") -> 2 | G57: =IFERROR(IF(LARGE(Vendas!$S$5:$S$2004,2)>0,INDEX(Vendas!$F$5:$F$2004,MATCH(LARGE(Vendas!$S$5:$S$2004,2),Vendas!$S$5:$S$2004,0)),""),"") -> 400 | H57: =IFERROR(IF(LARGE(Vendas!$S$5:$S$2004,2)>0,INDEX(Vendas!$N$5:$N$2004,MATCH(LARGE(Vendas!$S$5:$S$2004,2),Vendas!$S$5:$S$2004,0)),""),"") -> 384.4 | I57: =IFERROR(IF(LARGE(Vendas!$S$5:$S$2004,2)>0,INDEX(Vendas!$L$5:$L$2004,MATCH(LARGE(Vendas!$S$5:$S$2004,2),Vendas!$S$5:$S$2004,0)),""),"") -> 46247 | J57: =IF(I57="","",Config!$B$8-I57) -> 32
A58: 3 | B58: =IFERROR(IF(LARGE(Vendas!$S$5:$S$2004,3)>0,INDEX(Vendas!$A$5:$A$2004,MATCH(LARGE(Vendas!$S$5:$S$2004,3),Vendas!$S$5:$S$2004,0)),""),"") -> 46217 | C58: =IFERROR(IF(LARGE(Vendas!$S$5:$S$2004,3)>0,INDEX(Vendas!$B$5:$B$2004,MATCH(LARGE(Vendas!$S$5:$S$2004,3),Vendas!$S$5:$S$2004,0)),""),"") -> Thiago Melo | D58: =IFERROR(IF(LARGE(Vendas!$S$5:$S$2004,3)>0,INDEX(Vendas!$C$5:$C$2004,MATCH(LARGE(Vendas!$S$5:$S$2004,3),Vendas!$S$5:$S$2004,0)),""),"") -> Avaliação endócrina | E58: =IFERROR(IF(LARGE(Vendas!$S$5:$S$2004,3)>0,INDEX(Vendas!$D$5:$D$2004,MATCH(LARGE(Vendas!$S$5:$S$2004,3),Vendas!$S$5:$S$2004,0)),""),"") -> Cartão de crédito | F58: =IFERROR(IF(LARGE(Vendas!$S$5:$S$2004,3)>0,INDEX(Vendas!$E$5:$E$2004,MATCH(LARGE(Vendas!$S$5:$S$2004,3),Vendas!$S$5:$S$2004,0)),""),"") -> 2 | G58: =IFERROR(IF(LARGE(Vendas!$S$5:$S$2004,3)>0,INDEX(Vendas!$F$5:$F$2004,MATCH(LARGE(Vendas!$S$5:$S$2004,3),Vendas!$S$5:$S$2004,0)),""),"") -> 400 | H58: =IFERROR(IF(LARGE(Vendas!$S$5:$S$2004,3)>0,INDEX(Vendas!$N$5:$N$2004,MATCH(LARGE(Vendas!$S$5:$S$2004,3),Vendas!$S$5:$S$2004,0)),""),"") -> 384.4 | I58: =IFERROR(IF(LARGE(Vendas!$S$5:$S$2004,3)>0,INDEX(Vendas!$L$5:$L$2004,MATCH(LARGE(Vendas!$S$5:$S$2004,3),Vendas!$S$5:$S$2004,0)),""),"") -> 46247 | J58: =IF(I58="","",Config!$B$8-I58) -> 32
A59: 4 | B59: =IFERROR(IF(LARGE(Vendas!$S$5:$S$2004,4)>0,INDEX(Vendas!$A$5:$A$2004,MATCH(LARGE(Vendas!$S$5:$S$2004,4),Vendas!$S$5:$S$2004,0)),""),"") -> 46217 | C59: =IFERROR(IF(LARGE(Vendas!$S$5:$S$2004,4)>0,INDEX(Vendas!$B$5:$B$2004,MATCH(LARGE(Vendas!$S$5:$S$2004,4),Vendas!$S$5:$S$2004,0)),""),"") -> Marcelo Ferreira | D59: =IFERROR(IF(LARGE(Vendas!$S$5:$S$2004,4)>0,INDEX(Vendas!$C$5:$C$2004,MATCH(LARGE(Vendas!$S$5:$S$2004,4),Vendas!$S$5:$S$2004,0)),""),"") -> Consulta | E59: =IFERROR(IF(LARGE(Vendas!$S$5:$S$2004,4)>0,INDEX(Vendas!$D$5:$D$2004,MATCH(LARGE(Vendas!$S$5:$S$2004,4),Vendas!$S$5:$S$2004,0)),""),"") -> Cartão de crédito | F59: =IFERROR(IF(LARGE(Vendas!$S$5:$S$2004,4)>0,INDEX(Vendas!$E$5:$E$2004,MATCH(LARGE(Vendas!$S$5:$S$2004,4),Vendas!$S$5:$S$2004,0)),""),"") -> 2 | G59: =IFERROR(IF(LARGE(Vendas!$S$5:$S$2004,4)>0,INDEX(Vendas!$F$5:$F$2004,MATCH(LARGE(Vendas!$S$5:$S$2004,4),Vendas!$S$5:$S$2004,0)),""),"") -> 380 | H59: =IFERROR(IF(LARGE(Vendas!$S$5:$S$2004,4)>0,INDEX(Vendas!$N$5:$N$2004,MATCH(LARGE(Vendas!$S$5:$S$2004,4),Vendas!$S$5:$S$2004,0)),""),"") -> 365.18 | I59: =IFERROR(IF(LARGE(Vendas!$S$5:$S$2004,4)>0,INDEX(Vendas!$L$5:$L$2004,MATCH(LARGE(Vendas!$S$5:$S$2004,4),Vendas!$S$5:$S$2004,0)),""),"") -> 46247 | J59: =IF(I59="","",Config!$B$8-I59) -> 32
A60: 5 | B60: =IFERROR(IF(LARGE(Vendas!$S$5:$S$2004,5)>0,INDEX(Vendas!$A$5:$A$2004,MATCH(LARGE(Vendas!$S$5:$S$2004,5),Vendas!$S$5:$S$2004,0)),""),"") -> 46217 | C60: =IFERROR(IF(LARGE(Vendas!$S$5:$S$2004,5)>0,INDEX(Vendas!$B$5:$B$2004,MATCH(LARGE(Vendas!$S$5:$S$2004,5),Vendas!$S$5:$S$2004,0)),""),"") -> Helena Moreira | D60: =IFERROR(IF(LARGE(Vendas!$S$5:$S$2004,5)>0,INDEX(Vendas!$C$5:$C$2004,MATCH(LARGE(Vendas!$S$5:$S$2004,5),Vendas!$S$5:$S$2004,0)),""),"") -> MAPA | E60: =IFERROR(IF(LARGE(Vendas!$S$5:$S$2004,5)>0,INDEX(Vendas!$D$5:$D$2004,MATCH(LARGE(Vendas!$S$5:$S$2004,5),Vendas!$S$5:$S$2004,0)),""),"") -> Cartão de crédito | F60: =IFERROR(IF(LARGE(Vendas!$S$5:$S$2004,5)>0,INDEX(Vendas!$E$5:$E$2004,MATCH(LARGE(Vendas!$S$5:$S$2004,5),Vendas!$S$5:$S$2004,0)),""),"") -> 2 | G60: =IFERROR(IF(LARGE(Vendas!$S$5:$S$2004,5)>0,INDEX(Vendas!$F$5:$F$2004,MATCH(LARGE(Vendas!$S$5:$S$2004,5),Vendas!$S$5:$S$2004,0)),""),"") -> 300 | H60: =IFERROR(IF(LARGE(Vendas!$S$5:$S$2004,5)>0,INDEX(Vendas!$N$5:$N$2004,MATCH(LARGE(Vendas!$S$5:$S$2004,5),Vendas!$S$5:$S$2004,0)),""),"") -> 288.3 | I60: =IFERROR(IF(LARGE(Vendas!$S$5:$S$2004,5)>0,INDEX(Vendas!$L$5:$L$2004,MATCH(LARGE(Vendas!$S$5:$S$2004,5),Vendas!$S$5:$S$2004,0)),""),"") -> 46247 | J60: =IF(I60="","",Config!$B$8-I60) -> 32
A61: 6 | B61: =IFERROR(IF(LARGE(Vendas!$S$5:$S$2004,6)>0,INDEX(Vendas!$A$5:$A$2004,MATCH(LARGE(Vendas!$S$5:$S$2004,6),Vendas!$S$5:$S$2004,0)),""),"") -> 46275 | C61: =IFERROR(IF(LARGE(Vendas!$S$5:$S$2004,6)>0,INDEX(Vendas!$B$5:$B$2004,MATCH(LARGE(Vendas!$S$5:$S$2004,6),Vendas!$S$5:$S$2004,0)),""),"") -> Mônica Almeida | D61: =IFERROR(IF(LARGE(Vendas!$S$5:$S$2004,6)>0,INDEX(Vendas!$C$5:$C$2004,MATCH(LARGE(Vendas!$S$5:$S$2004,6),Vendas!$S$5:$S$2004,0)),""),"") -> Avaliação endócrina | E61: =IFERROR(IF(LARGE(Vendas!$S$5:$S$2004,6)>0,INDEX(Vendas!$D$5:$D$2004,MATCH(LARGE(Vendas!$S$5:$S$2004,6),Vendas!$S$5:$S$2004,0)),""),"") -> Pix | F61: =IFERROR(IF(LARGE(Vendas!$S$5:$S$2004,6)>0,INDEX(Vendas!$E$5:$E$2004,MATCH(LARGE(Vendas!$S$5:$S$2004,6),Vendas!$S$5:$S$2004,0)),""),"") -> 0 | G61: =IFERROR(IF(LARGE(Vendas!$S$5:$S$2004,6)>0,INDEX(Vendas!$F$5:$F$2004,MATCH(LARGE(Vendas!$S$5:$S$2004,6),Vendas!$S$5:$S$2004,0)),""),"") -> 400 | H61: =IFERROR(IF(LARGE(Vendas!$S$5:$S$2004,6)>0,INDEX(Vendas!$N$5:$N$2004,MATCH(LARGE(Vendas!$S$5:$S$2004,6),Vendas!$S$5:$S$2004,0)),""),"") -> 400 | I61: =IFERROR(IF(LARGE(Vendas!$S$5:$S$2004,6)>0,INDEX(Vendas!$L$5:$L$2004,MATCH(LARGE(Vendas!$S$5:$S$2004,6),Vendas!$S$5:$S$2004,0)),""),"") -> 46275 | J61: =IF(I61="","",Config!$B$8-I61) -> 4
A62: 7 | B62: =IFERROR(IF(LARGE(Vendas!$S$5:$S$2004,7)>0,INDEX(Vendas!$A$5:$A$2004,MATCH(LARGE(Vendas!$S$5:$S$2004,7),Vendas!$S$5:$S$2004,0)),""),"") -> 46245 | C62: =IFERROR(IF(LARGE(Vendas!$S$5:$S$2004,7)>0,INDEX(Vendas!$B$5:$B$2004,MATCH(LARGE(Vendas!$S$5:$S$2004,7),Vendas!$S$5:$S$2004,0)),""),"") -> Beatriz Monteiro | D62: =IFERROR(IF(LARGE(Vendas!$S$5:$S$2004,7)>0,INDEX(Vendas!$C$5:$C$2004,MATCH(LARGE(Vendas!$S$5:$S$2004,7),Vendas!$S$5:$S$2004,0)),""),"") -> Avaliação endócrina | E62: =IFERROR(IF(LARGE(Vendas!$S$5:$S$2004,7)>0,INDEX(Vendas!$D$5:$D$2004,MATCH(LARGE(Vendas!$S$5:$S$2004,7),Vendas!$S$5:$S$2004,0)),""),"") -> Cartão de crédito | F62: =IFERROR(IF(LARGE(Vendas!$S$5:$S$2004,7)>0,INDEX(Vendas!$E$5:$E$2004,MATCH(LARGE(Vendas!$S$5:$S$2004,7),Vendas!$S$5:$S$2004,0)),""),"") -> 0 | G62: =IFERROR(IF(LARGE(Vendas!$S$5:$S$2004,7)>0,INDEX(Vendas!$F$5:$F$2004,MATCH(LARGE(Vendas!$S$5:$S$2004,7),Vendas!$S$5:$S$2004,0)),""),"") -> 400 | H62: =IFERROR(IF(LARGE(Vendas!$S$5:$S$2004,7)>0,INDEX(Vendas!$N$5:$N$2004,MATCH(LARGE(Vendas!$S$5:$S$2004,7),Vendas!$S$5:$S$2004,0)),""),"") -> 387.2 | I62: =IFERROR(IF(LARGE(Vendas!$S$5:$S$2004,7)>0,INDEX(Vendas!$L$5:$L$2004,MATCH(LARGE(Vendas!$S$5:$S$2004,7),Vendas!$S$5:$S$2004,0)),""),"") -> 46275 | J62: =IF(I62="","",Config!$B$8-I62) -> 4
A63: 8 | B63: =IFERROR(IF(LARGE(Vendas!$S$5:$S$2004,8)>0,INDEX(Vendas!$A$5:$A$2004,MATCH(LARGE(Vendas!$S$5:$S$2004,8),Vendas!$S$5:$S$2004,0)),""),"") -> 46275 | C63: =IFERROR(IF(LARGE(Vendas!$S$5:$S$2004,8)>0,INDEX(Vendas!$B$5:$B$2004,MATCH(LARGE(Vendas!$S$5:$S$2004,8),Vendas!$S$5:$S$2004,0)),""),"") -> Regina Macedo | D63: =IFERROR(IF(LARGE(Vendas!$S$5:$S$2004,8)>0,INDEX(Vendas!$C$5:$C$2004,MATCH(LARGE(Vendas!$S$5:$S$2004,8),Vendas!$S$5:$S$2004,0)),""),"") -> Consulta | E63: =IFERROR(IF(LARGE(Vendas!$S$5:$S$2004,8)>0,INDEX(Vendas!$D$5:$D$2004,MATCH(LARGE(Vendas!$S$5:$S$2004,8),Vendas!$S$5:$S$2004,0)),""),"") -> Pix | F63: =IFERROR(IF(LARGE(Vendas!$S$5:$S$2004,8)>0,INDEX(Vendas!$E$5:$E$2004,MATCH(LARGE(Vendas!$S$5:$S$2004,8),Vendas!$S$5:$S$2004,0)),""),"") -> 0 | G63: =IFERROR(IF(LARGE(Vendas!$S$5:$S$2004,8)>0,INDEX(Vendas!$F$5:$F$2004,MATCH(LARGE(Vendas!$S$5:$S$2004,8),Vendas!$S$5:$S$2004,0)),""),"") -> 380 | H63: =IFERROR(IF(LARGE(Vendas!$S$5:$S$2004,8)>0,INDEX(Vendas!$N$5:$N$2004,MATCH(LARGE(Vendas!$S$5:$S$2004,8),Vendas!$S$5:$S$2004,0)),""),"") -> 380 | I63: =IFERROR(IF(LARGE(Vendas!$S$5:$S$2004,8)>0,INDEX(Vendas!$L$5:$L$2004,MATCH(LARGE(Vendas!$S$5:$S$2004,8),Vendas!$S$5:$S$2004,0)),""),"") -> 46275 | J63: =IF(I63="","",Config!$B$8-I63) -> 4
A64: 9 | B64: =IFERROR(IF(LARGE(Vendas!$S$5:$S$2004,9)>0,INDEX(Vendas!$A$5:$A$2004,MATCH(LARGE(Vendas!$S$5:$S$2004,9),Vendas!$S$5:$S$2004,0)),""),"") -> 46274 | C64: =IFERROR(IF(LARGE(Vendas!$S$5:$S$2004,9)>0,INDEX(Vendas!$B$5:$B$2004,MATCH(LARGE(Vendas!$S$5:$S$2004,9),Vendas!$S$5:$S$2004,0)),""),"") -> Cláudia Santos | D64: =IFERROR(IF(LARGE(Vendas!$S$5:$S$2004,9)>0,INDEX(Vendas!$C$5:$C$2004,MATCH(LARGE(Vendas!$S$5:$S$2004,9),Vendas!$S$5:$S$2004,0)),""),"") -> Consulta | E64: =IFERROR(IF(LARGE(Vendas!$S$5:$S$2004,9)>0,INDEX(Vendas!$D$5:$D$2004,MATCH(LARGE(Vendas!$S$5:$S$2004,9),Vendas!$S$5:$S$2004,0)),""),"") -> Cartão de débito | F64: =IFERROR(IF(LARGE(Vendas!$S$5:$S$2004,9)>0,INDEX(Vendas!$E$5:$E$2004,MATCH(LARGE(Vendas!$S$5:$S$2004,9),Vendas!$S$5:$S$2004,0)),""),"") -> 0 | G64: =IFERROR(IF(LARGE(Vendas!$S$5:$S$2004,9)>0,INDEX(Vendas!$F$5:$F$2004,MATCH(LARGE(Vendas!$S$5:$S$2004,9),Vendas!$S$5:$S$2004,0)),""),"") -> 380 | H64: =IFERROR(IF(LARGE(Vendas!$S$5:$S$2004,9)>0,INDEX(Vendas!$N$5:$N$2004,MATCH(LARGE(Vendas!$S$5:$S$2004,9),Vendas!$S$5:$S$2004,0)),""),"") -> 374.3 | I64: =IFERROR(IF(LARGE(Vendas!$S$5:$S$2004,9)>0,INDEX(Vendas!$L$5:$L$2004,MATCH(LARGE(Vendas!$S$5:$S$2004,9),Vendas!$S$5:$S$2004,0)),""),"") -> 46275 | J64: =IF(I64="","",Config!$B$8-I64) -> 4
A65: 10 | B65: =IFERROR(IF(LARGE(Vendas!$S$5:$S$2004,10)>0,INDEX(Vendas!$A$5:$A$2004,MATCH(LARGE(Vendas!$S$5:$S$2004,10),Vendas!$S$5:$S$2004,0)),""),"") -> 46245 | C65: =IFERROR(IF(LARGE(Vendas!$S$5:$S$2004,10)>0,INDEX(Vendas!$B$5:$B$2004,MATCH(LARGE(Vendas!$S$5:$S$2004,10),Vendas!$S$5:$S$2004,0)),""),"") -> Gustavo Ferreira | D65: =IFERROR(IF(LARGE(Vendas!$S$5:$S$2004,10)>0,INDEX(Vendas!$C$5:$C$2004,MATCH(LARGE(Vendas!$S$5:$S$2004,10),Vendas!$S$5:$S$2004,0)),""),"") -> Consulta | E65: =IFERROR(IF(LARGE(Vendas!$S$5:$S$2004,10)>0,INDEX(Vendas!$D$5:$D$2004,MATCH(LARGE(Vendas!$S$5:$S$2004,10),Vendas!$S$5:$S$2004,0)),""),"") -> Cartão de crédito | F65: =IFERROR(IF(LARGE(Vendas!$S$5:$S$2004,10)>0,INDEX(Vendas!$E$5:$E$2004,MATCH(LARGE(Vendas!$S$5:$S$2004,10),Vendas!$S$5:$S$2004,0)),""),"") -> 0 | G65: =IFERROR(IF(LARGE(Vendas!$S$5:$S$2004,10)>0,INDEX(Vendas!$F$5:$F$2004,MATCH(LARGE(Vendas!$S$5:$S$2004,10),Vendas!$S$5:$S$2004,0)),""),"") -> 380 | H65: =IFERROR(IF(LARGE(Vendas!$S$5:$S$2004,10)>0,INDEX(Vendas!$N$5:$N$2004,MATCH(LARGE(Vendas!$S$5:$S$2004,10),Vendas!$S$5:$S$2004,0)),""),"") -> 367.84 | I65: =IFERROR(IF(LARGE(Vendas!$S$5:$S$2004,10)>0,INDEX(Vendas!$L$5:$L$2004,MATCH(LARGE(Vendas!$S$5:$S$2004,10),Vendas!$S$5:$S$2004,0)),""),"") -> 46275 | J65: =IF(I65="","",Config!$B$8-I65) -> 4
A66: Venda que não caiu na conta na data prevista: confira o extrato da operadora (estorno, chargeback, erro de bandeira) antes de cobrar o paciente. A planilha aponta; a conferência é sua.

Sheet Config
A1: Configurações
A2: Células amarelas: você preenche. Taxas e prazos da sua operadora (o contrato da maquininha diz; confira no extrato).
A4: Clínica | B4: Clínica Vida Plena (exemplo fictício) | H4: Meses
A5: Ano do painel | B5: 2026 | H5: Janeiro
A6: Mês do painel | B6: Agosto | H6: Fevereiro
A7: Número do mês | B7: =MATCH(B6,$H$5:$H$16,0) -> 8 | H7: Março
A8: Data de referência (hoje) | B8: 46279 | H8: Abril
A9: Preço da consulta particular (para a comparação) | B9: 380 | H9: Maio
H10: Junho
A11: Tipo | B11: Taxa (%) | C11: Cai na conta em (dias) | D11: Observação | H11: Julho
A12: Pix | B12: 0 | C12: 0 | D12: Pix na conta PJ: no exemplo, sem taxa (alguns bancos cobram por recebimento). | H12: Agosto
A13: Cartão de débito | B13: 0.015 | C13: 1 | D13: Débito costuma cair no dia útil seguinte. | H13: Setembro
A14: Cartão de crédito | B14: 0.032 | C14: 30 | D14: Crédito à vista cai em 30 dias. | H14: Outubro
A15: Cartão de crédito parcelado | B15: 0.039 | C15: 30 | D15: Parcelado: cada parcela cai 30 dias depois da anterior; a taxa é maior. | H15: Novembro
H16: Dezembro
A17: Antecipar o crédito? (Sim/Não) | B17: Não | D17: Com antecipação, o crédito cai em 1 dia e a operadora cobra a taxa de antecipação sobre o valor pelo prazo antecipado. No exemplo, a clínica não antecipa.
A18: Taxa de antecipação (% ao mês) | B18: 0.018
A20: As taxas do exemplo são ilustrativas. Pegue as suas no contrato da maquininha ou no extrato da operadora; elas mudam por bandeira e por volume.

Sheet Vendas
A1: Vendas no cartão e no Pix
A2: Uma linha por pagamento (copie da Agenda da planilha 01: atendimentos particulares realizados com Pix ou cartão). Amarelo: data, paciente, procedimento, tipo, parcelas, valor bruto e a conferência no extrato.
A4: Data da venda | B4: Paciente | C4: Procedimento | D4: Tipo | E4: Parcelas | F4: Valor bruto (R$) | G4: Parcelas já conferidas | H4: Taxa (%) | I4: Taxa (R$) | J4: Valor líquido (R$) | K4: Líquido por parcela (R$) | L4: 1ª parcela cai em | M4: Última parcela cai em | N4: Já previsto até hoje (R$) | O4: Ainda vai cair (R$) | P4: Mês | Q4: Ano | R4: Situação
A5: 46174 | B5: Cláudia Santos | C5: MAPA | D5: Pix | F5: 300 | G5: 1 | H5: =IF(D5="","",IFERROR(INDEX(Config!$B$12:$B$15,MATCH(IF(AND(D5="Cartão de crédito",N(E5)>1),"Cartão de crédito parcelado",D5),Config!$A$12:$A$15,0)),0)+IF(AND(Config!$B$17="Sim",LEFT(D5,17)="Cartão de crédito"),Config!$B$18*IFERROR(INDEX(Config!$C$12:$C$15,MATCH(IF(AND(D5="Cartão de crédito",N(E5)>1),"Cartão de crédito parcelado",D5),Config!$A$12:$A$15,0)),0)/30*MAX(1,N(E5)),0)) -> 0 | I5: =IF(OR(D5="",F5=""),"",ROUND(F5*H5,2)) -> 0 | J5: =IF(I5="","",F5-I5) -> 300 | K5: =IF(J5="","",J5/MAX(1,N(E5))) -> 300 | L5: =IF(OR(D5="",A5=""),"",A5+IF(AND(Config!$B$17="Sim",LEFT(D5,17)="Cartão de crédito"),1,IFERROR(INDEX(Config!$C$12:$C$15,MATCH(IF(AND(D5="Cartão de crédito",N(E5)>1),"Cartão de crédito parcelado",D5),Config!$A$12:$A$15,0)),0))) -> 46174 | M5: =IF(L5="","",IF(AND(Config!$B$17="Sim",LEFT(D5,17)="Cartão de crédito"),L5,L5+30*(MAX(1,N(E5))-1))) -> 46174 | N5: =IF(OR(L5="",K5=""),"",K5*MIN(MAX(1,N(E5)),MAX(0,INT((Config!$B$8-L5)/30)+1))) -> 300 | O5: =IF(J5="","",J5-N(N5)) -> 0 | P5: =IF(A5="","",MONTH(A5)) -> 6 | Q5: =IF(A5="","",YEAR(A5)) -> 2026 | R5: =IF(L5="","",IF(L5>Config!$B$8,"A cair",IF(N(G5)>=MIN(MAX(1,N(E5)),MAX(0,INT((Config!$B$8-L5)/30)+1)),IF(N(G5)>=MAX(1,N(E5)),"Conferido","Conferido até aqui"),"A conferir"))) -> Conferido | S5: =IF(R5="A conferir",(Config!$B$8-L5)*1000+N(F5)/1000+ROW()/100000,0) -> 0 | T5: =IF(R5="A conferir",N(N5),0) -> 0 | U5: =IF(L5="",0,L5) -> 46174 | V5: =IF(L5="",0,MAX(1,N(E5))) -> 1 | W5: =IF(K5="",0,K5) -> 300
A6: 46175 | B6: Otávio Nascimento | C6: Consulta | D6: Cartão de crédito | F6: 380 | G6: 1 | H6: =IF(D6="","",IFERROR(INDEX(Config!$B$12:$B$15,MATCH(IF(AND(D6="Cartão de crédito",N(E6)>1),"Cartão de crédito parcelado",D6),Config!$A$12:$A$15,0)),0)+IF(AND(Config!$B$17="Sim",LEFT(D6,17)="Cartão de crédito"),Config!$B$18*IFERROR(INDEX(Config!$C$12:$C$15,MATCH(IF(AND(D6="Cartão de crédito",N(E6)>1),"Cartão de crédito parcelado",D6),Config!$A$12:$A$15,0)),0)/30*MAX(1,N(E6)),0)) -> 0.032 | I6: =IF(OR(D6="",F6=""),"",ROUND(F6*H6,2)) -> 12.16 | J6: =IF(I6="","",F6-I6) -> 367.84 | K6: =IF(J6="","",J6/MAX(1,N(E6))) -> 367.84 | L6: =IF(OR(D6="",A6=""),"",A6+IF(AND(Config!$B$17="Sim",LEFT(D6,17)="Cartão de crédito"),1,IFERROR(INDEX(Config!$C$12:$C$15,MATCH(IF(AND(D6="Cartão de crédito",N(E6)>1),"Cartão de crédito parcelado",D6),Config!$A$12:$A$15,0)),0))) -> 46205 | M6: =IF(L6="","",IF(AND(Config!$B$17="Sim",LEFT(D6,17)="Cartão de crédito"),L6,L6+30*(MAX(1,N(E6))-1))) -> 46205 | N6: =IF(OR(L6="",K6=""),"",K6*MIN(MAX(1,N(E6)),MAX(0,INT((Config!$B$8-L6)/30)+1))) -> 367.84 | O6: =IF(J6="","",J6-N(N6)) -> 0 | P6: =IF(A6="","",MONTH(A6)) -> 6 | Q6: =IF(A6="","",YEAR(A6)) -> 2026 | R6: =IF(L6="","",IF(L6>Config!$B$8,"A cair",IF(N(G6)>=MIN(MAX(1,N(E6)),MAX(0,INT((Config!$B$8-L6)/30)+1)),IF(N(G6)>=MAX(1,N(E6)),"Conferido","Conferido até aqui"),"A conferir"))) -> Conferido | S6: =IF(R6="A conferir",(Config!$B$8-L6)*1000+N(F6)/1000+ROW()/100000,0) -> 0 | T6: =IF(R6="A conferir",N(N6),0) -> 0 | U6: =IF(L6="",0,L6) -> 46205 | V6: =IF(L6="",0,MAX(1,N(E6))) -> 1 | W6: =IF(K6="",0,K6) -> 367.84
A7: 46175 | B7: Leandro Oliveira | C7: Consulta | D7: Pix | F7: 380 | G7: 1 | H7: =IF(D7="","",IFERROR(INDEX(Config!$B$12:$B$15,MATCH(IF(AND(D7="Cartão de crédito",N(E7)>1),"Cartão de crédito parcelado",D7),Config!$A$12:$A$15,0)),0)+IF(AND(Config!$B$17="Sim",LEFT(D7,17)="Cartão de crédito"),Config!$B$18*IFERROR(INDEX(Config!$C$12:$C$15,MATCH(IF(AND(D7="Cartão de crédito",N(E7)>1),"Cartão de crédito parcelado",D7),Config!$A$12:$A$15,0)),0)/30*MAX(1,N(E7)),0)) -> 0 | I7: =IF(OR(D7="",F7=""),"",ROUND(F7*H7,2)) -> 0 | J7: =IF(I7="","",F7-I7) -> 380 | K7: =IF(J7="","",J7/MAX(1,N(E7))) -> 380 | L7: =IF(OR(D7="",A7=""),"",A7+IF(AND(Config!$B$17="Sim",LEFT(D7,17)="Cartão de crédito"),1,IFERROR(INDEX(Config!$C$12:$C$15,MATCH(IF(AND(D7="Cartão de crédito",N(E7)>1),"Cartão de crédito parcelado",D7),Config!$A$12:$A$15,0)),0))) -> 46175 | M7: =IF(L7="","",IF(AND(Config!$B$17="Sim",LEFT(D7,17)="Cartão de crédito"),L7,L7+30*(MAX(1,N(E7))-1))) -> 46175 | N7: =IF(OR(L7="",K7=""),"",K7*MIN(MAX(1,N(E7)),MAX(0,INT((Config!$B$8-L7)/30)+1))) -> 380 | O7: =IF(J7="","",J7-N(N7)) -> 0 | P7: =IF(A7="","",MONTH(A7)) -> 6 | Q7: =IF(A7="","",YEAR(A7)) -> 2026 | R7: =IF(L7="","",IF(L7>Config!$B$8,"A cair",IF(N(G7)>=MIN(MAX(1,N(E7)),MAX(0,INT((Config!$B$8-L7)/30)+1)),IF(N(G7)>=MAX(1,N(E7)),"Conferido","Conferido até aqui"),"A conferir"))) -> Conferido | S7: =IF(R7="A conferir",(Config!$B$8-L7)*1000+N(F7)/1000+ROW()/100000,0) -> 0 | T7: =IF(R7="A conferir",N(N7),0) -> 0 | U7: =IF(L7="",0,L7) -> 46175 | V7: =IF(L7="",0,MAX(1,N(E7))) -> 1 | W7: =IF(K7="",0,K7) -> 380
A8: 46175 | B8: Cláudia Costa | C8: Consulta | D8: Pix | F8: 380 | G8: 1 | H8: =IF(D8="","",IFERROR(INDEX(Config!$B$12:$B$15,MATCH(IF(AND(D8="Cartão de crédito",N(E8)>1),"Cartão de crédito parcelado",D8),Config!$A$12:$A$15,0)),0)+IF(AND(Config!$B$17="Sim",LEFT(D8,17)="Cartão de crédito"),Config!$B$18*IFERROR(INDEX(Config!$C$12:$C$15,MATCH(IF(AND(D8="Cartão de crédito",N(E8)>1),"Cartão de crédito parcelado",D8),Config!$A$12:$A$15,0)),0)/30*MAX(1,N(E8)),0)) -> 0 | I8: =IF(OR(D8="",F8=""),"",ROUND(F8*H8,2)) -> 0 | J8: =IF(I8="","",F8-I8) -> 380 | K8: =IF(J8="","",J8/MAX(1,N(E8))) -> 380 | L8: =IF(OR(D8="",A8=""),"",A8+IF(AND(Config!$B$17="Sim",LEFT(D8,17)="Cartão de crédito"),1,IFERROR(INDEX(Config!$C$12:$C$15,MATCH(IF(AND(D8="Cartão de crédito",N(E8)>1),"Cartão de crédito parcelado",D8),Config!$A$12:$A$15,0)),0))) -> 46175 | M8: =IF(L8="","",IF(AND(Config!$B$17="Sim",LEFT(D8,17)="Cartão de crédito"),L8,L8+30*(MAX(1,N(E8))-1))) -> 46175 | N8: =IF(OR(L8="",K8=""),"",K8*MIN(MAX(1,N(E8)),MAX(0,INT((Config!$B$8-L8)/30)+1))) -> 380 | O8: =IF(J8="","",J8-N(N8)) -> 0 | P8: =IF(A8="","",MONTH(A8)) -> 6 | Q8: =IF(A8="","",YEAR(A8)) -> 2026 | R8: =IF(L8="","",IF(L8>Config!$B$8,"A cair",IF(N(G8)>=MIN(MAX(1,N(E8)),MAX(0,INT((Config!$B$8-L8)/30)+1)),IF(N(G8)>=MAX(1,N(E8)),"Conferido","Conferido até aqui"),"A conferir"))) -> Conferido | S8: =IF(R8="A conferir",(Config!$B$8-L8)*1000+N(F8)/1000+ROW()/100000,0) -> 0 | T8: =IF(R8="A conferir",N(N8),0) -> 0 | U8: =IF(L8="",0,L8) -> 46175 | V8: =IF(L8="",0,MAX(1,N(E8))) -> 1 | W8: =IF(K8="",0,K8) -> 380
A9: 46175 | B9: Eduardo Pereira | C9: Avaliação endócrina | D9: Pix | F9: 400 | G9: 1 | H9: =IF(D9="","",IFERROR(INDEX(Config!$B$12:$B$15,MATCH(IF(AND(D9="Cartão de crédito",N(E9)>1),"Cartão de crédito parcelado",D9),Config!$A$12:$A$15,0)),0)+IF(AND(Config!$B$17="Sim",LEFT(D9,17)="Cartão de crédito"),Config!$B$18*IFERROR(INDEX(Config!$C$12:$C$15,MATCH(IF(AND(D9="Cartão de crédito",N(E9)>1),"Cartão de crédito parcelado",D9),Config!$A$12:$A$15,0)),0)/30*MAX(1,N(E9)),0)) -> 0 | I9: =IF(OR(D9="",F9=""),"",ROUND(F9*H9,2)) -> 0 | J9: =IF(I9="","",F9-I9) -> 400 | K9: =IF(J9="","",J9/MAX(1,N(E9))) -> 400 | L9: =IF(OR(D9="",A9=""),"",A9+IF(AND(Config!$B$17="Sim",LEFT(D9,17)="Cartão de crédito"),1,IFERROR(INDEX(Config!$C$12:$C$15,MATCH(IF(AND(D9="Cartão de crédito",N(E9)>1),"Cartão de crédito parcelado",D9),Config!$A$12:$A$15,0)),0))) -> 46175 | M9: =IF(L9="","",IF(AND(Config!$B$17="Sim",LEFT(D9,17)="Cartão de crédito"),L9,L9+30*(MAX(1,N(E9))-1))) -> 46175 | N9: =IF(OR(L9="",K9=""),"",K9*MIN(MAX(1,N(E9)),MAX(0,INT((Config!$B$8-L9)/30)+1))) -> 400 | O9: =IF(J9="","",J9-N(N9)) -> 0 | P9: =IF(A9="","",MONTH(A9)) -> 6 | Q9: =IF(A9="","",YEAR(A9)) -> 2026 | R9: =IF(L9="","",IF(L9>Config!$B$8,"A cair",IF(N(G9)>=MIN(MAX(1,N(E9)),MAX(0,INT((Config!$B$8-L9)/30)+1)),IF(N(G9)>=MAX(1,N(E9)),"Conferido","Conferido até aqui"),"A conferir"))) -> Conferido | S9: =IF(R9="A conferir",(Config!$B$8-L9)*1000+N(F9)/1000+ROW()/100000,0) -> 0 | T9: =IF(R9="A conferir",N(N9),0) -> 0 | U9: =IF(L9="",0,L9) -> 46175 | V9: =IF(L9="",0,MAX(1,N(E9))) -> 1 | W9: =IF(K9="",0,K9) -> 400
A10: 46175 | B10: Rafael Pereira | C10: Avaliação endócrina | D10: Pix | F10: 400 | G10: 1 | H10: =IF(D10="","",IFERROR(INDEX(Config!$B$12:$B$15,MATCH(IF(AND(D10="Cartão de crédito",N(E10)>1),"Cartão de crédito parcelado",D10),Config!$A$12:$A$15,0)),0)+IF(AND(Config!$B$17="Sim",LEFT(D10,17)="Cartão de crédito"),Config!$B$18*IFERROR(INDEX(Config!$C$12:$C$15,MATCH(IF(AND(D10="Cartão de crédito",N(E10)>1),"Cartão de crédito parcelado",D10),Config!$A$12:$A$15,0)),0)/30*MAX(1,N(E10)),0)) -> 0 | I10: =IF(OR(D10="",F10=""),"",ROUND(F10*H10,2)) -> 0 | J10: =IF(I10="","",F10-I10) -> 400 | K10: =IF(J10="","",J10/MAX(1,N(E10))) -> 400 | L10: =IF(OR(D10="",A10=""),"",A10+IF(AND(Config!$B$17="Sim",LEFT(D10,17)="Cartão de crédito"),1,IFERROR(INDEX(Config!$C$12:$C$15,MATCH(IF(AND(D10="Cartão de crédito",N(E10)>1),"Cartão de crédito parcelado",D10),Config!$A$12:$A$15,0)),0))) -> 46175 | M10: =IF(L10="","",IF(AND(Config!$B$17="Sim",LEFT(D10,17)="Cartão de crédito"),L10,L10+30*(MAX(1,N(E10))-1))) -> 46175 | N10: =IF(OR(L10="",K10=""),"",K10*MIN(MAX(1,N(E10)),MAX(0,INT((Config!$B$8-L10)/30)+1))) -> 400 | O10: =IF(J10="","",J10-N(N10)) -> 0 | P10: =IF(A10="","",MONTH(A10)) -> 6 | Q10: =IF(A10="","",YEAR(A10)) -> 2026 | R10: =IF(L10="","",IF(L10>Config!$B$8,"A cair",IF(N(G10)>=MIN(MAX(1,N(E10)),MAX(0,INT((Config!$B$8-L10)/30)+1)),IF(N(G10)>=MAX(1,N(E10)),"Conferido","Conferido até aqui"),"A conferir"))) -> Conferido | S10: =IF(R10="A conferir",(Config!$B$8-L10)*1000+N(F10)/1000+ROW()/100000,0) -> 0 | T10: =IF(R10="A conferir",N(N10),0) -> 0 | U10: =IF(L10="",0,L10) -> 46175 | V10: =IF(L10="",0,MAX(1,N(E10))) -> 1 | W10: =IF(K10="",0,K10) -> 400
A11: 46175 | B11: Elaine Cardoso | C11: Teste ergométrico | D11: Cartão de crédito | E11: 2 | F11: 450 | G11: 2 | H11: =IF(D11="","",IFERROR(INDEX(Config!$B$12:$B$15,MATCH(IF(AND(D11="Cartão de crédito",N(E11)>1),"Cartão de crédito parcelado",D11),Config!$A$12:$A$15,0)),0)+IF(AND(Config!$B$17="Sim",LEFT(D11,17)="Cartão de crédito"),Config!$B$18*IFERROR(INDEX(Config!$C$12:$C$15,MATCH(IF(AND(D11="Cartão de crédito",N(E11)>1),"Cartão de crédito parcelado",D11),Config!$A$12:$A$15,0)),0)/30*MAX(1,N(E11)),0)) -> 0.039 | I11: =IF(OR(D11="",F11=""),"",ROUND(F11*H11,2)) -> 17.55 | J11: =IF(I11="","",F11-I11) -> 432.45 | K11: =IF(J11="","",J11/MAX(1,N(E11))) -> 216.225 | L11: =IF(OR(D11="",A11=""),"",A11+IF(AND(Config!$B$17="Sim",LEFT(D11,17)="Cartão de crédito"),1,IFERROR(INDEX(Config!$C$12:$C$15,MATCH(IF(AND(D11="Cartão de crédito",N(E11)>1),"Cartão de crédito parcelado",D11),Config!$A$12:$A$15,0)),0))) -> 46205 | M11: =IF(L11="","",IF(AND(Config!$B$17="Sim",LEFT(D11,17)="Cartão de crédito"),L11,L11+30*(MAX(1,N(E11))-1))) -> 46235 | N11: =IF(OR(L11="",K11=""),"",K11*MIN(MAX(1,N(E11)),MAX(0,INT((Config!$B$8-L11)/30)+1))) -> 432.45 | O11: =IF(J11="","",J11-N(N11)) -> 0 | P11: =IF(A11="","",MONTH(A11)) -> 6 | Q11: =IF(A11="","",YEAR(A11)) -> 2026 | R11: =IF(L11="","",IF(L11>Config!$B$8,"A cair",IF(N(G11)>=MIN(MAX(1,N(E11)),MAX(0,INT((Config!$B$8-L11)/30)+1)),IF(N(G11)>=MAX(1,N(E11)),"Conferido","Conferido até aqui"),"A conferir"))) -> Conferido | S11: =IF(R11="A conferir",(Config!$B$8-L11)*1000+N(F11)/1000+ROW()/100000,0) -> 0 | T11: =IF(R11="A conferir",N(N11),0) -> 0 | U11: =IF(L11="",0,L11) -> 46205 | V11: =IF(L11="",0,MAX(1,N(E11))) -> 2 | W11: =IF(K11="",0,K11) -> 216.225
A12: 46176 | B12: Lucas Lopes | C12: Consulta | D12: Cartão de crédito | F12: 380 | G12: 1 | H12: =IF(D12="","",IFERROR(INDEX(Config!$B$12:$B$15,MATCH(IF(AND(D12="Cartão de crédito",N(E12)>1),"Cartão de crédito parcelado",D12),Config!$A$12:$A$15,0)),0)+IF(AND(Config!$B$17="Sim",LEFT(D12,17)="Cartão de crédito"),Config!$B$18*IFERROR(INDEX(Config!$C$12:$C$15,MATCH(IF(AND(D12="Cartão de crédito",N(E12)>1),"Cartão de crédito parcelado",D12),Config!$A$12:$A$15,0)),0)/30*MAX(1,N(E12)),0)) -> 0.032 | I12: =IF(OR(D12="",F12=""),"",ROUND(F12*H12,2)) -> 12.16 | J12: =IF(I12="","",F12-I12) -> 367.84 | K12: =IF(J12="","",J12/MAX(1,N(E12))) -> 367.84 | L12: =IF(OR(D12="",A12=""),"",A12+IF(AND(Config!$B$17="Sim",LEFT(D12,17)="Cartão de crédito"),1,IFERROR(INDEX(Config!$C$12:$C$15,MATCH(IF(AND(D12="Cartão de crédito",N(E12)>1),"Cartão de crédito parcelado",D12),Config!$A$12:$A$15,0)),0))) -> 46206 | M12: =IF(L12="","",IF(AND(Config!$B$17="Sim",LEFT(D12,17)="Cartão de crédito"),L12,L12+30*(MAX(1,N(E12))-1))) -> 46206 | N12: =IF(OR(L12="",K12=""),"",K12*MIN(MAX(1,N(E12)),MAX(0,INT((Config!$B$8-L12)/30)+1))) -> 367.84 | O12: =IF(J12="","",J12-N(N12)) -> 0 | P12: =IF(A12="","",MONTH(A12)) -> 6 | Q12: =IF(A12="","",YEAR(A12)) -> 2026 | R12: =IF(L12="","",IF(L12>Config!$B$8,"A cair",IF(N(G12)>=MIN(MAX(1,N(E12)),MAX(0,INT((Config!$B$8-L12)/30)+1)),IF(N(G12)>=MAX(1,N(E12)),"Conferido","Conferido até aqui"),"A conferir"))) -> Conferido | S12: =IF(R12="A conferir",(Config!$B$8-L12)*1000+N(F12)/1000+ROW()/100000,0) -> 0 | T12: =IF(R12="A conferir",N(N12),0) -> 0 | U12: =IF(L12="",0,L12) -> 46206 | V12: =IF(L12="",0,MAX(1,N(E12))) -> 1 | W12: =IF(K12="",0,K12) -> 367.84
A13: 46176 | B13: Helena Moreira | C13: Consulta | D13: Pix | F13: 380 | G13: 1 | H13: =IF(D13="","",IFERROR(INDEX(Config!$B$12:$B$15,MATCH(IF(AND(D13="Cartão de crédito",N(E13)>1),"Cartão de crédito parcelado",D13),Config!$A$12:$A$15,0)),0)+IF(AND(Config!$B$17="Sim",LEFT(D13,17)="Cartão de crédito"),Config!$B$18*IFERROR(INDEX(Config!$C$12:$C$15,MATCH(IF(AND(D13="Cartão de crédito",N(E13)>1),"Cartão de crédito parcelado",D13),Config!$A$12:$A$15,0)),0)/30*MAX(1,N(E13)),0)) -> 0 | I13: =IF(OR(D13="",F13=""),"",ROUND(F13*H13,2)) -> 0 | J13: =IF(I13="","",F13-I13) -> 380 | K13: =IF(J13="","",J13/MAX(1,N(E13))) -> 380 | L13: =IF(OR(D13="",A13=""),"",A13+IF(AND(Config!$B$17="Sim",LEFT(D13,17)="Cartão de crédito"),1,IFERROR(INDEX(Config!$C$12:$C$15,MATCH(IF(AND(D13="Cartão de crédito",N(E13)>1),"Cartão de crédito parcelado",D13),Config!$A$12:$A$15,0)),0))) -> 46176 | M13: =IF(L13="","",IF(AND(Config!$B$17="Sim",LEFT(D13,17)="Cartão de crédito"),L13,L13+30*(MAX(1,N(E13))-1))) -> 46176 | N13: =IF(OR(L13="",K13=""),"",K13*MIN(MAX(1,N(E13)),MAX(0,INT((Config!$B$8-L13)/30)+1))) -> 380 | O13: =IF(J13="","",J13-N(N13)) -> 0 | P13: =IF(A13="","",MONTH(A13)) -> 6 | Q13: =IF(A13="","",YEAR(A13)) -> 2026 | R13: =IF(L13="","",IF(L13>Config!$B$8,"A cair",IF(N(G13)>=MIN(MAX(1,N(E13)),MAX(0,INT((Config!$B$8-L13)/30)+1)),IF(N(G13)>=MAX(1,N(E13)),"Conferido","Conferido até aqui"),"A conferir"))) -> Conferido | S13: =IF(R13="A conferir",(Config!$B$8-L13)*1000+N(F13)/1000+ROW()/100000,0) -> 0 | T13: =IF(R13="A conferir",N(N13),0) -> 0 | U13: =IF(L13="",0,L13) -> 46176 | V13: =IF(L13="",0,MAX(1,N(E13))) -> 1 | W13: =IF(K13="",0,K13) -> 380
A14: 46181 | B14: Mônica Martins | C14: Consulta | D14: Cartão de débito | F14: 380 | G14: 1 | H14: =IF(D14="","",IFERROR(INDEX(Config!$B$12:$B$15,MATCH(IF(AND(D14="Cartão de crédito",N(E14)>1),"Cartão de crédito parcelado",D14),Config!$A$12:$A$15,0)),0)+IF(AND(Config!$B$17="Sim",LEFT(D14,17)="Cartão de crédito"),Config!$B$18*IFERROR(INDEX(Config!$C$12:$C$15,MATCH(IF(AND(D14="Cartão de crédito",N(E14)>1),"Cartão de crédito parcelado",D14),Config!$A$12:$A$15,0)),0)/30*MAX(1,N(E14)),0)) -> 0.015 | I14: =IF(OR(D14="",F14=""),"",ROUND(F14*H14,2)) -> 5.7 | J14: =IF(I14="","",F14-I14) -> 374.3 | K14: =IF(J14="","",J14/MAX(1,N(E14))) -> 374.3 | L14: =IF(OR(D14="",A14=""),"",A14+IF(AND(Config!$B$17="Sim",LEFT(D14,17)="Cartão de crédito"),1,IFERROR(INDEX(Config!$C$12:$C$15,MATCH(IF(AND(D14="Cartão de crédito",N(E14)>1),"Cartão de crédito parcelado",D14),Config!$A$12:$A$15,0)),0))) -> 46182 | M14: =IF(L14="","",IF(AND(Config!$B$17="Sim",LEFT(D14,17)="Cartão de crédito"),L14,L14+30*(MAX(1,N(E14))-1))) -> 46182 | N14: =IF(OR(L14="",K14=""),"",K14*MIN(MAX(1,N(E14)),MAX(0,INT((Config!$B$8-L14)/30)+1))) -> 374.3 | O14: =IF(J14="","",J14-N(N14)) -> 0 | P14: =IF(A14="","",MONTH(A14)) -> 6 | Q14: =IF(A14="","",YEAR(A14)) -> 2026 | R14: =IF(L14="","",IF(L14>Config!$B$8,"A cair",IF(N(G14)>=MIN(MAX(1,N(E14)),MAX(0,INT((Config!$B$8-L14)/30)+1)),IF(N(G14)>=MAX(1,N(E14)),"Conferido","Conferido até aqui"),"A conferir"))) -> Conferido | S14: =IF(R14="A conferir",(Config!$B$8-L14)*1000+N(F14)/1000+ROW()/100000,0) -> 0 | T14: =IF(R14="A conferir",N(N14),0) -> 0 | U14: =IF(L14="",0,L14) -> 46182 | V14: =IF(L14="",0,MAX(1,N(E14))) -> 1 | W14: =IF(K14="",0,K14) -> 374.3
A15: 46181 | B15: Mariana Nascimento | C15: Consulta | D15: Pix | F15: 380 | G15: 1 | H15: =IF(D15="","",IFERROR(INDEX(Config!$B$12:$B$15,MATCH(IF(AND(D15="Cartão de crédito",N(E15)>1),"Cartão de crédito parcelado",D15),Config!$A$12:$A$15,0)),0)+IF(AND(Config!$B$17="Sim",LEFT(D15,17)="Cartão de crédito"),Config!$B$18*IFERROR(INDEX(Config!$C$12:$C$15,MATCH(IF(AND(D15="Cartão de crédito",N(E15)>1),"Cartão de crédito parcelado",D15),Config!$A$12:$A$15,0)),0)/30*MAX(1,N(E15)),0)) -> 0 | I15: =IF(OR(D15="",F15=""),"",ROUND(F15*H15,2)) -> 0 | J15: =IF(I15="","",F15-I15) -> 380 | K15: =IF(J15="","",J15/MAX(1,N(E15))) -> 380 | L15: =IF(OR(D15="",A15=""),"",A15+IF(AND(Config!$B$17="Sim",LEFT(D15,17)="Cartão de crédito"),1,IFERROR(INDEX(Config!$C$12:$C$15,MATCH(IF(AND(D15="Cartão de crédito",N(E15)>1),"Cartão de crédito parcelado",D15),Config!$A$12:$A$15,0)),0))) -> 46181 | M15: =IF(L15="","",IF(AND(Config!$B$17="Sim",LEFT(D15,17)="Cartão de crédito"),L15,L15+30*(MAX(1,N(E15))-1))) -> 46181 | N15: =IF(OR(L15="",K15=""),"",K15*MIN(MAX(1,N(E15)),MAX(0,INT((Config!$B$8-L15)/30)+1))) -> 380 | O15: =IF(J15="","",J15-N(N15)) -> 0 | P15: =IF(A15="","",MONTH(A15)) -> 6 | Q15: =IF(A15="","",YEAR(A15)) -> 2026 | R15: =IF(L15="","",IF(L15>Config!$B$8,"A cair",IF(N(G15)>=MIN(MAX(1,N(E15)),MAX(0,INT((Config!$B$8-L15)/30)+1)),IF(N(G15)>=MAX(1,N(E15)),"Conferido","Conferido até aqui"),"A conferir"))) -> Conferido | S15: =IF(R15="A conferir",(Config!$B$8-L15)*1000+N(F15)/1000+ROW()/100000,0) -> 0 | T15: =IF(R15="A conferir",N(N15),0) -> 0 | U15: =IF(L15="",0,L15) -> 46181 | V15: =IF(L15="",0,MAX(1,N(E15))) -> 1 | W15: =IF(K15="",0,K15) -> 380
A16: 46181 | B16: Rodrigo Moreira | C16: ECG | D16: Cartão de crédito | F16: 130 | G16: 1 | H16: =IF(D16="","",IFERROR(INDEX(Config!$B$12:$B$15,MATCH(IF(AND(D16="Cartão de crédito",N(E16)>1),"Cartão de crédito parcelado",D16),Config!$A$12:$A$15,0)),0)+IF(AND(Config!$B$17="Sim",LEFT(D16,17)="Cartão de crédito"),Config!$B$18*IFERROR(INDEX(Config!$C$12:$C$15,MATCH(IF(AND(D16="Cartão de crédito",N(E16)>1),"Cartão de crédito parcelado",D16),Config!$A$12:$A$15,0)),0)/30*MAX(1,N(E16)),0)) -> 0.032 | I16: =IF(OR(D16="",F16=""),"",ROUND(F16*H16,2)) -> 4.16 | J16: =IF(I16="","",F16-I16) -> 125.84 | K16: =IF(J16="","",J16/MAX(1,N(E16))) -> 125.84 | L16: =IF(OR(D16="",A16=""),"",A16+IF(AND(Config!$B$17="Sim",LEFT(D16,17)="Cartão de crédito"),1,IFERROR(INDEX(Config!$C$12:$C$15,MATCH(IF(AND(D16="Cartão de crédito",N(E16)>1),"Cartão de crédito parcelado",D16),Config!$A$12:$A$15,0)),0))) -> 46211 | M16: =IF(L16="","",IF(AND(Config!$B$17="Sim",LEFT(D16,17)="Cartão de crédito"),L16,L16+30*(MAX(1,N(E16))-1))) -> 46211 | N16: =IF(OR(L16="",K16=""),"",K16*MIN(MAX(1,N(E16)),MAX(0,INT((Config!$B$8-L16)/30)+1))) -> 125.84 | O16: =IF(J16="","",J16-N(N16)) -> 0 | P16: =IF(A16="","",MONTH(A16)) -> 6 | Q16: =IF(A16="","",YEAR(A16)) -> 2026 | R16: =IF(L16="","",IF(L16>Config!$B$8,"A cair",IF(N(G16)>=MIN(MAX(1,N(E16)),MAX(0,INT((Config!$B$8-L16)/30)+1)),IF(N(G16)>=MAX(1,N(E16)),"Conferido","Conferido até aqui"),"A conferir"))) -> Conferido | S16: =IF(R16="A conferir",(Config!$B$8-L16)*1000+N(F16)/1000+ROW()/100000,0) -> 0 | T16: =IF(R16="A conferir",N(N16),0) -> 0 | U16: =IF(L16="",0,L16) -> 46211 | V16: =IF(L16="",0,MAX(1,N(E16))) -> 1 | W16: =IF(K16="",0,K16) -> 125.84
A17: 46181 | B17: Wagner Santos | C17: ECG | D17: Cartão de crédito | F17: 130 | G17: 1 | H17: =IF(D17="","",IFERROR(INDEX(Config!$B$12:$B$15,MATCH(IF(AND(D17="Cartão de crédito",N(E17)>1),"Cartão de crédito parcelado",D17),Config!$A$12:$A$15,0)),0)+IF(AND(Config!$B$17="Sim",LEFT(D17,17)="Cartão de crédito"),Config!$B$18*IFERROR(INDEX(Config!$C$12:$C$15,MATCH(IF(AND(D17="Cartão de crédito",N(E17)>1),"Cartão de crédito parcelado",D17),Config!$A$12:$A$15,0)),0)/30*MAX(1,N(E17)),0)) -> 0.032 | I17: =IF(OR(D17="",F17=""),"",ROUND(F17*H17,2)) -> 4.16 | J17: =IF(I17="","",F17-I17) -> 125.84 | K17: =IF(J17="","",J17/MAX(1,N(E17))) -> 125.84 | L17: =IF(OR(D17="",A17=""),"",A17+IF(AND(Config!$B$17="Sim",LEFT(D17,17)="Cartão de crédito"),1,IFERROR(INDEX(Config!$C$12:$C$15,MATCH(IF(AND(D17="Cartão de crédito",N(E17)>1),"Cartão de crédito parcelado",D17),Config!$A$12:$A$15,0)),0))) -> 46211 | M17: =IF(L17="","",IF(AND(Config!$B$17="Sim",LEFT(D17,17)="Cartão de crédito"),L17,L17+30*(MAX(1,N(E17))-1))) -> 46211 | N17: =IF(OR(L17="",K17=""),"",K17*MIN(MAX(1,N(E17)),MAX(0,INT((Config!$B$8-L17)/30)+1))) -> 125.84 | O17: =IF(J17="","",J17-N(N17)) -> 0 | P17: =IF(A17="","",MONTH(A17)) -> 6 | Q17: =IF(A17="","",YEAR(A17)) -> 2026 | R17: =IF(L17="","",IF(L17>Config!$B$8,"A cair",IF(N(G17)>=MIN(MAX(1,N(E17)),MAX(0,INT((Config!$B$8-L17)/30)+1)),IF(N(G17)>=MAX(1,N(E17)),"Conferido","Conferido até aqui"),"A conferir"))) -> Conferido | S17: =IF(R17="A conferir",(Config!$B$8-L17)*1000+N(F17)/1000+ROW()/100000,0) -> 0 | T17: =IF(R17="A conferir",N(N17),0) -> 0 | U17: =IF(L17="",0,L17) -> 46211 | V17: =IF(L17="",0,MAX(1,N(E17))) -> 1 | W17: =IF(K17="",0,K17) -> 125.84
A18: 46182 | B18: Regina Macedo | C18: Consulta | D18: Cartão de crédito | F18: 380 | G18: 1 | H18: =IF(D18="","",IFERROR(INDEX(Config!$B$12:$B$15,MATCH(IF(AND(D18="Cartão de crédito",N(E18)>1),"Cartão de crédito parcelado",D18),Config!$A$12:$A$15,0)),0)+IF(AND(Config!$B$17="Sim",LEFT(D18,17)="Cartão de crédito"),Config!$B$18*IFERROR(INDEX(Config!$C$12:$C$15,MATCH(IF(AND(D18="Cartão de crédito",N(E18)>1),"Cartão de crédito parcelado",D18),Config!$A$12:$A$15,0)),0)/30*MAX(1,N(E18)),0)) -> 0.032 | I18: =IF(OR(D18="",F18=""),"",ROUND(F18*H18,2)) -> 12.16 | J18: =IF(I18="","",F18-I18) -> 367.84 | K18: =IF(J18="","",J18/MAX(1,N(E18))) -> 367.84 | L18: =IF(OR(D18="",A18=""),"",A18+IF(AND(Config!$B$17="Sim",LEFT(D18,17)="Cartão de crédito"),1,IFERROR(INDEX(Config!$C$12:$C$15,MATCH(IF(AND(D18="Cartão de crédito",N(E18)>1),"Cartão de crédito parcelado",D18),Config!$A$12:$A$15,0)),0))) -> 46212 | M18: =IF(L18="","",IF(AND(Config!$B$17="Sim",LEFT(D18,17)="Cartão de crédito"),L18,L18+30*(MAX(1,N(E18))-1))) -> 46212 | N18: =IF(OR(L18="",K18=""),"",K18*MIN(MAX(1,N(E18)),MAX(0,INT((Config!$B$8-L18)/30)+1))) -> 367.84 | O18: =IF(J18="","",J18-N(N18)) -> 0 | P18: =IF(A18="","",MONTH(A18)) -> 6 | Q18: =IF(A18="","",YEAR(A18)) -> 2026 | R18: =IF(L18="","",IF(L18>Config!$B$8,"A cair",IF(N(G18)>=MIN(MAX(1,N(E18)),MAX(0,INT((Config!$B$8-L18)/30)+1)),IF(N(G18)>=MAX(1,N(E18)),"Conferido","Conferido até aqui"),"A conferir"))) -> Conferido | S18: =IF(R18="A conferir",(Config!$B$8-L18)*1000+N(F18)/1000+ROW()/100000,0) -> 0 | T18: =IF(R18="A conferir",N(N18),0) -> 0 | U18: =IF(L18="",0,L18) -> 46212 | V18: =IF(L18="",0,MAX(1,N(E18))) -> 1 | W18: =IF(K18="",0,K18) -> 367.84
A19: 46182 | B19: Cláudia Santos | C19: Consulta | D19: Cartão de crédito | E19: 2 | F19: 380 | G19: 2 | H19: =IF(D19="","",IFERROR(INDEX(Config!$B$12:$B$15,MATCH(IF(AND(D19="Cartão de crédito",N(E19)>1),"Cartão de crédito parcelado",D19),Config!$A$12:$A$15,0)),0)+IF(AND(Config!$B$17="Sim",LEFT(D19,17)="Cartão de crédito"),Config!$B$18*IFERROR(INDEX(Config!$C$12:$C$15,MATCH(IF(AND(D19="Cartão de crédito",N(E19)>1),"Cartão de crédito parcelado",D19),Config!$A$12:$A$15,0)),0)/30*MAX(1,N(E19)),0)) -> 0.039 | I19: =IF(OR(D19="",F19=""),"",ROUND(F19*H19,2)) -> 14.82 | J19: =IF(I19="","",F19-I19) -> 365.18 | K19: =IF(J19="","",J19/MAX(1,N(E19))) -> 182.59 | L19: =IF(OR(D19="",A19=""),"",A19+IF(AND(Config!$B$17="Sim",LEFT(D19,17)="Cartão de crédito"),1,IFERROR(INDEX(Config!$C$12:$C$15,MATCH(IF(AND(D19="Cartão de crédito",N(E19)>1),"Cartão de crédito parcelado",D19),Config!$A$12:$A$15,0)),0))) -> 46212 | M19: =IF(L19="","",IF(AND(Config!$B$17="Sim",LEFT(D19,17)="Cartão de crédito"),L19,L19+30*(MAX(1,N(E19))-1))) -> 46242 | N19: =IF(OR(L19="",K19=""),"",K19*MIN(MAX(1,N(E19)),MAX(0,INT((Config!$B$8-L19)/30)+1))) -> 365.18 | O19: =IF(J19="","",J19-N(N19)) -> 0 | P19: =IF(A19="","",MONTH(A19)) -> 6 | Q19: =IF(A19="","",YEAR(A19)) -> 2026 | R19: =IF(L19="","",IF(L19>Config!$B$8,"A cair",IF(N(G19)>=MIN(MAX(1,N(E19)),MAX(0,INT((Config!$B$8-L19)/30)+1)),IF(N(G19)>=MAX(1,N(E19)),"Conferido","Conferido até aqui"),"A conferir"))) -> Conferido | S19: =IF(R19="A conferir",(Config!$B$8-L19)*1000+N(F19)/1000+ROW()/100000,0) -> 0 | T19: =IF(R19="A conferir",N(N19),0) -> 0 | U19: =IF(L19="",0,L19) -> 46212 | V19: =IF(L19="",0,MAX(1,N(E19))) -> 2 | W19: =IF(K19="",0,K19) -> 182.59
A20: 46182 | B20: Camila Dias | C20: Avaliação endócrina | D20: Pix | F20: 400 | G20: 1 | H20: =IF(D20="","",IFERROR(INDEX(Config!$B$12:$B$15,MATCH(IF(AND(D20="Cartão de crédito",N(E20)>1),"Cartão de crédito parcelado",D20),Config!$A$12:$A$15,0)),0)+IF(AND(Config!$B$17="Sim",LEFT(D20,17)="Cartão de crédito"),Config!$B$18*IFERROR(INDEX(Config!$C$12:$C$15,MATCH(IF(AND(D20="Cartão de crédito",N(E20)>1),"Cartão de crédito parcelado",D20),Config!$A$12:$A$15,0)),0)/30*MAX(1,N(E20)),0)) -> 0 | I20: =IF(OR(D20="",F20=""),"",ROUND(F20*H20,2)) -> 0 | J20: =IF(I20="","",F20-I20) -> 400 | K20: =IF(J20="","",J20/MAX(1,N(E20))) -> 400 | L20: =IF(OR(D20="",A20=""),"",A20+IF(AND(Config!$B$17="Sim",LEFT(D20,17)="Cartão de crédito"),1,IFERROR(INDEX(Config!$C$12:$C$15,MATCH(IF(AND(D20="Cartão de crédito",N(E20)>1),"Cartão de crédito parcelado",D20),Config!$A$12:$A$15,0)),0))) -> 46182 | M20: =IF(L20="","",IF(AND(Config!$B$17="Sim",LEFT(D20,17)="Cartão de crédito"),L20,L20+30*(MAX(1,N(E20))-1))) -> 46182 | N20: =IF(OR(L20="",K20=""),"",K20*MIN(MAX(1,N(E20)),MAX(0,INT((Config!$B$8-L20)/30)+1))) -> 400 | O20: =IF(J20="","",J20-N(N20)) -> 0 | P20: =IF(A20="","",MONTH(A20)) -> 6 | Q20: =IF(A20="","",YEAR(A20)) -> 2026 | R20: =IF(L20="","",IF(L20>Config!$B$8,"A cair",IF(N(G20)>=MIN(MAX(1,N(E20)),MAX(0,INT((Config!$B$8-L20)/30)+1)),IF(N(G20)>=MAX(1,N(E20)),"Conferido","Conferido até aqui"),"A conferir"))) -> Conferido | S20: =IF(R20="A conferir",(Config!$B$8-L20)*1000+N(F20)/1000+ROW()/100000,0) -> 0 | T20: =IF(R20="A conferir",N(N20),0) -> 0 | U20: =IF(L20="",0,L20) -> 46182 | V20: =IF(L20="",0,MAX(1,N(E20))) -> 1 | W20: =IF(K20="",0,K20) -> 400
A21: 46182 | B21: Mariana Gomes | C21: Avaliação endócrina | D21: Cartão de crédito | E21: 2 | F21: 400 | G21: 2 | H21: =IF(D21="","",IFERROR(INDEX(Config!$B$12:$B$15,MATCH(IF(AND(D21="Cartão de crédito",N(E21)>1),"Cartão de crédito parcelado",D21),Config!$A$12:$A$15,0)),0)+IF(AND(Config!$B$17="Sim",LEFT(D21,17)="Cartão de crédito"),Config!$B$18*IFERROR(INDEX(Config!$C$12:$C$15,MATCH(IF(AND(D21="Cartão de crédito",N(E21)>1),"Cartão de crédito parcelado",D21),Config!$A$12:$A$15,0)),0)/30*MAX(1,N(E21)),0)) -> 0.039 | I21: =IF(OR(D21="",F21=""),"",ROUND(F21*H21,2)) -> 15.6 | J21: =IF(I21="","",F21-I21) -> 384.4 | K21: =IF(J21="","",J21/MAX(1,N(E21))) -> 192.2 | L21: =IF(OR(D21="",A21=""),"",A21+IF(AND(Config!$B$17="Sim",LEFT(D21,17)="Cartão de crédito"),1,IFERROR(INDEX(Config!$C$12:$C$15,MATCH(IF(AND(D21="Cartão de crédito",N(E21)>1),"Cartão de crédito parcelado",D21),Config!$A$12:$A$15,0)),0))) -> 46212 | M21: =IF(L21="","",IF(AND(Config!$B$17="Sim",LEFT(D21,17)="Cartão de crédito"),L21,L21+30*(MAX(1,N(E21))-1))) -> 46242 | N21: =IF(OR(L21="",K21=""),"",K21*MIN(MAX(1,N(E21)),MAX(0,INT((Config!$B$8-L21)/30)+1))) -> 384.4 | O21: =IF(J21="","",J21-N(N21)) -> 0 | P21: =IF(A21="","",MONTH(A21)) -> 6 | Q21: =IF(A21="","",YEAR(A21)) -> 2026 | R21: =IF(L21="","",IF(L21>Config!$B$8,"A cair",IF(N(G21)>=MIN(MAX(1,N(E21)),MAX(0,INT((Config!$B$8-L21)/30)+1)),IF(N(G21)>=MAX(1,N(E21)),"Conferido","Conferido até aqui"),"A conferir"))) -> Conferido | S21: =IF(R21="A conferir",(Config!$B$8-L21)*1000+N(F21)/1000+ROW()/100000,0) -> 0 | T21: =IF(R21="A conferir",N(N21),0) -> 0 | U21: =IF(L21="",0,L21) -> 46212 | V21: =IF(L21="",0,MAX(1,N(E21))) -> 2 | W21: =IF(K21="",0,K21) -> 192.2
A22: 46182 | B22: Cláudia Melo | C22: Avaliação endócrina | D22: Cartão de crédito | F22: 400 | G22: 1 | H22: =IF(D22="","",IFERROR(INDEX(Config!$B$12:$B$15,MATCH(IF(AND(D22="Cartão de crédito",N(E22)>1),"Cartão de crédito parcelado",D22),Config!$A$12:$A$15,0)),0)+IF(AND(Config!$B$17="Sim",LEFT(D22,17)="Cartão de crédito"),Config!$B$18*IFERROR(INDEX(Config!$C$12:$C$15,MATCH(IF(AND(D22="Cartão de crédito",N(E22)>1),"Cartão de crédito parcelado",D22),Config!$A$12:$A$15,0)),0)/30*MAX(1,N(E22)),0)) -> 0.032 | I22: =IF(OR(D22="",F22=""),"",ROUND(F22*H22,2)) -> 12.8 | J22: =IF(I22="","",F22-I22) -> 387.2 | K22: =IF(J22="","",J22/MAX(1,N(E22))) -> 387.2 | L22: =IF(OR(D22="",A22=""),"",A22+IF(AND(Config!$B$17="Sim",LEFT(D22,17)="Cartão de crédito"),1,IFERROR(INDEX(Config!$C$12:$C$15,MATCH(IF(AND(D22="Cartão de crédito",N(E22)>1),"Cartão de crédito parcelado",D22),Config!$A$12:$A$15,0)),0))) -> 46212 | M22: =IF(L22="","",IF(AND(Config!$B$17="Sim",LEFT(D22,17)="Cartão de crédito"),L22,L22+30*(MAX(1,N(E22))-1))) -> 46212 | N22: =IF(OR(L22="",K22=""),"",K22*MIN(MAX(1,N(E22)),MAX(0,INT((Config!$B$8-L22)/30)+1))) -> 387.2 | O22: =IF(J22="","",J22-N(N22)) -> 0 | P22: =IF(A22="","",MONTH(A22)) -> 6 | Q22: =IF(A22="","",YEAR(A22)) -> 2026 | R22: =IF(L22="","",IF(L22>Config!$B$8,"A cair",IF(N(G22)>=MIN(MAX(1,N(E22)),MAX(0,INT((Config!$B$8-L22)/30)+1)),IF(N(G22)>=MAX(1,N(E22)),"Conferido","Conferido até aqui"),"A conferir"))) -> Conferido | S22: =IF(R22="A conferir",(Config!$B$8-L22)*1000+N(F22)/1000+ROW()/100000,0) -> 0 | T22: =IF(R22="A conferir",N(N22),0) -> 0 | U22: =IF(L22="",0,L22) -> 46212 | V22: =IF(L22="",0,MAX(1,N(E22))) -> 1 | W22: =IF(K22="",0,K22) -> 387.2
A23: 46182 | B23: Natália Martins | C23: Consulta | D23: Pix | F23: 380 | G23: 1 | H23: =IF(D23="","",IFERROR(INDEX(Config!$B$12:$B$15,MATCH(IF(AND(D23="Cartão de crédito",N(E23)>1),"Cartão de crédito parcelado",D23),Config!$A$12:$A$15,0)),0)+IF(AND(Config!$B$17="Sim",LEFT(D23,17)="Cartão de crédito"),Config!$B$18*IFERROR(INDEX(Config!$C$12:$C$15,MATCH(IF(AND(D23="Cartão de crédito",N(E23)>1),"Cartão de crédito parcelado",D23),Config!$A$12:$A$15,0)),0)/30*MAX(1,N(E23)),0)) -> 0 | I23: =IF(OR(D23="",F23=""),"",ROUND(F23*H23,2)) -> 0 | J23: =IF(I23="","",F23-I23) -> 380 | K23: =IF(J23="","",J23/MAX(1,N(E23))) -> 380 | L23: =IF(OR(D23="",A23=""),"",A23+IF(AND(Config!$B$17="Sim",LEFT(D23,17)="Cartão de crédito"),1,IFERROR(INDEX(Config!$C$12:$C$15,MATCH(IF(AND(D23="Cartão de crédito",N(E23)>1),"Cartão de crédito parcelado",D23),Config!$A$12:$A$15,0)),0))) -> 46182 | M23: =IF(L23="","",IF(AND(Config!$B$17="Sim",LEFT(D23,17)="Cartão de crédito"),L23,L23+30*(MAX(1,N(E23))-1))) -> 46182 | N23: =IF(OR(L23="",K23=""),"",K23*MIN(MAX(1,N(E23)),MAX(0,INT((Config!$B$8-L23)/30)+1))) -> 380 | O23: =IF(J23="","",J23-N(N23)) -> 0 | P23: =IF(A23="","",MONTH(A23)) -> 6 | Q23: =IF(A23="","",YEAR(A23)) -> 2026 | R23: =IF(L23="","",IF(L23>Config!$B$8,"A cair",IF(N(G23)>=MIN(MAX(1,N(E23)),MAX(0,INT((Config!$B$8-L23)/30)+1)),IF(N(G23)>=MAX(1,N(E23)),"Conferido","Conferido até aqui"),"A conferir"))) -> Conferido | S23: =IF(R23="A conferir",(Config!$B$8-L23)*1000+N(F23)/1000+ROW()/100000,0) -> 0 | T23: =IF(R23="A conferir",N(N23),0) -> 0 | U23: =IF(L23="",0,L23) -> 46182 | V23: =IF(L23="",0,MAX(1,N(E23))) -> 1 | W23: =IF(K23="",0,K23) -> 380
A24: 46182 | B24: Marcelo Santos | C24: ECG | D24: Pix | F24: 130 | G24: 1 | H24: =IF(D24="","",IFERROR(INDEX(Config!$B$12:$B$15,MATCH(IF(AND(D24="Cartão de crédito",N(E24)>1),"Cartão de crédito parcelado",D24),Config!$A$12:$A$15,0)),0)+IF(AND(Config!$B$17="Sim",LEFT(D24,17)="Cartão de crédito"),Config!$B$18*IFERROR(INDEX(Config!$C$12:$C$15,MATCH(IF(AND(D24="Cartão de crédito",N(E24)>1),"Cartão de crédito parcelado",D24),Config!$A$12:$A$15,0)),0)/30*MAX(1,N(E24)),0)) -> 0 | I24: =IF(OR(D24="",F24=""),"",ROUND(F24*H24,2)) -> 0 | J24: =IF(I24="","",F24-I24) -> 130 | K24: =IF(J24="","",J24/MAX(1,N(E24))) -> 130 | L24: =IF(OR(D24="",A24=""),"",A24+IF(AND(Config!$B$17="Sim",LEFT(D24,17)="Cartão de crédito"),1,IFERROR(INDEX(Config!$C$12:$C$15,MATCH(IF(AND(D24="Cartão de crédito",N(E24)>1),"Cartão de crédito parcelado",D24),Config!$A$12:$A$15,0)),0))) -> 46182 | M24: =IF(L24="","",IF(AND(Config!$B$17="Sim",LEFT(D24,17)="Cartão de crédito"),L24,L24+30*(MAX(1,N(E24))-1))) -> 46182 | N24: =IF(OR(L24="",K24=""),"",K24*MIN(MAX(1,N(E24)),MAX(0,INT((Config!$B$8-L24)/30)+1))) -> 130 | O24: =IF(J24="","",J24-N(N24)) -> 0 | P24: =IF(A24="","",MONTH(A24)) -> 6 | Q24: =IF(A24="","",YEAR(A24)) -> 2026 | R24: =IF(L24="","",IF(L24>Config!$B$8,"A cair",IF(N(G24)>=MIN(MAX(1,N(E24)),MAX(0,INT((Config!$B$8-L24)/30)+1)),IF(N(G24)>=MAX(1,N(E24)),"Conferido","Conferido até aqui"),"A conferir"))) -> Conferido | S24: =IF(R24="A conferir",(Config!$B$8-L24)*1000+N(F24)/1000+ROW()/100000,0) -> 0 | T24: =IF(R24="A conferir",N(N24),0) -> 0 | U24: =IF(L24="",0,L24) -> 46182 | V24: =IF(L24="",0,MAX(1,N(E24))) -> 1 | W24: =IF(K24="",0,K24) -> 130
A25: 46183 | B25: Lucas Lopes | C25: Consulta | D25: Pix | F25: 380 | G25: 1 | H25: =IF(D25="","",IFERROR(INDEX(Config!$B$12:$B$15,MATCH(IF(AND(D25="Cartão de crédito",N(E25)>1),"Cartão de crédito parcelado",D25),Config!$A$12:$A$15,0)),0)+IF(AND(Config!$B$17="Sim",LEFT(D25,17)="Cartão de crédito"),Config!$B$18*IFERROR(INDEX(Config!$C$12:$C$15,MATCH(IF(AND(D25="Cartão de crédito",N(E25)>1),"Cartão de crédito parcelado",D25),Config!$A$12:$A$15,0)),0)/30*MAX(1,N(E25)),0)) -> 0 | I25: =IF(OR(D25="",F25=""),"",ROUND(F25*H25,2)) -> 0 | J25: =IF(I25="","",F25-I25) -> 380 | K25: =IF(J25="","",J25/MAX(1,N(E25))) -> 380 | L25: =IF(OR(D25="",A25=""),"",A25+IF(AND(Config!$B$17="Sim",LEFT(D25,17)="Cartão de crédito"),1,IFERROR(INDEX(Config!$C$12:$C$15,MATCH(IF(AND(D25="Cartão de crédito",N(E25)>1),"Cartão de crédito parcelado",D25),Config!$A$12:$A$15,0)),0))) -> 46183 | M25: =IF(L25="","",IF(AND(Config!$B$17="Sim",LEFT(D25,17)="Cartão de crédito"),L25,L25+30*(MAX(1,N(E25))-1))) -> 46183 | N25: =IF(OR(L25="",K25=""),"",K25*MIN(MAX(1,N(E25)),MAX(0,INT((Config!$B$8-L25)/30)+1))) -> 380 | O25: =IF(J25="","",J25-N(N25)) -> 0 | P25: =IF(A25="","",MONTH(A25)) -> 6 | Q25: =IF(A25="","",YEAR(A25)) -> 2026 | R25: =IF(L25="","",IF(L25>Config!$B$8,"A cair",IF(N(G25)>=MIN(MAX(1,N(E25)),MAX(0,INT((Config!$B$8-L25)/30)+1)),IF(N(G25)>=MAX(1,N(E25)),"Conferido","Conferido até aqui"),"A conferir"))) -> Conferido | S25: =IF(R25="A conferir",(Config!$B$8-L25)*1000+N(F25)/1000+ROW()/100000,0) -> 0 | T25: =IF(R25="A conferir",N(N25),0) -> 0 | U25: =IF(L25="",0,L25) -> 46183 | V25: =IF(L25="",0,MAX(1,N(E25))) -> 1 | W25: =IF(K25="",0,K25) -> 380
A26: 46184 | B26: Elaine Cardoso | C26: Consulta | D26: Pix | F26: 380 | G26: 1 | H26: =IF(D26="","",IFERROR(INDEX(Config!$B$12:$B$15,MATCH(IF(AND(D26="Cartão de crédito",N(E26)>1),"Cartão de crédito parcelado",D26),Config!$A$12:$A$15,0)),0)+IF(AND(Config!$B$17="Sim",LEFT(D26,17)="Cartão de crédito"),Config!$B$18*IFERROR(INDEX(Config!$C$12:$C$15,MATCH(IF(AND(D26="Cartão de crédito",N(E26)>1),"Cartão de crédito parcelado",D26),Config!$A$12:$A$15,0)),0)/30*MAX(1,N(E26)),0)) -> 0 | I26: =IF(OR(D26="",F26=""),"",ROUND(F26*H26,2)) -> 0 | J26: =IF(I26="","",F26-I26) -> 380 | K26: =IF(J26="","",J26/MAX(1,N(E26))) -> 380 | L26: =IF(OR(D26="",A26=""),"",A26+IF(AND(Config!$B$17="Sim",LEFT(D26,17)="Cartão de crédito"),1,IFERROR(INDEX(Config!$C$12:$C$15,MATCH(IF(AND(D26="Cartão de crédito",N(E26)>1),"Cartão de crédito parcelado",D26),Config!$A$12:$A$15,0)),0))) -> 46184 | M26: =IF(L26="","",IF(AND(Config!$B$17="Sim",LEFT(D26,17)="Cartão de crédito"),L26,L26+30*(MAX(1,N(E26))-1))) -> 46184 | N26: =IF(OR(L26="",K26=""),"",K26*MIN(MAX(1,N(E26)),MAX(0,INT((Config!$B$8-L26)/30)+1))) -> 380 | O26: =IF(J26="","",J26-N(N26)) -> 0 | P26: =IF(A26="","",MONTH(A26)) -> 6 | Q26: =IF(A26="","",YEAR(A26)) -> 2026 | R26: =IF(L26="","",IF(L26>Config!$B$8,"A cair",IF(N(G26)>=MIN(MAX(1,N(E26)),MAX(0,INT((Config!$B$8-L26)/30)+1)),IF(N(G26)>=MAX(1,N(E26)),"Conferido","Conferido até aqui"),"A conferir"))) -> Conferido | S26: =IF(R26="A conferir",(Config!$B$8-L26)*1000+N(F26)/1000+ROW()/100000,0) -> 0 | T26: =IF(R26="A conferir",N(N26),0) -> 0 | U26: =IF(L26="",0,L26) -> 46184 | V26: =IF(L26="",0,MAX(1,N(E26))) -> 1 | W26: =IF(K26="",0,K26) -> 380
A27: 46184 | B27: Wagner Santos | C27: Consulta | D27: Pix | F27: 380 | G27: 1 | H27: =IF(D27="","",IFERROR(INDEX(Config!$B$12:$B$15,MATCH(IF(AND(D27="Cartão de crédito",N(E27)>1),"Cartão de crédito parcelado",D27),Config!$A$12:$A$15,0)),0)+IF(AND(Config!$B$17="Sim",LEFT(D27,17)="Cartão de crédito"),Config!$B$18*IFERROR(INDEX(Config!$C$12:$C$15,MATCH(IF(AND(D27="Cartão de crédito",N(E27)>1),"Cartão de crédito parcelado",D27),Config!$A$12:$A$15,0)),0)/30*MAX(1,N(E27)),0)) -> 0 | I27: =IF(OR(D27="",F27=""),"",ROUND(F27*H27,2)) -> 0 | J27: =IF(I27="","",F27-I27) -> 380 | K27: =IF(J27="","",J27/MAX(1,N(E27))) -> 380 | L27: =IF(OR(D27="",A27=""),"",A27+IF(AND(Config!$B$17="Sim",LEFT(D27,17)="Cartão de crédito"),1,IFERROR(INDEX(Config!$C$12:$C$15,MATCH(IF(AND(D27="Cartão de crédito",N(E27)>1),"Cartão de crédito parcelado",D27),Config!$A$12:$A$15,0)),0))) -> 46184 | M27: =IF(L27="","",IF(AND(Config!$B$17="Sim",LEFT(D27,17)="Cartão de crédito"),L27,L27+30*(MAX(1,N(E27))-1))) -> 46184 | N27: =IF(OR(L27="",K27=""),"",K27*MIN(MAX(1,N(E27)),MAX(0,INT((Config!$B$8-L27)/30)+1))) -> 380 | O27: =IF(J27="","",J27-N(N27)) -> 0 | P27: =IF(A27="","",MONTH(A27)) -> 6 | Q27: =IF(A27="","",YEAR(A27)) -> 2026 | R27: =IF(L27="","",IF(L27>Config!$B$8,"A cair",IF(N(G27)>=MIN(MAX(1,N(E27)),MAX(0,INT((Config!$B$8-L27)/30)+1)),IF(N(G27)>=MAX(1,N(E27)),"Conferido","Conferido até aqui"),"A conferir"))) -> Conferido | S27: =IF(R27="A conferir",(Config!$B$8-L27)*1000+N(F27)/1000+ROW()/100000,0) -> 0 | T27: =IF(R27="A conferir",N(N27),0) -> 0 | U27: =IF(L27="",0,L27) -> 46184 | V27: =IF(L27="",0,MAX(1,N(E27))) -> 1 | W27: =IF(K27="",0,K27) -> 380
A28: 46184 | B28: Roberta Lima | C28: Avaliação endócrina | D28: Pix | F28: 400 | G28: 1 | H28: =IF(D28="","",IFERROR(INDEX(Config!$B$12:$B$15,MATCH(IF(AND(D28="Cartão de crédito",N(E28)>1),"Cartão de crédito parcelado",D28),Config!$A$12:$A$15,0)),0)+IF(AND(Config!$B$17="Sim",LEFT(D28,17)="Cartão de crédito"),Config!$B$18*IFERROR(INDEX(Config!$C$12:$C$15,MATCH(IF(AND(D28="Cartão de crédito",N(E28)>1),"Cartão de crédito parcelado",D28),Config!$A$12:$A$15,0)),0)/30*MAX(1,N(E28)),0)) -> 0 | I28: =IF(OR(D28="",F28=""),"",ROUND(F28*H28,2)) -> 0 | J28: =IF(I28="","",F28-I28) -> 400 | K28: =IF(J28="","",J28/MAX(1,N(E28))) -> 400 | L28: =IF(OR(D28="",A28=""),"",A28+IF(AND(Config!$B$17="Sim",LEFT(D28,17)="Cartão de crédito"),1,IFERROR(INDEX(Config!$C$12:$C$15,MATCH(IF(AND(D28="Cartão de crédito",N(E28)>1),"Cartão de crédito parcelado",D28),Config!$A$12:$A$15,0)),0))) -> 46184 | M28: =IF(L28="","",IF(AND(Config!$B$17="Sim",LEFT(D28,17)="Cartão de crédito"),L28,L28+30*(MAX(1,N(E28))-1))) -> 46184 | N28: =IF(OR(L28="",K28=""),"",K28*MIN(MAX(1,N(E28)),MAX(0,INT((Config!$B$8-L28)/30)+1))) -> 400 | O28: =IF(J28="","",J28-N(N28)) -> 0 | P28: =IF(A28="","",MONTH(A28)) -> 6 | Q28: =IF(A28="","",YEAR(A28)) -> 2026 | R28: =IF(L28="","",IF(L28>Config!$B$8,"A cair",IF(N(G28)>=MIN(MAX(1,N(E28)),MAX(0,INT((Config!$B$8-L28)/30)+1)),IF(N(G28)>=MAX(1,N(E28)),"Conferido","Conferido até aqui"),"A conferir"))) -> Conferido | S28: =IF(R28="A conferir",(Config!$B$8-L28)*1000+N(F28)/1000+ROW()/100000,0) -> 0 | T28: =IF(R28="A conferir",N(N28),0) -> 0 | U28: =IF(L28="",0,L28) -> 46184 | V28: =IF(L28="",0,MAX(1,N(E28))) -> 1 | W28: =IF(K28="",0,K28) -> 400
A29: 46184 | B29: Thiago Melo | C29: Avaliação endócrina | D29: Pix | F29: 400 | G29: 1 | H29: =IF(D29="","",IFERROR(INDEX(Config!$B$12:$B$15,MATCH(IF(AND(D29="Cartão de crédito",N(E29)>1),"Cartão de crédito parcelado",D29),Config!$A$12:$A$15,0)),0)+IF(AND(Config!$B$17="Sim",LEFT(D29,17)="Cartão de crédito"),Config!$B$18*IFERROR(INDEX(Config!$C$12:$C$15,MATCH(IF(AND(D29="Cartão de crédito",N(E29)>1),"Cartão de crédito parcelado",D29),Config!$A$12:$A$15,0)),0)/30*MAX(1,N(E29)),0)) -> 0 | I29: =IF(OR(D29="",F29=""),"",ROUND(F29*H29,2)) -> 0 | J29: =IF(I29="","",F29-I29) -> 400 | K29: =IF(J29="","",J29/MAX(1,N(E29))) -> 400 | L29: =IF(OR(D29="",A29=""),"",A29+IF(AND(Config!$B$17="Sim",LEFT(D29,17)="Cartão de crédito"),1,IFERROR(INDEX(Config!$C$12:$C$15,MATCH(IF(AND(D29="Cartão de crédito",N(E29)>1),"Cartão de crédito parcelado",D29),Config!$A$12:$A$15,0)),0))) -> 46184 | M29: =IF(L29="","",IF(AND(Config!$B$17="Sim",LEFT(D29,17)="Cartão de crédito"),L29,L29+30*(MAX(1,N(E29))-1))) -> 46184 | N29: =IF(OR(L29="",K29=""),"",K29*MIN(MAX(1,N(E29)),MAX(0,INT((Config!$B$8-L29)/30)+1))) -> 400 | O29: =IF(J29="","",J29-N(N29)) -> 0 | P29: =IF(A29="","",MONTH(A29)) -> 6 | Q29: =IF(A29="","",YEAR(A29)) -> 2026 | R29: =IF(L29="","",IF(L29>Config!$B$8,"A cair",IF(N(G29)>=MIN(MAX(1,N(E29)),MAX(0,INT((Config!$B$8-L29)/30)+1)),IF(N(G29)>=MAX(1,N(E29)),"Conferido","Conferido até aqui"),"A conferir"))) -> Conferido | S29: =IF(R29="A conferir",(Config!$B$8-L29)*1000+N(F29)/1000+ROW()/100000,0) -> 0 | T29: =IF(R29="A conferir",N(N29),0) -> 0 | U29: =IF(L29="",0,L29) -> 46184 | V29: =IF(L29="",0,MAX(1,N(E29))) -> 1 | W29: =IF(K29="",0,K29) -> 400
A30: 46185 | B30: Gisele Xavier | C30: ECG | D30: Cartão de crédito | F30: 130 | G30: 1 | H30: =IF(D30="","",IFERROR(INDEX(Config!$B$12:$B$15,MATCH(IF(AND(D30="Cartão de crédito",N(E30)>1),"Cartão de crédito parcelado",D30),Config!$A$12:$A$15,0)),0)+IF(AND(Config!$B$17="Sim",LEFT(D30,17)="Cartão de crédito"),Config!$B$18*IFERROR(INDEX(Config!$C$12:$C$15,MATCH(IF(AND(D30="Cartão de crédito",N(E30)>1),"Cartão de crédito parcelado",D30),Config!$A$12:$A$15,0)),0)/30*MAX(1,N(E30)),0)) -> 0.032 | I30: =IF(OR(D30="",F30=""),"",ROUND(F30*H30,2)) -> 4.16 | J30: =IF(I30="","",F30-I30) -> 125.84 | K30: =IF(J30="","",J30/MAX(1,N(E30))) -> 125.84 | L30: =IF(OR(D30="",A30=""),"",A30+IF(AND(Config!$B$17="Sim",LEFT(D30,17)="Cartão de crédito"),1,IFERROR(INDEX(Config!$C$12:$C$15,MATCH(IF(AND(D30="Cartão de crédito",N(E30)>1),"Cartão de crédito parcelado",D30),Config!$A$12:$A$15,0)),0))) -> 46215 | M30: =IF(L30="","",IF(AND(Config!$B$17="Sim",LEFT(D30,17)="Cartão de crédito"),L30,L30+30*(MAX(1,N(E30))-1))) -> 46215 | N30: =IF(OR(L30="",K30=""),"",K30*MIN(MAX(1,N(E30)),MAX(0,INT((Config!$B$8-L30)/30)+1))) -> 125.84 | O30: =IF(J30="","",J30-N(N30)) -> 0 | P30: =IF(A30="","",MONTH(A30)) -> 6 | Q30: =IF(A30="","",YEAR(A30)) -> 2026 | R30: =IF(L30="","",IF(L30>Config!$B$8,"A cair",IF(N(G30)>=MIN(MAX(1,N(E30)),MAX(0,INT((Config!$B$8-L30)/30)+1)),IF(N(G30)>=MAX(1,N(E30)),"Conferido","Conferido até aqui"),"A conferir"))) -> Conferido | S30: =IF(R30="A conferir",(Config!$B$8-L30)*1000+N(F30)/1000+ROW()/100000,0) -> 0 | T30: =IF(R30="A conferir",N(N30),0) -> 0 | U30: =IF(L30="",0,L30) -> 46215 | V30: =IF(L30="",0,MAX(1,N(E30))) -> 1 | W30: =IF(K30="",0,K30) -> 125.84
A31: 46185 | B31: Mariana Nascimento | C31: Teste ergométrico | D31: Cartão de crédito | E31: 2 | F31: 450 | G31: 2 | H31: =IF(D31="","",IFERROR(INDEX(Config!$B$12:$B$15,MATCH(IF(AND(D31="Cartão de crédito",N(E31)>1),"Cartão de crédito parcelado",D31),Config!$A$12:$A$15,0)),0)+IF(AND(Config!$B$17="Sim",LEFT(D31,17)="Cartão de crédito"),Config!$B$18*IFERROR(INDEX(Config!$C$12:$C$15,MATCH(IF(AND(D31="Cartão de crédito",N(E31)>1),"Cartão de crédito parcelado",D31),Config!$A$12:$A$15,0)),0)/30*MAX(1,N(E31)),0)) -> 0.039 | I31: =IF(OR(D31="",F31=""),"",ROUND(F31*H31,2)) -> 17.55 | J31: =IF(I31="","",F31-I31) -> 432.45 | K31: =IF(J31="","",J31/MAX(1,N(E31))) -> 216.225 | L31: =IF(OR(D31="",A31=""),"",A31+IF(AND(Config!$B$17="Sim",LEFT(D31,17)="Cartão de crédito"),1,IFERROR(INDEX(Config!$C$12:$C$15,MATCH(IF(AND(D31="Cartão de crédito",N(E31)>1),"Cartão de crédito parcelado",D31),Config!$A$12:$A$15,0)),0))) -> 46215 | M31: =IF(L31="","",IF(AND(Config!$B$17="Sim",LEFT(D31,17)="Cartão de crédito"),L31,L31+30*(MAX(1,N(E31))-1))) -> 46245 | N31: =IF(OR(L31="",K31=""),"",K31*MIN(MAX(1,N(E31)),MAX(0,INT((Config!$B$8-L31)/30)+1))) -> 432.45 | O31: =IF(J31="","",J31-N(N31)) -> 0 | P31: =IF(A31="","",MONTH(A31)) -> 6 | Q31: =IF(A31="","",YEAR(A31)) -> 2026 | R31: =IF(L31="","",IF(L31>Config!$B$8,"A cair",IF(N(G31)>=MIN(MAX(1,N(E31)),MAX(0,INT((Config!$B$8-L31)/30)+1)),IF(N(G31)>=MAX(1,N(E31)),"Conferido","Conferido até aqui"),"A conferir"))) -> Conferido | S31: =IF(R31="A conferir",(Config!$B$8-L31)*1000+N(F31)/1000+ROW()/100000,0) -> 0 | T31: =IF(R31="A conferir",N(N31),0) -> 0 | U31: =IF(L31="",0,L31) -> 46215 | V31: =IF(L31="",0,MAX(1,N(E31))) -> 2 | W31: =IF(K31="",0,K31) -> 216.225
A32: 46188 | B32: Mariana Nascimento | C32: Consulta | D32: Pix | F32: 380 | G32: 1 | H32: =IF(D32="","",IFERROR(INDEX(Config!$B$12:$B$15,MATCH(IF(AND(D32="Cartão de crédito",N(E32)>1),"Cartão de crédito parcelado",D32),Config!$A$12:$A$15,0)),0)+IF(AND(Config!$B$17="Sim",LEFT(D32,17)="Cartão de crédito"),Config!$B$18*IFERROR(INDEX(Config!$C$12:$C$15,MATCH(IF(AND(D32="Cartão de crédito",N(E32)>1),"Cartão de crédito parcelado",D32),Config!$A$12:$A$15,0)),0)/30*MAX(1,N(E32)),0)) -> 0 | I32: =IF(OR(D32="",F32=""),"",ROUND(F32*H32,2)) -> 0 | J32: =IF(I32="","",F32-I32) -> 380 | K32: =IF(J32="","",J32/MAX(1,N(E32))) -> 380 | L32: =IF(OR(D32="",A32=""),"",A32+IF(AND(Config!$B$17="Sim",LEFT(D32,17)="Cartão de crédito"),1,IFERROR(INDEX(Config!$C$12:$C$15,MATCH(IF(AND(D32="Cartão de crédito",N(E32)>1),"Cartão de crédito parcelado",D32),Config!$A$12:$A$15,0)),0))) -> 46188 | M32: =IF(L32="","",IF(AND(Config!$B$17="Sim",LEFT(D32,17)="Cartão de crédito"),L32,L32+30*(MAX(1,N(E32))-1))) -> 46188 | N32: =IF(OR(L32="",K32=""),"",K32*MIN(MAX(1,N(E32)),MAX(0,INT((Config!$B$8-L32)/30)+1))) -> 380 | O32: =IF(J32="","",J32-N(N32)) -> 0 | P32: =IF(A32="","",MONTH(A32)) -> 6 | Q32: =IF(A32="","",YEAR(A32)) -> 2026 | R32: =IF(L32="","",IF(L32>Config!$B$8,"A cair",IF(N(G32)>=MIN(MAX(1,N(E32)),MAX(0,INT((Config!$B$8-L32)/30)+1)),IF(N(G32)>=MAX(1,N(E32)),"Conferido","Conferido até aqui"),"A conferir"))) -> Conferido | S32: =IF(R32="A conferir",(Config!$B$8-L32)*1000+N(F32)/1000+ROW()/100000,0) -> 0 | T32: =IF(R32="A conferir",N(N32),0) -> 0 | U32: =IF(L32="",0,L32) -> 46188 | V32: =IF(L32="",0,MAX(1,N(E32))) -> 1 | W32: =IF(K32="",0,K32) -> 380
A33: 46188 | B33: Ana Costa | C33: Consulta | D33: Cartão de débito | F33: 380 | G33: 1 | H33: =IF(D33="","",IFERROR(INDEX(Config!$B$12:$B$15,MATCH(IF(AND(D33="Cartão de crédito",N(E33)>1),"Cartão de crédito parcelado",D33),Config!$A$12:$A$15,0)),0)+IF(AND(Config!$B$17="Sim",LEFT(D33,17)="Cartão de crédito"),Config!$B$18*IFERROR(INDEX(Config!$C$12:$C$15,MATCH(IF(AND(D33="Cartão de crédito",N(E33)>1),"Cartão de crédito parcelado",D33),Config!$A$12:$A$15,0)),0)/30*MAX(1,N(E33)),0)) -> 0.015 | I33: =IF(OR(D33="",F33=""),"",ROUND(F33*H33,2)) -> 5.7 | J33: =IF(I33="","",F33-I33) -> 374.3 | K33: =IF(J33="","",J33/MAX(1,N(E33))) -> 374.3 | L33: =IF(OR(D33="",A33=""),"",A33+IF(AND(Config!$B$17="Sim",LEFT(D33,17)="Cartão de crédito"),1,IFERROR(INDEX(Config!$C$12:$C$15,MATCH(IF(AND(D33="Cartão de crédito",N(E33)>1),"Cartão de crédito parcelado",D33),Config!$A$12:$A$15,0)),0))) -> 46189 | M33: =IF(L33="","",IF(AND(Config!$B$17="Sim",LEFT(D33,17)="Cartão de crédito"),L33,L33+30*(MAX(1,N(E33))-1))) -> 46189 | N33: =IF(OR(L33="",K33=""),"",K33*MIN(MAX(1,N(E33)),MAX(0,INT((Config!$B$8-L33)/30)+1))) -> 374.3 | O33: =IF(J33="","",J33-N(N33)) -> 0 | P33: =IF(A33="","",MONTH(A33)) -> 6 | Q33: =IF(A33="","",YEAR(A33)) -> 2026 | R33: =IF(L33="","",IF(L33>Config!$B$8,"A cair",IF(N(G33)>=MIN(MAX(1,N(E33)),MAX(0,INT((Config!$B$8-L33)/30)+1)),IF(N(G33)>=MAX(1,N(E33)),"Conferido","Conferido até aqui"),"A conferir"))) -> Conferido | S33: =IF(R33="A conferir",(Config!$B$8-L33)*1000+N(F33)/1000+ROW()/100000,0) -> 0 | T33: =IF(R33="A conferir",N(N33),0) -> 0 | U33: =IF(L33="",0,L33) -> 46189 | V33: =IF(L33="",0,MAX(1,N(E33))) -> 1 | W33: =IF(K33="",0,K33) -> 374.3
A34: 46188 | B34: Leandro Oliveira | C34: Consulta | D34: Cartão de crédito | F34: 380 | G34: 1 | H34: =IF(D34="","",IFERROR(INDEX(Config!$B$12:$B$15,MATCH(IF(AND(D34="Cartão de crédito",N(E34)>1),"Cartão de crédito parcelado",D34),Config!$A$12:$A$15,0)),0)+IF(AND(Config!$B$17="Sim",LEFT(D34,17)="Cartão de crédito"),Config!$B$18*IFERROR(INDEX(Config!$C$12:$C$15,MATCH(IF(AND(D34="Cartão de crédito",N(E34)>1),"Cartão de crédito parcelado",D34),Config!$A$12:$A$15,0)),0)/30*MAX(1,N(E34)),0)) -> 0.032 | I34: =IF(OR(D34="",F34=""),"",ROUND(F34*H34,2)) -> 12.16 | J34: =IF(I34="","",F34-I34) -> 367.84 | K34: =IF(J34="","",J34/MAX(1,N(E34))) -> 367.84 | L34: =IF(OR(D34="",A34=""),"",A34+IF(AND(Config!$B$17="Sim",LEFT(D34,17)="Cartão de crédito"),1,IFERROR(INDEX(Config!$C$12:$C$15,MATCH(IF(AND(D34="Cartão de crédito",N(E34)>1),"Cartão de crédito parcelado",D34),Config!$A$12:$A$15,0)),0))) -> 46218 | M34: =IF(L34="","",IF(AND(Config!$B$17="Sim",LEFT(D34,17)="Cartão de crédito"),L34,L34+30*(MAX(1,N(E34))-1))) -> 46218 | N34: =IF(OR(L34="",K34=""),"",K34*MIN(MAX(1,N(E34)),MAX(0,INT((Config!$B$8-L34)/30)+1))) -> 367.84 | O34: =IF(J34="","",J34-N(N34)) -> 0 | P34: =IF(A34="","",MONTH(A34)) -> 6 | Q34: =IF(A34="","",YEAR(A34)) -> 2026 | R34: =IF(L34="","",IF(L34>Config!$B$8,"A cair",IF(N(G34)>=MIN(MAX(1,N(E34)),MAX(0,INT((Config!$B$8-L34)/30)+1)),IF(N(G34)>=MAX(1,N(E34)),"Conferido","Conferido até aqui"),"A conferir"))) -> Conferido | S34: =IF(R34="A conferir",(Config!$B$8-L34)*1000+N(F34)/1000+ROW()/100000,0) -> 0 | T34: =IF(R34="A conferir",N(N34),0) -> 0 | U34: =IF(L34="",0,L34) -> 46218 | V34: =IF(L34="",0,MAX(1,N(E34))) -> 1 | W34: =IF(K34="",0,K34) -> 367.84
A35: 46188 | B35: Lucas Cardoso | C35: Consulta | D35: Cartão de crédito | F35: 380 | G35: 1 | H35: =IF(D35="","",IFERROR(INDEX(Config!$B$12:$B$15,MATCH(IF(AND(D35="Cartão de crédito",N(E35)>1),"Cartão de crédito parcelado",D35),Config!$A$12:$A$15,0)),0)+IF(AND(Config!$B$17="Sim",LEFT(D35,17)="Cartão de crédito"),Config!$B$18*IFERROR(INDEX(Config!$C$12:$C$15,MATCH(IF(AND(D35="Cartão de crédito",N(E35)>1),"Cartão de crédito parcelado",D35),Config!$A$12:$A$15,0)),0)/30*MAX(1,N(E35)),0)) -> 0.032 | I35: =IF(OR(D35="",F35=""),"",ROUND(F35*H35,2)) -> 12.16 | J35: =IF(I35="","",F35-I35) -> 367.84 | K35: =IF(J35="","",J35/MAX(1,N(E35))) -> 367.84 | L35: =IF(OR(D35="",A35=""),"",A35+IF(AND(Config!$B$17="Sim",LEFT(D35,17)="Cartão de crédito"),1,IFERROR(INDEX(Config!$C$12:$C$15,MATCH(IF(AND(D35="Cartão de crédito",N(E35)>1),"Cartão de crédito parcelado",D35),Config!$A$12:$A$15,0)),0))) -> 46218 | M35: =IF(L35="","",IF(AND(Config!$B$17="Sim",LEFT(D35,17)="Cartão de crédito"),L35,L35+30*(MAX(1,N(E35))-1))) -> 46218 | N35: =IF(OR(L35="",K35=""),"",K35*MIN(MAX(1,N(E35)),MAX(0,INT((Config!$B$8-L35)/30)+1))) -> 367.84 | O35: =IF(J35="","",J35-N(N35)) -> 0 | P35: =IF(A35="","",MONTH(A35)) -> 6 | Q35: =IF(A35="","",YEAR(A35)) -> 2026 | R35: =IF(L35="","",IF(L35>Config!$B$8,"A cair",IF(N(G35)>=MIN(MAX(1,N(E35)),MAX(0,INT((Config!$B$8-L35)/30)+1)),IF(N(G35)>=MAX(1,N(E35)),"Conferido","Conferido até aqui"),"A conferir"))) -> Conferido | S35: =IF(R35="A conferir",(Config!$B$8-L35)*1000+N(F35)/1000+ROW()/100000,0) -> 0 | T35: =IF(R35="A conferir",N(N35),0) -> 0 | U35: =IF(L35="",0,L35) -> 46218 | V35: =IF(L35="",0,MAX(1,N(E35))) -> 1 | W35: =IF(K35="",0,K35) -> 367.84
A36: 46189 | B36: Mônica Martins | C36: Consulta | D36: Pix | F36: 380 | G36: 1 | H36: =IF(D36="","",IFERROR(INDEX(Config!$B$12:$B$15,MATCH(IF(AND(D36="Cartão de crédito",N(E36)>1),"Cartão de crédito parcelado",D36),Config!$A$12:$A$15,0)),0)+IF(AND(Config!$B$17="Sim",LEFT(D36,17)="Cartão de crédito"),Config!$B$18*IFERROR(INDEX(Config!$C$12:$C$15,MATCH(IF(AND(D36="Cartão de crédito",N(E36)>1),"Cartão de crédito parcelado",D36),Config!$A$12:$A$15,0)),0)/30*MAX(1,N(E36)),0)) -> 0 | I36: =IF(OR(D36="",F36=""),"",ROUND(F36*H36,2)) -> 0 | J36: =IF(I36="","",F36-I36) -> 380 | K36: =IF(J36="","",J36/MAX(1,N(E36))) -> 380 | L36: =IF(OR(D36="",A36=""),"",A36+IF(AND(Config!$B$17="Sim",LEFT(D36,17)="Cartão de crédito"),1,IFERROR(INDEX(Config!$C$12:$C$15,MATCH(IF(AND(D36="Cartão de crédito",N(E36)>1),"Cartão de crédito parcelado",D36),Config!$A$12:$A$15,0)),0))) -> 46189 | M36: =IF(L36="","",IF(AND(Config!$B$17="Sim",LEFT(D36,17)="Cartão de crédito"),L36,L36+30*(MAX(1,N(E36))-1))) -> 46189 | N36: =IF(OR(L36="",K36=""),"",K36*MIN(MAX(1,N(E36)),MAX(0,INT((Config!$B$8-L36)/30)+1))) -> 380 | O36: =IF(J36="","",J36-N(N36)) -> 0 | P36: =IF(A36="","",MONTH(A36)) -> 6 | Q36: =IF(A36="","",YEAR(A36)) -> 2026 | R36: =IF(L36="","",IF(L36>Config!$B$8,"A cair",IF(N(G36)>=MIN(MAX(1,N(E36)),MAX(0,INT((Config!$B$8-L36)/30)+1)),IF(N(G36)>=MAX(1,N(E36)),"Conferido","Conferido até aqui"),"A conferir"))) -> Conferido | S36: =IF(R36="A conferir",(Config!$B$8-L36)*1000+N(F36)/1000+ROW()/100000,0) -> 0 | T36: =IF(R36="A conferir",N(N36),0) -> 0 | U36: =IF(L36="",0,L36) -> 46189 | V36: =IF(L36="",0,MAX(1,N(E36))) -> 1 | W36: =IF(K36="",0,K36) -> 380
A37: 46189 | B37: Fábio Correia | C37: ECG | D37: Cartão de crédito | F37: 130 | G37: 1 | H37: =IF(D37="","",IFERROR(INDEX(Config!$B$12:$B$15,MATCH(IF(AND(D37="Cartão de crédito",N(E37)>1),"Cartão de crédito parcelado",D37),Config!$A$12:$A$15,0)),0)+IF(AND(Config!$B$17="Sim",LEFT(D37,17)="Cartão de crédito"),Config!$B$18*IFERROR(INDEX(Config!$C$12:$C$15,MATCH(IF(AND(D37="Cartão de crédito",N(E37)>1),"Cartão de crédito parcelado",D37),Config!$A$12:$A$15,0)),0)/30*MAX(1,N(E37)),0)) -> 0.032 | I37: =IF(OR(D37="",F37=""),"",ROUND(F37*H37,2)) -> 4.16 | J37: =IF(I37="","",F37-I37) -> 125.84 | K37: =IF(J37="","",J37/MAX(1,N(E37))) -> 125.84 | L37: =IF(OR(D37="",A37=""),"",A37+IF(AND(Config!$B$17="Sim",LEFT(D37,17)="Cartão de crédito"),1,IFERROR(INDEX(Config!$C$12:$C$15,MATCH(IF(AND(D37="Cartão de crédito",N(E37)>1),"Cartão de crédito parcelado",D37),Config!$A$12:$A$15,0)),0))) -> 46219 | M37: =IF(L37="","",IF(AND(Config!$B$17="Sim",LEFT(D37,17)="Cartão de crédito"),L37,L37+30*(MAX(1,N(E37))-1))) -> 46219 | N37: =IF(OR(L37="",K37=""),"",K37*MIN(MAX(1,N(E37)),MAX(0,INT((Config!$B$8-L37)/30)+1))) -> 125.84 | O37: =IF(J37="","",J37-N(N37)) -> 0 | P37: =IF(A37="","",MONTH(A37)) -> 6 | Q37: =IF(A37="","",YEAR(A37)) -> 2026 | R37: =IF(L37="","",IF(L37>Config!$B$8,"A cair",IF(N(G37)>=MIN(MAX(1,N(E37)),MAX(0,INT((Config!$B$8-L37)/30)+1)),IF(N(G37)>=MAX(1,N(E37)),"Conferido","Conferido até aqui"),"A conferir"))) -> Conferido | S37: =IF(R37="A conferir",(Config!$B$8-L37)*1000+N(F37)/1000+ROW()/100000,0) -> 0 | T37: =IF(R37="A conferir",N(N37),0) -> 0 | U37: =IF(L37="",0,L37) -> 46219 | V37: =IF(L37="",0,MAX(1,N(E37))) -> 1 | W37: =IF(K37="",0,K37) -> 125.84
A38: 46189 | B38: Gabriel Reis | C38: Avaliação endócrina | D38: Pix | F38: 400 | G38: 1 | H38: =IF(D38="","",IFERROR(INDEX(Config!$B$12:$B$15,MATCH(IF(AND(D38="Cartão de crédito",N(E38)>1),"Cartão de crédito parcelado",D38),Config!$A$12:$A$15,0)),0)+IF(AND(Config!$B$17="Sim",LEFT(D38,17)="Cartão de crédito"),Config!$B$18*IFERROR(INDEX(Config!$C$12:$C$15,MATCH(IF(AND(D38="Cartão de crédito",N(E38)>1),"Cartão de crédito parcelado",D38),Config!$A$12:$A$15,0)),0)/30*MAX(1,N(E38)),0)) -> 0 | I38: =IF(OR(D38="",F38=""),"",ROUND(F38*H38,2)) -> 0 | J38: =IF(I38="","",F38-I38) -> 400 | K38: =IF(J38="","",J38/MAX(1,N(E38))) -> 400 | L38: =IF(OR(D38="",A38=""),"",A38+IF(AND(Config!$B$17="Sim",LEFT(D38,17)="Cartão de crédito"),1,IFERROR(INDEX(Config!$C$12:$C$15,MATCH(IF(AND(D38="Cartão de crédito",N(E38)>1),"Cartão de crédito parcelado",D38),Config!$A$12:$A$15,0)),0))) -> 46189 | M38: =IF(L38="","",IF(AND(Config!$B$17="Sim",LEFT(D38,17)="Cartão de crédito"),L38,L38+30*(MAX(1,N(E38))-1))) -> 46189 | N38: =IF(OR(L38="",K38=""),"",K38*MIN(MAX(1,N(E38)),MAX(0,INT((Config!$B$8-L38)/30)+1))) -> 400 | O38: =IF(J38="","",J38-N(N38)) -> 0 | P38: =IF(A38="","",MONTH(A38)) -> 6 | Q38: =IF(A38="","",YEAR(A38)) -> 2026 | R38: =IF(L38="","",IF(L38>Config!$B$8,"A cair",IF(N(G38)>=MIN(MAX(1,N(E38)),MAX(0,INT((Config!$B$8-L38)/30)+1)),IF(N(G38)>=MAX(1,N(E38)),"Conferido","Conferido até aqui"),"A conferir"))) -> Conferido | S38: =IF(R38="A conferir",(Config!$B$8-L38)*1000+N(F38)/1000+ROW()/100000,0) -> 0 | T38: =IF(R38="A conferir",N(N38),0) -> 0 | U38: =IF(L38="",0,L38) -> 46189 | V38: =IF(L38="",0,MAX(1,N(E38))) -> 1 | W38: =IF(K38="",0,K38) -> 400
A39: 46189 | B39: Márcia Duarte | C39: Avaliação endócrina | D39: Pix | F39: 400 | G39: 1 | H39: =IF(D39="","",IFERROR(INDEX(Config!$B$12:$B$15,MATCH(IF(AND(D39="Cartão de crédito",N(E39)>1),"Cartão de crédito parcelado",D39),Config!$A$12:$A$15,0)),0)+IF(AND(Config!$B$17="Sim",LEFT(D39,17)="Cartão de crédito"),Config!$B$18*IFERROR(INDEX(Config!$C$12:$C$15,MATCH(IF(AND(D39="Cartão de crédito",N(E39)>1),"Cartão de crédito parcelado",D39),Config!$A$12:$A$15,0)),0)/30*MAX(1,N(E39)),0)) -> 0 | I39: =IF(OR(D39="",F39=""),"",ROUND(F39*H39,2)) -> 0 | J39: =IF(I39="","",F39-I39) -> 400 | K39: =IF(J39="","",J39/MAX(1,N(E39))) -> 400 | L39: =IF(OR(D39="",A39=""),"",A39+IF(AND(Config!$B$17="Sim",LEFT(D39,17)="Cartão de crédito"),1,IFERROR(INDEX(Config!$C$12:$C$15,MATCH(IF(AND(D39="Cartão de crédito",N(E39)>1),"Cartão de crédito parcelado",D39),Config!$A$12:$A$15,0)),0))) -> 46189 | M39: =IF(L39="","",IF(AND(Config!$B$17="Sim",LEFT(D39,17)="Cartão de crédito"),L39,L39+30*(MAX(1,N(E39))-1))) -> 46189 | N39: =IF(OR(L39="",K39=""),"",K39*MIN(MAX(1,N(E39)),MAX(0,INT((Config!$B$8-L39)/30)+1))) -> 400 | O39: =IF(J39="","",J39-N(N39)) -> 0 | P39: =IF(A39="","",MONTH(A39)) -> 6 | Q39: =IF(A39="","",YEAR(A39)) -> 2026 | R39: =IF(L39="","",IF(L39>Config!$B$8,"A cair",IF(N(G39)>=MIN(MAX(1,N(E39)),MAX(0,INT((Config!$B$8-L39)/30)+1)),IF(N(G39)>=MAX(1,N(E39)),"Conferido","Conferido até aqui"),"A conferir"))) -> Conferido | S39: =IF(R39="A conferir",(Config!$B$8-L39)*1000+N(F39)/1000+ROW()/100000,0) -> 0 | T39: =IF(R39="A conferir",N(N39),0) -> 0 | U39: =IF(L39="",0,L39) -> 46189 | V39: =IF(L39="",0,MAX(1,N(E39))) -> 1 | W39: =IF(K39="",0,K39) -> 400
A40: 46190 | B40: Cláudia Santos | C40: Consulta | D40: Pix | F40: 380 | G40: 1 | H40: =IF(D40="","",IFERROR(INDEX(Config!$B$12:$B$15,MATCH(IF(AND(D40="Cartão de crédito",N(E40)>1),"Cartão de crédito parcelado",D40),Config!$A$12:$A$15,0)),0)+IF(AND(Config!$B$17="Sim",LEFT(D40,17)="Cartão de crédito"),Config!$B$18*IFERROR(INDEX(Config!$C$12:$C$15,MATCH(IF(AND(D40="Cartão de crédito",N(E40)>1),"Cartão de crédito parcelado",D40),Config!$A$12:$A$15,0)),0)/30*MAX(1,N(E40)),0)) -> 0 | I40: =IF(OR(D40="",F40=""),"",ROUND(F40*H40,2)) -> 0 | J40: =IF(I40="","",F40-I40) -> 380 | K40: =IF(J40="","",J40/MAX(1,N(E40))) -> 380 | L40: =IF(OR(D40="",A40=""),"",A40+IF(AND(Config!$B$17="Sim",LEFT(D40,17)="Cartão de crédito"),1,IFERROR(INDEX(Config!$C$12:$C$15,MATCH(IF(AND(D40="Cartão de crédito",N(E40)>1),"Cartão de crédito parcelado",D40),Config!$A$12:$A$15,0)),0))) -> 46190 | M40: =IF(L40="","",IF(AND(Config!$B$17="Sim",LEFT(D40,17)="Cartão de crédito"),L40,L40+30*(MAX(1,N(E40))-1))) -> 46190 | N40: =IF(OR(L40="",K40=""),"",K40*MIN(MAX(1,N(E40)),MAX(0,INT((Config!$B$8-L40)/30)+1))) -> 380 | O40: =IF(J40="","",J40-N(N40)) -> 0 | P40: =IF(A40="","",MONTH(A40)) -> 6 | Q40: =IF(A40="","",YEAR(A40)) -> 2026 | R40: =IF(L40="","",IF(L40>Config!$B$8,"A cair",IF(N(G40)>=MIN(MAX(1,N(E40)),MAX(0,INT((Config!$B$8-L40)/30)+1)),IF(N(G40)>=MAX(1,N(E40)),"Conferido","Conferido até aqui"),"A conferir"))) -> Conferido | S40: =IF(R40="A conferir",(Config!$B$8-L40)*1000+N(F40)/1000+ROW()/100000,0) -> 0 | T40: =IF(R40="A conferir",N(N40),0) -> 0 | U40: =IF(L40="",0,L40) -> 46190 | V40: =IF(L40="",0,MAX(1,N(E40))) -> 1 | W40: =IF(K40="",0,K40) -> 380
A41: 46190 | B41: Helena Moreira | C41: Consulta | D41: Cartão de débito | F41: 380 | G41: 1 | H41: =IF(D41="","",IFERROR(INDEX(Config!$B$12:$B$15,MATCH(IF(AND(D41="Cartão de crédito",N(E41)>1),"Cartão de crédito parcelado",D41),Config!$A$12:$A$15,0)),0)+IF(AND(Config!$B$17="Sim",LEFT(D41,17)="Cartão de crédito"),Config!$B$18*IFERROR(INDEX(Config!$C$12:$C$15,MATCH(IF(AND(D41="Cartão de crédito",N(E41)>1),"Cartão de crédito parcelado",D41),Config!$A$12:$A$15,0)),0)/30*MAX(1,N(E41)),0)) -> 0.015 | I41: =IF(OR(D41="",F41=""),"",ROUND(F41*H41,2)) -> 5.7 | J41: =IF(I41="","",F41-I41) -> 374.3 | K41: =IF(J41="","",J41/MAX(1,N(E41))) -> 374.3 | L41: =IF(OR(D41="",A41=""),"",A41+IF(AND(Config!$B$17="Sim",LEFT(D41,17)="Cartão de crédito"),1,IFERROR(INDEX(Config!$C$12:$C$15,MATCH(IF(AND(D41="Cartão de crédito",N(E41)>1),"Cartão de crédito parcelado",D41),Config!$A$12:$A$15,0)),0))) -> 46191 | M41: =IF(L41="","",IF(AND(Config!$B$17="Sim",LEFT(D41,17)="Cartão de crédito"),L41,L41+30*(MAX(1,N(E41))-1))) -> 46191 | N41: =IF(OR(L41="",K41=""),"",K41*MIN(MAX(1,N(E41)),MAX(0,INT((Config!$B$8-L41)/30)+1))) -> 374.3 | O41: =IF(J41="","",J41-N(N41)) -> 0 | P41: =IF(A41="","",MONTH(A41)) -> 6 | Q41: =IF(A41="","",YEAR(A41)) -> 2026 | R41: =IF(L41="","",IF(L41>Config!$B$8,"A cair",IF(N(G41)>=MIN(MAX(1,N(E41)),MAX(0,INT((Config!$B$8-L41)/30)+1)),IF(N(G41)>=MAX(1,N(E41)),"Conferido","Conferido até aqui"),"A conferir"))) -> Conferido | S41: =IF(R41="A conferir",(Config!$B$8-L41)*1000+N(F41)/1000+ROW()/100000,0) -> 0 | T41: =IF(R41="A conferir",N(N41),0) -> 0 | U41: =IF(L41="",0,L41) -> 46191 | V41: =IF(L41="",0,MAX(1,N(E41))) -> 1 | W41: =IF(K41="",0,K41) -> 374.3
A42: 46190 | B42: Regina Macedo | C42: Consulta | D42: Pix | F42: 380 | G42: 1 | H42: =IF(D42="","",IFERROR(INDEX(Config!$B$12:$B$15,MATCH(IF(AND(D42="Cartão de crédito",N(E42)>1),"Cartão de crédito parcelado",D42),Config!$A$12:$A$15,0)),0)+IF(AND(Config!$B$17="Sim",LEFT(D42,17)="Cartão de crédito"),Config!$B$18*IFERROR(INDEX(Config!$C$12:$C$15,MATCH(IF(AND(D42="Cartão de crédito",N(E42)>1),"Cartão de crédito parcelado",D42),Config!$A$12:$A$15,0)),0)/30*MAX(1,N(E42)),0)) -> 0 | I42: =IF(OR(D42="",F42=""),"",ROUND(F42*H42,2)) -> 0 | J42: =IF(I42="","",F42-I42) -> 380 | K42: =IF(J42="","",J42/MAX(1,N(E42))) -> 380 | L42: =IF(OR(D42="",A42=""),"",A42+IF(AND(Config!$B$17="Sim",LEFT(D42,17)="Cartão de crédito"),1,IFERROR(INDEX(Config!$C$12:$C$15,MATCH(IF(AND(D42="Cartão de crédito",N(E42)>1),"Cartão de crédito parcelado",D42),Config!$A$12:$A$15,0)),0))) -> 46190 | M42: =IF(L42="","",IF(AND(Config!$B$17="Sim",LEFT(D42,17)="Cartão de crédito"),L42,L42+30*(MAX(1,N(E42))-1))) -> 46190 | N42: =IF(OR(L42="",K42=""),"",K42*MIN(MAX(1,N(E42)),MAX(0,INT((Config!$B$8-L42)/30)+1))) -> 380 | O42: =IF(J42="","",J42-N(N42)) -> 0 | P42: =IF(A42="","",MONTH(A42)) -> 6 | Q42: =IF(A42="","",YEAR(A42)) -> 2026 | R42: =IF(L42="","",IF(L42>Config!$B$8,"A cair",IF(N(G42)>=MIN(MAX(1,N(E42)),MAX(0,INT((Config!$B$8-L42)/30)+1)),IF(N(G42)>=MAX(1,N(E42)),"Conferido","Conferido até aqui"),"A conferir"))) -> Conferido | S42: =IF(R42="A conferir",(Config!$B$8-L42)*1000+N(F42)/1000+ROW()/100000,0) -> 0 | T42: =IF(R42="A conferir",N(N42),0) -> 0 | U42: =IF(L42="",0,L42) -> 46190 | V42: =IF(L42="",0,MAX(1,N(E42))) -> 1 | W42: =IF(K42="",0,K42) -> 380
A43: 46191 | B43: Roberta Lima | C43: Avaliação endócrina | D43: Pix | F43: 400 | G43: 1 | H43: =IF(D43="","",IFERROR(INDEX(Config!$B$12:$B$15,MATCH(IF(AND(D43="Cartão de crédito",N(E43)>1),"Cartão de crédito parcelado",D43),Config!$A$12:$A$15,0)),0)+IF(AND(Config!$B$17="Sim",LEFT(D43,17)="Cartão de crédito"),Config!$B$18*IFERROR(INDEX(Config!$C$12:$C$15,MATCH(IF(AND(D43="Cartão de crédito",N(E43)>1),"Cartão de crédito parcelado",D43),Config!$A$12:$A$15,0)),0)/30*MAX(1,N(E43)),0)) -> 0 | I43: =IF(OR(D43="",F43=""),"",ROUND(F43*H43,2)) -> 0 | J43: =IF(I43="","",F43-I43) -> 400 | K43: =IF(J43="","",J43/MAX(1,N(E43))) -> 400 | L43: =IF(OR(D43="",A43=""),"",A43+IF(AND(Config!$B$17="Sim",LEFT(D43,17)="Cartão de crédito"),1,IFERROR(INDEX(Config!$C$12:$C$15,MATCH(IF(AND(D43="Cartão de crédito",N(E43)>1),"Cartão de crédito parcelado",D43),Config!$A$12:$A$15,0)),0))) -> 46191 | M43: =IF(L43="","",IF(AND(Config!$B$17="Sim",LEFT(D43,17)="Cartão de crédito"),L43,L43+30*(MAX(1,N(E43))-1))) -> 46191 | N43: =IF(OR(L43="",K43=""),"",K43*MIN(MAX(1,N(E43)),MAX(0,INT((Config!$B$8-L43)/30)+1))) -> 400 | O43: =IF(J43="","",J43-N(N43)) -> 0 | P43: =IF(A43="","",MONTH(A43)) -> 6 | Q43: =IF(A43="","",YEAR(A43)) -> 2026 | R43: =IF(L43="","",IF(L43>Config!$B$8,"A cair",IF(N(G43)>=MIN(MAX(1,N(E43)),MAX(0,INT((Config!$B$8-L43)/30)+1)),IF(N(G43)>=MAX(1,N(E43)),"Conferido","Conferido até aqui"),"A conferir"))) -> Conferido | S43: =IF(R43="A conferir",(Config!$B$8-L43)*1000+N(F43)/1000+ROW()/100000,0) -> 0 | T43: =IF(R43="A conferir",N(N43),0) -> 0 | U43: =IF(L43="",0,L43) -> 46191 | V43: =IF(L43="",0,MAX(1,N(E43))) -> 1 | W43: =IF(K43="",0,K43) -> 400
... A52: 46195 | B52: Cláudia Costa | C52: Teste ergométrico | D52: Pix | F52: 450 | G52: 1 | H52: =IF(D52="","",IFERROR(INDEX(Config!$B$12:$B$15,MATCH(IF(AND(D52="Cartão de crédito",N(E52)>1),"Cartão de crédito parcelado",D52),Config!$A$12:$A$15,0)),0)+IF(AND(Config!$B$17="Sim",LEFT(D52,17)="Cartão de crédito"),Config!$B$18*IFERROR(INDEX(Config!$C$12:$C$15,MATCH(IF(AND(D52="Cartão de crédito",N(E52)>1),"Cartão de crédito parcelado",D52),Config!$A$12:$A$15,0)),0)/30*MAX(1,N(E52)),0)) -> 0 | I52: =IF(OR(D52="",F52=""),"",ROUND(F52*H52,2)) -> 0 | J52: =IF(I52="","",F52-I52) -> 450 | K52: =IF(J52="","",J52/MAX(1,N(E52))) -> 450 | L52: =IF(OR(D52="",A52=""),"",A52+IF(AND(Config!$B$17="Sim",LEFT(D52,17)="Cartão de crédito"),1,IFERROR(INDEX(Config!$C$12:$C$15,MATCH(IF(AND(D52="Cartão de crédito",N(E52)>1),"Cartão de crédito parcelado",D52),Config!$A$12:$A$15,0)),0))) -> 46195 | M52: =IF(L52="","",IF(AND(Config!$B$17="Sim",LEFT(D52,17)="Cartão de crédito"),L52,L52+30*(MAX(1,N(E52))-1))) -> 46195 | N52: =IF(OR(L52="",K52=""),"",K52*MIN(MAX(1,N(E52)),MAX(0,INT((Config!$B$8-L52)/30)+1))) -> 450 | O52: =IF(J52="","",J52-N(N52)) -> 0 | P52: =IF(A52="","",MONTH(A52)) -> 6 | Q52: =IF(A52="","",YEAR(A52)) -> 2026 | R52: =IF(L52="","",IF(L52>Config!$B$8,"A cair",IF(N(G52)>=MIN(MAX(1,N(E52)),MAX(0,INT((Config!$B$8-L52)/30)+1)),IF(N(G52)>=MAX(1,N(E52)),"Conferido","Conferido até aqui"),"A conferir"))) -> Conferido | S52: =IF(R52="A conferir",(Config!$B$8-L52)*1000+N(F52)/1000+ROW()/100000,0) -> 0 | T52: =IF(R52="A conferir",N(N52),0) -> 0 | U52: =IF(L52="",0,L52) -> 46195 | V52: =IF(L52="",0,MAX(1,N(E52))) -> 1 | W52: =IF(K52="",0,K52) -> 450
A53: 46196 | B53: Wagner Santos | C53: Consulta | D53: Cartão de crédito | E53: 2 | F53: 380 | G53: 2 | H53: =IF(D53="","",IFERROR(INDEX(Config!$B$12:$B$15,MATCH(IF(AND(D53="Cartão de crédito",N(E53)>1),"Cartão de crédito parcelado",D53),Config!$A$12:$A$15,0)),0)+IF(AND(Config!$B$17="Sim",LEFT(D53,17)="Cartão de crédito"),Config!$B$18*IFERROR(INDEX(Config!$C$12:$C$15,MATCH(IF(AND(D53="Cartão de crédito",N(E53)>1),"Cartão de crédito parcelado",D53),Config!$A$12:$A$15,0)),0)/30*MAX(1,N(E53)),0)) -> 0.039 | I53: =IF(OR(D53="",F53=""),"",ROUND(F53*H53,2)) -> 14.82 | J53: =IF(I53="","",F53-I53) -> 365.18 | K53: =IF(J53="","",J53/MAX(1,N(E53))) -> 182.59 | L53: =IF(OR(D53="",A53=""),"",A53+IF(AND(Config!$B$17="Sim",LEFT(D53,17)="Cartão de crédito"),1,IFERROR(INDEX(Config!$C$12:$C$15,MATCH(IF(AND(D53="Cartão de crédito",N(E53)>1),"Cartão de crédito parcelado",D53),Config!$A$12:$A$15,0)),0))) -> 46226 | M53: =IF(L53="","",IF(AND(Config!$B$17="Sim",LEFT(D53,17)="Cartão de crédito"),L53,L53+30*(MAX(1,N(E53))-1))) -> 46256 | N53: =IF(OR(L53="",K53=""),"",K53*MIN(MAX(1,N(E53)),MAX(0,INT((Config!$B$8-L53)/30)+1))) -> 365.18 | O53: =IF(J53="","",J53-N(N53)) -> 0 | P53: =IF(A53="","",MONTH(A53)) -> 6 | Q53: =IF(A53="","",YEAR(A53)) -> 2026 | R53: =IF(L53="","",IF(L53>Config!$B$8,"A cair",IF(N(G53)>=MIN(MAX(1,N(E53)),MAX(0,INT((Config!$B$8-L53)/30)+1)),IF(N(G53)>=MAX(1,N(E53)),"Conferido","Conferido até aqui"),"A conferir"))) -> Conferido | S53: =IF(R53="A conferir",(Config!$B$8-L53)*1000+N(F53)/1000+ROW()/100000,0) -> 0 | T53: =IF(R53="A conferir",N(N53),0) -> 0 | U53: =IF(L53="",0,L53) -> 46226 | V53: =IF(L53="",0,MAX(1,N(E53))) -> 2 | W53: =IF(K53="",0,K53) -> 182.59
A54: 46196 | B54: Gabriel Reis | C54: Avaliação endócrina | D54: Cartão de crédito | E54: 2 | F54: 400 | G54: 2 | H54: =IF(D54="","",IFERROR(INDEX(Config!$B$12:$B$15,MATCH(IF(AND(D54="Cartão de crédito",N(E54)>1),"Cartão de crédito parcelado",D54),Config!$A$12:$A$15,0)),0)+IF(AND(Config!$B$17="Sim",LEFT(D54,17)="Cartão de crédito"),Config!$B$18*IFERROR(INDEX(Config!$C$12:$C$15,MATCH(IF(AND(D54="Cartão de crédito",N(E54)>1),"Cartão de crédito parcelado",D54),Config!$A$12:$A$15,0)),0)/30*MAX(1,N(E54)),0)) -> 0.039 | I54: =IF(OR(D54="",F54=""),"",ROUND(F54*H54,2)) -> 15.6 | J54: =IF(I54="","",F54-I54) -> 384.4 | K54: =IF(J54="","",J54/MAX(1,N(E54))) -> 192.2 | L54: =IF(OR(D54="",A54=""),"",A54+IF(AND(Config!$B$17="Sim",LEFT(D54,17)="Cartão de crédito"),1,IFERROR(INDEX(Config!$C$12:$C$15,MATCH(IF(AND(D54="Cartão de crédito",N(E54)>1),"Cartão de crédito parcelado",D54),Config!$A$12:$A$15,0)),0))) -> 46226 | M54: =IF(L54="","",IF(AND(Config!$B$17="Sim",LEFT(D54,17)="Cartão de crédito"),L54,L54+30*(MAX(1,N(E54))-1))) -> 46256 | N54: =IF(OR(L54="",K54=""),"",K54*MIN(MAX(1,N(E54)),MAX(0,INT((Config!$B$8-L54)/30)+1))) -> 384.4 | O54: =IF(J54="","",J54-N(N54)) -> 0 | P54: =IF(A54="","",MONTH(A54)) -> 6 | Q54: =IF(A54="","",YEAR(A54)) -> 2026 | R54: =IF(L54="","",IF(L54>Config!$B$8,"A cair",IF(N(G54)>=MIN(MAX(1,N(E54)),MAX(0,INT((Config!$B$8-L54)/30)+1)),IF(N(G54)>=MAX(1,N(E54)),"Conferido","Conferido até aqui"),"A conferir"))) -> Conferido | S54: =IF(R54="A conferir",(Config!$B$8-L54)*1000+N(F54)/1000+ROW()/100000,0) -> 0 | T54: =IF(R54="A conferir",N(N54),0) -> 0 | U54: =IF(L54="",0,L54) -> 46226 | V54: =IF(L54="",0,MAX(1,N(E54))) -> 2 | W54: =IF(K54="",0,K54) -> 192.2
A55: 46196 | B55: Eduardo Lima | C55: Teste ergométrico | D55: Pix | F55: 450 | G55: 1 | H55: =IF(D55="","",IFERROR(INDEX(Config!$B$12:$B$15,MATCH(IF(AND(D55="Cartão de crédito",N(E55)>1),"Cartão de crédito parcelado",D55),Config!$A$12:$A$15,0)),0)+IF(AND(Config!$B$17="Sim",LEFT(D55,17)="Cartão de crédito"),Config!$B$18*IFERROR(INDEX(Config!$C$12:$C$15,MATCH(IF(AND(D55="Cartão de crédito",N(E55)>1),"Cartão de crédito parcelado",D55),Config!$A$12:$A$15,0)),0)/30*MAX(1,N(E55)),0)) -> 0 | I55: =IF(OR(D55="",F55=""),"",ROUND(F55*H55,2)) -> 0 | J55: =IF(I55="","",F55-I55) -> 450 | K55: =IF(J55="","",J55/MAX(1,N(E55))) -> 450 | L55: =IF(OR(D55="",A55=""),"",A55+IF(AND(Config!$B$17="Sim",LEFT(D55,17)="Cartão de crédito"),1,IFERROR(INDEX(Config!$C$12:$C$15,MATCH(IF(AND(D55="Cartão de crédito",N(E55)>1),"Cartão de crédito parcelado",D55),Config!$A$12:$A$15,0)),0))) -> 46196 | M55: =IF(L55="","",IF(AND(Config!$B$17="Sim",LEFT(D55,17)="Cartão de crédito"),L55,L55+30*(MAX(1,N(E55))-1))) -> 46196 | N55: =IF(OR(L55="",K55=""),"",K55*MIN(MAX(1,N(E55)),MAX(0,INT((Config!$B$8-L55)/30)+1))) -> 450 | O55: =IF(J55="","",J55-N(N55)) -> 0 | P55: =IF(A55="","",MONTH(A55)) -> 6 | Q55: =IF(A55="","",YEAR(A55)) -> 2026 | R55: =IF(L55="","",IF(L55>Config!$B$8,"A cair",IF(N(G55)>=MIN(MAX(1,N(E55)),MAX(0,INT((Config!$B$8-L55)/30)+1)),IF(N(G55)>=MAX(1,N(E55)),"Conferido","Conferido até aqui"),"A conferir"))) -> Conferido | S55: =IF(R55="A conferir",(Config!$B$8-L55)*1000+N(F55)/1000+ROW()/100000,0) -> 0 | T55: =IF(R55="A conferir",N(N55),0) -> 0 | U55: =IF(L55="",0,L55) -> 46196 | V55: =IF(L55="",0,MAX(1,N(E55))) -> 1 | W55: =IF(K55="",0,K55) -> 450
A56: 46196 | B56: Rafael Barros | C56: Consulta | D56: Cartão de débito | F56: 380 | G56: 1 | H56: =IF(D56="","",IFERROR(INDEX(Config!$B$12:$B$15,MATCH(IF(AND(D56="Cartão de crédito",N(E56)>1),"Cartão de crédito parcelado",D56),Config!$A$12:$A$15,0)),0)+IF(AND(Config!$B$17="Sim",LEFT(D56,17)="Cartão de crédito"),Config!$B$18*IFERROR(INDEX(Config!$C$12:$C$15,MATCH(IF(AND(D56="Cartão de crédito",N(E56)>1),"Cartão de crédito parcelado",D56),Config!$A$12:$A$15,0)),0)/30*MAX(1,N(E56)),0)) -> 0.015 | I56: =IF(OR(D56="",F56=""),"",ROUND(F56*H56,2)) -> 5.7 | J56: =IF(I56="","",F56-I56) -> 374.3 | K56: =IF(J56="","",J56/MAX(1,N(E56))) -> 374.3 | L56: =IF(OR(D56="",A56=""),"",A56+IF(AND(Config!$B$17="Sim",LEFT(D56,17)="Cartão de crédito"),1,IFERROR(INDEX(Config!$C$12:$C$15,MATCH(IF(AND(D56="Cartão de crédito",N(E56)>1),"Cartão de crédito parcelado",D56),Config!$A$12:$A$15,0)),0))) -> 46197 | M56: =IF(L56="","",IF(AND(Config!$B$17="Sim",LEFT(D56,17)="Cartão de crédito"),L56,L56+30*(MAX(1,N(E56))-1))) -> 46197 | N56: =IF(OR(L56="",K56=""),"",K56*MIN(MAX(1,N(E56)),MAX(0,INT((Config!$B$8-L56)/30)+1))) -> 374.3 | O56: =IF(J56="","",J56-N(N56)) -> 0 | P56: =IF(A56="","",MONTH(A56)) -> 6 | Q56: =IF(A56="","",YEAR(A56)) -> 2026 | R56: =IF(L56="","",IF(L56>Config!$B$8,"A cair",IF(N(G56)>=MIN(MAX(1,N(E56)),MAX(0,INT((Config!$B$8-L56)/30)+1)),IF(N(G56)>=MAX(1,N(E56)),"Conferido","Conferido até aqui"),"A conferir"))) -> Conferido | S56: =IF(R56="A conferir",(Config!$B$8-L56)*1000+N(F56)/1000+ROW()/100000,0) -> 0 | T56: =IF(R56="A conferir",N(N56),0) -> 0 | U56: =IF(L56="",0,L56) -> 46197 | V56: =IF(L56="",0,MAX(1,N(E56))) -> 1 | W56: =IF(K56="",0,K56) -> 374.3
A57: 46196 | B57: Regina Duarte | C57: Holter | D57: Pix | F57: 350 | G57: 1 | H57: =IF(D57="","",IFERROR(INDEX(Config!$B$12:$B$15,MATCH(IF(AND(D57="Cartão de crédito",N(E57)>1),"Cartão de crédito parcelado",D57),Config!$A$12:$A$15,0)),0)+IF(AND(Config!$B$17="Sim",LEFT(D57,17)="Cartão de crédito"),Config!$B$18*IFERROR(INDEX(Config!$C$12:$C$15,MATCH(IF(AND(D57="Cartão de crédito",N(E57)>1),"Cartão de crédito parcelado",D57),Config!$A$12:$A$15,0)),0)/30*MAX(1,N(E57)),0)) -> 0 | I57: =IF(OR(D57="",F57=""),"",ROUND(F57*H57,2)) -> 0 | J57: =IF(I57="","",F57-I57) -> 350 | K57: =IF(J57="","",J57/MAX(1,N(E57))) -> 350 | L57: =IF(OR(D57="",A57=""),"",A57+IF(AND(Config!$B$17="Sim",LEFT(D57,17)="Cartão de crédito"),1,IFERROR(INDEX(Config!$C$12:$C$15,MATCH(IF(AND(D57="Cartão de crédito",N(E57)>1),"Cartão de crédito parcelado",D57),Config!$A$12:$A$15,0)),0))) -> 46196 | M57: =IF(L57="","",IF(AND(Config!$B$17="Sim",LEFT(D57,17)="Cartão de crédito"),L57,L57+30*(MAX(1,N(E57))-1))) -> 46196 | N57: =IF(OR(L57="",K57=""),"",K57*MIN(MAX(1,N(E57)),MAX(0,INT((Config!$B$8-L57)/30)+1))) -> 350 | O57: =IF(J57="","",J57-N(N57)) -> 0 | P57: =IF(A57="","",MONTH(A57)) -> 6 | Q57: =IF(A57="","",YEAR(A57)) -> 2026 | R57: =IF(L57="","",IF(L57>Config!$B$8,"A cair",IF(N(G57)>=MIN(MAX(1,N(E57)),MAX(0,INT((Config!$B$8-L57)/30)+1)),IF(N(G57)>=MAX(1,N(E57)),"Conferido","Conferido até aqui"),"A conferir"))) -> Conferido | S57: =IF(R57="A conferir",(Config!$B$8-L57)*1000+N(F57)/1000+ROW()/100000,0) -> 0 | T57: =IF(R57="A conferir",N(N57),0) -> 0 | U57: =IF(L57="",0,L57) -> 46196 | V57: =IF(L57="",0,MAX(1,N(E57))) -> 1 | W57: =IF(K57="",0,K57) -> 350
A58: 46196 | B58: Beatriz Monteiro | C58: Avaliação endócrina | D58: Pix | F58: 400 | G58: 1 | H58: =IF(D58="","",IFERROR(INDEX(Config!$B$12:$B$15,MATCH(IF(AND(D58="Cartão de crédito",N(E58)>1),"Cartão de crédito parcelado",D58),Config!$A$12:$A$15,0)),0)+IF(AND(Config!$B$17="Sim",LEFT(D58,17)="Cartão de crédito"),Config!$B$18*IFERROR(INDEX(Config!$C$12:$C$15,MATCH(IF(AND(D58="Cartão de crédito",N(E58)>1),"Cartão de crédito parcelado",D58),Config!$A$12:$A$15,0)),0)/30*MAX(1,N(E58)),0)) -> 0 | I58: =IF(OR(D58="",F58=""),"",ROUND(F58*H58,2)) -> 0 | J58: =IF(I58="","",F58-I58) -> 400 | K58: =IF(J58="","",J58/MAX(1,N(E58))) -> 400 | L58: =IF(OR(D58="",A58=""),"",A58+IF(AND(Config!$B$17="Sim",LEFT(D58,17)="Cartão de crédito"),1,IFERROR(INDEX(Config!$C$12:$C$15,MATCH(IF(AND(D58="Cartão de crédito",N(E58)>1),"Cartão de crédito parcelado",D58),Config!$A$12:$A$15,0)),0))) -> 46196 | M58: =IF(L58="","",IF(AND(Config!$B$17="Sim",LEFT(D58,17)="Cartão de crédito"),L58,L58+30*(MAX(1,N(E58))-1))) -> 46196 | N58: =IF(OR(L58="",K58=""),"",K58*MIN(MAX(1,N(E58)),MAX(0,INT((Config!$B$8-L58)/30)+1))) -> 400 | O58: =IF(J58="","",J58-N(N58)) -> 0 | P58: =IF(A58="","",MONTH(A58)) -> 6 | Q58: =IF(A58="","",YEAR(A58)) -> 2026 | R58: =IF(L58="","",IF(L58>Config!$B$8,"A cair",IF(N(G58)>=MIN(MAX(1,N(E58)),MAX(0,INT((Config!$B$8-L58)/30)+1)),IF(N(G58)>=MAX(1,N(E58)),"Conferido","Conferido até aqui"),"A conferir"))) -> Conferido | S58: =IF(R58="A conferir",(Config!$B$8-L58)*1000+N(F58)/1000+ROW()/100000,0) -> 0 | T58: =IF(R58="A conferir",N(N58),0) -> 0 | U58: =IF(L58="",0,L58) -> 46196 | V58: =IF(L58="",0,MAX(1,N(E58))) -> 1 | W58: =IF(K58="",0,K58) -> 400
A59: 46197 | B59: Mônica Martins | C59: Consulta | D59: Cartão de crédito | F59: 380 | G59: 1 | H59: =IF(D59="","",IFERROR(INDEX(Config!$B$12:$B$15,MATCH(IF(AND(D59="Cartão de crédito",N(E59)>1),"Cartão de crédito parcelado",D59),Config!$A$12:$A$15,0)),0)+IF(AND(Config!$B$17="Sim",LEFT(D59,17)="Cartão de crédito"),Config!$B$18*IFERROR(INDEX(Config!$C$12:$C$15,MATCH(IF(AND(D59="Cartão de crédito",N(E59)>1),"Cartão de crédito parcelado",D59),Config!$A$12:$A$15,0)),0)/30*MAX(1,N(E59)),0)) -> 0.032 | I59: =IF(OR(D59="",F59=""),"",ROUND(F59*H59,2)) -> 12.16 | J59: =IF(I59="","",F59-I59) -> 367.84 | K59: =IF(J59="","",J59/MAX(1,N(E59))) -> 367.84 | L59: =IF(OR(D59="",A59=""),"",A59+IF(AND(Config!$B$17="Sim",LEFT(D59,17)="Cartão de crédito"),1,IFERROR(INDEX(Config!$C$12:$C$15,MATCH(IF(AND(D59="Cartão de crédito",N(E59)>1),"Cartão de crédito parcelado",D59),Config!$A$12:$A$15,0)),0))) -> 46227 | M59: =IF(L59="","",IF(AND(Config!$B$17="Sim",LEFT(D59,17)="Cartão de crédito"),L59,L59+30*(MAX(1,N(E59))-1))) -> 46227 | N59: =IF(OR(L59="",K59=""),"",K59*MIN(MAX(1,N(E59)),MAX(0,INT((Config!$B$8-L59)/30)+1))) -> 367.84 | O59: =IF(J59="","",J59-N(N59)) -> 0 | P59: =IF(A59="","",MONTH(A59)) -> 6 | Q59: =IF(A59="","",YEAR(A59)) -> 2026 | R59: =IF(L59="","",IF(L59>Config!$B$8,"A cair",IF(N(G59)>=MIN(MAX(1,N(E59)),MAX(0,INT((Config!$B$8-L59)/30)+1)),IF(N(G59)>=MAX(1,N(E59)),"Conferido","Conferido até aqui"),"A conferir"))) -> Conferido | S59: =IF(R59="A conferir",(Config!$B$8-L59)*1000+N(F59)/1000+ROW()/100000,0) -> 0 | T59: =IF(R59="A conferir",N(N59),0) -> 0 | U59: =IF(L59="",0,L59) -> 46227 | V59: =IF(L59="",0,MAX(1,N(E59))) -> 1 | W59: =IF(K59="",0,K59) -> 367.84
A60: 46197 | B60: Cláudia Santos | C60: Consulta | D60: Cartão de crédito | F60: 380 | G60: 1 | H60: =IF(D60="","",IFERROR(INDEX(Config!$B$12:$B$15,MATCH(IF(AND(D60="Cartão de crédito",N(E60)>1),"Cartão de crédito parcelado",D60),Config!$A$12:$A$15,0)),0)+IF(AND(Config!$B$17="Sim",LEFT(D60,17)="Cartão de crédito"),Config!$B$18*IFERROR(INDEX(Config!$C$12:$C$15,MATCH(IF(AND(D60="Cartão de crédito",N(E60)>1),"Cartão de crédito parcelado",D60),Config!$A$12:$A$15,0)),0)/30*MAX(1,N(E60)),0)) -> 0.032 | I60: =IF(OR(D60="",F60=""),"",ROUND(F60*H60,2)) -> 12.16 | J60: =IF(I60="","",F60-I60) -> 367.84 | K60: =IF(J60="","",J60/MAX(1,N(E60))) -> 367.84 | L60: =IF(OR(D60="",A60=""),"",A60+IF(AND(Config!$B$17="Sim",LEFT(D60,17)="Cartão de crédito"),1,IFERROR(INDEX(Config!$C$12:$C$15,MATCH(IF(AND(D60="Cartão de crédito",N(E60)>1),"Cartão de crédito parcelado",D60),Config!$A$12:$A$15,0)),0))) -> 46227 | M60: =IF(L60="","",IF(AND(Config!$B$17="Sim",LEFT(D60,17)="Cartão de crédito"),L60,L60+30*(MAX(1,N(E60))-1))) -> 46227 | N60: =IF(OR(L60="",K60=""),"",K60*MIN(MAX(1,N(E60)),MAX(0,INT((Config!$B$8-L60)/30)+1))) -> 367.84 | O60: =IF(J60="","",J60-N(N60)) -> 0 | P60: =IF(A60="","",MONTH(A60)) -> 6 | Q60: =IF(A60="","",YEAR(A60)) -> 2026 | R60: =IF(L60="","",IF(L60>Config!$B$8,"A cair",IF(N(G60)>=MIN(MAX(1,N(E60)),MAX(0,INT((Config!$B$8-L60)/30)+1)),IF(N(G60)>=MAX(1,N(E60)),"Conferido","Conferido até aqui"),"A conferir"))) -> Conferido | S60: =IF(R60="A conferir",(Config!$B$8-L60)*1000+N(F60)/1000+ROW()/100000,0) -> 0 | T60: =IF(R60="A conferir",N(N60),0) -> 0 | U60: =IF(L60="",0,L60) -> 46227 | V60: =IF(L60="",0,MAX(1,N(E60))) -> 1 | W60: =IF(K60="",0,K60) -> 367.84
A61: 46198 | B61: Gustavo Ferreira | C61: Consulta | D61: Pix | F61: 380 | G61: 1 | H61: =IF(D61="","",IFERROR(INDEX(Config!$B$12:$B$15,MATCH(IF(AND(D61="Cartão de crédito",N(E61)>1),"Cartão de crédito parcelado",D61),Config!$A$12:$A$15,0)),0)+IF(AND(Config!$B$17="Sim",LEFT(D61,17)="Cartão de crédito"),Config!$B$18*IFERROR(INDEX(Config!$C$12:$C$15,MATCH(IF(AND(D61="Cartão de crédito",N(E61)>1),"Cartão de crédito parcelado",D61),Config!$A$12:$A$15,0)),0)/30*MAX(1,N(E61)),0)) -> 0 | I61: =IF(OR(D61="",F61=""),"",ROUND(F61*H61,2)) -> 0 | J61: =IF(I61="","",F61-I61) -> 380 | K61: =IF(J61="","",J61/MAX(1,N(E61))) -> 380 | L61: =IF(OR(D61="",A61=""),"",A61+IF(AND(Config!$B$17="Sim",LEFT(D61,17)="Cartão de crédito"),1,IFERROR(INDEX(Config!$C$12:$C$15,MATCH(IF(AND(D61="Cartão de crédito",N(E61)>1),"Cartão de crédito parcelado",D61),Config!$A$12:$A$15,0)),0))) -> 46198 | M61: =IF(L61="","",IF(AND(Config!$B$17="Sim",LEFT(D61,17)="Cartão de crédito"),L61,L61+30*(MAX(1,N(E61))-1))) -> 46198 | N61: =IF(OR(L61="",K61=""),"",K61*MIN(MAX(1,N(E61)),MAX(0,INT((Config!$B$8-L61)/30)+1))) -> 380 | O61: =IF(J61="","",J61-N(N61)) -> 0 | P61: =IF(A61="","",MONTH(A61)) -> 6 | Q61: =IF(A61="","",YEAR(A61)) -> 2026 | R61: =IF(L61="","",IF(L61>Config!$B$8,"A cair",IF(N(G61)>=MIN(MAX(1,N(E61)),MAX(0,INT((Config!$B$8-L61)/30)+1)),IF(N(G61)>=MAX(1,N(E61)),"Conferido","Conferido até aqui"),"A conferir"))) -> Conferido | S61: =IF(R61="A conferir",(Config!$B$8-L61)*1000+N(F61)/1000+ROW()/100000,0) -> 0 | T61: =IF(R61="A conferir",N(N61),0) -> 0 | U61: =IF(L61="",0,L61) -> 46198 | V61: =IF(L61="",0,MAX(1,N(E61))) -> 1 | W61: =IF(K61="",0,K61) -> 380
A62: 46198 | B62: Otávio Cardoso | C62: Consulta | D62: Pix | F62: 380 | G62: 1 | H62: =IF(D62="","",IFERROR(INDEX(Config!$B$12:$B$15,MATCH(IF(AND(D62="Cartão de crédito",N(E62)>1),"Cartão de crédito parcelado",D62),Config!$A$12:$A$15,0)),0)+IF(AND(Config!$B$17="Sim",LEFT(D62,17)="Cartão de crédito"),Config!$B$18*IFERROR(INDEX(Config!$C$12:$C$15,MATCH(IF(AND(D62="Cartão de crédito",N(E62)>1),"Cartão de crédito parcelado",D62),Config!$A$12:$A$15,0)),0)/30*MAX(1,N(E62)),0)) -> 0 | I62: =IF(OR(D62="",F62=""),"",ROUND(F62*H62,2)) -> 0 | J62: =IF(I62="","",F62-I62) -> 380 | K62: =IF(J62="","",J62/MAX(1,N(E62))) -> 380 | L62: =IF(OR(D62="",A62=""),"",A62+IF(AND(Config!$B$17="Sim",LEFT(D62,17)="Cartão de crédito"),1,IFERROR(INDEX(Config!$C$12:$C$15,MATCH(IF(AND(D62="Cartão de crédito",N(E62)>1),"Cartão de crédito parcelado",D62),Config!$A$12:$A$15,0)),0))) -> 46198 | M62: =IF(L62="","",IF(AND(Config!$B$17="Sim",LEFT(D62,17)="Cartão de crédito"),L62,L62+30*(MAX(1,N(E62))-1))) -> 46198 | N62: =IF(OR(L62="",K62=""),"",K62*MIN(MAX(1,N(E62)),MAX(0,INT((Config!$B$8-L62)/30)+1))) -> 380 | O62: =IF(J62="","",J62-N(N62)) -> 0 | P62: =IF(A62="","",MONTH(A62)) -> 6 | Q62: =IF(A62="","",YEAR(A62)) -> 2026 | R62: =IF(L62="","",IF(L62>Config!$B$8,"A cair",IF(N(G62)>=MIN(MAX(1,N(E62)),MAX(0,INT((Config!$B$8-L62)/30)+1)),IF(N(G62)>=MAX(1,N(E62)),"Conferido","Conferido até aqui"),"A conferir"))) -> Conferido | S62: =IF(R62="A conferir",(Config!$B$8-L62)*1000+N(F62)/1000+ROW()/100000,0) -> 0 | T62: =IF(R62="A conferir",N(N62),0) -> 0 | U62: =IF(L62="",0,L62) -> 46198 | V62: =IF(L62="",0,MAX(1,N(E62))) -> 1 | W62: =IF(K62="",0,K62) -> 380
A63: 46198 | B63: Leandro Oliveira | C63: Consulta | D63: Pix | F63: 380 | G63: 1 | H63: =IF(D63="","",IFERROR(INDEX(Config!$B$12:$B$15,MATCH(IF(AND(D63="Cartão de crédito",N(E63)>1),"Cartão de crédito parcelado",D63),Config!$A$12:$A$15,0)),0)+IF(AND(Config!$B$17="Sim",LEFT(D63,17)="Cartão de crédito"),Config!$B$18*IFERROR(INDEX(Config!$C$12:$C$15,MATCH(IF(AND(D63="Cartão de crédito",N(E63)>1),"Cartão de crédito parcelado",D63),Config!$A$12:$A$15,0)),0)/30*MAX(1,N(E63)),0)) -> 0 | I63: =IF(OR(D63="",F63=""),"",ROUND(F63*H63,2)) -> 0 | J63: =IF(I63="","",F63-I63) -> 380 | K63: =IF(J63="","",J63/MAX(1,N(E63))) -> 380 | L63: =IF(OR(D63="",A63=""),"",A63+IF(AND(Config!$B$17="Sim",LEFT(D63,17)="Cartão de crédito"),1,IFERROR(INDEX(Config!$C$12:$C$15,MATCH(IF(AND(D63="Cartão de crédito",N(E63)>1),"Cartão de crédito parcelado",D63),Config!$A$12:$A$15,0)),0))) -> 46198 | M63: =IF(L63="","",IF(AND(Config!$B$17="Sim",LEFT(D63,17)="Cartão de crédito"),L63,L63+30*(MAX(1,N(E63))-1))) -> 46198 | N63: =IF(OR(L63="",K63=""),"",K63*MIN(MAX(1,N(E63)),MAX(0,INT((Config!$B$8-L63)/30)+1))) -> 380 | O63: =IF(J63="","",J63-N(N63)) -> 0 | P63: =IF(A63="","",MONTH(A63)) -> 6 | Q63: =IF(A63="","",YEAR(A63)) -> 2026 | R63: =IF(L63="","",IF(L63>Config!$B$8,"A cair",IF(N(G63)>=MIN(MAX(1,N(E63)),MAX(0,INT((Config!$B$8-L63)/30)+1)),IF(N(G63)>=MAX(1,N(E63)),"Conferido","Conferido até aqui"),"A conferir"))) -> Conferido | S63: =IF(R63="A conferir",(Config!$B$8-L63)*1000+N(F63)/1000+ROW()/100000,0) -> 0 | T63: =IF(R63="A conferir",N(N63),0) -> 0 | U63: =IF(L63="",0,L63) -> 46198 | V63: =IF(L63="",0,MAX(1,N(E63))) -> 1 | W63: =IF(K63="",0,K63) -> 380
A64: 46198 | B64: Helena Moreira | C64: Consulta | D64: Pix | F64: 380 | G64: 1 | H64: =IF(D64="","",IFERROR(INDEX(Config!$B$12:$B$15,MATCH(IF(AND(D64="Cartão de crédito",N(E64)>1),"Cartão de crédito parcelado",D64),Config!$A$12:$A$15,0)),0)+IF(AND(Config!$B$17="Sim",LEFT(D64,17)="Cartão de crédito"),Config!$B$18*IFERROR(INDEX(Config!$C$12:$C$15,MATCH(IF(AND(D64="Cartão de crédito",N(E64)>1),"Cartão de crédito parcelado",D64),Config!$A$12:$A$15,0)),0)/30*MAX(1,N(E64)),0)) -> 0 | I64: =IF(OR(D64="",F64=""),"",ROUND(F64*H64,2)) -> 0 | J64: =IF(I64="","",F64-I64) -> 380 | K64: =IF(J64="","",J64/MAX(1,N(E64))) -> 380 | L64: =IF(OR(D64="",A64=""),"",A64+IF(AND(Config!$B$17="Sim",LEFT(D64,17)="Cartão de crédito"),1,IFERROR(INDEX(Config!$C$12:$C$15,MATCH(IF(AND(D64="Cartão de crédito",N(E64)>1),"Cartão de crédito parcelado",D64),Config!$A$12:$A$15,0)),0))) -> 46198 | M64: =IF(L64="","",IF(AND(Config!$B$17="Sim",LEFT(D64,17)="Cartão de crédito"),L64,L64+30*(MAX(1,N(E64))-1))) -> 46198 | N64: =IF(OR(L64="",K64=""),"",K64*MIN(MAX(1,N(E64)),MAX(0,INT((Config!$B$8-L64)/30)+1))) -> 380 | O64: =IF(J64="","",J64-N(N64)) -> 0 | P64: =IF(A64="","",MONTH(A64)) -> 6 | Q64: =IF(A64="","",YEAR(A64)) -> 2026 | R64: =IF(L64="","",IF(L64>Config!$B$8,"A cair",IF(N(G64)>=MIN(MAX(1,N(E64)),MAX(0,INT((Config!$B$8-L64)/30)+1)),IF(N(G64)>=MAX(1,N(E64)),"Conferido","Conferido até aqui"),"A conferir"))) -> Conferido | S64: =IF(R64="A conferir",(Config!$B$8-L64)*1000+N(F64)/1000+ROW()/100000,0) -> 0 | T64: =IF(R64="A conferir",N(N64),0) -> 0 | U64: =IF(L64="",0,L64) -> 46198 | V64: =IF(L64="",0,MAX(1,N(E64))) -> 1 | W64: =IF(K64="",0,K64) -> 380
A65: 46198 | B65: Mariana Nascimento | C65: Consulta | D65: Pix | F65: 380 | G65: 1 | H65: =IF(D65="","",IFERROR(INDEX(Config!$B$12:$B$15,MATCH(IF(AND(D65="Cartão de crédito",N(E65)>1),"Cartão de crédito parcelado",D65),Config!$A$12:$A$15,0)),0)+IF(AND(Config!$B$17="Sim",LEFT(D65,17)="Cartão de crédito"),Config!$B$18*IFERROR(INDEX(Config!$C$12:$C$15,MATCH(IF(AND(D65="Cartão de crédito",N(E65)>1),"Cartão de crédito parcelado",D65),Config!$A$12:$A$15,0)),0)/30*MAX(1,N(E65)),0)) -> 0 | I65: =IF(OR(D65="",F65=""),"",ROUND(F65*H65,2)) -> 0 | J65: =IF(I65="","",F65-I65) -> 380 | K65: =IF(J65="","",J65/MAX(1,N(E65))) -> 380 | L65: =IF(OR(D65="",A65=""),"",A65+IF(AND(Config!$B$17="Sim",LEFT(D65,17)="Cartão de crédito"),1,IFERROR(INDEX(Config!$C$12:$C$15,MATCH(IF(AND(D65="Cartão de crédito",N(E65)>1),"Cartão de crédito parcelado",D65),Config!$A$12:$A$15,0)),0))) -> 46198 | M65: =IF(L65="","",IF(AND(Config!$B$17="Sim",LEFT(D65,17)="Cartão de crédito"),L65,L65+30*(MAX(1,N(E65))-1))) -> 46198 | N65: =IF(OR(L65="",K65=""),"",K65*MIN(MAX(1,N(E65)),MAX(0,INT((Config!$B$8-L65)/30)+1))) -> 380 | O65: =IF(J65="","",J65-N(N65)) -> 0 | P65: =IF(A65="","",MONTH(A65)) -> 6 | Q65: =IF(A65="","",YEAR(A65)) -> 2026 | R65: =IF(L65="","",IF(L65>Config!$B$8,"A cair",IF(N(G65)>=MIN(MAX(1,N(E65)),MAX(0,INT((Config!$B$8-L65)/30)+1)),IF(N(G65)>=MAX(1,N(E65)),"Conferido","Conferido até aqui"),"A conferir"))) -> Conferido | S65: =IF(R65="A conferir",(Config!$B$8-L65)*1000+N(F65)/1000+ROW()/100000,0) -> 0 | T65: =IF(R65="A conferir",N(N65),0) -> 0 | U65: =IF(L65="",0,L65) -> 46198 | V65: =IF(L65="",0,MAX(1,N(E65))) -> 1 | W65: =IF(K65="",0,K65) -> 380
A66: 46198 | B66: Fábio Ferreira | C66: Avaliação endócrina | D66: Pix | F66: 400 | G66: 1 | H66: =IF(D66="","",IFERROR(INDEX(Config!$B$12:$B$15,MATCH(IF(AND(D66="Cartão de crédito",N(E66)>1),"Cartão de crédito parcelado",D66),Config!$A$12:$A$15,0)),0)+IF(AND(Config!$B$17="Sim",LEFT(D66,17)="Cartão de crédito"),Config!$B$18*IFERROR(INDEX(Config!$C$12:$C$15,MATCH(IF(AND(D66="Cartão de crédito",N(E66)>1),"Cartão de crédito parcelado",D66),Config!$A$12:$A$15,0)),0)/30*MAX(1,N(E66)),0)) -> 0 | I66: =IF(OR(D66="",F66=""),"",ROUND(F66*H66,2)) -> 0 | J66: =IF(I66="","",F66-I66) -> 400 | K66: =IF(J66="","",J66/MAX(1,N(E66))) -> 400 | L66: =IF(OR(D66="",A66=""),"",A66+IF(AND(Config!$B$17="Sim",LEFT(D66,17)="Cartão de crédito"),1,IFERROR(INDEX(Config!$C$12:$C$15,MATCH(IF(AND(D66="Cartão de crédito",N(E66)>1),"Cartão de crédito parcelado",D66),Config!$A$12:$A$15,0)),0))) -> 46198 | M66: =IF(L66="","",IF(AND(Config!$B$17="Sim",LEFT(D66,17)="Cartão de crédito"),L66,L66+30*(MAX(1,N(E66))-1))) -> 46198 | N66: =IF(OR(L66="",K66=""),"",K66*MIN(MAX(1,N(E66)),MAX(0,INT((Config!$B$8-L66)/30)+1))) -> 400 | O66: =IF(J66="","",J66-N(N66)) -> 0 | P66: =IF(A66="","",MONTH(A66)) -> 6 | Q66: =IF(A66="","",YEAR(A66)) -> 2026 | R66: =IF(L66="","",IF(L66>Config!$B$8,"A cair",IF(N(G66)>=MIN(MAX(1,N(E66)),MAX(0,INT((Config!$B$8-L66)/30)+1)),IF(N(G66)>=MAX(1,N(E66)),"Conferido","Conferido até aqui"),"A conferir"))) -> Conferido | S66: =IF(R66="A conferir",(Config!$B$8-L66)*1000+N(F66)/1000+ROW()/100000,0) -> 0 | T66: =IF(R66="A conferir",N(N66),0) -> 0 | U66: =IF(L66="",0,L66) -> 46198 | V66: =IF(L66="",0,MAX(1,N(E66))) -> 1 | W66: =IF(K66="",0,K66) -> 400
... A70: 46202 | B70: Roberta Araújo | C70: Consulta | D70: Cartão de débito | F70: 380 | G70: 1 | H70: =IF(D70="","",IFERROR(INDEX(Config!$B$12:$B$15,MATCH(IF(AND(D70="Cartão de crédito",N(E70)>1),"Cartão de crédito parcelado",D70),Config!$A$12:$A$15,0)),0)+IF(AND(Config!$B$17="Sim",LEFT(D70,17)="Cartão de crédito"),Config!$B$18*IFERROR(INDEX(Config!$C$12:$C$15,MATCH(IF(AND(D70="Cartão de crédito",N(E70)>1),"Cartão de crédito parcelado",D70),Config!$A$12:$A$15,0)),0)/30*MAX(1,N(E70)),0)) -> 0.015 | I70: =IF(OR(D70="",F70=""),"",ROUND(F70*H70,2)) -> 5.7 | J70: =IF(I70="","",F70-I70) -> 374.3 | K70: =IF(J70="","",J70/MAX(1,N(E70))) -> 374.3 | L70: =IF(OR(D70="",A70=""),"",A70+IF(AND(Config!$B$17="Sim",LEFT(D70,17)="Cartão de crédito"),1,IFERROR(INDEX(Config!$C$12:$C$15,MATCH(IF(AND(D70="Cartão de crédito",N(E70)>1),"Cartão de crédito parcelado",D70),Config!$A$12:$A$15,0)),0))) -> 46203 | M70: =IF(L70="","",IF(AND(Config!$B$17="Sim",LEFT(D70,17)="Cartão de crédito"),L70,L70+30*(MAX(1,N(E70))-1))) -> 46203 | N70: =IF(OR(L70="",K70=""),"",K70*MIN(MAX(1,N(E70)),MAX(0,INT((Config!$B$8-L70)/30)+1))) -> 374.3 | O70: =IF(J70="","",J70-N(N70)) -> 0 | P70: =IF(A70="","",MONTH(A70)) -> 6 | Q70: =IF(A70="","",YEAR(A70)) -> 2026 | R70: =IF(L70="","",IF(L70>Config!$B$8,"A cair",IF(N(G70)>=MIN(MAX(1,N(E70)),MAX(0,INT((Config!$B$8-L70)/30)+1)),IF(N(G70)>=MAX(1,N(E70)),"Conferido","Conferido até aqui"),"A conferir"))) -> Conferido | S70: =IF(R70="A conferir",(Config!$B$8-L70)*1000+N(F70)/1000+ROW()/100000,0) -> 0 | T70: =IF(R70="A conferir",N(N70),0) -> 0 | U70: =IF(L70="",0,L70) -> 46203 | V70: =IF(L70="",0,MAX(1,N(E70))) -> 1 | W70: =IF(K70="",0,K70) -> 374.3
A71: 46202 | B71: Otávio Nascimento | C71: Consulta | D71: Cartão de crédito | E71: 2 | F71: 380 | G71: 2 | H71: =IF(D71="","",IFERROR(INDEX(Config!$B$12:$B$15,MATCH(IF(AND(D71="Cartão de crédito",N(E71)>1),"Cartão de crédito parcelado",D71),Config!$A$12:$A$15,0)),0)+IF(AND(Config!$B$17="Sim",LEFT(D71,17)="Cartão de crédito"),Config!$B$18*IFERROR(INDEX(Config!$C$12:$C$15,MATCH(IF(AND(D71="Cartão de crédito",N(E71)>1),"Cartão de crédito parcelado",D71),Config!$A$12:$A$15,0)),0)/30*MAX(1,N(E71)),0)) -> 0.039 | I71: =IF(OR(D71="",F71=""),"",ROUND(F71*H71,2)) -> 14.82 | J71: =IF(I71="","",F71-I71) -> 365.18 | K71: =IF(J71="","",J71/MAX(1,N(E71))) -> 182.59 | L71: =IF(OR(D71="",A71=""),"",A71+IF(AND(Config!$B$17="Sim",LEFT(D71,17)="Cartão de crédito"),1,IFERROR(INDEX(Config!$C$12:$C$15,MATCH(IF(AND(D71="Cartão de crédito",N(E71)>1),"Cartão de crédito parcelado",D71),Config!$A$12:$A$15,0)),0))) -> 46232 | M71: =IF(L71="","",IF(AND(Config!$B$17="Sim",LEFT(D71,17)="Cartão de crédito"),L71,L71+30*(MAX(1,N(E71))-1))) -> 46262 | N71: =IF(OR(L71="",K71=""),"",K71*MIN(MAX(1,N(E71)),MAX(0,INT((Config!$B$8-L71)/30)+1))) -> 365.18 | O71: =IF(J71="","",J71-N(N71)) -> 0 | P71: =IF(A71="","",MONTH(A71)) -> 6 | Q71: =IF(A71="","",YEAR(A71)) -> 2026 | R71: =IF(L71="","",IF(L71>Config!$B$8,"A cair",IF(N(G71)>=MIN(MAX(1,N(E71)),MAX(0,INT((Config!$B$8-L71)/30)+1)),IF(N(G71)>=MAX(1,N(E71)),"Conferido","Conferido até aqui"),"A conferir"))) -> Conferido | S71: =IF(R71="A conferir",(Config!$B$8-L71)*1000+N(F71)/1000+ROW()/100000,0) -> 0 | T71: =IF(R71="A conferir",N(N71),0) -> 0 | U71: =IF(L71="",0,L71) -> 46232 | V71: =IF(L71="",0,MAX(1,N(E71))) -> 2 | W71: =IF(K71="",0,K71) -> 182.59
A72: 46202 | B72: Roberta Araújo | C72: MAPA | D72: Pix | F72: 300 | G72: 1 | H72: =IF(D72="","",IFERROR(INDEX(Config!$B$12:$B$15,MATCH(IF(AND(D72="Cartão de crédito",N(E72)>1),"Cartão de crédito parcelado",D72),Config!$A$12:$A$15,0)),0)+IF(AND(Config!$B$17="Sim",LEFT(D72,17)="Cartão de crédito"),Config!$B$18*IFERROR(INDEX(Config!$C$12:$C$15,MATCH(IF(AND(D72="Cartão de crédito",N(E72)>1),"Cartão de crédito parcelado",D72),Config!$A$12:$A$15,0)),0)/30*MAX(1,N(E72)),0)) -> 0 | I72: =IF(OR(D72="",F72=""),"",ROUND(F72*H72,2)) -> 0 | J72: =IF(I72="","",F72-I72) -> 300 | K72: =IF(J72="","",J72/MAX(1,N(E72))) -> 300 | L72: =IF(OR(D72="",A72=""),"",A72+IF(AND(Config!$B$17="Sim",LEFT(D72,17)="Cartão de crédito"),1,IFERROR(INDEX(Config!$C$12:$C$15,MATCH(IF(AND(D72="Cartão de crédito",N(E72)>1),"Cartão de crédito parcelado",D72),Config!$A$12:$A$15,0)),0))) -> 46202 | M72: =IF(L72="","",IF(AND(Config!$B$17="Sim",LEFT(D72,17)="Cartão de crédito"),L72,L72+30*(MAX(1,N(E72))-1))) -> 46202 | N72: =IF(OR(L72="",K72=""),"",K72*MIN(MAX(1,N(E72)),MAX(0,INT((Config!$B$8-L72)/30)+1))) -> 300 | O72: =IF(J72="","",J72-N(N72)) -> 0 | P72: =IF(A72="","",MONTH(A72)) -> 6 | Q72: =IF(A72="","",YEAR(A72)) -> 2026 | R72: =IF(L72="","",IF(L72>Config!$B$8,"A cair",IF(N(G72)>=MIN(MAX(1,N(E72)),MAX(0,INT((Config!$B$8-L72)/30)+1)),IF(N(G72)>=MAX(1,N(E72)),"Conferido","Conferido até aqui"),"A conferir"))) -> Conferido | S72: =IF(R72="A conferir",(Config!$B$8-L72)*1000+N(F72)/1000+ROW()/100000,0) -> 0 | T72: =IF(R72="A conferir",N(N72),0) -> 0 | U72: =IF(L72="",0,L72) -> 46202 | V72: =IF(L72="",0,MAX(1,N(E72))) -> 1 | W72: =IF(K72="",0,K72) -> 300
A73: 46202 | B73: Gisele Xavier | C73: ECG | D73: Cartão de débito | F73: 130 | G73: 1 | H73: =IF(D73="","",IFERROR(INDEX(Config!$B$12:$B$15,MATCH(IF(AND(D73="Cartão de crédito",N(E73)>1),"Cartão de crédito parcelado",D73),Config!$A$12:$A$15,0)),0)+IF(AND(Config!$B$17="Sim",LEFT(D73,17)="Cartão de crédito"),Config!$B$18*IFERROR(INDEX(Config!$C$12:$C$15,MATCH(IF(AND(D73="Cartão de crédito",N(E73)>1),"Cartão de crédito parcelado",D73),Config!$A$12:$A$15,0)),0)/30*MAX(1,N(E73)),0)) -> 0.015 | I73: =IF(OR(D73="",F73=""),"",ROUND(F73*H73,2)) -> 1.95 | J73: =IF(I73="","",F73-I73) -> 128.05 | K73: =IF(J73="","",J73/MAX(1,N(E73))) -> 128.05 | L73: =IF(OR(D73="",A73=""),"",A73+IF(AND(Config!$B$17="Sim",LEFT(D73,17)="Cartão de crédito"),1,IFERROR(INDEX(Config!$C$12:$C$15,MATCH(IF(AND(D73="Cartão de crédito",N(E73)>1),"Cartão de crédito parcelado",D73),Config!$A$12:$A$15,0)),0))) -> 46203 | M73: =IF(L73="","",IF(AND(Config!$B$17="Sim",LEFT(D73,17)="Cartão de crédito"),L73,L73+30*(MAX(1,N(E73))-1))) -> 46203 | N73: =IF(OR(L73="",K73=""),"",K73*MIN(MAX(1,N(E73)),MAX(0,INT((Config!$B$8-L73)/30)+1))) -> 128.05 | O73: =IF(J73="","",J73-N(N73)) -> 0 | P73: =IF(A73="","",MONTH(A73)) -> 6 | Q73: =IF(A73="","",YEAR(A73)) -> 2026 | R73: =IF(L73="","",IF(L73>Config!$B$8,"A cair",IF(N(G73)>=MIN(MAX(1,N(E73)),MAX(0,INT((Config!$B$8-L73)/30)+1)),IF(N(G73)>=MAX(1,N(E73)),"Conferido","Conferido até aqui"),"A conferir"))) -> Conferido | S73: =IF(R73="A conferir",(Config!$B$8-L73)*1000+N(F73)/1000+ROW()/100000,0) -> 0 | T73: =IF(R73="A conferir",N(N73),0) -> 0 | U73: =IF(L73="",0,L73) -> 46203 | V73: =IF(L73="",0,MAX(1,N(E73))) -> 1 | W73: =IF(K73="",0,K73) -> 128.05
A74: 46203 | B74: Gisele Ribeiro | C74: Consulta | D74: Cartão de crédito | F74: 380 | G74: 1 | H74: =IF(D74="","",IFERROR(INDEX(Config!$B$12:$B$15,MATCH(IF(AND(D74="Cartão de crédito",N(E74)>1),"Cartão de crédito parcelado",D74),Config!$A$12:$A$15,0)),0)+IF(AND(Config!$B$17="Sim",LEFT(D74,17)="Cartão de crédito"),Config!$B$18*IFERROR(INDEX(Config!$C$12:$C$15,MATCH(IF(AND(D74="Cartão de crédito",N(E74)>1),"Cartão de crédito parcelado",D74),Config!$A$12:$A$15,0)),0)/30*MAX(1,N(E74)),0)) -> 0.032 | I74: =IF(OR(D74="",F74=""),"",ROUND(F74*H74,2)) -> 12.16 | J74: =IF(I74="","",F74-I74) -> 367.84 | K74: =IF(J74="","",J74/MAX(1,N(E74))) -> 367.84 | L74: =IF(OR(D74="",A74=""),"",A74+IF(AND(Config!$B$17="Sim",LEFT(D74,17)="Cartão de crédito"),1,IFERROR(INDEX(Config!$C$12:$C$15,MATCH(IF(AND(D74="Cartão de crédito",N(E74)>1),"Cartão de crédito parcelado",D74),Config!$A$12:$A$15,0)),0))) -> 46233 | M74: =IF(L74="","",IF(AND(Config!$B$17="Sim",LEFT(D74,17)="Cartão de crédito"),L74,L74+30*(MAX(1,N(E74))-1))) -> 46233 | N74: =IF(OR(L74="",K74=""),"",K74*MIN(MAX(1,N(E74)),MAX(0,INT((Config!$B$8-L74)/30)+1))) -> 367.84 | O74: =IF(J74="","",J74-N(N74)) -> 0 | P74: =IF(A74="","",MONTH(A74)) -> 6 | Q74: =IF(A74="","",YEAR(A74)) -> 2026 | R74: =IF(L74="","",IF(L74>Config!$B$8,"A cair",IF(N(G74)>=MIN(MAX(1,N(E74)),MAX(0,INT((Config!$B$8-L74)/30)+1)),IF(N(G74)>=MAX(1,N(E74)),"Conferido","Conferido até aqui"),"A conferir"))) -> Conferido | S74: =IF(R74="A conferir",(Config!$B$8-L74)*1000+N(F74)/1000+ROW()/100000,0) -> 0 | T74: =IF(R74="A conferir",N(N74),0) -> 0 | U74: =IF(L74="",0,L74) -> 46233 | V74: =IF(L74="",0,MAX(1,N(E74))) -> 1 | W74: =IF(K74="",0,K74) -> 367.84
A75: 46203 | B75: Marcelo Santos | C75: Consulta | D75: Cartão de crédito | F75: 380 | G75: 1 | H75: =IF(D75="","",IFERROR(INDEX(Config!$B$12:$B$15,MATCH(IF(AND(D75="Cartão de crédito",N(E75)>1),"Cartão de crédito parcelado",D75),Config!$A$12:$A$15,0)),0)+IF(AND(Config!$B$17="Sim",LEFT(D75,17)="Cartão de crédito"),Config!$B$18*IFERROR(INDEX(Config!$C$12:$C$15,MATCH(IF(AND(D75="Cartão de crédito",N(E75)>1),"Cartão de crédito parcelado",D75),Config!$A$12:$A$15,0)),0)/30*MAX(1,N(E75)),0)) -> 0.032 | I75: =IF(OR(D75="",F75=""),"",ROUND(F75*H75,2)) -> 12.16 | J75: =IF(I75="","",F75-I75) -> 367.84 | K75: =IF(J75="","",J75/MAX(1,N(E75))) -> 367.84 | L75: =IF(OR(D75="",A75=""),"",A75+IF(AND(Config!$B$17="Sim",LEFT(D75,17)="Cartão de crédito"),1,IFERROR(INDEX(Config!$C$12:$C$15,MATCH(IF(AND(D75="Cartão de crédito",N(E75)>1),"Cartão de crédito parcelado",D75),Config!$A$12:$A$15,0)),0))) -> 46233 | M75: =IF(L75="","",IF(AND(Config!$B$17="Sim",LEFT(D75,17)="Cartão de crédito"),L75,L75+30*(MAX(1,N(E75))-1))) -> 46233 | N75: =IF(OR(L75="",K75=""),"",K75*MIN(MAX(1,N(E75)),MAX(0,INT((Config!$B$8-L75)/30)+1))) -> 367.84 | O75: =IF(J75="","",J75-N(N75)) -> 0 | P75: =IF(A75="","",MONTH(A75)) -> 6 | Q75: =IF(A75="","",YEAR(A75)) -> 2026 | R75: =IF(L75="","",IF(L75>Config!$B$8,"A cair",IF(N(G75)>=MIN(MAX(1,N(E75)),MAX(0,INT((Config!$B$8-L75)/30)+1)),IF(N(G75)>=MAX(1,N(E75)),"Conferido","Conferido até aqui"),"A conferir"))) -> Conferido | S75: =IF(R75="A conferir",(Config!$B$8-L75)*1000+N(F75)/1000+ROW()/100000,0) -> 0 | T75: =IF(R75="A conferir",N(N75),0) -> 0 | U75: =IF(L75="",0,L75) -> 46233 | V75: =IF(L75="",0,MAX(1,N(E75))) -> 1 | W75: =IF(K75="",0,K75) -> 367.84
A76: 46203 | B76: Elaine Cardoso | C76: Consulta | D76: Cartão de débito | F76: 380 | G76: 1 | H76: =IF(D76="","",IFERROR(INDEX(Config!$B$12:$B$15,MATCH(IF(AND(D76="Cartão de crédito",N(E76)>1),"Cartão de crédito parcelado",D76),Config!$A$12:$A$15,0)),0)+IF(AND(Config!$B$17="Sim",LEFT(D76,17)="Cartão de crédito"),Config!$B$18*IFERROR(INDEX(Config!$C$12:$C$15,MATCH(IF(AND(D76="Cartão de crédito",N(E76)>1),"Cartão de crédito parcelado",D76),Config!$A$12:$A$15,0)),0)/30*MAX(1,N(E76)),0)) -> 0.015 | I76: =IF(OR(D76="",F76=""),"",ROUND(F76*H76,2)) -> 5.7 | J76: =IF(I76="","",F76-I76) -> 374.3 | K76: =IF(J76="","",J76/MAX(1,N(E76))) -> 374.3 | L76: =IF(OR(D76="",A76=""),"",A76+IF(AND(Config!$B$17="Sim",LEFT(D76,17)="Cartão de crédito"),1,IFERROR(INDEX(Config!$C$12:$C$15,MATCH(IF(AND(D76="Cartão de crédito",N(E76)>1),"Cartão de crédito parcelado",D76),Config!$A$12:$A$15,0)),0))) -> 46204 | M76: =IF(L76="","",IF(AND(Config!$B$17="Sim",LEFT(D76,17)="Cartão de crédito"),L76,L76+30*(MAX(1,N(E76))-1))) -> 46204 | N76: =IF(OR(L76="",K76=""),"",K76*MIN(MAX(1,N(E76)),MAX(0,INT((Config!$B$8-L76)/30)+1))) -> 374.3 | O76: =IF(J76="","",J76-N(N76)) -> 0 | P76: =IF(A76="","",MONTH(A76)) -> 6 | Q76: =IF(A76="","",YEAR(A76)) -> 2026 | R76: =IF(L76="","",IF(L76>Config!$B$8,"A cair",IF(N(G76)>=MIN(MAX(1,N(E76)),MAX(0,INT((Config!$B$8-L76)/30)+1)),IF(N(G76)>=MAX(1,N(E76)),"Conferido","Conferido até aqui"),"A conferir"))) -> Conferido | S76: =IF(R76="A conferir",(Config!$B$8-L76)*1000+N(F76)/1000+ROW()/100000,0) -> 0 | T76: =IF(R76="A conferir",N(N76),0) -> 0 | U76: =IF(L76="",0,L76) -> 46204 | V76: =IF(L76="",0,MAX(1,N(E76))) -> 1 | W76: =IF(K76="",0,K76) -> 374.3
A77: 46203 | B77: Regina Macedo | C77: Consulta | D77: Cartão de crédito | E77: 2 | F77: 380 | G77: 2 | H77: =IF(D77="","",IFERROR(INDEX(Config!$B$12:$B$15,MATCH(IF(AND(D77="Cartão de crédito",N(E77)>1),"Cartão de crédito parcelado",D77),Config!$A$12:$A$15,0)),0)+IF(AND(Config!$B$17="Sim",LEFT(D77,17)="Cartão de crédito"),Config!$B$18*IFERROR(INDEX(Config!$C$12:$C$15,MATCH(IF(AND(D77="Cartão de crédito",N(E77)>1),"Cartão de crédito parcelado",D77),Config!$A$12:$A$15,0)),0)/30*MAX(1,N(E77)),0)) -> 0.039 | I77: =IF(OR(D77="",F77=""),"",ROUND(F77*H77,2)) -> 14.82 | J77: =IF(I77="","",F77-I77) -> 365.18 | K77: =IF(J77="","",J77/MAX(1,N(E77))) -> 182.59 | L77: =IF(OR(D77="",A77=""),"",A77+IF(AND(Config!$B$17="Sim",LEFT(D77,17)="Cartão de crédito"),1,IFERROR(INDEX(Config!$C$12:$C$15,MATCH(IF(AND(D77="Cartão de crédito",N(E77)>1),"Cartão de crédito parcelado",D77),Config!$A$12:$A$15,0)),0))) -> 46233 | M77: =IF(L77="","",IF(AND(Config!$B$17="Sim",LEFT(D77,17)="Cartão de crédito"),L77,L77+30*(MAX(1,N(E77))-1))) -> 46263 | N77: =IF(OR(L77="",K77=""),"",K77*MIN(MAX(1,N(E77)),MAX(0,INT((Config!$B$8-L77)/30)+1))) -> 365.18 | O77: =IF(J77="","",J77-N(N77)) -> 0 | P77: =IF(A77="","",MONTH(A77)) -> 6 | Q77: =IF(A77="","",YEAR(A77)) -> 2026 | R77: =IF(L77="","",IF(L77>Config!$B$8,"A cair",IF(N(G77)>=MIN(MAX(1,N(E77)),MAX(0,INT((Config!$B$8-L77)/30)+1)),IF(N(G77)>=MAX(1,N(E77)),"Conferido","Conferido até aqui"),"A conferir"))) -> Conferido | S77: =IF(R77="A conferir",(Config!$B$8-L77)*1000+N(F77)/1000+ROW()/100000,0) -> 0 | T77: =IF(R77="A conferir",N(N77),0) -> 0 | U77: =IF(L77="",0,L77) -> 46233 | V77: =IF(L77="",0,MAX(1,N(E77))) -> 2 | W77: =IF(K77="",0,K77) -> 182.59
A78: 46203 | B78: Fábio Correia | C78: Consulta | D78: Pix | F78: 380 | G78: 1 | H78: =IF(D78="","",IFERROR(INDEX(Config!$B$12:$B$15,MATCH(IF(AND(D78="Cartão de crédito",N(E78)>1),"Cartão de crédito parcelado",D78),Config!$A$12:$A$15,0)),0)+IF(AND(Config!$B$17="Sim",LEFT(D78,17)="Cartão de crédito"),Config!$B$18*IFERROR(INDEX(Config!$C$12:$C$15,MATCH(IF(AND(D78="Cartão de crédito",N(E78)>1),"Cartão de crédito parcelado",D78),Config!$A$12:$A$15,0)),0)/30*MAX(1,N(E78)),0)) -> 0 | I78: =IF(OR(D78="",F78=""),"",ROUND(F78*H78,2)) -> 0 | J78: =IF(I78="","",F78-I78) -> 380 | K78: =IF(J78="","",J78/MAX(1,N(E78))) -> 380 | L78: =IF(OR(D78="",A78=""),"",A78+IF(AND(Config!$B$17="Sim",LEFT(D78,17)="Cartão de crédito"),1,IFERROR(INDEX(Config!$C$12:$C$15,MATCH(IF(AND(D78="Cartão de crédito",N(E78)>1),"Cartão de crédito parcelado",D78),Config!$A$12:$A$15,0)),0))) -> 46203 | M78: =IF(L78="","",IF(AND(Config!$B$17="Sim",LEFT(D78,17)="Cartão de crédito"),L78,L78+30*(MAX(1,N(E78))-1))) -> 46203 | N78: =IF(OR(L78="",K78=""),"",K78*MIN(MAX(1,N(E78)),MAX(0,INT((Config!$B$8-L78)/30)+1))) -> 380 | O78: =IF(J78="","",J78-N(N78)) -> 0 | P78: =IF(A78="","",MONTH(A78)) -> 6 | Q78: =IF(A78="","",YEAR(A78)) -> 2026 | R78: =IF(L78="","",IF(L78>Config!$B$8,"A cair",IF(N(G78)>=MIN(MAX(1,N(E78)),MAX(0,INT((Config!$B$8-L78)/30)+1)),IF(N(G78)>=MAX(1,N(E78)),"Conferido","Conferido até aqui"),"A conferir"))) -> Conferido | S78: =IF(R78="A conferir",(Config!$B$8-L78)*1000+N(F78)/1000+ROW()/100000,0) -> 0 | T78: =IF(R78="A conferir",N(N78),0) -> 0 | U78: =IF(L78="",0,L78) -> 46203 | V78: =IF(L78="",0,MAX(1,N(E78))) -> 1 | W78: =IF(K78="",0,K78) -> 380
A79: 46203 | B79: Eduardo Pereira | C79: Avaliação endócrina | D79: Cartão de crédito | E79: 2 | F79: 400 | G79: 2 | H79: =IF(D79="","",IFERROR(INDEX(Config!$B$12:$B$15,MATCH(IF(AND(D79="Cartão de crédito",N(E79)>1),"Cartão de crédito parcelado",D79),Config!$A$12:$A$15,0)),0)+IF(AND(Config!$B$17="Sim",LEFT(D79,17)="Cartão de crédito"),Config!$B$18*IFERROR(INDEX(Config!$C$12:$C$15,MATCH(IF(AND(D79="Cartão de crédito",N(E79)>1),"Cartão de crédito parcelado",D79),Config!$A$12:$A$15,0)),0)/30*MAX(1,N(E79)),0)) -> 0.039 | I79: =IF(OR(D79="",F79=""),"",ROUND(F79*H79,2)) -> 15.6 | J79: =IF(I79="","",F79-I79) -> 384.4 | K79: =IF(J79="","",J79/MAX(1,N(E79))) -> 192.2 | L79: =IF(OR(D79="",A79=""),"",A79+IF(AND(Config!$B$17="Sim",LEFT(D79,17)="Cartão de crédito"),1,IFERROR(INDEX(Config!$C$12:$C$15,MATCH(IF(AND(D79="Cartão de crédito",N(E79)>1),"Cartão de crédito parcelado",D79),Config!$A$12:$A$15,0)),0))) -> 46233 | M79: =IF(L79="","",IF(AND(Config!$B$17="Sim",LEFT(D79,17)="Cartão de crédito"),L79,L79+30*(MAX(1,N(E79))-1))) -> 46263 | N79: =IF(OR(L79="",K79=""),"",K79*MIN(MAX(1,N(E79)),MAX(0,INT((Config!$B$8-L79)/30)+1))) -> 384.4 | O79: =IF(J79="","",J79-N(N79)) -> 0 | P79: =IF(A79="","",MONTH(A79)) -> 6 | Q79: =IF(A79="","",YEAR(A79)) -> 2026 | R79: =IF(L79="","",IF(L79>Config!$B$8,"A cair",IF(N(G79)>=MIN(MAX(1,N(E79)),MAX(0,INT((Config!$B$8-L79)/30)+1)),IF(N(G79)>=MAX(1,N(E79)),"Conferido","Conferido até aqui"),"A conferir"))) -> Conferido | S79: =IF(R79="A conferir",(Config!$B$8-L79)*1000+N(F79)/1000+ROW()/100000,0) -> 0 | T79: =IF(R79="A conferir",N(N79),0) -> 0 | U79: =IF(L79="",0,L79) -> 46233 | V79: =IF(L79="",0,MAX(1,N(E79))) -> 2 | W79: =IF(K79="",0,K79) -> 192.2
A80: 46204 | B80: Cláudia Santos | C80: Consulta | D80: Pix | F80: 380 | G80: 1 | H80: =IF(D80="","",IFERROR(INDEX(Config!$B$12:$B$15,MATCH(IF(AND(D80="Cartão de crédito",N(E80)>1),"Cartão de crédito parcelado",D80),Config!$A$12:$A$15,0)),0)+IF(AND(Config!$B$17="Sim",LEFT(D80,17)="Cartão de crédito"),Config!$B$18*IFERROR(INDEX(Config!$C$12:$C$15,MATCH(IF(AND(D80="Cartão de crédito",N(E80)>1),"Cartão de crédito parcelado",D80),Config!$A$12:$A$15,0)),0)/30*MAX(1,N(E80)),0)) -> 0 | I80: =IF(OR(D80="",F80=""),"",ROUND(F80*H80,2)) -> 0 | J80: =IF(I80="","",F80-I80) -> 380 | K80: =IF(J80="","",J80/MAX(1,N(E80))) -> 380 | L80: =IF(OR(D80="",A80=""),"",A80+IF(AND(Config!$B$17="Sim",LEFT(D80,17)="Cartão de crédito"),1,IFERROR(INDEX(Config!$C$12:$C$15,MATCH(IF(AND(D80="Cartão de crédito",N(E80)>1),"Cartão de crédito parcelado",D80),Config!$A$12:$A$15,0)),0))) -> 46204 | M80: =IF(L80="","",IF(AND(Config!$B$17="Sim",LEFT(D80,17)="Cartão de crédito"),L80,L80+30*(MAX(1,N(E80))-1))) -> 46204 | N80: =IF(OR(L80="",K80=""),"",K80*MIN(MAX(1,N(E80)),MAX(0,INT((Config!$B$8-L80)/30)+1))) -> 380 | O80: =IF(J80="","",J80-N(N80)) -> 0 | P80: =IF(A80="","",MONTH(A80)) -> 7 | Q80: =IF(A80="","",YEAR(A80)) -> 2026 | R80: =IF(L80="","",IF(L80>Config!$B$8,"A cair",IF(N(G80)>=MIN(MAX(1,N(E80)),MAX(0,INT((Config!$B$8-L80)/30)+1)),IF(N(G80)>=MAX(1,N(E80)),"Conferido","Conferido até aqui"),"A conferir"))) -> Conferido | S80: =IF(R80="A conferir",(Config!$B$8-L80)*1000+N(F80)/1000+ROW()/100000,0) -> 0 | T80: =IF(R80="A conferir",N(N80),0) -> 0 | U80: =IF(L80="",0,L80) -> 46204 | V80: =IF(L80="",0,MAX(1,N(E80))) -> 1 | W80: =IF(K80="",0,K80) -> 380
A81: 46204 | B81: Lucas Lopes | C81: Consulta | D81: Cartão de débito | F81: 380 | G81: 1 | H81: =IF(D81="","",IFERROR(INDEX(Config!$B$12:$B$15,MATCH(IF(AND(D81="Cartão de crédito",N(E81)>1),"Cartão de crédito parcelado",D81),Config!$A$12:$A$15,0)),0)+IF(AND(Config!$B$17="Sim",LEFT(D81,17)="Cartão de crédito"),Config!$B$18*IFERROR(INDEX(Config!$C$12:$C$15,MATCH(IF(AND(D81="Cartão de crédito",N(E81)>1),"Cartão de crédito parcelado",D81),Config!$A$12:$A$15,0)),0)/30*MAX(1,N(E81)),0)) -> 0.015 | I81: =IF(OR(D81="",F81=""),"",ROUND(F81*H81,2)) -> 5.7 | J81: =IF(I81="","",F81-I81) -> 374.3 | K81: =IF(J81="","",J81/MAX(1,N(E81))) -> 374.3 | L81: =IF(OR(D81="",A81=""),"",A81+IF(AND(Config!$B$17="Sim",LEFT(D81,17)="Cartão de crédito"),1,IFERROR(INDEX(Config!$C$12:$C$15,MATCH(IF(AND(D81="Cartão de crédito",N(E81)>1),"Cartão de crédito parcelado",D81),Config!$A$12:$A$15,0)),0))) -> 46205 | M81: =IF(L81="","",IF(AND(Config!$B$17="Sim",LEFT(D81,17)="Cartão de crédito"),L81,L81+30*(MAX(1,N(E81))-1))) -> 46205 | N81: =IF(OR(L81="",K81=""),"",K81*MIN(MAX(1,N(E81)),MAX(0,INT((Config!$B$8-L81)/30)+1))) -> 374.3 | O81: =IF(J81="","",J81-N(N81)) -> 0 | P81: =IF(A81="","",MONTH(A81)) -> 7 | Q81: =IF(A81="","",YEAR(A81)) -> 2026 | R81: =IF(L81="","",IF(L81>Config!$B$8,"A cair",IF(N(G81)>=MIN(MAX(1,N(E81)),MAX(0,INT((Config!$B$8-L81)/30)+1)),IF(N(G81)>=MAX(1,N(E81)),"Conferido","Conferido até aqui"),"A conferir"))) -> Conferido | S81: =IF(R81="A conferir",(Config!$B$8-L81)*1000+N(F81)/1000+ROW()/100000,0) -> 0 | T81: =IF(R81="A conferir",N(N81),0) -> 0 | U81: =IF(L81="",0,L81) -> 46205 | V81: =IF(L81="",0,MAX(1,N(E81))) -> 1 | W81: =IF(K81="",0,K81) -> 374.3
A82: 46204 | B82: Mônica Martins | C82: Consulta | D82: Pix | F82: 380 | G82: 1 | H82: =IF(D82="","",IFERROR(INDEX(Config!$B$12:$B$15,MATCH(IF(AND(D82="Cartão de crédito",N(E82)>1),"Cartão de crédito parcelado",D82),Config!$A$12:$A$15,0)),0)+IF(AND(Config!$B$17="Sim",LEFT(D82,17)="Cartão de crédito"),Config!$B$18*IFERROR(INDEX(Config!$C$12:$C$15,MATCH(IF(AND(D82="Cartão de crédito",N(E82)>1),"Cartão de crédito parcelado",D82),Config!$A$12:$A$15,0)),0)/30*MAX(1,N(E82)),0)) -> 0 | I82: =IF(OR(D82="",F82=""),"",ROUND(F82*H82,2)) -> 0 | J82: =IF(I82="","",F82-I82) -> 380 | K82: =IF(J82="","",J82/MAX(1,N(E82))) -> 380 | L82: =IF(OR(D82="",A82=""),"",A82+IF(AND(Config!$B$17="Sim",LEFT(D82,17)="Cartão de crédito"),1,IFERROR(INDEX(Config!$C$12:$C$15,MATCH(IF(AND(D82="Cartão de crédito",N(E82)>1),"Cartão de crédito parcelado",D82),Config!$A$12:$A$15,0)),0))) -> 46204 | M82: =IF(L82="","",IF(AND(Config!$B$17="Sim",LEFT(D82,17)="Cartão de crédito"),L82,L82+30*(MAX(1,N(E82))-1))) -> 46204 | N82: =IF(OR(L82="",K82=""),"",K82*MIN(MAX(1,N(E82)),MAX(0,INT((Config!$B$8-L82)/30)+1))) -> 380 | O82: =IF(J82="","",J82-N(N82)) -> 0 | P82: =IF(A82="","",MONTH(A82)) -> 7 | Q82: =IF(A82="","",YEAR(A82)) -> 2026 | R82: =IF(L82="","",IF(L82>Config!$B$8,"A cair",IF(N(G82)>=MIN(MAX(1,N(E82)),MAX(0,INT((Config!$B$8-L82)/30)+1)),IF(N(G82)>=MAX(1,N(E82)),"Conferido","Conferido até aqui"),"A conferir"))) -> Conferido | S82: =IF(R82="A conferir",(Config!$B$8-L82)*1000+N(F82)/1000+ROW()/100000,0) -> 0 | T82: =IF(R82="A conferir",N(N82),0) -> 0 | U82: =IF(L82="",0,L82) -> 46204 | V82: =IF(L82="",0,MAX(1,N(E82))) -> 1 | W82: =IF(K82="",0,K82) -> 380
A83: 46205 | B83: Débora Ramos | C83: Consulta | D83: Cartão de crédito | F83: 380 | G83: 1 | H83: =IF(D83="","",IFERROR(INDEX(Config!$B$12:$B$15,MATCH(IF(AND(D83="Cartão de crédito",N(E83)>1),"Cartão de crédito parcelado",D83),Config!$A$12:$A$15,0)),0)+IF(AND(Config!$B$17="Sim",LEFT(D83,17)="Cartão de crédito"),Config!$B$18*IFERROR(INDEX(Config!$C$12:$C$15,MATCH(IF(AND(D83="Cartão de crédito",N(E83)>1),"Cartão de crédito parcelado",D83),Config!$A$12:$A$15,0)),0)/30*MAX(1,N(E83)),0)) -> 0.032 | I83: =IF(OR(D83="",F83=""),"",ROUND(F83*H83,2)) -> 12.16 | J83: =IF(I83="","",F83-I83) -> 367.84 | K83: =IF(J83="","",J83/MAX(1,N(E83))) -> 367.84 | L83: =IF(OR(D83="",A83=""),"",A83+IF(AND(Config!$B$17="Sim",LEFT(D83,17)="Cartão de crédito"),1,IFERROR(INDEX(Config!$C$12:$C$15,MATCH(IF(AND(D83="Cartão de crédito",N(E83)>1),"Cartão de crédito parcelado",D83),Config!$A$12:$A$15,0)),0))) -> 46235 | M83: =IF(L83="","",IF(AND(Config!$B$17="Sim",LEFT(D83,17)="Cartão de crédito"),L83,L83+30*(MAX(1,N(E83))-1))) -> 46235 | N83: =IF(OR(L83="",K83=""),"",K83*MIN(MAX(1,N(E83)),MAX(0,INT((Config!$B$8-L83)/30)+1))) -> 367.84 | O83: =IF(J83="","",J83-N(N83)) -> 0 | P83: =IF(A83="","",MONTH(A83)) -> 7 | Q83: =IF(A83="","",YEAR(A83)) -> 2026 | R83: =IF(L83="","",IF(L83>Config!$B$8,"A cair",IF(N(G83)>=MIN(MAX(1,N(E83)),MAX(0,INT((Config!$B$8-L83)/30)+1)),IF(N(G83)>=MAX(1,N(E83)),"Conferido","Conferido até aqui"),"A conferir"))) -> Conferido | S83: =IF(R83="A conferir",(Config!$B$8-L83)*1000+N(F83)/1000+ROW()/100000,0) -> 0 | T83: =IF(R83="A conferir",N(N83),0) -> 0 | U83: =IF(L83="",0,L83) -> 46235 | V83: =IF(L83="",0,MAX(1,N(E83))) -> 1 | W83: =IF(K83="",0,K83) -> 367.84
A84: 46205 | B84: Mariana Nascimento | C84: Consulta | D84: Cartão de crédito | F84: 380 | G84: 1 | H84: =IF(D84="","",IFERROR(INDEX(Config!$B$12:$B$15,MATCH(IF(AND(D84="Cartão de crédito",N(E84)>1),"Cartão de crédito parcelado",D84),Config!$A$12:$A$15,0)),0)+IF(AND(Config!$B$17="Sim",LEFT(D84,17)="Cartão de crédito"),Config!$B$18*IFERROR(INDEX(Config!$C$12:$C$15,MATCH(IF(AND(D84="Cartão de crédito",N(E84)>1),"Cartão de crédito parcelado",D84),Config!$A$12:$A$15,0)),0)/30*MAX(1,N(E84)),0)) -> 0.032 | I84: =IF(OR(D84="",F84=""),"",ROUND(F84*H84,2)) -> 12.16 | J84: =IF(I84="","",F84-I84) -> 367.84 | K84: =IF(J84="","",J84/MAX(1,N(E84))) -> 367.84 | L84: =IF(OR(D84="",A84=""),"",A84+IF(AND(Config!$B$17="Sim",LEFT(D84,17)="Cartão de crédito"),1,IFERROR(INDEX(Config!$C$12:$C$15,MATCH(IF(AND(D84="Cartão de crédito",N(E84)>1),"Cartão de crédito parcelado",D84),Config!$A$12:$A$15,0)),0))) -> 46235 | M84: =IF(L84="","",IF(AND(Config!$B$17="Sim",LEFT(D84,17)="Cartão de crédito"),L84,L84+30*(MAX(1,N(E84))-1))) -> 46235 | N84: =IF(OR(L84="",K84=""),"",K84*MIN(MAX(1,N(E84)),MAX(0,INT((Config!$B$8-L84)/30)+1))) -> 367.84 | O84: =IF(J84="","",J84-N(N84)) -> 0 | P84: =IF(A84="","",MONTH(A84)) -> 7 | Q84: =IF(A84="","",YEAR(A84)) -> 2026 | R84: =IF(L84="","",IF(L84>Config!$B$8,"A cair",IF(N(G84)>=MIN(MAX(1,N(E84)),MAX(0,INT((Config!$B$8-L84)/30)+1)),IF(N(G84)>=MAX(1,N(E84)),"Conferido","Conferido até aqui"),"A conferir"))) -> Conferido | S84: =IF(R84="A conferir",(Config!$B$8-L84)*1000+N(F84)/1000+ROW()/100000,0) -> 0 | T84: =IF(R84="A conferir",N(N84),0) -> 0 | U84: =IF(L84="",0,L84) -> 46235 | V84: =IF(L84="",0,MAX(1,N(E84))) -> 1 | W84: =IF(K84="",0,K84) -> 367.84
A85: 46205 | B85: Helena Moreira | C85: Consulta | D85: Cartão de crédito | F85: 380 | G85: 1 | H85: =IF(D85="","",IFERROR(INDEX(Config!$B$12:$B$15,MATCH(IF(AND(D85="Cartão de crédito",N(E85)>1),"Cartão de crédito parcelado",D85),Config!$A$12:$A$15,0)),0)+IF(AND(Config!$B$17="Sim",LEFT(D85,17)="Cartão de crédito"),Config!$B$18*IFERROR(INDEX(Config!$C$12:$C$15,MATCH(IF(AND(D85="Cartão de crédito",N(E85)>1),"Cartão de crédito parcelado",D85),Config!$A$12:$A$15,0)),0)/30*MAX(1,N(E85)),0)) -> 0.032 | I85: =IF(OR(D85="",F85=""),"",ROUND(F85*H85,2)) -> 12.16 | J85: =IF(I85="","",F85-I85) -> 367.84 | K85: =IF(J85="","",J85/MAX(1,N(E85))) -> 367.84 | L85: =IF(OR(D85="",A85=""),"",A85+IF(AND(Config!$B$17="Sim",LEFT(D85,17)="Cartão de crédito"),1,IFERROR(INDEX(Config!$C$12:$C$15,MATCH(IF(AND(D85="Cartão de crédito",N(E85)>1),"Cartão de crédito parcelado",D85),Config!$A$12:$A$15,0)),0))) -> 46235 | M85: =IF(L85="","",IF(AND(Config!$B$17="Sim",LEFT(D85,17)="Cartão de crédito"),L85,L85+30*(MAX(1,N(E85))-1))) -> 46235 | N85: =IF(OR(L85="",K85=""),"",K85*MIN(MAX(1,N(E85)),MAX(0,INT((Config!$B$8-L85)/30)+1))) -> 367.84 | O85: =IF(J85="","",J85-N(N85)) -> 0 | P85: =IF(A85="","",MONTH(A85)) -> 7 | Q85: =IF(A85="","",YEAR(A85)) -> 2026 | R85: =IF(L85="","",IF(L85>Config!$B$8,"A cair",IF(N(G85)>=MIN(MAX(1,N(E85)),MAX(0,INT((Config!$B$8-L85)/30)+1)),IF(N(G85)>=MAX(1,N(E85)),"Conferido","Conferido até aqui"),"A conferir"))) -> Conferido | S85: =IF(R85="A conferir",(Config!$B$8-L85)*1000+N(F85)/1000+ROW()/100000,0) -> 0 | T85: =IF(R85="A conferir",N(N85),0) -> 0 | U85: =IF(L85="",0,L85) -> 46235 | V85: =IF(L85="",0,MAX(1,N(E85))) -> 1 | W85: =IF(K85="",0,K85) -> 367.84
A86: 46205 | B86: Gabriel Oliveira | C86: ECG | D86: Pix | F86: 130 | G86: 1 | H86: =IF(D86="","",IFERROR(INDEX(Config!$B$12:$B$15,MATCH(IF(AND(D86="Cartão de crédito",N(E86)>1),"Cartão de crédito parcelado",D86),Config!$A$12:$A$15,0)),0)+IF(AND(Config!$B$17="Sim",LEFT(D86,17)="Cartão de crédito"),Config!$B$18*IFERROR(INDEX(Config!$C$12:$C$15,MATCH(IF(AND(D86="Cartão de crédito",N(E86)>1),"Cartão de crédito parcelado",D86),Config!$A$12:$A$15,0)),0)/30*MAX(1,N(E86)),0)) -> 0 | I86: =IF(OR(D86="",F86=""),"",ROUND(F86*H86,2)) -> 0 | J86: =IF(I86="","",F86-I86) -> 130 | K86: =IF(J86="","",J86/MAX(1,N(E86))) -> 130 | L86: =IF(OR(D86="",A86=""),"",A86+IF(AND(Config!$B$17="Sim",LEFT(D86,17)="Cartão de crédito"),1,IFERROR(INDEX(Config!$C$12:$C$15,MATCH(IF(AND(D86="Cartão de crédito",N(E86)>1),"Cartão de crédito parcelado",D86),Config!$A$12:$A$15,0)),0))) -> 46205 | M86: =IF(L86="","",IF(AND(Config!$B$17="Sim",LEFT(D86,17)="Cartão de crédito"),L86,L86+30*(MAX(1,N(E86))-1))) -> 46205 | N86: =IF(OR(L86="",K86=""),"",K86*MIN(MAX(1,N(E86)),MAX(0,INT((Config!$B$8-L86)/30)+1))) -> 130 | O86: =IF(J86="","",J86-N(N86)) -> 0 | P86: =IF(A86="","",MONTH(A86)) -> 7 | Q86: =IF(A86="","",YEAR(A86)) -> 2026 | R86: =IF(L86="","",IF(L86>Config!$B$8,"A cair",IF(N(G86)>=MIN(MAX(1,N(E86)),MAX(0,INT((Config!$B$8-L86)/30)+1)),IF(N(G86)>=MAX(1,N(E86)),"Conferido","Conferido até aqui"),"A conferir"))) -> Conferido | S86: =IF(R86="A conferir",(Config!$B$8-L86)*1000+N(F86)/1000+ROW()/100000,0) -> 0 | T86: =IF(R86="A conferir",N(N86),0) -> 0 | U86: =IF(L86="",0,L86) -> 46205 | V86: =IF(L86="",0,MAX(1,N(E86))) -> 1 | W86: =IF(K86="",0,K86) -> 130
A87: 46205 | B87: Beatriz Monteiro | C87: Avaliação endócrina | D87: Cartão de crédito | E87: 2 | F87: 400 | G87: 2 | H87: =IF(D87="","",IFERROR(INDEX(Config!$B$12:$B$15,MATCH(IF(AND(D87="Cartão de crédito",N(E87)>1),"Cartão de crédito parcelado",D87),Config!$A$12:$A$15,0)),0)+IF(AND(Config!$B$17="Sim",LEFT(D87,17)="Cartão de crédito"),Config!$B$18*IFERROR(INDEX(Config!$C$12:$C$15,MATCH(IF(AND(D87="Cartão de crédito",N(E87)>1),"Cartão de crédito parcelado",D87),Config!$A$12:$A$15,0)),0)/30*MAX(1,N(E87)),0)) -> 0.039 | I87: =IF(OR(D87="",F87=""),"",ROUND(F87*H87,2)) -> 15.6 | J87: =IF(I87="","",F87-I87) -> 384.4 | K87: =IF(J87="","",J87/MAX(1,N(E87))) -> 192.2 | L87: =IF(OR(D87="",A87=""),"",A87+IF(AND(Config!$B$17="Sim",LEFT(D87,17)="Cartão de crédito"),1,IFERROR(INDEX(Config!$C$12:$C$15,MATCH(IF(AND(D87="Cartão de crédito",N(E87)>1),"Cartão de crédito parcelado",D87),Config!$A$12:$A$15,0)),0))) -> 46235 | M87: =IF(L87="","",IF(AND(Config!$B$17="Sim",LEFT(D87,17)="Cartão de crédito"),L87,L87+30*(MAX(1,N(E87))-1))) -> 46265 | N87: =IF(OR(L87="",K87=""),"",K87*MIN(MAX(1,N(E87)),MAX(0,INT((Config!$B$8-L87)/30)+1))) -> 384.4 | O87: =IF(J87="","",J87-N(N87)) -> 0 | P87: =IF(A87="","",MONTH(A87)) -> 7 | Q87: =IF(A87="","",YEAR(A87)) -> 2026 | R87: =IF(L87="","",IF(L87>Config!$B$8,"A cair",IF(N(G87)>=MIN(MAX(1,N(E87)),MAX(0,INT((Config!$B$8-L87)/30)+1)),IF(N(G87)>=MAX(1,N(E87)),"Conferido","Conferido até aqui"),"A conferir"))) -> Conferido | S87: =IF(R87="A conferir",(Config!$B$8-L87)*1000+N(F87)/1000+ROW()/100000,0) -> 0 | T87: =IF(R87="A conferir",N(N87),0) -> 0 | U87: =IF(L87="",0,L87) -> 46235 | V87: =IF(L87="",0,MAX(1,N(E87))) -> 2 | W87: =IF(K87="",0,K87) -> 192.2
A88: 46206 | B88: Renato Dias | C88: ECG | D88: Pix | F88: 130 | G88: 1 | H88: =IF(D88="","",IFERROR(INDEX(Config!$B$12:$B$15,MATCH(IF(AND(D88="Cartão de crédito",N(E88)>1),"Cartão de crédito parcelado",D88),Config!$A$12:$A$15,0)),0)+IF(AND(Config!$B$17="Sim",LEFT(D88,17)="Cartão de crédito"),Config!$B$18*IFERROR(INDEX(Config!$C$12:$C$15,MATCH(IF(AND(D88="Cartão de crédito",N(E88)>1),"Cartão de crédito parcelado",D88),Config!$A$12:$A$15,0)),0)/30*MAX(1,N(E88)),0)) -> 0 | I88: =IF(OR(D88="",F88=""),"",ROUND(F88*H88,2)) -> 0 | J88: =IF(I88="","",F88-I88) -> 130 | K88: =IF(J88="","",J88/MAX(1,N(E88))) -> 130 | L88: =IF(OR(D88="",A88=""),"",A88+IF(AND(Config!$B$17="Sim",LEFT(D88,17)="Cartão de crédito"),1,IFERROR(INDEX(Config!$C$12:$C$15,MATCH(IF(AND(D88="Cartão de crédito",N(E88)>1),"Cartão de crédito parcelado",D88),Config!$A$12:$A$15,0)),0))) -> 46206 | M88: =IF(L88="","",IF(AND(Config!$B$17="Sim",LEFT(D88,17)="Cartão de crédito"),L88,L88+30*(MAX(1,N(E88))-1))) -> 46206 | N88: =IF(OR(L88="",K88=""),"",K88*MIN(MAX(1,N(E88)),MAX(0,INT((Config!$B$8-L88)/30)+1))) -> 130 | O88: =IF(J88="","",J88-N(N88)) -> 0 | P88: =IF(A88="","",MONTH(A88)) -> 7 | Q88: =IF(A88="","",YEAR(A88)) -> 2026 | R88: =IF(L88="","",IF(L88>Config!$B$8,"A cair",IF(N(G88)>=MIN(MAX(1,N(E88)),MAX(0,INT((Config!$B$8-L88)/30)+1)),IF(N(G88)>=MAX(1,N(E88)),"Conferido","Conferido até aqui"),"A conferir"))) -> Conferido | S88: =IF(R88="A conferir",(Config!$B$8-L88)*1000+N(F88)/1000+ROW()/100000,0) -> 0 | T88: =IF(R88="A conferir",N(N88),0) -> 0 | U88: =IF(L88="",0,L88) -> 46206 | V88: =IF(L88="",0,MAX(1,N(E88))) -> 1 | W88: =IF(K88="",0,K88) -> 130
A89: 46206 | B89: Wagner Costa | C89: Consulta | D89: Pix | F89: 380 | G89: 1 | H89: =IF(D89="","",IFERROR(INDEX(Config!$B$12:$B$15,MATCH(IF(AND(D89="Cartão de crédito",N(E89)>1),"Cartão de crédito parcelado",D89),Config!$A$12:$A$15,0)),0)+IF(AND(Config!$B$17="Sim",LEFT(D89,17)="Cartão de crédito"),Config!$B$18*IFERROR(INDEX(Config!$C$12:$C$15,MATCH(IF(AND(D89="Cartão de crédito",N(E89)>1),"Cartão de crédito parcelado",D89),Config!$A$12:$A$15,0)),0)/30*MAX(1,N(E89)),0)) -> 0 | I89: =IF(OR(D89="",F89=""),"",ROUND(F89*H89,2)) -> 0 | J89: =IF(I89="","",F89-I89) -> 380 | K89: =IF(J89="","",J89/MAX(1,N(E89))) -> 380 | L89: =IF(OR(D89="",A89=""),"",A89+IF(AND(Config!$B$17="Sim",LEFT(D89,17)="Cartão de crédito"),1,IFERROR(INDEX(Config!$C$12:$C$15,MATCH(IF(AND(D89="Cartão de crédito",N(E89)>1),"Cartão de crédito parcelado",D89),Config!$A$12:$A$15,0)),0))) -> 46206 | M89: =IF(L89="","",IF(AND(Config!$B$17="Sim",LEFT(D89,17)="Cartão de crédito"),L89,L89+30*(MAX(1,N(E89))-1))) -> 46206 | N89: =IF(OR(L89="",K89=""),"",K89*MIN(MAX(1,N(E89)),MAX(0,INT((Config!$B$8-L89)/30)+1))) -> 380 | O89: =IF(J89="","",J89-N(N89)) -> 0 | P89: =IF(A89="","",MONTH(A89)) -> 7 | Q89: =IF(A89="","",YEAR(A89)) -> 2026 | R89: =IF(L89="","",IF(L89>Config!$B$8,"A cair",IF(N(G89)>=MIN(MAX(1,N(E89)),MAX(0,INT((Config!$B$8-L89)/30)+1)),IF(N(G89)>=MAX(1,N(E89)),"Conferido","Conferido até aqui"),"A conferir"))) -> Conferido | S89: =IF(R89="A conferir",(Config!$B$8-L89)*1000+N(F89)/1000+ROW()/100000,0) -> 0 | T89: =IF(R89="A conferir",N(N89),0) -> 0 | U89: =IF(L89="",0,L89) -> 46206 | V89: =IF(L89="",0,MAX(1,N(E89))) -> 1 | W89: =IF(K89="",0,K89) -> 380
A90: 46209 | B90: Wagner Lima | C90: Consulta | D90: Cartão de crédito | E90: 2 | F90: 380 | G90: 2 | H90: =IF(D90="","",IFERROR(INDEX(Config!$B$12:$B$15,MATCH(IF(AND(D90="Cartão de crédito",N(E90)>1),"Cartão de crédito parcelado",D90),Config!$A$12:$A$15,0)),0)+IF(AND(Config!$B$17="Sim",LEFT(D90,17)="Cartão de crédito"),Config!$B$18*IFERROR(INDEX(Config!$C$12:$C$15,MATCH(IF(AND(D90="Cartão de crédito",N(E90)>1),"Cartão de crédito parcelado",D90),Config!$A$12:$A$15,0)),0)/30*MAX(1,N(E90)),0)) -> 0.039 | I90: =IF(OR(D90="",F90=""),"",ROUND(F90*H90,2)) -> 14.82 | J90: =IF(I90="","",F90-I90) -> 365.18 | K90: =IF(J90="","",J90/MAX(1,N(E90))) -> 182.59 | L90: =IF(OR(D90="",A90=""),"",A90+IF(AND(Config!$B$17="Sim",LEFT(D90,17)="Cartão de crédito"),1,IFERROR(INDEX(Config!$C$12:$C$15,MATCH(IF(AND(D90="Cartão de crédito",N(E90)>1),"Cartão de crédito parcelado",D90),Config!$A$12:$A$15,0)),0))) -> 46239 | M90: =IF(L90="","",IF(AND(Config!$B$17="Sim",LEFT(D90,17)="Cartão de crédito"),L90,L90+30*(MAX(1,N(E90))-1))) -> 46269 | N90: =IF(OR(L90="",K90=""),"",K90*MIN(MAX(1,N(E90)),MAX(0,INT((Config!$B$8-L90)/30)+1))) -> 365.18 | O90: =IF(J90="","",J90-N(N90)) -> 0 | P90: =IF(A90="","",MONTH(A90)) -> 7 | Q90: =IF(A90="","",YEAR(A90)) -> 2026 | R90: =IF(L90="","",IF(L90>Config!$B$8,"A cair",IF(N(G90)>=MIN(MAX(1,N(E90)),MAX(0,INT((Config!$B$8-L90)/30)+1)),IF(N(G90)>=MAX(1,N(E90)),"Conferido","Conferido até aqui"),"A conferir"))) -> Conferido | S90: =IF(R90="A conferir",(Config!$B$8-L90)*1000+N(F90)/1000+ROW()/100000,0) -> 0 | T90: =IF(R90="A conferir",N(N90),0) -> 0 | U90: =IF(L90="",0,L90) -> 46239 | V90: =IF(L90="",0,MAX(1,N(E90))) -> 2 | W90: =IF(K90="",0,K90) -> 182.59
A91: 46209 | B91: Paulo Reis | C91: Consulta | D91: Cartão de crédito | F91: 380 | G91: 1 | H91: =IF(D91="","",IFERROR(INDEX(Config!$B$12:$B$15,MATCH(IF(AND(D91="Cartão de crédito",N(E91)>1),"Cartão de crédito parcelado",D91),Config!$A$12:$A$15,0)),0)+IF(AND(Config!$B$17="Sim",LEFT(D91,17)="Cartão de crédito"),Config!$B$18*IFERROR(INDEX(Config!$C$12:$C$15,MATCH(IF(AND(D91="Cartão de crédito",N(E91)>1),"Cartão de crédito parcelado",D91),Config!$A$12:$A$15,0)),0)/30*MAX(1,N(E91)),0)) -> 0.032 | I91: =IF(OR(D91="",F91=""),"",ROUND(F91*H91,2)) -> 12.16 | J91: =IF(I91="","",F91-I91) -> 367.84 | K91: =IF(J91="","",J91/MAX(1,N(E91))) -> 367.84 | L91: =IF(OR(D91="",A91=""),"",A91+IF(AND(Config!$B$17="Sim",LEFT(D91,17)="Cartão de crédito"),1,IFERROR(INDEX(Config!$C$12:$C$15,MATCH(IF(AND(D91="Cartão de crédito",N(E91)>1),"Cartão de crédito parcelado",D91),Config!$A$12:$A$15,0)),0))) -> 46239 | M91: =IF(L91="","",IF(AND(Config!$B$17="Sim",LEFT(D91,17)="Cartão de crédito"),L91,L91+30*(MAX(1,N(E91))-1))) -> 46239 | N91: =IF(OR(L91="",K91=""),"",K91*MIN(MAX(1,N(E91)),MAX(0,INT((Config!$B$8-L91)/30)+1))) -> 367.84 | O91: =IF(J91="","",J91-N(N91)) -> 0 | P91: =IF(A91="","",MONTH(A91)) -> 7 | Q91: =IF(A91="","",YEAR(A91)) -> 2026 | R91: =IF(L91="","",IF(L91>Config!$B$8,"A cair",IF(N(G91)>=MIN(MAX(1,N(E91)),MAX(0,INT((Config!$B$8-L91)/30)+1)),IF(N(G91)>=MAX(1,N(E91)),"Conferido","Conferido até aqui"),"A conferir"))) -> Conferido | S91: =IF(R91="A conferir",(Config!$B$8-L91)*1000+N(F91)/1000+ROW()/100000,0) -> 0 | T91: =IF(R91="A conferir",N(N91),0) -> 0 | U91: =IF(L91="",0,L91) -> 46239 | V91: =IF(L91="",0,MAX(1,N(E91))) -> 1 | W91: =IF(K91="",0,K91) -> 367.84
A92: 46210 | B92: Marcelo Santos | C92: Consulta | D92: Pix | F92: 380 | G92: 1 | H92: =IF(D92="","",IFERROR(INDEX(Config!$B$12:$B$15,MATCH(IF(AND(D92="Cartão de crédito",N(E92)>1),"Cartão de crédito parcelado",D92),Config!$A$12:$A$15,0)),0)+IF(AND(Config!$B$17="Sim",LEFT(D92,17)="Cartão de crédito"),Config!$B$18*IFERROR(INDEX(Config!$C$12:$C$15,MATCH(IF(AND(D92="Cartão de crédito",N(E92)>1),"Cartão de crédito parcelado",D92),Config!$A$12:$A$15,0)),0)/30*MAX(1,N(E92)),0)) -> 0 | I92: =IF(OR(D92="",F92=""),"",ROUND(F92*H92,2)) -> 0 | J92: =IF(I92="","",F92-I92) -> 380 | K92: =IF(J92="","",J92/MAX(1,N(E92))) -> 380 | L92: =IF(OR(D92="",A92=""),"",A92+IF(AND(Config!$B$17="Sim",LEFT(D92,17)="Cartão de crédito"),1,IFERROR(INDEX(Config!$C$12:$C$15,MATCH(IF(AND(D92="Cartão de crédito",N(E92)>1),"Cartão de crédito parcelado",D92),Config!$A$12:$A$15,0)),0))) -> 46210 | M92: =IF(L92="","",IF(AND(Config!$B$17="Sim",LEFT(D92,17)="Cartão de crédito"),L92,L92+30*(MAX(1,N(E92))-1))) -> 46210 | N92: =IF(OR(L92="",K92=""),"",K92*MIN(MAX(1,N(E92)),MAX(0,INT((Config!$B$8-L92)/30)+1))) -> 380 | O92: =IF(J92="","",J92-N(N92)) -> 0 | P92: =IF(A92="","",MONTH(A92)) -> 7 | Q92: =IF(A92="","",YEAR(A92)) -> 2026 | R92: =IF(L92="","",IF(L92>Config!$B$8,"A cair",IF(N(G92)>=MIN(MAX(1,N(E92)),MAX(0,INT((Config!$B$8-L92)/30)+1)),IF(N(G92)>=MAX(1,N(E92)),"Conferido","Conferido até aqui"),"A conferir"))) -> Conferido | S92: =IF(R92="A conferir",(Config!$B$8-L92)*1000+N(F92)/1000+ROW()/100000,0) -> 0 | T92: =IF(R92="A conferir",N(N92),0) -> 0 | U92: =IF(L92="",0,L92) -> 46210 | V92: =IF(L92="",0,MAX(1,N(E92))) -> 1 | W92: =IF(K92="",0,K92) -> 380
A93: 46210 | B93: Regina Teixeira | C93: Consulta | D93: Pix | F93: 380 | G93: 1 | H93: =IF(D93="","",IFERROR(INDEX(Config!$B$12:$B$15,MATCH(IF(AND(D93="Cartão de crédito",N(E93)>1),"Cartão de crédito parcelado",D93),Config!$A$12:$A$15,0)),0)+IF(AND(Config!$B$17="Sim",LEFT(D93,17)="Cartão de crédito"),Config!$B$18*IFERROR(INDEX(Config!$C$12:$C$15,MATCH(IF(AND(D93="Cartão de crédito",N(E93)>1),"Cartão de crédito parcelado",D93),Config!$A$12:$A$15,0)),0)/30*MAX(1,N(E93)),0)) -> 0 | I93: =IF(OR(D93="",F93=""),"",ROUND(F93*H93,2)) -> 0 | J93: =IF(I93="","",F93-I93) -> 380 | K93: =IF(J93="","",J93/MAX(1,N(E93))) -> 380 | L93: =IF(OR(D93="",A93=""),"",A93+IF(AND(Config!$B$17="Sim",LEFT(D93,17)="Cartão de crédito"),1,IFERROR(INDEX(Config!$C$12:$C$15,MATCH(IF(AND(D93="Cartão de crédito",N(E93)>1),"Cartão de crédito parcelado",D93),Config!$A$12:$A$15,0)),0))) -> 46210 | M93: =IF(L93="","",IF(AND(Config!$B$17="Sim",LEFT(D93,17)="Cartão de crédito"),L93,L93+30*(MAX(1,N(E93))-1))) -> 46210 | N93: =IF(OR(L93="",K93=""),"",K93*MIN(MAX(1,N(E93)),MAX(0,INT((Config!$B$8-L93)/30)+1))) -> 380 | O93: =IF(J93="","",J93-N(N93)) -> 0 | P93: =IF(A93="","",MONTH(A93)) -> 7 | Q93: =IF(A93="","",YEAR(A93)) -> 2026 | R93: =IF(L93="","",IF(L93>Config!$B$8,"A cair",IF(N(G93)>=MIN(MAX(1,N(E93)),MAX(0,INT((Config!$B$8-L93)/30)+1)),IF(N(G93)>=MAX(1,N(E93)),"Conferido","Conferido até aqui"),"A conferir"))) -> Conferido | S93: =IF(R93="A conferir",(Config!$B$8-L93)*1000+N(F93)/1000+ROW()/100000,0) -> 0 | T93: =IF(R93="A conferir",N(N93),0) -> 0 | U93: =IF(L93="",0,L93) -> 46210 | V93: =IF(L93="",0,MAX(1,N(E93))) -> 1 | W93: =IF(K93="",0,K93) -> 380
A94: 46210 | B94: Gisele Ribeiro | C94: Consulta | D94: Pix | F94: 380 | G94: 1 | H94: =IF(D94="","",IFERROR(INDEX(Config!$B$12:$B$15,MATCH(IF(AND(D94="Cartão de crédito",N(E94)>1),"Cartão de crédito parcelado",D94),Config!$A$12:$A$15,0)),0)+IF(AND(Config!$B$17="Sim",LEFT(D94,17)="Cartão de crédito"),Config!$B$18*IFERROR(INDEX(Config!$C$12:$C$15,MATCH(IF(AND(D94="Cartão de crédito",N(E94)>1),"Cartão de crédito parcelado",D94),Config!$A$12:$A$15,0)),0)/30*MAX(1,N(E94)),0)) -> 0 | I94: =IF(OR(D94="",F94=""),"",ROUND(F94*H94,2)) -> 0 | J94: =IF(I94="","",F94-I94) -> 380 | K94: =IF(J94="","",J94/MAX(1,N(E94))) -> 380 | L94: =IF(OR(D94="",A94=""),"",A94+IF(AND(Config!$B$17="Sim",LEFT(D94,17)="Cartão de crédito"),1,IFERROR(INDEX(Config!$C$12:$C$15,MATCH(IF(AND(D94="Cartão de crédito",N(E94)>1),"Cartão de crédito parcelado",D94),Config!$A$12:$A$15,0)),0))) -> 46210 | M94: =IF(L94="","",IF(AND(Config!$B$17="Sim",LEFT(D94,17)="Cartão de crédito"),L94,L94+30*(MAX(1,N(E94))-1))) -> 46210 | N94: =IF(OR(L94="",K94=""),"",K94*MIN(MAX(1,N(E94)),MAX(0,INT((Config!$B$8-L94)/30)+1))) -> 380 | O94: =IF(J94="","",J94-N(N94)) -> 0 | P94: =IF(A94="","",MONTH(A94)) -> 7 | Q94: =IF(A94="","",YEAR(A94)) -> 2026 | R94: =IF(L94="","",IF(L94>Config!$B$8,"A cair",IF(N(G94)>=MIN(MAX(1,N(E94)),MAX(0,INT((Config!$B$8-L94)/30)+1)),IF(N(G94)>=MAX(1,N(E94)),"Conferido","Conferido até aqui"),"A conferir"))) -> Conferido | S94: =IF(R94="A conferir",(Config!$B$8-L94)*1000+N(F94)/1000+ROW()/100000,0) -> 0 | T94: =IF(R94="A conferir",N(N94),0) -> 0 | U94: =IF(L94="",0,L94) -> 46210 | V94: =IF(L94="",0,MAX(1,N(E94))) -> 1 | W94: =IF(K94="",0,K94) -> 380
A95: 46210 | B95: Beatriz Reis | C95: Avaliação endócrina | D95: Pix | F95: 400 | G95: 1 | H95: =IF(D95="","",IFERROR(INDEX(Config!$B$12:$B$15,MATCH(IF(AND(D95="Cartão de crédito",N(E95)>1),"Cartão de crédito parcelado",D95),Config!$A$12:$A$15,0)),0)+IF(AND(Config!$B$17="Sim",LEFT(D95,17)="Cartão de crédito"),Config!$B$18*IFERROR(INDEX(Config!$C$12:$C$15,MATCH(IF(AND(D95="Cartão de crédito",N(E95)>1),"Cartão de crédito parcelado",D95),Config!$A$12:$A$15,0)),0)/30*MAX(1,N(E95)),0)) -> 0 | I95: =IF(OR(D95="",F95=""),"",ROUND(F95*H95,2)) -> 0 | J95: =IF(I95="","",F95-I95) -> 400 | K95: =IF(J95="","",J95/MAX(1,N(E95))) -> 400 | L95: =IF(OR(D95="",A95=""),"",A95+IF(AND(Config!$B$17="Sim",LEFT(D95,17)="Cartão de crédito"),1,IFERROR(INDEX(Config!$C$12:$C$15,MATCH(IF(AND(D95="Cartão de crédito",N(E95)>1),"Cartão de crédito parcelado",D95),Config!$A$12:$A$15,0)),0))) -> 46210 | M95: =IF(L95="","",IF(AND(Config!$B$17="Sim",LEFT(D95,17)="Cartão de crédito"),L95,L95+30*(MAX(1,N(E95))-1))) -> 46210 | N95: =IF(OR(L95="",K95=""),"",K95*MIN(MAX(1,N(E95)),MAX(0,INT((Config!$B$8-L95)/30)+1))) -> 400 | O95: =IF(J95="","",J95-N(N95)) -> 0 | P95: =IF(A95="","",MONTH(A95)) -> 7 | Q95: =IF(A95="","",YEAR(A95)) -> 2026 | R95: =IF(L95="","",IF(L95>Config!$B$8,"A cair",IF(N(G95)>=MIN(MAX(1,N(E95)),MAX(0,INT((Config!$B$8-L95)/30)+1)),IF(N(G95)>=MAX(1,N(E95)),"Conferido","Conferido até aqui"),"A conferir"))) -> Conferido | S95: =IF(R95="A conferir",(Config!$B$8-L95)*1000+N(F95)/1000+ROW()/100000,0) -> 0 | T95: =IF(R95="A conferir",N(N95),0) -> 0 | U95: =IF(L95="",0,L95) -> 46210 | V95: =IF(L95="",0,MAX(1,N(E95))) -> 1 | W95: =IF(K95="",0,K95) -> 400
A96: 46210 | B96: Marcelo Ferreira | C96: Consulta | D96: Cartão de crédito | F96: 380 | G96: 1 | H96: =IF(D96="","",IFERROR(INDEX(Config!$B$12:$B$15,MATCH(IF(AND(D96="Cartão de crédito",N(E96)>1),"Cartão de crédito parcelado",D96),Config!$A$12:$A$15,0)),0)+IF(AND(Config!$B$17="Sim",LEFT(D96,17)="Cartão de crédito"),Config!$B$18*IFERROR(INDEX(Config!$C$12:$C$15,MATCH(IF(AND(D96="Cartão de crédito",N(E96)>1),"Cartão de crédito parcelado",D96),Config!$A$12:$A$15,0)),0)/30*MAX(1,N(E96)),0)) -> 0.032 | I96: =IF(OR(D96="",F96=""),"",ROUND(F96*H96,2)) -> 12.16 | J96: =IF(I96="","",F96-I96) -> 367.84 | K96: =IF(J96="","",J96/MAX(1,N(E96))) -> 367.84 | L96: =IF(OR(D96="",A96=""),"",A96+IF(AND(Config!$B$17="Sim",LEFT(D96,17)="Cartão de crédito"),1,IFERROR(INDEX(Config!$C$12:$C$15,MATCH(IF(AND(D96="Cartão de crédito",N(E96)>1),"Cartão de crédito parcelado",D96),Config!$A$12:$A$15,0)),0))) -> 46240 | M96: =IF(L96="","",IF(AND(Config!$B$17="Sim",LEFT(D96,17)="Cartão de crédito"),L96,L96+30*(MAX(1,N(E96))-1))) -> 46240 | N96: =IF(OR(L96="",K96=""),"",K96*MIN(MAX(1,N(E96)),MAX(0,INT((Config!$B$8-L96)/30)+1))) -> 367.84 | O96: =IF(J96="","",J96-N(N96)) -> 0 | P96: =IF(A96="","",MONTH(A96)) -> 7 | Q96: =IF(A96="","",YEAR(A96)) -> 2026 | R96: =IF(L96="","",IF(L96>Config!$B$8,"A cair",IF(N(G96)>=MIN(MAX(1,N(E96)),MAX(0,INT((Config!$B$8-L96)/30)+1)),IF(N(G96)>=MAX(1,N(E96)),"Conferido","Conferido até aqui"),"A conferir"))) -> Conferido | S96: =IF(R96="A conferir",(Config!$B$8-L96)*1000+N(F96)/1000+ROW()/100000,0) -> 0 | T96: =IF(R96="A conferir",N(N96),0) -> 0 | U96: =IF(L96="",0,L96) -> 46240 | V96: =IF(L96="",0,MAX(1,N(E96))) -> 1 | W96: =IF(K96="",0,K96) -> 367.84
A97: 46210 | B97: Lucas Cardoso | C97: Consulta | D97: Cartão de crédito | F97: 380 | G97: 1 | H97: =IF(D97="","",IFERROR(INDEX(Config!$B$12:$B$15,MATCH(IF(AND(D97="Cartão de crédito",N(E97)>1),"Cartão de crédito parcelado",D97),Config!$A$12:$A$15,0)),0)+IF(AND(Config!$B$17="Sim",LEFT(D97,17)="Cartão de crédito"),Config!$B$18*IFERROR(INDEX(Config!$C$12:$C$15,MATCH(IF(AND(D97="Cartão de crédito",N(E97)>1),"Cartão de crédito parcelado",D97),Config!$A$12:$A$15,0)),0)/30*MAX(1,N(E97)),0)) -> 0.032 | I97: =IF(OR(D97="",F97=""),"",ROUND(F97*H97,2)) -> 12.16 | J97: =IF(I97="","",F97-I97) -> 367.84 | K97: =IF(J97="","",J97/MAX(1,N(E97))) -> 367.84 | L97: =IF(OR(D97="",A97=""),"",A97+IF(AND(Config!$B$17="Sim",LEFT(D97,17)="Cartão de crédito"),1,IFERROR(INDEX(Config!$C$12:$C$15,MATCH(IF(AND(D97="Cartão de crédito",N(E97)>1),"Cartão de crédito parcelado",D97),Config!$A$12:$A$15,0)),0))) -> 46240 | M97: =IF(L97="","",IF(AND(Config!$B$17="Sim",LEFT(D97,17)="Cartão de crédito"),L97,L97+30*(MAX(1,N(E97))-1))) -> 46240 | N97: =IF(OR(L97="",K97=""),"",K97*MIN(MAX(1,N(E97)),MAX(0,INT((Config!$B$8-L97)/30)+1))) -> 367.84 | O97: =IF(J97="","",J97-N(N97)) -> 0 | P97: =IF(A97="","",MONTH(A97)) -> 7 | Q97: =IF(A97="","",YEAR(A97)) -> 2026 | R97: =IF(L97="","",IF(L97>Config!$B$8,"A cair",IF(N(G97)>=MIN(MAX(1,N(E97)),MAX(0,INT((Config!$B$8-L97)/30)+1)),IF(N(G97)>=MAX(1,N(E97)),"Conferido","Conferido até aqui"),"A conferir"))) -> Conferido | S97: =IF(R97="A conferir",(Config!$B$8-L97)*1000+N(F97)/1000+ROW()/100000,0) -> 0 | T97: =IF(R97="A conferir",N(N97),0) -> 0 | U97: =IF(L97="",0,L97) -> 46240 | V97: =IF(L97="",0,MAX(1,N(E97))) -> 1 | W97: =IF(K97="",0,K97) -> 367.84
A98: 46211 | B98: Cláudia Santos | C98: Consulta | D98: Pix | F98: 380 | G98: 1 | H98: =IF(D98="","",IFERROR(INDEX(Config!$B$12:$B$15,MATCH(IF(AND(D98="Cartão de crédito",N(E98)>1),"Cartão de crédito parcelado",D98),Config!$A$12:$A$15,0)),0)+IF(AND(Config!$B$17="Sim",LEFT(D98,17)="Cartão de crédito"),Config!$B$18*IFERROR(INDEX(Config!$C$12:$C$15,MATCH(IF(AND(D98="Cartão de crédito",N(E98)>1),"Cartão de crédito parcelado",D98),Config!$A$12:$A$15,0)),0)/30*MAX(1,N(E98)),0)) -> 0 | I98: =IF(OR(D98="",F98=""),"",ROUND(F98*H98,2)) -> 0 | J98: =IF(I98="","",F98-I98) -> 380 | K98: =IF(J98="","",J98/MAX(1,N(E98))) -> 380 | L98: =IF(OR(D98="",A98=""),"",A98+IF(AND(Config!$B$17="Sim",LEFT(D98,17)="Cartão de crédito"),1,IFERROR(INDEX(Config!$C$12:$C$15,MATCH(IF(AND(D98="Cartão de crédito",N(E98)>1),"Cartão de crédito parcelado",D98),Config!$A$12:$A$15,0)),0))) -> 46211 | M98: =IF(L98="","",IF(AND(Config!$B$17="Sim",LEFT(D98,17)="Cartão de crédito"),L98,L98+30*(MAX(1,N(E98))-1))) -> 46211 | N98: =IF(OR(L98="",K98=""),"",K98*MIN(MAX(1,N(E98)),MAX(0,INT((Config!$B$8-L98)/30)+1))) -> 380 | O98: =IF(J98="","",J98-N(N98)) -> 0 | P98: =IF(A98="","",MONTH(A98)) -> 7 | Q98: =IF(A98="","",YEAR(A98)) -> 2026 | R98: =IF(L98="","",IF(L98>Config!$B$8,"A cair",IF(N(G98)>=MIN(MAX(1,N(E98)),MAX(0,INT((Config!$B$8-L98)/30)+1)),IF(N(G98)>=MAX(1,N(E98)),"Conferido","Conferido até aqui"),"A conferir"))) -> Conferido | S98: =IF(R98="A conferir",(Config!$B$8-L98)*1000+N(F98)/1000+ROW()/100000,0) -> 0 | T98: =IF(R98="A conferir",N(N98),0) -> 0 | U98: =IF(L98="",0,L98) -> 46211 | V98: =IF(L98="",0,MAX(1,N(E98))) -> 1 | W98: =IF(K98="",0,K98) -> 380
A99: 46211 | B99: Otávio Nascimento | C99: Consulta | D99: Cartão de crédito | F99: 380 | G99: 1 | H99: =IF(D99="","",IFERROR(INDEX(Config!$B$12:$B$15,MATCH(IF(AND(D99="Cartão de crédito",N(E99)>1),"Cartão de crédito parcelado",D99),Config!$A$12:$A$15,0)),0)+IF(AND(Config!$B$17="Sim",LEFT(D99,17)="Cartão de crédito"),Config!$B$18*IFERROR(INDEX(Config!$C$12:$C$15,MATCH(IF(AND(D99="Cartão de crédito",N(E99)>1),"Cartão de crédito parcelado",D99),Config!$A$12:$A$15,0)),0)/30*MAX(1,N(E99)),0)) -> 0.032 | I99: =IF(OR(D99="",F99=""),"",ROUND(F99*H99,2)) -> 12.16 | J99: =IF(I99="","",F99-I99) -> 367.84 | K99: =IF(J99="","",J99/MAX(1,N(E99))) -> 367.84 | L99: =IF(OR(D99="",A99=""),"",A99+IF(AND(Config!$B$17="Sim",LEFT(D99,17)="Cartão de crédito"),1,IFERROR(INDEX(Config!$C$12:$C$15,MATCH(IF(AND(D99="Cartão de crédito",N(E99)>1),"Cartão de crédito parcelado",D99),Config!$A$12:$A$15,0)),0))) -> 46241 | M99: =IF(L99="","",IF(AND(Config!$B$17="Sim",LEFT(D99,17)="Cartão de crédito"),L99,L99+30*(MAX(1,N(E99))-1))) -> 46241 | N99: =IF(OR(L99="",K99=""),"",K99*MIN(MAX(1,N(E99)),MAX(0,INT((Config!$B$8-L99)/30)+1))) -> 367.84 | O99: =IF(J99="","",J99-N(N99)) -> 0 | P99: =IF(A99="","",MONTH(A99)) -> 7 | Q99: =IF(A99="","",YEAR(A99)) -> 2026 | R99: =IF(L99="","",IF(L99>Config!$B$8,"A cair",IF(N(G99)>=MIN(MAX(1,N(E99)),MAX(0,INT((Config!$B$8-L99)/30)+1)),IF(N(G99)>=MAX(1,N(E99)),"Conferido","Conferido até aqui"),"A conferir"))) -> Conferido | S99: =IF(R99="A conferir",(Config!$B$8-L99)*1000+N(F99)/1000+ROW()/100000,0) -> 0 | T99: =IF(R99="A conferir",N(N99),0) -> 0 | U99: =IF(L99="",0,L99) -> 46241 | V99: =IF(L99="",0,MAX(1,N(E99))) -> 1 | W99: =IF(K99="",0,K99) -> 367.84
A100: 46212 | B100: Elaine Cardoso | C100: Consulta | D100: Cartão de crédito | F100: 380 | G100: 1 | H100: =IF(D100="","",IFERROR(INDEX(Config!$B$12:$B$15,MATCH(IF(AND(D100="Cartão de crédito",N(E100)>1),"Cartão de crédito parcelado",D100),Config!$A$12:$A$15,0)),0)+IF(AND(Config!$B$17="Sim",LEFT(D100,17)="Cartão de crédito"),Config!$B$18*IFERROR(INDEX(Config!$C$12:$C$15,MATCH(IF(AND(D100="Cartão de crédito",N(E100)>1),"Cartão de crédito parcelado",D100),Config!$A$12:$A$15,0)),0)/30*MAX(1,N(E100)),0)) -> 0.032 | I100: =IF(OR(D100="",F100=""),"",ROUND(F100*H100,2)) -> 12.16 | J100: =IF(I100="","",F100-I100) -> 367.84 | K100: =IF(J100="","",J100/MAX(1,N(E100))) -> 367.84 | L100: =IF(OR(D100="",A100=""),"",A100+IF(AND(Config!$B$17="Sim",LEFT(D100,17)="Cartão de crédito"),1,IFERROR(INDEX(Config!$C$12:$C$15,MATCH(IF(AND(D100="Cartão de crédito",N(E100)>1),"Cartão de crédito parcelado",D100),Config!$A$12:$A$15,0)),0))) -> 46242 | M100: =IF(L100="","",IF(AND(Config!$B$17="Sim",LEFT(D100,17)="Cartão de crédito"),L100,L100+30*(MAX(1,N(E100))-1))) -> 46242 | N100: =IF(OR(L100="",K100=""),"",K100*MIN(MAX(1,N(E100)),MAX(0,INT((Config!$B$8-L100)/30)+1))) -> 367.84 | O100: =IF(J100="","",J100-N(N100)) -> 0 | P100: =IF(A100="","",MONTH(A100)) -> 7 | Q100: =IF(A100="","",YEAR(A100)) -> 2026 | R100: =IF(L100="","",IF(L100>Config!$B$8,"A cair",IF(N(G100)>=MIN(MAX(1,N(E100)),MAX(0,INT((Config!$B$8-L100)/30)+1)),IF(N(G100)>=MAX(1,N(E100)),"Conferido","Conferido até aqui"),"A conferir"))) -> Conferido | S100: =IF(R100="A conferir",(Config!$B$8-L100)*1000+N(F100)/1000+ROW()/100000,0) -> 0 | T100: =IF(R100="A conferir",N(N100),0) -> 0 | U100: =IF(L100="",0,L100) -> 46242 | V100: =IF(L100="",0,MAX(1,N(E100))) -> 1 | W100: =IF(K100="",0,K100) -> 367.84
A101: 46212 | B101: Roberta Araújo | C101: Consulta | D101: Pix | F101: 380 | G101: 1 | H101: =IF(D101="","",IFERROR(INDEX(Config!$B$12:$B$15,MATCH(IF(AND(D101="Cartão de crédito",N(E101)>1),"Cartão de crédito parcelado",D101),Config!$A$12:$A$15,0)),0)+IF(AND(Config!$B$17="Sim",LEFT(D101,17)="Cartão de crédito"),Config!$B$18*IFERROR(INDEX(Config!$C$12:$C$15,MATCH(IF(AND(D101="Cartão de crédito",N(E101)>1),"Cartão de crédito parcelado",D101),Config!$A$12:$A$15,0)),0)/30*MAX(1,N(E101)),0)) -> 0 | I101: =IF(OR(D101="",F101=""),"",ROUND(F101*H101,2)) -> 0 | J101: =IF(I101="","",F101-I101) -> 380 | K101: =IF(J101="","",J101/MAX(1,N(E101))) -> 380 | L101: =IF(OR(D101="",A101=""),"",A101+IF(AND(Config!$B$17="Sim",LEFT(D101,17)="Cartão de crédito"),1,IFERROR(INDEX(Config!$C$12:$C$15,MATCH(IF(AND(D101="Cartão de crédito",N(E101)>1),"Cartão de crédito parcelado",D101),Config!$A$12:$A$15,0)),0))) -> 46212 | M101: =IF(L101="","",IF(AND(Config!$B$17="Sim",LEFT(D101,17)="Cartão de crédito"),L101,L101+30*(MAX(1,N(E101))-1))) -> 46212 | N101: =IF(OR(L101="",K101=""),"",K101*MIN(MAX(1,N(E101)),MAX(0,INT((Config!$B$8-L101)/30)+1))) -> 380 | O101: =IF(J101="","",J101-N(N101)) -> 0 | P101: =IF(A101="","",MONTH(A101)) -> 7 | Q101: =IF(A101="","",YEAR(A101)) -> 2026 | R101: =IF(L101="","",IF(L101>Config!$B$8,"A cair",IF(N(G101)>=MIN(MAX(1,N(E101)),MAX(0,INT((Config!$B$8-L101)/30)+1)),IF(N(G101)>=MAX(1,N(E101)),"Conferido","Conferido até aqui"),"A conferir"))) -> Conferido | S101: =IF(R101="A conferir",(Config!$B$8-L101)*1000+N(F101)/1000+ROW()/100000,0) -> 0 | T101: =IF(R101="A conferir",N(N101),0) -> 0 | U101: =IF(L101="",0,L101) -> 46212 | V101: =IF(L101="",0,MAX(1,N(E101))) -> 1 | W101: =IF(K101="",0,K101) -> 380
A102: 46212 | B102: Fábio Gomes | C102: Avaliação endócrina | D102: Cartão de crédito | F102: 400 | G102: 1 | H102: =IF(D102="","",IFERROR(INDEX(Config!$B$12:$B$15,MATCH(IF(AND(D102="Cartão de crédito",N(E102)>1),"Cartão de crédito parcelado",D102),Config!$A$12:$A$15,0)),0)+IF(AND(Config!$B$17="Sim",LEFT(D102,17)="Cartão de crédito"),Config!$B$18*IFERROR(INDEX(Config!$C$12:$C$15,MATCH(IF(AND(D102="Cartão de crédito",N(E102)>1),"Cartão de crédito parcelado",D102),Config!$A$12:$A$15,0)),0)/30*MAX(1,N(E102)),0)) -> 0.032 | I102: =IF(OR(D102="",F102=""),"",ROUND(F102*H102,2)) -> 12.8 | J102: =IF(I102="","",F102-I102) -> 387.2 | K102: =IF(J102="","",J102/MAX(1,N(E102))) -> 387.2 | L102: =IF(OR(D102="",A102=""),"",A102+IF(AND(Config!$B$17="Sim",LEFT(D102,17)="Cartão de crédito"),1,IFERROR(INDEX(Config!$C$12:$C$15,MATCH(IF(AND(D102="Cartão de crédito",N(E102)>1),"Cartão de crédito parcelado",D102),Config!$A$12:$A$15,0)),0))) -> 46242 | M102: =IF(L102="","",IF(AND(Config!$B$17="Sim",LEFT(D102,17)="Cartão de crédito"),L102,L102+30*(MAX(1,N(E102))-1))) -> 46242 | N102: =IF(OR(L102="",K102=""),"",K102*MIN(MAX(1,N(E102)),MAX(0,INT((Config!$B$8-L102)/30)+1))) -> 387.2 | O102: =IF(J102="","",J102-N(N102)) -> 0 | P102: =IF(A102="","",MONTH(A102)) -> 7 | Q102: =IF(A102="","",YEAR(A102)) -> 2026 | R102: =IF(L102="","",IF(L102>Config!$B$8,"A cair",IF(N(G102)>=MIN(MAX(1,N(E102)),MAX(0,INT((Config!$B$8-L102)/30)+1)),IF(N(G102)>=MAX(1,N(E102)),"Conferido","Conferido até aqui"),"A conferir"))) -> Conferido | S102: =IF(R102="A conferir",(Config!$B$8-L102)*1000+N(F102)/1000+ROW()/100000,0) -> 0 | T102: =IF(R102="A conferir",N(N102),0) -> 0 | U102: =IF(L102="",0,L102) -> 46242 | V102: =IF(L102="",0,MAX(1,N(E102))) -> 1 | W102: =IF(K102="",0,K102) -> 387.2
... A111: 46216 | B111: Gisele Ribeiro | C111: ECG | D111: Cartão de crédito | F111: 130 | G111: 1 | H111: =IF(D111="","",IFERROR(INDEX(Config!$B$12:$B$15,MATCH(IF(AND(D111="Cartão de crédito",N(E111)>1),"Cartão de crédito parcelado",D111),Config!$A$12:$A$15,0)),0)+IF(AND(Config!$B$17="Sim",LEFT(D111,17)="Cartão de crédito"),Config!$B$18*IFERROR(INDEX(Config!$C$12:$C$15,MATCH(IF(AND(D111="Cartão de crédito",N(E111)>1),"Cartão de crédito parcelado",D111),Config!$A$12:$A$15,0)),0)/30*MAX(1,N(E111)),0)) -> 0.032 | I111: =IF(OR(D111="",F111=""),"",ROUND(F111*H111,2)) -> 4.16 | J111: =IF(I111="","",F111-I111) -> 125.84 | K111: =IF(J111="","",J111/MAX(1,N(E111))) -> 125.84 | L111: =IF(OR(D111="",A111=""),"",A111+IF(AND(Config!$B$17="Sim",LEFT(D111,17)="Cartão de crédito"),1,IFERROR(INDEX(Config!$C$12:$C$15,MATCH(IF(AND(D111="Cartão de crédito",N(E111)>1),"Cartão de crédito parcelado",D111),Config!$A$12:$A$15,0)),0))) -> 46246 | M111: =IF(L111="","",IF(AND(Config!$B$17="Sim",LEFT(D111,17)="Cartão de crédito"),L111,L111+30*(MAX(1,N(E111))-1))) -> 46246 | N111: =IF(OR(L111="",K111=""),"",K111*MIN(MAX(1,N(E111)),MAX(0,INT((Config!$B$8-L111)/30)+1))) -> 125.84 | O111: =IF(J111="","",J111-N(N111)) -> 0 | P111: =IF(A111="","",MONTH(A111)) -> 7 | Q111: =IF(A111="","",YEAR(A111)) -> 2026 | R111: =IF(L111="","",IF(L111>Config!$B$8,"A cair",IF(N(G111)>=MIN(MAX(1,N(E111)),MAX(0,INT((Config!$B$8-L111)/30)+1)),IF(N(G111)>=MAX(1,N(E111)),"Conferido","Conferido até aqui"),"A conferir"))) -> Conferido | S111: =IF(R111="A conferir",(Config!$B$8-L111)*1000+N(F111)/1000+ROW()/100000,0) -> 0 | T111: =IF(R111="A conferir",N(N111),0) -> 0 | U111: =IF(L111="",0,L111) -> 46246 | V111: =IF(L111="",0,MAX(1,N(E111))) -> 1 | W111: =IF(K111="",0,K111) -> 125.84
A112: 46216 | B112: Henrique Ribeiro | C112: Consulta | D112: Cartão de crédito | E112: 2 | F112: 380 | G112: 1 | H112: =IF(D112="","",IFERROR(INDEX(Config!$B$12:$B$15,MATCH(IF(AND(D112="Cartão de crédito",N(E112)>1),"Cartão de crédito parcelado",D112),Config!$A$12:$A$15,0)),0)+IF(AND(Config!$B$17="Sim",LEFT(D112,17)="Cartão de crédito"),Config!$B$18*IFERROR(INDEX(Config!$C$12:$C$15,MATCH(IF(AND(D112="Cartão de crédito",N(E112)>1),"Cartão de crédito parcelado",D112),Config!$A$12:$A$15,0)),0)/30*MAX(1,N(E112)),0)) -> 0.039 | I112: =IF(OR(D112="",F112=""),"",ROUND(F112*H112,2)) -> 14.82 | J112: =IF(I112="","",F112-I112) -> 365.18 | K112: =IF(J112="","",J112/MAX(1,N(E112))) -> 182.59 | L112: =IF(OR(D112="",A112=""),"",A112+IF(AND(Config!$B$17="Sim",LEFT(D112,17)="Cartão de crédito"),1,IFERROR(INDEX(Config!$C$12:$C$15,MATCH(IF(AND(D112="Cartão de crédito",N(E112)>1),"Cartão de crédito parcelado",D112),Config!$A$12:$A$15,0)),0))) -> 46246 | M112: =IF(L112="","",IF(AND(Config!$B$17="Sim",LEFT(D112,17)="Cartão de crédito"),L112,L112+30*(MAX(1,N(E112))-1))) -> 46276 | N112: =IF(OR(L112="",K112=""),"",K112*MIN(MAX(1,N(E112)),MAX(0,INT((Config!$B$8-L112)/30)+1))) -> 365.18 | O112: =IF(J112="","",J112-N(N112)) -> 0 | P112: =IF(A112="","",MONTH(A112)) -> 7 | Q112: =IF(A112="","",YEAR(A112)) -> 2026 | R112: =IF(L112="","",IF(L112>Config!$B$8,"A cair",IF(N(G112)>=MIN(MAX(1,N(E112)),MAX(0,INT((Config!$B$8-L112)/30)+1)),IF(N(G112)>=MAX(1,N(E112)),"Conferido","Conferido até aqui"),"A conferir"))) -> A conferir | S112: =IF(R112="A conferir",(Config!$B$8-L112)*1000+N(F112)/1000+ROW()/100000,0) -> 33000.381 | T112: =IF(R112="A conferir",N(N112),0) -> 365.18 | U112: =IF(L112="",0,L112) -> 46246 | V112: =IF(L112="",0,MAX(1,N(E112))) -> 2 | W112: =IF(K112="",0,K112) -> 182.59
A113: 46216 | B113: Gabriel Oliveira | C113: Consulta | D113: Pix | F113: 380 | G113: 1 | H113: =IF(D113="","",IFERROR(INDEX(Config!$B$12:$B$15,MATCH(IF(AND(D113="Cartão de crédito",N(E113)>1),"Cartão de crédito parcelado",D113),Config!$A$12:$A$15,0)),0)+IF(AND(Config!$B$17="Sim",LEFT(D113,17)="Cartão de crédito"),Config!$B$18*IFERROR(INDEX(Config!$C$12:$C$15,MATCH(IF(AND(D113="Cartão de crédito",N(E113)>1),"Cartão de crédito parcelado",D113),Config!$A$12:$A$15,0)),0)/30*MAX(1,N(E113)),0)) -> 0 | I113: =IF(OR(D113="",F113=""),"",ROUND(F113*H113,2)) -> 0 | J113: =IF(I113="","",F113-I113) -> 380 | K113: =IF(J113="","",J113/MAX(1,N(E113))) -> 380 | L113: =IF(OR(D113="",A113=""),"",A113+IF(AND(Config!$B$17="Sim",LEFT(D113,17)="Cartão de crédito"),1,IFERROR(INDEX(Config!$C$12:$C$15,MATCH(IF(AND(D113="Cartão de crédito",N(E113)>1),"Cartão de crédito parcelado",D113),Config!$A$12:$A$15,0)),0))) -> 46216 | M113: =IF(L113="","",IF(AND(Config!$B$17="Sim",LEFT(D113,17)="Cartão de crédito"),L113,L113+30*(MAX(1,N(E113))-1))) -> 46216 | N113: =IF(OR(L113="",K113=""),"",K113*MIN(MAX(1,N(E113)),MAX(0,INT((Config!$B$8-L113)/30)+1))) -> 380 | O113: =IF(J113="","",J113-N(N113)) -> 0 | P113: =IF(A113="","",MONTH(A113)) -> 7 | Q113: =IF(A113="","",YEAR(A113)) -> 2026 | R113: =IF(L113="","",IF(L113>Config!$B$8,"A cair",IF(N(G113)>=MIN(MAX(1,N(E113)),MAX(0,INT((Config!$B$8-L113)/30)+1)),IF(N(G113)>=MAX(1,N(E113)),"Conferido","Conferido até aqui"),"A conferir"))) -> Conferido | S113: =IF(R113="A conferir",(Config!$B$8-L113)*1000+N(F113)/1000+ROW()/100000,0) -> 0 | T113: =IF(R113="A conferir",N(N113),0) -> 0 | U113: =IF(L113="",0,L113) -> 46216 | V113: =IF(L113="",0,MAX(1,N(E113))) -> 1 | W113: =IF(K113="",0,K113) -> 380
A114: 46217 | B114: Regina Teixeira | C114: Consulta | D114: Pix | F114: 380 | G114: 1 | H114: =IF(D114="","",IFERROR(INDEX(Config!$B$12:$B$15,MATCH(IF(AND(D114="Cartão de crédito",N(E114)>1),"Cartão de crédito parcelado",D114),Config!$A$12:$A$15,0)),0)+IF(AND(Config!$B$17="Sim",LEFT(D114,17)="Cartão de crédito"),Config!$B$18*IFERROR(INDEX(Config!$C$12:$C$15,MATCH(IF(AND(D114="Cartão de crédito",N(E114)>1),"Cartão de crédito parcelado",D114),Config!$A$12:$A$15,0)),0)/30*MAX(1,N(E114)),0)) -> 0 | I114: =IF(OR(D114="",F114=""),"",ROUND(F114*H114,2)) -> 0 | J114: =IF(I114="","",F114-I114) -> 380 | K114: =IF(J114="","",J114/MAX(1,N(E114))) -> 380 | L114: =IF(OR(D114="",A114=""),"",A114+IF(AND(Config!$B$17="Sim",LEFT(D114,17)="Cartão de crédito"),1,IFERROR(INDEX(Config!$C$12:$C$15,MATCH(IF(AND(D114="Cartão de crédito",N(E114)>1),"Cartão de crédito parcelado",D114),Config!$A$12:$A$15,0)),0))) -> 46217 | M114: =IF(L114="","",IF(AND(Config!$B$17="Sim",LEFT(D114,17)="Cartão de crédito"),L114,L114+30*(MAX(1,N(E114))-1))) -> 46217 | N114: =IF(OR(L114="",K114=""),"",K114*MIN(MAX(1,N(E114)),MAX(0,INT((Config!$B$8-L114)/30)+1))) -> 380 | O114: =IF(J114="","",J114-N(N114)) -> 0 | P114: =IF(A114="","",MONTH(A114)) -> 7 | Q114: =IF(A114="","",YEAR(A114)) -> 2026 | R114: =IF(L114="","",IF(L114>Config!$B$8,"A cair",IF(N(G114)>=MIN(MAX(1,N(E114)),MAX(0,INT((Config!$B$8-L114)/30)+1)),IF(N(G114)>=MAX(1,N(E114)),"Conferido","Conferido até aqui"),"A conferir"))) -> Conferido | S114: =IF(R114="A conferir",(Config!$B$8-L114)*1000+N(F114)/1000+ROW()/100000,0) -> 0 | T114: =IF(R114="A conferir",N(N114),0) -> 0 | U114: =IF(L114="",0,L114) -> 46217 | V114: =IF(L114="",0,MAX(1,N(E114))) -> 1 | W114: =IF(K114="",0,K114) -> 380
A115: 46217 | B115: Priscila Reis | C115: Avaliação endócrina | D115: Pix | F115: 400 | G115: 1 | H115: =IF(D115="","",IFERROR(INDEX(Config!$B$12:$B$15,MATCH(IF(AND(D115="Cartão de crédito",N(E115)>1),"Cartão de crédito parcelado",D115),Config!$A$12:$A$15,0)),0)+IF(AND(Config!$B$17="Sim",LEFT(D115,17)="Cartão de crédito"),Config!$B$18*IFERROR(INDEX(Config!$C$12:$C$15,MATCH(IF(AND(D115="Cartão de crédito",N(E115)>1),"Cartão de crédito parcelado",D115),Config!$A$12:$A$15,0)),0)/30*MAX(1,N(E115)),0)) -> 0 | I115: =IF(OR(D115="",F115=""),"",ROUND(F115*H115,2)) -> 0 | J115: =IF(I115="","",F115-I115) -> 400 | K115: =IF(J115="","",J115/MAX(1,N(E115))) -> 400 | L115: =IF(OR(D115="",A115=""),"",A115+IF(AND(Config!$B$17="Sim",LEFT(D115,17)="Cartão de crédito"),1,IFERROR(INDEX(Config!$C$12:$C$15,MATCH(IF(AND(D115="Cartão de crédito",N(E115)>1),"Cartão de crédito parcelado",D115),Config!$A$12:$A$15,0)),0))) -> 46217 | M115: =IF(L115="","",IF(AND(Config!$B$17="Sim",LEFT(D115,17)="Cartão de crédito"),L115,L115+30*(MAX(1,N(E115))-1))) -> 46217 | N115: =IF(OR(L115="",K115=""),"",K115*MIN(MAX(1,N(E115)),MAX(0,INT((Config!$B$8-L115)/30)+1))) -> 400 | O115: =IF(J115="","",J115-N(N115)) -> 0 | P115: =IF(A115="","",MONTH(A115)) -> 7 | Q115: =IF(A115="","",YEAR(A115)) -> 2026 | R115: =IF(L115="","",IF(L115>Config!$B$8,"A cair",IF(N(G115)>=MIN(MAX(1,N(E115)),MAX(0,INT((Config!$B$8-L115)/30)+1)),IF(N(G115)>=MAX(1,N(E115)),"Conferido","Conferido até aqui"),"A conferir"))) -> Conferido | S115: =IF(R115="A conferir",(Config!$B$8-L115)*1000+N(F115)/1000+ROW()/100000,0) -> 0 | T115: =IF(R115="A conferir",N(N115),0) -> 0 | U115: =IF(L115="",0,L115) -> 46217 | V115: =IF(L115="",0,MAX(1,N(E115))) -> 1 | W115: =IF(K115="",0,K115) -> 400
