Workbook

Sheet Como usar
A1: Metas do Trimestre
A2: Kit de Gestão para Médicos · Seu Sócio Gestor · versão 1.0 (setembro de 2026)
A4: O que esta planilha faz | B4: Você define até 3 objetivos da clínica com até 3 resultados-chave cada (ponto de partida, meta, valor atual). Ela calcula o progresso, compara com o tempo já decorrido do trimestre e acende o semáforo: atingido, no ritmo, atenção ou em risco.
A5: Passo 1 | B5: Em Config, preencha o trimestre, as datas de início e fim, troque a data de referência por =HOJE() (no exemplo ela está congelada em 14/09/2026) e liste as pessoas da clínica (de cima para baixo, sem pular linha).
A6: Passo 2 | B6: Em Metas, escreva cada objetivo e seus resultados-chave. Ponto de partida é o valor no dia 1; meta é onde quer chegar; valor atual é o número de hoje. Diga se maior ou menor é melhor. No exemplo, cada resultado-chave é um número de outra planilha do kit: ocupação e faltas (01, 02), glosa e atrasos (13), inadimplência, reserva e provisão (14, 12, 10).
A7: Passo 3 | B7: Toda sexta, atualize o valor atual (os números vêm do Painel da clínica, 17, ou dos painéis das planilhas de origem) e copie para a coluna da semana em Semanas. Semana sem número: escreva "—", não 0. O Painel mostra o resumo por objetivo e a lista completa com semáforo. No exemplo, S1 a S11 são as sextas de 03/07 a 11/09/2026.
A8: Rotina | B8: Esta é uma planilha MENSAL. Na sexta, os valores já estão no Painel da clínica (17), que você atualiza em 3 minutos: copiar o número de cada resultado-chave para a coluna da semana em Semanas leva menos de um minuto e cabe nessa mesma parada. A conversa sobre as metas é mensal: primeira segunda do mês, 20 minutos entre os sócios olhando o Painel.
A9: Com a IA | B9: Copie a tabela "Todos os resultados-chave" e use o prompt "Painel 05 · Meta realista para o trimestre" ou "Painel 06 · Meta × realizado: explicar o desvio" da biblioteca do kit. No fim do trimestre, o modelo de apresentação "Resultado do mês para os sócios".
A10: Legenda | B10: Células amarelas: você preenche. Brancas: calculadas. Não é preciso mexer em nada fora do amarelo.
A11: Proteção | B11: Fórmulas protegidas sem senha. Para editar: Revisar > Desproteger planilha (Excel) ou Dados > Proteger intervalos (Google Sheets).
A12: Requisitos | B12: Excel 2016 ou mais novo, Microsoft 365 ou Google Sheets (só funções do Excel 2007+; nada de MÍNIMOSES, MÁXIMOSES ou UNIRTEXTO). No celular abre nos aplicativos; para preencher, use o computador.
A13: Dados de pacientes | B13: Guarde só o que a gestão precisa (nome, contato, valor, data). Nada de diagnóstico, prontuário ou exame nestas planilhas: o kit é gestão, não é prontuário. Veja o guia LGPD do kit antes de colar qualquer tabela em uma IA.
A14: Google Sheets | B14: Faça upload no Google Drive e abra com o Google Sheets. Fórmulas, listas, cores, semáforos e gráficos funcionam: as regras de cor que dependem do mês escolhido em Config usam INDIRECT, que é a forma que o Sheets aceita para regra condicional apontar para outra aba.
A15: Exemplos | B15: Clínica Vida Plena é uma clínica fictícia. Pacientes, convênios, nomes, contatos e valores são inventados; não há nenhum dado clínico. Apague o exemplo antes de começar.
... A17: Suporte | B17: suporte@seusociogestor.com.br · resposta em até 5 dias úteis · reembolso em até 7 dias pelo mesmo canal.

Sheet Painel
A1: =Config!B4&" · Metas do trimestre · "&Config!B5 -> Clínica Vida Plena (exemplo fictício) · Metas do trimestre · 3º trimestre de 2026
A2: ="Semana "&Config!B9&" de 13 · "&TEXT(Config!B10,"0%")&" do trimestre decorrido. Nada para preencher aqui." -> Semana 11 de 13 · 82% do trimestre decorrido. Nada para preencher aqui.
A4: Resultados-chave | C4: Atingidos | E4: Em risco | G4: Progresso médio
A5: =COUNTIFS(Metas!$B$5:$B$13,"<>") -> 9 | C5: =COUNTIFS(Metas!$J$5:$J$13,"Atingido") -> 1 | E5: =COUNTIFS(Metas!$J$5:$J$13,"Em risco") -> 6 | G5: =IFERROR(AVERAGEIFS(Metas!$H$5:$H$13,Metas!$B$5:$B$13,"<>"),0) -> 0.44464124
A7: Por objetivo
A8: Objetivo | B8: Resultados-chave | C8: Progresso médio | D8: Atingidos | E8: Em risco | F8: Barra
A9: =IF(Metas!$A$5="","",Metas!$A$5) -> Agenda cheia, sem faltas | B9: =IF(Metas!$A$5="","",COUNTIFS(Metas!$B$5:$B$7,"<>")) -> 3 | C9: =IF(OR(Metas!$A$5="",B9=0),"",AVERAGEIFS(Metas!$H$5:$H$7,Metas!$B$5:$B$7,"<>")) -> 0.33333333 | D9: =IF(Metas!$A$5="","",COUNTIFS(Metas!$J$5:$J$7,"Atingido")) -> 1 | E9: =IF(Metas!$A$5="","",COUNTIFS(Metas!$J$5:$J$7,"Em risco")) -> 2 | F9: =IF(C9="","",REPT("█",ROUND(C9*30,0))) -> ██████████
A10: =IF(Metas!$A$8="","",Metas!$A$8) -> Convênio sob controle | B10: =IF(Metas!$A$8="","",COUNTIFS(Metas!$B$8:$B$10,"<>")) -> 3 | C10: =IF(OR(Metas!$A$8="",B10=0),"",AVERAGEIFS(Metas!$H$8:$H$10,Metas!$B$8:$B$10,"<>")) -> 0.29623312 | D10: =IF(Metas!$A$8="","",COUNTIFS(Metas!$J$8:$J$10,"Atingido")) -> 0 | E10: =IF(Metas!$A$8="","",COUNTIFS(Metas!$J$8:$J$10,"Em risco")) -> 3 | F10: =IF(C10="","",REPT("█",ROUND(C10*30,0))) -> █████████
A11: =IF(Metas!$A$11="","",Metas!$A$11) -> Caixa previsível | B11: =IF(Metas!$A$11="","",COUNTIFS(Metas!$B$11:$B$13,"<>")) -> 3 | C11: =IF(OR(Metas!$A$11="",B11=0),"",AVERAGEIFS(Metas!$H$11:$H$13,Metas!$B$11:$B$13,"<>")) -> 0.70435727 | D11: =IF(Metas!$A$11="","",COUNTIFS(Metas!$J$11:$J$13,"Atingido")) -> 0 | E11: =IF(Metas!$A$11="","",COUNTIFS(Metas!$J$11:$J$13,"Em risco")) -> 1 | F11: =IF(C11="","",REPT("█",ROUND(C11*30,0))) -> █████████████████████
A13: Todos os resultados-chave
A14: Resultado-chave | B14: Dono | C14: Atual | D14: Meta | E14: Progresso | F14: Esperado | G14: Semáforo | H14: Barra
A15: =IF(Metas!B5="","",Metas!B5) -> Ocupação da agenda nas últimas 4 semanas (%) | B15: =IF(Metas!B5="","",Metas!C5) -> Bruna Carvalho | C15: =IF(Metas!B5="","",Metas!G5) -> 74.5 | D15: =IF(Metas!B5="","",Metas!F5) -> 80 | E15: =IF(Metas!B5="","",Metas!H5) -> 0 | F15: =IF(Metas!B5="","",Metas!I5) -> 0.82417582 | G15: =IF(Metas!B5="","",Metas!J5) -> Em risco | H15: =IF(E15="","",REPT("█",ROUND(E15*20,0)))
A16: =IF(Metas!B6="","",Metas!B6) -> Taxa de falta nas últimas 4 semanas (%) | B16: =IF(Metas!B6="","",Metas!C6) -> Bruna Carvalho | C16: =IF(Metas!B6="","",Metas!G6) -> 7.1 | D16: =IF(Metas!B6="","",Metas!F6) -> 5 | E16: =IF(Metas!B6="","",Metas!H6) -> 0 | F16: =IF(Metas!B6="","",Metas!I6) -> 0.82417582 | G16: =IF(Metas!B6="","",Metas!J6) -> Em risco | H16: =IF(E16="","",REPT("█",ROUND(E16*20,0)))
A17: =IF(Metas!B7="","",Metas!B7) -> Pacientes na lista de retorno sem agendamento | B17: =IF(Metas!B7="","",Metas!C7) -> Bruna Carvalho | C17: =IF(Metas!B7="","",Metas!G7) -> 8 | D17: =IF(Metas!B7="","",Metas!F7) -> 8 | E17: =IF(Metas!B7="","",Metas!H7) -> 1 | F17: =IF(Metas!B7="","",Metas!I7) -> 0.82417582 | G17: =IF(Metas!B7="","",Metas!J7) -> Atingido | H17: =IF(E17="","",REPT("█",ROUND(E17*20,0))) -> ████████████████████
A18: =IF(Metas!B8="","",Metas!B8) -> Glosa nos lotes pagos no ano (%) | B18: =IF(Metas!B8="","",Metas!C8) -> Dr. Paulo Andrade | C18: =IF(Metas!B8="","",Metas!G8) -> 5.5 | D18: =IF(Metas!B8="","",Metas!F8) -> 4 | E18: =IF(Metas!B8="","",Metas!H8) -> 0.28571429 | F18: =IF(Metas!B8="","",Metas!I8) -> 0.82417582 | G18: =IF(Metas!B8="","",Metas!J8) -> Em risco | H18: =IF(E18="","",REPT("█",ROUND(E18*20,0))) -> ██████
A19: =IF(Metas!B9="","",Metas!B9) -> Prazo real médio de pagamento dos lotes (dias) | B19: =IF(Metas!B9="","",Metas!C9) -> Dr. Paulo Andrade | C19: =IF(Metas!B9="","",Metas!G9) -> 44 | D19: =IF(Metas!B9="","",Metas!F9) -> 40 | E19: =IF(Metas!B9="","",Metas!H9) -> 0.40298507 | F19: =IF(Metas!B9="","",Metas!I9) -> 0.82417582 | G19: =IF(Metas!B9="","",Metas!J9) -> Em risco | H19: =IF(E19="","",REPT("█",ROUND(E19*20,0))) -> ████████
A20: =IF(Metas!B10="","",Metas!B10) -> Glosa recuperada por recurso no trimestre (R$) | B20: =IF(Metas!B10="","",Metas!C10) -> Dr. Paulo Andrade | C20: =IF(Metas!B10="","",Metas!G10) -> 200 | D20: =IF(Metas!B10="","",Metas!F10) -> 1000 | E20: =IF(Metas!B10="","",Metas!H10) -> 0.2 | F20: =IF(Metas!B10="","",Metas!I10) -> 0.82417582 | G20: =IF(Metas!B10="","",Metas!J10) -> Em risco | H20: =IF(E20="","",REPT("█",ROUND(E20*20,0))) -> ████
A21: =IF(Metas!B11="","",Metas!B11) -> Inadimplência a prazo: vencido ÷ (pago + vencido) (%) | B21: =IF(Metas!B11="","",Metas!C11) -> Dra. Carolina Mendes | C21: =IF(Metas!B11="","",Metas!G11) -> 9.4 | D21: =IF(Metas!B11="","",Metas!F11) -> 8 | E21: =IF(Metas!B11="","",Metas!H11) -> 0.51724138 | F21: =IF(Metas!B11="","",Metas!I11) -> 0.82417582 | G21: =IF(Metas!B11="","",Metas!J11) -> Em risco | H21: =IF(E21="","",REPT("█",ROUND(E21*20,0))) -> ██████████
A22: =IF(Metas!B12="","",Metas!B12) -> Reserva guardada em conta separada (R$) | B22: =IF(Metas!B12="","",Metas!C12) -> Dra. Carolina Mendes | C22: =IF(Metas!B12="","",Metas!G12) -> 14000 | D22: =IF(Metas!B12="","",Metas!F12) -> 17000 | E22: =IF(Metas!B12="","",Metas!H12) -> 0.66666667 | F22: =IF(Metas!B12="","",Metas!I12) -> 0.82417582 | G22: =IF(Metas!B12="","",Metas!J12) -> Atenção | H22: =IF(E22="","",REPT("█",ROUND(E22*20,0))) -> █████████████
A23: =IF(Metas!B13="","",Metas!B13) -> Conta de provisão de impostos, 13º e férias (R$) | B23: =IF(Metas!B13="","",Metas!C13) -> Dra. Carolina Mendes | C23: =IF(Metas!B13="","",Metas!G13) -> 17500 | D23: =IF(Metas!B13="","",Metas!F13) -> 18209 | E23: =IF(Metas!B13="","",Metas!H13) -> 0.92916375 | F23: =IF(Metas!B13="","",Metas!I13) -> 0.82417582 | G23: =IF(Metas!B13="","",Metas!J13) -> No ritmo | H23: =IF(E23="","",REPT("█",ROUND(E23*20,0))) -> ███████████████████
A25: Em risco primeiro: veja o que muda na rotina da semana (planilha 03) antes de mexer na meta.

Sheet Config
A1: Configurações
A2: Células amarelas: você preenche.
A4: Clínica | B4: Clínica Vida Plena (exemplo fictício)
A5: Trimestre | B5: 3º trimestre de 2026
A6: Início do trimestre | B6: 46204
A7: Fim do trimestre | B7: 46295
A8: Data de referência (hoje) | B8: 46279 | C8: Para simular o fim do trimestre, troque por uma data.
A9: Semana atual do trimestre | B9: =IF(B8<B6,0,MIN(13,INT((B8-B6)/7)+1)) -> 11
A10: % do trimestre decorrido | B10: =MAX(0,MIN(1,(B8-B6)/(B7-B6))) -> 0.82417582
A12: Pessoas da clínica (donos dos resultados-chave) | C12: Preencha de cima para baixo, sem pular linha.
A13: Nomes | B13: Dra. Carolina Mendes
B14: Dr. Paulo Andrade
B15: Bruna Carvalho

Sheet Metas
A1: Metas do trimestre da clínica
A2: Até 3 objetivos com até 3 resultados-chave cada. Preencha o amarelo; progresso e semáforo são calculados. Atualize o valor atual toda sexta.
A4: Objetivo | B4: Resultado-chave | C4: Dono | D4: Unidade | E4: Ponto de partida | F4: Meta | G4: Valor atual | H4: Progresso | I4: Esperado até hoje | J4: Semáforo | K4: Sentido | L4: Observação
A5: Agenda cheia, sem faltas | B5: Ocupação da agenda nas últimas 4 semanas (%) | C5: Bruna Carvalho | D5: % | E5: 75.2 | F5: 80 | G5: 74.5 | H5: =IF(OR(B5="",G5=""),"",IF(K5="Menor é melhor",IF(G5<=F5,1,IF(E5>F5,MAX(0,(E5-G5)/(E5-F5)),IF(G5=0,0,MAX(0,F5/G5)))),IF(G5>=F5,1,IF(E5<F5,MAX(0,(G5-E5)/(F5-E5)),IF(F5=0,0,MAX(0,G5/F5)))))) -> 0 | I5: =IF(B5="","",Config!$B$10) -> 0.82417582 | J5: =IF(OR(B5="",H5=""),"",IF(H5>=1,"Atingido",IF(H5>=I5-0.1,"No ritmo",IF(H5>=I5-0.25,"Atenção","Em risco")))) -> Em risco | K5: Maior é melhor | L5: Horas atendidas ÷ disponíveis nas 4 semanas até a sexta (Agenda da planilha 01). Partida = sexta 03/07, que olha 06/06 a 03/07: a agenda da 01 começa em 01/06, então dá para refazer a conta.
B6: Taxa de falta nas últimas 4 semanas (%) | C6: Bruna Carvalho | D6: % | E6: 6.9 | F6: 5 | G6: 7.1 | H6: =IF(OR(B6="",G6=""),"",IF(K6="Menor é melhor",IF(G6<=F6,1,IF(E6>F6,MAX(0,(E6-G6)/(E6-F6)),IF(G6=0,0,MAX(0,F6/G6)))),IF(G6>=F6,1,IF(E6<F6,MAX(0,(G6-E6)/(F6-E6)),IF(F6=0,0,MAX(0,G6/F6)))))) -> 0 | I6: =IF(B6="","",Config!$B$10) -> 0.82417582 | J6: =IF(OR(B6="",H6=""),"",IF(H6>=1,"Atingido",IF(H6>=I6-0.1,"No ritmo",IF(H6>=I6-0.25,"Atenção","Em risco")))) -> Em risco | K6: Menor é melhor | L6: Painel da planilha 02 (faltas ÷ (faltas + realizados)). Confirmação de véspera por mensagem e lista de espera.
B7: Pacientes na lista de retorno sem agendamento | C7: Bruna Carvalho | D7: pacientes | E7: 0 | F7: 8 | G7: 8 | H7: =IF(OR(B7="",G7=""),"",IF(K7="Menor é melhor",IF(G7<=F7,1,IF(E7>F7,MAX(0,(E7-G7)/(E7-F7)),IF(G7=0,0,MAX(0,F7/G7)))),IF(G7>=F7,1,IF(E7<F7,MAX(0,(G7-E7)/(F7-E7)),IF(F7=0,0,MAX(0,G7/F7)))))) -> 1 | I7: =IF(B7="","",Config!$B$10) -> 0.82417582 | J7: =IF(OR(B7="",H7=""),"",IF(H7>=1,"Atingido",IF(H7>=I7-0.1,"No ritmo",IF(H7>=I7-0.25,"Atenção","Em risco")))) -> Atingido | K7: Menor é melhor | L7: Lista de retorno da planilha 02 (hoje). Ligar na segunda-feira; a rotina da semana (03) tem esse passo.
A8: Convênio sob controle | B8: Glosa nos lotes pagos no ano (%) | C8: Dr. Paulo Andrade | D8: % | E8: 6.1 | F8: 4 | G8: 5.5 | H8: =IF(OR(B8="",G8=""),"",IF(K8="Menor é melhor",IF(G8<=F8,1,IF(E8>F8,MAX(0,(E8-G8)/(E8-F8)),IF(G8=0,0,MAX(0,F8/G8)))),IF(G8>=F8,1,IF(E8<F8,MAX(0,(G8-E8)/(F8-E8)),IF(F8=0,0,MAX(0,G8/F8)))))) -> 0.28571429 | I8: =IF(B8="","",Config!$B$10) -> 0.82417582 | J8: =IF(OR(B8="",H8=""),"",IF(H8>=1,"Atingido",IF(H8>=I8-0.1,"No ritmo",IF(H8>=I8-0.25,"Atenção","Em risco")))) -> Em risco | K8: Menor é melhor | L8: Painel da planilha 13 ("Glosa no ano %": glosa ÷ (pago + glosa) dos lotes pagos no ano). Conferir guias antes do envio (checklist do dia, 04).
B9: Prazo real médio de pagamento dos lotes (dias) | C9: Dr. Paulo Andrade | D9: dias | E9: 46.7 | F9: 40 | G9: 44 | H9: =IF(OR(B9="",G9=""),"",IF(K9="Menor é melhor",IF(G9<=F9,1,IF(E9>F9,MAX(0,(E9-G9)/(E9-F9)),IF(G9=0,0,MAX(0,F9/G9)))),IF(G9>=F9,1,IF(E9<F9,MAX(0,(G9-E9)/(F9-E9)),IF(F9=0,0,MAX(0,G9/F9)))))) -> 0.40298507 | I9: =IF(B9="","",Config!$B$10) -> 0.82417582 | J9: =IF(OR(B9="",H9=""),"",IF(H9>=1,"Atingido",IF(H9>=I9-0.1,"No ritmo",IF(H9>=I9-0.25,"Atenção","Em risco")))) -> Em risco | K9: Menor é melhor | L9: Dias entre o envio e o pagamento dos lotes pagos no trimestre (aba Lotes da 13, colunas Data de envio e Data do pagamento). Partida = mesma conta nos lotes pagos de janeiro a junho, que estão na mesma aba. Semana sem lote pago fica "—".
B10: Glosa recuperada por recurso no trimestre (R$) | C10: Dr. Paulo Andrade | D10: R$ | E10: 0 | F10: 1000 | G10: 200 | H10: =IF(OR(B10="",G10=""),"",IF(K10="Menor é melhor",IF(G10<=F10,1,IF(E10>F10,MAX(0,(E10-G10)/(E10-F10)),IF(G10=0,0,MAX(0,F10/G10)))),IF(G10>=F10,1,IF(E10<F10,MAX(0,(G10-E10)/(F10-E10)),IF(F10=0,0,MAX(0,G10/F10)))))) -> 0.2 | I10: =IF(B10="","",Config!$B$10) -> 0.82417582 | J10: =IF(OR(B10="",H10=""),"",IF(H10>=1,"Atingido",IF(H10>=I10-0.1,"No ritmo",IF(H10>=I10-0.25,"Atenção","Em risco")))) -> Em risco | K10: Maior é melhor | L10: Coluna "Valor recuperado" da planilha 13 (lotes com recurso aceito, recebido de julho a setembro).
A11: Caixa previsível | B11: Inadimplência a prazo: vencido ÷ (pago + vencido) (%) | C11: Dra. Carolina Mendes | D11: % | E11: 10.9 | F11: 8 | G11: 9.4 | H11: =IF(OR(B11="",G11=""),"",IF(K11="Menor é melhor",IF(G11<=F11,1,IF(E11>F11,MAX(0,(E11-G11)/(E11-F11)),IF(G11=0,0,MAX(0,F11/G11)))),IF(G11>=F11,1,IF(E11<F11,MAX(0,(G11-E11)/(F11-E11)),IF(F11=0,0,MAX(0,G11/F11)))))) -> 0.51724138 | I11: =IF(B11="","",Config!$B$10) -> 0.82417582 | J11: =IF(OR(B11="",H11=""),"",IF(H11>=1,"Atingido",IF(H11>=I11-0.1,"No ritmo",IF(H11>=I11-0.25,"Atenção","Em risco")))) -> Em risco | K11: Menor é melhor | L11: Painel da planilha 14 (só o que foi combinado a prazo). Régua de cobrança educada na 14.
B12: Reserva guardada em conta separada (R$) | C12: Dra. Carolina Mendes | D12: R$ | E12: 8000 | F12: 17000 | G12: 14000 | H12: =IF(OR(B12="",G12=""),"",IF(K12="Menor é melhor",IF(G12<=F12,1,IF(E12>F12,MAX(0,(E12-G12)/(E12-F12)),IF(G12=0,0,MAX(0,F12/G12)))),IF(G12>=F12,1,IF(E12<F12,MAX(0,(G12-E12)/(F12-E12)),IF(F12=0,0,MAX(0,G12/F12)))))) -> 0.66666667 | I12: =IF(B12="","",Config!$B$10) -> 0.82417582 | J12: =IF(OR(B12="",H12=""),"",IF(H12>=1,"Atingido",IF(H12>=I12-0.1,"No ritmo",IF(H12>=I12-0.25,"Atenção","Em risco")))) -> Atenção | K12: Maior é melhor | L12: Aporte de R$ 3.000 no fechamento de cada mês (planilha 12). A meta do ano é 1 mês de custo fixo com pró-labore (R$ 28.000); a do trimestre, três aportes.
B13: Conta de provisão de impostos, 13º e férias (R$) | C13: Dra. Carolina Mendes | D13: R$ | E13: 8200 | F13: 18209 | G13: 17500 | H13: =IF(OR(B13="",G13=""),"",IF(K13="Menor é melhor",IF(G13<=F13,1,IF(E13>F13,MAX(0,(E13-G13)/(E13-F13)),IF(G13=0,0,MAX(0,F13/G13)))),IF(G13>=F13,1,IF(E13<F13,MAX(0,(G13-E13)/(F13-E13)),IF(F13=0,0,MAX(0,G13/F13)))))) -> 0.92916375 | I13: =IF(B13="","",Config!$B$10) -> 0.82417582 | J13: =IF(OR(B13="",H13=""),"",IF(H13>=1,"Atingido",IF(H13>=I13-0.1,"No ritmo",IF(H13>=I13-0.25,"Atenção","Em risco")))) -> No ritmo | K13: Maior é melhor | L13: Meta = saldo provisionado de AGOSTO na planilha 10 (último mês fechado; o de setembro ainda muda até o dia 30). Atual = o que já está na conta separada (planilha 12).
A15: Progresso: valor atual no alvo = 100 %; fora do alvo, é o caminho andado entre o ponto de partida e a meta — e, quando o ponto de partida já estava dentro da meta (um teto ou piso a manter), é meta ÷ atual (16 pacientes para um teto de 8 = 50 %). Semáforo: Atingido (100%); No ritmo (progresso até 10 pontos abaixo do tempo decorrido); Atenção (até 25 pontos abaixo); Em risco (mais que isso). A planilha avisa; a ação é da clínica.
A16: Inadimplência = vencido ÷ (pago + vencido), a mesma conta das planilhas 14, 17 e 20 (só o que foi combinado a prazo). Valores em % digitados como 5,1 (não 0,051).

Sheet Semanas
A1: Acompanhamento semanal
A2: Toda sexta, copie o valor atual de cada resultado-chave para a coluna da semana. A linha fica com o histórico do trimestre.
A4: Resultado-chave | B4: Meta | C4: S1 | D4: S2 | E4: S3 | F4: S4 | G4: S5 | H4: S6 | I4: S7 | J4: S8 | K4: S9 | L4: S10 | M4: S11 | N4: S12 | O4: S13
A5: =IF(Metas!B5="","",Metas!B5) -> Ocupação da agenda nas últimas 4 semanas (%) | B5: =IF(Metas!B5="","",Metas!F5) -> 80 | C5: 75.2 | D5: 74.5 | E5: 71.7 | F5: 72.6 | G5: 71.7 | H5: 70.8 | I5: 72 | J5: 68.1 | K5: 70.3 | L5: 74.5 | M5: 74.5
A6: =IF(Metas!B6="","",Metas!B6) -> Taxa de falta nas últimas 4 semanas (%) | B6: =IF(Metas!B6="","",Metas!F6) -> 5 | C6: 6.9 | D6: 7.4 | E6: 8.7 | F6: 7.9 | G6: 9.1 | H6: 9.1 | I6: 8.6 | J6: 9.4 | K6: 8.8 | L6: 7.4 | M6: 7.1
A7: =IF(Metas!B7="","",Metas!B7) -> Pacientes na lista de retorno sem agendamento | B7: =IF(Metas!B7="","",Metas!F7) -> 8 | C7: 0 | D7: 0 | E7: 0 | F7: 0 | G7: 1 | H7: 1 | I7: 2 | J7: 2 | K7: 3 | L7: 5 | M7: 8
A8: =IF(Metas!B8="","",Metas!B8) -> Glosa nos lotes pagos no ano (%) | B8: =IF(Metas!B8="","",Metas!F8) -> 4 | C8: 6.1 | D8: 5.6 | E8: 5.6 | F8: 5.8 | G8: 5.8 | H8: 5.8 | I8: 5.8 | J8: 5.8 | K8: 5.8 | L8: 5.8 | M8: 5.5
A9: =IF(Metas!B9="","",Metas!B9) -> Prazo real médio de pagamento dos lotes (dias) | B9: =IF(Metas!B9="","",Metas!F9) -> 40 | C9: — | D9: 46.5 | E9: 46.5 | F9: 46 | G9: 46 | H9: 45.8 | I9: 45.8 | J9: 45.7 | K9: 45.7 | L9: 45.7 | M9: 44
A10: =IF(Metas!B10="","",Metas!B10) -> Glosa recuperada por recurso no trimestre (R$) | B10: =IF(Metas!B10="","",Metas!F10) -> 1000 | C10: 0 | D10: 0 | E10: 0 | F10: 0 | G10: 0 | H10: 0 | I10: 0 | J10: 0 | K10: 0 | L10: 0 | M10: 200
A11: =IF(Metas!B11="","",Metas!B11) -> Inadimplência a prazo: vencido ÷ (pago + vencido) (%) | B11: =IF(Metas!B11="","",Metas!F11) -> 8 | C11: 10.6 | D11: 9.8 | E11: 10.9 | F11: 10.7 | G11: 10 | H11: 10.9 | I11: 9.5 | J11: 10.8 | K11: 10.1 | L11: 8.8 | M11: 9.4
A12: =IF(Metas!B12="","",Metas!B12) -> Reserva guardada em conta separada (R$) | B12: =IF(Metas!B12="","",Metas!F12) -> 17000 | C12: 8000 | D12: 8000 | E12: 8000 | F12: 8000 | G12: 11000 | H12: 11000 | I12: 11000 | J12: 11000 | K12: 11000 | L12: 14000 | M12: 14000
A13: =IF(Metas!B13="","",Metas!B13) -> Conta de provisão de impostos, 13º e férias (R$) | B13: =IF(Metas!B13="","",Metas!F13) -> 18209 | C13: 8200 | D13: 8200 | E13: 8200 | F13: 8200 | G13: 11300 | H13: 11300 | I13: 11300 | J13: 11300 | K13: 11300 | L13: 14400 | M13: 17500
A15: A coluna da semana atual fica destacada. Valores em % são digitados como 16,8 (não 0,168). Semana sem nada a medir: escreva "—" (não escreva 0, que puxa a série para baixo como se o resultado tivesse desabado). No exemplo, S1 a S11 são as sextas de 03/07 a 11/09/2026, e o prazo real dos lotes fica "—" na S1 porque nenhum lote foi pago naquela semana do trimestre.
