Workbook

Sheet Como usar
A1: Semana Organizada
A2: Kit IA no Trabalho · Seu Sócio Gestor · versão 1.0 (setembro de 2026)
A4: O que esta planilha faz | B4: Lista as suas tarefas com prazo e prioridade e mostra, na aba Hoje, o que fazer primeiro, a carga dos próximos 7 dias e a situação de cada responsável.
A5: Passo 1 | B5: Abra a aba Config. Confira a data de referência (fica em =HOJE()) e a capacidade de horas por dia. Ajuste a lista de responsáveis e de projetos, preenchendo de cima para baixo, sem pular linha.
A6: Passo 2 | B6: Vá para a aba Tarefas. Apague os exemplos (linhas amarelas) e digite as suas tarefas: nome, projeto, responsável, prazo, impacto (1 a 3), urgência (1 a 3), horas e status.
A7: Passo 3 | B7: Abra a aba Hoje. Ela é só leitura: prioridades, carga por dia e resumo por pessoa se atualizam sozinhos.
A8: Passo 4 | B8: Todo dia, mude o status do que terminou para Feito. Uma vez por semana, revise prazos e horas.
A9: Com a IA | B9: Use o prompt "Organizar 01" da biblioteca do kit: cole uma lista bagunçada (e-mail, ata, áudio transcrito) e a IA devolve as tarefas no formato desta planilha, prontas para colar.
A10: Legenda | B10: Células amarelas: você preenche. Células brancas: calculadas, não mexa. Linhas vermelhas: atrasadas. Linhas amarelas na aba Hoje: vencem hoje.
A11: Proteção | B11: As fórmulas estão protegidas sem senha, só para evitar apagar sem querer. Para editar: Revisar > Desproteger planilha (Excel) ou Dados > Proteger intervalos (Google Sheets).
A12: Google Sheets | B12: Faça upload do arquivo no Google Drive e abra com o Google Sheets. Tudo funciona: listas, cores e fórmulas.
A13: Exemplos | B13: Os dados de exemplo são fictícios (Ana, Bruno e Carla numa agência inventada). Os exemplos usam datas relativas a hoje (prazos como =HOJE()+2); apague-os e digite as suas.
A14: Suporte | B14: suporte@seusociogestor.com.br · resposta em até 5 dias úteis · reembolso em até 7 dias pelo mesmo canal.
A16: Amostra | B16: Assim ficam as células que você preenche.

Sheet Hoje
A1: Hoje
A2: ="Painel de "&TEXT(Config!B4,"dd/mm/yyyy")&". Nada para preencher aqui: tudo vem da aba Tarefas." -> Painel de 18/09/2026. Nada para preencher aqui: tudo vem da aba Tarefas.
A4: Atrasadas | C4: Para hoje | E4: Esta semana | G4: Abertas no total | I4: Feitas
A5: =COUNTIF(Tarefas!$L$4:$L$303,"Atrasada") -> 2 | C5: =COUNTIF(Tarefas!$L$4:$L$303,"Hoje") -> 1 | E5: =COUNTIF(Tarefas!$L$4:$L$303,"Esta semana") -> 9 | G5: =COUNTIFS(Tarefas!$B$4:$B$303,"<>",Tarefas!$I$4:$I$303,"<>Feito",Tarefas!$I$4:$I$303,"<>Cancelado") -> 17 | I5: =COUNTIF(Tarefas!$I$4:$I$303,"Feito") -> 2
A7: O que fazer primeiro
A8: Ordem (as 12 primeiras): situação (atrasada, hoje, esta semana) combinada com impacto × urgência. Uma tarefa alta de hoje vem antes de uma baixa atrasada. As demais ficam na aba Tarefas.
A9: # | B9: Tarefa | C9: Prazo | D9: Situação | E9: Prioridade | F9: Responsável | G9: Horas
A10: 1 | B10: =IFERROR(IF(LARGE(Tarefas!$M$4:$M$303,1)>0,INDEX(Tarefas!$B$4:$B$303,MATCH(LARGE(Tarefas!$M$4:$M$303,1),Tarefas!$M$4:$M$303,0)),""),"") -> Enviar relatório de setembro para a diretoria | C10: =IFERROR(IF(LARGE(Tarefas!$M$4:$M$303,1)>0,INDEX(Tarefas!$E$4:$E$303,MATCH(LARGE(Tarefas!$M$4:$M$303,1),Tarefas!$M$4:$M$303,0)),""),"") -> 46282 | D10: =IFERROR(IF(LARGE(Tarefas!$M$4:$M$303,1)>0,INDEX(Tarefas!$L$4:$L$303,MATCH(LARGE(Tarefas!$M$4:$M$303,1),Tarefas!$M$4:$M$303,0)),""),"") -> Atrasada | E10: =IFERROR(IF(LARGE(Tarefas!$M$4:$M$303,1)>0,INDEX(Tarefas!$J$4:$J$303,MATCH(LARGE(Tarefas!$M$4:$M$303,1),Tarefas!$M$4:$M$303,0)),""),"") -> Alta | F10: =IFERROR(IF(LARGE(Tarefas!$M$4:$M$303,1)>0,INDEX(Tarefas!$D$4:$D$303,MATCH(LARGE(Tarefas!$M$4:$M$303,1),Tarefas!$M$4:$M$303,0)),""),"") -> Ana (você) | G10: =IFERROR(IF(LARGE(Tarefas!$M$4:$M$303,1)>0,INDEX(Tarefas!$H$4:$H$303,MATCH(LARGE(Tarefas!$M$4:$M$303,1),Tarefas!$M$4:$M$303,0)),""),"") -> 2
A11: 2 | B11: =IFERROR(IF(LARGE(Tarefas!$M$4:$M$303,2)>0,INDEX(Tarefas!$B$4:$B$303,MATCH(LARGE(Tarefas!$M$4:$M$303,2),Tarefas!$M$4:$M$303,0)),""),"") -> Revisar proposta comercial da Aurora | C11: =IFERROR(IF(LARGE(Tarefas!$M$4:$M$303,2)>0,INDEX(Tarefas!$E$4:$E$303,MATCH(LARGE(Tarefas!$M$4:$M$303,2),Tarefas!$M$4:$M$303,0)),""),"") -> 46283 | D11: =IFERROR(IF(LARGE(Tarefas!$M$4:$M$303,2)>0,INDEX(Tarefas!$L$4:$L$303,MATCH(LARGE(Tarefas!$M$4:$M$303,2),Tarefas!$M$4:$M$303,0)),""),"") -> Hoje | E11: =IFERROR(IF(LARGE(Tarefas!$M$4:$M$303,2)>0,INDEX(Tarefas!$J$4:$J$303,MATCH(LARGE(Tarefas!$M$4:$M$303,2),Tarefas!$M$4:$M$303,0)),""),"") -> Alta | F11: =IFERROR(IF(LARGE(Tarefas!$M$4:$M$303,2)>0,INDEX(Tarefas!$D$4:$D$303,MATCH(LARGE(Tarefas!$M$4:$M$303,2),Tarefas!$M$4:$M$303,0)),""),"") -> Ana (você) | G11: =IFERROR(IF(LARGE(Tarefas!$M$4:$M$303,2)>0,INDEX(Tarefas!$H$4:$H$303,MATCH(LARGE(Tarefas!$M$4:$M$303,2),Tarefas!$M$4:$M$303,0)),""),"") -> 1.5
A12: 3 | B12: =IFERROR(IF(LARGE(Tarefas!$M$4:$M$303,3)>0,INDEX(Tarefas!$B$4:$B$303,MATCH(LARGE(Tarefas!$M$4:$M$303,3),Tarefas!$M$4:$M$303,0)),""),"") -> Responder pesquisa de clima | C12: =IFERROR(IF(LARGE(Tarefas!$M$4:$M$303,3)>0,INDEX(Tarefas!$E$4:$E$303,MATCH(LARGE(Tarefas!$M$4:$M$303,3),Tarefas!$M$4:$M$303,0)),""),"") -> 46281 | D12: =IFERROR(IF(LARGE(Tarefas!$M$4:$M$303,3)>0,INDEX(Tarefas!$L$4:$L$303,MATCH(LARGE(Tarefas!$M$4:$M$303,3),Tarefas!$M$4:$M$303,0)),""),"") -> Atrasada | E12: =IFERROR(IF(LARGE(Tarefas!$M$4:$M$303,3)>0,INDEX(Tarefas!$J$4:$J$303,MATCH(LARGE(Tarefas!$M$4:$M$303,3),Tarefas!$M$4:$M$303,0)),""),"") -> Baixa | F12: =IFERROR(IF(LARGE(Tarefas!$M$4:$M$303,3)>0,INDEX(Tarefas!$D$4:$D$303,MATCH(LARGE(Tarefas!$M$4:$M$303,3),Tarefas!$M$4:$M$303,0)),""),"") -> Ana (você) | G12: =IFERROR(IF(LARGE(Tarefas!$M$4:$M$303,3)>0,INDEX(Tarefas!$H$4:$H$303,MATCH(LARGE(Tarefas!$M$4:$M$303,3),Tarefas!$M$4:$M$303,0)),""),"") -> 0.5
A13: 4 | B13: =IFERROR(IF(LARGE(Tarefas!$M$4:$M$303,4)>0,INDEX(Tarefas!$B$4:$B$303,MATCH(LARGE(Tarefas!$M$4:$M$303,4),Tarefas!$M$4:$M$303,0)),""),"") -> Montar apresentação da reunião de quinta | C13: =IFERROR(IF(LARGE(Tarefas!$M$4:$M$303,4)>0,INDEX(Tarefas!$E$4:$E$303,MATCH(LARGE(Tarefas!$M$4:$M$303,4),Tarefas!$M$4:$M$303,0)),""),"") -> 46284 | D13: =IFERROR(IF(LARGE(Tarefas!$M$4:$M$303,4)>0,INDEX(Tarefas!$L$4:$L$303,MATCH(LARGE(Tarefas!$M$4:$M$303,4),Tarefas!$M$4:$M$303,0)),""),"") -> Esta semana | E13: =IFERROR(IF(LARGE(Tarefas!$M$4:$M$303,4)>0,INDEX(Tarefas!$J$4:$J$303,MATCH(LARGE(Tarefas!$M$4:$M$303,4),Tarefas!$M$4:$M$303,0)),""),"") -> Alta | F13: =IFERROR(IF(LARGE(Tarefas!$M$4:$M$303,4)>0,INDEX(Tarefas!$D$4:$D$303,MATCH(LARGE(Tarefas!$M$4:$M$303,4),Tarefas!$M$4:$M$303,0)),""),"") -> Ana (você) | G13: =IFERROR(IF(LARGE(Tarefas!$M$4:$M$303,4)>0,INDEX(Tarefas!$H$4:$H$303,MATCH(LARGE(Tarefas!$M$4:$M$303,4),Tarefas!$M$4:$M$303,0)),""),"") -> 3
A14: 5 | B14: =IFERROR(IF(LARGE(Tarefas!$M$4:$M$303,5)>0,INDEX(Tarefas!$B$4:$B$303,MATCH(LARGE(Tarefas!$M$4:$M$303,5),Tarefas!$M$4:$M$303,0)),""),"") -> Aprovar arte do post de terça | C14: =IFERROR(IF(LARGE(Tarefas!$M$4:$M$303,5)>0,INDEX(Tarefas!$E$4:$E$303,MATCH(LARGE(Tarefas!$M$4:$M$303,5),Tarefas!$M$4:$M$303,0)),""),"") -> 46284 | D14: =IFERROR(IF(LARGE(Tarefas!$M$4:$M$303,5)>0,INDEX(Tarefas!$L$4:$L$303,MATCH(LARGE(Tarefas!$M$4:$M$303,5),Tarefas!$M$4:$M$303,0)),""),"") -> Esta semana | E14: =IFERROR(IF(LARGE(Tarefas!$M$4:$M$303,5)>0,INDEX(Tarefas!$J$4:$J$303,MATCH(LARGE(Tarefas!$M$4:$M$303,5),Tarefas!$M$4:$M$303,0)),""),"") -> Alta | F14: =IFERROR(IF(LARGE(Tarefas!$M$4:$M$303,5)>0,INDEX(Tarefas!$D$4:$D$303,MATCH(LARGE(Tarefas!$M$4:$M$303,5),Tarefas!$M$4:$M$303,0)),""),"") -> Carla | G14: =IFERROR(IF(LARGE(Tarefas!$M$4:$M$303,5)>0,INDEX(Tarefas!$H$4:$H$303,MATCH(LARGE(Tarefas!$M$4:$M$303,5),Tarefas!$M$4:$M$303,0)),""),"") -> 0.5
A15: 6 | B15: =IFERROR(IF(LARGE(Tarefas!$M$4:$M$303,6)>0,INDEX(Tarefas!$B$4:$B$303,MATCH(LARGE(Tarefas!$M$4:$M$303,6),Tarefas!$M$4:$M$303,0)),""),"") -> Fechar pauta de outubro | C15: =IFERROR(IF(LARGE(Tarefas!$M$4:$M$303,6)>0,INDEX(Tarefas!$E$4:$E$303,MATCH(LARGE(Tarefas!$M$4:$M$303,6),Tarefas!$M$4:$M$303,0)),""),"") -> 46286 | D15: =IFERROR(IF(LARGE(Tarefas!$M$4:$M$303,6)>0,INDEX(Tarefas!$L$4:$L$303,MATCH(LARGE(Tarefas!$M$4:$M$303,6),Tarefas!$M$4:$M$303,0)),""),"") -> Esta semana | E15: =IFERROR(IF(LARGE(Tarefas!$M$4:$M$303,6)>0,INDEX(Tarefas!$J$4:$J$303,MATCH(LARGE(Tarefas!$M$4:$M$303,6),Tarefas!$M$4:$M$303,0)),""),"") -> Alta | F15: =IFERROR(IF(LARGE(Tarefas!$M$4:$M$303,6)>0,INDEX(Tarefas!$D$4:$D$303,MATCH(LARGE(Tarefas!$M$4:$M$303,6),Tarefas!$M$4:$M$303,0)),""),"") -> Carla | G15: =IFERROR(IF(LARGE(Tarefas!$M$4:$M$303,6)>0,INDEX(Tarefas!$H$4:$H$303,MATCH(LARGE(Tarefas!$M$4:$M$303,6),Tarefas!$M$4:$M$303,0)),""),"") -> 2
A16: 7 | B16: =IFERROR(IF(LARGE(Tarefas!$M$4:$M$303,7)>0,INDEX(Tarefas!$B$4:$B$303,MATCH(LARGE(Tarefas!$M$4:$M$303,7),Tarefas!$M$4:$M$303,0)),""),"") -> Escrever e-mail de resultados para a Horizonte | C16: =IFERROR(IF(LARGE(Tarefas!$M$4:$M$303,7)>0,INDEX(Tarefas!$E$4:$E$303,MATCH(LARGE(Tarefas!$M$4:$M$303,7),Tarefas!$M$4:$M$303,0)),""),"") -> 46287 | D16: =IFERROR(IF(LARGE(Tarefas!$M$4:$M$303,7)>0,INDEX(Tarefas!$L$4:$L$303,MATCH(LARGE(Tarefas!$M$4:$M$303,7),Tarefas!$M$4:$M$303,0)),""),"") -> Esta semana | E16: =IFERROR(IF(LARGE(Tarefas!$M$4:$M$303,7)>0,INDEX(Tarefas!$J$4:$J$303,MATCH(LARGE(Tarefas!$M$4:$M$303,7),Tarefas!$M$4:$M$303,0)),""),"") -> Alta | F16: =IFERROR(IF(LARGE(Tarefas!$M$4:$M$303,7)>0,INDEX(Tarefas!$D$4:$D$303,MATCH(LARGE(Tarefas!$M$4:$M$303,7),Tarefas!$M$4:$M$303,0)),""),"") -> Ana (você) | G16: =IFERROR(IF(LARGE(Tarefas!$M$4:$M$303,7)>0,INDEX(Tarefas!$H$4:$H$303,MATCH(LARGE(Tarefas!$M$4:$M$303,7),Tarefas!$M$4:$M$303,0)),""),"") -> 1
A17: 8 | B17: =IFERROR(IF(LARGE(Tarefas!$M$4:$M$303,8)>0,INDEX(Tarefas!$B$4:$B$303,MATCH(LARGE(Tarefas!$M$4:$M$303,8),Tarefas!$M$4:$M$303,0)),""),"") -> Atualizar planilha de leads | C17: =IFERROR(IF(LARGE(Tarefas!$M$4:$M$303,8)>0,INDEX(Tarefas!$E$4:$E$303,MATCH(LARGE(Tarefas!$M$4:$M$303,8),Tarefas!$M$4:$M$303,0)),""),"") -> 46284 | D17: =IFERROR(IF(LARGE(Tarefas!$M$4:$M$303,8)>0,INDEX(Tarefas!$L$4:$L$303,MATCH(LARGE(Tarefas!$M$4:$M$303,8),Tarefas!$M$4:$M$303,0)),""),"") -> Esta semana | E17: =IFERROR(IF(LARGE(Tarefas!$M$4:$M$303,8)>0,INDEX(Tarefas!$J$4:$J$303,MATCH(LARGE(Tarefas!$M$4:$M$303,8),Tarefas!$M$4:$M$303,0)),""),"") -> Média | F17: =IFERROR(IF(LARGE(Tarefas!$M$4:$M$303,8)>0,INDEX(Tarefas!$D$4:$D$303,MATCH(LARGE(Tarefas!$M$4:$M$303,8),Tarefas!$M$4:$M$303,0)),""),"") -> Bruno | G17: =IFERROR(IF(LARGE(Tarefas!$M$4:$M$303,8)>0,INDEX(Tarefas!$H$4:$H$303,MATCH(LARGE(Tarefas!$M$4:$M$303,8),Tarefas!$M$4:$M$303,0)),""),"") -> 1
A18: 9 | B18: =IFERROR(IF(LARGE(Tarefas!$M$4:$M$303,9)>0,INDEX(Tarefas!$B$4:$B$303,MATCH(LARGE(Tarefas!$M$4:$M$303,9),Tarefas!$M$4:$M$303,0)),""),"") -> Reunião de alinhamento com o Bruno | C18: =IFERROR(IF(LARGE(Tarefas!$M$4:$M$303,9)>0,INDEX(Tarefas!$E$4:$E$303,MATCH(LARGE(Tarefas!$M$4:$M$303,9),Tarefas!$M$4:$M$303,0)),""),"") -> 46285 | D18: =IFERROR(IF(LARGE(Tarefas!$M$4:$M$303,9)>0,INDEX(Tarefas!$L$4:$L$303,MATCH(LARGE(Tarefas!$M$4:$M$303,9),Tarefas!$M$4:$M$303,0)),""),"") -> Esta semana | E18: =IFERROR(IF(LARGE(Tarefas!$M$4:$M$303,9)>0,INDEX(Tarefas!$J$4:$J$303,MATCH(LARGE(Tarefas!$M$4:$M$303,9),Tarefas!$M$4:$M$303,0)),""),"") -> Média | F18: =IFERROR(IF(LARGE(Tarefas!$M$4:$M$303,9)>0,INDEX(Tarefas!$D$4:$D$303,MATCH(LARGE(Tarefas!$M$4:$M$303,9),Tarefas!$M$4:$M$303,0)),""),"") -> Ana (você) | G18: =IFERROR(IF(LARGE(Tarefas!$M$4:$M$303,9)>0,INDEX(Tarefas!$H$4:$H$303,MATCH(LARGE(Tarefas!$M$4:$M$303,9),Tarefas!$M$4:$M$303,0)),""),"") -> 1
A19: 10 | B19: =IFERROR(IF(LARGE(Tarefas!$M$4:$M$303,10)>0,INDEX(Tarefas!$B$4:$B$303,MATCH(LARGE(Tarefas!$M$4:$M$303,10),Tarefas!$M$4:$M$303,0)),""),"") -> Preparar orçamento do vídeo institucional | C19: =IFERROR(IF(LARGE(Tarefas!$M$4:$M$303,10)>0,INDEX(Tarefas!$E$4:$E$303,MATCH(LARGE(Tarefas!$M$4:$M$303,10),Tarefas!$M$4:$M$303,0)),""),"") -> 46289 | D19: =IFERROR(IF(LARGE(Tarefas!$M$4:$M$303,10)>0,INDEX(Tarefas!$L$4:$L$303,MATCH(LARGE(Tarefas!$M$4:$M$303,10),Tarefas!$M$4:$M$303,0)),""),"") -> Esta semana | E19: =IFERROR(IF(LARGE(Tarefas!$M$4:$M$303,10)>0,INDEX(Tarefas!$J$4:$J$303,MATCH(LARGE(Tarefas!$M$4:$M$303,10),Tarefas!$M$4:$M$303,0)),""),"") -> Média | F19: =IFERROR(IF(LARGE(Tarefas!$M$4:$M$303,10)>0,INDEX(Tarefas!$D$4:$D$303,MATCH(LARGE(Tarefas!$M$4:$M$303,10),Tarefas!$M$4:$M$303,0)),""),"") -> Ana (você) | G19: =IFERROR(IF(LARGE(Tarefas!$M$4:$M$303,10)>0,INDEX(Tarefas!$H$4:$H$303,MATCH(LARGE(Tarefas!$M$4:$M$303,10),Tarefas!$M$4:$M$303,0)),""),"") -> 2
A20: 11 | B20: =IFERROR(IF(LARGE(Tarefas!$M$4:$M$303,11)>0,INDEX(Tarefas!$B$4:$B$303,MATCH(LARGE(Tarefas!$M$4:$M$303,11),Tarefas!$M$4:$M$303,0)),""),"") -> Conferir faturas dos fornecedores | C20: =IFERROR(IF(LARGE(Tarefas!$M$4:$M$303,11)>0,INDEX(Tarefas!$E$4:$E$303,MATCH(LARGE(Tarefas!$M$4:$M$303,11),Tarefas!$M$4:$M$303,0)),""),"") -> 46287 | D20: =IFERROR(IF(LARGE(Tarefas!$M$4:$M$303,11)>0,INDEX(Tarefas!$L$4:$L$303,MATCH(LARGE(Tarefas!$M$4:$M$303,11),Tarefas!$M$4:$M$303,0)),""),"") -> Esta semana | E20: =IFERROR(IF(LARGE(Tarefas!$M$4:$M$303,11)>0,INDEX(Tarefas!$J$4:$J$303,MATCH(LARGE(Tarefas!$M$4:$M$303,11),Tarefas!$M$4:$M$303,0)),""),"") -> Baixa | F20: =IFERROR(IF(LARGE(Tarefas!$M$4:$M$303,11)>0,INDEX(Tarefas!$D$4:$D$303,MATCH(LARGE(Tarefas!$M$4:$M$303,11),Tarefas!$M$4:$M$303,0)),""),"") -> Ana (você) | G20: =IFERROR(IF(LARGE(Tarefas!$M$4:$M$303,11)>0,INDEX(Tarefas!$H$4:$H$303,MATCH(LARGE(Tarefas!$M$4:$M$303,11),Tarefas!$M$4:$M$303,0)),""),"") -> 1
A21: 12 | B21: =IFERROR(IF(LARGE(Tarefas!$M$4:$M$303,12)>0,INDEX(Tarefas!$B$4:$B$303,MATCH(LARGE(Tarefas!$M$4:$M$303,12),Tarefas!$M$4:$M$303,0)),""),"") -> Organizar pasta de fotos do evento | C21: =IFERROR(IF(LARGE(Tarefas!$M$4:$M$303,12)>0,INDEX(Tarefas!$E$4:$E$303,MATCH(LARGE(Tarefas!$M$4:$M$303,12),Tarefas!$M$4:$M$303,0)),""),"") -> 46288 | D21: =IFERROR(IF(LARGE(Tarefas!$M$4:$M$303,12)>0,INDEX(Tarefas!$L$4:$L$303,MATCH(LARGE(Tarefas!$M$4:$M$303,12),Tarefas!$M$4:$M$303,0)),""),"") -> Esta semana | E21: =IFERROR(IF(LARGE(Tarefas!$M$4:$M$303,12)>0,INDEX(Tarefas!$J$4:$J$303,MATCH(LARGE(Tarefas!$M$4:$M$303,12),Tarefas!$M$4:$M$303,0)),""),"") -> Baixa | F21: =IFERROR(IF(LARGE(Tarefas!$M$4:$M$303,12)>0,INDEX(Tarefas!$D$4:$D$303,MATCH(LARGE(Tarefas!$M$4:$M$303,12),Tarefas!$M$4:$M$303,0)),""),"") -> Bruno | G21: =IFERROR(IF(LARGE(Tarefas!$M$4:$M$303,12)>0,INDEX(Tarefas!$H$4:$H$303,MATCH(LARGE(Tarefas!$M$4:$M$303,12),Tarefas!$M$4:$M$303,0)),""),"") -> 2
A23: Carga dos próximos 7 dias
A24: Dia | B24: Data | C24: Tarefas | D24: Horas | E24: % da capacidade | F24: Barra
A25: =CHOOSE(WEEKDAY(B25),"dom","seg","ter","qua","qui","sex","sáb") -> sex | B25: =Config!$B$4+0 -> 46283 | C25: =COUNTIFS(Tarefas!$E$4:$E$303,B25,Tarefas!$I$4:$I$303,"<>Feito",Tarefas!$I$4:$I$303,"<>Cancelado",Tarefas!$B$4:$B$303,"<>") -> 1 | D25: =SUMIFS(Tarefas!$H$4:$H$303,Tarefas!$E$4:$E$303,B25,Tarefas!$I$4:$I$303,"<>Feito",Tarefas!$I$4:$I$303,"<>Cancelado") -> 1.5 | E25: =IF(Config!$B$6>0,D25/Config!$B$6,0) -> 0.25 | F25: =REPT("█",ROUND(D25,0))&IF(D25>Config!$B$6," ⚠ acima da capacidade","") -> ██
A26: =CHOOSE(WEEKDAY(B26),"dom","seg","ter","qua","qui","sex","sáb") -> sáb | B26: =Config!$B$4+1 -> 46284 | C26: =COUNTIFS(Tarefas!$E$4:$E$303,B26,Tarefas!$I$4:$I$303,"<>Feito",Tarefas!$I$4:$I$303,"<>Cancelado",Tarefas!$B$4:$B$303,"<>") -> 3 | D26: =SUMIFS(Tarefas!$H$4:$H$303,Tarefas!$E$4:$E$303,B26,Tarefas!$I$4:$I$303,"<>Feito",Tarefas!$I$4:$I$303,"<>Cancelado") -> 4.5 | E26: =IF(Config!$B$6>0,D26/Config!$B$6,0) -> 0.75 | F26: =REPT("█",ROUND(D26,0))&IF(D26>Config!$B$6," ⚠ acima da capacidade","") -> █████
A27: =CHOOSE(WEEKDAY(B27),"dom","seg","ter","qua","qui","sex","sáb") -> dom | B27: =Config!$B$4+2 -> 46285 | C27: =COUNTIFS(Tarefas!$E$4:$E$303,B27,Tarefas!$I$4:$I$303,"<>Feito",Tarefas!$I$4:$I$303,"<>Cancelado",Tarefas!$B$4:$B$303,"<>") -> 1 | D27: =SUMIFS(Tarefas!$H$4:$H$303,Tarefas!$E$4:$E$303,B27,Tarefas!$I$4:$I$303,"<>Feito",Tarefas!$I$4:$I$303,"<>Cancelado") -> 1 | E27: =IF(Config!$B$6>0,D27/Config!$B$6,0) -> 0.16666667 | F27: =REPT("█",ROUND(D27,0))&IF(D27>Config!$B$6," ⚠ acima da capacidade","") -> █
A28: =CHOOSE(WEEKDAY(B28),"dom","seg","ter","qua","qui","sex","sáb") -> seg | B28: =Config!$B$4+3 -> 46286 | C28: =COUNTIFS(Tarefas!$E$4:$E$303,B28,Tarefas!$I$4:$I$303,"<>Feito",Tarefas!$I$4:$I$303,"<>Cancelado",Tarefas!$B$4:$B$303,"<>") -> 1 | D28: =SUMIFS(Tarefas!$H$4:$H$303,Tarefas!$E$4:$E$303,B28,Tarefas!$I$4:$I$303,"<>Feito",Tarefas!$I$4:$I$303,"<>Cancelado") -> 2 | E28: =IF(Config!$B$6>0,D28/Config!$B$6,0) -> 0.33333333 | F28: =REPT("█",ROUND(D28,0))&IF(D28>Config!$B$6," ⚠ acima da capacidade","") -> ██
A29: =CHOOSE(WEEKDAY(B29),"dom","seg","ter","qua","qui","sex","sáb") -> ter | B29: =Config!$B$4+4 -> 46287 | C29: =COUNTIFS(Tarefas!$E$4:$E$303,B29,Tarefas!$I$4:$I$303,"<>Feito",Tarefas!$I$4:$I$303,"<>Cancelado",Tarefas!$B$4:$B$303,"<>") -> 2 | D29: =SUMIFS(Tarefas!$H$4:$H$303,Tarefas!$E$4:$E$303,B29,Tarefas!$I$4:$I$303,"<>Feito",Tarefas!$I$4:$I$303,"<>Cancelado") -> 2 | E29: =IF(Config!$B$6>0,D29/Config!$B$6,0) -> 0.33333333 | F29: =REPT("█",ROUND(D29,0))&IF(D29>Config!$B$6," ⚠ acima da capacidade","") -> ██
A30: =CHOOSE(WEEKDAY(B30),"dom","seg","ter","qua","qui","sex","sáb") -> qua | B30: =Config!$B$4+5 -> 46288 | C30: =COUNTIFS(Tarefas!$E$4:$E$303,B30,Tarefas!$I$4:$I$303,"<>Feito",Tarefas!$I$4:$I$303,"<>Cancelado",Tarefas!$B$4:$B$303,"<>") -> 1 | D30: =SUMIFS(Tarefas!$H$4:$H$303,Tarefas!$E$4:$E$303,B30,Tarefas!$I$4:$I$303,"<>Feito",Tarefas!$I$4:$I$303,"<>Cancelado") -> 2 | E30: =IF(Config!$B$6>0,D30/Config!$B$6,0) -> 0.33333333 | F30: =REPT("█",ROUND(D30,0))&IF(D30>Config!$B$6," ⚠ acima da capacidade","") -> ██
A31: =CHOOSE(WEEKDAY(B31),"dom","seg","ter","qua","qui","sex","sáb") -> qui | B31: =Config!$B$4+6 -> 46289 | C31: =COUNTIFS(Tarefas!$E$4:$E$303,B31,Tarefas!$I$4:$I$303,"<>Feito",Tarefas!$I$4:$I$303,"<>Cancelado",Tarefas!$B$4:$B$303,"<>") -> 1 | D31: =SUMIFS(Tarefas!$H$4:$H$303,Tarefas!$E$4:$E$303,B31,Tarefas!$I$4:$I$303,"<>Feito",Tarefas!$I$4:$I$303,"<>Cancelado") -> 2 | E31: =IF(Config!$B$6>0,D31/Config!$B$6,0) -> 0.33333333 | F31: =REPT("█",ROUND(D31,0))&IF(D31>Config!$B$6," ⚠ acima da capacidade","") -> ██
A32: Capacidade por dia definida em Config (padrão 6 h).
A34: Por responsável
A35: Responsável | C35: Abertas | D35: Atrasadas | E35: Para hoje | F35: Horas abertas
A36: =IF(Config!$B$9="","",Config!$B$9) -> Ana (você) | C36: =IF(Config!$B$9="","",COUNTIFS(Tarefas!$D$4:$D$303,Config!$B$9,Tarefas!$I$4:$I$303,"<>Feito",Tarefas!$I$4:$I$303,"<>Cancelado",Tarefas!$B$4:$B$303,"<>")) -> 10 | D36: =IF(Config!$B$9="","",COUNTIFS(Tarefas!$D$4:$D$303,Config!$B$9,Tarefas!$L$4:$L$303,"Atrasada")) -> 2 | E36: =IF(Config!$B$9="","",COUNTIFS(Tarefas!$D$4:$D$303,Config!$B$9,Tarefas!$L$4:$L$303,"Hoje")) -> 1 | F36: =IF(Config!$B$9="","",SUMIFS(Tarefas!$H$4:$H$303,Tarefas!$D$4:$D$303,Config!$B$9,Tarefas!$I$4:$I$303,"<>Feito",Tarefas!$I$4:$I$303,"<>Cancelado")) -> 15
A37: =IF(Config!$B$10="","",Config!$B$10) -> Bruno | C37: =IF(Config!$B$10="","",COUNTIFS(Tarefas!$D$4:$D$303,Config!$B$10,Tarefas!$I$4:$I$303,"<>Feito",Tarefas!$I$4:$I$303,"<>Cancelado",Tarefas!$B$4:$B$303,"<>")) -> 4 | D37: =IF(Config!$B$10="","",COUNTIFS(Tarefas!$D$4:$D$303,Config!$B$10,Tarefas!$L$4:$L$303,"Atrasada")) -> 0 | E37: =IF(Config!$B$10="","",COUNTIFS(Tarefas!$D$4:$D$303,Config!$B$10,Tarefas!$L$4:$L$303,"Hoje")) -> 0 | F37: =IF(Config!$B$10="","",SUMIFS(Tarefas!$H$4:$H$303,Tarefas!$D$4:$D$303,Config!$B$10,Tarefas!$I$4:$I$303,"<>Feito",Tarefas!$I$4:$I$303,"<>Cancelado")) -> 8.5
A38: =IF(Config!$B$11="","",Config!$B$11) -> Carla | C38: =IF(Config!$B$11="","",COUNTIFS(Tarefas!$D$4:$D$303,Config!$B$11,Tarefas!$I$4:$I$303,"<>Feito",Tarefas!$I$4:$I$303,"<>Cancelado",Tarefas!$B$4:$B$303,"<>")) -> 3 | D38: =IF(Config!$B$11="","",COUNTIFS(Tarefas!$D$4:$D$303,Config!$B$11,Tarefas!$L$4:$L$303,"Atrasada")) -> 0 | E38: =IF(Config!$B$11="","",COUNTIFS(Tarefas!$D$4:$D$303,Config!$B$11,Tarefas!$L$4:$L$303,"Hoje")) -> 0 | F38: =IF(Config!$B$11="","",SUMIFS(Tarefas!$H$4:$H$303,Tarefas!$D$4:$D$303,Config!$B$11,Tarefas!$I$4:$I$303,"<>Feito",Tarefas!$I$4:$I$303,"<>Cancelado")) -> 3
A39: =IF(Config!$B$12="","",Config!$B$12) | C39: =IF(Config!$B$12="","",COUNTIFS(Tarefas!$D$4:$D$303,Config!$B$12,Tarefas!$I$4:$I$303,"<>Feito",Tarefas!$I$4:$I$303,"<>Cancelado",Tarefas!$B$4:$B$303,"<>")) | D39: =IF(Config!$B$12="","",COUNTIFS(Tarefas!$D$4:$D$303,Config!$B$12,Tarefas!$L$4:$L$303,"Atrasada")) | E39: =IF(Config!$B$12="","",COUNTIFS(Tarefas!$D$4:$D$303,Config!$B$12,Tarefas!$L$4:$L$303,"Hoje")) | F39: =IF(Config!$B$12="","",SUMIFS(Tarefas!$H$4:$H$303,Tarefas!$D$4:$D$303,Config!$B$12,Tarefas!$I$4:$I$303,"<>Feito",Tarefas!$I$4:$I$303,"<>Cancelado"))
A40: =IF(Config!$B$13="","",Config!$B$13) | C40: =IF(Config!$B$13="","",COUNTIFS(Tarefas!$D$4:$D$303,Config!$B$13,Tarefas!$I$4:$I$303,"<>Feito",Tarefas!$I$4:$I$303,"<>Cancelado",Tarefas!$B$4:$B$303,"<>")) | D40: =IF(Config!$B$13="","",COUNTIFS(Tarefas!$D$4:$D$303,Config!$B$13,Tarefas!$L$4:$L$303,"Atrasada")) | E40: =IF(Config!$B$13="","",COUNTIFS(Tarefas!$D$4:$D$303,Config!$B$13,Tarefas!$L$4:$L$303,"Hoje")) | F40: =IF(Config!$B$13="","",SUMIFS(Tarefas!$H$4:$H$303,Tarefas!$D$4:$D$303,Config!$B$13,Tarefas!$I$4:$I$303,"<>Feito",Tarefas!$I$4:$I$303,"<>Cancelado"))
A41: =IF(Config!$B$14="","",Config!$B$14) | C41: =IF(Config!$B$14="","",COUNTIFS(Tarefas!$D$4:$D$303,Config!$B$14,Tarefas!$I$4:$I$303,"<>Feito",Tarefas!$I$4:$I$303,"<>Cancelado",Tarefas!$B$4:$B$303,"<>")) | D41: =IF(Config!$B$14="","",COUNTIFS(Tarefas!$D$4:$D$303,Config!$B$14,Tarefas!$L$4:$L$303,"Atrasada")) | E41: =IF(Config!$B$14="","",COUNTIFS(Tarefas!$D$4:$D$303,Config!$B$14,Tarefas!$L$4:$L$303,"Hoje")) | F41: =IF(Config!$B$14="","",SUMIFS(Tarefas!$H$4:$H$303,Tarefas!$D$4:$D$303,Config!$B$14,Tarefas!$I$4:$I$303,"<>Feito",Tarefas!$I$4:$I$303,"<>Cancelado"))
A42: =IF(Config!$B$15="","",Config!$B$15) | C42: =IF(Config!$B$15="","",COUNTIFS(Tarefas!$D$4:$D$303,Config!$B$15,Tarefas!$I$4:$I$303,"<>Feito",Tarefas!$I$4:$I$303,"<>Cancelado",Tarefas!$B$4:$B$303,"<>")) | D42: =IF(Config!$B$15="","",COUNTIFS(Tarefas!$D$4:$D$303,Config!$B$15,Tarefas!$L$4:$L$303,"Atrasada")) | E42: =IF(Config!$B$15="","",COUNTIFS(Tarefas!$D$4:$D$303,Config!$B$15,Tarefas!$L$4:$L$303,"Hoje")) | F42: =IF(Config!$B$15="","",SUMIFS(Tarefas!$H$4:$H$303,Tarefas!$D$4:$D$303,Config!$B$15,Tarefas!$I$4:$I$303,"<>Feito",Tarefas!$I$4:$I$303,"<>Cancelado"))
A43: =IF(Config!$B$16="","",Config!$B$16) | C43: =IF(Config!$B$16="","",COUNTIFS(Tarefas!$D$4:$D$303,Config!$B$16,Tarefas!$I$4:$I$303,"<>Feito",Tarefas!$I$4:$I$303,"<>Cancelado",Tarefas!$B$4:$B$303,"<>")) | D43: =IF(Config!$B$16="","",COUNTIFS(Tarefas!$D$4:$D$303,Config!$B$16,Tarefas!$L$4:$L$303,"Atrasada")) | E43: =IF(Config!$B$16="","",COUNTIFS(Tarefas!$D$4:$D$303,Config!$B$16,Tarefas!$L$4:$L$303,"Hoje")) | F43: =IF(Config!$B$16="","",SUMIFS(Tarefas!$H$4:$H$303,Tarefas!$D$4:$D$303,Config!$B$16,Tarefas!$I$4:$I$303,"<>Feito",Tarefas!$I$4:$I$303,"<>Cancelado"))

Sheet Config
A1: Configurações
A2: Células amarelas: você preenche. As demais são calculadas.
A4: Data de referência (hoje) | B4: =TODAY() -> 46283 | C4: Deixe =HOJE() ou digite uma data (ex.: 13/09/2026) para simular outro dia.
A6: Capacidade por dia (horas) | B6: 6 | C6: Quantas horas de trabalho focado cabem no seu dia.
A8: Responsáveis | D8: Status | F8: Projetos ou clientes
B9: Ana (você) | D9: A fazer | F9: Relatório mensal
B10: Bruno | D10: Fazendo | F10: Cliente Aurora
B11: Carla | D11: Feito | F11: Interno
D12: Cancelado | F12: Cliente Horizonte
A18: A lista de status é fixa (fundo cinza): as fórmulas dependem de "Feito" e "Cancelado".
A19: Preencha responsáveis e projetos de cima para baixo, sem pular linha: as listas suspensas param na última linha preenchida.

Sheet Tarefas
A1: Tarefas
A2: Preencha só as colunas amarelas. Prioridade, dias, situação e ordem são calculados. Apague os exemplos e comece a sua lista.
A3: ID | B3: Tarefa | C3: Projeto ou cliente | D3: Responsável | E3: Prazo | F3: Impacto (1-3) | G3: Urgência (1-3) | H3: Horas | I3: Status | J3: Prioridade | K3: Dias p/ prazo | L3: Situação | M3: Ordem | N3: Observação
A4: =IF(B4="","",ROW()-3) -> 1 | B4: Enviar relatório de setembro para a diretoria | C4: Relatório mensal | D4: Ana (você) | E4: =TODAY()-1 -> 46282 | F4: 3 | G4: 3 | H4: 2 | I4: Fazendo | J4: =IF(B4="","",IF(F4*G4>=6,"Alta",IF(F4*G4>=3,"Média","Baixa"))) -> Alta | K4: =IF(OR(B4="",E4=""),"",E4-Config!$B$4) -> -1 | L4: =IF(B4="","",IF(OR(I4="Feito",I4="Cancelado"),I4,IF(E4="","Sem prazo",IF(K4<0,"Atrasada",IF(K4=0,"Hoje",IF(K4<=6,"Esta semana","Depois")))))) -> Atrasada | M4: =IF(OR(B4="",L4="Feito",L4="Cancelado",L4="Sem prazo",L4="Depois"),0,IF(L4="Atrasada",2000,IF(L4="Hoje",1500,500))+F4*G4*100+IF(K4<0,MIN(-K4,30),10-K4)-ROW()/100000) -> 2901 | N4: Faltam os gráficos de vendas
A5: =IF(B5="","",ROW()-3) -> 2 | B5: Revisar proposta comercial da Aurora | C5: Cliente Aurora | D5: Ana (você) | E5: =TODAY() -> 46283 | F5: 3 | G5: 2 | H5: 1.5 | I5: A fazer | J5: =IF(B5="","",IF(F5*G5>=6,"Alta",IF(F5*G5>=3,"Média","Baixa"))) -> Alta | K5: =IF(OR(B5="",E5=""),"",E5-Config!$B$4) -> 0 | L5: =IF(B5="","",IF(OR(I5="Feito",I5="Cancelado"),I5,IF(E5="","Sem prazo",IF(K5<0,"Atrasada",IF(K5=0,"Hoje",IF(K5<=6,"Esta semana","Depois")))))) -> Hoje | M5: =IF(OR(B5="",L5="Feito",L5="Cancelado",L5="Sem prazo",L5="Depois"),0,IF(L5="Atrasada",2000,IF(L5="Hoje",1500,500))+F5*G5*100+IF(K5<0,MIN(-K5,30),10-K5)-ROW()/100000) -> 2109.9999 | N5: Cliente pediu desconto de 10%
A6: =IF(B6="","",ROW()-3) -> 3 | B6: Responder pesquisa de clima | C6: Interno | D6: Ana (você) | E6: =TODAY()-2 -> 46281 | F6: 1 | G6: 1 | H6: 0.5 | I6: A fazer | J6: =IF(B6="","",IF(F6*G6>=6,"Alta",IF(F6*G6>=3,"Média","Baixa"))) -> Baixa | K6: =IF(OR(B6="",E6=""),"",E6-Config!$B$4) -> -2 | L6: =IF(B6="","",IF(OR(I6="Feito",I6="Cancelado"),I6,IF(E6="","Sem prazo",IF(K6<0,"Atrasada",IF(K6=0,"Hoje",IF(K6<=6,"Esta semana","Depois")))))) -> Atrasada | M6: =IF(OR(B6="",L6="Feito",L6="Cancelado",L6="Sem prazo",L6="Depois"),0,IF(L6="Atrasada",2000,IF(L6="Hoje",1500,500))+F6*G6*100+IF(K6<0,MIN(-K6,30),10-K6)-ROW()/100000) -> 2101.9999
A7: =IF(B7="","",ROW()-3) -> 4 | B7: Montar apresentação da reunião de quinta | C7: Cliente Horizonte | D7: Ana (você) | E7: =TODAY()+1 -> 46284 | F7: 3 | G7: 3 | H7: 3 | I7: A fazer | J7: =IF(B7="","",IF(F7*G7>=6,"Alta",IF(F7*G7>=3,"Média","Baixa"))) -> Alta | K7: =IF(OR(B7="",E7=""),"",E7-Config!$B$4) -> 1 | L7: =IF(B7="","",IF(OR(I7="Feito",I7="Cancelado"),I7,IF(E7="","Sem prazo",IF(K7<0,"Atrasada",IF(K7=0,"Hoje",IF(K7<=6,"Esta semana","Depois")))))) -> Esta semana | M7: =IF(OR(B7="",L7="Feito",L7="Cancelado",L7="Sem prazo",L7="Depois"),0,IF(L7="Atrasada",2000,IF(L7="Hoje",1500,500))+F7*G7*100+IF(K7<0,MIN(-K7,30),10-K7)-ROW()/100000) -> 1408.9999 | N7: Usar o modelo de 8 slides do kit
A8: =IF(B8="","",ROW()-3) -> 5 | B8: Atualizar planilha de leads | C8: Cliente Aurora | D8: Bruno | E8: =TODAY()+1 -> 46284 | F8: 2 | G8: 2 | H8: 1 | I8: Fazendo | J8: =IF(B8="","",IF(F8*G8>=6,"Alta",IF(F8*G8>=3,"Média","Baixa"))) -> Média | K8: =IF(OR(B8="",E8=""),"",E8-Config!$B$4) -> 1 | L8: =IF(B8="","",IF(OR(I8="Feito",I8="Cancelado"),I8,IF(E8="","Sem prazo",IF(K8<0,"Atrasada",IF(K8=0,"Hoje",IF(K8<=6,"Esta semana","Depois")))))) -> Esta semana | M8: =IF(OR(B8="",L8="Feito",L8="Cancelado",L8="Sem prazo",L8="Depois"),0,IF(L8="Atrasada",2000,IF(L8="Hoje",1500,500))+F8*G8*100+IF(K8<0,MIN(-K8,30),10-K8)-ROW()/100000) -> 908.99992
A9: =IF(B9="","",ROW()-3) -> 6 | B9: Aprovar arte do post de terça | C9: Cliente Horizonte | D9: Carla | E9: =TODAY()+1 -> 46284 | F9: 2 | G9: 3 | H9: 0.5 | I9: A fazer | J9: =IF(B9="","",IF(F9*G9>=6,"Alta",IF(F9*G9>=3,"Média","Baixa"))) -> Alta | K9: =IF(OR(B9="",E9=""),"",E9-Config!$B$4) -> 1 | L9: =IF(B9="","",IF(OR(I9="Feito",I9="Cancelado"),I9,IF(E9="","Sem prazo",IF(K9<0,"Atrasada",IF(K9=0,"Hoje",IF(K9<=6,"Esta semana","Depois")))))) -> Esta semana | M9: =IF(OR(B9="",L9="Feito",L9="Cancelado",L9="Sem prazo",L9="Depois"),0,IF(L9="Atrasada",2000,IF(L9="Hoje",1500,500))+F9*G9*100+IF(K9<0,MIN(-K9,30),10-K9)-ROW()/100000) -> 1108.9999
A10: =IF(B10="","",ROW()-3) -> 7 | B10: Reunião de alinhamento com o Bruno | C10: Interno | D10: Ana (você) | E10: =TODAY()+2 -> 46285 | F10: 2 | G10: 2 | H10: 1 | I10: A fazer | J10: =IF(B10="","",IF(F10*G10>=6,"Alta",IF(F10*G10>=3,"Média","Baixa"))) -> Média | K10: =IF(OR(B10="",E10=""),"",E10-Config!$B$4) -> 2 | L10: =IF(B10="","",IF(OR(I10="Feito",I10="Cancelado"),I10,IF(E10="","Sem prazo",IF(K10<0,"Atrasada",IF(K10=0,"Hoje",IF(K10<=6,"Esta semana","Depois")))))) -> Esta semana | M10: =IF(OR(B10="",L10="Feito",L10="Cancelado",L10="Sem prazo",L10="Depois"),0,IF(L10="Atrasada",2000,IF(L10="Hoje",1500,500))+F10*G10*100+IF(K10<0,MIN(-K10,30),10-K10)-ROW()/100000) -> 907.9999 | N10: 14h
A11: =IF(B11="","",ROW()-3) -> 8 | B11: Fechar pauta de outubro | C11: Cliente Aurora | D11: Carla | E11: =TODAY()+3 -> 46286 | F11: 3 | G11: 2 | H11: 2 | I11: A fazer | J11: =IF(B11="","",IF(F11*G11>=6,"Alta",IF(F11*G11>=3,"Média","Baixa"))) -> Alta | K11: =IF(OR(B11="",E11=""),"",E11-Config!$B$4) -> 3 | L11: =IF(B11="","",IF(OR(I11="Feito",I11="Cancelado"),I11,IF(E11="","Sem prazo",IF(K11<0,"Atrasada",IF(K11=0,"Hoje",IF(K11<=6,"Esta semana","Depois")))))) -> Esta semana | M11: =IF(OR(B11="",L11="Feito",L11="Cancelado",L11="Sem prazo",L11="Depois"),0,IF(L11="Atrasada",2000,IF(L11="Hoje",1500,500))+F11*G11*100+IF(K11<0,MIN(-K11,30),10-K11)-ROW()/100000) -> 1106.9999
A12: =IF(B12="","",ROW()-3) -> 9 | B12: Conferir faturas dos fornecedores | C12: Interno | D12: Ana (você) | E12: =TODAY()+4 -> 46287 | F12: 2 | G12: 1 | H12: 1 | I12: A fazer | J12: =IF(B12="","",IF(F12*G12>=6,"Alta",IF(F12*G12>=3,"Média","Baixa"))) -> Baixa | K12: =IF(OR(B12="",E12=""),"",E12-Config!$B$4) -> 4 | L12: =IF(B12="","",IF(OR(I12="Feito",I12="Cancelado"),I12,IF(E12="","Sem prazo",IF(K12<0,"Atrasada",IF(K12=0,"Hoje",IF(K12<=6,"Esta semana","Depois")))))) -> Esta semana | M12: =IF(OR(B12="",L12="Feito",L12="Cancelado",L12="Sem prazo",L12="Depois"),0,IF(L12="Atrasada",2000,IF(L12="Hoje",1500,500))+F12*G12*100+IF(K12<0,MIN(-K12,30),10-K12)-ROW()/100000) -> 705.99988
A13: =IF(B13="","",ROW()-3) -> 10 | B13: Escrever e-mail de resultados para a Horizonte | C13: Cliente Horizonte | D13: Ana (você) | E13: =TODAY()+4 -> 46287 | F13: 3 | G13: 2 | H13: 1 | I13: A fazer | J13: =IF(B13="","",IF(F13*G13>=6,"Alta",IF(F13*G13>=3,"Média","Baixa"))) -> Alta | K13: =IF(OR(B13="",E13=""),"",E13-Config!$B$4) -> 4 | L13: =IF(B13="","",IF(OR(I13="Feito",I13="Cancelado"),I13,IF(E13="","Sem prazo",IF(K13<0,"Atrasada",IF(K13=0,"Hoje",IF(K13<=6,"Esta semana","Depois")))))) -> Esta semana | M13: =IF(OR(B13="",L13="Feito",L13="Cancelado",L13="Sem prazo",L13="Depois"),0,IF(L13="Atrasada",2000,IF(L13="Hoje",1500,500))+F13*G13*100+IF(K13<0,MIN(-K13,30),10-K13)-ROW()/100000) -> 1105.9999 | N13: Usar prompt Escrever 04
A14: =IF(B14="","",ROW()-3) -> 11 | B14: Organizar pasta de fotos do evento | C14: Interno | D14: Bruno | E14: =TODAY()+5 -> 46288 | F14: 1 | G14: 1 | H14: 2 | I14: A fazer | J14: =IF(B14="","",IF(F14*G14>=6,"Alta",IF(F14*G14>=3,"Média","Baixa"))) -> Baixa | K14: =IF(OR(B14="",E14=""),"",E14-Config!$B$4) -> 5 | L14: =IF(B14="","",IF(OR(I14="Feito",I14="Cancelado"),I14,IF(E14="","Sem prazo",IF(K14<0,"Atrasada",IF(K14=0,"Hoje",IF(K14<=6,"Esta semana","Depois")))))) -> Esta semana | M14: =IF(OR(B14="",L14="Feito",L14="Cancelado",L14="Sem prazo",L14="Depois"),0,IF(L14="Atrasada",2000,IF(L14="Hoje",1500,500))+F14*G14*100+IF(K14<0,MIN(-K14,30),10-K14)-ROW()/100000) -> 604.99986
A15: =IF(B15="","",ROW()-3) -> 12 | B15: Preparar orçamento do vídeo institucional | C15: Cliente Aurora | D15: Ana (você) | E15: =TODAY()+6 -> 46289 | F15: 3 | G15: 1 | H15: 2 | I15: A fazer | J15: =IF(B15="","",IF(F15*G15>=6,"Alta",IF(F15*G15>=3,"Média","Baixa"))) -> Média | K15: =IF(OR(B15="",E15=""),"",E15-Config!$B$4) -> 6 | L15: =IF(B15="","",IF(OR(I15="Feito",I15="Cancelado"),I15,IF(E15="","Sem prazo",IF(K15<0,"Atrasada",IF(K15=0,"Hoje",IF(K15<=6,"Esta semana","Depois")))))) -> Esta semana | M15: =IF(OR(B15="",L15="Feito",L15="Cancelado",L15="Sem prazo",L15="Depois"),0,IF(L15="Atrasada",2000,IF(L15="Hoje",1500,500))+F15*G15*100+IF(K15<0,MIN(-K15,30),10-K15)-ROW()/100000) -> 803.99985
A16: =IF(B16="","",ROW()-3) -> 13 | B16: Treinar estagiário na planilha de leads | C16: Interno | D16: Bruno | E16: =TODAY()+7 -> 46290 | F16: 2 | G16: 1 | H16: 1.5 | I16: A fazer | J16: =IF(B16="","",IF(F16*G16>=6,"Alta",IF(F16*G16>=3,"Média","Baixa"))) -> Baixa | K16: =IF(OR(B16="",E16=""),"",E16-Config!$B$4) -> 7 | L16: =IF(B16="","",IF(OR(I16="Feito",I16="Cancelado"),I16,IF(E16="","Sem prazo",IF(K16<0,"Atrasada",IF(K16=0,"Hoje",IF(K16<=6,"Esta semana","Depois")))))) -> Depois | M16: =IF(OR(B16="",L16="Feito",L16="Cancelado",L16="Sem prazo",L16="Depois"),0,IF(L16="Atrasada",2000,IF(L16="Hoje",1500,500))+F16*G16*100+IF(K16<0,MIN(-K16,30),10-K16)-ROW()/100000) -> 0
A17: =IF(B17="","",ROW()-3) -> 14 | B17: Relatório de mídia de agosto | C17: Relatório mensal | D17: Ana (você) | E17: =TODAY()-9 -> 46274 | F17: 3 | G17: 3 | H17: 3 | I17: Feito | J17: =IF(B17="","",IF(F17*G17>=6,"Alta",IF(F17*G17>=3,"Média","Baixa"))) -> Alta | K17: =IF(OR(B17="",E17=""),"",E17-Config!$B$4) -> -9 | L17: =IF(B17="","",IF(OR(I17="Feito",I17="Cancelado"),I17,IF(E17="","Sem prazo",IF(K17<0,"Atrasada",IF(K17=0,"Hoje",IF(K17<=6,"Esta semana","Depois")))))) -> Feito | M17: =IF(OR(B17="",L17="Feito",L17="Cancelado",L17="Sem prazo",L17="Depois"),0,IF(L17="Atrasada",2000,IF(L17="Hoje",1500,500))+F17*G17*100+IF(K17<0,MIN(-K17,30),10-K17)-ROW()/100000) -> 0
A18: =IF(B18="","",ROW()-3) -> 15 | B18: Renovar domínio do site | C18: Interno | D18: Carla | E18: =TODAY()+10 -> 46293 | F18: 2 | G18: 1 | H18: 0.5 | I18: A fazer | J18: =IF(B18="","",IF(F18*G18>=6,"Alta",IF(F18*G18>=3,"Média","Baixa"))) -> Baixa | K18: =IF(OR(B18="",E18=""),"",E18-Config!$B$4) -> 10 | L18: =IF(B18="","",IF(OR(I18="Feito",I18="Cancelado"),I18,IF(E18="","Sem prazo",IF(K18<0,"Atrasada",IF(K18=0,"Hoje",IF(K18<=6,"Esta semana","Depois")))))) -> Depois | M18: =IF(OR(B18="",L18="Feito",L18="Cancelado",L18="Sem prazo",L18="Depois"),0,IF(L18="Atrasada",2000,IF(L18="Hoje",1500,500))+F18*G18*100+IF(K18<0,MIN(-K18,30),10-K18)-ROW()/100000) -> 0
A19: =IF(B19="","",ROW()-3) -> 16 | B19: Pesquisar concorrentes da Horizonte | C19: Cliente Horizonte | D19: Bruno | E19: =TODAY()+13 -> 46296 | F19: 2 | G19: 2 | H19: 4 | I19: A fazer | J19: =IF(B19="","",IF(F19*G19>=6,"Alta",IF(F19*G19>=3,"Média","Baixa"))) -> Média | K19: =IF(OR(B19="",E19=""),"",E19-Config!$B$4) -> 13 | L19: =IF(B19="","",IF(OR(I19="Feito",I19="Cancelado"),I19,IF(E19="","Sem prazo",IF(K19<0,"Atrasada",IF(K19=0,"Hoje",IF(K19<=6,"Esta semana","Depois")))))) -> Depois | M19: =IF(OR(B19="",L19="Feito",L19="Cancelado",L19="Sem prazo",L19="Depois"),0,IF(L19="Atrasada",2000,IF(L19="Hoje",1500,500))+F19*G19*100+IF(K19<0,MIN(-K19,30),10-K19)-ROW()/100000) -> 0
A20: =IF(B20="","",ROW()-3) -> 17 | B20: Briefing da campanha de fim de ano | C20: Cliente Aurora | D20: Ana (você) | E20: =TODAY()+16 -> 46299 | F20: 3 | G20: 1 | H20: 2 | I20: A fazer | J20: =IF(B20="","",IF(F20*G20>=6,"Alta",IF(F20*G20>=3,"Média","Baixa"))) -> Média | K20: =IF(OR(B20="",E20=""),"",E20-Config!$B$4) -> 16 | L20: =IF(B20="","",IF(OR(I20="Feito",I20="Cancelado"),I20,IF(E20="","Sem prazo",IF(K20<0,"Atrasada",IF(K20=0,"Hoje",IF(K20<=6,"Esta semana","Depois")))))) -> Depois | M20: =IF(OR(B20="",L20="Feito",L20="Cancelado",L20="Sem prazo",L20="Depois"),0,IF(L20="Atrasada",2000,IF(L20="Hoje",1500,500))+F20*G20*100+IF(K20<0,MIN(-K20,30),10-K20)-ROW()/100000) -> 0
A21: =IF(B21="","",ROW()-3) -> 18 | B21: Post sobre lançamento cancelado | C21: Cliente Horizonte | D21: Carla | E21: =TODAY()-3 -> 46280 | F21: 1 | G21: 2 | H21: 1 | I21: Cancelado | J21: =IF(B21="","",IF(F21*G21>=6,"Alta",IF(F21*G21>=3,"Média","Baixa"))) -> Baixa | K21: =IF(OR(B21="",E21=""),"",E21-Config!$B$4) -> -3 | L21: =IF(B21="","",IF(OR(I21="Feito",I21="Cancelado"),I21,IF(E21="","Sem prazo",IF(K21<0,"Atrasada",IF(K21=0,"Hoje",IF(K21<=6,"Esta semana","Depois")))))) -> Cancelado | M21: =IF(OR(B21="",L21="Feito",L21="Cancelado",L21="Sem prazo",L21="Depois"),0,IF(L21="Atrasada",2000,IF(L21="Hoje",1500,500))+F21*G21*100+IF(K21<0,MIN(-K21,30),10-K21)-ROW()/100000) -> 0 | N21: Cliente adiou o lançamento
A22: =IF(B22="","",ROW()-3) -> 19 | B22: Revisar contrato de prestação de serviço | C22: Interno | D22: Ana (você) | F22: 2 | G22: 1 | H22: 1 | I22: A fazer | J22: =IF(B22="","",IF(F22*G22>=6,"Alta",IF(F22*G22>=3,"Média","Baixa"))) -> Baixa | K22: =IF(OR(B22="",E22=""),"",E22-Config!$B$4) | L22: =IF(B22="","",IF(OR(I22="Feito",I22="Cancelado"),I22,IF(E22="","Sem prazo",IF(K22<0,"Atrasada",IF(K22=0,"Hoje",IF(K22<=6,"Esta semana","Depois")))))) -> Sem prazo | M22: =IF(OR(B22="",L22="Feito",L22="Cancelado",L22="Sem prazo",L22="Depois"),0,IF(L22="Atrasada",2000,IF(L22="Hoje",1500,500))+F22*G22*100+IF(K22<0,MIN(-K22,30),10-K22)-ROW()/100000) -> 0 | N22: Sem prazo definido ainda
A23: =IF(B23="","",ROW()-3) -> 20 | B23: Backup mensal dos arquivos | C23: Interno | D23: Bruno | E23: =TODAY()-6 -> 46277 | F23: 2 | G23: 2 | H23: 1 | I23: Feito | J23: =IF(B23="","",IF(F23*G23>=6,"Alta",IF(F23*G23>=3,"Média","Baixa"))) -> Média | K23: =IF(OR(B23="",E23=""),"",E23-Config!$B$4) -> -6 | L23: =IF(B23="","",IF(OR(I23="Feito",I23="Cancelado"),I23,IF(E23="","Sem prazo",IF(K23<0,"Atrasada",IF(K23=0,"Hoje",IF(K23<=6,"Esta semana","Depois")))))) -> Feito | M23: =IF(OR(B23="",L23="Feito",L23="Cancelado",L23="Sem prazo",L23="Depois"),0,IF(L23="Atrasada",2000,IF(L23="Hoje",1500,500))+F23*G23*100+IF(K23<0,MIN(-K23,30),10-K23)-ROW()/100000) -> 0
A24: =IF(B24="","",ROW()-3) | J24: =IF(B24="","",IF(F24*G24>=6,"Alta",IF(F24*G24>=3,"Média","Baixa"))) | K24: =IF(OR(B24="",E24=""),"",E24-Config!$B$4) | L24: =IF(B24="","",IF(OR(I24="Feito",I24="Cancelado"),I24,IF(E24="","Sem prazo",IF(K24<0,"Atrasada",IF(K24=0,"Hoje",IF(K24<=6,"Esta semana","Depois")))))) | M24: =IF(OR(B24="",L24="Feito",L24="Cancelado",L24="Sem prazo",L24="Depois"),0,IF(L24="Atrasada",2000,IF(L24="Hoje",1500,500))+F24*G24*100+IF(K24<0,MIN(-K24,30),10-K24)-ROW()/100000) -> 0
A25: =IF(B25="","",ROW()-3) | J25: =IF(B25="","",IF(F25*G25>=6,"Alta",IF(F25*G25>=3,"Média","Baixa"))) | K25: =IF(OR(B25="",E25=""),"",E25-Config!$B$4) | L25: =IF(B25="","",IF(OR(I25="Feito",I25="Cancelado"),I25,IF(E25="","Sem prazo",IF(K25<0,"Atrasada",IF(K25=0,"Hoje",IF(K25<=6,"Esta semana","Depois")))))) | M25: =IF(OR(B25="",L25="Feito",L25="Cancelado",L25="Sem prazo",L25="Depois"),0,IF(L25="Atrasada",2000,IF(L25="Hoje",1500,500))+F25*G25*100+IF(K25<0,MIN(-K25,30),10-K25)-ROW()/100000) -> 0
A26: =IF(B26="","",ROW()-3) | J26: =IF(B26="","",IF(F26*G26>=6,"Alta",IF(F26*G26>=3,"Média","Baixa"))) | K26: =IF(OR(B26="",E26=""),"",E26-Config!$B$4) | L26: =IF(B26="","",IF(OR(I26="Feito",I26="Cancelado"),I26,IF(E26="","Sem prazo",IF(K26<0,"Atrasada",IF(K26=0,"Hoje",IF(K26<=6,"Esta semana","Depois")))))) | M26: =IF(OR(B26="",L26="Feito",L26="Cancelado",L26="Sem prazo",L26="Depois"),0,IF(L26="Atrasada",2000,IF(L26="Hoje",1500,500))+F26*G26*100+IF(K26<0,MIN(-K26,30),10-K26)-ROW()/100000) -> 0
A27: =IF(B27="","",ROW()-3) | J27: =IF(B27="","",IF(F27*G27>=6,"Alta",IF(F27*G27>=3,"Média","Baixa"))) | K27: =IF(OR(B27="",E27=""),"",E27-Config!$B$4) | L27: =IF(B27="","",IF(OR(I27="Feito",I27="Cancelado"),I27,IF(E27="","Sem prazo",IF(K27<0,"Atrasada",IF(K27=0,"Hoje",IF(K27<=6,"Esta semana","Depois")))))) | M27: =IF(OR(B27="",L27="Feito",L27="Cancelado",L27="Sem prazo",L27="Depois"),0,IF(L27="Atrasada",2000,IF(L27="Hoje",1500,500))+F27*G27*100+IF(K27<0,MIN(-K27,30),10-K27)-ROW()/100000) -> 0
A28: =IF(B28="","",ROW()-3) | J28: =IF(B28="","",IF(F28*G28>=6,"Alta",IF(F28*G28>=3,"Média","Baixa"))) | K28: =IF(OR(B28="",E28=""),"",E28-Config!$B$4) | L28: =IF(B28="","",IF(OR(I28="Feito",I28="Cancelado"),I28,IF(E28="","Sem prazo",IF(K28<0,"Atrasada",IF(K28=0,"Hoje",IF(K28<=6,"Esta semana","Depois")))))) | M28: =IF(OR(B28="",L28="Feito",L28="Cancelado",L28="Sem prazo",L28="Depois"),0,IF(L28="Atrasada",2000,IF(L28="Hoje",1500,500))+F28*G28*100+IF(K28<0,MIN(-K28,30),10-K28)-ROW()/100000) -> 0
A29: =IF(B29="","",ROW()-3) | J29: =IF(B29="","",IF(F29*G29>=6,"Alta",IF(F29*G29>=3,"Média","Baixa"))) | K29: =IF(OR(B29="",E29=""),"",E29-Config!$B$4) | L29: =IF(B29="","",IF(OR(I29="Feito",I29="Cancelado"),I29,IF(E29="","Sem prazo",IF(K29<0,"Atrasada",IF(K29=0,"Hoje",IF(K29<=6,"Esta semana","Depois")))))) | M29: =IF(OR(B29="",L29="Feito",L29="Cancelado",L29="Sem prazo",L29="Depois"),0,IF(L29="Atrasada",2000,IF(L29="Hoje",1500,500))+F29*G29*100+IF(K29<0,MIN(-K29,30),10-K29)-ROW()/100000) -> 0
A30: =IF(B30="","",ROW()-3) | J30: =IF(B30="","",IF(F30*G30>=6,"Alta",IF(F30*G30>=3,"Média","Baixa"))) | K30: =IF(OR(B30="",E30=""),"",E30-Config!$B$4) | L30: =IF(B30="","",IF(OR(I30="Feito",I30="Cancelado"),I30,IF(E30="","Sem prazo",IF(K30<0,"Atrasada",IF(K30=0,"Hoje",IF(K30<=6,"Esta semana","Depois")))))) | M30: =IF(OR(B30="",L30="Feito",L30="Cancelado",L30="Sem prazo",L30="Depois"),0,IF(L30="Atrasada",2000,IF(L30="Hoje",1500,500))+F30*G30*100+IF(K30<0,MIN(-K30,30),10-K30)-ROW()/100000) -> 0
A31: =IF(B31="","",ROW()-3) | J31: =IF(B31="","",IF(F31*G31>=6,"Alta",IF(F31*G31>=3,"Média","Baixa"))) | K31: =IF(OR(B31="",E31=""),"",E31-Config!$B$4) | L31: =IF(B31="","",IF(OR(I31="Feito",I31="Cancelado"),I31,IF(E31="","Sem prazo",IF(K31<0,"Atrasada",IF(K31=0,"Hoje",IF(K31<=6,"Esta semana","Depois")))))) | M31: =IF(OR(B31="",L31="Feito",L31="Cancelado",L31="Sem prazo",L31="Depois"),0,IF(L31="Atrasada",2000,IF(L31="Hoje",1500,500))+F31*G31*100+IF(K31<0,MIN(-K31,30),10-K31)-ROW()/100000) -> 0
A32: =IF(B32="","",ROW()-3) | J32: =IF(B32="","",IF(F32*G32>=6,"Alta",IF(F32*G32>=3,"Média","Baixa"))) | K32: =IF(OR(B32="",E32=""),"",E32-Config!$B$4) | L32: =IF(B32="","",IF(OR(I32="Feito",I32="Cancelado"),I32,IF(E32="","Sem prazo",IF(K32<0,"Atrasada",IF(K32=0,"Hoje",IF(K32<=6,"Esta semana","Depois")))))) | M32: =IF(OR(B32="",L32="Feito",L32="Cancelado",L32="Sem prazo",L32="Depois"),0,IF(L32="Atrasada",2000,IF(L32="Hoje",1500,500))+F32*G32*100+IF(K32<0,MIN(-K32,30),10-K32)-ROW()/100000) -> 0
A33: =IF(B33="","",ROW()-3) | J33: =IF(B33="","",IF(F33*G33>=6,"Alta",IF(F33*G33>=3,"Média","Baixa"))) | K33: =IF(OR(B33="",E33=""),"",E33-Config!$B$4) | L33: =IF(B33="","",IF(OR(I33="Feito",I33="Cancelado"),I33,IF(E33="","Sem prazo",IF(K33<0,"Atrasada",IF(K33=0,"Hoje",IF(K33<=6,"Esta semana","Depois")))))) | M33: =IF(OR(B33="",L33="Feito",L33="Cancelado",L33="Sem prazo",L33="Depois"),0,IF(L33="Atrasada",2000,IF(L33="Hoje",1500,500))+F33*G33*100+IF(K33<0,MIN(-K33,30),10-K33)-ROW()/100000) -> 0
A34: =IF(B34="","",ROW()-3) | J34: =IF(B34="","",IF(F34*G34>=6,"Alta",IF(F34*G34>=3,"Média","Baixa"))) | K34: =IF(OR(B34="",E34=""),"",E34-Config!$B$4) | L34: =IF(B34="","",IF(OR(I34="Feito",I34="Cancelado"),I34,IF(E34="","Sem prazo",IF(K34<0,"Atrasada",IF(K34=0,"Hoje",IF(K34<=6,"Esta semana","Depois")))))) | M34: =IF(OR(B34="",L34="Feito",L34="Cancelado",L34="Sem prazo",L34="Depois"),0,IF(L34="Atrasada",2000,IF(L34="Hoje",1500,500))+F34*G34*100+IF(K34<0,MIN(-K34,30),10-K34)-ROW()/100000) -> 0
A35: =IF(B35="","",ROW()-3) | J35: =IF(B35="","",IF(F35*G35>=6,"Alta",IF(F35*G35>=3,"Média","Baixa"))) | K35: =IF(OR(B35="",E35=""),"",E35-Config!$B$4) | L35: =IF(B35="","",IF(OR(I35="Feito",I35="Cancelado"),I35,IF(E35="","Sem prazo",IF(K35<0,"Atrasada",IF(K35=0,"Hoje",IF(K35<=6,"Esta semana","Depois")))))) | M35: =IF(OR(B35="",L35="Feito",L35="Cancelado",L35="Sem prazo",L35="Depois"),0,IF(L35="Atrasada",2000,IF(L35="Hoje",1500,500))+F35*G35*100+IF(K35<0,MIN(-K35,30),10-K35)-ROW()/100000) -> 0
... A303: =IF(B303="","",ROW()-3) | J303: =IF(B303="","",IF(F303*G303>=6,"Alta",IF(F303*G303>=3,"Média","Baixa"))) | K303: =IF(OR(B303="",E303=""),"",E303-Config!$B$4) | L303: =IF(B303="","",IF(OR(I303="Feito",I303="Cancelado"),I303,IF(E303="","Sem prazo",IF(K303<0,"Atrasada",IF(K303=0,"Hoje",IF(K303<=6,"Esta semana","Depois")))))) | M303: =IF(OR(B303="",L303="Feito",L303="Cancelado",L303="Sem prazo",L303="Depois"),0,IF(L303="Atrasada",2000,IF(L303="Hoje",1500,500))+F303*G303*100+IF(K303<0,MIN(-K303,30),10-K303)-ROW()/100000) -> 0
